{
  "type": "Feature",
  "properties": {
    "date:cessation_lower": "1990-01-01",
    "date:cessation_upper": "1999-12-31",
    "date:inception_lower": "1990-01-01",
    "date:inception_upper": "1999-12-31",
    "iso:country": "XX",
    "millsfield:images": [
      1746680255
    ],
    "millsfield:primary_image": 1746680255,
    "sfomuseum:accession_number": "1995.29.08",
    "sfomuseum:category": "Toys",
    "sfomuseum:collection": "Aviation Museum",
    "sfomuseum:creditline": "Purchase",
    "sfomuseum:date": "1990s",
    "sfomuseum:date_acquired": "1995-06-06",
    "sfomuseum:daterange_end": "1990-12-31",
    "sfomuseum:daterange_start": "1990-01-01",
    "sfomuseum:description": "Toy airplane; single-engine toy biplane with blue fuselage, yellow wings and tail and red nose and propeller; stamped metal parts are joined by phillips head screws and nuts; rubber wheels.",
    "sfomuseum:dimensions": "6 1/4 x 18 1/2 x 14 inches (15.9 x 47 x 35.6 cm)",
    "sfomuseum:medium": "stamped metal, rubber, paint",
    "sfomuseum:placetype": "object",
    "sfomuseum:publication": ": , 1990s.",
    "sfomuseum:subcategory": "Toy Airplane",
    "wof:name": "toy airplane: single engine biplane",
    "wof:placetype": "custom",
    "wof:placetype_alt": "object"
  },
  "geometry": {"coordinates":[-122.386155,37.616357],"type":"Point"}
}
