{
  "type": "Feature",
  "properties": {
    "date:cessation_lower": "1951-01-01",
    "date:cessation_upper": "1951-12-31",
    "date:inception_lower": "1951-01-01",
    "date:inception_upper": "1951-12-31",
    "iso:country": "XX",
    "millsfield:images": [
      1763388359
    ],
    "millsfield:images_texts": [
      "Bren has\n3= London\nPais did\nRome'\nRot\nOld Curiosity Shop\nimmortalise\nCharles Dickens\nUntinue and Modern\nPORTSMOUTH:\nRet\nOnly the Clipper way offers you so much!\nGO ONE WAY\nRETURN THE OTHER\neen to marone mans\ntimes will tell you there's no more\nMASTERRUMOASOODS\n•-dockod \"Strato\"\nChoper.\nYou thy bich above the\nAve day in Paris because you've crossed the Atlartie in the\nyou pecter, lake\nToe Sumer\nern route: go by Constellation-type\nFree too on tO Pass\ncities than any other U. S. airline.\nFinally, if you plan your trip so you\nreturn before July Is, you'll make sub\nStrato Clippers to 9 citios\nOnly Pan American flies \"Strato\" Clip\nPAN AMERICAN\nciants ako fly to London, Shanno\nUbelli Mart Experienced Ailine\nIs ... 587.50 thereafter. Call your\nlocal travel Asens of"
    ],
    "millsfield:images_texts_ids": [
      1763388359
    ],
    "millsfield:primary_image": 1763388359,
    "sfomuseum:accession_number": "2001.038.164.058",
    "sfomuseum:airline": "Pan American World Airways",
    "sfomuseum:category": "Promotional, Archive",
    "sfomuseum:collection": "Aviation Archive",
    "sfomuseum:creditline": "Gift of Barnaby Conrad III",
    "sfomuseum:date": "1951",
    "sfomuseum:date_acquired": "2003-05-16",
    "sfomuseum:daterange_end": "1951-12-31",
    "sfomuseum:daterange_start": "1951-01-01",
    "sfomuseum:description": "Advertisement from March 17, 1951 issue of Saturday Evening Post promoting Pan American World Airways, titled “London Paris Rome / Only the Clipper way offers you so much!” with color illustration depicting storefront scene at Charles Dickens’ The Old Curiosity Shop.",
    "sfomuseum:dimensions": "14 x 10 1/2 inches (35.6 x 26.7 cm)",
    "sfomuseum:medium": "paper, ink",
    "sfomuseum:placetype": "object",
    "sfomuseum:publication": ": , 1951.",
    "sfomuseum:subcategory": "Advertisement, 2D",
    "sfomuseum:subject": "Pan Am promotional advertisement",
    "wof:depicts": [
      1159284989,
      1159286839
    ],
    "wof:name": "advertisement: Pan American World Airways, Saturday Evening Post",
    "wof:placetype": "custom",
    "wof:placetype_alt": "object"
  },
  "geometry": {"coordinates":[-122.386155,37.616357],"type":"Point"}
}
