{
  "type": "Feature",
  "properties": {
    "date:cessation_lower": "1969-12-31",
    "date:cessation_upper": "1969-12-31",
    "date:inception_lower": "1960-01-01",
    "date:inception_upper": "1960-01-01",
    "iso:country": "XX",
    "sfomuseum:accession_number": "1995.35.87",
    "sfomuseum:airline": "Pan American World Airways",
    "sfomuseum:category": "Promotional",
    "sfomuseum:collection": "Aviation Museum",
    "sfomuseum:creditline": "Gift of Beatrice H. Springer",
    "sfomuseum:date": "1960s",
    "sfomuseum:daterange_end": "1969-12-31",
    "sfomuseum:daterange_start": "1960-01-01",
    "sfomuseum:description": "Gold brushed metal lighter; blue \"Pan American\" servicemark and globe logo with jet streak and planform outline of airplane on narrow side; housed in turquoise blue box with \"Pan American\" and globe logo in gold.",
    "sfomuseum:maker": "Cygnus",
    "sfomuseum:medium": "metal",
    "sfomuseum:placetype": "object",
    "sfomuseum:subcategory": "Lighter",
    "wof:depicts": [
      1159284989
    ],
    "wof:name": "lighter: Pan American World Airways",
    "wof:placetype": "venue"
  },
  "geometry": {"coordinates":[-122.386155,37.616357],"type":"Point"}
}
