{
  "type": "Feature",
  "properties": {
    "date:cessation_lower": "1978-12-31",
    "date:cessation_upper": "1978-12-31",
    "date:inception_lower": "1978-01-01",
    "date:inception_upper": "1978-01-01",
    "iso:country": "XX",
    "sfomuseum:accession_number": "2002.127.671",
    "sfomuseum:category": "Passenger Amenity",
    "sfomuseum:collection": "Aviation Archive",
    "sfomuseum:creditline": "Gift of Thomas G. Dragges",
    "sfomuseum:date": "1978",
    "sfomuseum:daterange_end": "1978-12-31",
    "sfomuseum:daterange_start": "1978-01-01",
    "sfomuseum:description": "Safety information card issued by Western Airlines for its McDonnell Douglas DC-10 fleet; airline servicemark located in top quadrant; illustrations demonstrate aircraft safety and emergency procedures\r",
    "sfomuseum:media_ids": [
      1527850169, 
      1527850171
    ],
    "sfomuseum:medium": "paper, ink",
    "sfomuseum:placetype": "object",
    "sfomuseum:subcategory": "Safety Information Card",
    "wof:name": "safety information card: Western Airlines, McDonnell Douglas DC-10",
    "wof:placetype": "venue"
  },
  "geometry": {"coordinates":[-122.386155,37.616358],"type":"Point"}
}
