{
  "type": "Feature",
  "properties": {
    "date:cessation_lower": "1978-01-01",
    "date:cessation_upper": "1978-12-31",
    "date:inception_lower": "1978-01-01",
    "date:inception_upper": "1978-12-31",
    "iso:country": "XX",
    "millsfield:images": [
      1527850169,
      1527850171,
      1527850173
    ],
    "millsfield:primary_image": 1527850169,
    "sfomuseum:accession_number": "2002.127.671",
    "sfomuseum:aircraft": "McDonnell Douglas DC-10",
    "sfomuseum:airline": "Western Airlines",
    "sfomuseum:category": "Passenger Amenity, Archive",
    "sfomuseum:collection": "Aviation Archive",
    "sfomuseum:creditline": "Gift of Thomas G. Dragges",
    "sfomuseum:date": "1978",
    "sfomuseum:date_acquired": "2003-12-22",
    "sfomuseum:daterange_end": "1978-12-31",
    "sfomuseum:daterange_start": "1978-01-01",
    "sfomuseum:description": "Safety information card issued by Western Airlines for its McDonnell Douglas DC-10 fleet; double-sided bi-fold sheet with illustrations and text in English and Spanish demonstrating safety instructions and emergency procedures; information code SF-626 Rev. 3/78.",
    "sfomuseum:dimensions": "7 x 10 inches (17.8 x 25.4 cm)",
    "sfomuseum:media_ids": [
      1527850169,
      1527850171
    ],
    "sfomuseum:medium": "paper, ink",
    "sfomuseum:placetype": "object",
    "sfomuseum:publication": ": , 1978.",
    "sfomuseum:subcategory": "Safety Information Card",
    "wof:depicts": [
      1159294431,
      1159293083,
      1159291259,
      1159293561,
      1159287595
    ],
    "wof:name": "safety information card: Western Airlines, McDonnell Douglas DC-10",
    "wof:placetype": "custom",
    "wof:placetype_alt": "object"
  },
  "geometry": {"coordinates":[-122.386155,37.616357],"type":"Point"}
}
