{
  "type": "Feature",
  "properties": {
    "date:cessation_lower": "1931-01-01",
    "date:cessation_upper": "1931-12-31",
    "date:inception_lower": "1931-01-01",
    "date:inception_upper": "1931-12-31",
    "iso:country": "XX",
    "millsfield:images": [
      1527821401
    ],
    "millsfield:primary_image": 1527821401,
    "sfomuseum:accession_number": "2011.032.0125",
    "sfomuseum:airport": "San Francisco Airport",
    "sfomuseum:category": "Photograph",
    "sfomuseum:collection": "Aviation Archive",
    "sfomuseum:creditline": "Transfer",
    "sfomuseum:date": "c. 1931",
    "sfomuseum:daterange_end": "1936-12-31",
    "sfomuseum:daterange_start": "1926-01-01",
    "sfomuseum:description": "Black and white photographic negative depicting man with clipboard, standing outdoors in front of surveying equipment, releasing meteorological weather balloon; Pilot Balloon (Pibal) Optical Theodolite; Mills Field Municipal Airport of San Francisco.",
    "sfomuseum:dimensions": "4 x 5 inches (10.2 x 12.7 cm)",
    "sfomuseum:media_ids": [
      1527821401
    ],
    "sfomuseum:medium": "acetate negative",
    "sfomuseum:placetype": "object",
    "sfomuseum:subcategory": "Negative",
    "wof:depicts": [
      102527513,
      1360695655
    ],
    "wof:name": "negative: San Francisco Airport, meteorological equipment",
    "wof:placetype": "venue"
  },
  "geometry": {"coordinates":[-122.386155,37.616357],"type":"Point"}
}
