{
  "type": "Feature",
  "properties": {
    "date:cessation_lower": "1987-01-01",
    "date:cessation_upper": "1987-12-31",
    "date:inception_lower": "1987-01-01",
    "date:inception_upper": "1987-12-31",
    "iso:country": "XX",
    "sfomuseum:accession_number": "2008.055.024",
    "sfomuseum:aircraft": "Boeing 727",
    "sfomuseum:author": "Smith, Paul R.",
    "sfomuseum:callnumber": "TL686.B65 S54 1987",
    "sfomuseum:category": "Book",
    "sfomuseum:collection": "Aviation Library",
    "sfomuseum:creditline": "Gift of the William Hough Collection",
    "sfomuseum:date": "1987",
    "sfomuseum:daterange_end": "1987-12-31",
    "sfomuseum:daterange_start": "1987-01-01",
    "sfomuseum:description": "64 p. : col. ill. ; 20 x 25 cm.",
    "sfomuseum:medium": "paper, ink",
    "sfomuseum:placetype": "object",
    "sfomuseum:publication": "New York: Jane's Pub., 1987.",
    "sfomuseum:publisher": "Jane's Pub.",
    "sfomuseum:publisher_location": "New York",
    "sfomuseum:series": "Air Portfolios ; 5",
    "sfomuseum:subcategory": "Book",
    "sfomuseum:subject": "Boeing 727 (Jet transports)",
    "wof:depicts": [
      1159293593,
      1159289759
    ],
    "wof:name": "Boeing 727",
    "wof:placetype": "venue"
  },
  "geometry": {"coordinates":[-122.386155,37.616357],"type":"Point"}
}
