{
  "type": "Feature",
  "properties": {
    "date:cessation_lower": "1935-12-31",
    "date:cessation_upper": "1935-12-31",
    "date:inception_lower": "1925-01-01",
    "date:inception_upper": "1925-01-01",
    "iso:country": "XX",
    "sfomuseum:accession_number": "2000.057.022",
    "sfomuseum:aircraft": "Ford Tri-Motor",
    "sfomuseum:airline": "Transcontinental \u0026 Western Air  (TWA (Trans World Airlines))",
    "sfomuseum:category": "Promotional",
    "sfomuseum:collection": "Aviation Archive",
    "sfomuseum:creditline": "Purchase",
    "sfomuseum:date": "c. 1930",
    "sfomuseum:daterange_end": "1935-12-31",
    "sfomuseum:daterange_start": "1925-01-01",
    "sfomuseum:description": "Brochure titled “The Lindbergh Line, Standard Air Line Of The World “. Cream colored and black. Middle has three Ford Tri-motors, each with a word under each: Air Travel, Air mail and Air Express. Service mark on upper right has words \"The Lindbergh Line.\" ",
    "sfomuseum:medium": "print on paper",
    "sfomuseum:placetype": "object",
    "sfomuseum:subcategory": "Brochure, Airline",
    "wof:depicts": [
      1159285395,
      1159292297
    ],
    "wof:name": "brochure: Transcontinental \u0026 Western Air (TWA), Ford Tri-Motor",
    "wof:placetype": "venue"
  },
  "geometry": {"coordinates":[-122.386155,37.616357],"type":"Point"}
}
