{
  "type": "Feature",
  "properties": {
    "date:cessation_lower": "1930-01-01",
    "date:cessation_upper": "1930-12-31",
    "date:inception_lower": "1930-01-01",
    "date:inception_upper": "1930-12-31",
    "iso:country": "XX",
    "millsfield:images": [
      1729565569,
      1729565571
    ],
    "millsfield:primary_image": 1729565571,
    "sfomuseum:accession_number": "2000.057.022",
    "sfomuseum:aircraft": "Ford Tri-Motor",
    "sfomuseum:airline": "Transcontinental \u0026 Western Air",
    "sfomuseum:category": "Promotional, Archive",
    "sfomuseum:collection": "Aviation Archive",
    "sfomuseum:creditline": "Purchase",
    "sfomuseum:date": "c. 1930",
    "sfomuseum:date_acquired": "2000-08-22",
    "sfomuseum:daterange_end": "1935-12-31",
    "sfomuseum:daterange_start": "1925-01-01",
    "sfomuseum:description": "Brochure issued by Transcontinental \u0026 Western Air (TWA) promoting air travel, freight, and mail; off-white and black cover with illustrations of three Ford Tri-motor aircraft.",
    "sfomuseum:dimensions": "6 x 3 1/4 inches (15.2 x 8.3 cm)",
    "sfomuseum:medium": "paper, ink",
    "sfomuseum:placetype": "object",
    "sfomuseum:publication": ": , c. 1930.",
    "sfomuseum:subcategory": "Brochure, Airline",
    "wof:depicts": [
      1159285395,
      1159292297
    ],
    "wof:name": "brochure: Transcontinental \u0026 Western Air (TWA), Ford Tri-Motor",
    "wof:placetype": "custom",
    "wof:placetype_alt": "object"
  },
  "geometry": {"coordinates":[-122.386155,37.616357],"type":"Point"}
}
