{
  "type": "Feature",
  "properties": {
    "date:cessation_lower": "1989-12-31",
    "date:cessation_upper": "1989-12-31",
    "date:inception_lower": "1989-01-01",
    "date:inception_upper": "1989-01-01",
    "iso:country": "XX",
    "sfomuseum:accession_number": "2009.122.413",
    "sfomuseum:category": "Scheduling / Ticketing",
    "sfomuseum:collection": "Aviation Archive",
    "sfomuseum:creditline": "Gift of the William Hough Collection",
    "sfomuseum:date": "1989",
    "sfomuseum:daterange_end": "1989-12-31",
    "sfomuseum:daterange_start": "1989-01-01",
    "sfomuseum:description": "World timetable issued by KLM (Royal Dutch Airlines), effective March 26 through September 24, 1989; 122-page fold-out schedule. The cover is full color photographic image of blue sky with airplane in flight with clouds.",
    "sfomuseum:media_ids": [
      1527845861
    ],
    "sfomuseum:medium": "paper, ink",
    "sfomuseum:placetype": "object",
    "sfomuseum:subcategory": "Timetable",
    "wof:name": "timetable: KLM (Royal Dutch Airlines), World edition",
    "wof:placetype": "venue"
  },
  "geometry": {"coordinates":[-122.386155,37.616358],"type":"Point"}
}
