{
  "type": "Feature",
  "properties": {
    "date:cessation_lower": "1920-01-01",
    "date:cessation_upper": "1920-12-31",
    "date:inception_lower": "1920-01-01",
    "date:inception_upper": "1920-12-31",
    "iso:country": "XX",
    "loc:subject_headings": [
      "sh85001319"
    ],
    "sfomuseum:accession_number": "2000.160.1428",
    "sfomuseum:author": "Sweetser, Arthur",
    "sfomuseum:callnumber": "TL545 .S84 1920 SC",
    "sfomuseum:category": "Book",
    "sfomuseum:collection": "Aviation Library",
    "sfomuseum:creditline": "The Tony Bill Aviation Library Collection",
    "sfomuseum:date": "1920",
    "sfomuseum:date_acquired": "1999-05-18",
    "sfomuseum:daterange_end": "1920-12-31",
    "sfomuseum:daterange_start": "1920-01-01",
    "sfomuseum:description": "7 p. æ., 112, [1] p. front. 20 cm.",
    "sfomuseum:description_library": "7 p. æ., 112, [1] p. front. 20 cm.",
    "sfomuseum:medium": "paper, ink",
    "sfomuseum:notes_library": "Reprinted in part from the New York Evening Post.",
    "sfomuseum:placetype": "object",
    "sfomuseum:publication": "New York; London: Harper \u0026 Brothers, 1920.",
    "sfomuseum:publisher": "Harper \u0026 Brothers",
    "sfomuseum:publisher_location": "New York; London",
    "sfomuseum:subcategory": "Book",
    "sfomuseum:subject": "Aeronautics.",
    "wof:name": "Opportunities in aviation",
    "wof:placetype": "venue"
  },
  "geometry": {"coordinates":[-122.386155,37.616357],"type":"Point"}
}
