{
  "type": "Feature",
  "properties": {
    "date:cessation_lower": "1950-12-31",
    "date:cessation_upper": "1950-12-31",
    "date:inception_lower": "1940-01-01",
    "date:inception_upper": "1940-01-01",
    "iso:country": "XX",
    "millsfield:images": [
      1527820869
    ],
    "sfomuseum:accession_number": "2008.056.1030",
    "sfomuseum:airline": "Pan American Airways  (Pan American World Airways)",
    "sfomuseum:category": "Photograph",
    "sfomuseum:collection": "Aviation Archive",
    "sfomuseum:creditline": "Gift of Jon E. Krupnick",
    "sfomuseum:date": "c. 1945",
    "sfomuseum:daterange_end": "1950-12-31",
    "sfomuseum:daterange_start": "1940-01-01",
    "sfomuseum:description": "Black and white photograph depicting profile view of Hudson bomber in flight, PAA ferries; image taken from parallel aircraft in flight, with partial closeup view of wing at bottom left.",
    "sfomuseum:dimensions": "8 x 10 inches (20.3 x 25.4 cm)",
    "sfomuseum:issues_held": "\r",
    "sfomuseum:media_ids": [
      1527820869
    ],
    "sfomuseum:medium": "photograph",
    "sfomuseum:placetype": "object",
    "sfomuseum:subcategory": "Print, Photograph",
    "sfomuseum:subject": "Airlines -- Commercial -- Pan American World Airways",
    "wof:depicts": [
      1159284991,
      1159291067
    ],
    "wof:name": "photograph: Pan American Airways, Hudson bomber in flight",
    "wof:placetype": "venue"
  },
  "geometry": {"coordinates":[-122.386155,37.616357],"type":"Point"}
}
