{
  "type": "Feature",
  "properties": {
    "date:cessation_lower": "2003-01-01",
    "date:cessation_upper": "2003-12-31",
    "date:inception_lower": "2003-01-01",
    "date:inception_upper": "2003-12-31",
    "isbn:number": "1400049121 (Hardcover), 9781400049127 (Hardcover)",
    "iso:country": "XX",
    "loc:named_authorities": [
      "n79077415"
    ],
    "sfomuseum:accession_number": "2004.004.001",
    "sfomuseum:author": "Adams, Noah",
    "sfomuseum:callnumber": "TL540.W7 A64 2003",
    "sfomuseum:category": "Book",
    "sfomuseum:collection": "Aviation Library",
    "sfomuseum:creditline": "Collection of SFO Museum",
    "sfomuseum:date": "c. 2003",
    "sfomuseum:date_acquired": "2004-12-31",
    "sfomuseum:daterange_end": "2008-12-31",
    "sfomuseum:daterange_start": "1998-01-01",
    "sfomuseum:description": "xv, 212 p. : ill. ; 22 cm.",
    "sfomuseum:description_library": "xv, 212 p. : ill. ; 22 cm.",
    "sfomuseum:medium": "paper, ink",
    "sfomuseum:placetype": "object",
    "sfomuseum:publication": "New York: Crown, c. 2003.",
    "sfomuseum:publisher": "Crown",
    "sfomuseum:publisher_location": "New York",
    "sfomuseum:subcategory": "Book",
    "sfomuseum:subject": "Wright, Wilbur, 1867-1912.",
    "wof:name": "The flyers: in search of Wilbur and Orville Wright",
    "wof:placetype": "custom",
    "wof:placetype_alt": [
      "object"
    ]
  },
  "geometry": {"coordinates":[-122.386155,37.616357],"type":"Point"}
}
