{
  "type": "Feature",
  "properties": {
    "date:cessation_lower": "1984-01-01",
    "date:cessation_upper": "1984-12-31",
    "date:inception_lower": "1984-01-01",
    "date:inception_upper": "1984-12-31",
    "iso:country": "XX",
    "millsfield:images": [
      1527853313,
      1527858269,
      1527858271
    ],
    "millsfield:primary_image": 1527858269,
    "sfomuseum:accession_number": "2006.010.799",
    "sfomuseum:airline": "Avianca Airlines",
    "sfomuseum:category": "Promotional",
    "sfomuseum:collection": "Aviation Museum",
    "sfomuseum:creditline": "Gift of the William Hough Collection",
    "sfomuseum:date": "1984",
    "sfomuseum:date_acquired": "2010-08-04",
    "sfomuseum:daterange_end": "1984-12-31",
    "sfomuseum:daterange_start": "1984-01-01",
    "sfomuseum:description": "Desk calendar issued by Avianca Airlines for 1985; spiral bound; color illustrations of aircraft from the airline’s different eras with brief descriptions.",
    "sfomuseum:dimensions": "8 1/4 x 7 3/4 inches (21 x 19.7 cm)",
    "sfomuseum:media_ids": [
      1527853313,
      1527858269,
      1527858271
    ],
    "sfomuseum:medium": "paper, plastic, ink",
    "sfomuseum:placetype": "object",
    "sfomuseum:publication": ": , 1984.",
    "sfomuseum:subcategory": "Calendar, Wall / Desk",
    "wof:depicts": [
      1159287217,
      1159283957
    ],
    "wof:name": "desk calendar: Avianca Airlines, 1985",
    "wof:placetype": "custom",
    "wof:placetype_alt": "object"
  },
  "geometry": {"coordinates":[-122.386155,37.616357],"type":"Point"}
}
