{
  "type": "Feature",
  "properties": {
    "date:cessation_lower": "1934-01-01",
    "date:cessation_upper": "1934-12-31",
    "date:inception_lower": "1934-01-01",
    "date:inception_upper": "1934-12-31",
    "iso:country": "XX",
    "sfomuseum:accession_number": "00-2516",
    "sfomuseum:author": "Aeronautical Chamber of Commerce of America",
    "sfomuseum:callnumber": "TL501 .A5631 1936 c.3 SC",
    "sfomuseum:category": "Book",
    "sfomuseum:collection": "Aviation Library",
    "sfomuseum:date": "c. 1934",
    "sfomuseum:daterange_end": "1939-12-31",
    "sfomuseum:daterange_start": "1929-01-01",
    "sfomuseum:description": "v.\u003c1936-1938\u003e fronts., illus. 21 cm.",
    "sfomuseum:description_library": "v.\u003c1936-1938\u003e fronts., illus. 21 cm.",
    "sfomuseum:medium": "paper, ink",
    "sfomuseum:placetype": "object",
    "sfomuseum:publication": "New York: Aeronautical chamber of commerce of America, Inc., c. 1934.",
    "sfomuseum:publisher": "Aeronautical chamber of commerce of America, Inc.",
    "sfomuseum:publisher_location": "New York",
    "sfomuseum:series": "1936 ",
    "sfomuseum:subcategory": "Book",
    "sfomuseum:subject": "Aeronautics United States.Aeronautics Yearbooks.",
    "wof:name": "Flying ....1936",
    "wof:placetype": "venue"
  },
  "geometry": {"coordinates":[-122.386155,37.616357],"type":"Point"}
}
