{
  "type": "Feature",
  "properties": {
    "date:cessation_lower": "1993-01-01",
    "date:cessation_upper": "1993-12-31",
    "date:inception_lower": "1993-01-01",
    "date:inception_upper": "1993-12-31",
    "iso:country": "XX",
    "sfomuseum:accession_number": "99-0247",
    "sfomuseum:author": "Hillestad, Richard",
    "sfomuseum:callnumber": "TL725.3.S34 A37 1993",
    "sfomuseum:category": "Book",
    "sfomuseum:collection": "Aviation Library",
    "sfomuseum:date": "1993",
    "sfomuseum:daterange_end": "1993-12-31",
    "sfomuseum:daterange_start": "1993-01-01",
    "sfomuseum:description": "ix, 26 p. : map ; 29 cm.",
    "sfomuseum:description_library": "ix, 26 p. : map ; 29 cm.",
    "sfomuseum:medium": "paper, ink",
    "sfomuseum:placetype": "object",
    "sfomuseum:publication": "Santa Monica, CA: Rand, 1993.",
    "sfomuseum:publisher": "Rand",
    "sfomuseum:publisher_location": "Santa Monica, CA",
    "sfomuseum:subcategory": "Book",
    "sfomuseum:subject": "Schiphol (Airport)Risk assessment.Aircraft accidents.Airports Safety measures.",
    "wof:name": "Airport growth and safety: executive summary of the Schiphol project",
    "wof:placetype": "venue"
  },
  "geometry": {"coordinates":[-122.386155,37.616357],"type":"Point"}
}
