{
  "type": "Feature",
  "properties": {
    "date:cessation_lower":"1983-12-31",
    "date:cessation_upper":"1983-12-31",
    "date:inception_lower":"1983-01-01",
    "date:inception_upper":"1983-01-01",
    "iso:country":"XX",
    "sfomuseum:accession_number":"2000.058.1138",
    "sfomuseum:artist":"John T. McCoy",
    "sfomuseum:category":"Food Service",
    "sfomuseum:collection":"Aviation Museum",
    "sfomuseum:creditline":"Gift of the Pan Am Association",
    "sfomuseum:date":"1983",
    "sfomuseum:daterange_end":"1983-12-31",
    "sfomuseum:daterange_start":"1983-01-01",
    "sfomuseum:description":"Menu produced by Pan American World Airways; white cover with color reproduction of a watercolor of a Clipper first flight of Sikorsky S-40 with caption, \"American Clipper, the first Pan American four-engine aircraft, departs Dinner Key, Miami for Cristobal on its inaugural flight, November 19, 1931\" by John T. McCoy with information about historic flight and artist on inside cover, menu items include breakfast selections; menu number: 756C; class: Clipper (business); date: 10-20-83.",
    "sfomuseum:medium":"paper, ink",
    "sfomuseum:placetype":"object",
    "sfomuseum:subcategory":"Menu",
    "wof:name":"menu: Pan American World Airways, Historic First Flights series, Sikorsky S-40",
    "wof:placetype":"venue"
},
  "geometry": {"coordinates":[-122.386155,37.616358],"type":"Point"}
}