{
  "type": "Feature",
  "properties": {
    "date:cessation_lower": "1983-01-01",
    "date:cessation_upper": "1983-12-31",
    "date:inception_lower": "1983-01-01",
    "date:inception_upper": "1983-12-31",
    "iso:country": "XX",
    "millsfield:images": [
      1527846539,
      1527846547
    ],
    "millsfield:primary_image": 1527846539,
    "sfomuseum:accession_number": "2000.058.1138",
    "sfomuseum:aircraft": "Sikorsky (USA) S-40",
    "sfomuseum:airline": "Pan American World Airways",
    "sfomuseum:artist": "John T. McCoy",
    "sfomuseum:category": "Passenger Amenity, Archive",
    "sfomuseum:collection": "Aviation Archive",
    "sfomuseum:creditline": "Gift of the Pan Am Association",
    "sfomuseum:date": "1983",
    "sfomuseum:date_acquired": "2000-12-14",
    "sfomuseum:daterange_end": "1983-12-31",
    "sfomuseum:daterange_start": "1983-01-01",
    "sfomuseum:description": "Menu issued by Pan American World Airways; white cover with color reproduction of a watercolor of a Clipper first flight of Sikorsky S-40 with caption, \"American Clipper, the first Pan American four-engine aircraft, departs Dinner Key, Miami for Cristobal on its inaugural flight, November 19, 1931\" by John T. McCoy with information about historic flight and artist on inside cover, menu items include breakfast selections; menu number: 756C; class: Clipper (business); date: 10-20-83.",
    "sfomuseum:dimensions": "5 x 7 inches (12.7 x 17.8 cm)",
    "sfomuseum:media_ids": [
      1527846539,
      1527846547
    ],
    "sfomuseum:medium": "paper, ink",
    "sfomuseum:placetype": "object",
    "sfomuseum:publication": ": , 1983.",
    "sfomuseum:series": "Historic First Flights Series; cover illustrations by John T. McCoy",
    "sfomuseum:subcategory": "Menu",
    "wof:depicts": [
      1159291657,
      1159284989,
      1159286839
    ],
    "wof:name": "menu: Pan American World Airways, Historic First Flights series, Sikorsky S-40",
    "wof:placetype": "custom",
    "wof:placetype_alt": "object"
  },
  "geometry": {"coordinates":[-122.386155,37.616357],"type":"Point"}
}
