{
  "type": "Feature",
  "properties": {
    "date:cessation_lower": "1953-12-31",
    "date:cessation_upper": "1953-12-31",
    "date:inception_lower": "1953-01-01",
    "date:inception_upper": "1953-01-01",
    "iso:country": "XX",
    "sfomuseum:accession_number": "2014.156.199",
    "sfomuseum:category": "Philately",
    "sfomuseum:collection": "Aviation Archive",
    "sfomuseum:creditline": "Gift of Captain Jon Simmonds",
    "sfomuseum:date": "05/29/1953",
    "sfomuseum:daterange_end": "1953-05-29",
    "sfomuseum:daterange_start": "1953-05-29",
    "sfomuseum:description": "Airmail flight cover commemorating 50th anniversary of Wright brothers flight, postmarked May 29, 1953, Dayton, Ohio, with four 6-cent postage stamps; black cachet at left with text, “First day of issue / Golden anniversary of aviation 1903 - 1953”; envelope addressed to Donald M. Stule.",
    "sfomuseum:media_ids": [
      1527856597, 
      1527856599
    ],
    "sfomuseum:medium": "paper, ink",
    "sfomuseum:placetype": "object",
    "sfomuseum:subcategory": "Airmail Flight Cover",
    "wof:name": "airmail flight cover: Wright brothers flight, 50th anniversary",
    "wof:placetype": "venue"
  },
  "geometry": {"coordinates":[-122.386155,37.616358],"type":"Point"}
}
