{
  "type": "Feature",
  "properties": {
    "date:cessation_lower": "1938-01-01",
    "date:cessation_upper": "1938-12-31",
    "date:inception_lower": "1938-01-01",
    "date:inception_upper": "1938-12-31",
    "iso:country": "XX",
    "millsfield:images": [
      1527840589
    ],
    "millsfield:images_texts": [
      "2і \" лібі\nMIS /R AIRLINES\nSERVICES\nSERVICES\nEGYPTIAN AIR\nMISR\nAIRLINES\nWINTER\n1938-39\nTIME-TABLE AND FARES"
    ],
    "millsfield:images_texts_ids": [
      1527840589
    ],
    "millsfield:primary_image": 1527840589,
    "sfomuseum:accession_number": "2005.132.088",
    "sfomuseum:airline": "Misr Airlines",
    "sfomuseum:category": "Scheduling / Ticketing",
    "sfomuseum:collection": "Aviation Archive",
    "sfomuseum:creditline": "Gift of the William Hough Collection",
    "sfomuseum:date": "1938",
    "sfomuseum:date_acquired": "2006-12-05",
    "sfomuseum:daterange_end": "1938-12-31",
    "sfomuseum:daterange_start": "1938-01-01",
    "sfomuseum:description": "Timetable issued by MISR Airlines, effective October 15, 1938; multipage booklet; orange, blue, and gray cover with text, “Egyptian Air Services / Linking Egypt, Palestine, Syria, Iraq, Cyprus” and inset illustrations depicting landmarks in Middle East; 24 pages.",
    "sfomuseum:dimensions": "10 1/2 x 4 1/4 inches (26.7 x 10.8 cm)",
    "sfomuseum:media_ids": [
      1527840589
    ],
    "sfomuseum:medium": "paper, ink",
    "sfomuseum:placetype": "object",
    "sfomuseum:publication": ": , 1938.",
    "sfomuseum:subcategory": "Timetable",
    "wof:depicts": [
      1159287477,
      1159284809
    ],
    "wof:name": "timetable: MISR Airlines",
    "wof:placetype": "custom",
    "wof:placetype_alt": [
      "object"
    ]
  },
  "geometry": {"coordinates":[-122.386155,37.616357],"type":"Point"}
}
