{
  "type": "Feature",
  "properties": {
    "date:cessation_lower": "1947-01-01",
    "date:cessation_upper": "1947-12-31",
    "date:inception_lower": "1947-01-01",
    "date:inception_upper": "1947-12-31",
    "iso:country": "XX",
    "millsfield:images": [
      1527848647
    ],
    "millsfield:primary_image": 1527848647,
    "sfomuseum:accession_number": "2001.009.005",
    "sfomuseum:airline": "American Airlines",
    "sfomuseum:category": "Passenger Amenity",
    "sfomuseum:collection": "Aviation Archive",
    "sfomuseum:creditline": "Jane Glickman Cavala",
    "sfomuseum:date": "1947",
    "sfomuseum:daterange_end": "1947-12-31",
    "sfomuseum:daterange_start": "1947-01-01",
    "sfomuseum:description": "Seat occupied card issued by American Airlines; white background with red and blue print; image of empty airline seat with \"Sorry / This seat occupied! / Asiento Ocupado! / Lo sentimos mucho\"; company logo in red located lower right corner.",
    "sfomuseum:dimensions": "4 1/2 x 7 1/4 inches (11.4 x 18.4 cm)",
    "sfomuseum:media_ids": [
      1527848647
    ],
    "sfomuseum:medium": "paper, ink",
    "sfomuseum:placetype": "object",
    "sfomuseum:subcategory": "Seat Occupied Message",
    "sfomuseum:subject": "Airlines -- Commercial -- American",
    "wof:depicts": [
      1159283849
    ],
    "wof:name": "seat occupied card: American Airlines",
    "wof:placetype": "venue"
  },
  "geometry": {"coordinates":[-122.386155,37.616357],"type":"Point"}
}
