{
  "type": "Feature",
  "properties": {
    "date:cessation_lower": "2004-12-31",
    "date:cessation_upper": "2004-12-31",
    "date:inception_lower": "1985-01-01",
    "date:inception_upper": "1985-01-01",
    "iso:country": "AU",
    "sfomuseum:accession_number": "1999.045.003",
    "sfomuseum:airline": "Qantas Airways",
    "sfomuseum:category": "Promotional",
    "sfomuseum:collection": "Aviation Museum",
    "sfomuseum:continent": "Australia",
    "sfomuseum:creditline": "Gift of Qantas Airways Limited",
    "sfomuseum:date": "c. 1990s",
    "sfomuseum:daterange_end": "2004-12-31",
    "sfomuseum:daterange_start": "1985-01-01",
    "sfomuseum:description": "\"Fly to Australia So Near.\" Male and female figure sitting on patio that overlooks beach.  Woman is wearing a full piece bathing suit with her feet propped up on small glass table. ",
    "sfomuseum:dimensions": "11 3/4 x 8 1/2 inches (29.8 x 21.6 cm)",
    "sfomuseum:medium": "photographic reproduction",
    "sfomuseum:placetype": "object",
    "sfomuseum:subcategory": "Advertisement, 3D",
    "wof:depicts": [
      1159283999,
      1159285043
    ],
    "wof:name": "promotional print: BOAC (British Overseas Airways Corporation) and Qantas Airways",
    "wof:placetype": "venue"
  },
  "geometry": {"coordinates":[-122.386155,37.616357],"type":"Point"}
}
