{
  "type": "Feature",
  "properties": {
    "date:cessation_lower": "1990-01-01",
    "date:cessation_upper": "1999-12-31",
    "date:inception_lower": "1990-01-01",
    "date:inception_upper": "1999-12-31",
    "iso:country": "AU",
    "millsfield:images": [
      1729565191
    ],
    "millsfield:primary_image": 1729565191,
    "sfomuseum:accession_number": "1999.045.003",
    "sfomuseum:airline": "Qantas Airways",
    "sfomuseum:category": "Promotional, Museum",
    "sfomuseum:collection": "Aviation Museum",
    "sfomuseum:continent": "Australia",
    "sfomuseum:creditline": "Gift of Qantas Airways Limited",
    "sfomuseum:date": "c. 1990s",
    "sfomuseum:date_acquired": "2000-02-22",
    "sfomuseum:daterange_end": "2004-12-31",
    "sfomuseum:daterange_start": "1985-01-01",
    "sfomuseum:description": "Promotional print issued by BOAC (British Overseas Airways Corporation) and Qantas Empire Airways; color illustration of male and female figures sitting on patio overlooking beach.",
    "sfomuseum:dimensions": "11 3/4 x 8 1/2 inches (29.8 x 21.6 cm)",
    "sfomuseum:medium": "photographic reproduction",
    "sfomuseum:placetype": "object",
    "sfomuseum:publication": ": , c. 1990s.",
    "sfomuseum:subcategory": "Advertisement, 3D",
    "wof:depicts": [
      1159283999,
      1159285825,
      1159287479,
      1159285043
    ],
    "wof:name": "promotional print: BOAC (British Overseas Airways Corporation) and Qantas Empire Airways",
    "wof:placetype": "custom",
    "wof:placetype_alt": "object"
  },
  "geometry": {"coordinates":[-122.386155,37.616357],"type":"Point"}
}
