{
  "type": "Feature",
  "properties": {
    "date:cessation_lower": "1960-12-31",
    "date:cessation_upper": "1960-12-31",
    "date:inception_lower": "1960-01-01",
    "date:inception_upper": "1960-01-01",
    "iso:country": "XX",
    "millsfield:images": [
      1527837725
    ],
    "sfomuseum:accession_number": "2011.126.024.001",
    "sfomuseum:airline": "Northwest Orient Airlines",
    "sfomuseum:category": "Scheduling / Ticketing",
    "sfomuseum:collection": "Aviation Archive",
    "sfomuseum:creditline": "Gift of the Paul H. Kowalewski Collection",
    "sfomuseum:date": "1960",
    "sfomuseum:daterange_end": "1960-12-31",
    "sfomuseum:daterange_start": "1960-01-01",
    "sfomuseum:description": "Timetable issued by Northwest Orient Airlines, effective September 6 and September 16, 1960; white and blue cover with photographic image of airplane spanning both covers; “Northwest announces daily DC-8C Jet Service coast-to-coast” in red.",
    "sfomuseum:media_ids": [
      1527837725
    ],
    "sfomuseum:medium": "paper, ink",
    "sfomuseum:placetype": "object",
    "sfomuseum:subcategory": "Timetable",
    "wof:depicts": [
      1159284913
    ],
    "wof:name": "timetable: Northwest Orient Airlines",
    "wof:placetype": "venue"
  },
  "geometry": {"coordinates":[-122.386155,37.616357],"type":"Point"}
}
