{
  "type": "Feature",
  "properties": {
    "date:cessation_lower": "1978-01-01",
    "date:cessation_upper": "1978-12-31",
    "date:inception_lower": "1978-01-01",
    "date:inception_upper": "1978-12-31",
    "iso:country": "XX",
    "millsfield:images": [
      1527838715
    ],
    "millsfield:images_texts": [
      "/ UnITED\nWASHINGTON D.C./\nBALTIMORE\nOur Friendly TimeS EFFECTIVE DECEMBER 14, 1978\nTo Akroo. Ohio/\nCanton. Ohio, EST\n6.550 (N)\nFrom Akron, Ohio/\n1 11 503\nLARAINITE\nTo Atlanta. Ga\n5:150 (0) 8.305\nFrom Atlanta, Ga, EST\nTo Bakerstiald. CalIPSTI\n535-9732\n175/193 § YX*D\n325 /103 3 7X*CH\nFrom kore\nTo Buffalo, /\nNiagara Falls N..\n8866888\nFrom Suffalo,\n9.450 (1)\n82 121 5 9X%%\n2059 (N 7:45p\n1203(01 10280\nFrom Bakersfield, Cal. (PST)\n3981741\nTo Cedar Rapids/ (CST)\nранена\nFrom Cedar Rapids/,\nBEASTBaBES\nTI\nTo Charleston, W.V.\nXXADDADADD\n(N 424/126 4 9X0S\n8 450(0)\n897 / 54\n3.305\nTo Chattanooga,\nTrom oathere\nTo Boo\n08101 19 a\n60000 10 30\n1933 :\n**\n*68668888\nThe friendly skies of your land.\nThe friendly skies of your land.\n/ll UnITED AIRLInES\nUnITED AIRLINES"
    ],
    "millsfield:images_texts_ids": [
      1527838715
    ],
    "millsfield:primary_image": 1527838715,
    "sfomuseum:accession_number": "2006.059.101.015",
    "sfomuseum:airline": "United Airlines",
    "sfomuseum:category": "Scheduling / Ticketing",
    "sfomuseum:collection": "Aviation Archive",
    "sfomuseum:creditline": "Gift of the Paul Edward Fair Estate",
    "sfomuseum:date": "1978",
    "sfomuseum:date_acquired": "2006-10-19",
    "sfomuseum:daterange_end": "1978-12-31",
    "sfomuseum:daterange_start": "1978-01-01",
    "sfomuseum:description": "City timetable issued by United Airlines for service to and from Washington D.C. and Baltimore, effective December 14, 1978.",
    "sfomuseum:dimensions": "9 x 4 inches (22.9 x 10.2 cm)",
    "sfomuseum:media_ids": [
      1527838715
    ],
    "sfomuseum:medium": "paper, ink",
    "sfomuseum:placetype": "object",
    "sfomuseum:publication": ": , 1978.",
    "sfomuseum:subcategory": "Timetable",
    "wof:depicts": [
      1159285413,
      1159288779
    ],
    "wof:name": "timetable: United Airlines, Washington D.C. / Baltimore",
    "wof:placetype": "custom",
    "wof:placetype_alt": "object"
  },
  "geometry": {"coordinates":[-122.386155,37.616357],"type":"Point"}
}
