{
  "type": "Feature",
  "properties": {
    "date:cessation_lower": "1990-01-01",
    "date:cessation_upper": "1990-12-31",
    "date:inception_lower": "1990-01-01",
    "date:inception_upper": "1990-12-31",
    "iso:country": "XX",
    "millsfield:images": [
      1527830227
    ],
    "millsfield:primary_image": 1527830227,
    "sfomuseum:accession_number": "2004.045.027",
    "sfomuseum:airline": "Pan American World Airways",
    "sfomuseum:category": "Passenger Amenity, Archive",
    "sfomuseum:collection": "Aviation Archive",
    "sfomuseum:creditline": "The Estate of Fred Nott ",
    "sfomuseum:date": "1990",
    "sfomuseum:daterange_end": "1990-12-31",
    "sfomuseum:daterange_start": "1990-01-01",
    "sfomuseum:description": "Information guide, titled “Pan Am Travel Guide and Souvenir Menu”; white cover with illustration of globe in gray; includes menu with choice of Coq au Vin or spinach ravioli; tourist information includes \"Cruising... The Last Frontier\" and \"Famous Resorts... Miami, Florida\"; contains several color photographic advertisements.",
    "sfomuseum:dimensions": "8 1/4 x 5 3/4 inches (21 x 14.6 cm)",
    "sfomuseum:media_ids": [
      1527830227
    ],
    "sfomuseum:medium": "paper, ink",
    "sfomuseum:placetype": "object",
    "sfomuseum:publication": ": , 1990.",
    "sfomuseum:subcategory": "Menu",
    "sfomuseum:subject": "Airlines -- Commercial -- Pan American",
    "wof:depicts": [
      1159284989,
      1159286839
    ],
    "wof:name": "flight information guide and menu: Pan American World Airways",
    "wof:placetype": "custom",
    "wof:placetype_alt": "object"
  },
  "geometry": {"coordinates":[-122.386155,37.616357],"type":"Point"}
}
