{
  "type": "Feature",
  "properties": {
    "date:cessation_lower": "1990-12-31",
    "date:cessation_upper": "1990-12-31",
    "date:inception_lower": "1990-01-01",
    "date:inception_upper": "1990-01-01",
    "iso:country": "XX",
    "sfomuseum:accession_number": "2004.045.027",
    "sfomuseum:category": "Passenger Amenity",
    "sfomuseum:collection": "Aviation Archive",
    "sfomuseum:creditline": "The Estate of Fred Nott ",
    "sfomuseum:date": "1990",
    "sfomuseum:daterange_end": "1990-12-31",
    "sfomuseum:daterange_start": "1990-01-01",
    "sfomuseum:description": "Information guide, titled “Pan Am Travel Guide and Souvenir Menu”; white cover with turquoise print upper quadrant; illustration of globe in gray located lower quadrant; includes menu with choice of Coq au Vin or spinach ravioli; tourist information includes \"Cruising... The Last Frontier\" and \"Famous Resorts... Miami, Florida\"; contains several photographic full color advertisements throughout pamphlet ",
    "sfomuseum:media_ids": [
      1527830227
    ],
    "sfomuseum:medium": "paper, ink",
    "sfomuseum:placetype": "object",
    "sfomuseum:subcategory": "In-flight Information",
    "wof:name": "flight information guide and menu: Pan American World Airways",
    "wof:placetype": "venue"
  },
  "geometry": {"coordinates":[-122.386155,37.616358],"type":"Point"}
}
