{
  "type": "Feature",
  "properties": {
    "date:cessation_lower": "1960-01-01",
    "date:cessation_upper": "1969-12-31",
    "date:inception_lower": "1960-01-01",
    "date:inception_upper": "1969-12-31",
    "iso:country": "XX",
    "millsfield:exhibition_ids": [
      1159160381,
      1763594999
    ],
    "millsfield:images": [
      1729566709,
      1746312281,
      1746312283,
      1746312285,
      1746312287,
      1763172905
    ],
    "millsfield:images_texts": [
      "‡QANTAS\nAUSTRALIA'S ROUND THE WORLD AIRLINE",
      "^ T JET PASSENGER WITH\nQANTAS\nAUSTRALIA'S ROUND THE WORLD AIRLINE",
      "-JET PASSENGER WITH\nCANTAS\nAUSTRALIA'S ROUND THE WORLD AIRLINE",
      "AT JET PASSENGER WITH\n* DANTAS\nAUSTRALIA'S ROUND THE WORLD AIRLINE",
      "A-SET PASSENGER WITH\nAUSTRALIA'S ROUND THE WORLD\n‡ QANTAS\nAIRLINE",
      "- JET PASSENGER WITH\nQANTAS\nAUSTRALIA'S ROUND THE WORLD AIRLINE"
    ],
    "millsfield:images_texts_ids": [
      1729566709,
      1746312281,
      1746312283,
      1746312285,
      1746312287,
      1763172905
    ],
    "millsfield:on_view": 0,
    "millsfield:primary_image": 1763172905,
    "sfomuseum:accession_number": "2001.146.108",
    "sfomuseum:airline": "Qantas Empire Airways",
    "sfomuseum:category": "Promotional, Museum",
    "sfomuseum:collection": "Aviation Museum",
    "sfomuseum:creditline": "Gift of Thomas G. Dragges",
    "sfomuseum:date": "1960s",
    "sfomuseum:date_acquired": "2003-07-24",
    "sfomuseum:daterange_end": "1969-12-31",
    "sfomuseum:daterange_start": "1960-01-01",
    "sfomuseum:description": "Airline bag issued by Qantas Empire Airways; maroon background with white accents and piping; logotype on front zipper pocket; single white handle with wraparound zipper closure; text, \"A V-Jet Passenger With Qantas / Australia's Round the World Airline\"; wraparound zipper closure with one handle; five silver metal feet at bottom.",
    "sfomuseum:dimensions": "9 1/4 x 17 x 5 inches (23.5 x 43.2 x 12.7 cm)",
    "sfomuseum:exhibition_ids": [
      1232,
      1850
    ],
    "sfomuseum:medium": "synthetic textile, plastic, metal, leather, cardboard, ink",
    "sfomuseum:on_view": 1,
    "sfomuseum:placetype": "object",
    "sfomuseum:publication": ": , 1960s.",
    "sfomuseum:subcategory": "Airline Bag",
    "wof:depicts": [
      1159287479,
      1159285825
    ],
    "wof:name": "airline bag: Qantas Empire Airways",
    "wof:placetype": "custom",
    "wof:placetype_alt": "object"
  },
  "geometry": {"coordinates":[-122.386155,37.616357],"type":"Point"}
}
