{
  "type": "Feature",
  "properties": {
    "date:cessation_lower": "1974-12-31",
    "date:cessation_upper": "1974-12-31",
    "date:inception_lower": "1974-01-01",
    "date:inception_upper": "1974-01-01",
    "iso:country": "XX",
    "sfomuseum:accession_number": "2011.032.2639",
    "sfomuseum:category": "Photograph",
    "sfomuseum:collection": "Aviation Archive",
    "sfomuseum:creditline": "Transfer",
    "sfomuseum:date": "1974",
    "sfomuseum:daterange_end": "1974-12-31",
    "sfomuseum:daterange_start": "1974-01-01",
    "sfomuseum:description": "35mm photographic color negative depicting exterior view taken from upper level of Central Terminal (now Terminal 2 / T2) facing southwest of South Terminal (now Terminal 1 / T1) gates with parked aircraft; TWA (Trans World Airlines) 747 parked at gate; Millbrae and Burlingame visible in background.",
    "sfomuseum:media_ids": [
      1527828259
    ],
    "sfomuseum:medium": "negative",
    "sfomuseum:placetype": "object",
    "sfomuseum:subcategory": "Negative",
    "wof:name": "negative: San Francisco International Airport (SFO), South Terminal",
    "wof:placetype": "venue"
  },
  "geometry": {"coordinates":[-122.386155,37.616358],"type":"Point"}
}
