{
  "type": "Feature",
  "properties": {
    "date:cessation_lower": "1998-12-31",
    "date:cessation_upper": "1998-12-31",
    "date:inception_lower": "1988-01-01",
    "date:inception_upper": "1988-01-01",
    "iso:country": "XX",
    "sfomuseum:accession_number": "2004.004.024",
    "sfomuseum:author": "Brown, Don",
    "sfomuseum:callnumber": "TL540.L273 B760 1993 JUV",
    "sfomuseum:category": "Book",
    "sfomuseum:collection": "Aviation Library",
    "sfomuseum:creditline": "Purchase",
    "sfomuseum:date": "c. 1993",
    "sfomuseum:daterange_end": "1998-12-31",
    "sfomuseum:daterange_start": "1988-01-01",
    "sfomuseum:description": "32 p. : col. ill. ; 22 x 28 cm.",
    "sfomuseum:medium": "paper, ink",
    "sfomuseum:placetype": "object",
    "sfomuseum:publisher": "Houghton Mifflin",
    "sfomuseum:publisher_location": "Boston",
    "sfomuseum:series": "Soar to success",
    "sfomuseum:subcategory": "Book",
    "sfomuseum:subject": "Law, Ruth, 1887-  Juvenile literature.",
    "wof:name": "Ruth Law thrills a nation",
    "wof:placetype": "venue"
  },
  "geometry": {"coordinates":[-122.386155,37.616357],"type":"Point"}
}
