{
  "type": "Feature",
  "properties": {
    "date:cessation_lower": "1982-12-31",
    "date:cessation_upper": "1982-12-31",
    "date:inception_lower": "1982-01-01",
    "date:inception_upper": "1982-01-01",
    "iso:country": "XX",
    "sfomuseum:accession_number": "2009.122.568",
    "sfomuseum:category": "Scheduling / Ticketing",
    "sfomuseum:collection": "Aviation Archive",
    "sfomuseum:creditline": "Gift of the William Hough Collection",
    "sfomuseum:date": "1982",
    "sfomuseum:daterange_end": "1982-12-31",
    "sfomuseum:daterange_start": "1982-01-01",
    "sfomuseum:description": "Timetable issued by Sabena Belgian World Airlines, effective November 1, 1982 through March 26, 1983; eighty-eight page schedule; white cover with the company name in a blue oval at the top and a checkerboard design of gray clocks alternating with servicemark. In Dutch, French and English.",
    "sfomuseum:media_ids": [
      1527849623
    ],
    "sfomuseum:medium": "paper, ink",
    "sfomuseum:placetype": "object",
    "sfomuseum:subcategory": "Timetable",
    "wof:name": "timetable: Sabena Belgian World Airlines",
    "wof:placetype": "venue"
  },
  "geometry": {"coordinates":[-122.386155,37.616358],"type":"Point"}
}
