{
  "type": "Feature",
  "properties": {
    "date:cessation_lower": "1976-01-01",
    "date:cessation_upper": "1976-12-31",
    "date:inception_lower": "1976-01-01",
    "date:inception_upper": "1976-12-31",
    "isbn:number": "0870491962, 9780870491962",
    "iso:country": "XX",
    "sfomuseum:accession_number": "00-3720",
    "sfomuseum:author": "Morrow, John Howard",
    "sfomuseum:callnumber": "UG635.G3 M67 1976",
    "sfomuseum:category": "Book",
    "sfomuseum:collection": "Aviation Library",
    "sfomuseum:date": "c. 1976",
    "sfomuseum:daterange_end": "1981-12-31",
    "sfomuseum:daterange_start": "1971-01-01",
    "sfomuseum:description": "ix, 150 p. : ill. ; 19 x 26 cm.",
    "sfomuseum:description_library": "ix, 150 p. : ill. ; 19 x 26 cm.",
    "sfomuseum:medium": "paper, ink",
    "sfomuseum:placetype": "object",
    "sfomuseum:publication": "Knoxville: University of Tennessee Press, c. 1976.",
    "sfomuseum:publisher": "University of Tennessee Press",
    "sfomuseum:publisher_location": "Knoxville",
    "sfomuseum:subcategory": "Book",
    "sfomuseum:subject": "Aircraft industry Germany History.Aeronautics, Military Germany History.",
    "wof:name": "Building German airpower, 1909-1914",
    "wof:placetype": "custom",
    "wof:placetype_alt": "object"
  },
  "geometry": {"coordinates":[-122.386155,37.616357],"type":"Point"}
}
