{
  "type": "Feature",
  "properties": {
    "date:cessation_lower": "1968-01-01",
    "date:cessation_upper": "1968-12-31",
    "date:inception_lower": "1968-01-01",
    "date:inception_upper": "1968-12-31",
    "iso:country": "XX",
    "sfomuseum:accession_number": "00-3003",
    "sfomuseum:author": "Ingells, Douglas J.",
    "sfomuseum:callnumber": "TL686.F65 I54 1968 c.1",
    "sfomuseum:category": "Book",
    "sfomuseum:collection": "Aviation Library",
    "sfomuseum:date": "1968",
    "sfomuseum:daterange_end": "1968-12-31",
    "sfomuseum:daterange_start": "1968-01-01",
    "sfomuseum:description": "96 p. illus., maps, ports. 28 cm.",
    "sfomuseum:description_library": "96 p. illus., maps, ports. 28 cm.",
    "sfomuseum:medium": "paper, ink",
    "sfomuseum:placetype": "object",
    "sfomuseum:publication": "Fallbrook, CA: Aero Publishers, 1968.",
    "sfomuseum:publisher": "Aero Publishers",
    "sfomuseum:publisher_location": "Fallbrook, CA",
    "sfomuseum:subcategory": "Book",
    "sfomuseum:subject": "Transport planes History.Ford Motor Company.Ford Three-engined Monoplane (Transport plane)",
    "wof:name": "Tin Goose: the fabulous Ford trimotor",
    "wof:placetype": "custom",
    "wof:placetype_alt": "object"
  },
  "geometry": {"coordinates":[-122.386155,37.616357],"type":"Point"}
}
