{
  "type": "Feature",
  "properties": {
    "date:cessation_lower": "1994-01-01",
    "date:cessation_upper": "1994-12-31",
    "date:inception_lower": "1994-01-01",
    "date:inception_upper": "1994-12-31",
    "iso:country": "XX",
    "loc:named_authorities": {
      "n85015320": "Hauptmann, Bruno Richard, 1899-1936",
      "n86005571": "Lindbergh, Charles Augustus, 1930-1932"
    },
    "sfomuseum:accession_number": "2012.148.025",
    "sfomuseum:author": "Behn, Noel",
    "sfomuseum:callnumber": "HV6603.L53 B44 1994",
    "sfomuseum:category": "Book",
    "sfomuseum:collection": "Aviation Library",
    "sfomuseum:creditline": "Gift of the Captain John B. Russell Family",
    "sfomuseum:date": "1994",
    "sfomuseum:daterange_end": "1994-12-31",
    "sfomuseum:daterange_start": "1994-01-01",
    "sfomuseum:description": "x, 464 p. : ill. ; 24 cm.",
    "sfomuseum:edition": "1st ed.",
    "sfomuseum:medium": "paper, ink",
    "sfomuseum:placetype": "object",
    "sfomuseum:publication": "New York: Atlantic Monthly Press, 1994.",
    "sfomuseum:publisher": "Atlantic Monthly Press",
    "sfomuseum:publisher_location": "New York",
    "sfomuseum:subcategory": "Book",
    "sfomuseum:subject": "Lindbergh, Charles Augustus, 1930-1932.\rHauptmann, Bruno Richard, 1899-1936.\rKidnapping -- New Jersey -- Hopewell -- History. \rTrials (Kidnapping) -- New Jersey -- History. \rHauptmann, Richard \rLindbergh, Charles A. \rKindesentziehung",
    "wof:name": "Lindbergh: the crime 1st ed.",
    "wof:placetype": "venue"
  },
  "geometry": {"coordinates":[-122.386155,37.616357],"type":"Point"}
}
