{
  "type": "Feature",
  "properties": {
    "date:cessation_lower": "1982-01-01",
    "date:cessation_upper": "1982-12-31",
    "date:inception_lower": "1982-01-01",
    "date:inception_upper": "1982-12-31",
    "iso:country": "XX",
    "millsfield:images": [
      1527840813
    ],
    "millsfield:images_texts": [
      "Muse Ain\nFLIGHT SCHEDULE\nHouston/Hobby to Dallas/Love Field\nschedule effective March 15, 1982\nFlight\nMon thru\nNumber\nSunday\nFri\nSaturday\n802\n7:00a\n804\n8:10\n8:10a\n806\n9:20a\n9:20\n808\n10:30\n10:30\n810\n11:40\n11:40\n812\n1:10p\n1:10p\n1:10p\n814\n2:20\n2:20\n816\n3:30\n3:30\n3:30\n818\n4:40\n4:40\n820\n5:50\n5:50\n5:50\n822\n7:00\n7:00\n824\n8:10\n8:10\n8:10\n826\n9:30\n9:30*\nAll flights are scheduled to arrive 50 minutes later.\nPrime Time flights\nLeisure Time flights\n* Flight 826 weekdays $20.\nFor reservations in Houston 222-2828\nDallas/Love Field to Houston/Hobby\nschedule effective March 15, 1982\nFlight\nMon thru\nNumber\nSunday\nFri\nSaturday\n803\n7:00a\n805\n8:10a\n8:10\n807\n9:20\n9:20\n809\n10:30\n10:30\n811\n11:40\n11:40\n11:40\n813\n1:10p\n1:10p\n815\n2:20\n2:20\n2:20р\n817\n3:30\n3:30\n819\n4:40\n4:40\n4:40\n821\n5:50\n5:50\n823\n7:00\n7:00\n7:00\n825\n8:10\n8:10\n827\n9:30\n9:30*\nAll flights are scheduled to arrive 50 minutes later.\n• Prime Time flights\n• Leisure Time flights\n* Flight 827 weekdays $20.\nFor reservations in Dallas 352-2828\nin Fort Worth Metro 263-2828"
    ],
    "millsfield:images_texts_ids": [
      1527840813
    ],
    "millsfield:primary_image": 1527840813,
    "sfomuseum:accession_number": "2008.108.459",
    "sfomuseum:airline": "Muse Air",
    "sfomuseum:category": "Scheduling / Ticketing",
    "sfomuseum:collection": "Aviation Archive",
    "sfomuseum:creditline": "Gift of the William Hough Collection",
    "sfomuseum:date": "1982",
    "sfomuseum:date_acquired": "2008-11-10",
    "sfomuseum:daterange_end": "1982-12-31",
    "sfomuseum:daterange_start": "1982-01-01",
    "sfomuseum:description": "Timetable issued by Muse Air, effective March 15, 1982; light tan double-sided card listing flights between Dallas/Love Field and Houston/Hobby Field.",
    "sfomuseum:dimensions": "9 x 4 inches (22.9 x 10.2 cm)",
    "sfomuseum:media_ids": [
      1527840813
    ],
    "sfomuseum:medium": "paper, ink",
    "sfomuseum:placetype": "object",
    "sfomuseum:publication": ": , 1982.",
    "sfomuseum:subcategory": "Timetable",
    "sfomuseum:subject": "Airlines -- Commercial -- Muse Air",
    "wof:depicts": [
      1159284833,
      1159286705
    ],
    "wof:name": "timetable: Muse Air",
    "wof:placetype": "custom",
    "wof:placetype_alt": "object"
  },
  "geometry": {"coordinates":[-122.386155,37.616357],"type":"Point"}
}
