{
  "type": "Feature",
  "properties": {
    "date:cessation_lower": "1979-12-31",
    "date:cessation_upper": "1979-12-31",
    "date:inception_lower": "1970-01-01",
    "date:inception_upper": "1970-01-01",
    "iso:country": "XX",
    "millsfield:images": [
      1527858321,
      1527857139,
      1527857137,
      1527857133,
      1527857135
    ],
    "sfomuseum:accession_number": "2001.146.003",
    "sfomuseum:airline": "Braniff International Airways  (Braniff International)",
    "sfomuseum:category": "Promotional",
    "sfomuseum:collection": "Aviation Museum",
    "sfomuseum:creditline": "Gift of Thomas G. Dragges",
    "sfomuseum:date": "1970s",
    "sfomuseum:daterange_end": "1979-12-31",
    "sfomuseum:daterange_start": "1970-01-01",
    "sfomuseum:description": "Bright red bag with white piping; text, “Braniff International / Flying Colors” across front; two handles and zipper closure across top; four metallic rivets and designated space for personal identification on bottom.\r",
    "sfomuseum:maker": "Airline Textile MFG., Co. ",
    "sfomuseum:media_ids": [
      1527857133,
      1527857135,
      1527857137,
      1527857139,
      1527858321
    ],
    "sfomuseum:medium": "vinyl, metal, plastic, cardstock, laminate",
    "sfomuseum:placetype": "object",
    "sfomuseum:subcategory": "Airline Bag",
    "wof:depicts": [
      1159284009,
      1159286455
    ],
    "wof:name": "airline bag: Braniff International",
    "wof:placetype": "custom"
  },
  "geometry": {"coordinates":[-122.386155,37.616357],"type":"Point"}
}
