{
  "type": "Feature",
  "properties": {
    "date:cessation_lower": "1970-01-01",
    "date:cessation_upper": "1979-12-31",
    "date:inception_lower": "1970-01-01",
    "date:inception_upper": "1979-12-31",
    "iso:country": "XX",
    "millsfield:images": [
      1527857133,
      1527857135,
      1527857137,
      1527857139,
      1527858321
    ],
    "millsfield:images_texts": [
      "Braniff\nInternational\nFlying\nColors",
      "International\nFNN9\nColors",
      "Branitt\nInternationa\nFlying\nColors",
      "Fying\nColors",
      "Braniff\nInternational"
    ],
    "millsfield:images_texts_ids": [
      1527857133,
      1527857135,
      1527857137,
      1527857139,
      1527858321
    ],
    "millsfield:primary_image": 1527858321,
    "sfomuseum:accession_number": "2001.146.003",
    "sfomuseum:airline": "Braniff International",
    "sfomuseum:category": "Promotional, Museum",
    "sfomuseum:collection": "Aviation Museum",
    "sfomuseum:creditline": "Gift of Thomas G. Dragges",
    "sfomuseum:date": "1970s",
    "sfomuseum:date_acquired": "2003-07-24",
    "sfomuseum:daterange_end": "1979-12-31",
    "sfomuseum:daterange_start": "1970-01-01",
    "sfomuseum:description": "Airline bag issued by Braniff International, manufactured by Airline Textile Mfg. Co.; red background with red piping and logotype and text, “Flying Colors” on front pocket and back; adjustable shoulder strap and top zipper closure; four silver metal feet and personal information space at bottom. ",
    "sfomuseum:dimensions": "12 x 13 x 5 1/4 inches (30.5 x 33 x 13.3 cm)",
    "sfomuseum:maker": "Airline Textile Manufacturing Company",
    "sfomuseum:media_ids": [
      1527857133,
      1527857135,
      1527857137,
      1527857139,
      1527858321
    ],
    "sfomuseum:medium": "vinyl, metal, plastic, cardstock, laminate",
    "sfomuseum:placetype": "object",
    "sfomuseum:publication": ": , 1970s.",
    "sfomuseum:subcategory": "Airline Bag",
    "wof:depicts": [
      1159284009,
      1159286455,
      1159286951
    ],
    "wof:name": "airline bag: Braniff International",
    "wof:placetype": "custom",
    "wof:placetype_alt": "object"
  },
  "geometry": {"coordinates":[-122.386155,37.616357],"type":"Point"}
}
