{
  "type": "Feature",
  "properties": {
    "date:cessation_lower":"1970-12-31",
    "date:cessation_upper":"1970-12-31",
    "date:inception_lower":"1970-01-01",
    "date:inception_upper":"1970-01-01",
    "iso:country":"XX",
    "millsfield:images":[
        1527827837
    ],
    "sfomuseum:accession_number":"2011.032.2451",
    "sfomuseum:category":"Photograph",
    "sfomuseum:collection":"Aviation Archive",
    "sfomuseum:creditline":"Transfer",
    "sfomuseum:date":"1970",
    "sfomuseum:daterange_end":"1970-12-31",
    "sfomuseum:daterange_start":"1970-01-01",
    "sfomuseum:description":"Black and white photographic negative depicting McDonnell Road underpass, San Francisco International Airport (SFO).",
    "sfomuseum:media_ids":[
        1527827837
    ],
    "sfomuseum:medium":"negative",
    "sfomuseum:placetype":"object",
    "sfomuseum:subcategory":"Negative",
    "wof:depicts":[
        102527513
    ],
    "wof:name":"negative: San Francisco International Airport (SFO), McDonnell Road",
    "wof:placetype":"venue"
},
  "geometry": {"coordinates":[-122.386155,37.616358],"type":"Point"}
}