{
  "type": "Feature",
  "properties": {
    "date:cessation_lower": "1998-12-31",
    "date:cessation_upper": "1998-12-31",
    "date:inception_lower": "1998-01-01",
    "date:inception_upper": "1998-01-01",
    "iso:country": "XX",
    "sfomuseum:accession_number": "2018.075.021",
    "sfomuseum:author": "Farmer, Mark",
    "sfomuseum:callnumber": "TL540.F3 A3 1998 c.2",
    "sfomuseum:category": "Book",
    "sfomuseum:collection": "Aviation Library",
    "sfomuseum:creditline": "Gift of Captain Ross A. Butler Family",
    "sfomuseum:date": "1998",
    "sfomuseum:daterange_end": "1998-12-31",
    "sfomuseum:daterange_start": "1998-01-01",
    "sfomuseum:description": "228 p. : ill. ; 23 cm.",
    "sfomuseum:medium": "paper, ink",
    "sfomuseum:placetype": "object",
    "sfomuseum:publisher": "Coralreef Group",
    "sfomuseum:publisher_location": "Yountville, CA",
    "sfomuseum:subcategory": "Book",
    "sfomuseum:subject": "Air pilots United States Biography. Flight navigators United States Biography. Airplanes Piloting Anecdotes.\rPan American World Airways.",
    "wof:name": "Flight to anywhere: a navigator's life",
    "wof:placetype": "venue"
  },
  "geometry": {"coordinates":[-122.386155,37.616357],"type":"Point"}
}
