{
  "type": "Feature",
  "properties": {
    "date:cessation_lower": "1995-01-01",
    "date:cessation_upper": "1995-12-31",
    "date:inception_lower": "1995-01-01",
    "date:inception_upper": "1995-12-31",
    "isbn:number": "0884871789, 9780884871781",
    "iso:country": "XX",
    "loc:subject_headings": [
      "sh85084359"
    ],
    "sfomuseum:accession_number": "1999.659.108",
    "sfomuseum:author": "Lester, Peter F.",
    "sfomuseum:callnumber": "TL556 .L427 1995",
    "sfomuseum:category": "Book",
    "sfomuseum:collection": "Aviation Library",
    "sfomuseum:creditline": "Collection of SFO Museum",
    "sfomuseum:date": "1995",
    "sfomuseum:date_acquired": "1997-08-20",
    "sfomuseum:daterange_end": "1995-12-31",
    "sfomuseum:daterange_start": "1995-01-01",
    "sfomuseum:description": "1 v. (various pagings): ill. (some col.), maps (some col.) ; 28 cm.\r",
    "sfomuseum:description_library": "1 v. (various pagings): ill. (some col.), maps (some col.) ; 28 cm.\r",
    "sfomuseum:medium": "printed, bound paper",
    "sfomuseum:placetype": "object",
    "sfomuseum:publication": "Englewood, CO: Jeppesen Sanderson, 1995.",
    "sfomuseum:publisher": "Jeppesen Sanderson",
    "sfomuseum:publisher_location": "Englewood, CO",
    "sfomuseum:subcategory": "Book",
    "sfomuseum:subject": "Meteorology in aeronautics.",
    "wof:name": "Aviation weather",
    "wof:placetype": "custom",
    "wof:placetype_alt": "object"
  },
  "geometry": {"coordinates":[-122.386155,37.616357],"type":"Point"}
}
