{
  "type": "Feature",
  "properties": {
    "date:cessation_lower": "1980-01-01",
    "date:cessation_upper": "1980-12-31",
    "date:inception_lower": "1980-01-01",
    "date:inception_upper": "1980-12-31",
    "iso:country": "XX",
    "millsfield:images": [
      1527839821
    ],
    "millsfield:images_texts": [
      "GOLDEN GATE AIRLINES\nSchedule Supplement to the\nAugust 1, 1980\nSystem Time Table\nNEW ADDITIONAL FLIGHTS\n706 (Daily)\n750 (Except Sunday)\nLv Monterey\n3: 15p\nLv Stockton\n6:40a\nLv Bakersfield 4: 15p\nLv Modesto\n7: 15a\nAr Los Angeles 5:05p\nLv Los Angeles 8: 35a\n960 (Daily)\n709 (Daily)\nLv Los Angeles\n9:00p Lv Los Angeles\n5:25p\nAr Bakersfield\n9:45p Ar Bakersfield\n6:10р\nLv. Bakersfield\n10:05p Lv Bakersfield\n6: 30p\nAr Fresno\n10:40p Ar San Francisco\n7:50p\nLv Fresno\n11:00p\nAr Modesto\n11:35p 780 (Sunday Only)\nLv Modesto\n11:50p Lv Monterey\nAr Stockton\n1:30p\n12:10a Ar Los Angeles 2:45p\nCANCELLED FLIGHTS\nAll service to Santa Barbara and Las Vegas\nhas been cancelled. Also affected by these\ncancellations are the following:\n131 Stockton-Sacramento\n228 Sacramento-Stockton\n777 Sacramento-Los Angeles\n777 San Francisco-Los Angeles\n783 Los Angeles-Fresno\n783 Los Angeles-Merced\n783 Los Angeles-Modesto\n783 Los Angeles-Monterey\n783 Los Angeles-San Francisco\n822 Monterey-Los Angeles\n822 San Francisco-Los Angeles\n824 San Francisco-Los Angeles\n834 Monterey-San Francisco\n845 Bakersfield-Stockton-San Francisco\nAUGUST 9, 1980\nRevised"
    ],
    "millsfield:images_texts_ids": [
      1527839821
    ],
    "millsfield:primary_image": 1527839821,
    "sfomuseum:accession_number": "2008.108.337",
    "sfomuseum:airline": "Golden Gate Airlines",
    "sfomuseum:category": "Scheduling / Ticketing",
    "sfomuseum:collection": "Aviation Archive",
    "sfomuseum:creditline": "Gift of the William Hough Collection",
    "sfomuseum:date": "1980",
    "sfomuseum:date_acquired": "2008-11-10",
    "sfomuseum:daterange_end": "1980-12-31",
    "sfomuseum:daterange_start": "1980-01-01",
    "sfomuseum:description": "System timetable issued by Golden Gate Airlines, effective August 1, 1980; white supplement card listing changes to the existing schedule. ",
    "sfomuseum:dimensions": "9 x 4 inches (22.9 x 10.2 cm)",
    "sfomuseum:media_ids": [
      1527839821
    ],
    "sfomuseum:medium": "paper, ink",
    "sfomuseum:placetype": "object",
    "sfomuseum:publication": ": , 1980.",
    "sfomuseum:subcategory": "Timetable",
    "sfomuseum:subject": "Airlines -- Commercial -- Golden Gate",
    "wof:depicts": [
      1159284445,
      1159288283
    ],
    "wof:name": "timetable: Golden Gate Airlines",
    "wof:placetype": "custom",
    "wof:placetype_alt": [
      "object"
    ]
  },
  "geometry": {"coordinates":[-122.386155,37.616357],"type":"Point"}
}
