{
  "type": "Feature",
  "properties": {
    "date:cessation_lower": "1951-01-01",
    "date:cessation_upper": "1951-12-31",
    "date:inception_lower": "1951-01-01",
    "date:inception_upper": "1951-12-31",
    "iso:country": "XX",
    "millsfield:images": [
      1527838075,
      1527850749
    ],
    "millsfield:images_texts": [
      "COMPLETE TIMETABLE\nSEPT. 30, 1951\nSouthwest\nAirways\nASK ABOUT\n• ROUND TRIP DISCOUNT\n• FAMILY PLAN FARES\n• JOINT FARES\n(to eastern points)\nLEGEND",
      "Southwest Airways\nPACIFIC STANDARD TIME\nSouthwest\nAirways\nSOUTHBOUI\nNORTHBOUND\nMINE\n55599\nmirialmins\njiF\nMIglia.\nGeneral Information\nEQUIPMENT - Douglas DC.3'%\nRESERVATIONS - Reservations mouse be esede in advance and ase\ntentative until tickets are parchased.\ncamelithe reserratos o anse\nsenger who fails to g\nthe SOUTHWEST Airport tidket\nscheduled departure of flight on which his\nreservation was made (excer\nSCHEDULES - Schedules show the times at which planes may be\nwith otber\nSOUTHWEST\nAIRWAYS will no be responsible for cor\nsubject to change without notice.\nBAGGAGE- 40 pounds of perscoal buggage will be carried fres\nCHILDREN'S FARES -\nof age\nwith cach accoespasying passenger\nChiaro toro reste carace ad rede:\na8082\na la ala\nBAREEE\n13 83 49 B5\n5 ES ES\nSAVE 50% on Family Travel\n(in cilect Monday, Lucsday, Wednesday)\nwith con fell adale fare toe father ce enother, the whole family car\ntrip for HALF.FARE. This applies so all members\nose Mies for HALF.\non most coonecting airlines\nSAVE 10% on Return Trips\nBe caling advastage of use 3 per creet discount on gund trp fares you\nperenne\nSAVE Time\nSAVE Money\nUse Air Mail • Air Parcel Post • Air Express • Air Freight"
    ],
    "millsfield:images_texts_ids": [
      1527838075,
      1527850749
    ],
    "millsfield:primary_image": 1527838075,
    "sfomuseum:accession_number": "2005.132.047.007",
    "sfomuseum:airline": "Southwest Airways",
    "sfomuseum:category": "Scheduling / Ticketing",
    "sfomuseum:collection": "Aviation Archive",
    "sfomuseum:creditline": "Gift of the William Hough Collection",
    "sfomuseum:date": "1951",
    "sfomuseum:date_acquired": "2006-12-05",
    "sfomuseum:daterange_end": "1951-12-31",
    "sfomuseum:daterange_start": "1951-01-01",
    "sfomuseum:description": "Timetable issued by Southwest Airways, effective September 30, 1951; four page double-sided fold-out; dark green and yellow cover with a route map for destinations in California and Arizona.",
    "sfomuseum:dimensions": "9 x 4 inches (22.9 x 10.2 cm)",
    "sfomuseum:media_ids": [
      1527838075,
      1527850749
    ],
    "sfomuseum:medium": "paper, ink",
    "sfomuseum:placetype": "object",
    "sfomuseum:publication": ": , 1951.",
    "sfomuseum:subcategory": "Timetable",
    "wof:depicts": [
      1159284949,
      1159287837
    ],
    "wof:name": "timetable: Southwest Airways",
    "wof:placetype": "custom",
    "wof:placetype_alt": "object"
  },
  "geometry": {"coordinates":[-122.386155,37.616357],"type":"Point"}
}
