{
  "type": "Feature",
  "properties": {
    "date:cessation_lower":"1927-12-31",
    "date:cessation_upper":"1927-12-31",
    "date:inception_lower":"1927-01-01",
    "date:inception_upper":"1927-01-01",
    "iso:country":"XX",
    "sfomuseum:accession_number":"2000.018.027.001",
    "sfomuseum:category":"Company Record / Document",
    "sfomuseum:collection":"Aviation Archive",
    "sfomuseum:creditline":"Transfer from City and County of San Francisco",
    "sfomuseum:date":"1927",
    "sfomuseum:daterange_end":"1927-12-31",
    "sfomuseum:daterange_start":"1927-01-01",
    "sfomuseum:description":"Typed facsimile of correspondence from Joseph J. Phillips, Right of Way Agent, City and County of San Francisco, to A. Toriggino of Mills Estate Incorporated, dated July 7, 1927, concerning need for additional land to accommodate runway safety areas for Boeing Air Mail Company at Mills Field Municipal Airport; file copy, not signed.",
    "sfomuseum:medium":"paper, ink",
    "sfomuseum:placetype":"object",
    "sfomuseum:subcategory":"Correspondence, Company",
    "wof:name":"correspondence: Mills Field Municipal Airport of San Francisco, runway construction",
    "wof:placetype":"venue"
},
  "geometry": {"coordinates":[-122.386155,37.616358],"type":"Point"}
}