{
  "type": "Feature",
  "properties": {
    "date:cessation_lower": "1969-12-31",
    "date:cessation_upper": "1969-12-31",
    "date:inception_lower": "1967-01-01",
    "date:inception_upper": "1967-01-01",
    "iso:country": "XX",
    "sfomuseum:accession_number": "2007.051.077",
    "sfomuseum:airline": "JAL (Japan Air Lines)",
    "sfomuseum:category": "Insignia",
    "sfomuseum:collection": "Aviation Museum",
    "sfomuseum:creditline": "Purchase",
    "sfomuseum:date": "late 1960s",
    "sfomuseum:daterange_end": "1969-12-31",
    "sfomuseum:daterange_start": "1967-01-01",
    "sfomuseum:description": "Silver metal pin with JAL crane motif encircled in faux pearls; pin closure on back; this pin design worn 1967–1970.",
    "sfomuseum:medium": "metal, plastic",
    "sfomuseum:placetype": "object",
    "sfomuseum:subcategory": "Uniform Wing(s), Cabin Crew",
    "wof:depicts": [
      1159285785
    ],
    "wof:name": "air hostess wings: JAL (Japan Air Lines)",
    "wof:placetype": "venue"
  },
  "geometry": {"coordinates":[-122.386155,37.616357],"type":"Point"}
}
