{
  "type": "Feature",
  "properties": {
    "date:cessation_lower": "1960-12-01",
    "date:cessation_upper": "1960-12-31",
    "date:inception_lower": "1960-09-01",
    "date:inception_upper": "1960-09-30",
    "iso:country": "XX",
    "millsfield:images": [
      1763379107
    ],
    "millsfield:images_texts": [
      "JAIL"
    ],
    "millsfield:images_texts_ids": [
      1763379107
    ],
    "millsfield:primary_image": 1763379107,
    "sfomuseum:accession_number": "2007.051.077",
    "sfomuseum:airline": "Japan Air Lines",
    "sfomuseum:category": "Insignia",
    "sfomuseum:collection": "Aviation Museum",
    "sfomuseum:creditline": "Purchase",
    "sfomuseum:date": "late 1960s",
    "sfomuseum:date_acquired": "2007-06-22",
    "sfomuseum:daterange_end": "1969-12-31",
    "sfomuseum:daterange_start": "1967-01-01",
    "sfomuseum:description": "Stewardess wings issued by Japan Air Lines; silver openwork circular crane logo with faux pearls at edge; pin closure on back; worn 1967–1970.",
    "sfomuseum:dimensions": "1 3/4 x 1 3/4 inches (4.4 x 4.4 cm)",
    "sfomuseum:medium": "metal, plastic",
    "sfomuseum:placetype": "object",
    "sfomuseum:publication": ": , late 1960s.",
    "sfomuseum:subcategory": "Uniform Wing(s), Cabin Crew",
    "wof:depicts": [
      1159285785,
      1159288505
    ],
    "wof:name": "stewardess wings: Japan Air Lines",
    "wof:placetype": "custom",
    "wof:placetype_alt": "object"
  },
  "geometry": {"coordinates":[-122.386155,37.616357],"type":"Point"}
}
