{
  "type": "Feature",
  "properties": {
    "date:cessation_lower": "1985-01-01",
    "date:cessation_upper": "1985-12-31",
    "date:inception_lower": "1985-01-01",
    "date:inception_upper": "1985-12-31",
    "iso:country": "XX",
    "millsfield:images": [
      1527837539
    ],
    "millsfield:images_texts": [
      "NORTHWEST ORIENT\nCITY TIMETABLE\nSAN FRANCISCO/OAKLAND/SAN JOSE\nRESERVATIONS\nSan Francisco: (415) 392-2163\nOakland: (415) 392-2163\nSan Jose: (408) 280-1840\nSan Francisco Air Freight: (415) 761-4617\nSouth San Francisco Air Freight: (415) 877-6901\nvakian Air\nFreight: (41\n5) 761-4617\nSchedule Effective December 18, 1985\nTO\nFROM\nleave Active Fate Sets\nStops\n3 Frag.\nAberdeen, SD\n730 3159\n150/1005 MS\nAberdees Feservations: (800) 346-3540\n630 1021\n1002/151 15P\nAlbuquerque, NM\n2550 300\n682/1454 PIX\n5559 1559\nAboquerque Reservations: (800) 205-2525\n9350\n1461/681\nAnchorage, AK\n1003 400 31/5\n750 12790 653/51\n15 1019\n* S\nTEARS\nAnchorage Reservations: (907) 243-1123\n76/580\nAtlanta, GA\n1303 500 150/752 VS\n1139 350\nAbasta Resenatoes: (800) 225-2525\nBangkok, Thailand\nbanquet meservatora.@1-800/3/4\n606p 1240p\n4 caramama Henstion V 707\nBemidji, MN\n1259\nBillings, MT\nBemia, Reservations: (800) 662.5782\nESe M\nsalings Reservators: (800) 225-2525\nBismarck, ND\n1507455 S\nBamart Reservations: (800) 225-2525\n42 142\n550/151\nbids\nBoston, MA\n150/160 VS\nrators 517 257-4585\n100p\n185/159\n1183 9030\nVOCI\nDaly\nBrainerd, MN\n1130a 6450\nSYMBOLS:\nBraised Reservations: (800) 662-5762\nS Snack Service\nex. Camay Padfic Armav:\novernight stop in the Orien"
    ],
    "millsfield:images_texts_ids": [
      1527837539
    ],
    "millsfield:primary_image": 1527837539,
    "sfomuseum:accession_number": "2003.105.077.006",
    "sfomuseum:airline": "Northwest Airlines",
    "sfomuseum:category": "Scheduling / Ticketing",
    "sfomuseum:collection": "Aviation Archive",
    "sfomuseum:creditline": "Gift of Craig Lynes",
    "sfomuseum:date": "1985",
    "sfomuseum:date_acquired": "2003-12-29",
    "sfomuseum:daterange_end": "1985-12-31",
    "sfomuseum:daterange_start": "1985-01-01",
    "sfomuseum:description": "City timetable issued by Northwest Orient Airlines for flights to and from San Francisco, Oakland, and San Jose, effective December 18, 1985; three page double-sided fold-out; white, red, and blue cover.",
    "sfomuseum:dimensions": "9 x 4 inches (22.9 x 10.2 cm)",
    "sfomuseum:media_ids": [
      1527837539
    ],
    "sfomuseum:medium": "paper, ink",
    "sfomuseum:placetype": "object",
    "sfomuseum:publication": ": , 1985.",
    "sfomuseum:subcategory": "Timetable",
    "sfomuseum:subject": "Airlines -- Timetables -- Northwest Airlines",
    "wof:depicts": [
      1159287407,
      85633793,
      1159284907,
      1159284913,
      85921881,
      85688637
    ],
    "wof:name": "timetable: Northwest Orient Airlines, San Francisco / Oakland / San Jose",
    "wof:placetype": "custom",
    "wof:placetype_alt": "object"
  },
  "geometry": {"coordinates":[-122.386155,37.616357],"type":"Point"}
}
