{
  "type": "Feature",
  "properties": {
    "date:cessation_lower":"1985-12-31",
    "date:cessation_upper":"1985-12-31",
    "date:inception_lower":"1985-01-01",
    "date:inception_upper":"1985-01-01",
    "iso:country":"XX",
    "sfomuseum:accession_number":"2003.105.077.006",
    "sfomuseum:category":"Scheduling / Ticketing",
    "sfomuseum:collection":"Aviation Archive",
    "sfomuseum:creditline":"Gift of Craig Lynes",
    "sfomuseum:date":"1985",
    "sfomuseum:daterange_end":"1985-12-31",
    "sfomuseum:daterange_start":"1985-01-01",
    "sfomuseum:description":"City timetable issued by Northwest Orient Airlines for flights to and from San Francisco, Oakland, and San Jose, effective December 18, 1985; three page double-sided fold-out; white cover with the company name and logo at the top on a red field and blue text. The remainder of the page is the schedule.",
    "sfomuseum:medium":"paper, ink",
    "sfomuseum:placetype":"object",
    "sfomuseum:subcategory":"Timetable",
    "wof:name":"timetable: Northwest Orient Airlines, San Francisco / Oakland / San Jose",
    "wof:placetype":"venue"
},
  "geometry": {"coordinates":[-122.386155,37.616358],"type":"Point"}
}