{
  "type": "Feature",
  "properties": {
    "date:cessation_lower": "1985-01-01",
    "date:cessation_upper": "1985-12-31",
    "date:inception_lower": "1985-01-01",
    "date:inception_upper": "1985-12-31",
    "iso:country": "XX",
    "millsfield:images": [
      1527841059
    ],
    "millsfield:images_texts": [
      "AIR INTER\nLIGNES AÉRIENNES INTÉRIEURES\nHORAIRES\nNº 52\nVALABLES DU 27 OCTOBRE 1985 AU 29 MARS 1986\nHoraires, tarifs et coloration des vols susceptibles de modifications.\nAJ\nF-BUA\nCARTE EVASION : DES TARIFS REDUITS POUR TOUS"
    ],
    "millsfield:images_texts_ids": [
      1527841059
    ],
    "millsfield:primary_image": 1527841059,
    "sfomuseum:accession_number": "2009.122.138",
    "sfomuseum:airline": "Air Inter",
    "sfomuseum:category": "Scheduling / Ticketing",
    "sfomuseum:collection": "Aviation Archive",
    "sfomuseum:creditline": "Gift of the William Hough Collection",
    "sfomuseum:date": "1985",
    "sfomuseum:date_acquired": "2010-06-08",
    "sfomuseum:daterange_end": "1985-12-31",
    "sfomuseum:daterange_start": "1985-01-01",
    "sfomuseum:description": "Timetable issued by Air Inter, effective October 27, 1985 through March 29, 1986; 72-page schedule; white cover with color photographic image of the tail sections of parked jets. ",
    "sfomuseum:dimensions": "6 3/4 x 4 1/4 inches (17.1 x 10.8 cm)",
    "sfomuseum:media_ids": [
      1527841059
    ],
    "sfomuseum:medium": "paper, ink",
    "sfomuseum:placetype": "object",
    "sfomuseum:publication": ": , 1985.",
    "sfomuseum:subcategory": "Timetable",
    "wof:depicts": [
      1159286621,
      1159283651
    ],
    "wof:name": "timetable: Air Inter",
    "wof:placetype": "custom",
    "wof:placetype_alt": [
      "object"
    ]
  },
  "geometry": {"coordinates":[-122.386155,37.616357],"type":"Point"}
}
