{
  "type": "Feature",
  "properties": {
    "date:cessation_lower": "1994-01-01",
    "date:cessation_upper": "1994-12-31",
    "date:inception_lower": "1994-01-01",
    "date:inception_upper": "1994-12-31",
    "isbn:number": "0894648845, 9780894648847",
    "iso:country": "XX",
    "sfomuseum:accession_number": "1999.657.054",
    "sfomuseum:author": "Wells, Alexander T",
    "sfomuseum:callnumber": "HD9711.A2 W45 1994",
    "sfomuseum:category": "Book",
    "sfomuseum:collection": "Aviation Library",
    "sfomuseum:creditline": "Collection of SFO Museum",
    "sfomuseum:date": "1994",
    "sfomuseum:date_acquired": "1995-05-25",
    "sfomuseum:daterange_end": "1994-12-31",
    "sfomuseum:daterange_start": "1994-01-01",
    "sfomuseum:description": "xi, 322 p. : ill. ; 29 cm.",
    "sfomuseum:description_library": "xi, 322 p. : ill. ; 29 cm.",
    "sfomuseum:medium": "paper, ink",
    "sfomuseum:placetype": "object",
    "sfomuseum:publication": "Malabar, FL: Krieger, 1994.",
    "sfomuseum:publisher": "Krieger",
    "sfomuseum:publisher_location": "Malabar, FL",
    "sfomuseum:subcategory": "Book",
    "sfomuseum:subject": "Aircraft industry Management.Airplanes Marketing.",
    "wof:name": "General aviation marketing and management",
    "wof:placetype": "custom",
    "wof:placetype_alt": [
      "object"
    ]
  },
  "geometry": {"coordinates":[-122.386155,37.616357],"type":"Point"}
}
