{
  "type": "Feature",
  "properties": {
    "date:cessation_lower": "1980-01-01",
    "date:cessation_upper": "1989-12-31",
    "date:inception_lower": "1980-01-01",
    "date:inception_upper": "1989-12-31",
    "iso:country": "XX",
    "sfomuseum:accession_number": "2007.033.037",
    "sfomuseum:airline": "Eastern Air Lines",
    "sfomuseum:category": "Passenger Amenity, Museum",
    "sfomuseum:collection": "Aviation Museum",
    "sfomuseum:creditline": "Gift of Diana Rudner",
    "sfomuseum:date": "1980s",
    "sfomuseum:daterange_end": "1980-12-31",
    "sfomuseum:daterange_start": "1980-01-01",
    "sfomuseum:description": "Bronze-colored plastic pin in shape of wings flanking blue Eastern logo; \"Eastern\" printed on base in blue capital letters; pin clasp on reverse; inscription on reverse, \"Stoffel Seals, Tuckanoe, NY, Pat. No. 3.262.223.\"",
    "sfomuseum:dimensions": "3/4 x 2 1/2 x 1/4 inches (1.9 x 6.4 x .6 cm)",
    "sfomuseum:medium": "plastic, metal",
    "sfomuseum:placetype": "object",
    "sfomuseum:subcategory": "Children’s Amenity, Toys",
    "sfomuseum:subject": "Commercial Airlines -- Eastern Airlines.",
    "wof:depicts": [
      1159284309
    ],
    "wof:name": "children's souvenir wings: Eastern Air Lines",
    "wof:placetype": "venue"
  },
  "geometry": {"coordinates":[-122.386155,37.616357],"type":"Point"}
}
