{
  "type": "Feature",
  "properties": {
    "date:cessation_lower": "2000-01-01",
    "date:cessation_upper": "2009-12-31",
    "date:inception_lower": "2000-01-01",
    "date:inception_upper": "2009-12-31",
    "iso:country": "XX",
    "millsfield:images": [
      1527845471,
      1527845473
    ],
    "millsfield:primary_image": 1527845471,
    "sfomuseum:accession_number": "2006.034.131",
    "sfomuseum:airline": "Singapore Airlines",
    "sfomuseum:category": "Passenger Amenity",
    "sfomuseum:collection": "Aviation Archive",
    "sfomuseum:creditline": "Gift of Adan Wong",
    "sfomuseum:date": "2000s",
    "sfomuseum:daterange_end": "2000-12-31",
    "sfomuseum:daterange_start": "2000-01-01",
    "sfomuseum:description": "Menu issued by Singapore Airlines, New York - Frankfurt - Singapore route; color abstract design on cover; menu items include duck meat loaf, poached perch, and omelette; menu number: JUL-OCT EY SQ25 JFK-FRA-SIN (D/CB/L/B); class: economy; undated.",
    "sfomuseum:dimensions": "8 1/4 x 5 3/4 inches (21 x 14.6 cm)",
    "sfomuseum:media_ids": [
      1527845471,
      1527845473
    ],
    "sfomuseum:medium": "paper, ink, metal",
    "sfomuseum:placetype": "object",
    "sfomuseum:subcategory": "Menu",
    "wof:depicts": [
      1159285163
    ],
    "wof:name": "menu: Singapore Airlines, Economy Class",
    "wof:placetype": "venue"
  },
  "geometry": {"coordinates":[-122.386155,37.616357],"type":"Point"}
}
