{
  "type": "Feature",
  "properties": {
    "date:cessation_lower": "2000-01-01",
    "date:cessation_upper": "2009-12-31",
    "date:inception_lower": "2000-01-01",
    "date:inception_upper": "2009-12-31",
    "iso:country": "XX",
    "millsfield:images": [
      1527845471,
      1527845473
    ],
    "millsfield:images_texts": [
      "MENU",
      "FRANKFURT - SINGAPORE\nBREAKFAST\nNEW YORK - FRANKFURT\nHAUPTMAHLZEIT\nFruit juices\nFruit appetiser\nFruit yoghurt\nSeafood rice vermicelli\nOmelette with mixed herbs\nPan fried mixed capsicums\nBroiled whole mushrooms\nFried potatoes\nAssorted breakfast rolls\nButter - Fruit preserve\nCoffee - Tea\nVorspeise\n\" Entenhackbraten mit Süßkartoffelpüree\nGeschmortes Fischfilet\nmit scharfer Bohnensauce nach orientalischer Art\nAusgewähltes Gemüse der Saison\nGedämpfter Reis\nCracker mit Käse\nEiscreme\nBrötchen mit Butter\nKaffee - Tee\n\" Exklusiv erstellt von David Burke\nWir bitten um Ihr Vertändnis falls durch eine unerwartete hohe Nachfrage Ihr Menüwunsch nicht mehr erhältlich ist.\n12.22 WHOCT EV"
    ],
    "millsfield:images_texts_ids": [
      1527845471,
      1527845473
    ],
    "millsfield:primary_image": 1527845471,
    "sfomuseum:accession_number": "2006.034.131",
    "sfomuseum:airline": "Singapore Airlines",
    "sfomuseum:category": "Passenger Amenity, Archive",
    "sfomuseum:collection": "Aviation Archive",
    "sfomuseum:creditline": "Gift of Adan Wong",
    "sfomuseum:date": "2000s",
    "sfomuseum:date_acquired": "2007-04-06",
    "sfomuseum:daterange_end": "2000-12-31",
    "sfomuseum:daterange_start": "2000-01-01",
    "sfomuseum:description": "Menu issued by Singapore Airlines, New York - Frankfurt - Singapore route; color abstract design on cover; menu items include duck meat loaf, poached perch, and omelette; menu number: JUL-OCT EY SQ25 JFK-FRA-SIN (D/CB/L/B); class: economy; undated.",
    "sfomuseum:dimensions": "8 1/4 x 5 3/4 inches (21 x 14.6 cm)",
    "sfomuseum:media_ids": [
      1527845471,
      1527845473
    ],
    "sfomuseum:medium": "paper, ink, metal",
    "sfomuseum:placetype": "object",
    "sfomuseum:publication": ": , 2000s.",
    "sfomuseum:subcategory": "Menu",
    "wof:depicts": [
      1159285163,
      1159288903
    ],
    "wof:name": "menu: Singapore Airlines, Economy Class",
    "wof:placetype": "custom",
    "wof:placetype_alt": "object"
  },
  "geometry": {"coordinates":[-122.386155,37.616357],"type":"Point"}
}
