{
  "type": "Feature",
  "properties": {
    "date:cessation_lower": "1905-01-01",
    "date:cessation_upper": "1905-12-31",
    "date:inception_lower": "1905-01-01",
    "date:inception_upper": "1905-12-31",
    "iso:country": "XX",
    "loc:subject_headings": [
      "sh85001319"
    ],
    "millsfield:images": [
      1746681227
    ],
    "millsfield:primary_image": 1746681227,
    "sfomuseum:accession_number": "2000.160.0142",
    "sfomuseum:author": "Bacon, Gertrude",
    "sfomuseum:callnumber": "TL545 .B33 1905 SC",
    "sfomuseum:category": "Book",
    "sfomuseum:collection": "Aviation Library",
    "sfomuseum:creditline": "The Tony Bill Aviation Library Collection",
    "sfomuseum:date": "1905",
    "sfomuseum:date_acquired": "1999-05-18",
    "sfomuseum:daterange_end": "1905-12-31",
    "sfomuseum:daterange_start": "1905-01-01",
    "sfomuseum:description": "124 p. illus. 19 cm.",
    "sfomuseum:description_library": "124 p. illus. 19 cm.",
    "sfomuseum:medium": "paper, ink",
    "sfomuseum:placetype": "object",
    "sfomuseum:publication": "London: T.C. \u0026 E.C. Jack, 1905.",
    "sfomuseum:publisher": "T.C. \u0026 E.C. Jack",
    "sfomuseum:publisher_location": "London",
    "sfomuseum:series": "Shilling scientific series",
    "sfomuseum:subcategory": "Book",
    "sfomuseum:subject": "Aeronautics.",
    "wof:name": "Balloons, airships and flying machines",
    "wof:placetype": "custom",
    "wof:placetype_alt": "object"
  },
  "geometry": {"coordinates":[-122.386155,37.616357],"type":"Point"}
}
