{
  "type": "Feature",
  "properties": {
    "date:cessation_lower": "2001-01-01",
    "date:cessation_upper": "2001-12-31",
    "date:inception_lower": "2001-01-01",
    "date:inception_upper": "2001-12-31",
    "iso:country": "XX",
    "sfomuseum:accession_number": "2001.206.002",
    "sfomuseum:author": "Lavender, Kenneth",
    "sfomuseum:callnumber": "Z701 .L32 2001",
    "sfomuseum:category": "Book",
    "sfomuseum:collection": "Aviation Library",
    "sfomuseum:creditline": "Collection of SFO Museum",
    "sfomuseum:date": "c. 2001",
    "sfomuseum:daterange_end": "2006-12-31",
    "sfomuseum:daterange_start": "1996-01-01",
    "sfomuseum:description": "xxiv, 269 p. : ill. ; 28 cm.",
    "sfomuseum:medium": "paper, ink",
    "sfomuseum:placetype": "object",
    "sfomuseum:publisher": "Neal-Schuman Publishers",
    "sfomuseum:publisher_location": "New York",
    "sfomuseum:series": "How-to-do-it manuals for librarians ; no. 107",
    "sfomuseum:subcategory": "Book",
    "sfomuseum:subject": "Books Conservation and restoration Handbooks, manuals, etc.Library materials Conservation and restoration Handbooks, manuals, etc.Bookbinding Repairing Handbooks, manuals, etc.",
    "wof:name": "Book repair: a how-to-do-it manual",
    "wof:placetype": "venue"
  },
  "geometry": {"coordinates":[-122.386155,37.616357],"type":"Point"}
}
