{
  "type": "Feature",
  "properties": {
    "date:cessation_lower": "1990-01-01",
    "date:cessation_upper": "1990-12-31",
    "date:inception_lower": "1990-01-01",
    "date:inception_upper": "1990-12-31",
    "iso:country": "XX",
    "sfomuseum:accession_number": "1999.657.104",
    "sfomuseum:author": "Coombs, L.F.E",
    "sfomuseum:callnumber": "TL515 .C66 1990",
    "sfomuseum:category": "Book",
    "sfomuseum:collection": "Aviation Library",
    "sfomuseum:creditline": "Purchase",
    "sfomuseum:date": "1990",
    "sfomuseum:date_acquired": "1995-05-25",
    "sfomuseum:daterange_end": "1990-12-31",
    "sfomuseum:daterange_start": "1990-01-01",
    "sfomuseum:description": "(lim. ed.)\r240 p. : ill. ; 26 cm.\rIncludes bibliographical references and index.\rAeronautics - History.\rAircraft, history\r",
    "sfomuseum:description_library": "(lim. ed.)\r240 p. : ill. ; 26 cm.\rIncludes bibliographical references and index.\rAeronautics - History.\rAircraft, history\r",
    "sfomuseum:medium": "printed, bound paper",
    "sfomuseum:placetype": "object",
    "sfomuseum:publication": "Wellingborough, England: Patrick Stephens Limited, 1990.",
    "sfomuseum:publisher": "Patrick Stephens Limited",
    "sfomuseum:publisher_location": "Wellingborough, England",
    "sfomuseum:subcategory": "Book",
    "wof:name": "The aircraft cockpit: from stick-and-string to fly-by-wire",
    "wof:placetype": "custom",
    "wof:placetype_alt": "object"
  },
  "geometry": {"coordinates":[-122.386155,37.616357],"type":"Point"}
}
