{
  "type": "Feature",
  "properties": {
    "date:cessation_lower": "1935-04-01",
    "date:cessation_upper": "1935-04-01",
    "date:inception_lower": "1935-04-01",
    "date:inception_upper": "1935-04-01",
    "iso:country": "XX",
    "millsfield:images": [
      1527820643,
      1527820645
    ],
    "millsfield:images_texts": [
      "SOL\nAPRIT\ngAM\nL-Pan American Airway\nSan Francisco, Cal\nBYRD ANTARCTIC\nEXPEDITION I\nSANFRY\nUS POSTAGE\nCENTS\n8.3\nвошо ба рощею о PAA AMBRICAN CLIPPER\nFIRST^ELI\nCALIFORNIA HAI",
      "NEWARK. N. J.\nAWARE,\n19358\nSEC\n2007.053.001"
    ],
    "millsfield:images_texts_ids": [
      1527820643,
      1527820645
    ],
    "millsfield:primary_image": 1527820643,
    "sfomuseum:accession_number": "2007.053.001",
    "sfomuseum:aircraft": "Sikorsky (USA) S-42",
    "sfomuseum:airline": "Pan American Airways",
    "sfomuseum:category": "Philately",
    "sfomuseum:collection": "Aviation Archive",
    "sfomuseum:creditline": "Gift of Kenneth Andersen",
    "sfomuseum:date": "04/01/1935",
    "sfomuseum:date_acquired": "2007-06-01",
    "sfomuseum:daterange_end": "1935-04-01",
    "sfomuseum:daterange_start": "1935-04-01",
    "sfomuseum:description": "Airmail flight cover, Pan American Airways, first Pacific survey flight, California - Hawaii; red stamped cachet at right, “First flight California-Hawaii”; postmarked April 16, 1935 in San Francisco and April 1, 1935 in Honolulu with three stamps; backstamps: April 16, 1935 in Alameda and April 26, 1935 in Newark.",
    "sfomuseum:dimensions": "4 x 7 1/2 inches (10.2 x 19.1 cm)",
    "sfomuseum:media_ids": [
      1527820645,
      1527820643
    ],
    "sfomuseum:medium": "paper, ink",
    "sfomuseum:placetype": "object",
    "sfomuseum:publication": ": , 04/01/1935.",
    "sfomuseum:subcategory": "Airmail Flight Cover",
    "sfomuseum:subject": "Airmail",
    "wof:depicts": [
      1159286839,
      1159291669,
      1159284991
    ],
    "wof:name": "airmail flight cover: Pan American Airways, first Pacific survey flight, San Francisco - Hawaii route",
    "wof:placetype": "custom",
    "wof:placetype_alt": "object"
  },
  "geometry": {"coordinates":[-122.386155,37.616357],"type":"Point"}
}
