{
  "type": "Feature",
  "properties": {
    "date:cessation_lower": "1935-12-31",
    "date:cessation_upper": "1935-12-31",
    "date:inception_lower": "1935-01-01",
    "date:inception_upper": "1935-01-01",
    "iso:country": "XX",
    "sfomuseum:accession_number": "2007.053.001",
    "sfomuseum:category": "Philately",
    "sfomuseum:collection": "Aviation Archive",
    "sfomuseum:creditline": "Gift of Kenneth Andersen",
    "sfomuseum:date": "04/01/1935",
    "sfomuseum:daterange_end": "1935-04-01",
    "sfomuseum:daterange_start": "1935-04-01",
    "sfomuseum:description": "Airmail flight cover, Pan American Airways, first Pacific survey flight, California - Hawaii; red stamped cachet at right, “First flight California-Hawaii”; postmarked April 16, 1935 in San Francisco and April 1, 1935 in Honolulu with three stamps; backstamps: April 16, 1935 in Alameda and April 26, 1935 in Newark.",
    "sfomuseum:media_ids": [
      1527820645, 
      1527820643
    ],
    "sfomuseum:medium": "paper, ink",
    "sfomuseum:placetype": "object",
    "sfomuseum:subcategory": "Airmail Flight Cover",
    "wof:name": "airmail flight cover: Pan American Airways, first Pacific survey flight, San Francisco - Hawaii route",
    "wof:placetype": "venue"
  },
  "geometry": {"coordinates":[-122.386155,37.616358],"type":"Point"}
}
