{
  "type": "Feature",
  "properties": {
    "date:cessation_lower": "1933-01-01",
    "date:cessation_upper": "1933-12-31",
    "date:inception_lower": "1933-01-01",
    "date:inception_upper": "1933-12-31",
    "iso:country": "XX",
    "millsfield:images": [
      1527836267
    ],
    "millsfield:images_texts": [
      "AMERICAN\nAIRWAYS\nTIME\nTABLES\nCoast to Coast\nCanada to Mexico\nPASSENGERS\nMAIL• EXPRESS\nSeptember 14, 1933"
    ],
    "millsfield:images_texts_ids": [
      1527836267
    ],
    "millsfield:primary_image": 1527836267,
    "sfomuseum:accession_number": "2003.021.001",
    "sfomuseum:airline": "American Airways",
    "sfomuseum:category": "Scheduling / Ticketing",
    "sfomuseum:collection": "Aviation Archive",
    "sfomuseum:creditline": "Gift of James Clifford in memory of Raymond McShane",
    "sfomuseum:date": "1933",
    "sfomuseum:date_acquired": "2003-07-21",
    "sfomuseum:daterange_end": "1933-12-31",
    "sfomuseum:daterange_start": "1933-01-01",
    "sfomuseum:description": "Timetable issued by American Airways, effective September 14, 1933; blue and white cover with text: “Coast to Coast, Canada to Mexico: Passengers, Mail, Express” and illustration of seated passengers on a flight.",
    "sfomuseum:dimensions": "9 x 4 inches (22.9 x 10.2 cm)",
    "sfomuseum:media_ids": [
      1527836267
    ],
    "sfomuseum:medium": "paper, ink",
    "sfomuseum:placetype": "object",
    "sfomuseum:publication": ": , 1933.",
    "sfomuseum:subcategory": "Timetable",
    "wof:depicts": [
      1360700619,
      1159283849,
      1159286017
    ],
    "wof:name": "timetable: American Airways",
    "wof:placetype": "custom",
    "wof:placetype_alt": "object"
  },
  "geometry": {"coordinates":[-122.386155,37.616357],"type":"Point"}
}
