{
  "type": "Feature",
  "properties": {
    "date:cessation_lower": "1980-01-01",
    "date:cessation_upper": "1980-12-31",
    "date:inception_lower": "1980-01-01",
    "date:inception_upper": "1980-12-31",
    "iso:country": "XX",
    "millsfield:images": [
      1527853183,
      1746281541
    ],
    "millsfield:primary_image": 1527853183,
    "sfomuseum:accession_number": "2013.095.028",
    "sfomuseum:airline": "Pan American World Airways",
    "sfomuseum:category": "Passenger Amenity",
    "sfomuseum:collection": "Aviation Archive",
    "sfomuseum:creditline": "Gift of the Estate of Jane Gottschall",
    "sfomuseum:date": "1980",
    "sfomuseum:date_acquired": "2014-05-21",
    "sfomuseum:daterange_end": "1980-12-31",
    "sfomuseum:daterange_start": "1980-01-01",
    "sfomuseum:description": "Menu issued by Pan American World Airways for gala dinner for Pan American management employees in San Francisco, August 26, 1980; white cover with color reproduction of lithograph of the Clipper ship “Great Republic”; menu items include prime rib and roasted potatoes; no menu number.",
    "sfomuseum:dimensions": "10 x 12 1/2 inches (25.4 x 31.8 cm)",
    "sfomuseum:media_ids": [
      1527853183
    ],
    "sfomuseum:medium": "paper, ink",
    "sfomuseum:placetype": "object",
    "sfomuseum:publication": ": , 1980.",
    "sfomuseum:subcategory": "Menu",
    "wof:depicts": [
      1159284989
    ],
    "wof:name": "menu: Pan American World Airways",
    "wof:placetype": "venue"
  },
  "geometry": {"coordinates":[-122.386155,37.616357],"type":"Point"}
}
