{
  "type": "Feature",
  "properties": {
    "date:cessation_lower": "2000-01-01",
    "date:cessation_upper": "2000-12-31",
    "date:inception_lower": "2000-01-01",
    "date:inception_upper": "2000-12-31",
    "iso:country": "XX",
    "sfomuseum:accession_number": "2003.024.009",
    "sfomuseum:author": "Hill, Charles N.",
    "sfomuseum:callnumber": "HE9803.P36 H35 2000",
    "sfomuseum:category": "Book",
    "sfomuseum:collection": "Aviation Library",
    "sfomuseum:creditline": "Purchase",
    "sfomuseum:date": "c. 2000",
    "sfomuseum:date_acquired": "2003-12-31",
    "sfomuseum:daterange_end": "2005-12-31",
    "sfomuseum:daterange_start": "1995-01-01",
    "sfomuseum:description": "xxviii, 186 p. : ill., maps, facsims. ; 28 cm.",
    "sfomuseum:description_library": "xxviii, 186 p. : ill., maps, facsims. ; 28 cm.",
    "sfomuseum:medium": "paper, ink",
    "sfomuseum:placetype": "object",
    "sfomuseum:publication": "United States: 1st Books Library, c. 2000.",
    "sfomuseum:publisher": "1st Books Library",
    "sfomuseum:publisher_location": "United States",
    "sfomuseum:subcategory": "Book",
    "sfomuseum:subject": "Hijacking of aircraft Case studies.\rHawaii Clipper (Airplane) -- History.\rPan American World Airways, Inc. -- History.",
    "wof:name": "Fix on the rising sun: the Clipper hi-jacking of 1938 -- and the ultimate M.I.A.'s",
    "wof:placetype": "custom"
  },
  "geometry": {"coordinates":[-122.386155,37.616357],"type":"Point"}
}
