{
  "type": "Feature",
  "properties": {
    "date:cessation_lower": "1993-01-01",
    "date:cessation_upper": "1993-12-31",
    "date:inception_lower": "1993-01-01",
    "date:inception_upper": "1993-12-31",
    "isbn:number": "0887405843, 9780887405846",
    "iso:country": "XX",
    "sfomuseum:accession_number": "1999.663.007",
    "sfomuseum:author": "Allen, Richard Sanders",
    "sfomuseum:callnumber": "TL686.L6 A37 1993 c.2",
    "sfomuseum:category": "Book",
    "sfomuseum:collection": "Aviation Library",
    "sfomuseum:creditline": "Purchase",
    "sfomuseum:date": "c. 1993",
    "sfomuseum:date_acquired": "1999-01-01",
    "sfomuseum:daterange_end": "1998-12-31",
    "sfomuseum:daterange_start": "1988-01-01",
    "sfomuseum:description": "xii, 255 p. : ill. ; 29 cm.",
    "sfomuseum:description_library": "xii, 255 p. : ill. ; 29 cm.",
    "sfomuseum:medium": "paper, ink",
    "sfomuseum:placetype": "object",
    "sfomuseum:publication": "Atglen, PA: Schiffer Pub., c. 1993.",
    "sfomuseum:publisher": "Schiffer Pub.",
    "sfomuseum:publisher_location": "Atglen, PA",
    "sfomuseum:series": "Schiffer aviation history",
    "sfomuseum:subcategory": "Book",
    "sfomuseum:subject": "Aeronautics History.Lockheed airplanes History.",
    "wof:name": "Revolution in the sky: the Lockheeds of aviation's Golden Age",
    "wof:placetype": "custom",
    "wof:placetype_alt": "object"
  },
  "geometry": {"coordinates":[-122.386155,37.616357],"type":"Point"}
}
