{
  "type": "Feature",
  "properties": {
    "date:cessation_lower": "1950-01-01",
    "date:cessation_upper": "1950-12-31",
    "date:inception_lower": "1950-01-01",
    "date:inception_upper": "1950-12-31",
    "iso:country": "XX",
    "millsfield:images": [
      1527835035
    ],
    "millsfield:primary_image": 1527835035,
    "sfomuseum:accession_number": "2012.149.1146",
    "sfomuseum:aircraft": "Lockheed L-049 Constellation",
    "sfomuseum:airline": "Capital Airlines",
    "sfomuseum:category": "Promotional, Archive",
    "sfomuseum:collection": "Aviation Archive",
    "sfomuseum:creditline": "Gift of the Captain John B. Russell Family",
    "sfomuseum:date": "c. 1950",
    "sfomuseum:date_acquired": "2013-05-28",
    "sfomuseum:daterange_end": "1955-12-31",
    "sfomuseum:daterange_start": "1945-01-01",
    "sfomuseum:description": "Luggage label promoting Capital Airlines; circular shape,  white and red background with illustration of Lockheed L-049 Constellation in flight against stylized bird logo.",
    "sfomuseum:dimensions": "3 1/2 x 3 1/2 inches (8.9 x 8.9 cm)",
    "sfomuseum:media_ids": [
      1527835035
    ],
    "sfomuseum:medium": "paper, ink, adhesive",
    "sfomuseum:placetype": "object",
    "sfomuseum:publication": ": , c. 1950.",
    "sfomuseum:subcategory": "Luggage Label",
    "wof:depicts": [
      1159284093,
      1159291095,
      1159293697
    ],
    "wof:name": "luggage label: Capital Airlines, Lockheed L-049 Constellation",
    "wof:placetype": "custom",
    "wof:placetype_alt": "object"
  },
  "geometry": {"coordinates":[-122.386155,37.616357],"type":"Point"}
}
