{
  "type": "Feature",
  "properties": {
    "date:cessation_lower": "1931-01-01",
    "date:cessation_upper": "1931-12-31",
    "date:inception_lower": "1931-01-01",
    "date:inception_upper": "1931-12-31",
    "iso:country": "XX",
    "sfomuseum:accession_number": "2000.160.0171",
    "sfomuseum:author": "Bonn, O'Philip",
    "sfomuseum:callnumber": "PS3503.O53 R38 1931 SC",
    "sfomuseum:category": "Book",
    "sfomuseum:collection": "Aviation Library",
    "sfomuseum:creditline": "The Tony Bill Aviation Library Collection",
    "sfomuseum:date": "1931",
    "sfomuseum:date_acquired": "1999-05-18",
    "sfomuseum:daterange_end": "1931-12-31",
    "sfomuseum:daterange_start": "1931-01-01",
    "sfomuseum:description": "329 p. 20 cm.",
    "sfomuseum:description_library": "329 p. 20 cm.",
    "sfomuseum:medium": "paper, ink",
    "sfomuseum:notes_library": "Library's copy inscribed by author.",
    "sfomuseum:placetype": "object",
    "sfomuseum:publication": "Los Angeles: California Graphic Press, 1931.",
    "sfomuseum:publisher": "California Graphic Press",
    "sfomuseum:publisher_location": "Los Angeles",
    "sfomuseum:subcategory": "Book",
    "sfomuseum:subject": "World War, 1914-1918 Fiction.",
    "wof:name": "Ravens",
    "wof:placetype": "venue"
  },
  "geometry": {"coordinates":[-122.386155,37.616357],"type":"Point"}
}
