{
  "type": "Feature",
  "properties": {
    "date:cessation_lower": "1929-05-21",
    "date:cessation_upper": "1929-05-21",
    "date:inception_lower": "1929-05-21",
    "date:inception_upper": "1929-05-21",
    "iso:country": "XX",
    "millsfield:images": [
      1527832785,
      1527832793
    ],
    "millsfield:primary_image": 1527832785,
    "sfomuseum:accession_number": "2012.149.1554",
    "sfomuseum:category": "Philately",
    "sfomuseum:collection": "Aviation Archive",
    "sfomuseum:creditline": "Gift of the Captain John B. Russell Family",
    "sfomuseum:date": "05/21/1929",
    "sfomuseum:date_acquired": "2013-05-31",
    "sfomuseum:daterange_end": "1929-05-21",
    "sfomuseum:daterange_start": "1929-05-21",
    "sfomuseum:description": "Airmail flight cover issued in honor of Army air maneuvers at Norton Field in Columbus, Ohio, on Lindbergh Day; circular cachet at left with images of biplanes and airship; postmarked May 21, 1929, Columbus, Ohio, with “Let’s go / Citizens military training camp” cancellation mark over 5-cent postage stamp; no backstamp; envelope addressed to Harvey Lederman.",
    "sfomuseum:dimensions": "3 1/2 x 6 1/2 inches (8.9 x 16.5 cm)",
    "sfomuseum:media_ids": [
      1527832785,
      1527832793
    ],
    "sfomuseum:medium": "paper, ink",
    "sfomuseum:placetype": "object",
    "sfomuseum:publication": ": , 05/21/1929.",
    "sfomuseum:subcategory": "Airmail Flight Cover",
    "wof:name": "airmail flight cover: Army air maneuvers, Norton Field, Charles Lindbergh Day",
    "wof:placetype": "venue"
  },
  "geometry": {"coordinates":[-122.386155,37.616357],"type":"Point"}
}
