{
  "type": "Feature",
  "properties": {
    "date:cessation_lower": "1956-01-01",
    "date:cessation_upper": "1956-12-31",
    "date:inception_lower": "1956-01-01",
    "date:inception_upper": "1956-12-31",
    "iso:country": "XX",
    "millsfield:images": [
      1527850285,
      1527850289,
      1527850291,
      1527843495,
      1527843497
    ],
    "millsfield:primary_image": 1527843497,
    "sfomuseum:accession_number": "2008.039.005 a c",
    "sfomuseum:airline": "United Air Lines",
    "sfomuseum:category": "Scheduling / Ticketing",
    "sfomuseum:collection": "Aviation Archive",
    "sfomuseum:creditline": "Gift of Hal Amarantes",
    "sfomuseum:date": "1956",
    "sfomuseum:daterange_end": "1956-12-31",
    "sfomuseum:daterange_start": "1956-01-01",
    "sfomuseum:description": "a. Blue, white, and red ticket jacket and boarding pass issued by Western Airlines (United Air Lines boarding pass stapled to interior).\rb. Ticket with white cover and red/blue logo issued to passenger Mrs. C. E. Amarantes, from San Francisco to Los Angeles to Yuma, January 6, 1956.",
    "sfomuseum:dimensions": "3 1/2 x 5 1/2 inches (8.9 x 14 cm)",
    "sfomuseum:media_ids": [
      1527843495,
      1527843497,
      1527850285,
      1527850289,
      1527850291
    ],
    "sfomuseum:medium": "ink, paper",
    "sfomuseum:placetype": "object",
    "sfomuseum:publication": ": , 1956.",
    "sfomuseum:subcategory": "Ticket Jacket / Ticket",
    "wof:depicts": [
      1159285415
    ],
    "wof:name": "ticket jacket and ticket: Western Air Lines and United Air Lines ",
    "wof:placetype": "venue"
  },
  "geometry": {"coordinates":[-122.386155,37.616357],"type":"Point"}
}
