{
  "type": "Feature",
  "properties": {
    "date:cessation_lower":"1956-12-31",
    "date:cessation_upper":"1956-12-31",
    "date:inception_lower":"1956-01-01",
    "date:inception_upper":"1956-01-01",
    "iso:country":"XX",
    "sfomuseum:accession_number":"2008.039.005 a c",
    "sfomuseum:category":"Scheduling / Ticketing",
    "sfomuseum:collection":"Aviation Archive",
    "sfomuseum:creditline":"Gift of Hal Amarantes",
    "sfomuseum:date":"1956",
    "sfomuseum:daterange_end":"1956-12-31",
    "sfomuseum:daterange_start":"1956-01-01",
    "sfomuseum:description":"a. Blue, white, and red ticket jacket and boarding pass issued by Western Airlines (United Air Lines boarding pass stapled to interior).\rb. Ticket with white cover and red/blue logo issued to passenger Mrs. C. E. Amarantes, from San Francisco to Los Angeles to Yuma, January 6, 1956.",
    "sfomuseum:media_ids":[
        1527843495,
        1527843497,
        1527850285,
        1527850289,
        1527850291
    ],
    "sfomuseum:medium":"ink, paper",
    "sfomuseum:placetype":"object",
    "sfomuseum:subcategory":"Ticket Jacket / Ticket",
    "wof:name":"ticket jacket and ticket: Western Air Lines and United Air Lines ",
    "wof:placetype":"venue"
},
  "geometry": {"coordinates":[-122.386155,37.616358],"type":"Point"}
}