{
  "type": "Feature",
  "properties": {
    "date:cessation_lower": "1966-01-01",
    "date:cessation_upper": "1966-12-31",
    "date:inception_lower": "1966-01-01",
    "date:inception_upper": "1966-12-31",
    "iso:country": "XX",
    "sfomuseum:accession_number": "2010.116.001",
    "sfomuseum:author": "Horvat, William Joseph",
    "sfomuseum:callnumber": "TL522.H3 H6 1966\r",
    "sfomuseum:category": "Book",
    "sfomuseum:collection": "Aviation Library",
    "sfomuseum:creditline": "Collection of SFO Museum",
    "sfomuseum:date": "1966",
    "sfomuseum:date_acquired": "2010-05-10",
    "sfomuseum:daterange_end": "1966-12-31",
    "sfomuseum:daterange_start": "1966-01-01",
    "sfomuseum:description": "211, [13] p. illus., maps, ports. 28 cm.",
    "sfomuseum:description_library": "211, [13] p. illus., maps, ports. 28 cm.",
    "sfomuseum:medium": "paper, ink",
    "sfomuseum:placetype": "object",
    "sfomuseum:publication": "Fallbrook, CA: Aero Publishers, 1966.",
    "sfomuseum:publisher": "Aero Publishers",
    "sfomuseum:publisher_location": "Fallbrook, CA",
    "sfomuseum:subcategory": "Book",
    "sfomuseum:subject": "Aeronautics -- Hawaii -- History. \r",
    "wof:name": "Above the Pacific",
    "wof:placetype": "custom",
    "wof:placetype_alt": "object"
  },
  "geometry": {"coordinates":[-122.386155,37.616357],"type":"Point"}
}
