{
  "type": "Feature",
  "properties": {
    "date:cessation_lower": "1941-01-01",
    "date:cessation_upper": "1941-12-31",
    "date:inception_lower": "1941-01-01",
    "date:inception_upper": "1941-12-31",
    "iso:country": "XX",
    "sfomuseum:accession_number": "00-1114",
    "sfomuseum:author": "McGivern, Cecil",
    "sfomuseum:callnumber": "PN6120.R2 M19 1941",
    "sfomuseum:category": "Book",
    "sfomuseum:collection": "Aviation Library",
    "sfomuseum:date": "1941",
    "sfomuseum:daterange_end": "1941-12-31",
    "sfomuseum:daterange_start": "1941-01-01",
    "sfomuseum:description": "194 p. illus. 19 cm.",
    "sfomuseum:description_library": "194 p. illus. 19 cm.",
    "sfomuseum:medium": "paper, ink",
    "sfomuseum:placetype": "object",
    "sfomuseum:publication": "London: G. Allen \u0026 Unwin ltd, 1941.",
    "sfomuseum:publisher": "G. Allen \u0026 Unwin ltd",
    "sfomuseum:publisher_location": "London",
    "sfomuseum:series": "Front line library",
    "sfomuseum:subcategory": "Book",
    "sfomuseum:subject": "Radio plays.World War, 1939-1945 Drama.",
    "wof:name": "Bomb doors open, and other radio war features",
    "wof:placetype": "venue"
  },
  "geometry": {"coordinates":[-122.386155,37.616357],"type":"Point"}
}
