{
  "type": "Feature",
  "properties": {
    "date:cessation_lower": "1993-01-01",
    "date:cessation_upper": "1993-12-31",
    "date:inception_lower": "1993-01-01",
    "date:inception_upper": "1993-12-31",
    "isbn:number": "1857421345 (cased), 9781857421347 (cased),1857421353 (pbk.), 9781857421354 (pbk.)",
    "iso:country": "XX",
    "sfomuseum:accession_number": "99-1049",
    "sfomuseum:author": "Hawkins, Frank H.",
    "sfomuseum:callnumber": "TL671.2 .H38 1993",
    "sfomuseum:category": "Book",
    "sfomuseum:collection": "Aviation Library",
    "sfomuseum:date": "c. 1993",
    "sfomuseum:daterange_end": "1998-12-31",
    "sfomuseum:daterange_start": "1988-01-01",
    "sfomuseum:description": "384 p. : ill. ; 25 cm.",
    "sfomuseum:description_library": "384 p. : ill. ; 25 cm.",
    "sfomuseum:medium": "paper, ink",
    "sfomuseum:placetype": "object",
    "sfomuseum:publication": "Aldershot, England: Ashgate, c. 1993.",
    "sfomuseum:publisher": "Ashgate",
    "sfomuseum:publisher_location": "Aldershot, England",
    "sfomuseum:subcategory": "Book",
    "sfomuseum:subject": "Human engineering.Airplanes Design and construction.",
    "wof:name": "Human factors in flight",
    "wof:placetype": "custom",
    "wof:placetype_alt": "object"
  },
  "geometry": {"coordinates":[-122.386155,37.616357],"type":"Point"}
}
