{
  "type": "Feature",
  "properties": {
    "date:cessation_lower": "1923-01-01",
    "date:cessation_upper": "1923-12-31",
    "date:inception_lower": "1923-01-01",
    "date:inception_upper": "1923-12-31",
    "iso:country": "XX",
    "loc:subject_headings": [
      "sh85101264"
    ],
    "sfomuseum:accession_number": "00-0300",
    "sfomuseum:author": "Eastman Kodak Company of New York; and Eastman Kodak Company of New York",
    "sfomuseum:callnumber": "TR810 .E4 1923 SC",
    "sfomuseum:category": "Book",
    "sfomuseum:collection": "Aviation Library",
    "sfomuseum:date": "1923",
    "sfomuseum:daterange_end": "1923-12-31",
    "sfomuseum:daterange_start": "1923-01-01",
    "sfomuseum:description": "84 p. incl. illus., pl., diagrs. 22 cm.",
    "sfomuseum:description_library": "84 p. incl. illus., pl., diagrs. 22 cm.",
    "sfomuseum:medium": "paper, ink",
    "sfomuseum:placetype": "object",
    "sfomuseum:publication": "New York: D. Van Nostrand Company, 1923.",
    "sfomuseum:publisher": "D. Van Nostrand Company",
    "sfomuseum:publisher_location": "New York",
    "sfomuseum:series": "Monographs on the theory of photography, ed. by C. E. K. Mees, Mildred S. Schramm and Elsie L. Garvi",
    "sfomuseum:subcategory": "Book",
    "sfomuseum:subject": "Aerial photography.",
    "wof:name": "Aerial haze and its effect on photography from the air",
    "wof:placetype": "venue"
  },
  "geometry": {"coordinates":[-122.386155,37.616357],"type":"Point"}
}
