{
  "type": "Feature",
  "properties": {
    "date:cessation_lower": "2006-12-31",
    "date:cessation_upper": "2006-12-31",
    "date:inception_lower": "2006-01-01",
    "date:inception_upper": "2006-01-01",
    "iso:country": "XX",
    "sfomuseum:accession_number": "2007.086.160",
    "sfomuseum:category": "Food Service",
    "sfomuseum:collection": "Aviation Museum",
    "sfomuseum:creditline": "Gift of Ian H. Dally of Auckland, New Zealand",
    "sfomuseum:date": "2006",
    "sfomuseum:daterange_end": "2006-12-31",
    "sfomuseum:daterange_start": "2006-01-01",
    "sfomuseum:description": "Beverage menu / wine list produced by Austrian Airlines; white cover with color photographic image of wine in a glass; includes wine and spirits; in English, German, and Chinese; no menu number; class: first; undated.",
    "sfomuseum:media_ids": [
      1527843923, 
      1527843927
    ],
    "sfomuseum:medium": "paper, ink, metal",
    "sfomuseum:placetype": "object",
    "sfomuseum:subcategory": "Menu",
    "wof:name": "menu: Austrian Airlines, First Class",
    "wof:placetype": "venue"
  },
  "geometry": {"coordinates":[-122.386155,37.616358],"type":"Point"}
}
