{
  "type": "Feature",
  "properties": {
    "date:cessation_lower": "1987-01-01",
    "date:cessation_upper": "1987-12-31",
    "date:inception_lower": "1987-01-01",
    "date:inception_upper": "1987-12-31",
    "iso:country": "XX",
    "sfomuseum:accession_number": "2000.163.003",
    "sfomuseum:author": "Testrake, John",
    "sfomuseum:callnumber": "HV6432 .T48 1987 c.2",
    "sfomuseum:category": "Book",
    "sfomuseum:collection": "Aviation Library",
    "sfomuseum:creditline": "Purchase",
    "sfomuseum:date": "c. 1987",
    "sfomuseum:date_acquired": "2000-12-31",
    "sfomuseum:daterange_end": "1992-12-31",
    "sfomuseum:daterange_start": "1982-01-01",
    "sfomuseum:description": "256 p., [8] p. of plates : ill. ; 24 cm.",
    "sfomuseum:description_library": "256 p., [8] p. of plates : ill. ; 24 cm.",
    "sfomuseum:medium": "paper, ink",
    "sfomuseum:placetype": "object",
    "sfomuseum:publication": "Old Tappan, NJ: F.H. Revell, c. 1987.",
    "sfomuseum:publisher": "F.H. Revell",
    "sfomuseum:publisher_location": "Old Tappan, NJ",
    "sfomuseum:subcategory": "Book",
    "sfomuseum:subject": "Testrake, John, 1927-Hijacking of aircraft United States Case studies.TWA Flight 847 Hijacking Incident, 1985.Hostages United States Biography.Victims of terrorism United States Biography.",
    "wof:name": "Triumph over terror on Flight 847",
    "wof:placetype": "venue"
  },
  "geometry": {"coordinates":[-122.386155,37.616357],"type":"Point"}
}
