{
  "type": "Feature",
  "properties": {
    "date:cessation_lower":"1979-12-31",
    "date:cessation_upper":"1979-12-31",
    "date:inception_lower":"1960-01-01",
    "date:inception_upper":"1960-01-01",
    "iso:country":"XX",
    "sfomuseum:accession_number":"2007.051.041",
    "sfomuseum:airline":"Trans International Airlines",
    "sfomuseum:category":"Insignia",
    "sfomuseum:collection":"Aviation Museum",
    "sfomuseum:creditline":"Purchase",
    "sfomuseum:date":"1960s-1970s",
    "sfomuseum:daterange_end":"1979-12-31",
    "sfomuseum:daterange_start":"1960-01-01",
    "sfomuseum:description":"Gold oval-shaped pin with light blue enamel center; \"T I A\" printed in gold in center; small gold plane motif attached to lower right of pin; pin fasteners on back; this pin design worn 1960 - 1979.",
    "sfomuseum:medium":"metal",
    "sfomuseum:placetype":"object",
    "sfomuseum:subcategory":"Uniform Wing(s), Cabin Crew",
    "wof:depicts":[
        1159285319
    ],
    "wof:name":"stewardess wings: TIA (Trans International Airlines)",
    "wof:placetype":"venue"
},
  "geometry": {"coordinates":[-122.386155,37.616357],"type":"Point"}
}