{
  "type": "Feature",
  "properties": {
    "date:cessation_lower": "1938-12-31",
    "date:cessation_upper": "1938-12-31",
    "date:inception_lower": "1937-01-01",
    "date:inception_upper": "1937-01-01",
    "iso:country": "XX",
    "sfomuseum:accession_number": "00-1494",
    "sfomuseum:author": "Aero Industries Technical Institute (Los Angeles, Calif.)",
    "sfomuseum:callnumber": "TL671.2 .A37 1937 v.2",
    "sfomuseum:category": "Book",
    "sfomuseum:collection": "Aviation Library",
    "sfomuseum:date": "1937-1938",
    "sfomuseum:daterange_end": "1938-12-31",
    "sfomuseum:daterange_start": "1937-01-01",
    "sfomuseum:description": "2 v. (loose-leaf) : ill. ; 29 cm.",
    "sfomuseum:medium": "paper, ink",
    "sfomuseum:placetype": "object",
    "sfomuseum:publisher": "Aero Industries Technical Institute",
    "sfomuseum:publisher_location": "Los Angeles",
    "sfomuseum:subcategory": "Book",
    "sfomuseum:subject": "Machine-shop practice.Welding.Airplanes Design and construction.",
    "wof:name": "Modern aero metalcraft construction: theory, design, practice",
    "wof:placetype": "venue"
  },
  "geometry": {"coordinates":[-122.386155,37.616357],"type":"Point"}
}
