{
  "type": "Feature",
  "properties": {
    "date:cessation_lower":"1969-12-31",
    "date:cessation_upper":"1969-12-31",
    "date:inception_lower":"1969-01-01",
    "date:inception_upper":"1969-01-01",
    "iso:country":"XX",
    "sfomuseum:accession_number":"2001.122.021",
    "sfomuseum:category":"Company Record / Document",
    "sfomuseum:collection":"Aviation Archive",
    "sfomuseum:creditline":"Gift of Ingrid Templeton ",
    "sfomuseum:date":"1969",
    "sfomuseum:daterange_end":"1969-12-31",
    "sfomuseum:daterange_start":"1969-01-01",
    "sfomuseum:description":"Stewardess employee newsletter produced by Pan American World Airways; multipage booklet format with color photographic image depicting two flight attendants posing in cabin of Boeing 747, dressed in Superjet Blue and Galaxy Gold uniforms; interior includes \"From Rumor to Reality,\" \"Designer Analyzes the Uniform,\" and \"Candid Shots & Candid Comments...\"",
    "sfomuseum:media_ids":[
        1527828733
    ],
    "sfomuseum:medium":"paper, ink",
    "sfomuseum:placetype":"object",
    "sfomuseum:subcategory":"Company Newsletter",
    "wof:name":"employee newsletter: Pan American World Airways, Wing tips: a monthly publication by flight service for flight service [1 issue: 1969]",
    "wof:placetype":"venue"
},
  "geometry": {"coordinates":[-122.386155,37.616358],"type":"Point"}
}