{
  "type": "Feature",
  "properties": {
    "date:cessation_lower": "1983-12-31",
    "date:cessation_upper": "1983-12-31",
    "date:inception_lower": "1983-01-01",
    "date:inception_upper": "1983-01-01",
    "iso:country": "XX",
    "millsfield:images": [
      1527850573,
      1527835713
    ],
    "sfomuseum:accession_number": "2002.135.005.001",
    "sfomuseum:airline": "PEOPLExpress  (People Express Airlines)",
    "sfomuseum:airport": "Newark Liberty International Airport",
    "sfomuseum:category": "Scheduling / Ticketing",
    "sfomuseum:collection": "Aviation Archive",
    "sfomuseum:creditline": "Gift of Thomas G. Dragges",
    "sfomuseum:date": "1983",
    "sfomuseum:daterange_end": "1983-12-31",
    "sfomuseum:daterange_start": "1983-01-01",
    "sfomuseum:description": "Timetable issued by PEOPLExpress (People Express Airlines), effective September 20, 1983. The cover is brown with white and dark brown lettering.",
    "sfomuseum:dimensions": "9 x 3 3/4 inches (22.9 x 9.5 cm)",
    "sfomuseum:media_ids": [
      1527835713,
      1527850573
    ],
    "sfomuseum:medium": "paper, ink",
    "sfomuseum:placetype": "object",
    "sfomuseum:subcategory": "Timetable",
    "wof:depicts": [
      1159285013,
      102530049
    ],
    "wof:name": "timetable: PEOPLExpress (People Express Airlines)",
    "wof:placetype": "venue"
  },
  "geometry": {"coordinates":[-122.386155,37.616357],"type":"Point"}
}
