{
  "type": "Feature",
  "properties": {
    "date:cessation_lower":"2009-12-31",
    "date:cessation_upper":"2009-12-31",
    "date:inception_lower":"1999-01-01",
    "date:inception_upper":"1999-01-01",
    "iso:country":"XX",
    "sfomuseum:accession_number":"2006.049.004",
    "sfomuseum:category":"Book",
    "sfomuseum:collection":"Aviation Library",
    "sfomuseum:creditline":"Gift of Bruce McAllister",
    "sfomuseum:date":"c. 2004",
    "sfomuseum:daterange_end":"2009-12-31",
    "sfomuseum:daterange_start":"1999-01-01",
    "sfomuseum:description":"vii, 166 p. : ill. (chiefly col.) ; 22 x 28 cm.",
    "sfomuseum:medium":"paper, ink",
    "sfomuseum:placetype":"object",
    "sfomuseum:subcategory":"Book",
    "wof:name":"Wings over Denali: a photographic history of aviation in Denali National Park",
    "wof:placetype":"venue"
},
  "geometry": {"coordinates":[-122.386155,37.616358],"type":"Point"}
}