{
  "type": "Feature",
  "properties": {
    "date:cessation_lower":"1993-12-31",
    "date:cessation_upper":"1993-12-31",
    "date:inception_lower":"1993-01-01",
    "date:inception_upper":"1993-01-01",
    "iso:country":"XX",
    "sfomuseum:accession_number":"1999.657.125",
    "sfomuseum:airline":"Pan American World Airways",
    "sfomuseum:category":"Book",
    "sfomuseum:collection":"Aviation Library",
    "sfomuseum:creditline":"Purchase",
    "sfomuseum:date":"1993",
    "sfomuseum:daterange_end":"1993-12-31",
    "sfomuseum:daterange_start":"1993-01-01",
    "sfomuseum:description":"viii, 246 p. : ill., maps, ports. ; 24 cm.",
    "sfomuseum:medium":"paper, ink",
    "sfomuseum:placetype":"object",
    "sfomuseum:subcategory":"Book",
    "wof:depicts":[
        1159284989
    ],
    "wof:name":"For pilots' eyes only: confessions of a Pan Am veteran",
    "wof:placetype":"venue"
},
  "geometry": {"coordinates":[-122.386155,37.616357],"type":"Point"}
}