{
  "type": "Feature",
  "properties": {
    "date:cessation_lower": "1995-01-01",
    "date:cessation_upper": "1995-12-31",
    "date:inception_lower": "1995-01-01",
    "date:inception_upper": "1995-12-31",
    "iso:country": "XX",
    "millsfield:images": [
      1527848003,
      1527848007
    ],
    "millsfield:primary_image": 1527848003,
    "sfomuseum:accession_number": "2001.080.177",
    "sfomuseum:airline": "USAir",
    "sfomuseum:category": "Passenger Amenity",
    "sfomuseum:collection": "Aviation Archive",
    "sfomuseum:continent": "World Routes",
    "sfomuseum:creditline": "Gift of Thomas G. Dragges",
    "sfomuseum:date": "c. 1995",
    "sfomuseum:date_acquired": "2002-12-24",
    "sfomuseum:daterange_end": "2000-12-31",
    "sfomuseum:daterange_start": "1990-01-01",
    "sfomuseum:description": "Beverage menu and amenities list issued by USAir; white cover with gold text; menu items include spirits, beers, and soft drinks; no menu number; class: first; undated.",
    "sfomuseum:dimensions": "9 x 4 inches (22.9 x 10.2 cm)",
    "sfomuseum:media_ids": [
      1527848003,
      1527848007
    ],
    "sfomuseum:medium": "paper, ink",
    "sfomuseum:placetype": "object",
    "sfomuseum:publication": ": , c. 1995.",
    "sfomuseum:subcategory": "Menu",
    "wof:depicts": [
      1159285447,
      1159288239
    ],
    "wof:name": "menu: USAir, First Class",
    "wof:placetype": "venue"
  },
  "geometry": {"coordinates":[-122.386155,37.616357],"type":"Point"}
}
