{
  "type": "Feature",
  "properties": {
    "date:cessation_lower": "1972-01-01",
    "date:cessation_upper": "1972-12-31",
    "date:inception_lower": "1972-01-01",
    "date:inception_upper": "1972-12-31",
    "isbn:number": "0385070497, 9780385070492",
    "iso:country": "XX",
    "loc:named_authorities": [
      "no2014145449"
    ],
    "sfomuseum:accession_number": "2000.163.015",
    "sfomuseum:author": "Keith, Ronald A.",
    "sfomuseum:callnumber": "TL540.M224 K45 1972 c.2",
    "sfomuseum:category": "Book",
    "sfomuseum:collection": "Aviation Library",
    "sfomuseum:creditline": "Purchase",
    "sfomuseum:date": "1972",
    "sfomuseum:date_acquired": "2000-12-31",
    "sfomuseum:daterange_end": "1972-12-31",
    "sfomuseum:daterange_start": "1972-01-01",
    "sfomuseum:description": "322 p. 22 cm.",
    "sfomuseum:description_library": "322 p. 22 cm.",
    "sfomuseum:medium": "paper, ink",
    "sfomuseum:placetype": "object",
    "sfomuseum:publication": "Toronto, Canada; Garden City, NY: Doubleday, 1972.",
    "sfomuseum:publisher": "Doubleday",
    "sfomuseum:publisher_location": "Toronto, Canada; Garden City, NY",
    "sfomuseum:subcategory": "Book",
    "sfomuseum:subject": "McConachie, Grant, 1909-1965.",
    "wof:name": "Bush pilot with a briefcase: the happy-go-lucky story of Grant McConachie",
    "wof:placetype": "custom",
    "wof:placetype_alt": "object"
  },
  "geometry": {"coordinates":[-122.386155,37.616357],"type":"Point"}
}
