{
  "type": "Feature",
  "properties": {
    "date:cessation_lower": "1987-01-01",
    "date:cessation_upper": "1987-12-31",
    "date:inception_lower": "1987-01-01",
    "date:inception_upper": "1987-12-31",
    "iso:country": "XX",
    "millsfield:images": [
      1527839913,
      1527847905
    ],
    "millsfield:images_texts": [
      "Garuda Indonesia\nTimetable\nNorth American Edition\nApril 1st 1987 to\nOctober 31st 1987",
      "London\nInternational Network\nAmsterdam\nBrussels\nParis\nVienna\nTokyo\nAbu Dhabi\nHong Kong\n200x01\n•Manila\nSalam\nPenar\n•Kota Kinabalu\n•Menado\nto Los Angeles\nvia Honolulu\n® Biak\nJAKARTA\nDenpasar (Bali)]\n•Darwin\nPort Hedland\n•Perth\nSvdney\nMelbourne\nGaruda Indonesia"
    ],
    "millsfield:images_texts_ids": [
      1527839913,
      1527847905
    ],
    "millsfield:primary_image": 1527839913,
    "sfomuseum:accession_number": "2009.122.322",
    "sfomuseum:airline": "Garuda Indonesia",
    "sfomuseum:category": "Scheduling / Ticketing",
    "sfomuseum:collection": "Aviation Archive",
    "sfomuseum:creditline": "Gift of the William Hough Collection",
    "sfomuseum:date": "1987",
    "sfomuseum:date_acquired": "2010-06-08",
    "sfomuseum:daterange_end": "1987-12-31",
    "sfomuseum:daterange_start": "1987-01-01",
    "sfomuseum:description": "Timetable issued by Garuda Indonesia for North American service, effective April 1 through October 31, 1987; 14-page schedule; dark blue and white cover.",
    "sfomuseum:dimensions": "8 x 4 inches (20.3 x 10.2 cm)",
    "sfomuseum:media_ids": [
      1527847905,
      1527839913
    ],
    "sfomuseum:medium": "paper, ink",
    "sfomuseum:placetype": "object",
    "sfomuseum:publication": ": , 1987.",
    "sfomuseum:subcategory": "Timetable",
    "wof:depicts": [
      1159284415,
      1159288251
    ],
    "wof:name": "timetable: Garuda Indonesia",
    "wof:placetype": "custom",
    "wof:placetype_alt": "object"
  },
  "geometry": {"coordinates":[-122.386155,37.616357],"type":"Point"}
}
