{
  "type": "Feature",
  "properties": {
    "date:cessation_lower": "2000-01-01",
    "date:cessation_upper": "2009-12-31",
    "date:inception_lower": "2000-01-01",
    "date:inception_upper": "2009-12-31",
    "iso:country": "XX",
    "millsfield:images": [
      1746681283
    ],
    "millsfield:primary_image": 1746681283,
    "sfomuseum:accession_number": "2007.050.057",
    "sfomuseum:airline": "Cathay Pacific Airways",
    "sfomuseum:category": "Meal Service",
    "sfomuseum:collection": "Aviation Museum",
    "sfomuseum:creditline": "Gift of Cathay Pacific Airways",
    "sfomuseum:date": "2000s",
    "sfomuseum:date_acquired": "2008-03-26",
    "sfomuseum:daterange_end": "2000-12-31",
    "sfomuseum:daterange_start": "2000-01-01",
    "sfomuseum:description": "Fork issued by Cathay Pacific Airways for inflight meal service; silver fork with tapered handle; stamped circular design near end of handle; stamped logotype on reverse.",
    "sfomuseum:dimensions": "8 1/4 x 1 1/4 inches (21 x 3.2 cm)",
    "sfomuseum:medium": "stainless steel",
    "sfomuseum:placetype": "object",
    "sfomuseum:publication": ": , 2000s.",
    "sfomuseum:subcategory": "Flatware",
    "wof:depicts": [
      1159284127,
      1159286837
    ],
    "wof:name": "fork: Cathay Pacific Airways",
    "wof:placetype": "custom",
    "wof:placetype_alt": "object"
  },
  "geometry": {"coordinates":[-122.386155,37.616357],"type":"Point"}
}
