{
  "type": "Feature",
  "properties": {
    "date:cessation_lower":"1999-12-31",
    "date:cessation_upper":"1999-12-31",
    "date:inception_lower":"1999-01-01",
    "date:inception_upper":"1999-01-01",
    "iso:country":"XX",
    "sfomuseum:accession_number":"2003.105.020.011",
    "sfomuseum:category":"Scheduling / Ticketing",
    "sfomuseum:collection":"Aviation Archive",
    "sfomuseum:creditline":"Gift of Craig Lynes",
    "sfomuseum:date":"1999",
    "sfomuseum:daterange_end":"1999-12-31",
    "sfomuseum:daterange_start":"1999-01-01",
    "sfomuseum:description":"Timetable issued by Alaska Airlines, effective June 6 through September 14, 1999; twenty-four page schedule. The cover is a full page photographic image of a boy and lawn mower in front of a home. The company name is at the top. The lettering is white and black. The back is a map of the western United States including Alaska with airline destinations in black lettering.",
    "sfomuseum:medium":"paper, ink",
    "sfomuseum:placetype":"object",
    "sfomuseum:subcategory":"Timetable",
    "wof:name":"timetable: Alaska Airlines, includes Horizon Air",
    "wof:placetype":"venue"
},
  "geometry": {"coordinates":[-122.386155,37.616358],"type":"Point"}
}