{
  "type": "Feature",
  "properties": {
    "date:cessation_lower": "1996-01-01",
    "date:cessation_upper": "1996-12-31",
    "date:inception_lower": "1996-01-01",
    "date:inception_upper": "1996-12-31",
    "iso:country": "XX",
    "sfomuseum:accession_number": "2001.169.001",
    "sfomuseum:author": "Aircraft Owners and Pilots Association",
    "sfomuseum:callnumber": "TL726.2 .A72 2000",
    "sfomuseum:category": "Book",
    "sfomuseum:collection": "Aviation Library",
    "sfomuseum:creditline": "Gift of Frank A. Norick",
    "sfomuseum:date": "1996",
    "sfomuseum:date_acquired": "2002-11-13",
    "sfomuseum:daterange_end": "1996-12-31",
    "sfomuseum:daterange_start": "1996-01-01",
    "sfomuseum:description": "v. : ill. ; 28 cm.",
    "sfomuseum:description_library": "v. : ill. ; 28 cm.",
    "sfomuseum:issue": "2000",
    "sfomuseum:issues_held": "[2000]",
    "sfomuseum:medium": "paper, ink",
    "sfomuseum:placetype": "object",
    "sfomuseum:publication": "Frederick, MD: Aircraft Owners and Pilots Association, 1996.",
    "sfomuseum:publisher": "Aircraft Owners and Pilots Association",
    "sfomuseum:publisher_location": "Frederick, MD",
    "sfomuseum:subcategory": "Book",
    "sfomuseum:subject": "Airports United States Directories. Airplanes Piloting Handbooks, manuals, etc.",
    "wof:name": "AOPA's airport directory [2000]",
    "wof:placetype": "custom",
    "wof:placetype_alt": "object"
  },
  "geometry": {"coordinates":[-122.386155,37.616357],"type":"Point"}
}
