{
  "type": "Feature",
  "properties": {
    "date:cessation_lower":"1968-12-31",
    "date:cessation_upper":"1968-12-31",
    "date:inception_lower":"1968-01-01",
    "date:inception_upper":"1968-01-01",
    "iso:country":"XX",
    "sfomuseum:accession_number":"2011.032.1858",
    "sfomuseum:category":"Photograph",
    "sfomuseum:collection":"Aviation Archive",
    "sfomuseum:creditline":"Transfer",
    "sfomuseum:date":"1968",
    "sfomuseum:daterange_end":"1968-12-31",
    "sfomuseum:daterange_start":"1968-01-01",
    "sfomuseum:description":"From attached handwritten note: \u201c6-26-68 / Airport Terminal\u201d. Black and white photographic print depicting ground-level view of two aircraft on ramp / apron; rear view of Boeing 727 with emergency exit stairs extended on right side of image; port view of front end of Pacifica Southwest Airlines (PSA) aircraft on the left side; jetway and airport operations equipment visible; San Francisco International Airport (SFO); photograph taken on June 26, 1968.",
    "sfomuseum:media_ids":[
        1527826499
    ],
    "sfomuseum:medium":"photograph",
    "sfomuseum:placetype":"object",
    "sfomuseum:subcategory":"Print, Photograph",
    "wof:depicts":[
        1159284973
    ],
    "wof:name":"photograph: San Francisco International Airport (SFO), Pacific Southwest Airlines (PSA) jetway and aircraft",
    "wof:placetype":"venue"
},
  "geometry": {"coordinates":[-122.386155,37.616358],"type":"Point"}
}