{
  "type": "Feature",
  "properties": {
    "date:cessation_lower":"1967-12-31",
    "date:cessation_upper":"1967-12-31",
    "date:inception_lower":"1967-01-01",
    "date:inception_upper":"1967-01-01",
    "iso:country":"XX",
    "sfomuseum:accession_number":"2005.132.042.010",
    "sfomuseum:category":"Scheduling / Ticketing",
    "sfomuseum:collection":"Aviation Archive",
    "sfomuseum:creditline":"Gift of the William Hough Collection",
    "sfomuseum:date":"1967",
    "sfomuseum:daterange_end":"1967-12-31",
    "sfomuseum:daterange_start":"1967-01-01",
    "sfomuseum:description":"Timetable issued by Pacific Southwest Airlines (PSA), effective December 13, 1967 through January 2, 1968; folded double-sided single green sheet. The company logo is at the top.",
    "sfomuseum:medium":"paper, ink",
    "sfomuseum:placetype":"object",
    "sfomuseum:subcategory":"Timetable",
    "wof:depicts":[
        1159284973
    ],
    "wof:name":"timetable: Pacific Southwest Airlines (PSA)",
    "wof:placetype":"venue"
},
  "geometry": {"coordinates":[-122.386155,37.616358],"type":"Point"}
}