{
  "type": "Feature",
  "properties": {
    "date:cessation_lower":"1968-12-31",
    "date:cessation_upper":"1968-12-31",
    "date:inception_lower":"1968-01-01",
    "date:inception_upper":"1968-01-01",
    "iso:country":"XX",
    "sfomuseum:accession_number":"2011.032.1885",
    "sfomuseum:category":"Photograph",
    "sfomuseum:collection":"Aviation Archive",
    "sfomuseum:creditline":"Transfer",
    "sfomuseum:date":"1968",
    "sfomuseum:daterange_end":"1968-12-31",
    "sfomuseum:daterange_start":"1968-01-01",
    "sfomuseum:description":"From attached handwritten note: \u201c5-22-68 / PSA Jet loaders\u201d. Black and white photographic print depicting construction of Pacific Southwest Airlines (PSA) jet loaders at San Francisco International Airport (SFO); building framing and scaffolding visible; PSA ramp stairs with logo visible; photo taken May 22, 1968.",
    "sfomuseum:media_ids":[
        1527826559
    ],
    "sfomuseum:medium":"photograph",
    "sfomuseum:placetype":"object",
    "sfomuseum:subcategory":"Print, Photograph",
    "wof:depicts":[
        1159284973,
        102527513
    ],
    "wof:name":"photograph: San Francisco International Airport (SFO), construction of Pacific Southwest Airlines (PSA) pier and jetway",
    "wof:placetype":"venue"
},
  "geometry": {"coordinates":[-122.386155,37.616358],"type":"Point"}
}