{
  "type": "Feature",
  "properties": {
    "date:cessation_lower":"1952-12-31",
    "date:cessation_upper":"1952-12-31",
    "date:inception_lower":"1952-01-01",
    "date:inception_upper":"1952-01-01",
    "iso:country":"XX",
    "sfomuseum:accession_number":"2011.032.0288",
    "sfomuseum:category":"Photograph",
    "sfomuseum:collection":"Aviation Archive",
    "sfomuseum:creditline":"Transfer",
    "sfomuseum:date":"1952",
    "sfomuseum:daterange_end":"1952-12-31",
    "sfomuseum:daterange_start":"1952-01-01",
    "sfomuseum:description":"From attached handwritten note: \u201c03354 / 12-8-52 / Rwy 1L - 19R / View N Showing damaged surface\u201d. Black and white photograph of damaged asphalt on Runway 1L/19R at San Francisco Airport; surrounding by globes, presumably to separate area; photograph taken on December 8, 1952. ",
    "sfomuseum:media_ids":[
        1527821947
    ],
    "sfomuseum:medium":"negative",
    "sfomuseum:placetype":"object",
    "sfomuseum:subcategory":"Negative",
    "wof:name":"negative: San Francisco Airport, runway maintenance",
    "wof:placetype":"venue"
},
  "geometry": {"coordinates":[-122.386155,37.616358],"type":"Point"}
}