{
  "type": "Feature",
  "properties": {
    "date:cessation_lower":"1935-12-31",
    "date:cessation_upper":"1935-12-31",
    "date:inception_lower":"1935-01-01",
    "date:inception_upper":"1935-01-01",
    "iso:country":"US",
    "sfomuseum:accession_number":"1994.18.003",
    "sfomuseum:category":"Philately",
    "sfomuseum:collection":"Aviation Archive",
    "sfomuseum:continent":"Transpacific",
    "sfomuseum:country":"United States",
    "sfomuseum:creditline":"Purchase",
    "sfomuseum:date":"11/22/1935",
    "sfomuseum:daterange_end":"1935-11-22",
    "sfomuseum:daterange_start":"1935-11-22",
    "sfomuseum:description":"Airmail flight cover, Pan American Airways, commemorating first scheduled mail flight between San Francisco and Manila, San Francisco / Alameda Airport to Manila leg, FAM-14; green cachet with image of Martin M-130 and sailing ship; three stamps: blue 25-cent \u201cTrans-Pacific Air Mail\u201d (United States); postmark: November 22, 1935, San Francisco; type 1 killer; backstamp: November 29, 1935, Manila; type 5x killer, \u201cManila Trade Center of the Pacific\u201d; envelope: border type I; \"VIA AIR MAIL\"; addressed to \"Mr. J. T. Trippe\u201d.",
    "sfomuseum:maker":"Pan American Airways, Inc.",
    "sfomuseum:media_ids":[
        1527828857,
        1527828859
    ],
    "sfomuseum:medium":"ink on paper",
    "sfomuseum:placetype":"object",
    "sfomuseum:subcategory":"Airmail Flight Cover",
    "wof:name":"airmail flight cover: Pan American Airways, FAM-14, San Francisco (Alameda) - Manila route",
    "wof:placetype":"venue"
},
  "geometry": {"coordinates":[-122.386155,37.616358],"type":"Point"}
}