{
  "type": "Feature",
  "properties": {
    "date:cessation_lower": "1976-01-01",
    "date:cessation_upper": "1976-12-31",
    "date:inception_lower": "1976-01-01",
    "date:inception_upper": "1976-12-31",
    "iso:country": "XX",
    "sfomuseum:accession_number": "00-3384",
    "sfomuseum:author": "Bernhard Leopold, consort of Juliana, Queen of the Netherlands",
    "sfomuseum:callnumber": "TL521 .W56 1976",
    "sfomuseum:category": "Book",
    "sfomuseum:collection": "Aviation Library",
    "sfomuseum:date": "c. 1976",
    "sfomuseum:daterange_end": "1981-12-31",
    "sfomuseum:daterange_start": "1971-01-01",
    "sfomuseum:description": "32 p. : ill., ports. ; 24 cm.",
    "sfomuseum:description_library": "32 p. : ill., ports. ; 24 cm.",
    "sfomuseum:medium": "paper, ink",
    "sfomuseum:placetype": "object",
    "sfomuseum:publication": "New York: Wings Club, c. 1976.",
    "sfomuseum:publisher": "Wings Club",
    "sfomuseum:publisher_location": "New York",
    "sfomuseum:series": "Wings Club Sight lecture ; 1976",
    "sfomuseum:subcategory": "Book",
    "sfomuseum:subject": "Aeronautics Netherlands HistoryKLM (Airline)",
    "wof:name": "The Netherlands people, their country and their civil aviation, to-day and in the future",
    "wof:placetype": "venue"
  },
  "geometry": {"coordinates":[-122.386155,37.616357],"type":"Point"}
}
