{
  "type": "Feature",
  "properties": {
    "date:cessation_lower": "1983-01-01",
    "date:cessation_upper": "1983-12-31",
    "date:inception_lower": "1983-01-01",
    "date:inception_upper": "1983-12-31",
    "iso:country": "XX",
    "millsfield:images": [
      1527839231
    ],
    "millsfield:images_texts": [
      "PAN AM\nSystem Timetable\nEffective October 30, 1983\nIntroducing the\nPanAm/Pacific Express\nNow getting from the\nWest Coast to the World is easier."
    ],
    "millsfield:images_texts_ids": [
      1527839231
    ],
    "millsfield:primary_image": 1527839231,
    "sfomuseum:accession_number": "2005.132.039.013",
    "sfomuseum:airline": "Pacific Express",
    "sfomuseum:category": "Scheduling / Ticketing",
    "sfomuseum:collection": "Aviation Archive",
    "sfomuseum:creditline": "Gift of the William Hough Collection",
    "sfomuseum:date": "1983",
    "sfomuseum:date_acquired": "2006-12-05",
    "sfomuseum:daterange_end": "1983-12-31",
    "sfomuseum:daterange_start": "1983-01-01",
    "sfomuseum:description": "System timetable issued by Pacific Express / Pan American World Airways, effective October 30, 1983; color photographic image of skyline of San Francisco at sunrise and text announcing partnership with Pan American.",
    "sfomuseum:dimensions": "9 x 4 inches (22.9 x 10.2 cm)",
    "sfomuseum:media_ids": [
      1527839231
    ],
    "sfomuseum:medium": "paper, ink",
    "sfomuseum:placetype": "object",
    "sfomuseum:publication": ": , 1983.",
    "sfomuseum:subcategory": "Timetable",
    "wof:depicts": [
      1159286839,
      1159284965,
      1159284991
    ],
    "wof:name": "timetable: Pacific Express / Pan American World Airways",
    "wof:placetype": "custom",
    "wof:placetype_alt": [
      "object"
    ]
  },
  "geometry": {"coordinates":[-122.386155,37.616357],"type":"Point"}
}
