{
  "type": "Feature",
  "properties": {
    "date:cessation_lower": "1959-10-10",
    "date:cessation_upper": "1959-10-10",
    "date:inception_lower": "1959-10-10",
    "date:inception_upper": "1959-10-10",
    "iso:country": "XX",
    "millsfield:images": [
      1527833013,
      1527833015
    ],
    "millsfield:primary_image": 1527833013,
    "sfomuseum:accession_number": "2012.149.1843",
    "sfomuseum:airline": "Pan American World Airways",
    "sfomuseum:category": "Philately",
    "sfomuseum:collection": "Aviation Archive",
    "sfomuseum:creditline": "Gift of the Captain John B. Russell Family",
    "sfomuseum:date": "10/10/1959",
    "sfomuseum:date_acquired": "2013-05-31",
    "sfomuseum:daterange_end": "1959-10-10",
    "sfomuseum:daterange_start": "1959-10-10",
    "sfomuseum:description": "Airmail flight cover, Pan American World Airways; blue cachet at left depicting globe logo and profile view of jet, with text, “First Jet Air Mail Flight ‘Round the World / San Francisco - New York”; postmarked October 10, 1959, San Francisco, with 25-cent postage stamp; backstamp: October 14, 1959 in New York.",
    "sfomuseum:dimensions": "3 1/2 x 6 1/2 inches (8.9 x 16.5 cm)",
    "sfomuseum:media_ids": [
      1527833013,
      1527833015
    ],
    "sfomuseum:medium": "paper, ink",
    "sfomuseum:placetype": "object",
    "sfomuseum:publication": ": , 10/10/1959.",
    "sfomuseum:subcategory": "Airmail Flight Cover",
    "wof:depicts": [
      1159284989,
      1159286839
    ],
    "wof:name": "airmail flight cover: Pan American World Airways, San Francisco - New York route",
    "wof:placetype": "venue"
  },
  "geometry": {"coordinates":[-122.386155,37.616357],"type":"Point"}
}
