{
  "type": "Feature",
  "properties": {
    "date:cessation_lower": "1988-12-31",
    "date:cessation_upper": "1988-12-31",
    "date:inception_lower": "1978-01-01",
    "date:inception_upper": "1978-01-01",
    "geotag:angle": 68.90164157894264,
    "iso:country": "XX",
    "sfomuseum:accession_number": "2011.032.2754",
    "sfomuseum:category": "Photograph",
    "sfomuseum:collection": "Aviation Archive",
    "sfomuseum:creditline": "Transfer",
    "sfomuseum:date": "c. 1983",
    "sfomuseum:daterange_end": "1988-12-31",
    "sfomuseum:daterange_start": "1978-01-01",
    "sfomuseum:description": "Black and white negative depicting exterior view of Central Terminal (now Terminal 2 / T2), San Francisco International Airport (SFO); oblique view from curbside on departure level with roadways and curbside visible; clear midday conditions.",
    "sfomuseum:media_ids": [
      1527828501
    ],
    "sfomuseum:medium": "negative",
    "sfomuseum:placetype": "object",
    "sfomuseum:subcategory": "Negative",
    "wof:depicts": [
      102527513
    ],
    "wof:name": "negative: San Francisco International Airport (SFO), Central Terminal",
    "wof:placetype": "venue"
  },
  "geometry": {
    "coordinates": [
      -122.38417625427248,
      37.61602462360999
    ],
    "type": "Point"
  }
}