{
  "type": "Feature",
  "properties": {
    "date:cessation_lower": "2005-01-01",
    "date:cessation_upper": "2005-12-31",
    "date:inception_lower": "2005-01-01",
    "date:inception_upper": "2005-12-31",
    "iso:country": "XX",
    "sfomuseum:accession_number": "2005.009.052",
    "sfomuseum:author": "Downs, Mike",
    "sfomuseum:callnumber": "TL547 .D69 2005 JUV",
    "sfomuseum:category": "Book",
    "sfomuseum:collection": "Aviation Library",
    "sfomuseum:creditline": "Purchase",
    "sfomuseum:date": "2005",
    "sfomuseum:date_acquired": "2005-12-31",
    "sfomuseum:daterange_end": "2005-12-31",
    "sfomuseum:daterange_start": "2005-01-01",
    "sfomuseum:description": "32 p. : ill. ; 25 x 27 cm.",
    "sfomuseum:description_library": "32 p. : ill. ; 25 x 27 cm.",
    "sfomuseum:distributor_location": "Enfield",
    "sfomuseum:medium": "paper, ink",
    "sfomuseum:placetype": "object",
    "sfomuseum:publication": "Berkeley, CA: Tricycle, 2005.",
    "sfomuseum:publisher": "Tricycle",
    "sfomuseum:publisher_location": "Berkeley, CA",
    "sfomuseum:subcategory": "Book",
    "sfomuseum:subject": "Airplanes Noise Pictorial works Juvenile literature.",
    "wof:name": "The noisy airplane ride",
    "wof:placetype": "venue"
  },
  "geometry": {"coordinates":[-122.386155,37.616357],"type":"Point"}
}
