{
  "type": "Feature",
  "properties": {
    "date:cessation_lower": "1960-12-31",
    "date:cessation_upper": "1960-12-31",
    "date:inception_lower": "1960-01-01",
    "date:inception_upper": "1960-01-01",
    "iso:country": "XX",
    "millsfield:images": [
      1527822115
    ],
    "sfomuseum:accession_number": "2011.032.0363",
    "sfomuseum:aircraft": "Boeing 707",
    "sfomuseum:airline": "Lufthansa  (Lufthansa German Airlines)",
    "sfomuseum:airport": "San Francisco International Airport",
    "sfomuseum:artist": "Marshall Moxom",
    "sfomuseum:category": "Photograph",
    "sfomuseum:collection": "Aviation Archive",
    "sfomuseum:creditline": "Transfer",
    "sfomuseum:date": "1960",
    "sfomuseum:daterange_end": "1960-12-31",
    "sfomuseum:daterange_start": "1960-01-01",
    "sfomuseum:description": "From attached handwritten note: “04064 / 5-14-60 / Lufthansa inaugural flight / taken by: Moxom”. Black and white photographic negative depicting rear three-quarter view of Lufthansa German Airlines Boeing 707-430 aircraft, inaugural service to San Francisco International Airport (SFO); exterior ground-level view from behind aircraft; passengers boarding jet from ramp at Pier D; photo taken on May 14, 1960 by Marshall Moxom.",
    "sfomuseum:dimensions": "4 x 5 inches (10.2 x 12.7 cm)",
    "sfomuseum:media_ids": [
      1527822115
    ],
    "sfomuseum:medium": "negative",
    "sfomuseum:placetype": "object",
    "sfomuseum:subcategory": "Negative",
    "wof:depicts": [
      1159289653,
      1159293593,
      1159284711,
      102527513
    ],
    "wof:name": "negative: San Francisco International Airport (SFO), Lufthansa German Airlines, Boeing 707-430",
    "wof:placetype": "venue"
  },
  "geometry": {"coordinates":[-122.386155,37.616357],"type":"Point"}
}
