{
  "type": "Feature",
  "properties": {
    "date:cessation_lower": "1988-01-01",
    "date:cessation_upper": "1988-12-31",
    "date:inception_lower": "1988-01-01",
    "date:inception_upper": "1988-12-31",
    "iso:country": "XX",
    "sfomuseum:accession_number": "2003.079.009",
    "sfomuseum:author": "Alexander, Richard L.",
    "sfomuseum:callnumber": "UG626.2.A44 A3 1988",
    "sfomuseum:category": "Book",
    "sfomuseum:collection": "Aviation Library",
    "sfomuseum:creditline": "Gift of Robert A. Chaber",
    "sfomuseum:date": "c. 1988",
    "sfomuseum:daterange_end": "1993-12-31",
    "sfomuseum:daterange_start": "1983-01-01",
    "sfomuseum:description": "xiv, 271 p., [48] p. of plates : ill., maps, ports. ; 24 cm.",
    "sfomuseum:description_library": "xiv, 271 p., [48] p. of plates : ill., maps, ports. ; 24 cm.",
    "sfomuseum:medium": "paper, ink",
    "sfomuseum:notes_library": "Includes index.  Signed by author. Order form included. Needs new spine marker. ",
    "sfomuseum:placetype": "object",
    "sfomuseum:publication": "Hemet, CA: Robinson Typographics, c. 1988.",
    "sfomuseum:publisher": "Robinson Typographics",
    "sfomuseum:publisher_location": "Hemet, CA",
    "sfomuseum:subcategory": "Book",
    "sfomuseum:subject": "Alexander, Richard L., ca. 1914-",
    "wof:name": "They called me Dixie",
    "wof:placetype": "venue"
  },
  "geometry": {"coordinates":[-122.386155,37.616357],"type":"Point"}
}
