{
  "type": "Feature",
  "properties": {
    "date:cessation_lower": "1960-12-31",
    "date:cessation_upper": "1960-12-31",
    "date:inception_lower": "1960-01-01",
    "date:inception_upper": "1960-01-01",
    "iso:country": "XX",
    "sfomuseum:accession_number": "2012.149.1855",
    "sfomuseum:category": "Philately",
    "sfomuseum:collection": "Aviation Archive",
    "sfomuseum:creditline": "Gift of the Captain John B. Russell Family",
    "sfomuseum:date": "03/01/1960",
    "sfomuseum:daterange_end": "1960-03-01",
    "sfomuseum:daterange_start": "1960-03-01",
    "sfomuseum:description": "Airmail flight cover, Pan American World Airways, Air Mail Route 20; blue cachet at left depicting profile view of jet against Alaska route map, with text, “First Jet Air Mail / Seattle, Washington to Fairbanks, Alaska”; postmarked March 1, 1960 in Seattle, with 7-cent postage stamp; backstamp: March 1, 1960 in Fairbanks; addressed to Oscar H. Fatout.",
    "sfomuseum:media_ids": [
      1527833107, 
      1527833109
    ],
    "sfomuseum:medium": "paper, ink",
    "sfomuseum:placetype": "object",
    "sfomuseum:subcategory": "Airmail Flight Cover",
    "wof:name": "airmail flight cover: Pan American World Airways, Seattle - Fairbanks route",
    "wof:placetype": "venue"
  },
  "geometry": {"coordinates":[-122.386155,37.616358],"type":"Point"}
}
