{
  "type": "Feature",
  "properties": {
    "date:cessation_lower": "1993-12-31",
    "date:cessation_upper": "1993-12-31",
    "date:inception_lower": "1993-01-01",
    "date:inception_upper": "1993-01-01",
    "iso:country": "XX",
    "sfomuseum:accession_number": "2004.115.0269",
    "sfomuseum:aircraft": "Vickers Viscount",
    "sfomuseum:airline": "Capital Airlines",
    "sfomuseum:category": "Photograph",
    "sfomuseum:collection": "Aviation Archive",
    "sfomuseum:creditline": "Gift of the William Hough Collection",
    "sfomuseum:date": "1993",
    "sfomuseum:daterange_end": "1993-12-31",
    "sfomuseum:daterange_start": "1993-01-01",
    "sfomuseum:description": "Color photographic slide depicting Capital Airlines Vickers Viscount, July 10, 1993; photo taken by William Hough.",
    "sfomuseum:medium": "color slide",
    "sfomuseum:placetype": "object",
    "sfomuseum:subcategory": "Slide",
    "wof:depicts": [
      1159291963,
      1159293777,
      1159284093
    ],
    "wof:name": "slide: Capital Airlines, Vickers Viscount",
    "wof:placetype": "venue"
  },
  "geometry": {"coordinates":[-122.386155,37.616357],"type":"Point"}
}
