{
  "type": "Feature",
  "properties": {
    "date:cessation_lower": "2000-01-01",
    "date:cessation_upper": "2000-12-31",
    "date:inception_lower": "2000-01-01",
    "date:inception_upper": "2000-12-31",
    "iso:country": "XX",
    "millsfield:images": [
      1527846389,
      1527846391
    ],
    "millsfield:images_texts": [
      "MENU",
      "MANNICAL\nENTREE\nSPICED CHICKEN ON GARDEN GREENS\nMAIN COURSE\nBEFETENDERLOIN WITH MADEIRA SAUCE\nGRILLED SALMON WITH CHILLEAM AND STIR FRIED VEGETABLES\nSALAD OF PRAWNS AND PROSCIUTTO\nDESSERT\nMACADAMIA CHEESE CAKE\nSELECTION OF CHEESE AND FRUIT\nCOFFEE TEA HERBAL TEA\nPlease accept our apolosy if vour choice is not availablo\nWINE LIST\nFRENCH CHAMPAGNE\nAUSTRALIAN SPARKLING WINE\nThe Australian wine industry iS One DRA AN INTed in the world. The first vines were\nplanted in Sydney in 1788, and today, the wines of Australia are internationally recognised and\nacclalmed\nEach Australian state has premium wine growing regions,\nsour Australlas coonaward, Glare and Darossa,\nvictorias yarra valley and Mormmeron Feminsula,\nMaroaret Kiver in Western Australia.\nand the Hunter Valley in New South Wales.\nFrom these and other Australian regions we offer you a selection of the following wines:\nRIESLING\nCharacterised by a highly aromatic, flowery nose, a tangy freshness on the palate with a crisp, clean\nCHarDOnnay\nA very jull and complex wme, win gresh grunty favour ranging from green stone frut to ripe\nAUSTRALIAN SOFT REDS\nAstana makes javoursome reas generous or full-bodied stylen colour, men rasung and verging on\nKich and sweet flavour, a pron"
    ],
    "millsfield:images_texts_ids": [
      1527846389,
      1527846391
    ],
    "millsfield:primary_image": 1527846389,
    "sfomuseum:accession_number": "2007.086.095",
    "sfomuseum:airline": "Qantas Airways",
    "sfomuseum:category": "Passenger Amenity, Archive",
    "sfomuseum:collection": "Aviation Archive",
    "sfomuseum:creditline": "Gift of Ian H. Dally of Auckland, New Zealand",
    "sfomuseum:date": "c. 2000",
    "sfomuseum:date_acquired": "2007-09-29",
    "sfomuseum:daterange_end": "2005-12-31",
    "sfomuseum:daterange_start": "1995-01-01",
    "sfomuseum:description": "Menu and wine list issued by Qantas Airways; red-toned photographic image of ripples in sand; menu items include beef tenderloin and grilled salmon; menu number: J_TAS_MM1.039; date: NOV03.",
    "sfomuseum:dimensions": "11 x 4 inches (27.9 x 10.2 cm)",
    "sfomuseum:media_ids": [
      1527846389,
      1527846391
    ],
    "sfomuseum:medium": "paper, ink",
    "sfomuseum:placetype": "object",
    "sfomuseum:publication": ": , c. 2000.",
    "sfomuseum:subcategory": "Menu",
    "wof:depicts": [
      1159285043,
      1159287479
    ],
    "wof:name": "menu: Qantas Airways",
    "wof:placetype": "custom",
    "wof:placetype_alt": [
      "object"
    ]
  },
  "geometry": {"coordinates":[-122.386155,37.616357],"type":"Point"}
}
