{
  "type": "Feature",
  "properties": {
    "date:cessation_lower": "2000-01-01",
    "date:cessation_upper": "2000-12-31",
    "date:inception_lower": "2000-01-01",
    "date:inception_upper": "2000-12-31",
    "iso:country": "XX",
    "millsfield:images": [
      1527846391,
      1527846389
    ],
    "sfomuseum:accession_number": "2007.086.095",
    "sfomuseum:airline": "Qantas Airways",
    "sfomuseum:category": "Passenger Amenity",
    "sfomuseum:collection": "Aviation Archive",
    "sfomuseum:creditline": "Gift of Ian H. Dally of Auckland, New Zealand",
    "sfomuseum:date": "c. 2000",
    "sfomuseum:daterange_end": "2005-12-31",
    "sfomuseum:daterange_start": "1995-01-01",
    "sfomuseum:description": "Menu and wine list issued by Qantas Airways; red-toned photographic image of ripples in sand; menu items include beef tenderloin and grilled salmon; menu number: J_TAS_MM1.039; date: NOV03.",
    "sfomuseum:dimensions": "11 x 4 inches (27.9 x 10.2 cm)",
    "sfomuseum:media_ids": [
      1527846389,
      1527846391
    ],
    "sfomuseum:medium": "paper, ink",
    "sfomuseum:placetype": "object",
    "sfomuseum:subcategory": "Menu",
    "wof:depicts": [
      1159285043
    ],
    "wof:name": "menu: Qantas Airways",
    "wof:placetype": "venue"
  },
  "geometry": {"coordinates":[-122.386155,37.616357],"type":"Point"}
}
