{
  "type": "Feature",
  "properties": {
    "date:cessation_lower": "1968-01-01",
    "date:cessation_upper": "1968-12-31",
    "date:inception_lower": "1968-01-01",
    "date:inception_upper": "1968-12-31",
    "iso:country": "XX",
    "sfomuseum:accession_number": "2001.038.164.139",
    "sfomuseum:airline": "Pan American World Airways",
    "sfomuseum:category": "Promotional",
    "sfomuseum:collection": "Aviation Archive",
    "sfomuseum:creditline": "Gift of Barnaby Conrad III",
    "sfomuseum:date": "c. 1968",
    "sfomuseum:daterange_end": "1973-12-31",
    "sfomuseum:daterange_start": "1963-01-01",
    "sfomuseum:description": "Advertisement from April (year?) issue of Holiday promoting Pan American World Airways, titled “You can meet in London tonight” with color illustration depicting couple dining in restaurant with nighttime view of Big Ben clock tower; separate illustration of Boeing 707 Jet Clipper aircraft across bottom.",
    "sfomuseum:dimensions": "14 x 10 1/2 inches (35.6 x 26.7 cm)",
    "sfomuseum:medium": "paper, ink",
    "sfomuseum:placetype": "object",
    "sfomuseum:publication": ": , c. 1968.",
    "sfomuseum:subcategory": "Advertisement, 2D",
    "sfomuseum:subject": "Pan Am promotional advertisement",
    "wof:depicts": [
      1159284989,
      1159289653,
      1159293593
    ],
    "wof:name": "advertisement: Pan American World Airways, Holiday",
    "wof:placetype": "venue"
  },
  "geometry": {"coordinates":[-122.386155,37.616357],"type":"Point"}
}
