{
  "type": "Feature",
  "properties": {
    "date:cessation_lower": "1968-01-01",
    "date:cessation_upper": "1968-12-31",
    "date:inception_lower": "1968-01-01",
    "date:inception_upper": "1968-12-31",
    "iso:country": "XX",
    "millsfield:images": [
      1763388453
    ],
    "millsfield:images_texts": [
      "This is your year to enjoy the richness of travel, through the magic of Pan Am's Jet Clippers*.\nWorld's\nMost Experienced\nAirline\nYou can meet in London tonight\n(Pan Am takes you there in less than 7 magic hours by Jet Clipper )\nYour rendezvous doesn't have to\nwait! Pan Am brings Europe so much\ncloser by Jet Clipper. Now it's possi-\nble to breakfast in New York. lunch\non board Pan Am's Jet Clipper, and\nenjoy a candlelight dinner the same\nevening in London. On Pan Am's Jet\neconomy class — London is only $45360\nround trip, $48960 to Paris, $59150 to\nKome. Deluxe Fresident special service\navailable on every flight. No extra\nfare on either service.\nFor full information, call your Travel\nAgent or any of Pan Am's 61 con-\nveniently located U.S. and Canadian\nofaces. other direct services are also\navailable from the Midwest and West\nCoast.\n*Trade-Marks, Reg. U.S. Pat. Of.\nPan Am Jet Clippers... world's fastest airliners... the only economy-class Jet service.…..\nthe only Jets to all three capitals: London, Paris and Rome.\nPAN AMERICAN\nHOLIDAY / APRIL"
    ],
    "millsfield:images_texts_ids": [
      1763388453
    ],
    "millsfield:primary_image": 1763388453,
    "sfomuseum:accession_number": "2001.038.164.139",
    "sfomuseum:airline": "Pan American World Airways",
    "sfomuseum:category": "Promotional, Archive",
    "sfomuseum:collection": "Aviation Archive",
    "sfomuseum:creditline": "Gift of Barnaby Conrad III",
    "sfomuseum:date": "c. 1968",
    "sfomuseum:date_acquired": "2003-05-16",
    "sfomuseum:daterange_end": "1973-12-31",
    "sfomuseum:daterange_start": "1963-01-01",
    "sfomuseum:description": "Advertisement from April [unknown year] issue of Holiday promoting Pan American World Airways, titled “You can meet in London tonight” with color illustration depicting couple dining in restaurant with nighttime view of Big Ben clock tower; separate illustration of Boeing 707 Jet Clipper aircraft across bottom.",
    "sfomuseum:dimensions": "14 x 10 1/2 inches (35.6 x 26.7 cm)",
    "sfomuseum:medium": "paper, ink",
    "sfomuseum:placetype": "object",
    "sfomuseum:publication": ": , c. 1968.",
    "sfomuseum:subcategory": "Advertisement, 2D",
    "sfomuseum:subject": "Pan Am promotional advertisement",
    "wof:depicts": [
      1159284989,
      1159289653,
      1159293593,
      1159286839
    ],
    "wof:name": "advertisement: Pan American World Airways, Holiday",
    "wof:placetype": "custom",
    "wof:placetype_alt": [
      "object"
    ]
  },
  "geometry": {"coordinates":[-122.386155,37.616357],"type":"Point"}
}
