{
  "type": "Feature",
  "properties": {
    "date:cessation_lower": "1984-01-01",
    "date:cessation_upper": "1984-12-31",
    "date:inception_lower": "1984-01-01",
    "date:inception_upper": "1984-12-31",
    "iso:country": "XX",
    "millsfield:images": [
      1527839639
    ],
    "millsfield:images_texts": [
      "EFFECTIVE JUNE 17th, 1984\nHORIZON\nAIR\nFLF THE NORTHWEST\nNEW REDMOND-BEND/\nSAN FRANCISCO SERVICE\nTIME TABLE\nFOR RESERVATIONS CALL\nYOUR TRAVEL AGENT OR\nIn Seattle 762-3646\nIn Portland 249-4480\nNationwide Toll-Free\n1-800-547-9308"
    ],
    "millsfield:images_texts_ids": [
      1527839639
    ],
    "millsfield:primary_image": 1527839639,
    "sfomuseum:accession_number": "2003.105.058.002",
    "sfomuseum:airline": "Horizon Air",
    "sfomuseum:category": "Scheduling / Ticketing",
    "sfomuseum:collection": "Aviation Archive",
    "sfomuseum:creditline": "Gift of Craig Lynes",
    "sfomuseum:date": "1984",
    "sfomuseum:date_acquired": "2003-12-29",
    "sfomuseum:daterange_end": "1984-12-31",
    "sfomuseum:daterange_start": "1984-01-01",
    "sfomuseum:description": "Timetable issued by Horizon Air, effective June 17, 1984; 29-page schedule; blue and brown cover with color illustration of parked aircraft with text announcing new service Redmond-Bend / San Francisco.",
    "sfomuseum:dimensions": "9 x 4 inches (22.9 x 10.2 cm)",
    "sfomuseum:media_ids": [
      1527839639
    ],
    "sfomuseum:medium": "paper, ink",
    "sfomuseum:placetype": "object",
    "sfomuseum:publication": ": , 1984.",
    "sfomuseum:subcategory": "Timetable",
    "wof:depicts": [
      1159284505,
      1159287275
    ],
    "wof:name": "timetable: Horizon Air",
    "wof:placetype": "custom",
    "wof:placetype_alt": [
      "object"
    ]
  },
  "geometry": {"coordinates":[-122.386155,37.616357],"type":"Point"}
}
