{
  "type": "Feature",
  "properties": {
    "date:cessation_lower": "1990-01-01",
    "date:cessation_upper": "1990-12-31",
    "date:inception_lower": "1990-01-01",
    "date:inception_upper": "1990-12-31",
    "iso:country": "XX",
    "millsfield:images": [
      1527839887,
      1527848429
    ],
    "millsfield:images_texts": [
      "Interisland\nTimetable\nNO. 252 / Effective September 5, 1990\nHAWALAN\nAIRLINES",
      "9583888333888\nTo Hilo\nTo Honolulu\nSENBERRES\n3332038823888023:\n99900000888616-\n85380800588881008 9582 еев е\n2357\nTo Kahului.\nTo Kapalua-West Maui\n30000000000\nKaua\n300\nMaui\n2357\n*DISCONTINUED OCTOBER 27. 1990\n• DASHTRANSIT"
    ],
    "millsfield:images_texts_ids": [
      1527839887,
      1527848429
    ],
    "millsfield:primary_image": 1527839887,
    "sfomuseum:accession_number": "2008.108.368",
    "sfomuseum:airline": "Hawaiian Airlines",
    "sfomuseum:category": "Scheduling / Ticketing",
    "sfomuseum:collection": "Aviation Archive",
    "sfomuseum:creditline": "Gift of the William Hough Collection",
    "sfomuseum:date": "1990",
    "sfomuseum:date_acquired": "2008-11-10",
    "sfomuseum:daterange_end": "1990-12-31",
    "sfomuseum:daterange_start": "1990-01-01",
    "sfomuseum:description": "Interisland timetable issued by Hawaiian Airlines, effective September 5, 1990; four page double-sided fold-out; white cover with color photographic image of men in an outrigger canoe with island background.",
    "sfomuseum:dimensions": "9 x 4 inches (22.9 x 10.2 cm)",
    "sfomuseum:media_ids": [
      1527848429,
      1527839887
    ],
    "sfomuseum:medium": "paper, ink",
    "sfomuseum:placetype": "object",
    "sfomuseum:publication": ": , 1990.",
    "sfomuseum:subcategory": "Timetable",
    "sfomuseum:subject": "Airlines -- Commercial -- Hawaiian",
    "wof:depicts": [
      1159287913,
      1159284489
    ],
    "wof:name": "timetable: Hawaiian Airlines, interisland service",
    "wof:placetype": "custom",
    "wof:placetype_alt": [
      "object"
    ]
  },
  "geometry": {"coordinates":[-122.386155,37.616357],"type":"Point"}
}
