{
  "type": "Feature",
  "properties": {
    "date:cessation_lower": "1980-12-31",
    "date:cessation_upper": "1980-12-31",
    "date:inception_lower": "1970-01-01",
    "date:inception_upper": "1970-01-01",
    "iso:country": "XX",
    "millsfield:images": [
      1527845161,
      1527845163
    ],
    "sfomuseum:accession_number": "2001.080.096 a b ",
    "sfomuseum:airline": "Olympic Airlines",
    "sfomuseum:category": "Passenger Amenity",
    "sfomuseum:collection": "Aviation Archive",
    "sfomuseum:continent": "World Routes",
    "sfomuseum:creditline": "Gift of Thomas G. Dragges",
    "sfomuseum:date": "c. 1975",
    "sfomuseum:daterange_end": "1980-12-31",
    "sfomuseum:daterange_start": "1970-01-01",
    "sfomuseum:description": "Menu issued by Olympic Airways, Zurich - Athens route; white cover with color illustration of Greek pitcher; menu items include filets mignons sautes chasseur; no menu number; class: Tourist;  undated.\ra. cover\rb. insert with text",
    "sfomuseum:media_ids": [
      1527845161,
      1527845163
    ],
    "sfomuseum:medium": "paper, ink",
    "sfomuseum:placetype": "object",
    "sfomuseum:subcategory": "Menu",
    "wof:depicts": [
      1159284925
    ],
    "wof:name": "menu: Olympic Airways, Tourist Class",
    "wof:placetype": "venue"
  },
  "geometry": {"coordinates":[-122.386155,37.616357],"type":"Point"}
}
