{
  "type": "Feature",
  "properties": {
    "date:cessation_lower": "1935-04-16",
    "date:cessation_upper": "1935-04-16",
    "date:inception_lower": "1935-04-16",
    "date:inception_upper": "1935-04-16",
    "iso:country": "XX",
    "millsfield:images": [
      1527832469,
      1527832471
    ],
    "millsfield:primary_image": 1527832469,
    "sfomuseum:accession_number": "2012.149.1754",
    "sfomuseum:aircraft": "Sikorsky (USA) S-42",
    "sfomuseum:airline": "Pan American Airways",
    "sfomuseum:category": "Philately",
    "sfomuseum:collection": "Aviation Archive",
    "sfomuseum:creditline": "Gift of the Captain John B. Russell Family",
    "sfomuseum:date": "04/16/1935",
    "sfomuseum:date_acquired": "2013-05-31",
    "sfomuseum:daterange_end": "1935-04-16",
    "sfomuseum:daterange_start": "1935-04-16",
    "sfomuseum:description": "Airmail flight cover, Pan American Airways, first Pacific survey flight, California - Hawaii route; purple cachet at lower left depicting Clipper aircraft in flight with text, “Pan American Clipper / First Flight / California - Hawaii”; courtesy “Via Air Mail” stamp at top; postmarked April 16, 1935 in San Francisco and April 17, 1935 in Honolulu with football-shaped killer cancellations over eight postage stamps; backstamp: April 16, 1935, Alameda.",
    "sfomuseum:dimensions": "4 x 9 1/2 inches (10.2 x 24.1 cm)",
    "sfomuseum:media_ids": [
      1527832469,
      1527832471
    ],
    "sfomuseum:medium": "paper, ink",
    "sfomuseum:placetype": "object",
    "sfomuseum:publication": ": , 04/16/1935.",
    "sfomuseum:subcategory": "Airmail Flight Cover",
    "wof:depicts": [
      1159284991,
      1159291669
    ],
    "wof:name": "airmail flight cover: Pan American Airways, first Pacific survey flight, California - Hawaii route",
    "wof:placetype": "venue"
  },
  "geometry": {"coordinates":[-122.386155,37.616357],"type":"Point"}
}
