{
  "type": "Feature",
  "properties": {
    "date:cessation_lower": "1915-01-01",
    "date:cessation_upper": "1915-12-31",
    "date:inception_lower": "1915-01-01",
    "date:inception_upper": "1915-12-31",
    "iso:country": "XX",
    "sfomuseum:accession_number": "2000.160.0943",
    "sfomuseum:author": "Pulitzer, Ralph",
    "sfomuseum:callnumber": "D544 .P85 1915 c.2 SC",
    "sfomuseum:category": "Book",
    "sfomuseum:collection": "Aviation Library",
    "sfomuseum:creditline": "The Tony Bill Aviation Library Collection",
    "sfomuseum:date": "c. 1915",
    "sfomuseum:date_acquired": "1999-05-18",
    "sfomuseum:daterange_end": "1920-12-31",
    "sfomuseum:daterange_start": "1910-01-01",
    "sfomuseum:description": "6 p. l., 158, [1] p. front., plates. 19 cm.",
    "sfomuseum:description_library": "6 p. l., 158, [1] p. front., plates. 19 cm.",
    "sfomuseum:medium": "paper, ink",
    "sfomuseum:placetype": "object",
    "sfomuseum:publication": "New York: A. L. Burt co., c. 1915.",
    "sfomuseum:publisher": "A. L. Burt co.",
    "sfomuseum:publisher_location": "New York",
    "sfomuseum:subcategory": "Book",
    "sfomuseum:subject": "World War, 1914-1918 Campaigns France.",
    "wof:name": "Over the front in an aeroplane, and scenes inside the French and Flemish trenches",
    "wof:placetype": "custom",
    "wof:placetype_alt": "object"
  },
  "geometry": {"coordinates":[-122.386155,37.616357],"type":"Point"}
}
