{
  "type": "Feature",
  "properties": {
    "date:cessation_lower": "1983-12-31",
    "date:cessation_upper": "1983-12-31",
    "date:inception_lower": "1983-01-01",
    "date:inception_upper": "1983-01-01",
    "iso:country": "XX",
    "millsfield:images": [
      1527852885
    ],
    "sfomuseum:accession_number": "2011.001.045.058",
    "sfomuseum:airline": "Union de Transports Aériens (UTA)",
    "sfomuseum:category": "Promotional",
    "sfomuseum:collection": "Aviation Archive",
    "sfomuseum:creditline": "Gift of Robert Behr",
    "sfomuseum:date": "1983",
    "sfomuseum:daterange_end": "1983-12-31",
    "sfomuseum:daterange_start": "1983-01-01",
    "sfomuseum:description": "Half-page advertisement from November 1983 issue of Travel \u0026 Leisure magazine promoting UTA (Union de Transports Aeriens), with main caption, “Seven days that will live with you forever. / Tahiti via UTA”, and color image depicting rowing scene.",
    "sfomuseum:media_ids": [
      1527852885
    ],
    "sfomuseum:medium": "paper, ink",
    "sfomuseum:placetype": "object",
    "sfomuseum:subcategory": "Advertisement, 2D",
    "wof:depicts": [
      1159285411
    ],
    "wof:name": "advertisement: UTA (Union de Transports Aériens), Travel \u0026 Leisure",
    "wof:placetype": "venue"
  },
  "geometry": {"coordinates":[-122.386155,37.616357],"type":"Point"}
}
