{
  "type": "Feature",
  "properties": {
    "date:cessation_lower": "1950-12-31",
    "date:cessation_upper": "1950-12-31",
    "date:inception_lower": "1940-01-01",
    "date:inception_upper": "1940-01-01",
    "iso:country": "XX",
    "millsfield:images": [
      1527819409
    ],
    "sfomuseum:accession_number": "2001.038.116",
    "sfomuseum:airline": "Panagra (Pan American-Grace Airways)",
    "sfomuseum:category": "Promotional",
    "sfomuseum:collection": "Aviation Archive",
    "sfomuseum:continent": "World Routes",
    "sfomuseum:creditline": "Gift of Barnaby Conrad III",
    "sfomuseum:date": "c. 1945",
    "sfomuseum:daterange_end": "1950-12-31",
    "sfomuseum:daterange_start": "1940-01-01",
    "sfomuseum:description": "Advertisement promoting Panagra (Pan American-Grace Airways), green background with stylized route map of South America and partial map of North America; cropped image of engine with rotating propeller across top edge, followed by printed caption, \"See South America by Air!\"",
    "sfomuseum:dimensions": "10 x 6 3/4 inches (25.4 x 17.1 cm)",
    "sfomuseum:media_ids": [
      1527819409
    ],
    "sfomuseum:medium": "paper, ink",
    "sfomuseum:placetype": "object",
    "sfomuseum:subcategory": "Advertisement, 2D",
    "wof:depicts": [
      1159284993
    ],
    "wof:name": "advertisement: Panagra (Pan American-Grace Airways)",
    "wof:placetype": "venue"
  },
  "geometry": {"coordinates":[-122.386155,37.616357],"type":"Point"}
}
