{
  "type": "Feature",
  "properties": {
    "date:cessation_lower": "1945-01-01",
    "date:cessation_upper": "1945-12-31",
    "date:inception_lower": "1945-01-01",
    "date:inception_upper": "1945-12-31",
    "iso:country": "XX",
    "millsfield:images": [
      1527819409
    ],
    "millsfield:primary_image": 1527819409,
    "sfomuseum:accession_number": "2001.038.116",
    "sfomuseum:airline": "Panagra (Pan American-Grace Airways)",
    "sfomuseum:category": "Promotional, Archive",
    "sfomuseum:collection": "Aviation Archive",
    "sfomuseum:continent": "World Routes",
    "sfomuseum:creditline": "Gift of Barnaby Conrad III",
    "sfomuseum:date": "c. 1945",
    "sfomuseum:date_acquired": "2003-05-16",
    "sfomuseum:daterange_end": "1950-12-31",
    "sfomuseum:daterange_start": "1940-01-01",
    "sfomuseum:description": "Advertisement in magazine promoting Panagra (Pan American-Grace Airways), titled \"See South America by Air!\"; green background with stylized route map of South America and partial map of North America; cropped image of engine with rotating propeller across top edge.",
    "sfomuseum:dimensions": "10 x 6 3/4 inches (25.4 x 17.1 cm)",
    "sfomuseum:media_ids": [
      1527819409
    ],
    "sfomuseum:medium": "paper, ink",
    "sfomuseum:placetype": "object",
    "sfomuseum:publication": ": , c. 1945.",
    "sfomuseum:subcategory": "Advertisement, 2D",
    "wof:depicts": [
      1159284993,
      1159288567
    ],
    "wof:name": "advertisement: Panagra (Pan American-Grace Airways)",
    "wof:placetype": "custom",
    "wof:placetype_alt": "object"
  },
  "geometry": {"coordinates":[-122.386155,37.616357],"type":"Point"}
}
