{
  "type": "Feature",
  "properties": {
    "date:cessation_lower": "1997-01-01",
    "date:cessation_upper": "1997-12-31",
    "date:inception_lower": "1997-01-01",
    "date:inception_upper": "1997-12-31",
    "isbn:number": "1575100274, 9781575100272",
    "iso:country": "XX",
    "sfomuseum:accession_number": "2003.084.001",
    "sfomuseum:airline": "Pan American World Airways",
    "sfomuseum:author": "Krupnick, Jon E.",
    "sfomuseum:callnumber": "HE9803.P36 K78 1997 c.2",
    "sfomuseum:category": "Book",
    "sfomuseum:collection": "Aviation Library",
    "sfomuseum:creditline": "Gift of Lawrence A. Smookler, M.D.",
    "sfomuseum:date": "c. 1997",
    "sfomuseum:daterange_end": "2002-12-31",
    "sfomuseum:daterange_start": "1992-01-01",
    "sfomuseum:description": "v, 315 p. :  ill. (some col.) ; 31 cm.",
    "sfomuseum:description_library": "v, 315 p. :  ill. (some col.) ; 31 cm.",
    "sfomuseum:medium": "paper, ink",
    "sfomuseum:placetype": "object",
    "sfomuseum:publication": "Missoula, MT: Pictorial Histories Pub., c. 1997.",
    "sfomuseum:publisher": "Pictorial Histories Pub.",
    "sfomuseum:publisher_location": "Missoula, MT",
    "sfomuseum:subcategory": "Book",
    "sfomuseum:subject": "Pan American World Airways, inc. History.Postmarks Collectors and collecting United States.Covers (Philately)",
    "wof:depicts": [
      1159284989,
      1159286839
    ],
    "wof:name": "Pan American's pacific pioneers: a pictorial history of Pan Am's Pacific First Flights 1935-1946: Pan American Clippers unite the Pacific Rim",
    "wof:placetype": "custom",
    "wof:placetype_alt": "object"
  },
  "geometry": {"coordinates":[-122.386155,37.616357],"type":"Point"}
}
