{
  "type": "Feature",
  "properties": {
    "date:cessation_lower": "1979-01-01",
    "date:cessation_upper": "1979-12-31",
    "date:inception_lower": "1979-01-01",
    "date:inception_upper": "1979-12-31",
    "isbn:number": "1563110296 (v. 3), 9781563110290 (v. 3),1563113503 (v. 4), 9781563113505 (v. 4)",
    "iso:country": "XX",
    "sfomuseum:accession_number": "2009.064.010",
    "sfomuseum:author": "Brewer, James F., ed.; Harry G. Howton, ed.; and Janet M. Thies, ed.",
    "sfomuseum:callnumber": "D790 .C47 1979 v.4",
    "sfomuseum:category": "Book",
    "sfomuseum:collection": "Aviation Library",
    "sfomuseum:creditline": "Collection of SFO Museum",
    "sfomuseum:date": "1979",
    "sfomuseum:date_acquired": "2009-05-12",
    "sfomuseum:daterange_end": "1979-12-31",
    "sfomuseum:daterange_start": "1979-01-01",
    "sfomuseum:description": "4 v. : ill. (some col.) ; 32 cm.",
    "sfomuseum:description_library": "4 v. : ill. (some col.) ; 32 cm.",
    "sfomuseum:medium": "paper, ink",
    "sfomuseum:placetype": "object",
    "sfomuseum:publication": "Poplar Bluff, MO: Hump Pilots Association, 1979.",
    "sfomuseum:publisher": "Hump Pilots Association",
    "sfomuseum:publisher_location": "Poplar Bluff, MO",
    "sfomuseum:subcategory": "Book",
    "sfomuseum:subject": "World War, 1939-1945 Aerial operations, American.",
    "wof:name": "China airlift -- the Hump: China's aerial lifeline, the beginning of the China-Burma-India Hump Pilots Association",
    "wof:placetype": "custom",
    "wof:placetype_alt": "object"
  },
  "geometry": {"coordinates":[-122.386155,37.616357],"type":"Point"}
}
