{
  "type": "Feature",
  "properties": {
    "date:cessation_lower": "1998-01-01",
    "date:cessation_upper": "1998-12-31",
    "date:inception_lower": "1998-01-01",
    "date:inception_upper": "1998-12-31",
    "iso:country": "XX",
    "loc:subject_heading": {
      "sh85001319": "Aeronautics",
      "sh85002782": "Airplanes"
    },
    "loc:subject_headings": [
      "sh85002782",
      "sh85001319",
      "sh85001319",
      "sh85002782"
    ],
    "sfomuseum:accession_number": "2016.042.019",
    "sfomuseum:author": "Richards, Jon; and Cake, Walter J.",
    "sfomuseum:callnumber": "TL547 .R46 1998 JUV",
    "sfomuseum:category": "Book",
    "sfomuseum:collection": "Aviation Library",
    "sfomuseum:creditline": "Gift of Frank A. Norick",
    "sfomuseum:date": "1998",
    "sfomuseum:daterange_end": "1998-12-31",
    "sfomuseum:daterange_start": "1998-01-01",
    "sfomuseum:description_library": "39 pages : color illustrations ; 35 cm",
    "sfomuseum:medium": "paper, ink",
    "sfomuseum:placetype": "object",
    "sfomuseum:publication": "Brookfield, CT: Coper Beech Books, 1998.",
    "sfomuseum:publisher": "Coper Beech Books",
    "sfomuseum:publisher_location": "Brookfield, CT",
    "sfomuseum:subcategory": "Book",
    "sfomuseum:subject": "Aeronautics -- Juvenile literature. \rAirplanes -- Juvenile literature. \rAirplanes. \rAeronautics. \rAeronautics. \rAirplanes.",
    "wof:name": "The fantastic cutaway book of flight",
    "wof:placetype": "venue"
  },
  "geometry": {"coordinates":[-122.386155,37.616357],"type":"Point"}
}
