{
  "type": "Feature",
  "properties": {
    "date:cessation_lower": "1980-01-01",
    "date:cessation_upper": "1989-12-31",
    "date:inception_lower": "1980-01-01",
    "date:inception_upper": "1989-12-31",
    "iso:country": "XX",
    "millsfield:images": [
      1527858533
    ],
    "millsfield:primary_image": 1527858533,
    "sfomuseum:accession_number": "2002.112.005",
    "sfomuseum:airline": "Continental Airlines",
    "sfomuseum:category": "Beverage Service",
    "sfomuseum:collection": "Aviation Museum",
    "sfomuseum:creditline": "Gift of Richard R. Wallin",
    "sfomuseum:date": "1980s",
    "sfomuseum:date_acquired": "2003-07-21",
    "sfomuseum:daterange_end": "1989-12-31",
    "sfomuseum:daterange_start": "1980-01-01",
    "sfomuseum:description": "White background with red jetstream logo top, center edge of cup",
    "sfomuseum:dimensions": "2 1/4 x 4 1/4 x 3 1/4 inches (5.7 x 10.8 x 8.3 cm)",
    "sfomuseum:media_ids": [
      1527858533
    ],
    "sfomuseum:medium": "glazed ceramic",
    "sfomuseum:placetype": "object",
    "sfomuseum:publication": ": , 1980s.",
    "sfomuseum:subcategory": "Coffee cup / Teacup / Saucer",
    "wof:depicts": [
      1159284201,
      1360700741
    ],
    "wof:name": "coffee cup: Continental Airlines",
    "wof:placetype": "custom",
    "wof:placetype_alt": "object"
  },
  "geometry": {"coordinates":[-122.386155,37.616358],"type":"Point"}
}
