{
  "type": "Feature",
  "properties": {
    "date:cessation_lower": "1989-01-01",
    "date:cessation_upper": "1989-12-31",
    "date:inception_lower": "1989-01-01",
    "date:inception_upper": "1989-12-31",
    "iso:country": "XX",
    "millsfield:images": [
      1527843173
    ],
    "millsfield:primary_image": 1527843173,
    "sfomuseum:accession_number": "2003.105.108.007",
    "sfomuseum:airline": "USAir",
    "sfomuseum:category": "Scheduling / Ticketing",
    "sfomuseum:collection": "Aviation Archive",
    "sfomuseum:creditline": "Gift of Craig Lynes",
    "sfomuseum:date": "1989",
    "sfomuseum:date_acquired": "2003-12-29",
    "sfomuseum:daterange_end": "1989-12-31",
    "sfomuseum:daterange_start": "1989-01-01",
    "sfomuseum:description": "System timetable issued by USAir, effective December 1, 1989; white cover with color photographic image of beach and text promoting travel to Bahamas, Puerto Rico, Florida, California, Arizona; includes USAir Express.",
    "sfomuseum:dimensions": "9 x 4 inches (22.9 x 10.2 cm)",
    "sfomuseum:media_ids": [
      1527843173
    ],
    "sfomuseum:medium": "paper, ink",
    "sfomuseum:placetype": "object",
    "sfomuseum:publication": ": , 1989.",
    "sfomuseum:subcategory": "Timetable",
    "wof:depicts": [
      1159285447
    ],
    "wof:name": "timetable: USAir",
    "wof:placetype": "venue"
  },
  "geometry": {"coordinates":[-122.386155,37.616357],"type":"Point"}
}
