{
  "type": "Feature",
  "properties": {
    "date:cessation_lower": "1978-01-01",
    "date:cessation_upper": "1978-12-31",
    "date:inception_lower": "1978-01-01",
    "date:inception_upper": "1978-12-31",
    "iso:country": "XX",
    "sfomuseum:accession_number": "2002.033.022",
    "sfomuseum:author": "Ogden, Bob",
    "sfomuseum:callnumber": "TL506.E83 O34 1978",
    "sfomuseum:category": "Book",
    "sfomuseum:collection": "Aviation Library",
    "sfomuseum:creditline": "Gift of Bonnie Baskin",
    "sfomuseum:date": "c. 1978",
    "sfomuseum:daterange_end": "1983-12-31",
    "sfomuseum:daterange_start": "1973-01-01",
    "sfomuseum:description": "64 p. : ill. ; 19 cm.",
    "sfomuseum:description_library": "64 p. : ill. ; 19 cm.",
    "sfomuseum:edition": "European edition",
    "sfomuseum:medium": "paper, ink",
    "sfomuseum:placetype": "object",
    "sfomuseum:publication": "London: Battle of Britain Prints International, c. 1978.",
    "sfomuseum:publisher": "Battle of Britain Prints International",
    "sfomuseum:publisher_location": "London",
    "sfomuseum:subcategory": "Book",
    "sfomuseum:subject": "Aeronautical museums Europe Directories.",
    "wof:name": "Aircraft museums directory European edition",
    "wof:placetype": "custom",
    "wof:placetype_alt": "object"
  },
  "geometry": {"coordinates":[-122.386155,37.616357],"type":"Point"}
}
