{
  "type": "Feature",
  "properties": {
    "date:cessation_lower": "1948-05-15",
    "date:cessation_upper": "1948-05-15",
    "date:inception_lower": "1948-05-15",
    "date:inception_upper": "1948-05-15",
    "iso:country": "XX",
    "millsfield:images": [
      1527829993,
      1527829995
    ],
    "millsfield:images_texts": [
      "301 A ERSARY\n# MAY 15\nO NEW YORK\nPHILADELPHIA\n1948\nWASHINGTON\n-1918-\nU.S. Air Mail\nAIR MAIL\n5¢\n5¢\n1948\n11 Al\nMAIL FIEND\nMR. J. Turoustry\n65 EAST тіЙ ST.\nNEW YORKS NY.",
      "10. 1500000\nT MAY 15\n4\nPM\n1948\nNATIONAL AIRPORT\n- STA. +"
    ],
    "millsfield:images_texts_ids": [
      1527829993,
      1527829995
    ],
    "millsfield:primary_image": 1527829993,
    "sfomuseum:accession_number": "2000.054.011",
    "sfomuseum:category": "Philately",
    "sfomuseum:collection": "Aviation Archive",
    "sfomuseum:continent": "World Routes",
    "sfomuseum:creditline": "Gift of John Zukowsky",
    "sfomuseum:date": "05/15/1948",
    "sfomuseum:date_acquired": "2000-12-14",
    "sfomuseum:daterange_end": "1948-05-15",
    "sfomuseum:daterange_start": "1948-05-15",
    "sfomuseum:description": "Airmail flight cover commemorating the 30th anniversary of United States Air Mail; red cachet with image of two aircraft superimposed over route map; postmark: May 15, 1948, New York with four-line cancellation mark over 5-cent postal indicia; backstamp: May 15, 1948, Washington, DC; envelope: white envelope with red and blue rhomboids around border.",
    "sfomuseum:dimensions": "4 x 6 1/2 inches (10.2 x 16.5 cm)",
    "sfomuseum:media_ids": [
      1527829993,
      1527829995
    ],
    "sfomuseum:medium": "paper, ink",
    "sfomuseum:placetype": "object",
    "sfomuseum:publication": ": , 05/15/1948.",
    "sfomuseum:subcategory": "Airmail Flight Cover",
    "wof:name": "airmail flight cover: United States Air Mail, 30th Anniversary",
    "wof:placetype": "custom",
    "wof:placetype_alt": [
      "object"
    ]
  },
  "geometry": {"coordinates":[-122.386155,37.616357],"type":"Point"}
}
