{
  "type": "Feature",
  "properties": {
    "date:cessation_lower": "1950-01-01",
    "date:cessation_upper": "1950-12-31",
    "date:inception_lower": "1950-01-01",
    "date:inception_upper": "1950-12-31",
    "iso:country": "XX",
    "millsfield:images": [
      1527835097
    ],
    "millsfield:primary_image": 1527835097,
    "sfomuseum:accession_number": "2012.149.1184",
    "sfomuseum:airline": "KLM (Royal Dutch Airlines)",
    "sfomuseum:category": "Promotional",
    "sfomuseum:collection": "Aviation Archive",
    "sfomuseum:creditline": "Gift of the Captain John B. Russell Family",
    "sfomuseum:date": "c. 1950",
    "sfomuseum:daterange_end": "1955-12-31",
    "sfomuseum:daterange_start": "1945-01-01",
    "sfomuseum:description": "Luggage label promoting KLM (Royal Dutch Airlines); irregular cloud shape, light blue background with white border; small illustration depicting airplane in flight followed by text, “KLM / Royal Dutch Airlines.”",
    "sfomuseum:dimensions": "1 1/2 x 2 1/4 inches (3.8 x 5.7 cm)",
    "sfomuseum:media_ids": [
      1527835097
    ],
    "sfomuseum:medium": "paper, ink",
    "sfomuseum:placetype": "object",
    "sfomuseum:publication": ": , c. 1950.",
    "sfomuseum:subcategory": "Luggage Label",
    "wof:depicts": [
      1159284613
    ],
    "wof:name": "luggage label: KLM (Royal Dutch Airlines)",
    "wof:placetype": "venue"
  },
  "geometry": {"coordinates":[-122.386155,37.616357],"type":"Point"}
}
