{
  "type": "Feature",
  "properties": {
    "date:cessation_lower": "1975-12-31",
    "date:cessation_upper": "1975-12-31",
    "date:inception_lower": "1965-01-01",
    "date:inception_upper": "1965-01-01",
    "iso:country": "XX",
    "sfomuseum:accession_number": "2006.010.545",
    "sfomuseum:category": "Promotional",
    "sfomuseum:collection": "Aviation Archive",
    "sfomuseum:creditline": "Gift of the William Hough Collection",
    "sfomuseum:date": "c. 1970",
    "sfomuseum:daterange_end": "1975-12-31",
    "sfomuseum:daterange_start": "1965-01-01",
    "sfomuseum:description": "Brochure produced by TWA (Trans World Airlines) promoting Boeing 747 fleet, titled “Everything’s new on the TWA 747”; multi-fold color brochure with cover illustration of Boeing 747 aircraft in red; contains information about aircraft and in-flight service with seat section diagram.",
    "sfomuseum:media_ids": [
      1527853405, 
      1527853407, 
      1527820727
    ],
    "sfomuseum:medium": "paper, ink",
    "sfomuseum:placetype": "object",
    "sfomuseum:subcategory": "Brochure, Airline",
    "wof:name": "brochure: TWA (Trans World Airlines), Boeing 747",
    "wof:placetype": "venue"
  },
  "geometry": {"coordinates":[-122.386155,37.616358],"type":"Point"}
}
