{
  "type": "Feature",
  "properties": {
    "date:cessation_lower": "1952-01-01",
    "date:cessation_upper": "1952-12-31",
    "date:inception_lower": "1952-01-01",
    "date:inception_upper": "1952-12-31",
    "iso:country": "XX",
    "sfomuseum:accession_number": "2007.022.001",
    "sfomuseum:airline": "Pan American World Airways",
    "sfomuseum:author": "Hambleton, George",
    "sfomuseum:callnumber": "HE9803.P36 H35 1952 SC ENV",
    "sfomuseum:category": "Book",
    "sfomuseum:collection": "Aviation Library",
    "sfomuseum:creditline": "Gift of George B. E. Hambleton",
    "sfomuseum:date": "1952",
    "sfomuseum:date_acquired": "2008-03-03",
    "sfomuseum:daterange_end": "1952-12-31",
    "sfomuseum:daterange_start": "1952-01-01",
    "sfomuseum:description": "137-page subject thesis written by George B. E. Hambleton, former director of commercial sales at Pan American World Airways, while attending Princeton University.  Mr. Hambleton is the son of John A. Hambleton, co-founder of the Aviation Corporation of America (later Aviation Corporation of the Americas) and its operating division, Pan American Airways for which he was Vice-President.",
    "sfomuseum:description_library": "137-page subject thesis written by George B. E. Hambleton, former director of commercial sales at Pan American World Airways, while attending Princeton University.  Mr. Hambleton is the son of John A. Hambleton, co-founder of the Aviation Corporation of America (later Aviation Corporation of the Americas) and its operating division, Pan American Airways for which he was Vice-President.",
    "sfomuseum:medium": "paper, ink",
    "sfomuseum:placetype": "object",
    "sfomuseum:publication": ": , 1952.",
    "sfomuseum:subcategory": "Book",
    "sfomuseum:subject": "Airlines -- Commercial -- Pan American Airways.\rThesis.",
    "wof:depicts": [
      1159284989,
      1159286839
    ],
    "wof:name": "The chosen instrument",
    "wof:placetype": "custom",
    "wof:placetype_alt": [
      "object"
    ]
  },
  "geometry": {"coordinates":[-122.386155,37.616357],"type":"Point"}
}
