{
  "type": "Feature",
  "properties": {
    "date:cessation_lower": "2007-12-31",
    "date:cessation_upper": "2007-12-31",
    "date:inception_lower": "2007-01-01",
    "date:inception_upper": "2007-01-01",
    "iso:country": "XX",
    "millsfield:images": [
      1527849781
    ],
    "sfomuseum:accession_number": "2008.055.947",
    "sfomuseum:airport": "Lyon - Saint Exupéry Airport",
    "sfomuseum:category": "Scheduling / Ticketing",
    "sfomuseum:collection": "Aviation Archive",
    "sfomuseum:creditline": "Gift of the William Hough Collection",
    "sfomuseum:date": "2007",
    "sfomuseum:daterange_end": "2007-12-31",
    "sfomuseum:daterange_start": "2007-01-01",
    "sfomuseum:description": "Timetable issued by Lyon - Saint Exupéry Airport, effective October 27, 2007. A composite full color photographic image of a large round clock on a long stem in green grass against a deep blue sky. In French and English.",
    "sfomuseum:media_ids": [
      1527849781
    ],
    "sfomuseum:medium": "paper, ink",
    "sfomuseum:placetype": "object",
    "sfomuseum:subcategory": "Timetable",
    "wof:depicts": [
      102544687
    ],
    "wof:name": "timetable: Lyon - Saint Exupéry Airport, France",
    "wof:placetype": "venue"
  },
  "geometry": {"coordinates":[-122.386155,37.616357],"type":"Point"}
}
