{
  "type": "Feature",
  "properties": {
    "date:cessation_lower": "2007-01-01",
    "date:cessation_upper": "2007-12-31",
    "date:inception_lower": "2007-01-01",
    "date:inception_upper": "2007-12-31",
    "iso:country": "XX",
    "loc:subject_heading": {
      "sh85002960": "Airports"
    },
    "millsfield:images": [
      1527849781
    ],
    "millsfield:primary_image": 1527849781,
    "sfomuseum:accession_number": "2008.055.947",
    "sfomuseum:airport": "Lyon - Saint Exupéry Airport",
    "sfomuseum:category": "Scheduling / Ticketing",
    "sfomuseum:collection": "Aviation Archive",
    "sfomuseum:creditline": "Gift of the William Hough Collection",
    "sfomuseum:date": "2007",
    "sfomuseum:daterange_end": "2007-12-31",
    "sfomuseum:daterange_start": "2007-01-01",
    "sfomuseum:description": "Timetable issued by Lyon-Saint Exupéry Airport, identified on cover as “Aeroport Lyon Saint Exupéry”, effective October 27, 2007; color photographic image of clock mast on field; includes flight schedules, ground transportation, and lodging accommodations; in French and English.",
    "sfomuseum:dimensions": "9 x 4 1/4 inches (22.9 x 10.8 cm)",
    "sfomuseum:media_ids": [
      1527849781
    ],
    "sfomuseum:medium": "paper, ink",
    "sfomuseum:placetype": "object",
    "sfomuseum:publication": ": , 2007.",
    "sfomuseum:subcategory": "Timetable",
    "sfomuseum:subject": "Airports",
    "wof:depicts": [
      102544687
    ],
    "wof:name": "timetable: Lyon - Saint Exupéry Airport, France",
    "wof:placetype": "venue"
  },
  "geometry": {"coordinates":[-122.386155,37.616357],"type":"Point"}
}
