{
  "type": "Feature",
  "properties": {
    "date:cessation_lower": "1982-01-01",
    "date:cessation_upper": "1982-12-31",
    "date:inception_lower": "1982-01-01",
    "date:inception_upper": "1982-12-31",
    "iso:country": "XX",
    "millsfield:images": [
      1527841311
    ],
    "millsfield:images_texts": [
      "Lufthansa\nFirst Class\nauf allen Lufthansa-Flügen\non all Lufthansa flights\nen todos los vuelos de Lufthansa\nFlugplan\nTimetable\nHorario\n01 Nov 82 - 26 Mar 83"
    ],
    "millsfield:images_texts_ids": [
      1527841311
    ],
    "millsfield:primary_image": 1527841311,
    "sfomuseum:accession_number": "2009.122.455",
    "sfomuseum:airline": "Lufthansa",
    "sfomuseum:category": "Scheduling / Ticketing",
    "sfomuseum:collection": "Aviation Archive",
    "sfomuseum:creditline": "Gift of the William Hough Collection",
    "sfomuseum:date": "1982",
    "sfomuseum:date_acquired": "2010-06-08",
    "sfomuseum:daterange_end": "1982-12-31",
    "sfomuseum:daterange_start": "1982-01-01",
    "sfomuseum:description": "Timetable issued by Lufthansa, effective November 1, 1982 March 26, 1983; 269-page fold-out schedule; yellow cover; promoting first class service.",
    "sfomuseum:dimensions": "8 x 4 inches (20.3 x 10.2 cm)",
    "sfomuseum:media_ids": [
      1527841311
    ],
    "sfomuseum:medium": "paper, ink",
    "sfomuseum:placetype": "object",
    "sfomuseum:publication": ": , 1982.",
    "sfomuseum:subcategory": "Timetable",
    "wof:depicts": [
      1159288215,
      1159284711
    ],
    "wof:name": "timetable: Lufthansa",
    "wof:placetype": "custom",
    "wof:placetype_alt": "object"
  },
  "geometry": {"coordinates":[-122.386155,37.616357],"type":"Point"}
}
