{
  "type": "Feature",
  "properties": {
    "date:cessation_lower": "1979-12-31",
    "date:cessation_upper": "1979-12-31",
    "date:inception_lower": "1970-01-01",
    "date:inception_upper": "1970-01-01",
    "iso:country": "XX",
    "millsfield:images": [
      1527842381,
      1527842383
    ],
    "sfomuseum:accession_number": "2006.026.032",
    "sfomuseum:airline": "China Airlines",
    "sfomuseum:category": "Passenger Amenity",
    "sfomuseum:collection": "Aviation Museum",
    "sfomuseum:creditline": "The Henry Steiner Air Sickness Bag Collection",
    "sfomuseum:date": "1970s",
    "sfomuseum:daterange_end": "1979-12-31",
    "sfomuseum:daterange_start": "1970-01-01",
    "sfomuseum:description": "White with blue and red China Airlines logo and name printed in Chinese and English; three step illustrated graphic of bag on reverse; bag opening is on bottom.",
    "sfomuseum:dimensions": "10 3/4 x 5 inches (27.3 x 12.7 cm)",
    "sfomuseum:media_ids": [
      1527842381,
      1527842383
    ],
    "sfomuseum:medium": "paper, ink",
    "sfomuseum:placetype": "object",
    "sfomuseum:subcategory": "Airsickness Bag",
    "wof:depicts": [
      1159284153
    ],
    "wof:name": "airsickness bag: China Airlines",
    "wof:placetype": "venue"
  },
  "geometry": {"coordinates":[-122.386155,37.616357],"type":"Point"}
}
