{
  "type": "Feature",
  "properties": {
    "date:cessation_lower":"1964-12-31",
    "date:cessation_upper":"1964-12-31",
    "date:inception_lower":"1964-01-01",
    "date:inception_upper":"1964-01-01",
    "iso:country":"XX",
    "sfomuseum:accession_number":"2012.149.1893",
    "sfomuseum:category":"Philately",
    "sfomuseum:collection":"Aviation Archive",
    "sfomuseum:creditline":"Gift of the Captain John B. Russell Family",
    "sfomuseum:date":"07/02/1964",
    "sfomuseum:daterange_end":"1964-07-02",
    "sfomuseum:daterange_start":"1964-07-02",
    "sfomuseum:description":"Airmail flight cover, Pan American World Airways; red cachet at left depicting profile view of aircraft and globe with text, \u201cFirst DC-8 Jet Air Mail Flight / Pan Am - Panagra / Miami - Balboa - Quito\u201d; postmarked July 2, 1964, Miami, Florida, with three postage stamps; backstamp: July 2, 1964 in Quito; addressed to Oscar H. Fatout.",
    "sfomuseum:media_ids":[
        1527833455,
        1527833459
    ],
    "sfomuseum:medium":"paper, ink",
    "sfomuseum:placetype":"object",
    "sfomuseum:subcategory":"Airmail Flight Cover",
    "wof:depicts":[
        1159290443
    ],
    "wof:name":"airmail flight cover: Pan American World Airways, Panagra, Douglas DC-8",
    "wof:placetype":"venue"
},
  "geometry": {"coordinates":[-122.386155,37.616358],"type":"Point"}
}