{
  "type": "Feature",
  "properties": {
    "date:cessation_lower": "1970-12-01",
    "date:cessation_upper": "1970-12-31",
    "date:inception_lower": "1970-09-01",
    "date:inception_upper": "1970-09-30",
    "iso:country": "XX",
    "millsfield:images": [
      1729566271,
      1729566273
    ],
    "millsfield:primary_image": 1729566271,
    "sfomuseum:accession_number": "2003.105.193",
    "sfomuseum:aircraft": "Lockheed L-1011 TriStar",
    "sfomuseum:airline": "TWA (Trans World Airlines)",
    "sfomuseum:category": "Philately",
    "sfomuseum:collection": "Aviation Archive",
    "sfomuseum:creditline": "Gift of Craig Lynes",
    "sfomuseum:date": "late 1970s",
    "sfomuseum:date_acquired": "2003-12-29",
    "sfomuseum:daterange_end": "1979-12-31",
    "sfomuseum:daterange_start": "1977-01-01",
    "sfomuseum:description": "Oversized postcard of a TWA L-1011 in flight.",
    "sfomuseum:dimensions": "5 1/2 x 7 1/2 inches (14 x 19.1 cm)",
    "sfomuseum:medium": "paper, ink",
    "sfomuseum:placetype": "object",
    "sfomuseum:publication": ": , late 1970s.",
    "sfomuseum:subcategory": "Postcard",
    "wof:depicts": [
      1159291129,
      1159285393
    ],
    "wof:name": "postcard: TWA (Trans World Airlines), Lockheed L-1011",
    "wof:placetype": "venue"
  },
  "geometry": {"coordinates":[-122.386155,37.616357],"type":"Point"}
}
