{
  "type": "Feature",
  "properties": {
    "date:cessation_lower": "1910-01-01",
    "date:cessation_upper": "1910-12-31",
    "date:inception_lower": "1910-01-01",
    "date:inception_upper": "1910-12-31",
    "iso:country": "XX",
    "millsfield:images": [
      1746681209
    ],
    "millsfield:primary_image": 1746681209,
    "sfomuseum:accession_number": "2000.160.0253",
    "sfomuseum:author": "Fonvielle, W. de (Wilfrid)",
    "sfomuseum:callnumber": "TL616 .F66 1910 SC",
    "sfomuseum:category": "Book",
    "sfomuseum:collection": "Aviation Library",
    "sfomuseum:creditline": "The Tony Bill Aviation Library Collection",
    "sfomuseum:date": "1910",
    "sfomuseum:date_acquired": "1999-05-18",
    "sfomuseum:daterange_end": "1910-12-31",
    "sfomuseum:daterange_start": "1910-01-01",
    "sfomuseum:description": "2 p. æ., 310 p., 1 æ. illus. 28 cm.",
    "sfomuseum:description_library": "2 p. æ., 310 p., 1 æ. illus. 28 cm.",
    "sfomuseum:medium": "paper, ink",
    "sfomuseum:placetype": "object",
    "sfomuseum:publication": "Paris: Hachette et cie, 1910.",
    "sfomuseum:publisher": "Hachette et cie",
    "sfomuseum:publisher_location": "Paris",
    "sfomuseum:series": "Bibliotheque des ecoles et des familles",
    "sfomuseum:subcategory": "Book",
    "sfomuseum:subject": "Aeronautics History. Balloons.",
    "wof:name": "Histoire de la navigation aerienne. Ouvrage illustre de 99 gravures",
    "wof:placetype": "custom",
    "wof:placetype_alt": "object"
  },
  "geometry": {"coordinates":[-122.386155,37.616357],"type":"Point"}
}
