{
  "type": "Feature",
  "properties": {
    "date:cessation_lower": "1980-01-01",
    "date:cessation_upper": "1989-12-31",
    "date:inception_lower": "1980-01-01",
    "date:inception_upper": "1989-12-31",
    "iso:country": "XX",
    "millsfield:images": [
      1527824471,
      1527824473
    ],
    "millsfield:primary_image": 1527824471,
    "sfomuseum:accession_number": "1998.157.141",
    "sfomuseum:airline": "KLM (Royal Dutch Airlines)",
    "sfomuseum:category": "Passenger Amenity",
    "sfomuseum:collection": "Aviation Archive",
    "sfomuseum:creditline": "Gift of The Henry Steiner Air Sickness Bag Collection",
    "sfomuseum:date": "1980s",
    "sfomuseum:date_acquired": "1999-07-13",
    "sfomuseum:daterange_end": "1989-12-31",
    "sfomuseum:daterange_start": "1980-01-01",
    "sfomuseum:description": "Airsickness bag issued by KLM (Royal Dutch Airlines); white and blue bag with illustration of kangaroo with open pouch and written instructions for use in three languages; flat bottom, no closure.",
    "sfomuseum:dimensions": "9 x 5 inches (22.9 x 12.7 cm)",
    "sfomuseum:media_ids": [
      1527824471,
      1527824473
    ],
    "sfomuseum:medium": "paper, ink",
    "sfomuseum:placetype": "object",
    "sfomuseum:publication": ": , 1980s.",
    "sfomuseum:subcategory": "Airsickness Bag",
    "wof:depicts": [
      1159284613
    ],
    "wof:name": "airsickness bag: KLM (Royal Dutch Airlines)",
    "wof:placetype": "venue"
  },
  "geometry": {"coordinates":[-122.386155,37.616357],"type":"Point"}
}
