{
  "type": "Feature",
  "properties": {
    "date:cessation_lower": "1989-12-31",
    "date:cessation_upper": "1989-12-31",
    "date:inception_lower": "1980-01-01",
    "date:inception_upper": "1980-01-01",
    "iso:country": "XX",
    "sfomuseum:accession_number": "1998.157.141",
    "sfomuseum:category": "Passenger Amenity",
    "sfomuseum:collection": "Aviation Museum",
    "sfomuseum:creditline": "Gift of The Henry Steiner Air Sickness Bag Collection",
    "sfomuseum:date": "1980s",
    "sfomuseum:daterange_end": "1989-12-31",
    "sfomuseum:daterange_start": "1980-01-01",
    "sfomuseum:description": "Flat bottom, no closure. White bag, blue print. Airline servicemark on bottom of bag. Lower portion of bag features a kangaroo named Dusty against partial blue background with text “for a clean feeling” in white. Instructions in five languages. Design on both sides.",
    "sfomuseum:media_ids": [
      1527824471, 
      1527824473
    ],
    "sfomuseum:medium": "paper",
    "sfomuseum:placetype": "object",
    "sfomuseum:subcategory": "Airsickness Bag",
    "wof:name": "airsickness bag: KLM (Royal Dutch Airlines)",
    "wof:placetype": "venue"
  },
  "geometry": {"coordinates":[-122.386155,37.616358],"type":"Point"}
}
