{
  "type": "Feature",
  "properties": {
    "date:cessation_lower": "1958-01-01",
    "date:cessation_upper": "1958-12-31",
    "date:inception_lower": "1958-01-01",
    "date:inception_upper": "1958-12-31",
    "iso:country": "XX",
    "sfomuseum:accession_number": "2001.205.018",
    "sfomuseum:author": "Vaeth, J. Gordon (Joseph Gordon)",
    "sfomuseum:callnumber": "TL659 .V23 1958",
    "sfomuseum:category": "Book",
    "sfomuseum:collection": "Aviation Library",
    "sfomuseum:creditline": "Purchase",
    "sfomuseum:date": "1958",
    "sfomuseum:daterange_end": "1958-12-31",
    "sfomuseum:daterange_start": "1958-01-01",
    "sfomuseum:description": "235 p. p., illus., 23 cm.",
    "sfomuseum:medium": "paper, ink",
    "sfomuseum:placetype": "object",
    "sfomuseum:publication": "New York: Harper, 1958.",
    "sfomuseum:publisher": "Harper",
    "sfomuseum:publisher_location": "New York",
    "sfomuseum:subcategory": "Book",
    "sfomuseum:subject": "Eckener, Hugo, 1868-1954.\rGraf Zeppelin (Airship).",
    "wof:name": "Graf Zeppelin: the adventures of an aerial globetrotter",
    "wof:placetype": "venue"
  },
  "geometry": {"coordinates":[-122.386155,37.616357],"type":"Point"}
}
