{
  "type": "Feature",
  "properties": {
    "date:cessation_lower": "1991-10-12",
    "date:cessation_upper": "1991-10-12",
    "date:inception_lower": "1991-10-12",
    "date:inception_upper": "1991-10-12",
    "iso:country": "JP",
    "millsfield:images": [
      1527853983,
      1527853985
    ],
    "millsfield:primary_image": 1527853983,
    "sfomuseum:accession_number": "1997.46.14",
    "sfomuseum:aircraft": "Boeing 747F",
    "sfomuseum:airline": "Nippon Cargo Airlines",
    "sfomuseum:category": "Philately",
    "sfomuseum:collection": "Aviation Archive",
    "sfomuseum:continent": "World Routes",
    "sfomuseum:country": "Japan",
    "sfomuseum:creditline": "Gift of Nippon Cargo Airlines",
    "sfomuseum:date": "10/12/1991",
    "sfomuseum:daterange_end": "1991-10-12",
    "sfomuseum:daterange_start": "1991-10-12",
    "sfomuseum:description": "Airmail flight cover commemorating the first Nippon Cargo Airlines flight from Nagoya to Amsterdam; red cachet with image of building and fish; two stamps: 30-yen and 62-yen (Japan); postmark: October 12, 1991, Nagoya, Japan; backstamp: October 13, 1991, Amsterdam; white envelope with preprinted color photographic image of tulip field.",
    "sfomuseum:dimensions": "3 1/2 x 6 1/4 inches (8.9 x 15.9 cm)",
    "sfomuseum:media_ids": [
      1527853983,
      1527853985
    ],
    "sfomuseum:medium": "paper, ink",
    "sfomuseum:placetype": "object",
    "sfomuseum:publication": ": , 10/12/1991.",
    "sfomuseum:subcategory": "Airmail Flight Cover",
    "wof:depicts": [
      1159284873,
      1159289927,
      1159287387
    ],
    "wof:name": "airmail flight cover: Nippon Cargo Airlines, inaugurating flight, Nagoya - Amsterdam route",
    "wof:placetype": "custom",
    "wof:placetype_alt": "object"
  },
  "geometry": {"coordinates":[-122.386155,37.616357],"type":"Point"}
}
