{
  "type": "Feature",
  "properties": {
    "date:cessation_lower": "1991-12-31",
    "date:cessation_upper": "1991-12-31",
    "date:inception_lower": "1991-01-01",
    "date:inception_upper": "1991-01-01",
    "iso:country": "JP",
    "sfomuseum:accession_number": "1997.46.14",
    "sfomuseum:category": "Philately",
    "sfomuseum:collection": "Aviation Archive",
    "sfomuseum:continent": "World Routes",
    "sfomuseum:country": "Japan",
    "sfomuseum:creditline": "Gift of Nippon Cargo Airlines",
    "sfomuseum:date": "10/12/1991",
    "sfomuseum:daterange_end": "1991-10-12",
    "sfomuseum:daterange_start": "1991-10-12",
    "sfomuseum:description": "Airmail flight cover commemorating the first Nippon Cargo Airlines flight from Nagoya to Amsterdam; red cachet with image of building and fish; two stamps: 30-yen and 62-yen (Japan); postmark: October 12, 1991, Nagoya, Japan; backstamp: October 13, 1991, Amsterdam; white envelope with preprinted color photographic image of tulip field.",
    "sfomuseum:media_ids": [
      1527853983, 
      1527853985
    ],
    "sfomuseum:medium": "printed paper, stamps",
    "sfomuseum:placetype": "object",
    "sfomuseum:subcategory": "Airmail Flight Cover",
    "wof:name": "airmail flight cover: Nippon Cargo Airlines, inaugurating flight, Nagoya - Amsterdam route",
    "wof:placetype": "venue"
  },
  "geometry": {"coordinates":[-122.386155,37.616358],"type":"Point"}
}
