{
  "type": "Feature",
  "properties": {
    "date:cessation_lower": "1983-12-31",
    "date:cessation_upper": "1983-12-31",
    "date:inception_lower": "1983-01-01",
    "date:inception_upper": "1983-01-01",
    "iso:country": "US",
    "millsfield:images": [
      1527839495
    ],
    "sfomuseum:accession_number": "1999.047.491\r\r",
    "sfomuseum:airline": "United Airlines",
    "sfomuseum:category": "Scheduling / Ticketing",
    "sfomuseum:collection": "Aviation Archive",
    "sfomuseum:continent": "North America",
    "sfomuseum:country": "United States",
    "sfomuseum:creditline": "Gift of United Airlines Archives",
    "sfomuseum:date": "1983",
    "sfomuseum:daterange_end": "1983-12-31",
    "sfomuseum:daterange_start": "1983-01-01",
    "sfomuseum:description": "Quick reference timetable issued by United Airlines for service to and from Chicago, effective April 24, 1983; on cover: color illustration of airplane in flight.",
    "sfomuseum:media_ids": [
      1527839495
    ],
    "sfomuseum:medium": "paper, ink",
    "sfomuseum:placetype": "object",
    "sfomuseum:subcategory": "Timetable",
    "wof:depicts": [
      1159285413
    ],
    "wof:name": "timetable: United Airlines, quick reference Chicago",
    "wof:placetype": "custom"
  },
  "geometry": {"coordinates":[-122.386155,37.616357],"type":"Point"}
}
