{
  "type": "Feature",
  "properties": {
    "date:cessation_lower": "1986-01-01",
    "date:cessation_upper": "1986-12-31",
    "date:inception_lower": "1986-01-01",
    "date:inception_upper": "1986-12-31",
    "iso:country": "XX",
    "millsfield:images": [
      1527832373
    ],
    "millsfield:primary_image": 1527832373,
    "sfomuseum:accession_number": "2003.105.009.003",
    "sfomuseum:airline": "Aer Lingus",
    "sfomuseum:category": "Scheduling / Ticketing",
    "sfomuseum:collection": "Aviation Archive",
    "sfomuseum:creditline": "Gift of Craig Lynes",
    "sfomuseum:date": "1986",
    "sfomuseum:date_acquired": "2003-12-22",
    "sfomuseum:daterange_end": "1986-12-31",
    "sfomuseum:daterange_start": "1986-01-01",
    "sfomuseum:description": "Timetable issued by Aer Lingus, effective March 30 through October 25, 1986, summer service; 41-page schedule; white and gold cover with a fifty year anniversary announcement on the gold field; in English and some Gaelic.",
    "sfomuseum:dimensions": "8 x 4 inches (20.3 x 10.2 cm)",
    "sfomuseum:media_ids": [
      1527832373
    ],
    "sfomuseum:medium": "paper, ink",
    "sfomuseum:placetype": "object",
    "sfomuseum:publication": ": , 1986.",
    "sfomuseum:subcategory": "Timetable",
    "sfomuseum:subject": "Airlines -- Commercial -- Aer Lingus.",
    "wof:depicts": [
      1159283495,
      1159288269
    ],
    "wof:name": "timetable: Aer Lingus, summer schedule",
    "wof:placetype": "custom",
    "wof:placetype_alt": "object"
  },
  "geometry": {"coordinates":[-122.386155,37.616357],"type":"Point"}
}
