{
  "type": "Feature",
  "properties": {
    "date:cessation_lower": "1980-01-01",
    "date:cessation_upper": "1989-12-31",
    "date:inception_lower": "1980-01-01",
    "date:inception_upper": "1989-12-31",
    "iso:country": "XX",
    "millsfield:images": [
      1527848635
    ],
    "millsfield:primary_image": 1527848635,
    "sfomuseum:accession_number": "2006.010.773",
    "sfomuseum:airline": "World Airways",
    "sfomuseum:category": "Promotional",
    "sfomuseum:collection": "Aviation Archive",
    "sfomuseum:creditline": "Gift of the William Hough Collection",
    "sfomuseum:date": "1980s",
    "sfomuseum:date_acquired": "2010-08-04",
    "sfomuseum:daterange_end": "1980-12-31",
    "sfomuseum:daterange_start": "1980-01-01",
    "sfomuseum:description": "Promotional brochure issued by World Airways; fold-out format; white, gray, and orange cover with text “General information”; travel agency stamp visible on cover; contains route maps and area maps of Oakland, Newark, Baltimore, Los Angeles, and Honolulu.",
    "sfomuseum:dimensions": "9 x 4 inches (22.9 x 10.2 cm)",
    "sfomuseum:media_ids": [
      1527848635
    ],
    "sfomuseum:medium": "paper, ink",
    "sfomuseum:placetype": "object",
    "sfomuseum:publication": ": , 1980s.",
    "sfomuseum:subcategory": "Brochure, Airline",
    "sfomuseum:subject": "Airlines -- Commercial -- World Airways",
    "wof:depicts": [
      85921881,
      85688637,
      85633793,
      1159285551,
      1159288471
    ],
    "wof:name": "brochure: World Airways, general service",
    "wof:placetype": "custom",
    "wof:placetype_alt": "object"
  },
  "geometry": {"coordinates":[-122.386155,37.616357],"type":"Point"}
}
