{
  "type": "Feature",
  "properties": {
    "date:cessation_lower": "1961-12-31",
    "date:cessation_upper": "1961-12-31",
    "date:inception_lower": "1961-01-01",
    "date:inception_upper": "1961-01-01",
    "iso:country": "XX",
    "millsfield:images": [
      1527822883
    ],
    "sfomuseum:accession_number": "2011.032.0691",
    "sfomuseum:airport": "San Francisco International Airport",
    "sfomuseum:category": "Photograph",
    "sfomuseum:collection": "Aviation Archive",
    "sfomuseum:creditline": "Transfer",
    "sfomuseum:date": "1961",
    "sfomuseum:daterange_end": "1961-12-31",
    "sfomuseum:daterange_start": "1961-01-01",
    "sfomuseum:description": "From attached handwritten note: “03813 / 9-5-61 / Aerial of constr. S. Term”. Black and white photographic negative depicting oblique aerial view over bare construction site of future South Terminal (now Terminal 1 / T1) with terminals, planes, and fields, San Francisco International Airport (SFO), September 5, 1961.",
    "sfomuseum:dimensions": "4 x 5 inches (10.2 x 12.7 cm)",
    "sfomuseum:media_ids": [
      1527822883
    ],
    "sfomuseum:medium": "negative",
    "sfomuseum:placetype": "object",
    "sfomuseum:subcategory": "Negative",
    "wof:depicts": [
      102527513
    ],
    "wof:name": "negative: San Francisco International Airport (SFO), aerial, South Terminal construction",
    "wof:placetype": "venue"
  },
  "geometry": {"coordinates":[-122.386155,37.616357],"type":"Point"}
}
