{
  "type": "Feature",
  "properties": {
    "date:cessation_lower": "2003-01-01",
    "date:cessation_upper": "2003-12-31",
    "date:inception_lower": "2003-01-01",
    "date:inception_upper": "2003-12-31",
    "isbn:number": "1932302034, 9781932302035",
    "iso:country": "XX",
    "sfomuseum:accession_number": "2006.023.105",
    "sfomuseum:author": "Yenne, Bill",
    "sfomuseum:callnumber": "TL684 .Y46 2003",
    "sfomuseum:category": "Book",
    "sfomuseum:collection": "Aviation Library",
    "sfomuseum:creditline": "Gift of the collection of Frank J. Lichtanski",
    "sfomuseum:date": "2003",
    "sfomuseum:date_acquired": "2006-08-03",
    "sfomuseum:daterange_end": "2003-12-31",
    "sfomuseum:daterange_start": "2003-01-01",
    "sfomuseum:description": "176 p. : ill. (some col.) ; 31 cm.",
    "sfomuseum:description_library": "176 p. : ill. (some col.) ; 31 cm.",
    "sfomuseum:medium": "paper, ink",
    "sfomuseum:placetype": "object",
    "sfomuseum:publication": "New York: BCL Press, 2003.",
    "sfomuseum:publisher": "BCL Press",
    "sfomuseum:publisher_location": "New York",
    "sfomuseum:subcategory": "Book",
    "sfomuseum:subject": "Seaplanes History.",
    "wof:name": "Seaplanes \u0026 flying boats: a timeless collection from aviation's golden age",
    "wof:placetype": "custom",
    "wof:placetype_alt": [
      "object"
    ]
  },
  "geometry": {"coordinates":[-122.386155,37.616357],"type":"Point"}
}
