{
  "type": "Feature",
  "properties": {
    "date:cessation_lower":"1985-12-31",
    "date:cessation_upper":"1985-12-31",
    "date:inception_lower":"1985-01-01",
    "date:inception_upper":"1985-01-01",
    "iso:country":"XX",
    "sfomuseum:accession_number":"2000.058.1472",
    "sfomuseum:category":"Philately",
    "sfomuseum:collection":"Aviation Archive",
    "sfomuseum:creditline":"Gift of the Pan Am Association",
    "sfomuseum:date":"04/21/1985",
    "sfomuseum:daterange_end":"1985-04-21",
    "sfomuseum:daterange_start":"1985-04-21",
    "sfomuseum:description":"Airmail flight cover issued by Pan American World Airways honoring 50th anniversary of China Clipper transpacific service; white envelope with route map as footer; circular black cachet with image of Martin M-130 and commemorative text; postmarked April 21, 1986 in Rogers, AR over 39-cent postal meter stamp; no backstamp.",
    "sfomuseum:medium":"paper, ink, adhesive",
    "sfomuseum:placetype":"object",
    "sfomuseum:subcategory":"Airmail Flight Cover",
    "wof:name":"airmail flight cover: Pan American World Airways, 50th anniversary of China Clipper",
    "wof:placetype":"venue"
},
  "geometry": {"coordinates":[-122.386155,37.616358],"type":"Point"}
}