{
  "type": "Feature",
  "properties": {
    "date:cessation_lower": "1985-04-21",
    "date:cessation_upper": "1985-04-21",
    "date:inception_lower": "1985-04-21",
    "date:inception_upper": "1985-04-21",
    "iso:country": "XX",
    "millsfield:images": [
      1527853549
    ],
    "millsfield:primary_image": 1527853549,
    "sfomuseum:accession_number": "2000.058.1472",
    "sfomuseum:aircraft": "Martin M-130",
    "sfomuseum:airline": "Pan American World Airways",
    "sfomuseum:category": "Philately",
    "sfomuseum:collection": "Aviation Archive",
    "sfomuseum:creditline": "Gift of the Pan Am Association",
    "sfomuseum:date": "04/21/1985",
    "sfomuseum:date_acquired": "2000-12-14",
    "sfomuseum:daterange_end": "1985-04-21",
    "sfomuseum:daterange_start": "1985-04-21",
    "sfomuseum:description": "Airmail flight cover issued by Pan American World Airways honoring 50th anniversary of China Clipper transpacific service; white envelope with route map as footer; circular black cachet with image of Martin M-130 and commemorative text; postmarked April 21, 1986 in Rogers, AR over 39-cent postal meter stamp; no backstamp.",
    "sfomuseum:dimensions": "4 1/4 x 9 1/2 inches (10.8 x 24.1 cm)",
    "sfomuseum:media_ids": [
      1527853549
    ],
    "sfomuseum:medium": "paper, ink, adhesive",
    "sfomuseum:placetype": "object",
    "sfomuseum:publication": ": , 04/21/1985.",
    "sfomuseum:subcategory": "Airmail Flight Cover",
    "wof:depicts": [
      1159291191,
      1159284989,
      1159286839
    ],
    "wof:name": "airmail flight cover: Pan American World Airways, 50th anniversary of China Clipper",
    "wof:placetype": "custom",
    "wof:placetype_alt": "object"
  },
  "geometry": {"coordinates":[-122.386155,37.616357],"type":"Point"}
}
