{
  "type": "Feature",
  "properties": {
    "date:cessation_lower": "1947-12-31",
    "date:cessation_upper": "1947-12-31",
    "date:inception_lower": "1947-01-01",
    "date:inception_upper": "1947-01-01",
    "iso:country": "AU",
    "sfomuseum:accession_number": "1994.18.203 a b",
    "sfomuseum:category": "Philately",
    "sfomuseum:collection": "Aviation Archive",
    "sfomuseum:continent": "Transpacific",
    "sfomuseum:country": "Australia",
    "sfomuseum:creditline": "Purchase",
    "sfomuseum:date": "11/8/1947",
    "sfomuseum:daterange_end": "1947-11-08",
    "sfomuseum:daterange_start": "1947-11-08",
    "sfomuseum:description": "Airmail flight cover commemorating first Pan American clipper flight from Sydney to Suva, Fiji, FAM-19; blue cachet with image of route map with in-flight aircraft; stamp: dark red 1/6 (1 shilling 6 pence) (Australia); postmark: November 8, 1947, Sydney; backstamp: November 7, 1947, Nadi, Fiji; envelope: white airmail with red and blue rhomboids around border.\ra. envelope\rb. insert; “Another first flight cover carried by the system of the Flying Clippers”",
    "sfomuseum:maker": "Pan American Airways, Inc.",
    "sfomuseum:media_ids": [
      1527829831, 
      1527829833, 
      1527829835
    ],
    "sfomuseum:medium": "ink on paper",
    "sfomuseum:placetype": "object",
    "sfomuseum:subcategory": "Airmail Flight Cover",
    "wof:name": "airmail flight cover: Pan American World Airways, Sydney - Suva (Fiji) route",
    "wof:placetype": "venue"
  },
  "geometry": {"coordinates":[-122.386155,37.616358],"type":"Point"}
}
