{
  "type": "Feature",
  "properties": {
    "date:cessation_lower": "2003-01-01",
    "date:cessation_upper": "2003-12-31",
    "date:inception_lower": "2003-01-01",
    "date:inception_upper": "2003-12-31",
    "iso:country": "XX",
    "millsfield:images": [
      1527840209
    ],
    "millsfield:images_texts": [
      "e*mnEw*iss\nJAL GROUP INTERNATIONAL FLIGHT SCH\n2003\n4-5-6am\nApr.1~Jun.30,2003\nJ\nBI\n00Mn»\nJALIU-51+ I\nToll-free general reservations telephone numbers\nE#]* Ж# 0120-25-5931\nDomestic roservation\n0120-25-5971\nJASSU-S\u003cTI\nToll-free general reservations telephone numbers\n0120-7-11283\n0120-5-11283\nDomestic\n\u003cJAL\u003e www.jal.co.jp\n\u003cJAS\u003e www.ias.co.ip"
    ],
    "millsfield:images_texts_ids": [
      1527840209
    ],
    "millsfield:primary_image": 1527840209,
    "sfomuseum:accession_number": "2011.126.022.004",
    "sfomuseum:airline": "Japan Airlines",
    "sfomuseum:category": "Scheduling / Ticketing",
    "sfomuseum:collection": "Aviation Archive",
    "sfomuseum:creditline": "Gift of the Paul H. Kowalewski Collection",
    "sfomuseum:date": "2003",
    "sfomuseum:date_acquired": "2011-12-22",
    "sfomuseum:daterange_end": "2003-12-31",
    "sfomuseum:daterange_start": "2003-01-01",
    "sfomuseum:description": "International timetable issued by Japan Airlines, effective April 1 through June 30, 2003; full page photographic image of front view of Boeing 747; in Japanese.",
    "sfomuseum:dimensions": "6 x 6 3/4 inches (15.2 x 17.1 cm)",
    "sfomuseum:media_ids": [
      1527840209
    ],
    "sfomuseum:medium": "Paper, ink",
    "sfomuseum:placetype": "object",
    "sfomuseum:publication": ": , 2003.",
    "sfomuseum:subcategory": "Timetable",
    "wof:depicts": [
      1159289873,
      1159288585,
      1159293593,
      1159284563
    ],
    "wof:name": "timetable: Japan Airlines, international service",
    "wof:placetype": "custom",
    "wof:placetype_alt": "object"
  },
  "geometry": {"coordinates":[-122.386155,37.616357],"type":"Point"}
}
