{
  "type": "Feature",
  "properties": {
    "date:cessation_lower":"2015-12-31",
    "date:cessation_upper":"2015-12-31",
    "date:inception_lower":"2005-01-01",
    "date:inception_upper":"2005-01-01",
    "iso:country":"XX",
    "millsfield:images":[
        1527853465
    ],
    "sfomuseum:accession_number":"2012.096.042",
    "sfomuseum:category":"Philately",
    "sfomuseum:collection":"Aviation Archive",
    "sfomuseum:creditline":"Gift of the William Hough Collection",
    "sfomuseum:date":"c. 2010",
    "sfomuseum:daterange_end":"2015-12-31",
    "sfomuseum:daterange_start":"2005-01-01",
    "sfomuseum:description":"Postcard depicting color photographic image of beach-front landing by KLM (Royal Dutch Airlines) Boeing 747 aircraft at Princess Juliana International Airport, Saint Maarten, Netherlands Antilles; spectators on beach view aircraft at low altitude; \u201cSt. Maarten / Maho Bay & Juliana Airport\u201d printed at upper right; handwritten message on reverse addressed to Bill and Vivien Hough, dated February 22, 2010.",
    "sfomuseum:media_ids":[
        1527853465
    ],
    "sfomuseum:medium":"paper, ink",
    "sfomuseum:placetype":"object",
    "sfomuseum:subcategory":"Postcard",
    "wof:depicts":[
        1159289873,
        1159293593
    ],
    "wof:name":"postcard: KLM (Royal Dutch Airlines), Princess Juliana International Airport, Saint Maarten, Netherlands Antilles, Boeing 747",
    "wof:placetype":"venue"
},
  "geometry": {"coordinates":[-122.386155,37.616358],"type":"Point"}
}