{
  "type": "Feature",
  "properties": {
    "date:cessation_lower": "1974-01-01",
    "date:cessation_upper": "1974-12-31",
    "date:inception_lower": "1974-01-01",
    "date:inception_upper": "1974-12-31",
    "iso:country": "XX",
    "sfomuseum:accession_number": "2011.138.064",
    "sfomuseum:author": "Price, Alfred",
    "sfomuseum:callnumber": "UG1242.F5 P6 no.261",
    "sfomuseum:category": "Book",
    "sfomuseum:collection": "Aviation Library",
    "sfomuseum:creditline": "Gift of Helene and Rudy Stahl",
    "sfomuseum:date": "1974",
    "sfomuseum:date_acquired": "2012-03-29",
    "sfomuseum:daterange_end": "1974-12-31",
    "sfomuseum:daterange_start": "1974-01-01",
    "sfomuseum:description": "p. 49-72 : ill.",
    "sfomuseum:description_library": "p. 49-72 : ill.",
    "sfomuseum:medium": "paper, ink",
    "sfomuseum:placetype": "object",
    "sfomuseum:publication": "Windsor, England: Profile Publications, 1974.",
    "sfomuseum:publisher": "Profile Publications",
    "sfomuseum:publisher_location": "Windsor, England",
    "sfomuseum:series": "Profile publications ; no. 261",
    "sfomuseum:subcategory": "Book",
    "sfomuseum:subject": "Dornier 217 (Bomber) \rBombers -- Germany -- History.",
    "wof:name": "Dornier Do 217 variants",
    "wof:placetype": "custom",
    "wof:placetype_alt": [
      "object"
    ]
  },
  "geometry": {"coordinates":[-122.386155,37.616357],"type":"Point"}
}
