{
  "type": "Feature",
  "properties": {
    "date:cessation_lower":"2008-12-31",
    "date:cessation_upper":"2008-12-31",
    "date:inception_lower":"2008-01-01",
    "date:inception_upper":"2008-01-01",
    "iso:country":"XX",
    "sfomuseum:accession_number":"2009.108.038 a b",
    "sfomuseum:category":"Scheduling / Ticketing",
    "sfomuseum:collection":"Aviation Archive",
    "sfomuseum:creditline":"Gift of the William Hough Collection",
    "sfomuseum:date":"2008",
    "sfomuseum:daterange_end":"2008-12-31",
    "sfomuseum:daterange_start":"2008-01-01",
    "sfomuseum:description":"a. International flight schedule issued by JAL (Japan Airlines), September 1 through October 25, 2008; stylized photographic image on cover depicting profile view of JAL, Boeing 777 aircraft in flight; 126 pages.\rb. Addendum to timetable; single sheet, orange.",
    "sfomuseum:media_ids":[
        1527840041,
        1527840043
    ],
    "sfomuseum:medium":"paper, ink",
    "sfomuseum:placetype":"object",
    "sfomuseum:subcategory":"Timetable",
    "wof:depicts":[
        1159289979,
        1159293593
    ],
    "wof:name":"timetable: JAL (Japan Airlines)",
    "wof:placetype":"venue"
},
  "geometry": {"coordinates":[-122.386155,37.616358],"type":"Point"}
}