{
  "type": "Feature",
  "properties": {
    "date:cessation_lower": "2008-01-01",
    "date:cessation_upper": "2008-12-31",
    "date:inception_lower": "2008-01-01",
    "date:inception_upper": "2008-12-31",
    "iso:country": "XX",
    "millsfield:images": [
      1527840041,
      1527840043
    ],
    "millsfield:primary_image": 1527840041,
    "sfomuseum:accession_number": "2009.108.038 a b",
    "sfomuseum:aircraft": "Boeing 777",
    "sfomuseum:airline": "JAL (Japan Airlines)",
    "sfomuseum:category": "Scheduling / Ticketing",
    "sfomuseum:collection": "Aviation Archive",
    "sfomuseum:creditline": "Gift of the William Hough Collection",
    "sfomuseum:date": "2008",
    "sfomuseum:date_acquired": "2010-03-03",
    "sfomuseum:daterange_end": "2008-12-31",
    "sfomuseum:daterange_start": "2008-01-01",
    "sfomuseum:description": "a. International flight schedule issued by JAL (Japan Airlines), September 1 through October 25, 2008; 126 pages; color photographic image on cover depicting profile view of JAL, Boeing 777 aircraft in flight.\rb. Addendum to timetable; single sheet, orange.",
    "sfomuseum:dimensions": "6 3/4 x 3 x 1/4 inches (17.1 x 7.6 x .6 cm)",
    "sfomuseum:media_ids": [
      1527840041,
      1527840043
    ],
    "sfomuseum:medium": "paper, ink",
    "sfomuseum:placetype": "object",
    "sfomuseum:publication": ": , 2008.",
    "sfomuseum:subcategory": "Timetable",
    "wof:depicts": [
      1159293593,
      1159284563,
      1159289979,
      1159288585
    ],
    "wof:name": "timetable: JAL (Japan Airlines), international service",
    "wof:placetype": "custom",
    "wof:placetype_alt": "object"
  },
  "geometry": {"coordinates":[-122.386155,37.616357],"type":"Point"}
}
