{
  "type": "Feature",
  "properties": {
    "date:cessation_lower": "2008-01-01",
    "date:cessation_upper": "2008-12-31",
    "date:inception_lower": "2008-01-01",
    "date:inception_upper": "2008-12-31",
    "iso:country": "XX",
    "millsfield:images": [
      1527840041,
      1527840043
    ],
    "millsfield:images_texts": [
      "JALIIIIIH\nJAL INTERNATIONAL FLIGHT SCHEDULE\nJAL A#ME / JALWAYS JALDI17\nJAL\n2008 9.1 - 10.25\nJAL\nнети: стяака 0120-25-5931\nDomestie reservation\nBARES GEMAC#» 0120-25-5971\nwww.jal.co.jp\noneworld member",
      "JALWAYS JALDI17\n9/1-10/25H\nInternational Passenger Timetable:\nAdditional Information [Sep.1~ Oct.25 Edition]\nР71•72 -E70c*p\n+AZ#777-300ERDaAM 0$5€\nAH==1-3-71 JL006/JL00518\nJL002/JL00118\nut.\nP71•72 In-flight Services\nJAL To Introduce State-of-the Art\nFirst Class Suite \u0026 Business Class Seat\nIntroduction ef 777-300ER on US Routes Fased with Best Seating and Service in the skes.\nBrand new Tiresoser a roralt w start operating okvo -New York route\nfrom Avaust. Tokyo-San Frano sco route from September.\nThe route information for new 777-300ER aircraft.\n• New York=Tokyo JL005/JL006\nstarting Aug. 1, 2008\nService is available every other day until Aug. 10,\nand will be available daily from Aug. 11\n• San Francisco=Tokyo JL001/JL002\nstarting Sep. 13, 2008\nAvailable daily\n(Notice) Operating aircraft and seating configurations are subject\nto change without prior notice"
    ],
    "millsfield:images_texts_ids": [
      1527840041,
      1527840043
    ],
    "millsfield:primary_image": 1527840041,
    "sfomuseum:accession_number": "2009.108.038 a b",
    "sfomuseum:aircraft": "Boeing 777",
    "sfomuseum:airline": "Japan Airlines",
    "sfomuseum:category": "Scheduling / Ticketing",
    "sfomuseum:collection": "Aviation Archive",
    "sfomuseum:creditline": "Gift of the William Hough Collection",
    "sfomuseum:date": "2008",
    "sfomuseum:date_acquired": "2010-03-03",
    "sfomuseum:daterange_end": "2008-12-31",
    "sfomuseum:daterange_start": "2008-01-01",
    "sfomuseum:description": "a. International flight schedule issued by Japan Airlines, September 1 through October 25, 2008; 126 pages; color photographic image on cover depicting profile view of JAL, Boeing 777 aircraft in flight.\rb. Addendum to timetable; single sheet, orange.",
    "sfomuseum:dimensions": "6 3/4 x 3 x 1/4 inches (17.1 x 7.6 x .6 cm)",
    "sfomuseum:media_ids": [
      1527840041,
      1527840043
    ],
    "sfomuseum:medium": "paper, ink",
    "sfomuseum:placetype": "object",
    "sfomuseum:publication": ": , 2008.",
    "sfomuseum:subcategory": "Timetable",
    "wof:depicts": [
      1159288585,
      1159293593,
      1159284563,
      1159289979
    ],
    "wof:name": "timetable: Japan Airlines, international service",
    "wof:placetype": "custom",
    "wof:placetype_alt": "object"
  },
  "geometry": {"coordinates":[-122.386155,37.616357],"type":"Point"}
}
