{
  "type": "Feature",
  "properties": {
    "date:cessation_lower":"1984-12-31",
    "date:cessation_upper":"1984-12-31",
    "date:inception_lower":"1984-01-01",
    "date:inception_upper":"1984-01-01",
    "iso:country":"XX",
    "sfomuseum:accession_number":"2015.056.013",
    "sfomuseum:category":"Philately",
    "sfomuseum:collection":"Aviation Archive",
    "sfomuseum:creditline":"Gift of Robert Harris",
    "sfomuseum:date":"08/08/1984",
    "sfomuseum:daterange_end":"1984-08-08",
    "sfomuseum:daterange_start":"1984-08-08",
    "sfomuseum:description":"Airmail flight cover, part of International Tributes to the History of Flight series by the Postal Commemorative Society; white envelope with full color illustration cachet and inset stamp commemorating the Wright Brothers\u2019 first European flight in public on August 8, 1908, in Paris, France, by Wilbur Wright with Flyer (Type III) biplane; commemorative cancellation stamp dated August 8, 1984 in Paris; includes information on reverse.",
    "sfomuseum:medium":"paper, ink",
    "sfomuseum:placetype":"object",
    "sfomuseum:subcategory":"Airmail Flight Cover",
    "wof:name":"airmail flight cover: The Wright brothers\u2019 first European flight in public commemorative",
    "wof:placetype":"venue"
},
  "geometry": {"coordinates":[-122.386155,37.616358],"type":"Point"}
}