{
  "type": "Feature",
  "properties": {
    "date:cessation_lower":"1977-12-31",
    "date:cessation_upper":"1977-12-31",
    "date:inception_lower":"1967-01-01",
    "date:inception_upper":"1967-01-01",
    "iso:country":"XX",
    "millsfield:images":[
        1527819331,
        1527819333
    ],
    "sfomuseum:accession_number":"2010.181.001",
    "sfomuseum:category":"Promotional",
    "sfomuseum:collection":"Aviation Museum",
    "sfomuseum:creditline":"Gift of Doug Dickson",
    "sfomuseum:date":"c. 1972",
    "sfomuseum:daterange_end":"1977-12-31",
    "sfomuseum:daterange_start":"1967-01-01",
    "sfomuseum:description":"Small rectangular green bag with black piping; white airplane outline and contrail with \u201cAir Vietnam / Kim KY\u201d across center; adjustable green shoulder strap with zipper closure; interior cardboard support; five metallic rivets on bottom.",
    "sfomuseum:media_ids":[
        1527819333,
        1527819331
    ],
    "sfomuseum:medium":"cotton, plastic, ink, cardboard, metal",
    "sfomuseum:placetype":"object",
    "sfomuseum:subcategory":"Airline Bag",
    "wof:name":"miniature airline bag: Air Vietnam",
    "wof:placetype":"venue"
},
  "geometry": {"coordinates":[-122.386155,37.616358],"type":"Point"}
}