{
  "type": "Feature",
  "properties": {
    "date:cessation_lower": "1972-01-01",
    "date:cessation_upper": "1972-12-31",
    "date:inception_lower": "1972-01-01",
    "date:inception_upper": "1972-12-31",
    "iso:country": "XX",
    "sfomuseum:accession_number": "99-0055",
    "sfomuseum:author": "Martin, Paul K.",
    "sfomuseum:callnumber": "HE9768 .M37 1972",
    "sfomuseum:category": "Book",
    "sfomuseum:collection": "Aviation Library",
    "sfomuseum:date": "1972",
    "sfomuseum:daterange_end": "1972-12-31",
    "sfomuseum:daterange_start": "1972-01-01",
    "sfomuseum:description": "v. ill. 22 cm.",
    "sfomuseum:description_library": "v. ill. 22 cm.",
    "sfomuseum:medium": "paper, ink",
    "sfomuseum:placetype": "object",
    "sfomuseum:publication": "Cranston, RI: Aerotravel Research, 1972.",
    "sfomuseum:publisher": "Aerotravel Research",
    "sfomuseum:publisher_location": "Cranston, RI",
    "sfomuseum:subcategory": "Book",
    "sfomuseum:subject": "Airlines Directories.",
    "wof:name": "The airline handbook",
    "wof:placetype": "custom",
    "wof:placetype_alt": "object"
  },
  "geometry": {"coordinates":[-122.386155,37.616357],"type":"Point"}
}
