{
  "type": "Feature",
  "properties": {
    "date:cessation_lower":"1949-12-31",
    "date:cessation_upper":"1949-12-31",
    "date:inception_lower":"1949-01-01",
    "date:inception_upper":"1949-01-01",
    "iso:country":"US",
    "sfomuseum:accession_number":"1997.52.084.014",
    "sfomuseum:category":"Photograph",
    "sfomuseum:collection":"Aviation Archive",
    "sfomuseum:continent":"North America",
    "sfomuseum:country":"United States",
    "sfomuseum:creditline":"Transfer",
    "sfomuseum:date":"1949",
    "sfomuseum:daterange_end":"1949-12-31",
    "sfomuseum:daterange_start":"1949-01-01",
    "sfomuseum:description":"Black and white composite photograph depicting vertical aerial view of San Francisco Airport, dated December, 1949.",
    "sfomuseum:maker":"San Francisco Public Utilities Commission",
    "sfomuseum:media_ids":[
        1527818827
    ],
    "sfomuseum:medium":"photograph",
    "sfomuseum:placetype":"object",
    "sfomuseum:subcategory":"Print, Photograph",
    "wof:name":"photograph: San Francisco Airport, composite aerial view",
    "wof:placetype":"venue"
},
  "geometry": {"coordinates":[-122.386155,37.616358],"type":"Point"}
}