{
  "type": "Feature",
  "properties": {
    "date:cessation_lower":"2005-12-31",
    "date:cessation_upper":"2005-12-31",
    "date:inception_lower":"2005-01-01",
    "date:inception_upper":"2005-01-01",
    "iso:country":"XX",
    "sfomuseum:accession_number":"2007.086.078",
    "sfomuseum:category":"Food Service",
    "sfomuseum:collection":"Aviation Museum",
    "sfomuseum:creditline":"Gift of Ian H. Dally of Auckland, New Zealand",
    "sfomuseum:date":"2005",
    "sfomuseum:daterange_end":"2005-12-31",
    "sfomuseum:daterange_start":"2005-01-01",
    "sfomuseum:description":"Menu produced by Lufthansa German Airlines, Singapore - Frankfurt route; white cover with color illustration of fruit; dinner and breakfast menu items include Szechuan beef, cocciolette pasta, cold cuts, and poached eggs; menu number: 261C015-C; class: business; date: 5/05-6/05.",
    "sfomuseum:media_ids":[
        1527843963,
        1527853603
    ],
    "sfomuseum:medium":"paper, ink",
    "sfomuseum:placetype":"object",
    "sfomuseum:subcategory":"Menu",
    "wof:name":"menu: Lufthansa German Airlines, Business Class",
    "wof:placetype":"venue"
},
  "geometry": {"coordinates":[-122.386155,37.616358],"type":"Point"}
}