{
  "type": "Feature",
  "properties": {
    "date:cessation_lower": "2005-01-01",
    "date:cessation_upper": "2005-12-31",
    "date:inception_lower": "2005-01-01",
    "date:inception_upper": "2005-12-31",
    "iso:country": "XX",
    "millsfield:images": [
      1527843963,
      1527853603
    ],
    "millsfield:images_texts": [
      "TOKYO — FRANKFURT\nLunch\nAppetizer\nAssorted cold cuts\nColeslaw with cheese\nMain course\n(for September)\nBraised mackerel in miso sauce with rice [405 kcal]\nBeef hamburger steak with soy sauce [348 kcal]\n(for October)\nChicken teriyaki with rice [603 kcal]\nor\nSeafood with creamy tomato sauce [354 kcal]\n(for November)\nJapanese-style braised chicken with rice [418 kcal]\nor\nSeafood with creamy curry sauce [341 kcal]\nJapanese noodles\nDessert\nWe are happy to offer an assortment of snacks\nat our self-service counter. Please feel free to\nhelp yourself at any time after the meal service.\nFRANKFURT — TOKYO\nDinner\nAppetizer\nSmoked salmon with lemon garnish\nTurkey pastrami\nMain course\nJapanese-style chicken with vegetable sauce [381 kcal]\nor\nShrimp and whitefish with tomato sauce 1306 kcall\nJapanese noodles\nDessert\nRefreshment\nHot chicken-and-cheese pita sandwich\nFresh fruit\nRefreshment\nCannelloni\nFruit cocktail",
      "Lufthansa Business Class\nMenu"
    ],
    "millsfield:images_texts_ids": [
      1527843963,
      1527853603
    ],
    "millsfield:primary_image": 1527853603,
    "sfomuseum:accession_number": "2007.086.078",
    "sfomuseum:airline": "Lufthansa",
    "sfomuseum:category": "Passenger Amenity, Archive",
    "sfomuseum:collection": "Aviation Archive",
    "sfomuseum:creditline": "Gift of Ian H. Dally of Auckland, New Zealand",
    "sfomuseum:date": "2005",
    "sfomuseum:date_acquired": "2007-09-29",
    "sfomuseum:daterange_end": "2005-12-31",
    "sfomuseum:daterange_start": "2005-01-01",
    "sfomuseum:description": "Menu issued by Lufthansa, Singapore - Frankfurt route; white cover with color illustration of fruit; dinner and breakfast menu items include Szechuan beef, cocciolette pasta, cold cuts, and poached eggs; menu number: 261C015-C; class: business; date: 5/05-6/05.",
    "sfomuseum:dimensions": "12 x 8 inches (30.5 x 20.3 cm)",
    "sfomuseum:media_ids": [
      1527843963,
      1527853603
    ],
    "sfomuseum:medium": "paper, ink",
    "sfomuseum:placetype": "object",
    "sfomuseum:publication": ": , 2005.",
    "sfomuseum:subcategory": "Menu",
    "wof:depicts": [
      1159288215,
      1159284711
    ],
    "wof:name": "menu: Lufthansa, Business Class",
    "wof:placetype": "custom",
    "wof:placetype_alt": [
      "object"
    ]
  },
  "geometry": {"coordinates":[-122.386155,37.616357],"type":"Point"}
}
