{
  "type": "Feature",
  "properties": {
    "date:cessation_lower": "2005-01-01",
    "date:cessation_upper": "2005-12-31",
    "date:inception_lower": "2005-01-01",
    "date:inception_upper": "2005-12-31",
    "iso:country": "XX",
    "millsfield:images": [
      1527843963,
      1527853603
    ],
    "millsfield:primary_image": 1527853603,
    "sfomuseum:accession_number": "2007.086.078",
    "sfomuseum:airline": "Lufthansa",
    "sfomuseum:category": "Passenger Amenity, Archive",
    "sfomuseum:collection": "Aviation Archive",
    "sfomuseum:creditline": "Gift of Ian H. Dally of Auckland, New Zealand",
    "sfomuseum:date": "2005",
    "sfomuseum:date_acquired": "2007-09-29",
    "sfomuseum:daterange_end": "2005-12-31",
    "sfomuseum:daterange_start": "2005-01-01",
    "sfomuseum:description": "Menu issued by Lufthansa, Singapore - Frankfurt route; white cover with color illustration of fruit; dinner and breakfast menu items include Szechuan beef, cocciolette pasta, cold cuts, and poached eggs; menu number: 261C015-C; class: business; date: 5/05-6/05.",
    "sfomuseum:dimensions": "12 x 8 inches (30.5 x 20.3 cm)",
    "sfomuseum:media_ids": [
      1527843963,
      1527853603
    ],
    "sfomuseum:medium": "paper, ink",
    "sfomuseum:placetype": "object",
    "sfomuseum:publication": ": , 2005.",
    "sfomuseum:subcategory": "Menu",
    "wof:depicts": [
      1159284711,
      1159288215
    ],
    "wof:name": "menu: Lufthansa, Business Class",
    "wof:placetype": "custom",
    "wof:placetype_alt": "object"
  },
  "geometry": {"coordinates":[-122.386155,37.616357],"type":"Point"}
}
