{
  "type": "Feature",
  "properties": {
    "date:cessation_lower": "1982-12-31",
    "date:cessation_upper": "1982-12-31",
    "date:inception_lower": "1982-01-01",
    "date:inception_upper": "1982-01-01",
    "iso:country": "XX",
    "sfomuseum:accession_number": "2002.135.041.003",
    "sfomuseum:category": "Scheduling / Ticketing",
    "sfomuseum:collection": "Aviation Archive",
    "sfomuseum:creditline": "Gift of Thomas G. Dragges",
    "sfomuseum:date": "1982",
    "sfomuseum:daterange_end": "1982-12-31",
    "sfomuseum:daterange_start": "1982-01-01",
    "sfomuseum:description": "Timetable issued by Aspen Airways, effective January 29, 1982; three page double-sided fold-out; cover is white with an orange spade/aspen leaf image in the center. A sketch of an aircraft and a list of destinations are in black. ",
    "sfomuseum:media_ids": [
      1527837359
    ],
    "sfomuseum:medium": "paper, ink",
    "sfomuseum:placetype": "object",
    "sfomuseum:subcategory": "Timetable",
    "wof:name": "timetable: Aspen Airways",
    "wof:placetype": "venue"
  },
  "geometry": {"coordinates":[-122.386155,37.616358],"type":"Point"}
}
