{
  "type": "Feature",
  "properties": {
    "date:cessation_lower": "1960-01-01",
    "date:cessation_upper": "1969-12-31",
    "date:inception_lower": "1960-01-01",
    "date:inception_upper": "1969-12-31",
    "iso:country": "US",
    "sfomuseum:accession_number": "2010.022.001 a b",
    "sfomuseum:airline": "VIASA International Airways",
    "sfomuseum:category": "Audio / Visual",
    "sfomuseum:collection": "Aviation Archive",
    "sfomuseum:continent": "North America",
    "sfomuseum:country": "United States",
    "sfomuseum:creditline": "Purchase",
    "sfomuseum:date": "1960s",
    "sfomuseum:daterange_end": "1969-12-31",
    "sfomuseum:daterange_start": "1960-01-01",
    "sfomuseum:description": "a. phonograph cover, large colorful illustration of blue sky with colorful world city’s landmarks, large yellow “Music, in the air . . .” near center with in-flight airliner with jet stream, oval area with dark blue border and blue “All Jets,” orange “VIASA,” small dark blue “Venezuelan International Airways” below near lower right corner, black and white images of sites of Venezuela and description of music.\rb. black record with red center, silver “Ultra High Fidelity” and “Music in the Air” in center, same on reverse.",
    "sfomuseum:dimensions": "12 1/2 x 12 1/2 inches (31.8 x 31.8 cm)",
    "sfomuseum:maker": "ARTREC Productions, Ltd., Inc.",
    "sfomuseum:medium": "cardboard, paper, ink, vinyl, plastic",
    "sfomuseum:placetype": "object",
    "sfomuseum:publication": ": , 1960s.",
    "sfomuseum:subcategory": "Phonograph Record",
    "wof:depicts": [
      1159285477
    ],
    "wof:name": "phonograph record: VIASA Venezuelan International Airways, Music in the air...",
    "wof:placetype": "venue"
  },
  "geometry": {"coordinates":[-122.386155,37.616357],"type":"Point"}
}
