{
  "type": "Feature",
  "properties": {
    "date:cessation_lower":"1969-12-31",
    "date:cessation_upper":"1969-12-31",
    "date:inception_lower":"1960-01-01",
    "date:inception_upper":"1960-01-01",
    "iso:country":"US",
    "sfomuseum:accession_number":"2010.022.001 a b",
    "sfomuseum:category":"Audio / Visual",
    "sfomuseum:collection":"Aviation Archive",
    "sfomuseum:continent":"North America",
    "sfomuseum:country":"United States",
    "sfomuseum:creditline":"Purchase",
    "sfomuseum:date":"1960s",
    "sfomuseum:daterange_end":"1969-12-31",
    "sfomuseum:daterange_start":"1960-01-01",
    "sfomuseum:description":"a. phonograph cover, large colorful illustration of blue sky with colorful world city\u2019s landmarks, large yellow \u201cMusic, in the air . . .\u201d near center with in-flight airliner with jet stream, oval area with dark blue border and blue \u201cAll Jets,\u201d orange \u201cVIASA,\u201d small dark blue \u201cVenezuelan International Airways\u201d below near lower right corner, black and white images of sites of Venezuela and description of music.\rb. black record with red center, silver \u201cUltra High Fidelity\u201d and \u201cMusic in the Air\u201d in center, same on reverse.",
    "sfomuseum:maker":"ARTREC Productions, Ltd., Inc.",
    "sfomuseum:medium":"cardboard, paper, ink, vinyl, plastic",
    "sfomuseum:placetype":"object",
    "sfomuseum:subcategory":"Phonograph Record",
    "wof:name":"phonograph record: VIASA Venezuelan International Airways, Music in the air...",
    "wof:placetype":"venue"
},
  "geometry": {"coordinates":[-122.386155,37.616358],"type":"Point"}
}