{
  "type": "Feature",
  "properties": {
    "date:cessation_lower": "1934-12-31",
    "date:cessation_upper": "1934-12-31",
    "date:inception_lower": "1934-01-01",
    "date:inception_upper": "1934-01-01",
    "iso:country": "XX",
    "millsfield:images": [
      1527831813
    ],
    "sfomuseum:accession_number": "2008.075.046 a c",
    "sfomuseum:airline": "U.S. Navy",
    "sfomuseum:category": "Philately",
    "sfomuseum:collection": "Aviation Archive",
    "sfomuseum:creditline": "Gift of Jon E. Krupnick",
    "sfomuseum:date": "02/15/1934",
    "sfomuseum:daterange_end": "1934-02-15",
    "sfomuseum:daterange_start": "1934-02-15",
    "sfomuseum:description": "Airmail flight cover, U.S. Navy Pearl Harbor to Midway Flight, San Francisco - Hawaii, February 10, 1934.\ra. cover: postmarked February 15, 1934, U.S.S. Avocet, Laysan Island; one 3-cent postage stamp; addressed to Mr. R.C. Hendricks; on reverse: signature of Peter N. Kohl at bottom center edge with notation in pencil on flap, \"Avocet auxillary aircraft tender crew- about 50, at Pearl Harbor 7 Dec 41\".\rb. photocopied additional information supplied by donor.\rc. photocopied additional information supplied by donor.",
    "sfomuseum:media_ids": [
      1527831813
    ],
    "sfomuseum:medium": "paper, ink",
    "sfomuseum:placetype": "object",
    "sfomuseum:subcategory": "Airmail Flight Cover",
    "wof:depicts": [
      1159285407
    ],
    "wof:name": "airmail flight cover: U.S. Navy Pearl Harbor to Midway Flight, San Francisco - Hawaii, February 10, 1934",
    "wof:placetype": "venue"
  },
  "geometry": {"coordinates":[-122.386155,37.616357],"type":"Point"}
}
