{
  "type": "Feature",
  "properties": {
    "date:cessation_lower": "1998-01-01",
    "date:cessation_upper": "1998-12-31",
    "date:inception_lower": "1998-01-01",
    "date:inception_upper": "1998-12-31",
    "iso:country": "XX",
    "millsfield:images": [
      1527849033
    ],
    "millsfield:images_texts": [
      "BRITISH AIRWAYS\nWorldwide Timetable\n29 March - 24 October 1998"
    ],
    "millsfield:images_texts_ids": [
      1527849033
    ],
    "millsfield:primary_image": 1527849033,
    "sfomuseum:accession_number": "2003.105.030.006",
    "sfomuseum:airline": "British Airways",
    "sfomuseum:category": "Scheduling / Ticketing",
    "sfomuseum:collection": "Aviation Archive",
    "sfomuseum:creditline": "Gift of Craig Lynes",
    "sfomuseum:date": "1998",
    "sfomuseum:date_acquired": "2003-12-29",
    "sfomuseum:daterange_end": "1998-12-31",
    "sfomuseum:daterange_start": "1998-01-01",
    "sfomuseum:description": "Worldwide timetable issued by British Airways, effective March 29 through October 24, 1998; 320-page schedule; blue cover with color photographic image of children playing soccer (football).",
    "sfomuseum:dimensions": "8 x 4 1/2 inches (20.3 x 11.4 cm)",
    "sfomuseum:media_ids": [
      1527849033
    ],
    "sfomuseum:medium": "paper, ink",
    "sfomuseum:placetype": "object",
    "sfomuseum:publication": ": , 1998.",
    "sfomuseum:subcategory": "Timetable",
    "wof:depicts": [
      1159284021,
      1159287729
    ],
    "wof:name": "timetable: British Airways",
    "wof:placetype": "custom",
    "wof:placetype_alt": [
      "object"
    ]
  },
  "geometry": {"coordinates":[-122.386155,37.616357],"type":"Point"}
}
