{
  "type": "Feature",
  "properties": {
    "date:cessation_lower": "1992-11-01",
    "date:cessation_upper": "1992-11-30",
    "date:inception_lower": "1992-11-01",
    "date:inception_upper": "1992-11-30",
    "iso:country": "XX",
    "millsfield:images": [
      1527846425,
      1527846429
    ],
    "millsfield:images_texts": [
      "E\nN\nU\nF\nR\nWUnITED",
      "We are pleased to present an array of fine California wines\ncarefully selected for their excellence by United's Cellar Committee\nunder the guidance of wine judge and author; Bob Thompson.\nYour Flight Attendant will inform you which wines are being offered today.\nCHAMPAGNE\nDomaine Chandon Napa Valley Brut NV\nCHARDONNAY\nWilliam Wheeler\nVilla Mt. Eden\nSonoma County 1989 or Napa Valley 1989\nCABERNET SAUVIGNON\nChâteau Souverain 1988\nLouis Martini Reserve 1987\nEnjoy a glass of chilled Orange Juice\nor a hot cup of freshly brewed Coffee\nSara Lee Muffin and a Croissant\nwith Continental Butter and Preserves\nFines Herbes Omelette\nblends fresh Eggs with a taste of Tarragon, Basil and Chives\nCanadian Bacon Scottish Banger Fresh Fruit\ncheese bunves\nare Crêpes filled with a light Cottage Cheese\nblended with Orange Zest and Cinnamon\nRaspberry Orange Sauce\nCanadian Bacon Fresh Fruit\nMay We Suggest\na light alternative of Cantaloupe. Honevdew Melon, Grapes\nand Strawberries, served with Yogurt and cold Cereal\nThe Finishing Touch\nwe recommend is 100% Colombian Coffee,\nCappuccino or selected Herbal Teas\nEFORE\nY\nCalifornia Deli Buffet\nDesigned in consultation\nwith the renowned Nate 'n Al of Beverly Hills\nFeaturing an array of Smoked Salmon with traditional accompaniments,\nShrimp, Meats and Cheeses, assorted Breads\nand Bagels and a basket of seasonal fresh Fruit\n14003 1050103"
    ],
    "millsfield:images_texts_ids": [
      1527846425,
      1527846429
    ],
    "millsfield:primary_image": 1527846425,
    "sfomuseum:accession_number": "2006.059.307.230",
    "sfomuseum:airline": "United Airlines",
    "sfomuseum:category": "Passenger Amenity, Archive",
    "sfomuseum:collection": "Aviation Archive",
    "sfomuseum:creditline": "Gift of the Paul Edward Fair Estate",
    "sfomuseum:date": "11/1992",
    "sfomuseum:date_acquired": "2006-10-19",
    "sfomuseum:daterange_end": "1992-11-30",
    "sfomuseum:daterange_start": "1992-11-01",
    "sfomuseum:description": "Menu and wine list issued by United Airlines; dark blue and gray cover; menu items include herb omelette, cheese blintzes, and deli buffet; menu number: B01(J)-S01(J) 1400-3; class: First; date: 11/92.",
    "sfomuseum:dimensions": "9 1/2 x 6 3/4 inches (24.1 x 17.1 cm)",
    "sfomuseum:media_ids": [
      1527846425,
      1527846429
    ],
    "sfomuseum:medium": "paper, ink",
    "sfomuseum:placetype": "object",
    "sfomuseum:publication": ": , 1992.",
    "sfomuseum:subcategory": "Menu",
    "wof:depicts": [
      1159285413,
      1159288779
    ],
    "wof:name": "menu: United Airlines, First Class",
    "wof:placetype": "custom",
    "wof:placetype_alt": [
      "object"
    ]
  },
  "geometry": {"coordinates":[-122.386155,37.616357],"type":"Point"}
}
