{
  "type": "Feature",
  "properties": {
    "date:cessation_lower":"1992-12-31",
    "date:cessation_upper":"1992-12-31",
    "date:inception_lower":"1992-01-01",
    "date:inception_upper":"1992-01-01",
    "iso:country":"XX",
    "millsfield:images":[
        1527846429,
        1527846425
    ],
    "sfomuseum:accession_number":"2006.059.307.230",
    "sfomuseum:airline":"United Airlines",
    "sfomuseum:category":"Passenger Amenity",
    "sfomuseum:collection":"Aviation Archive",
    "sfomuseum:creditline":"Gift of the Paul Edward Fair Estate",
    "sfomuseum:date":"1992",
    "sfomuseum:daterange_end":"1992-11-30",
    "sfomuseum:daterange_start":"1992-11-01",
    "sfomuseum:description":"Menu and wine list issued by United Air Lines; dark blue and gray cover; menu items include herb omelette, cheese blintzes, and deli buffet; menu number: B01(J)-S01(J) 1400-3; class: First; date: 11/92.",
    "sfomuseum:media_ids":[
        1527846425,
        1527846429
    ],
    "sfomuseum:medium":"paper, ink",
    "sfomuseum:placetype":"object",
    "sfomuseum:subcategory":"Menu",
    "wof:depicts":[
        1159285413
    ],
    "wof:name":"menu: United Airlines, First Class",
    "wof:placetype":"venue"
},
  "geometry": {"coordinates":[-122.386155,37.616357],"type":"Point"}
}