{
  "type": "Feature",
  "properties": {
    "date:cessation_lower": "1992-11-01",
    "date:cessation_upper": "1992-11-30",
    "date:inception_lower": "1992-11-01",
    "date:inception_upper": "1992-11-30",
    "iso:country": "XX",
    "millsfield:images": [
      1527846425,
      1527846429
    ],
    "millsfield:images_texts": [
      "WUnITED",
      "He are pleased to present an array of fine California umes\ncarefully selected for their excellence by United's Cellar Committee\nunder the guidance of wine judge and author, Bob Thompson.\nfour Flight Attendant wall inform vou which unes are beins offered todav\nCHAMPAGNE\nDomaine Chandon Napa Valley Brut NV\nCHARDONNAY\nWilliam Wheeler\nSonoma County 1989\nVilla Mt. Eden\nNapa Valley 1989\nCABERNET SAUVIGNON\nChatean Sonseroin 1988 or Louis Martini Beserve 1987\nG\no\nM\nOR N IN G\nEnjoy a glass of chilled Orange Juice\nor a hot cup of freshly brewed Cottee\npara see rulin and a croissant\nwith Continental Butter and eresery\nTunes Herbes Omelette\nblends fresh Eggs with a taste of Tarragon, Basil and Chives\nCanadian Bacon\nScottish Banger Fresh Fruit\nCheese Blintzes\nare Crèpes filled with a light Cottage Cheese\nblended with Orange Zest and Cinnamon\nRaspberry Orange Sauce\nCanadian Bacon kresh krait\nMay We Suggest\na light alternative of Cantaloupe, Honeydew Melon, Grapes\nand Strawberres, served with Yogurt and cold Cereal\nThe Finishing Touch\nwe recommend is 100% Colombian Coffee,\nCappuccino or selectedurterballicas\nBE F\nO R\nG\nCalifornia Deli Buffet\nDesigned in consultation\nwith the renowned Nate n Al of Beverly Hills\nFeaturng an array of omoked salmon with traditional accompamments,\nShrimp. Meats and Cheeses, assorted Breads\nand Bagels and a basket\n14003 014480143"
    ],
    "millsfield:images_texts_ids": [
      1527846425,
      1527846429
    ],
    "millsfield:primary_image": 1527846425,
    "sfomuseum:accession_number": "2006.059.307.230",
    "sfomuseum:airline": "United Airlines",
    "sfomuseum:category": "Passenger Amenity, Archive",
    "sfomuseum:collection": "Aviation Archive",
    "sfomuseum:creditline": "Gift of the Paul Edward Fair Estate",
    "sfomuseum:date": "11/1992",
    "sfomuseum:date_acquired": "2006-10-19",
    "sfomuseum:daterange_end": "1992-11-30",
    "sfomuseum:daterange_start": "1992-11-01",
    "sfomuseum:description": "Menu and wine list issued by United Airlines; dark blue and gray cover; menu items include herb omelette, cheese blintzes, and deli buffet; menu number: B01(J)-S01(J) 1400-3; class: First; date: 11/92.",
    "sfomuseum:dimensions": "9 1/2 x 6 3/4 inches (24.1 x 17.1 cm)",
    "sfomuseum:media_ids": [
      1527846425,
      1527846429
    ],
    "sfomuseum:medium": "paper, ink",
    "sfomuseum:placetype": "object",
    "sfomuseum:publication": ": , 1992.",
    "sfomuseum:subcategory": "Menu",
    "wof:depicts": [
      1159285413,
      1159288779
    ],
    "wof:name": "menu: United Airlines, First Class",
    "wof:placetype": "custom",
    "wof:placetype_alt": "object"
  },
  "geometry": {"coordinates":[-122.386155,37.616357],"type":"Point"}
}
