{
  "type": "Feature",
  "properties": {
    "date:cessation_lower": "1994-12-31",
    "date:cessation_upper": "1994-12-31",
    "date:inception_lower": "1994-01-01",
    "date:inception_upper": "1994-01-01",
    "iso:country": "XX",
    "sfomuseum:accession_number": "2006.059.307.020.002",
    "sfomuseum:category": "Food Service",
    "sfomuseum:collection": "Aviation Museum",
    "sfomuseum:creditline": "Gift of the Paul Edward Fair Estate",
    "sfomuseum:date": "1994",
    "sfomuseum:daterange_end": "1994-12-31",
    "sfomuseum:daterange_start": "1994-01-01",
    "sfomuseum:description": "Menu and wine list produced by United Air Lines, Sydney - Los Angeles route; gray and dark red cover; menu items include rack of lamb, chicken breast, and pan-seared John Dory (fish); menu number: SYD-LAX LD63-S89-B87; class: Connoisseur (business); date: 4/94.",
    "sfomuseum:media_ids": [
      1527853711, 
      1527853713
    ],
    "sfomuseum:medium": "paper, ink",
    "sfomuseum:placetype": "object",
    "sfomuseum:subcategory": "Menu",
    "wof:name": "menu: United Airlines, Connoisseur (Business) Class",
    "wof:placetype": "venue"
  },
  "geometry": {"coordinates":[-122.386155,37.616358],"type":"Point"}
}
