{
  "type": "Feature",
  "properties": {
    "date:cessation_lower": "1994-01-01",
    "date:cessation_upper": "1994-12-31",
    "date:inception_lower": "1994-01-01",
    "date:inception_upper": "1994-12-31",
    "iso:country": "XX",
    "millsfield:images": [
      1527853711,
      1527853713
    ],
    "millsfield:images_texts": [
      "MENU AND\nWINE\nLIST\nCONNOISSEUR\nLA\nUUNITED",
      "Welcome aboard United Airlines Connoisseur Class!\nIt is our pleasure and privilege\nto offer you the hospitality, fine cuisine and impeccable service\nfor which United Airlines is known throughout the world.\nWe are confident that the dedication of our personnel\nwill make your journey a most memorable\nand enjoyable experience.\nbat Obria\nPat O'Brien\nVice President. Food Service\nUnited Airlines. Member of The Chaînes des Rôtisseurs"
    ],
    "millsfield:images_texts_ids": [
      1527853711,
      1527853713
    ],
    "millsfield:primary_image": 1527853711,
    "sfomuseum:accession_number": "2006.059.307.020.002",
    "sfomuseum:airline": "United Airlines",
    "sfomuseum:category": "Passenger Amenity, Archive",
    "sfomuseum:collection": "Aviation Archive",
    "sfomuseum:creditline": "Gift of the Paul Edward Fair Estate",
    "sfomuseum:date": "1994",
    "sfomuseum:date_acquired": "2007-04-10",
    "sfomuseum:daterange_end": "1994-12-31",
    "sfomuseum:daterange_start": "1994-01-01",
    "sfomuseum:description": "Menu and wine list issued by United Airlines, Sydney - Los Angeles route; gray and dark red cover; menu items include rack of lamb, chicken breast, and pan-seared John Dory (fish); menu number: SYD-LAX LD63-S89-B87; class: Connoisseur (business); date: 4/94.",
    "sfomuseum:dimensions": "8 1/2 x 8 1/2 inches (21.6 x 21.6 cm)",
    "sfomuseum:media_ids": [
      1527853711,
      1527853713
    ],
    "sfomuseum:medium": "paper, ink",
    "sfomuseum:placetype": "object",
    "sfomuseum:publication": ": , 1994.",
    "sfomuseum:subcategory": "Menu",
    "wof:depicts": [
      1159285413,
      1159288779
    ],
    "wof:name": "menu: United Airlines, Connoisseur (Business) Class",
    "wof:placetype": "custom",
    "wof:placetype_alt": "object"
  },
  "geometry": {"coordinates":[-122.386155,37.616357],"type":"Point"}
}
