{
  "type": "Feature",
  "properties": {
    "date:cessation_lower": "1964-12-31",
    "date:cessation_upper": "1964-12-31",
    "date:inception_lower": "1964-01-01",
    "date:inception_upper": "1964-01-01",
    "iso:country": "XX",
    "millsfield:images": [
      1527842705
    ],
    "sfomuseum:accession_number": "2001.106.401",
    "sfomuseum:airline": "Trans-Texas Airways",
    "sfomuseum:category": "Scheduling / Ticketing",
    "sfomuseum:collection": "Aviation Archive",
    "sfomuseum:creditline": "Gift of Mark F. Adams Collection",
    "sfomuseum:date": "1964",
    "sfomuseum:daterange_end": "1964-12-31",
    "sfomuseum:daterange_start": "1964-01-01",
    "sfomuseum:description": "Timetable issued by issued by Trans-Texas Airways, effective June 15, 1964; white, orange, and blue cover with company logotype at top and rear view of in-flight airplane at bottom.",
    "sfomuseum:dimensions": "9 1/4 x 4 inches (23.5 x 10.2 cm)",
    "sfomuseum:issues_held": "Effective:6-15-1964",
    "sfomuseum:media_ids": [
      1527842705
    ],
    "sfomuseum:medium": "paper, ink",
    "sfomuseum:placetype": "object",
    "sfomuseum:subcategory": "Timetable",
    "wof:depicts": [
      1159285335
    ],
    "wof:name": "timetable: Trans-Texas Airways",
    "wof:placetype": "venue"
  },
  "geometry": {"coordinates":[-122.386155,37.616357],"type":"Point"}
}
