{
  "type": "Feature",
  "properties": {
    "date:cessation_lower": "1953-05-27",
    "date:cessation_upper": "1953-05-27",
    "date:inception_lower": "1953-05-27",
    "date:inception_upper": "1953-05-27",
    "iso:country": "VN",
    "millsfield:images": [
      1527829583,
      1527829585
    ],
    "sfomuseum:accession_number": "1994.18.098",
    "sfomuseum:airline": "Pan American World Airways",
    "sfomuseum:category": "Philately",
    "sfomuseum:collection": "Aviation Archive",
    "sfomuseum:continent": "Transpacific",
    "sfomuseum:country": "Vietnam",
    "sfomuseum:creditline": "Purchase",
    "sfomuseum:date": "5/27/1953",
    "sfomuseum:daterange_end": "1953-05-27",
    "sfomuseum:daterange_start": "1953-05-27",
    "sfomuseum:description": "Airmail flight cover commemorating first air mail flight from Saigon to Wake Island; red cachet with text “27-6-1953 / 1ere Liason Aerienne / Saigon San Francisco”; four stamps: red 40c, purple 2$, red 50c, and brown 5$ (Vietnam); four postmarks: \"Saigon-R.P. Viet-Nam 27 5 1953”; backstamp: “Wake Island May 31, 1953 A.M.” with type 1 killer; envelope: white, addressed to Pan American World Airways at Wake Island.",
    "sfomuseum:dimensions": "3 1/2 x 6 1/2 inches (8.9 x 16.5 cm)",
    "sfomuseum:maker": "Pan American World Airways, Inc.",
    "sfomuseum:media_ids": [
      1527829583,
      1527829585
    ],
    "sfomuseum:medium": "ink on paper",
    "sfomuseum:placetype": "object",
    "sfomuseum:subcategory": "Airmail Flight Cover",
    "wof:depicts": [
      1159284989
    ],
    "wof:name": "airmail flight cover: Pan American World Airways, Saigon - Wake Island route",
    "wof:placetype": "venue"
  },
  "geometry": {"coordinates":[-122.386155,37.616357],"type":"Point"}
}
