{
  "type": "Feature",
  "properties": {
    "date:cessation_lower": "1985-01-01",
    "date:cessation_upper": "1985-12-31",
    "date:inception_lower": "1985-01-01",
    "date:inception_upper": "1985-12-31",
    "iso:country": "XX",
    "millsfield:images": [
      1527842387
    ],
    "millsfield:primary_image": 1527842387,
    "sfomuseum:accession_number": "2006.026.066",
    "sfomuseum:airline": "Malaysia Airlines",
    "sfomuseum:category": "Passenger Amenity",
    "sfomuseum:collection": "Aviation Archive",
    "sfomuseum:creditline": "The Henry Steiner Air Sickness Bag Collection",
    "sfomuseum:date": "c. 1985",
    "sfomuseum:daterange_end": "1990-12-31",
    "sfomuseum:daterange_start": "1980-01-01",
    "sfomuseum:description": "White with lower portion comprising parallel bands of red and tan; labeled \"Air Sickness Bag\" across center of front, \"Beg Mabuk Udara\" across center of reverse; \"mas\" printed at top right on both sides; wire closure, flat bottom.",
    "sfomuseum:dimensions": "9 x 5 inches (22.9 x 12.7 cm)",
    "sfomuseum:media_ids": [
      1527842387
    ],
    "sfomuseum:medium": "paper, ink, metal",
    "sfomuseum:placetype": "object",
    "sfomuseum:publication": ": , c. 1985.",
    "sfomuseum:subcategory": "Airsickness Bag",
    "wof:depicts": [
      1159284731
    ],
    "wof:name": "airsickness bag: Malaysia Airlines",
    "wof:placetype": "venue"
  },
  "geometry": {"coordinates":[-122.386155,37.616357],"type":"Point"}
}
