{
  "type": "Feature",
  "properties": {
    "date:cessation_lower": "1939-01-01",
    "date:cessation_upper": "1939-12-31",
    "date:inception_lower": "1939-01-01",
    "date:inception_upper": "1939-12-31",
    "iso:country": "XX",
    "sfomuseum:accession_number": "2000.160.1266",
    "sfomuseum:author": "Ricketts, Victor",
    "sfomuseum:callnumber": "TL712 .R53 1939 SC",
    "sfomuseum:category": "Book",
    "sfomuseum:collection": "Aviation Library",
    "sfomuseum:creditline": "The Tony Bill Aviation Library Collection",
    "sfomuseum:date": "1939",
    "sfomuseum:daterange_end": "1939-12-31",
    "sfomuseum:daterange_start": "1939-01-01",
    "sfomuseum:description": "94 p. : ill., map ; 19 cm.",
    "sfomuseum:medium": "paper, ink",
    "sfomuseum:placetype": "object",
    "sfomuseum:publication": "London: Hurst \u0026 Blackett, 1939.",
    "sfomuseum:publisher": "Hurst \u0026 Blackett",
    "sfomuseum:publisher_location": "London",
    "sfomuseum:subcategory": "Book",
    "sfomuseum:subject": "Flight training.Airplanes Piloting.",
    "wof:name": "Fly with me",
    "wof:placetype": "venue"
  },
  "geometry": {"coordinates":[-122.386155,37.616357],"type":"Point"}
}
