{
  "type": "Feature",
  "properties": {
    "date:cessation_lower": "1996-01-01",
    "date:cessation_upper": "1996-12-31",
    "date:inception_lower": "1996-01-01",
    "date:inception_upper": "1996-12-31",
    "millsfield:images": [
      1746680145
    ],
    "millsfield:images_texts": [
      "EALTLE\nvirgin atlantic"
    ],
    "millsfield:images_texts_ids": [
      1746680145
    ],
    "millsfield:primary_image": 1746680145,
    "sfomuseum:accession_number": "1995.86.02 a k",
    "sfomuseum:airline": "Virgin Atlantic",
    "sfomuseum:category": "Passenger Amenity, Museum",
    "sfomuseum:collection": "Aviation Museum",
    "sfomuseum:continent": "Europe",
    "sfomuseum:country": "England",
    "sfomuseum:creditline": "Gift of Virgin Atlantic Airways",
    "sfomuseum:date": "1996",
    "sfomuseum:daterange_end": "1996-12-31",
    "sfomuseum:daterange_start": "1996-01-01",
    "sfomuseum:description": "Amenity kit issued by Virgin Atlantic for Upper Class, in multiple parts:\ra. black amenity kit cover with red piping, wraparound top zipper closure, printed logo near lower right corner;\rb. cotton bag with drawstring closure, printed \"Upper Class\" on center;\rc.-e. contents of b: nail file, toothbrush, toothpaste;\rf. cologne by Molton Brown;\rg. body lotion by Molton Brown;\rh. bath gel by Molton Brown;\ri. mouthwash by Molton Brown;\rj. box containing earplugs;\rk. sealed in plastic bag, shoe shine cloth.",
    "sfomuseum:dimensions": "4 1/4 x 7 1/4 x 2 inches (10.8 x 18.4 x 5.1 cm)",
    "sfomuseum:medium": "fabric, plastic, cosmetic products, foam, metal, paper, ink",
    "sfomuseum:placetype": "object",
    "sfomuseum:publication": ": , 1996.",
    "sfomuseum:subcategory": "Amenity Kit",
    "wof:depicts": [
      1159285483,
      1159288557
    ],
    "wof:name": "amenity kit: Virgin Atlantic, Upper Class",
    "wof:placetype": "custom",
    "wof:placetype_alt": [
      "object"
    ]
  },
  "geometry": {"coordinates":[-122.386155,37.616357],"type":"Point"}
}
