{
  "type": "Feature",
  "properties": {
    "date:cessation_lower": "1975-01-01",
    "date:cessation_upper": "1975-12-31",
    "date:inception_lower": "1975-01-01",
    "date:inception_upper": "1975-12-31",
    "iso:country": "XX",
    "millsfield:images": [
      1527847943,
      1527847945
    ],
    "sfomuseum:accession_number": "2001.039.160",
    "sfomuseum:airline": "United Airlines",
    "sfomuseum:artist": "Peter Hayward",
    "sfomuseum:category": "Passenger Amenity",
    "sfomuseum:collection": "Aviation Archive",
    "sfomuseum:creditline": "Gift of David A. Abercrombie in memory of Stanley A. Abercrombie",
    "sfomuseum:date": "c. 1975",
    "sfomuseum:daterange_end": "1980-12-31",
    "sfomuseum:daterange_start": "1970-01-01",
    "sfomuseum:description": "Menu issued by United Air Lines; color illustration of Green Street on San Francisco’s Telegraph Hill; menu items include zucchini frittata, beef teriyaki, and seafood Newburg; menu code MCI L/D22-3Z; undated.",
    "sfomuseum:dimensions": "6 1/2 x 5 1/2 inches (16.5 x 14 cm)",
    "sfomuseum:media_ids": [
      1527847943,
      1527847945
    ],
    "sfomuseum:medium": "paper, ink",
    "sfomuseum:placetype": "object",
    "sfomuseum:subcategory": "Menu",
    "wof:depicts": [
      1159285413
    ],
    "wof:name": "menu: United Airlines",
    "wof:placetype": "venue"
  },
  "geometry": {"coordinates":[-122.386155,37.616357],"type":"Point"}
}
