{
  "type": "Feature",
  "properties": {
    "date:cessation_lower": "1992-01-01",
    "date:cessation_upper": "1992-12-31",
    "date:inception_lower": "1992-01-01",
    "date:inception_upper": "1992-12-31",
    "iso:country": "XX",
    "loc:named_authorities": [
      "n80003177"
    ],
    "sfomuseum:accession_number": "2001.106.457",
    "sfomuseum:author": "McIntyre, Ian",
    "sfomuseum:callnumber": "HD9711.E884 A345 1992\r",
    "sfomuseum:category": "Book",
    "sfomuseum:collection": "Aviation Library",
    "sfomuseum:creditline": "Gift of Mark F. Adams Collection",
    "sfomuseum:date": "1992",
    "sfomuseum:date_acquired": "2001-10-18",
    "sfomuseum:daterange_end": "1992-12-31",
    "sfomuseum:daterange_start": "1992-01-01",
    "sfomuseum:description": "xxvi, 312 p. ; 25 cm.",
    "sfomuseum:description_library": "xxvi, 312 p. ; 25 cm.",
    "sfomuseum:medium": "paper, ink",
    "sfomuseum:placetype": "object",
    "sfomuseum:publication": "Westport, CT: Praeger, 1992.",
    "sfomuseum:publisher": "Praeger",
    "sfomuseum:publisher_location": "Westport, CT",
    "sfomuseum:subcategory": "Book",
    "sfomuseum:subject": "Airbus Industrie.\rAircraft industry -- Europe.\rAircraft industry -- United States.\rCompetition, Unfair -- Europe.\rIndustrial policy -- Europe.",
    "wof:name": "Dogfight: the transatlantic battle over Airbus",
    "wof:placetype": "custom",
    "wof:placetype_alt": "object"
  },
  "geometry": {"coordinates":[-122.386155,37.616357],"type":"Point"}
}
