{
  "type": "Feature",
  "properties": {
    "date:cessation_lower": "1988-01-01",
    "date:cessation_upper": "1988-12-31",
    "date:inception_lower": "1988-01-01",
    "date:inception_upper": "1988-12-31",
    "iso:country": "XX",
    "sfomuseum:accession_number": "1999.672.015",
    "sfomuseum:author": "Arend, Geoffrey",
    "sfomuseum:callnumber": "HE9797 .A74 1988",
    "sfomuseum:category": "Book",
    "sfomuseum:collection": "Aviation Library",
    "sfomuseum:creditline": "From the estate of Louis A. Turpen",
    "sfomuseum:date": "c. 1988",
    "sfomuseum:daterange_end": "1993-12-31",
    "sfomuseum:daterange_start": "1983-01-01",
    "sfomuseum:description": "804 p. : ill., ports. ; 30 cm.",
    "sfomuseum:description_library": "804 p. : ill., ports. ; 30 cm.",
    "sfomuseum:medium": "paper, ink",
    "sfomuseum:placetype": "object",
    "sfomuseum:publication": "New York: Air Cargo News, c. 1988.",
    "sfomuseum:publisher": "Air Cargo News",
    "sfomuseum:publisher_location": "New York",
    "sfomuseum:series": "Great airports",
    "sfomuseum:subcategory": "Book",
    "sfomuseum:subject": "Airports History.Airports.",
    "wof:name": "Great airports worldwide",
    "wof:placetype": "custom",
    "wof:placetype_alt": [
      "object"
    ]
  },
  "geometry": {"coordinates":[-122.386155,37.616357],"type":"Point"}
}
