{
  "type": "Feature",
  "properties": {
    "date:cessation_lower": "1964-12-31",
    "date:cessation_upper": "1964-12-31",
    "date:inception_lower": "1964-01-01",
    "date:inception_upper": "1964-01-01",
    "iso:country": "XX",
    "sfomuseum:accession_number": "2000.055.025",
    "sfomuseum:category": "Map / Chart",
    "sfomuseum:collection": "Aviation Archive",
    "sfomuseum:creditline": "Purchase",
    "sfomuseum:date": "1964",
    "sfomuseum:daterange_end": "1964-12-31",
    "sfomuseum:daterange_start": "1964-01-01",
    "sfomuseum:description": "Route map produced by United Air Lines for domestic service routes, titled “Air atlas”; white cover with full color photographic image of a Douglas DC-8 aircraft in flight; fold-out format.",
    "sfomuseum:media_ids": [
      1527844515
    ],
    "sfomuseum:medium": "paper, ink",
    "sfomuseum:placetype": "object",
    "sfomuseum:subcategory": "Route",
    "wof:name": "route map: United Air Lines, domestic routes",
    "wof:placetype": "venue"
  },
  "geometry": {"coordinates":[-122.386155,37.616358],"type":"Point"}
}
