{
  "type": "Feature",
  "properties": {
    "date:cessation_lower": "1964-01-01",
    "date:cessation_upper": "1964-12-31",
    "date:inception_lower": "1964-01-01",
    "date:inception_upper": "1964-12-31",
    "iso:country": "XX",
    "millsfield:images": [
      1527844515
    ],
    "sfomuseum:accession_number": "2000.055.025",
    "sfomuseum:aircraft": "Douglas DC-8",
    "sfomuseum:airline": "United Air Lines",
    "sfomuseum:category": "Map / Chart",
    "sfomuseum:collection": "Aviation Archive",
    "sfomuseum:creditline": "Purchase",
    "sfomuseum:date": "1964",
    "sfomuseum:daterange_end": "1964-12-31",
    "sfomuseum:daterange_start": "1964-01-01",
    "sfomuseum:description": "Route map issued by United Air Lines for domestic service routes, titled “Air atlas”; white cover with full color photographic image of a Douglas DC-8 aircraft in flight; fold-out format.",
    "sfomuseum:dimensions": "6 x 10 1/2 inches (15.2 x 26.7 cm)",
    "sfomuseum:media_ids": [
      1527844515
    ],
    "sfomuseum:medium": "paper, ink",
    "sfomuseum:placetype": "object",
    "sfomuseum:subcategory": "Route",
    "sfomuseum:subject": "Airlines -- Commercial -- United Airlines.\rRoute maps -- United Airlines.\rAirlines -- Routes -- Maps.",
    "wof:depicts": [
      1159285415,
      1159290443
    ],
    "wof:name": "route map: United Air Lines, domestic routes",
    "wof:placetype": "custom"
  },
  "geometry": {"coordinates":[-122.386155,37.616357],"type":"Point"}
}
