{
  "type": "Feature",
  "properties": {
    "date:cessation_lower": "1964-01-01",
    "date:cessation_upper": "1964-12-31",
    "date:inception_lower": "1964-01-01",
    "date:inception_upper": "1964-12-31",
    "iso:country": "XX",
    "millsfield:images": [
      1527844515
    ],
    "millsfield:images_texts": [
      "air atlas\nUNITED\nTHE EXTRA CARE AIRLINE\nUNITED\nN80280\nUNITED"
    ],
    "millsfield:images_texts_ids": [
      1527844515
    ],
    "millsfield:primary_image": 1527844515,
    "sfomuseum:accession_number": "2000.055.025",
    "sfomuseum:aircraft": "Douglas DC-8",
    "sfomuseum:airline": "United Air Lines",
    "sfomuseum:category": "Map / Chart",
    "sfomuseum:collection": "Aviation Archive",
    "sfomuseum:creditline": "Collection of SFO Museum",
    "sfomuseum:date": "1964",
    "sfomuseum:date_acquired": "2000-03-09",
    "sfomuseum:daterange_end": "1964-12-31",
    "sfomuseum:daterange_start": "1964-01-01",
    "sfomuseum:description": "Route map issued by United Air Lines for domestic service routes, titled “Air atlas”; fold-out format; white cover with color photographic image of a Douglas DC-8 aircraft in flight.",
    "sfomuseum:dimensions": "6 x 10 1/2 inches (15.2 x 26.7 cm)",
    "sfomuseum:media_ids": [
      1527844515
    ],
    "sfomuseum:medium": "paper, ink",
    "sfomuseum:placetype": "object",
    "sfomuseum:publication": ": , 1964.",
    "sfomuseum:subcategory": "Route",
    "sfomuseum:subject": "Airlines -- Commercial -- United Airlines.\rRoute maps -- United Airlines.\rAirlines -- Routes -- Maps.",
    "wof:depicts": [
      1159288779,
      1159285415,
      1159290443
    ],
    "wof:name": "route map: United Air Lines, domestic routes",
    "wof:placetype": "custom",
    "wof:placetype_alt": [
      "object"
    ]
  },
  "geometry": {"coordinates":[-122.386155,37.616357],"type":"Point"}
}
