{
  "type": "Feature",
  "properties": {
    "date:cessation_lower": "1968-12-31",
    "date:cessation_upper": "1968-12-31",
    "date:inception_lower": "1968-01-01",
    "date:inception_upper": "1968-01-01",
    "iso:country": "XX",
    "sfomuseum:accession_number": "2005.010.040",
    "sfomuseum:airline": "Pan American World Airways",
    "sfomuseum:author": "Pan American World Airways, inc.",
    "sfomuseum:callnumber": "HE9805.P35 P25 1960",
    "sfomuseum:category": "Book",
    "sfomuseum:collection": "Aviation Library",
    "sfomuseum:creditline": "Gift of the Pan Am Association",
    "sfomuseum:date": "1968",
    "sfomuseum:daterange_end": "1968-12-31",
    "sfomuseum:daterange_start": "1968-01-01",
    "sfomuseum:medium": "paper, ink",
    "sfomuseum:placetype": "object",
    "sfomuseum:publisher": "Pan American World Airways, Inc.",
    "sfomuseum:publisher_location": "s.l.",
    "sfomuseum:subcategory": "Book",
    "sfomuseum:subject": "Airlines -- Commercial -- Pan American Airways -- Aircraft.\rPan American Airways -- Aircraft -- History.",
    "wof:depicts": [
      1159284989
    ],
    "wof:name": "Pan Am's Flying Clippers",
    "wof:placetype": "venue"
  },
  "geometry": {"coordinates":[-122.386155,37.616357],"type":"Point"}
}
