{
  "type": "Feature",
  "properties": {
    "date:cessation_lower":"1993-12-31",
    "date:cessation_upper":"1993-12-31",
    "date:inception_lower":"1993-01-01",
    "date:inception_upper":"1993-01-01",
    "iso:country":"XX",
    "sfomuseum:accession_number":"2004.115.0617",
    "sfomuseum:aircraft":"Boeing 727-200",
    "sfomuseum:airline":"Ansett Australia",
    "sfomuseum:airport":"Sydney (Kingsford Smith) Airport",
    "sfomuseum:category":"Photograph",
    "sfomuseum:collection":"Aviation Archive",
    "sfomuseum:creditline":"Gift of the William Hough Collection",
    "sfomuseum:date":"1993",
    "sfomuseum:daterange_end":"1993-12-31",
    "sfomuseum:daterange_start":"1993-01-01",
    "sfomuseum:description":"Color photographic slide depicting Ansett Airlines of Australia Boeing 727-200 at Sydney Airport (SYD), December 10, 1993; photo taken by William Hough.",
    "sfomuseum:medium":"color slide",
    "sfomuseum:placetype":"object",
    "sfomuseum:subcategory":"Slide",
    "wof:depicts":[
        1159289789,
        1159293593,
        1159289759,
        102557783,
        1159283877
    ],
    "wof:name":"slide: Ansett Airlines of Australia, Boeing 727-200, Sydney Airport (SYD)",
    "wof:placetype":"venue"
},
  "geometry": {"coordinates":[-122.386155,37.616357],"type":"Point"}
}