{
  "type": "Feature",
  "properties": {
    "date:cessation_lower": "1989-01-01",
    "date:cessation_upper": "1989-12-31",
    "date:inception_lower": "1989-01-01",
    "date:inception_upper": "1989-12-31",
    "iso:country": "XX",
    "sfomuseum:accession_number": "99-0167",
    "sfomuseum:author": "Stewart, John",
    "sfomuseum:callnumber": "TL725.3.T7 S83 1989",
    "sfomuseum:category": "Book",
    "sfomuseum:collection": "Aviation Library",
    "sfomuseum:date": "c. 1989",
    "sfomuseum:daterange_end": "1994-12-31",
    "sfomuseum:daterange_start": "1984-01-01",
    "sfomuseum:description": "xiv, 226 p. : ill. ; 25 cm.",
    "sfomuseum:medium": "paper, ink",
    "sfomuseum:placetype": "object",
    "sfomuseum:publisher": "Tab Books",
    "sfomuseum:publisher_location": "Blue Ridge Summit, PA",
    "sfomuseum:series": "Tab practical flying series.",
    "sfomuseum:subcategory": "Book",
    "sfomuseum:subject": "Errors. Airplanes Piloting. Air traffic control United States.",
    "wof:name": "Avoiding common pilot errors: an air traffic controller's view",
    "wof:placetype": "venue"
  },
  "geometry": {"coordinates":[-122.386155,37.616357],"type":"Point"}
}
