{
  "type": "Feature",
  "properties": {
    "date:cessation_lower": "1913-01-01",
    "date:cessation_upper": "1913-12-31",
    "date:inception_lower": "1913-01-01",
    "date:inception_upper": "1913-12-31",
    "iso:country": "XX",
    "loc:subject_headings": [
      "sh85001319"
    ],
    "millsfield:images": [
      1527858299
    ],
    "millsfield:primary_image": 1527858299,
    "sfomuseum:accession_number": "2000.160.0239",
    "sfomuseum:author": "Grahame-White, Claude",
    "sfomuseum:callnumber": "TL547 .G73 1913 SC",
    "sfomuseum:category": "Book",
    "sfomuseum:collection": "Aviation Library",
    "sfomuseum:creditline": "The Tony Bill Aviation Library Collection",
    "sfomuseum:date": "1913",
    "sfomuseum:date_acquired": "1999-05-18",
    "sfomuseum:daterange_end": "1913-12-31",
    "sfomuseum:daterange_start": "1913-01-01",
    "sfomuseum:description": "283 p. front. (port.) illus., plates. 21 cm.",
    "sfomuseum:description_library": "283 p. front. (port.) illus., plates. 21 cm.",
    "sfomuseum:media_ids": [
      1527858299
    ],
    "sfomuseum:medium": "paper, ink",
    "sfomuseum:placetype": "object",
    "sfomuseum:publication": "London: H. Frowde, 1913.",
    "sfomuseum:publisher": "H. Frowde",
    "sfomuseum:publisher_location": "London",
    "sfomuseum:subcategory": "Book",
    "sfomuseum:subject": "Aeronautics.",
    "wof:name": "With the airmen",
    "wof:placetype": "custom",
    "wof:placetype_alt": "object"
  },
  "geometry": {"coordinates":[-122.386155,37.616357],"type":"Point"}
}
