{
  "type": "Feature",
  "properties": {
    "date:cessation_lower": "1997-12-31",
    "date:cessation_upper": "1997-12-31",
    "date:inception_lower": "1997-01-01",
    "date:inception_upper": "1997-01-01",
    "iso:country": "XX",
    "sfomuseum:accession_number": "99-0696",
    "sfomuseum:author": "Davies, R. E. G. (Ronald Edward George)",
    "sfomuseum:callnumber": "HE9815.5.A3 D38 1984",
    "sfomuseum:category": "Book",
    "sfomuseum:collection": "Aviation Library",
    "sfomuseum:date": "1997",
    "sfomuseum:daterange_end": "1997-12-31",
    "sfomuseum:daterange_start": "1997-01-01",
    "sfomuseum:description": "xiv, 698 p. : ill., maps ; 22 cm.",
    "sfomuseum:medium": "paper, ink",
    "sfomuseum:placetype": "object",
    "sfomuseum:publisher": "Paladwr Press",
    "sfomuseum:publisher_location": "McLean, VA",
    "sfomuseum:subcategory": "Book",
    "sfomuseum:subject": "Airlines Latin America History.",
    "wof:name": "Airlines of Latin America since 1919",
    "wof:placetype": "custom"
  },
  "geometry": {"coordinates":[-122.386155,37.616357],"type":"Point"}
}
