{
  "type": "Feature",
  "properties": {
    "date:cessation_lower":"1961-12-31",
    "date:cessation_upper":"1961-12-31",
    "date:inception_lower":"1961-01-01",
    "date:inception_upper":"1961-01-01",
    "iso:country":"XX",
    "sfomuseum:accession_number":"2005.132.066.004",
    "sfomuseum:category":"Scheduling / Ticketing",
    "sfomuseum:collection":"Aviation Archive",
    "sfomuseum:creditline":"Gift of the William Hough Collection",
    "sfomuseum:date":"1961",
    "sfomuseum:daterange_end":"1961-12-31",
    "sfomuseum:daterange_start":"1961-01-01",
    "sfomuseum:description":"Timetable issued by BOAC (British Overseas Airways Corporation), effective June 1, 1961; fifty-eight page double fold-out. The cover is multi-colored, blue at the top and bottom and gray in the center with two white logos. A drawing of the east and west hemispheres in yellow outlined in with two wide red arrows is in the center. The hemispheres are staggered and only partially meet. The company logo is at the top.",
    "sfomuseum:medium":"paper, ink",
    "sfomuseum:placetype":"object",
    "sfomuseum:subcategory":"Timetable",
    "wof:name":"timetable: BOAC (British Overseas Airways Corporation)",
    "wof:placetype":"venue"
},
  "geometry": {"coordinates":[-122.386155,37.616358],"type":"Point"}
}