{
  "type": "Feature",
  "properties": {
    "date:cessation_lower": "1960-01-01",
    "date:cessation_upper": "1960-12-31",
    "date:inception_lower": "1960-01-01",
    "date:inception_upper": "1960-12-31",
    "iso:country": "XX",
    "millsfield:images": [
      1527819439
    ],
    "millsfield:images_texts": [
      "POLAR\nFRENCH\nJET\nFRENCH\nCUISINE\nPROMENADE\nSERVICE\nFASTEST\nDECOR\nLongest\nEXPERIENCE\nFRENCH\nBAR\nPARIS\nJETS\n5,000,000\nRange\nFRENCH\nSERVICE\nDELUXE OR\n11½ JET HOURS\nMILE PILOTS\nCOMFORT\nECONOMY\nVoilà! All jet service is not the same!\nyourself. Fly the Boeing 707 Intercontinental Jet-world's fast-\nStep aboard an Air France Jet-you're suddenly in France.\nFrom your pretty French hostess' welcoming\n\"Bonjour\"\nest, largest, longest-range jetliner now! Fly Air France's new\nto\nPolar Service direct to Paris from the Golden West via Los\nher friendly\n\"Au revoir,\" you're surrounded by the charming\nAngeles. De Luxe and Economy Class accommodations. Los\natmosphere, attentive service and Continental comfort that are\nAngeles-Paris round-trip Economy Fare $740.20. For informa-\nsynonymous only with France. Enjoy this fabulous difference\ntion and reservations see your Travel Agent or call Air France\nAIR FRANCE JET\nWORLD'S IARGEST AIRLINE / WORLD'S MOST PERSONAL SERVICE"
    ],
    "millsfield:images_texts_ids": [
      1527819439
    ],
    "millsfield:primary_image": 1527819439,
    "sfomuseum:accession_number": "2011.001.046.028",
    "sfomuseum:airline": "Air France",
    "sfomuseum:category": "Promotional, Archive",
    "sfomuseum:collection": "Aviation Archive",
    "sfomuseum:creditline": "Gift of Robert Behr",
    "sfomuseum:date": "1960",
    "sfomuseum:date_acquired": "2011-05-25",
    "sfomuseum:daterange_end": "1960-12-31",
    "sfomuseum:daterange_start": "1960-01-01",
    "sfomuseum:description": "Advertisement from May 1960 issue of Sunset magazine promoting Air France, with main caption, “Air France Jet”, and black and white illustrations representing flight crew, landmarks, and services.",
    "sfomuseum:dimensions": "11 x 8 1/4 inches (27.9 x 21 cm)",
    "sfomuseum:media_ids": [
      1527819439
    ],
    "sfomuseum:medium": "paper, ink",
    "sfomuseum:placetype": "object",
    "sfomuseum:publication": ": , 1960.",
    "sfomuseum:subcategory": "Advertisement, 2D",
    "wof:depicts": [
      1360700617,
      1159283627
    ],
    "wof:name": "advertisement: Air France, Sunset",
    "wof:placetype": "custom",
    "wof:placetype_alt": [
      "object"
    ]
  },
  "geometry": {"coordinates":[-122.386155,37.616357],"type":"Point"}
}
