{
  "type": "Feature",
  "properties": {
    "date:cessation_lower": "1985-01-01",
    "date:cessation_upper": "1985-12-31",
    "date:inception_lower": "1985-01-01",
    "date:inception_upper": "1985-12-31",
    "iso:country": "XX",
    "millsfield:images": [
      1527840025
    ],
    "millsfield:primary_image": 1527840025,
    "sfomuseum:accession_number": "2008.108.403",
    "sfomuseum:airline": "Jet America Airlines",
    "sfomuseum:airport": "Chicago O'Hare International Airport",
    "sfomuseum:category": "Scheduling / Ticketing",
    "sfomuseum:collection": "Aviation Archive",
    "sfomuseum:creditline": "Gift of the William Hough Collection",
    "sfomuseum:date": "1985",
    "sfomuseum:daterange_end": "1985-12-31",
    "sfomuseum:daterange_start": "1985-01-01",
    "sfomuseum:description": "Timetable issued by Jet America Airlines, effective March 18, 1985; four page double-sided fold-out. The cover is silver with blue lettering; text is “Introducing New Service. The company logo is at the top and a route map at the bottom.",
    "sfomuseum:dimensions": "9 x 4 inches (22.9 x 10.2 cm)",
    "sfomuseum:media_ids": [
      1527840025
    ],
    "sfomuseum:medium": "paper, ink",
    "sfomuseum:placetype": "object",
    "sfomuseum:publication": ": , 1985.",
    "sfomuseum:subcategory": "Timetable",
    "sfomuseum:subject": "Airlines -- Commercial -- Jet America",
    "wof:depicts": [
      1159284579,
      102533631
    ],
    "wof:name": "timetable: Jet America Airlines",
    "wof:placetype": "venue"
  },
  "geometry": {"coordinates":[-122.386155,37.616357],"type":"Point"}
}
