{
  "type": "Feature",
  "properties": {
    "date:cessation_lower": "1966-12-31",
    "date:cessation_upper": "1966-12-31",
    "date:inception_lower": "1966-01-01",
    "date:inception_upper": "1966-01-01",
    "iso:country": "XX",
    "sfomuseum:accession_number": "2006.010.645 a d",
    "sfomuseum:category": "Passenger Amenity",
    "sfomuseum:collection": "Aviation Archive",
    "sfomuseum:creditline": "Gift of the William Hough Collection",
    "sfomuseum:date": "1966",
    "sfomuseum:daterange_end": "1966-12-31",
    "sfomuseum:daterange_start": "1966-01-01",
    "sfomuseum:description": "Flight information packet produced by Continental Airlines, titled \"Welcome Aboard\", comprising\ra. white folder with pockets; full color photographic image of flight attendants in red hats at the top of a boarding staircase; bi-fold format; route map on interior\rb. comment card; white card with illustration of pleased and displeased faces; bi-fold format; sealed\rc. stationery envelope; airline servicemark on flap; sealed\rd. letterhead; white single-sided sheet with airline servicemark at top center",
    "sfomuseum:media_ids": [
      1527854549, 
      1527854551, 
      1527854555, 
      1527819553, 
      1527819555, 
      1527819557, 
      1527819551
    ],
    "sfomuseum:medium": "paper, ink",
    "sfomuseum:placetype": "object",
    "sfomuseum:subcategory": "In-flight Information",
    "wof:name": "flight information packet: Continental Airlines",
    "wof:placetype": "venue"
  },
  "geometry": {"coordinates":[-122.386155,37.616358],"type":"Point"}
}
