{
  "type": "Feature",
  "properties": {
    "date:cessation_lower": "1949-12-31",
    "date:cessation_upper": "1949-12-31",
    "date:inception_lower": "1940-01-01",
    "date:inception_upper": "1940-01-01",
    "iso:country": "XX",
    "sfomuseum:accession_number": "2010.188.015",
    "sfomuseum:category": "Promotional",
    "sfomuseum:collection": "Aviation Museum",
    "sfomuseum:creditline": "Gift of Thomas G. Dragges",
    "sfomuseum:date": "1940s",
    "sfomuseum:daterange_end": "1949-12-31",
    "sfomuseum:daterange_start": "1940-01-01",
    "sfomuseum:description": "Full color cardboard stand-up sign produced by Transcontinental \u0026 Western Air (TWA); image of TWA flight attendant in blue uniform with hat and skirt, right arm raised in salute; “Route of the Stratoliners” in navy blue along bottom, “TWA” in red and “The Transcontinental Airline” in navy blue on right side; triangular cardboard stand support on reverse.",
    "sfomuseum:media_ids": [
      1527858267
    ],
    "sfomuseum:medium": "cardboard, ink",
    "sfomuseum:placetype": "object",
    "sfomuseum:subcategory": "Advertisement, 3D",
    "wof:name": "stand-up counter sign: Transcontinental \u0026 Western Air (TWA)",
    "wof:placetype": "venue"
  },
  "geometry": {"coordinates":[-122.386155,37.616358],"type":"Point"}
}
