{
  "type": "Feature",
  "properties": {
    "date:cessation_lower": "1949-09-26",
    "date:cessation_upper": "1949-09-26",
    "date:inception_lower": "1949-09-26",
    "date:inception_upper": "1949-09-26",
    "iso:country": "XX",
    "millsfield:images": [
      1729565693,
      1729565695,
      1729565697
    ],
    "sfomuseum:accession_number": "2000.126.003",
    "sfomuseum:aircraft": "Lockheed L-049 Constellation",
    "sfomuseum:airline": "TWA (Trans World Airlines)",
    "sfomuseum:category": "Promotional",
    "sfomuseum:collection": "Aviation Archive",
    "sfomuseum:creditline": "Gift of Jane Glickman Cavala",
    "sfomuseum:date": "9/26/1949",
    "sfomuseum:daterange_end": "1949-09-26",
    "sfomuseum:daterange_start": "1949-09-26",
    "sfomuseum:description": "Passenger flight record and postcard issued by TWA (Trans World Airlines); color photographic image on cover depicting Lockheed L-049 Constellation; Flight 12, September 26, 1949 handwritten in pencil; reverse side addressed to Mr. and Mrs. [...], Oakland, California.",
    "sfomuseum:dimensions": "3 3/4 x 7 inches (9.5 x 17.8 cm)",
    "sfomuseum:medium": "ink on paper",
    "sfomuseum:placetype": "object",
    "sfomuseum:subcategory": "Souvenir Certificate",
    "wof:depicts": [
      1159285393,
      1159291095
    ],
    "wof:name": "souvenir passenger flight card: TWA (Trans World Airlines), Lockheed L-049 Constellation",
    "wof:placetype": "venue"
  },
  "geometry": {"coordinates":[-122.386155,37.616357],"type":"Point"}
}
