{
  "type": "Feature",
  "properties": {
    "date:cessation_lower": "1962-12-31",
    "date:cessation_upper": "1962-12-31",
    "date:inception_lower": "1962-01-01",
    "date:inception_upper": "1962-01-01",
    "iso:country": "XX",
    "sfomuseum:accession_number": "2011.032.0765",
    "sfomuseum:artist": "Marshall Moxom",
    "sfomuseum:category": "Photograph",
    "sfomuseum:collection": "Aviation Archive",
    "sfomuseum:creditline": "Transfer",
    "sfomuseum:date": "1962",
    "sfomuseum:daterange_end": "1962-12-31",
    "sfomuseum:daterange_start": "1962-01-01",
    "sfomuseum:description": "Black and white photographic negative depicting official portrait of Emmett Smith against gray background; San Francisco International Airport (SFO); photo taken by Marshall Moxom on May 15, 1962.",
    "sfomuseum:media_ids": [
      1527823049
    ],
    "sfomuseum:medium": "negative",
    "sfomuseum:placetype": "object",
    "sfomuseum:subcategory": "Negative",
    "wof:name": "negative: San Francisco International Airport (SFO), Emmett Smith",
    "wof:placetype": "venue"
  },
  "geometry": {"coordinates":[-122.386155,37.616358],"type":"Point"}
}
