{
  "type": "Feature",
  "properties": {
    "date:cessation_lower":"1960-12-31",
    "date:cessation_upper":"1960-12-31",
    "date:inception_lower":"1960-01-01",
    "date:inception_upper":"1960-01-01",
    "iso:country":"XX",
    "sfomuseum:accession_number":"2011.032.0563",
    "sfomuseum:artist":"Marshall Moxom",
    "sfomuseum:category":"Photograph",
    "sfomuseum:collection":"Aviation Archive",
    "sfomuseum:creditline":"Transfer",
    "sfomuseum:date":"1960",
    "sfomuseum:daterange_end":"1960-12-31",
    "sfomuseum:daterange_start":"1960-01-01",
    "sfomuseum:description":"From attached handwritten note: \u201c03785 / 4-12-60 / ballpark dedication opening (bay aviation helicopter) / P. O. Comm. / taken by: Moxom\u201d. Black and white photographic negative depicting helicopter in ascent over San Francisco Bay, April 12, 1960; crowd of people in foreground facing away from camera toward helicopter, with one woman facing camera; cropped view of Bay Bridge in background.",
    "sfomuseum:medium":"negative",
    "sfomuseum:placetype":"object",
    "sfomuseum:subcategory":"Negative",
    "wof:name":"negative: SFO Helicopter Airlines, downtown San Francisco heliport",
    "wof:placetype":"venue"
},
  "geometry": {"coordinates":[-122.386155,37.616358],"type":"Point"}
}