{
  "type": "Feature",
  "properties": {
    "date:cessation_lower": "1968-12-31",
    "date:cessation_upper": "1968-12-31",
    "date:inception_lower": "1968-01-01",
    "date:inception_upper": "1968-01-01",
    "iso:country": "XX",
    "sfomuseum:accession_number": "2011.032.1857",
    "sfomuseum:category": "Photograph",
    "sfomuseum:collection": "Aviation Archive",
    "sfomuseum:creditline": "Transfer",
    "sfomuseum:date": "1968",
    "sfomuseum:daterange_end": "1968-12-31",
    "sfomuseum:daterange_start": "1968-01-01",
    "sfomuseum:description": "From attached handwritten note: “6-26-68 / Airport Terminal”. Black and white photographic print depicting view down jetway to door of Pacific Southwest Airlines (PSA) airplane; construction debris visible in jetway; photo overexposed; San Francisco International Airport (SFO); photograph taken on June 26, 1968.",
    "sfomuseum:media_ids": [
      1527826497
    ],
    "sfomuseum:medium": "photograph",
    "sfomuseum:placetype": "object",
    "sfomuseum:subcategory": "Print, Photograph",
    "wof:name": "photograph: San Francisco International Airport (SFO), Pacific Southwest Airlines (PSA) jetway and airplane",
    "wof:placetype": "venue"
  },
  "geometry": {"coordinates":[-122.386155,37.616358],"type":"Point"}
}
