{
  "type": "Feature",
  "properties": {
    "date:cessation_lower": "1950-01-01",
    "date:cessation_upper": "1950-12-31",
    "date:inception_lower": "1950-01-01",
    "date:inception_upper": "1950-12-31",
    "iso:country": "XX",
    "millsfield:exhibition_ids": [
      1159160345
    ],
    "millsfield:images": [
      1527853497
    ],
    "millsfield:images_texts": [
      "-TWA\nTRANS WORLD AIRLINE"
    ],
    "millsfield:images_texts_ids": [
      1527853497
    ],
    "millsfield:on_view": 0,
    "millsfield:primary_image": 1527853497,
    "sfomuseum:accession_number": "2002.046.001",
    "sfomuseum:airline": "TWA (Trans World Airlines)",
    "sfomuseum:category": "Promotional, Museum",
    "sfomuseum:collection": "Aviation Museum",
    "sfomuseum:creditline": "Gift of Howard and Midge East",
    "sfomuseum:date": "c. 1950",
    "sfomuseum:daterange_end": "1955-12-31",
    "sfomuseum:daterange_start": "1945-01-01",
    "sfomuseum:description": "Airline bag issued by TWA (Trans World Airlines); tan background with red logotype both sides; brown piping with top zipper closure and two handles; four metal feet on bottom.\r",
    "sfomuseum:dimensions": "10 x 16 x 7 inches (25.4 x 40.6 x 17.8 cm)",
    "sfomuseum:exhibition_ids": [
      1206
    ],
    "sfomuseum:media_ids": [
      1527853497
    ],
    "sfomuseum:medium": "fabric, metal, leather, cardboard, ink",
    "sfomuseum:placetype": "object",
    "sfomuseum:publication": ": , c. 1950.",
    "sfomuseum:subcategory": "Airline Bag",
    "wof:depicts": [
      1159285393,
      1159287531
    ],
    "wof:name": "airline bag: TWA (Trans World Airlines)",
    "wof:placetype": "custom",
    "wof:placetype_alt": [
      "object"
    ]
  },
  "geometry": {"coordinates":[-122.386155,37.616357],"type":"Point"}
}
