{
  "type": "Feature",
  "properties": {
    "date:cessation_lower": "1955-12-31",
    "date:cessation_upper": "1955-12-31",
    "date:inception_lower": "1945-01-01",
    "date:inception_upper": "1945-01-01",
    "iso:country": "XX",
    "millsfield:images": [
      1527853497
    ],
    "sfomuseum:accession_number": "2002.046.001",
    "sfomuseum:airline": "TWA (Trans World Airlines)",
    "sfomuseum:category": "Promotional",
    "sfomuseum:collection": "Aviation Museum",
    "sfomuseum:creditline": "Gift of Howard and Midge East",
    "sfomuseum:date": "c. 1950",
    "sfomuseum:daterange_end": "1955-12-31",
    "sfomuseum:daterange_start": "1945-01-01",
    "sfomuseum:description": "Tan canvas bag with brown piping; red \"TWA\" initials with feathered arrow bisecting letters, followed by \"Trans World Airline\"; two handles and zipper closure at top with brown tabs on ends; four metallic rivets on bottom.\r",
    "sfomuseum:media_ids": [
      1527853497
    ],
    "sfomuseum:medium": "fabric, metal, leather, cardboard, pigment",
    "sfomuseum:placetype": "object",
    "sfomuseum:subcategory": "Airline Bag",
    "wof:depicts": [
      1159285393
    ],
    "wof:name": "airline bag: TWA (Trans World Airlines)",
    "wof:placetype": "venue"
  },
  "geometry": {"coordinates":[-122.386155,37.616357],"type":"Point"}
}
