{
  "type": "Feature",
  "properties": {
    "date:cessation_lower": "1982-01-01",
    "date:cessation_upper": "1982-12-31",
    "date:inception_lower": "1982-01-01",
    "date:inception_upper": "1982-12-31",
    "iso:country": "XX",
    "millsfield:images": [
      1527849213
    ],
    "millsfield:images_texts": [
      "Sky West\nAirlines\nQuick Reference Schedule\nEffective January 1, 1982\nFLAGSTAFF\nTo Phoenix\n8:10a\n11:40a\n1:55p\n4:30p\nTo Page\n1:50p\n7450\nSTPS\n8:50a\n12:22p\n2:30р\n5:05p\n2:35p\n8:20p\n517\n614\n616\n618\n615\n619\nDaily\nX67\nDaily\nDaly\nTo Flagstaff\n10:45a\n12:50p\n3:35p\n6:50p\nTo Page\n12:50p\n6:50р\nTo Phoenix\n7:25a\n12:45p\nTo Flagstaff\n7:25a\n12:45p\nPHOENIX\nESDO\n4:15p\n2:35p\n8:20p\n8:50a\n2:30p\n8:00a\n1:30p\n611\n615\n619\nX67\nBEF\n615\n619\nDaily\nDaily\nPAGE\n616\n612\n616\nDaily\nDaily\nBERK\nM/N\n0000\nN/M\nFor information and reservations call our\ntravel agent or dial toll free\n1-800-453-9417\nSKIES"
    ],
    "millsfield:images_texts_ids": [
      1527849213
    ],
    "millsfield:primary_image": 1527849213,
    "sfomuseum:accession_number": "2002.135.026.002",
    "sfomuseum:airline": "SkyWest Airlines",
    "sfomuseum:category": "Scheduling / Ticketing",
    "sfomuseum:collection": "Aviation Archive",
    "sfomuseum:creditline": "Gift of Thomas G. Dragges",
    "sfomuseum:date": "1982",
    "sfomuseum:date_acquired": "2022-04-18",
    "sfomuseum:daterange_end": "1982-12-31",
    "sfomuseum:daterange_start": "1982-01-01",
    "sfomuseum:description": "Quick reference schedule issued by SkyWest Airlines for service to and from Flagstaff, Phoenix, and Page, effective January 1, 1982; single page schedule.",
    "sfomuseum:dimensions": "9 1/4 x 4 inches (23.5 x 10.2 cm)",
    "sfomuseum:media_ids": [
      1527849213
    ],
    "sfomuseum:medium": "paper, ink",
    "sfomuseum:placetype": "object",
    "sfomuseum:publication": ": , 1982.",
    "sfomuseum:subcategory": "Timetable",
    "wof:depicts": [
      1159285179,
      1159288685
    ],
    "wof:name": "timetable: Sky West Airlines, quick reference",
    "wof:placetype": "custom",
    "wof:placetype_alt": "object"
  },
  "geometry": {"coordinates":[-122.386155,37.616357],"type":"Point"}
}
