{
  "type": "Feature",
  "properties": {
    "date:cessation_lower": "1985-01-01",
    "date:cessation_upper": "1985-12-31",
    "date:inception_lower": "1985-01-01",
    "date:inception_upper": "1985-12-31",
    "iso:country": "XX",
    "millsfield:images": [
      1729565785,
      1729565787
    ],
    "millsfield:images_texts": [
      "TWA\n:..\nTRANS WORLD\n...\n10",
      "TWA-TRANS WORLD AIRLINES\nBoeing 767\nEntering service in 1982, TWA's advanced-technology 767\nfeatures\ncomfortable twin-aisle\nseating, more\noverhead\nstorge space, plus in-flight audio and video entertainment.\nPhoto courtesv Trans World Airlines\nPublished by Aviation World, Inc., P.O. Box 188, Bethel, Conn. 06801 U.S.A.\nB-033\n82481-D\npost card\n20011082•1.19"
    ],
    "millsfield:images_texts_ids": [
      1729565785,
      1729565787
    ],
    "millsfield:primary_image": 1729565785,
    "sfomuseum:accession_number": "2001.082.119",
    "sfomuseum:aircraft": "Boeing 767",
    "sfomuseum:airline": "TWA (Trans World Airlines)",
    "sfomuseum:category": "Philately",
    "sfomuseum:collection": "Aviation Archive",
    "sfomuseum:creditline": "Gift of George Gayuski ",
    "sfomuseum:date": "c. 1985",
    "sfomuseum:date_acquired": "2001-12-18",
    "sfomuseum:daterange_end": "1990-12-31",
    "sfomuseum:daterange_start": "1980-01-01",
    "sfomuseum:description": "Postcard with color photographic image of TWA (Trans World Airlines) Boeing 767 in flight over clouds; text on reverse, “Entering service in 1982, TWA’s advanced-technology 767 features comforatble twin-aisle seating, more overhead storge [sic] space, plus in-flight audio and video entertainment”; unmailed.",
    "sfomuseum:dimensions": "3 1/2 x 5 1/2 inches (8.9 x 14 cm)",
    "sfomuseum:maker": "Trans World Airlines",
    "sfomuseum:medium": "paper, ink",
    "sfomuseum:placetype": "object",
    "sfomuseum:publication": ": , c. 1985.",
    "sfomuseum:subcategory": "Postcard",
    "wof:depicts": [
      1159287531,
      1159289949,
      1159285393,
      1159293593
    ],
    "wof:name": "postcard: TWA (Trans World Airlines), Boeing 767",
    "wof:placetype": "custom",
    "wof:placetype_alt": "object"
  },
  "geometry": {"coordinates":[-122.386155,37.616357],"type":"Point"}
}
