{
  "type": "Feature",
  "properties": {
    "date:cessation_lower":"1942-12-31",
    "date:cessation_upper":"1942-12-31",
    "date:inception_lower":"1942-01-01",
    "date:inception_upper":"1942-01-01",
    "iso:country":"XX",
    "sfomuseum:accession_number":"2002.113.197 ",
    "sfomuseum:airline":"Transcontinental & Western Air  (TWA (Trans World Airlines))",
    "sfomuseum:category":"Photograph",
    "sfomuseum:collection":"Aviation Archive",
    "sfomuseum:creditline":"Gift of TWA Clipped Wings International",
    "sfomuseum:date":"1942",
    "sfomuseum:daterange_end":"1942-12-31",
    "sfomuseum:daterange_start":"1942-01-01",
    "sfomuseum:description":"Caption for photograph 2002.113.197; \"Ida Staggers, Chief Hostess for Transcontinental & Western Air, Inc., has 175 air hostesses under her command . . . . \"",
    "sfomuseum:medium":"photograph",
    "sfomuseum:placetype":"object",
    "sfomuseum:subcategory":"Print, Photograph",
    "wof:depicts":[
        1159285395
    ],
    "wof:name":"photograph: Transcontinental & Western Air (TWA), Ida Staggers with 1942 graduating class",
    "wof:placetype":"venue"
},
  "geometry": {"coordinates":[-122.386155,37.616357],"type":"Point"}
}