{
  "type": "Feature",
  "properties": {
    "date:cessation_lower": "1936-01-01",
    "date:cessation_upper": "1936-12-31",
    "date:inception_lower": "1936-01-01",
    "date:inception_upper": "1936-12-31",
    "iso:country": "XX",
    "sfomuseum:accession_number": "2002.113.331",
    "sfomuseum:airline": "Transcontinental \u0026 Western Air",
    "sfomuseum:category": "Photograph",
    "sfomuseum:collection": "Aviation Archive",
    "sfomuseum:creditline": "Gift of TWA Clipped Wings International",
    "sfomuseum:date": "c. 1936",
    "sfomuseum:daterange_end": "1941-12-31",
    "sfomuseum:daterange_start": "1931-01-01",
    "sfomuseum:description": "Four separate shots glued to single sheet of paper; top left is of mother (Ruth Rhodes) sitting next to child with doll in sleeping berth, TWA in-flight blanket visible; top right photo shows Diana Graves kneeling next to Rhodes and smiling baby in sleeping berth; bottom left is of Graves giving baby a bottle while mother watches; bottom right photo is of Graves offering an openmouthed baby a bottle ",
    "sfomuseum:dimensions": "8 x 10 inches (20.3 x 25.4 cm)",
    "sfomuseum:maker": "TWA Municipal Airport, Advertising Department",
    "sfomuseum:medium": "photograph",
    "sfomuseum:placetype": "object",
    "sfomuseum:subcategory": "Print, Photograph",
    "wof:depicts": [
      1159285395
    ],
    "wof:name": "photographs: Transcontinental \u0026 Western Air (TWA), air hostess with mother and baby in sleeping berth",
    "wof:placetype": "venue"
  },
  "geometry": {"coordinates":[-122.386155,37.616357],"type":"Point"}
}
