{
  "type": "Feature",
  "properties": {
    "date:cessation_lower": "1996-01-01",
    "date:cessation_upper": "1996-12-31",
    "date:inception_lower": "1996-01-01",
    "date:inception_upper": "1996-12-31",
    "iso:country": "NL",
    "millsfield:images": [
      1527845757
    ],
    "millsfield:images_texts": [
      "0.б.\nKLM\n24 hours a day, 7 days a week\n+31-20-4747 747,\ncall KLM Amsterdam\nreservations\nWorld timetable\nMarch 31, 1996 - October 26, 1996\nFly World Business Class"
    ],
    "millsfield:images_texts_ids": [
      1527845757
    ],
    "millsfield:primary_image": 1527845757,
    "sfomuseum:accession_number": "1996.07.14 a",
    "sfomuseum:airline": "KLM (Royal Dutch Airlines)",
    "sfomuseum:category": "Scheduling / Ticketing",
    "sfomuseum:collection": "Aviation Archive",
    "sfomuseum:continent": "Europe",
    "sfomuseum:country": "Netherlands",
    "sfomuseum:creditline": "Gift of KLM Royal Dutch Airlines",
    "sfomuseum:date": "1996",
    "sfomuseum:date_acquired": "1998-02-23",
    "sfomuseum:daterange_end": "1996-12-31",
    "sfomuseum:daterange_start": "1996-01-01",
    "sfomuseum:description": "World timetable issued by KLM (Royal Dutch Airlines), effective March 31, 1996 through October 26, 1996; fold-out schedule; blue cover with duotone photographic image of blue sky with woman sleeping in airplane seat.",
    "sfomuseum:dimensions": "7 3/4 x 4 1/4 inches (19.7 x 10.8 cm)",
    "sfomuseum:media_ids": [
      1527845757
    ],
    "sfomuseum:medium": "paper, ink",
    "sfomuseum:placetype": "object",
    "sfomuseum:publication": ": , 1996.",
    "sfomuseum:subcategory": "Timetable",
    "wof:depicts": [
      1159284613,
      1159287541
    ],
    "wof:name": "timetable: KLM (Royal Dutch Airlines)",
    "wof:placetype": "custom",
    "wof:placetype_alt": "object"
  },
  "geometry": {"coordinates":[-122.386155,37.616357],"type":"Point"}
}
