{
  "type": "Feature",
  "properties": {
    "date:cessation_lower": "1939-12-31",
    "date:cessation_upper": "1939-12-31",
    "date:inception_lower": "1939-01-01",
    "date:inception_upper": "1939-01-01",
    "iso:country": "XX",
    "sfomuseum:accession_number": "2013.149.065",
    "sfomuseum:category": "Promotional",
    "sfomuseum:collection": "Aviation Archive",
    "sfomuseum:creditline": "Gift of Marjorie Pease Wilson, in memory of Kathleen Hitchcock",
    "sfomuseum:date": "1939",
    "sfomuseum:daterange_end": "1939-12-31",
    "sfomuseum:daterange_start": "1939-01-01",
    "sfomuseum:description": "Event program produced by Pan American Airways System for christening ceremonies for California Clipper at Treasure Island, San Francisco, dated Tuesday, April 25, 1939; white cover with blue text; interior contents: program, names for attendees at Speakers’ stand, and special notice.",
    "sfomuseum:media_ids": [
      1527854351, 
      1527854353
    ],
    "sfomuseum:medium": "paper, ink",
    "sfomuseum:placetype": "object",
    "sfomuseum:subcategory": "Event Program / Invitation",
    "wof:name": "event program: Pan American Airways System, Christening ceremonies, California Clipper",
    "wof:placetype": "venue"
  },
  "geometry": {"coordinates":[-122.386155,37.616358],"type":"Point"}
}
