{
  "type": "Feature",
  "properties": {
    "date:cessation_lower": "1941-01-01",
    "date:cessation_upper": "1941-12-31",
    "date:inception_lower": "1941-01-01",
    "date:inception_upper": "1941-12-31",
    "iso:country": "XX",
    "millsfield:images": [
      1527818345,
      1527818347
    ],
    "millsfield:primary_image": 1527818345,
    "sfomuseum:accession_number": "2009.175.114 a b",
    "sfomuseum:airline": "Pan American Airways",
    "sfomuseum:category": "Photograph",
    "sfomuseum:collection": "Aviation Archive",
    "sfomuseum:creditline": "Gift of Richard McLean",
    "sfomuseum:date": "c. 1941",
    "sfomuseum:date_acquired": "2010-03-03",
    "sfomuseum:daterange_end": "1946-12-31",
    "sfomuseum:daterange_start": "1936-01-01",
    "sfomuseum:description": "a. Digital scan of photograph, depicting black and white image of male employee of Pan American Airways raising United States flag at base on Guam.\rb. Digital scan of reverse, with printed description of photograph and credit attributed to International News Photo; original object housed in donor file titled “Guam.”",
    "sfomuseum:dimensions": "dimensions of original object",
    "sfomuseum:media_ids": [
      1527818345,
      1527818347
    ],
    "sfomuseum:medium": "digital file",
    "sfomuseum:placetype": "object",
    "sfomuseum:publication": ": , c. 1941.",
    "sfomuseum:subcategory": "Digital Image",
    "wof:depicts": [
      1159284991,
      1159286839
    ],
    "wof:name": "photograph: Pan American Airways, Guam [digital image]",
    "wof:placetype": "custom",
    "wof:placetype_alt": "object"
  },
  "geometry": {"coordinates":[-122.386155,37.616357],"type":"Point"}
}
