{
  "type": "Feature",
  "properties": {
    "date:cessation_lower": "1930-12-01",
    "date:cessation_upper": "1930-12-31",
    "date:inception_lower": "1930-09-01",
    "date:inception_upper": "1930-09-30",
    "iso:country": "XX",
    "sfomuseum:accession_number": "2010.282.109",
    "sfomuseum:airline": "Transcontinental \u0026 Western Air",
    "sfomuseum:category": "Insignia",
    "sfomuseum:collection": "Aviation Museum",
    "sfomuseum:creditline": "Gift of Edwin I. Power, Jr. and Linda L. Liscom",
    "sfomuseum:date": "late 1930s",
    "sfomuseum:date_acquired": "2011-01-28",
    "sfomuseum:daterange_end": "1939-12-31",
    "sfomuseum:daterange_start": "1937-01-01",
    "sfomuseum:description": "Flight officer hat badge issued by Transcontinental \u0026 Western Air (TWA); gold two wings with profile of man wearing feathered headdress and logo on center and “Transcontinental \u0026 Western Air”; two posts with screw-backs on back.",
    "sfomuseum:dimensions": "1 3/4 x 2 1/2 x 1/2 inches (4.4 x 6.4 x 1.3 cm)",
    "sfomuseum:medium": "metal",
    "sfomuseum:placetype": "object",
    "sfomuseum:publication": ": , late 1930s.",
    "sfomuseum:subcategory": "Hat Badge, Flight Crew",
    "wof:depicts": [
      1159285395,
      1159287531
    ],
    "wof:name": "flight officer cap badge: Transcontinental \u0026 Western Air (TWA)",
    "wof:placetype": "venue"
  },
  "geometry": {"coordinates":[-122.386155,37.616357],"type":"Point"}
}
