{
  "type": "Feature",
  "properties": {
    "date:cessation_lower":"1963-12-31",
    "date:cessation_upper":"1963-12-31",
    "date:inception_lower":"1937-01-01",
    "date:inception_upper":"1937-01-01",
    "iso:country":"XX",
    "sfomuseum:accession_number":"2010.282.109",
    "sfomuseum:airline":"Transcontinental & Western Air  (TWA (Trans World Airlines))",
    "sfomuseum:category":"Insignia",
    "sfomuseum:collection":"Aviation Museum",
    "sfomuseum:creditline":"Gift of Edwin I. Power, Jr. and Linda L. Liscom",
    "sfomuseum:date":"late 1930s-c. 1958",
    "sfomuseum:daterange_end":"1963-12-31",
    "sfomuseum:daterange_start":"1937-01-01",
    "sfomuseum:description":"Flight officer hat badge issued by Transcontinental & Western Air (TWA); gold two wings with large relief of an American Indian and logo on center, raised \u201cTranscontinental & Western Air\u201d on center and \u201cInc.\u201d below; stamped \u201c51\u201d on back, two posts with screw-backs on back.\r\rGold profile of man wearing feathered headdress; small raised \u201cTranscontinental & Western Air\u201d on two wings; raised design and \u201cInc\u201d below; two screwbacks on reverse; stamped \u201c51\u201d on back.",
    "sfomuseum:medium":"metal",
    "sfomuseum:placetype":"object",
    "sfomuseum:subcategory":"Hat Badge, Flight Crew",
    "wof:depicts":[
        1159285395
    ],
    "wof:name":"flight officer cap badge: Transcontinental & Western Air (TWA)",
    "wof:placetype":"venue"
},
  "geometry": {"coordinates":[-122.386155,37.616357],"type":"Point"}
}