{
  "type": "Feature",
  "properties": {
    "date:cessation_lower": "2002-01-01",
    "date:cessation_upper": "2002-12-31",
    "date:inception_lower": "2002-01-01",
    "date:inception_upper": "2002-12-31",
    "iso:country": "XX",
    "millsfield:images": [
      1527846317,
      1527846321
    ],
    "millsfield:primary_image": 1527846317,
    "sfomuseum:accession_number": "2006.059.307.111",
    "sfomuseum:airline": "United Airlines",
    "sfomuseum:category": "Passenger Amenity",
    "sfomuseum:collection": "Aviation Archive",
    "sfomuseum:creditline": "Gift of the Paul Edward Fair Estate",
    "sfomuseum:date": "2002",
    "sfomuseum:date_acquired": "2006-10-19",
    "sfomuseum:daterange_end": "2002-12-31",
    "sfomuseum:daterange_start": "2002-01-01",
    "sfomuseum:description": "Menu issued by United Airlines, Los Angeles - Auckland / Sydney and San Francisco - Sydney routes; color photographic image of olives in a bowl; menu items include beef tenderloin Hollandaise, stir-fried shrimp, and potato and bacon chowder; menu number: 290C003-1 LAX-AKL/SYD SFO-SYD (LD83-S89-B87); class: Business; date: 3/02.",
    "sfomuseum:dimensions": "9 3/4 x 5 1/2 inches (24.8 x 14 cm)",
    "sfomuseum:media_ids": [
      1527846317,
      1527846321
    ],
    "sfomuseum:medium": "paper, ink",
    "sfomuseum:placetype": "object",
    "sfomuseum:publication": ": , 2002.",
    "sfomuseum:subcategory": "Menu",
    "wof:depicts": [
      1159285413,
      1159288779
    ],
    "wof:name": "menu: United Airlines, Business Class",
    "wof:placetype": "custom",
    "wof:placetype_alt": "object"
  },
  "geometry": {"coordinates":[-122.386155,37.616357],"type":"Point"}
}
