{
  "type": "Feature",
  "properties": {
    "date:cessation_lower":"1957-12-31",
    "date:cessation_upper":"1957-12-31",
    "date:inception_lower":"1957-01-01",
    "date:inception_upper":"1957-01-01",
    "iso:country":"XX",
    "sfomuseum:accession_number":"2012.149.1816",
    "sfomuseum:category":"Philately",
    "sfomuseum:collection":"Aviation Archive",
    "sfomuseum:creditline":"Gift of the Captain John B. Russell Family",
    "sfomuseum:date":"02/21/1957",
    "sfomuseum:daterange_end":"1957-02-21",
    "sfomuseum:daterange_start":"1957-02-21",
    "sfomuseum:description":"Airmail flight cover, Pan American World Airways; black cachet at left depicting Statue of Liberty and tropical scene with text, \u201cFirst Flight / Nassau - New York / Pan American\u201d; postmarked February 21, 1957 in Nassau, Bahamas with 6-cent postage stamp; backstamp: February 21, 1957 in New York; addressed to Oscar H. Fatout.",
    "sfomuseum:medium":"paper, ink",
    "sfomuseum:placetype":"object",
    "sfomuseum:subcategory":"Airmail Flight Cover",
    "wof:name":"airmail flight cover: Pan American World Airways, Nassau - New York route",
    "wof:placetype":"venue"
},
  "geometry": {"coordinates":[-122.386155,37.616358],"type":"Point"}
}