{
  "type": "Feature",
  "properties": {
    "date:cessation_lower": "1955-01-01",
    "date:cessation_upper": "1955-12-31",
    "date:inception_lower": "1955-01-01",
    "date:inception_upper": "1955-12-31",
    "iso:country": "XX",
    "millsfield:images": [
      1527835083
    ],
    "millsfield:primary_image": 1527835083,
    "sfomuseum:accession_number": "2012.149.1174",
    "sfomuseum:airline": "Finnair",
    "sfomuseum:category": "Promotional",
    "sfomuseum:collection": "Aviation Archive",
    "sfomuseum:creditline": "Gift of the Captain John B. Russell Family",
    "sfomuseum:date": "c. 1955",
    "sfomuseum:date_acquired": "2013-05-31",
    "sfomuseum:daterange_end": "1960-12-31",
    "sfomuseum:daterange_start": "1950-01-01",
    "sfomuseum:description": "Luggage label promoting Finnair; rectangular shape with rounded corners; light blue background with white border and illustration depicting profile view of airplane in flight over Finnish national flag.",
    "sfomuseum:dimensions": "4 1/4 x 2 3/4 inches (10.8 x 7 cm)",
    "sfomuseum:media_ids": [
      1527835083
    ],
    "sfomuseum:medium": "paper, ink, adhesive",
    "sfomuseum:placetype": "object",
    "sfomuseum:publication": ": , c. 1955.",
    "sfomuseum:subcategory": "Luggage Label",
    "wof:depicts": [
      1159284389
    ],
    "wof:name": "luggage label: Finnair",
    "wof:placetype": "venue"
  },
  "geometry": {"coordinates":[-122.386155,37.616357],"type":"Point"}
}
