{
  "type": "Feature",
  "properties": {
    "date:cessation_lower": "1928-12-31",
    "date:cessation_upper": "1928-12-31",
    "date:inception_lower": "1928-01-01",
    "date:inception_upper": "1928-01-01",
    "iso:country": "XX",
    "sfomuseum:accession_number": "2000.160.0685",
    "sfomuseum:author": "Page, Major Victor Wilfred",
    "sfomuseum:callnumber": "TL545 .P16 1928 SC",
    "sfomuseum:category": "Book",
    "sfomuseum:collection": "Aviation Library",
    "sfomuseum:creditline": "The Tony Bill Aviation Library Collection",
    "sfomuseum:date": "1928",
    "sfomuseum:daterange_end": "1928-12-31",
    "sfomuseum:daterange_start": "1928-01-01",
    "sfomuseum:description": "v, 247 p. illus., diagrs. 20 cm.",
    "sfomuseum:medium": "paper, ink",
    "sfomuseum:placetype": "object",
    "sfomuseum:publisher": "The Norman W. Henley publishing co.",
    "sfomuseum:publisher_location": "New York",
    "sfomuseum:subcategory": "Book",
    "sfomuseum:subject": "Aeronautics.",
    "wof:name": "Everybody's aviation guide: a complete, simplified treatise in question and answer form for those wishing to obtain a general and diversified knowledge of aeronautics and aerodynamics. It considers all types of aircraft, both lighter-than-air and heavier-than-air forms, gives the principles on which their operation is based and describes construction of principal types of dirigibles and airplanes",
    "wof:placetype": "venue"
  },
  "geometry": {"coordinates":[-122.386155,37.616357],"type":"Point"}
}
