{
  "type": "Feature",
  "properties": {
    "date:cessation_lower": "1968-01-01",
    "date:cessation_upper": "1968-12-31",
    "date:inception_lower": "1968-01-01",
    "date:inception_upper": "1968-12-31",
    "iso:country": "XX",
    "millsfield:images": [
      1527846907
    ],
    "sfomuseum:accession_number": "2012.173.278",
    "sfomuseum:airline": "Northeast Airlines",
    "sfomuseum:category": "Scheduling / Ticketing",
    "sfomuseum:collection": "Aviation Archive",
    "sfomuseum:creditline": "Gift of Willard F. Keeney",
    "sfomuseum:date": "1968",
    "sfomuseum:daterange_end": "1968-12-31",
    "sfomuseum:daterange_start": "1968-01-01",
    "sfomuseum:description": "System timetable issued by Northeast Airlines, effective October 1, 1968; white and yellow cover with text, “Already this year we’ve broiled half a million steaks on our Yellowbirds on the way to Florida / You’ll wish we flew everywhere”; fold-out format; includes route map.",
    "sfomuseum:dimensions": "9 1/4 x 4 inches (23.5 x 10.2 cm)",
    "sfomuseum:media_ids": [
      1527846907
    ],
    "sfomuseum:medium": "paper, ink",
    "sfomuseum:placetype": "object",
    "sfomuseum:subcategory": "Timetable",
    "sfomuseum:subject": "Airlines -- Commercial -- Northeast Airlines.",
    "wof:depicts": [
      1159284893
    ],
    "wof:name": "timetable: Northeast Airlines",
    "wof:placetype": "venue"
  },
  "geometry": {"coordinates":[-122.386155,37.616357],"type":"Point"}
}
