{
  "type": "Feature",
  "properties": {
    "date:cessation_lower":"1965-12-31",
    "date:cessation_upper":"1965-12-31",
    "date:inception_lower":"1965-01-01",
    "date:inception_upper":"1965-01-01",
    "iso:country":"XX",
    "millsfield:images":[
        1527825463
    ],
    "sfomuseum:accession_number":"2011.032.1399",
    "sfomuseum:airport":"San Francisco International Airport",
    "sfomuseum:category":"Photograph",
    "sfomuseum:collection":"Aviation Archive",
    "sfomuseum:creditline":"Transfer",
    "sfomuseum:date":"1965",
    "sfomuseum:daterange_end":"1965-12-31",
    "sfomuseum:daterange_start":"1965-01-01",
    "sfomuseum:description":"From attached handwritten note: \u201c9-17-65 / Rwy 28R Fill / construction\u201d. Black and white photographic negative depicting bulldozer with checkered flag moving dirt and fill during construction of Runway 28R at San Francisco International Airport (SFO); San Francisco Bay in background; photograph taken on September 17, 1965.",
    "sfomuseum:media_ids":[
        1527825463
    ],
    "sfomuseum:medium":"negative",
    "sfomuseum:placetype":"object",
    "sfomuseum:subcategory":"Negative",
    "wof:depicts":[
        102527513
    ],
    "wof:name":"negative: San Francisco International Airport (SFO), runway construction",
    "wof:placetype":"venue"
},
  "geometry": {"coordinates":[-122.386155,37.616357],"type":"Point"}
}