{
  "type": "Feature",
  "properties": {
    "date:cessation_lower":"1951-12-31",
    "date:cessation_upper":"1951-12-31",
    "date:inception_lower":"1951-01-01",
    "date:inception_upper":"1951-01-01",
    "iso:country":"XX",
    "millsfield:images":[
        1527821891
    ],
    "sfomuseum:accession_number":"2011.032.0263",
    "sfomuseum:category":"Photograph",
    "sfomuseum:collection":"Aviation Archive",
    "sfomuseum:creditline":"Transfer",
    "sfomuseum:date":"1951",
    "sfomuseum:daterange_end":"1951-12-31",
    "sfomuseum:daterange_start":"1951-01-01",
    "sfomuseum:description":"From attached handwritten note: \u201c03250 / 10-5-51 / Dedication ceremonies new passenger terminal bldg. (CENTRAL)\u201d. Black and white photograph of four men in suits on tractor, three waving hats; man on left of image in pinstripes standing on treads; groundbreaking ceremony for Terminal Building (later Central Terminal, now Terminal 2 / T2); San Francisco Airport; photograph taken on October 5, 1951.",
    "sfomuseum:media_ids":[
        1527821891
    ],
    "sfomuseum:medium":"negative",
    "sfomuseum:placetype":"object",
    "sfomuseum:subcategory":"Negative",
    "wof:name":"negative: San Francisco Airport, Terminal Building, groundbreaking ceremony",
    "wof:placetype":"venue"
},
  "geometry": {"coordinates":[-122.386155,37.616358],"type":"Point"}
}