{
  "type": "Feature",
  "properties": {
    "date:cessation_lower": "1996-12-31",
    "date:cessation_upper": "1996-12-31",
    "date:inception_lower": "1986-01-01",
    "date:inception_upper": "1986-01-01",
    "iso:country": "XX",
    "sfomuseum:accession_number": "1999.659.094",
    "sfomuseum:author": "Freedman, Russell",
    "sfomuseum:callnumber": "TL540.W7 F69 1991 c.2 JUV",
    "sfomuseum:category": "Book",
    "sfomuseum:collection": "Aviation Library",
    "sfomuseum:creditline": "Purchase",
    "sfomuseum:date": "c. 1991",
    "sfomuseum:daterange_end": "1996-12-31",
    "sfomuseum:daterange_start": "1986-01-01",
    "sfomuseum:description": "129 p. : ill. ; 24 x 27 cm.",
    "sfomuseum:medium": "paper, ink",
    "sfomuseum:placetype": "object",
    "sfomuseum:publisher": "Holiday House",
    "sfomuseum:publisher_location": "New York",
    "sfomuseum:subcategory": "Book",
    "sfomuseum:subject": "Wright, Wilbur, 1867-1912. Wright, Orville, 1871-1948. Wright, Wilbur, 1867-1912 Juvenile literature. Wright, Orville, 1871-1948 Juvenile literature. Aeronautics Biography. Aeronautics United States Biography Juvenile literature.",
    "wof:name": "The Wright brothers: how they invented the airplane",
    "wof:placetype": "venue"
  },
  "geometry": {"coordinates":[-122.386155,37.616357],"type":"Point"}
}
