{
  "type": "Feature",
  "properties": {
    "date:cessation_lower": "2002-01-01",
    "date:cessation_upper": "2002-12-31",
    "date:inception_lower": "2002-01-01",
    "date:inception_upper": "2002-12-31",
    "iso:country": "XX",
    "millsfield:images": [
      1527846393,
      1527846397
    ],
    "millsfield:images_texts": [
      "ED FIRST\nmenu",
      "TO BEGIN\nBlack pepper-crusted tuna with vegetable slaw\nWasabi and Asian sesame dressing\nMAIN COURSE\nDeluxe double Cheddar cheeseburger\nMustard potato salad\nShrimp paella with a tomato and olive ragoût\nSautéed shrimp in brown rice with a bell pepper medley\nThe above entrees are accompanied by a southwestern salad\nwith roasted corn, tortilla chips and Asian sesame ginger\nor Thousand Island dressing\nPretzel-crusted breast of chicken over a mixture of seasonal greens\nBell pepper confit and honey Dijon dressing\nserved with a fresh fruit appetizer\nDESSERT\nBEN\u0026JERRY'S ice cream with sundae toppings\nFEATURED WINES\nYour flight attendant will inform you of today's selections.\nWhite Wine\nGeyser Peak Sonoma County Chardonnay 1999\nBurgundy Mâcon 2000, Lugny St.-Pierre Bouchard Père et Fils\nRed Wine\nChâteau Los Boldos Requinoa Cabernet Sauvignon 1998\nCarmen Valle Central Cabernet Sauvignon 1998\n2006 034 301 133"
    ],
    "millsfield:images_texts_ids": [
      1527846393,
      1527846397
    ],
    "millsfield:primary_image": 1527846393,
    "sfomuseum:accession_number": "2006.059.307.134",
    "sfomuseum:airline": "United Airlines",
    "sfomuseum:category": "Passenger Amenity, Archive",
    "sfomuseum:collection": "Aviation Archive",
    "sfomuseum:creditline": "Gift of the Paul Edward Fair Estate",
    "sfomuseum:date": "2002",
    "sfomuseum:date_acquired": "2006-10-19",
    "sfomuseum:daterange_end": "2002-12-31",
    "sfomuseum:daterange_start": "2002-01-01",
    "sfomuseum:description": "Menu issued by United Airlines, transcontinental routes; black and white photographic image of biscotti and filled wine glasses; menu items include beef tenderloin, pecan-crusted chicken breast, and grilled veal chop; menu number: 103D006-4 TRANSCON (D01); class: First; date: 9/02.",
    "sfomuseum:dimensions": "8 1/2 x 5 1/2 inches (21.6 x 14 cm)",
    "sfomuseum:media_ids": [
      1527846393,
      1527846397
    ],
    "sfomuseum:medium": "paper, ink",
    "sfomuseum:placetype": "object",
    "sfomuseum:publication": ": , 2002.",
    "sfomuseum:subcategory": "Menu",
    "wof:depicts": [
      1159285413,
      1159288779
    ],
    "wof:name": "menu: United Airlines, First Class",
    "wof:placetype": "custom",
    "wof:placetype_alt": "object"
  },
  "geometry": {"coordinates":[-122.386155,37.616357],"type":"Point"}
}
