{
  "type": "Feature",
  "properties": {
    "date:cessation_lower": "1969-12-31",
    "date:cessation_upper": "1969-12-31",
    "date:inception_lower": "1969-01-01",
    "date:inception_upper": "1969-01-01",
    "iso:country": "XX",
    "sfomuseum:accession_number": "2011.032.2000",
    "sfomuseum:artist": "Marshall Moxom",
    "sfomuseum:category": "Photograph",
    "sfomuseum:collection": "Aviation Archive",
    "sfomuseum:creditline": "Transfer",
    "sfomuseum:date": "1969",
    "sfomuseum:daterange_end": "1969-12-31",
    "sfomuseum:daterange_start": "1969-01-01",
    "sfomuseum:description": "From attached handwritten note: “03590 / 11-19-69 / Structural Steel Arrangement W. Underpass of main entrance rd. / taken by: Moxom”. Black and white photographic negative depicting construction of main entrance road at San Francisco International Airport (SFO) on Novermber 11, 1969; steel rebar and wood framing visible; construction workers and equipment visible in background; photo taken by Marshall Moxom.",
    "sfomuseum:media_ids": [
      1527826819
    ],
    "sfomuseum:medium": "negative",
    "sfomuseum:placetype": "object",
    "sfomuseum:subcategory": "Negative",
    "wof:name": "negative: San Francisco International Airport (SFO), road construction",
    "wof:placetype": "venue"
  },
  "geometry": {"coordinates":[-122.386155,37.616358],"type":"Point"}
}
