{
  "type": "Feature",
  "properties": {
    "date:cessation_lower": "1980-01-01",
    "date:cessation_upper": "1989-12-31",
    "date:inception_lower": "1980-01-01",
    "date:inception_upper": "1989-12-31",
    "iso:country": "XX",
    "millsfield:images": [
      1527844119,
      1527844529
    ],
    "millsfield:primary_image": 1527844529,
    "sfomuseum:accession_number": "2006.034.007",
    "sfomuseum:airline": "Air New Zealand",
    "sfomuseum:category": "Passenger Amenity",
    "sfomuseum:collection": "Aviation Archive",
    "sfomuseum:creditline": "Gift of Adan Wong",
    "sfomuseum:date": "1980s",
    "sfomuseum:date_acquired": "2007-04-06",
    "sfomuseum:daterange_end": "1980-12-31",
    "sfomuseum:daterange_start": "1980-01-01",
    "sfomuseum:description": "Menu issued by Air New Zealand, Los Angeles - London and return route; gold cover with color illustration of an America’s Cup sailor; dinner and breakfast menu items include beef Wellington, ham, and sandwiches; menu number: NZ2/1ATL/299; class: business; undated.",
    "sfomuseum:dimensions": "12 x 5 3/4 inches (30.5 x 14.6 cm)",
    "sfomuseum:media_ids": [
      1527844119,
      1527844529
    ],
    "sfomuseum:medium": "paper, ink, metal",
    "sfomuseum:placetype": "object",
    "sfomuseum:publication": ": , 1980s.",
    "sfomuseum:subcategory": "Menu",
    "wof:depicts": [
      1159283697
    ],
    "wof:name": "menu: Air New Zealand, Business Class",
    "wof:placetype": "venue"
  },
  "geometry": {"coordinates":[-122.386155,37.616357],"type":"Point"}
}
