{
  "type": "Feature",
  "properties": {
    "date:cessation_lower":"1980-12-31",
    "date:cessation_upper":"1980-12-31",
    "date:inception_lower":"1980-01-01",
    "date:inception_upper":"1980-01-01",
    "iso:country":"XX",
    "millsfield:images":[
        1527844529,
        1527844119
    ],
    "sfomuseum:accession_number":"2006.034.007",
    "sfomuseum:category":"Food Service",
    "sfomuseum:collection":"Aviation Museum",
    "sfomuseum:creditline":"Gift of Adan Wong",
    "sfomuseum:date":"1980s",
    "sfomuseum:daterange_end":"1980-12-31",
    "sfomuseum:daterange_start":"1980-01-01",
    "sfomuseum:description":"Menu produced by Air New Zealand, Los Angeles - London and return route; gold cover with full color illustration of an America\u2019s Cup sailor; dinner and breakfast menu items include beef Wellington, ham, and sandwiches; menu number: NZ2/1ATL/299; class: business; undated.",
    "sfomuseum:media_ids":[
        1527844119,
        1527844529
    ],
    "sfomuseum:medium":"paper, ink, metal",
    "sfomuseum:placetype":"object",
    "sfomuseum:subcategory":"Menu",
    "wof:name":"menu: Air New Zealand, Business Class",
    "wof:placetype":"venue"
},
  "geometry": {"coordinates":[-122.386155,37.616358],"type":"Point"}
}