{
  "type": "Feature",
  "properties": {
    "date:cessation_lower": "1980-01-01",
    "date:cessation_upper": "1989-12-31",
    "date:inception_lower": "1980-01-01",
    "date:inception_upper": "1989-12-31",
    "iso:country": "XX",
    "millsfield:images": [
      1527844119,
      1527844529
    ],
    "millsfield:images_texts": [
      "bu chefs from some of the wooridis\nHOTE\nReservasonis Telechone: 3104721211\nA fabiod recreat for over 50 years.\nAline bOrAr, Excoutive oner Gary casus00\nWo at Ar Nyw Zedland are exoind abort\nour colaboration with the Howl BN-Ar\nthat al lows us to bring some of the lavish\nmystique of this prostgious estate to you\nsügar club\nRm chef in Brisain Now Zedland-bom\nPedor Gordona London's Sugar ClUb\nfor Air New Zealand's London-Los Angeles\nservicos. His sii al comibining unexpectod\nload sivies and his natural passion for the\nfavours dl the Pacida region has resuitod\no\nA Supero Selection el\nNenu\nappetiser\nShitake miseraomisana\nuna esinasan ano no es\nmain course\nSeared ohn don\nwith tennel, peppers. olives.\nchutney. balsamic Gressing\nFillet of Angus bec!\nhorseradish polatoes\nwith artichoke and ricotta on\ndinner\ndessert\non fresh rasoberry coulis\nWarm caramelised pineaoole\nwith vanilla bean ice cream\ncheese and fruit\nA selection of fine cheese\nbeverages\nFresnly brewed of\ndecalleinated coffee\nLight Choice - an casily\nA quick meal consisting of a sclection of broads.\nthe appetisor of the day, chooso and choco ales\nmas matanstan tirorobon",
      "Wenture.\nrapera and.\nBUSINESS"
    ],
    "millsfield:images_texts_ids": [
      1527844119,
      1527844529
    ],
    "millsfield:primary_image": 1527844529,
    "sfomuseum:accession_number": "2006.034.007",
    "sfomuseum:airline": "Air New Zealand",
    "sfomuseum:category": "Passenger Amenity, Archive",
    "sfomuseum:collection": "Aviation Archive",
    "sfomuseum:creditline": "Gift of Adan Wong",
    "sfomuseum:date": "1980s",
    "sfomuseum:date_acquired": "2007-04-06",
    "sfomuseum:daterange_end": "1980-12-31",
    "sfomuseum:daterange_start": "1980-01-01",
    "sfomuseum:description": "Menu issued by Air New Zealand, Los Angeles - London and return route; gold cover with color illustration of an America’s Cup sailor; dinner and breakfast menu items include beef Wellington, ham, and sandwiches; menu number: NZ2/1ATL/299; class: business; undated.",
    "sfomuseum:dimensions": "12 x 5 3/4 inches (30.5 x 14.6 cm)",
    "sfomuseum:media_ids": [
      1527844119,
      1527844529
    ],
    "sfomuseum:medium": "paper, ink, metal",
    "sfomuseum:placetype": "object",
    "sfomuseum:publication": ": , 1980s.",
    "sfomuseum:subcategory": "Menu",
    "wof:depicts": [
      1159283697,
      1159287125
    ],
    "wof:name": "menu: Air New Zealand, Business Class",
    "wof:placetype": "custom",
    "wof:placetype_alt": "object"
  },
  "geometry": {"coordinates":[-122.386155,37.616357],"type":"Point"}
}
