{
  "type": "Feature",
  "properties": {
    "date:cessation_lower": "1945-12-31",
    "date:cessation_upper": "1945-12-31",
    "date:inception_lower": "1935-01-01",
    "date:inception_upper": "1935-01-01",
    "iso:country": "XX",
    "sfomuseum:accession_number": "2012.149.2399",
    "sfomuseum:category": "Scheduling / Ticketing",
    "sfomuseum:collection": "Aviation Archive",
    "sfomuseum:creditline": "Gift of the Captain John B. Russell Family",
    "sfomuseum:date": "c. 1940",
    "sfomuseum:daterange_end": "1945-12-31",
    "sfomuseum:daterange_start": "1935-01-01",
    "sfomuseum:description": "Round label with black, red, and yellow printing; “Ansett Airways Ltd.” at top edge; remainder of label is divided vertically into black and yellow fields; planform outline of an airplane on left side, spaces for personal identification on right side.",
    "sfomuseum:media_ids": [
      1527853093
    ],
    "sfomuseum:medium": "paper, ink",
    "sfomuseum:placetype": "object",
    "sfomuseum:subcategory": "Identification Tag / Form, Paper",
    "wof:name": "luggage identification label: Ansett Airways",
    "wof:placetype": "venue"
  },
  "geometry": {"coordinates":[-122.386155,37.616358],"type":"Point"}
}
