{
  "type": "Feature",
  "properties": {
    "date:cessation_lower": "1837-01-01",
    "date:cessation_upper": "1837-12-31",
    "date:inception_lower": "1837-01-01",
    "date:inception_upper": "1837-12-31",
    "iso:country": "XX",
    "sfomuseum:accession_number": "2007.077.012",
    "sfomuseum:author": "Mason, Thomas Monck",
    "sfomuseum:callnumber": "AC4 .F7 1837 v.5 SC",
    "sfomuseum:category": "Book",
    "sfomuseum:collection": "Aviation Library",
    "sfomuseum:creditline": "Purchase",
    "sfomuseum:date": "1837",
    "sfomuseum:daterange_end": "1837-12-31",
    "sfomuseum:daterange_start": "1837-01-01",
    "sfomuseum:description": "35 p. ; 20 cm.",
    "sfomuseum:medium": "paper, ink",
    "sfomuseum:placetype": "object",
    "sfomuseum:publisher": "Theodore Foster",
    "sfomuseum:publisher_location": "New York",
    "sfomuseum:series": "Aeronautical collection ; 214",
    "sfomuseum:subcategory": "Book",
    "sfomuseum:subject": "Balloon ascensions.",
    "wof:name": "Account of the late aeronautical expedition from London to Weilburg",
    "wof:placetype": "custom"
  },
  "geometry": {"coordinates":[-122.386155,37.616357],"type":"Point"}
}
