{
  "type": "Feature",
  "properties": {
    "date:cessation_lower":"1997-12-31",
    "date:cessation_upper":"1997-12-31",
    "date:inception_lower":"1987-01-01",
    "date:inception_upper":"1987-01-01",
    "iso:country":"XX",
    "sfomuseum:accession_number":"2006.034.022",
    "sfomuseum:category":"Food Service",
    "sfomuseum:collection":"Aviation Museum",
    "sfomuseum:creditline":"Gift of Adan Wong",
    "sfomuseum:date":"c. 1992",
    "sfomuseum:daterange_end":"1997-12-31",
    "sfomuseum:daterange_start":"1987-01-01",
    "sfomuseum:description":"Menu produced by American Airlines, international routes; white cover black and white illustration of fruits and vegetables; lunch menu items include chicken brochettes or beef Don Quixote; menu number: Y-M-U-3 and 3121-3; date: 7/92.",
    "sfomuseum:medium":"paper, ink",
    "sfomuseum:placetype":"object",
    "sfomuseum:subcategory":"Menu",
    "wof:name":"menu: American Airlines",
    "wof:placetype":"venue"
},
  "geometry": {"coordinates":[-122.386155,37.616358],"type":"Point"}
}