{
  "type": "Feature",
  "properties": {
    "date:cessation_lower": "1992-01-01",
    "date:cessation_upper": "1992-12-31",
    "date:inception_lower": "1992-01-01",
    "date:inception_upper": "1992-12-31",
    "iso:country": "XX",
    "millsfield:images": [
      1527843745,
      1527843749
    ],
    "millsfield:primary_image": 1527843745,
    "sfomuseum:accession_number": "2006.034.022",
    "sfomuseum:airline": "American Airlines",
    "sfomuseum:category": "Passenger Amenity",
    "sfomuseum:collection": "Aviation Archive",
    "sfomuseum:creditline": "Gift of Adan Wong",
    "sfomuseum:date": "c. 1992",
    "sfomuseum:daterange_end": "1997-12-31",
    "sfomuseum:daterange_start": "1987-01-01",
    "sfomuseum:description": "Menu issued by American Airlines, international routes; white cover black and white illustration of fruits and vegetables; lunch menu items include chicken brochettes or beef Don Quixote; menu number: Y-M-U-3 and 3121-3; date: 7/92.",
    "sfomuseum:dimensions": "7 3/4 x 4 1/4 inches (19.7 x 10.8 cm)",
    "sfomuseum:media_ids": [
      1527843745,
      1527843749
    ],
    "sfomuseum:medium": "paper, ink",
    "sfomuseum:placetype": "object",
    "sfomuseum:subcategory": "Menu",
    "wof:depicts": [
      1159283849
    ],
    "wof:name": "menu: American Airlines",
    "wof:placetype": "venue"
  },
  "geometry": {"coordinates":[-122.386155,37.616357],"type":"Point"}
}
