{
  "type": "Feature",
  "properties": {
    "date:cessation_lower":"1948-12-31",
    "date:cessation_upper":"1948-12-31",
    "date:inception_lower":"1948-01-01",
    "date:inception_upper":"1948-01-01",
    "iso:country":"XX",
    "millsfield:images":[
        1527821607
    ],
    "sfomuseum:accession_number":"2011.032.0206",
    "sfomuseum:category":"Photograph",
    "sfomuseum:collection":"Aviation Archive",
    "sfomuseum:creditline":"Transfer",
    "sfomuseum:date":"1948",
    "sfomuseum:daterange_end":"1948-12-31",
    "sfomuseum:daterange_start":"1948-01-01",
    "sfomuseum:description":"Black and white photographic negative depicting information booth in passenger waiting room, San Francisco Airport, January 6, 1948; female customer and male sailor standing at counter situated between columns under archway.",
    "sfomuseum:media_ids":[
        1527821607
    ],
    "sfomuseum:medium":"negative",
    "sfomuseum:placetype":"object",
    "sfomuseum:subcategory":"Negative",
    "wof:name":"negative: San Francisco Airport, passenger waiting room, ticket counter",
    "wof:placetype":"venue"
},
  "geometry": {"coordinates":[-122.386155,37.616358],"type":"Point"}
}