{
  "type": "Feature",
  "properties": {
    "date:cessation_lower": "1976-12-31",
    "date:cessation_upper": "1976-12-31",
    "date:inception_lower": "1976-01-01",
    "date:inception_upper": "1976-01-01",
    "iso:country": "XX",
    "millsfield:images": [
      1527844607
    ],
    "sfomuseum:accession_number": "2001.039.433",
    "sfomuseum:airline": "Pan American World Airways",
    "sfomuseum:category": "Scheduling / Ticketing",
    "sfomuseum:collection": "Aviation Archive",
    "sfomuseum:continent": "World Routes",
    "sfomuseum:creditline": "Gift of David A. Abercrombie in memory of Stanley A. Abercrombie",
    "sfomuseum:date": "1976",
    "sfomuseum:daterange_end": "1976-12-31",
    "sfomuseum:daterange_start": "1976-01-01",
    "sfomuseum:description": "Blue and white Economy Class boarding pass. \"Pan Am\" and globe logo in white along bottom edge, along with \"Guam\" with illustration of palm tree and text “Hafa Adai”. Passenger and flight information written in red and black ink.",
    "sfomuseum:media_ids": [
      1527844607
    ],
    "sfomuseum:medium": "paper, ink",
    "sfomuseum:placetype": "object",
    "sfomuseum:subcategory": "Boarding Pass",
    "wof:depicts": [
      1159284989
    ],
    "wof:name": "boarding pass: Pan American World Airways",
    "wof:placetype": "venue"
  },
  "geometry": {"coordinates":[-122.386155,37.616357],"type":"Point"}
}
