{
  "type": "Feature",
  "properties": {
    "date:cessation_lower": "1983-01-01",
    "date:cessation_upper": "1983-12-31",
    "date:inception_lower": "1983-01-01",
    "date:inception_upper": "1983-12-31",
    "iso:country": "XX",
    "millsfield:images": [
      1527846029
    ],
    "millsfield:primary_image": 1527846029,
    "sfomuseum:accession_number": "2002.135.018.007",
    "sfomuseum:airline": "Frontier Airlines",
    "sfomuseum:category": "Scheduling / Ticketing",
    "sfomuseum:collection": "Aviation Archive",
    "sfomuseum:creditline": "Gift of Thomas G. Dragges",
    "sfomuseum:date": "1983",
    "sfomuseum:date_acquired": "2022-04-18",
    "sfomuseum:daterange_end": "1983-12-31",
    "sfomuseum:daterange_start": "1983-01-01",
    "sfomuseum:description": "System timetable issued by Frontier Airlines, effective March 1, 1983; white and red cover with list of destination cities; includes schedules for Pioneer and Air Midwest.",
    "sfomuseum:dimensions": "9 x 4 inches (22.9 x 10.2 cm)",
    "sfomuseum:media_ids": [
      1527846029
    ],
    "sfomuseum:medium": "paper, ink",
    "sfomuseum:placetype": "object",
    "sfomuseum:publication": ": , 1983.",
    "sfomuseum:subcategory": "Timetable",
    "sfomuseum:subject": "Airlines -- Commercial -- Frontier",
    "wof:depicts": [
      1159284401,
      1159288193,
      1762973287,
      1159283679
    ],
    "wof:name": "timetable: Frontier Airlines",
    "wof:placetype": "custom",
    "wof:placetype_alt": "object"
  },
  "geometry": {"coordinates":[-122.386155,37.616357],"type":"Point"}
}
