{
  "type": "Feature",
  "properties": {
    "date:cessation_lower": "1986-01-01",
    "date:cessation_upper": "1986-12-31",
    "date:inception_lower": "1986-01-01",
    "date:inception_upper": "1986-12-31",
    "iso:country": "XX",
    "loc:subject_headings": [
      "sh85121805"
    ],
    "sfomuseum:accession_number": "2008.055.022",
    "sfomuseum:author": "Smith, P. R.",
    "sfomuseum:callnumber": "TL686.S47 S6 1986",
    "sfomuseum:category": "Book",
    "sfomuseum:collection": "Aviation Library",
    "sfomuseum:creditline": "Gift of the William Hough Collection",
    "sfomuseum:date": "1986",
    "sfomuseum:date_acquired": "2008-04-13",
    "sfomuseum:daterange_end": "1986-12-31",
    "sfomuseum:daterange_start": "1986-01-01",
    "sfomuseum:description": "[64] p. : col. ill. ; 25 cm.",
    "sfomuseum:description_library": "[64] p. : col. ill. ; 25 cm.",
    "sfomuseum:medium": "paper, ink",
    "sfomuseum:placetype": "object",
    "sfomuseum:publication": "Twickenham, England: Jane's Pub., 1986.",
    "sfomuseum:publisher": "Jane's Pub.",
    "sfomuseum:publisher_location": "Twickenham, England",
    "sfomuseum:series": "Air portfolios ; 2",
    "sfomuseum:subcategory": "Book",
    "sfomuseum:subject": "Short airplanes.",
    "wof:depicts": [
      1159294345,
      1159291605
    ],
    "wof:name": "Shorts 330 and 360",
    "wof:placetype": "custom",
    "wof:placetype_alt": "object"
  },
  "geometry": {"coordinates":[-122.386155,37.616357],"type":"Point"}
}
