{
  "type": "Feature",
  "properties": {
    "date:cessation_lower": "1951-12-31",
    "date:cessation_upper": "1951-12-31",
    "date:inception_lower": "1941-01-01",
    "date:inception_upper": "1941-01-01",
    "iso:country": "XX",
    "sfomuseum:accession_number": "2005.062.012 a",
    "sfomuseum:aircraft": "Lockheed L-049 Constellation",
    "sfomuseum:airline": "TWA (Trans World Airlines)",
    "sfomuseum:airport": "San Francisco International Airport",
    "sfomuseum:category": "Photograph",
    "sfomuseum:collection": "Aviation Archive",
    "sfomuseum:creditline": "Gift of Charles Loomis",
    "sfomuseum:date": "c. 1946",
    "sfomuseum:daterange_end": "1951-12-31",
    "sfomuseum:daterange_start": "1941-01-01",
    "sfomuseum:description": "Photograph and negative depicting TWA (Trans World Airlines) Lockheed L-049 Constellation at San Francisco Airport; photo taken by Charles C. Loomis.\ra. Black and white print.\rb. Negative, housed in NEG21 (8/24/2012).",
    "sfomuseum:medium": "photograph",
    "sfomuseum:placetype": "object",
    "sfomuseum:subcategory": "Print, Photograph",
    "wof:depicts": [
      1159285393,
      1159291095,
      102527513
    ],
    "wof:name": "photograph: TWA (Trans World Airlines), Lockheed L-049 Constellation",
    "wof:placetype": "venue"
  },
  "geometry": {"coordinates":[-122.386155,37.616357],"type":"Point"}
}
