{
  "type": "Feature",
  "properties": {
    "date:cessation_lower": "1976-01-01",
    "date:cessation_upper": "1976-12-31",
    "date:inception_lower": "1976-01-01",
    "date:inception_upper": "1976-12-31",
    "iso:country": "XX",
    "millsfield:images": [
      1527835667
    ],
    "millsfield:images_texts": [
      "PSA\nFLIGHT SCHEDULE\nSUPPLEMENT\nEFFECTIVE JULY 21, 1976\nMore service\nbetween Long Beach\nand San Francisco\nSacramento.\nLONG BEACH TO SAN FRANCISCO\nAR\nEx Su\nEx Su\n12888888\nSAN\nFRANCIS\n898\nSi TU W TH\nTO LONG BEACH\nО иииииииинии\nEx su\n8888899885\nTU WTh\nuW Th\nFREQUENCY\n8:35 51\n9.05 Ex sa St\n1:55\n12:25\n6:20\nEx Su\nM TU WTh\nFLT\nFREQUENCY\n18%\n10\n4:00\n5:30\n9:30\nFor RESERVATIONS Call:\nLong Seach .... 637-6767\nSacramento .\n.. 922-3021\nMTUWTh\nTu W\n• Boldface\nFARES (One-way, incl. tax)\nLong Beach -\n... 26.50\n0.27.50"
    ],
    "millsfield:images_texts_ids": [
      1527835667
    ],
    "millsfield:primary_image": 1527835667,
    "sfomuseum:accession_number": "2005.132.042.048",
    "sfomuseum:airline": "Pacific Southwest Airlines (PSA)",
    "sfomuseum:category": "Scheduling / Ticketing",
    "sfomuseum:collection": "Aviation Archive",
    "sfomuseum:creditline": "Gift of the William Hough Collection",
    "sfomuseum:date": "1976",
    "sfomuseum:date_acquired": "2006-12-05",
    "sfomuseum:daterange_end": "1976-12-31",
    "sfomuseum:daterange_start": "1976-01-01",
    "sfomuseum:description": "Supplemental timetable issued by Pacific Southwest Airlines (PSA), effective July 21, 1976; white single-sided card with text “More service between Long Beach and San Francisco / Sacramento”.",
    "sfomuseum:dimensions": "9 x 3 1/4 inches (22.9 x 8.3 cm)",
    "sfomuseum:media_ids": [
      1527835667
    ],
    "sfomuseum:medium": "paper, ink",
    "sfomuseum:placetype": "object",
    "sfomuseum:publication": ": , 1976.",
    "sfomuseum:subcategory": "Timetable",
    "wof:depicts": [
      1159284973,
      1159286629
    ],
    "wof:name": "timetable: Pacific Southwest Airlines (PSA), supplement",
    "wof:placetype": "custom",
    "wof:placetype_alt": "object"
  },
  "geometry": {"coordinates":[-122.386155,37.616357],"type":"Point"}
}
