{
  "type": "Feature",
  "properties": {
    "date:cessation_lower": "1985-01-01",
    "date:cessation_upper": "1985-12-31",
    "date:inception_lower": "1985-01-01",
    "date:inception_upper": "1985-12-31",
    "iso:country": "XX",
    "millsfield:images": [
      1527841671
    ],
    "millsfield:images_texts": [
      "America West\nAirlines\nTIMETABLE\nEFFECTIVE SEPTEMBER 15-OCTOBER 26, 1985\nTUCSON TUCSON TUCSON TUC\nA WICHITA WICHITA WICHITA WIG\nLERQUE ALBUQUERQUE ALBUQUE\nTIN AUSTIN AUSTIN AUSTIN AUSTI\nK BURBANK BURBANK BURBANK BU\nRY CALGARY CALGARY CALGARY CAL\nRINGS COLORADO SPRINGS COLOR\nS MOINES DES MOINES DES MOINE\nDURANGO DURANGO DURANGO D\nMONTON EDMONTON EDMONTO\nSO EL PASO EL PASO EL PASO EL P\nCTION GRAND JUNCTION GRAND\nLAS VEGAS LAS VEGAS LAS VEGAS I\nN LINCOLN LINCOLN LINCOLN LIN\nANGELES LOS ANGELES LOS ANCE\nOAKLAND OAKLAND OAKLAND C\nАНА ОМАНА ОМАНА ОМАНА ОМАН\nO ONTARIO ONTARIO ONTARIO ON\nDUNTY ORANGE COUNTY ORANGE\nX PHOENIX PHOENIX PHOENIX PH\nAMENTO SACRAMENTO SACRAMEN\nKE CITY SALT LAKE CITY SALT LAK\nSAN DIEGO SAN DIEGO SAN DIEGO\nSE SAN JOSE SAN JOSE SAN JOSE SA\nIN TUCSON TUCSON TUCSON TU\nTA WICHITA WICHITA WICHITA WIC\nLERQUE ALBUQUERQUE ALBUQUE"
    ],
    "millsfield:images_texts_ids": [
      1527841671
    ],
    "millsfield:primary_image": 1527841671,
    "sfomuseum:accession_number": "2008.108.049",
    "sfomuseum:airline": "America West Airlines",
    "sfomuseum:category": "Scheduling / Ticketing",
    "sfomuseum:collection": "Aviation Archive",
    "sfomuseum:creditline": "Gift of the William Hough Collection",
    "sfomuseum:date": "1985",
    "sfomuseum:date_acquired": "2008-11-10",
    "sfomuseum:daterange_end": "1985-12-31",
    "sfomuseum:daterange_start": "1985-01-01",
    "sfomuseum:description": "Timetable issued by America West Airlines, effective September 15 through October 26, 1985; tan and white cover with list of destination cities.",
    "sfomuseum:dimensions": "9 x 4 inches (22.9 x 10.2 cm)",
    "sfomuseum:media_ids": [
      1527841671
    ],
    "sfomuseum:medium": "paper, ink",
    "sfomuseum:placetype": "object",
    "sfomuseum:publication": ": , 1985.",
    "sfomuseum:subcategory": "Timetable",
    "sfomuseum:subject": "Airlines -- Commercial -- America West",
    "wof:depicts": [
      1159285439
    ],
    "wof:name": "timetable: America West Airlines",
    "wof:placetype": "custom",
    "wof:placetype_alt": "object"
  },
  "geometry": {"coordinates":[-122.386155,37.616357],"type":"Point"}
}
