{
  "type": "Feature",
  "properties": {
    "date:cessation_lower": "1959-12-31",
    "date:cessation_upper": "1959-12-31",
    "date:inception_lower": "1950-01-01",
    "date:inception_upper": "1950-01-01",
    "iso:country": "XX",
    "sfomuseum:accession_number": "2007.051.008",
    "sfomuseum:airline": "American Airlines",
    "sfomuseum:category": "Insignia",
    "sfomuseum:collection": "Aviation Museum",
    "sfomuseum:creditline": "Purchase",
    "sfomuseum:date": "1950s",
    "sfomuseum:daterange_end": "1959-12-31",
    "sfomuseum:daterange_start": "1950-01-01",
    "sfomuseum:description": "Stewardess wings issued by American Airlines for five year service; gold wings with logomark on center; pin with turn-clasp closure on back; worn 1953-1970.",
    "sfomuseum:medium": "metal",
    "sfomuseum:placetype": "object",
    "sfomuseum:subcategory": "Uniform Wing(s), Cabin Crew",
    "wof:depicts": [
      1159283849
    ],
    "wof:name": "stewardess wings/service pin: American Airlines, 5 year",
    "wof:placetype": "venue"
  },
  "geometry": {"coordinates":[-122.386155,37.616357],"type":"Point"}
}
