{
  "type": "Feature",
  "properties": {
    "date:cessation_lower": "1950-01-01",
    "date:cessation_upper": "1959-12-31",
    "date:inception_lower": "1950-01-01",
    "date:inception_upper": "1959-12-31",
    "iso:country": "XX",
    "millsfield:images": [
      1729566905
    ],
    "millsfield:primary_image": 1729566905,
    "sfomuseum:accession_number": "2007.051.008",
    "sfomuseum:airline": "American Airlines",
    "sfomuseum:category": "Insignia",
    "sfomuseum:collection": "Aviation Museum",
    "sfomuseum:creditline": "Purchase",
    "sfomuseum:date": "1950s",
    "sfomuseum:date_acquired": "2007-06-22",
    "sfomuseum:daterange_end": "1959-12-31",
    "sfomuseum:daterange_start": "1950-01-01",
    "sfomuseum:description": "Stewardess wings issued by American Airlines for five year service; gold wings with logomark at center; pin with turn-clasp closure on back; worn 1953-1970.",
    "sfomuseum:dimensions": "3/4 x 2 1/2 x 1/4 inches (1.9 x 6.4 x .6 cm)",
    "sfomuseum:medium": "metal",
    "sfomuseum:placetype": "object",
    "sfomuseum:publication": ": , 1950s.",
    "sfomuseum:subcategory": "Uniform Wing(s), Cabin Crew",
    "wof:depicts": [
      1360700619,
      1159283849
    ],
    "wof:name": "stewardess wings/service pin: American Airlines, 5 years",
    "wof:placetype": "custom",
    "wof:placetype_alt": "object"
  },
  "geometry": {"coordinates":[-122.386155,37.616357],"type":"Point"}
}
