{
  "type": "Feature",
  "properties": {
    "date:cessation_lower":"1969-12-31",
    "date:cessation_upper":"1969-12-31",
    "date:inception_lower":"1960-01-01",
    "date:inception_upper":"1960-01-01",
    "iso:country":"XX",
    "sfomuseum:accession_number":"2006.028.138",
    "sfomuseum:category":"Insignia",
    "sfomuseum:collection":"Aviation Museum",
    "sfomuseum:creditline":"Gift of Edith Lauterbach",
    "sfomuseum:date":"1960s",
    "sfomuseum:daterange_end":"1969-12-31",
    "sfomuseum:daterange_start":"1960-01-01",
    "sfomuseum:description":"Gold name pin assigned to United Air Lines flight attendant Edith Lauterbach; rectangular form with name \"Ms. Lauterbach\"; reverse has relief \"LGB\" and pin with clasp.",
    "sfomuseum:maker":"L. G. Balfour Company",
    "sfomuseum:medium":"metal, enamel",
    "sfomuseum:placetype":"object",
    "sfomuseum:subcategory":"Name Pin, Cabin Crew",
    "wof:name":"name pin: United Air Lines",
    "wof:placetype":"venue"
},
  "geometry": {"coordinates":[-122.386155,37.616358],"type":"Point"}
}