{
  "type": "Feature",
  "properties": {
    "date:cessation_lower": "1960-01-01",
    "date:cessation_upper": "1969-12-31",
    "date:inception_lower": "1960-01-01",
    "date:inception_upper": "1969-12-31",
    "iso:country": "XX",
    "millsfield:images": [
      1763379343
    ],
    "millsfield:images_texts": [
      "MS. LAUTERBACH"
    ],
    "millsfield:images_texts_ids": [
      1763379343
    ],
    "millsfield:primary_image": 1763379343,
    "sfomuseum:accession_number": "2006.028.138",
    "sfomuseum:airline": "United Air Lines",
    "sfomuseum:category": "Insignia",
    "sfomuseum:collection": "Aviation Museum",
    "sfomuseum:creditline": "Gift of Edith Lauterbach",
    "sfomuseum:date": "1960s",
    "sfomuseum:date_acquired": "2006-04-18",
    "sfomuseum:daterange_end": "1969-12-31",
    "sfomuseum:daterange_start": "1960-01-01",
    "sfomuseum:description": "Name pin issued by United Air Lines, manufactured by L.G. Balfour Company; gold plate with etched “Ms. Lauterbach” on center; stamped “LGB” and long pin with turn-clasp closure on back; worn on apron.",
    "sfomuseum:dimensions": "2 1/2 x 1/2 x 1/4 inches (6.4 x 1.3 x .6 cm)",
    "sfomuseum:maker": "L.G. Balfour Company",
    "sfomuseum:medium": "metal, enamel",
    "sfomuseum:placetype": "object",
    "sfomuseum:publication": ": , 1960s.",
    "sfomuseum:subcategory": "Name Pin, Cabin Crew",
    "wof:depicts": [
      1159288779,
      1159285415
    ],
    "wof:name": "name pin: United Air Lines, Ms. Lauterbach",
    "wof:placetype": "custom",
    "wof:placetype_alt": "object"
  },
  "geometry": {"coordinates":[-122.386155,37.616357],"type":"Point"}
}
