{
  "type": "Feature",
  "properties": {
    "date:cessation_lower": "1970-01-01",
    "date:cessation_upper": "1970-12-31",
    "date:inception_lower": "1970-01-01",
    "date:inception_upper": "1970-12-31",
    "iso:country": "XX",
    "millsfield:images": [
      1527853025,
      1527853027
    ],
    "sfomuseum:accession_number": "2012.149.2189",
    "sfomuseum:airline": "Pan American World Airways",
    "sfomuseum:category": "Promotional",
    "sfomuseum:collection": "Aviation Archive",
    "sfomuseum:creditline": "Gift of the Captain John B. Russell Family",
    "sfomuseum:date": "c. 1970",
    "sfomuseum:daterange_end": "1975-12-31",
    "sfomuseum:daterange_start": "1965-01-01",
    "sfomuseum:description": "a. Souvenir club card issued by Pan American World Airways for “First Moon Flights Club” membership, issued to Etta B. Richards; color illustration depicting astronauts on moon, with illustration on reverse of Pan Am rocket ship; serial number 12354.\rb. Black and white photocopied article clippings from April/May 1992 issue of Air \u0026 Space magazine, titled “Promise me the moon.”",
    "sfomuseum:dimensions": "2 1/2 x 3 1/2 inches (6.4 x 8.9 cm)",
    "sfomuseum:media_ids": [
      1527853025,
      1527853027
    ],
    "sfomuseum:medium": "paper, ink",
    "sfomuseum:placetype": "object",
    "sfomuseum:subcategory": "Other, Promotional",
    "wof:depicts": [
      1159284989
    ],
    "wof:name": "souvenir club card: Pan American World Airways, “First Moon Flights” Club",
    "wof:placetype": "venue"
  },
  "geometry": {"coordinates":[-122.386155,37.616357],"type":"Point"}
}
