{
  "type": "Feature",
  "properties": {
    "date:cessation_lower": "1948-01-01",
    "date:cessation_upper": "1948-12-31",
    "date:inception_lower": "1948-01-01",
    "date:inception_upper": "1948-12-31",
    "iso:country": "XX",
    "millsfield:images": [
      1527818161
    ],
    "millsfield:primary_image": 1527818161,
    "sfomuseum:accession_number": "2001.038.139",
    "sfomuseum:airline": "Pan American World Airways",
    "sfomuseum:category": "Promotional",
    "sfomuseum:collection": "Aviation Archive",
    "sfomuseum:creditline": "Gift of Barnaby Conrad III",
    "sfomuseum:date": "1948",
    "sfomuseum:date_acquired": "2003-05-16",
    "sfomuseum:daterange_end": "1948-12-31",
    "sfomuseum:daterange_start": "1948-01-01",
    "sfomuseum:description": "Brochure issued by Pan American World Airways, titled “Ship by Clipper Cargo”; yellow cover with stylized image of globe and aircraft; \"Corrected to March 1, 1948\"; interior contains information regarding rates, charges, rules and regulations. ",
    "sfomuseum:dimensions": "11 x 8 1/2 inches (27.9 x 21.6 cm)",
    "sfomuseum:media_ids": [
      1527818161
    ],
    "sfomuseum:medium": "paper, ink",
    "sfomuseum:placetype": "object",
    "sfomuseum:publication": ": , 1948.",
    "sfomuseum:subcategory": "Brochure, Cargo",
    "wof:depicts": [
      1159284989
    ],
    "wof:name": "brochure: Pan American World Airways, cargo",
    "wof:placetype": "venue"
  },
  "geometry": {"coordinates":[-122.386155,37.616357],"type":"Point"}
}
