{
  "type": "Feature",
  "properties": {
    "date:cessation_lower":"1948-12-31",
    "date:cessation_upper":"1948-12-31",
    "date:inception_lower":"1948-01-01",
    "date:inception_upper":"1948-01-01",
    "iso:country":"XX",
    "millsfield:images":[
        1527818161
    ],
    "sfomuseum:accession_number":"2001.038.139",
    "sfomuseum:category":"Promotional",
    "sfomuseum:collection":"Aviation Archive",
    "sfomuseum:creditline":"Gift of Barnaby Conrad III",
    "sfomuseum:date":"1948",
    "sfomuseum:daterange_end":"1948-12-31",
    "sfomuseum:daterange_start":"1948-01-01",
    "sfomuseum:description":"Brochure produced by Pan American World Airways, titled \u201cShip by Clipper Cargo\u201d. Yellow cover has stylized image of globe and aircraft, with single wing globe logo in top right corner; \"Corrected to March 1, 1948\" printed in top left corner; interior contains information regarding rates, charges, rules and regulations. ",
    "sfomuseum:media_ids":[
        1527818161
    ],
    "sfomuseum:medium":"paper, ink",
    "sfomuseum:placetype":"object",
    "sfomuseum:subcategory":"Brochure, Cargo",
    "wof:name":"brochure: Pan American World Airways, cargo",
    "wof:placetype":"venue"
},
  "geometry": {"coordinates":[-122.386155,37.616358],"type":"Point"}
}