{
  "type": "Feature",
  "properties": {
    "date:cessation_lower":"2004-12-31",
    "date:cessation_upper":"2004-12-31",
    "date:inception_lower":"2004-01-01",
    "date:inception_upper":"2004-01-01",
    "iso:country":"XX",
    "sfomuseum:accession_number":"2004.115.0015",
    "sfomuseum:category":"Photograph",
    "sfomuseum:collection":"Aviation Archive",
    "sfomuseum:creditline":"Gift of the William Hough Collection",
    "sfomuseum:date":"2004",
    "sfomuseum:daterange_end":"2004-12-31",
    "sfomuseum:daterange_start":"2004-01-01",
    "sfomuseum:description":"Color photographic slide depicting profile view of AeroMexico Boeing 757-200 at John F. Kennedy International Airport (JFK), New York, October 11, 2004; photo taken by William Hough.",
    "sfomuseum:media_ids":[
        1527854615
    ],
    "sfomuseum:medium":"color slide",
    "sfomuseum:placetype":"object",
    "sfomuseum:subcategory":"Slide",
    "wof:depicts":[
        102534365,
        1159289935,
        1159293593,
        1159289939
    ],
    "wof:name":"slide: AeroMexico, Boeing 757-200, John F. Kennedy International Airport (JFK)",
    "wof:placetype":"venue"
},
  "geometry": {"coordinates":[-122.386155,37.616358],"type":"Point"}
}