{
  "type": "Feature",
  "properties": {
    "date:cessation_lower": "1940-01-01",
    "date:cessation_upper": "1949-12-31",
    "date:inception_lower": "1940-01-01",
    "date:inception_upper": "1949-12-31",
    "iso:country": "XX",
    "sfomuseum:accession_number": "2012.147.084",
    "sfomuseum:category": "Insignia",
    "sfomuseum:collection": "Aviation Museum",
    "sfomuseum:creditline": "Gift of the Captain John B. Russell Family",
    "sfomuseum:date": "1940s",
    "sfomuseum:daterange_end": "1949-12-31",
    "sfomuseum:daterange_start": "1940-01-01",
    "sfomuseum:description": "Service pin issued by North American Aviation; gold wings with blue circular logotype “NAA” on center; post with screw-back closure on back.",
    "sfomuseum:dimensions": "1/4 x 1 x 1/4 inches (.6 x 2.5 x .6 cm)",
    "sfomuseum:maker": "Whitehead \u0026 Hoag Company",
    "sfomuseum:medium": "metal, enamel",
    "sfomuseum:placetype": "object",
    "sfomuseum:publication": ": , 1940s.",
    "sfomuseum:subcategory": "Pin, Service",
    "wof:name": "service pin: North American Aviation",
    "wof:placetype": "venue"
  },
  "geometry": {"coordinates":[-122.386155,37.616357],"type":"Point"}
}
