{
  "type": "Feature",
  "properties": {
    "date:cessation_lower": "1978-01-01",
    "date:cessation_upper": "1978-12-31",
    "date:inception_lower": "1978-01-01",
    "date:inception_upper": "1978-12-31",
    "iso:country": "XX",
    "millsfield:images": [
      1527845345
    ],
    "sfomuseum:accession_number": "2011.061.0324",
    "sfomuseum:airline": "Korean Air Lines",
    "sfomuseum:category": "Scheduling / Ticketing",
    "sfomuseum:collection": "Aviation Archive",
    "sfomuseum:creditline": "Gift of the Frank J. Lichtanski Collection",
    "sfomuseum:date": "c. 1978",
    "sfomuseum:daterange_end": "1983-12-31",
    "sfomuseum:daterange_start": "1973-01-01",
    "sfomuseum:description": "First class boarding pass issued by Korean Air Lines; white with red, purple, and tan lotus pattern across top and bottom edges. Blank space for passenger information at left; red airline name and logo at right; space on reverse for immigration and customs inspection.",
    "sfomuseum:dimensions": "3 3/4 x 8 1/2 inches (9.5 x 21.6 cm)",
    "sfomuseum:media_ids": [
      1527845345
    ],
    "sfomuseum:medium": "paper, ink",
    "sfomuseum:placetype": "object",
    "sfomuseum:subcategory": "Boarding Pass",
    "wof:depicts": [
      1159284623
    ],
    "wof:name": "boarding pass: Korean Air Lines",
    "wof:placetype": "venue"
  },
  "geometry": {"coordinates":[-122.386155,37.616357],"type":"Point"}
}
