{
  "type": "Feature",
  "properties": {
    "date:cessation_lower": "1954-01-01",
    "date:cessation_upper": "1954-12-31",
    "date:inception_lower": "1954-01-01",
    "date:inception_upper": "1954-12-31",
    "iso:country": "XX",
    "sfomuseum:accession_number": "2000.172.063",
    "sfomuseum:author": "Murchie, Guy",
    "sfomuseum:callnumber": "TL546.7 .M87 1954 c.2",
    "sfomuseum:category": "Book",
    "sfomuseum:collection": "Aviation Library",
    "sfomuseum:creditline": "Collection of SFO Museum",
    "sfomuseum:date": "c. 1954",
    "sfomuseum:date_acquired": "1999-12-08",
    "sfomuseum:daterange_end": "1959-12-31",
    "sfomuseum:daterange_start": "1949-01-01",
    "sfomuseum:description": "viii, 438 p. illus. 22 cm.",
    "sfomuseum:description_library": "viii, 438 p. illus. 22 cm.",
    "sfomuseum:medium": "paper, ink",
    "sfomuseum:placetype": "object",
    "sfomuseum:publication": "Boston: Houghton Mifflin, c. 1954.",
    "sfomuseum:publisher": "Houghton Mifflin",
    "sfomuseum:publisher_location": "Boston",
    "sfomuseum:subcategory": "Book",
    "sfomuseum:subject": "Meteorology in aeronautics.Atmosphere.Aeronautics.",
    "wof:name": "Song of the sky: with illus. by the author",
    "wof:placetype": "custom",
    "wof:placetype_alt": [
      "object"
    ]
  },
  "geometry": {"coordinates":[-122.386155,37.616357],"type":"Point"}
}
