{
  "type": "Feature",
  "properties": {
    "date:cessation_lower": "2000-01-01",
    "date:cessation_upper": "2000-12-31",
    "date:inception_lower": "2000-01-01",
    "date:inception_upper": "2000-12-31",
    "isbn:number": "0970501811 (hardcover), 9780970501813 (hardcover)",
    "iso:country": "XX",
    "sfomuseum:accession_number": "2010.171.004",
    "sfomuseum:author": "Martini, T. J.",
    "sfomuseum:callnumber": "HE9803.R46 M37 2000\r",
    "sfomuseum:category": "Book",
    "sfomuseum:collection": "Aviation Library",
    "sfomuseum:creditline": "Collection of SFO Museum",
    "sfomuseum:date": "2000",
    "sfomuseum:date_acquired": "2010-06-16",
    "sfomuseum:daterange_end": "2000-12-31",
    "sfomuseum:daterange_start": "2000-01-01",
    "sfomuseum:description": "335 p. : col. ill. ; 31 cm.",
    "sfomuseum:description_library": "335 p. : col. ill. ; 31 cm.",
    "sfomuseum:medium": "paper, ink",
    "sfomuseum:placetype": "object",
    "sfomuseum:publication": "Reno, NV: Wings Inc., 2000.",
    "sfomuseum:publisher": "Wings Inc.",
    "sfomuseum:publisher_location": "Reno, NV",
    "sfomuseum:subcategory": "Book",
    "sfomuseum:subject": "Reno Air -- History. \rAirlines -- Nevada -- Reno -- History. \r",
    "wof:name": "Wings of pride: the story of Reno Air and its people",
    "wof:placetype": "custom",
    "wof:placetype_alt": "object"
  },
  "geometry": {"coordinates":[-122.386155,37.616357],"type":"Point"}
}
