{
  "type": "Feature",
  "properties": {
    "date:cessation_lower": "1997-01-01",
    "date:cessation_upper": "1997-12-31",
    "date:inception_lower": "1997-01-01",
    "date:inception_upper": "1997-12-31",
    "iso:country": "XX",
    "sfomuseum:accession_number": "99-0242",
    "sfomuseum:airport": "Denver International Airport",
    "sfomuseum:author": "Dempsey, Paul Stephen",
    "sfomuseum:callnumber": "TL726.4.D58 D46 1997 c.2",
    "sfomuseum:category": "Book",
    "sfomuseum:collection": "Aviation Library",
    "sfomuseum:date": "c. 1997",
    "sfomuseum:daterange_end": "2002-12-31",
    "sfomuseum:daterange_start": "1992-01-01",
    "sfomuseum:description": "xviii, 557 p. : ill., maps ; 24 cm.",
    "sfomuseum:medium": "paper, ink",
    "sfomuseum:placetype": "object",
    "sfomuseum:publisher": "McGraw-Hill",
    "sfomuseum:publisher_location": "New York",
    "sfomuseum:subcategory": "Book",
    "sfomuseum:subject": "Denver International Airport.",
    "wof:depicts": [
      102531189
    ],
    "wof:name": "Denver International Airport: lessons learned",
    "wof:placetype": "venue"
  },
  "geometry": {"coordinates":[-122.386155,37.616357],"type":"Point"}
}
