{
  "type": "Feature",
  "properties": {
    "date:cessation_lower": "1940-01-01",
    "date:cessation_upper": "1940-12-31",
    "date:inception_lower": "1940-01-01",
    "date:inception_upper": "1940-12-31",
    "iso:country": "XX",
    "millsfield:images": [
      1763388305
    ],
    "millsfield:images_texts": [
      "4.54.\nNG/8601\nTHE GLORY OF\nAMERICAS\nCLIPPER SHIPS\nrecaptured\nBY PAN AMERICAN\nThose nim note a sipious caper in\nthe history of America's sea trade. Then came\nsteam, and gone was America's supremacy\non the seven seas\nToday, however, that supremacy is being\nrecaptured by a new kind of clipper ship.\nToday, an even more glorious chapter is\nbeing written-by Clipper Ships that fly.\nPan American Clippers are America's swift\nambassadors of trade over 65,000 miles ol\nairlanes, linking 55 countries, colonies and\nislands. They bring brand-new trade oppor-\ntunities and travel goals\nwithin days and\neven hours of every point in the U.S.\nPan American blanes already have flowr\n1,425,000 persons a total of 530,000,000\nmiles: have carried many thousand tons of\nexpress cargo and mail. Just as this country':\nproud boast once was its merchant marine\nof the sea, so today the world envies amer\nica's Merchant Marine of the Air—the Flying\nClippers.\nYou can get complete passenger details at\nany travel bureau or transportation line\noffice; express information at any Railway Ex-\npress agency; air mail data at\nany post office —and all three\nat any Pan American office. TRUST FLY\nPAA\nPAN AMERICAN AIRWAYS SYSTEM\nAMERICA'S MERCHANT MARINE OF THE AIR\nROUTES OF THE FLYING CLIPPER SHITO"
    ],
    "millsfield:images_texts_ids": [
      1763388305
    ],
    "millsfield:primary_image": 1763388305,
    "sfomuseum:accession_number": "2001.038.164.006",
    "sfomuseum:airline": "Pan American Airways",
    "sfomuseum:category": "Promotional, Archive",
    "sfomuseum:collection": "Aviation Archive",
    "sfomuseum:creditline": "Gift of Barnaby Conrad III",
    "sfomuseum:date": "c. 1940",
    "sfomuseum:date_acquired": "2003-05-16",
    "sfomuseum:daterange_end": "1945-12-31",
    "sfomuseum:daterange_start": "1935-01-01",
    "sfomuseum:description": "Advertisement from Saturday Evening Post promoting Pan American Airways System, titled “The Glory of America’s Clipper Ships Recaptured by Pan American”; color illustration depicting Boeing 314 seaplane in flight over sea with sail ship in background.",
    "sfomuseum:dimensions": "13 3/4 x 10 1/2 inches (34.9 x 26.7 cm)",
    "sfomuseum:medium": "paper, ink",
    "sfomuseum:placetype": "object",
    "sfomuseum:publication": ": , c. 1940.",
    "sfomuseum:subcategory": "Advertisement, 2D",
    "sfomuseum:subject": "Pan Am promotional advertisement",
    "wof:depicts": [
      1159286839,
      1159284991,
      1159285809
    ],
    "wof:name": "advertisement: Pan American Airways System, Saturday Evening Post",
    "wof:placetype": "custom",
    "wof:placetype_alt": [
      "object"
    ]
  },
  "geometry": {"coordinates":[-122.386155,37.616357],"type":"Point"}
}
