{
  "type": "Feature",
  "properties": {
    "date:cessation_lower":"1945-12-31",
    "date:cessation_upper":"1945-12-31",
    "date:inception_lower":"1935-01-01",
    "date:inception_upper":"1935-01-01",
    "iso:country":"XX",
    "sfomuseum:accession_number":"2001.038.164.006",
    "sfomuseum:category":"Promotional",
    "sfomuseum:collection":"Aviation Archive",
    "sfomuseum:creditline":"Gift of Barnaby Conrad III",
    "sfomuseum:date":"c. 1940",
    "sfomuseum:daterange_end":"1945-12-31",
    "sfomuseum:daterange_start":"1935-01-01",
    "sfomuseum:description":"Advertisement from Saturday Evening Post promoting Pan American Airways System, titled \u201cThe Glory of America\u2019s Clipper Ships Recaptured by Pan American\u201d; color illustration depicting Boeing 314 seaplane in flight over sea with sail ship in background.",
    "sfomuseum:medium":"paper, ink",
    "sfomuseum:placetype":"object",
    "sfomuseum:subcategory":"Advertisement, 2D",
    "wof:name":"advertisement: Pan American Airways System, Saturday Evening Post",
    "wof:placetype":"venue"
},
  "geometry": {"coordinates":[-122.386155,37.616358],"type":"Point"}
}