{
  "type": "Feature",
  "properties": {
    "date:cessation_lower": "1984-01-01",
    "date:cessation_upper": "1984-12-31",
    "date:inception_lower": "1984-01-01",
    "date:inception_upper": "1984-12-31",
    "iso:country": "XX",
    "loc:named_authorities": [
      "n84148073"
    ],
    "loc:subject_headings": [
      "sh2008117571"
    ],
    "sfomuseum:accession_number": "2005.012.001",
    "sfomuseum:airline": "Pan American World Airways",
    "sfomuseum:author": "Lodeesen, Marius",
    "sfomuseum:callnumber": "TL540.L64 A33 1984",
    "sfomuseum:category": "Book",
    "sfomuseum:collection": "Aviation Library",
    "sfomuseum:creditline": "Collection of SFO Museum",
    "sfomuseum:date": "1984",
    "sfomuseum:date_acquired": "2005-12-21",
    "sfomuseum:daterange_end": "1984-12-31",
    "sfomuseum:daterange_start": "1984-01-01",
    "sfomuseum:description": "xiv, 498 p. : ill. ; 23 cm.",
    "sfomuseum:description_library": "xiv, 498 p. : ill. ; 23 cm.",
    "sfomuseum:medium": "paper, ink",
    "sfomuseum:placetype": "object",
    "sfomuseum:publication": "Suttons Bay, MI: Argonaut Press, 1984.",
    "sfomuseum:publisher": "Argonaut Press",
    "sfomuseum:publisher_location": "Suttons Bay, MI",
    "sfomuseum:subcategory": "Book",
    "sfomuseum:subject": "Lodeesen, Marius, 1904-.\rAir pilots -- Biography. \rPan American World Airways -- Pilots -- Biography.",
    "wof:depicts": [
      1159286839,
      1159284989
    ],
    "wof:name": "Captain Lodi speaking: ten million leagues around the earth on the installment plan",
    "wof:placetype": "custom",
    "wof:placetype_alt": [
      "object"
    ]
  },
  "geometry": {"coordinates":[-122.386155,37.616357],"type":"Point"}
}
