{
  "type": "Feature",
  "properties": {
    "date:cessation_lower": "1952-01-01",
    "date:cessation_upper": "1952-12-31",
    "date:inception_lower": "1952-01-01",
    "date:inception_upper": "1952-12-31",
    "iso:country": "US",
    "sfomuseum:accession_number": "1999.660.014",
    "sfomuseum:author": "Kaucher, Dorothy",
    "sfomuseum:callnumber": "CT275.K38 A3 1952",
    "sfomuseum:category": "Book",
    "sfomuseum:collection": "Aviation Library",
    "sfomuseum:continent": "Oceania",
    "sfomuseum:country": "United States",
    "sfomuseum:creditline": "Purchase",
    "sfomuseum:date": "1952",
    "sfomuseum:daterange_end": "1952-12-31",
    "sfomuseum:daterange_start": "1952-01-01",
    "sfomuseum:description": "308 p. 25 cm.\r",
    "sfomuseum:description_library": "308 p. 25 cm.\r",
    "sfomuseum:medium": "book",
    "sfomuseum:placetype": "object",
    "sfomuseum:publication": "Boston: Christopher Pub. House, 1952.",
    "sfomuseum:publisher": "Christopher Pub. House",
    "sfomuseum:publisher_location": "Boston",
    "sfomuseum:subcategory": "Book",
    "sfomuseum:subject": "Kaucher, Dorothy. Air pilots - Biography\rWake Island - Description and travel.\r",
    "wof:name": "On your left the Milky Way",
    "wof:placetype": "venue"
  },
  "geometry": {"coordinates":[-122.386155,37.616357],"type":"Point"}
}
