{
  "type": "Feature",
  "properties": {
    "date:cessation_lower": "1998-01-01",
    "date:cessation_upper": "1998-12-31",
    "date:inception_lower": "1998-01-01",
    "date:inception_upper": "1998-12-31",
    "iso:country": "XX",
    "sfomuseum:accession_number": "99-0148",
    "sfomuseum:aircraft": "Lockheed L-049 Constellation",
    "sfomuseum:author": "Pace, Steve",
    "sfomuseum:callnumber": "TL686.L6 P33 1998",
    "sfomuseum:category": "Book",
    "sfomuseum:collection": "Aviation Library",
    "sfomuseum:date": "1998",
    "sfomuseum:daterange_end": "1998-12-31",
    "sfomuseum:daterange_start": "1998-01-01",
    "sfomuseum:description": "96 p. : col. ill. ; 23 cm.",
    "sfomuseum:description_library": "96 p. : col. ill. ; 23 cm.",
    "sfomuseum:medium": "paper, ink",
    "sfomuseum:placetype": "object",
    "sfomuseum:publication": "Osceola, WI: Motorbooks International Publishers \u0026 Wholesalers, 1998.",
    "sfomuseum:publisher": "Motorbooks International Publishers \u0026 Wholesalers",
    "sfomuseum:publisher_location": "Osceola, WI",
    "sfomuseum:series": "Enthusiast color series",
    "sfomuseum:subcategory": "Book",
    "sfomuseum:subject": "Constellation (Transport planes) History.Constellation (Transport planes) Pictorial works.",
    "wof:depicts": [
      1159291095,
      1159293697
    ],
    "wof:name": "Lockheed's constellation",
    "wof:placetype": "custom",
    "wof:placetype_alt": "object"
  },
  "geometry": {"coordinates":[-122.386155,37.616357],"type":"Point"}
}
