{
  "type": "Feature",
  "properties": {
    "date:cessation_lower": "1915-12-31",
    "date:cessation_upper": "1915-12-31",
    "date:inception_lower": "1915-01-01",
    "date:inception_upper": "1915-01-01",
    "iso:country": "XX",
    "sfomuseum:accession_number": "2010.282.085 a b",
    "sfomuseum:category": "Photograph",
    "sfomuseum:collection": "Aviation Archive",
    "sfomuseum:creditline": "Gift of Edwin I. Power, Jr. and Linda L. Liscom",
    "sfomuseum:date": "1915",
    "sfomuseum:daterange_end": "1915-12-31",
    "sfomuseum:daterange_start": "1915-01-01",
    "sfomuseum:description": "a. Glass negative depicting scene from Panama-Pacific International Exposition, San Francisco, February 20 through December 4, 1915; side view of a biplane on wooden planking on the shore of San Francisco Bay; possibly the Lockheed / Loughead Model G; military ship in background; image is dark, with low contrast; “25994” written in lower left corner; photograph taken in 1915  \rb. Handwritten inscription on original sleeve, “25994 / Three modern war machines / the areoplane [sic], the mine and battleship.”",
    "sfomuseum:media_ids": [
      1527831365
    ],
    "sfomuseum:medium": "glass negative",
    "sfomuseum:placetype": "object",
    "sfomuseum:subcategory": "Glass Negative",
    "wof:name": "glass negative: Panama-Pacific International Exposition",
    "wof:placetype": "venue"
  },
  "geometry": {"coordinates":[-122.386155,37.616358],"type":"Point"}
}
