{
  "type": "Feature",
  "properties": {
    "date:cessation_lower": "1986-01-01",
    "date:cessation_upper": "1986-12-31",
    "date:inception_lower": "1986-01-01",
    "date:inception_upper": "1986-12-31",
    "iso:country": "XX",
    "sfomuseum:accession_number": "1999.657.225",
    "sfomuseum:author": "Jerdone, Frank H",
    "sfomuseum:callnumber": "TL540.J47 A3 1986 SC",
    "sfomuseum:category": "Book",
    "sfomuseum:collection": "Aviation Library",
    "sfomuseum:creditline": "Purchase",
    "sfomuseum:date": "c. 1986",
    "sfomuseum:daterange_end": "1991-12-31",
    "sfomuseum:daterange_start": "1981-01-01",
    "sfomuseum:description": "x, 196 p. : ill. ; 24 cm.",
    "sfomuseum:description_library": "x, 196 p. : ill. ; 24 cm.",
    "sfomuseum:medium": "paper, ink",
    "sfomuseum:placetype": "object",
    "sfomuseum:publication": "New York: Vantage Press, c. 1986.",
    "sfomuseum:publisher": "Vantage Press",
    "sfomuseum:publisher_location": "New York",
    "sfomuseum:subcategory": "Book",
    "sfomuseum:subject": "Jerdone, Frank H.Air pilots United States Biography.",
    "wof:name": "Pilot of fortune",
    "wof:placetype": "custom"
  },
  "geometry": {"coordinates":[-122.386155,37.616357],"type":"Point"}
}
