{
  "type": "Feature",
  "properties": {
    "date:cessation_lower": "1999-01-01",
    "date:cessation_upper": "1999-12-31",
    "date:inception_lower": "1999-01-01",
    "date:inception_upper": "1999-12-31",
    "iso:country": "XX",
    "sfomuseum:accession_number": "00-0012 ",
    "sfomuseum:author": "Simbeck, Rob",
    "sfomuseum:callnumber": "D790 .S539 1999 ",
    "sfomuseum:category": "Book",
    "sfomuseum:collection": "Aviation Library",
    "sfomuseum:date": "1999",
    "sfomuseum:daterange_end": "1999-12-31",
    "sfomuseum:daterange_start": "1999-01-01",
    "sfomuseum:medium": "paper, ink",
    "sfomuseum:placetype": "object",
    "sfomuseum:publication": "New York: Atlantic Monthly Press, 1999.",
    "sfomuseum:publisher": "Atlantic Monthly Press",
    "sfomuseum:publisher_location": "New York",
    "sfomuseum:subcategory": "Book",
    "sfomuseum:subject": "Fort, Cornelia, 1919-1944.United States. Women's Auxiliary Ferrying Squadron Biography.Women air pilots United States Biography.World War, 1939-1945 Participation, Female.World War, 1939-1945 Aerial operations, American.",
    "wof:name": "Daughter of the air: the short soaring life of Cornelia Fort",
    "wof:placetype": "venue"
  },
  "geometry": {"coordinates":[-122.386155,37.616357],"type":"Point"}
}
