{
  "type": "Feature",
  "properties": {
    "date:cessation_lower": "1950-01-01",
    "date:cessation_upper": "1959-12-31",
    "date:inception_lower": "1950-01-01",
    "date:inception_upper": "1959-12-31",
    "iso:country": "XX",
    "millsfield:images": [
      1527856283,
      1527856285,
      1527856287
    ],
    "millsfield:images_texts": [
      "ENTER:\nUNIVERSIT\nOR CANE 1891\nSTANFORD\nWelcome Aboard!",
      "Pan American is pleased to serve you on your trip\nto the Stanford Campus at Stuttgart and we hope\nthat you are enjoying every moment of your\nClipper flight. Once again — Welcome Aboard!\nPAN AMERICAN",
      "SAN FRANCISCO — STUTTGART\nLuncheon\nRelishes\nChicken Consomme\nMonte Cristo Sandwich\nCottage Cheese and Pear Salad\nClipper Ice Cream\nFruit Basket\nCoffee\nTea\nMilk\nDinner\nVegetable Juice\nCheese Wafers\nSalted Nuts\nOlives\nWhite Wine, Pouilly Fuisse\nShrimp Cocktail\nStuffed Idlewild Farm Rock Cornish Game Hen\nChampagne Sauce\nButtered Peas and Carrots\nParisienne Potatoes\nSalad in Season\nFrench Pastries\nCoffee\nTea\nFruit Basket\nMilk\nJelly\nCoffee\nBreakfast\nChilled Orange Juice\nBreakfast Fruit\nMushroom Omelet\nPork Link Sausage\nPetit Danish\nButter\nJam\nTea\nToast\nHoney\nMilk\nChampagne Pereice\nChampagne, Charles Heidsieck\nAmerican College Sandwich\nStanford Cake\nCoffee\nTea\nMilk"
    ],
    "millsfield:images_texts_ids": [
      1527856283,
      1527856285,
      1527856287
    ],
    "millsfield:primary_image": 1527856283,
    "sfomuseum:accession_number": "2014.095.203",
    "sfomuseum:airline": "Pan American World Airways",
    "sfomuseum:category": "Passenger Amenity, Archive",
    "sfomuseum:collection": "Aviation Archive",
    "sfomuseum:creditline": "Gift of Thomas G. Dragges",
    "sfomuseum:date": "1950s",
    "sfomuseum:date_acquired": "2015-01-06",
    "sfomuseum:daterange_end": "1959-12-31",
    "sfomuseum:daterange_start": "1950-01-01",
    "sfomuseum:description": "Menu issued by Pan American World Airways, San Francisco - Stuttgart charter flight for Stanford University; off-white cover with red Stanford pennant; menu items include sandwich, stuffed game hen, and mushroom omelet; no menu number; undated.",
    "sfomuseum:dimensions": "6 x 8 3/4 inches (15.2 x 22.2 cm)",
    "sfomuseum:media_ids": [
      1527856283,
      1527856285,
      1527856287
    ],
    "sfomuseum:medium": "paper, ink",
    "sfomuseum:placetype": "object",
    "sfomuseum:publication": ": , 1950s.",
    "sfomuseum:subcategory": "Menu",
    "wof:depicts": [
      1159284989,
      1159286839
    ],
    "wof:name": "menu: Pan American World Airways",
    "wof:placetype": "custom",
    "wof:placetype_alt": "object"
  },
  "geometry": {"coordinates":[-122.386155,37.616357],"type":"Point"}
}
