{
  "type": "Feature",
  "properties": {
    "date:cessation_lower": "1947-12-31",
    "date:cessation_upper": "1947-12-31",
    "date:inception_lower": "1947-01-01",
    "date:inception_upper": "1947-01-01",
    "iso:country": "XX",
    "millsfield:images": [
      1527830189,
      1527830191
    ],
    "sfomuseum:accession_number": "2009.145.001",
    "sfomuseum:category": "Philately",
    "sfomuseum:collection": "Aviation Archive",
    "sfomuseum:creditline": "Anonymous gift",
    "sfomuseum:date": "08/01/1947",
    "sfomuseum:daterange_end": "1947-08-01",
    "sfomuseum:daterange_start": "1947-08-01",
    "sfomuseum:description": "Airmail flight cover commemorating extension of AM-63, San Francisco to Seattle; red cachet with image of route map of west coast; postmark: August 1, 1947, San Francisco with four-line cancellation mark over 5-cent stamp; backstamp: “Seattle Wash. August 1, 1947, Seattle; white envelope with red and blue rhomboids around the border (border type I).",
    "sfomuseum:media_ids": [
      1527830189,
      1527830191
    ],
    "sfomuseum:medium": "paper, ink",
    "sfomuseum:placetype": "object",
    "sfomuseum:subcategory": "Airmail Flight Cover",
    "wof:name": "airmail flight cover: AM-63, San Francisco - Seattle route",
    "wof:placetype": "venue"
  },
  "geometry": {"coordinates":[-122.386155,37.616357],"type":"Point"}
}
