{
  "type": "Feature",
  "properties": {
    "date:cessation_lower": "1926-12-31",
    "date:cessation_upper": "1926-12-31",
    "date:inception_lower": "1926-01-01",
    "date:inception_upper": "1926-01-01",
    "iso:country": "XX",
    "millsfield:images": [
      1527857065
    ],
    "sfomuseum:accession_number": "2000.018.079.006",
    "sfomuseum:airport": "Mills Field Municipal Airport of San Francisco",
    "sfomuseum:category": "Company Record / Document",
    "sfomuseum:collection": "Aviation Archive",
    "sfomuseum:creditline": "Transfer",
    "sfomuseum:date": "1926",
    "sfomuseum:daterange_end": "1926-12-31",
    "sfomuseum:daterange_start": "1926-01-01",
    "sfomuseum:description": "Document titled “Estimated Cost of Temporary Landing Field at Site No. 6,” January 27, 1927, containing summary and list of projected operating costs; from report prepared by City and County of San Francisco, Department of Public Works, Bureau of Engineering, to Board of Supervisors concerning proposed airport sites.",
    "sfomuseum:dimensions": "11 x 8 1/2 inches (27.9 x 21.6 cm)",
    "sfomuseum:media_ids": [
      1527857065
    ],
    "sfomuseum:medium": "paper, ink",
    "sfomuseum:placetype": "object",
    "sfomuseum:subcategory": "Report",
    "wof:depicts": [
      1360695653
    ],
    "wof:name": "report: San Francisco Department of Public Works, Bureau of Engineering, proposed airport site",
    "wof:placetype": "venue"
  },
  "geometry": {"coordinates":[-122.386155,37.616357],"type":"Point"}
}
