{
  "type": "Feature",
  "properties": {
    "date:cessation_lower": "1985-01-01",
    "date:cessation_upper": "1985-12-31",
    "date:inception_lower": "1985-01-01",
    "date:inception_upper": "1985-12-31",
    "iso:country": "XX",
    "sfomuseum:accession_number": "99-0007",
    "sfomuseum:author": "Miller, Jay",
    "sfomuseum:callnumber": "UG1242.B6 M56 1985",
    "sfomuseum:category": "Book",
    "sfomuseum:collection": "Aviation Library",
    "sfomuseum:date": "c. 1985",
    "sfomuseum:daterange_end": "1990-12-31",
    "sfomuseum:daterange_start": "1980-01-01",
    "sfomuseum:description": "136 p. : ill. (some col.) ; 28 cm.",
    "sfomuseum:description_library": "136 p. : ill. (some col.) ; 28 cm.",
    "sfomuseum:medium": "paper, ink",
    "sfomuseum:notes_library": "Includes index.Bibliography: p. 131-133.",
    "sfomuseum:placetype": "object",
    "sfomuseum:publication": "Arlington, TX: Aerofax, c. 1985.",
    "sfomuseum:publisher": "Aerofax",
    "sfomuseum:publisher_location": "Arlington, TX",
    "sfomuseum:series": "Aerograph ; 4",
    "sfomuseum:subcategory": "Book",
    "sfomuseum:subject": "B-58 bomber.Convair B-58 aeroplanes",
    "wof:name": "Convair B-58",
    "wof:placetype": "venue"
  },
  "geometry": {"coordinates":[-122.386155,37.616357],"type":"Point"}
}
