{
  "type": "Feature",
  "properties": {
    "date:cessation_lower": "1930-01-01",
    "date:cessation_upper": "1930-12-31",
    "date:inception_lower": "1930-01-01",
    "date:inception_upper": "1930-12-31",
    "iso:country": "XX",
    "millsfield:images": [
      1527828693
    ],
    "millsfield:primary_image": 1527828693,
    "sfomuseum:accession_number": "2001.043.003",
    "sfomuseum:airport": "Mills Field Municipal Airport of San Francisco",
    "sfomuseum:category": "Promotional",
    "sfomuseum:collection": "Aviation Archive",
    "sfomuseum:creditline": "Gift of Clifford Keithley",
    "sfomuseum:date": "1930",
    "sfomuseum:date_acquired": "2001-10-22",
    "sfomuseum:daterange_end": "1930-12-31",
    "sfomuseum:daterange_start": "1930-01-01",
    "sfomuseum:description": "Official program for airshow event at San Francisco Municipal Airport, Mills Field, titled “U.S. Army Air Maneuvers,” April 19 - 20, 1930, with cover illustration depicting airplanes and airships in flight over San Francisco Bay Area; contains event schedule, site plan, directory of city officials, and photographic images of various aircraft; 32 pages.",
    "sfomuseum:description_library": "32 p. : black and white photographs, maps, stapled booklet ; 30 cm.\r9 in x 12 in.",
    "sfomuseum:dimensions": "12 x 9 inches (30.5 x 22.9 cm)",
    "sfomuseum:media_ids": [
      1527828693
    ],
    "sfomuseum:medium": "paper, ink",
    "sfomuseum:placetype": "object",
    "sfomuseum:publication": "San Francisco: Municipal Publishing Co., Ltd., 1930.",
    "sfomuseum:publisher": "Municipal Publishing Co., Ltd.",
    "sfomuseum:publisher_location": "San Francisco",
    "sfomuseum:subcategory": "Event Program / Invitation",
    "sfomuseum:subject": "San Francisco International Airport -- Mills Field -- History.\rUnited States Army Air Manuevers.",
    "wof:depicts": [
      1360695653
    ],
    "wof:name": "program: San Francisco Municipal Airport, Mills Field, United States Army Air Maneuvers",
    "wof:placetype": "custom",
    "wof:placetype_alt": "object"
  },
  "geometry": {"coordinates":[-122.386155,37.616357],"type":"Point"}
}
