{
  "type": "Feature",
  "properties": {
    "date:cessation_lower":"1930-12-31",
    "date:cessation_upper":"1930-12-31",
    "date:inception_lower":"1930-01-01",
    "date:inception_upper":"1930-01-01",
    "iso:country":"XX",
    "sfomuseum:accession_number":"2001.043.003",
    "sfomuseum:category":"Promotional",
    "sfomuseum:collection":"Aviation Archive",
    "sfomuseum:creditline":"Gift of Cliff Keithley",
    "sfomuseum:date":"1930",
    "sfomuseum:daterange_end":"1930-12-31",
    "sfomuseum:daterange_start":"1930-01-01",
    "sfomuseum:description":"Official program for airshow event at San Francisco Municipal Airport, Mills Field, titled \u201cU.S. Army Air Maneuvers,\u201d April 19 - 20, 1930, with cover illustration depicting airplanes and airships in flight over San Francisco Bay Area; contains event schedule, site plan, directory of city officials, and photographic images of various aircraft; 32 pages.",
    "sfomuseum:media_ids":[
        1527828693
    ],
    "sfomuseum:medium":"paper, ink",
    "sfomuseum:placetype":"object",
    "sfomuseum:subcategory":"Event Program / Invitation",
    "wof:name":"program: San Francisco Municipal Airport, Mills Field, United States Army Air Maneuvers",
    "wof:placetype":"venue"
},
  "geometry": {"coordinates":[-122.386155,37.616358],"type":"Point"}
}