{
  "type": "Feature",
  "properties": {
    "date:cessation_lower": "1972-01-01",
    "date:cessation_upper": "1972-12-31",
    "date:inception_lower": "1972-01-01",
    "date:inception_upper": "1972-12-31",
    "iso:country": "XX",
    "sfomuseum:accession_number": "00-2836",
    "sfomuseum:author": "Stockholm International Peace Research Institute",
    "sfomuseum:callnumber": "UA10 .S69a 1974",
    "sfomuseum:category": "Book",
    "sfomuseum:collection": "Aviation Library",
    "sfomuseum:date": "c. 1972",
    "sfomuseum:daterange_end": "1977-12-31",
    "sfomuseum:daterange_start": "1967-01-01",
    "sfomuseum:description": "v. : ill. ; 24 cm.",
    "sfomuseum:description_library": "v. : ill. ; 24 cm.",
    "sfomuseum:medium": "paper, ink",
    "sfomuseum:notes_library": "Imprint varies.Issued by: Stockholm International Peace Research Institute.1968-1979.  1 v. (Includes index to yearbook under its earlier title)Issued also in Spanish under: Armamentos y desarme en el mundo.",
    "sfomuseum:placetype": "object",
    "sfomuseum:publication": "Stockholm, Sweden: Almquist \u0026 Wiksell, c. 1972.",
    "sfomuseum:publisher": "Almquist \u0026 Wiksell",
    "sfomuseum:publisher_location": "Stockholm, Sweden",
    "sfomuseum:subcategory": "Book",
    "sfomuseum:subject": "Disarmament Periodicals.Military readiness Periodicals.",
    "wof:name": "SIPRI [Stockholm International Peace Research Institute] yearbook: world armaments and disarmament",
    "wof:placetype": "venue"
  },
  "geometry": {"coordinates":[-122.386155,37.616357],"type":"Point"}
}
