{
  "type": "Feature",
  "properties": {
    "date:cessation_lower": "1935-04-16",
    "date:cessation_upper": "1935-04-16",
    "date:inception_lower": "1935-04-16",
    "date:inception_upper": "1935-04-16",
    "iso:country": "XX",
    "millsfield:images": [
      1527852489,
      1527853759,
      1527853763
    ],
    "millsfield:primary_image": 1527853763,
    "sfomuseum:accession_number": "2012.149.2307 a b",
    "sfomuseum:airline": "Pan American Airways",
    "sfomuseum:category": "Philately",
    "sfomuseum:collection": "Aviation Archive",
    "sfomuseum:creditline": "Gift of the Captain John B. Russell Family",
    "sfomuseum:date": "04/16/1935",
    "sfomuseum:daterange_end": "1935-04-16",
    "sfomuseum:daterange_start": "1935-04-16",
    "sfomuseum:description": "a. Airmail flight cover, Pan American Airways, first Pacific survey flight between California and Hawaii; blue stamped cachet at left, “First flight Hawaii-California” and red stamped cachet at right, “First flight California-Hawaii”; postmarked April 16, 1935 in San Francisco and April 23, 1935 and April 22, 1935 in Honolulu with football-shaped cancellations over two orange 6-cent stamps and one orange 6-cent postage indicia; backstamps: April 16, 1935 in Alameda and April 17, 1935 in Honolulu.\rb. Backing sheet with two sets of mounting corners, with handwritten caption: “Pan American survey flight - San Francisco to Honolulu \u0026 return”, and black and white photocopy of Pan American Clipper over Golden Gate Bridge.",
    "sfomuseum:dimensions": "3 3/4 x 6 1/2 inches (9.5 x 16.5 cm)",
    "sfomuseum:media_ids": [
      1527852489,
      1527853759,
      1527853763
    ],
    "sfomuseum:medium": "paper, ink",
    "sfomuseum:placetype": "object",
    "sfomuseum:subcategory": "Airmail Flight Cover",
    "sfomuseum:subject": "Airlines -- Commercial -- Pan American Airways.",
    "wof:depicts": [
      1159284991
    ],
    "wof:name": "airmail flight cover: Pan American Airways, first Pacific survey flight, California - Hawaii and return route",
    "wof:placetype": "venue"
  },
  "geometry": {"coordinates":[-122.386155,37.616357],"type":"Point"}
}
