{
  "type": "Feature",
  "properties": {
    "date:cessation_lower":"1935-12-31",
    "date:cessation_upper":"1935-12-31",
    "date:inception_lower":"1935-01-01",
    "date:inception_upper":"1935-01-01",
    "iso:country":"XX",
    "sfomuseum:accession_number":"2012.149.2307 a b",
    "sfomuseum:category":"Philately",
    "sfomuseum:collection":"Aviation Archive",
    "sfomuseum:creditline":"Gift of the Captain John B. Russell Family",
    "sfomuseum:date":"04/16/1935",
    "sfomuseum:daterange_end":"1935-04-16",
    "sfomuseum:daterange_start":"1935-04-16",
    "sfomuseum:description":"a. Airmail flight cover, Pan American Airways, first Pacific survey flight between California and Hawaii; blue stamped cachet at left, \u201cFirst flight Hawaii-California\u201d and red stamped cachet at right, \u201cFirst flight California-Hawaii\u201d; postmarked April 16, 1935 in San Francisco and April 23, 1935 and April 22, 1935 in Honolulu with football-shaped cancellations over two orange 6-cent stamps and one orange 6-cent postage indicia; backstamps: April 16, 1935 in Alameda and April 17, 1935 in Honolulu.\rb. Backing sheet with two sets of mounting corners, with handwritten caption: \u201cPan American survey flight - San Francisco to Honolulu & return\u201d, and black and white photocopy of Pan American Clipper over Golden Gate Bridge.",
    "sfomuseum:medium":"paper, ink",
    "sfomuseum:placetype":"object",
    "sfomuseum:subcategory":"Airmail Flight Cover",
    "wof:name":"airmail flight cover: Pan American Airways, first Pacific survey flight, California - Hawaii and return route",
    "wof:placetype":"venue"
},
  "geometry": {"coordinates":[-122.386155,37.616358],"type":"Point"}
}