{
  "type": "Feature",
  "properties": {
    "date:cessation_lower": "1936-01-01",
    "date:cessation_upper": "1936-12-31",
    "date:inception_lower": "1936-01-01",
    "date:inception_upper": "1936-12-31",
    "iso:country": "XX",
    "sfomuseum:accession_number": "2013.044.001",
    "sfomuseum:author": "Sargent, Eric, ed.",
    "sfomuseum:callnumber": "TL600 .S37 1936 c.3 SC",
    "sfomuseum:category": "Book",
    "sfomuseum:collection": "Aviation Library",
    "sfomuseum:creditline": "Gift of Robert Harmon",
    "sfomuseum:date": "1936",
    "sfomuseum:date_acquired": "2013-03-21",
    "sfomuseum:daterange_end": "1936-12-31",
    "sfomuseum:daterange_start": "1936-01-01",
    "sfomuseum:description": "xxii, 682 p. illus., plates (part col., part fold.) fold. maps. 11 x 13 cm.",
    "sfomuseum:description_library": "xxii, 682 p. illus., plates (part col., part fold.) fold. maps. 11 x 13 cm.",
    "sfomuseum:medium": "paper, ink",
    "sfomuseum:placetype": "object",
    "sfomuseum:publication": "New York; London: D. Appleton-Century, 1936.",
    "sfomuseum:publisher": "D. Appleton-Century",
    "sfomuseum:publisher_location": "New York; London",
    "sfomuseum:subcategory": "Book",
    "sfomuseum:subject": "Airplanes.Aeronautics.",
    "wof:name": "Aircraft and the air",
    "wof:placetype": "custom",
    "wof:placetype_alt": "object"
  },
  "geometry": {"coordinates":[-122.386155,37.616357],"type":"Point"}
}
