{
  "type": "Feature",
  "properties": {
    "date:cessation_lower": "1958-12-31",
    "date:cessation_upper": "1958-12-31",
    "date:inception_lower": "1958-01-01",
    "date:inception_upper": "1958-01-01",
    "iso:country": "US",
    "millsfield:images": [
      1527851661
    ],
    "sfomuseum:accession_number": "2002.108.032",
    "sfomuseum:aircraft": "Boeing 707-321",
    "sfomuseum:airline": "Pan American World Airways",
    "sfomuseum:category": "Company Record / Document",
    "sfomuseum:collection": "Aviation Archive",
    "sfomuseum:continent": "North America",
    "sfomuseum:country": "United States",
    "sfomuseum:creditline": "Gift of John J. Dunne",
    "sfomuseum:date": "1958",
    "sfomuseum:daterange_end": "1958-12-31",
    "sfomuseum:daterange_start": "1958-01-01",
    "sfomuseum:description": "Training manual produced by Pan American World Airways for Boeing 707-321 Intercontinental Jet Clipper; unpaginated softbound book with red, black, and white cover and image of Pan Am Boeing 707-321 in flight; contents: General, Dimensions, Jet Age Vocabulary, Performance, Questions and Answers; with illustrations, diagrams, cabin layouts, charts; plastic binding.",
    "sfomuseum:maker": "Pan American World Airways (Pacific - Alaska Division)",
    "sfomuseum:media_ids": [
      1527851661
    ],
    "sfomuseum:medium": "spiral bound printed paper",
    "sfomuseum:placetype": "object",
    "sfomuseum:subcategory": "Manual, Training",
    "wof:depicts": [
      1159289695,
      1159293593,
      1159289653,
      1159284989
    ],
    "wof:name": "training manual: Pan American World Airways, Boeing 707-321 Intercontinental Jet Clipper",
    "wof:placetype": "custom"
  },
  "geometry": {"coordinates":[-122.386155,37.616357],"type":"Point"}
}
