{
  "type": "Feature",
  "properties": {
    "date:cessation_lower": "1986-12-31",
    "date:cessation_upper": "1986-12-31",
    "date:inception_lower": "1986-01-01",
    "date:inception_upper": "1986-01-01",
    "iso:country": "XX",
    "sfomuseum:accession_number": "2009.125.002 a p",
    "sfomuseum:category": "Passenger Amenity",
    "sfomuseum:collection": "Aviation Archive",
    "sfomuseum:creditline": "Gift of Frank A. Norick",
    "sfomuseum:date": "1986",
    "sfomuseum:daterange_end": "1986-12-31",
    "sfomuseum:daterange_start": "1986-01-01",
    "sfomuseum:description": "Flight information packet produced by British Airways for Concorde service, comprising:\ra. light gray packet cover with flap, stamped imprinted “Concorde” with airline logo below on lower left corner, torn white square shape adhesive label closure with circular gray seal promoting the airline’s tenth anniversary for Concorde service\rb. brochure promoting Concorde service; white cover with airline servicemark; multipage booklet\rc. in-flight entertainment guide; gray cover with red “April” near top edge, black “Inflight Entertainment Guide” below, white area with full color musical notes; multipage booklet\rd. envelope containing schedule information, containing e and f\re. timetable for flights between London and the United States, effective summer 1986; double-sided laminated card\rf. timetable for flights between London and the United States, effective summer 1986; double-sided laminated card\rg. poster with full color photographic image of in-flight British Airways Concorde\rh. blank flight certificate; single-sided sheet\ri. stationery envelope with embossed airline servicemark\rj. stationery envelope with embossed airline servicemark\rk. stationery sheet with embossed 10th anniversary seal at top and airline servicemark at bottom\rl. stationery sheet with embossed 10th anniversary seal at top and airline servicemark at bottom\rm. stationery sheet with embossed 10th anniversary seal at top and airline servicemark at bottom\rn. stationery sheet with embossed 10th anniversary seal at top and airline servicemark at bottom\ro. in-flight magazine, titled “Business life”, April / May 1986 issue\rp. in-flight magazine, titled “British Airways highlife”, April 1986 issue",
    "sfomuseum:media_ids": [
      1527830323, 
      1527830327, 
      1527830329, 
      1527830333, 
      1527830335, 
      1527830337, 
      1527830339, 
      1527830351, 
      1527830353, 
      1527830355, 
      1527830357, 
      1527830359, 
      1527830331, 
      1527830341
    ],
    "sfomuseum:medium": "plastic, paper, ink, metal,",
    "sfomuseum:placetype": "object",
    "sfomuseum:subcategory": "In-flight Information",
    "wof:name": "flight information packet: British Airways, Concorde",
    "wof:placetype": "venue"
  },
  "geometry": {"coordinates":[-122.386155,37.616358],"type":"Point"}
}
