{
  "type": "Feature",
  "properties": {
    "date:cessation_lower": "1936-12-31",
    "date:cessation_upper": "1936-12-31",
    "date:inception_lower": "1936-01-01",
    "date:inception_upper": "1936-01-01",
    "iso:country": "US",
    "sfomuseum:accession_number": "2000.160.1088",
    "sfomuseum:author": "Aeronautical Chamber of Commerce of America",
    "sfomuseum:callnumber": "TL501 .A37 1936 REF",
    "sfomuseum:category": "Book",
    "sfomuseum:collection": "Aviation Library",
    "sfomuseum:continent": "North America",
    "sfomuseum:country": "United States",
    "sfomuseum:creditline": "The Tony Bill Aviation Library Collection",
    "sfomuseum:date": "1936",
    "sfomuseum:daterange_end": "1936-12-31",
    "sfomuseum:daterange_start": "1936-01-01",
    "sfomuseum:description": "Compiled, written and edited by the Aeronautical Chamber of Commerce of America, Inc.",
    "sfomuseum:issue": "1936",
    "sfomuseum:medium": "printed, bound paper",
    "sfomuseum:placetype": "object",
    "sfomuseum:publisher": "Lincoln Press",
    "sfomuseum:publisher_location": "Washington, D.C.",
    "sfomuseum:subcategory": "Reference",
    "sfomuseum:subject": "Airplanes.\rAeronautics.",
    "wof:name": "Aircraft year book [1936]",
    "wof:placetype": "venue"
  },
  "geometry": {"coordinates":[-122.386155,37.616357],"type":"Point"}
}
