{
  "type": "Feature",
  "properties": {
    "date:cessation_lower": "1980-01-01",
    "date:cessation_upper": "1980-12-31",
    "date:inception_lower": "1980-01-01",
    "date:inception_upper": "1980-12-31",
    "iso:country": "XX",
    "millsfield:images": [
      1527843643,
      1527843647
    ],
    "millsfield:images_texts": [
      "Braniff International",
      "APERITIFS\nCampari\nVermouth\nSherry\nPort\nCOCKTAILS\nPeru's Pisco Sour\n(A Braniff exclusive)\nChampagne Cocktail\nBloody Mary\nDry Martini\nScrewdriver\nManhattan\nLIQUORS\nBourbon\nCanadian\nScotch\nVodka\nGin\nRum\nLIQUEURS\nRemy Martin V.S.O.P.\nGrand Marnier\nDrambuie\nCrême De Menthe\nKahlúa\nAmaretto Di Saronno\nBenedictine \u0026 Brandy\nBEERS\nSelected Brands\nWINES\nMâcon Lugny\nNeirsteiner\nChâteau Citran\nBeaujolais Jadot\nCHAMPAGNE\nPiper Heidsieck Cuvée Diplomatique\n1\nDL55-Cy 2/4 5/80"
    ],
    "millsfield:images_texts_ids": [
      1527843643,
      1527843647
    ],
    "millsfield:primary_image": 1527843643,
    "sfomuseum:accession_number": "2001.080.064",
    "sfomuseum:airline": "Braniff International",
    "sfomuseum:artist": "Alexander Calder",
    "sfomuseum:category": "Passenger Amenity, Archive",
    "sfomuseum:collection": "Aviation Archive",
    "sfomuseum:continent": "World Routes",
    "sfomuseum:creditline": "Gift of Thomas G. Dragges",
    "sfomuseum:date": "1980",
    "sfomuseum:date_acquired": "2002-12-24",
    "sfomuseum:daterange_end": "1980-12-31",
    "sfomuseum:daterange_start": "1980-01-01",
    "sfomuseum:description": "Menu issued by Braniff International; white and red cover with illustration by artist Alexander Calder; lunch and dinner menu items include suckling pig, steak, chicken, and fish; menu number: DL55-Cy 2/4; date: 5/80.",
    "sfomuseum:dimensions": "13 x 8 1/4 inches (33 x 21 cm)",
    "sfomuseum:media_ids": [
      1527843643,
      1527843647
    ],
    "sfomuseum:medium": "paper, ink, metal",
    "sfomuseum:placetype": "object",
    "sfomuseum:publication": ": , 1980.",
    "sfomuseum:subcategory": "Menu",
    "wof:depicts": [
      1159286455,
      1159286951,
      1159284009
    ],
    "wof:name": "menu: Braniff International",
    "wof:placetype": "custom",
    "wof:placetype_alt": [
      "object"
    ]
  },
  "geometry": {"coordinates":[-122.386155,37.616357],"type":"Point"}
}
