{
  "type": "Feature",
  "properties": {
    "date:cessation_lower": "1979-01-01",
    "date:cessation_upper": "1979-12-31",
    "date:inception_lower": "1979-01-01",
    "date:inception_upper": "1979-12-31",
    "iso:country": "US",
    "millsfield:images": [
      1527818755,
      1527838683
    ],
    "millsfield:images_texts": [
      "VESTERNINTERNATIONACHOTECS\nPartners in travel wih Unted Airires\nUnted Airlines\nP.O. Box 391\nGenova, Illinois 60134\n(Fce Timecatle retures ONLY)\nAUGUST\nSMTWTFS\n567\n2 3\n8\n9 10 11\n12 13 14 15 16 17 18\n19 20 21 22 23 24 25\n26 27 28 29 30 31\nSEPTEMBER\nMT WT\n9 10 11 12 13 14 15\n16 17 18 19 20 21 22\n23 24 25 26 27 28 29\nHol1810 019180,101",
      "UNITED AIRLINES\nOur Friendly Times\nAugust 1, 1979\nVol. 3\nCharlotte, No. Carolina"
    ],
    "millsfield:images_texts_ids": [
      1527818755,
      1527838683
    ],
    "millsfield:primary_image": 1527838683,
    "sfomuseum:accession_number": "1999.047.417",
    "sfomuseum:airline": "United Airlines",
    "sfomuseum:category": "Scheduling / Ticketing",
    "sfomuseum:collection": "Aviation Archive",
    "sfomuseum:continent": "North America",
    "sfomuseum:country": "United States",
    "sfomuseum:creditline": "Gift of United Airlines Archives",
    "sfomuseum:date": "1979",
    "sfomuseum:date_acquired": "2000-05-11",
    "sfomuseum:daterange_end": "1979-12-31",
    "sfomuseum:daterange_start": "1979-01-01",
    "sfomuseum:description": "Timetable issued by United Airlines, effective August 1, 1979; white cover with color aerial photograph of downtown Charlotte, North Carolina.",
    "sfomuseum:dimensions": "9 x 4 inches (22.9 x 10.2 cm)",
    "sfomuseum:media_ids": [
      1527838683,
      1527818755
    ],
    "sfomuseum:medium": "paper, ink",
    "sfomuseum:placetype": "object",
    "sfomuseum:publication": ": , 1979.",
    "sfomuseum:subcategory": "Timetable",
    "wof:depicts": [
      1159288779,
      1159285413
    ],
    "wof:name": "timetable: United Airlines",
    "wof:placetype": "custom",
    "wof:placetype_alt": "object"
  },
  "geometry": {"coordinates":[-122.386155,37.616357],"type":"Point"}
}
