{
  "type": "Feature",
  "properties": {
    "date:cessation_lower": "1957-06-02",
    "date:cessation_upper": "1957-06-02",
    "date:inception_lower": "1957-06-02",
    "date:inception_upper": "1957-06-02",
    "iso:country": "XX",
    "millsfield:images": [
      1527832803,
      1527832811
    ],
    "millsfield:primary_image": 1527832803,
    "sfomuseum:accession_number": "2012.149.1818",
    "sfomuseum:airline": "Pan American World Airways",
    "sfomuseum:category": "Philately",
    "sfomuseum:collection": "Aviation Archive",
    "sfomuseum:creditline": "Gift of the Captain John B. Russell Family",
    "sfomuseum:date": "06/02/1957",
    "sfomuseum:date_acquired": "2013-05-31",
    "sfomuseum:daterange_end": "1957-06-02",
    "sfomuseum:daterange_start": "1957-06-02",
    "sfomuseum:description": "Airmail flight cover, Pan American World Airways, first airmail flight, FAM-18, Chicago - Rome route; blue cachet at left depicting view of Michigan Avenue with text, “Chicago - Rome F.A.M. 18 / First Air Mail Flight”; postmarked June 2, 1957 in Chicago with “14” cancellation mark over four 4-cent stamps; backstamp: June 3, 1957 in Rome.",
    "sfomuseum:dimensions": "3 1/2 x 6 1/2 inches (8.9 x 16.5 cm)",
    "sfomuseum:media_ids": [
      1527832803,
      1527832811
    ],
    "sfomuseum:medium": "paper, ink",
    "sfomuseum:placetype": "object",
    "sfomuseum:publication": ": , 06/02/1957.",
    "sfomuseum:subcategory": "Airmail Flight Cover",
    "wof:depicts": [
      1159284989
    ],
    "wof:name": "airmail flight cover: Pan American World Airways, FAM-18, Chicago - Rome route",
    "wof:placetype": "venue"
  },
  "geometry": {"coordinates":[-122.386155,37.616357],"type":"Point"}
}
