{
  "type": "Feature",
  "properties": {
    "date:cessation_lower": "1955-12-31",
    "date:cessation_upper": "1955-12-31",
    "date:inception_lower": "1945-01-01",
    "date:inception_upper": "1945-01-01",
    "iso:country": "AU",
    "sfomuseum:accession_number": "2001.145.004",
    "sfomuseum:airline": "British Commonwealth Pacific Airlines (BCPA)",
    "sfomuseum:category": "Passenger Amenity",
    "sfomuseum:collection": "Aviation Archive",
    "sfomuseum:continent": "Australia",
    "sfomuseum:creditline": "Gift of Mrs. Siusiadh Rasmussen ",
    "sfomuseum:date": "c. 1950",
    "sfomuseum:daterange_end": "1955-12-31",
    "sfomuseum:daterange_start": "1945-01-01",
    "sfomuseum:description": "Flight information packet issued by British Commonwealth Pacific Airlines (BCPA); blue and red folder only; tri-fold format; includes printed information about international date line, \"Southern Cross\" route, and instrument panels.",
    "sfomuseum:medium": "paper, ink, metal",
    "sfomuseum:placetype": "object",
    "sfomuseum:subcategory": "In-flight Information",
    "wof:depicts": [
      1159284025
    ],
    "wof:name": "flight information packet: British Commonwealth Pacific Airlines (BCPA)",
    "wof:placetype": "venue"
  },
  "geometry": {"coordinates":[-122.386155,37.616357],"type":"Point"}
}
