{
  "type": "Feature",
  "properties": {
    "date:cessation_lower": "1992-01-01",
    "date:cessation_upper": "1992-12-31",
    "date:inception_lower": "1992-01-01",
    "date:inception_upper": "1992-12-31",
    "iso:country": "XX",
    "sfomuseum:accession_number": "1999.657.176",
    "sfomuseum:author": "Holden, Henry M.",
    "sfomuseum:callnumber": "TL686.F66 H64 1992",
    "sfomuseum:category": "Book",
    "sfomuseum:collection": "Aviation Library",
    "sfomuseum:creditline": "Purchase",
    "sfomuseum:date": "1992",
    "sfomuseum:daterange_end": "1992-12-31",
    "sfomuseum:daterange_start": "1992-01-01",
    "sfomuseum:description": "xiv, 173 p.: ill. (some col.) ; 24 cm.\r\r\r",
    "sfomuseum:description_library": "xiv, 173 p.: ill. (some col.) ; 24 cm.\r\r\r",
    "sfomuseum:medium": "printed, bound paper",
    "sfomuseum:notes_library": "Includes bibliographical references (p. 165-168) and index.",
    "sfomuseum:placetype": "object",
    "sfomuseum:publication": "Blue Ridge Summit, PA: TAB / Aero, 1992.",
    "sfomuseum:publisher": "TAB / Aero",
    "sfomuseum:publisher_location": "Blue Ridge Summit, PA",
    "sfomuseum:series": "The Flying classics series",
    "sfomuseum:subcategory": "Book",
    "sfomuseum:subject": "Ford Three-engined Monoplane (Transport plane) -- History.",
    "wof:depicts": [
      1159292297
    ],
    "wof:name": "The fabulous Ford Tri-Motors",
    "wof:placetype": "venue"
  },
  "geometry": {"coordinates":[-122.386155,37.616357],"type":"Point"}
}
