{
  "type": "Feature",
  "properties": {
    "date:cessation_lower":"1985-12-31",
    "date:cessation_upper":"1985-12-31",
    "date:inception_lower":"1985-01-01",
    "date:inception_upper":"1985-01-01",
    "iso:country":"XX",
    "sfomuseum:accession_number":"2005.137.074.001",
    "sfomuseum:category":"Photograph",
    "sfomuseum:collection":"Aviation Archive",
    "sfomuseum:creditline":"Transfer",
    "sfomuseum:date":"1985",
    "sfomuseum:daterange_end":"1985-12-31",
    "sfomuseum:daterange_start":"1985-01-01",
    "sfomuseum:description":"Color photograph from report produced by San Francisco International Airport (SFO), titled \u201cSummary Progress Report / Bureau of Planning and Construction / May 1, 1985 through May 31, 1985\u201d; exterior view of South Terminal (Terminal 1) with caption, \u201cFirst glimpse of the new Boarding Area B,\u201d May 30, 1985.",
    "sfomuseum:medium":"photograph",
    "sfomuseum:placetype":"object",
    "sfomuseum:subcategory":"Print, Photograph",
    "wof:name":"photograph: San Francisco International Airport (SFO), South Terminal construction",
    "wof:placetype":"venue"
},
  "geometry": {"coordinates":[-122.386155,37.616358],"type":"Point"}
}