{
  "type": "Feature",
  "properties": {
    "date:cessation_lower": "1925-01-01",
    "date:cessation_upper": "1925-12-31",
    "date:inception_lower": "1925-01-01",
    "date:inception_upper": "1925-12-31",
    "iso:country": "IT",
    "millsfield:images": [
      1746680239
    ],
    "millsfield:primary_image": 1746680239,
    "sfomuseum:accession_number": "1994.02.01 a d",
    "sfomuseum:category": "Toys",
    "sfomuseum:collection": "Aviation Museum",
    "sfomuseum:continent": "Europe",
    "sfomuseum:country": "Italy",
    "sfomuseum:creditline": "Purchase",
    "sfomuseum:date": "1925",
    "sfomuseum:daterange_end": "1925-12-31",
    "sfomuseum:daterange_start": "1925-01-01",
    "sfomuseum:description": "Toy hangar and revolving airplane and globe  set manufactured by La Grande Fabbrica di giocattoli E. Cardini-Omegna:\ra. hangar on wood base with lithographed cardboard mounted on plexiglass;\rb. silver and yellow tinplate biplane. \"S-13\" on red flag on fuselage. \"Nord - Sud\" in blue on nose;\rc. multicolor tinplate globe with continents and oceans marked in Italian in contrasting colors;\rd. cardboard lithograph of children mounted on plexiglas sits in front;\re. instructions.",
    "sfomuseum:dimensions": "14 1/2 x 11 x 13 1/4 inches (36.8 x 27.9 x 33.7 cm)",
    "sfomuseum:maker": "La Grande Fabbrica Di Giocattoli E.  / Cardini - Omegna",
    "sfomuseum:medium": "tinplate, cardboard, plexiglass, wood, paper, ink",
    "sfomuseum:placetype": "object",
    "sfomuseum:publication": ": , 1925.",
    "sfomuseum:subcategory": "Toy Airport Set",
    "wof:name": "toy set: hangar and airplane",
    "wof:placetype": "custom"
  },
  "geometry": {"coordinates":[-122.386155,37.616357],"type":"Point"}
}
