{
  "type": "Feature",
  "properties": {
    "date:cessation_lower": "1998-01-01",
    "date:cessation_upper": "1998-12-31",
    "date:inception_lower": "1998-01-01",
    "date:inception_upper": "1998-12-31",
    "iso:country": "XX",
    "millsfield:images": [
      1763444215
    ],
    "millsfield:images_texts": [
      "UNITED AIRLINES"
    ],
    "millsfield:images_texts_ids": [
      1763444215
    ],
    "millsfield:primary_image": 1763444215,
    "sfomuseum:accession_number": "2004.115.0129",
    "sfomuseum:aircraft": "Boeing 777-100",
    "sfomuseum:airline": "United Airlines",
    "sfomuseum:artist": "William “Bill” Hough",
    "sfomuseum:category": "Photograph",
    "sfomuseum:collection": "Aviation Archive",
    "sfomuseum:creditline": "Gift of the William Hough Collection",
    "sfomuseum:date": "1998",
    "sfomuseum:date_acquired": "2004-12-28",
    "sfomuseum:daterange_end": "1998-12-31",
    "sfomuseum:daterange_start": "1998-01-01",
    "sfomuseum:description": "Color photographic slide depicting United Airlines Boeing 777-100, February 1, 1998.",
    "sfomuseum:dimensions": "1 x 1 1/2 inches (2.5 x 3.8 cm)",
    "sfomuseum:medium": "color slide",
    "sfomuseum:placetype": "object",
    "sfomuseum:publication": ": , 1998.",
    "sfomuseum:subcategory": "Slide",
    "wof:depicts": [
      1159293593,
      1159289983,
      1159285413,
      1159289979,
      1159288779
    ],
    "wof:name": "slide: United Airlines, Boeing 777-100",
    "wof:placetype": "custom",
    "wof:placetype_alt": "object"
  },
  "geometry": {"coordinates":[-122.386155,37.616357],"type":"Point"}
}
