{
  "type": "Feature",
  "properties": {
    "date:cessation_lower": "1985-02-15",
    "date:cessation_upper": "1985-02-15",
    "date:inception_lower": "1985-02-15",
    "date:inception_upper": "1985-02-15",
    "iso:country": "US",
    "millsfield:images": [
      1527820639
    ],
    "millsfield:primary_image": 1527820639,
    "sfomuseum:accession_number": "2007.011.521",
    "sfomuseum:airline": "Pan American World Airways",
    "sfomuseum:category": "Philately",
    "sfomuseum:collection": "Aviation Archive",
    "sfomuseum:continent": "North America",
    "sfomuseum:country": "United States",
    "sfomuseum:creditline": "Gift of the William Hough Collection",
    "sfomuseum:date": "2/15/1985",
    "sfomuseum:date_acquired": "2006-11-10",
    "sfomuseum:daterange_end": "1985-02-15",
    "sfomuseum:daterange_start": "1985-02-15",
    "sfomuseum:description": "Airmail flight cover, Pan American World Airways, first day of issue for stamp honoring 50th anniversary of China Clipper; printed cachet with illustration of Martin M-130 flying over Golden Gate Bridge; postmarked February 15, 1985 in San Francisco with commemorative cancellation mark over 44-cent “Transpacific Airmail 1935” stamp; envelope sealed with enclosure.",
    "sfomuseum:dimensions": "4 1/4 x 9 1/2 inches (10.8 x 24.1 cm)",
    "sfomuseum:media_ids": [
      1527820639
    ],
    "sfomuseum:medium": "paper, ink",
    "sfomuseum:placetype": "object",
    "sfomuseum:publication": ": , 2/15/1985.",
    "sfomuseum:subcategory": "Airmail Flight Cover",
    "sfomuseum:subject": "Airlines -- Commercial -- Pan American",
    "wof:depicts": [
      1159291191,
      1159284989,
      1159286839
    ],
    "wof:name": "airmail flight cover: Pan American World Airways, first day of issue, China Clipper 50th anniversary stamp",
    "wof:placetype": "custom",
    "wof:placetype_alt": "object"
  },
  "geometry": {"coordinates":[-122.386155,37.616357],"type":"Point"}
}
