{
  "type": "Feature",
  "properties": {
    "date:cessation_lower":"1985-12-31",
    "date:cessation_upper":"1985-12-31",
    "date:inception_lower":"1985-01-01",
    "date:inception_upper":"1985-01-01",
    "iso:country":"US",
    "sfomuseum:accession_number":"2007.011.521",
    "sfomuseum:category":"Philately",
    "sfomuseum:collection":"Aviation Archive",
    "sfomuseum:continent":"North America",
    "sfomuseum:country":"United States",
    "sfomuseum:creditline":"Gift of the William Hough Collection",
    "sfomuseum:date":"2/15/1985",
    "sfomuseum:daterange_end":"1985-02-15",
    "sfomuseum:daterange_start":"1985-02-15",
    "sfomuseum:description":"Airmail flight cover, Pan American World Airways, first day of issue for stamp honoring 50th anniversary of China Clipper; printed cachet with illustration of Martin M-130 flying over Golden Gate Bridge; postmarked February 15, 1985 in San Francisco with commemorative cancellation mark over 44-cent \u201cTranspacific Airmail 1935\u201d stamp; envelope sealed with enclosure.",
    "sfomuseum:media_ids":[
        1527820639
    ],
    "sfomuseum:medium":"paper, ink",
    "sfomuseum:placetype":"object",
    "sfomuseum:subcategory":"Airmail Flight Cover",
    "wof:depicts":[
        1159291191
    ],
    "wof:name":"airmail flight cover: Pan American World Airways, first day of issue, China Clipper 50th anniversary stamp",
    "wof:placetype":"venue"
},
  "geometry": {"coordinates":[-122.386155,37.616358],"type":"Point"}
}