{
  "type": "Feature",
  "properties": {
    "date:cessation_lower": "2001-01-01",
    "date:cessation_upper": "2001-12-31",
    "date:inception_lower": "2001-01-01",
    "date:inception_upper": "2001-12-31",
    "iso:country": "XX",
    "sfomuseum:accession_number": "2004.115.0731",
    "sfomuseum:aircraft": "Boeing 747-200",
    "sfomuseum:airline": "Pakistan International Airlines",
    "sfomuseum:airport": "John F. Kennedy International Airport",
    "sfomuseum:category": "Photograph",
    "sfomuseum:collection": "Aviation Archive",
    "sfomuseum:creditline": "Gift of the William Hough Collection",
    "sfomuseum:date": "2001",
    "sfomuseum:daterange_end": "2001-12-31",
    "sfomuseum:daterange_start": "2001-01-01",
    "sfomuseum:description": "Color photographic slide depicting Pakistan International Airlines Boeing 747-200 at John F. Kennedy International Airport (JFK), New York, October 28, 2001; photo credit William Hough.",
    "sfomuseum:dimensions": "1 x 1 1/2 inches (2.5 x 3.8 cm)",
    "sfomuseum:medium": "color slide",
    "sfomuseum:placetype": "object",
    "sfomuseum:publication": ": , 2001.",
    "sfomuseum:subcategory": "Slide",
    "wof:depicts": [
      1159289891,
      1159284979,
      102534365,
      1159289873,
      1159293593
    ],
    "wof:name": "slide: Pakistan International Airlines, Boeing 747-200, John F. Kennedy International Airport (JFK)",
    "wof:placetype": "venue"
  },
  "geometry": {"coordinates":[-122.386155,37.616357],"type":"Point"}
}
