{
  "type": "Feature",
  "properties": {
    "date:cessation_lower": "1937-12-31",
    "date:cessation_upper": "1937-12-31",
    "date:inception_lower": "1937-01-01",
    "date:inception_upper": "1937-01-01",
    "iso:country": "XX",
    "sfomuseum:accession_number": "2012.149.0124",
    "sfomuseum:category": "Scheduling / Ticketing",
    "sfomuseum:collection": "Aviation Archive",
    "sfomuseum:creditline": "Gift of the Captain John B. Russell Family",
    "sfomuseum:date": "1937",
    "sfomuseum:daterange_end": "1937-12-31",
    "sfomuseum:daterange_start": "1937-01-01",
    "sfomuseum:description": "Timetable issued by Imperial Airways (Bermuda), Ltd., part of Pan American Airways System, effective June 1, 1937; black text “New York - Bermuda” followed by green and white illustration depicting two aircraft in flight; contains listing of flight schedules.",
    "sfomuseum:media_ids": [
      1527858733, 
      1527842077
    ],
    "sfomuseum:medium": "paper, ink",
    "sfomuseum:placetype": "object",
    "sfomuseum:subcategory": "Timetable",
    "wof:name": "timetable: Imperial Airways",
    "wof:placetype": "venue"
  },
  "geometry": {"coordinates":[-122.386155,37.616358],"type":"Point"}
}
