{
  "type": "Feature",
  "properties": {
    "date:cessation_lower":"1929-12-31",
    "date:cessation_upper":"1929-12-31",
    "date:inception_lower":"1920-01-01",
    "date:inception_upper":"1920-01-01",
    "iso:country":"XX",
    "sfomuseum:accession_number":"2012.147.397",
    "sfomuseum:airline":"TWA (Trans World Airlines)",
    "sfomuseum:category":"Promotional",
    "sfomuseum:collection":"Aviation Museum",
    "sfomuseum:creditline":"Gift of the Captain John B. Russell Family",
    "sfomuseum:date":"1920s",
    "sfomuseum:daterange_end":"1929-12-31",
    "sfomuseum:daterange_start":"1920-01-01",
    "sfomuseum:description":"Small bronze pin in shape of airplane; white \u201cTWA\u201d initials on fuselage section; short pin with hook clasp on back.",
    "sfomuseum:medium":"metal",
    "sfomuseum:placetype":"object",
    "sfomuseum:subcategory":"Lapel Pin",
    "wof:depicts":[
        1159285393
    ],
    "wof:name":"lapel pin: TWA",
    "wof:placetype":"venue"
},
  "geometry": {"coordinates":[-122.386155,37.616357],"type":"Point"}
}