{
  "type": "Feature",
  "properties": {
    "date:cessation_lower": "1920-01-01",
    "date:cessation_upper": "1929-12-31",
    "date:inception_lower": "1920-01-01",
    "date:inception_upper": "1929-12-31",
    "iso:country": "XX",
    "sfomuseum:accession_number": "2012.147.397",
    "sfomuseum:airline": "TWA (Trans World Airlines)",
    "sfomuseum:category": "Promotional",
    "sfomuseum:collection": "Aviation Museum",
    "sfomuseum:creditline": "Gift of the Captain John B. Russell Family",
    "sfomuseum:date": "1920s",
    "sfomuseum:date_acquired": "2014-04-17",
    "sfomuseum:daterange_end": "1929-12-31",
    "sfomuseum:daterange_start": "1920-01-01",
    "sfomuseum:description": "Lapel pin; small bronze pin in shape of airplane with white “TWA” initials on fuselage section; short pin with hook clasp on back.",
    "sfomuseum:dimensions": "1 x 1 1/8 x 1/4 inches (2.5 x 2.9 x .6 cm)",
    "sfomuseum:medium": "metal",
    "sfomuseum:placetype": "object",
    "sfomuseum:publication": ": , 1920s.",
    "sfomuseum:subcategory": "Lapel Pin",
    "wof:depicts": [
      1159285393
    ],
    "wof:name": "lapel pin: TWA",
    "wof:placetype": "venue"
  },
  "geometry": {"coordinates":[-122.386155,37.616357],"type":"Point"}
}
