{
  "type": "Feature",
  "properties": {
    "date:cessation_lower": "1983-01-01",
    "date:cessation_upper": "1983-12-31",
    "date:inception_lower": "1983-01-01",
    "date:inception_upper": "1983-12-31",
    "iso:country": "XX",
    "millsfield:images": [
      1527835909
    ],
    "millsfield:images_texts": [
      "PSA\nQUICK\nREFERENCE\nSCHEDULE\nEFFECTIVE DECEMBER 1, 1983\nSAN FRANCISCO\nNONSTOP TO:\nTOS ANGELES\nRETURN FLIGHTS\nfight\n7:00a\n8:063 922 Daily\n8:00a\n9:063 126\nX7\n9:003 10:078\n220\nX6\n10:00a 11:083 226 Da\n11:00a 12:09p 324 X6\n12:00n\n180 70\n930\nDaily\n1:000\n2:090 228 X5\n2:00p\n3:090\n328\n3:000\n4:070\n424\nDaily\nDaily\n4:000\n5:090 522\nb:oUp\n69090\n932\nX6\nX6\n5:000\n6:09p\n934\n6:00p\n7:090 426 X6\n7:00p\n8:080\n724\nDaily\nSaVOo\n9:080 726 X6\n9:000\n10:05p 820 Daily\n10:00p 10:59p\n728\nХо\n12:15a\n1:182 708 X7\n\"THE\nMIDNIGHT FIVER\nFIt 895 Operates Dec. To to Jan 4\n7:00a 8:11a 287 X67\n8:00a\n9:093 121 Dally\n9:002 10:118 129 Daily\n10:00a 11:11a 223 X7\n11:00a\n12:11p 227 X6\n12:00n\n321 Г\nDaily\nLOUD\n2:090 325 X6\n2:00р\n3:00p\n4:110 827 Daily\n4:00p\n5:110 425 Daily\n5:00p\n621 Daily\n5:55p\n7:04p 895° Daily\n6:00p\n7080 623 X5\n7:00p\n8:080\n95 Daily\n8:00p\n9:08p 723 X6\n9:00p 10:06p 727 Daily\n10:000 11:060 821 X5\n11:55p 12:59a 709 X6\n\"THE MIDNIGHT FLYER'\nSee reverse side for other convenient nonstops and\npassenger reservations.\nFREQUENCY CODES: 1-Monday\n4-Thursday\n5.Friday\n2amuesday\n3-Wednesday\n6.Saturday 7-Sunday X-except\nSchedule subject to change without notice."
    ],
    "millsfield:images_texts_ids": [
      1527835909
    ],
    "millsfield:primary_image": 1527835909,
    "sfomuseum:accession_number": "2010.225.026",
    "sfomuseum:airline": "Pacific Southwest Airlines (PSA)",
    "sfomuseum:category": "Scheduling / Ticketing",
    "sfomuseum:collection": "Aviation Archive",
    "sfomuseum:creditline": "Gift of the William Hough Collection",
    "sfomuseum:date": "1983",
    "sfomuseum:date_acquired": "2011-11-10",
    "sfomuseum:daterange_end": "1983-12-31",
    "sfomuseum:daterange_start": "1983-01-01",
    "sfomuseum:description": "Quick reference schedule issued by PSA (Pacific Southwest Airlines), effective December 1, 1983, for service between San Francisco and the Los Angeles area; gray and orange cover.",
    "sfomuseum:dimensions": "9 x 4 inches (22.9 x 10.2 cm)",
    "sfomuseum:media_ids": [
      1527835909
    ],
    "sfomuseum:medium": "paper, ink",
    "sfomuseum:placetype": "object",
    "sfomuseum:publication": ": , 1983.",
    "sfomuseum:subcategory": "Timetable",
    "wof:depicts": [
      1159284973,
      1159286629
    ],
    "wof:name": "timetable: Pacific Southwest Airlines (PSA), quick reference San Francisco",
    "wof:placetype": "custom",
    "wof:placetype_alt": "object"
  },
  "geometry": {"coordinates":[-122.386155,37.616357],"type":"Point"}
}
