{
  "type": "Feature",
  "properties": {
    "date:cessation_lower": "1983-01-01",
    "date:cessation_upper": "1983-12-31",
    "date:inception_lower": "1983-01-01",
    "date:inception_upper": "1983-12-31",
    "iso:country": "XX",
    "millsfield:images": [
      1527835909
    ],
    "millsfield:images_texts": [
      "PSA\nQUICK\nREFERENCE\nCHEDULE\nEFFECTIVE DECEMBER 1, 1983\nSAN FRANCISCO\nNONSTOP TO:\nLOS ANGELES\nRETURN FLIGHTS\nDeparts\nArrives\nFlight\nFreq.\nDeparts\nArrives\nFlight\nFreq.\n7:00a\n8:06a\n922 Daily\n8:00a\n9:06a 126 X7\n9:00a\n10:07a 220 X6\n10:00a\n11:08a 226 Daily\n11:00a 12:09p\n324 X6\n12:00n\n1:07p 930 Daily\n1:00p\n2:09p 228 X6\n2:00p\n3:09р\n328\nDaily\n3:00р\n4:07p 424\nDaily\n4:00р\n5:09p\n522\n5:00p\n6:09p 932\n×6\n5:00p\n6:09p 934 6\n6:00p\n7:09p 426 X6\n7:00p\n8:08p\n724 Daily\n8:00p\n9:08p\n726 X6\n9:00p\n10:05p 820 Daily\n10:00p 10:59p 728 X6\n12:15a\n1:18a 708 X7\n\"THE MIDNIGHT FLYER\"'\n*FIt 895 Operates Dec. 15 to Jan 4\n7:00a\n8:11a 287 X67\n8:00a\n9:09a 121\nDaily\n9:00a 10:11a 129 Daily\n10:00a 11:11a 223 X7\n11:00a 12:11p 227 X6\n12:00n\n1:11p 321 Daily\n1:00p\n2:09p 325 X6\n2:00р\n3:09p 927 Daily\n3:00р\n4:11p 827 Daily\n4:00р\n5:11p 425 Daily\n5:00p\n6:11p\n621 Daily\n5:55p\n7:04p 895* Daily\n6:00р\n7:08p\n623 X6\n7:00p\n8:08р\n925 Daily\n8:00р\n9:08p 723 X6\n9:00p 10:06p 727 Daily\n10:00p 11:06p 821 X6\n11:55p 12:59a 709 X6\n\"THE MIDNIGHT FLYER\"'\nSee reverse side for other convenient nonstops and\npassenger reservations.\nFREQUENCY CODES: 1-Monday\n4- Thursday 5-Friday\n2-Tuesday\n6-Saturday 7-Sunday\nSchedule subject to change without notice.\n3-Wednesday\nX-Except"
    ],
    "millsfield:images_texts_ids": [
      1527835909
    ],
    "millsfield:primary_image": 1527835909,
    "sfomuseum:accession_number": "2010.225.026",
    "sfomuseum:airline": "Pacific Southwest Airlines (PSA)",
    "sfomuseum:category": "Scheduling / Ticketing",
    "sfomuseum:collection": "Aviation Archive",
    "sfomuseum:creditline": "Gift of the William Hough Collection",
    "sfomuseum:date": "1983",
    "sfomuseum:date_acquired": "2011-11-10",
    "sfomuseum:daterange_end": "1983-12-31",
    "sfomuseum:daterange_start": "1983-01-01",
    "sfomuseum:description": "Quick reference schedule issued by PSA (Pacific Southwest Airlines), effective December 1, 1983, for service between San Francisco and the Los Angeles area; gray and orange cover.",
    "sfomuseum:dimensions": "9 x 4 inches (22.9 x 10.2 cm)",
    "sfomuseum:media_ids": [
      1527835909
    ],
    "sfomuseum:medium": "paper, ink",
    "sfomuseum:placetype": "object",
    "sfomuseum:publication": ": , 1983.",
    "sfomuseum:subcategory": "Timetable",
    "wof:depicts": [
      1159286629,
      1159284973
    ],
    "wof:name": "timetable: Pacific Southwest Airlines (PSA), quick reference San Francisco",
    "wof:placetype": "custom",
    "wof:placetype_alt": [
      "object"
    ]
  },
  "geometry": {"coordinates":[-122.386155,37.616357],"type":"Point"}
}
