{
  "type": "Feature",
  "properties": {
    "date:cessation_lower": "1963-01-01",
    "date:cessation_upper": "1963-12-31",
    "date:inception_lower": "1963-01-01",
    "date:inception_upper": "1963-12-31",
    "iso:country": "XX",
    "sfomuseum:accession_number": "00-3134",
    "sfomuseum:author": "Great Britain. Ministry of Defence",
    "sfomuseum:callnumber": "UA647 .A32 1963",
    "sfomuseum:category": "Book",
    "sfomuseum:collection": "Aviation Library",
    "sfomuseum:date": "1963",
    "sfomuseum:daterange_end": "1963-12-31",
    "sfomuseum:daterange_start": "1963-01-01",
    "sfomuseum:description": "v. ; 25 cm.",
    "sfomuseum:description_library": "v. ; 25 cm.",
    "sfomuseum:medium": "paper, ink",
    "sfomuseum:placetype": "object",
    "sfomuseum:publication": "London: H. M. Stationery Office, 1963.",
    "sfomuseum:publisher": "H. M. Stationery Office",
    "sfomuseum:publisher_location": "London",
    "sfomuseum:series": "Cmd.",
    "sfomuseum:subcategory": "Book",
    "sfomuseum:subject": "Great Britain Defenses.Great Britain Military policy.",
    "wof:name": "Statement on defence",
    "wof:placetype": "custom",
    "wof:placetype_alt": [
      "object"
    ]
  },
  "geometry": {"coordinates":[-122.386155,37.616357],"type":"Point"}
}
