{
  "type": "Feature",
  "properties": {
    "date:cessation_lower": "1994-01-01",
    "date:cessation_upper": "1994-12-31",
    "date:inception_lower": "1994-01-01",
    "date:inception_upper": "1994-12-31",
    "iso:country": "XX",
    "millsfield:images": [
      1527840425
    ],
    "millsfield:primary_image": 1527840425,
    "sfomuseum:accession_number": "2006.059.101.053",
    "sfomuseum:airline": "United Airlines",
    "sfomuseum:category": "Scheduling / Ticketing",
    "sfomuseum:collection": "Aviation Archive",
    "sfomuseum:creditline": "Gift of the Paul Edward Fair Estate",
    "sfomuseum:date": "1994",
    "sfomuseum:date_acquired": "2006-10-19",
    "sfomuseum:daterange_end": "1994-12-31",
    "sfomuseum:daterange_start": "1994-01-01",
    "sfomuseum:description": "System timetable issued by United Airlines, effective April 12 through June 8, 1994; dark red and white cover with world map and text announcing use of 24-hour clock and Universal Time; includes United Express.",
    "sfomuseum:dimensions": "9 x 4 inches (22.9 x 10.2 cm)",
    "sfomuseum:media_ids": [
      1527840425
    ],
    "sfomuseum:medium": "paper, ink",
    "sfomuseum:placetype": "object",
    "sfomuseum:publication": ": , 1994.",
    "sfomuseum:subcategory": "Timetable",
    "wof:depicts": [
      1159285413,
      1159285417
    ],
    "wof:name": "timetable: United Airlines",
    "wof:placetype": "venue"
  },
  "geometry": {"coordinates":[-122.386155,37.616357],"type":"Point"}
}
