{
  "type": "Feature",
  "properties": {
    "date:cessation_lower": "1950-12-31",
    "date:cessation_upper": "1950-12-31",
    "date:inception_lower": "1940-01-01",
    "date:inception_upper": "1940-01-01",
    "iso:country": "XX",
    "millsfield:images": [
      1527853109
    ],
    "sfomuseum:accession_number": "2012.149.2428",
    "sfomuseum:aircraft": "Lockheed L-049 Constellation",
    "sfomuseum:airline": "Panair do Brasil",
    "sfomuseum:category": "Promotional",
    "sfomuseum:collection": "Aviation Archive",
    "sfomuseum:creditline": "Gift of the Captain John B. Russell Family",
    "sfomuseum:date": "c. 1945",
    "sfomuseum:daterange_end": "1950-12-31",
    "sfomuseum:daterange_start": "1940-01-01",
    "sfomuseum:description": "Commemorative stamp issued by Panair do Brasil, a subsidiary of Pan American Airways; white with green illustration of a Lockheed L-049 Constellation and white text “Publicidade da Panair.”",
    "sfomuseum:dimensions": "1 1/4 x 1 1/2 inches (3.2 x 3.8 cm)",
    "sfomuseum:media_ids": [
      1527853109
    ],
    "sfomuseum:medium": "paper, ink",
    "sfomuseum:placetype": "object",
    "sfomuseum:subcategory": "Other, Promotional",
    "wof:depicts": [
      1159284991,
      1159284995,
      1159291095,
      1159293697
    ],
    "wof:name": "commemorative stamp: Panair do Brasil, Lockheed L-049 Constellation",
    "wof:placetype": "venue"
  },
  "geometry": {"coordinates":[-122.386155,37.616357],"type":"Point"}
}
