{
  "type": "Feature",
  "properties": {
    "date:cessation_lower": "1981-01-01",
    "date:cessation_upper": "1981-12-31",
    "date:inception_lower": "1981-01-01",
    "date:inception_upper": "1981-12-31",
    "iso:country": "XX",
    "millsfield:images": [
      1527818061,
      1527845007
    ],
    "millsfield:images_texts": [
      "JAL\nJAPAN AIR LINES",
      "#** \"#0\"\n# E\n#$0##\nTV2 FV0247\n2+01- 3-14-‡\nN4 -\n1-k-\nI***\n** #*\nN AX\nA1*7"
    ],
    "millsfield:images_texts_ids": [
      1527818061,
      1527845007
    ],
    "millsfield:primary_image": 1527818061,
    "sfomuseum:accession_number": "2001.080.098",
    "sfomuseum:airline": "Japan Air Lines",
    "sfomuseum:category": "Passenger Amenity, Archive",
    "sfomuseum:collection": "Aviation Archive",
    "sfomuseum:continent": "World Routes",
    "sfomuseum:creditline": "Gift of Thomas G. Dragges",
    "sfomuseum:date": "c. 1981",
    "sfomuseum:date_acquired": "2002-12-24",
    "sfomuseum:daterange_end": "1986-12-31",
    "sfomuseum:daterange_start": "1976-01-01",
    "sfomuseum:description": "Menu issued by Japan Air Lines, multi-stop route; white cover with full color illustration; menu items in Japanese; commemorates Prime Minister Zenko Suzuki’s diplomatic trip in 1981; no menu number; undated.",
    "sfomuseum:dimensions": "10 1/4 x 5 1/2 inches (26 x 14 cm)",
    "sfomuseum:media_ids": [
      1527845007,
      1527818061
    ],
    "sfomuseum:medium": "paper, ink",
    "sfomuseum:placetype": "object",
    "sfomuseum:publication": ": , c. 1981.",
    "sfomuseum:subcategory": "Menu",
    "wof:depicts": [
      1159288505,
      1159285785
    ],
    "wof:name": "menu: Japan Air Lines",
    "wof:placetype": "custom",
    "wof:placetype_alt": [
      "object"
    ]
  },
  "geometry": {"coordinates":[-122.386155,37.616357],"type":"Point"}
}
