{
  "type": "Feature",
  "properties": {
    "date:cessation_lower": "1941-12-31",
    "date:cessation_upper": "1941-12-31",
    "date:inception_lower": "1941-01-01",
    "date:inception_upper": "1941-01-01",
    "iso:country": "XX",
    "millsfield:images": [
      1527834171,
      1527834173
    ],
    "sfomuseum:accession_number": "2012.149.1661",
    "sfomuseum:aircraft": "Airco DH.4",
    "sfomuseum:category": "Philately",
    "sfomuseum:collection": "Aviation Archive",
    "sfomuseum:creditline": "Gift of the Captain John B. Russell Family",
    "sfomuseum:date": "08/27/1941",
    "sfomuseum:daterange_end": "1941-08-27",
    "sfomuseum:daterange_start": "1941-08-27",
    "sfomuseum:description": "Airmail flight cover issued by New Regular Airmail Series featuring first coast to coast airway honoring the first day of issue for the 20-cent air mail stamp; postmarked August 27, 1941, Philadelphia, with commemorative cancellation mark over 20-cent postage stamp; addressed to Oscar H. Fatout.",
    "sfomuseum:dimensions": "3 1/2 x 6 1/2 inches (8.9 x 16.5 cm)",
    "sfomuseum:media_ids": [
      1527834171,
      1527834173
    ],
    "sfomuseum:medium": "paper, ink",
    "sfomuseum:placetype": "object",
    "sfomuseum:subcategory": "Airmail Flight Cover",
    "wof:depicts": [
      1729554269
    ],
    "wof:name": "airmail flight cover: New regular airmail series, first day of issue for the 20-cent airmail stamp",
    "wof:placetype": "venue"
  },
  "geometry": {"coordinates":[-122.386155,37.616357],"type":"Point"}
}
