{
  "type": "Feature",
  "properties": {
    "date:cessation_lower": "1947-12-31",
    "date:cessation_upper": "1947-12-31",
    "date:inception_lower": "1947-01-01",
    "date:inception_upper": "1947-01-01",
    "iso:country": "TH",
    "millsfield:images": [
      1527829419,
      1527829417,
      1527829421
    ],
    "sfomuseum:accession_number": "1994.18.063 a b",
    "sfomuseum:airline": "Pan American World Airways",
    "sfomuseum:category": "Philately",
    "sfomuseum:collection": "Aviation Archive",
    "sfomuseum:continent": "Asia",
    "sfomuseum:country": "Thailand",
    "sfomuseum:creditline": "Purchase",
    "sfomuseum:date": "6/29/1947",
    "sfomuseum:daterange_end": "1947-06-29",
    "sfomuseum:daterange_start": "1947-06-29",
    "sfomuseum:description": "Airmail flight cover commemorating first direct airmail flight from Guam to Bangkok; magenta cachet with image of Thai statuary and buildings; four stamps: two blue 15-satang, one purple 5-satang, and black 1-baht (Thailand); three postmarks: \"Bangkok G.P.O. 29.6.47|11”; backstamp: \"Calcutta Air 30 June [19]47\"; envelope: white with faint blue repeated eagle pattern.\ra. envelope\rb. insert: \"Aviation Safety Award Conferred by Inter-American Safety Council, Inc. for the year 1946 to Pan American World Airways for flying over its 48,440-mile network a total of 43,878,591 flying miles, totaling 760,238,654 passenger miles without an accident or fatality to passengers or crews.\"",
    "sfomuseum:maker": "Pan American Airways, Inc.",
    "sfomuseum:media_ids": [
      1527829417,
      1527829419,
      1527829421
    ],
    "sfomuseum:medium": "ink on paper",
    "sfomuseum:placetype": "object",
    "sfomuseum:subcategory": "Airmail Flight Cover",
    "wof:depicts": [
      1159284989
    ],
    "wof:name": "airmail flight cover: Pan American World Airways, Bangkok - Calcutta route",
    "wof:placetype": "venue"
  },
  "geometry": {"coordinates":[-122.386155,37.616357],"type":"Point"}
}
