{
  "type": "Feature",
  "properties": {
    "date:cessation_lower": "1977-01-01",
    "date:cessation_upper": "1977-12-31",
    "date:inception_lower": "1977-01-01",
    "date:inception_upper": "1977-12-31",
    "iso:country": "XX",
    "sfomuseum:accession_number": "2000.168.139",
    "sfomuseum:author": "Keskinen, Kalevi",
    "sfomuseum:callnumber": "D792.F5 K47 1977",
    "sfomuseum:category": "Book",
    "sfomuseum:collection": "Aviation Library",
    "sfomuseum:creditline": "Purchase",
    "sfomuseum:date": "1977",
    "sfomuseum:daterange_end": "1977-12-31",
    "sfomuseum:daterange_start": "1977-01-01",
    "sfomuseum:description": "128, v p. : ill. ; 25 cm.",
    "sfomuseum:description_library": "128, v p. : ill. ; 25 cm.",
    "sfomuseum:medium": "paper, ink",
    "sfomuseum:placetype": "object",
    "sfomuseum:publication": "Helsinki, Finland: Tietoteos, 1977.",
    "sfomuseum:publisher": "Tietoteos",
    "sfomuseum:publisher_location": "Helsinki, Finland",
    "sfomuseum:series": "Suomen ilmavoimien historia ; 3",
    "sfomuseum:subcategory": "Book",
    "sfomuseum:subject": "Finland. Ilmavoimat History.Airplanes, Military.World War, 1939-1945 Aerial operations, Finnish.",
    "wof:name": "Fokker D.XXI",
    "wof:placetype": "custom",
    "wof:placetype_alt": "object"
  },
  "geometry": {"coordinates":[-122.386155,37.616357],"type":"Point"}
}
