{
  "type": "Feature",
  "properties": {
    "date:cessation_lower": "2001-01-01",
    "date:cessation_upper": "2001-12-31",
    "date:inception_lower": "2001-01-01",
    "date:inception_upper": "2001-12-31",
    "iso:country": "JP",
    "millsfield:images": [
      1527850929
    ],
    "millsfield:primary_image": 1527850929,
    "sfomuseum:accession_number": "2007.050.020 a b",
    "sfomuseum:airline": "Cathay Pacific Airways",
    "sfomuseum:category": "Beverage Service",
    "sfomuseum:collection": "Aviation Museum",
    "sfomuseum:continent": "Asia",
    "sfomuseum:country": "Japan",
    "sfomuseum:creditline": "Gift of Cathay Pacific Airways",
    "sfomuseum:date": "c. 2001",
    "sfomuseum:daterange_end": "2006-12-31",
    "sfomuseum:daterange_start": "1996-01-01",
    "sfomuseum:description": "a. White bone China individual teapot with handle; faint gray and white abstract design on side; \"Cathay Pacific Noritake Bone China Made in Japan 06A\" printed on bottom.\rb. Small white detachable lid",
    "sfomuseum:dimensions": "6 x 5 1/2 x 3 inches (15.2 x 14 x 7.6 cm)",
    "sfomuseum:maker": "Noritake",
    "sfomuseum:media_ids": [
      1527850929
    ],
    "sfomuseum:medium": "bone China",
    "sfomuseum:placetype": "object",
    "sfomuseum:publication": ": , c. 2001.",
    "sfomuseum:subcategory": "Coffeepot / Teapot",
    "wof:depicts": [
      1159284127
    ],
    "wof:name": "teapot: Cathay Pacific Airways",
    "wof:placetype": "venue"
  },
  "geometry": {"coordinates":[-122.386155,37.616357],"type":"Point"}
}
