{
  "type": "Feature",
  "properties": {
    "date:cessation_lower":"1955-12-31",
    "date:cessation_upper":"1955-12-31",
    "date:inception_lower":"1945-01-01",
    "date:inception_upper":"1945-01-01",
    "iso:country":"XX",
    "sfomuseum:accession_number":"2014.110.312",
    "sfomuseum:airline":"Qantas Airways",
    "sfomuseum:category":"Promotional",
    "sfomuseum:collection":"Aviation Archive",
    "sfomuseum:creditline":"Gift of Thomas G. Dragges",
    "sfomuseum:date":"c. 1950",
    "sfomuseum:daterange_end":"1955-12-31",
    "sfomuseum:daterange_start":"1945-01-01",
    "sfomuseum:description":"Promotional brochure issued by Qantas Airways; red, black, and white cover titled \u201cQantas means the world to you\u201d; contains illustrated guide to passenger services and scenic attractions.",
    "sfomuseum:medium":"paper, ink",
    "sfomuseum:placetype":"object",
    "sfomuseum:subcategory":"Brochure, Airline",
    "wof:depicts":[
        1159285043
    ],
    "wof:name":"brochure: Qantas Airways",
    "wof:placetype":"venue"
},
  "geometry": {"coordinates":[-122.386155,37.616357],"type":"Point"}
}