{
  "type": "Feature",
  "properties": {
    "date:cessation_lower": "1965-01-01",
    "date:cessation_upper": "1965-12-31",
    "date:inception_lower": "1965-01-01",
    "date:inception_upper": "1965-12-31",
    "iso:country": "XX",
    "millsfield:images": [
      1527846767,
      1527850603
    ],
    "millsfield:images_texts": [
      "EFFECTIVE FEBRUARY 15, 1965\nNATIONAL\nAIRLINES\nSYSTEM TIMETABLE\nThis symbol is your assurance\nof the sumptuous meals, ready smiles\nand honest effort we make to provide\nyou with the finest in air transportation\ncoast to coast to coast.",
      "PACIFIC\nMOUNTAIN\nstandard\nstandard\nCENTRAL\n→3\nstandard\nEASTERN\nstandard\nBOSTON\n/Providence\nSAN FRANCISCO/\nOAKLAND\nLAS VEGAS.\nLOS ANGELES /\nLONG BEACH\nNEW ORLEANS\nHOUSTON\nSAN DIEGO\nNEW YORK\nNewark\nPHILADELPHIA\nBaltimore\nWASHINGTON\nRichmond\nNewport News / Hampton\nNorfolk\nCharleston\nSavannah\nTallahassee\nPanama City\nPensacola\nMobile\nJACKSONVILLE\nOrlando\nDaytona Beach\nCAPE KENNEDY\nMelbourne\nTAMPA/ST. PETERSBURG\nPalm Beach\nClearwater\nLakeland\nBradenton\nMIAMI/ FT. LAUDERDALE\nKey West\nFt. Myers\nBalboa * Panama City\n• Cali\n• Quito\n' Guayaquil\n• Lima\nSantiago\nAntofagasta\n* Buenos Aires\nNational Airlines, Inc., Certificated Routes-\nThru-Plane Service. National, Pan Am, Panagra _----\nJET NATIONAL I\nCoast to Coast to Coast"
    ],
    "millsfield:images_texts_ids": [
      1527846767,
      1527850603
    ],
    "millsfield:primary_image": 1527846767,
    "sfomuseum:accession_number": "2005.132.030.016",
    "sfomuseum:airline": "National Airlines",
    "sfomuseum:category": "Scheduling / Ticketing",
    "sfomuseum:collection": "Aviation Archive",
    "sfomuseum:creditline": "Gift of the William Hough Collection",
    "sfomuseum:date": "1965",
    "sfomuseum:date_acquired": "2006-12-05",
    "sfomuseum:daterange_end": "1965-12-31",
    "sfomuseum:daterange_start": "1965-01-01",
    "sfomuseum:description": "System timetable issued by National Airlines, effective February 15, 1965; 19-page fold-out; white cover with logo at center.",
    "sfomuseum:dimensions": "9 x 4 inches (22.9 x 10.2 cm)",
    "sfomuseum:media_ids": [
      1527846767,
      1527850603
    ],
    "sfomuseum:medium": "paper, ink",
    "sfomuseum:placetype": "object",
    "sfomuseum:publication": ": , 1965.",
    "sfomuseum:subcategory": "Timetable",
    "wof:depicts": [
      1159284841,
      1159288429
    ],
    "wof:name": "timetable: National Airlines",
    "wof:placetype": "custom",
    "wof:placetype_alt": "object"
  },
  "geometry": {"coordinates":[-122.386155,37.616357],"type":"Point"}
}
