{
  "type": "Feature",
  "properties": {
    "date:cessation_lower": "1957-12-31",
    "date:cessation_upper": "1957-12-31",
    "date:inception_lower": "1957-01-01",
    "date:inception_upper": "1957-01-01",
    "iso:country": "XX",
    "millsfield:images": [
      1527844253
    ],
    "sfomuseum:accession_number": "2001.106.420",
    "sfomuseum:airline": "British European Airways (BEA)",
    "sfomuseum:category": "Scheduling / Ticketing",
    "sfomuseum:collection": "Aviation Archive",
    "sfomuseum:creditline": "Gift of Mark F. Adams Collection",
    "sfomuseum:date": "1957",
    "sfomuseum:daterange_end": "1957-12-31",
    "sfomuseum:daterange_start": "1957-01-01",
    "sfomuseum:description": "Proposed Services Summer 1957 timetable issued by British European Airways (BEA), effective April 14, 1957; red with picture of a Viscount aircraft.",
    "sfomuseum:media_ids": [
      1527844253
    ],
    "sfomuseum:medium": "paper, ink",
    "sfomuseum:placetype": "object",
    "sfomuseum:subcategory": "Timetable",
    "wof:depicts": [
      1159284027
    ],
    "wof:name": "timetable: British European Airways (BEA), summer schedule",
    "wof:placetype": "venue"
  },
  "geometry": {"coordinates":[-122.386155,37.616357],"type":"Point"}
}
