{
  "type": "Feature",
  "properties": {
    "date:cessation_lower": "1957-01-01",
    "date:cessation_upper": "1957-12-31",
    "date:inception_lower": "1957-01-01",
    "date:inception_upper": "1957-12-31",
    "iso:country": "XX",
    "millsfield:images": [
      1527847927,
      1527847931,
      1527847933
    ],
    "millsfield:images_texts": [
      "Califormian\nChampagne Flights\nWESTERN AIRLINES",
      "MEN\nChampagne Cocktails\nSeafood Superbé\nSalad Escoffier\nDressing\nFilet Mignon - Mushroom Cap\nPotatoes Maison\nVegetable du jour\nDinner Roll\nCreamery Butter\nCalifornian Dessert\nCoffee\nTea\nMilk\nButter Mints\nChampagne from the choicest private stocks\nof the Italian Swiss Colony Wine Company.\nfron out i o o mate a pearl mite Wester, your stewardess\nwooters compriments.\nWESTERN AIRLINES",
      "SEATTLE O\nPORTLANDS\nGREAT FALLS\nFRANCISCULO\nDAKLAND\naboard a\nWESTERN AIRLINES\nchampagne flight\nPOST CARD\nMEXICO CITY O\n1999.035.004"
    ],
    "millsfield:images_texts_ids": [
      1527847927,
      1527847931,
      1527847933
    ],
    "millsfield:primary_image": 1527847927,
    "sfomuseum:accession_number": "1999.035.004",
    "sfomuseum:airline": "Western Airlines",
    "sfomuseum:category": "Passenger Amenity, Archive",
    "sfomuseum:collection": "Aviation Archive",
    "sfomuseum:continent": "World Routes",
    "sfomuseum:creditline": "Gift of Jim McDonald",
    "sfomuseum:date": "c. 1957",
    "sfomuseum:date_acquired": "1999-04-11",
    "sfomuseum:daterange_end": "1962-12-31",
    "sfomuseum:daterange_start": "1952-01-01",
    "sfomuseum:description": "Menu issued by Western Airlines; pink cover with illustration of a champagne glass and grapes; menu items include filet mignon and potatoes maison; menu number: 3; undated.",
    "sfomuseum:dimensions": "6 x 5 inches (15.2 x 12.7 cm)",
    "sfomuseum:media_ids": [
      1527847927,
      1527847931,
      1527847933
    ],
    "sfomuseum:medium": "paper, ink",
    "sfomuseum:placetype": "object",
    "sfomuseum:publication": ": , c. 1957.",
    "sfomuseum:subcategory": "Menu",
    "wof:depicts": [
      1159294431,
      1159287595
    ],
    "wof:name": "menu: Western Airlines",
    "wof:placetype": "custom",
    "wof:placetype_alt": "object"
  },
  "geometry": {"coordinates":[-122.386155,37.616357],"type":"Point"}
}
