{
  "type": "Feature",
  "properties": {
    "iso:country": "XX",
    "sfomuseum:accession_number": "2012.147.384",
    "sfomuseum:airline": "CSA (Ceske Aerolinie)  (CSA (Czech Airlines))",
    "sfomuseum:category": "Insignia",
    "sfomuseum:collection": "Aviation Museum",
    "sfomuseum:creditline": "Gift of the Captain John B. Russell Family",
    "sfomuseum:description": "Gold double-wing pin with yellow, navy blue and red shield on center, three small stars on top; two short posts with one lift back on back.",
    "sfomuseum:medium": "metal, enamel",
    "sfomuseum:placetype": "object",
    "sfomuseum:subcategory": "Hat Badge, Flight Crew",
    "wof:depicts": [
      1159285655
    ],
    "wof:name": "flight officer wings: CSA (Ceske Aerolinie)",
    "wof:placetype": "venue"
  },
  "geometry": {"coordinates":[-122.386155,37.616357],"type":"Point"}
}
