{
  "type": "Feature",
  "properties": {
    "date:cessation_lower": "1975-01-01",
    "date:cessation_upper": "1975-12-31",
    "date:inception_lower": "1975-01-01",
    "date:inception_upper": "1975-12-31",
    "iso:country": "XX",
    "millsfield:images": [
      1527853917,
      1527853919,
      1527858611
    ],
    "millsfield:primary_image": 1527858611,
    "sfomuseum:accession_number": "2012.042.016",
    "sfomuseum:airline": "Air Siam",
    "sfomuseum:category": "Scheduling / Ticketing",
    "sfomuseum:collection": "Aviation Archive",
    "sfomuseum:creditline": "Transfer",
    "sfomuseum:date": "1975",
    "sfomuseum:date_acquired": "2012-02-29",
    "sfomuseum:daterange_end": "1975-12-31",
    "sfomuseum:daterange_start": "1975-01-01",
    "sfomuseum:description": "Passenger ticket and baggage check issued by Air Siam, serial number 1552-091914; white and blue cover with red and white “ID 1”.",
    "sfomuseum:dimensions": "3 1/4 x 8 1/2 inches (8.3 x 21.6 cm)",
    "sfomuseum:media_ids": [
      1527853917,
      1527853919,
      1527858611
    ],
    "sfomuseum:medium": "paper, ink",
    "sfomuseum:placetype": "object",
    "sfomuseum:publication": ": , 1975.",
    "sfomuseum:subcategory": "Ticket Jacket / Ticket",
    "wof:depicts": [
      1159283739
    ],
    "wof:name": "ticket: Air Siam",
    "wof:placetype": "venue"
  },
  "geometry": {"coordinates":[-122.386155,37.616357],"type":"Point"}
}
