{
  "type": "Feature",
  "properties": {
    "date:cessation_lower": "2005-12-31",
    "date:cessation_upper": "2005-12-31",
    "date:inception_lower": "2005-01-01",
    "date:inception_upper": "2005-01-01",
    "iso:country": "XX",
    "millsfield:images": [
      1527844961,
      1527844957
    ],
    "sfomuseum:accession_number": "2011.046.048",
    "sfomuseum:airline": "Lufthansa  (Lufthansa German Airlines)",
    "sfomuseum:category": "Passenger Amenity",
    "sfomuseum:collection": "Aviation Archive",
    "sfomuseum:creditline": "Gift of Hans and Margret Steuck",
    "sfomuseum:date": "2005",
    "sfomuseum:daterange_end": "2005-12-31",
    "sfomuseum:daterange_start": "2005-01-01",
    "sfomuseum:description": "Beverage menu issued by Lufthansa German Airlines; white cover with raised outline of wine glass; menu number: 600W100-B; class: first; date: 3/05-4/05",
    "sfomuseum:media_ids": [
      1527844957,
      1527844961
    ],
    "sfomuseum:medium": "paper, ink",
    "sfomuseum:placetype": "object",
    "sfomuseum:subcategory": "Menu",
    "wof:depicts": [
      1159284711
    ],
    "wof:name": "menu: Lufthansa German Airlines, First Class",
    "wof:placetype": "venue"
  },
  "geometry": {"coordinates":[-122.386155,37.616357],"type":"Point"}
}
