{
  "type": "Feature",
  "properties": {
    "date:cessation_lower": "1970-12-31",
    "date:cessation_upper": "1970-12-31",
    "date:inception_lower": "1970-01-01",
    "date:inception_upper": "1970-01-01",
    "iso:country": "XX",
    "sfomuseum:accession_number": "2002.127.007",
    "sfomuseum:category": "Passenger Amenity",
    "sfomuseum:collection": "Aviation Archive",
    "sfomuseum:creditline": "Gift of Thomas G. Dragges",
    "sfomuseum:date": "1970s",
    "sfomuseum:daterange_end": "1970-12-31",
    "sfomuseum:daterange_start": "1970-01-01",
    "sfomuseum:description": "Safety information card produced by Aer Lingus for its Boeing 737 fleet; white in center with green bands of color along bottom and top edge; airline name along top right edge in black; \"B737\" in bold letters located top right corner; illustrations demonstrate safety and emergency procedures.\r",
    "sfomuseum:media_ids": [
      1527850019, 
      1527850021
    ],
    "sfomuseum:medium": "paper, plastic laminate",
    "sfomuseum:placetype": "object",
    "sfomuseum:subcategory": "Safety Information Card",
    "wof:name": "safety information card: Aer Lingus, Boeing 737",
    "wof:placetype": "venue"
  },
  "geometry": {"coordinates":[-122.386155,37.616358],"type":"Point"}
}
