{
  "type": "Feature",
  "properties": {
    "date:cessation_lower": "1970-01-01",
    "date:cessation_upper": "1979-12-31",
    "date:inception_lower": "1970-01-01",
    "date:inception_upper": "1979-12-31",
    "iso:country": "XX",
    "millsfield:images": [
      1527850019,
      1527850021
    ],
    "millsfield:primary_image": 1527850019,
    "sfomuseum:accession_number": "2002.127.007",
    "sfomuseum:aircraft": "Boeing 737",
    "sfomuseum:airline": "Aer Lingus",
    "sfomuseum:category": "Passenger Amenity",
    "sfomuseum:collection": "Aviation Archive",
    "sfomuseum:creditline": "Gift of Thomas G. Dragges",
    "sfomuseum:date": "1970s",
    "sfomuseum:date_acquired": "2003-12-22",
    "sfomuseum:daterange_end": "1970-12-31",
    "sfomuseum:daterange_start": "1970-01-01",
    "sfomuseum:description": "Safety information card issued by Aer Lingus for its Boeing 737 fleet; white and green double-sided card; illustrations demonstrating safety instructions and emergency procedures.",
    "sfomuseum:dimensions": "11 x 8 1/2 inches (27.9 x 21.6 cm)",
    "sfomuseum:media_ids": [
      1527850019,
      1527850021
    ],
    "sfomuseum:medium": "paper, plastic, ink",
    "sfomuseum:placetype": "object",
    "sfomuseum:publication": ": , 1970s.",
    "sfomuseum:subcategory": "Safety Information Card",
    "wof:depicts": [
      1159288269,
      1159289819,
      1159293593,
      1159283495
    ],
    "wof:name": "safety information card: Aer Lingus, Boeing 737",
    "wof:placetype": "custom"
  },
  "geometry": {"coordinates":[-122.386155,37.616357],"type":"Point"}
}
