{
  "type": "Feature",
  "properties": {
    "date:cessation_lower": "1981-01-01",
    "date:cessation_upper": "1981-12-31",
    "date:inception_lower": "1981-01-01",
    "date:inception_upper": "1981-12-31",
    "iso:country": "XX",
    "sfomuseum:accession_number": "00-2592",
    "sfomuseum:author": "Air-Britain (Historians)",
    "sfomuseum:callnumber": "HE9769.G7 U55 1981",
    "sfomuseum:category": "Book",
    "sfomuseum:collection": "Aviation Library",
    "sfomuseum:date": "1981",
    "sfomuseum:daterange_end": "1981-12-31",
    "sfomuseum:daterange_start": "1981-01-01",
    "sfomuseum:description": "v. : ill. ; 24 cm.",
    "sfomuseum:description_library": "v. : ill. ; 24 cm.",
    "sfomuseum:medium": "paper, ink",
    "sfomuseum:notes_library": "Vols. for \u003c1988-\u003e compiled by Malcolm P. Fillmore.Description based on: 1988; title from cover.",
    "sfomuseum:placetype": "object",
    "sfomuseum:publication": "Tonbridge, Kent , England: Air-Britain (Historians), 1981.",
    "sfomuseum:publisher": "Air-Britain (Historians)",
    "sfomuseum:publisher_location": "Tonbridge, Kent , England",
    "sfomuseum:subcategory": "Book",
    "sfomuseum:subject": "Airplanes Ireland Registers Periodicals.Airplanes Great Britain Registers Periodicals.",
    "wof:name": "United Kingdom and Ireland civil aircraft registers",
    "wof:placetype": "venue"
  },
  "geometry": {"coordinates":[-122.386155,37.616357],"type":"Point"}
}
