{
  "type": "Feature",
  "properties": {
    "date:cessation_lower": "1955-01-01",
    "date:cessation_upper": "1955-12-31",
    "date:inception_lower": "1955-01-01",
    "date:inception_upper": "1955-12-31",
    "iso:country": "XX",
    "millsfield:images": [
      1527848115,
      1527848117
    ],
    "millsfield:primary_image": 1527848115,
    "sfomuseum:accession_number": "2002.113.418",
    "sfomuseum:airline": "TWA (Trans World Airlines)",
    "sfomuseum:artist": "David Klein",
    "sfomuseum:category": "Passenger Amenity",
    "sfomuseum:collection": "Aviation Archive",
    "sfomuseum:creditline": "Gift of TWA Clipped Wings International",
    "sfomuseum:date": "c. 1955",
    "sfomuseum:date_acquired": "2004-12-08",
    "sfomuseum:daterange_end": "1960-12-31",
    "sfomuseum:daterange_start": "1950-01-01",
    "sfomuseum:description": "Menu issued by TWA (Trans World Airlines); blue cover with color illustration of the Water Tower (Chicago); menu items include filet of beef Zurichoise, loin of pork Kowloon, and barbecued chicken; menu number: D-95 / 101; undated.",
    "sfomuseum:dimensions": "7 x 5 inches (17.8 x 12.7 cm)",
    "sfomuseum:media_ids": [
      1527848115,
      1527848117
    ],
    "sfomuseum:medium": "paper, ink",
    "sfomuseum:placetype": "object",
    "sfomuseum:publication": ": , c. 1955.",
    "sfomuseum:subcategory": "Menu",
    "wof:depicts": [
      1159285393,
      1159287531
    ],
    "wof:name": "menu: TWA (Trans World Airlines)",
    "wof:placetype": "custom",
    "wof:placetype_alt": "object"
  },
  "geometry": {"coordinates":[-122.386155,37.616357],"type":"Point"}
}
