{
  "type": "Feature",
  "properties": {
    "date:cessation_lower": "1984-12-31",
    "date:cessation_upper": "1984-12-31",
    "date:inception_lower": "1984-01-01",
    "date:inception_upper": "1984-01-01",
    "iso:country": "XX",
    "millsfield:images": [
      1527851407,
      1527849741
    ],
    "sfomuseum:accession_number": "2003.105.114.003",
    "sfomuseum:airline": "Wien Air Alaska",
    "sfomuseum:category": "Scheduling / Ticketing",
    "sfomuseum:collection": "Aviation Archive",
    "sfomuseum:creditline": "Gift of Craig Lynes",
    "sfomuseum:date": "1984",
    "sfomuseum:daterange_end": "1984-12-31",
    "sfomuseum:daterange_start": "1984-01-01",
    "sfomuseum:description": "System timetable issued by Wien Air Alaska, effective September 1, 1984; twenty-five page schedule. The cover is dark blue with full color photographic image of Seattle skyline.",
    "sfomuseum:media_ids": [
      1527849741,
      1527851407
    ],
    "sfomuseum:medium": "paper, ink",
    "sfomuseum:placetype": "object",
    "sfomuseum:subcategory": "Timetable",
    "wof:depicts": [
      1159285529
    ],
    "wof:name": "timetable: Wien Air Alaska",
    "wof:placetype": "venue"
  },
  "geometry": {"coordinates":[-122.386155,37.616357],"type":"Point"}
}
