{
  "type": "Feature",
  "properties": {
    "date:cessation_lower": "2015-12-31",
    "date:cessation_upper": "2015-12-31",
    "date:inception_lower": "2015-01-01",
    "date:inception_upper": "2015-01-01",
    "iso:country": "XX",
    "sfomuseum:accession_number": "2017.048.010",
    "sfomuseum:aircraft": "Airbus A320",
    "sfomuseum:airline": "Virgin America",
    "sfomuseum:category": "Passenger Amenity",
    "sfomuseum:collection": "Aviation Archive",
    "sfomuseum:creditline": "Gift of Carolyn Gale",
    "sfomuseum:date": "2015",
    "sfomuseum:daterange_end": "2015-12-31",
    "sfomuseum:daterange_start": "2015-01-01",
    "sfomuseum:description": "Safety information card issued by Virgin America for Airbus A320 fleet; tri-fold format with purple cover and illustration depicting red and white empennage section of aircraft; contains sequential graphics displaying in-flight emergency procedures; exit seating assignment information on reverse; Revision 1 - September 2015.",
    "sfomuseum:medium": "paper, ink",
    "sfomuseum:placetype": "object",
    "sfomuseum:subcategory": "Safety Information Card",
    "wof:depicts": [
      1159285481,
      1159289409
    ],
    "wof:name": "safety information card: Virgin America, Airbus A320",
    "wof:placetype": "venue"
  },
  "geometry": {"coordinates":[-122.386155,37.616357],"type":"Point"}
}
