{
  "type": "Feature",
  "properties": {
    "date:cessation_lower": "2015-01-01",
    "date:cessation_upper": "2015-12-31",
    "date:inception_lower": "2015-01-01",
    "date:inception_upper": "2015-12-31",
    "iso:country": "XX",
    "millsfield:images": [
      1729566763
    ],
    "millsfield:images_texts": [
      "A320\nSAFETY INSTRUCTIONS\nINFORMACIÓN DE SEGURIDAD\nETOPS\nCERTIFIED\nVirgin\nFEDFRAEREGULATIONS RECURE COMPLIANCE WIR CREW INSTRUCTIONS LIGHTED\nGUEST INFORMATION SIGNS AND POSTED PLAÇARDS AT ALL TIMES. FOR YOUR SAFETY.\nGUESTS MUST COMPLY WITH THE FASTEN SEAT BELT SIGN AND IT IS RECOMMENDED\nSHALYOU KEEP YOUR SEATBLE -AS ENG AFALL IM WHERSATED-YOU ARE\nSEATED IN AN EXIT SEAT AND DO NOT UNDERSTAND ENGLISH OR THE INFORMATION\nON THIS CARD, PLEASE IDENTIFY YOURSELF TO AN INFLIGHT TEAMMATE FOR\nREStATING. DO NOTREMOVE THIS CARD FROM THE AIRCKAR\nNigin\namerica"
    ],
    "millsfield:images_texts_ids": [
      1729566763
    ],
    "millsfield:primary_image": 1729566763,
    "sfomuseum:accession_number": "2017.048.010",
    "sfomuseum:aircraft": "Airbus A320",
    "sfomuseum:airline": "Virgin America",
    "sfomuseum:category": "Passenger Amenity, Archive",
    "sfomuseum:collection": "Aviation Archive",
    "sfomuseum:creditline": "Anonymous gift",
    "sfomuseum:date": "2015",
    "sfomuseum:date_acquired": "2017-06-27",
    "sfomuseum:daterange_end": "2015-12-31",
    "sfomuseum:daterange_start": "2015-01-01",
    "sfomuseum:description": "Safety information card issued by Virgin America for its Airbus A320 fleet; purple double-sided tri-fold card with illustrations demonstrating inflight safety and emergency procedures; identification code: Revision 1; revision date: September 2015.",
    "sfomuseum:dimensions": "11 x 7 1/2 inches (27.9 x 19.1 cm)",
    "sfomuseum:medium": "paper, ink",
    "sfomuseum:placetype": "object",
    "sfomuseum:publication": ": , 2015.",
    "sfomuseum:subcategory": "Safety Information Card",
    "wof:depicts": [
      1159293829,
      1159289409,
      1159285481,
      1159288091
    ],
    "wof:name": "safety information card: Virgin America, Airbus A320",
    "wof:placetype": "custom",
    "wof:placetype_alt": [
      "object"
    ]
  },
  "geometry": {"coordinates":[-122.386155,37.616357],"type":"Point"}
}
