{
  "type": "Feature",
  "properties": {
    "date:cessation_lower": "1995-01-01",
    "date:cessation_upper": "1995-12-31",
    "date:inception_lower": "1995-01-01",
    "date:inception_upper": "1995-12-31",
    "iso:country": "XX",
    "sfomuseum:accession_number": "1997.76.02 a m",
    "sfomuseum:airline": "United Airlines",
    "sfomuseum:category": "Passenger Amenity, Museum",
    "sfomuseum:collection": "Aviation Archive",
    "sfomuseum:continent": "Transatlantic",
    "sfomuseum:country": "England",
    "sfomuseum:creditline": "Gift of Elsa Cameron",
    "sfomuseum:date": "c. 1995",
    "sfomuseum:daterange_end": "2000-12-31",
    "sfomuseum:daterange_start": "1990-01-01",
    "sfomuseum:description": "Amenity kit issued by United Airlines; unused; in multiple parts:\ra. blue amenity kit cover with top zipper closure;.\rb. sleep socks with paper band;\rc. sleep mask;\rd. toothbrush;\re. toothpaste;\rf. dental-pick;\rg. mouthwash;\rh. body lotion by Molton Brown;\ri. lip balm by Molton Brown;\rj. earplugs;\rk. tissues\rl. emery board;\rm. razor request card.",
    "sfomuseum:dimensions": "5 x 8 1/4 x 2 1/2 inches (12.7 x 21 x 6.4 cm)",
    "sfomuseum:maker": "United Air Lines, Inc.",
    "sfomuseum:medium": "polyester fabric, contents",
    "sfomuseum:placetype": "object",
    "sfomuseum:subcategory": "Amenity Kit",
    "wof:depicts": [
      1159285413
    ],
    "wof:name": "amenity kit: United Airlines",
    "wof:placetype": "venue"
  },
  "geometry": {"coordinates":[-122.386155,37.616358],"type":"Point"}
}
