{
  "type": "Feature",
  "properties": {
    "date:cessation_lower": "2002-12-31",
    "date:cessation_upper": "2002-12-31",
    "date:inception_lower": "1992-01-01",
    "date:inception_upper": "1992-01-01",
    "iso:country": "XX",
    "sfomuseum:accession_number": "1997.76.02 a m",
    "sfomuseum:category": "Passenger Amenity",
    "sfomuseum:collection": "Aviation Museum",
    "sfomuseum:continent": "Transatlantic",
    "sfomuseum:country": "England",
    "sfomuseum:creditline": "Gift of Elsa Cameron",
    "sfomuseum:date": "c. 1997",
    "sfomuseum:daterange_end": "2002-12-31",
    "sfomuseum:daterange_start": "1992-01-01",
    "sfomuseum:description": "Amenity kit produced by United Airlines with multiple parts:\ra. Half moon shape navy blue textured bag with top zipper, navy blue acetate lining.\rb. Pair of navy blue sleep socks with a navy blue paper band with small double “U” airline logo with “United Airlines” on center.\rc. Sealed small clear plastic package with small double “U” airline logo with “United Airlines” near top edge, white paper tissues. \rd. Navy blue sleep mask in a clear plastic sleeve, small navy blue paper tag with white double “U” airline logo on edge of sleep mask.\re. Sealed in clear plastic bag, black plastic toothbrush.\rf. Black and white emory board. \rg. Dark gray paper packet with small white double “U” airline logo and “United Airlines” on center, containing a toothpick and floss. \rh. White plastic tube of Rembrandt whitening toothpaste.\ri. Small clear plastic bottle of Rembrandt mouth rinse.\rj. Pair of earplugs in white paper container, small navy blue double “U” and “United Airlines” on center.\rk. Small clear plastic bottle of Molton Brown body lotion.\rl. Small short plastic jar of Molton Brown lip balm.\rm. Razor request card.",
    "sfomuseum:maker": "United Air Lines, Inc.",
    "sfomuseum:medium": "polyester fabric, contents",
    "sfomuseum:placetype": "object",
    "sfomuseum:subcategory": "Amenity Kit",
    "wof:name": "amenity kit: United Airlines",
    "wof:placetype": "venue"
  },
  "geometry": {"coordinates":[-122.386155,37.616358],"type":"Point"}
}
