{
  "type": "Feature",
  "properties": {
    "date:cessation_lower": "1975-12-31",
    "date:cessation_upper": "1975-12-31",
    "date:inception_lower": "1975-01-01",
    "date:inception_upper": "1975-01-01",
    "iso:country": "XX",
    "millsfield:images": [
      1527822187
    ],
    "sfomuseum:accession_number": "2012.096.221",
    "sfomuseum:airport": "San Francisco International Airport",
    "sfomuseum:category": "Design",
    "sfomuseum:collection": "Aviation Archive",
    "sfomuseum:creditline": "Gift of the William Hough Collection",
    "sfomuseum:date": "1975",
    "sfomuseum:daterange_end": "1975-12-31",
    "sfomuseum:daterange_start": "1975-01-01",
    "sfomuseum:description": "Black and white aerial image of San Francisco International Airport terminal and surrounding area. ",
    "sfomuseum:dimensions": "42 1/4 x 47 inches (107.3 x 119.4 cm)",
    "sfomuseum:issues_held": "1988 (Mar, May, Aug)\r1990 (Aug)",
    "sfomuseum:media_ids": [
      1527822187
    ],
    "sfomuseum:medium": "paper, ink",
    "sfomuseum:placetype": "object",
    "sfomuseum:publisher": "Mediacom S. A",
    "sfomuseum:publisher_location": "Geneva, Switzerland",
    "sfomuseum:subcategory": "Architectural Design Drawing",
    "wof:depicts": [
      102527513
    ],
    "wof:name": "photographic design drawing: San Francisco International Airport",
    "wof:placetype": "venue"
  },
  "geometry": {"coordinates":[-122.386155,37.616357],"type":"Point"}
}
