{
  "type": "Feature",
  "properties": {
    "date:cessation_lower": "1985-01-01",
    "date:cessation_upper": "1985-12-31",
    "date:inception_lower": "1985-01-01",
    "date:inception_upper": "1985-12-31",
    "iso:country": "CN",
    "millsfield:images": [
      1527843625,
      1527843629
    ],
    "millsfield:primary_image": 1527843625,
    "sfomuseum:accession_number": "1996.25.01",
    "sfomuseum:airline": "Cathay Pacific Airways",
    "sfomuseum:category": "Passenger Amenity, Archive",
    "sfomuseum:collection": "Aviation Archive",
    "sfomuseum:continent": "Asia",
    "sfomuseum:country": "China",
    "sfomuseum:creditline": "Gift of Mrs. Thelma Cain",
    "sfomuseum:date": "1985",
    "sfomuseum:date_acquired": "1999-07-13",
    "sfomuseum:daterange_end": "1985-12-31",
    "sfomuseum:daterange_start": "1985-01-01",
    "sfomuseum:description": "Menu issued by Cathay Pacific Airways, Hong Kong - Bangkok route; green cover with color illustration of a landscape with pagoda; menu items include lobster in cider cream and stir fried pork; menu number: CX703C-133 E/Y; undated.",
    "sfomuseum:dimensions": "8 1/2 x 5 1/2 inches (21.6 x 14 cm)",
    "sfomuseum:maker": "Cathay Pacific Airways, Ltd., The Swire Group",
    "sfomuseum:media_ids": [
      1527843625,
      1527843629
    ],
    "sfomuseum:medium": "paper, ink, string",
    "sfomuseum:placetype": "object",
    "sfomuseum:publication": ": , 1985.",
    "sfomuseum:subcategory": "Menu",
    "wof:depicts": [
      1159286837,
      1159284127
    ],
    "wof:name": "menu: Cathay Pacific Airways",
    "wof:placetype": "custom",
    "wof:placetype_alt": "object"
  },
  "geometry": {"coordinates":[-122.386155,37.616357],"type":"Point"}
}
