{
  "type": "Feature",
  "properties": {
    "date:cessation_lower":"1985-12-31",
    "date:cessation_upper":"1985-12-31",
    "date:inception_lower":"1985-01-01",
    "date:inception_upper":"1985-01-01",
    "iso:country":"CN",
    "millsfield:images":[
        1527843629,
        1527843625
    ],
    "sfomuseum:accession_number":"1996.25.01",
    "sfomuseum:airline":"Cathay Pacific Airways",
    "sfomuseum:category":"Passenger Amenity",
    "sfomuseum:collection":"Aviation Archive",
    "sfomuseum:continent":"Asia",
    "sfomuseum:country":"China",
    "sfomuseum:creditline":"Gift of Mrs. Thelma Cain",
    "sfomuseum:date":"1985",
    "sfomuseum:daterange_end":"1985-12-31",
    "sfomuseum:daterange_start":"1985-01-01",
    "sfomuseum:description":"Menu issued by Cathay Pacific Airways, Hong Kong - Bangkok route; green cover with color illustration of a landscape with pagoda; menu items include lobster in cider cream and stir fried pork; menu number: CX703C-133 E/Y; undated.",
    "sfomuseum:maker":"Cathay Pacific Airways, Ltd., The Swire Group",
    "sfomuseum:media_ids":[
        1527843625,
        1527843629
    ],
    "sfomuseum:medium":"paper, ink, string",
    "sfomuseum:placetype":"object",
    "sfomuseum:subcategory":"Menu",
    "wof:depicts":[
        1159284127
    ],
    "wof:name":"menu: Cathay Pacific Airways",
    "wof:placetype":"venue"
},
  "geometry": {"coordinates":[-122.386155,37.616357],"type":"Point"}
}