{
  "type": "Feature",
  "properties": {
    "date:cessation_lower":"1985-12-31",
    "date:cessation_upper":"1985-12-31",
    "date:inception_lower":"1975-01-01",
    "date:inception_upper":"1975-01-01",
    "iso:country":"XX",
    "sfomuseum:accession_number":"2013.057.028",
    "sfomuseum:category":"Employee Career History",
    "sfomuseum:collection":"Aviation Archive",
    "sfomuseum:creditline":"Gift of the Estate of Audrey McNamara Nevis",
    "sfomuseum:date":"c. 1980",
    "sfomuseum:daterange_end":"1985-12-31",
    "sfomuseum:daterange_start":"1975-01-01",
    "sfomuseum:description":"Employee identification card issued by TWA (Trans World Airlines) to flight attendant Audrey McNamara Nevis, expiration date December 1980; white and light blue background with color photographic identification at upper left.",
    "sfomuseum:medium":"plastic",
    "sfomuseum:placetype":"object",
    "sfomuseum:subcategory":"Identification",
    "wof:name":"employee identification card: TWA (Trans World Airlines), Audrey McNamara Nevis",
    "wof:placetype":"venue"
},
  "geometry": {"coordinates":[-122.386155,37.616358],"type":"Point"}
}