{
  "type": "Feature",
  "properties": {
    "date:cessation_lower": "1996-01-01",
    "date:cessation_upper": "1996-12-31",
    "date:inception_lower": "1996-01-01",
    "date:inception_upper": "1996-12-31",
    "iso:country": "SV",
    "millsfield:images": [
      1527857437,
      1527857439,
      1527857441,
      1527857443,
      1527857445,
      1527857447
    ],
    "millsfield:images_texts": [
      "762\nTACA",
      "767\n00000000000 0000",
      "THER\n767",
      "TRER"
    ],
    "millsfield:images_texts_ids": [
      1527857437,
      1527857439,
      1527857443,
      1527857445
    ],
    "millsfield:primary_image": 1527857437,
    "sfomuseum:accession_number": "1996.23.01 a b",
    "sfomuseum:aircraft": "Boeing 767",
    "sfomuseum:airline": "TACA International Airlines",
    "sfomuseum:category": "Model Aircraft",
    "sfomuseum:collection": "Aviation Museum",
    "sfomuseum:continent": "North America",
    "sfomuseum:country": "El Salvador",
    "sfomuseum:creditline": "Gift of TACA International Airlines",
    "sfomuseum:date": "1996",
    "sfomuseum:date_acquired": "1998-02-23",
    "sfomuseum:daterange_end": "1996-12-31",
    "sfomuseum:daterange_start": "1996-01-01",
    "sfomuseum:description": "Model airplane of TACA International Airlines, Boeing 767; \ra. white fuselage with blue, red and yellow cheatline extending to vertical stabilizer; white “TACA” lgotype on vertical stabilizer;\rb. wood stand with metal arm.",
    "sfomuseum:dimensions": "8 3/4 x 19 1/2 x 18 3/4 inches (22.2 x 49.5 x 47.6 cm)",
    "sfomuseum:media_ids": [
      1527857437,
      1527857439,
      1527857441,
      1527857443,
      1527857445,
      1527857447
    ],
    "sfomuseum:medium": "plastic, wood, metal and paint",
    "sfomuseum:placetype": "object",
    "sfomuseum:publication": ": , 1996.",
    "sfomuseum:subcategory": "Model Airplane",
    "wof:depicts": [
      1159289949,
      1159293593,
      1159288637,
      1159285255
    ],
    "wof:name": "model airplane: TACA International Airlines, Boeing 767",
    "wof:placetype": "custom",
    "wof:placetype_alt": "object"
  },
  "geometry": {"coordinates":[-122.386155,37.616357],"type":"Point"}
}
