{
  "type": "Feature",
  "properties": {
    "date:cessation_lower": "1956-01-01",
    "date:cessation_upper": "1956-12-31",
    "date:inception_lower": "1956-01-01",
    "date:inception_upper": "1956-12-31",
    "iso:country": "XX",
    "sfomuseum:accession_number": "1999.669.174",
    "sfomuseum:author": "Farley, Edward J.",
    "sfomuseum:callnumber": "UG633 .F33 1956",
    "sfomuseum:category": "Book",
    "sfomuseum:collection": "Aviation Library",
    "sfomuseum:creditline": "Purchase",
    "sfomuseum:date": "c. 1956",
    "sfomuseum:daterange_end": "1961-12-31",
    "sfomuseum:daterange_start": "1951-01-01",
    "sfomuseum:description": "1 v. (unpaged, chiefly ill.) ; 23 cm.",
    "sfomuseum:description_library": "1 v. (unpaged, chiefly ill.) ; 23 cm.",
    "sfomuseum:medium": "paper, ink",
    "sfomuseum:placetype": "object",
    "sfomuseum:publication": "Jacksonville, FL: Edward J. Farley, c. 1956.",
    "sfomuseum:publisher": "Edward J. Farley",
    "sfomuseum:publisher_location": "Jacksonville, FL",
    "sfomuseum:subcategory": "Book",
    "sfomuseum:subject": "Aeronautics, Military United States.Airplanes, Military.",
    "wof:name": "U.S. Army-U.S. Air Force fighter planes: P-1 to F-100",
    "wof:placetype": "custom",
    "wof:placetype_alt": "object"
  },
  "geometry": {"coordinates":[-122.386155,37.616357],"type":"Point"}
}
