{
  "type": "Feature",
  "properties": {
    "date:cessation_lower": "1950-01-01",
    "date:cessation_upper": "1959-12-31",
    "date:inception_lower": "1950-01-01",
    "date:inception_upper": "1959-12-31",
    "iso:country": "XX",
    "millsfield:images": [
      1527857115,
      1527857117
    ],
    "millsfield:images_texts": [
      "PAA\nPAN AMERICAN WORLD AIRWAYS",
      "PAA\nPAN AMERICAN WORLD AIRWAYS"
    ],
    "millsfield:images_texts_ids": [
      1527857115,
      1527857117
    ],
    "millsfield:primary_image": 1527857115,
    "sfomuseum:accession_number": "2001.038.102",
    "sfomuseum:airline": "Pan American World Airways",
    "sfomuseum:category": "Promotional, Museum",
    "sfomuseum:collection": "Aviation Museum",
    "sfomuseum:creditline": "Gift of Barnaby Conrad III",
    "sfomuseum:date": "1950s",
    "sfomuseum:date_acquired": "2003-05-16",
    "sfomuseum:daterange_end": "1959-12-31",
    "sfomuseum:daterange_start": "1950-01-01",
    "sfomuseum:description": "Miniature airline bag issued by Pan American World Airways; blue background with white logotype on both sides; two handles and top zipper closure.",
    "sfomuseum:dimensions": "4 x 7 x 2 1/4 inches (10.2 x 17.8 x 5.7 cm)",
    "sfomuseum:maker": "Natco Products Corporation",
    "sfomuseum:media_ids": [
      1527857115,
      1527857117
    ],
    "sfomuseum:medium": "plastic, ink, metal, synthetic fabric",
    "sfomuseum:placetype": "object",
    "sfomuseum:publication": ": , 1950s.",
    "sfomuseum:subcategory": "Airline Bag",
    "wof:depicts": [
      1159284989,
      1159286839
    ],
    "wof:name": "miniature airline bag: Pan American World Airways",
    "wof:placetype": "custom",
    "wof:placetype_alt": "object"
  },
  "geometry": {"coordinates":[-122.386155,37.616357],"type":"Point"}
}
