{
  "type": "Feature",
  "properties": {
    "date:cessation_lower": "1918-01-01",
    "date:cessation_upper": "1918-12-31",
    "date:inception_lower": "1918-01-01",
    "date:inception_upper": "1918-12-31",
    "iso:country": "XX",
    "sfomuseum:accession_number": "2000.160.1270",
    "sfomuseum:author": "Adams, Briggs Kilburn",
    "sfomuseum:callnumber": "D570.9 .A33 1918 SC",
    "sfomuseum:category": "Book",
    "sfomuseum:collection": "Aviation Library",
    "sfomuseum:creditline": "The Tony Bill Aviation Library Collection",
    "sfomuseum:date": "1918",
    "sfomuseum:date_acquired": "1999-05-18",
    "sfomuseum:daterange_end": "1918-12-31",
    "sfomuseum:daterange_start": "1918-01-01",
    "sfomuseum:description": "103 p. illus. 23 cm.",
    "sfomuseum:description_library": "103 p. illus. 23 cm.",
    "sfomuseum:medium": "paper, ink",
    "sfomuseum:placetype": "object",
    "sfomuseum:publication": "Boston: The Atlantic monthly press, 1918.",
    "sfomuseum:publisher": "The Atlantic monthly press",
    "sfomuseum:publisher_location": "Boston",
    "sfomuseum:subcategory": "Book",
    "sfomuseum:subject": "World War, 1914-1918 Personal narratives, American.",
    "wof:name": "The American spirit: letters of Briggs Kilburn Adams, lieutenant of the Royal flying corps",
    "wof:placetype": "venue"
  },
  "geometry": {"coordinates":[-122.386155,37.616357],"type":"Point"}
}
