{
  "type": "Feature",
  "properties": {
    "date:cessation_lower": "1983-01-01",
    "date:cessation_upper": "1983-12-31",
    "date:inception_lower": "1983-01-01",
    "date:inception_upper": "1983-12-31",
    "iso:country": "XX",
    "millsfield:images": [
      1527851323
    ],
    "millsfield:primary_image": 1527851323,
    "sfomuseum:accession_number": "2006.010.313",
    "sfomuseum:airline": "Union de Transports Aériens (UTA)",
    "sfomuseum:category": "Scheduling / Ticketing",
    "sfomuseum:collection": "Aviation Archive",
    "sfomuseum:creditline": "Gift of the William Hough Collection",
    "sfomuseum:date": "1983",
    "sfomuseum:daterange_end": "1983-12-31",
    "sfomuseum:daterange_start": "1983-01-01",
    "sfomuseum:description": "Timetable issued by UTA (Union de Transports Aeriens) for service between Paris and cities in Africa, effective October 10, 1983 through March 24, 1984; tri-fold sheet; cover is gray, brown, and black with a map of of the African continent and UTA’s destinations cities.",
    "sfomuseum:dimensions": "11 x 8 1/2 inches (27.9 x 21.6 cm)",
    "sfomuseum:media_ids": [
      1527851323
    ],
    "sfomuseum:medium": "paper, ink",
    "sfomuseum:placetype": "object",
    "sfomuseum:subcategory": "Timetable",
    "wof:depicts": [
      1159285411
    ],
    "wof:name": "timetable: UTA (Union de Transports Aériens)",
    "wof:placetype": "venue"
  },
  "geometry": {"coordinates":[-122.386155,37.616357],"type":"Point"}
}
