{
  "type": "Feature",
  "properties": {
    "date:cessation_lower": "1983-01-01",
    "date:cessation_upper": "1983-12-31",
    "date:inception_lower": "1983-01-01",
    "date:inception_upper": "1983-12-31",
    "iso:country": "XX",
    "millsfield:images": [
      1527851323
    ],
    "millsfield:images_texts": [
      "AFRICA JUTA\nTunis\nAlgiers\nMADEIRA\nSLANDS\nCasablanca\nMarrakech\nTUNISIA\n• Rabat\nAlexandria\nMOROCCO\nCANARY ISLANDS\nALGERIA\nEGYPT\nLIbIA\nSAHARA\nCAPE\nVERDE\nISLANDS\nNouaanibou\nMAURITANIA\n* Nouakchott\nMALI\nNIGER\nPrata\nSENEGAL\nCHAD\n• Khartoum\nNdjamena\nSUDAN\nDIBOUTT\nGAMBIA\nGUINEA BISSAU\nSSA\"GUINEA\nBENIN\nAddis Ababa\nSOMALIA\nYULIA\nOsarn\nNIGERIA\nFreetown\nLEONE\nIVORY\nGHANA\nPERTOPTA\nCAMEROON\nAFRICANTRAUBLIC\n• Paula\n• Yaounde\nMalahe\nEQUATORIAL GUINEA\nSEYCHELLE\nISLANDS\nREP.\nOF\nGABON\nCONGO\nKENYA\n• Nairobi\nLAIKE\nSAO TOME\nCABINDA\ninshasa\nKigali • R WANDA\nBujumbura • BURUNDI\nTANZANIA\nDar es Salaam\n* Luanda\nCOMOROS.\nMOZAMBIQUE Dzond\nANGOLA\nZAMBIA\nLusaka. *\nMALAWI\nalisbury *\nLIM BARWE\nMALAGASY\nMAURITIUS\ninanarive •\nWingh\n• NAMIBIA\nWal vis Ba\nBOTSWANA\nGaborone\n• St. Denis\nREUNION\nSLAND\nMaNAZILAND\nAFRICA SCHEDULE\nEffective Date\nOctober 10, 1983 - March 24, 1984\nSOUTHAFRICA\nLESOTHO\n• Oudtshoorn\nEast London\n*UTA Destination\n-UTA\nFrench Airlines"
    ],
    "millsfield:images_texts_ids": [
      1527851323
    ],
    "millsfield:primary_image": 1527851323,
    "sfomuseum:accession_number": "2006.010.313",
    "sfomuseum:airline": "Union de Transports Aériens (UTA)",
    "sfomuseum:category": "Scheduling / Ticketing",
    "sfomuseum:collection": "Aviation Archive",
    "sfomuseum:creditline": "Gift of the William Hough Collection",
    "sfomuseum:date": "1983",
    "sfomuseum:date_acquired": "2006-03-26",
    "sfomuseum:daterange_end": "1983-12-31",
    "sfomuseum:daterange_start": "1983-01-01",
    "sfomuseum:description": "Timetable issued by UTA (Union de Transports Aeriens) for service between Paris and cities on the African continent, effective October 10, 1983 through March 24, 1984; tri-fold sheet; gray and brown cover with map of the continent and UTA’s destinations cities.",
    "sfomuseum:dimensions": "11 x 8 1/2 inches (27.9 x 21.6 cm)",
    "sfomuseum:media_ids": [
      1527851323
    ],
    "sfomuseum:medium": "paper, ink",
    "sfomuseum:placetype": "object",
    "sfomuseum:publication": ": , 1983.",
    "sfomuseum:subcategory": "Timetable",
    "wof:depicts": [
      1159285411,
      1159286685
    ],
    "wof:name": "timetable: UTA (Union de Transports Aériens), Africa schedule",
    "wof:placetype": "custom",
    "wof:placetype_alt": "object"
  },
  "geometry": {"coordinates":[-122.386155,37.616357],"type":"Point"}
}
