{
  "type": "Feature",
  "properties": {
    "date:cessation_lower":"1927-12-31",
    "date:cessation_upper":"1927-12-31",
    "date:inception_lower":"1927-01-01",
    "date:inception_upper":"1927-01-01",
    "iso:country":"XX",
    "sfomuseum:accession_number":"2000.018.040.030",
    "sfomuseum:category":"Company Record / Document",
    "sfomuseum:collection":"Aviation Archive",
    "sfomuseum:creditline":"Collection of SFO Museum",
    "sfomuseum:date":"1927",
    "sfomuseum:daterange_end":"1927-12-31",
    "sfomuseum:daterange_start":"1927-01-01",
    "sfomuseum:description":"Typed facsimile of correspondence from Milo F. Kent, Chairman of the Airport Committee, Board of Supervisors, City and County of San Francisco, to San Mateo County Board of Supervisors in Redwood City, dated June 17, 1927, concerning zoning of adjacent property in conjunction with lease of Mills Estate property in San Mateo County for use as airport; file copy, not signed.",
    "sfomuseum:medium":"paper, ink",
    "sfomuseum:placetype":"object",
    "sfomuseum:subcategory":"Correspondence, Company",
    "wof:name":"correspondence: Joseph J. Phillips, Right of Way Agent for City and County of San Francisco",
    "wof:placetype":"venue"
},
  "geometry": {"coordinates":[-122.386155,37.616358],"type":"Point"}
}