{
  "type": "Feature",
  "properties": {
    "date:cessation_lower": "1962-12-31",
    "date:cessation_upper": "1962-12-31",
    "date:inception_lower": "1962-01-01",
    "date:inception_upper": "1962-01-01",
    "iso:country": "XX",
    "sfomuseum:accession_number": "2005.132.010.012",
    "sfomuseum:category": "Scheduling / Ticketing",
    "sfomuseum:collection": "Aviation Archive",
    "sfomuseum:creditline": "Gift of the William Hough Collection",
    "sfomuseum:date": "1962",
    "sfomuseum:daterange_end": "1962-12-31",
    "sfomuseum:daterange_start": "1962-01-01",
    "sfomuseum:description": "Timetable issued by Braniff International Airways, effective August 1, 1962; twenty-three page schedule. The cover is red, white and blue and has a drawing of jet flying across the face of a globe on the center white portion of the schedule; text is “Silver Service.” The company name is in large white letters at the top on a red field.",
    "sfomuseum:media_ids": [
      1527841237
    ],
    "sfomuseum:medium": "paper, ink",
    "sfomuseum:placetype": "object",
    "sfomuseum:subcategory": "Timetable",
    "wof:name": "timetable: Braniff International Airways",
    "wof:placetype": "venue"
  },
  "geometry": {"coordinates":[-122.386155,37.616358],"type":"Point"}
}
