{
  "type": "Feature",
  "properties": {
    "date:cessation_lower": "1948-07-03",
    "date:cessation_upper": "1948-07-03",
    "date:inception_lower": "1948-07-03",
    "date:inception_upper": "1948-07-03",
    "iso:country": "IN",
    "millsfield:images": [
      1527829193
    ],
    "millsfield:primary_image": 1527829193,
    "sfomuseum:accession_number": "1994.18.220 a b",
    "sfomuseum:airline": "Pan American World Airways",
    "sfomuseum:category": "Philately",
    "sfomuseum:collection": "Aviation Archive",
    "sfomuseum:continent": "Transpacific",
    "sfomuseum:country": "India",
    "sfomuseum:creditline": "Purchase",
    "sfomuseum:date": "7/3/1948",
    "sfomuseum:daterange_end": "1948-07-03",
    "sfomuseum:daterange_start": "1948-07-03",
    "sfomuseum:description": "Airmail flight cover commemorating first Pan American airmail flight from Calcutta to Guam; blue cachet with image of of aircraft in flight and text; two stamps: orange 2 AS (annas) and brown 12 AS (India); postmark: July 3 1948 in Calcutta; backstamp: July 5, 1948 in Guam; envelope: white and blue envelope with red and blue border.\ra. envelope\rb. insert: Pan Am World Route Map June 1, 1948 with timetable for domestic services in Colombia and Cuba",
    "sfomuseum:dimensions": "4 x 9 11/16 inches (10.2 x 24.6 cm)",
    "sfomuseum:maker": "Pan American Airways, Inc.",
    "sfomuseum:media_ids": [
      1527829193
    ],
    "sfomuseum:medium": "ink on paper",
    "sfomuseum:placetype": "object",
    "sfomuseum:subcategory": "Airmail Flight Cover",
    "wof:depicts": [
      1159284989
    ],
    "wof:name": "airmail flight cover: Pan American World Airways, Calcutta - Guam route",
    "wof:placetype": "venue"
  },
  "geometry": {"coordinates":[-122.386155,37.616357],"type":"Point"}
}
