{
  "type": "Feature",
  "properties": {
    "date:cessation_lower": "2013-01-01",
    "date:cessation_upper": "2013-12-31",
    "date:inception_lower": "2013-01-01",
    "date:inception_upper": "2013-12-31",
    "iso:country": "XX",
    "loc:named_authorities": [
      "n78095330"
    ],
    "loc:subject_headings": [
      "sh85002650"
    ],
    "sfomuseum:accession_number": "2014.070.008",
    "sfomuseum:author": "Russell, David Lee",
    "sfomuseum:callnumber": "HE9803.A35 R87 2013",
    "sfomuseum:category": "Book",
    "sfomuseum:collection": "Aviation Library",
    "sfomuseum:creditline": "Purchase",
    "sfomuseum:date": "2013",
    "sfomuseum:date_acquired": "2014-03-31",
    "sfomuseum:daterange_end": "2013-12-31",
    "sfomuseum:daterange_start": "2013-01-01",
    "sfomuseum:description_library": "vii, 238 p. : ill., maps ; 26 cm.",
    "sfomuseum:medium": "paper, ink",
    "sfomuseum:placetype": "object",
    "sfomuseum:publication": "Jefferson, NC: McFarland \u0026 Company, Inc., Publishers, 2013.",
    "sfomuseum:publisher": "McFarland \u0026 Company, Inc., Publishers",
    "sfomuseum:publisher_location": "Jefferson, NC",
    "sfomuseum:subcategory": "Book",
    "sfomuseum:subject": "Eastern Air Lines -- History.\rAirlines -- United States -- History.\rEastern Air Lines, inc.\rAirlines.\rUnited States.\rEastern Airlines Inc.\rUSA.",
    "wof:name": "Eastern Air Lines : a history, 1926-1991",
    "wof:placetype": "venue"
  },
  "geometry": {"coordinates":[-122.386155,37.616357],"type":"Point"}
}
