{
  "type": "Feature",
  "properties": {
    "date:cessation_lower": "2004-01-01",
    "date:cessation_upper": "2004-12-31",
    "date:inception_lower": "2004-01-01",
    "date:inception_upper": "2004-12-31",
    "iso:country": "XX",
    "millsfield:images": [
      1527838481,
      1527850491
    ],
    "millsfield:images_texts": [
      "SOUTHWEST\nJULY 6, 2004 FLIGHT SCHEDULE\nAs a Senior Attorney,\nI'm happy to provide\nlegal assistance to\nour departments.",
      "Pacific\ncentra\nEastern\nDeton Mages Fail\nReno/ Tanoe\n(San Francisco Area\n(San Francisco Area\nLas vega:\nLos Al\n(LAX) Orange\nsan Dieg\n(Palm Springs Area\nSalt Lake City\nAmarillo\nLubbock\nKansas City\nSt. Louis\nTulsa\nOklahoma City Little Rock\nNashville\nEl Paso\nSan Antonio\nChrist\nHarlingen/South Padre Island\nNew Orleans\nTamy\nNew nonstop service starts July 6, 2004.\nNew nonstop service starts August 8, 2004.\nIndianapolis, Phoenix, and Tucson do not observe daylight-saving time.\nManchester)\n(Biston Area)\nton (BWI)\n(D.C. Area)\nuthern virginia,\nRaleigh-Durham (RDU)\nWest Palm Beach\nMiami erdale\nVisit us at southwest.com® for an up-to-date\nflight schedule.\nYou can now check in for your flight and print\nyour boarding pass at southwest.com or at\nthe Southwest Skycap,* Ticket Counter,\nRAPID CHECK-IN Kiosk, or at your gate at\nleast one hour prior to departure. (20 minutes\nprior to scheduled departure, boarding pass\ndistribution is available at the Departure\nGate only.)\nCargo Customers, mail requests to:\nCargo Customer Schedule List, HDQ/3CM,\nP.O. Box 36611, Dallas, TX 75235-1611.\nAll other correspondence should be sent to:\nSouthwest Airlines Co.,\nP.O. Box 36611, Dallas, TX 75235-1611.\n*Where available\nSOUTHWEST"
    ],
    "millsfield:images_texts_ids": [
      1527838481,
      1527850491
    ],
    "millsfield:primary_image": 1527838481,
    "sfomuseum:accession_number": "2005.132.047.013",
    "sfomuseum:airline": "Southwest Airlines",
    "sfomuseum:category": "Scheduling / Ticketing",
    "sfomuseum:collection": "Aviation Archive",
    "sfomuseum:creditline": "Gift of the William Hough Collection",
    "sfomuseum:date": "2004",
    "sfomuseum:date_acquired": "2006-12-05",
    "sfomuseum:daterange_end": "2004-12-31",
    "sfomuseum:daterange_start": "2004-01-01",
    "sfomuseum:description": "Timetable issued by Southwest Airlines, effective July 6, 2004; 121-page schedule; black and white photographic image of a senior attorney with quoted text about that role.",
    "sfomuseum:dimensions": "9 x 4 inches (22.9 x 10.2 cm)",
    "sfomuseum:media_ids": [
      1527838481,
      1527850491
    ],
    "sfomuseum:medium": "paper, ink",
    "sfomuseum:placetype": "object",
    "sfomuseum:publication": ": , 2004.",
    "sfomuseum:subcategory": "Timetable",
    "wof:depicts": [
      1159285591,
      1360700737
    ],
    "wof:name": "timetable: Southwest Airlines",
    "wof:placetype": "custom",
    "wof:placetype_alt": [
      "object"
    ]
  },
  "geometry": {"coordinates":[-122.386155,37.616357],"type":"Point"}
}
