{
  "type": "Feature",
  "properties": {
    "date:cessation_lower":"1962-12-31",
    "date:cessation_upper":"1962-12-31",
    "date:inception_lower":"1962-01-01",
    "date:inception_upper":"1962-01-01",
    "iso:country":"XX",
    "sfomuseum:accession_number":"2006.026.027",
    "sfomuseum:category":"Passenger Amenity",
    "sfomuseum:collection":"Aviation Museum",
    "sfomuseum:creditline":"The Henry Steiner Air Sickness Bag Collection",
    "sfomuseum:date":"1962",
    "sfomuseum:daterange_end":"1962-12-31",
    "sfomuseum:daterange_start":"1962-01-01",
    "sfomuseum:description":"Brown bag with design of plane at takeoff, with Chinese characters printed in black.",
    "sfomuseum:medium":"paper, ink",
    "sfomuseum:placetype":"object",
    "sfomuseum:subcategory":"Airsickness Bag",
    "wof:name":"airsickness bag: CAAC (Civil Aviation Administration of China)",
    "wof:placetype":"venue"
},
  "geometry": {"coordinates":[-122.386155,37.616358],"type":"Point"}
}