{
  "type": "Feature",
  "properties": {
    "date:cessation_lower": "1973-12-31",
    "date:cessation_upper": "1973-12-31",
    "date:inception_lower": "1963-01-01",
    "date:inception_upper": "1963-01-01",
    "iso:country": "XX",
    "sfomuseum:accession_number": "2001.039.262",
    "sfomuseum:category": "Passenger Amenity",
    "sfomuseum:collection": "Aviation Archive",
    "sfomuseum:creditline": "Gift of David A. Abercrombie, in memory of Stanley A. Abercrombie ",
    "sfomuseum:date": "c. 1968",
    "sfomuseum:daterange_end": "1973-12-31",
    "sfomuseum:daterange_start": "1963-01-01",
    "sfomuseum:description": "In-flight information brochure produced by Northwest Orient Airlines, titled \"Welcome Aboard\"; interior contains information regarding aircraft fleet, meal service, cargo, with color photographic images and route maps. ",
    "sfomuseum:media_ids": [
      1527854525, 
      1527854527, 
      1527819637
    ],
    "sfomuseum:medium": "paper, ink",
    "sfomuseum:placetype": "object",
    "sfomuseum:subcategory": "In-flight Information",
    "wof:name": "flight information brochure: Northwest Orient Airlines",
    "wof:placetype": "venue"
  },
  "geometry": {"coordinates":[-122.386155,37.616358],"type":"Point"}
}
