{
  "type": "Feature",
  "properties": {
    "date:cessation_lower":"1998-12-31",
    "date:cessation_upper":"1998-12-31",
    "date:inception_lower":"1998-01-01",
    "date:inception_upper":"1998-01-01",
    "iso:country":"XX",
    "sfomuseum:accession_number":"2011.126.017.015",
    "sfomuseum:category":"Scheduling / Ticketing",
    "sfomuseum:collection":"Aviation Archive",
    "sfomuseum:creditline":"Gift of the Paul H. Kowalewski Collection",
    "sfomuseum:date":"1998",
    "sfomuseum:daterange_end":"1998-12-31",
    "sfomuseum:daterange_start":"1998-01-01",
    "sfomuseum:description":"Timetable issued by Hawaiian Airlines; double-sided card with schedules to and from Honolulu to the mainland and South Pacific; wordmark at the top on a blue field. Effective June 12, 1998.",
    "sfomuseum:media_ids":[
        1527839957,
        1527839959
    ],
    "sfomuseum:medium":"Paper, ink",
    "sfomuseum:placetype":"object",
    "sfomuseum:subcategory":"Timetable",
    "wof:name":"timetable: Hawaiian Airlines",
    "wof:placetype":"venue"
},
  "geometry": {"coordinates":[-122.386155,37.616358],"type":"Point"}
}