{
  "type": "Feature",
  "properties": {
    "date:cessation_lower": "1986-12-31",
    "date:cessation_upper": "1986-12-31",
    "date:inception_lower": "1986-01-01",
    "date:inception_upper": "1986-01-01",
    "iso:country": "XX",
    "sfomuseum:accession_number": "2006.028.148 a e",
    "sfomuseum:category": "Employee Career History",
    "sfomuseum:collection": "Aviation Archive",
    "sfomuseum:creditline": "Gift of Edith Lauterbach",
    "sfomuseum:date": "1986",
    "sfomuseum:daterange_end": "1986-12-31",
    "sfomuseum:daterange_start": "1986-01-01",
    "sfomuseum:description": "a. Guest book in honor of United Airlines flight attendant Edith Lauterbach; white cover with silver \"Guests\" printed in cursive script; matching white pen and stand.\rb. Invitation printed on light blue paper; line drawing of plane carrying banner with caption, \"Edith Lauterbach: Union Founder.\"\rc. Cocktail napkin; white with \"Edith Lauterbach 1944-1986\" printed in green.\rd. Cocktail napkin; white with \"Edith Lauterbach 1944-1986\" printed in green.\re. Cocktail napkin; white with \"Edith Lauterbach 1944-1986\" printed in green.",
    "sfomuseum:media_ids": [
      1527851677
    ],
    "sfomuseum:medium": "paper, ink, plastic, metal",
    "sfomuseum:placetype": "object",
    "sfomuseum:subcategory": "Other, Employee Career History",
    "wof:name": "guest book: Association of Flight Attendants, Edith Lauterbach",
    "wof:placetype": "venue"
  },
  "geometry": {"coordinates":[-122.386155,37.616358],"type":"Point"}
}
