{
  "type": "Feature",
  "properties": {
    "date:cessation_lower": "1986-01-01",
    "date:cessation_upper": "1986-12-31",
    "date:inception_lower": "1986-01-01",
    "date:inception_upper": "1986-12-31",
    "iso:country": "XX",
    "millsfield:images": [
      1527851677
    ],
    "millsfield:images_texts": [
      "Puesto"
    ],
    "millsfield:images_texts_ids": [
      1527851677
    ],
    "millsfield:primary_image": 1527851677,
    "sfomuseum:accession_number": "2006.028.148 a e",
    "sfomuseum:airline": "United Airlines",
    "sfomuseum:category": "Employee Career History",
    "sfomuseum:collection": "Aviation Archive",
    "sfomuseum:creditline": "Gift of Edith Lauterbach",
    "sfomuseum:date": "1986",
    "sfomuseum:date_acquired": "2006-04-18",
    "sfomuseum:daterange_end": "1986-12-31",
    "sfomuseum:daterange_start": "1986-01-01",
    "sfomuseum:description": "a. Guest book in honor of United Airlines flight attendant Edith Lauterbach; white cover with silver \"Guests\" printed in cursive script; matching white pen and stand;\rb. invitation printed on light blue paper; line drawing of plane carrying banner with caption, \"Edith Lauterbach: Union Founder\";\rc. cocktail napkin; white with \"Edith Lauterbach 1944-1986\" printed in green;\rd. cocktail napkin; white with \"Edith Lauterbach 1944-1986\" printed in green;\re. cocktail napkin; white with \"Edith Lauterbach 1944-1986\" printed in green.",
    "sfomuseum:dimensions": "6 3/4 x 10 x 1/2 inches (17.1 x 25.4 x 1.3 cm)",
    "sfomuseum:media_ids": [
      1527851677
    ],
    "sfomuseum:medium": "paper, plastic, metal, ink",
    "sfomuseum:placetype": "object",
    "sfomuseum:publication": ": , 1986.",
    "sfomuseum:subcategory": "Other, Employee Career History",
    "wof:depicts": [
      1159285413,
      1159288779
    ],
    "wof:name": "guest book: Association of Flight Attendants, Edith Lauterbach",
    "wof:placetype": "custom",
    "wof:placetype_alt": "object"
  },
  "geometry": {"coordinates":[-122.386155,37.616357],"type":"Point"}
}
