{
  "type": "Feature",
  "properties": {
    "date:cessation_lower": "1954-01-01",
    "date:cessation_upper": "1954-12-31",
    "date:inception_lower": "1954-01-01",
    "date:inception_upper": "1954-12-31",
    "iso:country": "XX",
    "loc:subject_headings": [
      "sh85090433"
    ],
    "sfomuseum:accession_number": "2012.124.002",
    "sfomuseum:author": "United States. \rDept. of the Air Force",
    "sfomuseum:callnumber": "TL586 .U51 1954",
    "sfomuseum:category": "Book",
    "sfomuseum:collection": "Aviation Library",
    "sfomuseum:creditline": "Gift of Frank A. Norick",
    "sfomuseum:date": "1954",
    "sfomuseum:date_acquired": "2012-11-09",
    "sfomuseum:daterange_end": "1954-12-31",
    "sfomuseum:daterange_start": "1954-01-01",
    "sfomuseum:description": "282 p. ; 28 cm.",
    "sfomuseum:description_library": "282 p. ; 28 cm.",
    "sfomuseum:dimensions": "4 1/2 x 2 1/4 x 1 1/4 inches (11.4 x 5.7 x 3.2 cm)",
    "sfomuseum:medium": "paper, ink",
    "sfomuseum:placetype": "object",
    "sfomuseum:publication": "Washington: , 1954.",
    "sfomuseum:publisher_location": "Washington",
    "sfomuseum:series": "Air Force manual\rUnited States. Dept. of the Air Force. Air Force manual 51-40.",
    "sfomuseum:subcategory": "Government Document",
    "sfomuseum:subject": "Navigation (Aeronautics).",
    "wof:name": "Air navigation",
    "wof:placetype": "custom",
    "wof:placetype_alt": "object"
  },
  "geometry": {"coordinates":[-122.386155,37.616357],"type":"Point"}
}
