{
  "type": "Feature",
  "properties": {
    "date:cessation_lower": "1970-01-01",
    "date:cessation_upper": "1979-12-31",
    "date:inception_lower": "1970-01-01",
    "date:inception_upper": "1979-12-31",
    "iso:country": "XX",
    "millsfield:images": [
      1763379599
    ],
    "millsfield:primary_image": 1763379599,
    "sfomuseum:accession_number": "2012.147.130",
    "sfomuseum:airline": "LTU International Airlines",
    "sfomuseum:category": "Passenger Amenity, Museum",
    "sfomuseum:collection": "Aviation Museum",
    "sfomuseum:creditline": "Gift of the Captain John B. Russell Family",
    "sfomuseum:date": "1970s",
    "sfomuseum:date_acquired": "2014-04-17",
    "sfomuseum:daterange_end": "1979-12-31",
    "sfomuseum:daterange_start": "1970-01-01",
    "sfomuseum:description": "Souvenir children’s wing issued by LTU International Airlines; gold and black wings pin with logotype at center; straight pin with hook closure on back. ",
    "sfomuseum:dimensions": "1 x 4 x 1/4 inches (2.5 x 10.2 x .6 cm)",
    "sfomuseum:medium": "plastic, ink",
    "sfomuseum:placetype": "object",
    "sfomuseum:publication": ": , 1970s.",
    "sfomuseum:subcategory": "Children’s Amenity, Toys",
    "wof:depicts": [
      1159284709,
      1159288201
    ],
    "wof:name": "children's souvenir wings: LTU International Airlines",
    "wof:placetype": "custom",
    "wof:placetype_alt": "object"
  },
  "geometry": {"coordinates":[-122.386155,37.616357],"type":"Point"}
}
