{
  "type": "Feature",
  "properties": {
    "date:cessation_lower": "1970-12-31",
    "date:cessation_upper": "1970-12-31",
    "date:inception_lower": "1960-01-01",
    "date:inception_upper": "1960-01-01",
    "iso:country": "XX",
    "sfomuseum:accession_number": "2001.082.077",
    "sfomuseum:aircraft": "Boeing 707-131B",
    "sfomuseum:airline": "TWA (Trans World Airlines)",
    "sfomuseum:artist": "Jon Proctor **",
    "sfomuseum:category": "Philately",
    "sfomuseum:collection": "Aviation Archive",
    "sfomuseum:creditline": "Gift of George Gayuski ",
    "sfomuseum:date": "c. 1965",
    "sfomuseum:daterange_end": "1970-12-31",
    "sfomuseum:daterange_start": "1960-01-01",
    "sfomuseum:description": "Color photographic image of Boeing 707 on tarmac. ",
    "sfomuseum:dimensions": "3 1/2 x 5 1/2 inches (8.9 x 14 cm)",
    "sfomuseum:maker": "Alleghany Publishers ",
    "sfomuseum:medium": "paper, ink",
    "sfomuseum:placetype": "object",
    "sfomuseum:subcategory": "Postcard",
    "wof:depicts": [
      1159289673,
      1159285393
    ],
    "wof:name": "postcard: TWA (Trans World Airlines), Boeing 707-131B",
    "wof:placetype": "venue"
  },
  "geometry": {"coordinates":[-122.386155,37.616357],"type":"Point"}
}
