{
  "type": "Feature",
  "properties": {
    "date:cessation_lower": "1959-01-01",
    "date:cessation_upper": "1959-12-31",
    "date:inception_lower": "1959-01-01",
    "date:inception_upper": "1959-12-31",
    "iso:country": "US",
    "millsfield:images": [
      1527828707,
      1527853579
    ],
    "millsfield:images_texts": [
      "LES HORS D'OEUVRE\nLES ENTREES\nCUISINE BY\nMAXiM'S\nOF\"PARIS\nThe President Special DINER A LA CARTE\nLes Canapés\nChampo Elysées - Se Caviar Brais\nd Iran\nLes Céleris en Branches - Les Délices culinaires de la Voiture\nLe Homard\nThermidor - Sa Sole \"Albert\"\nLe Rion\nde Veau Financière - La Perdrix des Neigeo du Tbet - Riz sauvage\nSe Cog de Bruyère farci Par-Am\"\nLE ROTI Notre Spécialité: a Cote o\nBoeuf rôtie à la Broche\nLA GRILLADE La Paire de Côtes d'Agneau grillée\nLES LEGUMES\nLes baricots verts fins au Beurre - Ses Pommes croquettes\nLES FROMAGES\nLa Selection\nde\nFromages de Pays\nLES ENTREMETS\nLa Bombe glacée Ent\nSauce Framboise\nSAUCE\nLES FRUITS\nLes Fruito de Saison\nCafé Américain - Cabe Sauka - The Orange Pekoe\nNOS GRANDS VINS\nDE FRANCE\nCHAMPAGNE\nBrut Millésimé\nspécialement sélectionné pour Pan American\nVIN ROUGE\nBordeaux-Grand Crû classé\nVIN BLANC\nSelection du Vignoble Bourguignor\nLES LIQUEURS\nCrème de Menthe\nDrambute\nCoutreau\nBenedichine\ncognac"
    ],
    "millsfield:images_texts_ids": [
      1527828707
    ],
    "millsfield:primary_image": 1527828707,
    "sfomuseum:accession_number": "1993.01.097",
    "sfomuseum:airline": "Pan American World Airways",
    "sfomuseum:category": "Passenger Amenity, Archive",
    "sfomuseum:collection": "Aviation Archive",
    "sfomuseum:continent": "North America",
    "sfomuseum:country": "United States",
    "sfomuseum:creditline": "Gift of Serge Mitt",
    "sfomuseum:date": "1959",
    "sfomuseum:date_acquired": "1999-10-06",
    "sfomuseum:daterange_end": "1959-12-31",
    "sfomuseum:daterange_start": "1959-01-01",
    "sfomuseum:description": "Menu issued by Pan American World Airways; red flocked cover; menu items include Iranian caviar, lobster thermidor, Himalayan partridge, and filet of sole; no menu number; class: President Special (first); undated.",
    "sfomuseum:dimensions": "9 x 11 3/4 inches (22.9 x 29.8 cm)",
    "sfomuseum:maker": "Pan American World Airways, Inc.",
    "sfomuseum:media_ids": [
      1527853579,
      1527828707
    ],
    "sfomuseum:medium": "flocked paper, fabric cord, tassel, ink",
    "sfomuseum:placetype": "object",
    "sfomuseum:publication": ": , 1959.",
    "sfomuseum:subcategory": "Menu",
    "wof:depicts": [
      1159284989,
      1159286839
    ],
    "wof:name": "menu: Pan American World Airways, President Special (first) class",
    "wof:placetype": "custom",
    "wof:placetype_alt": "object"
  },
  "geometry": {"coordinates":[-122.386155,37.616357],"type":"Point"}
}
