{
  "type": "Feature",
  "properties": {
    "date:cessation_lower": "1959-01-01",
    "date:cessation_upper": "1959-12-31",
    "date:inception_lower": "1959-01-01",
    "date:inception_upper": "1959-12-31",
    "iso:country": "US",
    "millsfield:images": [
      1527853579,
      1527828707
    ],
    "millsfield:primary_image": 1527828707,
    "sfomuseum:accession_number": "1993.01.097",
    "sfomuseum:airline": "Pan American World Airways",
    "sfomuseum:category": "Passenger Amenity",
    "sfomuseum:collection": "Aviation Archive",
    "sfomuseum:continent": "North America",
    "sfomuseum:country": "United States",
    "sfomuseum:creditline": "Gift of Serge Mitt",
    "sfomuseum:date": "1959",
    "sfomuseum:daterange_end": "1959-12-31",
    "sfomuseum:daterange_start": "1959-01-01",
    "sfomuseum:description": "Menu issued by Pan American World Airways; red flocked cover; menu items include Iranian caviar, lobster thermidor, Himalayan partridge, and filet of sole; no menu number; class: President Special (first); undated.",
    "sfomuseum:dimensions": "9 x 11 3/4 inches (22.9 x 29.8 cm)",
    "sfomuseum:maker": "Pan American World Airways, Inc.",
    "sfomuseum:media_ids": [
      1527853579,
      1527828707
    ],
    "sfomuseum:medium": "flocked paper, fabric cord, tassel, ink",
    "sfomuseum:placetype": "object",
    "sfomuseum:publication": ": , 1959.",
    "sfomuseum:subcategory": "Menu",
    "wof:depicts": [
      1159284989
    ],
    "wof:name": "menu: Pan American World Airways, President Special (First) Class",
    "wof:placetype": "venue"
  },
  "geometry": {"coordinates":[-122.386155,37.616357],"type":"Point"}
}
