{
  "type": "Feature",
  "properties": {
    "date:cessation_lower": "1980-01-01",
    "date:cessation_upper": "1980-12-31",
    "date:inception_lower": "1980-01-01",
    "date:inception_upper": "1980-12-31",
    "iso:country": "XX",
    "sfomuseum:accession_number": "2012.148.274",
    "sfomuseum:airline": "Pan American World Airways",
    "sfomuseum:author": "Brock, Horace",
    "sfomuseum:callnumber": "HE9803.P36 B76 1980 c.2",
    "sfomuseum:category": "Book",
    "sfomuseum:collection": "Aviation Library",
    "sfomuseum:creditline": "Gift of the Captain John B. Russell Family",
    "sfomuseum:date": "1980",
    "sfomuseum:date_acquired": "2013-05-31",
    "sfomuseum:daterange_end": "1980-12-31",
    "sfomuseum:daterange_start": "1980-01-01",
    "sfomuseum:description": "101 p., [3] p. of plates : ports. ; 24 cm.",
    "sfomuseum:description_library": "101 p., [3] p. of plates : ports. ; 24 cm.",
    "sfomuseum:dimensions": "11 x 8 1/2 inches (27.9 x 21.6 cm)",
    "sfomuseum:medium": "paper, ink",
    "sfomuseum:placetype": "object",
    "sfomuseum:publication": "Lunenburg, Vt.: Stinehour Press, 1980.",
    "sfomuseum:publisher": "Stinehour Press",
    "sfomuseum:publisher_location": "Lunenburg, Vt.",
    "sfomuseum:subcategory": "Book",
    "sfomuseum:subject": "Pan American World Airways, inc. -- History.",
    "wof:depicts": [
      1159286839,
      1159284989
    ],
    "wof:name": "More about Pan Am: a pilot's story continued",
    "wof:placetype": "custom",
    "wof:placetype_alt": [
      "object"
    ]
  },
  "geometry": {"coordinates":[-122.386155,37.616357],"type":"Point"}
}
