{
  "type": "Feature",
  "properties": {
    "date:cessation_lower": "1998-01-01",
    "date:cessation_upper": "1998-12-31",
    "date:inception_lower": "1998-01-01",
    "date:inception_upper": "1998-12-31",
    "iso:country": "XX",
    "millsfield:images": [
      1527847189
    ],
    "millsfield:images_texts": [
      "CHINA AIRLINES\nTIMETABLE\n1998 # 10 A 25 # ~ 1999 # 3 A 27 H\n25 October 1998~27 March 1999\nCHINA AIRLINES"
    ],
    "millsfield:images_texts_ids": [
      1527847189
    ],
    "millsfield:primary_image": 1527847189,
    "sfomuseum:accession_number": "2003.105.041.002",
    "sfomuseum:airline": "China Airlines",
    "sfomuseum:category": "Scheduling / Ticketing",
    "sfomuseum:collection": "Aviation Archive",
    "sfomuseum:creditline": "Gift of Craig Lynes",
    "sfomuseum:date": "1998",
    "sfomuseum:date_acquired": "2003-12-29",
    "sfomuseum:daterange_end": "1998-12-31",
    "sfomuseum:daterange_start": "1998-01-01",
    "sfomuseum:description": "Timetable issued by China Airlines, effective October 25, 1998 through March 27, 1999; 176-page schedule; white cover with color photographic image of two snowmen; in Chinese and English.",
    "sfomuseum:dimensions": "8 x 3 3/4 inches (20.3 x 9.5 cm)",
    "sfomuseum:media_ids": [
      1527847189
    ],
    "sfomuseum:medium": "paper, ink",
    "sfomuseum:placetype": "object",
    "sfomuseum:publication": ": , 1998.",
    "sfomuseum:subcategory": "Timetable",
    "wof:depicts": [
      1159288057,
      1159284153
    ],
    "wof:name": "timetable: China Airlines",
    "wof:placetype": "custom",
    "wof:placetype_alt": [
      "object"
    ]
  },
  "geometry": {"coordinates":[-122.386155,37.616357],"type":"Point"}
}
