{
  "type": "Feature",
  "properties": {
    "date:cessation_lower": "2003-01-01",
    "date:cessation_upper": "2003-12-31",
    "date:inception_lower": "2003-01-01",
    "date:inception_upper": "2003-12-31",
    "iso:country": "XX",
    "sfomuseum:accession_number": "2006.023.063",
    "sfomuseum:airport": "San Diego International Airport",
    "sfomuseum:author": "San Diego County Regional Airport Authority; and San Diego County Regional Airport Authority",
    "sfomuseum:callnumber": "HE9797.5.N6 S25 2003",
    "sfomuseum:category": "Book",
    "sfomuseum:collection": "Aviation Library",
    "sfomuseum:creditline": "Gift of the collection of Frank J. Lichtanski",
    "sfomuseum:date": "2003",
    "sfomuseum:daterange_end": "2003-12-31",
    "sfomuseum:daterange_start": "2003-01-01",
    "sfomuseum:description": "viii, 100 p. : ill. (some col.) ; 29 cm.",
    "sfomuseum:medium": "paper, ink",
    "sfomuseum:placetype": "object",
    "sfomuseum:publication": "San Diego, CA: San Diego County Regional Airport Authority, 2003.",
    "sfomuseum:publisher": "San Diego County Regional Airport Authority",
    "sfomuseum:publisher_location": "San Diego, CA",
    "sfomuseum:subcategory": "Book",
    "sfomuseum:subject": "San Diego International Airport History.",
    "wof:depicts": [
      102528997
    ],
    "wof:name": "The future takes wing: San Diego International Airport: 75 years of flight",
    "wof:placetype": "venue"
  },
  "geometry": {"coordinates":[-122.386155,37.616357],"type":"Point"}
}
