{
  "type": "Feature",
  "properties": {
    "date:cessation_lower": "2009-01-01",
    "date:cessation_upper": "2009-12-31",
    "date:inception_lower": "2009-01-01",
    "date:inception_upper": "2009-12-31",
    "iso:country": "XX",
    "sfomuseum:accession_number": "2011.048.002",
    "sfomuseum:author": "Kerr, Anne Billingsley",
    "sfomuseum:callnumber": "HD8039.A432 U635 2009",
    "sfomuseum:category": "Book",
    "sfomuseum:collection": "Aviation Library",
    "sfomuseum:creditline": "Purchase",
    "sfomuseum:date": "2009",
    "sfomuseum:date_acquired": "2011-06-21",
    "sfomuseum:daterange_end": "2009-12-31",
    "sfomuseum:daterange_start": "2009-01-01",
    "sfomuseum:description": "127 p. : ill. ; 23 cm.",
    "sfomuseum:description_library": "127 p. : ill. ; 23 cm.",
    "sfomuseum:edition": "1st ed.",
    "sfomuseum:medium": "paper, ink",
    "sfomuseum:placetype": "object",
    "sfomuseum:publication": "Minnetonka, Minn.: Lady Skywriter Publications, 2009.",
    "sfomuseum:publisher": "Lady Skywriter Publications",
    "sfomuseum:publisher_location": "Minnetonka, Minn.",
    "sfomuseum:subcategory": "Book",
    "sfomuseum:subject": "Northwest Airlines Corporation -- Anecdotes. \rFlight attendants -- United States -- Anecdotes.",
    "wof:name": "Fujiyama trays \u0026 oshibori towels: recalling a time when passenger flight was an adventure and the boeing stratocruiser ruled the skies 1st ed.",
    "wof:placetype": "custom",
    "wof:placetype_alt": "object"
  },
  "geometry": {"coordinates":[-122.386155,37.616357],"type":"Point"}
}
