{
  "type": "Feature",
  "properties": {
    "date:cessation_lower": "1961-12-31",
    "date:cessation_upper": "1961-12-31",
    "date:inception_lower": "1951-01-01",
    "date:inception_upper": "1951-01-01",
    "iso:country": "XX",
    "millsfield:images": [
      1527852821,
      1527852823
    ],
    "sfomuseum:accession_number": "2013.057.030",
    "sfomuseum:airline": "TWA (Trans World Airlines)",
    "sfomuseum:category": "Scheduling / Ticketing",
    "sfomuseum:collection": "Aviation Archive",
    "sfomuseum:creditline": "Gift of the Estate of Audrey McNamara Nevis",
    "sfomuseum:date": "c. 1956",
    "sfomuseum:daterange_end": "1961-12-31",
    "sfomuseum:daterange_start": "1951-01-01",
    "sfomuseum:description": "Crew tag issued by TWA (Trans World Airlines); printed red text “Crew Tag” over tan background; string attachment on side.",
    "sfomuseum:dimensions": "2 x 3 3/4 inches (5.1 x 9.5 cm)",
    "sfomuseum:media_ids": [
      1527852821,
      1527852823
    ],
    "sfomuseum:medium": "paper, ink, string",
    "sfomuseum:placetype": "object",
    "sfomuseum:subcategory": "Luggage Tag, Crew",
    "wof:depicts": [
      1159285393
    ],
    "wof:name": "crew luggage tag: TWA (Trans World Airlines)",
    "wof:placetype": "venue"
  },
  "geometry": {"coordinates":[-122.386155,37.616357],"type":"Point"}
}
