{
  "type": "Feature",
  "properties": {
    "date:cessation_lower":"1967-12-31",
    "date:cessation_upper":"1967-12-31",
    "date:inception_lower":"1967-01-01",
    "date:inception_upper":"1967-01-01",
    "iso:country":"XX",
    "sfomuseum:accession_number":"2011.032.1479",
    "sfomuseum:artist":"Marshall Moxom",
    "sfomuseum:category":"Photograph",
    "sfomuseum:collection":"Aviation Archive",
    "sfomuseum:creditline":"Transfer",
    "sfomuseum:date":"1967",
    "sfomuseum:daterange_end":"1967-12-31",
    "sfomuseum:daterange_start":"1967-01-01",
    "sfomuseum:description":"From attached handwritten note: \u201c03705 / 12-20-67 / Central term. bldg\u201d; second small attached handwritten note reads: \u201c72_025 (crossed out) 1479\u201d. Black and white photographic negative depicting Central Terminal (now Terminal 2 / T2) at San Francisco International Airport (SFO); three-quarter frontal view of port side of United Air Lines Douglas DC-8-61 aircraft; text \u201cUnited\u201d seen on port side of fuselage and vertical stabilizer; concrete ground visibly wet; text \u201cSan Francisco International Airport\u201d visible on Central Terminal; pushback trailer partially visible under aircraft; photo taken April 25, 1967, by Marshall Moxom.",
    "sfomuseum:media_ids":[
        1527825647
    ],
    "sfomuseum:medium":"negative",
    "sfomuseum:placetype":"object",
    "sfomuseum:subcategory":"Negative",
    "wof:depicts":[
        102527513
    ],
    "wof:name":"negative: San Francisco International Airport (SFO), Central Terminal and United Air Lines Douglas DC-8-61",
    "wof:placetype":"venue"
},
  "geometry": {"coordinates":[-122.386155,37.616358],"type":"Point"}
}