{
  "type": "Feature",
  "properties": {
    "date:cessation_lower": "1959-12-31",
    "date:cessation_upper": "1959-12-31",
    "date:inception_lower": "1950-01-01",
    "date:inception_upper": "1950-01-01",
    "iso:country": "XX",
    "sfomuseum:accession_number": "2002.011.043",
    "sfomuseum:airline": "Philippine Airlines",
    "sfomuseum:category": "Promotional",
    "sfomuseum:collection": "Aviation Museum",
    "sfomuseum:creditline": "Purchase",
    "sfomuseum:date": "1950s",
    "sfomuseum:daterange_end": "1959-12-31",
    "sfomuseum:daterange_start": "1950-01-01",
    "sfomuseum:description": "Beige background with blue and black print; text along rim, \"Philippine Air Lines / DC-6 Sleeper Service;\" stylized route map on reverse.",
    "sfomuseum:medium": "paper, metal",
    "sfomuseum:placetype": "object",
    "sfomuseum:subcategory": "Calculator / Converter, Rotary",
    "wof:depicts": [
      1159285015
    ],
    "wof:name": "time converter: Philippine Air Lines",
    "wof:placetype": "venue"
  },
  "geometry": {"coordinates":[-122.386155,37.616357],"type":"Point"}
}
