{
  "type": "Feature",
  "properties": {
    "date:cessation_lower": "1950-01-01",
    "date:cessation_upper": "1959-12-31",
    "date:inception_lower": "1950-01-01",
    "date:inception_upper": "1959-12-31",
    "iso:country": "XX",
    "millsfield:images": [
      1746680897
    ],
    "millsfield:images_texts": [
      "-\nLINES\n•\nD C - 6\nEDMONTONI\nDENVER\nPHOENIX\nWINNIPEG\nCHICAGO\nIDALLAS\nNEW ORLEANS\nINEW YORK\nMIAMI\nHAVANA\nLIMA\nSLEEPER\nSEATTLE\nSAN. FRANCISCO\nLOS ANGELES\nBERMUDA\nBUENOS AIRES\nSANTIAGO\nJUNEAU\nQ\nFAIRBANKS\nANCHORAGE\nHONOLULU\nNOME\nSAMOAI\nINTERNATIONAL\nDATE LINE\nAUCKLAND\nSUVA\n5\n5\nHOUR\nRIO DE JANEIRO\n6\nCLOCK\n8\nAM\nTIME\n10\n10\nPAL\nINSTRUCTION!\nON REVERSE SIDE\nz\nAZORES\nDAKAR\nLONDON\nG\nPARIS\n~ MADRID\nALGIERS\nAMSTERDAM\nL\nn\nTime Selector\nWAKE\nGUAM\nSYDNEY\nMELBOURNE\n0,\nWd\n1\nб\nDARWIN\n81\nTOKYO\nSHANGHAI\nHONG KONG\nMANILA\nPERTHI\nA CIFIC\nSINGAPORE\nDJAKARTA\nKARACHI\nDELHI\nCALCUTTA]\nBOMBAY\nRANGOON\nCOLOMBO\nSTOCKHOLM\nBERLIN\nGENEVA\nROME\nJOHANNESBURI\nHELSINKI\nLYDDA\nCAIRO\nMOSCOW\nDRAHRAN\nTEHERAN\nBAK\nNIER. ORIENT\nCHUNGKING\nSAIGON\nBANGKOK\nORIENT. EUROPE"
    ],
    "millsfield:images_texts_ids": [
      1746680897
    ],
    "millsfield:primary_image": 1746680897,
    "sfomuseum:accession_number": "2002.011.043",
    "sfomuseum:airline": "Philippine Airlines",
    "sfomuseum:category": "Promotional, Museum",
    "sfomuseum:collection": "Aviation Museum",
    "sfomuseum:creditline": "Purchase",
    "sfomuseum:date": "1950s",
    "sfomuseum:date_acquired": "2002-03-01",
    "sfomuseum:daterange_end": "1959-12-31",
    "sfomuseum:daterange_start": "1950-01-01",
    "sfomuseum:description": "Time converter issued by Philippine Air Lines; circular shape with beige background with blue and black print; text along rim, \"Philippine Air Lines / DC-6 Sleeper Service\"; wheel in center with 24-hour clock surrounded by names of destination cities; stylized route map on reverse.",
    "sfomuseum:dimensions": "4 x 4 inches (10.2 x 10.2 cm)",
    "sfomuseum:medium": "paper, metal",
    "sfomuseum:placetype": "object",
    "sfomuseum:publication": ": , 1950s.",
    "sfomuseum:subcategory": "Calculator / Converter, Rotary",
    "wof:depicts": [
      1159285015,
      1159287151
    ],
    "wof:name": "time converter: Philippine Air Lines",
    "wof:placetype": "custom",
    "wof:placetype_alt": "object"
  },
  "geometry": {"coordinates":[-122.386155,37.616357],"type":"Point"}
}
