{
  "type": "Feature",
  "properties": {
    "date:cessation_lower": "1950-01-01",
    "date:cessation_upper": "1959-12-31",
    "date:inception_lower": "1950-01-01",
    "date:inception_upper": "1959-12-31",
    "iso:country": "XX",
    "millsfield:images": [
      1746680897
    ],
    "millsfield:primary_image": 1746680897,
    "sfomuseum:accession_number": "2002.011.043",
    "sfomuseum:airline": "Philippine Airlines",
    "sfomuseum:category": "Promotional",
    "sfomuseum:collection": "Aviation Museum",
    "sfomuseum:creditline": "Purchase",
    "sfomuseum:date": "1950s",
    "sfomuseum:date_acquired": "2002-03-01",
    "sfomuseum:daterange_end": "1959-12-31",
    "sfomuseum:daterange_start": "1950-01-01",
    "sfomuseum:description": "Time converter issued by Philippine Air Lines; circular shape with beige background with blue and black print; text along rim, \"Philippine Air Lines / DC-6 Sleeper Service\"; wheel in center with 24-hour clock surrounded by names of destination cities; stylized route map on reverse.",
    "sfomuseum:dimensions": "4 x 4 inches (10.2 x 10.2 cm)",
    "sfomuseum:medium": "paper, metal",
    "sfomuseum:placetype": "object",
    "sfomuseum:publication": ": , 1950s.",
    "sfomuseum:subcategory": "Calculator / Converter, Rotary",
    "wof:depicts": [
      1159285015,
      1159287151
    ],
    "wof:name": "time converter: Philippine Air Lines",
    "wof:placetype": "custom",
    "wof:placetype_alt": "object"
  },
  "geometry": {"coordinates":[-122.386155,37.616357],"type":"Point"}
}
