{
  "type": "Feature",
  "properties": {
    "date:cessation_lower": "1999-01-01",
    "date:cessation_upper": "1999-12-31",
    "date:inception_lower": "1999-01-01",
    "date:inception_upper": "1999-12-31",
    "iso:country": "XX",
    "sfomuseum:accession_number": "00-0150",
    "sfomuseum:author": "Cage, Cheryl A",
    "sfomuseum:callnumber": "HF5549.5.I6 C33 1999",
    "sfomuseum:category": "Book",
    "sfomuseum:collection": "Aviation Library",
    "sfomuseum:date": "c. 1999",
    "sfomuseum:daterange_end": "2004-12-31",
    "sfomuseum:daterange_start": "1994-01-01",
    "sfomuseum:description": "vi, 118 p. ; 26 cm.",
    "sfomuseum:description_library": "vi, 118 p. ; 26 cm.",
    "sfomuseum:medium": "paper, ink",
    "sfomuseum:placetype": "object",
    "sfomuseum:publication": "Aurora, CO: Cage Consulting, c. 1999.",
    "sfomuseum:publisher": "Cage Consulting",
    "sfomuseum:publisher_location": "Aurora, CO",
    "sfomuseum:subcategory": "Book",
    "sfomuseum:subject": "Air pilots.Interviewing.Employment interviewing.",
    "wof:name": "Checklist for success: a pilot's guide to the successful airline interview",
    "wof:placetype": "custom",
    "wof:placetype_alt": "object"
  },
  "geometry": {"coordinates":[-122.386155,37.616357],"type":"Point"}
}
