{
  "type": "Feature",
  "properties": {
    "date:cessation_lower": "1976-01-01",
    "date:cessation_upper": "1976-12-31",
    "date:inception_lower": "1976-01-01",
    "date:inception_upper": "1976-12-31",
    "iso:country": "XX",
    "millsfield:images": [
      1527843011,
      1527851455
    ],
    "millsfield:images_texts": [
      "VARIG\nBrasilian Airlines\nCRUZEIRO\nBrasilian Airlines\n\"FLYING TOGETHER\"\nINTERNATIONAL\nTIMETABLE\nEFFECTIVE APRIL 25, 1976\nSCHEDULES SHOWN WITHIN ARE SUBJECT TO CHANGE WITHOUT NOTICE",
      "2009112.644\nALL TIME SHOWN ARE LOCAL TIMES.\n•\n- Refueling stop at Panama City.\nDCIU -\nDouglas DC10\n707\nBoeing 707\n737\nBoeing 737\nJohannesburg/Capetown\n3 Sta. Cruz/La Paz/Sta. Cruz.\n727\nBoeing 727\n*\n- Connecting flight\n• - Dep/Arr. Sao Paulo\nVia special connecting flight. (No local traffic Rio/Sao/ Rio\non these flights.)\neconomy Class\n1 Lisbon/Oporto/Lisbon\nTI\nFirst class\nNO TRAFFIC RIGHTS:\nTOKYO\nEXPLANATION OF NOTES\nVARIG\nLOS ANGELES\nNEW YORK\nPARIS\nMEXICO\nBELEM\nCARACAS\nMANAUS\nBOGOTA\nBRASILIA\nLIMA\nSAO PAULO\nASUNCION O\nIGUASSU\nSANTIAGO\nRECIFE\nSALVADOR\nRIO\nBUENOS AIRES\nMONTEVIDEO\nLONDON\nPORTO\nLISBON\nLUANDA\nALSO SERVES 54 CITIES WITHIN BRASIL\nCOPENHAGEN\nFRANKFURT\n• GENEVA\n• ZURICH\nMADRID\nROME\nJOHANNESBURG"
    ],
    "millsfield:images_texts_ids": [
      1527843011,
      1527851455
    ],
    "millsfield:primary_image": 1527843011,
    "sfomuseum:accession_number": "2009.122.644",
    "sfomuseum:airline": "VARIG",
    "sfomuseum:category": "Scheduling / Ticketing",
    "sfomuseum:collection": "Aviation Archive",
    "sfomuseum:creditline": "Gift of the William Hough Collection",
    "sfomuseum:date": "1976",
    "sfomuseum:date_acquired": "2010-06-08",
    "sfomuseum:daterange_end": "1976-12-31",
    "sfomuseum:daterange_start": "1976-01-01",
    "sfomuseum:description": "International timetable issued by VARIG Brasilian Airlines and Cruzeiro Brasilian Airlines, effective April 25, 1976; white cover with illustration of blue, white and black compass rose and blue checkerboard logo.",
    "sfomuseum:dimensions": "9 x 4 inches (22.9 x 10.2 cm)",
    "sfomuseum:media_ids": [
      1527843011,
      1527851455
    ],
    "sfomuseum:medium": "paper, ink",
    "sfomuseum:placetype": "object",
    "sfomuseum:publication": ": , 1976.",
    "sfomuseum:subcategory": "Timetable",
    "wof:depicts": [
      1159288487,
      1159285461
    ],
    "wof:name": "timetable: VARIG, international schedule",
    "wof:placetype": "custom",
    "wof:placetype_alt": "object"
  },
  "geometry": {"coordinates":[-122.386155,37.616357],"type":"Point"}
}
