{
  "type": "Feature",
  "properties": {
    "date:cessation_lower": "1965-07-16",
    "date:cessation_upper": "1965-07-16",
    "date:inception_lower": "1965-07-16",
    "date:inception_upper": "1965-07-16",
    "iso:country": "XX",
    "millsfield:images": [
      1527833577,
      1527833579
    ],
    "millsfield:primary_image": 1527833577,
    "sfomuseum:accession_number": "2012.149.1906 a b",
    "sfomuseum:airline": "Pan American World Airways",
    "sfomuseum:category": "Philately",
    "sfomuseum:collection": "Aviation Archive",
    "sfomuseum:creditline": "Gift of the Captain John B. Russell Family",
    "sfomuseum:date": "07/16/1965",
    "sfomuseum:daterange_end": "1965-07-16",
    "sfomuseum:daterange_start": "1965-07-16",
    "sfomuseum:description": "a. Airmail flight cover, Pan American World Airways, New York to Prague; red cachet at left depicting route map with text, “Pan Am First Jet Service / U.S.A. - Czechoslovakia”; postmarked July 16, 1965, Jamaica, New York, with 15-cent postage stamp; backstamp: July 17, 1966 in Prague; addressed to Oscar H. Fatout.\rb. Newspaper clipping, “New York to Prague Jet Flights Slated.”",
    "sfomuseum:dimensions": "3 1/2 x 6 1/2 inches (8.9 x 16.5 cm)",
    "sfomuseum:media_ids": [
      1527833577,
      1527833579
    ],
    "sfomuseum:medium": "paper, ink",
    "sfomuseum:placetype": "object",
    "sfomuseum:subcategory": "Airmail Flight Cover",
    "wof:depicts": [
      1159284989
    ],
    "wof:name": "airmail flight cover: Pan American World Airways, New York - Prague route",
    "wof:placetype": "venue"
  },
  "geometry": {"coordinates":[-122.386155,37.616357],"type":"Point"}
}
