{
  "type": "Feature",
  "properties": {
    "date:cessation_lower":"1965-12-31",
    "date:cessation_upper":"1965-12-31",
    "date:inception_lower":"1965-01-01",
    "date:inception_upper":"1965-01-01",
    "iso:country":"XX",
    "sfomuseum:accession_number":"2012.149.1906 a b",
    "sfomuseum:category":"Philately",
    "sfomuseum:collection":"Aviation Archive",
    "sfomuseum:creditline":"Gift of the Captain John B. Russell Family",
    "sfomuseum:date":"07/16/1965",
    "sfomuseum:daterange_end":"1965-07-16",
    "sfomuseum:daterange_start":"1965-07-16",
    "sfomuseum:description":"a. Airmail flight cover, Pan American World Airways, New York to Prague; red cachet at left depicting route map with text, \u201cPan Am First Jet Service / U.S.A. - Czechoslovakia\u201d; postmarked July 16, 1965, Jamaica, New York, with 15-cent postage stamp; backstamp: July 17, 1966 in Prague; addressed to Oscar H. Fatout.\rb. Newspaper clipping, \u201cNew York to Prague Jet Flights Slated.\u201d",
    "sfomuseum:medium":"paper, ink",
    "sfomuseum:placetype":"object",
    "sfomuseum:subcategory":"Airmail Flight Cover",
    "wof:name":"airmail flight cover: Pan American World Airways, New York - Prague route",
    "wof:placetype":"venue"
},
  "geometry": {"coordinates":[-122.386155,37.616358],"type":"Point"}
}