{
  "type": "Feature",
  "properties": {
    "date:cessation_lower": "1949-01-01",
    "date:cessation_upper": "1949-12-31",
    "date:inception_lower": "1949-01-01",
    "date:inception_upper": "1949-12-31",
    "iso:country": "XX",
    "sfomuseum:accession_number": "00-2152",
    "sfomuseum:author": "Shields, Bert A.",
    "sfomuseum:callnumber": "TL712 .S45 1949",
    "sfomuseum:category": "Book",
    "sfomuseum:collection": "Aviation Library",
    "sfomuseum:date": "1949",
    "sfomuseum:daterange_end": "1949-12-31",
    "sfomuseum:daterange_start": "1949-01-01",
    "sfomuseum:description": "xiv, 262 p. illus. 24 cm.",
    "sfomuseum:description_library": "xiv, 262 p. illus. 24 cm.",
    "sfomuseum:medium": "paper, ink",
    "sfomuseum:placetype": "object",
    "sfomuseum:publication": "New York: Pitman, 1949.",
    "sfomuseum:publisher": "Pitman",
    "sfomuseum:publisher_location": "New York",
    "sfomuseum:series": "Pitman books on private and business flying.",
    "sfomuseum:subcategory": "Book",
    "sfomuseum:subject": "Airplanes Piloting.Flight training.",
    "wof:name": "Learning to fly",
    "wof:placetype": "custom",
    "wof:placetype_alt": "object"
  },
  "geometry": {"coordinates":[-122.386155,37.616357],"type":"Point"}
}
