{
  "type": "Feature",
  "properties": {
    "date:cessation_lower": "1975-12-31",
    "date:cessation_upper": "1975-12-31",
    "date:inception_lower": "1965-01-01",
    "date:inception_upper": "1965-01-01",
    "iso:country": "XX",
    "sfomuseum:accession_number": "2011.032.2310",
    "sfomuseum:category": "Photograph",
    "sfomuseum:collection": "Aviation Archive",
    "sfomuseum:creditline": "Transfer",
    "sfomuseum:date": "c. 1970",
    "sfomuseum:daterange_end": "1975-12-31",
    "sfomuseum:daterange_start": "1965-01-01",
    "sfomuseum:description": "Affixed, handwritten note: “Various terminal and personal shots / 60s 70s?”. 35mm photographic color negative depicting interior of terminal at San Francisco International Airport (SFO); desk with sign “Charter Limousine Service”; personnel and customers visible.",
    "sfomuseum:media_ids": [
      1527827521
    ],
    "sfomuseum:medium": "negative",
    "sfomuseum:placetype": "object",
    "sfomuseum:subcategory": "Negative",
    "wof:name": "negative: San Francisco International Airport (SFO), lobby interior",
    "wof:placetype": "venue"
  },
  "geometry": {"coordinates":[-122.386155,37.616358],"type":"Point"}
}
