{
  "type": "Feature",
  "properties": {
    "date:cessation_lower": "1976-01-01",
    "date:cessation_upper": "1976-12-31",
    "date:inception_lower": "1976-01-01",
    "date:inception_upper": "1976-12-31",
    "iso:country": "XX",
    "sfomuseum:accession_number": "2012.148.076",
    "sfomuseum:author": "Windrow, Martin, ed.",
    "sfomuseum:callnumber": "TL670 .A368 v.3",
    "sfomuseum:category": "Book",
    "sfomuseum:collection": "Aviation Library",
    "sfomuseum:creditline": "Gift of the Captain John B. Russell Family",
    "sfomuseum:date": "1976",
    "sfomuseum:date_acquired": "2013-05-31",
    "sfomuseum:daterange_end": "1976-12-31",
    "sfomuseum:daterange_start": "1976-01-01",
    "sfomuseum:description": "v. : ill. (part col.) ; 24 cm.",
    "sfomuseum:description_library": "v. : ill. (part col.) ; 24 cm.",
    "sfomuseum:medium": "printed, bound paper",
    "sfomuseum:placetype": "object",
    "sfomuseum:publication": "Garden City, N.Y.: Doubleday and Co., Inc., 1976.",
    "sfomuseum:publisher": "Doubleday and Co., Inc.",
    "sfomuseum:publisher_location": "Garden City, N.Y.",
    "sfomuseum:subcategory": "Book",
    "sfomuseum:subject": "Airplanes -- History.",
    "wof:name": "Aircraft in profile. Volume 3",
    "wof:placetype": "venue"
  },
  "geometry": {"coordinates":[-122.386155,37.616357],"type":"Point"}
}
