{
  "type": "Feature",
  "properties": {
    "date:cessation_lower": "1983-01-01",
    "date:cessation_upper": "1983-12-31",
    "date:inception_lower": "1983-01-01",
    "date:inception_upper": "1983-12-31",
    "iso:country": "XX",
    "millsfield:images": [
      1527834265,
      1527844543
    ],
    "millsfield:images_texts": [
      "AIRCAL\nSYSTEM TIMETABLE\nEffective September 11, 1983\nSEATTLE\nPORTLAND\nSAN FRANCISCO\nOAKLAND\nRENO\n• LAKE TAHOE\nSACRAMENTO\nSAN JOSE\nSINGLE\nCALL\nSERVICE\nWe'll Confirm the Most\nConvenient Flight Available\nBURBANK\nONTARIO\nLOS ANGELES\nORANGE COUNTY",
      "THERE IS A DIFFERENCE\nWe give you more room... We removed over 15% of our seats in order to\nprovide you maximum comfort. Flying AirCal is easy with seat selection,\none stop check in, frequent flights and our spacious legroom.\nAirCals Boeing 737"
    ],
    "millsfield:images_texts_ids": [
      1527834265,
      1527844543
    ],
    "millsfield:primary_image": 1527834265,
    "sfomuseum:accession_number": "2003.105.019.004",
    "sfomuseum:airline": "AirCal",
    "sfomuseum:category": "Scheduling / Ticketing",
    "sfomuseum:collection": "Aviation Archive",
    "sfomuseum:creditline": "Gift of Craig Lynes",
    "sfomuseum:date": "1983",
    "sfomuseum:date_acquired": "2003-12-22",
    "sfomuseum:daterange_end": "1983-12-31",
    "sfomuseum:daterange_start": "1983-01-01",
    "sfomuseum:description": "System timetable issued by AirCal, effective September 11, 1983; seven page fold-out; white and blue cover with route map linking southern and northern destinations on the West Coast with text “Single call service”.",
    "sfomuseum:dimensions": "9 x 4 inches (22.9 x 10.2 cm)",
    "sfomuseum:media_ids": [
      1527844543,
      1527834265
    ],
    "sfomuseum:medium": "paper, ink",
    "sfomuseum:placetype": "object",
    "sfomuseum:publication": ": , 1983.",
    "sfomuseum:subcategory": "Timetable",
    "wof:depicts": [
      1159283791,
      1159286809
    ],
    "wof:name": "timetable: AirCal",
    "wof:placetype": "custom",
    "wof:placetype_alt": [
      "object"
    ]
  },
  "geometry": {"coordinates":[-122.386155,37.616357],"type":"Point"}
}
