{
  "type": "Feature",
  "properties": {
    "date:cessation_lower": "1934-01-01",
    "date:cessation_upper": "1934-12-31",
    "date:inception_lower": "1934-01-01",
    "date:inception_upper": "1934-12-31",
    "iso:country": "US",
    "millsfield:images": [
      1527821763
    ],
    "millsfield:images_texts": [
      "ALASKA\nWinter\nbuAIR and\nSchEdulE\nWATER\nMODERN RADIO- EQUIPPED PLANES\nPACIFIC-ALASKA\nAirways INC."
    ],
    "millsfield:images_texts_ids": [
      1527821763
    ],
    "millsfield:primary_image": 1527821763,
    "sfomuseum:accession_number": "2008.056.0446",
    "sfomuseum:airline": "Pacific Alaska Airways",
    "sfomuseum:category": "Scheduling / Ticketing",
    "sfomuseum:collection": "Aviation Archive",
    "sfomuseum:continent": "North America",
    "sfomuseum:country": "United States",
    "sfomuseum:creditline": "Gift of Jon E. Krupnick",
    "sfomuseum:date": "1934",
    "sfomuseum:date_acquired": "2008-12-31",
    "sfomuseum:daterange_end": "1934-12-31",
    "sfomuseum:daterange_start": "1934-01-01",
    "sfomuseum:description": "Timetable issued by Pacific Alaska Airways, effective November 1, 1934, winter service; blue and red cover with illustration of aircraft in flightand text “Alaska by air and water / Modern radio-equipped planes”; includes fare information, and route map.",
    "sfomuseum:dimensions": "9 x 4 inches (22.9 x 10.2 cm)",
    "sfomuseum:media_ids": [
      1527821763
    ],
    "sfomuseum:medium": "paper, ink",
    "sfomuseum:placetype": "object",
    "sfomuseum:publication": ": , 1934.",
    "sfomuseum:subcategory": "Timetable",
    "sfomuseum:subject": "Airlines -- Commercial -- Pacific Alaska Airways\r",
    "wof:depicts": [
      1159284957,
      1159288169
    ],
    "wof:name": "timetable: Pacific Alaska Airways, winter schedule",
    "wof:placetype": "custom",
    "wof:placetype_alt": "object"
  },
  "geometry": {"coordinates":[-122.386155,37.616357],"type":"Point"}
}
