{
  "type": "Feature",
  "properties": {
    "date:cessation_lower": "1965-01-01",
    "date:cessation_upper": "1965-12-31",
    "date:inception_lower": "1965-01-01",
    "date:inception_upper": "1965-12-31",
    "iso:country": "XX",
    "millsfield:images": [
      1527852233
    ],
    "millsfield:primary_image": 1527852233,
    "sfomuseum:accession_number": "2008.056.1119",
    "sfomuseum:airline": "Pan American World Airways",
    "sfomuseum:category": "Photograph",
    "sfomuseum:collection": "Aviation Archive",
    "sfomuseum:creditline": "Gift of Jon E. Krupnick",
    "sfomuseum:date": "c. 1965",
    "sfomuseum:daterange_end": "1970-12-31",
    "sfomuseum:daterange_start": "1960-01-01",
    "sfomuseum:description": "Color photograph of two-story structure displaying exterior sign, \"Birthplace of Pan American World Airways\". \"Tom Elder\" and \"Coconut Grove\" handwritten on verso.",
    "sfomuseum:dimensions": "3 1/2 x 5 inches (8.9 x 12.7 cm)",
    "sfomuseum:issues_held": "\r",
    "sfomuseum:media_ids": [
      1527852233
    ],
    "sfomuseum:medium": "photograph",
    "sfomuseum:placetype": "object",
    "sfomuseum:subcategory": "Print, Photograph",
    "sfomuseum:subject": "Airlines -- Commercial -- Pan American World Airways",
    "wof:depicts": [
      1159284989
    ],
    "wof:name": "photograph: Pan American World Airways",
    "wof:placetype": "venue"
  },
  "geometry": {"coordinates":[-122.386155,37.616357],"type":"Point"}
}
