{
  "type": "Feature",
  "properties": {
    "date:cessation_lower":"1940-12-31",
    "date:cessation_upper":"1940-12-31",
    "date:inception_lower":"1940-01-01",
    "date:inception_upper":"1940-01-01",
    "iso:country":"US",
    "millsfield:images":[
        1527829053
    ],
    "sfomuseum:accession_number":"1994.18.118",
    "sfomuseum:category":"Philately",
    "sfomuseum:collection":"Aviation Archive",
    "sfomuseum:continent":"Transpacific",
    "sfomuseum:country":"United States",
    "sfomuseum:creditline":"Purchase",
    "sfomuseum:date":"7/12/1940",
    "sfomuseum:daterange_end":"1940-07-12",
    "sfomuseum:daterange_start":"1940-07-12",
    "sfomuseum:description":"Airmail flight cover, Pan American Airways, part of first airmail service between United States and New Zealand, Los Angeles - Noumea route; blue cachet with image of route map with palm tree and building (type F19b); two stamps: two green 50-cent (United States); postmark: postmark: July 12, 1940, Los Angeles with four-bar cancellation mark; backstamp: July 16, 1940, Noumea; envelope: white air mail with blue and red rhomboids around border.",
    "sfomuseum:maker":"Pan American Airways, Inc.",
    "sfomuseum:media_ids":[
        1527829053
    ],
    "sfomuseum:medium":"ink on paper",
    "sfomuseum:placetype":"object",
    "sfomuseum:subcategory":"Airmail Flight Cover",
    "wof:name":"airmail flight cover: United States Air Mail, first airmail flight, FAM-19, Los Angeles - Noumea (New Caledonia) route",
    "wof:placetype":"venue"
},
  "geometry": {"coordinates":[-122.386155,37.616358],"type":"Point"}
}