{
  "type": "Feature",
  "properties": {
    "date:cessation_lower": "1954-12-31",
    "date:cessation_upper": "1954-12-31",
    "date:inception_lower": "1954-01-01",
    "date:inception_upper": "1954-01-01",
    "iso:country": "XX",
    "sfomuseum:accession_number": "2014.156.214 a b",
    "sfomuseum:category": "Philately",
    "sfomuseum:collection": "Aviation Archive",
    "sfomuseum:creditline": "Gift of Captain Jon Simmonds",
    "sfomuseum:date": "06/01/1954",
    "sfomuseum:daterange_end": "1954-06-01",
    "sfomuseum:daterange_start": "1954-06-01",
    "sfomuseum:description": "a. Airmail flight cover, United Air Lines, Douglas DC-7 first nonstop flight from San Francisco to New York, postmarked June 1, 1954, with imprinted 6-cent postage stamp; blue cachet at left with text, “First Non-Stop Flight / San Francisco - New York / United Air Lines / June 1, 1954 / DC-7”; envelope addressed to Mrs. L. I. Imlay, Camarillo, California; backstamped June 1, 1954, New York City.\rb. Enclosure with printed note.",
    "sfomuseum:media_ids": [
      1527856669, 
      1527856671
    ],
    "sfomuseum:medium": "paper, ink",
    "sfomuseum:placetype": "object",
    "sfomuseum:subcategory": "Airmail Flight Cover",
    "wof:name": "airmail flight cover: United Air Lines, Douglas DC-7, San Francisco - New York route",
    "wof:placetype": "venue"
  },
  "geometry": {"coordinates":[-122.386155,37.616358],"type":"Point"}
}
