{
  "type": "Feature",
  "properties": {
    "date:cessation_lower": "1936-12-31",
    "date:cessation_upper": "1936-12-31",
    "date:inception_lower": "1936-01-01",
    "date:inception_upper": "1936-01-01",
    "iso:country": "XX",
    "sfomuseum:accession_number": "2008.075.095",
    "sfomuseum:category": "Philately",
    "sfomuseum:collection": "Aviation Archive",
    "sfomuseum:creditline": "Gift of Jon E. Krupnick",
    "sfomuseum:date": "10/01/1936",
    "sfomuseum:daterange_end": "1936-10-01",
    "sfomuseum:daterange_start": "1936-10-01",
    "sfomuseum:description": "Airmail flight cover for U.S. Navy 1936 Pacific Maneuvers, April 22 - October 1, 1936.\rEnvelope with large navy blue cachet at left with text \"This cover was carried by me during the 1936, Naval Manouvres, and on all flights in which I participated\" and signed by pilot, St. C. Keene with plane number 1-S-10; postmarked October 1, 1936, San Diego. Calif with “U.S. Naval Air” cancellation mark over two 3-cent stamps; addressed to Mr. J.H. Spiegelberg.",
    "sfomuseum:media_ids": [
      1527851741
    ],
    "sfomuseum:medium": "paper, ink",
    "sfomuseum:placetype": "object",
    "sfomuseum:subcategory": "Airmail Flight Cover",
    "wof:name": "airmail flight cover: U.S. Navy, 1936 Pacific Maneuvers, April 22 - October 1, 1936",
    "wof:placetype": "venue"
  },
  "geometry": {"coordinates":[-122.386155,37.616358],"type":"Point"}
}
