{
  "type": "Feature",
  "properties": {
    "date:cessation_lower":"1979-12-31",
    "date:cessation_upper":"1979-12-31",
    "date:inception_lower":"1970-01-01",
    "date:inception_upper":"1970-01-01",
    "iso:country":"XX",
    "millsfield:images":[
        1527842279,
        1527842275
    ],
    "sfomuseum:accession_number":"2002.035.367",
    "sfomuseum:category":"Passenger Amenity",
    "sfomuseum:collection":"Aviation Museum",
    "sfomuseum:creditline":"Gift of Thomas G. Dragges",
    "sfomuseum:date":"1970s",
    "sfomuseum:daterange_end":"1979-12-31",
    "sfomuseum:daterange_start":"1970-01-01",
    "sfomuseum:description":"Flat bottom, wire closure. White bag with yellow print; \"TWA\" and interlocking globe logo located top quadrant. Front features illustration of a dog\u2019s head with text \"After You've Had a Chance to Roam Don't Forget Those Left Back Home.\" Reverse features scoreboard for gin rummy game. \"For Motion Discomfort . . .\" printed on bottom with written instructions for use in English and French.",
    "sfomuseum:media_ids":[
        1527842275,
        1527842279
    ],
    "sfomuseum:medium":"paper, ink, wire",
    "sfomuseum:placetype":"object",
    "sfomuseum:subcategory":"Airsickness Bag",
    "wof:name":"airsickness / doggie bag: TWA (Trans World Airlines)",
    "wof:placetype":"venue"
},
  "geometry": {"coordinates":[-122.386155,37.616358],"type":"Point"}
}