{
  "type": "Feature",
  "properties": {
    "date:cessation_lower": "1967-12-31",
    "date:cessation_upper": "1967-12-31",
    "date:inception_lower": "1967-01-01",
    "date:inception_upper": "1967-01-01",
    "iso:country": "XX",
    "sfomuseum:accession_number": "2005.132.002.001",
    "sfomuseum:category": "Scheduling / Ticketing",
    "sfomuseum:collection": "Aviation Archive",
    "sfomuseum:creditline": "Gift of the William Hough Collection",
    "sfomuseum:date": "1967",
    "sfomuseum:daterange_end": "1967-12-31",
    "sfomuseum:daterange_start": "1967-01-01",
    "sfomuseum:description": "Timetable issued by Air California, effective September 22, 1967; single double-sided sheet. The schedule is gray with red lettering. The front cites various fares and has servicemark at top center. The verso is the schedule.",
    "sfomuseum:media_ids": [
      1527832177, 
      1527844223
    ],
    "sfomuseum:medium": "paper, ink",
    "sfomuseum:placetype": "object",
    "sfomuseum:subcategory": "Timetable",
    "wof:name": "timetable: Air California",
    "wof:placetype": "venue"
  },
  "geometry": {"coordinates":[-122.386155,37.616358],"type":"Point"}
}
