{
  "type": "Feature",
  "properties": {
    "date:cessation_lower": "1974-01-01",
    "date:cessation_upper": "1974-12-31",
    "date:inception_lower": "1974-01-01",
    "date:inception_upper": "1974-12-31",
    "iso:country": "XX",
    "millsfield:images": [
      1527840089
    ],
    "millsfield:primary_image": 1527840089,
    "sfomuseum:accession_number": "2009.122.347",
    "sfomuseum:airline": "Japan Air Lines",
    "sfomuseum:category": "Scheduling / Ticketing",
    "sfomuseum:collection": "Aviation Archive",
    "sfomuseum:creditline": "Gift of the William Hough Collection",
    "sfomuseum:date": "1974",
    "sfomuseum:date_acquired": "2010-06-08",
    "sfomuseum:daterange_end": "1974-12-31",
    "sfomuseum:daterange_start": "1974-01-01",
    "sfomuseum:description": "Timetable issued by Japan Air Lines, effective November 1, 1974 through March 31, 1975; 41-page fold-out schedule; color photographic image of a field in low light; in Japanese, French, German and English.",
    "sfomuseum:dimensions": "8 x 4 inches (20.3 x 10.2 cm)",
    "sfomuseum:media_ids": [
      1527840089
    ],
    "sfomuseum:medium": "paper, ink",
    "sfomuseum:placetype": "object",
    "sfomuseum:publication": ": , 1974.",
    "sfomuseum:subcategory": "Timetable",
    "wof:depicts": [
      1159288505,
      1159285785
    ],
    "wof:name": "timetable: Japan Air Lines (Japan Airlines)",
    "wof:placetype": "custom",
    "wof:placetype_alt": "object"
  },
  "geometry": {"coordinates":[-122.386155,37.616357],"type":"Point"}
}
