{
  "type": "Feature",
  "properties": {
    "date:cessation_lower":"1974-12-31",
    "date:cessation_upper":"1974-12-31",
    "date:inception_lower":"1974-01-01",
    "date:inception_upper":"1974-01-01",
    "iso:country":"XX",
    "millsfield:images":[
        1527840089
    ],
    "sfomuseum:accession_number":"2009.122.347",
    "sfomuseum:category":"Scheduling / Ticketing",
    "sfomuseum:collection":"Aviation Archive",
    "sfomuseum:creditline":"Gift of the William Hough Collection",
    "sfomuseum:date":"1974",
    "sfomuseum:daterange_end":"1974-12-31",
    "sfomuseum:daterange_start":"1974-01-01",
    "sfomuseum:description":"Timetable issued by JAL (Japan Air Lines), effective November 1, 1974 through March 31, 1975; forty-one page fold-out schedule; on cover: color photographic image of a field. A large company logo is in the upper left hand corner; in Japanese, French, German and English.",
    "sfomuseum:media_ids":[
        1527840089
    ],
    "sfomuseum:medium":"paper, ink",
    "sfomuseum:placetype":"object",
    "sfomuseum:subcategory":"Timetable",
    "wof:name":"timetable: JAL (Japan Air Lines)",
    "wof:placetype":"venue"
},
  "geometry": {"coordinates":[-122.386155,37.616358],"type":"Point"}
}