{
  "type": "Feature",
  "properties": {
    "date:cessation_lower": "1980-01-01",
    "date:cessation_upper": "1989-12-31",
    "date:inception_lower": "1980-01-01",
    "date:inception_upper": "1989-12-31",
    "iso:country": "XX",
    "millsfield:images": [
      1729565521
    ],
    "millsfield:primary_image": 1729565521,
    "sfomuseum:accession_number": "2007.007.028",
    "sfomuseum:airline": "Trans Australia Airlines (TAA)",
    "sfomuseum:category": "Map / Chart",
    "sfomuseum:collection": "Aviation Archive",
    "sfomuseum:creditline": "Gift of Hiller Aviation Museum",
    "sfomuseum:date": "1980s",
    "sfomuseum:date_acquired": "2008-03-03",
    "sfomuseum:daterange_end": "1980-12-31",
    "sfomuseum:daterange_start": "1980-01-01",
    "sfomuseum:description": "Route map issued by Trans Australia Airlines (TAA) for routes between Papua New Guinea and nearby islands; fold-out format; color photographic image of man with painted face.",
    "sfomuseum:dimensions": "9 x 3 1/4 inches (22.9 x 8.3 cm)",
    "sfomuseum:medium": "paper, ink",
    "sfomuseum:placetype": "object",
    "sfomuseum:publication": ": , 1980s.",
    "sfomuseum:subcategory": "Route",
    "sfomuseum:subject": "Airlines -- Commercial --",
    "wof:depicts": [
      1159285345
    ],
    "wof:name": "route map: Trans Australia Airlines (TAA), Papua New Guinea",
    "wof:placetype": "venue"
  },
  "geometry": {"coordinates":[-122.386155,37.616357],"type":"Point"}
}
