{
  "type": "Feature",
  "properties": {
    "date:cessation_lower": "1958-12-31",
    "date:cessation_upper": "1958-12-31",
    "date:inception_lower": "1958-01-01",
    "date:inception_upper": "1958-01-01",
    "iso:country": "XX",
    "sfomuseum:accession_number": "2000.181.096",
    "sfomuseum:author": "Knight, Clayton",
    "sfomuseum:callnumber": "TL553.5 .K6 1958 c.1",
    "sfomuseum:category": "Book",
    "sfomuseum:collection": "Aviation Library",
    "sfomuseum:creditline": "Gift of William A. Mathis",
    "sfomuseum:date": "1958",
    "sfomuseum:daterange_end": "1958-12-31",
    "sfomuseum:daterange_start": "1958-01-01",
    "sfomuseum:description": "213 p. illus. 22 cm.",
    "sfomuseum:medium": "paper, ink",
    "sfomuseum:placetype": "object",
    "sfomuseum:publisher": "Greenberg",
    "sfomuseum:publisher_location": "New York",
    "sfomuseum:subcategory": "Book",
    "sfomuseum:subject": "Aeronautics Accidents.",
    "wof:name": "Plane crash: the mysteries of major air disasters and how they were solved",
    "wof:placetype": "venue"
  },
  "geometry": {"coordinates":[-122.386155,37.616357],"type":"Point"}
}
