{
  "type": "Feature",
  "properties": {
    "date:cessation_lower": "1989-01-01",
    "date:cessation_upper": "1989-12-31",
    "date:inception_lower": "1989-01-01",
    "date:inception_upper": "1989-12-31",
    "iso:country": "XX",
    "millsfield:images": [
      1527836217
    ],
    "millsfield:primary_image": 1527836217,
    "sfomuseum:accession_number": "2003.105.047.024",
    "sfomuseum:airline": "Delta Air Lines",
    "sfomuseum:category": "Scheduling / Ticketing",
    "sfomuseum:collection": "Aviation Archive",
    "sfomuseum:creditline": "Gift of Craig Lynes",
    "sfomuseum:date": "1989",
    "sfomuseum:date_acquired": "2003-12-29",
    "sfomuseum:daterange_end": "1989-12-31",
    "sfomuseum:daterange_start": "1989-01-01",
    "sfomuseum:description": "System timetable issued by Delta Air Lines, effective December 15, 1989; 441-page schedule; color photographic image of a young woman in traditional Thai dress with text, “Delta Adds Another Level in Asia: Bangkok.”",
    "sfomuseum:dimensions": "9 x 4 inches (22.9 x 10.2 cm)",
    "sfomuseum:media_ids": [
      1527836217
    ],
    "sfomuseum:medium": "paper, ink",
    "sfomuseum:placetype": "object",
    "sfomuseum:publication": ": , 1989.",
    "sfomuseum:subcategory": "Timetable",
    "wof:depicts": [
      1159284261,
      1159287931
    ],
    "wof:name": "timetable: Delta Air Lines",
    "wof:placetype": "custom",
    "wof:placetype_alt": "object"
  },
  "geometry": {"coordinates":[-122.386155,37.616357],"type":"Point"}
}
