{
  "type": "Feature",
  "properties": {
    "date:cessation_lower":"2007-12-31",
    "date:cessation_upper":"2007-12-31",
    "date:inception_lower":"2007-01-01",
    "date:inception_upper":"2007-01-01",
    "iso:country":"XX",
    "sfomuseum:accession_number":"2008.022.001",
    "sfomuseum:category":"Audio / Visual",
    "sfomuseum:collection":"Aviation Archive",
    "sfomuseum:creditline":"Transfer from City and County of San Francisco",
    "sfomuseum:date":"2007",
    "sfomuseum:daterange_end":"2007-12-31",
    "sfomuseum:daterange_start":"2007-01-01",
    "sfomuseum:description":"Video formatted to DVD with following chapters:\r1. The beginning\r2. The Dole Race\r3. Lindbergh at Oakland\r4. Amelia Earhart\r5. The 1930s\r6. Post- World War II\r7. World Airways\r8. The Jet Age\r9. The Future\rIncludes case.",
    "sfomuseum:medium":"DVD",
    "sfomuseum:placetype":"object",
    "sfomuseum:subcategory":"DVD",
    "wof:depicts":[
        85921881,
        85688637,
        85633793
    ],
    "wof:name":"DVD: Oakland International: a history in flight [DVD] / Port of Oakland",
    "wof:placetype":"venue"
},
  "geometry": {"coordinates":[-122.386155,37.616357],"type":"Point"}
}