{
  "type": "Feature",
  "properties": {
    "date:cessation_lower": "2007-01-01",
    "date:cessation_upper": "2007-12-31",
    "date:inception_lower": "2007-01-01",
    "date:inception_upper": "2007-12-31",
    "iso:country": "XX",
    "sfomuseum:accession_number": "2008.022.001",
    "sfomuseum:airport": "Oakland International Airport",
    "sfomuseum:category": "Audio / Visual",
    "sfomuseum:collection": "Aviation Archive",
    "sfomuseum:creditline": "Transfer from City and County of San Francisco",
    "sfomuseum:date": "2007",
    "sfomuseum:date_acquired": "2008-08-21",
    "sfomuseum:daterange_end": "2007-12-31",
    "sfomuseum:daterange_start": "2007-01-01",
    "sfomuseum:description": "DVD produced by the Port of Oakland, titled “Oakland International: a history in flight”; includes the following chapters:\r1. The beginning\r2. The Dole Race\r3. Lindbergh at Oakland\r4. Amelia Earhart\r5. The 1930s\r6. Post- World War II\r7. World Airways\r8. The Jet Age\r9. The Future\rIncludes case.",
    "sfomuseum:dimensions": "7 1/4 x 5 1/4 inches (18.4 x 13.3 cm)",
    "sfomuseum:medium": "plastic, foil",
    "sfomuseum:placetype": "object",
    "sfomuseum:publication": "Oakland, CA: Port of Oakland, 2007.",
    "sfomuseum:publisher": "Port of Oakland",
    "sfomuseum:publisher_location": "Oakland, CA",
    "sfomuseum:subcategory": "DVD",
    "sfomuseum:subject": "Oakland International Airport",
    "wof:depicts": [
      85688637,
      85633793,
      85921881,
      102531041
    ],
    "wof:name": "DVD: Oakland International: a history in flight [DVD] / Port of Oakland",
    "wof:placetype": "venue"
  },
  "geometry": {"coordinates":[-122.386155,37.616357],"type":"Point"}
}
