{
  "type": "Feature",
  "properties": {
    "date:cessation_lower": "1929-01-01",
    "date:cessation_upper": "1929-12-31",
    "date:inception_lower": "1929-01-01",
    "date:inception_upper": "1929-12-31",
    "iso:country": "XX",
    "millsfield:images": [
      1527831509
    ],
    "millsfield:primary_image": 1527831509,
    "sfomuseum:accession_number": "2010.279.001.074",
    "sfomuseum:airline": "New York, Rio, and Buenos Aires Line (NYRBA)",
    "sfomuseum:category": "Company Record / Document",
    "sfomuseum:collection": "Aviation Archive",
    "sfomuseum:creditline": "Gift of Jon E. Krupnick",
    "sfomuseum:date": "1929",
    "sfomuseum:daterange_end": "1929-12-31",
    "sfomuseum:daterange_start": "1929-01-01",
    "sfomuseum:description": "Orange and white stock certificate issued to Ralph A. O’Neill for 1000 shares of New York, Rio \u0026 Buenos Aires Line Inc.; certificate number 1497, dated September 20, 1929; original signatures of [?] Reynolds, Treasurer, and [illegible signature], Vice President; countersigned by Chatham Phenix National Bank and Trust Company, registered September 21, 1929 by Irving Trust Company.",
    "sfomuseum:dimensions": "8 1/4 x 11 3/4 inches (21 x 29.8 cm)",
    "sfomuseum:media_ids": [
      1527831509
    ],
    "sfomuseum:medium": "paper, ink",
    "sfomuseum:placetype": "object",
    "sfomuseum:publication": ": , 1929.",
    "sfomuseum:subcategory": "Stock Certificate / Bond",
    "wof:depicts": [
      1159284865
    ],
    "wof:name": "stock certificate: New York, Rio \u0026 Buenos Aires Line",
    "wof:placetype": "venue"
  },
  "geometry": {"coordinates":[-122.386155,37.616357],"type":"Point"}
}
