{
  "type": "Feature",
  "properties": {
    "date:cessation_lower": "1991-01-01",
    "date:cessation_upper": "1991-12-31",
    "date:inception_lower": "1991-01-01",
    "date:inception_upper": "1991-12-31",
    "isbn:number": "0711020256 (pbk.), 9780711020252 (pbk.)",
    "iso:country": "XX",
    "sfomuseum:accession_number": "1999.659.115",
    "sfomuseum:author": "Endres, GËunter G.",
    "sfomuseum:callnumber": "TL603 .E53 1991",
    "sfomuseum:category": "Book",
    "sfomuseum:collection": "Aviation Library",
    "sfomuseum:creditline": "Collection of SFO Museum",
    "sfomuseum:date": "1991",
    "sfomuseum:date_acquired": "1997-08-20",
    "sfomuseum:daterange_end": "1991-12-31",
    "sfomuseum:daterange_start": "1991-01-01",
    "sfomuseum:description": "[128] p. :  col. ill. ; 19 cm.",
    "sfomuseum:description_library": "[128] p. :  col. ill. ; 19 cm.",
    "sfomuseum:medium": "paper, ink",
    "sfomuseum:placetype": "object",
    "sfomuseum:publication": "Shepperton, Surrey, England: Ian Allan, 1991.",
    "sfomuseum:publisher": "Ian Allan",
    "sfomuseum:publisher_location": "Shepperton, Surrey, England",
    "sfomuseum:subcategory": "Book",
    "sfomuseum:subject": "Aeronautics, Commercial.Airlines Pictorial works.Airplanes Markings.Aircraft Markings",
    "wof:name": "Abc airline liveries",
    "wof:placetype": "custom",
    "wof:placetype_alt": [
      "object"
    ]
  },
  "geometry": {"coordinates":[-122.386155,37.616357],"type":"Point"}
}
