{
  "type": "Feature",
  "properties": {
    "date:cessation_lower": "1992-01-01",
    "date:cessation_upper": "1992-12-31",
    "date:inception_lower": "1992-01-01",
    "date:inception_upper": "1992-12-31",
    "iso:country": "XX",
    "loc:subject_headings": [
      "sh90000314"
    ],
    "sfomuseum:accession_number": "2004.004.058",
    "sfomuseum:airline": "Pan American World Airways",
    "sfomuseum:author": "Cox, Matthew",
    "sfomuseum:callnumber": "HV6431 .C695 1992",
    "sfomuseum:category": "Book",
    "sfomuseum:collection": "Aviation Library",
    "sfomuseum:creditline": "Purchase",
    "sfomuseum:date": "1992",
    "sfomuseum:date_acquired": "2004-12-31",
    "sfomuseum:daterange_end": "1992-12-31",
    "sfomuseum:daterange_start": "1992-01-01",
    "sfomuseum:description": "xiv, 233 p., [8] p. of plates : ill., map ; 25 cm.",
    "sfomuseum:description_library": "xiv, 233 p., [8] p. of plates : ill., map ; 25 cm.",
    "sfomuseum:medium": "paper, ink",
    "sfomuseum:placetype": "object",
    "sfomuseum:publication": "New York: Grove Weidenfeld, 1992.",
    "sfomuseum:publisher": "Grove Weidenfeld",
    "sfomuseum:publisher_location": "New York",
    "sfomuseum:subcategory": "Book",
    "sfomuseum:subject": "Pan Am Flight 103 Bombing Incident, 1988.",
    "wof:depicts": [
      1159284989,
      1159286839
    ],
    "wof:name": "Their darkest day: the tragedy of Pan Am 103 and its legacy of hope",
    "wof:placetype": "venue"
  },
  "geometry": {"coordinates":[-122.386155,37.616357],"type":"Point"}
}
