{
  "type": "Feature",
  "properties": {
    "date:cessation_lower":"1999-12-31",
    "date:cessation_upper":"1999-12-31",
    "date:inception_lower":"1990-01-01",
    "date:inception_upper":"1990-01-01",
    "iso:country":"XX",
    "sfomuseum:accession_number":"1998.157.196",
    "sfomuseum:category":"Passenger Amenity",
    "sfomuseum:collection":"Aviation Museum",
    "sfomuseum:creditline":"Gift of The Henry Steiner Air Sickness Bag Collection",
    "sfomuseum:date":"1990s",
    "sfomuseum:daterange_end":"1999-12-31",
    "sfomuseum:daterange_start":"1990-01-01",
    "sfomuseum:description":"Flat bottom, wire tab closure. White, yellow, blue bag, white print. White at top followed by yellow stripe. Remaining two-thirds of bag is blue. \"Singapore Airlines\" in white on lower portion. Logo above it, bird in white. Design on both sides.",
    "sfomuseum:medium":"paper",
    "sfomuseum:placetype":"object",
    "sfomuseum:subcategory":"Airsickness Bag",
    "wof:name":"airsickness bag: Singapore Airlines",
    "wof:placetype":"venue"
},
  "geometry": {"coordinates":[-122.386155,37.616358],"type":"Point"}
}