{
  "type": "Feature",
  "properties": {
    "date:cessation_lower": "1972-01-01",
    "date:cessation_upper": "1972-12-31",
    "date:inception_lower": "1972-01-01",
    "date:inception_upper": "1972-12-31",
    "iso:country": "XX",
    "millsfield:images": [
      1527839695
    ],
    "millsfield:primary_image": 1527839695,
    "sfomuseum:accession_number": "2005.132.022.014",
    "sfomuseum:airline": "Golden West Airlines",
    "sfomuseum:category": "Scheduling / Ticketing",
    "sfomuseum:collection": "Aviation Archive",
    "sfomuseum:creditline": "Gift of the William Hough Collection",
    "sfomuseum:date": "1972",
    "sfomuseum:daterange_end": "1972-12-31",
    "sfomuseum:daterange_start": "1972-01-01",
    "sfomuseum:description": "Timetable issued by Golden West Airlines, effective July 1, 1972; four page double-sided fold-out. The cover is white and with white logos and names of various airlines. A large number 1 on the gold field advertises “One call does it all.” ",
    "sfomuseum:dimensions": "9 x 4 inches (22.9 x 10.2 cm)",
    "sfomuseum:media_ids": [
      1527839695
    ],
    "sfomuseum:medium": "paper, ink",
    "sfomuseum:placetype": "object",
    "sfomuseum:subcategory": "Timetable",
    "wof:depicts": [
      1159284453
    ],
    "wof:name": "timetable: Golden West Airlines",
    "wof:placetype": "venue"
  },
  "geometry": {"coordinates":[-122.386155,37.616357],"type":"Point"}
}
