{
  "type": "Feature",
  "properties": {
    "date:cessation_lower": "1939-05-24",
    "date:cessation_upper": "1939-05-24",
    "date:inception_lower": "1939-05-24",
    "date:inception_upper": "1939-05-24",
    "iso:country": "XX",
    "millsfield:images": [
      1527852027,
      1527852029
    ],
    "millsfield:images_texts": [
      "AVION\nERVICE POSTAL\nAERIEN\nPAR\nFRANCE• ETATS- UNIS\nYANKEE CLIPPER\nFIRST FLIGHT\nRE EXPOSITION INTERTATIONALE\nNEW-YORK 1939\n225\n10F POSTeS RF\nTATION\n9-76\n39\nH.M.Strouss\n2846 Lincolnte\nAlameda\nCaliF\nV.S.A\nRANS • ATLANTIC\nAIR SERVICE",
      "* MAY 27\nш 530PM\n7939\n629X"
    ],
    "millsfield:images_texts_ids": [
      1527852027,
      1527852029
    ],
    "millsfield:primary_image": 1527852027,
    "sfomuseum:accession_number": "2012.149.2213",
    "sfomuseum:aircraft": "Boeing 314 Yankee Clipper",
    "sfomuseum:airline": "Pan American Airways",
    "sfomuseum:category": "Philately",
    "sfomuseum:collection": "Aviation Archive",
    "sfomuseum:creditline": "Gift of the Captain John B. Russell Family",
    "sfomuseum:date": "05/24/1939",
    "sfomuseum:date_acquired": "2013-05-31",
    "sfomuseum:daterange_end": "1939-05-24",
    "sfomuseum:daterange_start": "1939-05-24",
    "sfomuseum:description": "Airmail flight cover, Pan American Airways, first Clipper flight, FAM-18, Marseilles - New York route; red stamped cachet with image of airplane over Statue of Liberty at left; postmarked May 24, 1939 in Paris with two postage stamps and blue courtesy stamp; backstamp: May 27, 1939 in New York; red and blue border at bottom edge with red globe and text, “Yankee Clipper first flight / trans-atlantic air service”. Originally mounted to backing sheet 2012.149.2212 b with typewritten caption: “F18-6 Marseilles - New York”.",
    "sfomuseum:dimensions": "3 3/4 x 6 1/2 inches (9.5 x 16.5 cm)",
    "sfomuseum:media_ids": [
      1527852027,
      1527852029
    ],
    "sfomuseum:medium": "paper, ink",
    "sfomuseum:placetype": "object",
    "sfomuseum:publication": ": , 05/24/1939.",
    "sfomuseum:subcategory": "Airmail Flight Cover",
    "sfomuseum:subject": "Airlines -- Commercial -- Pan American Airways.",
    "wof:depicts": [
      1159289633,
      1159293593,
      1159284991
    ],
    "wof:name": "airmail flight cover: Pan American Airways, FAM-18, first airmail flight, Marseilles - New York route",
    "wof:placetype": "custom",
    "wof:placetype_alt": "object"
  },
  "geometry": {"coordinates":[-122.386155,37.616357],"type":"Point"}
}
