{
  "type": "Feature",
  "properties": {
    "date:cessation_lower": "1939-12-31",
    "date:cessation_upper": "1939-12-31",
    "date:inception_lower": "1939-01-01",
    "date:inception_upper": "1939-01-01",
    "iso:country": "XX",
    "sfomuseum:accession_number": "2012.149.2213",
    "sfomuseum:category": "Philately",
    "sfomuseum:collection": "Aviation Archive",
    "sfomuseum:creditline": "Gift of the Captain John B. Russell Family",
    "sfomuseum:date": "05/24/1939",
    "sfomuseum:daterange_end": "1939-05-24",
    "sfomuseum:daterange_start": "1939-05-24",
    "sfomuseum:description": "Airmail flight cover, Pan American Airways, first Clipper flight, FAM-18, Marseilles - New York route; red stamped cachet with image of airplane over Statue of Liberty at left; postmarked May 24, 1939 in Paris with two postage stamps and blue courtesy stamp; backstamp: May 27, 1939 in New York; red and blue border at bottom edge with red globe and text, “Yankee Clipper first flight / trans-atlantic air service”. Originally mounted to backing sheet 2012.149.2212 b with typewritten caption: “F18-6 Marseilles - New York”.",
    "sfomuseum:media_ids": [
      1527852027, 
      1527852029
    ],
    "sfomuseum:medium": "paper, ink",
    "sfomuseum:placetype": "object",
    "sfomuseum:subcategory": "Airmail Flight Cover",
    "wof:name": "airmail flight cover: Pan American Airways, FAM-18, first airmail flight, Marseilles - New York route",
    "wof:placetype": "venue"
  },
  "geometry": {"coordinates":[-122.386155,37.616358],"type":"Point"}
}
