{
  "type": "Feature",
  "properties": {
    "date:cessation_lower": "1958-01-01",
    "date:cessation_upper": "1958-12-31",
    "date:inception_lower": "1958-01-01",
    "date:inception_upper": "1958-12-31",
    "iso:country": "XX",
    "loc:subject_headings": [
      "sh85095629",
      "sh00006421"
    ],
    "sfomuseum:accession_number": "2006.057.002",
    "sfomuseum:author": "Gatty, Harold",
    "sfomuseum:callnumber": "GV200.4 .G37 1958 c.1",
    "sfomuseum:category": "Book",
    "sfomuseum:collection": "Aviation Library",
    "sfomuseum:creditline": "Collection of SFO Museum",
    "sfomuseum:date": "1958",
    "sfomuseum:date_acquired": "2006-12-13",
    "sfomuseum:daterange_end": "1958-12-31",
    "sfomuseum:daterange_start": "1958-01-01",
    "sfomuseum:description": "254 p., [20] p. of plates : ill. (1 col.), maps ; 21 cm.",
    "sfomuseum:description_library": "254 p., [20] p. of plates : ill. (1 col.), maps ; 21 cm.",
    "sfomuseum:medium": "paper, ink",
    "sfomuseum:placetype": "object",
    "sfomuseum:publication": "London: Collins, 1958.",
    "sfomuseum:publisher": "Collins",
    "sfomuseum:publisher_location": "London",
    "sfomuseum:subcategory": "Book",
    "sfomuseum:subject": "Orientation.",
    "wof:name": "Nature is your guide: how to find your way on land \u0026 sea",
    "wof:placetype": "custom",
    "wof:placetype_alt": [
      "object"
    ]
  },
  "geometry": {"coordinates":[-122.386155,37.616357],"type":"Point"}
}
