{
  "type": "Feature",
  "properties": {
    "date:cessation_lower": "1939-01-01",
    "date:cessation_upper": "1939-12-31",
    "date:inception_lower": "1939-01-01",
    "date:inception_upper": "1939-12-31",
    "iso:country": "XX",
    "millsfield:exhibition_ids": [
      1159160217
    ],
    "millsfield:images": [
      1746680181,
      1897761875,
      1897761877,
      1897761881
    ],
    "millsfield:images_colors_refs": {
      "crayola": [
        {
          "hex": "#85754e"
        },
        {
          "hex": "#cdc5c2"
        },
        {
          "hex": "#dbd7d2"
        },
        {
          "hex": "#414a4c"
        },
        {
          "hex": "#fddde6"
        }
      ],
      "css4": [
        {
          "hex": "#d3d3d3"
        },
        {
          "hex": "#556b2f"
        },
        {
          "hex": "#dcdcdc"
        },
        {
          "hex": "#696969"
        },
        {
          "hex": "#f5f5f5"
        }
      ],
      "marekm4": [
        {
          "hex": "#edeeec"
        },
        {
          "hex": "#523e34"
        },
        {
          "hex": "#8e6851"
        },
        {
          "hex": "#d8d7d7"
        },
        {
          "hex": "#534235"
        },
        {
          "hex": "#574c3e"
        },
        {
          "hex": "#cdcecd"
        },
        {
          "hex": "#dfdbdb"
        },
        {
          "hex": "#5a493c"
        }
      ]
    },
    "millsfield:images_texts": [
      "MERRY\nXMAS"
    ],
    "millsfield:images_texts_ids": [
      1746680181
    ],
    "millsfield:on_view": 0,
    "millsfield:primary_image": 1746680181,
    "sfomuseum:accession_number": "2000.058.0058",
    "sfomuseum:airline": "Pan American Airways",
    "sfomuseum:category": "Promotional, Museum",
    "sfomuseum:collection": "Aviation Museum",
    "sfomuseum:creditline": "Gift of the Pan Am Association",
    "sfomuseum:date": "1939",
    "sfomuseum:date_acquired": "2000-12-14",
    "sfomuseum:daterange_end": "1939-12-31",
    "sfomuseum:daterange_start": "1939-01-01",
    "sfomuseum:description": "Souvenir box commemorating Christmas 1939 on Midway Island; lidded box with engraved text, \"Merry X-mas / \"Midway '39.\"",
    "sfomuseum:dimensions": "3/4 x 1 1/2 x 1 inches (1.9 x 3.8 x 2.5 cm)",
    "sfomuseum:exhibition_ids": [
      1131
    ],
    "sfomuseum:medium": "copper",
    "sfomuseum:placetype": "object",
    "sfomuseum:publication": ": , 1939.",
    "sfomuseum:subcategory": "Product",
    "wof:depicts": [
      1159284991,
      1159286839
    ],
    "wof:name": "souvenir box: Pan American Airways, Midway Island",
    "wof:placetype": "custom",
    "wof:placetype_alt": [
      "object"
    ]
  },
  "geometry": {"coordinates":[-122.386155,37.616357],"type":"Point"}
}
