{
  "type": "Feature",
  "properties": {
    "date:cessation_lower": "1983-01-01",
    "date:cessation_upper": "1983-12-31",
    "date:inception_lower": "1983-01-01",
    "date:inception_upper": "1983-12-31",
    "iso:country": "XX",
    "millsfield:images": [
      1527844747
    ],
    "millsfield:images_texts": [
      "System Timetable\nEffective April 24 through May 31, 1983\nFM TO DPT\nFLI EU FREd\nSTL 8010P 864N\n444 727\nDFw JFK 1149h 0409r 716 /c/\nDSM STL 97504 0845\nED FREQ\n555 7275 X6\nEUR ORD\nSTL 0645\n29 D98\nFLL MCO 0258P 0345P 497 721\nX13\nIAD CDG\n93338\n00.08\n01188\nTO SK 100 120P 00 77\nКерер\n9882888\n022888\n886556t\n87758⅔9⅝88\n8086\nEU FRE\nSYR STL 0950A 1115A 71 72\nTLY CDG 6720A 1155A 801 L1\nTOL STL 0959 BS 7 TE"
    ],
    "millsfield:images_texts_ids": [
      1527844747
    ],
    "millsfield:primary_image": 1527844747,
    "sfomuseum:accession_number": "2008.055.988",
    "sfomuseum:airline": "TWA (Trans World Airlines)",
    "sfomuseum:category": "Scheduling / Ticketing",
    "sfomuseum:collection": "Aviation Archive",
    "sfomuseum:creditline": "Gift of the William Hough Collection",
    "sfomuseum:date": "1983",
    "sfomuseum:date_acquired": "2008-04-13",
    "sfomuseum:daterange_end": "1983-12-31",
    "sfomuseum:daterange_start": "1983-01-01",
    "sfomuseum:description": "Timetable issued by TWA (Trans World Airlines), effective April 24 through May 31, 1983; double-sided newspaper tearsheet with system schedule on one side and general airline news on the other.",
    "sfomuseum:dimensions": "16 x 11 1/4 inches (40.6 x 28.6 cm)",
    "sfomuseum:media_ids": [
      1527844747
    ],
    "sfomuseum:medium": "paper, ink",
    "sfomuseum:placetype": "object",
    "sfomuseum:publication": ": , 1983.",
    "sfomuseum:subcategory": "Timetable",
    "sfomuseum:subject": "Airlines -- Commercial -- TWA (Trans World Airlines)",
    "wof:depicts": [
      1159285393,
      1159287531
    ],
    "wof:name": "timetable / newspaper tearsheet: TWA (Trans World Airlines)",
    "wof:placetype": "custom",
    "wof:placetype_alt": [
      "object"
    ]
  },
  "geometry": {"coordinates":[-122.386155,37.616357],"type":"Point"}
}
