{
  "type": "Feature",
  "properties": {
    "date:cessation_lower": "1950-01-01",
    "date:cessation_upper": "1950-12-31",
    "date:inception_lower": "1950-01-01",
    "date:inception_upper": "1950-12-31",
    "iso:country": "XX",
    "millsfield:images": [
      1527818333
    ],
    "millsfield:images_texts": [
      "in HAWAIl vacation with\nALONA\nAIRLINES\nto flightsee all the islands\nFor\nFlightseeing\nComfort\nALOHA AIRLINES\nHONOLULU INTERNATIONAL AIRPOR. HONOLULU, HAWAIl\nFICE: 2235 KALAKAUA AVENUE"
    ],
    "millsfield:images_texts_ids": [
      1527818333
    ],
    "millsfield:primary_image": 1527818333,
    "sfomuseum:accession_number": "2007.011.358",
    "sfomuseum:airline": "Aloha Airlines",
    "sfomuseum:category": "Promotional, Archive",
    "sfomuseum:collection": "Aviation Archive",
    "sfomuseum:creditline": "Gift of the William Hough Collection",
    "sfomuseum:date": "c. 1950",
    "sfomuseum:date_acquired": "2006-11-10",
    "sfomuseum:daterange_end": "1955-12-31",
    "sfomuseum:daterange_start": "1945-01-01",
    "sfomuseum:description": "Tourist information brochure issued by Aloha Airlines, titled \"In Hawaii vacation with Aloha Airlines to flightsee all the islands\"; fold-out format; yellow cover with color photographic image of Hawaiian woman in traditional dress; contains descriptions of the major islands except Oahu; large fold-out map of the islands with major points of interest and air mileages between the island airports.",
    "sfomuseum:dimensions": "9 x 4 inches (22.9 x 10.2 cm)",
    "sfomuseum:media_ids": [
      1527818333
    ],
    "sfomuseum:medium": "paper, ink",
    "sfomuseum:placetype": "object",
    "sfomuseum:publication": ": , c. 1950.",
    "sfomuseum:subcategory": "Brochure, Tourist Information",
    "wof:depicts": [
      1159283845,
      1159286909
    ],
    "wof:name": "tourist information: Aloha Airlines",
    "wof:placetype": "custom",
    "wof:placetype_alt": "object"
  },
  "geometry": {"coordinates":[-122.386155,37.616357],"type":"Point"}
}
