{
  "type": "Feature",
  "properties": {
    "date:cessation_lower": "2012-01-01",
    "date:cessation_upper": "2012-12-31",
    "date:inception_lower": "2012-01-01",
    "date:inception_upper": "2012-12-31",
    "iso:country": "XX",
    "loc:subject_headings": [
      "sh85127066"
    ],
    "sfomuseum:accession_number": "2012.120.001",
    "sfomuseum:author": "Dodson, Jamie",
    "sfomuseum:callnumber": "PS3604.O33 M37 2012",
    "sfomuseum:category": "Book",
    "sfomuseum:collection": "Aviation Library",
    "sfomuseum:creditline": "Gift of Jamie Dodson",
    "sfomuseum:date": "2012",
    "sfomuseum:date_acquired": "2012-11-01",
    "sfomuseum:daterange_end": "2012-12-31",
    "sfomuseum:daterange_start": "2012-01-01",
    "sfomuseum:description": "205 p. : ill. ; 21 cm.",
    "sfomuseum:description_library": "205 p. : ill. ; 21 cm.",
    "sfomuseum:medium": "paper, ink",
    "sfomuseum:placetype": "object",
    "sfomuseum:publication": "Madison, Ala.: Onstage Pub., 2012.",
    "sfomuseum:publisher": "Onstage Pub.",
    "sfomuseum:publisher_location": "Madison, Ala.",
    "sfomuseum:subcategory": "Book",
    "sfomuseum:subject": "Spy stories. \rGrant, Nick (Fictitious character) -- Fiction. \rUnited States -- History -- 1933-1945 -- Fiction.",
    "wof:name": "Mission Shanghai: a Nick Grant adventure",
    "wof:placetype": "venue"
  },
  "geometry": {"coordinates":[-122.386155,37.616357],"type":"Point"}
}
