{
  "type": "Feature",
  "properties": {
    "date:cessation_lower":"1999-12-31",
    "date:cessation_upper":"1999-12-31",
    "date:inception_lower":"1990-01-01",
    "date:inception_upper":"1990-01-01",
    "iso:country":"XX",
    "sfomuseum:accession_number":"1998.157.178",
    "sfomuseum:category":"Passenger Amenity",
    "sfomuseum:collection":"Aviation Museum",
    "sfomuseum:creditline":"Gift of The Henry Steiner Air Sickness Bag Collection",
    "sfomuseum:date":"1990s",
    "sfomuseum:daterange_end":"1999-12-31",
    "sfomuseum:daterange_start":"1990-01-01",
    "sfomuseum:description":"Gusset wedge, no closure. White bag, blue and red print. Airline logo in left lower corner, red triangle with white kangaroo. Instructions in blue in eleven languages.",
    "sfomuseum:media_ids":[
        1527842113
    ],
    "sfomuseum:medium":"paper",
    "sfomuseum:placetype":"object",
    "sfomuseum:subcategory":"Airsickness Bag",
    "wof:depicts":[
        [
            1159285043
        ],
        1159285043
    ],
    "wof:name":"airsickness bag: Qantas Airways",
    "wof:placetype":"venue"
},
  "geometry": {"coordinates":[-122.386155,37.616358],"type":"Point"}
}