{
  "type": "Feature",
  "properties": {
    "date:cessation_lower": "1990-01-01",
    "date:cessation_upper": "1999-12-31",
    "date:inception_lower": "1990-01-01",
    "date:inception_upper": "1999-12-31",
    "iso:country": "XX",
    "millsfield:images": [
      1527842113
    ],
    "millsfield:images_texts": [
      "WASTE BAG\nAfter using this bag, please leave it on your seat at the next stop and\na replacement bag will be provided. Thank you.\nCHANDELEI, BERRENT, ESK. X\nABFALLTÜTE\nBitte lassen Sie die Tüte nach Gebrauch bei der nächsten Landung\nauf Ihrem Sitz liegen. Ihnen wird dann eine neue Tüte gegeben.\nDanke.\nPOCHETTE A ORDURES\nAprès usage, veuiliez laisser cette pochette sur votre siège à la\nprochaine escale et elle sera remplacée. Merci.\nSACCHETTO PER I RIFIUTI\nDopo aver usato questo sacchetto, per cortesia lasciatelo sui vostro\nsedile al prossimo scalo e sara sostituito. Grazie.\nгАКОУЛА АПОРРІМАТО\nАфо хопошопоаєте аті ти сакойла, афроте ту пш ото\nOE avTIKaTáOTaON TS. EuxapIoToúuE.\nAFVALZAK\nWilt u na gebruik deze zak bij de volgende stop op uw plaats laten\nliggen. U wordt dan voorzien van een nieuwe. Dank u.\nBOLSA PARA LOS DESPERDICIOS\nDespués de usar esta bolsa, sírvase dejarla sobre su asiento en la\npróxima escala del avión y se la reemplazará por una bolsa nueva.\nGracias.\nKANTUNG KOTORAN\nSesudah kantung ini dipergunakan, tinggalkaniah kantung tersebut di\natas tempat duduk anda di perhentian yang berikut dan kantung baru\nakan diberikan. Terima kash.\nand be"
    ],
    "millsfield:images_texts_ids": [
      1527842113
    ],
    "millsfield:primary_image": 1527842113,
    "sfomuseum:accession_number": "1998.157.178",
    "sfomuseum:airline": "Qantas Airways",
    "sfomuseum:category": "Passenger Amenity, Archive",
    "sfomuseum:collection": "Aviation Archive",
    "sfomuseum:creditline": "Gift of The Henry Steiner Air Sickness Bag Collection",
    "sfomuseum:date": "1990s",
    "sfomuseum:date_acquired": "1999-07-13",
    "sfomuseum:daterange_end": "1999-12-31",
    "sfomuseum:daterange_start": "1990-01-01",
    "sfomuseum:description": "Airsickness bag issued by Qantas Airways; white bag with red logo and instructions for use in eleven languages; gusset wedge, no closure.",
    "sfomuseum:dimensions": "10 1/4 x 6 1/4 inches (26 x 15.9 cm)",
    "sfomuseum:media_ids": [
      1527842113
    ],
    "sfomuseum:medium": "paper, ink",
    "sfomuseum:placetype": "object",
    "sfomuseum:publication": ": , 1990s.",
    "sfomuseum:subcategory": "Airsickness Bag",
    "wof:depicts": [
      1159285043,
      1159287479
    ],
    "wof:name": "airsickness bag: Qantas Airways",
    "wof:placetype": "custom",
    "wof:placetype_alt": [
      "object"
    ]
  },
  "geometry": {"coordinates":[-122.386155,37.616357],"type":"Point"}
}
