{
  "type": "Feature",
  "properties": {
    "date:cessation_lower": "1935-01-01",
    "date:cessation_upper": "1935-12-31",
    "date:inception_lower": "1935-01-01",
    "date:inception_upper": "1935-12-31",
    "iso:country": "US",
    "millsfield:images": [
      1527820831
    ],
    "millsfield:primary_image": 1527820831,
    "sfomuseum:accession_number": "2008.056.0918",
    "sfomuseum:airline": "SCADTA (Sociedad Colombo Alemana de Transporte Aéreo)",
    "sfomuseum:category": "Scheduling / Ticketing",
    "sfomuseum:collection": "Aviation Archive",
    "sfomuseum:continent": "North America",
    "sfomuseum:country": "United States",
    "sfomuseum:creditline": "Gift of Jon E. Krupnick",
    "sfomuseum:date": "1935",
    "sfomuseum:date_acquired": "2008-12-31",
    "sfomuseum:daterange_end": "1935-12-31",
    "sfomuseum:daterange_start": "1935-01-01",
    "sfomuseum:description": "Folded timetable issued by SCADTA (Sociedad Colombo-Alemana de Transpoertes Aereos), effective May 1, 1935; white, green and red, titled \"Seguridad Rapidez Economia\"; in Spanish.",
    "sfomuseum:dimensions": "6 1/4 x 3 1/2 inches (15.9 x 8.9 cm)",
    "sfomuseum:media_ids": [
      1527820831
    ],
    "sfomuseum:medium": "paper, ink",
    "sfomuseum:placetype": "object",
    "sfomuseum:publication": ": , 1935.",
    "sfomuseum:subcategory": "Timetable",
    "sfomuseum:subject": "Airlines -- Commercial -- SCADTA",
    "wof:depicts": [
      1159285127,
      1159286991
    ],
    "wof:name": "timetable: SCADTA (Sociedad Colombo-Alemana de Transpoertes Aereos)",
    "wof:placetype": "custom",
    "wof:placetype_alt": "object"
  },
  "geometry": {"coordinates":[-122.386155,37.616357],"type":"Point"}
}
