{
  "type": "Feature",
  "properties": {
    "date:cessation_lower": "2001-01-01",
    "date:cessation_upper": "2001-12-31",
    "date:inception_lower": "2001-01-01",
    "date:inception_upper": "2001-12-31",
    "iso:country": "XX",
    "millsfield:images": [
      1527840541
    ],
    "millsfield:images_texts": [
      "Worldwide Timetable\nVOLUME 1, 2001\nJAN 8 - FEB 14\nStretch out\nand fly\nUnited makes flying even more\ncomfortable by increasing\nlegroom on international flights\nWUNITED\nA STAR ALLIANCE MEMBER T"
    ],
    "millsfield:images_texts_ids": [
      1527840541
    ],
    "millsfield:primary_image": 1527840541,
    "sfomuseum:accession_number": "2006.059.101.095",
    "sfomuseum:airline": "United Airlines",
    "sfomuseum:category": "Scheduling / Ticketing",
    "sfomuseum:collection": "Aviation Archive",
    "sfomuseum:creditline": "Gift of the Paul Edward Fair Estate",
    "sfomuseum:date": "2001",
    "sfomuseum:date_acquired": "2006-10-19",
    "sfomuseum:daterange_end": "2001-12-31",
    "sfomuseum:daterange_start": "2001-01-01",
    "sfomuseum:description": "Worldwide timetable issued by United Airlines, effective January 8 through February 14, 2001; on cover: low color photographic image of a person jumping off of a hilltop with text “Stretch out and fly”; includes United Express and United Shuttle.",
    "sfomuseum:dimensions": "8 1/2 x 4 inches (21.6 x 10.2 cm)",
    "sfomuseum:media_ids": [
      1527840541
    ],
    "sfomuseum:medium": "paper, ink",
    "sfomuseum:placetype": "object",
    "sfomuseum:publication": ": , 2001.",
    "sfomuseum:subcategory": "Timetable",
    "wof:depicts": [
      1159285417,
      1159285423,
      1159288779,
      1159285413
    ],
    "wof:name": "timetable: United Airlines",
    "wof:placetype": "custom",
    "wof:placetype_alt": [
      "object"
    ]
  },
  "geometry": {"coordinates":[-122.386155,37.616357],"type":"Point"}
}
