{
  "type": "Feature",
  "properties": {
    "date:cessation_lower": "1996-01-01",
    "date:cessation_upper": "1996-12-31",
    "date:inception_lower": "1996-01-01",
    "date:inception_upper": "1996-12-31",
    "iso:country": "XX",
    "sfomuseum:accession_number": "2005.013.001",
    "sfomuseum:author": "Nilsson, Lars-Axel",
    "sfomuseum:callnumber": "UG1245.S70 N56 1996",
    "sfomuseum:category": "Book",
    "sfomuseum:collection": "Aviation Library",
    "sfomuseum:creditline": "Gift of the author",
    "sfomuseum:date": "1996",
    "sfomuseum:date_acquired": "2005-12-01",
    "sfomuseum:daterange_end": "1996-12-31",
    "sfomuseum:daterange_start": "1996-01-01",
    "sfomuseum:description": "303 p. ill., ports. 25 cm.\r387.709485 NIL",
    "sfomuseum:description_library": "303 p. ill., ports. 25 cm.\r387.709485 NIL",
    "sfomuseum:medium": "paper, ink",
    "sfomuseum:placetype": "object",
    "sfomuseum:publication": "Sweden: The authors, 1996.",
    "sfomuseum:publisher": "The authors",
    "sfomuseum:publisher_location": "Sweden",
    "sfomuseum:subcategory": "Book",
    "sfomuseum:subject": "Florman, Carl.",
    "wof:name": "Blockade Runners: Sweden's lifeline in the Second World War [swedish title: Kurirflgy, en livlina under andra vèarldskriget.]",
    "wof:placetype": "custom",
    "wof:placetype_alt": "object"
  },
  "geometry": {"coordinates":[-122.386155,37.616357],"type":"Point"}
}
