{
  "type": "Feature",
  "properties": {
    "date:cessation_lower":"1958-12-31",
    "date:cessation_upper":"1958-12-31",
    "date:inception_lower":"1958-01-01",
    "date:inception_upper":"1958-01-01",
    "iso:country":"XX",
    "sfomuseum:accession_number":"2001.039.287",
    "sfomuseum:category":"Map / Chart",
    "sfomuseum:collection":"Aviation Archive",
    "sfomuseum:creditline":"Gift of David A. Abercrombie, in memory of Stanley A. Abercrombie ",
    "sfomuseum:date":"1958",
    "sfomuseum:daterange_end":"1958-12-31",
    "sfomuseum:daterange_start":"1958-01-01",
    "sfomuseum:description":"Route map produced by TWA (Trans World Airlines), titled \u201cUnited States route map and souvenir atlas\u201d; white cover with red and brown illustration depicting arrows orbiting planet Earth; fold-out format.",
    "sfomuseum:medium":"paper, ink",
    "sfomuseum:placetype":"object",
    "sfomuseum:subcategory":"Route",
    "wof:name":"route map: TWA (Trans World Airlines)",
    "wof:placetype":"venue"
},
  "geometry": {"coordinates":[-122.386155,37.616358],"type":"Point"}
}