{
  "type": "Feature",
  "properties": {
    "date:cessation_lower": "1958-01-01",
    "date:cessation_upper": "1958-12-31",
    "date:inception_lower": "1958-01-01",
    "date:inception_upper": "1958-12-31",
    "iso:country": "XX",
    "millsfield:images": [
      1527844127
    ],
    "millsfield:images_texts": [
      "TWA\nUNITED STATES ROUTE MAP\nand SOUVENIR ATLAS"
    ],
    "millsfield:images_texts_ids": [
      1527844127
    ],
    "millsfield:primary_image": 1527844127,
    "sfomuseum:accession_number": "2001.039.287",
    "sfomuseum:airline": "TWA (Trans World Airlines)",
    "sfomuseum:category": "Map / Chart",
    "sfomuseum:collection": "Aviation Archive",
    "sfomuseum:creditline": "Gift of David A. Abercrombie in memory of Stanley A. Abercrombie",
    "sfomuseum:date": "1958",
    "sfomuseum:date_acquired": "2001-07-19",
    "sfomuseum:daterange_end": "1958-12-31",
    "sfomuseum:daterange_start": "1958-01-01",
    "sfomuseum:description": "Route map issued by TWA (Trans World Airlines), titled “United States route map and souvenir atlas”; fold-out format; white cover with red and brown illustration depicting arrows orbiting planet Earth.",
    "sfomuseum:dimensions": "7 1/4 x 4 inches (18.4 x 10.2 cm)",
    "sfomuseum:media_ids": [
      1527844127
    ],
    "sfomuseum:medium": "paper, ink",
    "sfomuseum:placetype": "object",
    "sfomuseum:publication": ": , 1958.",
    "sfomuseum:subcategory": "Route",
    "wof:depicts": [
      1159285393,
      1159287531
    ],
    "wof:name": "route map: TWA (Trans World Airlines)",
    "wof:placetype": "custom",
    "wof:placetype_alt": [
      "object"
    ]
  },
  "geometry": {"coordinates":[-122.386155,37.616357],"type":"Point"}
}
