{
  "type": "Feature",
  "properties": {
    "date:cessation_lower": "1991-01-01",
    "date:cessation_upper": "1991-12-31",
    "date:inception_lower": "1991-01-01",
    "date:inception_upper": "1991-12-31",
    "iso:country": "XX",
    "millsfield:images": [
      1527842989,
      1527851211
    ],
    "millsfield:images_texts": [
      "USAir\nSYSTEM TIMETABLE\nEFFECTIVE NOVEMBER I, 1991\n• RRSERVATIONS: 1-800-428-432\nIntroducing new nonstop service\nbetween Charlotte and Frankfurt.\nUSAir begins with you",
      "With Our Connections,\nYou Can GoA Long Way.\n• USAR\nA USUR DEFRESS\nMINIUSARUSAR EXFRESS\nSERVICE BASEDUPON\nNOVEMBER 1, 191 SCHEDULING\nTogether, USAir and USAir Express have over 4,600 flights a day to more than 262 cities\nacross the United States and Canada. Plus flights to Bermuda, the Bahamas, Puerto Rico, London,\nFrankfurt, and beginning January 1992, Paris. So when it's time to travel, remember the airlines\nthat are well connected: USAir and USAir Express. For reservations and information, call your\ntravel consultant or USAir toll-free at 1(800)428-4322\nUSAir\nUSAir\nEXPRESS"
    ],
    "millsfield:images_texts_ids": [
      1527842989,
      1527851211
    ],
    "millsfield:primary_image": 1527842989,
    "sfomuseum:accession_number": "2008.108.879",
    "sfomuseum:airline": "USAir",
    "sfomuseum:category": "Scheduling / Ticketing",
    "sfomuseum:collection": "Aviation Archive",
    "sfomuseum:creditline": "Gift of the William Hough Collection",
    "sfomuseum:date": "1991",
    "sfomuseum:date_acquired": "2008-11-10",
    "sfomuseum:daterange_end": "1991-12-31",
    "sfomuseum:daterange_start": "1991-01-01",
    "sfomuseum:description": "System timetable issued by USAir, effective November 1, 1991; white cover with color photographic image of boy in traditional Bavarian attire and text promoting Frankfurt, Germany service; includes USAir Express.",
    "sfomuseum:dimensions": "9 x 4 inches (22.9 x 10.2 cm)",
    "sfomuseum:media_ids": [
      1527842989,
      1527851211
    ],
    "sfomuseum:medium": "paper, ink",
    "sfomuseum:placetype": "object",
    "sfomuseum:publication": ": , 1991.",
    "sfomuseum:subcategory": "Timetable",
    "sfomuseum:subject": "Airlines -- Commercial -- USAir",
    "wof:depicts": [
      1159285447,
      1159288239
    ],
    "wof:name": "timetable: USAir",
    "wof:placetype": "custom",
    "wof:placetype_alt": "object"
  },
  "geometry": {"coordinates":[-122.386155,37.616357],"type":"Point"}
}
