{
  "type": "Feature",
  "properties": {
    "date:cessation_lower": "1996-01-01",
    "date:cessation_upper": "1996-12-31",
    "date:inception_lower": "1996-01-01",
    "date:inception_upper": "1996-12-31",
    "iso:country": "XX",
    "sfomuseum:accession_number": "00-2097",
    "sfomuseum:author": "Penlington, Valerie Ann",
    "sfomuseum:callnumber": "DS796.H7 P46 1996",
    "sfomuseum:category": "Book",
    "sfomuseum:collection": "Aviation Library",
    "sfomuseum:date": "1996",
    "sfomuseum:daterange_end": "1996-12-31",
    "sfomuseum:daterange_start": "1996-01-01",
    "sfomuseum:description": "224 p. : ill. (some col.) ; 26 cm.",
    "sfomuseum:description_library": "224 p. : ill. (some col.) ; 26 cm.",
    "sfomuseum:medium": "paper, ink",
    "sfomuseum:placetype": "object",
    "sfomuseum:publication": "s.l.: Odyssey, 1996.",
    "sfomuseum:publisher": "Odyssey",
    "sfomuseum:publisher_location": "s.l.",
    "sfomuseum:subcategory": "Book",
    "sfomuseum:subject": "Royal Hong Kong Auxiliary Air Force History.Military service, Voluntary China Hong Kong.",
    "wof:name": "Winged dragon: the history of the Royal Hong Kong Auxiliary Air Force",
    "wof:placetype": "custom",
    "wof:placetype_alt": "object"
  },
  "geometry": {"coordinates":[-122.386155,37.616357],"type":"Point"}
}
