{
  "type": "Feature",
  "properties": {
    "date:cessation_lower": "1935-01-01",
    "date:cessation_upper": "1935-12-31",
    "date:inception_lower": "1935-01-01",
    "date:inception_upper": "1935-12-31",
    "iso:country": "US",
    "sfomuseum:accession_number": "2003.114.001",
    "sfomuseum:aircraft": "Martin M-130 China Clipper",
    "sfomuseum:airline": "Pan American Airways",
    "sfomuseum:category": "Décor",
    "sfomuseum:collection": "Aviation Museum",
    "sfomuseum:continent": "North America",
    "sfomuseum:country": "United States",
    "sfomuseum:creditline": "Anonymous gift",
    "sfomuseum:date": "c. 1935",
    "sfomuseum:daterange_end": "1940-12-31",
    "sfomuseum:daterange_start": "1930-01-01",
    "sfomuseum:description": "Thermometer manufactured by Syroco, depicting decorative wood relief of Pan American Airways, Martin M-130 “China Clipper” seaplane in flight above city skyline and waves; propeller blade representation on base.",
    "sfomuseum:dimensions": "3 1/2 x 3 3/4 x 1 1/4 inches (8.9 x 9.5 x 3.2 cm)",
    "sfomuseum:maker": "SyrocoWood",
    "sfomuseum:medium": "composite wood, plastic",
    "sfomuseum:placetype": "object",
    "sfomuseum:publication": ": , c. 1935.",
    "sfomuseum:subcategory": "Thermometer",
    "wof:depicts": [
      1159284991,
      1159291193,
      1159291191
    ],
    "wof:name": "thermometer: Pan American Airways, Martin M-130 “China Clipper”",
    "wof:placetype": "venue"
  },
  "geometry": {"coordinates":[-122.386155,37.616357],"type":"Point"}
}
