{
  "type": "Feature",
  "properties": {
    "date:cessation_lower":"1940-12-31",
    "date:cessation_upper":"1940-12-31",
    "date:inception_lower":"1930-01-01",
    "date:inception_upper":"1930-01-01",
    "iso:country":"US",
    "sfomuseum:accession_number":"2003.114.001",
    "sfomuseum:category":"D\u00e9cor",
    "sfomuseum:collection":"Aviation Museum",
    "sfomuseum:continent":"North America",
    "sfomuseum:country":"United States",
    "sfomuseum:creditline":"Gift of anonymous donor",
    "sfomuseum:date":"c. 1935",
    "sfomuseum:daterange_end":"1940-12-31",
    "sfomuseum:daterange_start":"1930-01-01",
    "sfomuseum:description":"Thermometer manufactured by Syroco, depicting decorative wood relief of Pan American Airways, Martin M-130 \u201cChina Clipper\u201d seaplane in flight above city skyline and waves; propeller blade representation on base.",
    "sfomuseum:maker":"SyrocoWood",
    "sfomuseum:medium":"composite wood, plastic",
    "sfomuseum:placetype":"object",
    "sfomuseum:subcategory":"Thermometer",
    "wof:name":"thermometer: Pan American Airways, Martin M-130 \u201cChina Clipper\u201d",
    "wof:placetype":"venue"
},
  "geometry": {"coordinates":[-122.386155,37.616358],"type":"Point"}
}