{
  "type": "Feature",
  "properties": {
    "date:cessation_lower": "1999-01-01",
    "date:cessation_upper": "1999-12-31",
    "date:inception_lower": "1999-01-01",
    "date:inception_upper": "1999-12-31",
    "iso:country": "XX",
    "millsfield:images": [
      1527840579
    ],
    "millsfield:primary_image": 1527840579,
    "sfomuseum:accession_number": "2011.126.033.014",
    "sfomuseum:airline": "United Airlines",
    "sfomuseum:category": "Scheduling / Ticketing",
    "sfomuseum:collection": "Aviation Archive",
    "sfomuseum:creditline": "Gift of the Paul H. Kowalewski Collection",
    "sfomuseum:date": "1999",
    "sfomuseum:date_acquired": "2011-12-22",
    "sfomuseum:daterange_end": "1999-12-31",
    "sfomuseum:daterange_start": "1999-01-01",
    "sfomuseum:description": "Worldwide timetable issued by United Air Lines, effective April 4 through June 9, 1999; blue cover with duotone photographic image depicting Dulles International Airport and control tower; includes United Express and United Shuttle.",
    "sfomuseum:dimensions": "9 x 4 x 3/4 inches (22.9 x 10.2 x 1.9 cm)",
    "sfomuseum:media_ids": [
      1527840579
    ],
    "sfomuseum:medium": "paper, ink",
    "sfomuseum:placetype": "object",
    "sfomuseum:publication": ": , 1999.",
    "sfomuseum:subcategory": "Timetable",
    "wof:depicts": [
      1159285413,
      1159285417,
      1159288779,
      1159285423
    ],
    "wof:name": "timetable: United Airlines",
    "wof:placetype": "custom",
    "wof:placetype_alt": "object"
  },
  "geometry": {"coordinates":[-122.386155,37.616357],"type":"Point"}
}
