{
  "type": "Feature",
  "properties": {
    "date:cessation_lower": "1938-01-01",
    "date:cessation_upper": "1938-12-31",
    "date:inception_lower": "1938-01-01",
    "date:inception_upper": "1938-12-31",
    "iso:country": "XX",
    "millsfield:images": [
      1763372847,
      1763372849
    ],
    "millsfield:primary_image": 1763372847,
    "sfomuseum:accession_number": "2006.028.109",
    "sfomuseum:airline": "Transcontinental \u0026 Western Air",
    "sfomuseum:category": "Meal Service",
    "sfomuseum:collection": "Aviation Museum",
    "sfomuseum:creditline": "Gift of Edith Lauterbach",
    "sfomuseum:date": "c. 1938",
    "sfomuseum:date_acquired": "2006-04-18",
    "sfomuseum:daterange_end": "1943-12-31",
    "sfomuseum:daterange_start": "1933-01-01",
    "sfomuseum:description": "Spoon issued by Transcontinental \u0026 Western Air for inflight meal service; silver spoon with tapered handle; logotype stamped on reverse.",
    "sfomuseum:dimensions": "5 3/4 x 1 x 3/4 inches (14.6 x 2.5 x 1.9 cm)",
    "sfomuseum:maker": "Gorham Plate",
    "sfomuseum:medium": "silver plate metal",
    "sfomuseum:placetype": "object",
    "sfomuseum:publication": ": , c. 1938.",
    "sfomuseum:subcategory": "Flatware",
    "wof:depicts": [
      1159285395,
      1159287531
    ],
    "wof:name": "spoon: Transcontinental \u0026 Western Air (TWA)",
    "wof:placetype": "custom",
    "wof:placetype_alt": "object"
  },
  "geometry": {"coordinates":[-122.386155,37.616357],"type":"Point"}
}
