{
  "type": "Feature",
  "properties": {
    "date:cessation_lower": "1943-12-31",
    "date:cessation_upper": "1943-12-31",
    "date:inception_lower": "1933-01-01",
    "date:inception_upper": "1933-01-01",
    "iso:country": "XX",
    "sfomuseum:accession_number": "2006.028.109",
    "sfomuseum:airline": "Transcontinental \u0026 Western Air  (TWA (Trans World Airlines))",
    "sfomuseum:category": "Meal Service",
    "sfomuseum:collection": "Aviation Museum",
    "sfomuseum:creditline": "Gift of Edith Lauterbach",
    "sfomuseum:date": "c. 1938",
    "sfomuseum:daterange_end": "1943-12-31",
    "sfomuseum:daterange_start": "1933-01-01",
    "sfomuseum:description": "Spoon issued by Transcontinental \u0026 Western Air for inflight meal service; logotype stamped on reverse.",
    "sfomuseum:medium": "metal",
    "sfomuseum:placetype": "object",
    "sfomuseum:subcategory": "Flatware",
    "wof:depicts": [
      1159285395
    ],
    "wof:name": "spoon: Transcontinental \u0026 Western Air (TWA)",
    "wof:placetype": "venue"
  },
  "geometry": {"coordinates":[-122.386155,37.616357],"type":"Point"}
}
