{
  "type": "Feature",
  "properties": {
    "date:cessation_lower": "1922-12-31",
    "date:cessation_upper": "1922-12-31",
    "date:inception_lower": "1912-01-01",
    "date:inception_upper": "1912-01-01",
    "iso:country": "XX",
    "millsfield:images": [
      1527852849
    ],
    "sfomuseum:accession_number": "2010.174.049.004",
    "sfomuseum:category": "Employee Career History",
    "sfomuseum:collection": "Aviation Archive",
    "sfomuseum:creditline": "Gift of Charles Page",
    "sfomuseum:date": "c. 1917",
    "sfomuseum:daterange_end": "1922-12-31",
    "sfomuseum:daterange_start": "1912-01-01",
    "sfomuseum:description": "Membership card for the Pacific Aero Club, issued to Mr. S. H. Page, undated; from a set of typed and handwritten correspondence documents pertaining to The Early Birds aeronautical society, 1912-1963.",
    "sfomuseum:dimensions": "2 1/2 x 4 inches (6.4 x 10.2 cm)",
    "sfomuseum:media_ids": [
      1527852849
    ],
    "sfomuseum:medium": "paper, ink",
    "sfomuseum:placetype": "object",
    "sfomuseum:subcategory": "Identification",
    "wof:name": "membership card: Stanley Page, Pacific Aero Club",
    "wof:placetype": "venue"
  },
  "geometry": {"coordinates":[-122.386155,37.616357],"type":"Point"}
}
