{
  "type": "Feature",
  "properties": {
    "date:cessation_lower":"1960-12-31",
    "date:cessation_upper":"1960-12-31",
    "date:inception_lower":"1950-01-01",
    "date:inception_upper":"1950-01-01",
    "iso:country":"XX",
    "millsfield:images":[
        1527854061
    ],
    "sfomuseum:accession_number":"2013.146.069",
    "sfomuseum:category":"Promotional",
    "sfomuseum:collection":"Aviation Archive",
    "sfomuseum:creditline":"Gift of the Ralph F. Mitchell, Jr. Family",
    "sfomuseum:date":"c. 1955",
    "sfomuseum:daterange_end":"1960-12-31",
    "sfomuseum:daterange_start":"1950-01-01",
    "sfomuseum:description":"Luggage label promoting Aer Lingus; orange circle with green and white clover illustration; \u201cAer Lingus / Irish Air Lines\u201d logotype across center.",
    "sfomuseum:media_ids":[
        1527854061
    ],
    "sfomuseum:medium":"paper, ink, adhesive",
    "sfomuseum:placetype":"object",
    "sfomuseum:subcategory":"Luggage Label",
    "wof:name":"luggage label: Aer Lingus",
    "wof:placetype":"venue"
},
  "geometry": {"coordinates":[-122.386155,37.616358],"type":"Point"}
}