{
  "type": "Feature",
  "properties": {
    "date:cessation_lower": "1911-01-01",
    "date:cessation_upper": "1911-12-31",
    "date:inception_lower": "1911-01-01",
    "date:inception_upper": "1911-12-31",
    "iso:country": "XX",
    "millsfield:exhibition_ids": [
      1159160581
    ],
    "millsfield:images": [
      1746680929
    ],
    "millsfield:images_texts": [
      "THE NEW ART\nOF FLYING\nWALDEMAR KAEMPFFERT"
    ],
    "millsfield:images_texts_ids": [
      1746680929
    ],
    "millsfield:on_view": 0,
    "millsfield:primary_image": 1746680929,
    "sfomuseum:accession_number": "2000.160.0400",
    "sfomuseum:author": "Kaempffert, Waldemar",
    "sfomuseum:callnumber": "TL545 .K15 1911 SC",
    "sfomuseum:category": "Book",
    "sfomuseum:collection": "Aviation Library",
    "sfomuseum:creditline": "Collection of SFO Museum, The Tony Bill Aviation Library Collection",
    "sfomuseum:date": "1911",
    "sfomuseum:date_acquired": "1999-05-18",
    "sfomuseum:daterange_end": "1911-12-31",
    "sfomuseum:daterange_start": "1911-01-01",
    "sfomuseum:description": "xvii, 291 p. front., plates, diagrs. 20 cm.",
    "sfomuseum:description_library": "xvii, 291 p. front., plates, diagrs. 20 cm.",
    "sfomuseum:exhibition_ids": [
      1387
    ],
    "sfomuseum:medium": "paper, ink",
    "sfomuseum:placetype": "object",
    "sfomuseum:publication": "New York: Dodd, Mead \u0026 Company, 1911.",
    "sfomuseum:publisher": "Dodd, Mead \u0026 Company",
    "sfomuseum:publisher_location": "New York",
    "sfomuseum:subcategory": "Book",
    "sfomuseum:subject": "Airplanes.Aeronautics.",
    "wof:name": "The new art of flying",
    "wof:placetype": "custom",
    "wof:placetype_alt": [
      "object"
    ]
  },
  "geometry": {"coordinates":[-122.386155,37.616357],"type":"Point"}
}
