{
  "type": "Feature",
  "properties": {
    "date:cessation_lower": "1950-01-01",
    "date:cessation_upper": "1950-12-31",
    "date:inception_lower": "1950-01-01",
    "date:inception_upper": "1950-12-31",
    "iso:country": "XX",
    "sfomuseum:accession_number": "00-3202",
    "sfomuseum:author": "Royal Air Force, Great Britain",
    "sfomuseum:callnumber": "U102 .W37 1950 SC",
    "sfomuseum:category": "Book",
    "sfomuseum:collection": "Aviation Library",
    "sfomuseum:date": "1950",
    "sfomuseum:daterange_end": "1950-12-31",
    "sfomuseum:daterange_start": "1950-01-01",
    "sfomuseum:description": "108 p. : ill. ; 26 cm.",
    "sfomuseum:description_library": "108 p. : ill. ; 26 cm.",
    "sfomuseum:medium": "paper, ink",
    "sfomuseum:placetype": "object",
    "sfomuseum:publication": "London: Air Ministry, 1950.",
    "sfomuseum:publisher": "Air Ministry",
    "sfomuseum:publisher_location": "London",
    "sfomuseum:series": "A.P. ; 1300",
    "sfomuseum:subcategory": "Book",
    "sfomuseum:subject": "Military art and science Great Britain.Great Britain Armed forces Handbooks, manuals, etc.",
    "wof:name": "War manual. Part 1, Operations",
    "wof:placetype": "custom",
    "wof:placetype_alt": "object"
  },
  "geometry": {"coordinates":[-122.386155,37.616357],"type":"Point"}
}
