{
  "type": "Feature",
  "properties": {
    "date:cessation_lower": "2006-01-01",
    "date:cessation_upper": "2006-12-31",
    "date:inception_lower": "2006-01-01",
    "date:inception_upper": "2006-12-31",
    "iso:country": "XX",
    "millsfield:images": [
      1527819427
    ],
    "millsfield:primary_image": 1527819427,
    "sfomuseum:accession_number": "2008.009.006",
    "sfomuseum:aircraft": "Airbus A380",
    "sfomuseum:airline": "Qantas Airways",
    "sfomuseum:category": "Promotional",
    "sfomuseum:collection": "Aviation Archive",
    "sfomuseum:creditline": "Transfer",
    "sfomuseum:date": "c. 2006",
    "sfomuseum:date_acquired": "2008-08-21",
    "sfomuseum:daterange_end": "2011-12-31",
    "sfomuseum:daterange_start": "2001-01-01",
    "sfomuseum:description": "Print issued by Qantas Airways promoting the Airbus A380; folded full color, double-sided poster with photographic image of AVRO biplane in flight over Australian outback with shadow of Airbus A380 below with caption \"We always did have big plans for the future\"; on reverse, series of color photographs and descriptions of seating in the A380.",
    "sfomuseum:dimensions": "20 x 29 inches (50.8 x 73.7 cm)",
    "sfomuseum:media_ids": [
      1527819427
    ],
    "sfomuseum:medium": "paper, ink",
    "sfomuseum:placetype": "object",
    "sfomuseum:publication": ": , c. 2006.",
    "sfomuseum:subcategory": "Print",
    "sfomuseum:subject": "Qantas airlines.",
    "wof:depicts": [
      1159293829,
      1159287479,
      1159285043,
      1159289435
    ],
    "wof:name": "aircraft promotional print: Qantas Airways, Airbus A380",
    "wof:placetype": "venue"
  },
  "geometry": {"coordinates":[-122.386155,37.616357],"type":"Point"}
}
