{
  "type": "Feature",
  "properties": {
    "date:cessation_lower":"1941-12-31",
    "date:cessation_upper":"1941-12-31",
    "date:inception_lower":"1941-01-01",
    "date:inception_upper":"1941-01-01",
    "iso:country":"XX",
    "sfomuseum:accession_number":"1994.18.177",
    "sfomuseum:category":"Philately",
    "sfomuseum:collection":"Aviation Archive",
    "sfomuseum:continent":"Transpacific",
    "sfomuseum:creditline":"Purchase",
    "sfomuseum:date":"11/9/1941",
    "sfomuseum:daterange_end":"1941-11-09",
    "sfomuseum:daterange_start":"1941-11-09",
    "sfomuseum:description":"Airmail flight cover commemorating first transpacific airmail flight from Suva, Fiji to Auckland, New Zealand, FAM-19; purple cachet with image of a person\u2019s head in profile (F19L); two stamps: green/red 2d (pence) and one gray 1/\u2019 (shilling) (Fiji); two postmarks: November 9, 1941, Suva; backstamp: November 11, 1941, Auckland; envelope: white airmail with blue printed interior and red and blue lines around border.",
    "sfomuseum:maker":"Pan American Airways, Inc.",
    "sfomuseum:medium":"ink on paper",
    "sfomuseum:placetype":"object",
    "sfomuseum:subcategory":"Airmail Flight Cover",
    "wof:name":"airmail flight cover: Transpacific Air Mail, Suva (Fiji) - Auckland route",
    "wof:placetype":"venue"
},
  "geometry": {"coordinates":[-122.386155,37.616358],"type":"Point"}
}