{
  "type": "Feature",
  "properties": {
    "date:cessation_lower": "1961-01-01",
    "date:cessation_upper": "1961-12-31",
    "date:inception_lower": "1961-01-01",
    "date:inception_upper": "1961-12-31",
    "iso:country": "XX",
    "millsfield:images": [
      1527847127,
      1527848291
    ],
    "millsfield:images_texts": [
      "JETS TO\nALASKA\nIN SPEED AND\nSPLENDOR\n* ALASKA\nAIRLINES",
      "FARES - GENERAL INFORMATION\nCHILOREN'S FARES- A chad is arms soder tea years of age wil be carried fise when\nBAGCAGE-Sity-six (66) pounds bretage wit be carried thee on each tichet beteses Alasta\nee otherwise denvered into the custody de Carrier, is leited la $100 for each passenger wait\nDAUTONETRATESESPECIAL GUANTLETTARDIOLLARLORATES STOLEN DONNIESE\nAlatka Alrises Bights up to 24 bours peise to departure, by reporteng sales to the searest set\nEXPLANATION OF REFERENCE MARKS AND SYMBOLS:\nTimes printed is Light Type (19 10) lodicates A.M.; Sees is Beld Type (12 1) ledicates P.D\nCONVENIENT\nConnections AT SEATTLE\nTO AND FROM ALASKA\nAlaska Airlines Golden Nugget schedule permits same day all jet travel to the\nLast Frontier. Northbound passengers from California, the Midwest\nand the East Coast can fly to Seattle, transfer to the Golden Nugget Jet\nand be in Alaska by 6:50 p.m. \"Going out,\" as Alaskans say, the Golden\nNugget Jet provides the same quick and convenient\nconnections with jet flights South and East.\nRESERVATIONS AND TICKET OFFICE\nSara.\nPORTLAND/SEATTL\nNONE\nAlask\nFlight Schedules\nFLY IN\nSPEED and SPLENDOR\nALASKA AIRLINES\n880M JET SERVICE\nSEATTLE • FAIRBANKS\nANCHORAGE\nANCHORAGE • McGRATH • UNALA\nME\ngIRL\nFlight Schedules, Fares and General Information effective AUG. 20, 19611"
    ],
    "millsfield:images_texts_ids": [
      1527847127,
      1527848291
    ],
    "millsfield:primary_image": 1527847127,
    "sfomuseum:accession_number": "2005.132.004.001",
    "sfomuseum:airline": "Alaska Airlines",
    "sfomuseum:category": "Scheduling / Ticketing",
    "sfomuseum:collection": "Aviation Archive",
    "sfomuseum:creditline": "Gift of the William Hough Collection",
    "sfomuseum:date": "1961",
    "sfomuseum:date_acquired": "2006-12-05",
    "sfomuseum:daterange_end": "1961-12-31",
    "sfomuseum:daterange_start": "1961-01-01",
    "sfomuseum:description": "Timetable issued by Alaska Airlines, effective August 20, 1961; two page double-sided fold-out; yellow cover with color illustration of a jet on a white field in flight over a snow-covered mountain.",
    "sfomuseum:dimensions": "9 x 4 inches (22.9 x 10.2 cm)",
    "sfomuseum:media_ids": [
      1527847127,
      1527848291
    ],
    "sfomuseum:medium": "paper, ink",
    "sfomuseum:placetype": "object",
    "sfomuseum:publication": ": , 1961.",
    "sfomuseum:subcategory": "Timetable",
    "wof:depicts": [
      1159283813,
      1159288915
    ],
    "wof:name": "timetable: Alaska Airlines",
    "wof:placetype": "custom",
    "wof:placetype_alt": "object"
  },
  "geometry": {"coordinates":[-122.386155,37.616357],"type":"Point"}
}
