{
  "type": "Feature",
  "properties": {
    "date:cessation_lower": "1961-01-01",
    "date:cessation_upper": "1961-12-31",
    "date:inception_lower": "1961-01-01",
    "date:inception_upper": "1961-12-31",
    "iso:country": "XX",
    "millsfield:images": [
      1527847127,
      1527848291
    ],
    "millsfield:images_texts": [
      "JETS TO\nALASKA\nIN SPEED AND\nSPLENDOR\nVA ALASKA\nAIRLINES",
      "UNALARLEET:\nAll fares que\nINFORMATION\nEXPLANATION OF REFERENCE MARKS AND SYMBOLS:\n•SPECIAL QUANTITY AND\nDEFERRED RATES avalable s\nCONVENIENT\nConnections AT SEATTLE\nTO AND FROM ALASKA\nAlaska Airlines' Golden Nugget schedule permits same-day all-jet travel to the\nLast Frontier. Northbound passengers from California, the Midwest\nand the East Coast can fly to Seattle, transfer to the Golden Nugget Jet\nand be in Alaska by 6:50 p.m. \"Going out,\" as Alaskans say, the Golden\nNugget Jet provides the same quick and convenient\nconnections with jet flights South and East.\nRESERVATIONS AND TICKET OFFICE\nTICKET OFFICE\nAIREREIGHT\nORTLAND\nAlaska\nFlight Schedules\nANCHORAGE\nFLY IN\nSPEED and SPLENDOR\nALASKA AIRLINES\n880M JET SERVICE\nSEATTLE • FAIRBANKS\nANCHORAGE\n•SEATTIE\nPORTLAND\nPORTLAND/SEATTLE • FAIRBANKS • ANCHORAGE • McGRATH • UNALAKLEET • NOME • KOTZEBUE\nDaly Tu T Daly Baly Daily MoW Tu Th Baly Bal\nANCHORAGE\nPolden Nugget\n;olden Nugget\n10z0\nNOME\nFliaht Schedules."
    ],
    "millsfield:images_texts_ids": [
      1527847127,
      1527848291
    ],
    "millsfield:primary_image": 1527847127,
    "sfomuseum:accession_number": "2005.132.004.001",
    "sfomuseum:airline": "Alaska Airlines",
    "sfomuseum:category": "Scheduling / Ticketing",
    "sfomuseum:collection": "Aviation Archive",
    "sfomuseum:creditline": "Gift of the William Hough Collection",
    "sfomuseum:date": "1961",
    "sfomuseum:date_acquired": "2006-12-05",
    "sfomuseum:daterange_end": "1961-12-31",
    "sfomuseum:daterange_start": "1961-01-01",
    "sfomuseum:description": "Timetable issued by Alaska Airlines, effective August 20, 1961; two page double-sided fold-out; yellow cover with color illustration of a jet on a white field in flight over a snow-covered mountain.",
    "sfomuseum:dimensions": "9 x 4 inches (22.9 x 10.2 cm)",
    "sfomuseum:media_ids": [
      1527847127,
      1527848291
    ],
    "sfomuseum:medium": "paper, ink",
    "sfomuseum:placetype": "object",
    "sfomuseum:publication": ": , 1961.",
    "sfomuseum:subcategory": "Timetable",
    "wof:depicts": [
      1159283813,
      1159288915
    ],
    "wof:name": "timetable: Alaska Airlines",
    "wof:placetype": "custom",
    "wof:placetype_alt": "object"
  },
  "geometry": {"coordinates":[-122.386155,37.616357],"type":"Point"}
}
