{
  "type": "Feature",
  "properties": {
    "date:cessation_lower": "1935-12-31",
    "date:cessation_upper": "1935-12-31",
    "date:inception_lower": "1935-01-01",
    "date:inception_upper": "1935-01-01",
    "iso:country": "XX",
    "sfomuseum:accession_number": "2008.075.073",
    "sfomuseum:category": "Philately",
    "sfomuseum:collection": "Aviation Archive",
    "sfomuseum:creditline": "Gift of Jon E. Krupnick",
    "sfomuseum:date": "05/24/1935",
    "sfomuseum:daterange_end": "1935-05-24",
    "sfomuseum:daterange_start": "1935-05-24",
    "sfomuseum:description": "Airmail flight cover, U.S. Navy Pacific Fleet, Midway Island Mass Return Flight, May 23-24, 1935; six-line certificate on front at upper left, signed by pilot Hamilton; postmarked May 24, 1935, U.S.S. Beaver, with cancellation mark \"Midway Islands\"; orange 6-cent postage stamp; backstamp: May 24, 1935, Fleet Air Base, Pearl Harbor, Hawaii; addressed to Lieutenant George K. Huff.",
    "sfomuseum:media_ids": [
      1527831871
    ],
    "sfomuseum:medium": "paper, ink",
    "sfomuseum:placetype": "object",
    "sfomuseum:subcategory": "Airmail Flight Cover",
    "wof:name": "airmail flight cover: U.S. Navy Hawaii, Midway Island Mass Return Flight, May 23-24, 1935",
    "wof:placetype": "venue"
  },
  "geometry": {"coordinates":[-122.386155,37.616358],"type":"Point"}
}
