{
  "type": "Feature",
  "properties": {
    "date:cessation_lower": "1989-01-01",
    "date:cessation_upper": "1989-12-31",
    "date:inception_lower": "1989-01-01",
    "date:inception_upper": "1989-12-31",
    "iso:country": "XX",
    "millsfield:images": [
      1527823345,
      1527823347
    ],
    "millsfield:primary_image": 1527823347,
    "sfomuseum:accession_number": "1998.157.003",
    "sfomuseum:airline": "Air Atlantis",
    "sfomuseum:category": "Passenger Amenity",
    "sfomuseum:collection": "Aviation Archive",
    "sfomuseum:creditline": "Gift of The Henry Steiner Air Sickness Bag Collection",
    "sfomuseum:date": "c. 1989",
    "sfomuseum:date_acquired": "1999-07-13",
    "sfomuseum:daterange_end": "1994-12-31",
    "sfomuseum:daterange_start": "1984-01-01",
    "sfomuseum:description": "Gusset wedge, adhesive closure. White bag, green print. \"Air Atlantis\" printed across bottom with logo in left upper corner. Instructions also on front of bag.",
    "sfomuseum:dimensions": "10 x 4 1/2 inches (25.4 x 11.4 cm)",
    "sfomuseum:media_ids": [
      1527823345,
      1527823347
    ],
    "sfomuseum:medium": "paper",
    "sfomuseum:placetype": "object",
    "sfomuseum:publication": ": , c. 1989.",
    "sfomuseum:subcategory": "Airsickness Bag",
    "wof:depicts": [
      1159283579
    ],
    "wof:name": "airsickness bag: Air Atlantis",
    "wof:placetype": "venue"
  },
  "geometry": {"coordinates":[-122.386155,37.616357],"type":"Point"}
}
