{
  "type": "Feature",
  "properties": {
    "date:cessation_lower": "1994-12-31",
    "date:cessation_upper": "1994-12-31",
    "date:inception_lower": "1984-01-01",
    "date:inception_upper": "1984-01-01",
    "iso:country": "XX",
    "millsfield:images": [
      1527823347,
      1527823345
    ],
    "sfomuseum:accession_number": "1998.157.003",
    "sfomuseum:airline": "Air Atlantis",
    "sfomuseum:category": "Passenger Amenity",
    "sfomuseum:collection": "Aviation Museum",
    "sfomuseum:creditline": "Gift of The Henry Steiner Air Sickness Bag Collection",
    "sfomuseum:date": "c. 1989",
    "sfomuseum:daterange_end": "1994-12-31",
    "sfomuseum:daterange_start": "1984-01-01",
    "sfomuseum:description": "Gusset wedge, adhesive closure. White bag, green print. \"Air Atlantis\" printed across bottom with logo in left upper corner. Instructions also on front of bag.",
    "sfomuseum:media_ids": [
      1527823345,
      1527823347
    ],
    "sfomuseum:medium": "paper",
    "sfomuseum:placetype": "object",
    "sfomuseum:subcategory": "Airsickness Bag",
    "wof:depicts": [
      1159283579
    ],
    "wof:name": "airsickness bag: Air Atlantis",
    "wof:placetype": "venue"
  },
  "geometry": {"coordinates":[-122.386155,37.616357],"type":"Point"}
}
