{
  "type": "Feature",
  "properties": {
    "date:cessation_lower": "1979-01-01",
    "date:cessation_upper": "1979-12-31",
    "date:inception_lower": "1979-01-01",
    "date:inception_upper": "1979-12-31",
    "iso:country": "XX",
    "millsfield:images": [
      1527845165,
      1527845167
    ],
    "millsfield:images_texts": [
      "NATIONALS AIR SEA SERVICE\nCOCKTAILS and WHiSKIES\nHarveys Bristel Cream Sherry\nManhattan\nчили Манино моа Монино Иоану на roshies\nBludy Mary\nOrange Blossom\nScotch\nSin\nBourbon\nCanadian\nYodha\nRam\nBeen\nWINES\nA Soloction of California Minos\nand Champagne\nвоса Cola\nbIQUEURS\nBonedicine and Brandy\nPrambuie\nKahlua\nKonnesy вкупас\nAmaretto di Saronno\nBBVBRAGE,S\nSugar Free 7. Up\n7.9\nI Shecke\nCONTINENTAL BREAKFAST\nfuller stoosed oake, aleces of farah fowl range poi and steaming het alle\nJungeness Crab\nfrom the waters of San Francise Buy\nspared with a delecolely flavered mastant wun\nCalifornia Salad Bar\nch messed gwews with shives f esomter tomale and egg gorwashed with freshly grotel worn\nChoice of How cherin vamy goslie on cel and vinegar doesings Selection of hot all, and war dewgk load\nPork Gain Roast\ncheatede wasted hook his cosset at talleral\nwith r\nFilet Mignon\ncheice lenderhine ofloof\ngrilled over chancel as you like it\nBreast of Chickon Delmonies\nloneless breest of chicken stooflect with a nich ladles waner aNd wangs\nScuthorn Cornbroad Prosing Sealloped Spples Rice Pilaf Baby Carrels\nGrand Marnior Souffle\nrich frogen cream with fruit and delectable seshrees\nCoffee\nTon Sanka Milk\nBisceyno Coffer\nhat coffee with .Nahlao # Brandy"
    ],
    "millsfield:images_texts_ids": [
      1527845167
    ],
    "millsfield:primary_image": 1527845165,
    "sfomuseum:accession_number": "2001.080.099",
    "sfomuseum:airline": "National Airlines",
    "sfomuseum:category": "Passenger Amenity, Archive",
    "sfomuseum:collection": "Aviation Archive",
    "sfomuseum:continent": "World Routes",
    "sfomuseum:creditline": "Gift of Thomas G. Dragges",
    "sfomuseum:date": "1979",
    "sfomuseum:date_acquired": "2002-12-24",
    "sfomuseum:daterange_end": "1979-12-31",
    "sfomuseum:daterange_start": "1979-01-01",
    "sfomuseum:description": "Menu issued by National Airlines for Air Sea Service; white cover with color illustration and logo; menu items include Dungeness crab, California salad bar, and chicken Delmonico; menu number: 54 4/79 Cycle A; date: 4/79.",
    "sfomuseum:dimensions": "9 3/4 x 9 inches (24.8 x 22.9 cm)",
    "sfomuseum:media_ids": [
      1527845165,
      1527845167
    ],
    "sfomuseum:medium": "paper, ink",
    "sfomuseum:placetype": "object",
    "sfomuseum:publication": ": , 1979.",
    "sfomuseum:subcategory": "Menu",
    "wof:depicts": [
      1159284841,
      1159288429
    ],
    "wof:name": "menu: National Airlines",
    "wof:placetype": "custom",
    "wof:placetype_alt": "object"
  },
  "geometry": {"coordinates":[-122.386155,37.616357],"type":"Point"}
}
