{
  "type": "Feature",
  "properties": {
    "date:cessation_lower": "1979-01-01",
    "date:cessation_upper": "1979-12-31",
    "date:inception_lower": "1979-01-01",
    "date:inception_upper": "1979-12-31",
    "iso:country": "XX",
    "millsfield:images": [
      1527845165,
      1527845167
    ],
    "millsfield:primary_image": 1527845165,
    "sfomuseum:accession_number": "2001.080.099",
    "sfomuseum:airline": "National Airlines",
    "sfomuseum:category": "Passenger Amenity",
    "sfomuseum:collection": "Aviation Archive",
    "sfomuseum:continent": "World Routes",
    "sfomuseum:creditline": "Gift of Thomas G. Dragges",
    "sfomuseum:date": "1979",
    "sfomuseum:daterange_end": "1979-12-31",
    "sfomuseum:daterange_start": "1979-01-01",
    "sfomuseum:description": "Menu issued by National Airlines for Air Sea Service; white cover with color illustration and logo; menu items include Dungeness crab, California salad bar, and chicken Delmonico; menu number: 54 4/79 Cycle A; date: 4/79.",
    "sfomuseum:dimensions": "9 3/4 x 9 inches (24.8 x 22.9 cm)",
    "sfomuseum:media_ids": [
      1527845165,
      1527845167
    ],
    "sfomuseum:medium": "paper, ink",
    "sfomuseum:placetype": "object",
    "sfomuseum:publication": ": , 1979.",
    "sfomuseum:subcategory": "Menu",
    "wof:depicts": [
      1159284841
    ],
    "wof:name": "menu: National Airlines",
    "wof:placetype": "venue"
  },
  "geometry": {"coordinates":[-122.386155,37.616357],"type":"Point"}
}
