{
  "type": "Feature",
  "properties": {
    "date:cessation_lower":"1999-12-31",
    "date:cessation_upper":"1999-12-31",
    "date:inception_lower":"1966-01-01",
    "date:inception_upper":"1966-01-01",
    "iso:country":"US",
    "sfomuseum:accession_number":"1995.54.068",
    "sfomuseum:airline":"TWA (Trans World Airlines)",
    "sfomuseum:category":"Photograph",
    "sfomuseum:collection":"Aviation Archive",
    "sfomuseum:continent":"North America",
    "sfomuseum:country":"United States",
    "sfomuseum:creditline":"Collection of the Library of Congress, Washington, DC",
    "sfomuseum:date":"c. 1971 (reproduced c. 1994)",
    "sfomuseum:daterange_end":"1999-12-31",
    "sfomuseum:daterange_start":"1966-01-01",
    "sfomuseum:description":"Black and white photograph of a reservationist or travel agent sitting at a desk looking through airline books (before computer reservation systems). A customer is on the other side of the desk holding a schedule. TWA booklets on a rack in background. \"TWA Getaway Guide Rome, TWA Getaway Guide Los Angeles, TWA Getaway Guide Athens, TWA Getaway Guide Las Vegas\"",
    "sfomuseum:medium":"gelatin silver print",
    "sfomuseum:placetype":"object",
    "sfomuseum:subcategory":"Print, Photograph",
    "wof:depicts":[
        1159285393
    ],
    "wof:name":"photograph: TWA (Trans World Airlines), reservationist",
    "wof:placetype":"venue"
},
  "geometry": {"coordinates":[-122.386155,37.616357],"type":"Point"}
}