{
  "type": "Feature",
  "properties": {
    "date:cessation_lower": "1958-01-01",
    "date:cessation_upper": "1958-12-31",
    "date:inception_lower": "1958-01-01",
    "date:inception_upper": "1958-12-31",
    "iso:country": "XX",
    "millsfield:images": [
      1746680309
    ],
    "millsfield:primary_image": 1746680309,
    "sfomuseum:accession_number": "2010.176.015",
    "sfomuseum:airline": "TWA (Trans World Airlines)",
    "sfomuseum:author": "Trans World Airlines, Inc. (TWA)",
    "sfomuseum:callnumber": "G153.T7 G4 1958 c.1",
    "sfomuseum:category": "Book",
    "sfomuseum:collection": "Aviation Library",
    "sfomuseum:creditline": "Purchase",
    "sfomuseum:date": "1958",
    "sfomuseum:date_acquired": "2010-05-20",
    "sfomuseum:daterange_end": "1958-12-31",
    "sfomuseum:daterange_start": "1958-01-01",
    "sfomuseum:medium": "paper, ink",
    "sfomuseum:placetype": "object",
    "sfomuseum:publication": "s.l.: Trans World Airlines, Inc. (TWA), 1958.",
    "sfomuseum:publisher": "Trans World Airlines, Inc. (TWA)",
    "sfomuseum:publisher_location": "s.l.",
    "sfomuseum:series": "TWA Travel Tips",
    "sfomuseum:subcategory": "Book",
    "sfomuseum:subject": "Airlines -- Trans World Airlines (TWA) -- Travel guidebooks.",
    "wof:depicts": [
      1159285393
    ],
    "wof:name": "Travel tips for Germany",
    "wof:placetype": "venue"
  },
  "geometry": {"coordinates":[-122.386155,37.616357],"type":"Point"}
}
