{
  "type": "Feature",
  "properties": {
    "date:cessation_lower": "1930-01-01",
    "date:cessation_upper": "1930-12-31",
    "date:inception_lower": "1930-01-01",
    "date:inception_upper": "1930-12-31",
    "iso:country": "XX",
    "loc:subject_headings": [
      "sh85107489"
    ],
    "sfomuseum:accession_number": "2000.160.1101",
    "sfomuseum:author": "Weick, Fred Ernest",
    "sfomuseum:callnumber": "TL705 .W45 1930 SC",
    "sfomuseum:category": "Book",
    "sfomuseum:collection": "Aviation Library",
    "sfomuseum:creditline": "Collection of SFO Museum, The Tony Bill Aviation Library Collection",
    "sfomuseum:date": "1930",
    "sfomuseum:date_acquired": "1999-05-18",
    "sfomuseum:daterange_end": "1930-12-31",
    "sfomuseum:daterange_start": "1930-01-01",
    "sfomuseum:description": "xiii, 294 p. illus., diagrs. 24 cm.",
    "sfomuseum:description_library": "xiii, 294 p. illus., diagrs. 24 cm.",
    "sfomuseum:medium": "paper, ink",
    "sfomuseum:placetype": "object",
    "sfomuseum:publication": "New York; London: McGraw-Hill Book, 1930.",
    "sfomuseum:publisher": "McGraw-Hill Book",
    "sfomuseum:publisher_location": "New York; London",
    "sfomuseum:subcategory": "Book",
    "sfomuseum:subject": "Propellers, Aerial.",
    "wof:name": "Aircraft propeller design",
    "wof:placetype": "custom",
    "wof:placetype_alt": [
      "object"
    ]
  },
  "geometry": {"coordinates":[-122.386155,37.616357],"type":"Point"}
}
