{
  "type": "Feature",
  "properties": {
    "date:cessation_lower": "1979-12-31",
    "date:cessation_upper": "1979-12-31",
    "date:inception_lower": "1970-01-01",
    "date:inception_upper": "1970-01-01",
    "iso:country": "XX",
    "millsfield:images": [
      1527842163
    ],
    "sfomuseum:accession_number": "1998.157.208",
    "sfomuseum:airline": "Thai Airways International",
    "sfomuseum:category": "Passenger Amenity",
    "sfomuseum:collection": "Aviation Museum",
    "sfomuseum:creditline": "Gift of The Henry Steiner Air Sickness Bag Collection",
    "sfomuseum:date": "1970s",
    "sfomuseum:daterange_end": "1979-12-31",
    "sfomuseum:daterange_start": "1970-01-01",
    "sfomuseum:description": "Flat, no closure. Brown paper bag, magenta print. Rectangle with magenta swirl border in center. Inside on lower portion \"Thai Airways,\" above are Thai characters. Above this is magenta swirl design. Plastic on inside extends to cover 1.75 of exterior edge.",
    "sfomuseum:dimensions": "9 3/4 x 6 1/4 inches (24.8 x 15.9 cm)",
    "sfomuseum:media_ids": [
      1527842163
    ],
    "sfomuseum:medium": "paper",
    "sfomuseum:placetype": "object",
    "sfomuseum:subcategory": "Airsickness Bag",
    "wof:depicts": [
      1159285291
    ],
    "wof:name": "airsickness bag: Thai Airways International",
    "wof:placetype": "venue"
  },
  "geometry": {"coordinates":[-122.386155,37.616357],"type":"Point"}
}
