{
  "type": "Feature",
  "properties": {
    "date:cessation_lower": "1944-01-01",
    "date:cessation_upper": "1944-12-31",
    "date:inception_lower": "1944-01-01",
    "date:inception_upper": "1944-12-31",
    "iso:country": "XX",
    "millsfield:images": [
      1527841967,
      1527850331
    ],
    "millsfield:primary_image": 1527841967,
    "sfomuseum:accession_number": "2002.017.007.012",
    "sfomuseum:airline": "Pan American World Airways",
    "sfomuseum:category": "Scheduling / Ticketing",
    "sfomuseum:collection": "Aviation Archive",
    "sfomuseum:creditline": "Gift of the San Francisco Aeronautical Society",
    "sfomuseum:date": "1944",
    "sfomuseum:date_acquired": "2010-06-09",
    "sfomuseum:daterange_end": "1944-12-31",
    "sfomuseum:daterange_start": "1944-01-01",
    "sfomuseum:description": "Timetable issued by Pan American World Airways for Latin America service, effective October 1944; blue and red cover with illustration of top view of three-dimensional winged globe logo.",
    "sfomuseum:dimensions": "9 1/4 x 4 inches (23.5 x 10.2 cm)",
    "sfomuseum:media_ids": [
      1527841967,
      1527850331
    ],
    "sfomuseum:medium": "paper, ink, metal",
    "sfomuseum:placetype": "object",
    "sfomuseum:publication": ": , 1944.",
    "sfomuseum:subcategory": "Timetable",
    "wof:depicts": [
      1159284991,
      1159284989,
      1159286839
    ],
    "wof:name": "timetable: Pan American World Airways, Latin America",
    "wof:placetype": "custom",
    "wof:placetype_alt": "object"
  },
  "geometry": {"coordinates":[-122.386155,37.616357],"type":"Point"}
}
