{
  "type": "Feature",
  "properties": {
    "date:cessation_lower": "1944-01-01",
    "date:cessation_upper": "1944-12-31",
    "date:inception_lower": "1944-01-01",
    "date:inception_upper": "1944-12-31",
    "iso:country": "XX",
    "millsfield:images": [
      1527841967,
      1527850331
    ],
    "millsfield:images_texts": [
      "OCTOBER 1944\nPAN AMERICAN\nWORLD AIRWAYS\nAmerica\nPASSENGER • MAIL • EXPRESS\nTIME TABLES\nThe Syptem of the Flying Clipper Ships,",
      "PAN AMERICAN WORLD AIRWAYS\nLATIN AMERICA SERVICES\nCircled numbers refer to corresponding tables in Current Time Table\n105°\nOctober 1944\nWOUNDLAND\nTO NEWFOUNDLAND AND EUROPE\nTO BERMUDA AND EUROPE\nMAZATLA\nGUADALAJARI\nAMPICO\nTUXTLA GUTIERREZ\nTAPACHULA (Max)\nEsmeraldas 9o\n18) Manito\nSALINASCO\nTALARA\nPACIFIC\nOCE\n120'\nRoutes of the\nFLYING CLIPPER\nSHIPS\nI Same is Vind Airways Services\n•ONASSAU N.P.\nOther Airlines\nMAGUEY Cuba\nSANTIAGO Cuba\nPORT AU PRINCE Mait;\nIUDAD TRUJILLO DR.\nATLANTIC AND PACIFIC SERVICES\nthese services are operating out war time regulations do not\nSAN JUAN Puerto Rico\nST. THOMAS Virgin Is\nANTIGUA, B.W.L.\nPOINTE A PITRE\nGuadeloupe\nGUAIRA\nFT DE FRANCE Martinique\nBARBADOS\nPORT OF SPAIN\nGEORGETOWN B.C\nPARAMARIbO Surin.\nONCAYENNE F. C\nCOLONRIA\nEQUATOR\nLEM(PARA)\nCAMOCIM\nFORTALEZA\nRIO BRANCOPOR TO VELHE\nAQUIN B\nLIMA\nPERU\nAREQUIPA\n• RECIFE\nMACEIO\n†SAO\nA SALVADOR(BAHIA)\nO CANNAVIEIRAS\nANTOFAGASTA\nALLEGRANDE\nIGUASSU FALLS\nASUNCION\n• 015\nCARAVELLAG\nVICTORIA\nRIO DE JANEIRO\nSALTA\n• TUCUMAN\nVALLENAR\n- 70\nPORTO AL EGRE\nJUAN FERNANDEZ I\n/TO C RIVADAVIA, RIO GRANDE, ETC.\n309\n90°"
    ],
    "millsfield:images_texts_ids": [
      1527841967,
      1527850331
    ],
    "millsfield:primary_image": 1527841967,
    "sfomuseum:accession_number": "2002.017.007.012",
    "sfomuseum:airline": "Pan American World Airways",
    "sfomuseum:category": "Scheduling / Ticketing",
    "sfomuseum:collection": "Aviation Archive",
    "sfomuseum:creditline": "Gift of the San Francisco Aeronautical Society",
    "sfomuseum:date": "1944",
    "sfomuseum:date_acquired": "2010-06-09",
    "sfomuseum:daterange_end": "1944-12-31",
    "sfomuseum:daterange_start": "1944-01-01",
    "sfomuseum:description": "Timetable issued by Pan American World Airways for Latin America service, effective October 1944; blue and red cover with illustration of top view of three-dimensional winged globe logo.",
    "sfomuseum:dimensions": "9 1/4 x 4 inches (23.5 x 10.2 cm)",
    "sfomuseum:media_ids": [
      1527841967,
      1527850331
    ],
    "sfomuseum:medium": "paper, ink, metal",
    "sfomuseum:placetype": "object",
    "sfomuseum:publication": ": , 1944.",
    "sfomuseum:subcategory": "Timetable",
    "wof:depicts": [
      1159284991,
      1159284989,
      1159286839
    ],
    "wof:name": "timetable: Pan American World Airways, Latin America",
    "wof:placetype": "custom",
    "wof:placetype_alt": [
      "object"
    ]
  },
  "geometry": {"coordinates":[-122.386155,37.616357],"type":"Point"}
}
