{
  "type": "Feature",
  "properties": {
    "date:cessation_lower": "1917-01-01",
    "date:cessation_upper": "1917-12-31",
    "date:inception_lower": "1917-01-01",
    "date:inception_upper": "1917-12-31",
    "iso:country": "XX",
    "sfomuseum:accession_number": "2000.160.1289",
    "sfomuseum:author": "Anderson, R. Wherry",
    "sfomuseum:callnumber": "D602 .A54 1917 SC ENV",
    "sfomuseum:category": "Book",
    "sfomuseum:collection": "Aviation Library",
    "sfomuseum:creditline": "The Tony Bill Aviation Library Collection",
    "sfomuseum:date": "1917",
    "sfomuseum:daterange_end": "1917-12-31",
    "sfomuseum:daterange_start": "1917-01-01",
    "sfomuseum:description": "iii, p., 1 l., 7-31 p. 19 cm.",
    "sfomuseum:medium": "paper, ink",
    "sfomuseum:placetype": "object",
    "sfomuseum:publication": "New York: George H. Doran, 1917.",
    "sfomuseum:publisher": "George H. Doran",
    "sfomuseum:publisher_location": "New York",
    "sfomuseum:subcategory": "Book",
    "sfomuseum:subject": "Aeronautics, Military.World War, 1914-1918 Aerial operations, British.",
    "wof:name": "The romance of air-fighting",
    "wof:placetype": "venue"
  },
  "geometry": {"coordinates":[-122.386155,37.616357],"type":"Point"}
}
