{
  "type": "Feature",
  "properties": {
    "date:cessation_lower": "1969-12-31",
    "date:cessation_upper": "1969-12-31",
    "date:inception_lower": "1969-01-01",
    "date:inception_upper": "1969-01-01",
    "iso:country": "XX",
    "sfomuseum:accession_number": "99-0080",
    "sfomuseum:callnumber": "TL685.3 .W28 1969",
    "sfomuseum:category": "Book",
    "sfomuseum:collection": "Aviation Library",
    "sfomuseum:date": "1969",
    "sfomuseum:daterange_end": "1969-12-31",
    "sfomuseum:daterange_start": "1969-01-01",
    "sfomuseum:description": "[24] p. (chiefly photos) 25 cm.",
    "sfomuseum:medium": "paper, ink",
    "sfomuseum:placetype": "object",
    "sfomuseum:publisher": "Kookaburra Technical Publications",
    "sfomuseum:publisher_location": "Dandenong, Australia",
    "sfomuseum:series": "Historic aircraft books, Series 1 no. 3",
    "sfomuseum:subcategory": "Book",
    "sfomuseum:subject": "Australia. Royal Australian Air Force.Fighter planes.",
    "wof:name": "Warplanes of the R.A.A.F.: fighters 1921-69",
    "wof:placetype": "venue"
  },
  "geometry": {"coordinates":[-122.386155,37.616357],"type":"Point"}
}
