{
  "type": "Feature",
  "properties": {
    "date:cessation_lower": "1918-01-01",
    "date:cessation_upper": "1918-12-31",
    "date:inception_lower": "1918-01-01",
    "date:inception_upper": "1918-12-31",
    "iso:country": "XX",
    "sfomuseum:accession_number": "2002.064.006",
    "sfomuseum:author": "Great Britain. War Cabinet",
    "sfomuseum:callnumber": "TL526.G7 S6 1918 SC ENV",
    "sfomuseum:category": "Book",
    "sfomuseum:collection": "Aviation Library",
    "sfomuseum:creditline": "Purchase",
    "sfomuseum:date": "1918",
    "sfomuseum:date_acquired": "2002-01-01",
    "sfomuseum:daterange_end": "1918-12-31",
    "sfomuseum:daterange_start": "1918-01-01",
    "sfomuseum:description": "[3] p., 5-8 p. ; 25 cm.",
    "sfomuseum:description_library": "[3] p., 5-8 p. ; 25 cm.",
    "sfomuseum:medium": "paper, ink",
    "sfomuseum:placetype": "object",
    "sfomuseum:publication": "Washington, D.C.: Smithsonian Institution Press, 1918.",
    "sfomuseum:publisher": "Smithsonian Institution Press",
    "sfomuseum:publisher_location": "Washington, D.C.",
    "sfomuseum:series": "Smithsonian miscellaneous collections ; v. 69, no. 7",
    "sfomuseum:subcategory": "Book",
    "sfomuseum:subject": "Airplanes -- Great Britain.",
    "wof:name": "Report on aircraft supply of Great Britain and discussion of the difficulties involved in production",
    "wof:placetype": "custom",
    "wof:placetype_alt": "object"
  },
  "geometry": {"coordinates":[-122.386155,37.616357],"type":"Point"}
}
