{
  "type": "Feature",
  "properties": {
    "date:cessation_lower": "1910-01-01",
    "date:cessation_upper": "1910-12-31",
    "date:inception_lower": "1910-01-01",
    "date:inception_upper": "1910-12-31",
    "iso:country": "XX",
    "loc:subject_headings": [
      "sh85001346"
    ],
    "sfomuseum:accession_number": "2010.116.003",
    "sfomuseum:author": "Trowbridge, J. T. (John Townsend)",
    "sfomuseum:callnumber": "PS3097 .D3 1910 c.2",
    "sfomuseum:category": "Book",
    "sfomuseum:collection": "Aviation Library",
    "sfomuseum:creditline": "Collection of SFO Museum",
    "sfomuseum:date": "1910",
    "sfomuseum:date_acquired": "2010-05-10",
    "sfomuseum:daterange_end": "1910-12-31",
    "sfomuseum:daterange_start": "1910-01-01",
    "sfomuseum:description": "53, [1] p. incl. front., plates. 18 cm.",
    "sfomuseum:description_library": "53, [1] p. incl. front., plates. 18 cm.",
    "sfomuseum:medium": "paper, ink",
    "sfomuseum:placetype": "object",
    "sfomuseum:publication": "Boston and New York: Houghton Mifflin company, 1910.",
    "sfomuseum:publisher": "Houghton Mifflin company",
    "sfomuseum:publisher_location": "Boston and New York",
    "sfomuseum:subcategory": "Book",
    "sfomuseum:subject": "Aeronautics -- Poetry. \r",
    "wof:name": "Darius Green and his flying-machine, by J. T. Trowbridge; with illustrations by Wallace Goldsmith.\r",
    "wof:placetype": "custom",
    "wof:placetype_alt": [
      "object"
    ]
  },
  "geometry": {"coordinates":[-122.386155,37.616357],"type":"Point"}
}
