{
  "type": "Feature",
  "properties": {
    "date:cessation_lower": "1992-12-31",
    "date:cessation_upper": "1992-12-31",
    "date:inception_lower": "1982-01-01",
    "date:inception_upper": "1982-01-01",
    "iso:country": "XX",
    "sfomuseum:accession_number": "00-1342\r",
    "sfomuseum:author": "Pearson, David E. (David Eric)",
    "sfomuseum:callnumber": "E183.8.S65 P43 1987",
    "sfomuseum:category": "Book",
    "sfomuseum:collection": "Aviation Library",
    "sfomuseum:date": "c. 1987",
    "sfomuseum:daterange_end": "1992-12-31",
    "sfomuseum:daterange_start": "1982-01-01",
    "sfomuseum:description": "462 p., [2] p. of plates : ill. ; 24 cm.",
    "sfomuseum:medium": "paper, ink",
    "sfomuseum:placetype": "object",
    "sfomuseum:publisher": "Summit Books",
    "sfomuseum:publisher_location": "New York",
    "sfomuseum:subcategory": "Book",
    "sfomuseum:subject": "Korean Air Lines Incident, 1983.",
    "wof:name": "KAL 007: the cover-up",
    "wof:placetype": "venue"
  },
  "geometry": {"coordinates":[-122.386155,37.616357],"type":"Point"}
}
