{
  "type": "Feature",
  "properties": {
    "date:cessation_lower": "1940-12-01",
    "date:cessation_upper": "1940-12-31",
    "date:inception_lower": "1940-09-01",
    "date:inception_upper": "1940-09-30",
    "iso:country": "XX",
    "millsfield:images": [
      1763372843
    ],
    "millsfield:primary_image": 1763372843,
    "sfomuseum:accession_number": "2012.127.001",
    "sfomuseum:aircraft": "Lockheed L-749 Constellation",
    "sfomuseum:airline": "Qantas Empire Airways",
    "sfomuseum:category": "Promotional, Museum",
    "sfomuseum:collection": "Aviation Museum",
    "sfomuseum:creditline": "Purchase",
    "sfomuseum:date": "late 1940s",
    "sfomuseum:date_acquired": "2012-09-11",
    "sfomuseum:daterange_end": "1949-12-31",
    "sfomuseum:daterange_start": "1947-01-01",
    "sfomuseum:description": "Poster issued by Qantas Empire Airways promoting London to Sydney service; full color illustration depicting cutaway view of Lockheed Constellation in flight over landscape; airline servicemark at top center.",
    "sfomuseum:dimensions": "16 3/4 x 11 inches (42.5 x 27.9 cm)",
    "sfomuseum:medium": "paper, ink",
    "sfomuseum:placetype": "object",
    "sfomuseum:publication": ": , late 1940s.",
    "sfomuseum:subcategory": "Poster, Airline",
    "wof:depicts": [
      1159293697,
      1159285825,
      1159291123
    ],
    "wof:name": "poster: Qantas Empire Airways, Lockheed L-749 Constellation",
    "wof:placetype": "custom",
    "wof:placetype_alt": "object"
  },
  "geometry": {"coordinates":[-122.386155,37.616357],"type":"Point"}
}
