{
  "type": "Feature",
  "properties": {
    "date:cessation_lower": "1949-12-31",
    "date:cessation_upper": "1949-12-31",
    "date:inception_lower": "1947-01-01",
    "date:inception_upper": "1947-01-01",
    "iso:country": "XX",
    "sfomuseum:accession_number": "2012.127.001",
    "sfomuseum:aircraft": "Lockheed L-749 Constellation",
    "sfomuseum:airline": "Qantas Empire Airways  (Qantas Airways)",
    "sfomuseum:category": "Promotional",
    "sfomuseum:collection": "Aviation Museum",
    "sfomuseum:creditline": "Purchase",
    "sfomuseum:date": "late 1940s",
    "sfomuseum:daterange_end": "1949-12-31",
    "sfomuseum:daterange_start": "1947-01-01",
    "sfomuseum:description": "Poster produced by Qantas Empire Airways promoting London to Sydney service; full color illustration depicting cutaway view of Lockheed Constellation in flight over landscape; airline servicemark at top center.",
    "sfomuseum:dimensions": "16 3/4 x 11 inches (42.5 x 27.9 cm)",
    "sfomuseum:medium": "paper, ink",
    "sfomuseum:placetype": "object",
    "sfomuseum:subcategory": "Poster, Airline",
    "wof:depicts": [
      1159285825,
      1159291123
    ],
    "wof:name": "poster: Qantas Empire Airways, Lockheed L-749 Constellation",
    "wof:placetype": "venue"
  },
  "geometry": {"coordinates":[-122.386155,37.616357],"type":"Point"}
}
