{
  "type": "Feature",
  "properties": {
    "date:cessation_lower": "1993-01-01",
    "date:cessation_upper": "1993-12-31",
    "date:inception_lower": "1993-01-01",
    "date:inception_upper": "1993-12-31",
    "iso:country": "XX",
    "sfomuseum:accession_number": "2006.010.385",
    "sfomuseum:airline": "Braniff Inc.",
    "sfomuseum:author": "Cearley, George Walker",
    "sfomuseum:callnumber": "HE9803.B73 C38 1993",
    "sfomuseum:category": "Book",
    "sfomuseum:collection": "Aviation Library",
    "sfomuseum:creditline": "Gift of the William Hough Collection",
    "sfomuseum:date": "c. 1993",
    "sfomuseum:date_acquired": "2006-03-26",
    "sfomuseum:daterange_end": "1998-12-31",
    "sfomuseum:daterange_start": "1988-01-01",
    "sfomuseum:description": "64 p. : col. ill. ; 28 cm.",
    "sfomuseum:description_library": "64 p. : col. ill. ; 28 cm.",
    "sfomuseum:medium": "paper, ink",
    "sfomuseum:placetype": "object",
    "sfomuseum:publication": "Dallas, TX: G.W. Cearley, Jr., c. 1993.",
    "sfomuseum:publisher": "G.W. Cearley, Jr.",
    "sfomuseum:publisher_location": "Dallas, TX",
    "sfomuseum:subcategory": "Book",
    "sfomuseum:subject": "Braniff Airways History.",
    "wof:depicts": [
      1159286457,
      1159288679
    ],
    "wof:name": "Braniff International Airways: a pictorial history in color",
    "wof:placetype": "venue"
  },
  "geometry": {"coordinates":[-122.386155,37.616357],"type":"Point"}
}
