{
  "type": "Feature",
  "properties": {
    "date:cessation_lower": "1986-01-01",
    "date:cessation_upper": "1986-12-31",
    "date:inception_lower": "1986-01-01",
    "date:inception_upper": "1986-12-31",
    "iso:country": "XX",
    "sfomuseum:accession_number": "1999.660.029",
    "sfomuseum:airline": "Air Canada",
    "sfomuseum:author": "Smith, Philip",
    "sfomuseum:callnumber": "HE9815.A95 S65 1986 c.1",
    "sfomuseum:category": "Book",
    "sfomuseum:collection": "Aviation Library",
    "sfomuseum:creditline": "Purchase",
    "sfomuseum:date": "c. 1986",
    "sfomuseum:daterange_end": "1991-12-31",
    "sfomuseum:daterange_start": "1981-01-01",
    "sfomuseum:description": "368 p., [32] p. of plates : ill. ; 24 cm.",
    "sfomuseum:description_library": "368 p., [32] p. of plates : ill. ; 24 cm.",
    "sfomuseum:medium": "paper, ink",
    "sfomuseum:notes_library": "Includes index.",
    "sfomuseum:placetype": "object",
    "sfomuseum:publication": "Toronto, Ontario, Canada: McClelland and Stewart, c. 1986.",
    "sfomuseum:publisher": "McClelland and Stewart",
    "sfomuseum:publisher_location": "Toronto, Ontario, Canada",
    "sfomuseum:subcategory": "Book",
    "sfomuseum:subject": "Air Canada History.Airlines Canada History.",
    "wof:depicts": [
      1159288851,
      1159283597
    ],
    "wof:name": "It seems like only yesterday: Air Canada, the first 50 years",
    "wof:placetype": "custom"
  },
  "geometry": {"coordinates":[-122.386155,37.616357],"type":"Point"}
}
