{
  "type": "Feature",
  "properties": {
    "date:cessation_lower": "1960-01-01",
    "date:cessation_upper": "1960-12-31",
    "date:inception_lower": "1960-01-01",
    "date:inception_upper": "1960-12-31",
    "iso:country": "XX",
    "sfomuseum:accession_number": "1999.669.067",
    "sfomuseum:author": "Caidin, Martin",
    "sfomuseum:callnumber": "VG93 .C23 1960 c.1",
    "sfomuseum:category": "Book",
    "sfomuseum:collection": "Aviation Library",
    "sfomuseum:creditline": "Purchase",
    "sfomuseum:date": "1960",
    "sfomuseum:date_acquired": "1999-01-01",
    "sfomuseum:daterange_end": "1960-12-31",
    "sfomuseum:daterange_start": "1960-01-01",
    "sfomuseum:description": "232 p. illus. 31 cm.  Book plate, \"Ex libris: Johs Thinesen\" on interior flyleaf.",
    "sfomuseum:description_library": "232 p. illus. 31 cm.  Book plate, \"Ex libris: Johs Thinesen\" on interior flyleaf.",
    "sfomuseum:medium": "paper, ink",
    "sfomuseum:placetype": "object",
    "sfomuseum:publication": "New York: Random House, 1960.",
    "sfomuseum:publisher": "Random House",
    "sfomuseum:publisher_location": "New York",
    "sfomuseum:subcategory": "Book",
    "sfomuseum:subject": "United States. Marine Corps Aviation.United States. Navy Aviation.",
    "wof:name": "Golden wings: a pictorial history of the United States Navy and Marine Corps in the air",
    "wof:placetype": "custom",
    "wof:placetype_alt": [
      "object"
    ]
  },
  "geometry": {"coordinates":[-122.386155,37.616357],"type":"Point"}
}
