{
  "type": "Feature",
  "properties": {
    "date:cessation_lower": "1904-01-01",
    "date:cessation_upper": "1904-12-31",
    "date:inception_lower": "1904-01-01",
    "date:inception_upper": "1904-12-31",
    "iso:country": "XX",
    "millsfield:images": [
      1527828701,
      1527828703
    ],
    "millsfield:primary_image": 1527828701,
    "sfomuseum:accession_number": "2012.086.001",
    "sfomuseum:category": "Company Record / Document",
    "sfomuseum:collection": "Aviation Archive",
    "sfomuseum:creditline": "Anonymous gift",
    "sfomuseum:date": "1904",
    "sfomuseum:date_acquired": "2012-08-03",
    "sfomuseum:daterange_end": "1904-12-31",
    "sfomuseum:daterange_start": "1904-01-01",
    "sfomuseum:description": "Check in amount of $50.00 issued by National Bank of D. O. Mills \u0026 Company, Sacramento, California to A. Judis Co.; serial number 1668, dated September 27, 1904; voided September 30, 1904 with signatures.",
    "sfomuseum:dimensions": "3 1/4 x 9 inches (8.3 x 22.9 cm)",
    "sfomuseum:media_ids": [
      1527828701,
      1527828703
    ],
    "sfomuseum:medium": "paper, ink",
    "sfomuseum:placetype": "object",
    "sfomuseum:publication": ": , 1904.",
    "sfomuseum:subcategory": "Other, Company Record / Document",
    "wof:name": "check: National Bank of D. O. Mills \u0026 Company",
    "wof:placetype": "venue"
  },
  "geometry": {"coordinates":[-122.386155,37.616357],"type":"Point"}
}
