{
  "type": "Feature",
  "properties": {
    "date:cessation_lower": "1990-01-01",
    "date:cessation_upper": "1990-12-31",
    "date:inception_lower": "1990-01-01",
    "date:inception_upper": "1990-12-31",
    "iso:country": "XX",
    "millsfield:images": [
      1527850223,
      1527850225
    ],
    "millsfield:primary_image": 1527850223,
    "sfomuseum:accession_number": "2003.200.038.029 a b",
    "sfomuseum:airline": "Japan Asia Airways",
    "sfomuseum:category": "Scheduling / Ticketing",
    "sfomuseum:collection": "Aviation Archive",
    "sfomuseum:creditline": "Gift of Thomas G. Dragges",
    "sfomuseum:date": "c. 1990",
    "sfomuseum:daterange_end": "1995-12-31",
    "sfomuseum:daterange_start": "1985-01-01",
    "sfomuseum:description": "Baggage destination tag issued by Japan Asia Airways, SFO (San Francisco, California); pink and white with elastic attachment, serial number EG-01-73-76; used.",
    "sfomuseum:dimensions": "3 x 2 1/2 inches (7.6 x 6.4 cm)",
    "sfomuseum:media_ids": [
      1527850223,
      1527850225
    ],
    "sfomuseum:medium": "paper, elastic, ink",
    "sfomuseum:placetype": "object",
    "sfomuseum:publication": ": , c. 1990.",
    "sfomuseum:subcategory": "Baggage Destination / Handling Tag",
    "wof:depicts": [
      102527513,
      1159284571
    ],
    "wof:name": "baggage destination tag: Japan Asia Airways",
    "wof:placetype": "venue"
  },
  "geometry": {"coordinates":[-122.386155,37.616357],"type":"Point"}
}
