{
  "type": "Feature",
  "properties": {
    "date:cessation_lower": "2004-01-01",
    "date:cessation_upper": "2004-12-31",
    "date:inception_lower": "2004-01-01",
    "date:inception_upper": "2004-12-31",
    "iso:country": "XX",
    "loc:named_authorities": [
      "n2005021639"
    ],
    "loc:subject_headings": [
      "sh2008113567",
      "sh2008113878",
      "sh2008113877",
      "sh2008113356",
      "sh2007100711"
    ],
    "sfomuseum:accession_number": "2012.032.006",
    "sfomuseum:author": "King, Steven C.",
    "sfomuseum:callnumber": "D790.2 .K56 2004",
    "sfomuseum:category": "Book",
    "sfomuseum:collection": "Aviation Library",
    "sfomuseum:creditline": "Purchase",
    "sfomuseum:date": "2004",
    "sfomuseum:date_acquired": "2012-01-11",
    "sfomuseum:daterange_end": "2004-12-31",
    "sfomuseum:daterange_start": "2004-01-01",
    "sfomuseum:description": "192 p. : ill., maps ; 23 cm.",
    "sfomuseum:description_library": "192 p. : ill., maps ; 23 cm.",
    "sfomuseum:medium": "paper, ink",
    "sfomuseum:placetype": "object",
    "sfomuseum:publication": "Bloomington, Ind.: AuthorHouse, 2004.",
    "sfomuseum:publisher": "AuthorHouse",
    "sfomuseum:publisher_location": "Bloomington, Ind.",
    "sfomuseum:subcategory": "Book",
    "sfomuseum:subject": "King, Steven C., 1921-\rWorld War, 1939-1945 -- Aerial operations, American. \rWorld War, 1939-1945 -- Himalaya Mountains. \rWorld War, 1939-1945 -- China. \rWorld War, 1939-1945 -- India. \rWorld War, 1939-1945 -- Personal narratives, American. \rAirlift, Military -- United States -- History. \rAir pilots, Military -- United States -- Biography.",
    "wof:name": "Flying the Hump to China",
    "wof:placetype": "custom",
    "wof:placetype_alt": "object"
  },
  "geometry": {"coordinates":[-122.386155,37.616357],"type":"Point"}
}
