{
  "type": "Feature",
  "properties": {
    "date:cessation_lower": "2011-01-01",
    "date:cessation_upper": "2011-12-31",
    "date:inception_lower": "2011-01-01",
    "date:inception_upper": "2011-12-31",
    "iso:country": "XX",
    "loc:named_authorities": [
      "no2006022464"
    ],
    "sfomuseum:accession_number": "2013.109.004",
    "sfomuseum:author": "Martin, Barry S. ",
    "sfomuseum:callnumber": "TL539 .M37 2011 c.2",
    "sfomuseum:category": "Book",
    "sfomuseum:collection": "Aviation Library",
    "sfomuseum:creditline": "Purchase",
    "sfomuseum:date": "2011",
    "sfomuseum:date_acquired": "2012-07-02",
    "sfomuseum:daterange_end": "2011-12-31",
    "sfomuseum:daterange_start": "2011-01-01",
    "sfomuseum:description": "245 p. : ill., map ; 23 cm.",
    "sfomuseum:description_library": "245 p. : ill., map ; 23 cm.",
    "sfomuseum:notes_library": "Includes bibliographical references (p. 220-235) and index.",
    "sfomuseum:placetype": "object",
    "sfomuseum:publication": "Indianopolis, IN: Dog Ear Pub, 2011.",
    "sfomuseum:publisher": "Dog Ear Pub",
    "sfomuseum:publisher_location": "Indianopolis, IN",
    "sfomuseum:subcategory": "Book",
    "sfomuseum:subject": "Leonard, Royal. \rAir pilots -- United States -- Biography. \rChina. Lu jun. -- Officers -- Biography. \rChina National Aviation Corporation -- Employees. \rChina -- History -- 1937-1945. \rChiang, Kai-shek, 1887-1975 -- Friends and associates. \rZhang, Xueliang, 1901-2001 -- Friends and associates. \rSino-Japanese War, 1937-1945 -- Aerial operations. ",
    "wof:name": "Forgotten aviator: the adventures of Royal Leonard: mail pilot, racer, China aviator",
    "wof:placetype": "venue"
  },
  "geometry": {"coordinates":[-122.386155,37.616357],"type":"Point"}
}
