{
  "type": "Feature",
  "properties": {
    "date:cessation_lower": "1940-01-01",
    "date:cessation_upper": "1940-12-31",
    "date:inception_lower": "1940-01-01",
    "date:inception_upper": "1940-12-31",
    "iso:country": "XX",
    "millsfield:images": [
      1527820855
    ],
    "millsfield:images_texts": [
      "LIMA\nVia PANAGRA\nLA PAZ\nVia the\nDIAGONAL\nUNITED STATES\nLIMA, LA PAZ\nBUENOS AIRES\nBS AIRES"
    ],
    "millsfield:images_texts_ids": [
      1527820855
    ],
    "millsfield:primary_image": 1527820855,
    "sfomuseum:accession_number": "2008.056.0965",
    "sfomuseum:airline": "Panagra (Pan American-Grace Airways)",
    "sfomuseum:category": "Promotional, Archive",
    "sfomuseum:collection": "Aviation Archive",
    "sfomuseum:creditline": "Gift of Jon E. Krupnick",
    "sfomuseum:date": "c. 1940",
    "sfomuseum:date_acquired": "2008-12-31",
    "sfomuseum:daterange_end": "1945-12-31",
    "sfomuseum:daterange_start": "1935-01-01",
    "sfomuseum:description": "Promotional brochure issued by Panagra (Pan American-Grace Airways), titled \"Via the Diagonal: United States, Lima, La Paz, Buenos Aires\"; bi-fold format; red cover with double-pointed arrow and inset images of city scenes; in English; for travel from Lima to Buenos Aires and stopping points in between.",
    "sfomuseum:dimensions": "6 1/4 x 3 3/8 inches (15.9 x 8.6 cm)",
    "sfomuseum:issues_held": "\r",
    "sfomuseum:media_ids": [
      1527820855
    ],
    "sfomuseum:medium": "paper, ink",
    "sfomuseum:placetype": "object",
    "sfomuseum:publication": ": , c. 1940.",
    "sfomuseum:subcategory": "Brochure, Airline",
    "sfomuseum:subject": "Airlines -- Commercial -- Pan American World Airways\rAirlines -- Commercial -- Panagra",
    "wof:depicts": [
      1159288567,
      1159284993
    ],
    "wof:name": "brochure: Panagra (Pan American-Grace Airways), Via the Diagonal",
    "wof:placetype": "custom",
    "wof:placetype_alt": "object"
  },
  "geometry": {"coordinates":[-122.386155,37.616357],"type":"Point"}
}
