{
  "type": "Feature",
  "properties": {
    "date:cessation_lower": "1947-01-01",
    "date:cessation_upper": "1947-12-31",
    "date:inception_lower": "1947-01-01",
    "date:inception_upper": "1947-12-31",
    "iso:country": "XX",
    "millsfield:images": [
      1527858571
    ],
    "millsfield:primary_image": 1527858571,
    "sfomuseum:accession_number": "2016.042.023",
    "sfomuseum:aircraft": "Hughes H-4 Hercules",
    "sfomuseum:author": "San Francisco Board of Supervisors, Airport Committee.",
    "sfomuseum:category": "Photograph",
    "sfomuseum:collection": "Aviation Archive",
    "sfomuseum:creditline": "Gift of Frank A. Norick",
    "sfomuseum:date": "1947",
    "sfomuseum:date_acquired": "2016-03-28",
    "sfomuseum:daterange_end": "1947-12-31",
    "sfomuseum:daterange_start": "1947-01-01",
    "sfomuseum:description": "Black and white photograph depicting oblique view of Howard Hughes' H-4 Flying Boat \"Spruce Goose\" navigating on water; aircraft viewed from air with boats in background; \"NX37602\" on vertical stabilizer; location unknown.",
    "sfomuseum:dimensions": "8 x 10 inches (20.3 x 25.4 cm)",
    "sfomuseum:media_ids": [
      1527858571
    ],
    "sfomuseum:medium": "paper, ink",
    "sfomuseum:placetype": "object",
    "sfomuseum:publication": ": , 1947.",
    "sfomuseum:subcategory": "Print, Photograph",
    "sfomuseum:subject": "Spruce Goose\rHoward Hughes",
    "wof:depicts": [
      1159290943
    ],
    "wof:name": "photograph: Hughes H-4 Hercules (Spruce Goose)",
    "wof:placetype": "venue"
  },
  "geometry": {"coordinates":[-122.386155,37.616357],"type":"Point"}
}
