{
  "type": "Feature",
  "properties": {
    "date:cessation_lower": "1963-01-01",
    "date:cessation_upper": "1963-12-31",
    "date:inception_lower": "1963-01-01",
    "date:inception_upper": "1963-12-31",
    "iso:country": "XX",
    "millsfield:images": [
      1527835289,
      1527851513
    ],
    "millsfield:images_texts": [
      "FFECTIVE\nTWA\nWORLDWIDE SYSTEM\nA B L",
      "TRANS WORLD AIRLINES WORLD ROUTES\nGrest Folls\nACROSS THE U\nOrate\nShines\nNationwide\nWorldwide\ndepend on\nTWA\nEUROPE, AFRICA, ASIA"
    ],
    "millsfield:images_texts_ids": [
      1527835289,
      1527851513
    ],
    "millsfield:primary_image": 1527835289,
    "sfomuseum:accession_number": "2001.106.408",
    "sfomuseum:airline": "TWA (Trans World Airlines)",
    "sfomuseum:category": "Scheduling / Ticketing",
    "sfomuseum:collection": "Aviation Archive",
    "sfomuseum:creditline": "Gift of Mark F. Adams Collection",
    "sfomuseum:date": "1963",
    "sfomuseum:date_acquired": "2001-10-18",
    "sfomuseum:daterange_end": "1963-12-31",
    "sfomuseum:daterange_start": "1963-01-01",
    "sfomuseum:description": "Worldwide system timetable issued by TWA (Trans World Airlines), effective October 27, 1963; blue and white cover with branding for TWA as official airline for the Transportation and Travel Pavilion at the 1964-65 New York World’s Fair.",
    "sfomuseum:dimensions": "8 3/4 x 4 inches (22.2 x 10.2 cm)",
    "sfomuseum:issues_held": "Effective:10-27-1963",
    "sfomuseum:media_ids": [
      1527835289,
      1527851513
    ],
    "sfomuseum:medium": "paper, ink",
    "sfomuseum:placetype": "object",
    "sfomuseum:publication": ": , 1963.",
    "sfomuseum:subcategory": "Timetable",
    "wof:depicts": [
      1159285393,
      1159287531
    ],
    "wof:name": "timetable: TWA (Trans World Airlines)",
    "wof:placetype": "custom",
    "wof:placetype_alt": "object"
  },
  "geometry": {"coordinates":[-122.386155,37.616357],"type":"Point"}
}
