{
  "type": "Feature",
  "properties": {
    "date:cessation_lower":"1960-12-31",
    "date:cessation_upper":"1960-12-31",
    "date:inception_lower":"1950-01-01",
    "date:inception_upper":"1950-01-01",
    "iso:country":"XX",
    "millsfield:images":[
        1527819321
    ],
    "sfomuseum:accession_number":"2011.061.0952",
    "sfomuseum:airline":"TACA International Airlines",
    "sfomuseum:category":"Scheduling / Ticketing",
    "sfomuseum:collection":"Aviation Archive",
    "sfomuseum:creditline":"Gift of the Frank J. Lichtanski Collection",
    "sfomuseum:date":"c. 1955",
    "sfomuseum:daterange_end":"1960-12-31",
    "sfomuseum:daterange_start":"1950-01-01",
    "sfomuseum:description":"Luggage identification label issued by TACA International Airlines; oval shape within rectangular border separated by red and yellow border; blank spaces for personal identification; logo on right side with red, yellow, and blue illustration of elongated parrot followed by white and yellow text, \u201cTACA International Airlines.\u201d",
    "sfomuseum:media_ids":[
        1527819321
    ],
    "sfomuseum:medium":"paper, ink",
    "sfomuseum:placetype":"object",
    "sfomuseum:subcategory":"Identification Tag / Form, Paper",
    "wof:depicts":[
        1159285255
    ],
    "wof:name":"luggage identification label: TACA International Airlines",
    "wof:placetype":"venue"
},
  "geometry": {"coordinates":[-122.386155,37.616357],"type":"Point"}
}