{
  "type": "Feature",
  "properties": {
    "date:cessation_lower":"1950-12-31",
    "date:cessation_upper":"1950-12-31",
    "date:inception_lower":"1950-01-01",
    "date:inception_upper":"1950-01-01",
    "iso:country":"XX",
    "millsfield:images":[
        1527847481
    ],
    "sfomuseum:accession_number":"2005.132.044.001",
    "sfomuseum:airline":"Piedmont Airlines",
    "sfomuseum:category":"Scheduling / Ticketing",
    "sfomuseum:collection":"Aviation Archive",
    "sfomuseum:creditline":"Gift of the William Hough Collection",
    "sfomuseum:date":"1950",
    "sfomuseum:daterange_end":"1950-12-31",
    "sfomuseum:daterange_start":"1950-01-01",
    "sfomuseum:description":"Timetable issued by Piedmont Airlines, effective July 1, 1950; four page double-sided fold-out. The cover is red, blue and gray with white and blue lettering. The company name is at the top. A route map is on a red field representing the East Coast is in the center. High center is a white rectangle advertising Direct service between The Ohio River Valley and The Tidewater Cities of North Carolina and Virginia. The company logo is bottom right. The back is white with contacts, general information and a four month schedule.",
    "sfomuseum:media_ids":[
        1527847481
    ],
    "sfomuseum:medium":"paper, ink",
    "sfomuseum:placetype":"object",
    "sfomuseum:subcategory":"Timetable",
    "wof:depicts":[
        1159285019
    ],
    "wof:name":"timetable: Piedmont Airlines",
    "wof:placetype":"venue"
},
  "geometry": {"coordinates":[-122.386155,37.616357],"type":"Point"}
}