{
  "type": "Feature",
  "properties": {
    "date:cessation_lower": "1950-01-01",
    "date:cessation_upper": "1950-12-31",
    "date:inception_lower": "1950-01-01",
    "date:inception_upper": "1950-12-31",
    "iso:country": "XX",
    "millsfield:images": [
      1527847481
    ],
    "millsfield:primary_image": 1527847481,
    "sfomuseum:accession_number": "2005.132.044.001",
    "sfomuseum:airline": "Piedmont Airlines",
    "sfomuseum:category": "Scheduling / Ticketing",
    "sfomuseum:collection": "Aviation Archive",
    "sfomuseum:creditline": "Gift of the William Hough Collection",
    "sfomuseum:date": "1950",
    "sfomuseum:date_acquired": "2006-12-05",
    "sfomuseum:daterange_end": "1950-12-31",
    "sfomuseum:daterange_start": "1950-01-01",
    "sfomuseum:description": "Timetable issued by Piedmont Airlines, effective July 1, 1950; four-page double-sided fold-out; red and white cover with illustration of route map and text announcing direct service between Ohio River Valley and Tidewater Cities of North Carolina and Virginia; includes passenger information.",
    "sfomuseum:dimensions": "9 x 4 inches (22.9 x 10.2 cm)",
    "sfomuseum:media_ids": [
      1527847481
    ],
    "sfomuseum:medium": "paper, ink",
    "sfomuseum:placetype": "object",
    "sfomuseum:publication": ": , 1950.",
    "sfomuseum:subcategory": "Timetable",
    "wof:depicts": [
      1159285019
    ],
    "wof:name": "timetable: Piedmont Airlines",
    "wof:placetype": "venue"
  },
  "geometry": {"coordinates":[-122.386155,37.616357],"type":"Point"}
}
