{
  "type": "Feature",
  "properties": {
    "date:cessation_lower":"1968-12-31",
    "date:cessation_upper":"1968-12-31",
    "date:inception_lower":"1968-01-01",
    "date:inception_upper":"1968-01-01",
    "iso:country":"XX",
    "millsfield:images":[
        1527846899
    ],
    "sfomuseum:accession_number":"2012.173.277",
    "sfomuseum:airline":"Northeast Airlines  (Northeast Airlines (Massachusetts, USA))",
    "sfomuseum:category":"Scheduling / Ticketing",
    "sfomuseum:collection":"Aviation Archive",
    "sfomuseum:creditline":"Gift of Willard F. Keeney",
    "sfomuseum:date":"1968",
    "sfomuseum:daterange_end":"1968-12-31",
    "sfomuseum:daterange_start":"1968-01-01",
    "sfomuseum:description":"System timetable issued by Northeast Airlines, effective September 9, 1968; white cover with text, \u201cAlready this year we\u2019ve broiled half a million steaks on our Yellowbirds on the way to Florida / You\u2019ll wish we flew everywhere\u201d enclosed in black rectangle; fold-out format; includes route map.",
    "sfomuseum:media_ids":[
        1527846899
    ],
    "sfomuseum:medium":"paper, ink",
    "sfomuseum:placetype":"object",
    "sfomuseum:subcategory":"Timetable",
    "wof:depicts":[
        1159284893
    ],
    "wof:name":"timetable: Northeast Airlines",
    "wof:placetype":"venue"
},
  "geometry": {"coordinates":[-122.386155,37.616357],"type":"Point"}
}