{
  "type": "Feature",
  "properties": {
    "date:cessation_lower": "1976-01-01",
    "date:cessation_upper": "1976-12-31",
    "date:inception_lower": "1976-01-01",
    "date:inception_upper": "1976-12-31",
    "iso:country": "US",
    "millsfield:images": [
      1527842175
    ],
    "sfomuseum:accession_number": "2013.046.089",
    "sfomuseum:airline": "Pan American World Airways",
    "sfomuseum:category": "Scheduling / Ticketing",
    "sfomuseum:collection": "Aviation Archive",
    "sfomuseum:continent": "North America",
    "sfomuseum:country": "United States",
    "sfomuseum:creditline": "Gift of the Family of Captain Roger J. Sherron, Jr.",
    "sfomuseum:date": "1976",
    "sfomuseum:daterange_end": "1976-12-31",
    "sfomuseum:daterange_start": "1976-01-01",
    "sfomuseum:description": "Timetable issued by Pan American World Airways, effective October 31, 1976; blue and white background with large globe logo pattern.",
    "sfomuseum:dimensions": "9 x 4 inches (22.9 x 10.2 cm)",
    "sfomuseum:issues_held": "c. 1970 (747 souvenir edition)",
    "sfomuseum:maker": "Pan American World Airways, Inc.",
    "sfomuseum:media_ids": [
      1527842175
    ],
    "sfomuseum:medium": "paper, ink, metal",
    "sfomuseum:placetype": "object",
    "sfomuseum:subcategory": "Timetable",
    "wof:depicts": [
      1159284989
    ],
    "wof:name": "timetable: Pan American World Airways",
    "wof:placetype": "venue"
  },
  "geometry": {"coordinates":[-122.386155,37.616357],"type":"Point"}
}
