{
  "type": "Feature",
  "properties": {
    "date:cessation_lower": "1955-01-01",
    "date:cessation_upper": "1955-12-31",
    "date:inception_lower": "1955-01-01",
    "date:inception_upper": "1955-12-31",
    "iso:country": "XX",
    "millsfield:images": [
      1527829297
    ],
    "millsfield:primary_image": 1527829297,
    "sfomuseum:accession_number": "2011.068.343.003",
    "sfomuseum:airline": "JAL (Japan Air Lines)",
    "sfomuseum:airport": "San Francisco International Airport",
    "sfomuseum:category": "Photograph",
    "sfomuseum:collection": "Aviation Archive",
    "sfomuseum:creditline": "Transfer",
    "sfomuseum:date": "c. 1955",
    "sfomuseum:date_acquired": "2011-06-21",
    "sfomuseum:daterange_end": "1960-12-31",
    "sfomuseum:daterange_start": "1950-01-01",
    "sfomuseum:description": "From set of 28 black and white slides depicting various scenes pertaining to San Francisco Airport and related subjects. Three men standing in front of parked station wagon on San Francisco street, exchanging automobile license plate; “Japan Air Lines” wordmark on side of vehicle; large palm tree and San Francisco Mint visible in background.",
    "sfomuseum:dimensions": "2 x 2 inches (5.1 x 5.1 cm)",
    "sfomuseum:media_ids": [
      1527829297
    ],
    "sfomuseum:medium": "slide",
    "sfomuseum:placetype": "object",
    "sfomuseum:publication": ": , c. 1955.",
    "sfomuseum:subcategory": "Slide",
    "wof:depicts": [
      1159285785,
      102527513
    ],
    "wof:name": "slide: JAL (Japan Air Lines), San Francisco Mint",
    "wof:placetype": "venue"
  },
  "geometry": {"coordinates":[-122.386155,37.616357],"type":"Point"}
}
