{
  "type": "Feature",
  "properties": {
    "date:cessation_lower": "1942-01-01",
    "date:cessation_upper": "1942-12-31",
    "date:inception_lower": "1942-01-01",
    "date:inception_upper": "1942-12-31",
    "iso:country": "XX",
    "sfomuseum:accession_number": "2000.172.050",
    "sfomuseum:author": "De Seversky, AMajor lexander Procofieff",
    "sfomuseum:callnumber": "UG633 .D45 1942 c.1",
    "sfomuseum:category": "Book",
    "sfomuseum:collection": "Aviation Library",
    "sfomuseum:creditline": "Collection of SFO Museum",
    "sfomuseum:date": "1942",
    "sfomuseum:date_acquired": "1999-12-08",
    "sfomuseum:daterange_end": "1942-12-31",
    "sfomuseum:daterange_start": "1942-01-01",
    "sfomuseum:description": "160 p. illus. 19 cm.",
    "sfomuseum:description_library": "160 p. illus. 19 cm.",
    "sfomuseum:medium": "paper, ink",
    "sfomuseum:placetype": "object",
    "sfomuseum:publication": "London; New York: Hutchinson, 1942.",
    "sfomuseum:publisher": "Hutchinson",
    "sfomuseum:publisher_location": "London; New York",
    "sfomuseum:subcategory": "Book",
    "sfomuseum:subject": "World War, 1939-1945 Aerial operations.Aeronautics, Military United States.",
    "wof:name": "Victory through air power",
    "wof:placetype": "custom",
    "wof:placetype_alt": "object"
  },
  "geometry": {"coordinates":[-122.386155,37.616357],"type":"Point"}
}
