{
  "type": "Feature",
  "properties": {
    "date:cessation_lower": "1936-12-31",
    "date:cessation_upper": "1936-12-31",
    "date:inception_lower": "1936-01-01",
    "date:inception_upper": "1936-01-01",
    "iso:country": "XX",
    "millsfield:images": [
      1527821509
    ],
    "sfomuseum:accession_number": "2011.032.0161",
    "sfomuseum:airport": "San Francisco Airport",
    "sfomuseum:category": "Photograph",
    "sfomuseum:collection": "Aviation Archive",
    "sfomuseum:creditline": "Transfer",
    "sfomuseum:date": "1936",
    "sfomuseum:daterange_end": "1936-12-31",
    "sfomuseum:daterange_start": "1936-01-01",
    "sfomuseum:description": "From attached handwritten note: “03958 / 3-6-36 Concrete Foundation Additional hangars\". Black and white photographic negative of space immediately in front of hangar doors, surrounded by concrete and wood barrier; open space filled with water; two weight bearing wooden frames facing hangars; two workmen; Mills Field Municipal Airport of San Francisco; photograph taken on March 6, 1936. Inscribed on black border, bottom: “X340. Airport 3-6-36. Concr. Foundation. Add’n hangars 3 \u0026 4.”",
    "sfomuseum:dimensions": "3 1/2 x 5 inches (8.9 x 12.7 cm)",
    "sfomuseum:media_ids": [
      1527821509
    ],
    "sfomuseum:medium": "nitrate negative",
    "sfomuseum:placetype": "object",
    "sfomuseum:subcategory": "Negative",
    "wof:depicts": [
      1360695655,
      102527513
    ],
    "wof:name": "negative: San Francisco Airport, construction",
    "wof:placetype": "venue"
  },
  "geometry": {"coordinates":[-122.386155,37.616357],"type":"Point"}
}
