{
  "type": "Feature",
  "properties": {
    "date:cessation_lower": "1970-01-01",
    "date:cessation_upper": "1979-12-31",
    "date:inception_lower": "1970-01-01",
    "date:inception_upper": "1979-12-31",
    "iso:country": "XX",
    "millsfield:images": [
      1527845287
    ],
    "millsfield:images_texts": [
      "A\nSAL\nSOUTH AFRICAN AIRWAYS • SUID-AFRIKAANSE LUGDIENS"
    ],
    "millsfield:images_texts_ids": [
      1527845287
    ],
    "millsfield:primary_image": 1527845287,
    "sfomuseum:accession_number": "2007.011.157.001 a b",
    "sfomuseum:airline": "South African Airways (SAA)",
    "sfomuseum:category": "Scheduling / Ticketing",
    "sfomuseum:collection": "Aviation Archive",
    "sfomuseum:creditline": "Gift of the William Hough Collection",
    "sfomuseum:date": "1970s",
    "sfomuseum:date_acquired": "2006-11-10",
    "sfomuseum:daterange_end": "1979-12-31",
    "sfomuseum:daterange_start": "1970-01-01",
    "sfomuseum:description": "a. Ticket jacket issued by South African Airways (SAA/SAL); white and orange cover with illustration of aircraft vertical stabilizer.\rb. Boarding pass for CN-235 commuter press flight.",
    "sfomuseum:dimensions": "4 x 8 3/4 inches (10.2 x 22.2 cm)",
    "sfomuseum:media_ids": [
      1527845287
    ],
    "sfomuseum:medium": "paper, ink",
    "sfomuseum:placetype": "object",
    "sfomuseum:publication": ": , 1970s.",
    "sfomuseum:subcategory": "Ticket Jacket / Ticket",
    "wof:depicts": [
      1159285187,
      1159286813,
      1159285183
    ],
    "wof:name": "ticket jacket: South African Airways",
    "wof:placetype": "custom",
    "wof:placetype_alt": "object"
  },
  "geometry": {"coordinates":[-122.386155,37.616357],"type":"Point"}
}
