{
  "type": "Feature",
  "properties": {
    "date:cessation_lower": "1983-01-01",
    "date:cessation_upper": "1983-12-31",
    "date:inception_lower": "1983-01-01",
    "date:inception_upper": "1983-12-31",
    "isbn:number": "0207146306, 9780207146305",
    "iso:country": "XX",
    "sfomuseum:accession_number": "00-1209",
    "sfomuseum:author": "Smith, Dick",
    "sfomuseum:callnumber": "TL721.S65 S65 1983",
    "sfomuseum:category": "Book",
    "sfomuseum:collection": "Aviation Library",
    "sfomuseum:date": "1983",
    "sfomuseum:daterange_end": "1983-12-31",
    "sfomuseum:daterange_start": "1983-01-01",
    "sfomuseum:description": "254 p. : ill. (some col.) ; 30 cm.",
    "sfomuseum:description_library": "254 p. : ill. (some col.) ; 30 cm.",
    "sfomuseum:medium": "paper, ink",
    "sfomuseum:placetype": "object",
    "sfomuseum:publication": "London: Angus and Robertson, 1983.",
    "sfomuseum:publisher": "Angus and Robertson",
    "sfomuseum:publisher_location": "London",
    "sfomuseum:subcategory": "Book",
    "sfomuseum:subject": "Helicopters.Flights around the world.World Circumnavigation by helicopters, 1982",
    "wof:name": "The earth beneath me: Dick Smith's epic journey across the world",
    "wof:placetype": "custom",
    "wof:placetype_alt": "object"
  },
  "geometry": {"coordinates":[-122.386155,37.616357],"type":"Point"}
}
