{
  "type": "Feature",
  "properties": {
    "date:cessation_lower": "2005-01-01",
    "date:cessation_upper": "2005-12-31",
    "date:inception_lower": "2005-01-01",
    "date:inception_upper": "2005-12-31",
    "iso:country": "XX",
    "loc:subject_headings": [
      "sh94005279",
      "sh97009091"
    ],
    "sfomuseum:accession_number": "2009.167.011",
    "sfomuseum:airline": "Southwest Airlines",
    "sfomuseum:author": "Grubbs-West, Lorraine",
    "sfomuseum:callnumber": "HF5549 .G755 2005 ",
    "sfomuseum:category": "Book",
    "sfomuseum:collection": "Aviation Library",
    "sfomuseum:creditline": "Purchase",
    "sfomuseum:date": "2005",
    "sfomuseum:date_acquired": "2009-12-02",
    "sfomuseum:daterange_end": "2005-12-31",
    "sfomuseum:daterange_start": "2005-01-01",
    "sfomuseum:description": "125 p. ; 23 cm.",
    "sfomuseum:description_library": "125 p. ; 23 cm.",
    "sfomuseum:medium": "paper, ink",
    "sfomuseum:placetype": "object",
    "sfomuseum:publication": "Dallas, TX: CornerStone Leadership Institute, 2005.",
    "sfomuseum:publisher": "CornerStone Leadership Institute",
    "sfomuseum:publisher_location": "Dallas, TX",
    "sfomuseum:series": "\r",
    "sfomuseum:subcategory": "Book",
    "sfomuseum:subject": "Southwest Airlines Co. -- Personnel management. \rEmployee loyalty. \rCustomer loyalty.",
    "wof:depicts": [
      1159285591,
      1360700737
    ],
    "wof:name": "Lessons in loyalty: how Southwest Airlines does it: an insider's view",
    "wof:placetype": "custom",
    "wof:placetype_alt": "object"
  },
  "geometry": {"coordinates":[-122.386155,37.616357],"type":"Point"}
}
