{
  "type": "Feature",
  "properties": {
    "date:cessation_lower": "1983-01-01",
    "date:cessation_upper": "1983-12-31",
    "date:inception_lower": "1983-01-01",
    "date:inception_upper": "1983-12-31",
    "iso:country": "XX",
    "millsfield:images": [
      1527841319
    ],
    "millsfield:primary_image": 1527841319,
    "sfomuseum:accession_number": "2009.122.457",
    "sfomuseum:airline": "Lufthansa",
    "sfomuseum:category": "Scheduling / Ticketing",
    "sfomuseum:collection": "Aviation Archive",
    "sfomuseum:creditline": "Gift of the William Hough Collection",
    "sfomuseum:date": "1983",
    "sfomuseum:date_acquired": "2010-06-08",
    "sfomuseum:daterange_end": "1983-12-31",
    "sfomuseum:daterange_start": "1983-01-01",
    "sfomuseum:description": "Timetable issued by Lufthansa, effective July 1 through October 31 1983; 309-page fold-out schedule; yellow cover.",
    "sfomuseum:dimensions": "8 x 4 inches (20.3 x 10.2 cm)",
    "sfomuseum:media_ids": [
      1527841319
    ],
    "sfomuseum:medium": "paper, ink",
    "sfomuseum:placetype": "object",
    "sfomuseum:publication": ": , 1983.",
    "sfomuseum:subcategory": "Timetable",
    "wof:depicts": [
      1159288215,
      1159284711
    ],
    "wof:name": "timetable: Lufthansa",
    "wof:placetype": "custom",
    "wof:placetype_alt": "object"
  },
  "geometry": {"coordinates":[-122.386155,37.616357],"type":"Point"}
}
