{
  "type": "Feature",
  "properties": {
    "date:cessation_lower": "1988-01-01",
    "date:cessation_upper": "1988-12-31",
    "date:inception_lower": "1988-01-01",
    "date:inception_upper": "1988-12-31",
    "iso:country": "XX",
    "millsfield:images": [
      1527841423
    ],
    "millsfield:primary_image": 1527841423,
    "sfomuseum:accession_number": "2008.108.155",
    "sfomuseum:airline": "Braniff Inc.",
    "sfomuseum:category": "Scheduling / Ticketing",
    "sfomuseum:collection": "Aviation Archive",
    "sfomuseum:creditline": "Gift of the William Hough Collection",
    "sfomuseum:date": "1988",
    "sfomuseum:daterange_end": "1988-12-31",
    "sfomuseum:daterange_start": "1988-01-01",
    "sfomuseum:description": "Timetable issued by Braniff Inc., effective October 1, 1988; on cover: full color photographic image of autumn tree and text, “New service to Boston, Philadelphia, Tulsa, Oklahoma City and Houston\".",
    "sfomuseum:dimensions": "9 x 4 inches (22.9 x 10.2 cm)",
    "sfomuseum:media_ids": [
      1527841423
    ],
    "sfomuseum:medium": "paper, ink",
    "sfomuseum:placetype": "object",
    "sfomuseum:publication": ": , 1988.",
    "sfomuseum:subcategory": "Timetable",
    "sfomuseum:subject": "Airlines -- Commercial -- Braniff International Airways",
    "wof:depicts": [
      1159286457
    ],
    "wof:name": "timetable: Braniff Inc.",
    "wof:placetype": "custom"
  },
  "geometry": {"coordinates":[-122.386155,37.616357],"type":"Point"}
}
