{
  "type": "Feature",
  "properties": {
    "date:cessation_lower": "1989-12-31",
    "date:cessation_upper": "1989-12-31",
    "date:inception_lower": "1989-01-01",
    "date:inception_upper": "1989-01-01",
    "iso:country": "XX",
    "millsfield:images": [
      1527830287
    ],
    "sfomuseum:accession_number": "2006.008.014",
    "sfomuseum:airline": "Pan American World Airways",
    "sfomuseum:category": "Employee Career History",
    "sfomuseum:collection": "Aviation Archive",
    "sfomuseum:creditline": "Gift of Marion L. Yates in memory of John A. Yates, PAA April 1938-1973",
    "sfomuseum:date": "1989",
    "sfomuseum:daterange_end": "1989-12-31",
    "sfomuseum:daterange_start": "1989-01-01",
    "sfomuseum:description": "White plastic identification card with globe blue logo and clipper ship. Signed \"J A Yates\", expires June 1989. From collection of John A. Yates.",
    "sfomuseum:media_ids": [
      1527830287
    ],
    "sfomuseum:medium": "paper, ink",
    "sfomuseum:placetype": "object",
    "sfomuseum:subcategory": "Identification",
    "wof:depicts": [
      1159284989
    ],
    "wof:name": "identification card: Pan American World Airways, retired employee identification card for John Yates",
    "wof:placetype": "venue"
  },
  "geometry": {"coordinates":[-122.386155,37.616357],"type":"Point"}
}
