{
  "type": "Feature",
  "properties": {
    "date:cessation_lower":"2005-12-31",
    "date:cessation_upper":"2005-12-31",
    "date:inception_lower":"2005-01-01",
    "date:inception_upper":"2005-01-01",
    "iso:country":"XX",
    "sfomuseum:accession_number":"2009.007.054",
    "sfomuseum:airline":"Pan American World Airways",
    "sfomuseum:artist":"John T. McCoy",
    "sfomuseum:category":"Book",
    "sfomuseum:collection":"Aviation Library",
    "sfomuseum:creditline":"Transfer from City and County of San Francisco",
    "sfomuseum:date":"2005",
    "sfomuseum:daterange_end":"2005-12-31",
    "sfomuseum:daterange_start":"2005-01-01",
    "sfomuseum:description":"Images of John T. McCoy's Pan Am watercolors.  Companion to ALM exhibit, Famous Firsts: John T. McCoy's Pan Am Watercolors, SFO IT-Aviation Museum  Gallery 2, October 2005-February 2006.",
    "sfomuseum:medium":"paper, ink",
    "sfomuseum:placetype":"object",
    "sfomuseum:subcategory":"Book",
    "wof:depicts":[
        1159284989
    ],
    "wof:name":"Famous firsts: The John T. McCoy Pan Am watercolors",
    "wof:placetype":"venue"
},
  "geometry": {"coordinates":[-122.386155,37.616357],"type":"Point"}
}