{
  "type": "Feature",
  "properties": {
    "date:cessation_lower": "2005-01-01",
    "date:cessation_upper": "2005-12-31",
    "date:inception_lower": "2005-01-01",
    "date:inception_upper": "2005-12-31",
    "iso:country": "XX",
    "sfomuseum:accession_number": "2009.007.054",
    "sfomuseum:airline": "Pan American World Airways",
    "sfomuseum:artist": "John T. McCoy",
    "sfomuseum:author": "San Francisco Airport Museums",
    "sfomuseum:callnumber": "HE9803.P36 M22 2005",
    "sfomuseum:category": "Book",
    "sfomuseum:collection": "Aviation Library",
    "sfomuseum:creditline": "Transfer from City and County of San Francisco",
    "sfomuseum:date": "2005",
    "sfomuseum:date_acquired": "2009-02-05",
    "sfomuseum:daterange_end": "2005-12-31",
    "sfomuseum:daterange_start": "2005-01-01",
    "sfomuseum:description": "Images of John T. McCoy's Pan Am watercolors.  Companion to ALM exhibit, Famous Firsts: John T. McCoy's Pan Am Watercolors, SFO IT-Aviation Museum  Gallery 2, October 2005-February 2006.",
    "sfomuseum:description_library": "Images of John T. McCoy's Pan Am watercolors.  Companion to ALM exhibit, Famous Firsts: John T. McCoy's Pan Am Watercolors, SFO IT-Aviation Museum  Gallery 2, October 2005-February 2006.",
    "sfomuseum:dimensions": "8 x 10 inches (20.3 x 25.4 cm)",
    "sfomuseum:medium": "paper, ink",
    "sfomuseum:placetype": "object",
    "sfomuseum:publication": ": San Francisco Airport Museums, 2005.",
    "sfomuseum:publisher": "San Francisco Airport Museums",
    "sfomuseum:subcategory": "Book",
    "sfomuseum:subject": "Pan American World Airways, inc. History.Airlines United States History.Aeronautics, Commercial United States History.",
    "wof:depicts": [
      1159284989,
      1159286839
    ],
    "wof:name": "Famous firsts: The John T. McCoy Pan Am watercolors",
    "wof:placetype": "custom",
    "wof:placetype_alt": "object"
  },
  "geometry": {"coordinates":[-122.386155,37.616357],"type":"Point"}
}
