{
  "type": "Feature",
  "properties": {
    "date:cessation_lower": "1930-02-09",
    "date:cessation_upper": "1930-02-09",
    "date:inception_lower": "1930-02-09",
    "date:inception_upper": "1930-02-09",
    "iso:country": "XX",
    "millsfield:images": [
      1527834163,
      1527834169
    ],
    "millsfield:primary_image": 1527834163,
    "sfomuseum:accession_number": "2012.149.2015",
    "sfomuseum:airline": "New York, Rio, and Buenos Aires Line (NYRBA)",
    "sfomuseum:category": "Philately",
    "sfomuseum:collection": "Aviation Archive",
    "sfomuseum:creditline": "Gift of the Captain John B. Russell Family",
    "sfomuseum:date": "02/09/1930",
    "sfomuseum:daterange_end": "1930-02-09",
    "sfomuseum:daterange_start": "1930-02-09",
    "sfomuseum:description": "Airmail flight cover, New York, Rio \u0026 Buenos Aires Line (NYRBA), signed by first pilot William Grooch; red cachet at left depicting state building with text, “Argentina - Estados Unidos / Primer Correio Aereo de la NYRBA”; postmarked February 9, 1930, Buenos Aires, with two postage stamps; no backstamp; addressed to Eva Grooch.",
    "sfomuseum:dimensions": "3 1/4 x 6 1/2 inches (8.3 x 16.5 cm)",
    "sfomuseum:media_ids": [
      1527834163,
      1527834169
    ],
    "sfomuseum:medium": "paper, ink",
    "sfomuseum:placetype": "object",
    "sfomuseum:subcategory": "Airmail Flight Cover",
    "wof:depicts": [
      1159284865
    ],
    "wof:name": "airmail flight cover: New York, Rio \u0026 Buenos Aires Line (NYRBA), William Grooch",
    "wof:placetype": "venue"
  },
  "geometry": {"coordinates":[-122.386155,37.616357],"type":"Point"}
}
