{
  "type": "Feature",
  "properties": {
    "date:cessation_lower": "1930-12-31",
    "date:cessation_upper": "1930-12-31",
    "date:inception_lower": "1930-01-01",
    "date:inception_upper": "1930-01-01",
    "iso:country": "XX",
    "millsfield:images": [
      1527832817,
      1527832813
    ],
    "sfomuseum:accession_number": "2012.149.1557",
    "sfomuseum:category": "Philately",
    "sfomuseum:collection": "Aviation Archive",
    "sfomuseum:creditline": "Gift of the Captain John B. Russell Family",
    "sfomuseum:date": "09/21/1930",
    "sfomuseum:daterange_end": "1930-09-21",
    "sfomuseum:daterange_start": "1930-09-21",
    "sfomuseum:description": "Airmail flight cover issued in honor of third anniversary of Charles Lindbergh Good Will Tour, San Diego, California, September 21, 1927; blue rectangular cachet at lower left; postmarked September 21, 1930, San Diego, with “Air mail saves time” cancellation mark over 5-cent postage stamp; backstamp: September 22 (no year, no location); envelope addressed to William C. Vestal.",
    "sfomuseum:media_ids": [
      1527832813,
      1527832817
    ],
    "sfomuseum:medium": "paper, ink",
    "sfomuseum:placetype": "object",
    "sfomuseum:subcategory": "Airmail Flight Cover",
    "wof:name": "airmail flight cover: Third anniversary of Charles Lindbergh Good Will Tour",
    "wof:placetype": "venue"
  },
  "geometry": {"coordinates":[-122.386155,37.616357],"type":"Point"}
}
