{
  "type": "Feature",
  "properties": {
    "date:cessation_lower": "1969-01-01",
    "date:cessation_upper": "1969-12-31",
    "date:inception_lower": "1969-01-01",
    "date:inception_upper": "1969-12-31",
    "iso:country": "XX",
    "millsfield:images": [
      1527848201,
      1527848203
    ],
    "millsfield:primary_image": 1527848201,
    "sfomuseum:accession_number": "2007.007.001",
    "sfomuseum:airline": "TWA (Trans World Airlines)",
    "sfomuseum:artist": "David Klein",
    "sfomuseum:category": "Passenger Amenity",
    "sfomuseum:collection": "Aviation Archive",
    "sfomuseum:creditline": "Gift of Hiller Aviation Museum",
    "sfomuseum:date": "c. 1969",
    "sfomuseum:date_acquired": "2008-03-03",
    "sfomuseum:daterange_end": "1974-12-31",
    "sfomuseum:daterange_start": "1964-01-01",
    "sfomuseum:description": "Menu issued by TWA (Trans World Airlines); green-toned color illustration of Mt. Rainier; menu items include roast Chateaubriand, grilled Colorado lamb chops, and lemon butter veal; menu number: D-40 / 49; undated.",
    "sfomuseum:dimensions": "10 1/2 x 7 inches (26.7 x 17.8 cm)",
    "sfomuseum:media_ids": [
      1527848201,
      1527848203
    ],
    "sfomuseum:medium": "paper, ink",
    "sfomuseum:placetype": "object",
    "sfomuseum:publication": ": , c. 1969.",
    "sfomuseum:subcategory": "Menu",
    "sfomuseum:subject": "Airlines -- Commercial -- TWA (Trans World Airlines)",
    "wof:depicts": [
      1159285393
    ],
    "wof:name": "menu: TWA (Trans World Airlines)",
    "wof:placetype": "venue"
  },
  "geometry": {"coordinates":[-122.386155,37.616357],"type":"Point"}
}
