{
  "type": "Feature",
  "properties": {
    "date:cessation_lower": "1945-01-01",
    "date:cessation_upper": "1945-12-31",
    "date:inception_lower": "1945-01-01",
    "date:inception_upper": "1945-12-31",
    "iso:country": "XX",
    "millsfield:images": [
      1527831583
    ],
    "millsfield:primary_image": 1527831583,
    "sfomuseum:accession_number": "2013.046.204",
    "sfomuseum:aircraft": "Douglas DC-3",
    "sfomuseum:airline": "Cubana de Aviación S.A.",
    "sfomuseum:category": "Photograph",
    "sfomuseum:collection": "Aviation Archive",
    "sfomuseum:creditline": "Gift of the Family of Captain Roger J. Sherron, Jr.",
    "sfomuseum:date": "1945",
    "sfomuseum:date_acquired": "2013-09-27",
    "sfomuseum:daterange_end": "1945-12-31",
    "sfomuseum:daterange_start": "1945-01-01",
    "sfomuseum:description": "Black and white photograph depicting Cuba president Ramon Grau standing on ramp stairs in front of Compania Cubana de Aviacion Douglas DC-3 airplane, Camaguey Airport, Cuba, April 10, 1945; Grau surrounded by various officials, waving hat to onlookers.",
    "sfomuseum:dimensions": "7 x 5 inches (17.8 x 12.7 cm)",
    "sfomuseum:media_ids": [
      1527831583
    ],
    "sfomuseum:medium": "photograph",
    "sfomuseum:placetype": "object",
    "sfomuseum:publication": ": , 1945.",
    "sfomuseum:subcategory": "Print, Photograph",
    "wof:depicts": [
      1159285623,
      1159290417,
      1159288275
    ],
    "wof:name": "photograph: Compania Cubana de Aviacion, Douglas DC-3",
    "wof:placetype": "venue"
  },
  "geometry": {"coordinates":[-122.386155,37.616357],"type":"Point"}
}
