{
  "type": "Feature",
  "properties": {
    "date:cessation_lower": "1930-12-31",
    "date:cessation_upper": "1930-12-31",
    "date:inception_lower": "1930-01-01",
    "date:inception_upper": "1930-01-01",
    "iso:country": "XX",
    "sfomuseum:accession_number": "2014.156.148",
    "sfomuseum:category": "Philately",
    "sfomuseum:collection": "Aviation Archive",
    "sfomuseum:creditline": "Gift of Captain Jon Simmonds",
    "sfomuseum:date": "09/02/1930",
    "sfomuseum:daterange_end": "1930-09-02",
    "sfomuseum:daterange_start": "1930-09-02",
    "sfomuseum:description": "Airmail flight cover promoting Gordon Bennett International Balloon Race and Aerial Carnival, postmarked September 2, 1930, Cleveland Ohio, with one 5-cent postage stamp; pink cachet at left with image of balloon and text, “Gordon Bennett International Balloon Race and Aerial Carnival / Cleveland / Aug. 31 and Sep. 1, 1930”; envelope addressed to James C. Burns, San Diego, California.",
    "sfomuseum:media_ids": [
      1527856385, 
      1527856387
    ],
    "sfomuseum:medium": "paper, ink",
    "sfomuseum:placetype": "object",
    "sfomuseum:subcategory": "Airmail Flight Cover",
    "wof:name": "airmail flight cover: Gordon Bennett International Balloon Race and Aerial Carnival",
    "wof:placetype": "venue"
  },
  "geometry": {"coordinates":[-122.386155,37.616358],"type":"Point"}
}
