{
  "type": "Feature",
  "properties": {
    "date:cessation_lower": "1942-01-01",
    "date:cessation_upper": "1942-12-31",
    "date:inception_lower": "1942-01-01",
    "date:inception_upper": "1942-12-31",
    "iso:country": "XX",
    "millsfield:images": [
      1527819285
    ],
    "millsfield:primary_image": 1527819285,
    "sfomuseum:accession_number": "2011.061.0715",
    "sfomuseum:airline": "Canadian Pacific Airlines",
    "sfomuseum:category": "Promotional",
    "sfomuseum:collection": "Aviation Archive",
    "sfomuseum:creditline": "Gift of the Frank J. Lichtanski Collection",
    "sfomuseum:date": "c. 1942",
    "sfomuseum:date_acquired": "2011-08-02",
    "sfomuseum:daterange_end": "1947-12-31",
    "sfomuseum:daterange_start": "1937-01-01",
    "sfomuseum:description": "Luggage label promoting Canadian Pacific Air Lines; red and blue shield shape; blue and red with illustration of airplane in flight.",
    "sfomuseum:dimensions": "3 1/2 x 2 1/4 inches (8.9 x 5.7 cm)",
    "sfomuseum:media_ids": [
      1527819285
    ],
    "sfomuseum:medium": "paper, ink, adhesive",
    "sfomuseum:placetype": "object",
    "sfomuseum:publication": ": , c. 1942.",
    "sfomuseum:subcategory": "Luggage Label",
    "wof:depicts": [
      1159284217,
      1159288301
    ],
    "wof:name": "luggage label: Canadian Pacific Air Lines",
    "wof:placetype": "venue"
  },
  "geometry": {"coordinates":[-122.386155,37.616357],"type":"Point"}
}
