{
  "type": "Feature",
  "properties": {
    "date:cessation_lower": "1935-12-31",
    "date:cessation_upper": "1935-12-31",
    "date:inception_lower": "1935-01-01",
    "date:inception_upper": "1935-01-01",
    "iso:country": "XX",
    "sfomuseum:accession_number": "2008.075.124",
    "sfomuseum:category": "Philately",
    "sfomuseum:collection": "Aviation Archive",
    "sfomuseum:creditline": "Gift of Jon E. Krupnick",
    "sfomuseum:date": "10/28/1935",
    "sfomuseum:daterange_end": "1935-10-28",
    "sfomuseum:daterange_start": "1935-10-28",
    "sfomuseum:description": "Mail ship cover for U.S.S. Chester- October 28, 1935; envelope postmarked October 28, 1935, U.S.S. Chester with cancellation mark with text “Navy Day, Hong Kong BCC” on purple 3-cent postage stamp; addressed to Captain Wm. V. Miller; no return addressee; identified by donor with additional information: \"Pacific Naval Ship covers\".",
    "sfomuseum:media_ids": [
      1527851803
    ],
    "sfomuseum:medium": "paper, ink",
    "sfomuseum:placetype": "object",
    "sfomuseum:subcategory": "Airmail Flight Cover",
    "wof:name": "mail ship cover: Pacific Naval Ship, U.S.S. Chester, October 28, 1935",
    "wof:placetype": "venue"
  },
  "geometry": {"coordinates":[-122.386155,37.616358],"type":"Point"}
}
