{
  "type": "Feature",
  "properties": {
    "date:cessation_lower": "1985-01-01",
    "date:cessation_upper": "1985-12-31",
    "date:inception_lower": "1985-01-01",
    "date:inception_upper": "1985-12-31",
    "iso:country": "XX",
    "millsfield:images": [
      1527846169
    ],
    "millsfield:primary_image": 1527846169,
    "sfomuseum:accession_number": "2012.096.034",
    "sfomuseum:airline": "Alitalia",
    "sfomuseum:category": "Promotional",
    "sfomuseum:collection": "Aviation Archive",
    "sfomuseum:creditline": "Gift of the William Hough Collection",
    "sfomuseum:date": "c. 1985",
    "sfomuseum:date_acquired": "2013-03-21",
    "sfomuseum:daterange_end": "1990-12-31",
    "sfomuseum:daterange_start": "1980-01-01",
    "sfomuseum:description": "Brochure issued by Alitalia promoting Top Class (first) and business class service; white cover with color oval-shaped photographic images of jets in flight; contains information for service and amenities.",
    "sfomuseum:dimensions": "7 x 9 inches (17.8 x 22.9 cm)",
    "sfomuseum:media_ids": [
      1527846169
    ],
    "sfomuseum:medium": "paper, ink",
    "sfomuseum:placetype": "object",
    "sfomuseum:publication": ": , c. 1985.",
    "sfomuseum:subcategory": "Brochure, Airline",
    "wof:depicts": [
      1159283823,
      1159288221
    ],
    "wof:name": "brochure: Alitalia, Top and Business Class service",
    "wof:placetype": "custom",
    "wof:placetype_alt": "object"
  },
  "geometry": {"coordinates":[-122.386155,37.616357],"type":"Point"}
}
