{
  "type": "Feature",
  "properties": {
    "date:cessation_lower":"1979-12-31",
    "date:cessation_upper":"1979-12-31",
    "date:inception_lower":"1979-01-01",
    "date:inception_upper":"1979-01-01",
    "iso:country":"XX",
    "sfomuseum:accession_number":"2008.108.122",
    "sfomuseum:category":"Scheduling / Ticketing",
    "sfomuseum:collection":"Aviation Archive",
    "sfomuseum:creditline":"Gift of the William Hough Collection",
    "sfomuseum:date":"1979",
    "sfomuseum:daterange_end":"1979-12-31",
    "sfomuseum:daterange_start":"1979-01-01",
    "sfomuseum:description":"Timetable issued by Apollo Airways, effective February 1, 1979; three page double-sided fold-out with a white with blue cover.",
    "sfomuseum:medium":"paper, ink",
    "sfomuseum:placetype":"object",
    "sfomuseum:subcategory":"Timetable",
    "wof:name":"timetable: Apollo Airways",
    "wof:placetype":"venue"
},
  "geometry": {"coordinates":[-122.386155,37.616358],"type":"Point"}
}