{
  "type": "Feature",
  "properties": {
    "date:cessation_lower": "1975-01-01",
    "date:cessation_upper": "1975-12-31",
    "date:inception_lower": "1975-01-01",
    "date:inception_upper": "1975-12-31",
    "isbn:number": "085475069X 9780854750696 ",
    "iso:country": "XX",
    "sfomuseum:accession_number": "2001.205.012",
    "sfomuseum:author": "Wiggan, Richard",
    "sfomuseum:callnumber": "HD8039.A43 W44 1975",
    "sfomuseum:category": "Book",
    "sfomuseum:collection": "Aviation Library",
    "sfomuseum:creditline": "Collection of SFO Museum",
    "sfomuseum:date": "1975",
    "sfomuseum:date_acquired": "2001-09-05",
    "sfomuseum:daterange_end": "1975-12-31",
    "sfomuseum:daterange_start": "1975-01-01",
    "sfomuseum:description": "180 p., [12] p. of plates ; p., 21 cm.",
    "sfomuseum:description_library": "180 p., [12] p. of plates ; p., 21 cm.",
    "sfomuseum:medium": "paper, ink",
    "sfomuseum:placetype": "object",
    "sfomuseum:publication": "Melksham, United Kingdom: Venton, 1975.",
    "sfomuseum:publisher": "Venton",
    "sfomuseum:publisher_location": "Melksham, United Kingdom",
    "sfomuseum:subcategory": "Book",
    "sfomuseum:subject": "Flight attendants -- Vocational guidance.\rFlight attendants -- Training.",
    "wof:name": "So you want to be an air hostess",
    "wof:placetype": "custom",
    "wof:placetype_alt": "object"
  },
  "geometry": {"coordinates":[-122.386155,37.616357],"type":"Point"}
}
