{
  "type": "Feature",
  "properties": {
    "date:cessation_lower": "1957-01-01",
    "date:cessation_upper": "1957-12-31",
    "date:inception_lower": "1957-01-01",
    "date:inception_upper": "1957-12-31",
    "iso:country": "XX",
    "sfomuseum:accession_number": "2001.205.005",
    "sfomuseum:author": "Air Transport Association of America",
    "sfomuseum:callnumber": "HD8039.A428 1957 ",
    "sfomuseum:category": "Book",
    "sfomuseum:collection": "Aviation Library",
    "sfomuseum:creditline": "Purchase",
    "sfomuseum:date": "1957",
    "sfomuseum:date_acquired": "2001-07-23",
    "sfomuseum:daterange_end": "1957-12-31",
    "sfomuseum:daterange_start": "1957-01-01",
    "sfomuseum:description": "vi, 75 p. : p., ill. ;, 22 cm.",
    "sfomuseum:description_library": "vi, 75 p. : p., ill. ;, 22 cm.",
    "sfomuseum:medium": "paper, ink",
    "sfomuseum:notes_library": "Includes bibliographical references and index.",
    "sfomuseum:placetype": "object",
    "sfomuseum:publication": "Washington, D.C.: Air Transport Association of America, 1957.",
    "sfomuseum:publisher": "Air Transport Association of America",
    "sfomuseum:publisher_location": "Washington, D.C.",
    "sfomuseum:subcategory": "Book",
    "sfomuseum:subject": "Aeronautics, Commercial -- North America -- Vocational guidance. \rAirlines -- United States -- Employees.  ",
    "wof:name": "Career opportunities with the airlines: \"the scheduled airlines can be your future.\"",
    "wof:placetype": "venue"
  },
  "geometry": {"coordinates":[-122.386155,37.616357],"type":"Point"}
}
