{
  "type": "Feature",
  "properties": {
    "date:cessation_lower": "1989-01-01",
    "date:cessation_upper": "1989-12-31",
    "date:inception_lower": "1989-01-01",
    "date:inception_upper": "1989-12-31",
    "iso:country": "XX",
    "loc:named_authorities": {
      "n50000654": "Earhart, Amelia, 1897-1937"
    },
    "sfomuseum:accession_number": "00-3421",
    "sfomuseum:author": "Rich, Doris L.",
    "sfomuseum:callnumber": "TL540.E3 R53 1989",
    "sfomuseum:category": "Book",
    "sfomuseum:collection": "Aviation Library",
    "sfomuseum:date": "c. 1989",
    "sfomuseum:daterange_end": "1994-12-31",
    "sfomuseum:daterange_start": "1984-01-01",
    "sfomuseum:description": "xiii, 321 p., [8] p. of plates : ill. ; 24 cm.",
    "sfomuseum:medium": "paper, ink",
    "sfomuseum:placetype": "object",
    "sfomuseum:publication": "Washington, D.C.: Smithsonian Institution Press, c. 1989.",
    "sfomuseum:publisher": "Smithsonian Institution Press",
    "sfomuseum:publisher_location": "Washington, D.C.",
    "sfomuseum:subcategory": "Book",
    "sfomuseum:subject": "Earhart, Amelia, 1897-1937.Air pilots United States Biography.Earhart, Amelia, 1897-1937.Air pilots.",
    "wof:name": "Amelia Earhart: a biography",
    "wof:placetype": "venue"
  },
  "geometry": {"coordinates":[-122.386155,37.616357],"type":"Point"}
}
