{
  "type": "Feature",
  "properties": {
    "date:cessation_lower": "1977-01-01",
    "date:cessation_upper": "1977-12-31",
    "date:inception_lower": "1977-01-01",
    "date:inception_upper": "1977-12-31",
    "iso:country": "XX",
    "millsfield:images": [
      1527844151,
      1527844153
    ],
    "millsfield:primary_image": 1527844151,
    "sfomuseum:accession_number": "2006.034.024",
    "sfomuseum:airline": "American Airlines",
    "sfomuseum:category": "Passenger Amenity",
    "sfomuseum:collection": "Aviation Archive",
    "sfomuseum:creditline": "Gift of Adan Wong",
    "sfomuseum:date": "1977",
    "sfomuseum:daterange_end": "1977-12-31",
    "sfomuseum:daterange_start": "1977-01-01",
    "sfomuseum:description": "Menu issued by American Airlines; white cover with color photographic image of folk art quilt; breakfast menu items include filet mignon with eggs or Eggs Goldenrod; menu number: M711-2-6; date: 77 CYCLE 2.",
    "sfomuseum:dimensions": "6 x 6 inches (15.2 x 15.2 cm)",
    "sfomuseum:media_ids": [
      1527844151,
      1527844153
    ],
    "sfomuseum:medium": "paper, ink",
    "sfomuseum:placetype": "object",
    "sfomuseum:subcategory": "Menu",
    "wof:depicts": [
      1159283849
    ],
    "wof:name": "menu: American Airlines",
    "wof:placetype": "venue"
  },
  "geometry": {"coordinates":[-122.386155,37.616357],"type":"Point"}
}
