{
  "type": "Feature",
  "properties": {
    "date:cessation_lower": "1977-01-01",
    "date:cessation_upper": "1977-12-31",
    "date:inception_lower": "1977-01-01",
    "date:inception_upper": "1977-12-31",
    "iso:country": "XX",
    "millsfield:images": [
      1527844151,
      1527844153
    ],
    "millsfield:images_texts": [
      "9181€\n- 187\n18767\nLT CENTENNIALR\nACKNAPPENBERGER",
      "Welcome Aboard AmericanAirlines\nBeverages\nA choice of spirits and cocktails is available at $1.50\nAmerican beer is available at $1.00\nSpecially selected wines are available at $1.00\nAmerican champagne is available at $1.00\nA selection of cordials is available at $1.50\nTomato Juice, Orange Juice, Coca'Cola and other soft drinks\nFreshly Brewed Coffee, Tea, Milk and Sanka\nWith its oriains stretching back as far as those of our nation.\n1. Itsing one Deciall or independence\nthe rised, working Americans. Farmers, teachers and tradesmen\nbecame artists in addition to their daily occupations.\nmade in Pennsylvania in\nviales. vouresv o\nkhea gooeman. cult. inc.. New rork. New York\nMenu\nAppetizer\nSpecially chosen to tempt your palate\nand complement your entree selection.\nEntree Selections\nFilet Mignon\nChoice filet mignon, carefully broiled,\nserved with fluffy scrambled eggs and\na fresh tomato half.\nEggs Goldenrod\nA lightly grilled corn muffin, topped\nwith egg slices and a creamy\ncheese\nsauce.\nLean\nCanadian bacon.\nsmoked\nManicotti\nTender crepes filled with creamy\nRicotta cheese and baked to\nperfection in a zesty tomato sauce.\nSweet Cake and Butter\nPlease accept our apology if occasionally your selection is not available.\n2006.034.024"
    ],
    "millsfield:images_texts_ids": [
      1527844151,
      1527844153
    ],
    "millsfield:primary_image": 1527844151,
    "sfomuseum:accession_number": "2006.034.024",
    "sfomuseum:airline": "American Airlines",
    "sfomuseum:category": "Passenger Amenity, Archive",
    "sfomuseum:collection": "Aviation Archive",
    "sfomuseum:creditline": "Gift of Adan Wong",
    "sfomuseum:date": "1977",
    "sfomuseum:date_acquired": "2007-04-06",
    "sfomuseum:daterange_end": "1977-12-31",
    "sfomuseum:daterange_start": "1977-01-01",
    "sfomuseum:description": "Menu issued by American Airlines; white cover with color photographic image of folk art quilt; breakfast menu items include filet mignon with eggs or Eggs Goldenrod; menu number: M711-2-6; date: 77 CYCLE 2.",
    "sfomuseum:dimensions": "6 x 6 inches (15.2 x 15.2 cm)",
    "sfomuseum:media_ids": [
      1527844151,
      1527844153
    ],
    "sfomuseum:medium": "paper, ink",
    "sfomuseum:placetype": "object",
    "sfomuseum:publication": ": , 1977.",
    "sfomuseum:subcategory": "Menu",
    "wof:depicts": [
      1159283849,
      1360700619
    ],
    "wof:name": "menu: American Airlines",
    "wof:placetype": "custom",
    "wof:placetype_alt": "object"
  },
  "geometry": {"coordinates":[-122.386155,37.616357],"type":"Point"}
}
