{
  "type": "Feature",
  "properties": {
    "date:cessation_lower": "2000-12-31",
    "date:cessation_upper": "2000-12-31",
    "date:inception_lower": "2000-01-01",
    "date:inception_upper": "2000-01-01",
    "iso:country": "XX",
    "sfomuseum:accession_number": "2006.034.158",
    "sfomuseum:category": "Food Service",
    "sfomuseum:collection": "Aviation Museum",
    "sfomuseum:creditline": "Gift of Adan Wong",
    "sfomuseum:date": "2000s",
    "sfomuseum:daterange_end": "2000-12-31",
    "sfomuseum:daterange_start": "2000-01-01",
    "sfomuseum:description": "Menu produced by United Air Lines; white cover with dark red logo; menu items include barbecued pork chop, croissant sandwich, and chicken Milano; menu number: SEA L03-4; undated.",
    "sfomuseum:media_ids": [
      1527853595, 
      1527845489
    ],
    "sfomuseum:medium": "paper, ink",
    "sfomuseum:placetype": "object",
    "sfomuseum:subcategory": "Menu",
    "wof:name": "menu: United Airlines",
    "wof:placetype": "venue"
  },
  "geometry": {"coordinates":[-122.386155,37.616358],"type":"Point"}
}
