{
  "type": "Feature",
  "properties": {
    "date:cessation_lower": "2000-01-01",
    "date:cessation_upper": "2009-12-31",
    "date:inception_lower": "2000-01-01",
    "date:inception_upper": "2009-12-31",
    "iso:country": "XX",
    "millsfield:images": [
      1527845489,
      1527853595
    ],
    "millsfield:primary_image": 1527853595,
    "sfomuseum:accession_number": "2006.034.158",
    "sfomuseum:airline": "United Airlines",
    "sfomuseum:category": "Passenger Amenity",
    "sfomuseum:collection": "Aviation Archive",
    "sfomuseum:creditline": "Gift of Adan Wong",
    "sfomuseum:date": "2000s",
    "sfomuseum:date_acquired": "2007-04-06",
    "sfomuseum:daterange_end": "2000-12-31",
    "sfomuseum:daterange_start": "2000-01-01",
    "sfomuseum:description": "Menu issued by United Airlines; white cover with dark red logo; menu items include barbecued pork chop, croissant sandwich, and chicken Milano; menu number: SEA L03-4; undated.",
    "sfomuseum:dimensions": "11 x 8 1/2 inches (27.9 x 21.6 cm)",
    "sfomuseum:media_ids": [
      1527853595,
      1527845489
    ],
    "sfomuseum:medium": "paper, ink",
    "sfomuseum:placetype": "object",
    "sfomuseum:publication": ": , 2000s.",
    "sfomuseum:subcategory": "Menu",
    "wof:depicts": [
      1159285413
    ],
    "wof:name": "menu: United Airlines",
    "wof:placetype": "venue"
  },
  "geometry": {"coordinates":[-122.386155,37.616357],"type":"Point"}
}
