{
  "type": "Feature",
  "properties": {
    "date:cessation_lower": "2000-01-01",
    "date:cessation_upper": "2000-12-31",
    "date:inception_lower": "2000-01-01",
    "date:inception_upper": "2000-12-31",
    "iso:country": "XX",
    "millsfield:images": [
      1527846107,
      1527846113
    ],
    "millsfield:primary_image": 1527846107,
    "sfomuseum:accession_number": "2011.001.012",
    "sfomuseum:airline": "ANA (All Nippon Airways)",
    "sfomuseum:category": "Promotional",
    "sfomuseum:collection": "Aviation Archive",
    "sfomuseum:creditline": "Gift of Robert Behr",
    "sfomuseum:date": "c. 2000",
    "sfomuseum:date_acquired": "2011-05-25",
    "sfomuseum:daterange_end": "2005-12-31",
    "sfomuseum:daterange_start": "1995-01-01",
    "sfomuseum:description": "Promotional brochure issued by ANA (All Nippon Airways), titled “ANA Business Privilege / Supports your business trip to Japan from start to finish”; orange and white cover with close-up frontal photographic image of Boeing 747 aircraft nose seen from above, followed by sequence of round inset images; contains traveler information pertaining to lodging rates and accommodations.",
    "sfomuseum:dimensions": "9 x 4 inches (22.9 x 10.2 cm)",
    "sfomuseum:media_ids": [
      1527846107,
      1527846113
    ],
    "sfomuseum:medium": "paper, ink",
    "sfomuseum:placetype": "object",
    "sfomuseum:publication": ": , c. 2000.",
    "sfomuseum:subcategory": "Brochure, Airline",
    "wof:depicts": [
      1159283875,
      1159289873,
      1159293593
    ],
    "wof:name": "brochure: ANA (All Nippon Airways), business travel",
    "wof:placetype": "venue"
  },
  "geometry": {"coordinates":[-122.386155,37.616357],"type":"Point"}
}
