{
  "type": "Feature",
  "properties": {
    "date:cessation_lower": "2005-12-31",
    "date:cessation_upper": "2005-12-31",
    "date:inception_lower": "1995-01-01",
    "date:inception_upper": "1995-01-01",
    "iso:country": "XX",
    "sfomuseum:accession_number": "2011.001.012",
    "sfomuseum:category": "Promotional",
    "sfomuseum:collection": "Aviation Archive",
    "sfomuseum:creditline": "Gift of Robert Behr",
    "sfomuseum:date": "c. 2000",
    "sfomuseum:daterange_end": "2005-12-31",
    "sfomuseum:daterange_start": "1995-01-01",
    "sfomuseum:description": "Promotional brochure produced by ANA (All Nippon Airways), titled “ANA Business Privilege / Supports your business trip to Japan from start to finish”; orange and white cover with close-up frontal photographic image of Boeing 747 aircraft nose seen from above, followed by sequence of round inset images; contains traveler information pertaining to lodging rates and accommodations.",
    "sfomuseum:media_ids": [
      1527846107, 
      1527846113
    ],
    "sfomuseum:medium": "paper, ink",
    "sfomuseum:placetype": "object",
    "sfomuseum:subcategory": "Brochure, Airline",
    "wof:name": "brochure: ANA (All Nippon Airways), business travel",
    "wof:placetype": "venue"
  },
  "geometry": {"coordinates":[-122.386155,37.616358],"type":"Point"}
}
