{
  "type": "Feature",
  "properties": {
    "date:cessation_lower": "1999-01-01",
    "date:cessation_upper": "1999-12-31",
    "date:inception_lower": "1999-01-01",
    "date:inception_upper": "1999-12-31",
    "iso:country": "XX",
    "millsfield:images": [
      1527845191
    ],
    "millsfield:images_texts": [
      "TO BEGIN\nWarm roasted nuts\nserved with your preferred\ncocktail or beverage\nAPPETIZER\nLobster half with lemon\naccompanied by Du Barry sauce\nSALAD\nLollo rosso, butter lettuce and baby spinach\nwith yellow pear tomato\nand buffalo mozzarella with crushed pepper\nOffered with your choice of basil vinaigrette\nor Parmesan-pepper dressing\nFreshly baked sourdough bread and assorted rolls with butter\nMAIN COURSES\nChef's Seasonal Selection\nCreated by Award-Winning\nChef Jean-Louis Dumonet of Trois Jean Bistro,\nin New York City\nVeal Chop au Jus\nserved with mashed potatoes with black truffle\naccompanied by green asparagus spears and buttered baby carrots\nOriental Duck\nTender breast of duck enhanced by natural pan gravy\nJasmine rice\nChinese-style vegetables Fruit chutney\nSalmon\nFillet of salmon with a macadamia nut crust\nRed bell pepper julienne\nPapaya-mango chutney Asparagus\nPasta Bowl\nSpinach ravioli complemented by Alfredo sauce,\nwith artichoke hearts, yellow bell pepper julienne\nand diced tomatoes\nFreshly grated Parmesan cheese\nDESSERT\nHäagen-Dazs™ vanilla ice cream\noffered with your choice of toppings\nINTERNATIONAL COFFEES\nFreshly brewed\nTimothy's Custom Roasted Italian Blend Gourmet Coffee\nDecaffeinated coffee\noffered with a splash of your favorite liqueur, topped with whipped cream\nItaliano with Amaretto\nRoyal with Cognac\nFrançais with Grand Marnier\nMexican with Kahlúa\nScottish with Drambuie\nIrish with Baileys Irish Cream\nContimental Airlines"
    ],
    "millsfield:images_texts_ids": [
      1527845191
    ],
    "millsfield:primary_image": 1527845191,
    "sfomuseum:accession_number": "2006.010.822",
    "sfomuseum:airline": "Continental Airlines",
    "sfomuseum:category": "Passenger Amenity, Archive",
    "sfomuseum:collection": "Aviation Archive",
    "sfomuseum:creditline": "Gift of the William Hough Collection",
    "sfomuseum:date": "1999",
    "sfomuseum:date_acquired": "2010-08-04",
    "sfomuseum:daterange_end": "1999-12-31",
    "sfomuseum:daterange_start": "1999-01-01",
    "sfomuseum:description": "Menu issued by Continental Airlines; double-sided white card; dinner menu items include veal chop, salmon, and pasta Alfredo; menu number: 203C002-2 5140W; date: 2/99.",
    "sfomuseum:dimensions": "12 x 6 inches (30.5 x 15.2 cm)",
    "sfomuseum:media_ids": [
      1527845191
    ],
    "sfomuseum:medium": "paper, ink",
    "sfomuseum:placetype": "object",
    "sfomuseum:publication": ": , 1999.",
    "sfomuseum:subcategory": "Menu",
    "sfomuseum:subject": "Airlines -- Commercial -- Continental",
    "wof:depicts": [
      1159284201,
      1360700741
    ],
    "wof:name": "menu: Continental Airlines",
    "wof:placetype": "custom",
    "wof:placetype_alt": "object"
  },
  "geometry": {"coordinates":[-122.386155,37.616357],"type":"Point"}
}
