{
  "type": "Feature",
  "properties": {
    "date:cessation_lower":"1999-12-31",
    "date:cessation_upper":"1999-12-31",
    "date:inception_lower":"1999-01-01",
    "date:inception_upper":"1999-01-01",
    "iso:country":"XX",
    "sfomuseum:accession_number":"2006.010.822",
    "sfomuseum:category":"Food Service",
    "sfomuseum:collection":"Aviation Museum",
    "sfomuseum:creditline":"Gift of the William Hough Collection",
    "sfomuseum:date":"1999",
    "sfomuseum:daterange_end":"1999-12-31",
    "sfomuseum:daterange_start":"1999-01-01",
    "sfomuseum:description":"Menu produced by Continental Airlines; double-sided white card; dinner menu items include veal chop, salmon, and pasta Alfredo; menu number: 203C002-2 5140W; date: 2/99.",
    "sfomuseum:media_ids":[
        1527845191
    ],
    "sfomuseum:medium":"paper, ink",
    "sfomuseum:placetype":"object",
    "sfomuseum:subcategory":"Menu",
    "wof:name":"menu: Continental Airlines",
    "wof:placetype":"venue"
},
  "geometry": {"coordinates":[-122.386155,37.616358],"type":"Point"}
}