{
  "type": "Feature",
  "properties": {
    "date:cessation_lower": "1990-01-01",
    "date:cessation_upper": "1990-12-31",
    "date:inception_lower": "1990-01-01",
    "date:inception_upper": "1990-12-31",
    "isbn:number": "0679401741, 9780679401742",
    "iso:country": "XX",
    "sfomuseum:accession_number": "1999.657.131",
    "sfomuseum:author": "Barlay, Stephen",
    "sfomuseum:callnumber": "TL553.5 .B34 1990",
    "sfomuseum:category": "Book",
    "sfomuseum:collection": "Aviation Library",
    "sfomuseum:creditline": "Purchase",
    "sfomuseum:date": "c. 1990",
    "sfomuseum:date_acquired": "1995-05-25",
    "sfomuseum:daterange_end": "1995-12-31",
    "sfomuseum:daterange_start": "1985-01-01",
    "sfomuseum:description": "xv, 457 p. : ill., maps ; 25 cm.",
    "sfomuseum:description_library": "xv, 457 p. : ill., maps ; 25 cm.",
    "sfomuseum:medium": "paper, ink",
    "sfomuseum:placetype": "object",
    "sfomuseum:publication": "New York: Pantheon Books, c. 1990.",
    "sfomuseum:publisher": "Pantheon Books",
    "sfomuseum:publisher_location": "New York",
    "sfomuseum:subcategory": "Book",
    "sfomuseum:subject": "Aircraft accidents.Aircraft accidents Investigation.",
    "wof:name": "The final call: why airline disasters continue to happen",
    "wof:placetype": "custom",
    "wof:placetype_alt": "object"
  },
  "geometry": {"coordinates":[-122.386155,37.616357],"type":"Point"}
}
