{
  "type": "Feature",
  "properties": {
    "date:cessation_lower": "1988-01-01",
    "date:cessation_upper": "1988-12-31",
    "date:inception_lower": "1988-01-01",
    "date:inception_upper": "1988-12-31",
    "iso:country": "XX",
    "sfomuseum:accession_number": "2012.148.114",
    "sfomuseum:author": "Maloney, Edward T.",
    "sfomuseum:callnumber": "TL684.6 .M2 1988",
    "sfomuseum:category": "Book",
    "sfomuseum:collection": "Aviation Library",
    "sfomuseum:creditline": "Gift of the Captain John B. Russell Family",
    "sfomuseum:date": "1988",
    "sfomuseum:date_acquired": "2013-05-31",
    "sfomuseum:daterange_end": "1988-12-31",
    "sfomuseum:daterange_start": "1988-01-01",
    "sfomuseum:description": "ii, 55, [27] p. : ill., 2 fold. leaves ; 28 cm.",
    "sfomuseum:description_library": "ii, 55, [27] p. : ill., 2 fold. leaves ; 28 cm.",
    "sfomuseum:medium": "paper, ink",
    "sfomuseum:placetype": "object",
    "sfomuseum:publication": "Corona Del Mar, CA: World War II publications, 1988.",
    "sfomuseum:publisher": "World War II publications",
    "sfomuseum:publisher_location": "Corona Del Mar, CA",
    "sfomuseum:subcategory": "Book",
    "sfomuseum:subject": "Airplanes, Tailless -- Design and construction. ",
    "wof:name": "Northrop flying wings",
    "wof:placetype": "custom",
    "wof:placetype_alt": "object"
  },
  "geometry": {"coordinates":[-122.386155,37.616357],"type":"Point"}
}
