{
  "type": "Feature",
  "properties": {
    "date:cessation_lower": "1988-01-01",
    "date:cessation_upper": "1988-12-31",
    "date:inception_lower": "1988-01-01",
    "date:inception_upper": "1988-12-31",
    "isbn:number": "3613012243, 9783613012240",
    "iso:country": "XX",
    "sfomuseum:accession_number": "2006.023.101",
    "sfomuseum:author": "Nowarra, Heinz J.",
    "sfomuseum:callnumber": "TL686.J8 N68 1988",
    "sfomuseum:category": "Book",
    "sfomuseum:collection": "Aviation Library",
    "sfomuseum:creditline": "Gift of the collection of Frank J. Lichtanski",
    "sfomuseum:date": "1988",
    "sfomuseum:date_acquired": "2006-08-03",
    "sfomuseum:daterange_end": "1988-12-31",
    "sfomuseum:daterange_start": "1988-01-01",
    "sfomuseum:description": "158 p. : ill. ; 25 cm.",
    "sfomuseum:description_library": "158 p. : ill. ; 25 cm.",
    "sfomuseum:medium": "paper, ink",
    "sfomuseum:placetype": "object",
    "sfomuseum:publication": "Stuttgart, Germany: Motorbuch Verlag, 1988.",
    "sfomuseum:publisher": "Motorbuch Verlag",
    "sfomuseum:publisher_location": "Stuttgart, Germany",
    "sfomuseum:subcategory": "Book",
    "sfomuseum:subject": "Junkers airplanes History.",
    "wof:name": "Junkers Grossflugzeuge: Geschichte und Technik",
    "wof:placetype": "custom",
    "wof:placetype_alt": "object"
  },
  "geometry": {"coordinates":[-122.386155,37.616357],"type":"Point"}
}
