{
  "type": "Feature",
  "properties": {
    "date:cessation_lower": "1949-11-18",
    "date:cessation_upper": "1949-11-18",
    "date:inception_lower": "1949-11-18",
    "date:inception_upper": "1949-11-18",
    "iso:country": "XX",
    "millsfield:images": [
      1527834383,
      1527834385
    ],
    "millsfield:primary_image": 1527834383,
    "sfomuseum:accession_number": "2012.149.1683",
    "sfomuseum:category": "Philately",
    "sfomuseum:collection": "Aviation Archive",
    "sfomuseum:creditline": "Gift of the Captain John B. Russell Family",
    "sfomuseum:date": "11/18/1949",
    "sfomuseum:daterange_end": "1949-11-18",
    "sfomuseum:daterange_start": "1949-11-18",
    "sfomuseum:description": "Airmail flight cover, United States Air Mail, First Day of Issue series, commemorating first day of issue for 6-cent air mail stamp booklet pane; engraved cachet at left depicting city skyline; postmarked November 18, 1949 in New York with “First Day of Issue” cancellation mark over six 6-cent postage stamps; addressed to Oscar H. Fatout.",
    "sfomuseum:dimensions": "3 1/2 x 6 1/2 inches (8.9 x 16.5 cm)",
    "sfomuseum:media_ids": [
      1527834383,
      1527834385
    ],
    "sfomuseum:medium": "paper, ink",
    "sfomuseum:placetype": "object",
    "sfomuseum:subcategory": "Airmail Flight Cover",
    "wof:name": "airmail flight cover: United States Air Mail",
    "wof:placetype": "venue"
  },
  "geometry": {"coordinates":[-122.386155,37.616357],"type":"Point"}
}
