{
  "type": "Feature",
  "properties": {
    "date:cessation_lower": "1999-01-01",
    "date:cessation_upper": "1999-12-31",
    "date:inception_lower": "1999-01-01",
    "date:inception_upper": "1999-12-31",
    "iso:country": "XX",
    "sfomuseum:accession_number": "2003.039.005",
    "sfomuseum:author": "Melberg, William F.",
    "sfomuseum:callnumber": "TL685.7 .M4497 1999",
    "sfomuseum:category": "Book",
    "sfomuseum:collection": "Aviation Library",
    "sfomuseum:creditline": "Gift of Thomas G. Dragges",
    "sfomuseum:date": "c. 1999",
    "sfomuseum:daterange_end": "2004-12-31",
    "sfomuseum:daterange_start": "1994-01-01",
    "sfomuseum:description": "xi, 229 p. : ill. (some col.) ; 26 cm.",
    "sfomuseum:medium": "paper, ink",
    "sfomuseum:placetype": "object",
    "sfomuseum:publisher": "Plymouth Press",
    "sfomuseum:publisher_location": "Vergennes, VT",
    "sfomuseum:subcategory": "Book",
    "sfomuseum:subject": "Transport planes History.",
    "wof:name": "Famous airliners: from biplane to jetliner: the story of travel by air",
    "wof:placetype": "custom"
  },
  "geometry": {"coordinates":[-122.386155,37.616357],"type":"Point"}
}
