{
  "type": "Feature",
  "properties": {
    "date:cessation_lower": "1943-12-31",
    "date:cessation_upper": "1943-12-31",
    "date:inception_lower": "1933-01-01",
    "date:inception_upper": "1933-01-01",
    "iso:country": "XX",
    "millsfield:images": [
      1527830435
    ],
    "sfomuseum:accession_number": "2005.062.010 a",
    "sfomuseum:aircraft": "Douglas DC-3",
    "sfomuseum:airline": "Transcontinental \u0026 Western Air  (TWA (Trans World Airlines))",
    "sfomuseum:airport": "San Francisco International Airport",
    "sfomuseum:artist": "Charles C. Loomis",
    "sfomuseum:category": "Photograph",
    "sfomuseum:collection": "Aviation Archive",
    "sfomuseum:creditline": "Gift of Charles Loomis",
    "sfomuseum:date": "c. 1938",
    "sfomuseum:daterange_end": "1943-12-31",
    "sfomuseum:daterange_start": "1933-01-01",
    "sfomuseum:description": "Black and white photograph depicting distant view of San Francisco Airport Administration Building and control tower through cockpit windshield of Douglas DC-3; view facing north toward San Bruno Mountain; photographed by Charles C. Loomis.\ra. Black and white print.\rb. Negative.",
    "sfomuseum:media_ids": [
      1527830435
    ],
    "sfomuseum:medium": "photograph",
    "sfomuseum:placetype": "object",
    "sfomuseum:subcategory": "Print, Photograph",
    "wof:depicts": [
      1159290417,
      1159285395,
      102527513
    ],
    "wof:name": "photograph: Transcontinental \u0026 Western Air (TWA), Douglas DC-3",
    "wof:placetype": "venue"
  },
  "geometry": {"coordinates":[-122.386155,37.616357],"type":"Point"}
}
