{
  "type": "Feature",
  "properties": {
    "date:cessation_lower": "1953-01-01",
    "date:cessation_upper": "1953-12-31",
    "date:inception_lower": "1953-01-01",
    "date:inception_upper": "1953-12-31",
    "iso:country": "XX",
    "millsfield:images": [
      1527836413
    ],
    "millsfield:primary_image": 1527836413,
    "sfomuseum:accession_number": "2001.106.341",
    "sfomuseum:aircraft": "Convair 340 Convair-Liner",
    "sfomuseum:airline": "Continental Air Lines",
    "sfomuseum:category": "Scheduling / Ticketing",
    "sfomuseum:collection": "Aviation Archive",
    "sfomuseum:creditline": "Gift of Mark F. Adams Collection",
    "sfomuseum:date": "1953",
    "sfomuseum:date_acquired": "2001-10-18",
    "sfomuseum:daterange_end": "1953-12-31",
    "sfomuseum:daterange_start": "1953-01-01",
    "sfomuseum:description": "Timetable issued by Continental Air Lines, effective January 5, 1953; white and blue cover with drawing of aircraft; promotes Super Convair 340 service.",
    "sfomuseum:dimensions": "8 3/4 x 3 3/4 inches (22.2 x 9.5 cm)",
    "sfomuseum:issues_held": "Effective: 1-05-1953",
    "sfomuseum:media_ids": [
      1527836413
    ],
    "sfomuseum:medium": "paper, ink",
    "sfomuseum:placetype": "object",
    "sfomuseum:publication": ": , 1953.",
    "sfomuseum:subcategory": "Timetable",
    "wof:depicts": [
      1159290199,
      1159284203
    ],
    "wof:name": "timetable: Continental Air Lines",
    "wof:placetype": "venue"
  },
  "geometry": {"coordinates":[-122.386155,37.616357],"type":"Point"}
}
