{
  "type": "Feature",
  "properties": {
    "date:cessation_lower": "1982-01-01",
    "date:cessation_upper": "1982-12-31",
    "date:inception_lower": "1982-01-01",
    "date:inception_upper": "1982-12-31",
    "iso:country": "XX",
    "millsfield:images": [
      1527843319
    ],
    "millsfield:images_texts": [
      "•Air\nTIME\nTABLE\nApril 1 to October 31, 1982\nThe tomb of Zhuyuanzhang Founder of the Ming Dynasty\nCAAC\nCIVIL AVIATION ADMINISTRATION OF CHINA"
    ],
    "millsfield:images_texts_ids": [
      1527843319
    ],
    "millsfield:primary_image": 1527843319,
    "sfomuseum:accession_number": "2009.122.245",
    "sfomuseum:airline": "CAAC (Civil Aviation Administration of China)",
    "sfomuseum:category": "Scheduling / Ticketing",
    "sfomuseum:collection": "Aviation Archive",
    "sfomuseum:creditline": "Gift of the William Hough Collection",
    "sfomuseum:date": "1982",
    "sfomuseum:date_acquired": "2010-06-08",
    "sfomuseum:daterange_end": "1982-12-31",
    "sfomuseum:daterange_start": "1982-01-01",
    "sfomuseum:description": "Timetable issued by CAAC (Civil Aviation Administration of China), effective April 1 through October 31, 1982; four-page double-sided fold-out; white and blue cover with color photographic image of the entryway to the tomb of Zhuyauanzhang, founder of the Ming Dynasty; in Chinese and English.",
    "sfomuseum:dimensions": "5 1/2 x 3 inches (14 x 7.6 cm)",
    "sfomuseum:media_ids": [
      1527843319
    ],
    "sfomuseum:medium": "paper, ink",
    "sfomuseum:placetype": "object",
    "sfomuseum:publication": ": , 1982.",
    "sfomuseum:subcategory": "Timetable",
    "sfomuseum:subject": "Airlines -- Commercial -- CAAC\rAirlines -- timetables",
    "wof:depicts": [
      1159286763,
      1159284059
    ],
    "wof:name": "timetable: CAAC (Civil Aviation Administration of China)",
    "wof:placetype": "custom",
    "wof:placetype_alt": "object"
  },
  "geometry": {"coordinates":[-122.386155,37.616357],"type":"Point"}
}
