{
  "type": "Feature",
  "properties": {
    "date:cessation_lower": "1968-12-31",
    "date:cessation_upper": "1968-12-31",
    "date:inception_lower": "1968-01-01",
    "date:inception_upper": "1968-01-01",
    "iso:country": "XX",
    "sfomuseum:accession_number": "2011.032.1881",
    "sfomuseum:category": "Photograph",
    "sfomuseum:collection": "Aviation Archive",
    "sfomuseum:creditline": "Transfer",
    "sfomuseum:date": "1968",
    "sfomuseum:daterange_end": "1968-12-31",
    "sfomuseum:daterange_start": "1968-01-01",
    "sfomuseum:description": "From attached handwritten note: “5-18-68 / Soil stability / TWA apron”. Black and white photographic print depicting construction at San Francisco International Airport (SFO); deep trench with large pipe; Atlantic Richfield Company; airside view of airport buildings and airplanes in background; photograph taken in May 18, 1968.",
    "sfomuseum:media_ids": [
      1527826551
    ],
    "sfomuseum:medium": "photograph",
    "sfomuseum:placetype": "object",
    "sfomuseum:subcategory": "Print, Photograph",
    "wof:name": "photograph: San Francisco International Airport (SFO), pipeline construction",
    "wof:placetype": "venue"
  },
  "geometry": {"coordinates":[-122.386155,37.616358],"type":"Point"}
}
