{
  "type": "Feature",
  "properties": {
    "date:cessation_lower": "1999-12-31",
    "date:cessation_upper": "1999-12-31",
    "date:inception_lower": "1990-01-01",
    "date:inception_upper": "1990-01-01",
    "iso:country": "XX",
    "sfomuseum:accession_number": "1998.157.155",
    "sfomuseum:category": "Passenger Amenity",
    "sfomuseum:collection": "Aviation Museum",
    "sfomuseum:creditline": "Gift of The Henry Steiner Air Sickness Bag Collection",
    "sfomuseum:date": "1990s",
    "sfomuseum:daterange_end": "1999-12-31",
    "sfomuseum:daterange_start": "1990-01-01",
    "sfomuseum:description": "Flat bottom, no closure. Brown bag, white print. \"Lufthansa\" in white on lower left corner. Design on both sides.",
    "sfomuseum:media_ids": [
      1527824531, 
      1527824533
    ],
    "sfomuseum:medium": "paper",
    "sfomuseum:placetype": "object",
    "sfomuseum:subcategory": "Airsickness Bag",
    "wof:name": "airsickness bag: Lufthansa",
    "wof:placetype": "venue"
  },
  "geometry": {"coordinates":[-122.386155,37.616358],"type":"Point"}
}
