{
  "type": "Feature",
  "properties": {
    "date:cessation_lower": "1973-01-01",
    "date:cessation_upper": "1973-12-31",
    "date:inception_lower": "1973-01-01",
    "date:inception_upper": "1973-12-31",
    "iso:country": "XX",
    "millsfield:images": [
      1527828443
    ],
    "millsfield:primary_image": 1527828443,
    "sfomuseum:accession_number": "2011.032.2728",
    "sfomuseum:airport": "San Francisco International Airport",
    "sfomuseum:category": "Photograph",
    "sfomuseum:collection": "Aviation Archive",
    "sfomuseum:creditline": "Transfer from San Francisco International Airport",
    "sfomuseum:date": "1973",
    "sfomuseum:date_acquired": "2011-03-02",
    "sfomuseum:daterange_end": "1973-12-31",
    "sfomuseum:daterange_start": "1973-01-01",
    "sfomuseum:description": "Color photographic negative depicting dedication of SFO Medical Clinic, San Francisco International Airport (SFO), October 25, 1973; view of doorway before ribbon-cutting ceremony.",
    "sfomuseum:dimensions": "1 x 1 1/2 inches (2.5 x 3.8 cm)",
    "sfomuseum:media_ids": [
      1527828443
    ],
    "sfomuseum:medium": "negative",
    "sfomuseum:placetype": "object",
    "sfomuseum:publication": ": , 1973.",
    "sfomuseum:subcategory": "Negative",
    "wof:depicts": [
      102527513
    ],
    "wof:name": "negative: San Francisco International Airport (SFO), medical clinic",
    "wof:placetype": "custom",
    "wof:placetype_alt": "object"
  },
  "geometry": {"coordinates":[-122.386155,37.616357],"type":"Point"}
}
