{
  "type": "Feature",
  "properties": {
    "date:cessation_lower": "1994-01-01",
    "date:cessation_upper": "1994-12-31",
    "date:inception_lower": "1994-01-01",
    "date:inception_upper": "1994-12-31",
    "iso:country": "XX",
    "millsfield:images": [
      1527844789
    ],
    "millsfield:images_texts": [
      "VIETNAM AIRLINES\nA GOOD CHOICE FOR YOUR FASCINATING TRIP\nProudly announces direct flights\nBERLIN / VIETNAM / BERLIN\nEFFECTIVE 02 JULY 1994 TO 24 SEPTEMBER 1994\nTO HO CHI MINH\nDAY\nFLT NBR\nDEP\nWED\nSAT\nVN531\nVN531\n0905\n0905\nARR\n0735*\n0735*\nVIA\nCDG/DXB\nCDG/DXB\nDAY\nFLT NBR\nTUE\nFRI\nVN531\nVN531\nFROM HO CHI MINH\nDEP\nARR\n2130\n0740*\n2130\n0740*\nVIA\nDXB\nDXB\nTO HANOI\nDAY\nFLT NBR\nDEP\nWED\nSAT\nVN531\nVN531\n0905\n0905\nARR\n1035*\n1035*\nVIA\nCDG/DXB/SGN\nCDG/DXB/SGN\nDAY\nFLT NBR\nTUE\nFRI\nVN531\nVN531\nDEP\n1800\n1800\nFROM HANOI\nARR\nVIA\n0740*\n0740*\nSGN/DXB\nSGN/DXB\nEFFECTIVE 25 SEPTEMBER TO 27 OCTOBER 1994\nTO HO CHI MINH\nDAY\nFLT NBR\nDEP\nWED\nSAT\nVN531\nVN531\n0805\n0805\nARR\nVIA\n0735*\n0735*\nCDG/DXB\nCDG/DXB\nDAY FLT NBR\nTUE\nVN531\nFRI\nVN531\nFROM HO CHI MINH\nDEP\nARR\nVIA\n2130\n0640*\n2130\n0640*\nDXB\nDXB\nTO HANOI\nDAY\nFLT NBR\nWED\nVN531\nSAT\nVN531\nDEP\n0805\n0805\nARR\n1035*\n1035*\nVIA\nCDG/DXB/SGN\nCDG/DXB/SGN\nDAY\nTUE\nFRI\nFLT NBR\nVN531\nVN531\nDEP\n1800\n1800\nFROM HANOI\nARR\nVIA\n0640*\nSGN/DXB\n0640*\nSGN/DXB\nJETAIR DEUTSCHLAND GMBH\nDUSSELDORF\nLIESEGANGSTRASSE 18\n40211 DUSSELDORF\nTELEPHONE:\n0211-361 3051\nFAX:\n0211-164 9386\nFRANKFURT\nKAISERSTRASSE 72\n60329 FRANKFURT/MAIN 1\nTELEPHONE:\n069-25 27 29\nFAX:\n069-25 36 03\nMUNICH\nLINDWURMSTRASSE 3\n80337 MUNICH\nTELEPHONE:\n089-268001\nFAX:\n089-267274\nALL TIMINGS ARE SUBJECT TO CHANGE WITHOUT NOTICE"
    ],
    "millsfield:images_texts_ids": [
      1527844789
    ],
    "millsfield:primary_image": 1527844789,
    "sfomuseum:accession_number": "2011.061.0420",
    "sfomuseum:airline": "Vietnam Airlines",
    "sfomuseum:category": "Scheduling / Ticketing",
    "sfomuseum:collection": "Aviation Archive",
    "sfomuseum:creditline": "Gift of the Frank J. Lichtanski Collection",
    "sfomuseum:date": "1994",
    "sfomuseum:date_acquired": "2011-08-02",
    "sfomuseum:daterange_end": "1994-12-31",
    "sfomuseum:daterange_start": "1994-01-01",
    "sfomuseum:description": "Photocopy of timetable issued by Vietnam Airlines, effective July 2 - October 27, 1994; single-sided sheet with schedules for flights from Hanoi and Ho Chi Minh to Berlin.",
    "sfomuseum:dimensions": "11 x 8 1/2 inches (27.9 x 21.6 cm)",
    "sfomuseum:media_ids": [
      1527844789
    ],
    "sfomuseum:medium": "paper, ink",
    "sfomuseum:placetype": "object",
    "sfomuseum:publication": ": , 1994.",
    "sfomuseum:subcategory": "Timetable",
    "wof:depicts": [
      1159286777,
      1159285479
    ],
    "wof:name": "timetable: Vietnam Airlines",
    "wof:placetype": "custom",
    "wof:placetype_alt": "object"
  },
  "geometry": {"coordinates":[-122.386155,37.616357],"type":"Point"}
}
