{
  "type": "Feature",
  "properties": {
    "date:cessation_lower": "1964-12-31",
    "date:cessation_upper": "1964-12-31",
    "date:inception_lower": "1964-01-01",
    "date:inception_upper": "1964-01-01",
    "iso:country": "XX",
    "sfomuseum:accession_number": "2005.132.038.004",
    "sfomuseum:category": "Scheduling / Ticketing",
    "sfomuseum:collection": "Aviation Archive",
    "sfomuseum:creditline": "Gift of the William Hough Collection",
    "sfomuseum:date": "1964",
    "sfomuseum:daterange_end": "1964-12-31",
    "sfomuseum:daterange_start": "1964-01-01",
    "sfomuseum:description": "Timetable issued by Pacific Air Lines, effective January 10, 1964. The cover is blue, red, and white. The company name is at the top on the blue field and servicemark is at the bottom on a blue field. In the center is a listing of 6-day excursion fares.",
    "sfomuseum:media_ids": [
      1527839161
    ],
    "sfomuseum:medium": "paper, ink",
    "sfomuseum:placetype": "object",
    "sfomuseum:subcategory": "Timetable",
    "wof:name": "timetable: Pacific Air Lines",
    "wof:placetype": "venue"
  },
  "geometry": {"coordinates":[-122.386155,37.616358],"type":"Point"}
}
