{
  "type": "Feature",
  "properties": {
    "date:cessation_lower": "2001-01-01",
    "date:cessation_upper": "2001-12-31",
    "date:inception_lower": "2001-01-01",
    "date:inception_upper": "2001-12-31",
    "iso:country": "XX",
    "sfomuseum:accession_number": "2009.067.009",
    "sfomuseum:author": "Jamieson, C. H",
    "sfomuseum:callnumber": "HD8039.A42 U537 2001",
    "sfomuseum:category": "Book",
    "sfomuseum:collection": "Aviation Library",
    "sfomuseum:creditline": "Purchase",
    "sfomuseum:date": "2001",
    "sfomuseum:daterange_end": "2001-12-31",
    "sfomuseum:daterange_start": "2001-01-01",
    "sfomuseum:description": "314 p. ; 22 cm.",
    "sfomuseum:medium": "paper, ink",
    "sfomuseum:placetype": "object",
    "sfomuseum:publisher": "Xilibris Corp.",
    "sfomuseum:publisher_location": "Philadelphia, PA",
    "sfomuseum:subcategory": "Book",
    "sfomuseum:subject": "Air pilots -- United States -- History -- 20th century. ",
    "wof:name": "On top of the clouds: the story of an airmail pilot",
    "wof:placetype": "venue"
  },
  "geometry": {"coordinates":[-122.386155,37.616357],"type":"Point"}
}
