{
  "type": "Feature",
  "properties": {
    "date:cessation_lower": "1979-12-31",
    "date:cessation_upper": "1979-12-31",
    "date:inception_lower": "1970-01-01",
    "date:inception_upper": "1970-01-01",
    "iso:country": "XX",
    "millsfield:images": [
      1527823379,
      1527823375
    ],
    "sfomuseum:accession_number": "1998.157.011",
    "sfomuseum:airline": "Air Florida",
    "sfomuseum:category": "Passenger Amenity",
    "sfomuseum:collection": "Aviation Museum",
    "sfomuseum:creditline": "Gift of The Henry Steiner Air Sickness Bag Collection",
    "sfomuseum:date": "1970s",
    "sfomuseum:daterange_end": "1979-12-31",
    "sfomuseum:daterange_start": "1970-01-01",
    "sfomuseum:description": "Box bottom, wire closure. Blue and green bag, white print. \"Air Florida\" in white print, diagonally across lower portion of bag, logo in white on upper portion of bag.",
    "sfomuseum:media_ids": [
      1527823375,
      1527823379
    ],
    "sfomuseum:medium": "paper",
    "sfomuseum:placetype": "object",
    "sfomuseum:subcategory": "Airsickness Bag",
    "wof:depicts": [
      1159283623
    ],
    "wof:name": "airsickness bag: Air Florida",
    "wof:placetype": "venue"
  },
  "geometry": {"coordinates":[-122.386155,37.616357],"type":"Point"}
}
