{
  "type": "Feature",
  "properties": {
    "date:cessation_lower": "1953-01-01",
    "date:cessation_upper": "1953-12-31",
    "date:inception_lower": "1953-01-01",
    "date:inception_upper": "1953-12-31",
    "iso:country": "XX",
    "millsfield:images": [
      1527850307,
      1527841929
    ],
    "millsfield:primary_image": 1527841929,
    "sfomuseum:accession_number": "2001.038.118",
    "sfomuseum:airline": "Pan American World Airways",
    "sfomuseum:category": "Scheduling / Ticketing",
    "sfomuseum:collection": "Aviation Archive",
    "sfomuseum:continent": "World Routes",
    "sfomuseum:creditline": "Gift of Barnaby Conrad III",
    "sfomuseum:date": "1953",
    "sfomuseum:daterange_end": "1953-12-31",
    "sfomuseum:daterange_start": "1953-01-01",
    "sfomuseum:description": "Pacific-Alaska timetable issued by Pan American World Airways, effective January 1 through February 28, 1953; blue and gray cover with winged globe logo. ",
    "sfomuseum:dimensions": "Measured folded. ",
    "sfomuseum:media_ids": [
      1527850307,
      1527841929
    ],
    "sfomuseum:medium": "paper, ink",
    "sfomuseum:placetype": "object",
    "sfomuseum:subcategory": "Timetable",
    "wof:depicts": [
      1159284989
    ],
    "wof:name": "timetable: Pan American World Airways",
    "wof:placetype": "venue"
  },
  "geometry": {"coordinates":[-122.386155,37.616357],"type":"Point"}
}
