{
  "type": "Feature",
  "properties": {
    "date:cessation_lower": "1966-01-01",
    "date:cessation_upper": "1966-12-31",
    "date:inception_lower": "1966-01-01",
    "date:inception_upper": "1966-12-31",
    "iso:country": "XX",
    "loc:subject_headings": [
      "sh85066764"
    ],
    "sfomuseum:accession_number": "2015.156.001",
    "sfomuseum:author": "United States. Department of Transportation. Federal Aviation Administration",
    "sfomuseum:callnumber": "TL546.5.U52 I6 1966",
    "sfomuseum:category": "Book",
    "sfomuseum:collection": "Aviation Library",
    "sfomuseum:creditline": "Gift of John Achor",
    "sfomuseum:date": "1966",
    "sfomuseum:date_acquired": "2015-12-15",
    "sfomuseum:daterange_end": "1966-12-31",
    "sfomuseum:daterange_start": "1966-01-01",
    "sfomuseum:description_library": "226 p. ; 26 cm.",
    "sfomuseum:medium": "paper, ink",
    "sfomuseum:placetype": "object",
    "sfomuseum:publication": "Washington, D.C.: Federal Aviation Administration, 1966.",
    "sfomuseum:publisher": "Federal Aviation Administration",
    "sfomuseum:publisher_location": "Washington, D.C.",
    "sfomuseum:subcategory": "Book",
    "sfomuseum:subject": "Instrument flying -- Handbooks, manuals, etc. \rInstrument flying. ",
    "wof:name": "Instrument flying handbook",
    "wof:placetype": "custom",
    "wof:placetype_alt": [
      "object"
    ]
  },
  "geometry": {"coordinates":[-122.386155,37.616357],"type":"Point"}
}
