{
  "type": "Feature",
  "properties": {
    "date:cessation_lower": "1999-01-01",
    "date:cessation_upper": "1999-12-31",
    "date:inception_lower": "1999-01-01",
    "date:inception_upper": "1999-12-31",
    "iso:country": "XX",
    "sfomuseum:accession_number": "2001.082.267",
    "sfomuseum:author": "Hooks, M. J.",
    "sfomuseum:callnumber": "TL670.3 .H66 1999 c.1",
    "sfomuseum:category": "Book",
    "sfomuseum:collection": "Aviation Library",
    "sfomuseum:creditline": "Gift of George Gayuski ",
    "sfomuseum:date": "c. 1999",
    "sfomuseum:date_acquired": "2001-12-18",
    "sfomuseum:daterange_end": "2004-12-31",
    "sfomuseum:daterange_start": "1994-01-01",
    "sfomuseum:description": "120 p. : col. ill. ; 21 x 27 cm.",
    "sfomuseum:description_library": "120 p. : col. ill. ; 21 x 27 cm.",
    "sfomuseum:medium": "paper, ink",
    "sfomuseum:placetype": "object",
    "sfomuseum:publication": "Sandpoint, ID: Airways International, c. 1999.",
    "sfomuseum:publisher": "Airways International",
    "sfomuseum:publisher_location": "Sandpoint, ID",
    "sfomuseum:series": "InCamera ; 3",
    "sfomuseum:subcategory": "Book",
    "sfomuseum:subject": "Aeronautics, Commercial History Pictorial works.Airplanes History Pictorial works.",
    "wof:name": "Classic props",
    "wof:placetype": "venue"
  },
  "geometry": {"coordinates":[-122.386155,37.616357],"type":"Point"}
}
