{
  "type": "Feature",
  "properties": {
    "date:cessation_lower": "1930-01-01",
    "date:cessation_upper": "1930-12-31",
    "date:inception_lower": "1930-01-01",
    "date:inception_upper": "1930-12-31",
    "iso:country": "XX",
    "loc:subject_headings": [
      "sh85001336",
      "sh85092525"
    ],
    "sfomuseum:accession_number": "99-1330",
    "sfomuseum:author": "Putnam, George Palmer",
    "sfomuseum:callnumber": "TL540.A5 P8 1930 c.1 SC",
    "sfomuseum:category": "Book",
    "sfomuseum:collection": "Aviation Library",
    "sfomuseum:creditline": "Collection of SFO Museum",
    "sfomuseum:date": "1930",
    "sfomuseum:daterange_end": "1930-12-31",
    "sfomuseum:daterange_start": "1930-01-01",
    "sfomuseum:description": "6 p. æ., 11-239, [1] p. front., illus. (map) plates, ports. 21 cm.\r",
    "sfomuseum:description_library": "6 p. æ., 11-239, [1] p. front., illus. (map) plates, ports. 21 cm.\r",
    "sfomuseum:medium": "paper, ink",
    "sfomuseum:placetype": "object",
    "sfomuseum:publication": "New York: Brewer \u0026 Warren, 1930.",
    "sfomuseum:publisher": "Brewer \u0026 Warren",
    "sfomuseum:publisher_location": "New York",
    "sfomuseum:subcategory": "Book",
    "sfomuseum:subject": "Andree, Salomon August, b. 1854.\rAeronautics--Flights.\rNorth Pole.",
    "wof:name": "Andree: the record of a tragic adventure",
    "wof:placetype": "custom",
    "wof:placetype_alt": [
      "object"
    ]
  },
  "geometry": {"coordinates":[-122.386155,37.616357],"type":"Point"}
}
