{
  "type": "Feature",
  "properties": {
    "date:cessation_lower": "1940-07-21",
    "date:cessation_upper": "1940-07-21",
    "date:inception_lower": "1940-07-21",
    "date:inception_upper": "1940-07-21",
    "iso:country": "XX",
    "millsfield:images": [
      1527832587,
      1527832589
    ],
    "millsfield:images_texts": [
      "10%\n* are this cachet\nnot listed AAMC\nCU X\n148-174\n2012.144 178",
      "TED NOUVELLE-CALEDONIES\nU POSTES\nPAN AMERICAN AIRWAYS SYSTEM\n185 EAST 42nd STREET, NEW YORK Cm\"\nNoumea, N. C. - Los Angeles\nPOSTE AÉRIENNE\n1ERE TRAVERSÉE\nSAN FRANCISCO\n10 NOUVELLE CALEDONIE RF\nJUIL\nVIAFAIR MAIL\npar\nDAN AMERICAN\nCLIPPER\nHONOLULU\nCANTON\nISLAND\nCuES\nNOUMEA\nENTRE\nNOUVELLE - CALÉDONIE\nET ETATS UNIS\nMr. William Van Dusen\n135 East 42 Street\nNew York City\n53 COURRIED\nPIN AMERICAN ASSES"
    ],
    "millsfield:images_texts_ids": [
      1527832587,
      1527832589
    ],
    "millsfield:primary_image": 1527832589,
    "sfomuseum:accession_number": "2012.149.1781",
    "sfomuseum:airline": "Pan American Airways",
    "sfomuseum:category": "Philately",
    "sfomuseum:collection": "Aviation Archive",
    "sfomuseum:creditline": "Gift of the Captain John B. Russell Family",
    "sfomuseum:date": "07/21/1940",
    "sfomuseum:date_acquired": "2013-05-31",
    "sfomuseum:daterange_end": "1940-07-21",
    "sfomuseum:daterange_start": "1940-07-21",
    "sfomuseum:description": "Airmail flight cover, Pan American Airways, Noumea - Los Angeles route; part of first airmail service between United States and New Zealand; green cachet at left, “Poste Aerienne 1ere Traversee” with illustration of flying boat on route trajectory; postmarked July 21, 1940 in Noumea, New Caldonia with three postage stamps; backstamp: July 24, 1940 in Los Angeles; addressed to William Van Dusen.",
    "sfomuseum:dimensions": "4 1/4 x 9 1/4 inches (10.8 x 23.5 cm)",
    "sfomuseum:media_ids": [
      1527832587,
      1527832589
    ],
    "sfomuseum:medium": "paper, ink",
    "sfomuseum:placetype": "object",
    "sfomuseum:publication": ": , 07/21/1940.",
    "sfomuseum:subcategory": "Airmail Flight Cover",
    "wof:depicts": [
      1159284991,
      1159286839
    ],
    "wof:name": "airmail flight cover: Pan American Airways, first airmail flight, Noumea (New Caledonia) - Los Angeles route",
    "wof:placetype": "custom",
    "wof:placetype_alt": "object"
  },
  "geometry": {"coordinates":[-122.386155,37.616357],"type":"Point"}
}
