{
  "type": "Feature",
  "properties": {
    "date:cessation_lower": "1939-05-26",
    "date:cessation_upper": "1939-05-26",
    "date:inception_lower": "1939-05-26",
    "date:inception_upper": "1939-05-26",
    "iso:country": "XX",
    "millsfield:images": [
      1527852109,
      1527852111
    ],
    "millsfield:images_texts": [
      "FIRST FLIGHT\nAZORES TO NEW YORK\nVIA CLIPPER AIRMAIL\nCORREIO\nAEREO\nMOVE YORK\nF-16-3\nCORRELL DO\nORTUGAL\n5\n$\nPORTUGAL\nCORREIO\nAEREO\nOR\nCORREIO AEREO I $ 75\nMr. Raymond E. Yaeck\n621 E. Wishart Street\nPhiladelphia, Penna.",
      "from\nTHOMAS F. WHITBREAD\nOn the Berkshire Trail\nWEST CUMMINGTON, MASS.\n5 685L\n1\nW012.149. 223\\a"
    ],
    "millsfield:images_texts_ids": [
      1527852109,
      1527852111
    ],
    "millsfield:primary_image": 1527852109,
    "sfomuseum:accession_number": "2012.149.2231 a b",
    "sfomuseum:airline": "Pan American Airways",
    "sfomuseum:category": "Philately",
    "sfomuseum:collection": "Aviation Archive",
    "sfomuseum:creditline": "Gift of the Captain John B. Russell Family",
    "sfomuseum:date": "05/26/1939",
    "sfomuseum:date_acquired": "2013-05-31",
    "sfomuseum:daterange_end": "1939-05-26",
    "sfomuseum:daterange_start": "1939-05-26",
    "sfomuseum:description": "a. Airmail flight cover, Pan American Airways, first Clipper flight, FAM-18, Horta - New York route; blue stamped cachet with image of airplane over map of north Atlantic at left; postmarked May 26, 1939 in Horta with three stamps; backstamp: May 27, 1939 in New York; printed in red and blue ink at top left corner, “First flight Azores to New York via Clipper airmail”.\rb. Backing sheet with two sets of black backing and mounting corners, with typewritten caption: “F18-3 Horta - New York; May 26, 1939 - arrived May 27, 1939; pilot - Arthur E. LaPorte”. Note: upper mounting set empty upon receipt.",
    "sfomuseum:dimensions": "3 3/4 x 6 1/2 inches (9.5 x 16.5 cm)",
    "sfomuseum:media_ids": [
      1527852109,
      1527852111
    ],
    "sfomuseum:medium": "paper, ink",
    "sfomuseum:placetype": "object",
    "sfomuseum:publication": ": , 05/26/1939.",
    "sfomuseum:subcategory": "Airmail Flight Cover",
    "sfomuseum:subject": "Airlines -- Commercial -- Pan American Airways.",
    "wof:depicts": [
      1159284991,
      1159286839
    ],
    "wof:name": "airmail flight cover: Pan American Airways, FAM-18, first airmail flight, Horta - New York route",
    "wof:placetype": "custom",
    "wof:placetype_alt": "object"
  },
  "geometry": {"coordinates":[-122.386155,37.616357],"type":"Point"}
}
