{
  "type": "Feature",
  "properties": {
    "date:cessation_lower": "1966-01-01",
    "date:cessation_upper": "1966-12-31",
    "date:inception_lower": "1966-01-01",
    "date:inception_upper": "1966-12-31",
    "iso:country": "XX",
    "loc:subject_headings": [
      "sh2002009824"
    ],
    "sfomuseum:accession_number": "2011.138.042",
    "sfomuseum:author": "Francillon, René J.",
    "sfomuseum:callnumber": "UG1242.F5 P6 no.70",
    "sfomuseum:category": "Book",
    "sfomuseum:collection": "Aviation Library",
    "sfomuseum:creditline": "Gift of Helene and Rudy Stahl",
    "sfomuseum:date": "1966",
    "sfomuseum:date_acquired": "2012-03-29",
    "sfomuseum:daterange_end": "1966-12-31",
    "sfomuseum:daterange_start": "1966-01-01",
    "sfomuseum:description": "10, [2] p. : ill. (some col.) ; 24 cm.",
    "sfomuseum:description_library": "10, [2] p. : ill. (some col.) ; 24 cm.",
    "sfomuseum:medium": "paper, ink",
    "sfomuseum:placetype": "object",
    "sfomuseum:publication": "Leatherhead, Surrey, England: Profile Publications, 1966.",
    "sfomuseum:publisher": "Profile Publications",
    "sfomuseum:publisher_location": "Leatherhead, Surrey, England",
    "sfomuseum:series": "Profile publications ; no. 70",
    "sfomuseum:subcategory": "Book",
    "sfomuseum:subject": "Hayate (Fighter planes) \rAirplanes, Military -- Japan. \rWorld War, 1939-1945 -- Aerial operations, Japanese.",
    "wof:name": "Nakajima Ki-84",
    "wof:placetype": "custom",
    "wof:placetype_alt": "object"
  },
  "geometry": {"coordinates":[-122.386155,37.616357],"type":"Point"}
}
