{
  "type": "Feature",
  "properties": {
    "date:cessation_lower":"1930-12-31",
    "date:cessation_upper":"1930-12-31",
    "date:inception_lower":"1930-01-01",
    "date:inception_upper":"1930-01-01",
    "iso:country":"XX",
    "sfomuseum:accession_number":"2012.149.1705",
    "sfomuseum:category":"Philately",
    "sfomuseum:collection":"Aviation Archive",
    "sfomuseum:creditline":"Gift of the Captain John B. Russell Family",
    "sfomuseum:date":"11/15/1930",
    "sfomuseum:daterange_end":"1930-11-15",
    "sfomuseum:daterange_start":"1930-11-15",
    "sfomuseum:description":"Airmail flight cover, New York, Rio & Buenos Aires Line (NYRBA); postmarked November 15, 1930 in Recife, Brazil; with Brazilian 300-reis stamp and 1000-reis, and 2000-reis overstrike stamps; stamped \u201cVia NYRBA / Correspondencia Aerea\u201d; addressed to Harry L. Green.",
    "sfomuseum:medium":"paper, ink",
    "sfomuseum:placetype":"object",
    "sfomuseum:subcategory":"Airmail Flight Cover",
    "wof:name":"airmail flight cover: New York, Rio & Buenos Aires Line (NYRBA)",
    "wof:placetype":"venue"
},
  "geometry": {"coordinates":[-122.386155,37.616358],"type":"Point"}
}