{
  "type": "Feature",
  "properties": {
    "date:cessation_lower": "1930-11-15",
    "date:cessation_upper": "1930-11-15",
    "date:inception_lower": "1930-11-15",
    "date:inception_upper": "1930-11-15",
    "iso:country": "XX",
    "millsfield:images": [
      1527834623,
      1527834625
    ],
    "millsfield:primary_image": 1527834623,
    "sfomuseum:accession_number": "2012.149.1705",
    "sfomuseum:airline": "New York, Rio, and Buenos Aires Line (NYRBA)",
    "sfomuseum:category": "Philately",
    "sfomuseum:collection": "Aviation Archive",
    "sfomuseum:creditline": "Gift of the Captain John B. Russell Family",
    "sfomuseum:date": "11/15/1930",
    "sfomuseum:daterange_end": "1930-11-15",
    "sfomuseum:daterange_start": "1930-11-15",
    "sfomuseum:description": "Airmail flight cover, New York, Rio \u0026 Buenos Aires Line (NYRBA); postmarked November 15, 1930 in Recife, Brazil; with Brazilian 300-reis stamp and 1000-reis, and 2000-reis overstrike stamps; stamped “Via NYRBA / Correspondencia Aerea”; addressed to Harry L. Green.",
    "sfomuseum:dimensions": "3 1/2 x 6 1/2 inches (8.9 x 16.5 cm)",
    "sfomuseum:media_ids": [
      1527834623,
      1527834625
    ],
    "sfomuseum:medium": "paper, ink",
    "sfomuseum:placetype": "object",
    "sfomuseum:publication": ": , 11/15/1930.",
    "sfomuseum:subcategory": "Airmail Flight Cover",
    "wof:depicts": [
      1159284865
    ],
    "wof:name": "airmail flight cover: New York, Rio \u0026 Buenos Aires Line (NYRBA)",
    "wof:placetype": "venue"
  },
  "geometry": {"coordinates":[-122.386155,37.616357],"type":"Point"}
}
