{
  "type": "Feature",
  "properties": {
    "date:cessation_lower": "1967-12-31",
    "date:cessation_upper": "1967-12-31",
    "date:inception_lower": "1967-01-01",
    "date:inception_upper": "1967-01-01",
    "iso:country": "XX",
    "millsfield:images": [
      1527837897
    ],
    "sfomuseum:accession_number": "2005.132.035.013",
    "sfomuseum:airline": "Northwest Orient Airlines",
    "sfomuseum:category": "Scheduling / Ticketing",
    "sfomuseum:collection": "Aviation Archive",
    "sfomuseum:creditline": "Gift of the William Hough Collection",
    "sfomuseum:date": "1967",
    "sfomuseum:daterange_end": "1967-12-31",
    "sfomuseum:daterange_start": "1967-01-01",
    "sfomuseum:description": "Timetable issued by Northwest Orient Airlines, effective August 15, 1967. The cover is white. The lettering and drawing are blue and red. The company name is in blue and red lettering at the top. In the center is a large drawing of the tail section of Boeing 707.",
    "sfomuseum:dimensions": "9 x 4 inches (22.9 x 10.2 cm)",
    "sfomuseum:media_ids": [
      1527837897
    ],
    "sfomuseum:medium": "paper, ink",
    "sfomuseum:placetype": "object",
    "sfomuseum:subcategory": "Timetable",
    "sfomuseum:subject": "Airlines -- Timetable -- Northwest Orient Airlines",
    "wof:depicts": [
      1159284913,
      1159289653,
      1159293593
    ],
    "wof:name": "timetable: Northwest Orient Airlines",
    "wof:placetype": "venue"
  },
  "geometry": {"coordinates":[-122.386155,37.616357],"type":"Point"}
}
