{
  "type": "Feature",
  "properties": {
    "date:cessation_lower": "2006-12-31",
    "date:cessation_upper": "2006-12-31",
    "date:inception_lower": "1996-01-01",
    "date:inception_upper": "1996-01-01",
    "iso:country": "XX",
    "sfomuseum:accession_number": "2006.034.081 a b",
    "sfomuseum:category": "Food Service",
    "sfomuseum:collection": "Aviation Museum",
    "sfomuseum:creditline": "Gift of Adan Wong",
    "sfomuseum:date": "c. 2001",
    "sfomuseum:daterange_end": "2006-12-31",
    "sfomuseum:daterange_start": "1996-01-01",
    "sfomuseum:description": "Menu and wine list produced by Cathay Pacific Airways, Tokyo - Hong Kong route; full color photographic image of asparagus; dinner menu items include beef tenderloin, grilled cutlass fish, and Sakuraba soba.\ra. menu; menu number: CX7505-JAPJ APR; class: business; undated\rb. beverage list; menu number CX8501, 503, 505, 507, 509, 533, 571 class: business; date: 1-12-2001",
    "sfomuseum:media_ids": [
      1527843981, 
      1527843983, 
      1527844549
    ],
    "sfomuseum:medium": "paper, ink, string",
    "sfomuseum:placetype": "object",
    "sfomuseum:subcategory": "Menu",
    "wof:name": "menu: Cathay Pacific Airways, Business Class",
    "wof:placetype": "venue"
  },
  "geometry": {"coordinates":[-122.386155,37.616358],"type":"Point"}
}
