{
  "type": "Feature",
  "properties": {
    "date:cessation_lower": "1929-12-31",
    "date:cessation_upper": "1929-12-31",
    "date:inception_lower": "1929-01-01",
    "date:inception_upper": "1929-01-01",
    "iso:country": "XX",
    "sfomuseum:accession_number": "2001.038.191",
    "sfomuseum:category": "Philately",
    "sfomuseum:collection": "Aviation Archive",
    "sfomuseum:creditline": "Gift of Barnaby Conrad III",
    "sfomuseum:date": "01/09/1929",
    "sfomuseum:daterange_end": "1929-01-09",
    "sfomuseum:daterange_start": "1929-01-09",
    "sfomuseum:description": "Airmail flight cover, FAM-6, first airmail flight, Miami - San Juan (Puerto Rico) route; purple cachet with route map and in-flight tri-motor aircraft; postmarked January 9, 1929 in Miami with football-shaped “2” cancellation marks on three stamps; backstamp: January 10, 1929 in San Juan.",
    "sfomuseum:maker": "Dahlke Stationary and Manufacturing Company",
    "sfomuseum:media_ids": [
      1527830103, 
      1527830105
    ],
    "sfomuseum:medium": "paper, ink, adhesive",
    "sfomuseum:placetype": "object",
    "sfomuseum:subcategory": "Airmail Flight Cover",
    "wof:name": "airmail flight cover: First airmail flight, FAM-6, Miami - San Juan route",
    "wof:placetype": "venue"
  },
  "geometry": {"coordinates":[-122.386155,37.616358],"type":"Point"}
}
