{
  "type": "Feature",
  "properties": {
    "date:cessation_lower": "1929-01-09",
    "date:cessation_upper": "1929-01-09",
    "date:inception_lower": "1929-01-09",
    "date:inception_upper": "1929-01-09",
    "iso:country": "XX",
    "millsfield:images": [
      1527830103,
      1527830105
    ],
    "millsfield:images_texts": [
      "INTERNATIONAL CIVIL AERONAUTICS\nCONFERENCE\n85\nAIR\n830\nFL\nViewa\n2 1 DECEMBER 12.13.11-1928.\nFIRST FLIGHT\nAIR MAIL\nFROM\nMIAMI\nVIA AIR MANL\nUAN S\n830AM\n*LA\nINTERNATIONAI\nI. A.M. 6\nFrank W. Wright,\n% Postmaster,\nSan Juan,\nPorto\nRico.\n1929",
      "126330495\nC5 SAN IO\n530 PM\n1929\nFRANK W. WRIGUT,\nThis envelope approved by the U. S. Post Office Dept.,.\nUse for other purposes not permitted.\n2P FIR MAlt ONEY Ave.,\nMANUFACTURED BY DAHLKE STATIONERY \u0026 MFG. CO.. BUFFALO. N. Y.\nELMIRA, N. Y.\n200.038.191"
    ],
    "millsfield:images_texts_ids": [
      1527830103,
      1527830105
    ],
    "millsfield:primary_image": 1527830103,
    "sfomuseum:accession_number": "2001.038.191",
    "sfomuseum:aircraft": "Fokker F-10",
    "sfomuseum:airline": "Pan American Airways",
    "sfomuseum:category": "Philately",
    "sfomuseum:collection": "Aviation Archive",
    "sfomuseum:creditline": "Gift of Barnaby Conrad III",
    "sfomuseum:date": "01/09/1929",
    "sfomuseum:date_acquired": "2003-05-16",
    "sfomuseum:daterange_end": "1929-01-09",
    "sfomuseum:daterange_start": "1929-01-09",
    "sfomuseum:description": "Airmail flight cover, FAM-6, first airmail flight, Miami - San Juan (Puerto Rico) route; purple cachet with route map and tri-motor aircraft in flight; postmarked January 9, 1929 in Miami with football-shaped “2” cancellation marks on three stamps; backstamp: January 10, 1929 in San Juan.",
    "sfomuseum:dimensions": "3 3/4 x 6 1/2 inches (9.5 x 16.5 cm)",
    "sfomuseum:maker": "Dahlke Stationary and Manufacturing Company",
    "sfomuseum:media_ids": [
      1527830103,
      1527830105
    ],
    "sfomuseum:medium": "paper, ink, adhesive",
    "sfomuseum:placetype": "object",
    "sfomuseum:publication": ": , 01/09/1929.",
    "sfomuseum:subcategory": "Airmail Flight Cover",
    "wof:depicts": [
      1159284991,
      1159286839,
      1159290633
    ],
    "wof:name": "airmail flight cover: First airmail flight, FAM-6, Miami - San Juan route",
    "wof:placetype": "custom",
    "wof:placetype_alt": "object"
  },
  "geometry": {"coordinates":[-122.386155,37.616357],"type":"Point"}
}
