{
  "type": "Feature",
  "properties": {
    "date:cessation_lower": "1959-01-01",
    "date:cessation_upper": "1959-12-31",
    "date:inception_lower": "1959-01-01",
    "date:inception_upper": "1959-12-31",
    "iso:country": "XX",
    "sfomuseum:accession_number": "2002.064.011",
    "sfomuseum:author": "United States. Dept. of Commerce. Office of Area Development",
    "sfomuseum:callnumber": "HC108.S7 A55 1959 c.1",
    "sfomuseum:category": "Book",
    "sfomuseum:collection": "Aviation Library",
    "sfomuseum:creditline": "Purchase",
    "sfomuseum:date": "1959",
    "sfomuseum:daterange_end": "1959-12-31",
    "sfomuseum:daterange_start": "1959-01-01",
    "sfomuseum:description": "1 v. (various pagings) diagrs., tables. 26 cm.",
    "sfomuseum:description_library": "1 v. (various pagings) diagrs., tables. 26 cm.",
    "sfomuseum:medium": "paper, ink",
    "sfomuseum:notes_library": "Bibliography: p. E 1-E 12.",
    "sfomuseum:placetype": "object",
    "sfomuseum:publication": "Washington, D.C.: , 1959.",
    "sfomuseum:publisher_location": "Washington, D.C.",
    "sfomuseum:subcategory": "Book",
    "sfomuseum:subject": "San Francisco Bay Area (Calif.) Economic conditions.",
    "wof:name": "Future development of the San Francisco Bay area, 1960-2020:  economic aspects of comprehensive survey of San Francisco Bay and tributaries",
    "wof:placetype": "custom"
  },
  "geometry": {"coordinates":[-122.386155,37.616357],"type":"Point"}
}
