{
  "type": "Feature",
  "properties": {
    "date:cessation_lower": "1984-01-01",
    "date:cessation_upper": "1984-12-31",
    "date:inception_lower": "1984-01-01",
    "date:inception_upper": "1984-12-31",
    "iso:country": "XX",
    "millsfield:images": [
      1527843199,
      1527851581
    ],
    "millsfield:images_texts": [
      "USAIR\nSystem Timetable\nEffective February 1, 1984\nEffective April 29, 1984\nall arrivals and departures at\nIndianapolis, Phoenix, and\nTucson will be 1 hour earlier.\nJoin\nJEBIR\nCLUB\nNow open in:\nBoston\nBuffalo\nPhiladelphia\nPittsburgh\nWashington, D.C.\nIncludes Allegheny Commuter Service",
      "1.00 PM.\nPACAC TRE\n200 PM.\n300 PM.\nUSAIR\nService to over 90 citles In the U.S. and Canada.\n@ ST. LOUS\nUSAir \u0026\nAllegheny Commuter-\nA great team to go with.\nService to over 120 citles\nIn the U.S. and Canada.\nALLEGHENY\nCOMMUTER\nService to over 50\ncities In the U.S."
    ],
    "millsfield:images_texts_ids": [
      1527843199,
      1527851581
    ],
    "millsfield:primary_image": 1527843199,
    "sfomuseum:accession_number": "2008.108.855",
    "sfomuseum:airline": "USAir",
    "sfomuseum:category": "Scheduling / Ticketing",
    "sfomuseum:collection": "Aviation Archive",
    "sfomuseum:creditline": "Gift of the William Hough Collection",
    "sfomuseum:date": "1984",
    "sfomuseum:date_acquired": "2008-11-10",
    "sfomuseum:daterange_end": "1984-12-31",
    "sfomuseum:daterange_start": "1984-01-01",
    "sfomuseum:description": "System timetable issued by USAir, effective February 1, 1984; white cover with text promoting Boston, Buffalo, Philadelphia, Pittsburgh and Washington, D.C. service; includes Allegheny Commuter Service.",
    "sfomuseum:dimensions": "9 x 4 inches (22.9 x 10.2 cm)",
    "sfomuseum:media_ids": [
      1527843199,
      1527851581
    ],
    "sfomuseum:medium": "paper, ink",
    "sfomuseum:placetype": "object",
    "sfomuseum:publication": ": , 1984.",
    "sfomuseum:subcategory": "Timetable",
    "sfomuseum:subject": "Airlines -- Commercial -- USAir",
    "wof:depicts": [
      1159285447,
      1159288239
    ],
    "wof:name": "timetable: USAir",
    "wof:placetype": "custom",
    "wof:placetype_alt": "object"
  },
  "geometry": {"coordinates":[-122.386155,37.616357],"type":"Point"}
}
