{
  "type": "Feature",
  "properties": {
    "date:cessation_lower": "1989-01-01",
    "date:cessation_upper": "1989-12-31",
    "date:inception_lower": "1984-01-01",
    "date:inception_upper": "1984-12-31",
    "iso:country": "XX",
    "millsfield:images": [
      1527828819
    ],
    "sfomuseum:accession_number": "2007.051.107",
    "sfomuseum:airline": "Braniff Inc.",
    "sfomuseum:category": "Insignia",
    "sfomuseum:collection": "Aviation Museum",
    "sfomuseum:creditline": "Purchase",
    "sfomuseum:date": "1984-1989",
    "sfomuseum:daterange_end": "1989-12-31",
    "sfomuseum:daterange_start": "1984-01-01",
    "sfomuseum:description": "Flight officer wings issued by Braniff, Inc.; silver wings with logotype on center, star at top; two posts with clutch-back closures on back; worn by captain, worn 1984-1989.\r\rStylized silver wings with raised \"Braniff\" across center, topped by five-pointed star; slight convex horizontal curve; two button stud fasteners on back; this pin design worn 1984-89.",
    "sfomuseum:dimensions": "3/4 x 3 1/4 x 1/2 inches (1.9 x 8.3 x 1.3 cm)",
    "sfomuseum:media_ids": [
      1527828819
    ],
    "sfomuseum:medium": "metal",
    "sfomuseum:placetype": "object",
    "sfomuseum:subcategory": "Uniform Wing(s), Flight Crew",
    "wof:depicts": [
      1159286457
    ],
    "wof:name": "flight officer wings: Braniff Inc.",
    "wof:placetype": "venue"
  },
  "geometry": {"coordinates":[-122.386155,37.616357],"type":"Point"}
}
