{
  "type": "Feature",
  "properties": {
    "date:cessation_lower": "1989-12-31",
    "date:cessation_upper": "1989-12-31",
    "date:inception_lower": "1984-01-01",
    "date:inception_upper": "1984-01-01",
    "iso:country": "XX",
    "sfomuseum:accession_number": "2007.051.107",
    "sfomuseum:category": "Insignia",
    "sfomuseum:collection": "Aviation Museum",
    "sfomuseum:creditline": "Purchase",
    "sfomuseum:date": "1984-1989",
    "sfomuseum:daterange_end": "1989-12-31",
    "sfomuseum:daterange_start": "1984-01-01",
    "sfomuseum:description": "Stylized silver wings with raised \"Braniff\" across center, topped by five-pointed star; slight convex horizontal curve; two button stud fasteners on back; this pin design worn 1984-89.",
    "sfomuseum:media_ids": [
      1527828819
    ],
    "sfomuseum:medium": "metal",
    "sfomuseum:placetype": "object",
    "sfomuseum:subcategory": "Uniform Wing(s), Flight Crew",
    "wof:name": "flight officer wings: Braniff Inc.",
    "wof:placetype": "venue"
  },
  "geometry": {"coordinates":[-122.386155,37.616358],"type":"Point"}
}
