{
  "type": "Feature",
  "properties": {
    "date:cessation_lower": "1970-01-01",
    "date:cessation_upper": "1979-12-31",
    "date:inception_lower": "1970-01-01",
    "date:inception_upper": "1979-12-31",
    "iso:country": "XX",
    "millsfield:images": [
      1527857279,
      1527857281,
      1527857283,
      1527857285
    ],
    "millsfield:primary_image": 1527857279,
    "sfomuseum:accession_number": "2001.146.111",
    "sfomuseum:airline": "Philippine Airlines",
    "sfomuseum:category": "Promotional",
    "sfomuseum:collection": "Aviation Museum",
    "sfomuseum:creditline": "Gift of Thomas G. Dragges",
    "sfomuseum:date": "1970s",
    "sfomuseum:date_acquired": "2003-07-24",
    "sfomuseum:daterange_end": "1979-12-31",
    "sfomuseum:daterange_start": "1970-01-01",
    "sfomuseum:description": "Airline bag issued by Philippine Airlines; blue background with servicemark on front pocket and back side; white piping with top zipper closure and adjustable shoulder strap; four metal feet and identification panel on bottom. ",
    "sfomuseum:dimensions": "14 x 10 1/2 x 5 inches (35.6 x 26.7 x 12.7 cm)",
    "sfomuseum:maker": "Airline Textile Manufacturing Company",
    "sfomuseum:media_ids": [
      1527857279,
      1527857281,
      1527857283,
      1527857285
    ],
    "sfomuseum:medium": "synthetic textile (vinyl?), plastic, metal, pigment",
    "sfomuseum:placetype": "object",
    "sfomuseum:publication": ": , 1970s.",
    "sfomuseum:subcategory": "Airline Bag",
    "wof:depicts": [
      1159285015
    ],
    "wof:name": "airline bag: Philippine Airlines",
    "wof:placetype": "venue"
  },
  "geometry": {"coordinates":[-122.386155,37.616357],"type":"Point"}
}
