{
  "type": "Feature",
  "properties": {
    "date:cessation_lower": "1952-01-01",
    "date:cessation_upper": "1952-12-31",
    "date:inception_lower": "1952-01-01",
    "date:inception_upper": "1952-12-31",
    "iso:country": "XX",
    "millsfield:images": [
      1729566555,
      1729566557
    ],
    "millsfield:images_texts": [
      "You sleep like a top in these roomy, luxuriously-appointed, fut\nsicep, refresised -ready for business or pleasuro.\nAsk your Travel Agent about the B.C.P.A. Service\nG.CP.A OFFICES\nHEAD\nOFFICE: A.P A. Suld no.\nSAN FRANCISCO: 347 Stockton St., Sen Franciso\nFUl: Nandi Airport and 13 Victors Parsde. Sara\nS.CRA, AGENTS\nAUSTRALIA: TAA, 339 Swanston St., Melbourne, CI. Booking\narices an\nN.ZNAC.\nAir Centre,\nAUCKETSOR\nMONOLOCUS Used. M. Dares o co, Limited, Davies Build ing\nHonolulu\nU.SA.: B.OA.C.: New York, 342 Madison Ave., New York.\nAiso chicago, Los Angeles, Washington, Boston, Miami, Detroit.\nCANADA: T.C.A., 656 Hone Street,\nOffices\nPRINTCO IN AUSTRALIA N/5191/S\n284.(84,128)",
      "EFFECTIVE AUGUST 1st, 1952\nВСРА\nDC-6 Sleeper Service\nCANADA - USA -HAWAII - FIJI\nAUSTRALIA - NEW ZEALAND\n• P\nBritish Commonwealth\nPacific Airlines Ltd.\nAllEinformation contoined hercin subicet to chon‹\nwithout monso\nES\nCARGO RATES\nEXCESS BAGGAGE RATES\nGENERA\nINFORMATION"
    ],
    "millsfield:images_texts_ids": [
      1729566555,
      1729566557
    ],
    "millsfield:primary_image": 1729566557,
    "sfomuseum:accession_number": "2014.084.1381",
    "sfomuseum:aircraft": "Douglas DC-6",
    "sfomuseum:airline": "British Commonwealth Pacific Airlines (BCPA)",
    "sfomuseum:category": "Scheduling / Ticketing",
    "sfomuseum:collection": "Aviation Archive",
    "sfomuseum:creditline": "Gift of Thomas G. Dragges",
    "sfomuseum:date": "1952",
    "sfomuseum:date_acquired": "2015-07-02",
    "sfomuseum:daterange_end": "1952-12-31",
    "sfomuseum:daterange_start": "1952-01-01",
    "sfomuseum:description": "Timetable issued by BCPA (British Commonwealth Pacific Airlines) for transpacific DC-6 sleeper service, effective August 1, 1952; fold-out format; blue, red, and white cover with text promoting service to Canada, USA, Hawaii, Fiji, Australia, and New Zealand.",
    "sfomuseum:dimensions": "9 x 4 inches (22.9 x 10.2 cm)",
    "sfomuseum:medium": "paper, ink",
    "sfomuseum:placetype": "object",
    "sfomuseum:publication": ": , 1952.",
    "sfomuseum:subcategory": "Timetable",
    "wof:depicts": [
      1159286739,
      1159284025
    ],
    "wof:name": "timetable: British Commonwealth Pacific Airlines (BCPA), transpacific Douglas DC-6 Sleeper Service",
    "wof:placetype": "custom",
    "wof:placetype_alt": "object"
  },
  "geometry": {"coordinates":[-122.386155,37.616357],"type":"Point"}
}
