{
  "type": "Feature",
  "properties": {
    "date:cessation_lower": "1990-12-31",
    "date:cessation_upper": "1990-12-31",
    "date:inception_lower": "1990-01-01",
    "date:inception_upper": "1990-01-01",
    "iso:country": "CN",
    "sfomuseum:accession_number": "1999.672.014",
    "sfomuseum:airport": "Hong Kong Kai Tak Airport",
    "sfomuseum:author": "Pigott, Peter",
    "sfomuseum:callnumber": "TL726.7.H85 P54 1990",
    "sfomuseum:category": "Book",
    "sfomuseum:collection": "Aviation Library",
    "sfomuseum:continent": "Asia",
    "sfomuseum:country": "China",
    "sfomuseum:creditline": "Gift of Louis A. Turpen",
    "sfomuseum:date": "1990",
    "sfomuseum:daterange_end": "1990-12-31",
    "sfomuseum:daterange_start": "1990-01-01",
    "sfomuseum:description": "184 p. :ill. (some col.) ; 22 cm.\r\"P59538900E0\"--P. [4] of the cover.",
    "sfomuseum:medium": "book",
    "sfomuseum:placetype": "object",
    "sfomuseum:publisher": "Government Information Services",
    "sfomuseum:publisher_location": "Hong Kong",
    "sfomuseum:subcategory": "Book",
    "sfomuseum:subject": "Kai Tak Airport.\rInternational airports - Hong Kong.\rAeronautics, Commercial - Hong Kong.",
    "wof:depicts": [
      1360691531
    ],
    "wof:name": "Kai Tak: a history of aviation in Hong Kong",
    "wof:placetype": "venue"
  },
  "geometry": {"coordinates":[-122.386155,37.616357],"type":"Point"}
}
