{
  "type": "Feature",
  "properties": {
    "date:cessation_lower": "1964-01-01",
    "date:cessation_upper": "1964-12-31",
    "date:inception_lower": "1964-01-01",
    "date:inception_upper": "1964-12-31",
    "iso:country": "XX",
    "millsfield:images": [
      1527828725
    ],
    "millsfield:primary_image": 1527828725,
    "sfomuseum:accession_number": "2001.038.169 a t",
    "sfomuseum:airline": "Pan American World Airways",
    "sfomuseum:category": "Promotional",
    "sfomuseum:collection": "Aviation Archive",
    "sfomuseum:creditline": "Gift of Barnaby Conrad III",
    "sfomuseum:date": "1964",
    "sfomuseum:date_acquired": "2003-05-16",
    "sfomuseum:daterange_end": "1964-12-31",
    "sfomuseum:daterange_start": "1964-01-01",
    "sfomuseum:description": "Press kit issued by Pan American World Airways promoting the airline's inaugural first direct flight New York to Berlin on May 30, 1964; \ra. portfolio with blue and white cover with silhouette of aircraft in black, smaller white airplane shapes, and outline of German map;\rb-t. press releases with description of the New York - Berlin service; background information on Pan Am's Jet service and Berlin; short biographies on the captain, first officer, second officer, flight engineer, pursers, and stewardesses.",
    "sfomuseum:media_ids": [
      1527828725
    ],
    "sfomuseum:medium": "paper, ink",
    "sfomuseum:placetype": "object",
    "sfomuseum:publication": ": , 1964.",
    "sfomuseum:subcategory": "Press Kit / Release",
    "sfomuseum:subject": "Airlines -- Commercial -- Pan American World Airways\rNew York to Berlin.",
    "wof:depicts": [
      1159284989,
      1159286839
    ],
    "wof:name": "press kit: Pan American World Airways, Berlin inaugural service",
    "wof:placetype": "venue"
  },
  "geometry": {"coordinates":[-122.386155,37.616357],"type":"Point"}
}
