{
  "type": "Feature",
  "properties": {
    "date:cessation_lower": "1975-01-01",
    "date:cessation_upper": "1975-12-31",
    "date:inception_lower": "1975-01-01",
    "date:inception_upper": "1975-12-31",
    "iso:country": "XX",
    "millsfield:images": [
      1527844691,
      1527844693
    ],
    "millsfield:images_texts": [
      "N\nTL",
      "Beverages\nSherry\nManhattan\nMartini\nWhiskey Sour\nGin\nVodka\nMenu\nHors d'Oeuvre\nAPPRITZER\nScotch\nBourbon\nCanadian\nSelected Red or White Wines\nChampagne\nSelected Premium Beer\nCigarettes-Assorted Brands\nCocktails, Wines and Liquors $.50\nBeer \u0026 Cigarettes $.30\nChampagne (Split) $1.00\nBoeuf à la Bourguignonne\nWITH ED SHEF BUS AND PEARL ONIONS\nou\nUn\nSuprême de Chapon à la Hongroise\nPROTED WANDA PARAM AERES\nNouilles au beurre\nBUTTERED NOODLES\nSalade\nSALAD\nFromage\nCHEESE AND CRACKERS\nPâtisserie\nPASTRY\nCafé\nCOFFEE\nThé\nTEA\n1995.35.64"
    ],
    "millsfield:images_texts_ids": [
      1527844691,
      1527844693
    ],
    "millsfield:primary_image": 1527844691,
    "sfomuseum:accession_number": "1995.35.64",
    "sfomuseum:aircraft": "Boeing 747",
    "sfomuseum:airline": "Pan American World Airways",
    "sfomuseum:category": "Passenger Amenity, Archive",
    "sfomuseum:collection": "Aviation Archive",
    "sfomuseum:continent": "Transatlantic",
    "sfomuseum:creditline": "Gift of Beatrice H. Springer",
    "sfomuseum:date": "c. 1975",
    "sfomuseum:date_acquired": "1997-07-06",
    "sfomuseum:daterange_end": "1980-12-31",
    "sfomuseum:daterange_start": "1970-01-01",
    "sfomuseum:description": "Menu issued by Pan American World Airways; blue and white cover with repeating pattern of “747”; menu items include beef Bourguignonne or breast of capon; menu number: 0200-747; undated.",
    "sfomuseum:dimensions": "9 1/2 x 5 1/2 inches (24.1 x 14 cm)",
    "sfomuseum:maker": "Pan American World Airways, Inc.",
    "sfomuseum:media_ids": [
      1527844691,
      1527844693
    ],
    "sfomuseum:medium": "paper, ink",
    "sfomuseum:placetype": "object",
    "sfomuseum:publication": ": , c. 1975.",
    "sfomuseum:subcategory": "Menu",
    "wof:depicts": [
      1159289873,
      1159284989,
      1159286839,
      1159293593
    ],
    "wof:name": "menu: Pan American World Airways",
    "wof:placetype": "custom",
    "wof:placetype_alt": "object"
  },
  "geometry": {"coordinates":[-122.386155,37.616357],"type":"Point"}
}
