{
  "type": "Feature",
  "properties": {
    "date:cessation_lower": "1961-01-01",
    "date:cessation_upper": "1961-12-31",
    "date:inception_lower": "1961-01-01",
    "date:inception_upper": "1961-12-31",
    "iso:country": "XX",
    "sfomuseum:accession_number": "2000.181.012",
    "sfomuseum:author": "Moscow, Alvin",
    "sfomuseum:callnumber": "TL533.9 .M6 1961 c.2",
    "sfomuseum:category": "Book",
    "sfomuseum:collection": "Aviation Library",
    "sfomuseum:creditline": "Gift of William A. Mathis",
    "sfomuseum:date": "1961",
    "sfomuseum:date_acquired": "1999-10-05",
    "sfomuseum:daterange_end": "1961-12-31",
    "sfomuseum:daterange_start": "1961-01-01",
    "sfomuseum:description": "252 p., [16] p. of plates : ports. ; 22 cm.",
    "sfomuseum:description_library": "252 p., [16] p. of plates : ports. ; 22 cm.",
    "sfomuseum:medium": "paper, ink",
    "sfomuseum:placetype": "object",
    "sfomuseum:publication": "New York: Putnam, 1961.",
    "sfomuseum:publisher": "Putnam",
    "sfomuseum:publisher_location": "New York",
    "sfomuseum:subcategory": "Book",
    "sfomuseum:subject": "Northeast Airlines, inc.Aeronautics, Commercial United States Statistics.Aeronautics Accidents 1957.",
    "wof:name": "Tiger on a leash",
    "wof:placetype": "custom",
    "wof:placetype_alt": "object"
  },
  "geometry": {"coordinates":[-122.386155,37.616357],"type":"Point"}
}
