{
  "type": "Feature",
  "properties": {
    "date:cessation_lower": "1932-01-01",
    "date:cessation_upper": "1932-12-31",
    "date:inception_lower": "1932-01-01",
    "date:inception_upper": "1932-12-31",
    "iso:country": "XX",
    "millsfield:images": [
      1527831467
    ],
    "millsfield:primary_image": 1527831467,
    "sfomuseum:accession_number": "2010.279.001.009 a b",
    "sfomuseum:airline": "Pan American Airways",
    "sfomuseum:category": "Company Record / Document",
    "sfomuseum:collection": "Aviation Archive",
    "sfomuseum:creditline": "Gift of Jon E. Krupnick",
    "sfomuseum:date": "1932",
    "sfomuseum:daterange_end": "1932-12-31",
    "sfomuseum:daterange_start": "1932-01-01",
    "sfomuseum:description": "a. Blue and white stock certificate issued to Park Corporation (William S. Paley) for 1000 shares of Pan American Airways Corporation; certificate number 5931, dated November 9, 1932; engraved corporate seal and signatures of H. Preston Morris, Secretary, and J. T. Trippe, President; countersigned by The Chase National Bank of the City of New York, registered November 10, 1932 by the New York Trust Company; certificate note by Quayle \u0026 Son, New York; document defaced by hole punch cancellation at left and lower right.\rb. Attached assignment signed by Paley, dated December 11, 1933; document defaced by hole punch cancellation at lower right.\rc. Folded attachment with postage stamps.",
    "sfomuseum:dimensions": "8 x 11 1/4 inches (20.3 x 28.6 cm)",
    "sfomuseum:media_ids": [
      1527831467
    ],
    "sfomuseum:medium": "paper, ink",
    "sfomuseum:placetype": "object",
    "sfomuseum:publication": ": , 1932.",
    "sfomuseum:subcategory": "Stock Certificate / Bond",
    "wof:depicts": [
      1159284991
    ],
    "wof:name": "stock certificate: Pan American Airways Corporation",
    "wof:placetype": "venue"
  },
  "geometry": {"coordinates":[-122.386155,37.616357],"type":"Point"}
}
