{
  "type": "Feature",
  "properties": {
    "date:cessation_lower": "1958-12-31",
    "date:cessation_upper": "1958-12-31",
    "date:inception_lower": "1958-01-01",
    "date:inception_upper": "1958-01-01",
    "iso:country": "XX",
    "sfomuseum:accession_number": "2000.054.016",
    "sfomuseum:category": "Philately",
    "sfomuseum:collection": "Aviation Archive",
    "sfomuseum:continent": "World Routes",
    "sfomuseum:creditline": "Gift of John Zukowsky",
    "sfomuseum:date": "07/31/1958",
    "sfomuseum:daterange_end": "1958-07-31",
    "sfomuseum:daterange_start": "1958-07-31",
    "sfomuseum:description": "Airmail postcard commemorating first day of issue for seven-cent air mail coil; gray cachet with illustration of in-flight aircraft; commemorative cancellation mark over two blue 7-cent stamps, July 31, 1958, Miami, Florida; addressed to Rose Shine.",
    "sfomuseum:media_ids": [
      1527830011
    ],
    "sfomuseum:medium": "ink, printed paper",
    "sfomuseum:placetype": "object",
    "sfomuseum:subcategory": "Airmail Flight Cover",
    "wof:name": "airmail flight cover: Seven-cent Air Mail Coil, first day of issue",
    "wof:placetype": "venue"
  },
  "geometry": {"coordinates":[-122.386155,37.616358],"type":"Point"}
}
