{
  "type": "Feature",
  "properties": {
    "date:cessation_lower": "1989-12-31",
    "date:cessation_upper": "1989-12-31",
    "date:inception_lower": "1980-01-01",
    "date:inception_upper": "1980-01-01",
    "iso:country": "XX",
    "sfomuseum:accession_number": "1998.157.078",
    "sfomuseum:category": "Passenger Amenity",
    "sfomuseum:collection": "Aviation Museum",
    "sfomuseum:creditline": "Gift of The Henry Steiner Air Sickness Bag Collection",
    "sfomuseum:date": "1980s",
    "sfomuseum:daterange_end": "1989-12-31",
    "sfomuseum:daterange_start": "1980-01-01",
    "sfomuseum:description": "Gusset wedge, no closure. White bag, blue and red print. \"China Airlines\" in red, upper right corner. Above is Asian character, to left is logo, blue circle with \"CAL\" in white in circle. Below logo and \"China Airlines\" is blue rectangle with flowers. Flowers extend out of box to other areas of bag. Back has usage instructions in print and picture. Bounded edge of bag at top.",
    "sfomuseum:media_ids": [
      1527823789, 
      1527823793
    ],
    "sfomuseum:medium": "paper",
    "sfomuseum:placetype": "object",
    "sfomuseum:subcategory": "Airsickness Bag",
    "wof:name": "airsickness bag: China Airlines",
    "wof:placetype": "venue"
  },
  "geometry": {"coordinates":[-122.386155,37.616358],"type":"Point"}
}
