{
  "type": "Feature",
  "properties": {
    "date:cessation_lower":"1999-12-31",
    "date:cessation_upper":"1999-12-31",
    "date:inception_lower":"1990-01-01",
    "date:inception_upper":"1990-01-01",
    "iso:country":"XX",
    "millsfield:images":[
        1527824783,
        1527824779
    ],
    "sfomuseum:accession_number":"1998.157.124",
    "sfomuseum:category":"Passenger Amenity",
    "sfomuseum:collection":"Aviation Museum",
    "sfomuseum:creditline":"Gift of The Henry Steiner Air Sickness Bag Collection",
    "sfomuseum:date":"1990s",
    "sfomuseum:daterange_end":"1999-12-31",
    "sfomuseum:daterange_start":"1990-01-01",
    "sfomuseum:description":"Flat bottom, wire tab closure. Blue bag, white print. \"Gulf Air\" printed in white; above it are Middle Eastern characters on lower portion. Logo to right, line drawing of falcon (?). Whole thing flanked by single white line in double line box.",
    "sfomuseum:media_ids":[
        1527824779,
        1527824783
    ],
    "sfomuseum:medium":"paper",
    "sfomuseum:placetype":"object",
    "sfomuseum:subcategory":"Airsickness Bag",
    "wof:name":"airsickness bag: Gulf Air",
    "wof:placetype":"venue"
},
  "geometry": {"coordinates":[-122.386155,37.616358],"type":"Point"}
}