{
  "type": "Feature",
  "properties": {
    "date:cessation_lower": "1965-12-31",
    "date:cessation_upper": "1965-12-31",
    "date:inception_lower": "1955-01-01",
    "date:inception_upper": "1955-01-01",
    "iso:country": "AU",
    "millsfield:images": [
      1527853153,
      1527853155
    ],
    "sfomuseum:accession_number": "2013.095.019",
    "sfomuseum:airline": "Pan American World Airways",
    "sfomuseum:artist": "Lillian Sader",
    "sfomuseum:category": "Passenger Amenity",
    "sfomuseum:collection": "Aviation Archive",
    "sfomuseum:continent": "Australia",
    "sfomuseum:country": "Australia",
    "sfomuseum:creditline": "Gift of the Estate of Jane Gottschall",
    "sfomuseum:date": "c. 1960",
    "sfomuseum:daterange_end": "1965-12-31",
    "sfomuseum:daterange_start": "1955-01-01",
    "sfomuseum:description": "Menu issued by Pan American World Airways, Tokyo - Wake Island route; beige cover with color illustrations of iconic East Asian images; cover design by Lillian Sader; dinner menu items include broiled filet of beef and baked potato; no menu number; undated.",
    "sfomuseum:maker": "Pan American World Airways, Inc.",
    "sfomuseum:media_ids": [
      1527853153,
      1527853155
    ],
    "sfomuseum:medium": "paper",
    "sfomuseum:placetype": "object",
    "sfomuseum:subcategory": "Menu",
    "wof:depicts": [
      1159284989
    ],
    "wof:name": "menu: Pan American World Airways",
    "wof:placetype": "venue"
  },
  "geometry": {"coordinates":[-122.386155,37.616357],"type":"Point"}
}
