{
  "type": "Feature",
  "properties": {
    "date:cessation_lower":"2009-12-31",
    "date:cessation_upper":"2009-12-31",
    "date:inception_lower":"1999-01-01",
    "date:inception_upper":"1999-01-01",
    "iso:country":"XX",
    "millsfield:images":[
        1527844621,
        1527844619
    ],
    "sfomuseum:accession_number":"2006.034.078 a b",
    "sfomuseum:airline":"Cathay Pacific Airways",
    "sfomuseum:category":"Passenger Amenity",
    "sfomuseum:collection":"Aviation Archive",
    "sfomuseum:creditline":"Gift of Adan Wong",
    "sfomuseum:date":"c. 2004",
    "sfomuseum:daterange_end":"2009-12-31",
    "sfomuseum:daterange_start":"1999-01-01",
    "sfomuseum:description":"Menu and wine list issued by Cathay Pacific Airways, Auckland - Hong Kong route; full color photographic image of two snow pea pods; lunch and light meal menu items include stir-fried seafood, chicken teriyaki, and seafood noodle soup.\ra. menu; menu number: CX108-5013J <MAY/JUN/JUL>; class: business; undated\rb. wine list; menu number CX100, 104, 108, 114, 118, 134 class: business; date: 1-5-2004",
    "sfomuseum:media_ids":[
        1527844619,
        1527844621
    ],
    "sfomuseum:medium":"paper, ink, string",
    "sfomuseum:placetype":"object",
    "sfomuseum:subcategory":"Menu",
    "wof:depicts":[
        1159284127
    ],
    "wof:name":"menu: Cathay Pacific Airways, Business Class",
    "wof:placetype":"venue"
},
  "geometry": {"coordinates":[-122.386155,37.616357],"type":"Point"}
}