{
  "type": "Feature",
  "properties": {
    "iso:country": "XX",
    "millsfield:images": [
      1527852871,
      1527852873
    ],
    "millsfield:primary_image": 1527852871,
    "sfomuseum:accession_number": "1998.157.156",
    "sfomuseum:airline": "Malév Hungarian Airlines",
    "sfomuseum:category": "Passenger Amenity, Archive",
    "sfomuseum:collection": "Aviation Archive",
    "sfomuseum:creditline": "Gift of The Henry Steiner Air Sickness Bag Collection",
    "sfomuseum:date_acquired": "1999-07-13",
    "sfomuseum:description": "Airsickness bag issued by Malev Hugarian Airlines; white and blue bag with servicemark; gusset wedge, no closure.",
    "sfomuseum:dimensions": "10 1/2 x 4 3/4 inches (26.7 x 12.1 cm)",
    "sfomuseum:media_ids": [
      1527852871,
      1527852873
    ],
    "sfomuseum:medium": "paper, ink",
    "sfomuseum:placetype": "object",
    "sfomuseum:subcategory": "Airsickness Bag",
    "wof:depicts": [
      1159284747,
      1159287257
    ],
    "wof:name": "airsickness bag: Malev Hugarian Airlines",
    "wof:placetype": "custom",
    "wof:placetype_alt": "object"
  },
  "geometry": {"coordinates":[-122.386155,37.616357],"type":"Point"}
}
