{
  "type": "Feature",
  "properties": {
    "date:cessation_lower": "1950-01-01",
    "date:cessation_upper": "1950-12-31",
    "date:inception_lower": "1950-01-01",
    "date:inception_upper": "1950-12-31",
    "iso:country": "XX",
    "millsfield:images": [
      1527835049
    ],
    "millsfield:images_texts": [
      "CESKOSLOVENSKE AERDLINIE\nESA\nTU-104 A\nMOSKVA"
    ],
    "millsfield:images_texts_ids": [
      1527835049
    ],
    "millsfield:primary_image": 1527835049,
    "sfomuseum:accession_number": "2012.149.1154",
    "sfomuseum:airline": "Československé Statni Aerolinie (ČSA)",
    "sfomuseum:category": "Promotional, Archive",
    "sfomuseum:collection": "Aviation Archive",
    "sfomuseum:creditline": "Gift of the Captain John B. Russell Family",
    "sfomuseum:date": "c. 1950",
    "sfomuseum:date_acquired": "2013-05-31",
    "sfomuseum:daterange_end": "1955-12-31",
    "sfomuseum:daterange_start": "1945-01-01",
    "sfomuseum:description": "Luggage label issued by Československé Aerolinie; blue and white rectangular label with color illustration of Kremlin, St. Basil’s Cathedral, and airline logotype with text, \"Fly CSA / TU-104 A\" at top and “Moskva (Moscow).”",
    "sfomuseum:dimensions": "4 x 2 3/4 inches (10.2 x 7 cm)",
    "sfomuseum:media_ids": [
      1527835049
    ],
    "sfomuseum:medium": "paper, ink, adhesive",
    "sfomuseum:placetype": "object",
    "sfomuseum:publication": ": , c. 1950.",
    "sfomuseum:subcategory": "Luggage Label",
    "wof:depicts": [
      1159288321,
      1159284241,
      1159284239
    ],
    "wof:name": "luggage label: Československé Aerolinie",
    "wof:placetype": "custom",
    "wof:placetype_alt": "object"
  },
  "geometry": {"coordinates":[-122.386155,37.616357],"type":"Point"}
}
