{
  "type": "Feature",
  "properties": {
    "date:cessation_lower": "1927-01-01",
    "date:cessation_upper": "1927-12-31",
    "date:inception_lower": "1927-01-01",
    "date:inception_upper": "1927-12-31",
    "iso:country": "XX",
    "millsfield:images": [
      1527821243
    ],
    "millsfield:primary_image": 1527821243,
    "sfomuseum:accession_number": "2011.032.0036",
    "sfomuseum:airport": "Alameda Airport",
    "sfomuseum:category": "Photograph",
    "sfomuseum:collection": "Aviation Archive",
    "sfomuseum:creditline": "Transfer",
    "sfomuseum:date": "1927",
    "sfomuseum:date_acquired": "2011-03-02",
    "sfomuseum:daterange_end": "1927-12-31",
    "sfomuseum:daterange_start": "1927-01-01",
    "sfomuseum:description": "Black and white photographic negative depicting view of airfield, Alameda Airport, June 25, 1927; inscribed on black border, bottom: “A369 6-25-27 ALAMEDA AIRPORT.”",
    "sfomuseum:dimensions": "3 1/2 x 5 3/4 inches (8.9 x 14.6 cm)",
    "sfomuseum:media_ids": [
      1527821243
    ],
    "sfomuseum:medium": "nitrate negative",
    "sfomuseum:placetype": "object",
    "sfomuseum:publication": ": , 1927.",
    "sfomuseum:subcategory": "Negative",
    "wof:depicts": [
      102529283
    ],
    "wof:name": "negative: Alameda Airport",
    "wof:placetype": "venue"
  },
  "geometry": {"coordinates":[-122.386155,37.616357],"type":"Point"}
}
