{
  "type": "Feature",
  "properties": {
    "date:cessation_lower": "1966-01-01",
    "date:cessation_upper": "1966-12-31",
    "date:inception_lower": "1966-01-01",
    "date:inception_upper": "1966-12-31",
    "iso:country": "XX",
    "loc:subject_headings": [
      "sh85039206"
    ],
    "sfomuseum:accession_number": "2000.181.087",
    "sfomuseum:author": "Ingells, Douglas J.",
    "sfomuseum:callnumber": "TL686.D65 I5 1966 c.3",
    "sfomuseum:category": "Book",
    "sfomuseum:collection": "Aviation Library",
    "sfomuseum:creditline": "Gift of William A. Mathis",
    "sfomuseum:date": "1966",
    "sfomuseum:date_acquired": "1999-10-05",
    "sfomuseum:daterange_end": "1966-12-31",
    "sfomuseum:daterange_start": "1966-01-01",
    "sfomuseum:description": "256 p. illus. (part col.) ports. (part col.) 28 cm.",
    "sfomuseum:description_library": "256 p. illus. (part col.) ports. (part col.) 28 cm.",
    "sfomuseum:medium": "paper, ink",
    "sfomuseum:placetype": "object",
    "sfomuseum:publication": "Fallbrook, CA: Aero Publishers, 1966.",
    "sfomuseum:publisher": "Aero Publishers",
    "sfomuseum:publisher_location": "Fallbrook, CA",
    "sfomuseum:subcategory": "Book",
    "sfomuseum:subject": "Douglas transport planes.",
    "wof:name": "The plane that changed the world: a biography of the DC-3",
    "wof:placetype": "custom",
    "wof:placetype_alt": "object"
  },
  "geometry": {"coordinates":[-122.386155,37.616357],"type":"Point"}
}
