{
  "type": "Feature",
  "properties": {
    "date:cessation_lower": "1970-04-01",
    "date:cessation_upper": "1970-04-30",
    "date:inception_lower": "1970-01-01",
    "date:inception_upper": "1970-01-31",
    "iso:country": "XX",
    "millsfield:exhibition_ids": [
      1159160453
    ],
    "millsfield:images": [
      1527853429
    ],
    "millsfield:images_texts": [
      "Whether you're 3'7\" or 7'3\"\nAll of a sudden you can snooze your way to Europe, the Caribbean, the Pacific, or\nthe Orient. With plenty of leg room, head room, stretch room. On Pan Am's 747. The\nplane that's a ship, the ship that's a plane. And any time the plane isn't full, you're\nwelcome to flip up the arm rests and take over the seats next to you . Just call us or\nsee a Pan Am® Travel Agent. Our 747 won't cost you a penny more than ordinary\nplanes, no matter how much room you take up.\nPan Am's 747\nThe plane with all the room in the world."
    ],
    "millsfield:images_texts_ids": [
      1527853429
    ],
    "millsfield:on_view": 0,
    "millsfield:primary_image": 1527853429,
    "sfomuseum:accession_number": "2012.149.0797",
    "sfomuseum:aircraft": "Boeing 747",
    "sfomuseum:airline": "Pan American World Airways",
    "sfomuseum:category": "Promotional, Archive",
    "sfomuseum:collection": "Aviation Archive",
    "sfomuseum:creditline": "Gift of the Captain John B. Russell Family",
    "sfomuseum:date": "early 1970s",
    "sfomuseum:date_acquired": "2013-05-31",
    "sfomuseum:daterange_end": "1973-12-31",
    "sfomuseum:daterange_start": "1970-01-01",
    "sfomuseum:description": "Advertisement from magazine promoting Pan American World Airways Boeing 747 aircraft fleet, titled “Whether you’re 3’7” or 7’3”; color photographic image depicting inflight scene on wide-body jet; tall businessman asleep with outstretched legs across four seats as girl in row behind peers over headrest.",
    "sfomuseum:dimensions": "13 x 10 1/4 inches (33 x 26 cm)",
    "sfomuseum:exhibition_ids": [
      1286
    ],
    "sfomuseum:media_ids": [
      1527853429
    ],
    "sfomuseum:medium": "paper, ink",
    "sfomuseum:placetype": "object",
    "sfomuseum:publication": ": , early 1970s.",
    "sfomuseum:subcategory": "Advertisement, 2D",
    "wof:depicts": [
      1159293593,
      1159284989,
      1159286839,
      1159289873
    ],
    "wof:name": "advertisement: Pan American World Airways, Boeing 747",
    "wof:placetype": "custom",
    "wof:placetype_alt": "object"
  },
  "geometry": {"coordinates":[-122.386155,37.616357],"type":"Point"}
}
