{
  "type": "Feature",
  "properties": {
    "date:cessation_lower":"1970-12-31",
    "date:cessation_upper":"1970-12-31",
    "date:inception_lower":"1970-01-01",
    "date:inception_upper":"1970-01-01",
    "iso:country":"XX",
    "millsfield:images":[
        1527853429
    ],
    "sfomuseum:accession_number":"2012.149.0797",
    "sfomuseum:category":"Promotional",
    "sfomuseum:collection":"Aviation Archive",
    "sfomuseum:creditline":"Gift of the Captain John B. Russell Family",
    "sfomuseum:date":"early 1970s",
    "sfomuseum:daterange_end":"1970-04-30",
    "sfomuseum:daterange_start":"1970-01-01",
    "sfomuseum:description":"Color advertisement promoting Pan American World Airways Boeing 747 aircraft fleet with main caption, \u201cWhether you\u2019re 3\u20197\u201d or 7\u20193\u201d with full spread photographic image depicting in-flight scene on wide-body jet; tall businessman asleep with outstretched legs across four seats as young girl in row behind peers over headrest.",
    "sfomuseum:media_ids":[
        1527853429
    ],
    "sfomuseum:medium":"paper, ink",
    "sfomuseum:placetype":"object",
    "sfomuseum:subcategory":"Advertisement, 2D",
    "wof:depicts":[
        1159289873,
        1159293593
    ],
    "wof:name":"advertisement: Pan American World Airways, Boeing 747",
    "wof:placetype":"venue"
},
  "geometry": {"coordinates":[-122.386155,37.616358],"type":"Point"}
}