{
  "type": "Feature",
  "properties": {
    "date:cessation_lower": "1989-01-01",
    "date:cessation_upper": "1989-12-31",
    "date:inception_lower": "1989-01-01",
    "date:inception_upper": "1989-12-31",
    "iso:country": "XX",
    "millsfield:images": [
      1527841817
    ],
    "millsfield:images_texts": [
      "PANAM\nCHED\nULE\nEFFECTIVE OCTOBER 29, 1989\nWere growing\nin Florida.\nNassau •\n• Boston\nNew service\nNew service\nAntigua\nSan Juan\nNew service\nMiami\nNew service\nNew York ®\nSt. Maarten\nAdded service\nNew service\nCharlotte\nNew service\nPhiladelphia\nNew service\nGrand Cayman\nRaleigh/Durham\nNew service\nNew service\nNow flying to over 100 cities from Miami."
    ],
    "millsfield:images_texts_ids": [
      1527841817
    ],
    "millsfield:primary_image": 1527841817,
    "sfomuseum:accession_number": "2008.108.613",
    "sfomuseum:airline": "Pan American World Airways",
    "sfomuseum:category": "Scheduling / Ticketing",
    "sfomuseum:collection": "Aviation Archive",
    "sfomuseum:creditline": "Gift of the William Hough Collection",
    "sfomuseum:date": "1989",
    "sfomuseum:date_acquired": "2008-11-10",
    "sfomuseum:daterange_end": "1989-12-31",
    "sfomuseum:daterange_start": "1989-01-01",
    "sfomuseum:description": "Timetable issued by Pan American World Airways, effective October 29, 1989; blue and white cover with illustration of a palm tree with text “We’re growing in Florida” and list of destinations from Miami.",
    "sfomuseum:dimensions": "9 x 4 inches (22.9 x 10.2 cm)",
    "sfomuseum:media_ids": [
      1527841817
    ],
    "sfomuseum:medium": "paper, ink",
    "sfomuseum:placetype": "object",
    "sfomuseum:publication": ": , 1989.",
    "sfomuseum:subcategory": "Timetable",
    "sfomuseum:subject": "Airlines -- Commercial -- Pan American Airways",
    "wof:depicts": [
      1159286839,
      1159284989
    ],
    "wof:name": "timetable: Pan American World Airways",
    "wof:placetype": "custom",
    "wof:placetype_alt": [
      "object"
    ]
  },
  "geometry": {"coordinates":[-122.386155,37.616357],"type":"Point"}
}
