{
  "type": "Feature",
  "properties": {
    "date:cessation_lower": "1938-01-01",
    "date:cessation_upper": "1938-12-31",
    "date:inception_lower": "1938-01-01",
    "date:inception_upper": "1938-12-31",
    "iso:country": "XX",
    "millsfield:images": [
      1729565305
    ],
    "sfomuseum:accession_number": "2006.025.012",
    "sfomuseum:aircraft": "Douglas DC-3",
    "sfomuseum:airline": "Transcontinental \u0026 Western Air",
    "sfomuseum:category": "Photograph",
    "sfomuseum:collection": "Aviation Archive",
    "sfomuseum:creditline": "Gift of Denis Neumann",
    "sfomuseum:date": "1938",
    "sfomuseum:daterange_end": "1938-12-31",
    "sfomuseum:daterange_start": "1938-01-01",
    "sfomuseum:description": "Black and white photograph depicting Transcontinental \u0026 Western Air (TWA) flight captain Harold Neumann receiving box of cigars from man upon announcement of birth of his son Denis Neumann, August 5, 1938; standing on stairway in front of Douglas DC-3.",
    "sfomuseum:dimensions": "10 x 8 inches (25.4 x 20.3 cm)",
    "sfomuseum:medium": "photograph, ink",
    "sfomuseum:placetype": "object",
    "sfomuseum:publisher": "TWA Master Executive Council",
    "sfomuseum:publisher_location": "New York",
    "sfomuseum:subcategory": "Print, Photograph",
    "sfomuseum:subject": "Trans World Airlines.",
    "wof:depicts": [
      1159290417,
      1159285395
    ],
    "wof:name": "photograph: Transcontinental \u0026 Western Air (TWA), Douglas DC-3, Harold Earnest Neumann",
    "wof:placetype": "venue"
  },
  "geometry": {"coordinates":[-122.386155,37.616357],"type":"Point"}
}
