{
  "type": "Feature",
  "properties": {
    "date:cessation_lower": "1999-01-01",
    "date:cessation_upper": "1999-12-31",
    "date:inception_lower": "1999-01-01",
    "date:inception_upper": "1999-12-31",
    "iso:country": "XX",
    "millsfield:images": [
      1527840517
    ],
    "millsfield:primary_image": 1527840517,
    "sfomuseum:accession_number": "2006.059.101.088",
    "sfomuseum:airline": "United Airlines",
    "sfomuseum:category": "Scheduling / Ticketing",
    "sfomuseum:collection": "Aviation Archive",
    "sfomuseum:creditline": "Gift of the Paul Edward Fair Estate",
    "sfomuseum:date": "1999",
    "sfomuseum:date_acquired": "2006-10-19",
    "sfomuseum:daterange_end": "1999-12-31",
    "sfomuseum:daterange_start": "1999-01-01",
    "sfomuseum:description": "Worldwide timetable issued by United Airlines, effective September 7 through October 30, 1999; on cover: color photographic image of a skier in motion on slope; includes United Express and Shuttle by United.",
    "sfomuseum:dimensions": "8 1/2 x 4 inches (21.6 x 10.2 cm)",
    "sfomuseum:media_ids": [
      1527840517
    ],
    "sfomuseum:medium": "paper, ink",
    "sfomuseum:placetype": "object",
    "sfomuseum:publication": ": , 1999.",
    "sfomuseum:subcategory": "Timetable",
    "wof:depicts": [
      1159285413,
      1159285417,
      1159288779,
      1159285423
    ],
    "wof:name": "timetable: United Airlines",
    "wof:placetype": "custom",
    "wof:placetype_alt": "object"
  },
  "geometry": {"coordinates":[-122.386155,37.616357],"type":"Point"}
}
