{
  "type": "Feature",
  "properties": {
    "date:cessation_lower": "1992-12-31",
    "date:cessation_upper": "1992-12-31",
    "date:inception_lower": "1992-01-01",
    "date:inception_upper": "1992-01-01",
    "iso:country": "XX",
    "sfomuseum:accession_number": "2008.108.882",
    "sfomuseum:category": "Scheduling / Ticketing",
    "sfomuseum:collection": "Aviation Archive",
    "sfomuseum:creditline": "Gift of the William Hough Collection",
    "sfomuseum:date": "1992",
    "sfomuseum:daterange_end": "1992-12-31",
    "sfomuseum:daterange_start": "1992-01-01",
    "sfomuseum:description": "System timetable issued by USAir, effective November 1, 1992; blue and white cover with illustration of clock and calendar.",
    "sfomuseum:media_ids": [
      1527842995
    ],
    "sfomuseum:medium": "paper, ink",
    "sfomuseum:placetype": "object",
    "sfomuseum:subcategory": "Timetable",
    "wof:name": "timetable: USAir",
    "wof:placetype": "venue"
  },
  "geometry": {"coordinates":[-122.386155,37.616358],"type":"Point"}
}
