{
  "type": "Feature",
  "properties": {
    "date:cessation_lower": "1935-12-02",
    "date:cessation_upper": "1935-12-02",
    "date:inception_lower": "1935-12-02",
    "date:inception_upper": "1935-12-02",
    "iso:country": "PH",
    "millsfield:images": [
      1527828947,
      1527828949
    ],
    "millsfield:images_texts": [
      "FIRST FLIGHT\nPHILIPPINES - 8, S.\nWaxe Is\nVIA PAN-AMERICAN AIDWAYS\nCLIPPER DEC21935\nPOSTAG\nVIA AIR MAIL\nMr. J.T.\nTrippe, President\nPan American Airways System,\nHonolulu, I.H.",
      "DEC 4\nNOH\n7 - PM.\n7y\n35\n200/20\nBUY U.S. SAVINGS\nBONDS\nASK YOUR POSTMASTER"
    ],
    "millsfield:images_texts_ids": [
      1527828947,
      1527828949
    ],
    "millsfield:primary_image": 1527828947,
    "sfomuseum:accession_number": "1994.18.023",
    "sfomuseum:airline": "Pan American Airways",
    "sfomuseum:category": "Philately",
    "sfomuseum:collection": "Aviation Archive",
    "sfomuseum:continent": "Transpacific",
    "sfomuseum:country": "Philippines",
    "sfomuseum:creditline": "Collection of SFO Museum",
    "sfomuseum:date": "12/2/1935",
    "sfomuseum:date_acquired": "1994-06-29",
    "sfomuseum:daterange_end": "1935-12-02",
    "sfomuseum:daterange_start": "1935-12-02",
    "sfomuseum:description": "Airmail flight cover commemorating first Pan American Airways flight from the Philippines to the United States, Manila to Honolulu leg; black cachet with image of route map over the Pacific Ocean; two stamps: purple 6-centavo and orange/black 1-peso (Commonwealth of the Philippines); postmark: December 2, 1935, Manila; type 5x killer \"Manila Trade Center of the Pacific\"; backstamp: December 4, 1935, Honolulu; type 5x killer \"Buy U.S. Savings Bonds\"; envelope: border type I \"VIA AIR MAIL\"; addressed to \"Mr. J. T. Trippe”.",
    "sfomuseum:dimensions": "4 1/8 x 9 1/2 inches (10.5 x 24.1 cm)",
    "sfomuseum:maker": "Pan American Airways, Inc.",
    "sfomuseum:media_ids": [
      1527828947,
      1527828949
    ],
    "sfomuseum:medium": "paper, ink",
    "sfomuseum:placetype": "object",
    "sfomuseum:publication": ": , 12/2/1935.",
    "sfomuseum:subcategory": "Airmail Flight Cover",
    "wof:depicts": [
      1159284991,
      1159286839
    ],
    "wof:name": "airmail flight cover: Pan American Airways, Philippines - United States route",
    "wof:placetype": "custom",
    "wof:placetype_alt": "object"
  },
  "geometry": {"coordinates":[-122.386155,37.616357],"type":"Point"}
}
