{
  "type": "Feature",
  "properties": {
    "date:cessation_lower":"1935-12-31",
    "date:cessation_upper":"1935-12-31",
    "date:inception_lower":"1935-01-01",
    "date:inception_upper":"1935-01-01",
    "iso:country":"PH",
    "sfomuseum:accession_number":"1994.18.023",
    "sfomuseum:category":"Philately",
    "sfomuseum:collection":"Aviation Archive",
    "sfomuseum:continent":"Transpacific",
    "sfomuseum:country":"Philippines",
    "sfomuseum:creditline":"Purchase",
    "sfomuseum:date":"12/2/1935",
    "sfomuseum:daterange_end":"1935-12-02",
    "sfomuseum:daterange_start":"1935-12-02",
    "sfomuseum:description":"Airmail flight cover commemorating first Pan American Airways flight from the Philippines to the United States, Manila to Honolulu leg; black cachet with image of route map over the Pacific Ocean; two stamps: purple 6-centavo and orange/black 1-peso (Commonwealth of the Philippines); postmark: December 2, 1935, Manila; type 5x killer \"Manila Trade Center of the Pacific\"; backstamp: December 4, 1935, Honolulu; type 5x killer \"Buy U.S. Savings Bonds\"; envelope: border type I \"VIA AIR MAIL\"; addressed to \"Mr. J. T. Trippe\u201d.",
    "sfomuseum:maker":"Pan American Airways, Inc.",
    "sfomuseum:medium":"ink on paper",
    "sfomuseum:placetype":"object",
    "sfomuseum:subcategory":"Airmail Flight Cover",
    "wof:name":"airmail flight cover: Pan American Airways, Philippines - United States route",
    "wof:placetype":"venue"
},
  "geometry": {"coordinates":[-122.386155,37.616358],"type":"Point"}
}