{
  "type": "Feature",
  "properties": {
    "date:cessation_lower": "1931-01-01",
    "date:cessation_upper": "1931-12-31",
    "date:inception_lower": "1931-01-01",
    "date:inception_upper": "1931-12-31",
    "iso:country": "XX",
    "sfomuseum:accession_number": "2000.160.0079",
    "sfomuseum:author": "Med ËOrnen mot polen. English",
    "sfomuseum:callnumber": "TL620.A65 M4313 1931 SC",
    "sfomuseum:category": "Book",
    "sfomuseum:collection": "Aviation Library",
    "sfomuseum:creditline": "The Tony Bill Aviation Library Collection",
    "sfomuseum:date": "1931",
    "sfomuseum:daterange_end": "1931-12-31",
    "sfomuseum:daterange_start": "1931-01-01",
    "sfomuseum:description": "xx, 471 p., [1] folded leaf of plates : ill., maps (1 col.), facsims. ; 23 cm.",
    "sfomuseum:medium": "paper, ink",
    "sfomuseum:placetype": "object",
    "sfomuseum:publisher": "John Lane, the Bodley Head",
    "sfomuseum:publisher_location": "London",
    "sfomuseum:subcategory": "Book",
    "sfomuseum:subject": "Strindberg, Nils, 1872-1897.Frµnkel, Knut Hjalmar Ferdinand, 1870-1897.Andr‚ee, Salomon August, 1854-1897.Andr‚ee Expedition (1897)Balloon ascensions Arctic regions.Balloonists Sweden Diaries.Balloonists Sweden Biography.Arctic regions Discovery and exploration Swedish.Arctic regions Aerial exploration.",
    "wof:name": "The Andree diaries: being the diaries and records of S.A. Andree, Nils Strindberg and Knut Fraenkel, written during their balloon expedition to the North Pole in 1897 and discovered on White Island in 1930, together with a complete record of the expedition and discovery",
    "wof:placetype": "venue"
  },
  "geometry": {"coordinates":[-122.386155,37.616357],"type":"Point"}
}
