{
  "type": "Feature",
  "properties": {
    "date:cessation_lower": "1999-01-01",
    "date:cessation_upper": "1999-12-31",
    "date:inception_lower": "1999-01-01",
    "date:inception_upper": "1999-12-31",
    "iso:country": "XX",
    "sfomuseum:accession_number": "2002.031.018",
    "sfomuseum:author": "Burden, Maria Schell",
    "sfomuseum:callnumber": "TL540.F68 B87 1999",
    "sfomuseum:category": "Book",
    "sfomuseum:collection": "Aviation Library",
    "sfomuseum:creditline": "Purchase",
    "sfomuseum:date": "c. 1999",
    "sfomuseum:date_acquired": "1997-01-10",
    "sfomuseum:daterange_end": "2004-12-31",
    "sfomuseum:daterange_start": "1994-01-01",
    "sfomuseum:description": "157 p. : ill. ; 22 cm.",
    "sfomuseum:description_library": "157 p. : ill. ; 22 cm.",
    "sfomuseum:medium": "paper, ink",
    "sfomuseum:placetype": "object",
    "sfomuseum:publication": "Los Angeles: Borden, c. 1999.",
    "sfomuseum:publisher": "Borden",
    "sfomuseum:publisher_location": "Los Angeles",
    "sfomuseum:subcategory": "Book",
    "sfomuseum:subject": "Fowler, Robert G.Aeronautics United States History.",
    "wof:name": "The life and times of Robert G. Fowler: a pictorial history",
    "wof:placetype": "custom",
    "wof:placetype_alt": "object"
  },
  "geometry": {"coordinates":[-122.386155,37.616357],"type":"Point"}
}
