{
  "type": "Feature",
  "properties": {
    "date:cessation_lower": "1995-01-01",
    "date:cessation_upper": "1995-12-31",
    "date:inception_lower": "1995-01-01",
    "date:inception_upper": "1995-12-31",
    "iso:country": "XX",
    "millsfield:images": [
      1527845169,
      1527845171
    ],
    "millsfield:primary_image": 1527845169,
    "sfomuseum:accession_number": "2001.080.136",
    "sfomuseum:airline": "Northwest Airlines",
    "sfomuseum:artist": "Charles Waldo Love",
    "sfomuseum:category": "Passenger Amenity",
    "sfomuseum:collection": "Aviation Archive",
    "sfomuseum:continent": "World Routes",
    "sfomuseum:creditline": "Gift of Thomas G. Dragges",
    "sfomuseum:date": "c. 1995",
    "sfomuseum:date_acquired": "2002-12-24",
    "sfomuseum:daterange_end": "2000-12-31",
    "sfomuseum:daterange_start": "1990-01-01",
    "sfomuseum:description": "Menu issued by Northwest Airlines, London - North America route; white cover with color reproduction of painting of Monument Valley; menu items include saffron chicken, sole Meuniere, and grilled beef; menu number: LGW/MSP, BOS, DTW 2; class: business; undated.",
    "sfomuseum:dimensions": "11 x 6 1/4 inches (27.9 x 15.9 cm)",
    "sfomuseum:media_ids": [
      1527845169,
      1527845171
    ],
    "sfomuseum:medium": "paper, ink",
    "sfomuseum:placetype": "object",
    "sfomuseum:publication": ": , c. 1995.",
    "sfomuseum:subcategory": "Menu",
    "wof:depicts": [
      1159284907
    ],
    "wof:name": "menu: Northwest Airlines, Business Class",
    "wof:placetype": "venue"
  },
  "geometry": {"coordinates":[-122.386155,37.616357],"type":"Point"}
}
