{
  "type": "Feature",
  "properties": {
    "date:cessation_lower":"2000-12-31",
    "date:cessation_upper":"2000-12-31",
    "date:inception_lower":"1990-01-01",
    "date:inception_upper":"1990-01-01",
    "iso:country":"XX",
    "sfomuseum:accession_number":"2001.080.136",
    "sfomuseum:artist":"Charles Waldo Love",
    "sfomuseum:category":"Food Service",
    "sfomuseum:collection":"Aviation Museum",
    "sfomuseum:continent":"World Routes",
    "sfomuseum:creditline":"Gift of Thomas G. Dragges",
    "sfomuseum:date":"c. 1995",
    "sfomuseum:daterange_end":"2000-12-31",
    "sfomuseum:daterange_start":"1990-01-01",
    "sfomuseum:description":"Menu produced by Northwest Airlines, London - North America route; white cover with color reproduction of painting of Monument Valley; menu items include saffron chicken, sole Meuniere, and grilled beef; menu number: LGW/MSP, BOS, DTW 2; class: business; undated.",
    "sfomuseum:media_ids":[
        1527845169,
        1527845171
    ],
    "sfomuseum:medium":"paper, ink",
    "sfomuseum:placetype":"object",
    "sfomuseum:subcategory":"Menu",
    "wof:name":"menu: Northwest Airlines, Business Class",
    "wof:placetype":"venue"
},
  "geometry": {"coordinates":[-122.386155,37.616358],"type":"Point"}
}