{
  "type": "Feature",
  "properties": {
    "date:cessation_lower": "1993-01-01",
    "date:cessation_upper": "1993-12-31",
    "date:inception_lower": "1993-01-01",
    "date:inception_upper": "1993-12-31",
    "iso:country": "XX",
    "loc:named_authorities": [
      "n78095330"
    ],
    "loc:subject_headings": [
      "sh95007473"
    ],
    "sfomuseum:accession_number": "99-0866",
    "sfomuseum:author": "Rich, Doris L.",
    "sfomuseum:callnumber": "TL540.C646 R52 1993",
    "sfomuseum:category": "Book",
    "sfomuseum:collection": "Aviation Library",
    "sfomuseum:date": "c. 1993",
    "sfomuseum:daterange_end": "1998-12-31",
    "sfomuseum:daterange_start": "1988-01-01",
    "sfomuseum:description": "xiv, 153 p., [16] p. of plates : ill. ; 24 cm.",
    "sfomuseum:description_library": "xiv, 153 p., [16] p. of plates : ill. ; 24 cm.",
    "sfomuseum:medium": "paper, ink",
    "sfomuseum:notes_library": "Includes bibliographical references (p. 137-141) and index.",
    "sfomuseum:placetype": "object",
    "sfomuseum:publication": "Washington, D.C.: Smithsonian Institution Press, c. 1993.",
    "sfomuseum:publisher": "Smithsonian Institution Press",
    "sfomuseum:publisher_location": "Washington, D.C.",
    "sfomuseum:subcategory": "Book",
    "sfomuseum:subject": "Coleman, Bessie, 1896-1926.\rAfrican American women air pilots \rBiography. \rUnited States\rFlying (Aircraft)",
    "wof:name": "Queen Bess: daredevil aviator",
    "wof:placetype": "custom"
  },
  "geometry": {"coordinates":[-122.386155,37.616357],"type":"Point"}
}
