{
  "type": "Feature",
  "properties": {
    "date:cessation_lower": "2004-01-01",
    "date:cessation_upper": "2004-12-31",
    "date:inception_lower": "2004-01-01",
    "date:inception_upper": "2004-12-31",
    "iso:country": "XX",
    "sfomuseum:accession_number": "2008.055.019",
    "sfomuseum:author": "Sapienza, Antonio Luis",
    "sfomuseum:callnumber": "HE9838.L56 S27 2004",
    "sfomuseum:category": "Book",
    "sfomuseum:collection": "Aviation Library",
    "sfomuseum:creditline": "Gift of the William Hough Collection",
    "sfomuseum:date": "2004",
    "sfomuseum:date_acquired": "2008-04-13",
    "sfomuseum:daterange_end": "2004-12-31",
    "sfomuseum:daterange_start": "2004-01-01",
    "sfomuseum:description": "542 p. : ill. ; 22 cm.",
    "sfomuseum:description_library": "542 p. : ill. ; 22 cm.",
    "sfomuseum:medium": "paper, ink",
    "sfomuseum:placetype": "object",
    "sfomuseum:publication": "Asuncion: [s.n.], 2004.",
    "sfomuseum:publisher": "[s.n.]",
    "sfomuseum:publisher_location": "Asuncion",
    "sfomuseum:subcategory": "Book",
    "sfomuseum:subject": "L‚ineas A‚ereas Paraguayas History.",
    "wof:name": "La historia de Lineas Aereas Paraguayas",
    "wof:placetype": "venue"
  },
  "geometry": {"coordinates":[-122.386155,37.616357],"type":"Point"}
}
