{
  "type": "Feature",
  "properties": {
    "date:cessation_lower":"1982-12-31",
    "date:cessation_upper":"1982-12-31",
    "date:inception_lower":"1982-01-01",
    "date:inception_upper":"1982-01-01",
    "iso:country":"XX",
    "sfomuseum:accession_number":"2009.122.368",
    "sfomuseum:category":"Scheduling / Ticketing",
    "sfomuseum:collection":"Aviation Archive",
    "sfomuseum:creditline":"Gift of the William Hough Collection",
    "sfomuseum:date":"1982",
    "sfomuseum:daterange_end":"1982-12-31",
    "sfomuseum:daterange_start":"1982-01-01",
    "sfomuseum:description":"Timetable issued by JAL (Japan Air Lines), effective April 1 through June 30, 1982; one hundred and ninety-one page schedule. The cover is blue with the company name at the top. A large company logo is in a white square in the center. There is also a flight of solid red birds at the bottom. In Japanese, French, Spanish and English.",
    "sfomuseum:medium":"paper, ink",
    "sfomuseum:placetype":"object",
    "sfomuseum:subcategory":"Timetable",
    "wof:name":"timetable: JAL (Japan Air Lines)",
    "wof:placetype":"venue"
},
  "geometry": {"coordinates":[-122.386155,37.616358],"type":"Point"}
}