{
  "type": "Feature",
  "properties": {
    "date:cessation_lower": "2000-12-31",
    "date:cessation_upper": "2000-12-31",
    "date:inception_lower": "2000-01-01",
    "date:inception_upper": "2000-01-01",
    "iso:country": "XX",
    "millsfield:images": [
      1527845469,
      1527845467
    ],
    "sfomuseum:accession_number": "2006.034.128",
    "sfomuseum:airline": "Singapore Airlines",
    "sfomuseum:category": "Passenger Amenity",
    "sfomuseum:collection": "Aviation Archive",
    "sfomuseum:creditline": "Gift of Adan Wong",
    "sfomuseum:date": "2000s",
    "sfomuseum:daterange_end": "2000-12-31",
    "sfomuseum:daterange_start": "2000-01-01",
    "sfomuseum:description": "Menu issued by Singapore Airlines, Singapore - Seoul - San Francisco route; purple cover; menu items include poached salmon, sauteed prawns, and egg fritatta; menu number: MAR-JUN EY SQ16 SIN-SEL-SFO (L/D/HB); class: economy; undated.",
    "sfomuseum:media_ids": [
      1527845467,
      1527845469
    ],
    "sfomuseum:medium": "paper, ink, metal",
    "sfomuseum:placetype": "object",
    "sfomuseum:subcategory": "Menu",
    "wof:depicts": [
      1159285163
    ],
    "wof:name": "menu: Singapore Airlines, Economy Class",
    "wof:placetype": "venue"
  },
  "geometry": {"coordinates":[-122.386155,37.616357],"type":"Point"}
}
