{
  "type": "Feature",
  "properties": {
    "date:cessation_lower": "1970-01-01",
    "date:cessation_upper": "1979-12-31",
    "date:inception_lower": "1970-01-01",
    "date:inception_upper": "1979-12-31",
    "iso:country": "XX",
    "millsfield:images": [
      1527858537
    ],
    "millsfield:primary_image": 1527858537,
    "sfomuseum:accession_number": "2001.106.011",
    "sfomuseum:airline": "Continental Airlines",
    "sfomuseum:category": "Beverage Service",
    "sfomuseum:collection": "Aviation Museum",
    "sfomuseum:continent": "World Routes",
    "sfomuseum:creditline": "Gift of Mark F. Adams Collection",
    "sfomuseum:date": "1970s",
    "sfomuseum:date_acquired": "2001-10-18",
    "sfomuseum:daterange_end": "1979-12-31",
    "sfomuseum:daterange_start": "1970-01-01",
    "sfomuseum:description": "Wine glass issued by Continental Airlines for inflight beverage service; footed stemmed glass with white stripe on center and logo on side.\r\rClear wine glass with bowl of glass wider towards stem and narrowing towards rim; stem is straight and ends in round foot; white stripe around bowl of glass near top center with Continental Airlines jetstream logo in white on one side of glass. ",
    "sfomuseum:dimensions": "5 1/2 x 2 3/4 x 2 3/4 inches (14 x 7 x 7 cm)",
    "sfomuseum:media_ids": [
      1527858537
    ],
    "sfomuseum:medium": "glass",
    "sfomuseum:placetype": "object",
    "sfomuseum:publication": ": , 1970s.",
    "sfomuseum:subcategory": "Stemware",
    "wof:depicts": [
      1159284201
    ],
    "wof:name": "wine glass: Continental Airlines",
    "wof:placetype": "venue"
  },
  "geometry": {"coordinates":[-122.386155,37.616357],"type":"Point"}
}
