{
  "type": "Feature",
  "properties": {
    "date:cessation_lower": "1941-01-01",
    "date:cessation_upper": "1941-12-31",
    "date:inception_lower": "1941-01-01",
    "date:inception_upper": "1941-12-31",
    "iso:country": "XX",
    "sfomuseum:accession_number": "2001.038.164.013",
    "sfomuseum:airline": "Pan American Airways System",
    "sfomuseum:category": "Promotional",
    "sfomuseum:collection": "Aviation Archive",
    "sfomuseum:creditline": "Gift of Barnaby Conrad III",
    "sfomuseum:date": "1941",
    "sfomuseum:date_acquired": "2003-05-16",
    "sfomuseum:daterange_end": "1941-12-31",
    "sfomuseum:daterange_start": "1941-01-01",
    "sfomuseum:description": "Two-page advertisement from November 22, 1941 issue of Saturday Evening Post promoting Pan American Airways System, titled “America’s New Lifeline to Africa”; color illustration depicting aircraft engine hoisted by crane on African port; Boeing 314 in flight overhead.",
    "sfomuseum:dimensions": "13 3/4 x 21 inches (34.9 x 53.3 cm)",
    "sfomuseum:medium": "paper, ink",
    "sfomuseum:placetype": "object",
    "sfomuseum:publication": ": , 1941.",
    "sfomuseum:subcategory": "Advertisement, 2D",
    "sfomuseum:subject": "Pan Am promotional advertisement",
    "wof:depicts": [
      1159285809,
      1159286839,
      1159284991
    ],
    "wof:name": "advertisement: Pan American Airways System, Saturday Evening Post",
    "wof:placetype": "venue"
  },
  "geometry": {"coordinates":[-122.386155,37.616357],"type":"Point"}
}
