{
  "type": "Feature",
  "properties": {
    "date:cessation_lower": "1916-01-01",
    "date:cessation_upper": "1916-12-31",
    "date:inception_lower": "1916-01-01",
    "date:inception_upper": "1916-12-31",
    "iso:country": "XX",
    "sfomuseum:accession_number": "2000.160.0915",
    "sfomuseum:author": "Robson, William Alexander",
    "sfomuseum:callnumber": "TL545 .R76 1916 SC",
    "sfomuseum:category": "Book",
    "sfomuseum:collection": "Aviation Library",
    "sfomuseum:creditline": "The Tony Bill Aviation Library Collection",
    "sfomuseum:date": "1916",
    "sfomuseum:date_acquired": "1999-05-18",
    "sfomuseum:daterange_end": "1916-12-31",
    "sfomuseum:daterange_start": "1916-01-01",
    "sfomuseum:description": "xi, 176 p. front., plates. 19 cm.",
    "sfomuseum:description_library": "xi, 176 p. front., plates. 19 cm.",
    "sfomuseum:medium": "paper, ink",
    "sfomuseum:placetype": "object",
    "sfomuseum:publication": "London: Macmillan, 1916.",
    "sfomuseum:publisher": "Macmillan",
    "sfomuseum:publisher_location": "London",
    "sfomuseum:subcategory": "Book",
    "sfomuseum:subject": "World War, 1914-1918 Aerial operations.Aeronautics, Military.Airplanes.Airships.",
    "wof:name": "Aircraft in war and peace",
    "wof:placetype": "custom",
    "wof:placetype_alt": "object"
  },
  "geometry": {"coordinates":[-122.386155,37.616357],"type":"Point"}
}
