{
  "type": "Feature",
  "properties": {
    "date:cessation_lower": "1992-01-01",
    "date:cessation_upper": "1992-12-31",
    "date:inception_lower": "1992-01-01",
    "date:inception_upper": "1992-12-31",
    "iso:country": "XX",
    "millsfield:images": [
      1527843761,
      1527843765
    ],
    "millsfield:primary_image": 1527843761,
    "sfomuseum:accession_number": "2006.034.064",
    "sfomuseum:airline": "Cathay Pacific Airways",
    "sfomuseum:category": "Passenger Amenity",
    "sfomuseum:collection": "Aviation Archive",
    "sfomuseum:creditline": "Gift of Adan Wong",
    "sfomuseum:date": "1992",
    "sfomuseum:daterange_end": "1992-12-31",
    "sfomuseum:daterange_start": "1992-01-01",
    "sfomuseum:description": "Wine list issued by Cathay Pacific Airways; white cover with blue and black reproductions of woodprints about winemaking; menu number: CX838, 839, 880, 881; class: Marco Polo (business); date: 1-5-92.",
    "sfomuseum:dimensions": "10 x 6 3/4 inches (25.4 x 17.1 cm)",
    "sfomuseum:media_ids": [
      1527843761,
      1527843765
    ],
    "sfomuseum:medium": "paper, ink",
    "sfomuseum:placetype": "object",
    "sfomuseum:subcategory": "Menu",
    "wof:depicts": [
      1159284127
    ],
    "wof:name": "menu: Cathay Pacific Airways, Marco Polo (Business) Class",
    "wof:placetype": "venue"
  },
  "geometry": {"coordinates":[-122.386155,37.616357],"type":"Point"}
}
