{
  "type": "Feature",
  "properties": {
    "date:cessation_lower":"1992-12-31",
    "date:cessation_upper":"1992-12-31",
    "date:inception_lower":"1992-01-01",
    "date:inception_upper":"1992-01-01",
    "iso:country":"XX",
    "sfomuseum:accession_number":"2006.034.064",
    "sfomuseum:category":"Food Service",
    "sfomuseum:collection":"Aviation Museum",
    "sfomuseum:creditline":"Gift of Adan Wong",
    "sfomuseum:date":"1992",
    "sfomuseum:daterange_end":"1992-12-31",
    "sfomuseum:daterange_start":"1992-01-01",
    "sfomuseum:description":"Wine list produced by Cathay Pacific Airways; white cover with blue and black reproductions of woodprints about winemaking; menu number: CX838, 839, 880, 881; class: Marco Polo (business); date: 1-5-92.",
    "sfomuseum:medium":"paper, ink",
    "sfomuseum:placetype":"object",
    "sfomuseum:subcategory":"Menu",
    "wof:name":"menu: Cathay Pacific Airways, Marco Polo (Business) Class",
    "wof:placetype":"venue"
},
  "geometry": {"coordinates":[-122.386155,37.616358],"type":"Point"}
}