{
  "type": "Feature",
  "properties": {
    "date:cessation_lower": "1940-01-01",
    "date:cessation_upper": "1949-12-31",
    "date:inception_lower": "1940-01-01",
    "date:inception_upper": "1949-12-31",
    "iso:country": "XX",
    "millsfield:images": [
      1763372725
    ],
    "millsfield:primary_image": 1763372725,
    "sfomuseum:accession_number": "2006.028.101",
    "sfomuseum:airline": "Pennsylvania Central Airlines",
    "sfomuseum:category": "Meal Service",
    "sfomuseum:collection": "Aviation Museum",
    "sfomuseum:creditline": "Gift of Edith Lauterbach",
    "sfomuseum:date": "1940s",
    "sfomuseum:date_acquired": "2006-04-18",
    "sfomuseum:daterange_end": "1949-12-31",
    "sfomuseum:daterange_start": "1940-01-01",
    "sfomuseum:description": "Fork issued by Pennsylvania Central Airlines for inflight meal service; silver fork with logo stamped on tapered handle.",
    "sfomuseum:dimensions": "6 1/4 x 3/4 x 1/2 inches (15.9 x 1.9 x 1.3 cm)",
    "sfomuseum:maker": "International Silver Company",
    "sfomuseum:medium": "metal",
    "sfomuseum:placetype": "object",
    "sfomuseum:publication": ": , 1940s.",
    "sfomuseum:subcategory": "Flatware",
    "wof:depicts": [
      1159285009,
      1159288787
    ],
    "wof:name": "fork: Pennsylvania Central Airlines",
    "wof:placetype": "custom",
    "wof:placetype_alt": "object"
  },
  "geometry": {"coordinates":[-122.386155,37.616357],"type":"Point"}
}
