{
  "type": "Feature",
  "properties": {
    "date:cessation_lower": "1998-01-01",
    "date:cessation_upper": "1998-12-31",
    "date:inception_lower": "1998-01-01",
    "date:inception_upper": "1998-12-31",
    "iso:country": "XX",
    "sfomuseum:accession_number": "2009.174.001",
    "sfomuseum:author": "Guttery, Ben R.",
    "sfomuseum:callnumber": "HE9882.A35 G88 1998",
    "sfomuseum:category": "Book",
    "sfomuseum:collection": "Aviation Library",
    "sfomuseum:creditline": "Gift of Frank A. Norick",
    "sfomuseum:date": "1998",
    "sfomuseum:date_acquired": "2009-12-31",
    "sfomuseum:daterange_end": "1998-12-31",
    "sfomuseum:daterange_start": "1998-01-01",
    "sfomuseum:description": "xvi, 291 p. : ill. ; 26 cm.",
    "sfomuseum:description_library": "xvi, 291 p. : ill. ; 26 cm.",
    "sfomuseum:medium": "paper, ink",
    "sfomuseum:notes_library": "Includes bibliographical references (p. 243-262) and index.",
    "sfomuseum:placetype": "object",
    "sfomuseum:publication": "Jefferson, NC: McFarland, 1998.",
    "sfomuseum:publisher": "McFarland",
    "sfomuseum:publisher_location": "Jefferson, NC",
    "sfomuseum:subcategory": "Book",
    "sfomuseum:subject": "Aeronautics, Commercial -- Africa -- Encyclopedias. ",
    "wof:name": "Encyclopedia of African airlines",
    "wof:placetype": "custom"
  },
  "geometry": {"coordinates":[-122.386155,37.616357],"type":"Point"}
}
