{
  "type": "Feature",
  "properties": {
    "date:cessation_lower":"1950-12-31",
    "date:cessation_upper":"1950-12-31",
    "date:inception_lower":"1950-01-01",
    "date:inception_upper":"1950-01-01",
    "iso:country":"XX",
    "sfomuseum:accession_number":"2011.032.0188",
    "sfomuseum:category":"Photograph",
    "sfomuseum:collection":"Aviation Archive",
    "sfomuseum:creditline":"Transfer",
    "sfomuseum:date":"1950",
    "sfomuseum:daterange_end":"1950-12-31",
    "sfomuseum:daterange_start":"1950-01-01",
    "sfomuseum:description":"From attached handwritten note: \u201c03761 / 7-20-50 / Asphalt details on extension of TWX 3 / sta. 22+58 NE and 59+00\u201d. Black and white photograph of asphalt/ pavement with white streaks; San Francisco Airport; photograph taken on July 20, 1950.",
    "sfomuseum:medium":"negative",
    "sfomuseum:placetype":"object",
    "sfomuseum:subcategory":"Negative",
    "wof:name":"negative: San Francisco Airport, maintenance",
    "wof:placetype":"venue"
},
  "geometry": {"coordinates":[-122.386155,37.616358],"type":"Point"}
}