{
  "type": "Feature",
  "properties": {
    "date:cessation_lower": "1980-01-01",
    "date:cessation_upper": "1989-12-31",
    "date:inception_lower": "1980-01-01",
    "date:inception_upper": "1989-12-31",
    "iso:country": "XX",
    "millsfield:images": [
      1527819373
    ],
    "millsfield:primary_image": 1527819373,
    "sfomuseum:accession_number": "2001.146.134",
    "sfomuseum:airline": "TWA (Trans World Airlines)",
    "sfomuseum:category": "Promotional",
    "sfomuseum:collection": "Aviation Museum",
    "sfomuseum:creditline": "Gift of Thomas G. Dragges",
    "sfomuseum:date": "1980s",
    "sfomuseum:daterange_end": "1989-12-31",
    "sfomuseum:daterange_start": "1980-01-01",
    "sfomuseum:description": "Red bag with white piping and large \"TWA\" initials on both sides; two red handles with metal zipper closure.",
    "sfomuseum:dimensions": "4 x 7 x 3 inches (10.2 x 17.8 x 7.6 cm)",
    "sfomuseum:maker": "Airline Textile MFG., Co. ",
    "sfomuseum:media_ids": [
      1527819373
    ],
    "sfomuseum:medium": "vinyl, plastic, metal",
    "sfomuseum:placetype": "object",
    "sfomuseum:publication": ": , 1980s.",
    "sfomuseum:subcategory": "Airline Bag",
    "wof:depicts": [
      1159285393
    ],
    "wof:name": "miniature airline bag: TWA (Trans World Airlines)",
    "wof:placetype": "venue"
  },
  "geometry": {"coordinates":[-122.386155,37.616357],"type":"Point"}
}
