{
  "type": "Feature",
  "properties": {
    "date:cessation_lower": "1968-12-31",
    "date:cessation_upper": "1968-12-31",
    "date:inception_lower": "1968-01-01",
    "date:inception_upper": "1968-01-01",
    "geotag:angle": 29.79047760190474,
    "iso:country": "XX",
    "sfomuseum:accession_number": "2011.032.1629",
    "sfomuseum:category": "Photograph",
    "sfomuseum:collection": "Aviation Archive",
    "sfomuseum:creditline": "Transfer",
    "sfomuseum:date": "1968",
    "sfomuseum:daterange_end": "1968-12-31",
    "sfomuseum:daterange_start": "1968-01-01",
    "sfomuseum:description": "Black and white photographic negative depicting interior view of air traffic control tower cab, San Francisco International Airport (SFO); cab operators at work facing windows overlooking airfield and runways.",
    "sfomuseum:media_ids": [
      1527825983
    ],
    "sfomuseum:medium": "negative",
    "sfomuseum:placetype": "object",
    "sfomuseum:subcategory": "Negative",
    "wof:depicts": [
      102527513
    ],
    "wof:name": "negative: San Francisco International Airport (SFO), air traffic control tower",
    "wof:placetype": "venue"
  },
  "geometry": {
    "coordinates": [
      -122.38477706909181,
      37.61654136131665
    ],
    "type": "Point"
  }
}