{
  "type": "Feature",
  "properties": {
    "date:cessation_lower": "1934-01-01",
    "date:cessation_upper": "1934-12-31",
    "date:inception_lower": "1934-01-01",
    "date:inception_upper": "1934-12-31",
    "iso:country": "XX",
    "sfomuseum:accession_number": "2000.160.1292",
    "sfomuseum:author": "Mignet, Henri",
    "sfomuseum:callnumber": "TL686.M5 A4 1934 SC",
    "sfomuseum:category": "Book",
    "sfomuseum:collection": "Aviation Library",
    "sfomuseum:creditline": "The Tony Bill Aviation Library Collection",
    "sfomuseum:date": "1934",
    "sfomuseum:date_acquired": "1999-05-18",
    "sfomuseum:daterange_end": "1934-12-31",
    "sfomuseum:daterange_start": "1934-01-01",
    "sfomuseum:description": "444 p. : ill. (some col.), col. port. ; 25 cm.",
    "sfomuseum:description_library": "444 p. : ill. (some col.), col. port. ; 25 cm.",
    "sfomuseum:medium": "paper, ink",
    "sfomuseum:notes_library": "At head of title: L'aviation de l'amateur ...First published, Paris, 1930, under title: Comment j'ai construit mon avionnette.",
    "sfomuseum:placetype": "object",
    "sfomuseum:publication": "Paris: Imprimeie A. Taffin-Lefort, 1934.",
    "sfomuseum:publisher": "Imprimeie A. Taffin-Lefort",
    "sfomuseum:publisher_location": "Paris",
    "sfomuseum:subcategory": "Book",
    "sfomuseum:subject": "Aeronautics.Airplanes Design and construction.",
    "wof:name": "Le sport de l'air: pourquoi et comment j'ai construit le pou-du-ciel: le vol a voile cinetique des oiseaux: constructions, experiences, observations personnelles, croquis directs de l'auteur",
    "wof:placetype": "venue"
  },
  "geometry": {"coordinates":[-122.386155,37.616357],"type":"Point"}
}
