{
  "type": "Feature",
  "properties": {
    "date:cessation_lower": "1988-01-01",
    "date:cessation_upper": "1988-12-31",
    "date:inception_lower": "1988-01-01",
    "date:inception_upper": "1988-12-31",
    "iso:country": "XX",
    "millsfield:images": [
      1527849881
    ],
    "millsfield:primary_image": 1527849881,
    "sfomuseum:accession_number": "2011.126.390",
    "sfomuseum:airport": "Norman Y. Mineta San Jose International Airport",
    "sfomuseum:category": "Scheduling / Ticketing",
    "sfomuseum:collection": "Aviation Archive",
    "sfomuseum:creditline": "Gift of the Paul H. Kowalewski Collection",
    "sfomuseum:date": "1988",
    "sfomuseum:daterange_end": "1988-12-31",
    "sfomuseum:daterange_start": "1988-01-01",
    "sfomuseum:description": "Timetable issued by San Jose International Airport, effective June 1988; blue and white cover with illustration of ticket agent and customer at counter.",
    "sfomuseum:dimensions": "9 x 4 inches (22.9 x 10.2 cm)",
    "sfomuseum:media_ids": [
      1527849881
    ],
    "sfomuseum:medium": "paper, ink",
    "sfomuseum:placetype": "object",
    "sfomuseum:publication": ": , 1988.",
    "sfomuseum:subcategory": "Timetable",
    "wof:name": "timetable: San Jose International Airport",
    "wof:placetype": "venue"
  },
  "geometry": {"coordinates":[-122.386155,37.616357],"type":"Point"}
}
