{
  "type": "Feature",
  "properties": {
    "date:cessation_lower": "1984-12-31",
    "date:cessation_upper": "1984-12-31",
    "date:inception_lower": "1984-01-01",
    "date:inception_upper": "1984-01-01",
    "iso:country": "XX",
    "millsfield:images": [
      1527841177
    ],
    "sfomuseum:accession_number": "2003.105.031.003",
    "sfomuseum:airline": "Braniff Inc.",
    "sfomuseum:category": "Scheduling / Ticketing",
    "sfomuseum:collection": "Aviation Archive",
    "sfomuseum:creditline": "Gift of Craig Lynes",
    "sfomuseum:date": "1984",
    "sfomuseum:daterange_end": "1984-12-31",
    "sfomuseum:daterange_start": "1984-01-01",
    "sfomuseum:description": "Timetable issued by Braniff Inc., effective November 5, 1984; three page double-sided fold-out. The cover is white, blue, and red with the company name in red at the top and vertically in large letters along the left side.",
    "sfomuseum:media_ids": [
      1527841177
    ],
    "sfomuseum:medium": "paper, ink",
    "sfomuseum:placetype": "object",
    "sfomuseum:subcategory": "Timetable",
    "wof:depicts": [
      1159286457
    ],
    "wof:name": "timetable: Braniff Inc.",
    "wof:placetype": "venue"
  },
  "geometry": {"coordinates":[-122.386155,37.616357],"type":"Point"}
}
