{
  "type": "Feature",
  "properties": {
    "date:cessation_lower": "2012-01-01",
    "date:cessation_upper": "2012-12-31",
    "date:inception_lower": "2012-01-01",
    "date:inception_upper": "2012-12-31",
    "iso:country": "XX",
    "loc:named_authorities": [
      "no99019808"
    ],
    "sfomuseum:accession_number": "2013.073.008",
    "sfomuseum:author": "Heaton, Daniel J",
    "sfomuseum:callnumber": "UG626.2.J65 H32 2012",
    "sfomuseum:category": "Book",
    "sfomuseum:collection": "Aviation Library",
    "sfomuseum:creditline": "Purchase",
    "sfomuseum:date": "2012",
    "sfomuseum:date_acquired": "2013-06-06",
    "sfomuseum:daterange_end": "2012-12-31",
    "sfomuseum:daterange_start": "2012-01-01",
    "sfomuseum:description": "129 p. : ill. ; 24 cm.",
    "sfomuseum:description_library": "129 p. : ill. ; 24 cm.",
    "sfomuseum:medium": "paper, ink",
    "sfomuseum:placetype": "object",
    "sfomuseum:publication": "Wellesley, MA: Branden Books, 2012.",
    "sfomuseum:publisher": "Branden Books",
    "sfomuseum:publisher_location": "Wellesley, MA",
    "sfomuseum:subcategory": "Book",
    "sfomuseum:subject": "Jones, Byron Q. (Byron Quinby), 1888-1959.\rAir pilots, Military -- United States -- Biography.\rAir pilots -- United States -- Biography.\rInventors -- United States -- Biography.\rEducators -- United States -- Biography.\rFlight training -- United States -- History -- 20th century.\rAeronautics, Military -- Study and teaching -- United States -- History -- 20th century.\rSelfridge Air National Guard Base (Mich.) -- History -- 20th century.\rWorld War, 1914-1918 -- Aerial operations, American.",
    "wof:name": "Forgotten aviator: the Byron Q. Jones story",
    "wof:placetype": "custom",
    "wof:placetype_alt": "object"
  },
  "geometry": {"coordinates":[-122.386155,37.616357],"type":"Point"}
}
