{
  "type": "Feature",
  "properties": {
    "date:cessation_lower": "1964-12-31",
    "date:cessation_upper": "1964-12-31",
    "date:inception_lower": "1963-01-01",
    "date:inception_upper": "1963-01-01",
    "iso:country": "XX",
    "sfomuseum:accession_number": "2001.136.081.001-.004",
    "sfomuseum:airline": "United Air Lines  (United Airlines)",
    "sfomuseum:category": "Company Record / Document",
    "sfomuseum:collection": "Aviation Archive",
    "sfomuseum:creditline": "Gift of Howard Knapp",
    "sfomuseum:date": "1963-1964",
    "sfomuseum:daterange_end": "1964-12-31",
    "sfomuseum:daterange_start": "1963-01-01",
    "sfomuseum:description": "Monthly newsletter, approx. 16 pages. Later issues in color; stapled booklets. ",
    "sfomuseum:dimensions": "11 x 8 1/2 inches (27.9 x 21.6 cm)",
    "sfomuseum:issue": "4 issues: 1963-1964",
    "sfomuseum:issues_held": "1963 (Feb, Mar)\r1964 (Jul/Aug, Sep/Oct)",
    "sfomuseum:medium": "paper, ink",
    "sfomuseum:placetype": "object",
    "sfomuseum:publisher": "San Francisco Mainliner Club",
    "sfomuseum:publisher_location": "San Francisco International Airport",
    "sfomuseum:subcategory": "Company Newsletter",
    "sfomuseum:subject": "Airlines -- Commercial -- United",
    "wof:depicts": [
      1159285415
    ],
    "wof:name": "employee newsletter: United Air Lines, Wing tips: published by the San Francisco Mainliner Club [4 issues: 1963-1964]",
    "wof:placetype": "venue"
  },
  "geometry": {"coordinates":[-122.386155,37.616357],"type":"Point"}
}
