{
  "type": "Feature",
  "properties": {
    "date:cessation_lower": "1946-01-01",
    "date:cessation_upper": "1946-12-31",
    "date:inception_lower": "1946-01-01",
    "date:inception_upper": "1946-12-31",
    "iso:country": "XX",
    "sfomuseum:accession_number": "2011.128.002",
    "sfomuseum:author": "Ogburn, William Fielding",
    "sfomuseum:callnumber": "TL553 .O35 1946",
    "sfomuseum:category": "Book",
    "sfomuseum:collection": "Aviation Library",
    "sfomuseum:creditline": "Gift of Frank A. Norick",
    "sfomuseum:date": "1946",
    "sfomuseum:daterange_end": "1946-12-31",
    "sfomuseum:daterange_start": "1946-01-01",
    "sfomuseum:description": "vi, 755 p. : ill. ; 23 cm.",
    "sfomuseum:medium": "paper, ink",
    "sfomuseum:placetype": "object",
    "sfomuseum:publication": "Boston: Houghton Mifflin Company, 1946.",
    "sfomuseum:publisher": "Houghton Mifflin Company",
    "sfomuseum:publisher_location": "Boston",
    "sfomuseum:subcategory": "Book",
    "sfomuseum:subject": "Aeronautics, Commercial.",
    "wof:name": "The social effects of aviation",
    "wof:placetype": "venue"
  },
  "geometry": {"coordinates":[-122.386155,37.616357],"type":"Point"}
}
