{
  "type": "Feature",
  "properties": {
    "date:cessation_lower":"1926-12-31",
    "date:cessation_upper":"1926-12-31",
    "date:inception_lower":"1926-01-01",
    "date:inception_upper":"1926-01-01",
    "iso:country":"US",
    "sfomuseum:accession_number":"2002.011.019",
    "sfomuseum:category":"Philately",
    "sfomuseum:collection":"Aviation Archive",
    "sfomuseum:continent":"North America",
    "sfomuseum:country":"United States",
    "sfomuseum:creditline":"Purchase",
    "sfomuseum:date":"10/10/1926",
    "sfomuseum:daterange_end":"1926-10-10",
    "sfomuseum:daterange_start":"1926-10-10",
    "sfomuseum:description":"Airmail flight cover, first flight inaugurating contract air mail, Philadelphia - Norfolk route; round purple cachet with commemorative cancellation mark; postmarked October 10, 1926 in Norfolk, Virginia with wavy cancellation mark over 10-cent stamp; backstamp: October 10, 1926 in Washington, DC with football-shaped cancellation mark with notation \u201cDEL\u201d in center.",
    "sfomuseum:medium":"paper, ink",
    "sfomuseum:placetype":"object",
    "sfomuseum:subcategory":"Airmail Flight Cover",
    "wof:name":"airmail flight cover: First airmail flight, CAM, Philadelphia - Norfolk route",
    "wof:placetype":"venue"
},
  "geometry": {"coordinates":[-122.386155,37.616358],"type":"Point"}
}