{
  "type": "Feature",
  "properties": {
    "date:cessation_lower": "1955-01-01",
    "date:cessation_upper": "1955-12-31",
    "date:inception_lower": "1954-01-01",
    "date:inception_upper": "1954-12-31",
    "iso:country": "XX",
    "sfomuseum:accession_number": "2000.168.240",
    "sfomuseum:author": "Laidlaw-Dickson, D.J.; and Rushbrooke, C.S",
    "sfomuseum:callnumber": "TL770.A1 A37 1954-55",
    "sfomuseum:category": "Book",
    "sfomuseum:collection": "Aviation Library",
    "sfomuseum:creditline": "Purchase",
    "sfomuseum:date": "1954-1955",
    "sfomuseum:daterange_end": "1955-12-31",
    "sfomuseum:daterange_start": "1954-01-01",
    "sfomuseum:description": "v. : ill. ; 22 cm.",
    "sfomuseum:description_library": "v. : ill. ; 22 cm.",
    "sfomuseum:medium": "paper, ink",
    "sfomuseum:notes_library": "Description based on: 1959/60. A review of the year's aeromodelling throughout the world ... produced by staff and contributors of the Aeromodeller.Imprint varies: Published by Model \u0026 Allied Publications.",
    "sfomuseum:placetype": "object",
    "sfomuseum:publication": "Watford, Hertfordshire, England: Model Aeronautical Press, 1954-1955.",
    "sfomuseum:publisher": "Model Aeronautical Press",
    "sfomuseum:publisher_location": "Watford, Hertfordshire, England",
    "sfomuseum:subcategory": "Book",
    "sfomuseum:subject": "Airplanes Models Periodicals.",
    "wof:name": "Aeromodeller annual",
    "wof:placetype": "venue"
  },
  "geometry": {"coordinates":[-122.386155,37.616357],"type":"Point"}
}
