{
  "type": "Feature",
  "properties": {
    "date:cessation_lower": "1936-01-01",
    "date:cessation_upper": "1936-12-31",
    "date:inception_lower": "1936-01-01",
    "date:inception_upper": "1936-12-31",
    "iso:country": "XX",
    "sfomuseum:accession_number": "2015.068.018",
    "sfomuseum:author": "Diehl, Walter Stuart",
    "sfomuseum:callnumber": "TL573 .D46 1936 c.2 SC",
    "sfomuseum:category": "Book",
    "sfomuseum:collection": "Aviation Library",
    "sfomuseum:creditline": "Gift of Robin M. Aslin and Robert W. Reedy, in memory of Robert E. Reedy",
    "sfomuseum:date": "c. 1936",
    "sfomuseum:date_acquired": "2015-08-28",
    "sfomuseum:daterange_end": "1941-12-31",
    "sfomuseum:daterange_start": "1931-01-01",
    "sfomuseum:description_library": "xviii, 556 p. incl. illus., tables, diagrs. 22 cm.",
    "sfomuseum:medium": "paper, ink",
    "sfomuseum:placetype": "object",
    "sfomuseum:publication": "New York: The Ronald press company, c. 1936.",
    "sfomuseum:publisher": "The Ronald press company",
    "sfomuseum:publisher_location": "New York",
    "sfomuseum:subcategory": "Book",
    "sfomuseum:subject": "Airplanes.Aerodynamics.",
    "wof:name": "Engineering aerodynamics",
    "wof:placetype": "custom",
    "wof:placetype_alt": "object"
  },
  "geometry": {"coordinates":[-122.386155,37.616357],"type":"Point"}
}
