{
  "type": "Feature",
  "properties": {
    "date:cessation_lower": "1988-01-01",
    "date:cessation_upper": "1988-12-31",
    "date:inception_lower": "1988-01-01",
    "date:inception_upper": "1988-12-31",
    "iso:country": "XX",
    "millsfield:images": [
      1527832399
    ],
    "millsfield:primary_image": 1527832399,
    "sfomuseum:accession_number": "2009.122.006",
    "sfomuseum:airline": "Aer Lingus",
    "sfomuseum:category": "Scheduling / Ticketing",
    "sfomuseum:collection": "Aviation Archive",
    "sfomuseum:creditline": "Gift of the William Hough Collection",
    "sfomuseum:date": "1988",
    "sfomuseum:daterange_end": "1988-12-31",
    "sfomuseum:daterange_start": "1988-01-01",
    "sfomuseum:description": "Timetable issued by Aer Lingus, effective May 1 through October 22, 1988 through March 26, 1988; 68-page schedule; full color photographic image of airplane in flight and servicemark at top center; in English and some Gaelic.",
    "sfomuseum:dimensions": "7 3/4 x 4 1/4 inches (19.7 x 10.8 cm)",
    "sfomuseum:media_ids": [
      1527832399
    ],
    "sfomuseum:medium": "paper, ink",
    "sfomuseum:placetype": "object",
    "sfomuseum:subcategory": "Timetable",
    "sfomuseum:subject": "Airlines -- Commercial -- Aer Lingus.",
    "wof:depicts": [
      1159283495
    ],
    "wof:name": "timetable: Aer Lingus, Summer revised edition",
    "wof:placetype": "custom"
  },
  "geometry": {"coordinates":[-122.386155,37.616357],"type":"Point"}
}
