{
  "type": "Feature",
  "properties": {
    "date:cessation_lower": "1940-07-21",
    "date:cessation_upper": "1940-07-21",
    "date:inception_lower": "1940-07-21",
    "date:inception_upper": "1940-07-21",
    "iso:country": "XX",
    "millsfield:images": [
      1527829131
    ],
    "millsfield:images_texts": [
      "New Caledonia To U.S.\nPOSTE AÉRIENNE\n1ERE TRAVERSEE\nSAN FRANCISCO\npar\nPAN AMERICAN\nCLIPPER\nHONOLULU\nCANTON\nISLAND\nNOUMEA\nENTRE\nNOUVELLE - CALÉDONIE\nET ETATS UNIS\nINCA\nCOURDIS\nPAN-AMERICAN A!PL\nPOSTES I\nPOSTES\n• NOUVELLE CALEAUNE RE\nET DEPENDANCES\nNOUVELLE\nCALEDONIE R\nET DEPENDANCES\nVIA AIR MAIL\nPan American Airways Co.\nSan Francisco,, Calif."
    ],
    "millsfield:images_texts_ids": [
      1527829131
    ],
    "millsfield:primary_image": 1527829131,
    "sfomuseum:accession_number": "1994.18.153",
    "sfomuseum:aircraft": "Boeing 314 Clipper",
    "sfomuseum:airline": "Pan American Airways",
    "sfomuseum:category": "Philately",
    "sfomuseum:collection": "Aviation Archive",
    "sfomuseum:continent": "Transpacific",
    "sfomuseum:creditline": "Purchase",
    "sfomuseum:date": "7/21/1940",
    "sfomuseum:date_acquired": "1994-06-29",
    "sfomuseum:daterange_end": "1940-07-21",
    "sfomuseum:daterange_start": "1940-07-21",
    "sfomuseum:description": "Airmail flight cover, Pan American Airways, part of first airmail service between United States and New Zealand, Noumea - San Francisco route; green cachet with image of Boeing 314 in flight over coastline; three stamps: magenta/brown 5-franc, blue/brown 5-franc, and orange 20-franc (New Caledonia); three postmarks: July 21, 1940 in Noumea; backstamp: July 24, 1940 in San Francisco with “Golden Gate International Exposition 1940” cancellation mark; additional stamp: Pan American Airways “1er courrier Noumea N’lle Caledonie”; envelope: white air mail with blue and red rhomboids around border.",
    "sfomuseum:dimensions": "4 1/8 x 9 1/2 inches (10.5 x 24.1 cm)",
    "sfomuseum:maker": "Pan American Airways, Inc.",
    "sfomuseum:media_ids": [
      1527829131
    ],
    "sfomuseum:medium": "paper, ink",
    "sfomuseum:placetype": "object",
    "sfomuseum:publication": ": , 7/21/1940.",
    "sfomuseum:subcategory": "Airmail Flight Cover",
    "wof:depicts": [
      1159284991,
      1159289619,
      1159293593
    ],
    "wof:name": "airmail flight cover: Pan American Airways, first airmail flight, Noumea (New Caledonia) - San Francisco route",
    "wof:placetype": "custom",
    "wof:placetype_alt": "object"
  },
  "geometry": {"coordinates":[-122.386155,37.616357],"type":"Point"}
}
