{
  "type": "Feature",
  "properties": {
    "date:cessation_lower": "1996-01-01",
    "date:cessation_upper": "1996-12-31",
    "date:inception_lower": "1996-01-01",
    "date:inception_upper": "1996-12-31",
    "iso:country": "XX",
    "sfomuseum:accession_number": "1999.659.062",
    "sfomuseum:author": "Hamilton, J. Scott",
    "sfomuseum:callnumber": "KF2400 .H36 1996",
    "sfomuseum:category": "Book",
    "sfomuseum:collection": "Aviation Library",
    "sfomuseum:creditline": "Purchase",
    "sfomuseum:date": "1996",
    "sfomuseum:daterange_end": "1996-12-31",
    "sfomuseum:daterange_start": "1996-01-01",
    "sfomuseum:description": "viii, 216 p. : ill., maps, ; 24 cm.",
    "sfomuseum:description_library": "viii, 216 p. : ill., maps, ; 24 cm.",
    "sfomuseum:medium": "paper, ink",
    "sfomuseum:placetype": "object",
    "sfomuseum:publication": "Ames, IA: Iowa State University Press, 1996.",
    "sfomuseum:publisher": "Iowa State University Press",
    "sfomuseum:publisher_location": "Ames, IA",
    "sfomuseum:subcategory": "Book",
    "sfomuseum:subject": "Aeronautics Law and legislation United States.",
    "wof:name": "Practical aviation law",
    "wof:placetype": "venue"
  },
  "geometry": {"coordinates":[-122.386155,37.616357],"type":"Point"}
}
