{
  "type": "Feature",
  "properties": {
    "date:cessation_lower":"1935-12-31",
    "date:cessation_upper":"1935-12-31",
    "date:inception_lower":"1935-01-01",
    "date:inception_upper":"1935-01-01",
    "iso:country":"XX",
    "sfomuseum:accession_number":"2008.075.147 a b ",
    "sfomuseum:category":"Philately",
    "sfomuseum:collection":"Aviation Archive",
    "sfomuseum:creditline":"Gift of Jon E. Krupnick",
    "sfomuseum:date":"10/16/1935",
    "sfomuseum:daterange_end":"1935-10-16",
    "sfomuseum:daterange_start":"1935-10-16",
    "sfomuseum:description":"Airmail flight cover, Pan American Airways, fourth Pacific survey flight, San Francisco to Guam and return; identified by donor with additional information: \"Signed by entire crew, San Francisco - Honolulu, October 5-6; Honolulu - Midway, October 10; Midway - Wake, October 11 - 12; Wake-Guam, October 13.\"\ra. cover: green cachet at bottom left corner on front with illustration of aircraft in flight over globe with seahorse and text, \"First flight eastbound from Guam, Pan American Clipper\"; purple cachet at bottom right corner on front with illustration of aircraft in flight over route from San Francisco to Guam with text, \"First flight westbound to Guam, Pan American Clipper\"; three postmarks on front: October 5, 1935, San Francisco, October 16, 1935, Guam, and October 24, 1935, San Francisco with football-shaped killers over three stamps; two backstamps: October 5, 1935, Alameda, California, and October 13, 1935, Guam; signed by R.O.D. Sullivan, J. Tilton, M. [illegible], W. T. Jarboe Jr., H.R. Canaday, V.A. Wright.\rb. information sheet: 8 1/2 x 11 with black text; additional information prepared by donor, including route information; flight cover was received mounted to sheet with photo corners.",
    "sfomuseum:media_ids":[
        1527818365
    ],
    "sfomuseum:medium":"paper, ink",
    "sfomuseum:placetype":"object",
    "sfomuseum:subcategory":"Airmail Flight Cover",
    "wof:name":"airmail flight cover: Pan American Airways, Fourth Pacific survey fight, San Francisco - Guam and return",
    "wof:placetype":"venue"
},
  "geometry": {"coordinates":[-122.386155,37.616358],"type":"Point"}
}