{
  "type": "Feature",
  "properties": {
    "date:cessation_lower": "1973-01-01",
    "date:cessation_upper": "1973-12-31",
    "date:inception_lower": "1973-01-01",
    "date:inception_upper": "1973-12-31",
    "isbn:number": "0879810246, 9780879810245",
    "iso:country": "XX",
    "sfomuseum:accession_number": "2000.160.0450",
    "sfomuseum:author": "Irwin, James B. (James Benson)",
    "sfomuseum:callnumber": "TL789.85.I78 A3 1973 SC",
    "sfomuseum:category": "Book",
    "sfomuseum:collection": "Aviation Library",
    "sfomuseum:creditline": "The Tony Bill Aviation Library Collection",
    "sfomuseum:date": "1973",
    "sfomuseum:date_acquired": "1999-05-18",
    "sfomuseum:daterange_end": "1973-12-31",
    "sfomuseum:daterange_start": "1973-01-01",
    "sfomuseum:description": "251 p. illus. 22 cm.",
    "sfomuseum:description_library": "251 p. illus. 22 cm.",
    "sfomuseum:medium": "paper, ink",
    "sfomuseum:placetype": "object",
    "sfomuseum:publication": "Philadelphia: A. J. Holman, 1973.",
    "sfomuseum:publisher": "A. J. Holman",
    "sfomuseum:publisher_location": "Philadelphia",
    "sfomuseum:subcategory": "Book",
    "sfomuseum:subject": "Irwin, James B. (James Benson)Project Apollo (U.S.)Religion and astronautics.",
    "wof:name": "To rule the night: the discovery voyage of astronaut Jim Irwin",
    "wof:placetype": "custom",
    "wof:placetype_alt": "object"
  },
  "geometry": {"coordinates":[-122.386155,37.616357],"type":"Point"}
}
