{
  "type": "Feature",
  "properties": {
    "date:cessation_lower": "2012-01-01",
    "date:cessation_upper": "2012-12-31",
    "date:inception_lower": "2012-01-01",
    "date:inception_upper": "2012-12-31",
    "iso:country": "XX",
    "sfomuseum:accession_number": "2013.074.001",
    "sfomuseum:airline": "Alaska Airlines",
    "sfomuseum:author": "Hollenbeck, Cliff.\rHollenbeck, Nancy",
    "sfomuseum:callnumber": "HE9803.A94 H64 2012",
    "sfomuseum:category": "Book",
    "sfomuseum:collection": "Aviation Library",
    "sfomuseum:creditline": "Transfer",
    "sfomuseum:date": "2012",
    "sfomuseum:date_acquired": "2013-06-06",
    "sfomuseum:daterange_end": "2012-12-31",
    "sfomuseum:daterange_start": "2012-01-01",
    "sfomuseum:description": "224 p. : ill. (chiefly col.) ; 25 x 32 cm.",
    "sfomuseum:description_library": "224 p. : ill. (chiefly col.) ; 25 x 32 cm.",
    "sfomuseum:medium": "paper, ink",
    "sfomuseum:placetype": "object",
    "sfomuseum:publication": "Seattle, WA: Hollenbeck Productions, 2012.",
    "sfomuseum:publisher": "Hollenbeck Productions",
    "sfomuseum:publisher_location": "Seattle, WA",
    "sfomuseum:subcategory": "Book",
    "sfomuseum:subject": "Alaska Airlines -- History.\rAlaska Airlines -- History -- Pictorial works.\rAirlines -- Alaska -- History.\rAeronautics, Commercial -- United States -- History. ",
    "wof:depicts": [
      1159283813,
      1159288915
    ],
    "wof:name": "Alaska Airlines: a visual celebration",
    "wof:placetype": "custom",
    "wof:placetype_alt": "object"
  },
  "geometry": {"coordinates":[-122.386155,37.616357],"type":"Point"}
}
