{
  "type": "Feature",
  "properties": {
    "date:cessation_lower": "1980-01-01",
    "date:cessation_upper": "1989-12-31",
    "date:inception_lower": "1980-01-01",
    "date:inception_upper": "1989-12-31",
    "iso:country": "XX",
    "millsfield:images": [
      1746680835
    ],
    "millsfield:primary_image": 1746680835,
    "sfomuseum:accession_number": "2002.113.273",
    "sfomuseum:aircraft": "Douglas DC-9",
    "sfomuseum:airline": "TWA (Trans World Airlines)",
    "sfomuseum:category": "Company Record / Document",
    "sfomuseum:collection": "Aviation Archive",
    "sfomuseum:creditline": "Gift of TWA Clipped Wings International",
    "sfomuseum:date": "1980s",
    "sfomuseum:date_acquired": "2004-12-08",
    "sfomuseum:daterange_end": "1989-12-31",
    "sfomuseum:daterange_start": "1980-01-01",
    "sfomuseum:description": "Cabin crew training manual issued by TWA (Trans World Airlines) for Douglas DC-9 inflight service; navy binder with handwritten tabs; includes training documents and worksheets.",
    "sfomuseum:dimensions": "11 1/2 x 11 inches (29.2 x 27.9 cm)",
    "sfomuseum:medium": "paper, plastic, metal, ink",
    "sfomuseum:placetype": "object",
    "sfomuseum:publication": ": , 1980s.",
    "sfomuseum:subcategory": "Manual, Training",
    "wof:depicts": [
      1159291223,
      1159285393
    ],
    "wof:name": "training manual: TWA (Trans World Airlines), Douglas DC-9 Cabin Trainer",
    "wof:placetype": "venue"
  },
  "geometry": {"coordinates":[-122.386155,37.616357],"type":"Point"}
}
