{
  "type": "Feature",
  "properties": {
    "date:cessation_lower": "1930-01-01",
    "date:cessation_upper": "1939-12-31",
    "date:inception_lower": "1930-01-01",
    "date:inception_upper": "1939-12-31",
    "iso:country": "US",
    "sfomuseum:accession_number": "1995.29.29",
    "sfomuseum:category": "Toys",
    "sfomuseum:collection": "Aviation Museum",
    "sfomuseum:continent": "North America",
    "sfomuseum:country": "United States",
    "sfomuseum:creditline": "Purchase",
    "sfomuseum:date": "1930s",
    "sfomuseum:date_acquired": "1995-06-06",
    "sfomuseum:daterange_end": "1930-12-31",
    "sfomuseum:daterange_start": "1930-01-01",
    "sfomuseum:description": "Purple two-engine toy airplane with orange wings. ",
    "sfomuseum:dimensions": "2 7/8 x 13 x 9 3/4 inches (7.3 x 33 x 24.8 cm)",
    "sfomuseum:maker": "Wyandotte Toys",
    "sfomuseum:medium": "polychrome steel, wood, paint",
    "sfomuseum:placetype": "object",
    "sfomuseum:publication": ": , 1930s.",
    "sfomuseum:subcategory": "Toy Airplane",
    "wof:name": "toy airplane: twin engine aircraft",
    "wof:placetype": "venue"
  },
  "geometry": {"coordinates":[-122.386155,37.616357],"type":"Point"}
}
