{
  "type": "Feature",
  "properties": {
    "date:cessation_lower": "1991-01-01",
    "date:cessation_upper": "1991-12-31",
    "date:inception_lower": "1991-01-01",
    "date:inception_upper": "1991-12-31",
    "iso:country": "XX",
    "sfomuseum:accession_number": "00-2385",
    "sfomuseum:airline": "Pan American World Airways",
    "sfomuseum:author": "Taylor, Barry",
    "sfomuseum:callnumber": "HE9803.P36 T39 1991 c.1",
    "sfomuseum:category": "Book",
    "sfomuseum:collection": "Aviation Library",
    "sfomuseum:date": "c. 1991",
    "sfomuseum:daterange_end": "1996-12-31",
    "sfomuseum:daterange_start": "1986-01-01",
    "sfomuseum:description": "x, 213 p. : ill., maps ; 24 cm.",
    "sfomuseum:description_library": "x, 213 p. : ill., maps ; 24 cm.",
    "sfomuseum:medium": "paper, ink",
    "sfomuseum:placetype": "object",
    "sfomuseum:publication": "Blue Ridge Summit, PA: Aero, c. 1991.",
    "sfomuseum:publisher": "Aero",
    "sfomuseum:publisher_location": "Blue Ridge Summit, PA",
    "sfomuseum:series": "The Flying classics series",
    "sfomuseum:subcategory": "Book",
    "sfomuseum:subject": "Pan American World Airways, inc. -- History. Transpacific flights -- History. Seaplanes -- United States -- History.",
    "wof:depicts": [
      1159284989,
      1159286839
    ],
    "wof:name": "Pan American's ocean clippers",
    "wof:placetype": "custom"
  },
  "geometry": {"coordinates":[-122.386155,37.616357],"type":"Point"}
}
