{
  "type": "Feature",
  "properties": {
    "date:cessation_lower":"1982-12-31",
    "date:cessation_upper":"1982-12-31",
    "date:inception_lower":"1982-01-01",
    "date:inception_upper":"1982-01-01",
    "iso:country":"XX",
    "sfomuseum:accession_number":"2005.137.034.004",
    "sfomuseum:airport":"San Francisco International Airport",
    "sfomuseum:category":"Photograph",
    "sfomuseum:collection":"Aviation Archive",
    "sfomuseum:creditline":"Transfer",
    "sfomuseum:date":"1982",
    "sfomuseum:daterange_end":"1982-12-31",
    "sfomuseum:daterange_start":"1982-01-01",
    "sfomuseum:description":"Color photograph from report produced by Bureau of Planning and Construction, San Francisco International Airport (SFO), titled \u201cSummary Progress Report / Modernization and Replacement Phase of the Terminal Construction Program / January 1, 1982 through January 31, 1982\u201d; interior view of North Terminal (Terminal 3) with caption, \u201cConstruction of concession spaces (ice cream, cookies & art gallery) in North Terminal visually screened from the public by dust barrier,\u201d January 26, 1982.",
    "sfomuseum:medium":"photograph",
    "sfomuseum:placetype":"object",
    "sfomuseum:subcategory":"Print, Photograph",
    "wof:depicts":[
        102527513
    ],
    "wof:name":"photograph: San Francisco International Airport (SFO), North Terminal construction",
    "wof:placetype":"venue"
},
  "geometry": {"coordinates":[-122.386155,37.616357],"type":"Point"}
}