{
  "type": "Feature",
  "properties": {
    "date:cessation_lower": "1961-01-01",
    "date:cessation_upper": "1961-12-31",
    "date:inception_lower": "1961-01-01",
    "date:inception_upper": "1961-12-31",
    "iso:country": "XX",
    "loc:subject_heading": {
      "sh85148721": "X-15 (Rocket aircraft)"
    },
    "loc:subject_headings": [
      "sh85148721"
    ],
    "sfomuseum:accession_number": "2008.107.033",
    "sfomuseum:author": "Caidin, Martin",
    "sfomuseum:callnumber": "TL789.8.U6 X53 1961",
    "sfomuseum:category": "Book",
    "sfomuseum:collection": "Aviation Library",
    "sfomuseum:creditline": "Gift of Thomas G. Dragges",
    "sfomuseum:date": "1961",
    "sfomuseum:daterange_end": "1961-12-31",
    "sfomuseum:daterange_start": "1961-01-01",
    "sfomuseum:description": "64 p. : ill. ; 20 cm.",
    "sfomuseum:medium": "paper, ink",
    "sfomuseum:placetype": "object",
    "sfomuseum:publication": "New York: Ridge Press : Published for Scholastic Book Services, 1961.",
    "sfomuseum:publisher": "Ridge Press : Published for Scholastic Book Services",
    "sfomuseum:publisher_location": "New York",
    "sfomuseum:series": "A Rutledge book ; RB22",
    "sfomuseum:subcategory": "Book",
    "sfomuseum:subject": "X-15 (Rocket aircraft)",
    "wof:name": "X-15: man's daring flight into space",
    "wof:placetype": "venue"
  },
  "geometry": {"coordinates":[-122.386155,37.616357],"type":"Point"}
}
