{
  "type": "Feature",
  "properties": {
    "date:cessation_lower": "1980-01-01",
    "date:cessation_upper": "1980-12-31",
    "date:inception_lower": "1980-01-01",
    "date:inception_upper": "1980-12-31",
    "iso:country": "XX",
    "millsfield:images": [
      1527850949
    ],
    "millsfield:primary_image": 1527850949,
    "sfomuseum:accession_number": "2012.061.094",
    "sfomuseum:airline": "China Airlines",
    "sfomuseum:category": "Meal Service",
    "sfomuseum:collection": "Aviation Museum",
    "sfomuseum:creditline": "Gift of Masako Matsuo",
    "sfomuseum:date": "1980",
    "sfomuseum:daterange_end": "1980-12-31",
    "sfomuseum:daterange_start": "1980-01-01",
    "sfomuseum:description": "Entree plate issued by China Airlines for inflight meal service; white plate with blue lotus blossom pattern.",
    "sfomuseum:dimensions": "1 x 7 1/2 x 7 1/2 inches (2.5 x 19.1 x 19.1 cm)",
    "sfomuseum:media_ids": [
      1527850949
    ],
    "sfomuseum:medium": "glazed ceramic",
    "sfomuseum:placetype": "object",
    "sfomuseum:subcategory": "Plate / Dish / Bowl",
    "wof:depicts": [
      1159284153
    ],
    "wof:name": "entree plate: China Airlines",
    "wof:placetype": "venue"
  },
  "geometry": {"coordinates":[-122.386155,37.616357],"type":"Point"}
}
