{
  "type": "Feature",
  "properties": {
    "date:cessation_lower": "1960-01-01",
    "date:cessation_upper": "1960-12-31",
    "date:inception_lower": "1960-01-01",
    "date:inception_upper": "1960-12-31",
    "iso:country": "XX",
    "millsfield:images": [
      1527847403,
      1527847871
    ],
    "millsfield:images_texts": [
      "CAPITAL\nAIRLINES\nJULY 10 THRU SEPTEMBER 24, 1960\nThis Summer, save 25%\n-fly Capital to New York\nfor less than it costs to\ndrive or go by train!\nASK YOUR TRAVEL AGENT ABOUT\nCAPITAL'S NEW LOW FESTIVAL FARES!",
      "Bermuda or Canada\nbu COLONIAL\nShycruiser\nYou can fly to glamorous Bermuda or romantic\nCanada quickly, safely and comfortably. Colonial's\nrecord of O consecutive years of safety is augmented\nby his traditionallv hian service standards.\nYou can afford it tool Only $85.00 round trip (plus\ntax) to Bermuda- you can save 10% on round trip\nfares to canada and ZOo on excursion fares.\nWASHINGTON\nOTTAWA\nRoute of the Shycruisers\nCOLONIAL AIRLINES\n51 VANDERBILT AVE.\nNEW YORK 17, N. Y.\n\"NOW IN OUR 21st YEAR OF SAFETY!\"\nCANADA • U.S.A. • BERMUDA\nCANADA - U. S. A. - BERMUDA\nTrio 190\nTrip 500\nWESTIOUND\n......BEL.\nBERMUDA…….....O LY\nMATTINUITORI\n× 1245 P.M\n34S P. M\nTrip 901\n* 6.45 P.M.\n§ 10.09 P. M\n11.35 P. M\nCocoperoratary food servo\nwires costae so, Breakdaut.\nKirt mores Fares ca dare"
    ],
    "millsfield:images_texts_ids": [
      1527847403,
      1527847871
    ],
    "millsfield:primary_image": 1527847403,
    "sfomuseum:accession_number": "2006.059.120",
    "sfomuseum:airline": "Capital Airlines",
    "sfomuseum:category": "Scheduling / Ticketing",
    "sfomuseum:collection": "Aviation Archive",
    "sfomuseum:creditline": "Gift of the Paul Edward Fair Estate",
    "sfomuseum:date": "1960",
    "sfomuseum:date_acquired": "2006-10-19",
    "sfomuseum:daterange_end": "1960-12-31",
    "sfomuseum:daterange_start": "1960-01-01",
    "sfomuseum:description": "Timetable issued by Capital Airlines, effective July 10 through September 14, 1960; red-orange and navy blue cover with duotone photographic image of the New York skyline and text, \"This Summer, save 25%\"; includes route map.",
    "sfomuseum:dimensions": "8 1/2 x 3 3/4 inches (21.6 x 9.5 cm)",
    "sfomuseum:issues_held": "Effective: July 10 through September 24, 1960.",
    "sfomuseum:media_ids": [
      1527847403,
      1527847871
    ],
    "sfomuseum:medium": "paper, ink",
    "sfomuseum:placetype": "object",
    "sfomuseum:publication": ": , 1960.",
    "sfomuseum:subcategory": "Timetable",
    "sfomuseum:subject": "Airlines -- timetables",
    "wof:depicts": [
      1159288671,
      1159284093
    ],
    "wof:name": "timetable: Capital Airlines",
    "wof:placetype": "custom",
    "wof:placetype_alt": "object"
  },
  "geometry": {"coordinates":[-122.386155,37.616357],"type":"Point"}
}
