{
  "type": "Feature",
  "properties": {
    "date:cessation_lower": "1981-01-01",
    "date:cessation_upper": "1981-12-31",
    "date:inception_lower": "1980-01-01",
    "date:inception_upper": "1980-12-31",
    "iso:country": "XX",
    "millsfield:images": [
      1527853631
    ],
    "millsfield:images_texts": [
      "ORD\nLAR\nBRU\nĐXB\nTHR\nLHR\n#\nCHIG XOOKINEWARK, J. F. Kennedy International.\nLONDON. Heathrow\nRRUSSELS\nFRANKEN Heathrow\nWESTBOUND\nBUBAI\nBONDON, Heathrow\nFRANKFORT\nLONDON. Heathron\nNEW TORK/NEWARK, r. kennedy international\nATLANTIC ALL-CARGO SERVICES\nđóp\n160\n0430\n21'00\nSNA\n01 25\n91888\nder\nđếp\nWe S\nPôo\n1820\n21 50 21 00\nfôi\nTối\nNo to\n∞ 10\n12.30\n13'30\n16.25\n03 35 03 35 03 35\n09 30 19 30\nORD\nLAX\nNAN\nAKL\n-IC\n+ 10\nPACIFIC ALL-CARGO SERVICES\nWESTBOUND\nEASTBOUND\nLOS ANGELES\ntep) HONOLULU.\nSYDNEY.\ndep\nAUCKLAND ...\nSYONET.\nX-Operational landing.\n{ dep\nđót\nBeg See\nSOUTHBOUND\nMEN YORKINEWARK, I. F. Kennedy International.\nABCA CITY.\nNORTHBOUND\nPOT SPA VI TRINIDAD TOBAGO,\nABA CITY:\nORKINEWARK,.. Kennedy Interna\nLATIN AMERICA ALL-CARGO SERVICES\nWe Sa\n04 30\n08 iS\n11'20\n∞ is\n21.00\n23 11\n03'20\n23 00\n1912221\n14.00 02 40\n05 0\nos'so\n18'35\n∞ 10\n08 45 11 30\nis 45\n16'25\n12'10 14'35\n14 40\n1730\nis o\n18'20\n21 10 2110"
    ],
    "millsfield:images_texts_ids": [
      1527853631
    ],
    "millsfield:primary_image": 1527853631,
    "sfomuseum:accession_number": "2005.127.002.009",
    "sfomuseum:airline": "Pan American World Airways",
    "sfomuseum:category": "Scheduling / Ticketing",
    "sfomuseum:collection": "Aviation Archive",
    "sfomuseum:creditline": "Gift of the William Hough Collection",
    "sfomuseum:date": "1980-1981",
    "sfomuseum:date_acquired": "2006-12-14",
    "sfomuseum:daterange_end": "1981-12-31",
    "sfomuseum:daterange_start": "1980-01-01",
    "sfomuseum:description": "Cargo schedule for Pan American World Airways; single-sided on pink paper; with information on services in the Atlantic, Latin America and Pacific; part of 11 issues dated 1980-1981.",
    "sfomuseum:dimensions": "14 x 8 1/2 inches (35.6 x 21.6 cm)",
    "sfomuseum:media_ids": [
      1527853631
    ],
    "sfomuseum:medium": "paper, ink",
    "sfomuseum:placetype": "object",
    "sfomuseum:publication": ": , 1980-1981.",
    "sfomuseum:subcategory": "Timetable",
    "wof:depicts": [
      1159284991,
      1159284989,
      1159286839
    ],
    "wof:name": "timetable: Pan American World Airways, cargo schedule",
    "wof:placetype": "custom",
    "wof:placetype_alt": [
      "object"
    ]
  },
  "geometry": {"coordinates":[-122.386155,37.616357],"type":"Point"}
}
