{
  "type": "Feature",
  "properties": {
    "date:cessation_lower":"1952-12-31",
    "date:cessation_upper":"1952-12-31",
    "date:inception_lower":"1942-01-01",
    "date:inception_upper":"1942-01-01",
    "iso:country":"XX",
    "sfomuseum:accession_number":"2006.025.014",
    "sfomuseum:category":"Photograph",
    "sfomuseum:collection":"Aviation Archive",
    "sfomuseum:creditline":"Gift of Denis Neumann",
    "sfomuseum:date":"c. 1947",
    "sfomuseum:daterange_end":"1952-12-31",
    "sfomuseum:daterange_start":"1942-01-01",
    "sfomuseum:description":"Black and white photograph depicting group of men posing in front of TWA (Trans World Airlines) Lockheed L-049 Constellation on tarmac; pilot Harold Neumann standing at far right; on reverse, handwritten markings \"846\" and \"H.E. Neumann\".",
    "sfomuseum:media_ids":[
        1527821077
    ],
    "sfomuseum:medium":"photograph",
    "sfomuseum:placetype":"object",
    "sfomuseum:subcategory":"Print, Photograph",
    "wof:name":"photograph: TWA (Trans World Airlines) L-049 Constellation, Harold Earnest Neumann",
    "wof:placetype":"venue"
},
  "geometry": {"coordinates":[-122.386155,37.616358],"type":"Point"}
}