{
  "type": "Feature",
  "properties": {
    "date:cessation_lower": "1992-01-01",
    "date:cessation_upper": "1992-12-31",
    "date:inception_lower": "1992-01-01",
    "date:inception_upper": "1992-12-31",
    "iso:country": "XX",
    "sfomuseum:accession_number": "1997.13.02",
    "sfomuseum:author": "Rowe, Frank",
    "sfomuseum:callnumber": "LT2030 .R68 1992 JUV",
    "sfomuseum:category": "Book",
    "sfomuseum:collection": "Aviation Library",
    "sfomuseum:creditline": "Gift of Teresa Grana",
    "sfomuseum:date": "1992",
    "sfomuseum:daterange_end": "1992-12-31",
    "sfomuseum:daterange_start": "1992-01-01",
    "sfomuseum:description": "[62 p.] : ill. ; 31 cm.",
    "sfomuseum:description_library": "[62 p.] : ill. ; 31 cm.",
    "sfomuseum:medium": "paper, ink",
    "sfomuseum:notes_library": "Aircraft coloring book with flight facts, dates and information about a variety of aircraft produced in Kansas. Longren Pusher, Cessna Jones 6, Laird Swallow, Knoll KN - 1, Travelair 2000, Travelair R, Stearman 75, Beech C-45 Expediter, Waco CG - 4A Glider, Boeing B-29 Superfortress, North American B - 25J, Beech V-Tail Bonanza, Funk F2B - 85C, Boeing L-15 Scout, Boeing B - 47B Stratojet, Helio Courier YL - 24, Beech T - 34A Mentor, Boeing B - 52D Stratofortress, Cessna 310D SkyKing, Cessna L19 Birddog, Learjet 23, Cessna A37B, Cessna Citation I, Cessna 150K, Bede BD - 5, Beech Super King Air 300, Piaggio P-180 Avanti and Beech Starship 2000A.",
    "sfomuseum:placetype": "object",
    "sfomuseum:publication": "Wichita, KS: The Wichita Eagle \u0026 Beacon Publishing Company, 1992.",
    "sfomuseum:publisher": "The Wichita Eagle \u0026 Beacon Publishing Company",
    "sfomuseum:publisher_location": "Wichita, KS",
    "sfomuseum:subcategory": "Book",
    "sfomuseum:subject": "Juvenile literature. Coloring books. Aircraft industry. Kansas History.",
    "wof:name": "The famous airplanes of Kansas",
    "wof:placetype": "custom"
  },
  "geometry": {"coordinates":[-122.386155,37.616357],"type":"Point"}
}
