{
  "type": "Feature",
  "properties": {
    "date:cessation_lower": "2008-08-05",
    "date:cessation_upper": "2008-08-05",
    "date:inception_lower": "2008-08-05",
    "date:inception_upper": "2008-08-05",
    "iso:country": "XX",
    "millsfield:images": [
      1746512147,
      1746512149
    ],
    "millsfield:primary_image": 1746512147,
    "sfomuseum:accession_number": "2008.122.016",
    "sfomuseum:aircraft": "Airbus A380",
    "sfomuseum:airline": "Qantas Airways",
    "sfomuseum:airport": "Sydney (Kingsford Smith) Airport",
    "sfomuseum:category": "Philately",
    "sfomuseum:collection": "Aviation Archive",
    "sfomuseum:creditline": "Gift of Suzanne de Monchaux",
    "sfomuseum:date": "08/05/2008",
    "sfomuseum:date_acquired": "2009-12-31",
    "sfomuseum:daterange_end": "2008-08-05",
    "sfomuseum:daterange_start": "2008-08-05",
    "sfomuseum:description": "Airmail flight cover issued by Australia Post and Qantas commemorating first day of issue for stamp featuring Qantas Airways Airbus A380; aircraft pin affixed to return address portion of envelope; reverse features text describing the aircraft; postmarked August 5, 2008 in Sydney with metallic red cancellation mark; issue 12,154 of 15,000.",
    "sfomuseum:dimensions": "4 1/4 x 7 1/2 inches (10.8 x 19.1 cm)",
    "sfomuseum:medium": "paper, ink, metal, enamel",
    "sfomuseum:placetype": "object",
    "sfomuseum:publication": ": , 08/05/2008.",
    "sfomuseum:subcategory": "Airmail Flight Cover",
    "sfomuseum:subject": "Airlines -- Commercial -- Qantas Airways.",
    "wof:depicts": [
      1159285043,
      1159289435,
      1159293829,
      102557783,
      1159287479
    ],
    "wof:name": "airmail flight cover: Qantas Airways",
    "wof:placetype": "custom",
    "wof:placetype_alt": "object"
  },
  "geometry": {"coordinates":[-122.386155,37.616357],"type":"Point"}
}
