{
  "type": "Feature",
  "properties": {
    "date:cessation_lower": "1959-12-31",
    "date:cessation_upper": "1959-12-31",
    "date:inception_lower": "1950-01-01",
    "date:inception_upper": "1950-01-01",
    "iso:country": "XX",
    "sfomuseum:accession_number": "1998.141.017",
    "sfomuseum:aircraft": "Lockheed L-749A Constellation",
    "sfomuseum:airline": "TWA (Trans World Airlines)",
    "sfomuseum:category": "Philately",
    "sfomuseum:collection": "Aviation Archive",
    "sfomuseum:creditline": "Purchase",
    "sfomuseum:date": "1950s",
    "sfomuseum:daterange_end": "1959-12-31",
    "sfomuseum:daterange_start": "1950-01-01",
    "sfomuseum:description": "Postcard depicting color photographic image of TWA (Trans World Airlines) Lockheed L-749A Constellation in flight over water; air-to-air three-quarter view.",
    "sfomuseum:medium": "printed coated paper",
    "sfomuseum:placetype": "object",
    "sfomuseum:subcategory": "Postcard",
    "wof:depicts": [
      1159285393,
      1159291127
    ],
    "wof:name": "postcard: TWA (Trans World Airlines), Lockheed Model L-749A Constellation",
    "wof:placetype": "custom"
  },
  "geometry": {"coordinates":[-122.386155,37.616357],"type":"Point"}
}
