{
  "type": "Feature",
  "properties": {
    "date:cessation_lower": "1989-01-01",
    "date:cessation_upper": "1989-12-31",
    "date:inception_lower": "1989-01-01",
    "date:inception_upper": "1989-12-31",
    "iso:country": "XX",
    "sfomuseum:accession_number": "99-0824",
    "sfomuseum:author": "Crouch, Tom D.",
    "sfomuseum:callnumber": "TL521 .C65 1989",
    "sfomuseum:category": "Book",
    "sfomuseum:collection": "Aviation Library",
    "sfomuseum:date": "c. 1989",
    "sfomuseum:daterange_end": "1994-12-31",
    "sfomuseum:daterange_start": "1984-01-01",
    "sfomuseum:description": "349 p. : ill. ; 23 cm.",
    "sfomuseum:description_library": "349 p. : ill. ; 23 cm.",
    "sfomuseum:medium": "paper, ink",
    "sfomuseum:placetype": "object",
    "sfomuseum:publication": "Washington, D.C.: Smithsonian Institution Press, c. 1989.",
    "sfomuseum:publisher": "Smithsonian Institution Press",
    "sfomuseum:publisher_location": "Washington, D.C.",
    "sfomuseum:subcategory": "Book",
    "sfomuseum:subject": "Aeronautics United States History.",
    "wof:name": "A dream of wings: Americans and the airplane, 1875-1905",
    "wof:placetype": "custom",
    "wof:placetype_alt": "object"
  },
  "geometry": {"coordinates":[-122.386155,37.616357],"type":"Point"}
}
