{
  "type": "Feature",
  "properties": {
    "date:cessation_lower": "1982-12-31",
    "date:cessation_upper": "1982-12-31",
    "date:inception_lower": "1982-01-01",
    "date:inception_upper": "1982-01-01",
    "iso:country": "XX",
    "sfomuseum:accession_number": "2005.132.002.083",
    "sfomuseum:category": "Scheduling / Ticketing",
    "sfomuseum:collection": "Aviation Archive",
    "sfomuseum:creditline": "Gift of the William Hough Collection",
    "sfomuseum:date": "1982",
    "sfomuseum:daterange_end": "1982-12-31",
    "sfomuseum:daterange_start": "1982-01-01",
    "sfomuseum:description": "Timetable issued by AirCal, effective December 1, 1982; four page double-sided fold-out with text, “New expanded service.” The cover features a full color photographic image of a female employee.  The top of the schedule is white with the company name in dark brown lettering.",
    "sfomuseum:media_ids": [
      1527844521, 
      1527834463
    ],
    "sfomuseum:medium": "paper, ink",
    "sfomuseum:placetype": "object",
    "sfomuseum:subcategory": "Timetable",
    "wof:name": "timetable: AirCal",
    "wof:placetype": "venue"
  },
  "geometry": {"coordinates":[-122.386155,37.616358],"type":"Point"}
}
