{
  "type": "Feature",
  "properties": {
    "date:cessation_lower": "1944-12-31",
    "date:cessation_upper": "1944-12-31",
    "date:inception_lower": "1934-01-01",
    "date:inception_upper": "1934-01-01",
    "iso:country": "XX",
    "millsfield:images": [
      1527835087
    ],
    "sfomuseum:accession_number": "2012.149.1382",
    "sfomuseum:airline": "Pan American World Airways",
    "sfomuseum:category": "Promotional",
    "sfomuseum:collection": "Aviation Archive",
    "sfomuseum:creditline": "Gift of the Captain John B. Russell Family",
    "sfomuseum:date": "c. 1939",
    "sfomuseum:daterange_end": "1944-12-31",
    "sfomuseum:daterange_start": "1934-01-01",
    "sfomuseum:description": "Luggage label promoting Pan American World Airways; rectangular format with white background; aircraft in flight over flag with Pan Am logo.",
    "sfomuseum:dimensions": "4 x 4 1/4 inches (10.2 x 10.8 cm)",
    "sfomuseum:media_ids": [
      1527835087
    ],
    "sfomuseum:medium": "paper, ink",
    "sfomuseum:placetype": "object",
    "sfomuseum:subcategory": "Luggage Label",
    "wof:depicts": [
      1159284989
    ],
    "wof:name": "luggage label: Pan American World Airways",
    "wof:placetype": "venue"
  },
  "geometry": {"coordinates":[-122.386155,37.616357],"type":"Point"}
}
