{
  "type": "Feature",
  "properties": {
    "date:cessation_lower": "1995-01-01",
    "date:cessation_upper": "1995-12-31",
    "date:inception_lower": "1995-01-01",
    "date:inception_upper": "1995-12-31",
    "iso:country": "XX",
    "sfomuseum:accession_number": "1999.030.023",
    "sfomuseum:airline": "Pan American World Airways",
    "sfomuseum:author": "Gandt, Robert L.",
    "sfomuseum:callnumber": "HE9803.P36 G36 1995 c.3",
    "sfomuseum:category": "Book",
    "sfomuseum:collection": "Aviation Library",
    "sfomuseum:creditline": "Gift of Marjory D. Karnacki",
    "sfomuseum:date": "1995",
    "sfomuseum:date_acquired": "1999-10-06",
    "sfomuseum:daterange_end": "1995-12-31",
    "sfomuseum:daterange_start": "1995-01-01",
    "sfomuseum:description": "viii, 326 p. : ill. ; 25 cm.",
    "sfomuseum:description_library": "viii, 326 p. : ill. ; 25 cm.",
    "sfomuseum:medium": "paper, ink",
    "sfomuseum:placetype": "object",
    "sfomuseum:publication": "New York: Morrow, 1995.",
    "sfomuseum:publisher": "Morrow",
    "sfomuseum:publisher_location": "New York",
    "sfomuseum:subcategory": "Book",
    "sfomuseum:subject": "Pan American World Airways, inc. History.Airlines United States History.",
    "wof:depicts": [
      1159286839,
      1159284989
    ],
    "wof:name": "Skygods: the fall of Pan Am",
    "wof:placetype": "custom",
    "wof:placetype_alt": "object"
  },
  "geometry": {"coordinates":[-122.386155,37.616357],"type":"Point"}
}
