{
  "type": "Feature",
  "properties": {
    "date:cessation_lower":"1950-12-31",
    "date:cessation_upper":"1950-12-31",
    "date:inception_lower":"1950-01-01",
    "date:inception_upper":"1950-01-01",
    "iso:country":"XX",
    "millsfield:images":[
        1527832709,
        1527832705
    ],
    "sfomuseum:accession_number":"2012.149.1806",
    "sfomuseum:category":"Philately",
    "sfomuseum:collection":"Aviation Archive",
    "sfomuseum:creditline":"Gift of the Captain John B. Russell Family",
    "sfomuseum:date":"11/22/1950",
    "sfomuseum:daterange_end":"1950-11-22",
    "sfomuseum:daterange_start":"1950-11-22",
    "sfomuseum:description":"Airmail flight cover, Pan American World Airways, honoring fifteenth anniversary of first airmail flight from San Francisco to Honolulu; green cachet at center with text, \u201c15th Anniversary / First Airmail Flight / San Francisco to Honolulu / November 22, 1935 - 1950\u201d; postmarked November 22, 1950 with 6-cent postage stamp; backstamp: November 22, 1950 in Honolulu; addressed to Paul H. Anderson.",
    "sfomuseum:media_ids":[
        1527832705,
        1527832709
    ],
    "sfomuseum:medium":"paper, ink",
    "sfomuseum:placetype":"object",
    "sfomuseum:subcategory":"Airmail Flight Cover",
    "wof:name":"airmail flight cover: Pan American World Airways, San Francisco - Honolulu First airmail flight, 15th Anniversary",
    "wof:placetype":"venue"
},
  "geometry": {"coordinates":[-122.386155,37.616358],"type":"Point"}
}