{
  "type": "Feature",
  "properties": {
    "date:cessation_lower": "1986-01-01",
    "date:cessation_upper": "1986-12-31",
    "date:inception_lower": "1986-01-01",
    "date:inception_upper": "1986-12-31",
    "iso:country": "XX",
    "loc:named_authorities": [
      "n82075719"
    ],
    "sfomuseum:accession_number": "2000.181.040",
    "sfomuseum:airline": "Continental Airlines",
    "sfomuseum:author": "Murphy, Michael E.",
    "sfomuseum:callnumber": "HE9803.C65 M87 1986 c.1",
    "sfomuseum:category": "Book",
    "sfomuseum:collection": "Aviation Library",
    "sfomuseum:creditline": "Gift of William A. Mathis",
    "sfomuseum:date": "1986",
    "sfomuseum:date_acquired": "1999-10-05",
    "sfomuseum:daterange_end": "1986-12-31",
    "sfomuseum:daterange_start": "1986-01-01",
    "sfomuseum:description": "289 p. ; 24 cm.",
    "sfomuseum:description_library": "289 p. ; 24 cm.",
    "sfomuseum:medium": "paper, ink",
    "sfomuseum:placetype": "object",
    "sfomuseum:publication": "New York: F. Watts, 1986.",
    "sfomuseum:publisher": "F. Watts",
    "sfomuseum:publisher_location": "New York",
    "sfomuseum:subcategory": "Book",
    "sfomuseum:subject": "Continental Airlines.",
    "wof:depicts": [
      1360700741,
      1159284201
    ],
    "wof:name": "The airline that pride almost bought: the struggle to take over Continental Airlines",
    "wof:placetype": "custom",
    "wof:placetype_alt": "object"
  },
  "geometry": {"coordinates":[-122.386155,37.616357],"type":"Point"}
}
