{
  "type": "Feature",
  "properties": {
    "date:cessation_lower": "1994-01-01",
    "date:cessation_upper": "1994-12-31",
    "date:inception_lower": "1994-01-01",
    "date:inception_upper": "1994-12-31",
    "iso:country": "XX",
    "sfomuseum:accession_number": "99-0974",
    "sfomuseum:author": "Nader, Ralph",
    "sfomuseum:callnumber": "TL553.5 .N25 1994 c.2",
    "sfomuseum:category": "Book",
    "sfomuseum:collection": "Aviation Library",
    "sfomuseum:date": "c. 1994",
    "sfomuseum:daterange_end": "1999-12-31",
    "sfomuseum:daterange_start": "1989-01-01",
    "sfomuseum:description": "xxii, 378 p. ; 24 cm.",
    "sfomuseum:medium": "paper, ink",
    "sfomuseum:placetype": "object",
    "sfomuseum:publisher": "Tab Books",
    "sfomuseum:publisher_location": "Blue Ridge Summit, PA",
    "sfomuseum:subcategory": "Book",
    "sfomuseum:subject": "Aeronautics, Commercial United States Safety measures.",
    "wof:name": "Collision course: the truth about airline safety",
    "wof:placetype": "custom"
  },
  "geometry": {"coordinates":[-122.386155,37.616357],"type":"Point"}
}
