{
  "type": "Feature",
  "properties": {
    "date:cessation_lower": "1943-01-01",
    "date:cessation_upper": "1943-12-31",
    "date:inception_lower": "1943-01-01",
    "date:inception_upper": "1943-12-31",
    "iso:country": "XX",
    "sfomuseum:accession_number": "2004.020.010",
    "sfomuseum:author": "Cleveland, Reginald",
    "sfomuseum:callnumber": "TL501 .C63 1944 c.2",
    "sfomuseum:category": "Book",
    "sfomuseum:collection": "Aviation Library",
    "sfomuseum:creditline": "Gift of Helene and Rudy Stahl",
    "sfomuseum:date": "1943",
    "sfomuseum:date_acquired": "2005-01-26",
    "sfomuseum:daterange_end": "1943-12-31",
    "sfomuseum:daterange_start": "1943-01-01",
    "sfomuseum:medium": "paper, ink",
    "sfomuseum:notes_library": "Valued at $16.00 on DOG(KY 1/20/2006)",
    "sfomuseum:placetype": "object",
    "sfomuseum:publication": "Garden City, NY: Aviation Research Associates, 1943.",
    "sfomuseum:publisher": "Aviation Research Associates",
    "sfomuseum:publisher_location": "Garden City, NY",
    "sfomuseum:subcategory": "Book",
    "wof:name": "The Aviation annual of 1944",
    "wof:placetype": "venue"
  },
  "geometry": {"coordinates":[-122.386155,37.616357],"type":"Point"}
}
