{
  "type": "Feature",
  "properties": {
    "date:cessation_lower":"1965-12-31",
    "date:cessation_upper":"1965-12-31",
    "date:inception_lower":"1965-01-01",
    "date:inception_upper":"1965-01-01",
    "iso:country":"XX",
    "millsfield:images":[
        1527833557,
        1527833561
    ],
    "sfomuseum:accession_number":"2012.149.1903",
    "sfomuseum:airline":"Pan American World Airways",
    "sfomuseum:category":"Philately",
    "sfomuseum:collection":"Aviation Archive",
    "sfomuseum:creditline":"Gift of the Captain John B. Russell Family",
    "sfomuseum:date":"07/01/1965",
    "sfomuseum:daterange_end":"1965-07-01",
    "sfomuseum:daterange_start":"1965-07-01",
    "sfomuseum:description":"Airmail flight cover, Pan American World Airways, San Francisco to New York around the world; black cachet at left depicting global route map with text, \u201cFirst \u2018Round the World Jet Freighter Service\u201d; postmarked July 1, 1965, San Francisco, with 25-cent postage stamp; backstamped July 5, 1965, New York; addressed to Oscar H. Fatout.",
    "sfomuseum:media_ids":[
        1527833557,
        1527833561
    ],
    "sfomuseum:medium":"paper, ink",
    "sfomuseum:placetype":"object",
    "sfomuseum:subcategory":"Airmail Flight Cover",
    "wof:depicts":[
        1159284989
    ],
    "wof:name":"airmail flight cover: Pan American World Airways, Jet Freighter Service, San Francisco - New York route",
    "wof:placetype":"venue"
},
  "geometry": {"coordinates":[-122.386155,37.616357],"type":"Point"}
}