{
  "type": "Feature",
  "properties": {
    "date:cessation_lower":"1969-12-31",
    "date:cessation_upper":"1969-12-31",
    "date:inception_lower":"1960-01-01",
    "date:inception_upper":"1960-01-01",
    "iso:country":"XX",
    "sfomuseum:accession_number":"2011.052.001",
    "sfomuseum:category":"Promotional",
    "sfomuseum:collection":"Aviation Museum",
    "sfomuseum:creditline":"Purchase",
    "sfomuseum:date":"1960s",
    "sfomuseum:daterange_end":"1969-12-31",
    "sfomuseum:daterange_start":"1960-01-01",
    "sfomuseum:description":"Small red and white cylindrical bag with drawstring closure; white \u201cNorthwest Orient\u201d logotype across center, surrounded by repeating tile pattern of faint airline logos; \u201cHawaii\u201d printed across base.",
    "sfomuseum:medium":"vinyl, ink, metal",
    "sfomuseum:placetype":"object",
    "sfomuseum:subcategory":"Airline Bag",
    "wof:name":"miniature airline bag: Northwest Orient Airlines",
    "wof:placetype":"venue"
},
  "geometry": {"coordinates":[-122.386155,37.616358],"type":"Point"}
}