{
  "type": "Feature",
  "properties": {
    "date:cessation_lower": "1957-01-01",
    "date:cessation_upper": "1957-12-31",
    "date:inception_lower": "1957-01-01",
    "date:inception_upper": "1957-12-31",
    "iso:country": "XX",
    "millsfield:images": [
      1729566515
    ],
    "millsfield:images_texts": [
      "EFFECTIVE DATE 14th APRIL,\n1957\nNEXT ISSUE Ist JUNE, 1957\nQANTAS\nTIMETABLE\nSCHEDULES \u0026 FARES\nAUSTRALIAS OVERSEAS AIRLINE"
    ],
    "millsfield:images_texts_ids": [
      1729566515
    ],
    "millsfield:primary_image": 1729566515,
    "sfomuseum:accession_number": "2014.084.1158",
    "sfomuseum:airline": "Qantas Empire Airways",
    "sfomuseum:category": "Scheduling / Ticketing",
    "sfomuseum:collection": "Aviation Archive",
    "sfomuseum:creditline": "Gift of Thomas G. Dragges",
    "sfomuseum:date": "1957",
    "sfomuseum:date_acquired": "2015-07-02",
    "sfomuseum:daterange_end": "1957-12-31",
    "sfomuseum:daterange_start": "1957-01-01",
    "sfomuseum:description": "Timetable issued by Qantas Empire Airways, effective April 14, 1957; multipage booklet; yellow, black, and white cover with illustration depicting globe.",
    "sfomuseum:dimensions": "8 3/4 x 3 3/4 inches (22.2 x 9.5 cm)",
    "sfomuseum:medium": "paper, ink, metal",
    "sfomuseum:placetype": "object",
    "sfomuseum:publication": ": , 1957.",
    "sfomuseum:subcategory": "Timetable",
    "wof:depicts": [
      1159287479,
      1159285825
    ],
    "wof:name": "timetable: Qantas Empire Airways",
    "wof:placetype": "custom",
    "wof:placetype_alt": "object"
  },
  "geometry": {"coordinates":[-122.386155,37.616357],"type":"Point"}
}
