{
  "type": "Feature",
  "properties": {
    "date:cessation_lower":"1957-12-31",
    "date:cessation_upper":"1957-12-31",
    "date:inception_lower":"1957-01-01",
    "date:inception_upper":"1957-01-01",
    "iso:country":"XX",
    "sfomuseum:accession_number":"2014.084.1158",
    "sfomuseum:airline":"Qantas Empire Airways  (Qantas Airways)",
    "sfomuseum:category":"Scheduling / Ticketing",
    "sfomuseum:collection":"Aviation Archive",
    "sfomuseum:creditline":"Gift of Thomas G. Dragges",
    "sfomuseum:date":"1957",
    "sfomuseum:daterange_end":"1957-12-31",
    "sfomuseum:daterange_start":"1957-01-01",
    "sfomuseum:description":"Timetable issued by Qantas Empire Airways, effective April 14, 1957; multipage booklet; yellow, black, and white cover with illustration depicting globe.",
    "sfomuseum:medium":"paper, ink, metal",
    "sfomuseum:placetype":"object",
    "sfomuseum:subcategory":"Timetable",
    "wof:depicts":[
        1159285825
    ],
    "wof:name":"timetable: Qantas Empire Airways",
    "wof:placetype":"venue"
},
  "geometry": {"coordinates":[-122.386155,37.616357],"type":"Point"}
}