{
  "type": "Feature",
  "properties": {
    "date:cessation_lower": "1988-12-31",
    "date:cessation_upper": "1988-12-31",
    "date:inception_lower": "1988-01-01",
    "date:inception_upper": "1988-01-01",
    "iso:country": "XX",
    "sfomuseum:accession_number": "2008.108.451",
    "sfomuseum:category": "Scheduling / Ticketing",
    "sfomuseum:collection": "Aviation Archive",
    "sfomuseum:creditline": "Gift of the William Hough Collection",
    "sfomuseum:date": "1988",
    "sfomuseum:daterange_end": "1988-12-31",
    "sfomuseum:daterange_start": "1988-01-01",
    "sfomuseum:description": "Timetable issued by Midwest Express Airlines (Midwest Airlines), effective July 15, 1988; four page double-sided fold-out; silver cover with color photographic image of male flight crew member in front of partial view of aircraft.",
    "sfomuseum:media_ids": [
      1527840795
    ],
    "sfomuseum:medium": "paper, ink",
    "sfomuseum:placetype": "object",
    "sfomuseum:subcategory": "Timetable",
    "wof:name": "timetable: Midwest Express Airlines (Midwest Airlines)",
    "wof:placetype": "venue"
  },
  "geometry": {"coordinates":[-122.386155,37.616358],"type":"Point"}
}
