{
  "type": "Feature",
  "properties": {
    "date:cessation_lower": "1930-01-01",
    "date:cessation_upper": "1930-12-31",
    "date:inception_lower": "1930-01-01",
    "date:inception_upper": "1930-12-31",
    "iso:country": "US",
    "millsfield:images": [
      1527820793
    ],
    "millsfield:primary_image": 1527820793,
    "sfomuseum:accession_number": "2008.056.0881",
    "sfomuseum:airline": "New York, Rio, and Buenos Aires Line (NYRBA)",
    "sfomuseum:category": "Promotional",
    "sfomuseum:collection": "Aviation Archive",
    "sfomuseum:continent": "North America",
    "sfomuseum:country": "United States",
    "sfomuseum:creditline": "Gift of Jon E. Krupnick",
    "sfomuseum:date": "c. 1930",
    "sfomuseum:daterange_end": "1935-12-31",
    "sfomuseum:daterange_start": "1925-01-01",
    "sfomuseum:description": "Rectangular luggage label issued by New York, Rio \u0026 Buenos Aires (NYRBA); with text \"Lineas NYRBA, El Vinculo de Las Americas\"; blue and white illustration of Commodore aircraft in flight over water.",
    "sfomuseum:dimensions": "4 1/2 x 3 5/8 inches (11.4 x 9.2 cm)",
    "sfomuseum:media_ids": [
      1527820793
    ],
    "sfomuseum:medium": "paper, ink, adhesive",
    "sfomuseum:placetype": "object",
    "sfomuseum:subcategory": "Luggage Label",
    "sfomuseum:subject": "Airlines -- Commercial -- NYRBA",
    "wof:depicts": [
      1159284865
    ],
    "wof:name": "luggage label: New York, Rio \u0026 Buenos Aires Line (NYRBA)",
    "wof:placetype": "venue"
  },
  "geometry": {"coordinates":[-122.386155,37.616357],"type":"Point"}
}
