{
  "type": "Feature",
  "properties": {
    "date:cessation_lower": "2004-01-01",
    "date:cessation_upper": "2004-12-31",
    "date:inception_lower": "2004-01-01",
    "date:inception_upper": "2004-12-31",
    "iso:country": "XX",
    "millsfield:images": [
      1527846335,
      1527846337
    ],
    "sfomuseum:accession_number": "2006.059.307.116",
    "sfomuseum:airline": "United Airlines",
    "sfomuseum:category": "Passenger Amenity",
    "sfomuseum:collection": "Aviation Archive",
    "sfomuseum:creditline": "Gift of the Paul Edward Fair Estate",
    "sfomuseum:date": "2004",
    "sfomuseum:daterange_end": "2004-12-31",
    "sfomuseum:daterange_start": "2004-01-01",
    "sfomuseum:description": "Menu issued by United Airlines, Los Angeles / San Francisco - Sydney route; color photographic image of breadsticks in a container; menu items include filet mignon Hollandaise, rotisserie chicken, and potato and bacon chowder; menu number: 290C003-1 LAX-/SFO-SYD (LD83-S89-B87); class: Business; date: 3/02.",
    "sfomuseum:dimensions": "9 3/4 x 5 1/2 inches (24.8 x 14 cm)",
    "sfomuseum:media_ids": [
      1527846335,
      1527846337
    ],
    "sfomuseum:medium": "paper, ink",
    "sfomuseum:placetype": "object",
    "sfomuseum:subcategory": "Menu",
    "wof:depicts": [
      1159285413
    ],
    "wof:name": "menu: United Airlines, Business Class",
    "wof:placetype": "venue"
  },
  "geometry": {"coordinates":[-122.386155,37.616357],"type":"Point"}
}
