{
  "type": "Feature",
  "properties": {
    "date:cessation_lower": "1947-05-01",
    "date:cessation_upper": "1947-05-01",
    "date:inception_lower": "1947-05-01",
    "date:inception_upper": "1947-05-01",
    "iso:country": "XX",
    "millsfield:images": [
      1527834301,
      1527834307
    ],
    "millsfield:images_texts": [
      "AIR MAIL\n5¢\n5¢\nUNITED STATES OF AMERICA\n1947\n5AM\nHAWAI\nFIRST\nFLIGHT\nU. S.\nAIR\nMAIL\nMrs. William F. Springer\n3686- Pershing Anenne\nSau Diego - 4\n710-6 8\nbalifaricia",
      "N 2.\nFIRST FLIGHT\nNONGLULUTO\nSAN FRANCISCO\nUNITED\nMAINLINER 300\n5C AIR MAIL TO THE STATES\n2012149.1673"
    ],
    "millsfield:images_texts_ids": [
      1527834301,
      1527834307
    ],
    "millsfield:primary_image": 1527834301,
    "sfomuseum:accession_number": "2012.149.1673",
    "sfomuseum:airline": "United Air Lines",
    "sfomuseum:category": "Philately",
    "sfomuseum:collection": "Aviation Archive",
    "sfomuseum:creditline": "Gift of the Captain John B. Russell Family",
    "sfomuseum:date": "05/01/1947",
    "sfomuseum:date_acquired": "2013-05-31",
    "sfomuseum:daterange_end": "1947-05-01",
    "sfomuseum:daterange_start": "1947-05-01",
    "sfomuseum:description": "Airmail flight cover issued by United Air Lines for first airmail flight of Mainliner 300, Honolulu to San Francisco; oval blue cachet at left depicting Golden Gate Bridge; blue cachet on reverse with commemorative text; postmarked May 1, 1947 in Honolulu with four-bar cancellation mark over 5-cent stamp; backstamp: May 1, 1947 in San Francisco; addressed to Mrs. William F. Springer.",
    "sfomuseum:dimensions": "4 x 6 3/4 inches (10.2 x 17.1 cm)",
    "sfomuseum:media_ids": [
      1527834301,
      1527834307
    ],
    "sfomuseum:medium": "paper, ink",
    "sfomuseum:placetype": "object",
    "sfomuseum:publication": ": , 05/01/1947.",
    "sfomuseum:subcategory": "Airmail Flight Cover",
    "wof:depicts": [
      1159285415,
      1159288779
    ],
    "wof:name": "airmail flight cover: FAM-30, United Air Lines, Mainliner 300",
    "wof:placetype": "custom",
    "wof:placetype_alt": "object"
  },
  "geometry": {"coordinates":[-122.386155,37.616357],"type":"Point"}
}
