{
  "type": "Feature",
  "properties": {
    "date:cessation_lower": "1928-01-01",
    "date:cessation_upper": "1928-12-31",
    "date:inception_lower": "1928-01-01",
    "date:inception_upper": "1928-12-31",
    "iso:country": "XX",
    "millsfield:images": [
      1527821087
    ],
    "millsfield:primary_image": 1527821087,
    "sfomuseum:accession_number": "2001.015.018",
    "sfomuseum:aircraft": "Ford Tri-Motor",
    "sfomuseum:airline": "Maddux Air Lines",
    "sfomuseum:artist": "Wayne “Dick” Whittington",
    "sfomuseum:category": "Photograph",
    "sfomuseum:collection": "Aviation Archive",
    "sfomuseum:creditline": "Gift of Thomas G. Dragges",
    "sfomuseum:date": "c. 1928",
    "sfomuseum:date_acquired": "2003-10-23",
    "sfomuseum:daterange_end": "1933-12-31",
    "sfomuseum:daterange_start": "1923-01-01",
    "sfomuseum:description": "Black and white photograph depicting interior view of Maddux Air Lines Ford Tri-Motor with seated passengers Pricilla Dean (?), Helene Chadwick, and Edna Murphy at left, \"Belt\" (?) Tomlinson and Mrs. Maddux at right.",
    "sfomuseum:dimensions": "8 x 10 inches (20.3 x 25.4 cm)",
    "sfomuseum:media_ids": [
      1527821087
    ],
    "sfomuseum:medium": "photograph",
    "sfomuseum:placetype": "object",
    "sfomuseum:publication": ": , c. 1928.",
    "sfomuseum:subcategory": "Print, Photograph",
    "wof:depicts": [
      1159292297,
      1159284723
    ],
    "wof:name": "photograph: Maddux Air Lines, Ford Tri-Motor, interior",
    "wof:placetype": "venue"
  },
  "geometry": {"coordinates":[-122.386155,37.616358],"type":"Point"}
}
