{
  "type": "Feature",
  "properties": {
    "date:cessation_lower": "1959-12-31",
    "date:cessation_upper": "1959-12-31",
    "date:inception_lower": "1949-01-01",
    "date:inception_upper": "1949-01-01",
    "iso:country": "XX",
    "millsfield:images": [
      1527821095
    ],
    "sfomuseum:accession_number": "2002.093.013.020",
    "sfomuseum:airline": "Pan American World Airways",
    "sfomuseum:category": "Photograph",
    "sfomuseum:collection": "Aviation Archive",
    "sfomuseum:creditline": "Gift of the Pottorff family in memory of George B. Pottorff, Jr. ",
    "sfomuseum:date": "c. 1954",
    "sfomuseum:daterange_end": "1959-12-31",
    "sfomuseum:daterange_start": "1949-01-01",
    "sfomuseum:description": "Black and white publicity photograph produced by Pacific Rim division of Pan American World Airways, Honolulu base, depicting officials posing with San Francisco 49ers’ mule mascot Clementine; Boeing 377 Stratocruiser “Clipper Golden Gate” in background.",
    "sfomuseum:dimensions": "10 x 8 inches (25.4 x 20.3 cm)",
    "sfomuseum:media_ids": [
      1527821095
    ],
    "sfomuseum:medium": "photograph",
    "sfomuseum:placetype": "object",
    "sfomuseum:subcategory": "Print, Photograph",
    "sfomuseum:subject": "Airlines -- Commercial -- Pan American World Airways\rFlight attendants",
    "wof:depicts": [
      1159284989,
      1159289651,
      1159293593
    ],
    "wof:name": "photograph: Pan American World Airways, mule Clementine",
    "wof:placetype": "custom"
  },
  "geometry": {"coordinates":[-122.386155,37.616357],"type":"Point"}
}
