{
  "type": "Feature",
  "properties": {
    "date:cessation_lower": "2003-01-01",
    "date:cessation_upper": "2003-12-31",
    "date:inception_lower": "2003-01-01",
    "date:inception_upper": "2003-12-31",
    "iso:country": "XX",
    "sfomuseum:accession_number": "2009.007.044",
    "sfomuseum:airport": "San Francisco International Airport",
    "sfomuseum:author": "Ardema, Mark D",
    "sfomuseum:category": "Audio / Visual",
    "sfomuseum:collection": "Aviation Archive",
    "sfomuseum:creditline": "Transfer from City and County of San Francisco",
    "sfomuseum:date": "2003",
    "sfomuseum:date_acquired": "2009-02-05",
    "sfomuseum:daterange_end": "2003-12-31",
    "sfomuseum:daterange_start": "2003-01-01",
    "sfomuseum:description": "Audio cassette tape recorded at San Francisco Airport Museums' Centennial of Flight lecture series;  lecture by Dr. Mark D. Ardema presented on September 27, 2003; 54 minutes.",
    "sfomuseum:dimensions": "3 x 4 inches (7.6 x 10.2 cm)",
    "sfomuseum:medium": "paper, ink",
    "sfomuseum:placetype": "object",
    "sfomuseum:publication": ": San Francisco Airport Museums, 2003.",
    "sfomuseum:publisher": "San Francisco Airport Museums",
    "sfomuseum:series": "Centennial of flight lecture",
    "sfomuseum:subcategory": "Audio Tape",
    "wof:depicts": [
      102527513
    ],
    "wof:name": "audio cassette tape: John J. Montgomery: California's pioneer of flight / Dr. Mark D. Ardema",
    "wof:placetype": "custom",
    "wof:placetype_alt": "object"
  },
  "geometry": {"coordinates":[-122.386155,37.616357],"type":"Point"}
}
