{
  "type": "Feature",
  "properties": {
    "date:cessation_lower": "1950-12-31",
    "date:cessation_upper": "1950-12-31",
    "date:inception_lower": "1950-01-01",
    "date:inception_upper": "1950-01-01",
    "iso:country": "XX",
    "sfomuseum:accession_number": "2001.173.003",
    "sfomuseum:airline": "Pan American World Airways",
    "sfomuseum:category": "Book",
    "sfomuseum:collection": "Aviation Library",
    "sfomuseum:creditline": "Anonymous gift",
    "sfomuseum:date": "1950",
    "sfomuseum:daterange_end": "1950-12-31",
    "sfomuseum:daterange_start": "1950-01-01",
    "sfomuseum:description": "48 p.",
    "sfomuseum:medium": "paper, ink",
    "sfomuseum:placetype": "object",
    "sfomuseum:subcategory": "Book",
    "wof:depicts": [
      1159284989
    ],
    "wof:name": "The Pacific - Alaska flying clippers",
    "wof:placetype": "venue"
  },
  "geometry": {"coordinates":[-122.386155,37.616357],"type":"Point"}
}
