{
  "type": "Feature",
  "properties": {
    "date:cessation_lower": "1996-01-01",
    "date:cessation_upper": "1996-12-31",
    "date:inception_lower": "1996-01-01",
    "date:inception_upper": "1996-12-31",
    "iso:country": "XX",
    "millsfield:images": [
      1527818057,
      1527843709
    ],
    "millsfield:primary_image": 1527818057,
    "sfomuseum:accession_number": "2002.094.037",
    "sfomuseum:aircraft": "Concorde",
    "sfomuseum:airline": "British Airways",
    "sfomuseum:category": "Passenger Amenity",
    "sfomuseum:collection": "Aviation Archive",
    "sfomuseum:creditline": "Gift of Thomas G. Dragges",
    "sfomuseum:date": "1996",
    "sfomuseum:date_acquired": "2003-10-23",
    "sfomuseum:daterange_end": "1996-12-31",
    "sfomuseum:daterange_start": "1996-01-01",
    "sfomuseum:description": "Wine list issued by British Airways for Concorde service; dark blue cover with embossed horizontal lines; menu number: JFK; class: Concorde; date: 1996.",
    "sfomuseum:dimensions": "11 3/4 x 6 3/4 inches (29.8 x 17.1 cm)",
    "sfomuseum:media_ids": [
      1527843709,
      1527818057
    ],
    "sfomuseum:medium": "paper, ink",
    "sfomuseum:placetype": "object",
    "sfomuseum:publication": ": , 1996.",
    "sfomuseum:subcategory": "Menu",
    "wof:depicts": [
      1159290173,
      1159293811,
      1159284021
    ],
    "wof:name": "menu: British Airways, Concorde",
    "wof:placetype": "custom"
  },
  "geometry": {"coordinates":[-122.386155,37.616357],"type":"Point"}
}
