{
  "type": "Feature",
  "properties": {
    "date:cessation_lower":"1996-12-31",
    "date:cessation_upper":"1996-12-31",
    "date:inception_lower":"1996-01-01",
    "date:inception_upper":"1996-01-01",
    "iso:country":"XX",
    "sfomuseum:accession_number":"2002.094.037",
    "sfomuseum:category":"Food Service",
    "sfomuseum:collection":"Aviation Museum",
    "sfomuseum:creditline":"Gift of Thomas G. Dragges",
    "sfomuseum:date":"1996",
    "sfomuseum:daterange_end":"1996-12-31",
    "sfomuseum:daterange_start":"1996-01-01",
    "sfomuseum:description":"Wine list produced by British Airways for Concorde service; dark red cover with embossed horizontal lines; menu number: JFK; class: Concorde; date: 1796.",
    "sfomuseum:media_ids":[
        1527843709,
        1527818057
    ],
    "sfomuseum:medium":"paper, ink",
    "sfomuseum:placetype":"object",
    "sfomuseum:subcategory":"Menu",
    "wof:name":"menu: British Airways, Concorde",
    "wof:placetype":"venue"
},
  "geometry": {"coordinates":[-122.386155,37.616358],"type":"Point"}
}