{
  "type": "Feature",
  "properties": {
    "date:cessation_lower": "1997-01-01",
    "date:cessation_upper": "1997-12-31",
    "date:inception_lower": "1997-01-01",
    "date:inception_upper": "1997-12-31",
    "isbn:number": "0924272082, 9780924272080",
    "iso:country": "XX",
    "sfomuseum:accession_number": "00-1128",
    "sfomuseum:author": "Macha, Gary Patric",
    "sfomuseum:callnumber": "TL553.5 .M33 1997",
    "sfomuseum:category": "Book",
    "sfomuseum:collection": "Aviation Library",
    "sfomuseum:date": "c. 1997",
    "sfomuseum:daterange_end": "2002-12-31",
    "sfomuseum:daterange_start": "1992-01-01",
    "sfomuseum:description": "xv, 213 p. : ill., map ; 23 cm.",
    "sfomuseum:description_library": "xv, 213 p. : ill., map ; 23 cm.",
    "sfomuseum:medium": "paper, ink",
    "sfomuseum:placetype": "object",
    "sfomuseum:publication": "San Clemente, CA: Info Net, c. 1997.",
    "sfomuseum:publisher": "Info Net",
    "sfomuseum:publisher_location": "San Clemente, CA",
    "sfomuseum:subcategory": "Book",
    "sfomuseum:subject": "Aircraft accidents California History.",
    "wof:name": "Aircraft wrecks in the mountains and deserts of California, 1909-1996",
    "wof:placetype": "custom",
    "wof:placetype_alt": "object"
  },
  "geometry": {"coordinates":[-122.386155,37.616357],"type":"Point"}
}
