{
  "type": "Feature",
  "properties": {
    "date:cessation_lower": "1984-04-12",
    "date:cessation_upper": "1984-04-12",
    "date:inception_lower": "1984-04-12",
    "date:inception_upper": "1984-04-12",
    "iso:country": "XX",
    "sfomuseum:accession_number": "2015.056.050",
    "sfomuseum:category": "Philately",
    "sfomuseum:collection": "Aviation Archive",
    "sfomuseum:creditline": "Gift of Robert Harris",
    "sfomuseum:date": "04/12/1984",
    "sfomuseum:date_acquired": "2015-05-12",
    "sfomuseum:daterange_end": "1984-04-12",
    "sfomuseum:daterange_start": "1984-04-12",
    "sfomuseum:description": "Airmail flight cover, part of International Tributes to the History of Flight series by the Postal Commemorative Society; white envelope with full color illustration cachet and inset stamp commemorating flight of the first space shuttle on April 12, 1981, at Cape Canaveral, Florida, U.S.A., by John Young and Robert Crippen with space shuttle “Columbia”; cancellation stamp dated April 12, 1984 in Cape Canaveral; includes information on reverse.",
    "sfomuseum:dimensions": "5 x 7 1/2 inches (12.7 x 19.1 cm)",
    "sfomuseum:medium": "paper, ink",
    "sfomuseum:placetype": "object",
    "sfomuseum:publication": ": , 04/12/1984.",
    "sfomuseum:subcategory": "Airmail Flight Cover",
    "wof:name": "airmail flight cover: Flight of the first space shuttle commemorative",
    "wof:placetype": "custom",
    "wof:placetype_alt": "object"
  },
  "geometry": {"coordinates":[-122.386155,37.616357],"type":"Point"}
}
