{
  "type": "Feature",
  "properties": {
    "date:cessation_lower": "1995-01-01",
    "date:cessation_upper": "1995-12-31",
    "date:inception_lower": "1995-01-01",
    "date:inception_upper": "1995-12-31",
    "iso:country": "XX",
    "sfomuseum:accession_number": "00-0659",
    "sfomuseum:author": "Davies, R. E. G. (Ronald Edward George)",
    "sfomuseum:callnumber": "HE9868.6.S25 D39 1995 ",
    "sfomuseum:category": "Book",
    "sfomuseum:collection": "Aviation Library",
    "sfomuseum:date": "c. 1995",
    "sfomuseum:daterange_end": "2000-12-31",
    "sfomuseum:daterange_start": "1990-01-01",
    "sfomuseum:description": "64 p. : ill. (some col.) ; 23 x 29 cm.",
    "sfomuseum:description_library": "64 p. : ill. (some col.) ; 23 x 29 cm.",
    "sfomuseum:medium": "paper, ink",
    "sfomuseum:placetype": "object",
    "sfomuseum:publication": "McLean, VA: Paladwr Press, c. 1995.",
    "sfomuseum:publisher": "Paladwr Press",
    "sfomuseum:publisher_location": "McLean, VA",
    "sfomuseum:subcategory": "Book",
    "sfomuseum:subject": "SaÚaudaiyah (Airline) History.",
    "wof:name": "Saudi Arabian Airlines, an airline and its aircraft: the illustrated history of the largest airline in the Middle East",
    "wof:placetype": "custom"
  },
  "geometry": {"coordinates":[-122.386155,37.616357],"type":"Point"}
}
