{
  "type": "Feature",
  "properties": {
    "date:cessation_lower":"1954-12-31",
    "date:cessation_upper":"1954-12-31",
    "date:inception_lower":"1954-01-01",
    "date:inception_upper":"1954-01-01",
    "iso:country":"XX",
    "sfomuseum:accession_number":"2001.078.001",
    "sfomuseum:category":"Promotional",
    "sfomuseum:collection":"Aviation Archive",
    "sfomuseum:creditline":"Gift of Thomas G. Dragges",
    "sfomuseum:date":"1954",
    "sfomuseum:daterange_end":"1954-12-31",
    "sfomuseum:daterange_start":"1954-01-01",
    "sfomuseum:description":"Event program for dedication of International Terminal, \u201cSan Francisco International Airport Dedication and Flight Festival,\u201d dated August 27 through 29, 1954; cover features black and white illustration of Boeing 377 Strato-Clipper with stylized surrounding crowd; interior pages include black and white photographic reproductions and diagrams.",
    "sfomuseum:media_ids":[
        1527848575,
        1527848579,
        1527820693
    ],
    "sfomuseum:medium":"paper, ink",
    "sfomuseum:placetype":"object",
    "sfomuseum:subcategory":"Event Program / Invitation",
    "wof:depicts":[
        102527513
    ],
    "wof:name":"event program: Pan American World Airways, San Francisco International Airport (SFO) dedication",
    "wof:placetype":"venue"
},
  "geometry": {"coordinates":[-122.386155,37.616358],"type":"Point"}
}