{
  "type": "Feature",
  "properties": {
    "date:cessation_lower": "1950-01-01",
    "date:cessation_upper": "1959-12-31",
    "date:inception_lower": "1950-01-01",
    "date:inception_upper": "1959-12-31",
    "iso:country": "XX",
    "millsfield:images": [
      1729566771
    ],
    "millsfield:primary_image": 1729566771,
    "sfomuseum:accession_number": "2015.140.001",
    "sfomuseum:airline": "Qantas Empire Airways",
    "sfomuseum:category": "Beverage Service",
    "sfomuseum:collection": "Aviation Museum",
    "sfomuseum:date": "1950s",
    "sfomuseum:date_acquired": "2014-08-07",
    "sfomuseum:daterange_end": "1959-12-31",
    "sfomuseum:daterange_start": "1950-01-01",
    "sfomuseum:description": "Espresso cup manufactured by Royal Grafton Fine Bone China, England, for Qantas Empire Airways  (Qantas Airways) featuring off-white cup with handle; a pair of wings illustrated in dark red at top front; white glazed interior; bottom of cup stamped with manufacturer’s servicemark, and “Gibsons \u0026 Paterson Pty. / Australia \u0026 N.Z.”, at bottom, in dark red. ",
    "sfomuseum:dimensions": "2 1/4 x 3 x 2 inches (5.7 x 7.6 x 5.1 cm)",
    "sfomuseum:maker": "Royal Grafton",
    "sfomuseum:medium": "ceramic, pigment",
    "sfomuseum:placetype": "object",
    "sfomuseum:publication": ": , 1950s.",
    "sfomuseum:subcategory": "Coffee cup / Teacup / Saucer",
    "wof:depicts": [
      1159285825
    ],
    "wof:name": "espresso cup: Qantas Empire Airways  (Qantas Airways)",
    "wof:placetype": "venue"
  },
  "geometry": {"coordinates":[-122.386155,37.616357],"type":"Point"}
}
