{
  "type": "Feature",
  "properties": {
    "date:cessation_lower": "1976-12-31",
    "date:cessation_upper": "1976-12-31",
    "date:inception_lower": "1976-01-01",
    "date:inception_upper": "1976-01-01",
    "iso:country": "XX",
    "sfomuseum:accession_number": "2010.012.050 a b",
    "sfomuseum:aircraft": "Boeing 727",
    "sfomuseum:airline": "Hughes Airwest",
    "sfomuseum:category": "Philately",
    "sfomuseum:collection": "Aviation Archive",
    "sfomuseum:creditline": "Gift of Trudy and Henry Sandoval",
    "sfomuseum:date": "03/19/1976",
    "sfomuseum:daterange_end": "1976-03-19",
    "sfomuseum:daterange_start": "1976-03-19",
    "sfomuseum:description": "Airmail flight cover issued by Hughes Airwest on occasion of air carrier’s thirtieth anniversary; square preprinted cachet at left, “Commemorating 30 years of air service in the West by Hughes Airwest and its predecessors”; postmarked March 19, 1976 in Chicago with “First day of issue” cancellation mark over 13-cent stamp.\ra. Envelope\rb. Enclosed typed memo folded in thirds, dated March 19, 1976",
    "sfomuseum:medium": "paper, ink",
    "sfomuseum:placetype": "object",
    "sfomuseum:subcategory": "Airmail Flight Cover",
    "wof:depicts": [
      1159284507,
      1159289759
    ],
    "wof:name": "airmail flight cover: Hughes Airwest, 30th anniversary",
    "wof:placetype": "venue"
  },
  "geometry": {"coordinates":[-122.386155,37.616357],"type":"Point"}
}
