{
  "type": "Feature",
  "properties": {
    "date:cessation_lower": "1950-01-01",
    "date:cessation_upper": "1950-12-31",
    "date:inception_lower": "1950-01-01",
    "date:inception_upper": "1950-12-31",
    "iso:country": "XX",
    "loc:subject_headings": [
      "sh85001360"
    ],
    "sfomuseum:accession_number": "2000.171.116",
    "sfomuseum:author": "James, J. W. G., ed.; and John Stroud, ed.",
    "sfomuseum:callnumber": "TL552 .W67 1950",
    "sfomuseum:category": "Book",
    "sfomuseum:collection": "Aviation Library",
    "sfomuseum:creditline": "Collection of SFO Museum",
    "sfomuseum:date": "1950",
    "sfomuseum:date_acquired": "2000-01-01",
    "sfomuseum:daterange_end": "1950-12-31",
    "sfomuseum:daterange_start": "1950-01-01",
    "sfomuseum:description": "319 p. illus., port., maps. 23 cm.",
    "sfomuseum:description_library": "319 p. illus., port., maps. 23 cm.",
    "sfomuseum:medium": "paper, ink",
    "sfomuseum:placetype": "object",
    "sfomuseum:publication": "London: Odhams Press, 1950.",
    "sfomuseum:publisher": "Odhams Press",
    "sfomuseum:publisher_location": "London",
    "sfomuseum:subcategory": "Book",
    "sfomuseum:subject": "Aeronautics, Commercial.",
    "wof:name": "The World's airways and how they work",
    "wof:placetype": "custom",
    "wof:placetype_alt": [
      "object"
    ]
  },
  "geometry": {"coordinates":[-122.386155,37.616357],"type":"Point"}
}
