{
  "type": "Feature",
  "properties": {
    "date:cessation_lower": "1958-01-01",
    "date:cessation_upper": "1958-12-31",
    "date:inception_lower": "1958-01-01",
    "date:inception_upper": "1958-12-31",
    "iso:country": "XX",
    "sfomuseum:accession_number": "2007.114.001",
    "sfomuseum:airline": "Pan American World Airways",
    "sfomuseum:category": "Audio / Visual",
    "sfomuseum:collection": "Aviation Archive",
    "sfomuseum:creditline": "Gift of Grant Young",
    "sfomuseum:date": "1958",
    "sfomuseum:daterange_end": "1958-12-31",
    "sfomuseum:daterange_start": "1958-01-01",
    "sfomuseum:description": "LP phonograph record album titled, \"Jazz Impressions of Eurasia: The Dave Brubeck Quartet\"; cover with color photographic image of Brubeck greeted by locals carrying blue Pan Am tote bags; LP enclosed in paper sleeve; released by Columbia Records, catalogue no. CL 1251,",
    "sfomuseum:dimensions": "12 1/4 x 12 1/4 x 1/4 inches (31.1 x 31.1 x .6 cm)",
    "sfomuseum:medium": "cardboard, paper, ink, vinyl",
    "sfomuseum:placetype": "object",
    "sfomuseum:publication": ": , 1958.",
    "sfomuseum:subcategory": "Phonograph Record",
    "wof:depicts": [
      1159284989
    ],
    "wof:name": "phonograph record: Pan American World Airways, Jazz Impressions of Eurasia: The Dave Brubeck Quartet",
    "wof:placetype": "venue"
  },
  "geometry": {"coordinates":[-122.386155,37.616357],"type":"Point"}
}
