{
  "type": "Feature",
  "properties": {
    "date:cessation_lower": "1970-12-31",
    "date:cessation_upper": "1970-12-31",
    "date:inception_lower": "1970-01-01",
    "date:inception_upper": "1970-01-01",
    "iso:country": "XX",
    "millsfield:images": [
      1527827345
    ],
    "sfomuseum:accession_number": "2011.032.2234",
    "sfomuseum:aircraft": "Boeing 747-100",
    "sfomuseum:airline": "TWA (Trans World Airlines)",
    "sfomuseum:airport": "San Francisco International Airport",
    "sfomuseum:artist": "Marshall Moxom",
    "sfomuseum:category": "Photograph",
    "sfomuseum:collection": "Aviation Archive",
    "sfomuseum:creditline": "Transfer",
    "sfomuseum:date": "1970",
    "sfomuseum:daterange_end": "1970-12-31",
    "sfomuseum:daterange_start": "1970-01-01",
    "sfomuseum:description": "From attached handwritten note: “03588 / 4-5-70 / Shirley Temple Black \u0026 JK Carr dedicating the first 747 scheduled flight from S.F.O., taken by: Moxom”. Black and white photographic negative depicting dedication ceremony for first TWA (Trans World Airlines) 747-100 scheduled flight from San Francisco International Airport (SFO); three people standing in front of airplane with cargo door open; Shirley Temple Black standing on right, Airport Director James K. Carr at center, unidentified man on left; photo taken on April 5, 1970.",
    "sfomuseum:media_ids": [
      1527827345
    ],
    "sfomuseum:medium": "negative",
    "sfomuseum:placetype": "object",
    "sfomuseum:subcategory": "Negative",
    "wof:depicts": [
      102527513,
      1159289873,
      1159293593,
      1159285393,
      1159289885
    ],
    "wof:name": "negative: San Francisco International Airport (SFO), inaugural TWA (Trans World Airlines) Boeing 747 flight",
    "wof:placetype": "venue"
  },
  "geometry": {"coordinates":[-122.386155,37.616357],"type":"Point"}
}
