{
  "type": "Feature",
  "properties": {
    "date:cessation_lower": "1949-12-31",
    "date:cessation_upper": "1949-12-31",
    "date:inception_lower": "1949-01-01",
    "date:inception_upper": "1949-01-01",
    "iso:country": "XX",
    "sfomuseum:accession_number": "2012.149.0794 a b",
    "sfomuseum:category": "Promotional",
    "sfomuseum:collection": "Aviation Archive",
    "sfomuseum:creditline": "Gift of the Captain John B. Russell Family",
    "sfomuseum:date": "1949",
    "sfomuseum:daterange_end": "1949-12-31",
    "sfomuseum:daterange_start": "1949-01-01",
    "sfomuseum:description": "Full spread two-page advertisement from October 1949 issue of Holiday promoting Panagra, titled “Swift new luxury service to South America by Panagra’s new DC-7B’s equipped with radar”; color illustration depicting profile view of green, yellow, and white Panagra aircraft against pictorial map of South America.",
    "sfomuseum:media_ids": [
      1527853425, 
      1527853427
    ],
    "sfomuseum:medium": "paper, ink",
    "sfomuseum:placetype": "object",
    "sfomuseum:subcategory": "Advertisement, 2D",
    "wof:name": "advertisement: Panagra (Pan American-Grace Airways), Holiday",
    "wof:placetype": "venue"
  },
  "geometry": {"coordinates":[-122.386155,37.616358],"type":"Point"}
}
