{
  "type": "Feature",
  "properties": {
    "date:cessation_lower": "1972-01-01",
    "date:cessation_upper": "1972-12-31",
    "date:inception_lower": "1972-01-01",
    "date:inception_upper": "1972-12-31",
    "iso:country": "XX",
    "millsfield:images": [
      1527831997
    ],
    "millsfield:primary_image": 1527831997,
    "sfomuseum:accession_number": "2009.122.040",
    "sfomuseum:airline": "Air Canada",
    "sfomuseum:category": "Scheduling / Ticketing",
    "sfomuseum:collection": "Aviation Archive",
    "sfomuseum:creditline": "Gift of the William Hough Collection",
    "sfomuseum:date": "1972",
    "sfomuseum:date_acquired": "2010-06-08",
    "sfomuseum:daterange_end": "1972-12-31",
    "sfomuseum:daterange_start": "1972-01-01",
    "sfomuseum:description": "Timetable issued by Air Canada, effective October 29, 1972; 27-page fold-out; color photographic image of snowmobile and Banff Springs Hotel, Alberta and text “Air Canada to Canada / Let’s go there together”.",
    "sfomuseum:dimensions": "9 x 4 inches (22.9 x 10.2 cm)",
    "sfomuseum:media_ids": [
      1527831997
    ],
    "sfomuseum:medium": "paper, ink",
    "sfomuseum:placetype": "object",
    "sfomuseum:publication": ": , 1972.",
    "sfomuseum:subcategory": "Timetable",
    "wof:depicts": [
      1159288851,
      1159283597
    ],
    "wof:name": "timetable: Air Canada",
    "wof:placetype": "custom",
    "wof:placetype_alt": "object"
  },
  "geometry": {"coordinates":[-122.386155,37.616357],"type":"Point"}
}
