{
  "type": "Feature",
  "properties": {
    "date:cessation_lower": "1992-01-01",
    "date:cessation_upper": "1992-12-31",
    "date:inception_lower": "1992-01-01",
    "date:inception_upper": "1992-12-31",
    "iso:country": "XX",
    "sfomuseum:accession_number": "99-0795",
    "sfomuseum:author": "Sanderson, Jeppesen",
    "sfomuseum:callnumber": "TL509 .A37 1992 REF",
    "sfomuseum:category": "Book",
    "sfomuseum:collection": "Aviation Library",
    "sfomuseum:creditline": "Purchase",
    "sfomuseum:date": "1992",
    "sfomuseum:daterange_end": "1992-12-31",
    "sfomuseum:daterange_start": "1992-01-01",
    "sfomuseum:description": "502 p.: ill. ; 23 cm.\r",
    "sfomuseum:description_library": "502 p.: ill. ; 23 cm.\r",
    "sfomuseum:medium": "printed, bound paper",
    "sfomuseum:placetype": "object",
    "sfomuseum:publication": "Englewood, CO: Jeppesen Sanderson, 1992.",
    "sfomuseum:publisher": "Jeppesen Sanderson",
    "sfomuseum:publisher_location": "Englewood, CO",
    "sfomuseum:subcategory": "Reference",
    "sfomuseum:subject": "Astronautics -- Dictionaries.\rAeronautics -- Dictionaries.\r",
    "wof:name": "Aircraft technical dictionary",
    "wof:placetype": "custom",
    "wof:placetype_alt": "object"
  },
  "geometry": {"coordinates":[-122.386155,37.616357],"type":"Point"}
}
