{
  "type": "Feature",
  "properties": {
    "date:cessation_lower": "1928-01-01",
    "date:cessation_upper": "1928-12-31",
    "date:inception_lower": "1928-01-01",
    "date:inception_upper": "1928-12-31",
    "iso:country": "US",
    "millsfield:images": [
      1746680793
    ],
    "millsfield:images_texts": [
      "WINsS\nTHE AIR MAIL GAME\nPARKER BROTHERS InC.\nDIRECTIONS FOR PLAYIN'\nWIN\nDIRECTIONS FOR PLAYING\nWINGS\nThe Air Mail Game\nFor Two, Three or Four Players\nPARKER BROTHERS, Inc."
    ],
    "millsfield:images_texts_ids": [
      1746680793
    ],
    "millsfield:primary_image": 1746680793,
    "sfomuseum:accession_number": "1999.062.002 a g",
    "sfomuseum:category": "Toys",
    "sfomuseum:collection": "Aviation Museum",
    "sfomuseum:continent": "North America",
    "sfomuseum:country": "United States",
    "sfomuseum:creditline": "Purchase",
    "sfomuseum:date": "1928",
    "sfomuseum:date_acquired": "2000-01-07",
    "sfomuseum:daterange_end": "1928-12-31",
    "sfomuseum:daterange_start": "1928-01-01",
    "sfomuseum:description": "Card game made by Parker Brothers, “Wings, the Air Mail Game” with multiple parts:\ra. box lid; blue with illustrations of three biplanes;\rb. box bottom;\rc. stapled paper booklet of instructions;\rd. stapled paper booklet of instructions;\re. advertisement card for \"Rook\";\rf.  advertisement page for \"Camelot\";\rg. 72 red cards with illustration of high wing monoplane in flight on front with numbers, city names and city illustrations on reverse; includes 8 blue \"Delay Cards,\" 3 blue \"High Speed\" cards, 10  \"Release Cards,\" 3 \"Transfer Mail\" cards, and 3 \"Descend by Parachute\" cards.",
    "sfomuseum:dimensions": "1 x 5 1/2 x 4 inches (2.5 x 14 x 10.2 cm)",
    "sfomuseum:maker": "Parker Brothers Inc.",
    "sfomuseum:medium": "paper, cardboard, metal, ink",
    "sfomuseum:placetype": "object",
    "sfomuseum:publication": ": , 1928.",
    "sfomuseum:subcategory": "Card Game",
    "wof:name": "game: Wings, the Air Mail Game",
    "wof:placetype": "custom",
    "wof:placetype_alt": "object"
  },
  "geometry": {"coordinates":[-122.386155,37.616357],"type":"Point"}
}
