{
  "type": "Feature",
  "properties": {
    "date:cessation_lower":"1928-12-31",
    "date:cessation_upper":"1928-12-31",
    "date:inception_lower":"1928-01-01",
    "date:inception_upper":"1928-01-01",
    "iso:country":"US",
    "sfomuseum:accession_number":"1999.062.002 a g",
    "sfomuseum:category":"Toys",
    "sfomuseum:collection":"Aviation Museum",
    "sfomuseum:continent":"North America",
    "sfomuseum:country":"United States",
    "sfomuseum:creditline":"Purchase",
    "sfomuseum:date":"1928",
    "sfomuseum:daterange_end":"1928-12-31",
    "sfomuseum:daterange_start":"1928-01-01",
    "sfomuseum:description":"Card game, \u201cWings, the Air Mail Game\u201d with multiple parts:\ra. Box lid: Image of three biplanes.\rb. Box bottom.\rc. Small stapled paper booklet of instructions.\rd. Small stapled paper booklet of instructions.\re. Advertisement card for \"Rook\".\rf.  Advertisement page for \"Camelot\".\rg. 72 red cards with in-flight high wing monoplane on front with numbers, city names and city illustrations on reverse.  8 blue \"Delay Cards,\" 3 blue \"High Speed\" cards, 10  \"Release Cards,\"  3  \"Transfer Mail\" cards, and 3 \"Descend by Parachute\" cards.",
    "sfomuseum:maker":"Parker Brothers Inc.",
    "sfomuseum:medium":"paper, cardboard",
    "sfomuseum:placetype":"object",
    "sfomuseum:subcategory":"Card Game",
    "wof:name":"game: Wings, the Air Mail Game",
    "wof:placetype":"venue"
},
  "geometry": {"coordinates":[-122.386155,37.616358],"type":"Point"}
}