{
  "type": "Feature",
  "properties": {
    "date:cessation_lower": "1940-12-31",
    "date:cessation_upper": "1940-12-31",
    "date:inception_lower": "1940-01-01",
    "date:inception_upper": "1940-01-01",
    "iso:country": "XX",
    "sfomuseum:accession_number": "2008.075.136",
    "sfomuseum:category": "Philately",
    "sfomuseum:collection": "Aviation Archive",
    "sfomuseum:creditline": "Gift of Jon E. Krupnick",
    "sfomuseum:date": "11/25/1940",
    "sfomuseum:daterange_end": "1940-11-25",
    "sfomuseum:daterange_start": "1940-11-25",
    "sfomuseum:description": "Mail ship cover for U.S.S. J.D. Edwards- November 25, 1940; envelope postmarked U.S.S. J.D. Edwards, November 25, 1940, Asia Station; cancellation mark on one blue 3-cent postage stamp in black ink; addressed to Colt's Patent Fire Arms Mfg. Co; identified by donor with additional information: \"Pacific Naval Ship covers\".",
    "sfomuseum:media_ids": [
      1527818267
    ],
    "sfomuseum:medium": "paper, ink",
    "sfomuseum:placetype": "object",
    "sfomuseum:subcategory": "Airmail Flight Cover",
    "wof:name": "mail ship cover: Pacific Naval Ship, U.S.S. J.D. Edwards, November 25, 1940",
    "wof:placetype": "venue"
  },
  "geometry": {"coordinates":[-122.386155,37.616358],"type":"Point"}
}
