{
  "type": "Feature",
  "properties": {
    "date:cessation_lower": "1927-12-31",
    "date:cessation_upper": "1927-12-31",
    "date:inception_lower": "1927-01-01",
    "date:inception_upper": "1927-01-01",
    "iso:country": "XX",
    "millsfield:images": [
      1527856775
    ],
    "sfomuseum:accession_number": "2000.018.021.001",
    "sfomuseum:airport": "Mills Field Municipal Airport of San Francisco",
    "sfomuseum:category": "Company Record / Document",
    "sfomuseum:collection": "Aviation Archive",
    "sfomuseum:creditline": "Transfer from City and County of San Francisco",
    "sfomuseum:date": "1927",
    "sfomuseum:daterange_end": "1927-12-31",
    "sfomuseum:daterange_start": "1927-01-01",
    "sfomuseum:description": "Typed facsimile of correspondence from Luke T. Curran to Frederick Shutts, Supervising Engineer, dated December 8, 1927, concerning removal of grass and hay by Millbrae Dairy Company at Mills Field Municipal Airport; copy of File 531.9, not signed.",
    "sfomuseum:media_ids": [
      1527856775
    ],
    "sfomuseum:medium": "paper, ink",
    "sfomuseum:placetype": "object",
    "sfomuseum:subcategory": "Correspondence, Company",
    "wof:depicts": [
      1360695653
    ],
    "wof:name": "correspondence: City and County of San Francisco, Millbrae Dairy Company",
    "wof:placetype": "custom"
  },
  "geometry": {"coordinates":[-122.386155,37.616357],"type":"Point"}
}
