{
  "type": "Feature",
  "properties": {
    "date:cessation_lower": "1935-12-31",
    "date:cessation_upper": "1935-12-31",
    "date:inception_lower": "1935-01-01",
    "date:inception_upper": "1935-01-01",
    "iso:country": "XX",
    "millsfield:images": [
      1527833773,
      1527833769
    ],
    "sfomuseum:accession_number": "2012.149.1623",
    "sfomuseum:aircraft": "Martin M-130",
    "sfomuseum:airline": "Pan American Airways  (Pan American World Airways)",
    "sfomuseum:category": "Philately",
    "sfomuseum:collection": "Aviation Archive",
    "sfomuseum:creditline": "Gift of the Captain John B. Russell Family",
    "sfomuseum:date": "11/22/1935",
    "sfomuseum:daterange_end": "1935-11-22",
    "sfomuseum:daterange_start": "1935-11-22",
    "sfomuseum:description": "Airmail flight cover commemorating first Pan American Airways transpacific airmail flight between San Francisco (Alameda) and Manila, FAM-14; green cachet with image of Martin M-130 and sailing ship; postmarked November 22, 1935, San Francisco with four-bar cancellation over three blue 25-cent stamps; backstamp: November 29, 1935, Manila.",
    "sfomuseum:media_ids": [
      1527833769,
      1527833773
    ],
    "sfomuseum:medium": "paper, ink",
    "sfomuseum:placetype": "object",
    "sfomuseum:subcategory": "Airmail Flight Cover",
    "wof:depicts": [
      1159291191,
      1159284991
    ],
    "wof:name": "airmail flight cover: Pan American Airways, FAM-14, first transpacific airmail flight, San Francisco - Manila route",
    "wof:placetype": "venue"
  },
  "geometry": {"coordinates":[-122.386155,37.616357],"type":"Point"}
}
