{
  "type": "Feature",
  "properties": {
    "date:cessation_lower": "2000-01-01",
    "date:cessation_upper": "2000-12-31",
    "date:inception_lower": "2000-01-01",
    "date:inception_upper": "2000-12-31",
    "iso:country": "XX",
    "sfomuseum:accession_number": "2008.055.018",
    "sfomuseum:author": "Singfield, Tom",
    "sfomuseum:callnumber": "TL685.7 .S53 2000 c.2",
    "sfomuseum:category": "Book",
    "sfomuseum:collection": "Aviation Library",
    "sfomuseum:creditline": "Gift of the William Hough Collection",
    "sfomuseum:date": "2000",
    "sfomuseum:date_acquired": "2008-04-13",
    "sfomuseum:daterange_end": "2000-12-31",
    "sfomuseum:daterange_start": "2000-01-01",
    "sfomuseum:description": "160 p. : col. ill. ; 24 cm.",
    "sfomuseum:description_library": "160 p. : col. ill. ; 24 cm.",
    "sfomuseum:distributor_location": "North Branch, MN",
    "sfomuseum:medium": "paper, ink",
    "sfomuseum:placetype": "object",
    "sfomuseum:publication": "Leicester, England: Midland Pub., 2000.",
    "sfomuseum:publisher": "Midland Pub.",
    "sfomuseum:publisher_location": "Leicester, England",
    "sfomuseum:subcategory": "Book",
    "sfomuseum:subject": "Transport planes Pictorial works.",
    "wof:name": "Classic airliners: 76 older types, worldwide, described and illustrated in colour",
    "wof:placetype": "custom",
    "wof:placetype_alt": "object"
  },
  "geometry": {"coordinates":[-122.386155,37.616357],"type":"Point"}
}
