{
  "type": "Feature",
  "properties": {
    "date:cessation_lower": "1995-01-01",
    "date:cessation_upper": "1995-12-31",
    "date:inception_lower": "1995-01-01",
    "date:inception_upper": "1995-12-31",
    "iso:country": "XX",
    "sfomuseum:accession_number": "99-0197",
    "sfomuseum:author": "Ryan, Craig",
    "sfomuseum:callnumber": "TL618 .R95 1995",
    "sfomuseum:category": "Book",
    "sfomuseum:collection": "Aviation Library",
    "sfomuseum:date": "c. 1995",
    "sfomuseum:daterange_end": "2000-12-31",
    "sfomuseum:daterange_start": "1990-01-01",
    "sfomuseum:description": "xiv, 327 p. : ill. ; 24 cm.",
    "sfomuseum:description_library": "xiv, 327 p. : ill. ; 24 cm.",
    "sfomuseum:medium": "paper, ink",
    "sfomuseum:placetype": "object",
    "sfomuseum:publication": "Annapolis, MD: Naval Institute Press, c. 1995.",
    "sfomuseum:publisher": "Naval Institute Press",
    "sfomuseum:publisher_location": "Annapolis, MD",
    "sfomuseum:subcategory": "Book",
    "sfomuseum:subject": "Atmosphere, Upper Research United States History.Balloon ascensions United States History.Outer space Exploration United States History.",
    "wof:name": "The pre-astronauts: manned ballooning on the threshold of space",
    "wof:placetype": "custom",
    "wof:placetype_alt": "object"
  },
  "geometry": {"coordinates":[-122.386155,37.616357],"type":"Point"}
}
