{
  "type": "Feature",
  "properties": {
    "date:cessation_lower": "1936-01-01",
    "date:cessation_upper": "1936-12-31",
    "date:inception_lower": "1936-01-01",
    "date:inception_upper": "1936-12-31",
    "iso:country": "XX",
    "loc:subject_headings": [
      "sh85001319"
    ],
    "sfomuseum:accession_number": "2000.160.1175",
    "sfomuseum:callnumber": "TL547 .B644 1933 SC",
    "sfomuseum:category": "Book",
    "sfomuseum:collection": "Aviation Library",
    "sfomuseum:creditline": "The Tony Bill Aviation Library Collection",
    "sfomuseum:date": "1936",
    "sfomuseum:date_acquired": "1999-05-18",
    "sfomuseum:daterange_end": "1936-12-31",
    "sfomuseum:daterange_start": "1936-01-01",
    "sfomuseum:description": "111 p. col. front., illus., col. plates. 29 cm.",
    "sfomuseum:description_library": "111 p. col. front., illus., col. plates. 29 cm.",
    "sfomuseum:edition": "1st",
    "sfomuseum:medium": "paper, ink",
    "sfomuseum:placetype": "object",
    "sfomuseum:publication": "London: F. Warne \u0026 Company, 1936.",
    "sfomuseum:publisher": "F. Warne \u0026 Company",
    "sfomuseum:publisher_location": "London",
    "sfomuseum:subcategory": "Book",
    "sfomuseum:subject": "Aeronautics.",
    "wof:name": "The book about aircraft: with nineteen colour plates and one hundred and thirty-four text illustrations 1st",
    "wof:placetype": "venue"
  },
  "geometry": {"coordinates":[-122.386155,37.616357],"type":"Point"}
}
