{
  "type": "Feature",
  "properties": {
    "date:cessation_lower": "1939-12-31",
    "date:cessation_upper": "1939-12-31",
    "date:inception_lower": "1937-01-01",
    "date:inception_upper": "1937-01-01",
    "iso:country": "US",
    "sfomuseum:accession_number": "1995.29.39",
    "sfomuseum:category": "Toys",
    "sfomuseum:collection": "Aviation Museum",
    "sfomuseum:continent": "North America",
    "sfomuseum:country": "United States",
    "sfomuseum:creditline": "Purchase",
    "sfomuseum:date": "late 1930s",
    "sfomuseum:daterange_end": "1939-12-31",
    "sfomuseum:daterange_start": "1937-01-01",
    "sfomuseum:description": "Orange two-engine airplane with green wings and black chassis.",
    "sfomuseum:dimensions": "3 x 13 x 9 1/2 inches (7.6 x 33 x 24.1 cm)",
    "sfomuseum:maker": "Wyandotte Toys",
    "sfomuseum:medium": "polychrome steel, wood",
    "sfomuseum:placetype": "object",
    "sfomuseum:subcategory": "Toy Airplane",
    "sfomuseum:subject": "ALM_P/U_10092018",
    "wof:name": "toy airplane: twin engine aircraft",
    "wof:placetype": "venue"
  },
  "geometry": {"coordinates":[-122.386155,37.616357],"type":"Point"}
}
