{
  "type": "Feature",
  "properties": {
    "date:cessation_lower": "1965-12-31",
    "date:cessation_upper": "1965-12-31",
    "date:inception_lower": "1965-01-01",
    "date:inception_upper": "1965-01-01",
    "iso:country": "XX",
    "sfomuseum:accession_number": "2008.056.1124",
    "sfomuseum:category": "Photograph",
    "sfomuseum:collection": "Aviation Archive",
    "sfomuseum:creditline": "Gift of Jon E. Krupnick",
    "sfomuseum:date": "1965",
    "sfomuseum:daterange_end": "1965-12-31",
    "sfomuseum:daterange_start": "1965-01-01",
    "sfomuseum:description": "Black and white photograph of female flight attendant posing for viewer. Printed caption on bottom \"Pan Am Stewardess Uniform - 1965-1969.\"",
    "sfomuseum:media_ids": [
      1527852239
    ],
    "sfomuseum:medium": "photograph",
    "sfomuseum:placetype": "object",
    "sfomuseum:subcategory": "Print, Photograph",
    "wof:name": "photograph: Pan American World Airways, flight attendant in uniform",
    "wof:placetype": "venue"
  },
  "geometry": {"coordinates":[-122.386155,37.616358],"type":"Point"}
}
