{
  "type": "Feature",
  "properties": {
    "date:cessation_lower": "1930-01-01",
    "date:cessation_upper": "1930-12-31",
    "date:inception_lower": "1930-01-01",
    "date:inception_upper": "1930-12-31",
    "iso:country": "XX",
    "loc:subject_heading": {
      "sh85001319": "Aeronautics"
    },
    "sfomuseum:accession_number": "2000.171.087",
    "sfomuseum:author": "Dunn, Captain Ray A.",
    "sfomuseum:callnumber": "HG8811.A9 D86 1930 SC",
    "sfomuseum:category": "Book",
    "sfomuseum:collection": "Aviation Library",
    "sfomuseum:creditline": "Purchase",
    "sfomuseum:date": "c. 1930",
    "sfomuseum:daterange_end": "1935-12-31",
    "sfomuseum:daterange_start": "1925-01-01",
    "sfomuseum:description": "112 p. diagr. 24cm.",
    "sfomuseum:medium": "paper, ink",
    "sfomuseum:placetype": "object",
    "sfomuseum:publication": "New York: The Daniel Guggenheim fund for the promotion of aeronautics, Inc., c. 1930.",
    "sfomuseum:publisher": "The Daniel Guggenheim fund for the promotion of aeronautics, Inc.",
    "sfomuseum:publisher_location": "New York",
    "sfomuseum:subcategory": "Book",
    "sfomuseum:subject": "Aeronautics.Insurance, Life.",
    "wof:name": "Aviation and life insurance: a study of the death rate and the hazard of flying in relation to policy underwriting",
    "wof:placetype": "venue"
  },
  "geometry": {"coordinates":[-122.386155,37.616357],"type":"Point"}
}
