{
  "type": "Feature",
  "properties": {
    "date:cessation_lower": "1909-01-01",
    "date:cessation_upper": "1909-12-31",
    "date:inception_lower": "1909-01-01",
    "date:inception_upper": "1909-12-31",
    "iso:country": "XX",
    "sfomuseum:accession_number": "2000.172.056",
    "sfomuseum:author": "Moedebeck, Hermann Wilhelm Ludwig",
    "sfomuseum:callnumber": "TL670.3 .M6 1909 SC",
    "sfomuseum:category": "Book",
    "sfomuseum:collection": "Aviation Library",
    "sfomuseum:creditline": "Purchase",
    "sfomuseum:date": "1909",
    "sfomuseum:date_acquired": "1999-12-08",
    "sfomuseum:daterange_end": "1909-12-31",
    "sfomuseum:daterange_start": "1909-01-01",
    "sfomuseum:description": "2 p. l., 98 p. illus., viii pl. 25 cm.",
    "sfomuseum:description_library": "2 p. l., 98 p. illus., viii pl. 25 cm.",
    "sfomuseum:medium": "paper, ink",
    "sfomuseum:placetype": "object",
    "sfomuseum:publication": "Berlin: O. Salle, 1909.",
    "sfomuseum:publisher": "O. Salle",
    "sfomuseum:publisher_location": "Berlin",
    "sfomuseum:subcategory": "Book",
    "sfomuseum:subject": "Airplanes.Aeronautics History.",
    "wof:name": "Fliegende Menschen! Das Ringen um die Beherrschung der Luft mittels Flugmaschinen, leicht fasslich dargestellt von Hermann W. L. Moedebeck ... ; Mit 67 Abbildungen im Test und 13 Abbildungen auf 8 Tafeln",
    "wof:placetype": "venue"
  },
  "geometry": {"coordinates":[-122.386155,37.616357],"type":"Point"}
}
