{
  "type": "Feature",
  "properties": {
    "date:cessation_lower": "1981-01-01",
    "date:cessation_upper": "1981-12-31",
    "date:inception_lower": "1981-01-01",
    "date:inception_upper": "1981-12-31",
    "iso:country": "XX",
    "millsfield:images": [
      1527840127
    ],
    "millsfield:primary_image": 1527840127,
    "sfomuseum:accession_number": "2009.122.365",
    "sfomuseum:airline": "Japan Air Lines",
    "sfomuseum:category": "Scheduling / Ticketing",
    "sfomuseum:collection": "Aviation Archive",
    "sfomuseum:creditline": "Gift of the William Hough Collection",
    "sfomuseum:date": "1981",
    "sfomuseum:date_acquired": "2010-06-08",
    "sfomuseum:daterange_end": "1981-12-31",
    "sfomuseum:daterange_start": "1981-01-01",
    "sfomuseum:description": "International timetable issued by Japan Air Lines, effective November 1 through December 31, 1981; 191-page schedule; dark blue cover with red cranes in flight; in Japanese, French, Spanish and English.",
    "sfomuseum:dimensions": "8 x 4 inches (20.3 x 10.2 cm)",
    "sfomuseum:media_ids": [
      1527840127
    ],
    "sfomuseum:medium": "paper, ink",
    "sfomuseum:placetype": "object",
    "sfomuseum:publication": ": , 1981.",
    "sfomuseum:subcategory": "Timetable",
    "wof:depicts": [
      1159285785,
      1159288505
    ],
    "wof:name": "timetable: Japan Air Lines (Japan Airlines), international service",
    "wof:placetype": "custom",
    "wof:placetype_alt": "object"
  },
  "geometry": {"coordinates":[-122.386155,37.616357],"type":"Point"}
}
