{
  "type": "Feature",
  "properties": {
    "date:cessation_lower": "1980-01-01",
    "date:cessation_upper": "1980-12-31",
    "date:inception_lower": "1980-01-01",
    "date:inception_upper": "1980-12-31",
    "iso:country": "XX",
    "loc:subject_headings": [
      "sh85002650"
    ],
    "sfomuseum:accession_number": "99-0637",
    "sfomuseum:callnumber": "HE9776 .A37 1980z v.2",
    "sfomuseum:category": "Book",
    "sfomuseum:collection": "Aviation Library",
    "sfomuseum:date": "1980",
    "sfomuseum:daterange_end": "1980-12-31",
    "sfomuseum:daterange_start": "1980-01-01",
    "sfomuseum:description": "5 v. : ill. ; 29 cm.",
    "sfomuseum:medium": "paper, ink",
    "sfomuseum:placetype": "object",
    "sfomuseum:publication": "United States: H.E. Ahrens, 1980.",
    "sfomuseum:publisher": "H.E. Ahrens",
    "sfomuseum:publisher_location": "United States",
    "sfomuseum:subcategory": "Book",
    "sfomuseum:subject": "Airlines.",
    "wof:name": "Airlines of the world compendium: volume 2. C-I",
    "wof:placetype": "venue"
  },
  "geometry": {"coordinates":[-122.386155,37.616357],"type":"Point"}
}
