{
  "type": "Feature",
  "properties": {
    "date:cessation_lower": "1968-01-01",
    "date:cessation_upper": "1968-12-31",
    "date:inception_lower": "1968-01-01",
    "date:inception_upper": "1968-12-31",
    "iso:country": "XX",
    "millsfield:images": [
      1527844429
    ],
    "millsfield:primary_image": 1527844429,
    "sfomuseum:accession_number": "2005.132.067.002",
    "sfomuseum:airline": "BWIA West Indies Airways",
    "sfomuseum:category": "Scheduling / Ticketing",
    "sfomuseum:collection": "Aviation Archive",
    "sfomuseum:creditline": "Gift of the William Hough Collection",
    "sfomuseum:date": "1968",
    "sfomuseum:daterange_end": "1968-12-31",
    "sfomuseum:daterange_start": "1968-01-01",
    "sfomuseum:description": "Timetable for BWIA for Caribbean service, effective June 15, 1968; 11-page fold-out. The cover is white and orange with map of Caribbean islands inside a large version of servicemark.",
    "sfomuseum:dimensions": "9 x 4 inches (22.9 x 10.2 cm)",
    "sfomuseum:media_ids": [
      1527844429
    ],
    "sfomuseum:medium": "paper, ink",
    "sfomuseum:placetype": "object",
    "sfomuseum:publication": ": , 1968.",
    "sfomuseum:subcategory": "Timetable",
    "wof:depicts": [
      1159284057
    ],
    "wof:name": "timetable: BWIA",
    "wof:placetype": "venue"
  },
  "geometry": {"coordinates":[-122.386155,37.616357],"type":"Point"}
}
