{
  "type": "Feature",
  "properties": {
    "date:cessation_lower": "1950-01-01",
    "date:cessation_upper": "1950-12-31",
    "date:inception_lower": "1950-01-01",
    "date:inception_upper": "1950-12-31",
    "iso:country": "XX",
    "millsfield:images": [
      1746681379
    ],
    "millsfield:primary_image": 1746681379,
    "sfomuseum:accession_number": "2002.035.848",
    "sfomuseum:airline": "British Commonwealth Pacific Airlines (BCPA)",
    "sfomuseum:category": "Beverage Service",
    "sfomuseum:collection": "Aviation Museum",
    "sfomuseum:creditline": "Gift of Thomas G. Dragges",
    "sfomuseum:date": "c. 1950",
    "sfomuseum:date_acquired": "2003-10-23",
    "sfomuseum:daterange_end": "1955-12-31",
    "sfomuseum:daterange_start": "1945-01-01",
    "sfomuseum:description": "Coaster issued by BCPA for inflight beverage service; wood circular shape with gold colored logo in center; “Australian Mulga” along top edge; logotype along bottom edge.",
    "sfomuseum:dimensions": "3 1/4 x 3 1/4 inches (8.3 x 8.3 cm)",
    "sfomuseum:medium": "Australian mulga wood",
    "sfomuseum:on_view": 1,
    "sfomuseum:placetype": "object",
    "sfomuseum:publication": ": , c. 1950.",
    "sfomuseum:subcategory": "Coaster",
    "wof:depicts": [
      1159284025
    ],
    "wof:name": "coaster: British Commonwealth Pacific Airlines (BCPA)",
    "wof:placetype": "venue"
  },
  "geometry": {"coordinates":[-122.386155,37.616357],"type":"Point"}
}
