{
  "type": "Feature",
  "properties": {
    "date:cessation_lower": "1911-01-01",
    "date:cessation_upper": "1911-12-31",
    "date:inception_lower": "1911-01-01",
    "date:inception_upper": "1911-12-31",
    "iso:country": "XX",
    "sfomuseum:accession_number": "2000.160.0999",
    "sfomuseum:author": "Smithsonian Institution. Board of Regents",
    "sfomuseum:callnumber": "Q11 .S66 1911 REF",
    "sfomuseum:category": "Book",
    "sfomuseum:collection": "Aviation Library",
    "sfomuseum:creditline": "The Tony Bill Aviation Library Collection",
    "sfomuseum:date": "1911",
    "sfomuseum:date_acquired": "1999-05-18",
    "sfomuseum:daterange_end": "1911-12-31",
    "sfomuseum:daterange_start": "1911-01-01",
    "sfomuseum:description": "688 p. : ill. maps ; 23-24 cm.",
    "sfomuseum:description_library": "688 p. : ill. maps ; 23-24 cm.",
    "sfomuseum:medium": "paper, ink",
    "sfomuseum:placetype": "object",
    "sfomuseum:publication": "Washington, D.C.: Institution, 1911.",
    "sfomuseum:publisher": "Institution",
    "sfomuseum:publisher_location": "Washington, D.C.",
    "sfomuseum:series": "1917/18-1963/64: Publication / Smithsonian Institution",
    "sfomuseum:subcategory": "Reference",
    "sfomuseum:subject": "Smithsonian Institution Periodicals.",
    "wof:name": "Annual report of the Board of Regents of the Smithsonian Institution: showing the operations, expenditures, and condition of the Institution for the year ending June 30, 1911",
    "wof:placetype": "custom",
    "wof:placetype_alt": "object"
  },
  "geometry": {"coordinates":[-122.386155,37.616357],"type":"Point"}
}
