{
  "type": "Feature",
  "properties": {
    "date:cessation_lower": "2006-12-31",
    "date:cessation_upper": "2006-12-31",
    "date:inception_lower": "2006-01-01",
    "date:inception_upper": "2006-01-01",
    "iso:country": "CN",
    "millsfield:images": [
      1527858213
    ],
    "sfomuseum:accession_number": "2007.041.007",
    "sfomuseum:airline": "Cathay Pacific Airways",
    "sfomuseum:category": "Promotional",
    "sfomuseum:collection": "Aviation Museum",
    "sfomuseum:continent": "Asia",
    "sfomuseum:country": "China",
    "sfomuseum:creditline": "Gift of Cathay Pacific Airways",
    "sfomuseum:date": "2006",
    "sfomuseum:daterange_end": "2006-12-31",
    "sfomuseum:daterange_start": "2006-01-01",
    "sfomuseum:description": "Reissued retro rectangular blue bag with white piping; white caption on one side in Chinese and English, \"Cathay Pacific Airways Limited / Serving the Orient and the South Seas\" with CPA logo at top; two handles and zipper closure at top; four metallic rivets on bottom; single interior zipper pocket.\r\rAirline bag manufactured by COMPANY for AIRLINES; COLOR background with COLOR printed [servicemark/logotype] on AREA (front/top/bottom/sides); printed “TYPE” on reverse; [long/short/adjustable/shoulder strap/handles]; [other details: feet/pockets, side panels].",
    "sfomuseum:dimensions": "14 1/2 x 18 x 7 1/2 inches (36.8 x 45.7 x 19.1 cm)",
    "sfomuseum:media_ids": [
      1527858213
    ],
    "sfomuseum:medium": "fabric, synthetic textile, metal, plastic, ink",
    "sfomuseum:placetype": "object",
    "sfomuseum:subcategory": "Airline Bag",
    "wof:depicts": [
      1159284127
    ],
    "wof:name": "airline bag: Cathay Pacific Airways",
    "wof:placetype": "venue"
  },
  "geometry": {"coordinates":[-122.386155,37.616357],"type":"Point"}
}
