{
  "type": "Feature",
  "properties": {
    "date:cessation_lower": "2006-01-01",
    "date:cessation_upper": "2006-12-31",
    "date:inception_lower": "2006-01-01",
    "date:inception_upper": "2006-12-31",
    "iso:country": "CN",
    "millsfield:images": [
      1527858213
    ],
    "millsfield:primary_image": 1527858213,
    "sfomuseum:accession_number": "2007.041.007",
    "sfomuseum:airline": "Cathay Pacific Airways",
    "sfomuseum:category": "Promotional, Museum",
    "sfomuseum:collection": "Aviation Museum",
    "sfomuseum:continent": "Asia",
    "sfomuseum:country": "China",
    "sfomuseum:creditline": "Gift of Cathay Pacific Airways",
    "sfomuseum:date": "2006",
    "sfomuseum:date_acquired": "2007-12-10",
    "sfomuseum:daterange_end": "2006-12-31",
    "sfomuseum:daterange_start": "2006-01-01",
    "sfomuseum:description": "Airline bag issued by Cathay Pacific Airways; reissued and based on 1950s design; blue background with white piping, white logotype with text, “Serving the Orient and the South Seas” and servicemark; handles with top zipper closure, four silver metal feet on bottom and single interior zipper pocket.",
    "sfomuseum:dimensions": "14 1/2 x 18 x 7 1/2 inches (36.8 x 45.7 x 19.1 cm)",
    "sfomuseum:media_ids": [
      1527858213
    ],
    "sfomuseum:medium": "fabric, synthetic textile, metal, plastic, paint",
    "sfomuseum:placetype": "object",
    "sfomuseum:publication": ": , 2006.",
    "sfomuseum:subcategory": "Airline Bag",
    "wof:depicts": [
      1159284127,
      1159286837
    ],
    "wof:name": "airline bag: Cathay Pacific Airways",
    "wof:placetype": "custom",
    "wof:placetype_alt": "object"
  },
  "geometry": {"coordinates":[-122.386155,37.616357],"type":"Point"}
}
