{
  "type": "Feature",
  "properties": {
    "date:cessation_lower": "1950-01-01",
    "date:cessation_upper": "1950-12-31",
    "date:inception_lower": "1950-01-01",
    "date:inception_upper": "1950-12-31",
    "iso:country": "XX",
    "millsfield:images": [
      1746681369
    ],
    "millsfield:primary_image": 1746681369,
    "sfomuseum:accession_number": "2008.007.002",
    "sfomuseum:airline": "British Commonwealth Pacific Airlines (BCPA)",
    "sfomuseum:category": "Décor",
    "sfomuseum:collection": "Aviation Museum",
    "sfomuseum:creditline": "Gift of Walton F. Kemmerle",
    "sfomuseum:date": "c. 1950",
    "sfomuseum:date_acquired": "2007-12-10",
    "sfomuseum:daterange_end": "1955-12-31",
    "sfomuseum:daterange_start": "1945-01-01",
    "sfomuseum:description": "Ashtray issued by British Commonwealth Pacific Airlines (BCPA); circular metal bowl encased within Mulga wood disk with gold adhesive labels on Mulga wood disk: \"With the Compliments of British Commonwealth Pacific Airlines. Genuine Australian Mulga product.\"",
    "sfomuseum:dimensions": "1 1/2 x 5 inches (3.8 x 12.7 cm)",
    "sfomuseum:medium": "metal, wood, paper, ink",
    "sfomuseum:on_view": 1,
    "sfomuseum:placetype": "object",
    "sfomuseum:publication": ": , c. 1950.",
    "sfomuseum:subcategory": "Ashtray",
    "wof:depicts": [
      1159284025
    ],
    "wof:name": "ashtray: British Commonwealth Pacific Airlines (BCPA)",
    "wof:placetype": "venue"
  },
  "geometry": {"coordinates":[-122.386155,37.616357],"type":"Point"}
}
