{
  "type": "Feature",
  "properties": {
    "date:cessation_lower":"1955-12-31",
    "date:cessation_upper":"1955-12-31",
    "date:inception_lower":"1945-01-01",
    "date:inception_upper":"1945-01-01",
    "iso:country":"XX",
    "sfomuseum:accession_number":"2008.007.002",
    "sfomuseum:airline":"British Commonwealth Pacific Airlines (BCPA)",
    "sfomuseum:category":"D\u00e9cor",
    "sfomuseum:collection":"Aviation Museum",
    "sfomuseum:creditline":"Gift of Walton F. Kemmerle",
    "sfomuseum:date":"c. 1950",
    "sfomuseum:daterange_end":"1955-12-31",
    "sfomuseum:daterange_start":"1945-01-01",
    "sfomuseum:description":"Small metal ashtray dish encased within Mulga wood disk. On gold adhesive label affixed to Mulga wood disk: \"With the Compliments of/British Commonwealth Pacific Airlines.\"  On small gold adhesive label shaped like Australia, affixed to rim: \"Genuine Australian Mulga product.\"",
    "sfomuseum:medium":"metal, wood, paper, ink",
    "sfomuseum:placetype":"object",
    "sfomuseum:subcategory":"Ashtray",
    "wof:depicts":[
        1159284025
    ],
    "wof:name":"ashtray: British Commonwealth Pacific Airlines (BCPA)",
    "wof:placetype":"venue"
},
  "geometry": {"coordinates":[-122.386155,37.616357],"type":"Point"}
}