{
  "type": "Feature",
  "properties": {
    "date:cessation_lower": "1963-12-31",
    "date:cessation_upper": "1963-12-31",
    "date:inception_lower": "1963-01-01",
    "date:inception_upper": "1963-01-01",
    "iso:country": "XX",
    "millsfield:images": [
      1527823981
    ],
    "sfomuseum:accession_number": "2011.032.0921",
    "sfomuseum:airport": "San Francisco International Airport",
    "sfomuseum:category": "Photograph",
    "sfomuseum:collection": "Aviation Archive",
    "sfomuseum:creditline": "Transfer",
    "sfomuseum:date": "1963",
    "sfomuseum:daterange_end": "1963-12-31",
    "sfomuseum:daterange_start": "1963-01-01",
    "sfomuseum:description": "From attached handwritten note: “03520 / 7-26-63 / View S.W. of boundary corner parcel K”. Black and white photographic negative depicting the view southwest of boundary corner of parcel K at San Francisco International Airport (SFO), taken on July 26, 1963.",
    "sfomuseum:media_ids": [
      1527823981
    ],
    "sfomuseum:medium": "negative",
    "sfomuseum:placetype": "object",
    "sfomuseum:subcategory": "Negative",
    "wof:depicts": [
      102527513
    ],
    "wof:name": "negative: San Francisco International Airport (SFO), photographic land survey",
    "wof:placetype": "venue"
  },
  "geometry": {"coordinates":[-122.386155,37.616357],"type":"Point"}
}
