{
  "type": "Feature",
  "properties": {
    "date:cessation_lower":"1965-12-31",
    "date:cessation_upper":"1965-12-31",
    "date:inception_lower":"1965-01-01",
    "date:inception_upper":"1965-01-01",
    "iso:country":"XX",
    "millsfield:images":[
        1527853321
    ],
    "sfomuseum:accession_number":"2012.096.068",
    "sfomuseum:aircraft":"Boeing 727-100",
    "sfomuseum:airline":"Eastern Air Lines",
    "sfomuseum:airport":"Philadelphia International Airport",
    "sfomuseum:category":"Photograph",
    "sfomuseum:collection":"Aviation Archive",
    "sfomuseum:creditline":"Gift of the William Hough Collection",
    "sfomuseum:date":"1965",
    "sfomuseum:daterange_end":"1965-12-31",
    "sfomuseum:daterange_start":"1965-01-01",
    "sfomuseum:description":"Color photograph depicting three-quarter elevated view of Eastern Air Lines Boeing 727-100 Whisperjet at Philadelphia Airport, November 1965; night scene facing aircraft from raised angle; white fuselage with cheatline stripes and \u201cEastern\u201d name and logo across side.",
    "sfomuseum:media_ids":[
        1527853321
    ],
    "sfomuseum:medium":"photograph",
    "sfomuseum:placetype":"object",
    "sfomuseum:subcategory":"Print, Photograph",
    "wof:depicts":[
        1159289759,
        1159293593,
        1159289777,
        1159284309,
        102529403
    ],
    "wof:name":"photograph: Eastern Air Lines, Boeing 727-100",
    "wof:placetype":"venue"
},
  "geometry": {"coordinates":[-122.386155,37.616357],"type":"Point"}
}