{
  "type": "Feature",
  "properties": {
    "date:cessation_lower": "1974-12-31",
    "date:cessation_upper": "1974-12-31",
    "date:inception_lower": "1974-01-01",
    "date:inception_upper": "1974-01-01",
    "iso:country": "XX",
    "sfomuseum:accession_number": "2002.127.565",
    "sfomuseum:aircraft": "Lockheed L-1011 TriStar",
    "sfomuseum:airline": "TWA (Trans World Airlines)",
    "sfomuseum:category": "Passenger Amenity",
    "sfomuseum:collection": "Aviation Archive",
    "sfomuseum:creditline": "Gift of Thomas G. Dragges",
    "sfomuseum:date": "1974",
    "sfomuseum:daterange_end": "1974-12-31",
    "sfomuseum:daterange_start": "1974-01-01",
    "sfomuseum:description": "\rSafety information card issued by TWA for the Lockheed L-1011; pale yellow background, double-sided.",
    "sfomuseum:medium": "plastic",
    "sfomuseum:placetype": "object",
    "sfomuseum:subcategory": "Safety Information Card",
    "wof:depicts": [
      1159285393,
      1159291129
    ],
    "wof:name": "safety information card: TWA (Trans World Airlines), Lockheed L-1011 TriStar",
    "wof:placetype": "venue"
  },
  "geometry": {"coordinates":[-122.386155,37.616357],"type":"Point"}
}
