{
  "type": "Feature",
  "properties": {
    "date:cessation_lower": "1974-01-01",
    "date:cessation_upper": "1974-12-31",
    "date:inception_lower": "1974-01-01",
    "date:inception_upper": "1974-12-31",
    "iso:country": "XX",
    "millsfield:images": [
      1729566035,
      1729566037
    ],
    "sfomuseum:accession_number": "2002.127.565",
    "sfomuseum:aircraft": "Lockheed L-1011 TriStar",
    "sfomuseum:airline": "TWA (Trans World Airlines)",
    "sfomuseum:category": "Passenger Amenity",
    "sfomuseum:collection": "Aviation Archive",
    "sfomuseum:creditline": "Gift of Thomas G. Dragges",
    "sfomuseum:date": "1974",
    "sfomuseum:daterange_end": "1974-12-31",
    "sfomuseum:daterange_start": "1974-01-01",
    "sfomuseum:description": "Safety information card issued by TWA for  Lockheed L-1011 TriStar; double-sided with diagrams of emergency procedures and text.",
    "sfomuseum:dimensions": "10 1/2 x 6 1/4 inches (26.7 x 15.9 cm)",
    "sfomuseum:medium": "plastic",
    "sfomuseum:placetype": "object",
    "sfomuseum:subcategory": "Safety Information Card",
    "wof:depicts": [
      1159291129,
      1159285393
    ],
    "wof:name": "safety information card: TWA (Trans World Airlines), Lockheed L-1011 TriStar",
    "wof:placetype": "venue"
  },
  "geometry": {"coordinates":[-122.386155,37.616357],"type":"Point"}
}
