{
  "type": "Feature",
  "properties": {
    "date:cessation_lower": "1963-01-01",
    "date:cessation_upper": "1963-12-31",
    "date:inception_lower": "1963-01-01",
    "date:inception_upper": "1963-12-31",
    "iso:country": "XX",
    "sfomuseum:accession_number": "00-1532",
    "sfomuseum:author": "Ellis, Frank H",
    "sfomuseum:callnumber": "TL531 .E45 1963",
    "sfomuseum:category": "Book",
    "sfomuseum:collection": "Aviation Library",
    "sfomuseum:date": "1963",
    "sfomuseum:daterange_end": "1963-12-31",
    "sfomuseum:daterange_start": "1963-01-01",
    "sfomuseum:description": "223 p. : ill. ; 25 cm.",
    "sfomuseum:description_library": "223 p. : ill. ; 25 cm.",
    "sfomuseum:medium": "paper, ink",
    "sfomuseum:placetype": "object",
    "sfomuseum:publication": "London: W. Kimber, 1963.",
    "sfomuseum:publisher": "W. Kimber",
    "sfomuseum:publisher_location": "London",
    "sfomuseum:subcategory": "Book",
    "sfomuseum:subject": "Aeronautics Flights.Atlantic Ocean.",
    "wof:name": "Atlantic air conquest: the complete story of all North Atlantic flights and attempts during the pioneer years from 1910 to 1940",
    "wof:placetype": "custom",
    "wof:placetype_alt": "object"
  },
  "geometry": {"coordinates":[-122.386155,37.616357],"type":"Point"}
}
