{
  "type": "Feature",
  "properties": {
    "date:cessation_lower": "1985-01-01",
    "date:cessation_upper": "1985-12-31",
    "date:inception_lower": "1985-01-01",
    "date:inception_upper": "1985-12-31",
    "iso:country": "US",
    "millsfield:images": [
      1527843143
    ],
    "millsfield:images_texts": [
      "2002.005.012\nUSAIR\nCity Timetable\nEffective May 1, 1985\nLexington\nLouisville\nLouisville to\nLos Angeles and\nnew connections\nto San Francisco\n© 1985 USAIR, INC\nIncludes Allegheny Commuter Service"
    ],
    "millsfield:images_texts_ids": [
      1527843143
    ],
    "millsfield:primary_image": 1527843143,
    "sfomuseum:accession_number": "2002.005.012",
    "sfomuseum:airline": "USAir",
    "sfomuseum:category": "Scheduling / Ticketing",
    "sfomuseum:collection": "Aviation Archive",
    "sfomuseum:continent": "North America",
    "sfomuseum:country": "United States",
    "sfomuseum:creditline": "Gift of John R. Barker",
    "sfomuseum:date": "1985",
    "sfomuseum:date_acquired": "2002-11-13",
    "sfomuseum:daterange_end": "1985-12-31",
    "sfomuseum:daterange_start": "1985-01-01",
    "sfomuseum:description": "City timetable for Lexington/Louisville issued by USAir, effective May 1, 1985; white cover with text promoting service from Louisville to Los Angeles and San Francisco; includes Allegheny Commuter Service.",
    "sfomuseum:dimensions": "9 x 4 inches (22.9 x 10.2 cm)",
    "sfomuseum:media_ids": [
      1527843143
    ],
    "sfomuseum:medium": "paper, ink",
    "sfomuseum:placetype": "object",
    "sfomuseum:publication": ": , 1985.",
    "sfomuseum:subcategory": "Timetable",
    "wof:depicts": [
      1159288239,
      1159285447
    ],
    "wof:name": "timetable: USAir, Lexington/Louisville",
    "wof:placetype": "custom",
    "wof:placetype_alt": [
      "object"
    ]
  },
  "geometry": {"coordinates":[-122.386155,37.616357],"type":"Point"}
}
