{
  "type": "Feature",
  "properties": {
    "date:cessation_lower": "1985-12-31",
    "date:cessation_upper": "1985-12-31",
    "date:inception_lower": "1985-01-01",
    "date:inception_upper": "1985-01-01",
    "iso:country": "US",
    "sfomuseum:accession_number": "2002.005.012\r",
    "sfomuseum:category": "Scheduling / Ticketing",
    "sfomuseum:collection": "Aviation Archive",
    "sfomuseum:continent": "North America",
    "sfomuseum:country": "United States",
    "sfomuseum:creditline": "Gift of John R. Barker",
    "sfomuseum:date": "1985",
    "sfomuseum:daterange_end": "1985-12-31",
    "sfomuseum:daterange_start": "1985-01-01",
    "sfomuseum:description": "City timetable for Louisville issued by USAir, effective May 1, 1985 and includes Allegheny Commuter Service; white cover.",
    "sfomuseum:media_ids": [
      1527843143
    ],
    "sfomuseum:medium": "paper, ink",
    "sfomuseum:placetype": "object",
    "sfomuseum:subcategory": "Timetable",
    "wof:name": "timetable: USAir",
    "wof:placetype": "venue"
  },
  "geometry": {"coordinates":[-122.386155,37.616358],"type":"Point"}
}
