{
  "type": "Feature",
  "properties": {
    "date:cessation_lower": "1958-12-31",
    "date:cessation_upper": "1958-12-31",
    "date:inception_lower": "1958-01-01",
    "date:inception_upper": "1958-01-01",
    "iso:country": "XX",
    "sfomuseum:accession_number": "2002.097.001",
    "sfomuseum:airport": "San Francisco International Airport",
    "sfomuseum:category": "Book",
    "sfomuseum:collection": "Aviation Library",
    "sfomuseum:creditline": "Gift of Leigh Fisher Associates",
    "sfomuseum:date": "3/3/1958",
    "sfomuseum:daterange_end": "1958-03-03",
    "sfomuseum:daterange_start": "1958-03-03",
    "sfomuseum:description": "31 p.: charts.",
    "sfomuseum:medium": "paper, ink",
    "sfomuseum:placetype": "object",
    "sfomuseum:subcategory": "Book",
    "wof:depicts": [
      102527513
    ],
    "wof:name": "Progress and Preliminary Recommendations on Terminal Expansion: San Francisco International Airport",
    "wof:placetype": "custom"
  },
  "geometry": {"coordinates":[-122.386155,37.616357],"type":"Point"}
}
