{
  "type": "Feature",
  "properties": {
    "date:cessation_lower": "1958-03-03",
    "date:cessation_upper": "1958-03-03",
    "date:inception_lower": "1958-03-03",
    "date:inception_upper": "1958-03-03",
    "iso:country": "XX",
    "sfomuseum:accession_number": "2002.097.001",
    "sfomuseum:airport": "San Francisco International Airport",
    "sfomuseum:author": "Leigh Fisher and Associates",
    "sfomuseum:callnumber": "TL726.4.S4 L3 1958",
    "sfomuseum:category": "Book",
    "sfomuseum:collection": "Aviation Library",
    "sfomuseum:creditline": "Gift of Leigh Fisher Associates",
    "sfomuseum:date": "3/3/1958",
    "sfomuseum:date_acquired": "2003-05-16",
    "sfomuseum:daterange_end": "1958-03-03",
    "sfomuseum:daterange_start": "1958-03-03",
    "sfomuseum:description": "31 p.: charts.",
    "sfomuseum:description_library": "31 p.: charts.",
    "sfomuseum:issues_held": "1958",
    "sfomuseum:medium": "paper, ink",
    "sfomuseum:notes_library": "March 3, 1958",
    "sfomuseum:placetype": "object",
    "sfomuseum:publication": "South Bend, Ind: Leigh Fisher and Associates, 3/3/1958.",
    "sfomuseum:publisher": "Leigh Fisher and Associates",
    "sfomuseum:publisher_location": "South Bend, Ind",
    "sfomuseum:subcategory": "Book",
    "sfomuseum:subject": "Airports -- California -- San Francisco -- Planning.\rSan Francisco International Airport.",
    "wof:depicts": [
      102527513
    ],
    "wof:name": "Progress and Preliminary Recommendations on Terminal Expansion: San Francisco International Airport",
    "wof:placetype": "custom"
  },
  "geometry": {"coordinates":[-122.386155,37.616357],"type":"Point"}
}
