{
  "type": "Feature",
  "properties": {
    "date:cessation_lower": "1994-01-01",
    "date:cessation_upper": "1994-12-31",
    "date:inception_lower": "1994-01-01",
    "date:inception_upper": "1994-12-31",
    "iso:country": "XX",
    "millsfield:images": [
      1763442961
    ],
    "millsfield:images_texts": [
      "Garuda Indonesia"
    ],
    "millsfield:images_texts_ids": [
      1763442961
    ],
    "millsfield:primary_image": 1763442961,
    "sfomuseum:accession_number": "2004.115.0292",
    "sfomuseum:aircraft": "Airbus A300",
    "sfomuseum:airline": "Garuda Indonesia",
    "sfomuseum:artist": "William “Bill” Hough",
    "sfomuseum:category": "Photograph",
    "sfomuseum:collection": "Aviation Archive",
    "sfomuseum:creditline": "Gift of the William Hough Collection",
    "sfomuseum:date": "1994",
    "sfomuseum:date_acquired": "2004-12-28",
    "sfomuseum:daterange_end": "1994-12-31",
    "sfomuseum:daterange_start": "1994-01-01",
    "sfomuseum:description": "Color photographic slide depicting Garuda Indonesia Airbus A300, November 25, 1994.",
    "sfomuseum:dimensions": "1 x 1 1/2 inches (2.5 x 3.8 cm)",
    "sfomuseum:medium": "color slide",
    "sfomuseum:placetype": "object",
    "sfomuseum:publication": ": , 1994.",
    "sfomuseum:subcategory": "Slide",
    "wof:depicts": [
      1159293829,
      1159288251,
      1159284415,
      1159289389
    ],
    "wof:name": "slide: Garuda Indonesia, Airbus A300",
    "wof:placetype": "custom",
    "wof:placetype_alt": "object"
  },
  "geometry": {"coordinates":[-122.386155,37.616357],"type":"Point"}
}
