{
  "type": "Feature",
  "properties": {
    "date:cessation_lower": "1971-01-01",
    "date:cessation_upper": "1971-12-31",
    "date:inception_lower": "1971-01-01",
    "date:inception_upper": "1971-12-31",
    "iso:country": "XX",
    "millsfield:images": [
      1527846717
    ],
    "millsfield:primary_image": 1527846717,
    "sfomuseum:accession_number": "2001.106.432",
    "sfomuseum:airline": "Northeast Airlines",
    "sfomuseum:category": "Scheduling / Ticketing",
    "sfomuseum:collection": "Aviation Archive",
    "sfomuseum:creditline": "Gift of Mark F. Adams Collection",
    "sfomuseum:date": "1971",
    "sfomuseum:daterange_end": "1971-12-31",
    "sfomuseum:daterange_start": "1971-01-01",
    "sfomuseum:description": "System timetable issued by Northeast Airlines, effective September 15, 1971; yellow and white cover with company servicemark at top and illustration of birds (Yellowbirds) and eggs promoting “West End Service” and “Fall Breakaway”.",
    "sfomuseum:dimensions": "9 x 4 inches (22.9 x 10.2 cm)",
    "sfomuseum:issues_held": "Effective: 9-15-1971",
    "sfomuseum:media_ids": [
      1527846717
    ],
    "sfomuseum:medium": "paper, ink",
    "sfomuseum:placetype": "object",
    "sfomuseum:publication": ": , 1971.",
    "sfomuseum:subcategory": "Timetable",
    "wof:depicts": [
      1159284893
    ],
    "wof:name": "timetable: Northeast Airlines",
    "wof:placetype": "venue"
  },
  "geometry": {"coordinates":[-122.386155,37.616357],"type":"Point"}
}
