{
  "type": "Feature",
  "properties": {
    "date:cessation_lower": "1928-02-21",
    "date:cessation_upper": "1928-02-21",
    "date:inception_lower": "1928-02-21",
    "date:inception_upper": "1928-02-21",
    "iso:country": "XX",
    "millsfield:images": [
      1527832747,
      1527832749
    ],
    "millsfield:images_texts": [
      "* FEB 21\n4 AM\n1928\nCHICAGO\nST. LOUIS\nC. A. M. 2\n-VES TIME\nANIT\nCHICAGO,\nILL.\n2-21-28\n$/09\n12 50 Case St.\nE. Reona\n2ll.",
      ": FEB 21\n* 12 - M\n40\nADDRESS\nYOUR MAIL\nTO\nSTREL, AND\nNUMBER\n2012.140.1550"
    ],
    "millsfield:images_texts_ids": [
      1527832747,
      1527832749
    ],
    "millsfield:primary_image": 1527832747,
    "sfomuseum:accession_number": "2012.149.1550",
    "sfomuseum:category": "Philately",
    "sfomuseum:collection": "Aviation Archive",
    "sfomuseum:creditline": "Gift of the Captain John B. Russell Family",
    "sfomuseum:date": "02/21/1928",
    "sfomuseum:date_acquired": "2013-05-31",
    "sfomuseum:daterange_end": "1928-02-21",
    "sfomuseum:daterange_start": "1928-02-21",
    "sfomuseum:description": "Airmail flight cover issued in honor of Charles Lindbergh flight, CAM-2, Chicago - St. Louis; black horseshoe cachet with text, “Lindbergh again flies the air mail”; postmarked February 21, 1928 in Chicago with “Air Mail Saves time” cancellation mark over 10-cent postage stamp; backstamp: February 21, 1928 in St. Louis.",
    "sfomuseum:dimensions": "3 1/2 x 6 inches (8.9 x 15.2 cm)",
    "sfomuseum:media_ids": [
      1527832747,
      1527832749
    ],
    "sfomuseum:medium": "paper, ink",
    "sfomuseum:placetype": "object",
    "sfomuseum:publication": ": , 02/21/1928.",
    "sfomuseum:subcategory": "Airmail Flight Cover",
    "wof:name": "airmail flight cover: Charles Lindbergh flight, CAM-2, Chicago - St. Louis route",
    "wof:placetype": "custom",
    "wof:placetype_alt": "object"
  },
  "geometry": {"coordinates":[-122.386155,37.616357],"type":"Point"}
}
