{
  "type": "Feature",
  "properties": {
    "date:cessation_lower": "1969-01-01",
    "date:cessation_upper": "1969-12-31",
    "date:inception_lower": "1969-01-01",
    "date:inception_upper": "1969-12-31",
    "iso:country": "XX",
    "millsfield:images": [
      1527838483
    ],
    "millsfield:images_texts": [
      "WASHINGTON \u0026 BALTIMORE\nUnited Air Lines\nQuick Reference\nSchedule\nEffective October 26, 1969\nTO LOS ANGELES\nLEAVE\n9:30am (8)\n1:00pm (D)\n* 6:000m (5)\nARRIVE\n11:55am\nsesvom\n7:45pm\n8:25pm\nFLIGHT\nSTOPS\nFROM LOS ANGELES\n9:00am\n4:45pm (D)\n* 9:55am\n5:25pm (B)\n*12:00n\n7:40pm (D)\n0000\nCLASS\nMEALS\nfIl\nBEE\nBEER\n9838\n9:30am (B)\n* 5:15pm (D)\n1:18pm\n9:58pm\n55\n65/83a\n7:35am\n* 8:10am\n2:20pm\n9:45pm\n4:45pm (D) 104/52a\n5:25pm (B)\n82/64a\n7:40pm (D)\n896/54a\n12:35am (B)\n110\n6:30am (B)\n302/58a\nSAN FRANCISCO, OAKLAND G\n9:00am (D)\n11:45am\n12:00n\n(B)\n5:20pm (D)\n* 5:45pm (D)\n9:2500\n8:35pm\n(S)\n885\nFROM SAN\nFRANCISCO, OAKLAND\n8:35am (S)\n5:570m (D)\n* 9:00am\n5:00pm (D)\n1690m\n9:25pm (B)\n9:150m\n5:30am (5)\n10:300m\n(D)\n88898\nTO PORTLAND\n8:25am\n1.00am (5)\n6:30pm (B)\n12-25pm\n3:10pm\n4:36pm\n10-070m\n421/1416\n743\nBEBEE\nJOSE\n:\nSuES\nABBa"
    ],
    "millsfield:images_texts_ids": [
      1527838483
    ],
    "millsfield:primary_image": 1527838483,
    "sfomuseum:accession_number": "2006.059.101.004",
    "sfomuseum:airline": "United Air Lines",
    "sfomuseum:category": "Scheduling / Ticketing",
    "sfomuseum:collection": "Aviation Archive",
    "sfomuseum:creditline": "Gift of the Paul Edward Fair Estate",
    "sfomuseum:date": "1969",
    "sfomuseum:date_acquired": "2006-10-19",
    "sfomuseum:daterange_end": "1969-12-31",
    "sfomuseum:daterange_start": "1969-01-01",
    "sfomuseum:description": "Quick reference schedule issued by United Air Lines for flights to and from Washington and Baltimore-area airports, effective October 26, 1969; double-sided card.",
    "sfomuseum:dimensions": "7 x 3 1/2 inches (17.8 x 8.9 cm)",
    "sfomuseum:media_ids": [
      1527838483
    ],
    "sfomuseum:medium": "paper, ink",
    "sfomuseum:placetype": "object",
    "sfomuseum:publication": ": , 1969.",
    "sfomuseum:subcategory": "Timetable",
    "wof:depicts": [
      1159285415,
      1159288779
    ],
    "wof:name": "timetable: United Air Lines, quick reference, Washington and Baltimore",
    "wof:placetype": "custom",
    "wof:placetype_alt": "object"
  },
  "geometry": {"coordinates":[-122.386155,37.616357],"type":"Point"}
}
