{
  "type": "Feature",
  "properties": {
    "date:cessation_lower": "1969-01-01",
    "date:cessation_upper": "1969-12-31",
    "date:inception_lower": "1969-01-01",
    "date:inception_upper": "1969-12-31",
    "iso:country": "XX",
    "millsfield:images": [
      1527838483
    ],
    "millsfield:images_texts": [
      "WASHINGTON \u0026 BALTIMORE\nUnited Air Lines\nQuick Reference\nSchedule\nEffective October 26, 1969\nTO LOS ANGELES\nLEAVE\n9:30 am (B)\n1:00pm (D)\n* 5:15pm (D)\n* 6:00pm (B)\nARRIVE\n11:55am\n3:30pm\n7:45pm\n8:25pm\nFLIGHT\n51\n59\n55\n65\nSTOPS\nCLASS\nF/Y\nF/Y\nF/Y\nF/Y\nFROM LOS ANGELES\n9:00 am\n4:45pm (D)\n* 9:55am\n5:25pm (B)\n*12:00n\n7:40pm (D)\n11:05pm\n6:30 am (B)\n52\n64\n54\n58\nF/Y\nF/Y\nF/Y\nF/Y\nTO SAN DIEGO\n9:30 am (B)\n* 5:15pm (D)\n* 6:00pm (B)\n1:18pm\n9:03pm\n9:58pm\n51/1a\n55\n65/83a\n1\nF/Y\nF/Y\nF/Y\nFROM SAN DIEGO\n7:35 am\n* 8:10am\n*10:05 am\n2:20pm\n9:45pm\n4:45pm (D)\n5:25pm (B)\n7:40pm (D)\n12:35am (B)\n6:30am (B)\n104/52a\n82/64a\n896/54a\n110\n302/58a\nF/Y\nF/Y\nF/Y\nF/Y\nF/Y\nTO SAN FRANCISCO, OAKLAND \u0026 SAN JOSE\n9:00am (D)\n11:45 am\n12:00n\n(B)\n2:40pm\n5:20pm (D)\n9:25pm (S)\n* 5:45pm (D)\n8:35pm\n* 6:00pm (B)\n10:14pm\n53\n63\n689\n57\n65\nF/Y\nF/Y\nF/Y\nF/Y\nF/Y\nFROM SAN FRANCISCO, OAKLAND \u0026 SAN JOSE\n8:35am (S)\n5:57pm (D)\n* 9:00 am\n5:00pm (D)\n1:45pm\n9:25pm (B)\n9:15pm\n6:30am (B)\n10:30pm\n6:20am (D)\n322\n50\n62\n58\n56\nF/Y\nF/Y\nF/Y\nF/Y\nF/Y\nPORTLAND\n8:25am (W)\n11:00am (B)\n12:55pm (D)\n6:30pm (B)\n12:25pm\n3:10pm\n4:36pm\n10:07pm\n421/141b\n991/149b\n743\n41\nF/Y\nF/Y\nF/Y\nF/Y\nMEALS\n2188\n8188\n2808\n2888\n8188\n2088\n2088\n8188\n8188\n2188\n2188\n2188\n2088\n2888\n8188\n8188\n2188\n2088\n2008\n2188\n2888\n8088\nES\n2188\n8188\n8188\n2188\n2006.059.101.004"
    ],
    "millsfield:images_texts_ids": [
      1527838483
    ],
    "millsfield:primary_image": 1527838483,
    "sfomuseum:accession_number": "2006.059.101.004",
    "sfomuseum:airline": "United Air Lines",
    "sfomuseum:category": "Scheduling / Ticketing",
    "sfomuseum:collection": "Aviation Archive",
    "sfomuseum:creditline": "Gift of the Paul Edward Fair Estate",
    "sfomuseum:date": "1969",
    "sfomuseum:date_acquired": "2006-10-19",
    "sfomuseum:daterange_end": "1969-12-31",
    "sfomuseum:daterange_start": "1969-01-01",
    "sfomuseum:description": "Quick reference schedule issued by United Air Lines for flights to and from Washington and Baltimore-area airports, effective October 26, 1969; double-sided card.",
    "sfomuseum:dimensions": "7 x 3 1/2 inches (17.8 x 8.9 cm)",
    "sfomuseum:media_ids": [
      1527838483
    ],
    "sfomuseum:medium": "paper, ink",
    "sfomuseum:placetype": "object",
    "sfomuseum:publication": ": , 1969.",
    "sfomuseum:subcategory": "Timetable",
    "wof:depicts": [
      1159285415,
      1159288779
    ],
    "wof:name": "timetable: United Air Lines, quick reference, Washington and Baltimore",
    "wof:placetype": "custom",
    "wof:placetype_alt": "object"
  },
  "geometry": {"coordinates":[-122.386155,37.616357],"type":"Point"}
}
