{
  "type": "Feature",
  "properties": {
    "date:cessation_lower": "1970-12-31",
    "date:cessation_upper": "1970-12-31",
    "date:inception_lower": "1960-01-01",
    "date:inception_upper": "1960-01-01",
    "iso:country": "XX",
    "millsfield:images": [
      1527845561,
      1527845563
    ],
    "sfomuseum:accession_number": "2001.080.094",
    "sfomuseum:airline": "Philippine Airlines",
    "sfomuseum:artist": "Michael Jones",
    "sfomuseum:category": "Passenger Amenity",
    "sfomuseum:collection": "Aviation Archive",
    "sfomuseum:continent": "World Routes",
    "sfomuseum:creditline": "Gift of Thomas G. Dragges",
    "sfomuseum:date": "c. 1965",
    "sfomuseum:daterange_end": "1970-12-31",
    "sfomuseum:daterange_start": "1960-01-01",
    "sfomuseum:description": "Menu issued by Philippine Airlines, Manila - Honolulu - San Francisco route; full color photographic image of coral and other sea animals; menu items include country smoked ham, green pepper steak, and chicken Madagaskar [sic]; menu number: 106-02-Y; class: Fiesta (economy); undated.",
    "sfomuseum:media_ids": [
      1527845561,
      1527845563
    ],
    "sfomuseum:medium": "paper, ink",
    "sfomuseum:placetype": "object",
    "sfomuseum:subcategory": "Menu",
    "wof:depicts": [
      1159285015
    ],
    "wof:name": "menu: Philippine Airlines, Fiesta (Economy) Class",
    "wof:placetype": "venue"
  },
  "geometry": {"coordinates":[-122.386155,37.616357],"type":"Point"}
}
