{
  "type": "Feature",
  "properties": {
    "date:cessation_lower": "1965-01-01",
    "date:cessation_upper": "1965-12-31",
    "date:inception_lower": "1965-01-01",
    "date:inception_upper": "1965-12-31",
    "iso:country": "XX",
    "millsfield:images": [
      1527845561,
      1527845563
    ],
    "millsfield:images_texts": [
      "ine Airlines",
      "Manila - Honolulu\nDinner\nCOUNTRY SMOKED HAM ROLL PRINCESS\nPORK CUTLETS WITH MINT, CITRUS AND ONION SAUCE\nMIXED VEGETABLES\nPILAFF RICE\nOR\nGREEN PEPPER STEAK\nBUTTERED GREEN BEANS\nCROQUETTE POTATOES\nMIXED GREEN SALAD\nFRENCH DRESSING\nCANNOLO WITH BLUEBERRY CREAM\nCOFFEE or TEA\nBreakfast\nFRESH FRUIT COCKTAIL\nSCRAMBLED EGGS WITH HAM\nOR\nOMELETTE CHASSEUR\nBREAKFAST ROLL\nDANISH PASTRY\nCOFFEE or TEA\nHonolulu-San Francisco\nBunch\nSHRIMP SALAD IN HALF TOMATO\nBREAST OF CHICKEN MADAGASKAR\nBUTTERED BROCCOLI\nDUCHESS POTATOES\nOR\nTENDERLOIN TIPS STROGANOFF\nGREEN PEAS WITH MINT\nSTEAMED RICE\nTOSSED GREEN SALAD\nFRENCH DRESSING\nSTRAWBERRY MOUSSE\nSESAME TWIST ROLL\nCOFFEE or TEA\nWERNER BERGER\ndemore, de ta connene de a CHAINS DES ROTISSEURS"
    ],
    "millsfield:images_texts_ids": [
      1527845561,
      1527845563
    ],
    "millsfield:primary_image": 1527845561,
    "sfomuseum:accession_number": "2001.080.094",
    "sfomuseum:airline": "Philippine Airlines",
    "sfomuseum:artist": "Michael Jones",
    "sfomuseum:category": "Passenger Amenity, Archive",
    "sfomuseum:collection": "Aviation Archive",
    "sfomuseum:continent": "World Routes",
    "sfomuseum:creditline": "Gift of Thomas G. Dragges",
    "sfomuseum:date": "c. 1965",
    "sfomuseum:date_acquired": "2002-12-24",
    "sfomuseum:daterange_end": "1970-12-31",
    "sfomuseum:daterange_start": "1960-01-01",
    "sfomuseum:description": "Menu issued by Philippine Airlines, Manila - Honolulu - San Francisco route; full color photographic image of coral and other sea animals; menu items include country smoked ham, green pepper steak, and chicken Madagaskar [sic]; menu number: 106-02-Y; class: Fiesta (economy); undated.",
    "sfomuseum:dimensions": "9 1/4 x 6 inches (23.5 x 15.2 cm)",
    "sfomuseum:media_ids": [
      1527845561,
      1527845563
    ],
    "sfomuseum:medium": "paper, ink",
    "sfomuseum:placetype": "object",
    "sfomuseum:publication": ": , c. 1965.",
    "sfomuseum:subcategory": "Menu",
    "wof:depicts": [
      1159285015,
      1159287151
    ],
    "wof:name": "menu: Philippine Airlines, Fiesta (Economy) Class",
    "wof:placetype": "custom",
    "wof:placetype_alt": "object"
  },
  "geometry": {"coordinates":[-122.386155,37.616357],"type":"Point"}
}
