{
  "type": "Feature",
  "properties": {
    "date:cessation_lower": "1990-01-01",
    "date:cessation_upper": "1990-12-31",
    "date:inception_lower": "1990-01-01",
    "date:inception_upper": "1990-12-31",
    "iso:country": "XX",
    "millsfield:images": [
      1527843337
    ],
    "millsfield:images_texts": [
      "722\nTRUMP\nTRUMPAIR\nFLIGHT SCHEDULE"
    ],
    "millsfield:images_texts_ids": [
      1527843337
    ],
    "millsfield:primary_image": 1527843337,
    "sfomuseum:accession_number": "2010.225.039",
    "sfomuseum:airline": "Trump Airlines",
    "sfomuseum:category": "Scheduling / Ticketing",
    "sfomuseum:collection": "Aviation Archive",
    "sfomuseum:creditline": "Gift of the William Hough Collection",
    "sfomuseum:date": "c. 1990",
    "sfomuseum:date_acquired": "2011-11-10",
    "sfomuseum:daterange_end": "1995-12-31",
    "sfomuseum:daterange_start": "1985-01-01",
    "sfomuseum:description": "Timetable issued by Trump Air; no date; bi-fold card with black cover and contour illustration of helicopter in flight; contains listing of flights between New York (Manhattan) and Atlantic City.",
    "sfomuseum:dimensions": "5 1/2 x 6 inches (14 x 15.2 cm)",
    "sfomuseum:media_ids": [
      1527843337
    ],
    "sfomuseum:medium": "paper, ink",
    "sfomuseum:placetype": "object",
    "sfomuseum:publication": ": , c. 1990.",
    "sfomuseum:subcategory": "Timetable",
    "wof:depicts": [
      1159285379,
      1159286807
    ],
    "wof:name": "timetable: Trump Air",
    "wof:placetype": "custom",
    "wof:placetype_alt": "object"
  },
  "geometry": {"coordinates":[-122.386155,37.616357],"type":"Point"}
}
