{
  "type": "Feature",
  "properties": {
    "date:cessation_lower": "2011-01-01",
    "date:cessation_upper": "2011-12-31",
    "date:inception_lower": "2011-01-01",
    "date:inception_upper": "2011-12-31",
    "isbn:number": "9781470153199 (pbk.), 147015319X (pbk.)",
    "iso:country": "XX",
    "loc:subject_headings": [
      "sh2009113866"
    ],
    "sfomuseum:accession_number": "2013.073.002",
    "sfomuseum:author": "Block, Thomas",
    "sfomuseum:callnumber": "G445 .S75 2011",
    "sfomuseum:category": "Book",
    "sfomuseum:collection": "Aviation Library",
    "sfomuseum:creditline": "Purchase",
    "sfomuseum:date": "2011",
    "sfomuseum:date_acquired": "2013-06-06",
    "sfomuseum:daterange_end": "2011-12-31",
    "sfomuseum:daterange_start": "2011-01-01",
    "sfomuseum:description": "v, 261 p. : ill. ; 23 cm.",
    "sfomuseum:description_library": "v, 261 p. : ill. ; 23 cm.",
    "sfomuseum:medium": "paper, ink",
    "sfomuseum:placetype": "object",
    "sfomuseum:publication": "Jefferson, NC: McFarland \u0026 Co., 2011.",
    "sfomuseum:publisher": "McFarland \u0026 Co.",
    "sfomuseum:publisher_location": "Jefferson, NC",
    "sfomuseum:subcategory": "Book",
    "sfomuseum:subject": "Aeronautics -- Fiction.\rMystery -- Fiction.",
    "wof:name": "Skyfall",
    "wof:placetype": "custom",
    "wof:placetype_alt": "object"
  },
  "geometry": {"coordinates":[-122.386155,37.616357],"type":"Point"}
}
