{
  "type": "Feature",
  "properties": {
    "date:cessation_lower": "1970-01-01",
    "date:cessation_upper": "1970-12-31",
    "date:inception_lower": "1970-01-01",
    "date:inception_upper": "1970-12-31",
    "iso:country": "XX",
    "millsfield:images": [
      1527843245
    ],
    "millsfield:images_texts": [
      "(news)\nPSA\nLONG BEACH SERVICE\nAll Fan Jet\nEffective December 23rd, 1970\nFit\n117\nNORTHBOUND\nSOUTHBOUND\nMONDAY\nTHRU THURSDAY\nLV\nAR\nLV\nLGB\nLGB\nAR\nFit\nLV\nAR\nSF\niB\n7:00\n7:20\n7:40\n8:45\n116\n9:15 10:20\n10:45 11:50\n1:30\n2:35\n216\n11:45 12:50\n3:00\n4:05\n4:30\n316\n5:35\n416\n6:00\n7:05\n7:20\nFRIDAY\nAR\nSI\n7:40\nFit\nFanta\n7:00\nAR\nGB\n7:20\nLV\nAR\n_GB\nSF\nFit\n7:40\n8:45\n116\n10:45 11:50\n216\n1:30\n2:35\n4:30\n316\nPEND\n7:30\n51\n616\nSATURDAY\nAR\nLs\nAR\nSI\n9:15 10:20\n11:45 12:50\n3:00\n4:05\n6:00\n:05\n9:00 10:05 10:25 10:45\nFit\nENoR\n7:00\nAR\nLGB\n7:20\nLV.\nAR\nLGB\nSF\nFit\n7:40\n8:45\n10:45 11:50\n118\n1:50\n2:55\n5:00\n6:05\n816\n916\nLV\nAR\nLGB\nLV\nGB\n9:15\n10:20\n12:15\n1:20\n3:30\n4:35\n7:35\n7:50\nAR\nSD\n8:10\nSUNDAY\nFit\n119\n219\n319\n419\n519\nLV\nAR\nSD\n_GB\n8:00\n8:20\nLY\nAR\nLGB\nSF\nFit\nSAAO\n9905 11 81\n11:50 12:55\n2:00\n218\nSHUD\n5:55\n418\n8:00\n9:05\n518\nLV AR.\nLY\nLGB\n_GB\nAR\nSD\n10:15 11:20\nBETS\n6125\n4:20\n7:30\n9:30 10:35 10:50 11:10\nAM-Lightface / PM-Boldface\nFARE (incl. tax) Long Beach - San Francisco\n$18.00\nSAN FRANCISCO\nLONG BEACH\nFOR RESERVATIONS\n.. . . .Int'l Airport\n761-0818\nMunicipal Airport\n429-2447 or 776-0125\nSchedule subject to change without notice"
    ],
    "millsfield:images_texts_ids": [
      1527843245
    ],
    "millsfield:primary_image": 1527843245,
    "sfomuseum:accession_number": "2005.132.042.091",
    "sfomuseum:airline": "Pacific Southwest Airlines (PSA)",
    "sfomuseum:category": "Scheduling / Ticketing",
    "sfomuseum:collection": "Aviation Archive",
    "sfomuseum:creditline": "Gift of the William Hough Collection",
    "sfomuseum:date": "1970",
    "sfomuseum:date_acquired": "2006-12-05",
    "sfomuseum:daterange_end": "1970-12-31",
    "sfomuseum:daterange_start": "1970-01-01",
    "sfomuseum:description": "Timetable issued by Pacific Southwest Airlines (PSA), effective December 23, 1970, for service to and from Long Beach; double-sided card; includes office phones numbers and index of fares.",
    "sfomuseum:dimensions": "6 x 3 1/2 inches (15.2 x 8.9 cm)",
    "sfomuseum:media_ids": [
      1527843245
    ],
    "sfomuseum:medium": "paper, ink",
    "sfomuseum:placetype": "object",
    "sfomuseum:publication": ": , 1970.",
    "sfomuseum:subcategory": "Timetable",
    "wof:depicts": [
      1159284973,
      1159286629
    ],
    "wof:name": "timetable: Pacific Southwest Airlines (PSA), Long Beach",
    "wof:placetype": "custom",
    "wof:placetype_alt": "object"
  },
  "geometry": {"coordinates":[-122.386155,37.616357],"type":"Point"}
}
