{
  "type": "Feature",
  "properties": {
    "date:cessation_lower": "2005-01-01",
    "date:cessation_upper": "2005-12-31",
    "date:inception_lower": "2005-01-01",
    "date:inception_upper": "2005-12-31",
    "iso:country": "XX",
    "sfomuseum:accession_number": "2007.056.089",
    "sfomuseum:author": "Roe, Kathleen",
    "sfomuseum:callnumber": "CD950 .R64 2005",
    "sfomuseum:category": "Book",
    "sfomuseum:collection": "Aviation Library",
    "sfomuseum:creditline": "Purchase",
    "sfomuseum:date": "2005",
    "sfomuseum:date_acquired": "2007-07-17",
    "sfomuseum:daterange_end": "2005-12-31",
    "sfomuseum:daterange_start": "2005-01-01",
    "sfomuseum:description": "xv, 180 p. ; 23 cm.",
    "sfomuseum:description_library": "xv, 180 p. ; 23 cm.",
    "sfomuseum:medium": "paper, ink",
    "sfomuseum:placetype": "object",
    "sfomuseum:publication": "Chicago: Society of American Archivists, 2005.",
    "sfomuseum:publisher": "Society of American Archivists",
    "sfomuseum:publisher_location": "Chicago",
    "sfomuseum:series": "Archival fundamentals series. II",
    "sfomuseum:subcategory": "Book",
    "sfomuseum:subject": "Archives.",
    "wof:name": "Arranging \u0026 describing archives \u0026 manuscripts",
    "wof:placetype": "venue"
  },
  "geometry": {"coordinates":[-122.386155,37.616357],"type":"Point"}
}
