{
  "type": "Feature",
  "properties": {
    "date:cessation_lower": "1970-01-01",
    "date:cessation_upper": "1970-12-31",
    "date:inception_lower": "1970-01-01",
    "date:inception_upper": "1970-12-31",
    "iso:country": "XX",
    "sfomuseum:accession_number": "00-1955",
    "sfomuseum:author": "Olsen, Jack",
    "sfomuseum:callnumber": "D785 .O47 1970 c.2",
    "sfomuseum:category": "Book",
    "sfomuseum:collection": "Aviation Library",
    "sfomuseum:date": "1970",
    "sfomuseum:daterange_end": "1970-12-31",
    "sfomuseum:daterange_start": "1970-01-01",
    "sfomuseum:description": "328 p. illus., map. 22 cm.",
    "sfomuseum:description_library": "328 p. illus., map. 22 cm.",
    "sfomuseum:medium": "paper, ink",
    "sfomuseum:placetype": "object",
    "sfomuseum:publication": "New York: Putnam, 1970.",
    "sfomuseum:publisher": "Putnam",
    "sfomuseum:publisher_location": "New York",
    "sfomuseum:subcategory": "Book",
    "sfomuseum:subject": "World War, 1939-1945 Aerial operations.",
    "wof:name": "Aphrodite: desperate mission",
    "wof:placetype": "custom",
    "wof:placetype_alt": "object"
  },
  "geometry": {"coordinates":[-122.386155,37.616357],"type":"Point"}
}
