{
  "type": "Feature",
  "properties": {
    "date:cessation_lower":"1963-12-31",
    "date:cessation_upper":"1963-12-31",
    "date:inception_lower":"1963-01-01",
    "date:inception_upper":"1963-01-01",
    "iso:country":"XX",
    "sfomuseum:accession_number":"2012.149.2210 a b",
    "sfomuseum:category":"Philately",
    "sfomuseum:collection":"Aviation Archive",
    "sfomuseum:creditline":"Gift of the Captain John B. Russell Family",
    "sfomuseum:date":"02/09/1963",
    "sfomuseum:daterange_end":"1963-02-09",
    "sfomuseum:daterange_start":"1963-02-09",
    "sfomuseum:description":"a. Airmail flight cover, Boeing 727 first flight, Renton, Washington, Transport Division; purple cachet at lower left; envelope postmarked February 9, 1963, Renton, with two purple 4-cent stamps; addressed to Oscar H. Fatout, Long Beach, California.\rb. Backing sheet with collection of Boeing articles and philately information.",
    "sfomuseum:media_ids":[
        1527853091
    ],
    "sfomuseum:medium":"paper, ink",
    "sfomuseum:placetype":"object",
    "sfomuseum:subcategory":"Airmail Flight Cover",
    "wof:name":"airmail flight cover: Boeing 727, first flight, Renton, Washington",
    "wof:placetype":"venue"
},
  "geometry": {"coordinates":[-122.386155,37.616358],"type":"Point"}
}