{
  "type": "Feature",
  "properties": {
    "date:cessation_lower": "1963-02-09",
    "date:cessation_upper": "1963-02-09",
    "date:inception_lower": "1963-02-09",
    "date:inception_upper": "1963-02-09",
    "iso:country": "XX",
    "millsfield:images": [
      1527853091
    ],
    "millsfield:images_texts": [
      "BOEING 727\nRENTON, WASHINGTON\nFIRST\nFLIGHT\nr.T.\nTRANSPORT DIVISION\nRENTON\n430PM =\nFER 9\n1963\nWAS\nTONIC ENEROP\nPEACEFUL~\nU.S. POSTAGE\nMONIC ENEROY ACR\nPEACEFUI USES\nU.S POSTAGE\nOSCAR H. FATOUT\n4000 E. 5 TIt ST\nLONG BEACH /4 CALIF."
    ],
    "millsfield:images_texts_ids": [
      1527853091
    ],
    "millsfield:primary_image": 1527853091,
    "sfomuseum:accession_number": "2012.149.2210 a b",
    "sfomuseum:aircraft": "Boeing 727",
    "sfomuseum:category": "Philately",
    "sfomuseum:collection": "Aviation Archive",
    "sfomuseum:creditline": "Gift of the Captain John B. Russell Family",
    "sfomuseum:date": "02/09/1963",
    "sfomuseum:date_acquired": "2013-05-31",
    "sfomuseum:daterange_end": "1963-02-09",
    "sfomuseum:daterange_start": "1963-02-09",
    "sfomuseum:description": "a. Airmail flight cover, Boeing 727 first flight, Renton, Washington, Transport Division; purple cachet at lower left; envelope postmarked February 9, 1963, Renton, with two purple 4-cent stamps; addressed to Oscar H. Fatout, Long Beach, California.\rb. Backing sheet with collection of Boeing articles and philately information.",
    "sfomuseum:dimensions": "3 3/4 x 6 1/2 inches (9.5 x 16.5 cm)",
    "sfomuseum:media_ids": [
      1527853091
    ],
    "sfomuseum:medium": "paper, ink",
    "sfomuseum:placetype": "object",
    "sfomuseum:publication": ": , 02/09/1963.",
    "sfomuseum:subcategory": "Airmail Flight Cover",
    "wof:depicts": [
      1159289759,
      1159293593
    ],
    "wof:name": "airmail flight cover: Boeing 727, first flight, Renton, Washington",
    "wof:placetype": "custom",
    "wof:placetype_alt": "object"
  },
  "geometry": {"coordinates":[-122.386155,37.616357],"type":"Point"}
}
