{
  "type": "Feature",
  "properties": {
    "date:cessation_lower": "1996-01-01",
    "date:cessation_upper": "1996-12-31",
    "date:inception_lower": "1996-01-01",
    "date:inception_upper": "1996-12-31",
    "iso:country": "XX",
    "sfomuseum:accession_number": "2004.115.0302",
    "sfomuseum:aircraft": "Douglas DC-8-60",
    "sfomuseum:airline": "Rich International Airways",
    "sfomuseum:airport": "John F. Kennedy International Airport",
    "sfomuseum:artist": "William “Bill” Hough",
    "sfomuseum:category": "Photograph",
    "sfomuseum:collection": "Aviation Archive",
    "sfomuseum:creditline": "Gift of the William Hough Collection",
    "sfomuseum:date": "1996",
    "sfomuseum:date_acquired": "2004-12-28",
    "sfomuseum:daterange_end": "1996-12-31",
    "sfomuseum:daterange_start": "1996-01-01",
    "sfomuseum:description": "Color photographic slide depicting Rich International Airways Douglas DC-8-60 at John F. Kennedy International Airport (JFK), New York, February 25, 1996.",
    "sfomuseum:dimensions": "1 x 1 1/2 inches (2.5 x 3.8 cm)",
    "sfomuseum:medium": "color slide",
    "sfomuseum:placetype": "object",
    "sfomuseum:publication": ": , 1996.",
    "sfomuseum:subcategory": "Slide",
    "wof:depicts": [
      1159285069,
      102534365,
      1159288565,
      1159290443,
      1159290465
    ],
    "wof:name": "slide: Rich International Airways, Douglas DC-8-60, John F. Kennedy International Airport (JFK)",
    "wof:placetype": "custom",
    "wof:placetype_alt": "object"
  },
  "geometry": {"coordinates":[-122.386155,37.616357],"type":"Point"}
}
