{
  "type": "Feature",
  "properties": {
    "date:cessation_lower": "1998-01-01",
    "date:cessation_upper": "1998-12-31",
    "date:inception_lower": "1998-01-01",
    "date:inception_upper": "1998-12-31",
    "iso:country": "XX",
    "sfomuseum:accession_number": "99-1507",
    "sfomuseum:author": "Wilkes, Peter",
    "sfomuseum:callnumber": "TL670.3 .W55 1988 REF",
    "sfomuseum:category": "Book",
    "sfomuseum:collection": "Aviation Library",
    "sfomuseum:date": "1998",
    "sfomuseum:daterange_end": "1998-12-31",
    "sfomuseum:daterange_start": "1998-01-01",
    "sfomuseum:description": "1607p. : ill. ; 23 cm.",
    "sfomuseum:description_library": "1607p. : ill. ; 23 cm.",
    "sfomuseum:medium": "paper, ink",
    "sfomuseum:placetype": "object",
    "sfomuseum:publication": "New York: Smithmark Publishers, 1998.",
    "sfomuseum:publisher": "Smithmark Publishers",
    "sfomuseum:publisher_location": "New York",
    "sfomuseum:subcategory": "Reference",
    "sfomuseum:subject": "Airplanes History.",
    "wof:name": "100 Planes, 100 Years",
    "wof:placetype": "venue"
  },
  "geometry": {"coordinates":[-122.386155,37.616357],"type":"Point"}
}
