{
  "type": "Feature",
  "properties": {
    "date:cessation_lower": "1939-06-30",
    "date:cessation_upper": "1939-06-30",
    "date:inception_lower": "1939-06-30",
    "date:inception_upper": "1939-06-30",
    "iso:country": "XX",
    "millsfield:images": [
      1527820207,
      1527820213,
      1527820215,
      1527820211
    ],
    "sfomuseum:accession_number": "2000.058.1276 a c",
    "sfomuseum:aircraft": "Boeing 314 Dixie Clipper",
    "sfomuseum:airline": "Pan American Airways",
    "sfomuseum:category": "Philately",
    "sfomuseum:collection": "Aviation Archive",
    "sfomuseum:creditline": "Gift of the Pan Am Association",
    "sfomuseum:date": "06/30/1939",
    "sfomuseum:daterange_end": "1939-06-30",
    "sfomuseum:daterange_start": "1939-06-30",
    "sfomuseum:description": "Airmail flight cover, carried by Clara Adams on the first around-the-world (circumglobal) passenger flight on the Pan American Airways “Dixie Clipper”; typed certificate in upper left corner indicating letter was carried on the transatlantic leg of the trip; signed by Clara Adams and W.J. Eck with note “Ticket No. 1”; postmarked June 30, 1939 in Lisbon with three Portuguese stamps; written on reverse in pencil \"Captain R.O.D. Sullivan, Dixie Clipper, Pt Washington”; no backstamp.\ra. Envelope\rb \u0026 c. Insert; two identical typed unsigned letters from Clara Adams on Pan American Airways letterhead, New York City, \"Clara Adams is thinking of you while soaring over land and sea on her world flight. The Inaugural Passenger Flight across the Atlantic in the Pan American Clipper \"Dixie\" was a wonderful start. If all goes well, I should be back in New York between July 14 and 20th.\" ",
    "sfomuseum:dimensions": "b) 11 x 8.5\" ",
    "sfomuseum:media_ids": [
      1527820207,
      1527820213,
      1527820215,
      1527820211
    ],
    "sfomuseum:medium": "paper, ink",
    "sfomuseum:placetype": "object",
    "sfomuseum:subcategory": "Airmail Flight Cover",
    "wof:depicts": [
      1159284991,
      1159289627
    ],
    "wof:name": "airmail flight cover: Pan American Airways, Boeing 314 “Dixie Clipper”, Clara Adams",
    "wof:placetype": "custom"
  },
  "geometry": {"coordinates":[-122.386155,37.616357],"type":"Point"}
}
