{
  "type": "Feature",
  "properties": {
    "date:cessation_lower": "1913-01-01",
    "date:cessation_upper": "1913-12-31",
    "date:inception_lower": "1882-01-01",
    "date:inception_upper": "1882-12-31",
    "iso:country": "XX",
    "millsfield:exhibition_ids": [
      1159160581
    ],
    "millsfield:images": [
      1746680911
    ],
    "millsfield:on_view": 0,
    "millsfield:primary_image": 1746680911,
    "sfomuseum:accession_number": "2000.160.1006",
    "sfomuseum:author": "Century Company",
    "sfomuseum:callnumber": "AP2 .C46 1908 v.76 SC",
    "sfomuseum:category": "Book",
    "sfomuseum:collection": "Aviation Library",
    "sfomuseum:creditline": "Collection of SFO Museum, The Tony Bill Aviation Library Collection",
    "sfomuseum:date": "1882-1913",
    "sfomuseum:date_acquired": "1999-05-18",
    "sfomuseum:daterange_end": "1913-12-31",
    "sfomuseum:daterange_start": "1882-01-01",
    "sfomuseum:description": "64 v. : ill. ; 24 cm.",
    "sfomuseum:description_library": "64 v. : ill. ; 24 cm.",
    "sfomuseum:exhibition_ids": [
      1387
    ],
    "sfomuseum:issues_held": "1908 (Sep)",
    "sfomuseum:medium": "paper, ink",
    "sfomuseum:placetype": "object",
    "sfomuseum:publication": "New York: The Century Company, 1882-1913.",
    "sfomuseum:publisher": "The Century Company",
    "sfomuseum:publisher_location": "New York",
    "sfomuseum:subcategory": "Book",
    "wof:name": "The Century Illustrated monthly magazine",
    "wof:placetype": "custom",
    "wof:placetype_alt": [
      "object"
    ]
  },
  "geometry": {"coordinates":[-122.386155,37.616357],"type":"Point"}
}
