{
  "type": "Feature",
  "properties": {
    "date:cessation_lower": "1977-01-01",
    "date:cessation_upper": "1977-12-31",
    "date:inception_lower": "1977-01-01",
    "date:inception_upper": "1977-12-31",
    "iso:country": "XX",
    "millsfield:images": [
      1527832037
    ],
    "millsfield:images_texts": [
      "AIR\nCANADA\nInternational\nHoraire\nTimetable\nInternational\nEFFECTIVE\nEN VIGUEUR\n24\n• AVRIL\nAPRIL 1977\n19,"
    ],
    "millsfield:images_texts_ids": [
      1527832037
    ],
    "millsfield:primary_image": 1527832037,
    "sfomuseum:accession_number": "2009.122.057",
    "sfomuseum:airline": "Air Canada",
    "sfomuseum:category": "Scheduling / Ticketing",
    "sfomuseum:collection": "Aviation Archive",
    "sfomuseum:creditline": "Gift of the William Hough Collection",
    "sfomuseum:date": "1977",
    "sfomuseum:date_acquired": "2010-06-08",
    "sfomuseum:daterange_end": "1977-12-31",
    "sfomuseum:daterange_start": "1977-01-01",
    "sfomuseum:description": "International timetable issued by Air Canada, effective April 24, 1977; 34-page fold-out; color photographic image of airplanes at night; 40th anniversary; in English and French.",
    "sfomuseum:dimensions": "9 x 4 inches (22.9 x 10.2 cm)",
    "sfomuseum:media_ids": [
      1527832037
    ],
    "sfomuseum:medium": "paper, ink",
    "sfomuseum:placetype": "object",
    "sfomuseum:publication": ": , 1977.",
    "sfomuseum:subcategory": "Timetable",
    "wof:depicts": [
      1159288851,
      1159283597
    ],
    "wof:name": "timetable: Air Canada, international service",
    "wof:placetype": "custom",
    "wof:placetype_alt": "object"
  },
  "geometry": {"coordinates":[-122.386155,37.616357],"type":"Point"}
}
