{
  "type": "Feature",
  "properties": {
    "date:cessation_lower": "1960-01-01",
    "date:cessation_upper": "1960-12-31",
    "date:inception_lower": "1960-01-01",
    "date:inception_upper": "1960-12-31",
    "iso:country": "XX",
    "millsfield:images": [
      1527858379
    ],
    "sfomuseum:accession_number": "2012.147.452",
    "sfomuseum:category": "Insignia",
    "sfomuseum:collection": "Aviation Museum",
    "sfomuseum:creditline": "Gift of the Captain John B. Russell Family",
    "sfomuseum:date": "1960",
    "sfomuseum:daterange_end": "1960-12-31",
    "sfomuseum:daterange_start": "1960-01-01",
    "sfomuseum:description": "Gold bullion on black background, large gold laurels with blue circle with gold “IPC” on center, small gold eagle near top center; black fabric backing on back.",
    "sfomuseum:dimensions": "2 1/2 x 4 x 1/2 inches (6.4 x 10.2 x 1.3 cm)",
    "sfomuseum:media_ids": [
      1527858379
    ],
    "sfomuseum:medium": "textile",
    "sfomuseum:placetype": "object",
    "sfomuseum:subcategory": "Hat Badge, Flight Crew",
    "wof:name": "flight officer cap badge: Iraq Petroleum Company",
    "wof:placetype": "venue"
  },
  "geometry": {"coordinates":[-122.386155,37.616357],"type":"Point"}
}
