{
  "type": "Feature",
  "properties": {
    "date:cessation_lower": "2000-12-31",
    "date:cessation_upper": "2000-12-31",
    "date:inception_lower": "2000-01-01",
    "date:inception_upper": "2000-01-01",
    "iso:country": "XX",
    "sfomuseum:accession_number": "2011.126.008.008",
    "sfomuseum:category": "Scheduling / Ticketing",
    "sfomuseum:collection": "Aviation Archive",
    "sfomuseum:creditline": "Gift of the Paul H. Kowalewski Collection",
    "sfomuseum:date": "2000",
    "sfomuseum:daterange_end": "2000-12-31",
    "sfomuseum:daterange_start": "2000-01-01",
    "sfomuseum:description": "Timetable issued by Alaska Airlines; full page color photographic image of young Alaskan girl in traditional dress; monotone photographic image of older woman pulling handcart loaded with luggage and advertising Alaska’s mileage plan on verso. Effective June 11, 2000.",
    "sfomuseum:media_ids": [
      1527847421
    ],
    "sfomuseum:medium": "paper, ink",
    "sfomuseum:placetype": "object",
    "sfomuseum:subcategory": "Timetable",
    "wof:name": "timetable: Alaska Airlines, includes Horizon Air",
    "wof:placetype": "venue"
  },
  "geometry": {"coordinates":[-122.386155,37.616358],"type":"Point"}
}
