{
  "type": "Feature",
  "properties": {
    "date:cessation_lower": "1964-12-31",
    "date:cessation_upper": "1964-12-31",
    "date:inception_lower": "1964-01-01",
    "date:inception_upper": "1964-01-01",
    "iso:country": "XX",
    "millsfield:images": [
      1527844051,
      1527844053
    ],
    "sfomuseum:accession_number": "2004.093.006 a b",
    "sfomuseum:aircraft": "Boeing",
    "sfomuseum:airline": "Air France",
    "sfomuseum:artist": "Pierre Pages",
    "sfomuseum:category": "Passenger Amenity",
    "sfomuseum:collection": "Aviation Archive",
    "sfomuseum:creditline": "Gift of John M. Burnard",
    "sfomuseum:date": "1964",
    "sfomuseum:daterange_end": "1964-12-31",
    "sfomuseum:daterange_start": "1964-01-01",
    "sfomuseum:description": "Menu issued by Air France, Paris to Tokyo route; bi-fold format, cover and insert; white cover with color reproduction of painting “Les Chateaux de France Versailles”; lists lunch and dinner choices including veal, roast beef, and squab; menu number 22.065; date: 7-64.\ra. menu cover\rb. menu insert",
    "sfomuseum:dimensions": "11 x 8 1/2 inches (27.9 x 21.6 cm)",
    "sfomuseum:media_ids": [
      1527844051,
      1527844053
    ],
    "sfomuseum:medium": "paper, ink",
    "sfomuseum:placetype": "object",
    "sfomuseum:subcategory": "Menu",
    "wof:depicts": [
      1159283627
    ],
    "wof:name": "menu: Air France",
    "wof:placetype": "venue"
  },
  "geometry": {"coordinates":[-122.386155,37.616357],"type":"Point"}
}
