{
  "type": "Feature",
  "properties": {
    "date:cessation_lower":"1964-12-31",
    "date:cessation_upper":"1964-12-31",
    "date:inception_lower":"1964-01-01",
    "date:inception_upper":"1964-01-01",
    "iso:country":"XX",
    "sfomuseum:accession_number":"2004.093.006 a b",
    "sfomuseum:artist":"Pierre Pages",
    "sfomuseum:category":"Food Service",
    "sfomuseum:collection":"Aviation Museum",
    "sfomuseum:creditline":"Gift of John M. Burnard",
    "sfomuseum:date":"1964",
    "sfomuseum:daterange_end":"1964-12-31",
    "sfomuseum:daterange_start":"1964-01-01",
    "sfomuseum:description":"Menu produced by Air France, Paris to Tokyo route; bi-fold format, cover and insert; white cover with color reproduction of painting \u201cLes Chateaux de France Versailles\u201d; lists lunch and dinner choices including veal, roast beef, and squab; menu number 22.065; date: 7-64.\ra. menu cover\rb. menu insert",
    "sfomuseum:medium":"paper, ink",
    "sfomuseum:placetype":"object",
    "sfomuseum:subcategory":"Menu",
    "wof:name":"menu: Air France",
    "wof:placetype":"venue"
},
  "geometry": {"coordinates":[-122.386155,37.616358],"type":"Point"}
}