{
  "type": "Feature",
  "properties": {
    "date:cessation_lower": "1992-01-01",
    "date:cessation_upper": "1992-12-31",
    "date:inception_lower": "1992-01-01",
    "date:inception_upper": "1992-12-31",
    "iso:country": "XX",
    "millsfield:images": [
      1527843911,
      1527853597
    ],
    "millsfield:images_texts": [
      "Bar Service\nAPERITIFS\nSherry\nCampari\nVermouth, sweet or dry\nSPIRITS\nScotch, American and Canadian Whiskies\nGin • Rum • Vodka\nWINES\nSelected red or white wines\nChampagne is also available at\ncurrent bar tariff rate\nLIQUEURS\nCognac • Drambuie • Cointreau\nTia Maria • Port\nBEERS\nEnglish beers\nLager\nSOFT DRINKS\nSquashes: Orange • Lemon • Lime\nColas • Ginger Ale\nBitter Lemon • Tonic Water\nMineral Water\nCAN/USA-LHR MENU A\u0026B Econ QC 16986\nMenu\nFresh honeydew and cantaloup melon with\nstrawberry and a light lime\nGrilled fillet of Atlantic salmon with\nBay shrimps, spring onions and capers,\ndressed with lemon herb sauce and served\nwith leaf spinach, carrots and\nparsley potatoes\nor\nPrime fillet steak in a rich red wine sauce\nwith mushroom and bacon served with\nbuttered beans, cherry tomato\nand potato gnocchis\nTraditional bread and butter pudding\nglazed with apricot sauce\nCoffee or decaffeinated coffee\nWe apologise if, owing to previous passenger\nselection, your choice is not available\nRefreshments\nwill be served",
      "WINES \u0026 SPIRITS\nCONNOISSEUR\nCLA\nWUNITED"
    ],
    "millsfield:images_texts_ids": [
      1527843911,
      1527853597
    ],
    "millsfield:primary_image": 1527853597,
    "sfomuseum:accession_number": "2006.059.307.001 a b",
    "sfomuseum:airline": "United Airlines",
    "sfomuseum:category": "Passenger Amenity, Archive",
    "sfomuseum:collection": "Aviation Archive",
    "sfomuseum:creditline": "Gift of the Paul Edward Fair Estate",
    "sfomuseum:date": "1992",
    "sfomuseum:date_acquired": "2006-10-19",
    "sfomuseum:daterange_end": "1992-12-31",
    "sfomuseum:daterange_start": "1992-01-01",
    "sfomuseum:description": "Wines and spirits menu issued by United Airlines; gray and dark red cover.\ra. menu number: 8 PACIFIC 2001-3; class: Connoisseur (business); date: 292\rb. menu number: 8 PACIFIC 2001-3; class: Connoisseur (business); date: 292",
    "sfomuseum:dimensions": "8 1/2 x 5 1/2 inches (21.6 x 14 cm)",
    "sfomuseum:media_ids": [
      1527843911,
      1527853597
    ],
    "sfomuseum:medium": "paper, ink",
    "sfomuseum:placetype": "object",
    "sfomuseum:publication": ": , 1992.",
    "sfomuseum:subcategory": "Menu",
    "wof:depicts": [
      1159288779,
      1159285413
    ],
    "wof:name": "menu: United Airlines, Connoisseur (Business) Class",
    "wof:placetype": "custom",
    "wof:placetype_alt": [
      "object"
    ]
  },
  "geometry": {"coordinates":[-122.386155,37.616357],"type":"Point"}
}
