{
  "type": "Feature",
  "properties": {
    "date:cessation_lower": "1992-01-01",
    "date:cessation_upper": "1992-12-31",
    "date:inception_lower": "1992-01-01",
    "date:inception_upper": "1992-12-31",
    "iso:country": "XX",
    "millsfield:images": [
      1527843911,
      1527853597
    ],
    "millsfield:primary_image": 1527853597,
    "sfomuseum:accession_number": "2006.059.307.001 a b",
    "sfomuseum:airline": "United Airlines",
    "sfomuseum:category": "Passenger Amenity",
    "sfomuseum:collection": "Aviation Archive",
    "sfomuseum:creditline": "Gift of the Paul Edward Fair Estate",
    "sfomuseum:date": "1992",
    "sfomuseum:daterange_end": "1992-12-31",
    "sfomuseum:daterange_start": "1992-01-01",
    "sfomuseum:description": "Wines and spirits menu issued by United Airlines; gray and dark red cover.\ra. menu number: 8 PACIFIC 2001-3; class: Connoisseur (business); date: 292\rb. menu number: 8 PACIFIC 2001-3; class: Connoisseur (business); date: 292",
    "sfomuseum:dimensions": "8 1/2 x 5 1/2 inches (21.6 x 14 cm)",
    "sfomuseum:media_ids": [
      1527843911,
      1527853597
    ],
    "sfomuseum:medium": "paper, ink",
    "sfomuseum:placetype": "object",
    "sfomuseum:publication": ": , 1992.",
    "sfomuseum:subcategory": "Menu",
    "wof:depicts": [
      1159285413
    ],
    "wof:name": "menu: United Airlines, Connoisseur (Business) Class",
    "wof:placetype": "venue"
  },
  "geometry": {"coordinates":[-122.386155,37.616357],"type":"Point"}
}
