{
  "type": "Feature",
  "properties": {
    "date:cessation_lower": "1960-12-31",
    "date:cessation_upper": "1960-12-31",
    "date:inception_lower": "1950-01-01",
    "date:inception_upper": "1950-01-01",
    "iso:country": "XX",
    "sfomuseum:accession_number": "2011.061.0657",
    "sfomuseum:category": "Promotional",
    "sfomuseum:collection": "Aviation Archive",
    "sfomuseum:creditline": "Gift of the Frank J. Lichtanski Collection",
    "sfomuseum:date": "c. 1955",
    "sfomuseum:daterange_end": "1960-12-31",
    "sfomuseum:daterange_start": "1950-01-01",
    "sfomuseum:description": "Luggage label promoting Avianca Airlines; oval shape, white, yellow, blue, and red striped background with illustration of Douglas DC-6 in flight followed by text,, “Aerovias Nacionales de Colombia / Avianca / La Empresa de Aviacion Mas Antigua de America.”",
    "sfomuseum:media_ids": [
      1527819275
    ],
    "sfomuseum:medium": "paper, ink",
    "sfomuseum:placetype": "object",
    "sfomuseum:subcategory": "Luggage Label",
    "wof:name": "luggage label: Avianca Airlines",
    "wof:placetype": "venue"
  },
  "geometry": {"coordinates":[-122.386155,37.616358],"type":"Point"}
}
