{
  "type": "Feature",
  "properties": {
    "date:cessation_lower": "1955-01-01",
    "date:cessation_upper": "1955-12-31",
    "date:inception_lower": "1955-01-01",
    "date:inception_upper": "1955-12-31",
    "iso:country": "XX",
    "millsfield:images": [
      1527819275
    ],
    "millsfield:primary_image": 1527819275,
    "sfomuseum:accession_number": "2011.061.0657",
    "sfomuseum:airline": "Avianca Airlines",
    "sfomuseum:category": "Promotional",
    "sfomuseum:collection": "Aviation Archive",
    "sfomuseum:creditline": "Gift of the Frank J. Lichtanski Collection",
    "sfomuseum:date": "c. 1955",
    "sfomuseum:date_acquired": "2011-08-02",
    "sfomuseum:daterange_end": "1960-12-31",
    "sfomuseum:daterange_start": "1950-01-01",
    "sfomuseum:description": "Luggage label promoting Avianca Airlines; oval shape, white, yellow, blue, and red striped background with illustration of aircraft in flight followed by text, “Aerovias Nacionales de Colombia / Avianca / La Empresa de Aviacion Mas Antigua de America.”",
    "sfomuseum:dimensions": "3 x 4 inches (7.6 x 10.2 cm)",
    "sfomuseum:media_ids": [
      1527819275
    ],
    "sfomuseum:medium": "paper, ink, adhesive",
    "sfomuseum:placetype": "object",
    "sfomuseum:publication": ": , c. 1955.",
    "sfomuseum:subcategory": "Luggage Label",
    "wof:depicts": [
      1159283957,
      1159290427,
      1159287217
    ],
    "wof:name": "luggage label: Avianca Airlines",
    "wof:placetype": "custom",
    "wof:placetype_alt": "object"
  },
  "geometry": {"coordinates":[-122.386155,37.616357],"type":"Point"}
}
