{
  "type": "Feature",
  "properties": {
    "date:cessation_lower": "2012-01-01",
    "date:cessation_upper": "2012-12-31",
    "date:inception_lower": "2012-01-01",
    "date:inception_upper": "2012-12-31",
    "isbn:number": "9781610804455 (lib. bdg.),1610804457 (lib. bdg.), 9781610805322 (e-book),1610805321 (e-book), 9781610806190 (pbk.),1610806190 (pbk.)",
    "iso:country": "XX",
    "sfomuseum:accession_number": "2013.032.008",
    "sfomuseum:author": "Gregory, Josh",
    "sfomuseum:callnumber": "UG1423 .G74 2012",
    "sfomuseum:category": "Book",
    "sfomuseum:collection": "Aviation Library",
    "sfomuseum:creditline": "Collection of SFO Museum",
    "sfomuseum:date": "2012",
    "sfomuseum:date_acquired": "2013-03-07",
    "sfomuseum:daterange_end": "2012-12-31",
    "sfomuseum:daterange_start": "2012-01-01",
    "sfomuseum:description": "32 p. : col. ill. ; 25 cm.",
    "sfomuseum:description_library": "32 p. : col. ill. ; 25 cm.",
    "sfomuseum:medium": "paper, ink",
    "sfomuseum:placetype": "object",
    "sfomuseum:publication": "Ann Arbor, MI: Cherry Lake Pub., 2012.",
    "sfomuseum:publisher": "Cherry Lake Pub.",
    "sfomuseum:publisher_location": "Ann Arbor, MI",
    "sfomuseum:subcategory": "Book",
    "sfomuseum:subject": "United States. Air Force -- Aviation electronics technicians -- Juvenile literature.\rUnited States. Navy -- Aviation electronics technicians -- Juvenile literature.\rUnited States -- Armed Forces -- Vocational guidance -- Juvenile literature. ",
    "wof:name": "Avionics technician",
    "wof:placetype": "custom",
    "wof:placetype_alt": [
      "object"
    ]
  },
  "geometry": {"coordinates":[-122.386155,37.616357],"type":"Point"}
}
