{
  "type": "Feature",
  "properties": {
    "date:cessation_lower": "1984-12-31",
    "date:cessation_upper": "1984-12-31",
    "date:inception_lower": "1984-01-01",
    "date:inception_upper": "1984-01-01",
    "iso:country": "XX",
    "sfomuseum:accession_number": "2003.105.109.004",
    "sfomuseum:category": "Scheduling / Ticketing",
    "sfomuseum:collection": "Aviation Archive",
    "sfomuseum:creditline": "Gift of Craig Lynes",
    "sfomuseum:date": "1984",
    "sfomuseum:daterange_end": "1984-12-31",
    "sfomuseum:daterange_start": "1984-01-01",
    "sfomuseum:description": "Timetable issued by United Airlines, effective June 1, 1984; 288-page schedule; white cover with a full color photographic image of palm trees and a rose with text, “Los Angeles, site of the 1984 Summer Olympics”; servicemark at top.",
    "sfomuseum:media_ids": [
      1527839531
    ],
    "sfomuseum:medium": "paper, ink",
    "sfomuseum:placetype": "object",
    "sfomuseum:subcategory": "Timetable",
    "wof:name": "timetable: United Airlines",
    "wof:placetype": "venue"
  },
  "geometry": {"coordinates":[-122.386155,37.616358],"type":"Point"}
}
