{
  "type": "Feature",
  "properties": {
    "date:cessation_lower": "1984-01-01",
    "date:cessation_upper": "1984-12-31",
    "date:inception_lower": "1984-01-01",
    "date:inception_upper": "1984-12-31",
    "iso:country": "XX",
    "millsfield:images": [
      1527839531
    ],
    "millsfield:images_texts": [
      "UNITED AIRLINES\nOur Friendly Times\nJune 1, 1984\nVol. 4\nSALINE OF THE 1984 OUN\nUnITED AIRLInES\nGAMES\n© 1980 L.A. Olympic Committee\nLos Angeles, site of the 1984 Summer Olympics"
    ],
    "millsfield:images_texts_ids": [
      1527839531
    ],
    "millsfield:primary_image": 1527839531,
    "sfomuseum:accession_number": "2003.105.109.004",
    "sfomuseum:airline": "United Airlines",
    "sfomuseum:category": "Scheduling / Ticketing",
    "sfomuseum:collection": "Aviation Archive",
    "sfomuseum:creditline": "Gift of Craig Lynes",
    "sfomuseum:date": "1984",
    "sfomuseum:date_acquired": "2003-12-29",
    "sfomuseum:daterange_end": "1984-12-31",
    "sfomuseum:daterange_start": "1984-01-01",
    "sfomuseum:description": "Timetable issued by United Airlines, effective June 1, 1984; 288-page booklet; white cover with color photographic image of palm trees and rose; includes symbol identifying United’s role as the official airline of the 1984 Summer Olympic Games in Los Angeles.",
    "sfomuseum:dimensions": "9 x 4 inches (22.9 x 10.2 cm)",
    "sfomuseum:media_ids": [
      1527839531
    ],
    "sfomuseum:medium": "paper, ink",
    "sfomuseum:placetype": "object",
    "sfomuseum:publication": ": , 1984.",
    "sfomuseum:subcategory": "Timetable",
    "wof:depicts": [
      1159285413,
      1159288779
    ],
    "wof:name": "timetable: United Airlines",
    "wof:placetype": "custom",
    "wof:placetype_alt": "object"
  },
  "geometry": {"coordinates":[-122.386155,37.616357],"type":"Point"}
}
