{
  "type": "Feature",
  "properties": {
    "date:cessation_lower": "1978-01-01",
    "date:cessation_upper": "1978-12-31",
    "date:inception_lower": "1978-01-01",
    "date:inception_upper": "1978-12-31",
    "iso:country": "XX",
    "millsfield:images": [
      1527837767
    ],
    "millsfield:images_texts": [
      "Lv. New York (JFK)\nAr. Detroit\nLv. Detroit\nLy Chicago (O'Hare)\nAr Mpls./St. Paul\nLv Mpls./St. Paul\nAr Billings\nLv Billings\nAr Seattle/Tacoma\nNORTHWEST ORIENT\nTIMETABLE\nSchedule effective June 26, 1978\nFor the duration of the strike by the\nNorthwest pilots' union these flights will be\noperated on a regular basis\nFIt.\n415\nEX. SU.\nFIt.\n125\nDAILY\nFit.\n729\nDAILY\nEX. SA.\nFIt.\n707\nWE. TH. FR.\nSU. ONLY\nFIt.\n445\nEX. SA.\n8:00am B\n9:04am\n2:15pm\n3:21 pm\n4:10pm\n5:16pm\n6:00pm S\n7:07pm\nFIt.\n221\nDAILY\n7:30pm D\n9:15pm\n10:00pm\n10:27pm\nFIt.\n180\nEX. SU.\n12:30pm S\n1:34pm\n2:30pm\n3:27 pm\n4:15pm D\n4:58pm\nFit.\n440\nDAILY\nEX. SU.\nFIt.\n220\nDAILY\nFIt.\n716\nWE. TH. FR.\nSU. ONLY\nFit.\n184\nEX. SA.\nLy Seattle/Tacoma\nAr Billings\nLv Billings\nAr Mpis./St. Paul\nLy Mpls./St. Paul\nAr Chicago (O'Hare)\nAr Detroit\nLy Detroit\nAr New York (JFK)\nFit.\n458\nDAILY\n10:35am L\n1:07pm\n1:50pm\n4:32pm\n5:30pm S\n6:34pm\n8:00am B\n9:06am\n11:25am S\n12:15pm L\n12:31 pm\n2:15 pm\n3:20pm\n4:00pm\n5:06pm\n2:38pm\n3:20pm\n4:52pm\nLEGEND:\nB-Breakfast\nS-Snack\nL-Lunch\nD-Dinner\nCertain flights will not operate during holiday periods.\nConsult Northwest for details.\nAll flights on 747 aircraft.\nFOR RESERVATIONS:\nCALL YOUR TRAVEL AGENT OR NORTHWEST.\nCall Northwest Airlines for information about bus service\nbetween Rochester, Minnesota and the Minneapolis/St. Paul\nInternational Airport."
    ],
    "millsfield:images_texts_ids": [
      1527837767
    ],
    "millsfield:primary_image": 1527837767,
    "sfomuseum:accession_number": "2011.126.024.010",
    "sfomuseum:airline": "Northwest Airlines",
    "sfomuseum:category": "Scheduling / Ticketing",
    "sfomuseum:collection": "Aviation Archive",
    "sfomuseum:creditline": "Gift of the Paul H. Kowalewski Collection",
    "sfomuseum:date": "1978",
    "sfomuseum:date_acquired": "2011-12-22",
    "sfomuseum:daterange_end": "1978-12-31",
    "sfomuseum:daterange_start": "1978-01-01",
    "sfomuseum:description": "Timetable issued by Northwest Orient (Northwest Airlines), effective June 26, 1978; single sheet; white and blue cover with schedule tables.",
    "sfomuseum:dimensions": "9 x 4 inches (22.9 x 10.2 cm)",
    "sfomuseum:media_ids": [
      1527837767
    ],
    "sfomuseum:medium": "paper, ink",
    "sfomuseum:placetype": "object",
    "sfomuseum:publication": ": , 1978.",
    "sfomuseum:subcategory": "Timetable",
    "wof:depicts": [
      1159287407,
      1159284907,
      1159284913
    ],
    "wof:name": "timetable: Northwest Orient, strike schedule",
    "wof:placetype": "custom",
    "wof:placetype_alt": [
      "object"
    ]
  },
  "geometry": {"coordinates":[-122.386155,37.616357],"type":"Point"}
}
