{
  "type": "Feature",
  "properties": {
    "date:cessation_lower": "1978-01-01",
    "date:cessation_upper": "1978-12-31",
    "date:inception_lower": "1978-01-01",
    "date:inception_upper": "1978-12-31",
    "iso:country": "XX",
    "millsfield:images": [
      1527837767
    ],
    "millsfield:images_texts": [
      "NORTHWEST ORIENT\nTIMETABLE\nSchedule effective June 26, 1978\nFor the duration of the strike by the\nNorthwest pilots' union these flights will be\noperarecronrareouracoasis\n125\n729\n707\nWE. TH. FE\nFit.\n445\n221\n7:30pm D\n9-1 Sam\nSAMOSSAFTE\n9:04am\nAr Seattle/Tacom»\n12:300m S\n2:30pm\n3:27pm\nso som\nFIt.\n2:15pm\n3:21pm\n4:10pm\n5:160m\n6:00pm S\n7:07pm\n10.27pm\nFIt.\n180\nFY SI\n#8]\nLy Seattle/Tacoma\nTARTSITIOS\nFIt.\n458\nDAILY\n10.35am L\n1:07pm\nAr Chicano tO Hare\n8:003m B11:253m S 12:15cm\n2:15 or\n9:06аг\n12:310\n3:20оп\n2.38cm\n320om\n4:52pm\nShack\neat in fronts win moscowarassauraneronesy\nAllliants on ran aircraft\n4:00pm\n5:06pm\n5.30pm S\nFOR RESERVATIONS:\nCALL YOUR TRAVEL AGENT OR NORTHWEST\nal podones telninos тортоста тол дрото орого\nbetweeo Rochester. Minnesota and the MinneapolisiSt. Pau"
    ],
    "millsfield:images_texts_ids": [
      1527837767
    ],
    "millsfield:primary_image": 1527837767,
    "sfomuseum:accession_number": "2011.126.024.010",
    "sfomuseum:airline": "Northwest Airlines",
    "sfomuseum:category": "Scheduling / Ticketing",
    "sfomuseum:collection": "Aviation Archive",
    "sfomuseum:creditline": "Gift of the Paul H. Kowalewski Collection",
    "sfomuseum:date": "1978",
    "sfomuseum:date_acquired": "2011-12-22",
    "sfomuseum:daterange_end": "1978-12-31",
    "sfomuseum:daterange_start": "1978-01-01",
    "sfomuseum:description": "Timetable issued by Northwest Orient Airlines, effective June 26, 1978; single sheet; white and blue cover with schedule tables.",
    "sfomuseum:dimensions": "9 x 4 inches (22.9 x 10.2 cm)",
    "sfomuseum:media_ids": [
      1527837767
    ],
    "sfomuseum:medium": "paper, ink",
    "sfomuseum:placetype": "object",
    "sfomuseum:publication": ": , 1978.",
    "sfomuseum:subcategory": "Timetable",
    "wof:depicts": [
      1159284907,
      1159284913,
      1159287407
    ],
    "wof:name": "timetable: Northwest Orient Airlines, strike schedule",
    "wof:placetype": "custom",
    "wof:placetype_alt": "object"
  },
  "geometry": {"coordinates":[-122.386155,37.616357],"type":"Point"}
}
