{
  "type": "Feature",
  "properties": {
    "date:cessation_lower": "2006-01-01",
    "date:cessation_upper": "2006-12-31",
    "date:inception_lower": "2006-01-01",
    "date:inception_upper": "2006-12-31",
    "iso:country": "XX",
    "millsfield:images": [
      1527845063,
      1527845315
    ],
    "millsfield:primary_image": 1527845063,
    "sfomuseum:accession_number": "2007.086.060",
    "sfomuseum:airline": "Finnair",
    "sfomuseum:category": "Passenger Amenity, Archive",
    "sfomuseum:collection": "Aviation Archive",
    "sfomuseum:creditline": "Gift of Ian H. Dally of Auckland, New Zealand",
    "sfomuseum:date": "2006",
    "sfomuseum:date_acquired": "2009-08-08",
    "sfomuseum:daterange_end": "2006-12-31",
    "sfomuseum:daterange_start": "2006-01-01",
    "sfomuseum:description": "Wine list issued by Finnair; blue and white cover with illustration of a champagne flute; menu number: WL/603; class: business; undated.",
    "sfomuseum:dimensions": "12 1/4 x 7 inches (31.1 x 17.8 cm)",
    "sfomuseum:media_ids": [
      1527845063,
      1527845315
    ],
    "sfomuseum:medium": "paper, ink, metal",
    "sfomuseum:placetype": "object",
    "sfomuseum:publication": ": , 2006.",
    "sfomuseum:subcategory": "Menu",
    "wof:depicts": [
      1159284389,
      1159287841
    ],
    "wof:name": "menu: Finnair, Business Class",
    "wof:placetype": "custom",
    "wof:placetype_alt": "object"
  },
  "geometry": {"coordinates":[-122.386155,37.616357],"type":"Point"}
}
