{
  "type": "Feature",
  "properties": {
    "date:cessation_lower": "2006-01-01",
    "date:cessation_upper": "2006-12-31",
    "date:inception_lower": "2006-01-01",
    "date:inception_upper": "2006-12-31",
    "iso:country": "XX",
    "millsfield:images": [
      1527845063,
      1527845315
    ],
    "millsfield:images_texts": [
      "wines",
      "19991Joseph Perrier Cuvée Royale Brut Vintage####\n1999###Joseph Perrier Cuvée Royale Brut VintageS#M#W##105Grand Cru##deeJa\n(Chardonnay) . #B20 (Pinot Noir) 70X706KI (Pinot Meunier) =#400/4FD) 105R0\nSUNNAN, HANDE SANENANONNARNER, 08N286, 8920.\n2003 Chablis Premier Cru Les VaucopinsE 11#2\n## Albert BichottUE\n2003#JChablis Premier Cru Les Vaucopins#5@100%WEWMAN, DEMN, A78\n2003 Riesling Zöbinger Heiligenstein 1 #25\n2003#8 Riesling Zöbinger HeiligensteiN 000 A\n##8.\n20021Osoyoos Larose/TAi 15\n2001#Grandarella Apassimento IGT7075\nGrandarella Apassiment1084, NON, 2 HEW, MA0#00, 0Е\n2000 Château Guiraud Et\n###ElSauternest#Premier Cru Classé#E\n2000#892 Chateau Guiraud Premier CuR#STA WAW, ANOM ERNENG\n1#720#Nipoor###ENHE\nNiepoort (Vinhos) S.A.ZAN#J\n19991FJoseph Perrier Cuvée Royale Brut VintageF##\nFORTSAX\n1999478 Joseph Perrier Cuvée Royale Brut VintageE#MW###Grand CruMEN\n2003 Chablis Premier Cru Les Vaucopins 11 #2\nFOLEAlbert BichotitX\n2003#9Chablis Premier Cru Les Vaucopins##@100% WWWOANN, WOOD, ANI\n2003 Riesling Zöbinger HeiligensteinE 11075\n20034 Riesling Zobinger HeiligenteiGNES 35A 00 Dom\n20021Osoyoos Larose 1105\n2001EGrandarella Apassimento IGT 11825\nFORt#|VenetotUX#JMasi#E\nGrandarella Apassiment#0008TR, UNON, 2 REN#8, #ArOTOMON, 6R\n2000 #Château Guiraud 31725\n####SauternesttPremier Cru Classe1506\n2000780Z #Château Guiraud Premier CuRIX4, 5ТШ#, A50 RaNG\n##720#Niepoor##*ENH\nNienoort (Vinhos) SA 4a59#||\n20#Nepor™#**#5060Ф, ААХОЕТ80*, О8ФН, 8HWRON, А"
    ],
    "millsfield:images_texts_ids": [
      1527845063,
      1527845315
    ],
    "millsfield:primary_image": 1527845063,
    "sfomuseum:accession_number": "2007.086.060",
    "sfomuseum:airline": "Finnair",
    "sfomuseum:category": "Passenger Amenity, Archive",
    "sfomuseum:collection": "Aviation Archive",
    "sfomuseum:creditline": "Gift of Ian H. Dally of Auckland, New Zealand",
    "sfomuseum:date": "2006",
    "sfomuseum:date_acquired": "2009-08-08",
    "sfomuseum:daterange_end": "2006-12-31",
    "sfomuseum:daterange_start": "2006-01-01",
    "sfomuseum:description": "Wine list issued by Finnair; blue and white cover with illustration of a champagne flute; menu number: WL/603; class: business; undated.",
    "sfomuseum:dimensions": "12 1/4 x 7 inches (31.1 x 17.8 cm)",
    "sfomuseum:media_ids": [
      1527845063,
      1527845315
    ],
    "sfomuseum:medium": "paper, ink, metal",
    "sfomuseum:placetype": "object",
    "sfomuseum:publication": ": , 2006.",
    "sfomuseum:subcategory": "Menu",
    "wof:depicts": [
      1159284389,
      1159287841
    ],
    "wof:name": "menu: Finnair, Business Class",
    "wof:placetype": "custom",
    "wof:placetype_alt": "object"
  },
  "geometry": {"coordinates":[-122.386155,37.616357],"type":"Point"}
}
