{
  "type": "Feature",
  "properties": {
    "date:cessation_lower": "2006-01-01",
    "date:cessation_upper": "2006-12-31",
    "date:inception_lower": "2006-01-01",
    "date:inception_upper": "2006-12-31",
    "iso:country": "XX",
    "millsfield:images": [
      1527845063,
      1527845315
    ],
    "millsfield:images_texts": [
      "wines",
      "1999 Joseph Perrier Cuvée Royale Brut VintagellE8\nпаланка\n19994 ME8SJoseph Perrier Curée Rovale Brut Vintago 75-88/0iL IR 4594K-El Grand Cruit/09e3e381\n(Chardonnay). NIBIELIB (Pinot Noir) KOIR@ISEB238HI (Phot Meurier) ENLACE4 FFOLEAVI\nMOMAto. 1001033. 48018325864. 061953.0920,\n2003 Chablis Premier Cru Les Vaucopins Et al/7\nMESIAbert Bichoticad\n200096Chablis Premier Cru Les VaucopirsC19839#100% JEROREMANS. DAMA. MER\n2003 \u0026 Riesling Zöbinger Heiligenstein B N 447\n2003466 Riesling Zobinger HeilgensteinER249 23 85 94180035 75. FAStIaS/OMANOBLeSSEUR. DIGA115\n2002Osoyoos LaroselIA4.2\n20018Grandarella ApossimentoIGT@N@7\n2000 #Château Guiraud I2\nRABO. NORACHIBINAIR. 8620R, C04091, MAIRESSE, ILAGOSHMIEROUAI: 2005 # % 2008 #,\nNaccor Minhos) SAoMA\n1999 Joseph Perrier Cuvée Royale Brut Vintago F-1\n188947°8SJoseph Perrier Cuvée Royale Brut Vientago05 630/B08.0505(507608 Grand Crus*8983 63.35918\n(Chardonnay). IIBR87 (Pinot Noir) KOIR 3315 R8207EXI (Pinot Meunier) EKAMON4FCLE B$78\nMOSSAS. AFR36, ETOMBA ANOS 23A0X62. D012873. 0920.\n2003 Chablis Premier Cru Les Vaucopins E 1187\nPOSESAbert Bichotiel?\n200395Chabls Premier Cru Les Vaucopins B ME#100% 978 A EN 10951095. 55101700, 443113\n2003 # Riesling Zöbinger Helligenstein B Mai\nE. EPOSAPRIMBIS RU. AMENS8KEN. BA. ORSRE. BUSKINKNESS\n2002#0soyoos LarosefT1 17\n20018 Grandarella Apassimento IGTE N6 49%\nP'BBtAVenetot3C806MasidE\n2000 #Château Guiraud 88 %\n200048522.3C-lteau Guiraud Premier Cru/fR7L50/80CM 7501J9. 788675817. 141135750658225, 259RKO06180S\n* 41520 # Niepoont##Ж881%"
    ],
    "millsfield:images_texts_ids": [
      1527845063,
      1527845315
    ],
    "millsfield:primary_image": 1527845063,
    "sfomuseum:accession_number": "2007.086.060",
    "sfomuseum:airline": "Finnair",
    "sfomuseum:category": "Passenger Amenity, Archive",
    "sfomuseum:collection": "Aviation Archive",
    "sfomuseum:creditline": "Gift of Ian H. Dally of Auckland, New Zealand",
    "sfomuseum:date": "2006",
    "sfomuseum:date_acquired": "2009-08-08",
    "sfomuseum:daterange_end": "2006-12-31",
    "sfomuseum:daterange_start": "2006-01-01",
    "sfomuseum:description": "Wine list issued by Finnair; blue and white cover with illustration of a champagne flute; menu number: WL/603; class: business; undated.",
    "sfomuseum:dimensions": "12 1/4 x 7 inches (31.1 x 17.8 cm)",
    "sfomuseum:media_ids": [
      1527845063,
      1527845315
    ],
    "sfomuseum:medium": "paper, ink, metal",
    "sfomuseum:placetype": "object",
    "sfomuseum:publication": ": , 2006.",
    "sfomuseum:subcategory": "Menu",
    "wof:depicts": [
      1159284389,
      1159287841
    ],
    "wof:name": "menu: Finnair, Business Class",
    "wof:placetype": "custom",
    "wof:placetype_alt": "object"
  },
  "geometry": {"coordinates":[-122.386155,37.616357],"type":"Point"}
}
