{
  "type": "Feature",
  "properties": {
    "date:cessation_lower": "1998-01-01",
    "date:cessation_upper": "1998-12-31",
    "date:inception_lower": "1997-01-01",
    "date:inception_upper": "1997-12-31",
    "iso:country": "XX",
    "sfomuseum:accession_number": "99-0728",
    "sfomuseum:author": "R.R. Bowker Company",
    "sfomuseum:callnumber": "N50 .A54 1997-98",
    "sfomuseum:category": "Book",
    "sfomuseum:collection": "Aviation Library",
    "sfomuseum:date": "1997-1998",
    "sfomuseum:daterange_end": "1998-12-31",
    "sfomuseum:daterange_start": "1997-01-01",
    "sfomuseum:description": "v. ill., ports. 23-28 cm.",
    "sfomuseum:description_library": "v. ill., ports. 23-28 cm.",
    "sfomuseum:medium": "paper, ink",
    "sfomuseum:placetype": "object",
    "sfomuseum:publication": "New York: Jaques Cattell Press, 1997-1998.",
    "sfomuseum:publisher": "Jaques Cattell Press",
    "sfomuseum:publisher_location": "New York",
    "sfomuseum:subcategory": "Book",
    "sfomuseum:subject": "Artists Directories.Art Latin America Directories.Art Canada Directories.Art United States Directories.",
    "wof:name": "American art directory",
    "wof:placetype": "venue"
  },
  "geometry": {"coordinates":[-122.386155,37.616357],"type":"Point"}
}
