{
  "type": "Feature",
  "properties": {
    "date:cessation_lower":"1997-12-31",
    "date:cessation_upper":"1997-12-31",
    "date:inception_lower":"1997-01-01",
    "date:inception_upper":"1997-01-01",
    "iso:country":"XX",
    "millsfield:images":[
        1527849101
    ],
    "sfomuseum:accession_number":"2001.057.069",
    "sfomuseum:category":"Company Record / Document",
    "sfomuseum:collection":"Aviation Archive",
    "sfomuseum:creditline":"Transfer",
    "sfomuseum:date":"1997",
    "sfomuseum:daterange_end":"1997-12-31",
    "sfomuseum:daterange_start":"1997-01-01",
    "sfomuseum:description":"Annual report produced by San Francisco International Airport (SFO), 1997; 34 p.",
    "sfomuseum:media_ids":[
        1527849101
    ],
    "sfomuseum:medium":"paper, ink",
    "sfomuseum:placetype":"object",
    "sfomuseum:subcategory":"Annual Report",
    "wof:depicts":[
        102527513
    ],
    "wof:name":"annual report: San Francisco International Airport (SFO), 1997 [1 issue: 1997]",
    "wof:placetype":"venue"
},
  "geometry": {"coordinates":[-122.386155,37.616358],"type":"Point"}
}