{
  "type": "Feature",
  "properties": {
    "date:cessation_lower": "1928-01-01",
    "date:cessation_upper": "1928-12-31",
    "date:inception_lower": "1928-01-01",
    "date:inception_upper": "1928-12-31",
    "iso:country": "XX",
    "millsfield:images": [
      1527828697,
      1527828699
    ],
    "millsfield:primary_image": 1527828697,
    "sfomuseum:accession_number": "2007.036.002",
    "sfomuseum:airport": "Mills Field Municipal Airport of San Francisco",
    "sfomuseum:category": "Philately",
    "sfomuseum:collection": "Aviation Archive",
    "sfomuseum:creditline": "Purchase",
    "sfomuseum:date": "1928",
    "sfomuseum:daterange_end": "1928-12-31",
    "sfomuseum:daterange_start": "1928-01-01",
    "sfomuseum:description": "Silver certificate displaying printed signature of United States Secretary of the Treasury Ogden Livingston Mills, of Mills Estate Incorporated.",
    "sfomuseum:dimensions": "2 1/2 x 6 1/4 inches (6.4 x 15.9 cm)",
    "sfomuseum:media_ids": [
      1527828697,
      1527828699
    ],
    "sfomuseum:medium": "paper, ink",
    "sfomuseum:placetype": "object",
    "sfomuseum:subcategory": "Other, Philately",
    "wof:depicts": [
      1360695653
    ],
    "wof:name": "currency: United States one-dollar bill, Ogden Livingston Mills",
    "wof:placetype": "venue"
  },
  "geometry": {"coordinates":[-122.386155,37.616357],"type":"Point"}
}
