{
  "type": "Feature",
  "properties": {
    "date:cessation_lower": "1940-07-23",
    "date:cessation_upper": "1940-07-23",
    "date:inception_lower": "1940-07-23",
    "date:inception_upper": "1940-07-23",
    "iso:country": "XX",
    "millsfield:images": [
      1527830211,
      1527830213
    ],
    "millsfield:primary_image": 1527830211,
    "sfomuseum:accession_number": "2010.266.003",
    "sfomuseum:airline": "Pan American Airways",
    "sfomuseum:category": "Philately",
    "sfomuseum:collection": "Aviation Archive",
    "sfomuseum:creditline": "Gift of Louis A. Turpen",
    "sfomuseum:date": "07/23/1940",
    "sfomuseum:date_acquired": "2011-05-25",
    "sfomuseum:daterange_end": "1940-07-23",
    "sfomuseum:daterange_start": "1940-07-23",
    "sfomuseum:description": "Airmail flight cover, FAM-19, first Pan American Airways flight, Honolulu - Los Angeles route; part of first airmail service between United States and New Zealand; purple cachet “U.S. Air Mail / South Pacific Service” stamped at left with illustration of Pacific route map; two 10-cent postage stamps; postmarked July 23, 1940 in Honolulu with four-line cancellation mark over two 10-cent stamps; striped ticker across footer, “United States, Honolulu, Canton Island, Noumea, New Zealand”; backstamp: July 24, 1940 in Los Angeles; no addressee.",
    "sfomuseum:dimensions": "3 3/4 x 6 1/2 inches (9.5 x 16.5 cm)",
    "sfomuseum:media_ids": [
      1527830213,
      1527830211
    ],
    "sfomuseum:medium": "paper, ink",
    "sfomuseum:placetype": "object",
    "sfomuseum:publication": ": , 07/23/1940.",
    "sfomuseum:subcategory": "Airmail Flight Cover",
    "wof:depicts": [
      1159284991
    ],
    "wof:name": "airmail flight cover: United States Air Mail, FAM-19, first airmail flight, Honolulu - Los Angeles route",
    "wof:placetype": "venue"
  },
  "geometry": {"coordinates":[-122.386155,37.616357],"type":"Point"}
}
