{
  "type": "Feature",
  "properties": {
    "date:cessation_lower":"1940-12-31",
    "date:cessation_upper":"1940-12-31",
    "date:inception_lower":"1940-01-01",
    "date:inception_upper":"1940-01-01",
    "iso:country":"XX",
    "millsfield:images":[
        1527830211,
        1527830213
    ],
    "sfomuseum:accession_number":"2010.266.003",
    "sfomuseum:category":"Philately",
    "sfomuseum:collection":"Aviation Archive",
    "sfomuseum:creditline":"Gift of Louis A. Turpen",
    "sfomuseum:date":"07/23/1940",
    "sfomuseum:daterange_end":"1940-07-23",
    "sfomuseum:daterange_start":"1940-07-23",
    "sfomuseum:description":"Airmail flight cover, FAM-19, first Pan American Airways flight, Honolulu - Los Angeles route; part of first airmail service between United States and New Zealand; purple cachet \u201cU.S. Air Mail / South Pacific Service\u201d stamped at left with illustration of Pacific route map; two 10-cent postage stamps; postmarked July 23, 1940 in Honolulu with four-line cancellation mark over two 10-cent stamps; striped ticker across footer, \u201cUnited States, Honolulu, Canton Island, Noumea, New Zealand\u201d; backstamp: July 24, 1940 in Los Angeles; no addressee.",
    "sfomuseum:media_ids":[
        1527830213,
        1527830211
    ],
    "sfomuseum:medium":"paper, ink",
    "sfomuseum:placetype":"object",
    "sfomuseum:subcategory":"Airmail Flight Cover",
    "wof:name":"airmail flight cover: United States Air Mail, FAM-19, first airmail flight, Honolulu - Los Angeles route",
    "wof:placetype":"venue"
},
  "geometry": {"coordinates":[-122.386155,37.616358],"type":"Point"}
}