{
  "type": "Feature",
  "properties": {
    "date:cessation_lower": "1939-01-01",
    "date:cessation_upper": "1939-12-31",
    "date:inception_lower": "1939-01-01",
    "date:inception_upper": "1939-12-31",
    "iso:country": "XX",
    "millsfield:images": [
      1527821759
    ],
    "millsfield:primary_image": 1527821759,
    "sfomuseum:accession_number": "2008.056.0407",
    "sfomuseum:category": "Promotional",
    "sfomuseum:collection": "Aviation Archive",
    "sfomuseum:creditline": "Gift of Jon E. Krupnick",
    "sfomuseum:date": "1939",
    "sfomuseum:date_acquired": "2008-12-31",
    "sfomuseum:daterange_end": "1939-12-31",
    "sfomuseum:daterange_start": "1939-01-01",
    "sfomuseum:description": "Promotional brochure issued by Northern Pacific Railway for Golden Gate International Exposition,  titled “Treasure Island on San Francisco Bay, Golden Gate International Exposition, February 18 to December 2, 1939”; 22-page booklet; full color illustration on cover depicting Tower of the Sun at night; interior includes description of attractions, maps, and advertisement for Northern Pacific Railway's Northern Pacific Route from Chicago to the Pacific Coast.",
    "sfomuseum:dimensions": "9 x 8 inches (22.9 x 20.3 cm)",
    "sfomuseum:media_ids": [
      1527821759
    ],
    "sfomuseum:medium": "paper, ink",
    "sfomuseum:placetype": "object",
    "sfomuseum:publication": ": Northern Pacific Railway, 1939.",
    "sfomuseum:publisher": "Northern Pacific Railway",
    "sfomuseum:subcategory": "Brochure, Travel",
    "sfomuseum:subject": "Golden Gate International Exposition, 1939 -- Treasure Island\r",
    "wof:name": "tour package brochure: Northern Pacific Railway, Golden Gate International Exposition, Treasure Island",
    "wof:placetype": "venue"
  },
  "geometry": {"coordinates":[-122.386155,37.616357],"type":"Point"}
}
