{
  "type": "Feature",
  "properties": {
    "date:cessation_lower":"1939-12-31",
    "date:cessation_upper":"1939-12-31",
    "date:inception_lower":"1939-01-01",
    "date:inception_upper":"1939-01-01",
    "iso:country":"XX",
    "sfomuseum:accession_number":"2008.056.0407",
    "sfomuseum:category":"Promotional",
    "sfomuseum:collection":"Aviation Archive",
    "sfomuseum:creditline":"Gift of Jon E. Krupnick",
    "sfomuseum:date":"1939",
    "sfomuseum:daterange_end":"1939-12-31",
    "sfomuseum:daterange_start":"1939-01-01",
    "sfomuseum:description":"Promotional brochure for Golden Gate International Exposition, as promoted by Northern Pacific Railway, titled \u201cTreasure Island on San Francisco Bay, Golden Gate International Exposition, February 18 to December 2, 1939\u201d. 22-page brochure with full color illustration on cover depicting Tower of the Sun at night; interior includes description of attractions, maps, and advertisement for Northern Pacific Railway's Northern Pacific Route from Chicago to the Pacific Coast.",
    "sfomuseum:media_ids":[
        1527821759
    ],
    "sfomuseum:medium":"ink, paper",
    "sfomuseum:placetype":"object",
    "sfomuseum:subcategory":"Brochure, Travel",
    "wof:name":"tour package brochure: Northern Pacific Railway, Golden Gate International Exposition, Treasure Island",
    "wof:placetype":"venue"
},
  "geometry": {"coordinates":[-122.386155,37.616358],"type":"Point"}
}