{
  "type": "Feature",
  "properties": {
    "date:cessation_lower": "1937-01-01",
    "date:cessation_upper": "1937-12-31",
    "date:inception_lower": "1937-01-01",
    "date:inception_upper": "1937-12-31",
    "iso:country": "XX",
    "sfomuseum:accession_number": "2000.160.0901",
    "sfomuseum:author": "Richthofen, Kunigunde von Schickfuss",
    "sfomuseum:callnumber": "D604 .R46 1937 SC",
    "sfomuseum:category": "Book",
    "sfomuseum:collection": "Aviation Library",
    "sfomuseum:creditline": "Collection of SFO Museum, The Tony Bill Aviation Library Collection",
    "sfomuseum:date": "c. 1937",
    "sfomuseum:date_acquired": "1999-05-18",
    "sfomuseum:daterange_end": "1942-12-31",
    "sfomuseum:daterange_start": "1932-01-01",
    "sfomuseum:description": "195, [1] p., 1 l. front., illus. (facsim.) plates, ports. 22 cm.",
    "sfomuseum:description_library": "195, [1] p., 1 l. front., illus. (facsim.) plates, ports. 22 cm.",
    "sfomuseum:medium": "paper, ink",
    "sfomuseum:placetype": "object",
    "sfomuseum:publication": "Berlin: Ullstein, c. 1937.",
    "sfomuseum:publisher": "Ullstein",
    "sfomuseum:publisher_location": "Berlin",
    "sfomuseum:subcategory": "Book",
    "sfomuseum:subject": "Richthofen, Manfred, Freiherr von, 1892-1918World War, 1914-1918 Germany.",
    "wof:name": "Mein kriegstagebuch: die erinnerungen der mutter des roten kampffliegers. Mit einem geleitwort von generaloberst GËoring. Mit 43 aufnahmen aus familienbesitz",
    "wof:placetype": "custom",
    "wof:placetype_alt": "object"
  },
  "geometry": {"coordinates":[-122.386155,37.616357],"type":"Point"}
}
