{
  "type": "Feature",
  "properties": {
    "date:cessation_lower": "1962-12-31",
    "date:cessation_upper": "1962-12-31",
    "date:inception_lower": "1962-01-01",
    "date:inception_upper": "1962-01-01",
    "iso:country": "XX",
    "sfomuseum:accession_number": "2008.115.003",
    "sfomuseum:airline": "Pan American World Airways",
    "sfomuseum:category": "Book",
    "sfomuseum:collection": "Aviation Library",
    "sfomuseum:creditline": "Gift of John and Sara Cleary",
    "sfomuseum:date": "1962",
    "sfomuseum:daterange_end": "1962-12-31",
    "sfomuseum:daterange_start": "1962-01-01",
    "sfomuseum:medium": "paper, ink",
    "sfomuseum:placetype": "object",
    "sfomuseum:subcategory": "Book",
    "wof:depicts": [
      1159284989
    ],
    "wof:name": "PAN AM complete reference guide to France",
    "wof:placetype": "custom"
  },
  "geometry": {"coordinates":[-122.386155,37.616357],"type":"Point"}
}
