{
  "type": "Feature",
  "properties": {
    "date:cessation_lower": "2008-01-01",
    "date:cessation_upper": "2008-12-31",
    "date:inception_lower": "2008-01-01",
    "date:inception_upper": "2008-12-31",
    "iso:country": "XX",
    "millsfield:images": [
      1527840593
    ],
    "sfomuseum:accession_number": "2012.030.011",
    "sfomuseum:airline": "United Airlines",
    "sfomuseum:category": "Scheduling / Ticketing",
    "sfomuseum:collection": "Aviation Archive",
    "sfomuseum:creditline": "Gift of Manuel de Alba Perez",
    "sfomuseum:date": "2008",
    "sfomuseum:daterange_end": "2008-12-31",
    "sfomuseum:daterange_start": "2008-01-01",
    "sfomuseum:description": "Timetable issued by United Airlines; beige background with color illustration depicting Tower Bridge, London; folded brochure containing abbreviated flight schedule of service between Denver and London Heathrow with connections to other cities; includes route map.",
    "sfomuseum:dimensions": "8 1/4 x 4 inches (21 x 10.2 cm)",
    "sfomuseum:media_ids": [
      1527840593
    ],
    "sfomuseum:medium": "paper, ink",
    "sfomuseum:placetype": "object",
    "sfomuseum:subcategory": "Timetable",
    "wof:depicts": [
      1159285413
    ],
    "wof:name": "timetable: United Airlines, London Heathrow / Denver",
    "wof:placetype": "venue"
  },
  "geometry": {"coordinates":[-122.386155,37.616357],"type":"Point"}
}
