{
  "type": "Feature",
  "properties": {
    "date:cessation_lower": "1970-01-01",
    "date:cessation_upper": "1979-12-31",
    "date:inception_lower": "1970-01-01",
    "date:inception_upper": "1979-12-31",
    "iso:country": "XX",
    "millsfield:images": [
      1527845669
    ],
    "millsfield:primary_image": 1527845669,
    "sfomuseum:accession_number": "2004.106.124",
    "sfomuseum:airline": "Golden West Airlines",
    "sfomuseum:airport": "John Wayne Airport",
    "sfomuseum:category": "Scheduling / Ticketing",
    "sfomuseum:collection": "Aviation Archive",
    "sfomuseum:creditline": "Gift of the William Hough Collection",
    "sfomuseum:date": "1970s",
    "sfomuseum:date_acquired": "2006-12-05",
    "sfomuseum:daterange_end": "1970-12-31",
    "sfomuseum:daterange_start": "1970-01-01",
    "sfomuseum:description": "Timetable issued by Golden West Airlines, effective June 17, no year given; single sheet with black and white photographic image of a seaplane on water and text, \"Now! Fly direct to Catalina Island from Orange County Airport!\"",
    "sfomuseum:dimensions": "11 x 8 1/2 inches (27.9 x 21.6 cm)",
    "sfomuseum:media_ids": [
      1527845669
    ],
    "sfomuseum:medium": "paper, ink",
    "sfomuseum:placetype": "object",
    "sfomuseum:publication": ": , 1970s.",
    "sfomuseum:subcategory": "Timetable",
    "sfomuseum:subject": "Airlines -- Commuter -- Timetable\r",
    "wof:depicts": [
      102534161,
      1159284453
    ],
    "wof:name": "timetable: Golden West Airlines",
    "wof:placetype": "venue"
  },
  "geometry": {"coordinates":[-122.386155,37.616357],"type":"Point"}
}
