{
  "type": "Feature",
  "properties": {
    "date:cessation_lower": "1970-12-31",
    "date:cessation_upper": "1970-12-31",
    "date:inception_lower": "1970-01-01",
    "date:inception_upper": "1970-01-01",
    "iso:country": "XX",
    "millsfield:images": [
      1527827209
    ],
    "sfomuseum:accession_number": "2011.032.2174",
    "sfomuseum:airport": "San Francisco International Airport",
    "sfomuseum:artist": "Marshall Moxom",
    "sfomuseum:category": "Photograph",
    "sfomuseum:collection": "Aviation Archive",
    "sfomuseum:creditline": "Transfer",
    "sfomuseum:date": "1970",
    "sfomuseum:daterange_end": "1970-12-31",
    "sfomuseum:daterange_start": "1970-01-01",
    "sfomuseum:description": "From attached handwritten note: “03612 / 7-29-70 / Park \u0026 Fly and Terminal Blg \u0026 Roadways / taken by: Moxom”. Black and white photographic negative depicting oblique east-facing aerial view of San Francisco International Airport (SFO); freeway access road and roundabout in foreground; Central Terminal (now Terminal 2 / T2) in background; photo taken by Marshall Moxom on July 29, 1970.",
    "sfomuseum:media_ids": [
      1527827209
    ],
    "sfomuseum:medium": "negative",
    "sfomuseum:placetype": "object",
    "sfomuseum:subcategory": "Negative",
    "wof:depicts": [
      102527513
    ],
    "wof:name": "negative: San Francisco International Airport (SFO), aerial, roundabout",
    "wof:placetype": "venue"
  },
  "geometry": {"coordinates":[-122.386155,37.616357],"type":"Point"}
}
