{
  "type": "Feature",
  "properties": {
    "date:cessation_lower": "1954-01-01",
    "date:cessation_upper": "1954-12-31",
    "date:inception_lower": "1954-01-01",
    "date:inception_upper": "1954-12-31",
    "iso:country": "XX",
    "sfomuseum:accession_number": "2010.227.003",
    "sfomuseum:author": "Fahey, James C. (James Charles)",
    "sfomuseum:callnumber": "VA61 .F3 1941a",
    "sfomuseum:category": "Book",
    "sfomuseum:collection": "Aviation Library",
    "sfomuseum:creditline": "Gift of Frank A. Norick",
    "sfomuseum:date": "c. 1954",
    "sfomuseum:date_acquired": "2011-01-28",
    "sfomuseum:daterange_end": "1959-12-31",
    "sfomuseum:daterange_start": "1949-01-01",
    "sfomuseum:description": "48 p. : ill. ; 24 cm.",
    "sfomuseum:description_library": "48 p. : ill. ; 24 cm.",
    "sfomuseum:edition": "Two-ocean fleet edition",
    "sfomuseum:medium": "paper, ink",
    "sfomuseum:placetype": "object",
    "sfomuseum:publication": "New York, N.Y.: Herald-Nathan Press, c. 1954.",
    "sfomuseum:publisher": "Herald-Nathan Press",
    "sfomuseum:publisher_location": "New York, N.Y.",
    "sfomuseum:subcategory": "Book",
    "sfomuseum:subject": "United States. Navy 20th century.Airplanes, Military United States 20th century.Ships United States 20th century.United States Government vessels 20th century.  Warships -- United States -- Periodicals. \rUnited States. Navy -- Lists of vessels -- Periodicals. \rAirplanes, Military -- United States -- Periodicals.",
    "wof:name": "The ships and aircraft of the United States fleet Two-ocean fleet edition",
    "wof:placetype": "custom",
    "wof:placetype_alt": "object"
  },
  "geometry": {"coordinates":[-122.386155,37.616357],"type":"Point"}
}
