{
  "type": "Feature",
  "properties": {
    "date:cessation_lower":"1934-12-31",
    "date:cessation_upper":"1934-12-31",
    "date:inception_lower":"1934-01-01",
    "date:inception_upper":"1934-01-01",
    "iso:country":"XX",
    "millsfield:images":[
        1527856463,
        1527856465
    ],
    "sfomuseum:accession_number":"2014.156.169",
    "sfomuseum:category":"Philately",
    "sfomuseum:collection":"Aviation Archive",
    "sfomuseum:creditline":"Gift of Captain Jon Simmonds",
    "sfomuseum:date":"10/22/1934",
    "sfomuseum:daterange_end":"1934-10-22",
    "sfomuseum:daterange_start":"1934-10-22",
    "sfomuseum:description":"First airmail flight cover, Lynchburg, Virginia, postmarked October 22, 1934, with one 6-cent postage stamp; black cachet at left with text, \u201cFirst Flight United States Air Mail / Lynchburg, Virginia\u201d; envelope addressed to Virginia Le Count, Woodside, New York.",
    "sfomuseum:media_ids":[
        1527856463,
        1527856465
    ],
    "sfomuseum:medium":"paper, ink",
    "sfomuseum:placetype":"object",
    "sfomuseum:subcategory":"Airmail Flight Cover",
    "wof:name":"airmail flight cover: Lynchburg, Virginia",
    "wof:placetype":"venue"
},
  "geometry": {"coordinates":[-122.386155,37.616358],"type":"Point"}
}