{
  "type": "Feature",
  "properties": {
    "date:cessation_lower":"1968-12-31",
    "date:cessation_upper":"1968-12-31",
    "date:inception_lower":"1968-01-01",
    "date:inception_upper":"1968-01-01",
    "iso:country":"XX",
    "millsfield:images":[
        1527819445
    ],
    "sfomuseum:accession_number":"2011.001.066",
    "sfomuseum:category":"Promotional",
    "sfomuseum:collection":"Aviation Archive",
    "sfomuseum:creditline":"Gift of Robert Behr",
    "sfomuseum:date":"1968",
    "sfomuseum:daterange_end":"1968-12-31",
    "sfomuseum:daterange_start":"1968-01-01",
    "sfomuseum:description":"Single-page color advertisement promoting Air New Zealand, from June 1968 issue of Sunset magazine; main caption, \u201cFly the Flight Fantastic to Tahiti\u201d with illustration depicting mountains, waves, animals, and plants perched atop profile view of aircraft.",
    "sfomuseum:media_ids":[
        1527819445
    ],
    "sfomuseum:medium":"paper, ink",
    "sfomuseum:placetype":"object",
    "sfomuseum:subcategory":"Advertisement, 2D",
    "wof:name":"advertisement: Air New Zealand, Tahiti",
    "wof:placetype":"venue"
},
  "geometry": {"coordinates":[-122.386155,37.616358],"type":"Point"}
}