{
  "type": "Feature",
  "properties": {
    "date:cessation_lower": "1956-01-01",
    "date:cessation_upper": "1956-12-31",
    "date:inception_lower": "1956-01-01",
    "date:inception_upper": "1956-12-31",
    "iso:country": "XX",
    "millsfield:images": [
      1527844523,
      1527844525
    ],
    "millsfield:images_texts": [
      "flight\ninformation\nUn\nUNITED\nAIR LINES\nThe nation's number 1 coast-to-coast airline\ni to a gra\n155226 assal",
      "UNITED\nSYSTEM MAP\nbordersto border, and on to Howoil"
    ],
    "millsfield:images_texts_ids": [
      1527844523,
      1527844525
    ],
    "millsfield:primary_image": 1527844525,
    "sfomuseum:accession_number": "2002.005.021",
    "sfomuseum:airline": "United Air Lines",
    "sfomuseum:category": "Map / Chart",
    "sfomuseum:collection": "Aviation Archive",
    "sfomuseum:creditline": "Gift of John R. Barker",
    "sfomuseum:date": "1956",
    "sfomuseum:date_acquired": "2002-11-13",
    "sfomuseum:daterange_end": "1956-12-31",
    "sfomuseum:daterange_start": "1956-01-01",
    "sfomuseum:description": "Route map issued by United Air Lines for domestic routes, titled “Flight information”; folded format; blue and white cover with blue duotone photographic images of aircraft and destinations; map dated 1956.",
    "sfomuseum:media_ids": [
      1527844523,
      1527844525
    ],
    "sfomuseum:medium": "paper, ink",
    "sfomuseum:placetype": "object",
    "sfomuseum:publication": ": , 1956.",
    "sfomuseum:subcategory": "Route",
    "wof:depicts": [
      1159285415,
      1159288779
    ],
    "wof:name": "route map: United Air Lines",
    "wof:placetype": "custom",
    "wof:placetype_alt": "object"
  },
  "geometry": {"coordinates":[-122.386155,37.616357],"type":"Point"}
}
