{
  "type": "Feature",
  "properties": {
    "date:cessation_lower": "1956-12-31",
    "date:cessation_upper": "1956-12-31",
    "date:inception_lower": "1956-01-01",
    "date:inception_upper": "1956-01-01",
    "iso:country": "XX",
    "sfomuseum:accession_number": "2002.005.021",
    "sfomuseum:category": "Map / Chart",
    "sfomuseum:collection": "Aviation Archive",
    "sfomuseum:creditline": "Gift of John R. Barker",
    "sfomuseum:date": "1956",
    "sfomuseum:daterange_end": "1956-12-31",
    "sfomuseum:daterange_start": "1956-01-01",
    "sfomuseum:description": "Route map produced by United Air Lines for domestic routes, titled “Flight information”; blue and white cover with monotone photographic images of aircraft and destinations; map dated 1956; folded format.",
    "sfomuseum:media_ids": [
      1527844523, 
      1527844525
    ],
    "sfomuseum:medium": "paper, ink",
    "sfomuseum:placetype": "object",
    "sfomuseum:subcategory": "Route",
    "wof:name": "route map: United Air Lines",
    "wof:placetype": "venue"
  },
  "geometry": {"coordinates":[-122.386155,37.616358],"type":"Point"}
}
