{
  "type": "Feature",
  "properties": {
    "date:cessation_lower": "2000-01-01",
    "date:cessation_upper": "2000-12-31",
    "date:inception_lower": "2000-01-01",
    "date:inception_upper": "2000-12-31",
    "iso:country": "XX",
    "millsfield:images": [
      1527838427,
      1527850475
    ],
    "millsfield:images_texts": [
      "SOUTHWEST AIRLINES\nA SYMBOL OF FREEDOM®\nApril 2, 2000 Flight Schedule\nAs Senior Director of Ground\nOperations, I strive to keep things\nrunning smoothly for the\nconvenience of our Customers.",
      "Mountain\nSeattle\nSpokane\nPortland\nBoise\noaklane\nFrancisco\nReno/Tahoe\nSalt Lake City\npal rose\nLas Vegas\n*\nLos Angeles\n(LAX)\norangecounty\nsan Dieec\nPhoenix\nTucson\nAlbuquerque\nEl Paso\nAlbany service starts May 7.\nSouthwest Airlines Ski Vacation States.\nIndianapolis, Phoenix, and Tucson\ndo not observe daylight-saving time.\nLubbock\ncnicago\n(Midway)\nkansas city\nSLOUISE\nTulsa\nLittle Rock\nLove Field)\nSan Antonic\nbetroi\nCleveland\nColumbus\nIndianapolis\nLouisville\nNashville\nBirmingham\nJackson\nNew Orleans\n•* Providence\nHartford/Springfield\nLong ISland/Is.p\nRaleigh-Durham\nJacksonville\nerlando\nTampa\nbay\nFt. Lauderdale\nSouth Padre Island\nHarlingen)\n©2000 Southwest Airlines Co.\nTo receive a flight schedule, mail requests to:\nSouthwest Airlines Schedule List,\nP.O. Box 650331, Dallas, TX 75265-0331.\nCargo Customers mail requests to:\nCargo Customer Schedule List, HDQ/3CM,\nP.O. Box 36611, Dallas, TX 75235-1611.\nAll other correspondence should be sent to:\nSouthwest Airlines Co.,\nP.O. Box 36611, Dallas, TX 75235-1611.\nSOUTHWEST AIRLINES\nA SYMBOL OF FREEDOM\nPrinted on recycled paper."
    ],
    "millsfield:images_texts_ids": [
      1527838427,
      1527850475
    ],
    "millsfield:primary_image": 1527838427,
    "sfomuseum:accession_number": "2003.105.097.017",
    "sfomuseum:airline": "Southwest Airlines",
    "sfomuseum:category": "Scheduling / Ticketing",
    "sfomuseum:collection": "Aviation Archive",
    "sfomuseum:creditline": "Gift of Craig Lynes",
    "sfomuseum:date": "2000",
    "sfomuseum:date_acquired": "2003-12-29",
    "sfomuseum:daterange_end": "2000-12-31",
    "sfomuseum:daterange_start": "2000-01-01",
    "sfomuseum:description": "Timetable issued by Southwest Airlines, effective April 2, 2000; 104-page schedule; black and white photographic image of a senior director of ground operations with quoted text about that role.",
    "sfomuseum:dimensions": "9 x 4 inches (22.9 x 10.2 cm)",
    "sfomuseum:media_ids": [
      1527838427,
      1527850475
    ],
    "sfomuseum:medium": "paper, ink",
    "sfomuseum:placetype": "object",
    "sfomuseum:publication": ": , 2000.",
    "sfomuseum:subcategory": "Timetable",
    "wof:depicts": [
      1159285591,
      1360700737
    ],
    "wof:name": "timetable: Southwest Airlines",
    "wof:placetype": "custom",
    "wof:placetype_alt": "object"
  },
  "geometry": {"coordinates":[-122.386155,37.616357],"type":"Point"}
}
