{
  "type": "Feature",
  "properties": {
    "date:cessation_lower": "1980-01-01",
    "date:cessation_upper": "1989-12-31",
    "date:inception_lower": "1980-01-01",
    "date:inception_upper": "1989-12-31",
    "iso:country": "XX",
    "millsfield:images": [
      1527858435
    ],
    "millsfield:primary_image": 1527858435,
    "sfomuseum:accession_number": "2002.065.004",
    "sfomuseum:airline": "Continental Airlines",
    "sfomuseum:category": "Meal Service",
    "sfomuseum:collection": "Aviation Museum",
    "sfomuseum:creditline": "Gift of Frank A. Norick",
    "sfomuseum:date": "1980s",
    "sfomuseum:date_acquired": "2002-12-24",
    "sfomuseum:daterange_end": "1989-12-31",
    "sfomuseum:daterange_start": "1980-01-01",
    "sfomuseum:description": "Entree dish issued by Continental Airlines for inflight meal service; “Contrails-Red” pattern; white rectangular dish with red logo near top edge; airline and manufacturer logos on bottom.",
    "sfomuseum:dimensions": "1 x 6 x 4 inches (2.5 x 15.2 x 10.2 cm)",
    "sfomuseum:maker": "TQ Tradex, Ltd.",
    "sfomuseum:media_ids": [
      1527858435
    ],
    "sfomuseum:medium": "glazed ceramic",
    "sfomuseum:placetype": "object",
    "sfomuseum:publication": ": , 1980s.",
    "sfomuseum:subcategory": "Plate / Dish / Bowl",
    "wof:depicts": [
      1159284201,
      1360700741
    ],
    "wof:name": "entree dish: Continental Airlines",
    "wof:placetype": "custom",
    "wof:placetype_alt": "object"
  },
  "geometry": {"coordinates":[-122.386155,37.616358],"type":"Point"}
}
