{
  "type": "Feature",
  "properties": {
    "date:cessation_lower": "1994-01-01",
    "date:cessation_upper": "1994-12-31",
    "date:inception_lower": "1994-01-01",
    "date:inception_upper": "1994-12-31",
    "iso:country": "XX",
    "sfomuseum:accession_number": "1999.659.177",
    "sfomuseum:author": "Andersson, Lennart",
    "sfomuseum:callnumber": "TL526.S65 A54 1994b",
    "sfomuseum:category": "Book",
    "sfomuseum:collection": "Aviation Library",
    "sfomuseum:creditline": "Purchase",
    "sfomuseum:date": "c. 1994",
    "sfomuseum:daterange_end": "1999-12-31",
    "sfomuseum:daterange_start": "1989-01-01",
    "sfomuseum:description": "360 p. : ill., maps ; 28 cm.",
    "sfomuseum:description_library": "360 p. : ill., maps ; 28 cm.",
    "sfomuseum:medium": "paper, ink",
    "sfomuseum:placetype": "object",
    "sfomuseum:publication": "Annapolis, MD: Naval Institute Press, c. 1994.",
    "sfomuseum:publisher": "Naval Institute Press",
    "sfomuseum:publisher_location": "Annapolis, MD",
    "sfomuseum:subcategory": "Book",
    "sfomuseum:subject": "Airplanes, Military Soviet Union History.Airplanes Soviet Union History.Aeronautics Soviet Union History.",
    "wof:name": "Soviet aircraft and aviation, 1917-1941",
    "wof:placetype": "custom"
  },
  "geometry": {"coordinates":[-122.386155,37.616357],"type":"Point"}
}
