{
  "type": "Feature",
  "properties": {
    "date:cessation_lower": "1942-01-01",
    "date:cessation_upper": "1942-12-31",
    "date:inception_lower": "1942-01-01",
    "date:inception_upper": "1942-12-31",
    "iso:country": "XX",
    "sfomuseum:accession_number": "2000.160.0556",
    "sfomuseum:author": "Manly, Gardener Burnell",
    "sfomuseum:callnumber": "TL545 .M18 1942",
    "sfomuseum:category": "Book",
    "sfomuseum:collection": "Aviation Library",
    "sfomuseum:creditline": "The Tony Bill Aviation Library Collection",
    "sfomuseum:date": "1942",
    "sfomuseum:date_acquired": "1999-05-18",
    "sfomuseum:daterange_end": "1942-12-31",
    "sfomuseum:daterange_start": "1942-01-01",
    "sfomuseum:description": "369 (i.e. 415) p. incl. front., illus., diagrs. 21 cm.",
    "sfomuseum:medium": "paper, ink",
    "sfomuseum:placetype": "object",
    "sfomuseum:publication": "Chicago: F. J. Drake \u0026 Company, 1942.",
    "sfomuseum:publisher": "F. J. Drake \u0026 Company",
    "sfomuseum:publisher_location": "Chicago",
    "sfomuseum:subcategory": "Book",
    "sfomuseum:subject": "Airplanes.Aeronautics.",
    "wof:name": "Aviation from the ground up: a practical instruction and reference work on aviation and allied subjects, including theory of flight, details of airplane construction, airplane engines, rigging, instruments, weather forecasting, aerial navigation, stunts, how to learn flying, parachutes, air commerce regulations and a dictionary of aviation words and terms",
    "wof:placetype": "venue"
  },
  "geometry": {"coordinates":[-122.386155,37.616357],"type":"Point"}
}
