{
  "type": "Feature",
  "properties": {
    "date:cessation_lower": "1950-01-01",
    "date:cessation_upper": "1950-12-31",
    "date:inception_lower": "1950-01-01",
    "date:inception_upper": "1950-12-31",
    "iso:country": "US",
    "millsfield:images": [
      1527819499,
      1527819501,
      1527819503,
      1527819509,
      1527819513
    ],
    "millsfield:primary_image": 1527819499,
    "sfomuseum:accession_number": "1999.049.009 a e",
    "sfomuseum:airline": "American Airlines",
    "sfomuseum:category": "Passenger Amenity",
    "sfomuseum:collection": "Aviation Archive",
    "sfomuseum:continent": "North America",
    "sfomuseum:country": "United States",
    "sfomuseum:creditline": "Gift of anonymous donor",
    "sfomuseum:date": "c. 1950",
    "sfomuseum:daterange_end": "1955-12-31",
    "sfomuseum:daterange_start": "1945-01-01",
    "sfomuseum:description": "Flight information packet issued by American Airlines, comprised of:\ra. outer jacket with diagrams of route maps. Folded into three sections with pockets, \"Business\", \"Airfreight\", and \"Pleasure\"\rb. route map for domestic and international service; tri-fold format\rc. brochure promoting winter travel to Europe; tri-fold\rd. comment card; bi-fold format\re. brochure promoting freight services, titled “The shipper’s book of Father Goose”; multipage booklet",
    "sfomuseum:dimensions": "10 x 5 inches (25.4 x 12.7 cm)",
    "sfomuseum:media_ids": [
      1527819499,
      1527819503,
      1527819509,
      1527819513,
      1527819501
    ],
    "sfomuseum:medium": "paper, ink",
    "sfomuseum:placetype": "object",
    "sfomuseum:subcategory": "In-flight Information",
    "wof:depicts": [
      1159283849
    ],
    "wof:name": "flight information packet: American Airlines",
    "wof:placetype": "venue"
  },
  "geometry": {"coordinates":[-122.386155,37.616357],"type":"Point"}
}
