{
  "type": "Feature",
  "properties": {
    "date:cessation_lower": "1995-01-01",
    "date:cessation_upper": "1995-12-31",
    "date:inception_lower": "1995-01-01",
    "date:inception_upper": "1995-12-31",
    "iso:country": "XX",
    "millsfield:images": [
      1527840435
    ],
    "millsfield:images_texts": [
      "UNITED AIRLINES\nUNITED EXPRESS\nWashington Baltimore\nTIMETABLE\nINCLUDING\nShuttle\nBY UNITED\nEffective January 4, 1995 - February 7, 1995\nWorldwide Service\nOFFICIAL AIRLINE SPONSOR\nOF THE 1996\nU.S. OLYMPIC TEAM\n36USC 380"
    ],
    "millsfield:images_texts_ids": [
      1527840435
    ],
    "millsfield:primary_image": 1527840435,
    "sfomuseum:accession_number": "2006.059.101.058",
    "sfomuseum:airline": "United Airlines",
    "sfomuseum:category": "Scheduling / Ticketing",
    "sfomuseum:collection": "Aviation Archive",
    "sfomuseum:creditline": "Gift of the Paul Edward Fair Estate",
    "sfomuseum:date": "1995",
    "sfomuseum:date_acquired": "2006-10-19",
    "sfomuseum:daterange_end": "1995-12-31",
    "sfomuseum:daterange_start": "1995-01-01",
    "sfomuseum:description": "City timetable issued by United Airlines for service to and from Washington and Baltimore, effective January 4 through February 7, 1995; dark red and white cover with world map and text “Official Airline Sponsor of the 1996 U.S. Olympic Team”; includes United Express and Shuttle by United.",
    "sfomuseum:dimensions": "9 x 4 inches (22.9 x 10.2 cm)",
    "sfomuseum:media_ids": [
      1527840435
    ],
    "sfomuseum:medium": "paper, ink",
    "sfomuseum:placetype": "object",
    "sfomuseum:publication": ": , 1995.",
    "sfomuseum:subcategory": "Timetable",
    "wof:depicts": [
      1159288779,
      1159285417,
      1159285423,
      1159285413
    ],
    "wof:name": "timetable: United Airlines, Washington / Baltimore",
    "wof:placetype": "custom",
    "wof:placetype_alt": [
      "object"
    ]
  },
  "geometry": {"coordinates":[-122.386155,37.616357],"type":"Point"}
}
