{
  "type": "Feature",
  "properties": {
    "date:cessation_lower":"1939-12-31",
    "date:cessation_upper":"1939-12-31",
    "date:inception_lower":"1939-01-01",
    "date:inception_upper":"1939-01-01",
    "iso:country":"XX",
    "sfomuseum:accession_number":"2008.075.134",
    "sfomuseum:category":"Philately",
    "sfomuseum:collection":"Aviation Archive",
    "sfomuseum:creditline":"Gift of Jon E. Krupnick",
    "sfomuseum:date":"05/30/1939",
    "sfomuseum:daterange_end":"1939-05-30",
    "sfomuseum:daterange_start":"1939-05-30",
    "sfomuseum:description":"Mail ship cover for U.S.S. Astoria- May 30, 1939; envelope postmarked May 30, 1939 on the U.S.S. Astoria with International Date Line cancellation mark over one red 2-cent postage stamp in black ink; addressed to Robert W. Matthews; identified by donor with additional information: \"Pacific Naval Ship covers\".",
    "sfomuseum:media_ids":[
        1527851825
    ],
    "sfomuseum:medium":"paper, ink",
    "sfomuseum:placetype":"object",
    "sfomuseum:subcategory":"Airmail Flight Cover",
    "wof:name":"mail ship cover: Pacific Naval Ship, U.S.S. Astoria, May 30, 1939",
    "wof:placetype":"venue"
},
  "geometry": {"coordinates":[-122.386155,37.616358],"type":"Point"}
}