{
  "type": "Feature",
  "properties": {
    "date:cessation_lower": "1987-01-01",
    "date:cessation_upper": "1987-12-31",
    "date:inception_lower": "1982-01-01",
    "date:inception_upper": "1982-12-31",
    "iso:country": "XX",
    "sfomuseum:accession_number": "2000.168.233",
    "sfomuseum:author": "Taylor, Michael J.H",
    "sfomuseum:callnumber": "TL501 .J36 1986",
    "sfomuseum:category": "Book",
    "sfomuseum:collection": "Aviation Library",
    "sfomuseum:creditline": "Purchase",
    "sfomuseum:date": "1982-1987",
    "sfomuseum:daterange_end": "1987-12-31",
    "sfomuseum:daterange_start": "1982-01-01",
    "sfomuseum:description": "5 v. : ill. ; 28 cm.",
    "sfomuseum:description_library": "5 v. : ill. ; 28 cm.",
    "sfomuseum:medium": "paper, ink",
    "sfomuseum:placetype": "object",
    "sfomuseum:publication": "London: Jane's, 1982-1987.",
    "sfomuseum:publisher": "Jane's",
    "sfomuseum:publisher_location": "London",
    "sfomuseum:subcategory": "Book",
    "sfomuseum:subject": "Astronautics Yearbooks.Airplanes Yearbooks.Aeronautics Yearbooks.Astronautics Periodicals.Aeronautics Periodicals.",
    "wof:name": "Jane's aviation review",
    "wof:placetype": "custom",
    "wof:placetype_alt": "object"
  },
  "geometry": {"coordinates":[-122.386155,37.616357],"type":"Point"}
}
