{
  "type": "Feature",
  "properties": {
    "date:cessation_lower": "1921-12-31",
    "date:cessation_upper": "1921-12-31",
    "date:inception_lower": "1921-01-01",
    "date:inception_upper": "1921-01-01",
    "iso:country": "XX",
    "sfomuseum:accession_number": "2010.174.018",
    "sfomuseum:category": "Employee Career History",
    "sfomuseum:collection": "Aviation Archive",
    "sfomuseum:creditline": "Gift of Charles Page",
    "sfomuseum:date": "1921",
    "sfomuseum:daterange_end": "1921-12-31",
    "sfomuseum:daterange_start": "1921-01-01",
    "sfomuseum:description": "Logbook with caption on cover, “Things to do Today” followed by “XXXX Nickel, The Supreme Babbitt Metal, Great Western Smelting \u0026 Refining Co., 75-99 Folsom Street, San Francisco, Cal.”; contains handwritten journal entries dated 1921; employee career history document of Stanley H. Page.",
    "sfomuseum:media_ids": [
      1527854163, 
      1527854165
    ],
    "sfomuseum:medium": "paper, ink",
    "sfomuseum:placetype": "object",
    "sfomuseum:subcategory": "Logbook, Employee",
    "wof:name": "logbook: Stanley Henry Page",
    "wof:placetype": "venue"
  },
  "geometry": {"coordinates":[-122.386155,37.616358],"type":"Point"}
}
