{
  "type": "Feature",
  "properties": {
    "date:cessation_lower": "1950-01-01",
    "date:cessation_upper": "1959-12-31",
    "date:inception_lower": "1950-01-01",
    "date:inception_upper": "1959-12-31",
    "iso:country": "XX",
    "millsfield:images": [
      1729565677,
      1729565679
    ],
    "millsfield:images_texts": [
      "The Liberty Bell\nColor-fato by TWA\nSymbolic of our freedom, the\nhistoric Liberty Bell stands on\ndisplay in Independence Hall,\nPhiladelphia. Here also our\nnation's founders signed the\nDeclaration of Independence.\nTHA",
      "POST CARD\nPOSTAGE\nONE\nCENT\nLitho in U.S.A.—250M 10-51\n2001.109.151"
    ],
    "millsfield:images_texts_ids": [
      1729565677,
      1729565679
    ],
    "millsfield:primary_image": 1729565677,
    "sfomuseum:accession_number": "2001.109.151",
    "sfomuseum:airline": "TWA (Trans World Airlines)",
    "sfomuseum:category": "Philately",
    "sfomuseum:collection": "Aviation Archive",
    "sfomuseum:creditline": "Gift of Thomas G. Dragges in memory of Robert May",
    "sfomuseum:date": "1950s",
    "sfomuseum:date_acquired": "2002-12-24",
    "sfomuseum:daterange_end": "1950-12-31",
    "sfomuseum:daterange_start": "1950-01-01",
    "sfomuseum:description": "Color postcard issued by TWA (Trans World Airlines) promoting destination with photographic image of Liberty Bell at Independence Hall, Philadelphia; text, \"Symbolic of our freedom, the historic Liberty Bell stands on display in Independence Hall, Philadelphia”; unmailed.",
    "sfomuseum:dimensions": "3 1/2 x 5 1/2 inches (8.9 x 14 cm)",
    "sfomuseum:medium": "paper, ink",
    "sfomuseum:placetype": "object",
    "sfomuseum:publication": ": , 1950s.",
    "sfomuseum:subcategory": "Postcard",
    "wof:depicts": [
      1159285393,
      1159287531
    ],
    "wof:name": "postcard: TWA (Trans World Airlines)",
    "wof:placetype": "custom",
    "wof:placetype_alt": "object"
  },
  "geometry": {"coordinates":[-122.386155,37.616357],"type":"Point"}
}
