{
  "type": "Feature",
  "properties": {
    "date:cessation_lower": "1967-12-31",
    "date:cessation_upper": "1967-12-31",
    "date:inception_lower": "1967-01-01",
    "date:inception_upper": "1967-01-01",
    "iso:country": "XX",
    "sfomuseum:accession_number": "2005.132.009.024",
    "sfomuseum:category": "Scheduling / Ticketing",
    "sfomuseum:collection": "Aviation Archive",
    "sfomuseum:creditline": "Gift of the William Hough Collection",
    "sfomuseum:date": "1967",
    "sfomuseum:daterange_end": "1967-12-31",
    "sfomuseum:daterange_start": "1967-01-01",
    "sfomuseum:description": "Timetable issued by Bonanza Air Lines, effective September 1, 1967; four page double-sided fold-out. The cover is fuchsia with a large black and white photographic image of a male in the center. Text is “What’s so much fun about September 1?” A company jet is just above and to the right of the photo. The company name is in large black letters at the top.",
    "sfomuseum:media_ids": [
      1527837487
    ],
    "sfomuseum:medium": "paper, ink",
    "sfomuseum:placetype": "object",
    "sfomuseum:subcategory": "Timetable",
    "wof:name": "timetable: Bonanza Air Lines",
    "wof:placetype": "venue"
  },
  "geometry": {"coordinates":[-122.386155,37.616358],"type":"Point"}
}
