{
  "type": "Feature",
  "properties": {
    "date:cessation_lower": "1947-12-31",
    "date:cessation_upper": "1947-12-31",
    "date:inception_lower": "1937-01-01",
    "date:inception_upper": "1937-01-01",
    "iso:country": "XX",
    "sfomuseum:accession_number": "2007.007.010",
    "sfomuseum:category": "Philately",
    "sfomuseum:collection": "Aviation Archive",
    "sfomuseum:creditline": "Gift of Hiller Aviation Museum",
    "sfomuseum:date": "c. 1942",
    "sfomuseum:daterange_end": "1947-12-31",
    "sfomuseum:daterange_start": "1937-01-01",
    "sfomuseum:description": "Postcard with illustrated black and white map of continental U.S. showing American Airlines flight routes; stamped on reverse; writing in black ink; postmarked July 6, 1942; message discusses the flight and begins \"Arrived more or less in one piece. Good thing I didn't eat dinner.\" ",
    "sfomuseum:media_ids": [
      1527830237
    ],
    "sfomuseum:medium": "paper, ink",
    "sfomuseum:placetype": "object",
    "sfomuseum:subcategory": "Postcard",
    "wof:name": "postcard: American Airlines",
    "wof:placetype": "venue"
  },
  "geometry": {"coordinates":[-122.386155,37.616358],"type":"Point"}
}
