{
  "type": "Feature",
  "properties": {
    "date:cessation_lower": "1955-01-01",
    "date:cessation_upper": "1955-12-31",
    "date:inception_lower": "1955-01-01",
    "date:inception_upper": "1955-12-31",
    "iso:country": "XX",
    "millsfield:images": [
      1527835079
    ],
    "millsfield:primary_image": 1527835079,
    "sfomuseum:accession_number": "2012.149.1173",
    "sfomuseum:airline": "El Al Israel Airlines",
    "sfomuseum:category": "Promotional",
    "sfomuseum:collection": "Aviation Archive",
    "sfomuseum:creditline": "Gift of the Captain John B. Russell Family",
    "sfomuseum:date": "c. 1955",
    "sfomuseum:daterange_end": "1960-12-31",
    "sfomuseum:daterange_start": "1950-01-01",
    "sfomuseum:description": "Luggage label promoting El Al Israel Air; circular shape, dark blue background with white border; yellow “El Al” followed by light blue “Israel Airlines” with winged Star of David at center.",
    "sfomuseum:dimensions": "3 3/4 x 3 3/4 inches (9.5 x 9.5 cm)",
    "sfomuseum:media_ids": [
      1527835079
    ],
    "sfomuseum:medium": "paper, ink",
    "sfomuseum:placetype": "object",
    "sfomuseum:publication": ": , c. 1955.",
    "sfomuseum:subcategory": "Luggage Label",
    "wof:depicts": [
      1159284327
    ],
    "wof:name": "luggage label: El Al Israel Air",
    "wof:placetype": "venue"
  },
  "geometry": {"coordinates":[-122.386155,37.616357],"type":"Point"}
}
