{
  "type": "Feature",
  "properties": {
    "date:cessation_lower": "1987-12-31",
    "date:cessation_upper": "1987-12-31",
    "date:inception_lower": "1987-01-01",
    "date:inception_upper": "1987-01-01",
    "iso:country": "XX",
    "millsfield:images": [
      1527834579
    ],
    "sfomuseum:accession_number": "2005.132.002.097",
    "sfomuseum:airline": "AirCal",
    "sfomuseum:airport": "Chicago O'Hare International Airport",
    "sfomuseum:category": "Scheduling / Ticketing",
    "sfomuseum:collection": "Aviation Archive",
    "sfomuseum:creditline": "Gift of the William Hough Collection",
    "sfomuseum:date": "1987",
    "sfomuseum:daterange_end": "1987-12-31",
    "sfomuseum:daterange_start": "1987-01-01",
    "sfomuseum:description": "Timetable issued by AirCal, effective March 2, 1987, with American Airlines Chicago O’Hare Connection Supplement. The cover is blue with four small full color photographic images of points of interest. The lettering is black and white. The top of the schedule has the company name in black lettering.",
    "sfomuseum:dimensions": "9 x 4 inches (22.9 x 10.2 cm)",
    "sfomuseum:media_ids": [
      1527834579
    ],
    "sfomuseum:medium": "paper, ink",
    "sfomuseum:placetype": "object",
    "sfomuseum:subcategory": "Timetable",
    "wof:depicts": [
      102533631,
      1159283791,
      1159283849
    ],
    "wof:name": "timetable: AirCal, American Airlines",
    "wof:placetype": "venue"
  },
  "geometry": {"coordinates":[-122.386155,37.616357],"type":"Point"}
}
