{
  "type": "Feature",
  "properties": {
    "date:cessation_lower":"1993-12-31",
    "date:cessation_upper":"1993-12-31",
    "date:inception_lower":"1983-01-01",
    "date:inception_upper":"1983-01-01",
    "iso:country":"XX",
    "sfomuseum:accession_number":"2001.080.059",
    "sfomuseum:category":"Food Service",
    "sfomuseum:collection":"Aviation Museum",
    "sfomuseum:continent":"World Routes",
    "sfomuseum:creditline":"Gift of Thomas G. Dragges",
    "sfomuseum:date":"c. 1988",
    "sfomuseum:daterange_end":"1993-12-31",
    "sfomuseum:daterange_start":"1983-01-01",
    "sfomuseum:description":"Menu produced by Lufthansa German Airlines, Las Palmas - Frankfurt route; black cover with color photographic image of food items; lunch menu items include wild boar and Turbot in lobster sauce; menu number: 1923; class: first; date: 88/IX-X (September - October 1988).",
    "sfomuseum:media_ids":[
        1527844803,
        1527844805
    ],
    "sfomuseum:medium":"paper, ink",
    "sfomuseum:placetype":"object",
    "sfomuseum:subcategory":"Menu",
    "wof:name":"menu: Lufthansa German Airlines, First Class",
    "wof:placetype":"venue"
},
  "geometry": {"coordinates":[-122.386155,37.616358],"type":"Point"}
}