{
  "type": "Feature",
  "properties": {
    "date:cessation_lower": "1981-01-01",
    "date:cessation_upper": "1981-12-31",
    "date:inception_lower": "1980-01-01",
    "date:inception_upper": "1980-12-31",
    "iso:country": "XX",
    "sfomuseum:accession_number": "2014.062.025",
    "sfomuseum:author": "Aerospace Industries Association of America",
    "sfomuseum:callnumber": "TL501 .A818 1983-84",
    "sfomuseum:category": "Book",
    "sfomuseum:collection": "Aviation Library",
    "sfomuseum:creditline": "Gift of Gerald W. Bernstein",
    "sfomuseum:date": "1980-1981",
    "sfomuseum:date_acquired": "2014-08-07",
    "sfomuseum:daterange_end": "1981-12-31",
    "sfomuseum:daterange_start": "1980-01-01",
    "sfomuseum:description": "v. : ill. ; 23 cm.",
    "sfomuseum:description_library": "v. : ill. ; 23 cm.",
    "sfomuseum:medium": "paper, ink",
    "sfomuseum:notes_library": "Description based on: 1963.Vols. for \u003c1986-1987-\u003e compiled by: Economic Data Service, Aerospace Research Center.",
    "sfomuseum:placetype": "object",
    "sfomuseum:publication": "Los Angeles: Aero Publishers, 1980-1981.",
    "sfomuseum:publisher": "Aero Publishers",
    "sfomuseum:publisher_location": "Los Angeles",
    "sfomuseum:subcategory": "Book",
    "sfomuseum:subject": "Astronautics Periodicals.Aeronautics Periodicals.",
    "wof:name": "Aerospace facts and figures",
    "wof:placetype": "venue"
  },
  "geometry": {"coordinates":[-122.386155,37.616357],"type":"Point"}
}
