{
  "type": "Feature",
  "properties": {
    "date:cessation_lower": "1927-01-01",
    "date:cessation_upper": "1927-12-31",
    "date:inception_lower": "1927-01-01",
    "date:inception_upper": "1927-12-31",
    "iso:country": "XX",
    "sfomuseum:accession_number": "2005.054.006",
    "sfomuseum:author": "Warner, Edward Pearson",
    "sfomuseum:callnumber": "TL671.2 .W37 1927 c.1 SC",
    "sfomuseum:category": "Book",
    "sfomuseum:collection": "Aviation Library",
    "sfomuseum:creditline": "Gift of Kenneth E. Bourke",
    "sfomuseum:date": "1927",
    "sfomuseum:date_acquired": "2005-11-22",
    "sfomuseum:daterange_end": "1927-12-31",
    "sfomuseum:daterange_start": "1927-01-01",
    "sfomuseum:description": "598 p. ill. 24 cm.",
    "sfomuseum:medium": "paper, ink",
    "sfomuseum:placetype": "object",
    "sfomuseum:publication": "New York: McGraw-Hill Book, 1927.",
    "sfomuseum:publisher": "McGraw-Hill Book",
    "sfomuseum:publisher_location": "New York",
    "sfomuseum:subcategory": "Book",
    "sfomuseum:subject": "Aerodynamics.Airplanes Design and construction.",
    "wof:name": "Airplane design: aerodynamics",
    "wof:placetype": "venue"
  },
  "geometry": {"coordinates":[-122.386155,37.616357],"type":"Point"}
}
