{
  "type": "Feature",
  "properties": {
    "date:cessation_lower":"1967-12-31",
    "date:cessation_upper":"1967-12-31",
    "date:inception_lower":"1957-01-01",
    "date:inception_upper":"1957-01-01",
    "iso:country":"XX",
    "millsfield:images":[
        1527843929,
        1527843931
    ],
    "sfomuseum:accession_number":"2007.002.007",
    "sfomuseum:airline":"BOAC (British Overseas Airways Corporation)",
    "sfomuseum:category":"Passenger Amenity",
    "sfomuseum:collection":"Aviation Archive",
    "sfomuseum:creditline":"Gift of John J. Larish",
    "sfomuseum:date":"c. 1962",
    "sfomuseum:daterange_end":"1967-12-31",
    "sfomuseum:daterange_start":"1957-01-01",
    "sfomuseum:description":"Menu issued by BOAC (British Overseas Airways Corporation), Chicago - London route; white cover with color illustration of running deer (antelope); dinner and breakfast menu items include filet mignon and continental breakfast; no menu number; undated.",
    "sfomuseum:media_ids":[
        1527843929,
        1527843931
    ],
    "sfomuseum:medium":"paper, ink",
    "sfomuseum:placetype":"object",
    "sfomuseum:subcategory":"Menu",
    "wof:depicts":[
        1159283999
    ],
    "wof:name":"menu: BOAC (British Overseas Airways Corporation)",
    "wof:placetype":"venue"
},
  "geometry": {"coordinates":[-122.386155,37.616357],"type":"Point"}
}