{
  "type": "Feature",
  "properties": {
    "date:cessation_lower": "1970-01-01",
    "date:cessation_upper": "1970-12-31",
    "date:inception_lower": "1970-01-01",
    "date:inception_upper": "1970-12-31",
    "iso:country": "XX",
    "millsfield:images": [
      1527845187,
      1527845189
    ],
    "millsfield:images_texts": [
      "BEING 707-320\nSuper fan fel\n\u003cITY OF ATHENS",
      "Paris - Athens\nNew York - Paris\nLE\nPETIT\nDEJEUNER\nBREAKFAST\nLE DEJEUNER\nLUNCH\nLE SAUMON FUME SUR CANAPE\nSmoked Salmon on Canape\nLA COUPE D'ORANGE ET D'ANANAS\nPineapple and Orange\nLE GRENADIN DE VEAU VALEE D'AUGE\nCAROTTES NOUVELLES\nSirloin of Veal Vallée d'Auge with Carrots\nLE BEURRE LA MARMELADE LA CONFITURE\nButter\nMarmelade\nJam\nLA SALADE DE SAISON\nGreen Garden Salad\nLE CROISSANT\nCrescent Roll\nLA PATISSERIE DANOISE\nDanish Pastry\nLE CAMEMBERT DE NORMANDIE\nCamembert Cheese\nLA TARTELETTE AUX FRUITS\nFruit Tart\nLE CAFE\nCoffee\nLE CAFE\nCoffee\nPrepared by \"LES TROIS SOLEILS\" Orly"
    ],
    "millsfield:images_texts_ids": [
      1527845187,
      1527845189
    ],
    "millsfield:primary_image": 1527845187,
    "sfomuseum:accession_number": "2001.080.219",
    "sfomuseum:aircraft": "Boeing 707-320",
    "sfomuseum:airline": "Olympic Airlines",
    "sfomuseum:category": "Passenger Amenity, Archive",
    "sfomuseum:collection": "Aviation Archive",
    "sfomuseum:continent": "World Routes",
    "sfomuseum:creditline": "Gift of Thomas G. Dragges",
    "sfomuseum:date": "1970",
    "sfomuseum:date_acquired": "2002-12-24",
    "sfomuseum:daterange_end": "1970-12-31",
    "sfomuseum:daterange_start": "1970-01-01",
    "sfomuseum:description": "Menu issued by Olympic Airways, New York - Paris - Athens route; off-white cover with black and white illustration of scene in historical Acropolis; menu items include filet mignon, pastries, and veal sirloin; no menu number; undated.",
    "sfomuseum:dimensions": "11 x 7 1/2 inches (27.9 x 19.1 cm)",
    "sfomuseum:media_ids": [
      1527845187,
      1527845189
    ],
    "sfomuseum:medium": "paper, ink, fabric",
    "sfomuseum:placetype": "object",
    "sfomuseum:publication": ": , 1970.",
    "sfomuseum:subcategory": "Menu",
    "wof:depicts": [
      1159289689,
      1159286755,
      1159293593,
      1159289653,
      1159284925
    ],
    "wof:name": "menu: Olympic Airways",
    "wof:placetype": "custom",
    "wof:placetype_alt": [
      "object"
    ]
  },
  "geometry": {"coordinates":[-122.386155,37.616357],"type":"Point"}
}
