{
  "type": "Feature",
  "properties": {
    "date:cessation_lower": "2003-01-01",
    "date:cessation_upper": "2003-12-31",
    "date:inception_lower": "2003-01-01",
    "date:inception_upper": "2003-12-31",
    "iso:country": "XX",
    "sfomuseum:accession_number": "2005.009.040",
    "sfomuseum:author": "Oates, Carl",
    "sfomuseum:callnumber": "HE9803.P36 O37 2003 c.2",
    "sfomuseum:category": "Book",
    "sfomuseum:collection": "Aviation Library",
    "sfomuseum:creditline": "Collection of SFO Museum",
    "sfomuseum:date": "c. 2003",
    "sfomuseum:daterange_end": "2008-12-31",
    "sfomuseum:daterange_start": "1998-01-01",
    "sfomuseum:description": "xiii, 228 p. : ill., maps ; 24 cm.",
    "sfomuseum:medium": "paper, ink",
    "sfomuseum:placetype": "object",
    "sfomuseum:publisher": "Paladwr Press",
    "sfomuseum:publisher_location": "McLean, VA",
    "sfomuseum:subcategory": "Book",
    "sfomuseum:subject": "Kanton (Kiribati) History.\rPan American World Airways, inc. -- History. Transpacific flights History. China Clipper (Airplane) -- History. Canton Island -- Personal narratives.",
    "wof:name": "Canton Island: aerial crossroads of the South Pacific",
    "wof:placetype": "venue"
  },
  "geometry": {"coordinates":[-122.386155,37.616357],"type":"Point"}
}
