{
  "type": "Feature",
  "properties": {
    "date:cessation_lower": "2003-01-01",
    "date:cessation_upper": "2003-12-31",
    "date:inception_lower": "2003-01-01",
    "date:inception_upper": "2003-12-31",
    "iso:country": "XX",
    "sfomuseum:accession_number": "2008.070.022",
    "sfomuseum:author": "Holden, Henry M.",
    "sfomuseum:callnumber": "TL539 .H563 2003 JUV",
    "sfomuseum:category": "Book",
    "sfomuseum:collection": "Aviation Library",
    "sfomuseum:creditline": "Purchase",
    "sfomuseum:date": "2003",
    "sfomuseum:date_acquired": "2009-07-13",
    "sfomuseum:daterange_end": "2003-12-31",
    "sfomuseum:daterange_start": "2003-01-01",
    "sfomuseum:description": "112 p. : ill. ; 24 cm.",
    "sfomuseum:description_library": "112 p. : ill. ; 24 cm.",
    "sfomuseum:medium": "paper, ink",
    "sfomuseum:placetype": "object",
    "sfomuseum:publication": "Berkeley Heights, NJ: Enslow Publishers, 2003.",
    "sfomuseum:publisher": "Enslow Publishers",
    "sfomuseum:publisher_location": "Berkeley Heights, NJ",
    "sfomuseum:series": "Collective biographies",
    "sfomuseum:subcategory": "Book",
    "sfomuseum:subject": "Women air pilots Biography Juvenile literature.",
    "wof:name": "American women of flight: pilots and pioneers",
    "wof:placetype": "custom",
    "wof:placetype_alt": "object"
  },
  "geometry": {"coordinates":[-122.386155,37.616357],"type":"Point"}
}
