{
  "type": "Feature",
  "properties": {
    "date:cessation_lower": "2002-01-01",
    "date:cessation_upper": "2002-12-31",
    "date:inception_lower": "2002-01-01",
    "date:inception_upper": "2002-12-31",
    "iso:country": "XX",
    "millsfield:tailnumbers": [
      "P-885"
    ],
    "sfomuseum:accession_number": "2004.115.0540",
    "sfomuseum:aircraft": "Ilyushin Il-62M",
    "sfomuseum:airline": "Air Koryo",
    "sfomuseum:airport": "Beijing Capital International Airport",
    "sfomuseum:artist": "William “Bill” Hough",
    "sfomuseum:category": "Photograph",
    "sfomuseum:collection": "Aviation Archive",
    "sfomuseum:creditline": "Gift of the William Hough Collection",
    "sfomuseum:date": "2002",
    "sfomuseum:date_acquired": "2004-12-28",
    "sfomuseum:daterange_end": "2002-12-31",
    "sfomuseum:daterange_start": "2002-01-01",
    "sfomuseum:description": "Color photographic slide depicting Air Koryo Ilyushin Il-62M at Beijing Capital International Airport (PEK), November 9, 2002.",
    "sfomuseum:dimensions": "1 x 1 1/2 inches (2.5 x 3.8 cm)",
    "sfomuseum:medium": "color slide",
    "sfomuseum:placetype": "object",
    "sfomuseum:publication": ": , 2002.",
    "sfomuseum:registration_number": "P-885",
    "sfomuseum:subcategory": "Slide",
    "wof:depicts": [
      102550367,
      1159283657,
      1159288591,
      1159290959,
      1159294129,
      1159290961
    ],
    "wof:name": "slide: Air Koryo, Ilyushin Il-62M, Beijing Capital International Airport (PEK)",
    "wof:placetype": "custom",
    "wof:placetype_alt": "object"
  },
  "geometry": {"coordinates":[-122.386155,37.616357],"type":"Point"}
}
