{
  "type": "Feature",
  "properties": {
    "date:cessation_lower":"2002-12-31",
    "date:cessation_upper":"2002-12-31",
    "date:inception_lower":"2002-01-01",
    "date:inception_upper":"2002-01-01",
    "iso:country":"XX",
    "millsfield:images":[
        1527846231,
        1527846235
    ],
    "sfomuseum:accession_number":"2003.009.001",
    "sfomuseum:airline":"United Airlines",
    "sfomuseum:category":"Passenger Amenity",
    "sfomuseum:collection":"Aviation Archive",
    "sfomuseum:creditline":"Gift of J. Abram Garfield",
    "sfomuseum:date":"2002",
    "sfomuseum:daterange_end":"2002-12-31",
    "sfomuseum:daterange_start":"2002-01-01",
    "sfomuseum:description":"Menu issued by United Air Lines, transcontinental route; black and white photographic image of bread; menu items include cheeseburger, chicken breast, and portobello stuffed gnocchi; menu number: TRANS-CON (L01); class: First; date: 12/02.",
    "sfomuseum:media_ids":[
        1527846231,
        1527846235
    ],
    "sfomuseum:medium":"paper, ink",
    "sfomuseum:placetype":"object",
    "sfomuseum:subcategory":"Menu",
    "wof:depicts":[
        1159285413
    ],
    "wof:name":"menu: United Airlines, First Class",
    "wof:placetype":"venue"
},
  "geometry": {"coordinates":[-122.386155,37.616357],"type":"Point"}
}