{
  "type": "Feature",
  "properties": {
    "date:cessation_lower": "1987-01-01",
    "date:cessation_upper": "1987-12-31",
    "date:inception_lower": "1987-01-01",
    "date:inception_upper": "1987-12-31",
    "isbn:number": "087938266X 9780879382667",
    "iso:country": "XX",
    "loc:subject_headings": [
      "sh87004586"
    ],
    "sfomuseum:accession_number": "99-0224",
    "sfomuseum:author": "Valant, Gary M.",
    "sfomuseum:callnumber": "UG1240 .V35 1987 c.2",
    "sfomuseum:category": "Book",
    "sfomuseum:collection": "Aviation Library",
    "sfomuseum:date": "1987",
    "sfomuseum:daterange_end": "1987-12-31",
    "sfomuseum:daterange_start": "1987-01-01",
    "sfomuseum:description": "208 p. : p., ill. (some col.) ; 32 cm.",
    "sfomuseum:description_library": "208 pages : illustrations (some color) ; 32 cm",
    "sfomuseum:medium": "paper, ink",
    "sfomuseum:placetype": "object",
    "sfomuseum:publication": "Osceola, WI: Motorbooks International, 1987.",
    "sfomuseum:publisher": "Motorbooks International",
    "sfomuseum:publisher_location": "Osceola, WI",
    "sfomuseum:subcategory": "Book",
    "sfomuseum:subject": "Airplanes, Military -- Decoration.  \rAirplanes, Military -- Decoration -- Pictorial works.                                            Antique and classic aircraft -- Pictorial works.  ",
    "wof:name": "Vintage aircraft nose art",
    "wof:placetype": "custom",
    "wof:placetype_alt": "object"
  },
  "geometry": {"coordinates":[-122.386155,37.616357],"type":"Point"}
}
