{
  "type": "Feature",
  "properties": {
    "date:cessation_lower": "1931-11-15",
    "date:cessation_upper": "1931-11-15",
    "date:inception_lower": "1931-11-15",
    "date:inception_upper": "1931-11-15",
    "iso:country": "XX",
    "millsfield:images": [
      1527834635,
      1527834637
    ],
    "millsfield:images_texts": [
      "Lindbergh Flicht.\n*****************\nMiami-Cienfuegos.\n******************\nPar Avion\nBy Air Mail\nFORM 2978\n1811l Schneider Jr.,\nCientuegos,\nС u\nЖ***",
      "839\nлла\nSTA SIT TA\non SAME\nSON\nHON SHA SHINI\nBILI. SCHNEIDER, Jr.,\nBox 76 - RED. #2,, COMPRE AZARRE AZUCA\nRahway, New Jersey. CUBAN cUB7\n280\nNY- 11\nVN\n2012.149.1707"
    ],
    "millsfield:images_texts_ids": [
      1527834635,
      1527834637
    ],
    "millsfield:primary_image": 1527834635,
    "sfomuseum:accession_number": "2012.149.1707",
    "sfomuseum:category": "Philately",
    "sfomuseum:collection": "Aviation Archive",
    "sfomuseum:creditline": "Gift of the Captain John B. Russell Family",
    "sfomuseum:date": "11/15/1931",
    "sfomuseum:date_acquired": "2013-05-31",
    "sfomuseum:daterange_end": "1931-11-15",
    "sfomuseum:daterange_start": "1931-11-15",
    "sfomuseum:description": "Airmail flight cover, Pan American Airways’ American Clipper first flight, Miami - Barranquilla route, flown by Charles Lindbergh; purple inverted cachet at center depicting profile view of aircraft; postmarked November 15, 1931 in Ne[illegible] with 5-cent postage stamp; two backstamps: November 19, 1931 in Havana and November 20, 1931 in Cienfuegos, Cuba; addressed to Bill Schneider, Jr.",
    "sfomuseum:dimensions": "3 1/2 x 6 1/2 inches (8.9 x 16.5 cm)",
    "sfomuseum:media_ids": [
      1527834635,
      1527834637
    ],
    "sfomuseum:medium": "paper, ink",
    "sfomuseum:placetype": "object",
    "sfomuseum:publication": ": , 11/15/1931.",
    "sfomuseum:subcategory": "Airmail Flight Cover",
    "wof:name": "airmail flight cover: Pan American Airways, first flight, American Clipper, Charles Lindbergh, Miami - Barranquilla route",
    "wof:placetype": "custom",
    "wof:placetype_alt": "object"
  },
  "geometry": {"coordinates":[-122.386155,37.616357],"type":"Point"}
}
