{
  "type": "Feature",
  "properties": {
    "date:cessation_lower": "1996-01-01",
    "date:cessation_upper": "1996-12-31",
    "date:inception_lower": "1996-01-01",
    "date:inception_upper": "1996-12-31",
    "iso:country": "XX",
    "sfomuseum:accession_number": "99-1012",
    "sfomuseum:author": "Morton, John K.",
    "sfomuseum:callnumber": "TL603 .M675 1996 REF",
    "sfomuseum:category": "Book",
    "sfomuseum:collection": "Aviation Library",
    "sfomuseum:date": "1996",
    "sfomuseum:daterange_end": "1996-12-31",
    "sfomuseum:daterange_start": "1996-01-01",
    "sfomuseum:description": "112 p. : col. ill. ; 27 cm.",
    "sfomuseum:description_library": "112 p. : col. ill. ; 27 cm.",
    "sfomuseum:medium": "paper, ink",
    "sfomuseum:placetype": "object",
    "sfomuseum:publication": "Osceola, WI: Motorbooks International, 1996.",
    "sfomuseum:publisher": "Motorbooks International",
    "sfomuseum:publisher_location": "Osceola, WI",
    "sfomuseum:subcategory": "Reference",
    "sfomuseum:subject": "Airlines History.Airplanes Identification marks.Transport planes Decoration.",
    "wof:name": "Lost airline liveries: airline color schemes of the past",
    "wof:placetype": "custom",
    "wof:placetype_alt": "object"
  },
  "geometry": {"coordinates":[-122.386155,37.616357],"type":"Point"}
}
