{
  "type": "Feature",
  "properties": {
    "date:cessation_lower": "2002-01-01",
    "date:cessation_upper": "2002-12-31",
    "date:inception_lower": "2002-01-01",
    "date:inception_upper": "2002-12-31",
    "iso:country": "XX",
    "sfomuseum:accession_number": "2010.171.013",
    "sfomuseum:aircraft": "Airbus",
    "sfomuseum:author": "Anderson, John David",
    "sfomuseum:callnumber": "TL670.3 .A49 2002\r",
    "sfomuseum:category": "Book",
    "sfomuseum:collection": "Aviation Library",
    "sfomuseum:creditline": "Purchase",
    "sfomuseum:date": "2002",
    "sfomuseum:date_acquired": "2010-06-16",
    "sfomuseum:daterange_end": "2002-12-31",
    "sfomuseum:daterange_start": "2002-01-01",
    "sfomuseum:description": "viii, 369 p. : ill. ; 29 cm.",
    "sfomuseum:description_library": "viii, 369 p. : ill. ; 29 cm.",
    "sfomuseum:edition": "[2nd ed.]",
    "sfomuseum:medium": "paper, ink",
    "sfomuseum:placetype": "object",
    "sfomuseum:publication": "Reston, VA: American Institute of Aeronautics and Astronautics, 2002.",
    "sfomuseum:publisher": "American Institute of Aeronautics and Astronautics",
    "sfomuseum:publisher_location": "Reston, VA",
    "sfomuseum:subcategory": "Book",
    "sfomuseum:subject": "Airplanes -- Design and construction -- History. \rAerospace engineering -- History.",
    "wof:name": "The airplane : a history of its technology / John D. Anderson, Jr.\r The airplane: a history of its technology [2nd ed.]",
    "wof:placetype": "custom",
    "wof:placetype_alt": "object"
  },
  "geometry": {"coordinates":[-122.386155,37.616357],"type":"Point"}
}
