{
  "type": "Feature",
  "properties": {
    "date:cessation_lower": "1981-01-01",
    "date:cessation_upper": "1981-12-31",
    "date:inception_lower": "1981-01-01",
    "date:inception_upper": "1981-12-31",
    "iso:country": "XX",
    "millsfield:images": [
      1527853647
    ],
    "millsfield:images_texts": [
      "DEL\nCHR\nBRU\nEFFECTIVE 01 JANUARY, 1981\nATLANTIC ALL-CARGO SERVICES\nFASTBOUND\nNEW YORK, . f. Kennedy International\nNTW YORK, J. F. Kennedy International\n•A LONDON. Heathrow\nTh'fr\nMo Su\n04.30 04.30 08.00 07.00 07 30 03Jan 10345\nin 9 200\n20 00 1 30\n23 05\nLAX\n12400\nNAN\n13A50\nSYD\n04440\n20250\n233-\n11 50\nSYD\nGUA\nMAR\nPOS\n+HA\nPACIFIC ALL-CARGO SERVICES\nWESTBOUND\nEASTBOUND\ndP NEW TORK,.. Kennedy International\n07 00\nIp) HONOLULU\n{ dep\nSYDNEY\nAUCKLAND\n23400\nAFT SYDNEY\nLATIN AMERICA ALL-CARGO SERVICES\n08 45\nOn 1S 0s 40\n07.45\n22.00\n10 80 20 0 1700 1750\n23 35\n12'50\n21 10\nWESTBOUND\n-SDELHI\nII BERLIN. Terel\nOLONDON. Heathrow\n*I FRANKFURT\nI BRUSSELS\n•A LONDON, Heathrow…_\nNEW YORK, J. F. Kennedy International\n145t\nsitu\n2330\n{ ap\nder\n{ dep\n{ #р\n2923\nTôi\n22000\nSaos\n10 50/\n12A30\n14335\nSASS\n14 50\nMAR\nSOUTHBOUND\nNEW YORK, .. Kennedy International\nMARACAIBO\nPORT OLSTAIN (TRINIDAD TOBAGO\nBUENOS AIRES, Exeixa\nBUENOS AIRES, Exeiza\nPORT OF SPAIN (TRINIDAD-TOBAGO)\nGUATEMALA CITY\nMIAMI\nNEW YORK, J. F. Kennedy International\n33\n21 20\n23145\n423\n15 00 15 35 12 20\n17 45 14 30 05 50 05 35\n2355"
    ],
    "millsfield:images_texts_ids": [
      1527853647
    ],
    "millsfield:primary_image": 1527853647,
    "sfomuseum:accession_number": "2005.127.002.002",
    "sfomuseum:airline": "Pan American World Airways",
    "sfomuseum:category": "Scheduling / Ticketing",
    "sfomuseum:collection": "Aviation Archive",
    "sfomuseum:creditline": "Gift of the William Hough Collection",
    "sfomuseum:date": "1981",
    "sfomuseum:date_acquired": "2006-12-14",
    "sfomuseum:daterange_end": "1981-12-31",
    "sfomuseum:daterange_start": "1981-01-01",
    "sfomuseum:description": "Cargo schedule for Pan American World Airways; effective January 1, 1981; single-sided on green paper; with information on services in the Atlantic, Latin America and Pacific; part of 11 issues dated 1980-1981.",
    "sfomuseum:dimensions": "14 x 8 1/2 inches (35.6 x 21.6 cm)",
    "sfomuseum:media_ids": [
      1527853647
    ],
    "sfomuseum:medium": "paper, ink",
    "sfomuseum:placetype": "object",
    "sfomuseum:publication": ": , 1981.",
    "sfomuseum:subcategory": "Timetable",
    "wof:depicts": [
      1159284991,
      1159286839,
      1159284989
    ],
    "wof:name": "timetable: Pan American World Airways, cargo schedule",
    "wof:placetype": "custom",
    "wof:placetype_alt": "object"
  },
  "geometry": {"coordinates":[-122.386155,37.616357],"type":"Point"}
}
