{
  "type": "Feature",
  "properties": {
    "date:cessation_lower": "1999-01-01",
    "date:cessation_upper": "1999-12-31",
    "date:inception_lower": "1999-01-01",
    "date:inception_upper": "1999-12-31",
    "iso:country": "XX",
    "sfomuseum:accession_number": "99-1487",
    "sfomuseum:airline": "TWA (Trans World Airlines)",
    "sfomuseum:author": "Milton, Pat",
    "sfomuseum:callnumber": "TL553.5 .M55 1999",
    "sfomuseum:category": "Book",
    "sfomuseum:collection": "Aviation Library",
    "sfomuseum:date": "c. 1999",
    "sfomuseum:daterange_end": "2004-12-31",
    "sfomuseum:daterange_start": "1994-01-01",
    "sfomuseum:description": "xii, 368 p. : ill. ; 25 cm.",
    "sfomuseum:description_library": "xii, 368 p. : ill. ; 25 cm.",
    "sfomuseum:medium": "paper, ink",
    "sfomuseum:notes_library": "Includes index.",
    "sfomuseum:placetype": "object",
    "sfomuseum:publication": "New York: Random House, c. 1999.",
    "sfomuseum:publisher": "Random House",
    "sfomuseum:publisher_location": "New York",
    "sfomuseum:subcategory": "Book",
    "sfomuseum:subject": "Aircraft accidents New York (State) Long Island Region.Aircraft Accidents North Atlantic Ocean.Aircraft accidents Investigation United StatesTerrorism.TWA Flight 800 Crash, 1996.",
    "wof:depicts": [
      1159287531,
      1159285393
    ],
    "wof:name": "In the blink of an eye: the FBI investigation of TWA flight 800",
    "wof:placetype": "venue"
  },
  "geometry": {"coordinates":[-122.386155,37.616357],"type":"Point"}
}
