{
  "type": "Feature",
  "properties": {
    "date:cessation_lower": "1946-01-01",
    "date:cessation_upper": "1946-12-31",
    "date:inception_lower": "1946-01-01",
    "date:inception_upper": "1946-12-31",
    "iso:country": "XX",
    "sfomuseum:accession_number": "2004.016.001 a c",
    "sfomuseum:airline": "Pan American World Airways",
    "sfomuseum:callnumber": "HE9803.P36 S89 1946 SC",
    "sfomuseum:category": "Book",
    "sfomuseum:collection": "Aviation Library",
    "sfomuseum:creditline": "The Estate of Fred Nott ",
    "sfomuseum:date": "1946",
    "sfomuseum:daterange_end": "1946-12-31",
    "sfomuseum:daterange_start": "1946-01-01",
    "sfomuseum:description": "Survey for and description of landing fields in the South Pacific\r3 Volumes:\ra. Report of survey flight, South Pacific; January 6 - 29, 1946\rb. Report of South Pacific Proving Flight #2 Feb. 12 - 25, 1946\rc. Report of South Pacific Proving Flight #3 Mar. 1 - 17, 1946",
    "sfomuseum:medium": "paper, ink",
    "sfomuseum:placetype": "object",
    "sfomuseum:publication": ": , 1946.",
    "sfomuseum:subcategory": "Book",
    "wof:depicts": [
      1159284989,
      1159286839
    ],
    "wof:name": "Reports of flight surveys in the South Pacific, 1946",
    "wof:placetype": "custom",
    "wof:placetype_alt": "object"
  },
  "geometry": {"coordinates":[-122.386155,37.616357],"type":"Point"}
}
