{
  "type": "Feature",
  "properties": {
    "date:cessation_lower": "1975-01-01",
    "date:cessation_upper": "1975-12-31",
    "date:inception_lower": "1975-01-01",
    "date:inception_upper": "1975-12-31",
    "iso:country": "US",
    "millsfield:images": [
      1527857323,
      1527857327
    ],
    "millsfield:primary_image": 1527857323,
    "sfomuseum:accession_number": "1996.33.01",
    "sfomuseum:airline": "Pan American World Airways",
    "sfomuseum:category": "Promotional",
    "sfomuseum:collection": "Aviation Museum",
    "sfomuseum:continent": "North America",
    "sfomuseum:country": "United States",
    "sfomuseum:creditline": "Gift of Ronald V. Wilson",
    "sfomuseum:date": "c. 1975",
    "sfomuseum:daterange_end": "1980-12-31",
    "sfomuseum:daterange_start": "1970-01-01",
    "sfomuseum:description": "Airline bag issued by Pan American World Airways; Small duffle bag with drawstring closure; white background with horizontal gray pinstripes throughout; blue “Pan Am” globe logo followed by “Hawaiian Holiday” printed on both sides.\r",
    "sfomuseum:dimensions": "11 1/4 x 9 inches dia. (28.6 x 22.9 cm dia.)",
    "sfomuseum:maker": "Natco Products Corporation",
    "sfomuseum:media_ids": [
      1527857323,
      1527857327
    ],
    "sfomuseum:medium": "synthetic textile, plastic, cotton, metal, pigment",
    "sfomuseum:placetype": "object",
    "sfomuseum:subcategory": "Airline Bag",
    "wof:depicts": [
      1159284989
    ],
    "wof:name": "airline bag: Pan American World Airways",
    "wof:placetype": "venue"
  },
  "geometry": {"coordinates":[-122.386155,37.616357],"type":"Point"}
}
