{
  "type": "Feature",
  "properties": {
    "date:cessation_lower": "1948-12-31",
    "date:cessation_upper": "1948-12-31",
    "date:inception_lower": "1948-01-01",
    "date:inception_upper": "1948-01-01",
    "iso:country": "XX",
    "sfomuseum:accession_number": "2011.032.0210",
    "sfomuseum:category": "Photograph",
    "sfomuseum:collection": "Aviation Archive",
    "sfomuseum:creditline": "Transfer",
    "sfomuseum:date": "1948",
    "sfomuseum:daterange_end": "1948-12-31",
    "sfomuseum:daterange_start": "1948-01-01",
    "sfomuseum:description": "From attached handwritten note: “03650 / 1-16-48 / Admin. bldg. lobby”. Black and white photographic negative depicting interior view of passenger waiting room from upper level mezzanine at staircase, San Francisco Airport, January 16, 1948; portion of staircase handrail visible in foreground at lower left; passengers and employees visible on main floor, surrounded by ticket counters for United Air Lines, TWA, American Airlines, and Western Airlines; chandelier suspended from ceiling.",
    "sfomuseum:media_ids": [
      1527821617
    ],
    "sfomuseum:medium": "negative",
    "sfomuseum:placetype": "object",
    "sfomuseum:subcategory": "Negative",
    "wof:name": "negative: San Francisco Airport, passenger waiting room",
    "wof:placetype": "venue"
  },
  "geometry": {"coordinates":[-122.386155,37.616358],"type":"Point"}
}
