{
  "type": "Feature",
  "properties": {
    "date:cessation_lower": "1950-01-01",
    "date:cessation_upper": "1950-12-31",
    "date:inception_lower": "1950-01-01",
    "date:inception_upper": "1950-12-31",
    "iso:country": "XX",
    "millsfield:images": [
      1527856201,
      1527856203
    ],
    "millsfield:images_texts": [
      "Tempting, flavorful luncheons are popular summertime\nfeatures aboard United Mainliners ... on the Main Line\nAirway to all of America's leading vacationlands.\nUNITED AIR LINES • ROUTE OF THE MAINLINERS • UNITED AIR LINES • ROUTE OF THE MAINLINERS\nPOST CARD\nSPEED\nYOUR MAIL\nBY AIR\n2014 095 217",
      "luncheon menu\nThis menu prepared in United Air Lines Flight Kitchen\nat Omaha, Albert Reber, Chef.\nLorraine Salad with Tomato Wedges\nLorenzo Dressing\nGalantine of Turkey, Garni\nPoppy Seed Roll\nOld Fashioned Apple and Raisin Pie\nCoffee\nTea\nDinner Mint\nMilk\nUNITED AIR LINES"
    ],
    "millsfield:images_texts_ids": [
      1527856201,
      1527856203
    ],
    "millsfield:primary_image": 1527856203,
    "sfomuseum:accession_number": "2014.095.217",
    "sfomuseum:airline": "United Air Lines",
    "sfomuseum:category": "Passenger Amenity, Archive",
    "sfomuseum:collection": "Aviation Archive",
    "sfomuseum:creditline": "Gift of Thomas G. Dragges",
    "sfomuseum:date": "c. 1950",
    "sfomuseum:date_acquired": "2015-01-06",
    "sfomuseum:daterange_end": "1955-12-31",
    "sfomuseum:daterange_start": "1945-01-01",
    "sfomuseum:description": "Menu issued by United Air Lines; blue postcard with color illustration of meal service; menu items include galantine of turkey and Lorraine salad; menu prepared in Omaha; no menu number; undated.",
    "sfomuseum:dimensions": "3 1/2 x 5 1/2 inches (8.9 x 14 cm)",
    "sfomuseum:media_ids": [
      1527856201,
      1527856203
    ],
    "sfomuseum:medium": "paper, ink",
    "sfomuseum:placetype": "object",
    "sfomuseum:publication": ": , c. 1950.",
    "sfomuseum:subcategory": "Menu",
    "wof:depicts": [
      1159285415,
      1159288779
    ],
    "wof:name": "menu: United Air Lines",
    "wof:placetype": "custom",
    "wof:placetype_alt": [
      "object"
    ]
  },
  "geometry": {"coordinates":[-122.386155,37.616357],"type":"Point"}
}
