{
  "type": "Feature",
  "properties": {
    "date:cessation_lower": "1985-12-31",
    "date:cessation_upper": "1985-12-31",
    "date:inception_lower": "1985-01-01",
    "date:inception_upper": "1985-01-01",
    "iso:country": "XX",
    "sfomuseum:accession_number": "2003.105.420",
    "sfomuseum:airline": "TWA (Trans World Airlines)",
    "sfomuseum:category": "Scheduling / Ticketing",
    "sfomuseum:collection": "Aviation Archive",
    "sfomuseum:creditline": "Gift of Craig Lynes",
    "sfomuseum:date": "1985",
    "sfomuseum:daterange_end": "1985-12-31",
    "sfomuseum:daterange_start": "1985-01-01",
    "sfomuseum:description": "TWA Royal Ambassador First Class ticket jacket(6/1985)",
    "sfomuseum:dimensions": "8 1/2 x 4 inches (21.6 x 10.2 cm)",
    "sfomuseum:medium": "paper, ink",
    "sfomuseum:placetype": "object",
    "sfomuseum:subcategory": "Ticket Jacket / Ticket",
    "wof:depicts": [
      1159285393
    ],
    "wof:name": "ticket jacket: TWA (Trans World Airlines)",
    "wof:placetype": "venue"
  },
  "geometry": {"coordinates":[-122.386155,37.616357],"type":"Point"}
}
