{
  "type": "Feature",
  "properties": {
    "date:cessation_lower": "1992-01-01",
    "date:cessation_upper": "1992-12-31",
    "date:inception_lower": "1992-01-01",
    "date:inception_upper": "1992-12-31",
    "iso:country": "XX",
    "millsfield:images": [
      1527846175,
      1527846177
    ],
    "millsfield:images_texts": [
      "E\nN\nU\nCONNOISSEUR\nA\nU UnITED",
      "UNC\nCocktail Service\nA ramekin of Mixed Nuts\nto accompany your preferred Cocktail or Beverage\nCanapés\nSevruga Caviar on Pastry, Avocado and Salmon Mousse Canapé\nand Ham and Cream Cheese Canapé\nSalad\nHearts of Romaine, Red and Oak Leaf Lettuce\nwith Red and Yellow Pepper;\nSherry or Caesar Dressing\nRolls and Sweet Butter\nFilet Mignon\nOffered with Café de Paris Butter;\nPotatoes Dauphinoise, Carrots Château\nand Green Beans wrapped in Prosciutto\nBreast of Chicken, Apple Ginger Chutney\nAccompanied by Green Beans wrapped in Prosciutto,\nArtichoke Bottoms with Marron Puree\nand Carrots Château\nCONNOISSPUR SELECTION\nAlaskan Halibut\nGrilled Fillet of Halibut\nserved with fresh Tomato Salsa, grilled Baby Zucchini\nand a blend of Corn and black beans\nCheese Sampler\nsulton andicontma Cheese\nwith Crackers and a fresh Fruit Garnish\nSacher Torte\nChocolate Torte layered with Apricot Jam\nand topped with Chocolate leing\nGodiva Chocolates\n100% Colombian Coffee"
    ],
    "millsfield:images_texts_ids": [
      1527846175,
      1527846177
    ],
    "millsfield:primary_image": 1527846175,
    "sfomuseum:accession_number": "2006.059.307.004",
    "sfomuseum:airline": "United Airlines",
    "sfomuseum:category": "Passenger Amenity, Archive",
    "sfomuseum:collection": "Aviation Archive",
    "sfomuseum:creditline": "Gift of the Paul Edward Fair Estate",
    "sfomuseum:date": "1992",
    "sfomuseum:date_acquired": "2006-10-19",
    "sfomuseum:daterange_end": "1992-12-31",
    "sfomuseum:daterange_start": "1992-01-01",
    "sfomuseum:description": "Menu issued by United Airlines, Madrid - North America route; gray and dark red cover; menu items include filet mignon and chicken breast; menu number: MAD-USA LD63-S67 2801-2; in Spanish; class: Connoisseur (business); date: 392.",
    "sfomuseum:dimensions": "8 1/2 x 8 1/2 inches (21.6 x 21.6 cm)",
    "sfomuseum:media_ids": [
      1527846175,
      1527846177
    ],
    "sfomuseum:medium": "paper, ink",
    "sfomuseum:placetype": "object",
    "sfomuseum:publication": ": , 1992.",
    "sfomuseum:subcategory": "Menu",
    "wof:depicts": [
      1159285413,
      1159288779
    ],
    "wof:name": "menu: United Airlines, Connoisseur (Business) Class",
    "wof:placetype": "custom",
    "wof:placetype_alt": "object"
  },
  "geometry": {"coordinates":[-122.386155,37.616357],"type":"Point"}
}
