{
  "type": "Feature",
  "properties": {
    "date:cessation_lower": "1970-01-01",
    "date:cessation_upper": "1979-12-31",
    "date:inception_lower": "1970-01-01",
    "date:inception_upper": "1979-12-31",
    "iso:country": "XX",
    "millsfield:images": [
      1527842093
    ],
    "millsfield:primary_image": 1527842093,
    "sfomuseum:accession_number": "1998.157.167",
    "sfomuseum:airline": "Pan American World Airways",
    "sfomuseum:category": "Passenger Amenity",
    "sfomuseum:collection": "Aviation Archive",
    "sfomuseum:creditline": "Gift of The Henry Steiner Air Sickness Bag Collection",
    "sfomuseum:date": "c. 1970s",
    "sfomuseum:date_acquired": "1999-07-13",
    "sfomuseum:daterange_end": "1984-12-31",
    "sfomuseum:daterange_start": "1965-01-01",
    "sfomuseum:description": "Flat bottom, wire closure. Blue bag, white print. Pan Am world logo in upper right corner. \"Waste Bag\" in white on upper left corner. Design on both sides. Attached handwritten note: \"Pan Am (Made in W. Germany).\"\rAirsickness bag issued by ; COLOR and DESC bag; gusset wedge / flat bottom, wire / no closure.",
    "sfomuseum:dimensions": "9 1/4 x 6 1/4 inches (23.5 x 15.9 cm)",
    "sfomuseum:media_ids": [
      1527842093
    ],
    "sfomuseum:medium": "paper, metal, ink",
    "sfomuseum:placetype": "object",
    "sfomuseum:publication": ": , c. 1970s.",
    "sfomuseum:subcategory": "Airsickness Bag",
    "wof:depicts": [
      1159284989
    ],
    "wof:name": "airsickness bag: Pan American Airways",
    "wof:placetype": "venue"
  },
  "geometry": {"coordinates":[-122.386155,37.616357],"type":"Point"}
}
