{
  "type": "Feature",
  "properties": {
    "date:cessation_lower": "1973-12-31",
    "date:cessation_upper": "1973-12-31",
    "date:inception_lower": "1973-01-01",
    "date:inception_upper": "1973-01-01",
    "iso:country": "XX",
    "sfomuseum:accession_number": "2005.009.050",
    "sfomuseum:author": "Gann, Ernest Kellogg",
    "sfomuseum:callnumber": "PS3513.A56 B36 1973",
    "sfomuseum:category": "Book",
    "sfomuseum:collection": "Aviation Library",
    "sfomuseum:creditline": "Purchase",
    "sfomuseum:date": "1973",
    "sfomuseum:daterange_end": "1973-12-31",
    "sfomuseum:daterange_start": "1973-01-01",
    "sfomuseum:description": "316 p. 25 cm.",
    "sfomuseum:medium": "paper, ink",
    "sfomuseum:placetype": "object",
    "sfomuseum:publisher": "Simon \u0026 Schuster",
    "sfomuseum:publisher_location": "New York",
    "sfomuseum:subcategory": "Book",
    "wof:name": "Band of brothers",
    "wof:placetype": "venue"
  },
  "geometry": {"coordinates":[-122.386155,37.616357],"type":"Point"}
}
