{
  "type": "Feature",
  "properties": {
    "date:cessation_lower": "1970-01-01",
    "date:cessation_upper": "1979-12-31",
    "date:inception_lower": "1970-01-01",
    "date:inception_upper": "1979-12-31",
    "iso:country": "XX",
    "sfomuseum:accession_number": "1995.35.86",
    "sfomuseum:airline": "Pan American World Airways",
    "sfomuseum:category": "Promotional, Museum",
    "sfomuseum:collection": "Aviation Museum",
    "sfomuseum:creditline": "Gift of Beatrice H. Springer",
    "sfomuseum:date": "1970s",
    "sfomuseum:date_acquired": "1997-07-06",
    "sfomuseum:daterange_end": "1979-12-31",
    "sfomuseum:daterange_start": "1970-01-01",
    "sfomuseum:description": "Lighter issued by Pan American World Airways; silver brushed metal lighter with hinged top and blue globe logo on front with text, \"Services of Supply / Overseas Division\"; text on reverse, \"An airplane is a large group of spare parts flying in close formation\"; Zippo-style with fuel reservoir, flint and wick; \"Penguin high quality lighter, no. 11857\" inscribed on base.",
    "sfomuseum:dimensions": "2 1/8 x 1 1/2 x 3/8 inches (5.4 x 3.8 x 1 cm)",
    "sfomuseum:maker": "Penguin",
    "sfomuseum:medium": "metal",
    "sfomuseum:placetype": "object",
    "sfomuseum:publication": ": , 1970s.",
    "sfomuseum:subcategory": "Lighter",
    "wof:depicts": [
      1159284989,
      1159286839
    ],
    "wof:name": "lighter: Pan American Airways",
    "wof:placetype": "custom",
    "wof:placetype_alt": "object"
  },
  "geometry": {"coordinates":[-122.386155,37.616357],"type":"Point"}
}
