{
  "type": "Feature",
  "properties": {
    "date:cessation_lower": "1964-01-01",
    "date:cessation_upper": "1964-12-31",
    "date:inception_lower": "1964-01-01",
    "date:inception_upper": "1964-12-31",
    "iso:country": "US",
    "millsfield:images": [
      1527818385,
      1527818387
    ],
    "millsfield:images_texts": [
      "SAN FRANCISCO /\nOAKLAND\nEFFECIVERONE ISS\nUNITED\nUNITED JETS\nTO HAWAII. . .\nECONOMY COACH JETS\nONLY $100\nCUSTOM COACH JETS\nONLY $MO*\n(see map pago)",
      "FOR INFORMATION OR RESERVATIONS CALL\nYOUR TRAVEL AGENT OR UNITED AIR LINES\nSan Francisco...\n000.0 E7122100\naskano.......\n500000000200000000500000000000.000000 83555500\nRichmond,.. BE 5.730\nMarin county....\n...DU 8-3774\nSan Jose........241-8565\nSan Marco...\n666660amaras.040000. 981:6933\nRedwood City. ....EM 6-8001\n..813-1004\nYou can check your bagooge direcly to deslination from the\nAirline termnaurend op sin check.in.\nTrelus arancest rescro\nano selecson as appacadie, and grcund transconationo\nSan Francisro international amponawaidols.at\nDowntown airline Terminal\nsip Obarrell Street, San\nJUNE-1964\nJULY_1964\nS MT W T\nS\n• 18\n58%0\n88 0\nEcarcoical Family Plan availssio 12:60 Most Mantay trough 630 A.M. Fritay.\nSHIP ON UNITED'S\nDC-8F JET FREIGHTERS\nNONSTOP TO CHICAGO\nAND NEW YORK\n(sco schedules inside back cover)"
    ],
    "millsfield:images_texts_ids": [
      1527818385,
      1527818387
    ],
    "millsfield:primary_image": 1527818385,
    "sfomuseum:accession_number": "1999.015.155 a b",
    "sfomuseum:airline": "United Air Lines",
    "sfomuseum:category": "Scheduling / Ticketing",
    "sfomuseum:collection": "Aviation Archive",
    "sfomuseum:continent": "North America",
    "sfomuseum:country": "United States",
    "sfomuseum:creditline": "Gift of Homer Hudson",
    "sfomuseum:date": "1964",
    "sfomuseum:date_acquired": "1999-07-06",
    "sfomuseum:daterange_end": "1964-12-31",
    "sfomuseum:daterange_start": "1964-01-01",
    "sfomuseum:description": "City timetable issued by United Air Lines for service to and from San Francisco and Oakland, effective June 1, 1964; white and blue cover with promoting low-cost fares to Hawaii.",
    "sfomuseum:dimensions": "9 x 4 inches (22.9 x 10.2 cm)",
    "sfomuseum:media_ids": [
      1527818385,
      1527818387
    ],
    "sfomuseum:medium": "paper, ink",
    "sfomuseum:placetype": "object",
    "sfomuseum:publication": ": , 1964.",
    "sfomuseum:subcategory": "Timetable",
    "wof:depicts": [
      1159285415,
      85921881,
      1159288779,
      85688637,
      85633793
    ],
    "wof:name": "timetable: United Air Lines, San Francisco and Oakland",
    "wof:placetype": "custom",
    "wof:placetype_alt": "object"
  },
  "geometry": {"coordinates":[-122.386155,37.616357],"type":"Point"}
}
