{
  "type": "Feature",
  "properties": {
    "date:cessation_lower": "1964-01-01",
    "date:cessation_upper": "1964-12-31",
    "date:inception_lower": "1964-01-01",
    "date:inception_upper": "1964-12-31",
    "iso:country": "US",
    "millsfield:images": [
      1527818385,
      1527818387
    ],
    "millsfield:images_texts": [
      "SAN FRANCISCO /\nOAKLAND\nEFFECTIVE JUNG 1, 1984\nUNITED\nUNITED JETS\nTO HAWAII . ..\nECONOMY COACH JETS\nONLY $100\nCUSTOM COACH JETS\nONLY $110*\n(see map page)",
      "FOR INFORMATION OR RESERVATIONS CALL\nYOUR TRAVEL AGENT OR UNITED AIR LINES.\nSan Francisco.\nOakland..\nEX 7-2100\nHawward\nMarin County.......\nDU 8.3774\n.241-8565\nvallejo.\nWalnut Creek.\n613-1024\n. YE 4-1600\ntou can check your bago80e direely to destination from the\nAirline Terminal and obtain check in, including soat reserva\ntion and selection as applicable, and ground transportation to\nSan Francisco International Airport available\nDowntown Airline Terminal\n375 O'Farrell Street, San Francisco\nS\nJUNE-1964\nTW\nF S\n144415\n9\n10\n11\n12\n13\n21\n16\n22\n23\n19\n20\n24 25 26 27\n20 2U\n30\nJULY—1964\nSM\nTWTFS\n2\n3\n11\n12\n19\n18\n14 15 16\n17\n18\n26\n20\n27\n21\n24 25\n28\n29\n30\n31\nForested only Saut He Ma Ma 60 AM Ties.\n4115-510-6/04\nSHIP ON UNITED'S\nDC-8F JET FREIGHTERS\nNONSTOP TO CHICAGO\nAND NEW YORK\n(sco schedules inside back cover)"
    ],
    "millsfield:images_texts_ids": [
      1527818385,
      1527818387
    ],
    "millsfield:primary_image": 1527818385,
    "sfomuseum:accession_number": "1999.015.155 a b",
    "sfomuseum:airline": "United Air Lines",
    "sfomuseum:category": "Scheduling / Ticketing",
    "sfomuseum:collection": "Aviation Archive",
    "sfomuseum:continent": "North America",
    "sfomuseum:country": "United States",
    "sfomuseum:creditline": "Gift of Homer Hudson",
    "sfomuseum:date": "1964",
    "sfomuseum:date_acquired": "1999-07-06",
    "sfomuseum:daterange_end": "1964-12-31",
    "sfomuseum:daterange_start": "1964-01-01",
    "sfomuseum:description": "City timetable issued by United Air Lines for service to and from San Francisco and Oakland, effective June 1, 1964; white and blue cover with promoting low-cost fares to Hawaii.",
    "sfomuseum:dimensions": "9 x 4 inches (22.9 x 10.2 cm)",
    "sfomuseum:media_ids": [
      1527818385,
      1527818387
    ],
    "sfomuseum:medium": "paper, ink",
    "sfomuseum:placetype": "object",
    "sfomuseum:publication": ": , 1964.",
    "sfomuseum:subcategory": "Timetable",
    "wof:depicts": [
      1159285415,
      85921881,
      1159288779,
      85688637,
      85633793
    ],
    "wof:name": "timetable: United Air Lines, San Francisco and Oakland",
    "wof:placetype": "custom",
    "wof:placetype_alt": [
      "object"
    ]
  },
  "geometry": {"coordinates":[-122.386155,37.616357],"type":"Point"}
}
