{
  "type": "Feature",
  "properties": {
    "date:cessation_lower": "1968-12-31",
    "date:cessation_upper": "1968-12-31",
    "date:inception_lower": "1968-01-01",
    "date:inception_upper": "1968-01-01",
    "iso:country": "XX",
    "sfomuseum:accession_number": "2001.039.805",
    "sfomuseum:airport": "London Gatwick Airport",
    "sfomuseum:author": "Allward, Maurice F.",
    "sfomuseum:callnumber": "TL726.6.G72 A55 1968",
    "sfomuseum:category": "Book",
    "sfomuseum:collection": "Aviation Library",
    "sfomuseum:creditline": "Gift of David A. Abercrombie in memory of Stanley A. Abercrombie",
    "sfomuseum:date": "1968",
    "sfomuseum:daterange_end": "1968-12-31",
    "sfomuseum:daterange_start": "1968-01-01",
    "sfomuseum:description": "36 p. p., illus., 24 cm.",
    "sfomuseum:medium": "paper, ink",
    "sfomuseum:placetype": "object",
    "sfomuseum:publisher": "Ian Allan",
    "sfomuseum:publisher_location": "London",
    "sfomuseum:subcategory": "Book",
    "sfomuseum:subject": "Airports -- London -- Heathrow.  \rAirports -- London -- Gatwick.\rAirports -- London -- Stansted.",
    "wof:depicts": [
      102556703,
      102556713
    ],
    "wof:name": "London's airports: Heathrow, Gatwick, Stansted",
    "wof:placetype": "venue"
  },
  "geometry": {"coordinates":[-122.386155,37.616357],"type":"Point"}
}
