{
  "type": "Feature",
  "properties": {
    "date:cessation_lower": "1910-01-01",
    "date:cessation_upper": "1910-12-31",
    "date:inception_lower": "1910-01-01",
    "date:inception_upper": "1910-12-31",
    "iso:country": "XX",
    "sfomuseum:accession_number": "2000.160.0517",
    "sfomuseum:author": "Hearne, R. P",
    "sfomuseum:callnumber": "UG630 .H43 1910 c.1 SC",
    "sfomuseum:category": "Book",
    "sfomuseum:collection": "Aviation Library",
    "sfomuseum:creditline": "Collection of SFO Museum, The Tony Bill Aviation Library Collection",
    "sfomuseum:date": "1910",
    "sfomuseum:date_acquired": "1999-05-18",
    "sfomuseum:daterange_end": "1910-12-31",
    "sfomuseum:daterange_start": "1910-01-01",
    "sfomuseum:description": "2 p. æ., vii-xiviii, 324 p. incl. maps, tables, diagrs. 73 pl. (incl. Front.) 22 1/2 cm.",
    "sfomuseum:description_library": "2 p. æ., vii-xiviii, 324 p. incl. maps, tables, diagrs. 73 pl. (incl. Front.) 22 1/2 cm.",
    "sfomuseum:medium": "paper, ink",
    "sfomuseum:placetype": "object",
    "sfomuseum:publication": "London; New York: J. Lane company, 1910.",
    "sfomuseum:publisher": "J. Lane company",
    "sfomuseum:publisher_location": "London; New York",
    "sfomuseum:subcategory": "Book",
    "wof:name": "Airships in peace and war, being the second edition of Aerial warfare; with seven new chapters",
    "wof:placetype": "custom",
    "wof:placetype_alt": [
      "object"
    ]
  },
  "geometry": {"coordinates":[-122.386155,37.616357],"type":"Point"}
}
