{
  "type": "Feature",
  "properties": {
    "date:cessation_lower": "1935-11-22",
    "date:cessation_upper": "1935-11-22",
    "date:inception_lower": "1935-11-22",
    "date:inception_upper": "1935-11-22",
    "iso:country": "XX",
    "millsfield:images": [
      1527833795,
      1527833801
    ],
    "millsfield:images_texts": [
      "GARNETT YOUNG AND COMPANY\nGENERAL OFFICES\n390 FOURTH STREET\nSAN FRANCISCO, CALIF\nTRST FLIGHT\nSAN\nNOV\n22\n1 PM\n1935\nCALIF\nVIA AIR MAIL\n50.\n00\nROUTE 14\nTHE HAWAITAN ELEC. CO., LTD.,\nHONOLULU, T. H.\nHONOLULU\nVIA FIRST CONTRACT TRANS-PACIFIC\nFLIGHT SAN FRANCISCO TO HONOLULU",
      "14 →\n* 1000\n• NOV 23\n1935\n140.1025"
    ],
    "millsfield:images_texts_ids": [
      1527833795,
      1527833801
    ],
    "millsfield:primary_image": 1527833795,
    "sfomuseum:accession_number": "2012.149.1625",
    "sfomuseum:airline": "Pan American Airways",
    "sfomuseum:category": "Philately",
    "sfomuseum:collection": "Aviation Archive",
    "sfomuseum:creditline": "Gift of the Captain John B. Russell Family",
    "sfomuseum:date": "11/22/1935",
    "sfomuseum:date_acquired": "2013-05-31",
    "sfomuseum:daterange_end": "1935-11-22",
    "sfomuseum:daterange_start": "1935-11-22",
    "sfomuseum:description": "Airmail flight cover commemorating first Pan American Airways transpacific airmail flight between San Francisco and Manila, San Francisco (Alameda) to Honolulu leg, FAM-14; green cachet with image of Martin M-130 and sailing ship; postmarked November 22, 1935, San Francisco with four-bar cancellation over two blue 25-cent stamps; backstamp: November 23, 1935, Honolulu.",
    "sfomuseum:dimensions": "4 x 9 1/2 inches (10.2 x 24.1 cm)",
    "sfomuseum:media_ids": [
      1527833795,
      1527833801
    ],
    "sfomuseum:medium": "paper, ink",
    "sfomuseum:placetype": "object",
    "sfomuseum:publication": ": , 11/22/1935.",
    "sfomuseum:subcategory": "Airmail Flight Cover",
    "wof:depicts": [
      1159291191,
      1159284991,
      1159286839
    ],
    "wof:name": "airmail flight cover: Pan American Airways, FAM-14, first transpacific airmail flight, San Francisco - Honolulu route",
    "wof:placetype": "custom",
    "wof:placetype_alt": [
      "object"
    ]
  },
  "geometry": {"coordinates":[-122.386155,37.616357],"type":"Point"}
}
