{
  "type": "Feature",
  "properties": {
    "iso:country": "XX",
    "sfomuseum:accession_number": "2006.010.345",
    "sfomuseum:airline": "TWA (Trans World Airlines)",
    "sfomuseum:airport": "Saint Louis Lambert International Airport",
    "sfomuseum:category": "Scheduling / Ticketing",
    "sfomuseum:collection": "Aviation Archive",
    "sfomuseum:creditline": "Gift of the William Hough Collection",
    "sfomuseum:description": "Rectangular shape, bright red background, wide eyelet, black \"STL\" near eyelet, two black \"TWA\" near eyelet, black \"This Bag Due to Transfer at STL,\" box with black \"Originating flight\" written \"509\"; white and bright red background with same  two black \"TWA\" near eyelet, black \"This Bag Due to Transfer at STL\" on back.",
    "sfomuseum:dimensions": "6 x 1 1/4 inches (15.2 x 3.2 cm)",
    "sfomuseum:medium": "paper, ink",
    "sfomuseum:placetype": "object",
    "sfomuseum:subcategory": "Baggage Destination / Handling Tag",
    "wof:depicts": [
      1159285393,
      102525961
    ],
    "wof:name": "baggage destination tag: TWA (Trans World Airlines)",
    "wof:placetype": "venue"
  },
  "geometry": {"coordinates":[-122.386155,37.616357],"type":"Point"}
}
