{
  "type": "Feature",
  "properties": {
    "date:cessation_lower": "1976-01-01",
    "date:cessation_upper": "1976-12-31",
    "date:inception_lower": "1976-01-01",
    "date:inception_upper": "1976-12-31",
    "iso:country": "XX",
    "millsfield:images": [
      1746680555
    ],
    "millsfield:primary_image": 1746680555,
    "sfomuseum:accession_number": "2002.135.013.002",
    "sfomuseum:airline": "TWA (Trans World Airlines)",
    "sfomuseum:category": "Scheduling / Ticketing",
    "sfomuseum:collection": "Aviation Archive",
    "sfomuseum:creditline": "Gift of Thomas G. Dragges",
    "sfomuseum:date": "1976",
    "sfomuseum:daterange_end": "1976-12-31",
    "sfomuseum:daterange_start": "1976-01-01",
    "sfomuseum:description": "Timetable issued by TWA (Trans World Airlines), effective October 31, 1976; white cover with text promoting TWA’s on-time performance.",
    "sfomuseum:dimensions": "9 x 4 inches (22.9 x 10.2 cm)",
    "sfomuseum:medium": "paper, ink",
    "sfomuseum:placetype": "object",
    "sfomuseum:publication": ": , 1976.",
    "sfomuseum:subcategory": "Timetable",
    "wof:depicts": [
      1159285393
    ],
    "wof:name": "timetable: TWA (Trans World Airlines)",
    "wof:placetype": "venue"
  },
  "geometry": {"coordinates":[-122.386155,37.616357],"type":"Point"}
}
