{
  "type": "Feature",
  "properties": {
    "date:cessation_lower": "2012-01-01",
    "date:cessation_upper": "2012-12-31",
    "date:inception_lower": "2012-01-01",
    "date:inception_upper": "2012-12-31",
    "iso:country": "XX",
    "millsfield:images": [
      1527854259
    ],
    "millsfield:images_texts": [
      "U\nN\nUNITED\nні птит\nD\nHOLLYWOOD\nBoeing 787 Dreamliner*\nFirst to Fly in North America\nUNITED"
    ],
    "millsfield:images_texts_ids": [
      1527854259
    ],
    "millsfield:primary_image": 1527854259,
    "sfomuseum:accession_number": "2012.130.004",
    "sfomuseum:aircraft": "Boeing 787 Dreamliner",
    "sfomuseum:airline": "United Airlines",
    "sfomuseum:category": "Promotional, Archive",
    "sfomuseum:collection": "Aviation Archive",
    "sfomuseum:creditline": "Transfer from City and County of San Francisco",
    "sfomuseum:date": "2012",
    "sfomuseum:date_acquired": "2012-09-11",
    "sfomuseum:daterange_end": "2012-12-31",
    "sfomuseum:daterange_start": "2012-01-01",
    "sfomuseum:description": "Poster issued by United Airlines promoting the Boeing 787 Dreamliner; color illustration of aircraft at center over montage of musical score and clouds, with band of photographic images of North American landmarks at bottom and text, “Boeing 787 Dreamliner / first to fly North America”.",
    "sfomuseum:dimensions": "6 1/2 x 19 inches (16.5 x 48.3 cm)",
    "sfomuseum:media_ids": [
      1527854259
    ],
    "sfomuseum:medium": "paper, ink",
    "sfomuseum:placetype": "object",
    "sfomuseum:publication": ": , 2012.",
    "sfomuseum:subcategory": "Advertisement, 2D",
    "wof:depicts": [
      1159285413,
      1159292849,
      1159293593,
      1159289995
    ],
    "wof:name": "poster: United Airlines, Boeing 787 Dreamliner",
    "wof:placetype": "custom",
    "wof:placetype_alt": "object"
  },
  "geometry": {"coordinates":[-122.386155,37.616357],"type":"Point"}
}
