{
  "type": "Feature",
  "properties": {
    "date:cessation_lower": "1987-01-01",
    "date:cessation_upper": "1987-12-31",
    "date:inception_lower": "1987-01-01",
    "date:inception_upper": "1987-12-31",
    "isbn:number": "0451625552 :, 9780451625557",
    "iso:country": "XX",
    "sfomuseum:accession_number": "99-0730",
    "sfomuseum:author": "Franklin, Jon",
    "sfomuseum:callnumber": "PN187 .F73 1987",
    "sfomuseum:category": "Book",
    "sfomuseum:collection": "Aviation Library",
    "sfomuseum:date": "1987",
    "sfomuseum:daterange_end": "1987-12-31",
    "sfomuseum:daterange_start": "1987-01-01",
    "sfomuseum:description": "xix, 284 p. ; 18 cm.",
    "sfomuseum:description_library": "xix, 284 p. ; 18 cm.",
    "sfomuseum:medium": "paper, ink",
    "sfomuseum:placetype": "object",
    "sfomuseum:publication": "New York: New American Library, 1987.",
    "sfomuseum:publisher": "New American Library",
    "sfomuseum:publisher_location": "New York",
    "sfomuseum:subcategory": "Book",
    "sfomuseum:subject": "Rhetoric.",
    "wof:name": "Writing for story: craft secrets of dramatic nonfiction by a two-time Pulitzer Prize winner",
    "wof:placetype": "custom",
    "wof:placetype_alt": "object"
  },
  "geometry": {"coordinates":[-122.386155,37.616357],"type":"Point"}
}
