{
  "type": "Feature",
  "properties": {
    "date:cessation_lower": "1980-01-01",
    "date:cessation_upper": "1989-12-31",
    "date:inception_lower": "1980-01-01",
    "date:inception_upper": "1989-12-31",
    "iso:country": "XX",
    "millsfield:images": [
      1527824399,
      1527824401
    ],
    "millsfield:primary_image": 1527824399,
    "sfomuseum:accession_number": "1998.157.094",
    "sfomuseum:airline": "Crossair",
    "sfomuseum:category": "Passenger Amenity, Archive",
    "sfomuseum:collection": "Aviation Archive",
    "sfomuseum:creditline": "Gift of The Henry Steiner Air Sickness Bag Collection",
    "sfomuseum:date": "1980s",
    "sfomuseum:date_acquired": "1999-07-13",
    "sfomuseum:daterange_end": "1989-12-31",
    "sfomuseum:daterange_start": "1980-01-01",
    "sfomuseum:description": "Airsickness bag issued by Crossair; red bag with servicemark; flat bottom, no closure.",
    "sfomuseum:dimensions": "9 1/2 x 5 inches (24.1 x 12.7 cm)",
    "sfomuseum:media_ids": [
      1527824399,
      1527824401
    ],
    "sfomuseum:medium": "paper, ink",
    "sfomuseum:placetype": "object",
    "sfomuseum:publication": ": , 1980s.",
    "sfomuseum:subcategory": "Airsickness Bag",
    "wof:depicts": [
      1159284221,
      1159288583
    ],
    "wof:name": "airsickness bag: Crossair",
    "wof:placetype": "custom",
    "wof:placetype_alt": "object"
  },
  "geometry": {"coordinates":[-122.386155,37.616357],"type":"Point"}
}
