{
  "type": "Feature",
  "properties": {
    "date:cessation_lower": "1968-01-01",
    "date:cessation_upper": "1968-12-31",
    "date:inception_lower": "1968-01-01",
    "date:inception_upper": "1968-12-31",
    "iso:country": "XX",
    "millsfield:images": [
      1527819343
    ],
    "millsfield:primary_image": 1527819343,
    "sfomuseum:accession_number": "2011.059.001",
    "sfomuseum:airline": "Northwest Orient Airlines",
    "sfomuseum:category": "Promotional",
    "sfomuseum:collection": "Aviation Museum",
    "sfomuseum:creditline": "Gift of Cheryl Peterson",
    "sfomuseum:date": "c. 1968",
    "sfomuseum:date_acquired": "2011-08-02",
    "sfomuseum:daterange_end": "1973-12-31",
    "sfomuseum:daterange_start": "1963-01-01",
    "sfomuseum:description": "Small dark blue bag with white piping; red and blue illustration depicting vertical stabilizer of aircraft with “Northwest Orient” logotype and text in italic script, “The Fan-Jet Airline”; two handles and zipper closure across top; manufacturer label, four metallic feet, and writing “Cheryl, 5” on bottom.",
    "sfomuseum:dimensions": "7 1/2 x 11 1/2 x 4 1/4 inches (19.1 x 29.2 x 10.8 cm)",
    "sfomuseum:maker": "Airline Textile MFG., Co. ",
    "sfomuseum:media_ids": [
      1527819343
    ],
    "sfomuseum:medium": "vinyl, ink, metal",
    "sfomuseum:placetype": "object",
    "sfomuseum:publication": ": , c. 1968.",
    "sfomuseum:subcategory": "Airline Bag",
    "wof:depicts": [
      1159284913
    ],
    "wof:name": "miniature airline bag: Northwest Orient Airlines",
    "wof:placetype": "venue"
  },
  "geometry": {"coordinates":[-122.386155,37.616357],"type":"Point"}
}
