{
  "type": "Feature",
  "properties": {
    "date:cessation_lower":"1973-12-31",
    "date:cessation_upper":"1973-12-31",
    "date:inception_lower":"1963-01-01",
    "date:inception_upper":"1963-01-01",
    "iso:country":"XX",
    "sfomuseum:accession_number":"2011.059.001",
    "sfomuseum:category":"Promotional",
    "sfomuseum:collection":"Aviation Museum",
    "sfomuseum:creditline":"Gift of Cheryl Peterson",
    "sfomuseum:date":"c. 1968",
    "sfomuseum:daterange_end":"1973-12-31",
    "sfomuseum:daterange_start":"1963-01-01",
    "sfomuseum:description":"Small dark blue bag with white piping; red and blue illustration depicting vertical stabilizer of aircraft with \u201cNorthwest Orient\u201d logotype and text in italic script, \u201cThe Fan-Jet Airline\u201d; two handles and zipper closure across top; manufacturer label, four metallic feet, and writing \u201cCheryl, 5\u201d on bottom.",
    "sfomuseum:maker":"Airline Textile MFG., Co. ",
    "sfomuseum:medium":"vinyl, ink, metal",
    "sfomuseum:placetype":"object",
    "sfomuseum:subcategory":"Airline Bag",
    "wof:name":"miniature airline bag: Northwest Orient Airlines",
    "wof:placetype":"venue"
},
  "geometry": {"coordinates":[-122.386155,37.616358],"type":"Point"}
}