{
  "type": "Feature",
  "properties": {
    "date:cessation_lower": "2003-01-01",
    "date:cessation_upper": "2003-12-31",
    "date:inception_lower": "2003-01-01",
    "date:inception_upper": "2003-12-31",
    "iso:country": "XX",
    "sfomuseum:accession_number": "2004.004.068",
    "sfomuseum:author": "Stone, Ilene",
    "sfomuseum:callnumber": "ML420.F866 S76 2003eb",
    "sfomuseum:category": "Book",
    "sfomuseum:collection": "Aviation Library",
    "sfomuseum:creditline": "Purchase",
    "sfomuseum:date": "c. 2003",
    "sfomuseum:daterange_end": "2008-12-31",
    "sfomuseum:daterange_start": "1998-01-01",
    "sfomuseum:description": "xvii, 142 p. : ill. ; 23 cm.",
    "sfomuseum:medium": "paper, ink",
    "sfomuseum:placetype": "object",
    "sfomuseum:publication": "Columbia, OH: University of Missouri Press, c. 2003.",
    "sfomuseum:publisher": "University of Missouri Press",
    "sfomuseum:publisher_location": "Columbia, OH",
    "sfomuseum:subcategory": "Book",
    "sfomuseum:subject": "Froman, Jane, 1907-1980.",
    "wof:name": "Jane Froman: Missouri's first lady of song",
    "wof:placetype": "venue"
  },
  "geometry": {"coordinates":[-122.386155,37.616357],"type":"Point"}
}
