{
  "type": "Feature",
  "properties": {
    "date:cessation_lower": "1971-01-01",
    "date:cessation_upper": "1971-12-31",
    "date:inception_lower": "1971-01-01",
    "date:inception_upper": "1971-12-31",
    "iso:country": "XX",
    "loc:named_authorities": [
      "n81114434"
    ],
    "sfomuseum:accession_number": "2002.031.021",
    "sfomuseum:author": "Wagner, William",
    "sfomuseum:callnumber": "TL540.R89 W3 1971",
    "sfomuseum:category": "Book",
    "sfomuseum:collection": "Aviation Library",
    "sfomuseum:creditline": "Purchase",
    "sfomuseum:date": "1971",
    "sfomuseum:date_acquired": "1997-01-10",
    "sfomuseum:daterange_end": "1971-12-31",
    "sfomuseum:daterange_start": "1971-01-01",
    "sfomuseum:description": "xi, 253 p. illus., facsims., ports. 28 cm.",
    "sfomuseum:description_library": "xi, 253 p. illus., facsims., ports. 28 cm.",
    "sfomuseum:medium": "paper, ink",
    "sfomuseum:placetype": "object",
    "sfomuseum:publication": "New York: McGraw-Hill, 1971.",
    "sfomuseum:publisher": "McGraw-Hill",
    "sfomuseum:publisher_location": "New York",
    "sfomuseum:subcategory": "Book",
    "sfomuseum:subject": "Ryan, Tubal Claude, 1898-  .\rRyan Aeronautical Company.",
    "wof:name": "Ryan, the aviator: being the adventures \u0026 ventures of pioneer airman \u0026 businessman, T. Claude Ryan",
    "wof:placetype": "custom",
    "wof:placetype_alt": "object"
  },
  "geometry": {"coordinates":[-122.386155,37.616357],"type":"Point"}
}
