{
  "type": "Feature",
  "properties": {
    "date:cessation_lower": "1966-01-01",
    "date:cessation_upper": "1966-12-31",
    "date:inception_lower": "1966-01-01",
    "date:inception_upper": "1966-12-31",
    "iso:country": "XX",
    "millsfield:images": [
      1527842739,
      1527850497
    ],
    "millsfield:images_texts": [
      "CAA\n- AIR AUSTRALIA\ntimetable\n(U.K. \u0026 European Edition)\nINCLUDING SERVICES TO PAPUA / NEW GUINEA\nOCT-NOV\n1966\nEFFECTIVE FROM\nSth O--ли]h Nov\nTRANS-AUSTRALIA AIRLINES",
      "ZAA\nabridged timetables\nZAA\nExcept whare marked, all flights are First class a DAILY\nbined sires and erassmy sass\nComprehensive timetoble covering all TAA Schedules available on\nROURNE-CANRERRA^SYDNEY-NEWCASTLES COOLANGATTA^BRISBANE\nBRISBANE-COOLANGATASNEWCE\nSYDNEY^ CANBERRA\nNEW GUINEA/PAPUA-AUSTRALIA\nTRISTAN\nCAIRNS TOWNS!\nBRISBANI\nADELAIDEISTONETBRISSANT\nTOWNSVILLE\nCABANS\nTOWNSVETE\nSYDNEY IMELROURNE\nADELAIDE S PERTH\nPERTHE\nADELAIDE\nMELBOURNE / SYDNEY\nSYDNEYTADELAIDE\nSYDNEY IMELROURNE\nTASMANIA\nPIESE NE\nMELROURNE SYDNEY\nMESS NAPS\nMONSTER\nPlight Nave\n_HORART\nI STON\nLy. 97.50"
    ],
    "millsfield:images_texts_ids": [
      1527842739,
      1527850497
    ],
    "millsfield:primary_image": 1527842739,
    "sfomuseum:accession_number": "2005.132.099.002",
    "sfomuseum:airline": "Trans Australia Airlines (TAA)",
    "sfomuseum:category": "Scheduling / Ticketing",
    "sfomuseum:collection": "Aviation Archive",
    "sfomuseum:creditline": "Gift of the William Hough Collection",
    "sfomuseum:date": "1966",
    "sfomuseum:date_acquired": "2006-12-05",
    "sfomuseum:daterange_end": "1966-12-31",
    "sfomuseum:daterange_start": "1966-01-01",
    "sfomuseum:description": "Timetable issued by Trans Australia Airlines (TAA), effective October 5 through November 30, 1966, UK and Europe edition; double-sided fold-out; brown and white cover with image of flight attendant and servicemark at top.",
    "sfomuseum:dimensions": "8 3/4 x 3 3/4 inches (22.2 x 9.5 cm)",
    "sfomuseum:media_ids": [
      1527842739,
      1527850497
    ],
    "sfomuseum:medium": "paper, ink",
    "sfomuseum:placetype": "object",
    "sfomuseum:publication": ": , 1966.",
    "sfomuseum:subcategory": "Timetable",
    "wof:depicts": [
      1159285345,
      1159288387
    ],
    "wof:name": "timetable: Trans Australia Airlines (TAA)",
    "wof:placetype": "custom",
    "wof:placetype_alt": "object"
  },
  "geometry": {"coordinates":[-122.386155,37.616357],"type":"Point"}
}
