{
  "type": "Feature",
  "properties": {
    "date:cessation_lower": "1982-01-01",
    "date:cessation_upper": "1982-12-31",
    "date:inception_lower": "1982-01-01",
    "date:inception_upper": "1982-12-31",
    "iso:country": "XX",
    "sfomuseum:accession_number": "2008.107.043",
    "sfomuseum:author": "Serling, Robert J",
    "sfomuseum:callnumber": "PS3569.E7 S7 1982",
    "sfomuseum:category": "Book",
    "sfomuseum:collection": "Aviation Library",
    "sfomuseum:creditline": "Gift of Thomas G. Dragges",
    "sfomuseum:date": "1982",
    "sfomuseum:date_acquired": "2009-12-31",
    "sfomuseum:daterange_end": "1982-12-31",
    "sfomuseum:daterange_start": "1982-01-01",
    "sfomuseum:description": "340 p. ; 22 cm.",
    "sfomuseum:description_library": "340 p. ; 22 cm.",
    "sfomuseum:edition": "1st ed.",
    "sfomuseum:medium": "paper, ink",
    "sfomuseum:placetype": "object",
    "sfomuseum:publication": "New York: St. Martin's / Marek, 1982.",
    "sfomuseum:publisher": "St. Martin's / Marek",
    "sfomuseum:publisher_location": "New York",
    "sfomuseum:subcategory": "Book",
    "sfomuseum:subject": "Flight attendants Fiction.",
    "wof:name": "Stewardess 1st ed.",
    "wof:placetype": "custom",
    "wof:placetype_alt": "object"
  },
  "geometry": {"coordinates":[-122.386155,37.616357],"type":"Point"}
}
