{
  "type": "Feature",
  "properties": {
    "date:cessation_lower": "1912-01-01",
    "date:cessation_upper": "1912-12-31",
    "date:inception_lower": "1912-01-01",
    "date:inception_upper": "1912-12-31",
    "iso:country": "XX",
    "loc:subject_headings": [
      "sh85001319"
    ],
    "millsfield:images": [
      1746680957
    ],
    "millsfield:primary_image": 1746680957,
    "sfomuseum:accession_number": "2000.160.0364",
    "sfomuseum:author": "Greenhill, Sir G. (George)",
    "sfomuseum:callnumber": "TL570 .G83 1912 SC",
    "sfomuseum:category": "Book",
    "sfomuseum:collection": "Aviation Library",
    "sfomuseum:creditline": "The Tony Bill Aviation Library Collection",
    "sfomuseum:date": "1912",
    "sfomuseum:date_acquired": "1999-05-18",
    "sfomuseum:daterange_end": "1912-12-31",
    "sfomuseum:daterange_start": "1912-01-01",
    "sfomuseum:description": "121 p., illus., tab., diagrs. 23 cm.",
    "sfomuseum:description_library": "121 p., illus., tab., diagrs. 23 cm.",
    "sfomuseum:medium": "paper, ink",
    "sfomuseum:placetype": "object",
    "sfomuseum:publication": "London: Constable, 1912.",
    "sfomuseum:publisher": "Constable",
    "sfomuseum:publisher_location": "London",
    "sfomuseum:subcategory": "Book",
    "sfomuseum:subject": "Aeronautics.",
    "wof:name": "The dynamics of mechanical flight : lectures delivered at the Imperial college of science and technology, March, 1910 and 1911",
    "wof:placetype": "venue"
  },
  "geometry": {"coordinates":[-122.386155,37.616357],"type":"Point"}
}
