{
  "type": "Feature",
  "properties": {
    "date:cessation_lower":"1912-12-31",
    "date:cessation_upper":"1912-12-31",
    "date:inception_lower":"1912-01-01",
    "date:inception_upper":"1912-01-01",
    "iso:country":"XX",
    "sfomuseum:accession_number":"2000.160.0364",
    "sfomuseum:category":"Book",
    "sfomuseum:collection":"Aviation Library",
    "sfomuseum:creditline":"The Tony Bill Aviation Library Collection",
    "sfomuseum:date":"1912",
    "sfomuseum:daterange_end":"1912-12-31",
    "sfomuseum:daterange_start":"1912-01-01",
    "sfomuseum:description":"121 p., illus., tab., diagrs. 23 cm.",
    "sfomuseum:medium":"paper, ink",
    "sfomuseum:placetype":"object",
    "sfomuseum:subcategory":"Book",
    "wof:name":"The dynamics of mechanical flight : lectures delivered at the Imperial college of science and technology, March, 1910 and 1911",
    "wof:placetype":"venue"
},
  "geometry": {"coordinates":[-122.386155,37.616358],"type":"Point"}
}