{
  "type": "Feature",
  "properties": {
    "date:cessation_lower": "1988-01-01",
    "date:cessation_upper": "1988-12-31",
    "date:inception_lower": "1988-01-01",
    "date:inception_upper": "1988-12-31",
    "iso:country": "XX",
    "millsfield:images": [
      1527841231
    ],
    "millsfield:images_texts": [
      "Lufthansa\nTimetable\nFlugplan\nHoraire\n27 Mar _\n- 30 Jun 88"
    ],
    "millsfield:images_texts_ids": [
      1527841231
    ],
    "millsfield:primary_image": 1527841231,
    "sfomuseum:accession_number": "2003.105.070.006",
    "sfomuseum:airline": "Lufthansa",
    "sfomuseum:category": "Scheduling / Ticketing",
    "sfomuseum:collection": "Aviation Archive",
    "sfomuseum:creditline": "Gift of Craig Lynes",
    "sfomuseum:date": "1988",
    "sfomuseum:date_acquired": "2003-12-29",
    "sfomuseum:daterange_end": "1988-12-31",
    "sfomuseum:daterange_start": "1988-01-01",
    "sfomuseum:description": "Timetable issued by Lufthansa, effective March 27 through June 30, 1988; 228-page fold-out schedule; yellow cover.",
    "sfomuseum:dimensions": "7 3/4 x 4 inches (19.7 x 10.2 cm)",
    "sfomuseum:media_ids": [
      1527841231
    ],
    "sfomuseum:medium": "paper, ink",
    "sfomuseum:placetype": "object",
    "sfomuseum:publication": ": , 1988.",
    "sfomuseum:subcategory": "Timetable",
    "wof:depicts": [
      1159288215,
      1159284711
    ],
    "wof:name": "timetable: Lufthansa",
    "wof:placetype": "custom",
    "wof:placetype_alt": "object"
  },
  "geometry": {"coordinates":[-122.386155,37.616357],"type":"Point"}
}
