{
  "type": "Feature",
  "properties": {
    "date:cessation_lower": "1965-12-31",
    "date:cessation_upper": "1965-12-31",
    "date:inception_lower": "1965-01-01",
    "date:inception_upper": "1965-01-01",
    "iso:country": "XX",
    "sfomuseum:accession_number": "2011.032.1906",
    "sfomuseum:category": "Photograph",
    "sfomuseum:collection": "Aviation Archive",
    "sfomuseum:creditline": "Transfer",
    "sfomuseum:date": "1965",
    "sfomuseum:daterange_end": "1965-12-31",
    "sfomuseum:daterange_start": "1965-01-01",
    "sfomuseum:description": "From attached handwritten note: “10-15-65 / Airport Parking Garage”. Color photographic print depicting parking lot, buildings, and exterior lighting at San Francisco International Airport (SFO) on October 15, 1965; three-quarter partial view of structure on left side of image.",
    "sfomuseum:media_ids": [
      1527826607
    ],
    "sfomuseum:medium": "photograph",
    "sfomuseum:placetype": "object",
    "sfomuseum:subcategory": "Print, Photograph",
    "wof:name": "photograph: San Francisco International Airport (SFO), parking garage",
    "wof:placetype": "venue"
  },
  "geometry": {"coordinates":[-122.386155,37.616358],"type":"Point"}
}
