{
  "type": "Feature",
  "properties": {
    "date:cessation_lower": "1976-01-01",
    "date:cessation_upper": "1976-12-31",
    "date:inception_lower": "1976-01-01",
    "date:inception_upper": "1976-12-31",
    "iso:country": "XX",
    "millsfield:images": [
      1527835651
    ],
    "millsfield:images_texts": [
      "PSA\nFLIGHT SCHEDULE\nSUPPLEMENT\nEFFECTIVE JANUARY 30, 1976\nPSA'S\nNew ELEGTRA\nJet Fares\nSave S11 round trip!\nHOLT YWOOD BUBRANK TO SAN FRANCISCO\na Fo\nEX SUN\n85\n7:09\nSUN\nSAN FRANCISCO TO HOLLYWOOD.BURBANK\nSFO\n9:45\n9:00\n10:45\n19:08\nEX SUN\nNUN\nHOLLYWOOD-BURBANK TO OAKLAND\nSOSGUENGY\n12:15\nSUN\nFRIE\n• SUN\nà Fo\nFREQUENCY\nOAK\nHWB\nSUN\nSUN\nHOLLYWOOD BURBANK TO SON DIEGO\nFREQUENCY\nSHARE\n10:55\nEX FRI \u0026 SUN\nAM-LiontracoPM-Boldface\nFARES (One-way, incl. tax)\nSTANDBY\nPOSITIVE SPACE ..........\n20.00\nFOR RESERVATIONS CALL\nHOLINWOOS\n787-4750\n240-7300\nOakland . . . . . . ...\n568-4433\nSan Francisco..\n761-0818\nFLY PSA'S BARGAIN BIRD."
    ],
    "millsfield:images_texts_ids": [
      1527835651
    ],
    "millsfield:primary_image": 1527835651,
    "sfomuseum:accession_number": "2005.132.042.042",
    "sfomuseum:airline": "Pacific Southwest Airlines (PSA)",
    "sfomuseum:category": "Scheduling / Ticketing",
    "sfomuseum:collection": "Aviation Archive",
    "sfomuseum:creditline": "Gift of the William Hough Collection",
    "sfomuseum:date": "1976",
    "sfomuseum:date_acquired": "2006-12-05",
    "sfomuseum:daterange_end": "1976-12-31",
    "sfomuseum:daterange_start": "1976-01-01",
    "sfomuseum:description": "Supplemental timetable issued by Pacific Southwest Airlines (PSA), effective January 30, 1976; white single-sided card with text “PSA’s New ELECTRA Jet Fares”.",
    "sfomuseum:dimensions": "9 x 3 1/4 inches (22.9 x 8.3 cm)",
    "sfomuseum:media_ids": [
      1527835651
    ],
    "sfomuseum:medium": "paper, ink",
    "sfomuseum:placetype": "object",
    "sfomuseum:publication": ": , 1976.",
    "sfomuseum:subcategory": "Timetable",
    "wof:depicts": [
      1159286629,
      1159284973
    ],
    "wof:name": "timetable: Pacific Southwest Airlines (PSA), supplement",
    "wof:placetype": "custom",
    "wof:placetype_alt": "object"
  },
  "geometry": {"coordinates":[-122.386155,37.616357],"type":"Point"}
}
