{
  "type": "Feature",
  "properties": {
    "date:cessation_lower": "1976-01-01",
    "date:cessation_upper": "1976-12-31",
    "date:inception_lower": "1976-01-01",
    "date:inception_upper": "1976-12-31",
    "iso:country": "XX",
    "millsfield:images": [
      1527835651
    ],
    "millsfield:images_texts": [
      "PSA\nFLIGHT SCHEDULE\nSUPPLEMENT\nEFFECTIVE JANUARY 30, 1976\nPSA's\nNew ELECTRA\nJet Fares\nSave $11 round trip!\nHOLLYWOOD-BURBANK TO SAN FRANCISCO\nFLT\nNO\nCoco 00 0\nLV\nHWB\n7:30\n4:00\n7:00\n7:15\nAR\nSFO\n8:30\n5:00\n8:00\n8:15\nFREQUENCY\nEX SUN\nSUN\nSUN\nEX SUN\nSAN FRANCISCO TO HOLLYWOOD-BURBANK\nFLT\nNO\n00 CO\nNEOL\nLV\nSFO\n9:45\n5:30\n00\n10:00\nAR\nHWB\n10:45\n6:30\n10:00\n11:00\nFREQUENCY\nEX SUN\nSUN\nEX SUN\nSUN\nHOLLYWOOD-BURBANK TO OAKLAND\nFLT\nNO\nLV\nHWB\n8:00\n12:15\n3:45\nAR\nOAK\n9:00\n1:15\n4:45\nFREQUENCY\nSUN\nFRI \u0026 SUN\nEX SUN\nOAKLAND TO HOLLYWOOD-BURBANK\nFLT\nNO\n82\n64\n66\nLV\nOAK\n10:30\n2:15\n5:30\nAR\nHWB\n11:30\n3:15\n6:30\nFREQUENCY\nSUN\nFRI \u0026 SUN\nEX SUN\nHOLLYWOOD-BURBANK TO SAN DIEGO\nFLT\nNO\n68\nLV.\nHWB\n10:20\nAR\nSAN\n10:55\nFREQUENCY\nEX FRI \u0026 SUN\nAM-Lightface\nPM-Boldface\nFARES (One-way, incl. tax)\nSTANDBY\nPOSITIVE SPACE\n17.00\n20.00\n(Except Hollywood-Burbank to San Diego)\nFOR RESERVATIONS CALL:\nHollywood-Burbank\n787-4750\nor\n240-7300\nOakland\n568-4433\nSan Francisco\n761-0818\nFLY PSA's BARGAIN BIRD."
    ],
    "millsfield:images_texts_ids": [
      1527835651
    ],
    "millsfield:primary_image": 1527835651,
    "sfomuseum:accession_number": "2005.132.042.042",
    "sfomuseum:airline": "Pacific Southwest Airlines (PSA)",
    "sfomuseum:category": "Scheduling / Ticketing",
    "sfomuseum:collection": "Aviation Archive",
    "sfomuseum:creditline": "Gift of the William Hough Collection",
    "sfomuseum:date": "1976",
    "sfomuseum:date_acquired": "2006-12-05",
    "sfomuseum:daterange_end": "1976-12-31",
    "sfomuseum:daterange_start": "1976-01-01",
    "sfomuseum:description": "Supplemental timetable issued by Pacific Southwest Airlines (PSA), effective January 30, 1976; white single-sided card with text “PSA’s New ELECTRA Jet Fares”.",
    "sfomuseum:dimensions": "9 x 3 1/4 inches (22.9 x 8.3 cm)",
    "sfomuseum:media_ids": [
      1527835651
    ],
    "sfomuseum:medium": "paper, ink",
    "sfomuseum:placetype": "object",
    "sfomuseum:publication": ": , 1976.",
    "sfomuseum:subcategory": "Timetable",
    "wof:depicts": [
      1159286629,
      1159284973
    ],
    "wof:name": "timetable: Pacific Southwest Airlines (PSA), supplement",
    "wof:placetype": "custom",
    "wof:placetype_alt": "object"
  },
  "geometry": {"coordinates":[-122.386155,37.616357],"type":"Point"}
}
