{
  "type": "Feature",
  "properties": {
    "date:cessation_lower": "1949-12-31",
    "date:cessation_upper": "1949-12-31",
    "date:inception_lower": "1949-01-01",
    "date:inception_upper": "1949-01-01",
    "iso:country": "US",
    "millsfield:images": [
      1527853839,
      1527853837,
      1527853831,
      1527853835,
      1527853841,
      1527853843,
      1527853845,
      1527853829,
      1527853827,
      1527853821,
      1527853823,
      1527853825,
      1527853819,
      1527853817,
      1527853813
    ],
    "sfomuseum:accession_number": "1993.01.005 a f",
    "sfomuseum:airline": "Pan American World Airways",
    "sfomuseum:category": "Passenger Amenity",
    "sfomuseum:collection": "Aviation Archive",
    "sfomuseum:continent": "Transpacific",
    "sfomuseum:country": "United States",
    "sfomuseum:creditline": "Gift of Serge Mitt",
    "sfomuseum:date": "1949",
    "sfomuseum:daterange_end": "1949-12-31",
    "sfomuseum:daterange_start": "1949-01-01",
    "sfomuseum:description": "Flight information packet produced by Pan American World Airways, titled \"Your adventure in the Pacific,\" comprising:\ra. folder; tri-fold format with three pockets\rb. brochure titled \"Flying Clipper-wise\"; multipage booklet\rc. bar service menu; quad-fold format\rd. timetable for transpacific flights, effective November 1949; fold-out format; includes shipping rates for cargo\re. time selector; two round cards attached at center; used to determine time in other zones\rf. postcard with full color photographic image of of Wat Benchamabopit [Marble Temple] in Bangkok",
    "sfomuseum:dimensions": "9 1/4 x 7 1/4 inches (23.5 x 18.4 cm)",
    "sfomuseum:maker": "Vaugham Bass for American World Airways, Inc.",
    "sfomuseum:media_ids": [
      1527853813,
      1527853817,
      1527853819,
      1527853821,
      1527853823,
      1527853825,
      1527853827,
      1527853829,
      1527853831,
      1527853835,
      1527853837,
      1527853839,
      1527853841,
      1527853843,
      1527853845
    ],
    "sfomuseum:medium": "paper, ink, metal",
    "sfomuseum:placetype": "object",
    "sfomuseum:subcategory": "In-flight Information",
    "wof:depicts": [
      1159284989
    ],
    "wof:name": "flight information packet: Pan American World Airways",
    "wof:placetype": "venue"
  },
  "geometry": {"coordinates":[-122.386155,37.616358],"type":"Point"}
}
