{
  "type": "Feature",
  "properties": {
    "date:cessation_lower": "1999-12-31",
    "date:cessation_upper": "1999-12-31",
    "date:inception_lower": "1990-01-01",
    "date:inception_upper": "1990-01-01",
    "iso:country": "XX",
    "sfomuseum:accession_number": "2006.026.102",
    "sfomuseum:category": "Passenger Amenity",
    "sfomuseum:collection": "Aviation Museum",
    "sfomuseum:creditline": "The Henry Steiner Air Sickness Bag Collection",
    "sfomuseum:date": "1990s",
    "sfomuseum:daterange_end": "1999-12-31",
    "sfomuseum:daterange_start": "1990-01-01",
    "sfomuseum:description": "Gray with repeated \"Sickness bag\" alternating between three languages (English, German, French); captions bisected by sleek plane design on front and ship on reverse; wire closure, flat bottom.",
    "sfomuseum:media_ids": [
      1527823717, 
      1527823721
    ],
    "sfomuseum:medium": "paper, ink, metal",
    "sfomuseum:placetype": "object",
    "sfomuseum:subcategory": "Airsickness Bag",
    "wof:name": "airsickness bag: Arkia Israel Airlines",
    "wof:placetype": "venue"
  },
  "geometry": {"coordinates":[-122.386155,37.616358],"type":"Point"}
}
