{
  "type": "Feature",
  "properties": {
    "date:cessation_lower":"1981-12-31",
    "date:cessation_upper":"1981-12-31",
    "date:inception_lower":"1981-01-01",
    "date:inception_upper":"1981-01-01",
    "iso:country":"XX",
    "millsfield:images":[
        1527837089
    ],
    "sfomuseum:accession_number":"2012.149.0158",
    "sfomuseum:category":"Scheduling / Ticketing",
    "sfomuseum:collection":"Aviation Archive",
    "sfomuseum:creditline":"Gift of the Captain John B. Russell Family",
    "sfomuseum:date":"1981",
    "sfomuseum:daterange_end":"1981-12-31",
    "sfomuseum:daterange_start":"1981-01-01",
    "sfomuseum:description":"Timetable issued by Western Airlines; San Francisco / Oakland / San Jose quick reference, effective January 6 through February 28, 1981; white cover with red \u201cW\u201d logo; contains listing of U.S. and Mexico flights.",
    "sfomuseum:media_ids":[
        1527837089
    ],
    "sfomuseum:medium":"paper, ink",
    "sfomuseum:placetype":"object",
    "sfomuseum:subcategory":"Timetable",
    "wof:depicts":[
        85921881,
        85688637,
        85633793
    ],
    "wof:name":"timetable: Western Airlines, San Francisco / Oakland / San Jose quick reference",
    "wof:placetype":"venue"
},
  "geometry": {"coordinates":[-122.386155,37.616358],"type":"Point"}
}