{
  "type": "Feature",
  "properties": {
    "date:cessation_lower": "2005-01-01",
    "date:cessation_upper": "2005-12-31",
    "date:inception_lower": "2005-01-01",
    "date:inception_upper": "2005-12-31",
    "isbn:number": "1413486037 9781413486032 1413486029 9781413486025",
    "iso:country": "XX",
    "loc:subject_headings": [
      "sh2008117571"
    ],
    "sfomuseum:accession_number": "2005.048.001",
    "sfomuseum:airline": "Pan American World Airways",
    "sfomuseum:author": "Kewin, Thomas",
    "sfomuseum:callnumber": "TL540 .K38 2005",
    "sfomuseum:category": "Book",
    "sfomuseum:collection": "Aviation Library",
    "sfomuseum:creditline": "Gift of the author",
    "sfomuseum:date": "2005",
    "sfomuseum:date_acquired": "2005-10-17",
    "sfomuseum:daterange_end": "2005-12-31",
    "sfomuseum:daterange_start": "2005-01-01",
    "sfomuseum:description": "177 p.; b\u0026w photographs.",
    "sfomuseum:description_library": "177 pages : illustrations ; 23 cm",
    "sfomuseum:issues_held": "The Pan Am Journey.",
    "sfomuseum:medium": "paper, ink",
    "sfomuseum:placetype": "object",
    "sfomuseum:publication": ": Xlibris, 2005.",
    "sfomuseum:publisher": "Xlibris",
    "sfomuseum:subcategory": "Book",
    "sfomuseum:subject": "Thomas Kewin.\rAir pilots -- Biography. \rPan American World Airways -- Pilots -- Biography.",
    "wof:depicts": [
      1159284989,
      1159286839
    ],
    "wof:name": "The Pan Am journey",
    "wof:placetype": "custom",
    "wof:placetype_alt": [
      "object"
    ]
  },
  "geometry": {"coordinates":[-122.386155,37.616357],"type":"Point"}
}
