{
  "type": "Feature",
  "properties": {
    "date:cessation_lower": "1981-01-01",
    "date:cessation_upper": "1981-12-31",
    "date:inception_lower": "1981-01-01",
    "date:inception_upper": "1981-12-31",
    "iso:country": "XX",
    "sfomuseum:accession_number": "00-2881",
    "sfomuseum:callnumber": "TL509 .I55 1981 vol.5 REF",
    "sfomuseum:category": "Book",
    "sfomuseum:collection": "Aviation Library",
    "sfomuseum:date": "c. 1981",
    "sfomuseum:daterange_end": "1986-12-31",
    "sfomuseum:daterange_start": "1976-01-01",
    "sfomuseum:description": "18 v. : ill. (some col.) ; 30 cm.",
    "sfomuseum:description_library": "18 v. : ill. (some col.) ; 30 cm.",
    "sfomuseum:medium": "paper, ink",
    "sfomuseum:placetype": "object",
    "sfomuseum:publication": "London: Orbis, c. 1981.",
    "sfomuseum:publisher": "Orbis",
    "sfomuseum:publisher_location": "London",
    "sfomuseum:subcategory": "Reference",
    "sfomuseum:subject": "Aeronautics Encyclopedias.",
    "wof:name": "The Illustrated encyclopedia of aircraft",
    "wof:placetype": "custom",
    "wof:placetype_alt": "object"
  },
  "geometry": {"coordinates":[-122.386155,37.616357],"type":"Point"}
}
