{
  "type": "Feature",
  "properties": {
    "date:cessation_lower": "1969-12-31",
    "date:cessation_upper": "1969-12-31",
    "date:inception_lower": "1969-01-01",
    "date:inception_upper": "1969-01-01",
    "iso:country": "XX",
    "sfomuseum:accession_number": "2010.279.001.078",
    "sfomuseum:category": "Company Record / Document",
    "sfomuseum:collection": "Aviation Archive",
    "sfomuseum:creditline": "Gift of Jon E. Krupnick",
    "sfomuseum:date": "1969",
    "sfomuseum:daterange_end": "1969-12-31",
    "sfomuseum:daterange_start": "1969-01-01",
    "sfomuseum:description": "Brown and white stock certificate issued to Janice B. Langston and Clarence A. Langston for 19 shares of Pan American World Airways, Inc.; certificate number EF0011112, dated September 30, 1969; engraved signatures of [illegible signature], Secretary, and H. E. Gray, Chairman of the Board; countersigned by Bankers Trust Company, registered by Chemical Bank (New York); certificate note by American Bank Note Company.",
    "sfomuseum:media_ids": [
      1527831517
    ],
    "sfomuseum:medium": "paper, ink",
    "sfomuseum:placetype": "object",
    "sfomuseum:subcategory": "Stock Certificate / Bond",
    "wof:name": "stock certificate: Pan American World Airways",
    "wof:placetype": "venue"
  },
  "geometry": {"coordinates":[-122.386155,37.616358],"type":"Point"}
}
