{
  "type": "Feature",
  "properties": {
    "date:cessation_lower": "1935-11-24",
    "date:cessation_upper": "1935-11-24",
    "date:inception_lower": "1935-11-24",
    "date:inception_upper": "1935-11-24",
    "iso:country": "XX",
    "millsfield:images": [
      1527852601,
      1527852603
    ],
    "millsfield:images_texts": [
      "I Vis First Contract Trans-Facific Flight\n\" Hawaii to Philipine Islands\nNOV'\n5\nAM\n1935\nA/ A\nPILGRIM TERCENTENAR\nPACIFIC\nFA.M. ROUTE 14\nHONOLULU \"\n- MANILA\nSphs talker\nPostmaster\nHenry M• Horn,\nRailway Mail Clerk,\n32 Sterling Place,\nBrooklyn,N.Y.,U.S.A.",
      "ShE2 bh1 2102\nSANIT\nNOV 29 7\n5 PM\n1935\nP.\nMANILA\nTRADE CENTER\nOF\nTHE\nPACIFIC\n2-7/3"
    ],
    "millsfield:images_texts_ids": [
      1527852601,
      1527852603
    ],
    "millsfield:primary_image": 1527852601,
    "sfomuseum:accession_number": "2012.149.2348 a b",
    "sfomuseum:aircraft": "Martin M-130",
    "sfomuseum:airline": "Pan American Airways",
    "sfomuseum:category": "Philately",
    "sfomuseum:collection": "Aviation Archive",
    "sfomuseum:creditline": "Gift of the Captain John B. Russell Family",
    "sfomuseum:date": "11/24/1935",
    "sfomuseum:date_acquired": "2013-05-31",
    "sfomuseum:daterange_end": "1935-11-24",
    "sfomuseum:daterange_start": "1935-11-24",
    "sfomuseum:description": "a. Airmail flight cover, Pan American Airways, FAM-14, first transpacific airmail flight between San Francisco and Manila, Honolulu - Manila leg; purple stamped cachet at left with text “First flight trans-Pacific / F.A.M. Route 14 / Honolulu to Manila”; typewritten text at top left: “Via first contract trans-Pacific flight / Hawaii to Philipine [sic] Islands”; postmarked November 24, 1935 in Honolulu with four-bar cancellation over two 20-cent stamps, one 5-cent stamp, and one 6-cent postage indicia; backstamp: November 29, 1935, Manila; signed by Postmaster John W. Wilson.\rb. Backing sheet with two sets of mounting corners, with handwritten caption: “November 1935, Honolulu to Manila segment”, and black and white photocopy of back side of envelope with Manila receiving stamp.",
    "sfomuseum:dimensions": "3 3/4 x 6 1/2 inches (9.5 x 16.5 cm)",
    "sfomuseum:media_ids": [
      1527852601,
      1527852603
    ],
    "sfomuseum:medium": "paper, ink",
    "sfomuseum:placetype": "object",
    "sfomuseum:publication": ": , 11/24/1935.",
    "sfomuseum:subcategory": "Airmail Flight Cover",
    "sfomuseum:subject": "Airlines -- Commercial -- Pan American Airways.",
    "wof:depicts": [
      1159284991,
      1159286839,
      1159291191
    ],
    "wof:name": "airmail flight cover: Pan American Airways, FAM-14, first transpacific airmail flight, Honolulu - Manila route",
    "wof:placetype": "custom",
    "wof:placetype_alt": "object"
  },
  "geometry": {"coordinates":[-122.386155,37.616357],"type":"Point"}
}
