{
  "type": "Feature",
  "properties": {
    "date:cessation_lower": "1934-01-01",
    "date:cessation_upper": "1934-12-31",
    "date:inception_lower": "1934-01-01",
    "date:inception_upper": "1934-12-31",
    "iso:country": "XX",
    "millsfield:images": [
      1527820847
    ],
    "millsfield:primary_image": 1527820847,
    "sfomuseum:accession_number": "2008.056.0951",
    "sfomuseum:airline": "Pacific Alaska Airways",
    "sfomuseum:category": "Promotional, Archive",
    "sfomuseum:collection": "Aviation Archive",
    "sfomuseum:creditline": "Gift of Jon E. Krupnick",
    "sfomuseum:date": "c. 1934",
    "sfomuseum:date_acquired": "2008-12-31",
    "sfomuseum:daterange_end": "1939-12-31",
    "sfomuseum:daterange_start": "1929-01-01",
    "sfomuseum:description": "Promotional brochure issued by Pacific-Alaska Airways, titled \"Alaska by Air and Water”; red cover with reproduction of watercolor illustration depicting aircraft in flight above ship and glacier; contains fold-out map of Alaska, with descriptions and illustrations.",
    "sfomuseum:dimensions": "9 x 4 inches (22.9 x 10.2 cm)",
    "sfomuseum:issues_held": "\r",
    "sfomuseum:media_ids": [
      1527820847
    ],
    "sfomuseum:medium": "paper, ink",
    "sfomuseum:placetype": "object",
    "sfomuseum:publication": ": , c. 1934.",
    "sfomuseum:subcategory": "Brochure, Airline",
    "sfomuseum:subject": "Airlines -- Commercial -- Pacific Alaska Airways",
    "wof:depicts": [
      1159284957,
      1159288169
    ],
    "wof:name": "brochure: Pacific Alaska Airways, Alaska by Air and Water",
    "wof:placetype": "custom",
    "wof:placetype_alt": "object"
  },
  "geometry": {"coordinates":[-122.386155,37.616357],"type":"Point"}
}
