{
  "type": "Feature",
  "properties": {
    "date:cessation_lower": "1968-12-31",
    "date:cessation_upper": "1968-12-31",
    "date:inception_lower": "1968-01-01",
    "date:inception_upper": "1968-01-01",
    "iso:country": "XX",
    "sfomuseum:accession_number": "2011.032.1919",
    "sfomuseum:artist": "Marshall Moxom",
    "sfomuseum:category": "Photograph",
    "sfomuseum:collection": "Aviation Archive",
    "sfomuseum:creditline": "Transfer",
    "sfomuseum:date": "1968",
    "sfomuseum:daterange_end": "1968-12-31",
    "sfomuseum:daterange_start": "1968-01-01",
    "sfomuseum:description": "From attached handwritten note: “03987 / 4-20-68 / Reception for Airport Operations Ass’n. at World Trade Club / taken by: Moxom”. Black and white photographic negative depicting five unidentified men standing or seated in front of a window with a view of the western span of the Bay Bridge; San Francisco International Airport (SFO); photo taken April 20, 1968, by Marshall Moxom.",
    "sfomuseum:media_ids": [
      1527826637
    ],
    "sfomuseum:medium": "negative",
    "sfomuseum:placetype": "object",
    "sfomuseum:subcategory": "Negative",
    "wof:name": "negative: San Francisco International Airport (SFO), reception for airport operations personnel",
    "wof:placetype": "venue"
  },
  "geometry": {"coordinates":[-122.386155,37.616358],"type":"Point"}
}
