{
  "type": "Feature",
  "properties": {
    "date:cessation_lower": "2005-01-01",
    "date:cessation_upper": "2005-12-31",
    "date:inception_lower": "2005-01-01",
    "date:inception_upper": "2005-12-31",
    "iso:country": "XX",
    "millsfield:images": [
      1527845485,
      1527845487
    ],
    "millsfield:images_texts": [
      "menu",
      "NANCY OAKES\nTEENNETEERINTENSTEITON\n\"In our kitchen,\nwe all feel a reverence\nfor the ingredients\nwe use. We share\nSan Francisco's\nlove and commitment\nto good food.\"\nHeller\nNEI\nORE TOUCH-DOWN MENU \u003eS\nfresh flavours from nancy oakes\nThe moving spirit behind San Francisco's\nbest-known restaurant, chef Nancy Oakes marks\nher modern American cuisine with classic French\nsensibilities and tresh, flavourtul ingredients."
    ],
    "millsfield:images_texts_ids": [
      1527845485,
      1527845487
    ],
    "millsfield:primary_image": 1527845485,
    "sfomuseum:accession_number": "2006.034.137",
    "sfomuseum:airline": "Singapore Airlines",
    "sfomuseum:category": "Passenger Amenity, Archive",
    "sfomuseum:collection": "Aviation Archive",
    "sfomuseum:creditline": "Gift of Adan Wong",
    "sfomuseum:date": "c. 2005",
    "sfomuseum:date_acquired": "2007-04-06",
    "sfomuseum:daterange_end": "2010-12-31",
    "sfomuseum:daterange_start": "2000-01-01",
    "sfomuseum:description": "Menu issued by Singapore Airlines, Singapore - Los Angeles route; color photographic image of Walt Disney Concert Hall on cover; menu items include seared scallops, lamb chops, wok-fried seabass; menu number: SQ20 SIN-LAX (D/SR2/HB) 07-10 RC; class: first; undated.",
    "sfomuseum:dimensions": "11 1/4 x 7 inches (28.6 x 17.8 cm)",
    "sfomuseum:media_ids": [
      1527845485,
      1527845487
    ],
    "sfomuseum:medium": "paper, ink, metal",
    "sfomuseum:placetype": "object",
    "sfomuseum:publication": ": , c. 2005.",
    "sfomuseum:subcategory": "Menu",
    "wof:depicts": [
      1159285163,
      1159288903
    ],
    "wof:name": "menu: Singapore Airlines, First Class",
    "wof:placetype": "custom",
    "wof:placetype_alt": "object"
  },
  "geometry": {"coordinates":[-122.386155,37.616357],"type":"Point"}
}
