{
  "type": "Feature",
  "properties": {
    "date:cessation_lower": "2010-12-31",
    "date:cessation_upper": "2010-12-31",
    "date:inception_lower": "2000-01-01",
    "date:inception_upper": "2000-01-01",
    "iso:country": "XX",
    "sfomuseum:accession_number": "2006.034.137",
    "sfomuseum:category": "Food Service",
    "sfomuseum:collection": "Aviation Museum",
    "sfomuseum:creditline": "Gift of Adan Wong",
    "sfomuseum:date": "c. 2005",
    "sfomuseum:daterange_end": "2010-12-31",
    "sfomuseum:daterange_start": "2000-01-01",
    "sfomuseum:description": "Menu produced by Singapore Airlines, Singapore - Los Angeles route; color photographic image of Walt Disney Concert Hall on cover; menu items include seared scallops, lamb chops, wok-fried seabass; menu number: SQ20 SIN-LAX (D/SR2/HB) 07-10 RC; class: first; undated.",
    "sfomuseum:media_ids": [
      1527845485, 
      1527845487
    ],
    "sfomuseum:medium": "paper, ink, metal",
    "sfomuseum:placetype": "object",
    "sfomuseum:subcategory": "Menu",
    "wof:name": "menu: Singapore Airlines, First Class",
    "wof:placetype": "venue"
  },
  "geometry": {"coordinates":[-122.386155,37.616358],"type":"Point"}
}
