{
  "type": "Feature",
  "properties": {
    "date:cessation_lower": "1980-01-01",
    "date:cessation_upper": "1989-12-31",
    "date:inception_lower": "1980-01-01",
    "date:inception_upper": "1989-12-31",
    "iso:country": "XX",
    "sfomuseum:accession_number": "2000.145.001",
    "sfomuseum:airline": "Qantas Airways",
    "sfomuseum:category": "Passenger Amenity, Museum",
    "sfomuseum:collection": "Aviation Museum",
    "sfomuseum:continent": "World Routes",
    "sfomuseum:creditline": "Gift of Stephen Sutley ",
    "sfomuseum:date": "1980s",
    "sfomuseum:date_acquired": "2001-12-19",
    "sfomuseum:daterange_end": "1989-12-31",
    "sfomuseum:daterange_start": "1980-01-01",
    "sfomuseum:description": "Deck of playing cards issued by Qantas Airways; in half of plastic case; yellow cards with orange map in background; airline servicemark in double-ended format.",
    "sfomuseum:dimensions": "4 x 2 1/2 inches (10.2 x 6.4 cm)",
    "sfomuseum:medium": "paper, plastic, ink",
    "sfomuseum:placetype": "object",
    "sfomuseum:publication": ": , 1980s.",
    "sfomuseum:subcategory": "Playing Cards",
    "wof:depicts": [
      1159285043
    ],
    "wof:name": "playing cards: Qantas Airways",
    "wof:placetype": "venue"
  },
  "geometry": {"coordinates":[-122.386155,37.616357],"type":"Point"}
}
