{
  "type": "Feature",
  "properties": {
    "date:cessation_lower": "1976-01-01",
    "date:cessation_upper": "1976-12-31",
    "date:inception_lower": "1976-01-01",
    "date:inception_upper": "1976-12-31",
    "iso:country": "XX",
    "millsfield:images": [
      1763381049
    ],
    "millsfield:images_texts": [
      "DANTAS\nHO T\nSUANHO"
    ],
    "millsfield:images_texts_ids": [
      1763381049
    ],
    "millsfield:primary_image": 1763381049,
    "sfomuseum:accession_number": "2000.145.001",
    "sfomuseum:airline": "Qantas Airways",
    "sfomuseum:category": "Passenger Amenity, Museum",
    "sfomuseum:collection": "Aviation Museum",
    "sfomuseum:continent": "World Routes",
    "sfomuseum:creditline": "Gift of Stephen Sutley ",
    "sfomuseum:date": "1976",
    "sfomuseum:date_acquired": "2001-12-19",
    "sfomuseum:daterange_end": "1976-12-31",
    "sfomuseum:daterange_start": "1976-01-01",
    "sfomuseum:description": "Deck of playing cards issued by Qantas Airways; includes half of case; yellow cards with orange map and airline servicemark in double-ended format.",
    "sfomuseum:dimensions": "4 x 2 1/2 inches (10.2 x 6.4 cm)",
    "sfomuseum:medium": "cardboard, plastic, ink",
    "sfomuseum:placetype": "object",
    "sfomuseum:publication": ": , 1976.",
    "sfomuseum:subcategory": "Playing Cards",
    "wof:depicts": [
      1159285043,
      1159287479
    ],
    "wof:name": "playing cards: Qantas Airways",
    "wof:placetype": "custom",
    "wof:placetype_alt": [
      "object"
    ]
  },
  "geometry": {"coordinates":[-122.386155,37.616357],"type":"Point"}
}
