{
  "type": "Feature",
  "properties": {
    "date:cessation_lower": "1987-01-01",
    "date:cessation_upper": "1987-12-31",
    "date:inception_lower": "1987-01-01",
    "date:inception_upper": "1987-12-31",
    "iso:country": "XX",
    "millsfield:images": [
      1527845851
    ],
    "millsfield:primary_image": 1527845851,
    "sfomuseum:accession_number": "2009.122.409",
    "sfomuseum:airline": "KLM (Royal Dutch Airlines)",
    "sfomuseum:category": "Scheduling / Ticketing",
    "sfomuseum:collection": "Aviation Archive",
    "sfomuseum:creditline": "Gift of the William Hough Collection",
    "sfomuseum:date": "1987",
    "sfomuseum:date_acquired": "2010-06-08",
    "sfomuseum:daterange_end": "1987-12-31",
    "sfomuseum:daterange_start": "1987-01-01",
    "sfomuseum:description": "World timetable issued by KLM (Royal Dutch Airlines), effective March 29 through September 26, 1987; 114-page fold-out schedule; color photographic image of blue sky with airplane in flight.",
    "sfomuseum:dimensions": "8 1/4 x 4 inches (21 x 10.2 cm)",
    "sfomuseum:media_ids": [
      1527845851
    ],
    "sfomuseum:medium": "paper, ink",
    "sfomuseum:placetype": "object",
    "sfomuseum:publication": ": , 1987.",
    "sfomuseum:subcategory": "Timetable",
    "wof:depicts": [
      1159284613,
      1159287541
    ],
    "wof:name": "timetable: KLM (Royal Dutch Airlines), World edition",
    "wof:placetype": "custom",
    "wof:placetype_alt": "object"
  },
  "geometry": {"coordinates":[-122.386155,37.616357],"type":"Point"}
}
