{
  "type": "Feature",
  "properties": {
    "date:cessation_lower": "1957-12-31",
    "date:cessation_upper": "1957-12-31",
    "date:inception_lower": "1957-01-01",
    "date:inception_upper": "1957-01-01",
    "iso:country": "XX",
    "sfomuseum:accession_number": "2001.080.217",
    "sfomuseum:category": "Food Service",
    "sfomuseum:collection": "Aviation Museum",
    "sfomuseum:continent": "World Routes",
    "sfomuseum:creditline": "Gift of Thomas G. Dragges",
    "sfomuseum:date": "1957",
    "sfomuseum:daterange_end": "1957-12-31",
    "sfomuseum:daterange_start": "1957-01-01",
    "sfomuseum:description": "Menu produced by Air France, New York to Paris route; blue cover with color illustration of winged sea horse with a meal tray; lists menu choices including Virginia ham and chicken Lafayette; menu number 708/P/7-56; date: July 1957.",
    "sfomuseum:media_ids": [
      1527844011, 
      1527844013
    ],
    "sfomuseum:medium": "paper, ink",
    "sfomuseum:placetype": "object",
    "sfomuseum:subcategory": "Menu",
    "wof:name": "menu: Air France",
    "wof:placetype": "venue"
  },
  "geometry": {"coordinates":[-122.386155,37.616358],"type":"Point"}
}
