{
  "type": "Feature",
  "properties": {
    "date:cessation_lower": "1957-01-01",
    "date:cessation_upper": "1957-12-31",
    "date:inception_lower": "1957-01-01",
    "date:inception_upper": "1957-12-31",
    "iso:country": "XX",
    "millsfield:images": [
      1527844011,
      1527844013
    ],
    "millsfield:primary_image": 1527844011,
    "sfomuseum:accession_number": "2001.080.217",
    "sfomuseum:airline": "Air France",
    "sfomuseum:category": "Passenger Amenity, Archive",
    "sfomuseum:collection": "Aviation Archive",
    "sfomuseum:continent": "World Routes",
    "sfomuseum:creditline": "Gift of Thomas G. Dragges",
    "sfomuseum:date": "1957",
    "sfomuseum:date_acquired": "2003-01-02",
    "sfomuseum:daterange_end": "1957-12-31",
    "sfomuseum:daterange_start": "1957-01-01",
    "sfomuseum:description": "Menu issued by Air France, New York to Paris route; blue cover with color illustration of winged sea horse with a meal tray; lists menu choices including Virginia ham and chicken Lafayette; menu number 708/P/7-56; date: July 1957.",
    "sfomuseum:dimensions": "8 1/4 x 5 1/4 inches (21 x 13.3 cm)",
    "sfomuseum:media_ids": [
      1527844011,
      1527844013
    ],
    "sfomuseum:medium": "paper, ink",
    "sfomuseum:placetype": "object",
    "sfomuseum:publication": ": , 1957.",
    "sfomuseum:subcategory": "Menu",
    "wof:depicts": [
      1159283627,
      1360700617
    ],
    "wof:name": "menu: Air France",
    "wof:placetype": "custom",
    "wof:placetype_alt": "object"
  },
  "geometry": {"coordinates":[-122.386155,37.616357],"type":"Point"}
}
