{
  "type": "Feature",
  "properties": {
    "date:cessation_lower": "1997-01-01",
    "date:cessation_upper": "1997-12-31",
    "date:inception_lower": "1997-01-01",
    "date:inception_upper": "1997-12-31",
    "iso:country": "XX",
    "sfomuseum:accession_number": "2004.115.0587",
    "sfomuseum:aircraft": "Boeing 727-200",
    "sfomuseum:airline": "U.S. Postal Service",
    "sfomuseum:airport": "John F. Kennedy International Airport",
    "sfomuseum:artist": "William “Bill” Hough",
    "sfomuseum:category": "Photograph",
    "sfomuseum:collection": "Aviation Archive",
    "sfomuseum:creditline": "Gift of the William Hough Collection",
    "sfomuseum:date": "1997",
    "sfomuseum:date_acquired": "2004-12-28",
    "sfomuseum:daterange_end": "1997-12-31",
    "sfomuseum:daterange_start": "1997-01-01",
    "sfomuseum:description": "Color photographic slide depicting U.S. Postal Service Boeing 727-200 at John F. Kennedy International Airport (JFK), New York, June 8, 1997; photo credit William Hough.",
    "sfomuseum:dimensions": "1 x 1 1/2 inches (2.5 x 3.8 cm)",
    "sfomuseum:medium": "color slide",
    "sfomuseum:placetype": "object",
    "sfomuseum:publication": ": , 1997.",
    "sfomuseum:subcategory": "Slide",
    "wof:depicts": [
      1159293593,
      1159289759,
      1159288179,
      1159285409,
      102534365,
      1159289789
    ],
    "wof:name": "slide: U.S. Postal Service, Boeing 727-200, John F. Kennedy International Airport (JFK)",
    "wof:placetype": "venue"
  },
  "geometry": {"coordinates":[-122.386155,37.616357],"type":"Point"}
}
