{
  "type": "Feature",
  "properties": {
    "date:cessation_lower": "1997-12-31",
    "date:cessation_upper": "1997-12-31",
    "date:inception_lower": "1997-01-01",
    "date:inception_upper": "1997-01-01",
    "iso:country": "XX",
    "sfomuseum:accession_number": "2004.115.0451",
    "sfomuseum:aircraft": "Lockheed L-1011 TriStar",
    "sfomuseum:airline": "American Trans Air  (ATA Airlines)",
    "sfomuseum:airport": "Los Angeles International Airport",
    "sfomuseum:category": "Photograph",
    "sfomuseum:collection": "Aviation Archive",
    "sfomuseum:creditline": "Gift of the William Hough Collection",
    "sfomuseum:date": "1997",
    "sfomuseum:daterange_end": "1997-12-31",
    "sfomuseum:daterange_start": "1997-01-01",
    "sfomuseum:description": "Color photographic slide depicting profile view of American Trans Air (ATA) Lockheed L-1011 TriStar at Los Angeles International Airport (LAX), August 17, 1997; photo taken by William Hough.",
    "sfomuseum:dimensions": "1 x 1 1/2 inches (2.5 x 3.8 cm)",
    "sfomuseum:medium": "color slide",
    "sfomuseum:placetype": "object",
    "sfomuseum:subcategory": "Slide",
    "wof:depicts": [
      1159291129,
      1159293697,
      102533795,
      1159283927
    ],
    "wof:name": "slide: American Trans Air (ATA), Lockheed L-1011 TriStar, Los Angeles International Airport (LAX)",
    "wof:placetype": "venue"
  },
  "geometry": {"coordinates":[-122.386155,37.616357],"type":"Point"}
}
