{
  "type": "Feature",
  "properties": {
    "date:cessation_lower":"1937-12-31",
    "date:cessation_upper":"1937-12-31",
    "date:inception_lower":"1937-01-01",
    "date:inception_upper":"1937-01-01",
    "iso:country":"XX",
    "millsfield:images":[
        1527856529,
        1527856531
    ],
    "sfomuseum:accession_number":"2014.156.184",
    "sfomuseum:category":"Philately",
    "sfomuseum:collection":"Aviation Archive",
    "sfomuseum:creditline":"Gift of Captain Jon Simmonds",
    "sfomuseum:date":"09/06/1937",
    "sfomuseum:daterange_end":"1937-09-06",
    "sfomuseum:daterange_start":"1937-09-06",
    "sfomuseum:description":"First airmail flight cover, A.M. Route 26, Watertown, South Dakota, postmarked September 6, 1937, with two 3-cent postage stamps; blue cachet at left with text, \u201cUnited States Air Mail / First Flight Route AM 26 / Watertown, South Dakota\u201d; envelope addressed to Virginia Le Count, Woodside, New York.",
    "sfomuseum:media_ids":[
        1527856529,
        1527856531
    ],
    "sfomuseum:medium":"paper, ink",
    "sfomuseum:placetype":"object",
    "sfomuseum:subcategory":"Airmail Flight Cover",
    "wof:name":"airmail flight cover: AM-26, Watertown, South Dakota",
    "wof:placetype":"venue"
},
  "geometry": {"coordinates":[-122.386155,37.616358],"type":"Point"}
}