{
  "type": "Feature",
  "properties": {
    "date:cessation_lower": "1929-09-20",
    "date:cessation_upper": "1929-09-20",
    "date:inception_lower": "1929-09-20",
    "date:inception_upper": "1929-09-20",
    "iso:country": "XX",
    "millsfield:images": [
      1527834601,
      1527834603
    ],
    "millsfield:images_texts": [
      "After 6 days, return to\nA M\nGrady C. Harris.\nSEP 20\n1929\n641-643 Seybold Builaing, is\nMIAMI, FLA.\nFIRESI\nFLIGHT\nAlL\nPostmaster,\nParamaribo,\nDutch Guiana.\nHown\nCAN JUAN - PARAM",
      "20t.1 b n1 2102"
    ],
    "millsfield:images_texts_ids": [
      1527834601,
      1527834603
    ],
    "millsfield:primary_image": 1527834601,
    "sfomuseum:accession_number": "2012.149.1703",
    "sfomuseum:category": "Philately",
    "sfomuseum:collection": "Aviation Archive",
    "sfomuseum:creditline": "Gift of the Captain John B. Russell Family",
    "sfomuseum:date": "09/20/1929",
    "sfomuseum:date_acquired": "2013-05-31",
    "sfomuseum:daterange_end": "1929-09-20",
    "sfomuseum:daterange_start": "1929-09-20",
    "sfomuseum:description": "Airmail flight cover, first flight, San Juan - Paramaribo (now Suriname) route; vertically oriented purple cachet at right with image of flying boat over two-masted ship; postmarked September 20, 1929 in Miami, Florida over two 20-cent stamps and one 5-cent postage indicia; backstamp: September 23, 1929 in Paramaibo; addressed to postmaster, Paramaribo, Dutch Guiana.",
    "sfomuseum:dimensions": "3 3/4 x 6 3/4 inches (9.5 x 17.1 cm)",
    "sfomuseum:media_ids": [
      1527834601,
      1527834603
    ],
    "sfomuseum:medium": "paper, ink",
    "sfomuseum:placetype": "object",
    "sfomuseum:publication": ": , 09/20/1929.",
    "sfomuseum:subcategory": "Airmail Flight Cover",
    "wof:name": "airmail flight cover: First flight, San Juan - Paramaribo route",
    "wof:placetype": "custom",
    "wof:placetype_alt": "object"
  },
  "geometry": {"coordinates":[-122.386155,37.616357],"type":"Point"}
}
