{
  "type": "Feature",
  "properties": {
    "date:cessation_lower": "1930-01-01",
    "date:cessation_upper": "1930-12-31",
    "date:inception_lower": "1930-01-01",
    "date:inception_upper": "1930-12-31",
    "iso:country": "XX",
    "millsfield:images": [
      1527851847
    ],
    "millsfield:images_texts": [
      "INTER-ISLAND\nAIRWAYS, LID.\nSubsidiary of Inter-Island Steam Navigation Co., Ltd.\nHONOLULU, HAWAII\nSchedule\nand\nFares\nNo. 9- Effective November 17th, 1930\nWinter Season\nSAFETY — COMFORT - SPEED\nEQUIPMENT\nSikorsky Twin-Motored Eight-Passenger Am-\nphibion Planes.\nThese planes alight and fly from either land or\nwater and are the type best suited for Inter-Island\nservice."
    ],
    "millsfield:images_texts_ids": [
      1527851847
    ],
    "millsfield:primary_image": 1527851847,
    "sfomuseum:accession_number": "2008.075.162",
    "sfomuseum:airline": "Inter-Island Airways",
    "sfomuseum:category": "Scheduling / Ticketing",
    "sfomuseum:collection": "Aviation Archive",
    "sfomuseum:creditline": "Gift of Jon E. Krupnick",
    "sfomuseum:date": "1930",
    "sfomuseum:date_acquired": "2008-12-31",
    "sfomuseum:daterange_end": "1930-12-31",
    "sfomuseum:daterange_start": "1930-01-01",
    "sfomuseum:description": "Timetable issued by Inter Island Airways, effective November 17, 1930, winter service; white and green cover with halftone image of Sikorsky Amphibion with text promoting the airline and aircraft/",
    "sfomuseum:dimensions": "6 1/4 x 3 1/2 inches (15.9 x 8.9 cm)",
    "sfomuseum:issues_held": "\r",
    "sfomuseum:media_ids": [
      1527851847
    ],
    "sfomuseum:medium": "paper, ink",
    "sfomuseum:placetype": "object",
    "sfomuseum:publication": ": , 1930.",
    "sfomuseum:subcategory": "Timetable",
    "sfomuseum:subject": "Airlines -- Commercial -- Inter-Island",
    "wof:depicts": [
      1159287797,
      1159284533
    ],
    "wof:name": "timetable: Inter Island Airways, winter schedule",
    "wof:placetype": "custom",
    "wof:placetype_alt": "object"
  },
  "geometry": {"coordinates":[-122.386155,37.616357],"type":"Point"}
}
