{
  "type": "Feature",
  "properties": {
    "date:cessation_lower": "1960-01-01",
    "date:cessation_upper": "1960-12-31",
    "date:inception_lower": "1960-01-01",
    "date:inception_upper": "1960-12-31",
    "iso:country": "XX",
    "millsfield:images": [
      1527822113
    ],
    "millsfield:primary_image": 1527822113,
    "sfomuseum:accession_number": "2011.032.0362",
    "sfomuseum:aircraft": "Boeing 707",
    "sfomuseum:airline": "Lufthansa",
    "sfomuseum:airport": "San Francisco International Airport",
    "sfomuseum:artist": "Marshall Moxom",
    "sfomuseum:category": "Photograph",
    "sfomuseum:collection": "Aviation Archive",
    "sfomuseum:creditline": "Transfer",
    "sfomuseum:date": "1960",
    "sfomuseum:date_acquired": "2011-03-02",
    "sfomuseum:daterange_end": "1960-12-31",
    "sfomuseum:daterange_start": "1960-01-01",
    "sfomuseum:description": "Black and white photographic negative depicting inaugural service of Lufthansa Boeing 707-430, San Francisco International Airport (SFO), May 14, 1960; American Airlines ramp stairs at right; image credit Marshall Moxom.",
    "sfomuseum:dimensions": "4 x 5 inches (10.2 x 12.7 cm)",
    "sfomuseum:media_ids": [
      1527822113
    ],
    "sfomuseum:medium": "negative",
    "sfomuseum:placetype": "object",
    "sfomuseum:publication": ": , 1960.",
    "sfomuseum:subcategory": "Negative",
    "wof:depicts": [
      1159284711,
      102527513,
      1159289653,
      1159293593
    ],
    "wof:name": "negative: San Francisco International Airport (SFO), Lufthansa, Boeing 707-430",
    "wof:placetype": "venue"
  },
  "geometry": {"coordinates":[-122.386155,37.616357],"type":"Point"}
}
