{
  "type": "Feature",
  "properties": {
    "date:cessation_lower": "1960-01-01",
    "date:cessation_upper": "1960-12-31",
    "date:inception_lower": "1960-01-01",
    "date:inception_upper": "1960-12-31",
    "iso:country": "XX",
    "millsfield:images": [
      1527822113
    ],
    "sfomuseum:accession_number": "2011.032.0362",
    "sfomuseum:aircraft": "Boeing 707",
    "sfomuseum:airline": "Lufthansa",
    "sfomuseum:airport": "San Francisco International Airport",
    "sfomuseum:artist": "Marshall Moxom",
    "sfomuseum:category": "Photograph",
    "sfomuseum:collection": "Aviation Archive",
    "sfomuseum:creditline": "Transfer",
    "sfomuseum:date": "1960",
    "sfomuseum:daterange_end": "1960-12-31",
    "sfomuseum:daterange_start": "1960-01-01",
    "sfomuseum:description": "From attached handwritten note: “04003 / 5-14-60 / Lufthansa airlines inaugural flight. / taken by: Moxom”. Black and white photographic negative depicting partial view of port side of airplane; passengers on tarmac boarding Lufthansa Boeing 707 at San Francisco International Airport (SFO); ramp stairs have American Airlines logo and name; photograph taken by Marshall Moxom on May 14, 1960.",
    "sfomuseum:dimensions": "4 x 5 inches (10.2 x 12.7 cm)",
    "sfomuseum:media_ids": [
      1527822113
    ],
    "sfomuseum:medium": "negative",
    "sfomuseum:placetype": "object",
    "sfomuseum:subcategory": "Negative",
    "wof:depicts": [
      102527513,
      1159289653,
      1159293593,
      1159284711
    ],
    "wof:name": "negative: San Francisco International Airport (SFO), Lufthansa inaugural flight",
    "wof:placetype": "venue"
  },
  "geometry": {"coordinates":[-122.386155,37.616357],"type":"Point"}
}
