{
  "type": "Feature",
  "properties": {
    "date:cessation_lower": "1966-01-01",
    "date:cessation_upper": "1966-12-31",
    "date:inception_lower": "1966-01-01",
    "date:inception_upper": "1966-12-31",
    "iso:country": "XX",
    "loc:named_authorities": [
      "n79077415",
      "n79077414"
    ],
    "loc:subject_heading": {
      "sh85002782": "Airplanes"
    },
    "loc:subject_headings": [
      "sh85002782"
    ],
    "sfomuseum:accession_number": "1999.661.002",
    "sfomuseum:callnumber": "TL540.W7 T8 1929",
    "sfomuseum:category": "Book",
    "sfomuseum:collection": "Aviation Library",
    "sfomuseum:creditline": "Purchase",
    "sfomuseum:date": "1966",
    "sfomuseum:daterange_end": "1966-12-31",
    "sfomuseum:daterange_start": "1966-01-01",
    "sfomuseum:description": "30 p. illus. , 24 cm.",
    "sfomuseum:medium": "paper, ink",
    "sfomuseum:placetype": "object",
    "sfomuseum:publication": "Washington, D.C.: U.S. Govt. print. off., 1966.",
    "sfomuseum:publisher": "U.S. Govt. print. off.",
    "sfomuseum:publisher_location": "Washington, D.C.",
    "sfomuseum:subcategory": "Book",
    "sfomuseum:subject": "Wright, Wilbur, 1867-1912.\rWright, Orville, 1871-1948.\rAirplanes.",
    "wof:name": "Twenty-fifth anniversary of the first airplane flight. Proceedings at the exercises held at Kitty Hawk, N.C., on December 17, 1928, in commemoration of the Twenty-fifth anniversary of the first flight of an airplane made by Wilbur and Orville Wright",
    "wof:placetype": "venue"
  },
  "geometry": {"coordinates":[-122.386155,37.616357],"type":"Point"}
}
