{
  "type": "Feature",
  "properties": {
    "date:cessation_lower": "1975-12-31",
    "date:cessation_upper": "1975-12-31",
    "date:inception_lower": "1975-01-01",
    "date:inception_upper": "1975-01-01",
    "iso:country": "XX",
    "millsfield:images": [
      1527847431
    ],
    "sfomuseum:accession_number": "2012.173.058",
    "sfomuseum:airline": "Alia (Royal Jordanian Airlines)",
    "sfomuseum:category": "Scheduling / Ticketing",
    "sfomuseum:collection": "Aviation Archive",
    "sfomuseum:creditline": "Gift of Willard F. Keeney",
    "sfomuseum:date": "1975",
    "sfomuseum:daterange_end": "1975-12-31",
    "sfomuseum:daterange_start": "1975-01-01",
    "sfomuseum:description": "Summer timetable for Alia (Royal Jordanian Airline), effective April 1, 1975 through October 31, 1975; red, white and black cover with company logotype at top; fold-out format with route map.",
    "sfomuseum:dimensions": "8 1/2 x 3 1/2 inches (21.6 x 8.9 cm)",
    "sfomuseum:media_ids": [
      1527847431
    ],
    "sfomuseum:medium": "paper, ink",
    "sfomuseum:placetype": "object",
    "sfomuseum:subcategory": "Timetable",
    "sfomuseum:subject": "Airlines -- Commercial -- Alia.",
    "wof:depicts": [
      1159283819
    ],
    "wof:name": "timetable: Alia (Royal Jordanian Airlines), summer schedule",
    "wof:placetype": "venue"
  },
  "geometry": {"coordinates":[-122.386155,37.616357],"type":"Point"}
}
