{
  "type": "Feature",
  "properties": {
    "date:cessation_lower": "1975-01-01",
    "date:cessation_upper": "1975-12-31",
    "date:inception_lower": "1975-01-01",
    "date:inception_upper": "1975-12-31",
    "isbn:number": "0914594036, 9780914594031",
    "iso:country": "XX",
    "sfomuseum:accession_number": "1999.660.100",
    "sfomuseum:author": "Sato, Bunsei",
    "sfomuseum:callnumber": "HE9775 .S2713 1975 c.1",
    "sfomuseum:category": "Book",
    "sfomuseum:collection": "Aviation Library",
    "sfomuseum:creditline": "Purchase",
    "sfomuseum:date": "1975",
    "sfomuseum:date_acquired": "1999-01-01",
    "sfomuseum:daterange_end": "1975-12-31",
    "sfomuseum:daterange_start": "1975-01-01",
    "sfomuseum:description": "196 p. : ill. ; 22 cm.",
    "sfomuseum:description_library": "196 p. : ill. ; 22 cm.",
    "sfomuseum:distributor_location": "Elmsford, NY",
    "sfomuseum:medium": "paper, ink",
    "sfomuseum:placetype": "object",
    "sfomuseum:publication": "Los Angeles: Gateway Publishers, 1975.",
    "sfomuseum:publisher": "Gateway Publishers",
    "sfomuseum:publisher_location": "Los Angeles",
    "sfomuseum:subcategory": "Book",
    "sfomuseum:subject": "Nihon KÂokÂu.Hijacking of aircraft.",
    "wof:name": "Hijack: 144 lives in the balance: a firsthand report",
    "wof:placetype": "custom",
    "wof:placetype_alt": [
      "object"
    ]
  },
  "geometry": {"coordinates":[-122.386155,37.616357],"type":"Point"}
}
