{
  "type": "Feature",
  "properties": {
    "date:cessation_lower": "1980-01-01",
    "date:cessation_upper": "1980-12-31",
    "date:inception_lower": "1980-01-01",
    "date:inception_upper": "1980-12-31",
    "iso:country": "XX",
    "millsfield:images": [
      1527842149,
      1527842153
    ],
    "millsfield:images_texts": [
      "TEAR OFF TO OPEN\nIN CASE OF MOTION SICKNESS\nTDA\nREEMATE",
      "TEAR OFF TO OPEN\nFOLD\nFOLD\nTO DISPOSE\n* 1+5\nAFTER USE\n1020T\nFOLD DOTTED\nLINE O\n7737-77588171\nHAND TO STEWARDESS\nFOLD DOTTED\nLINE ?\n1998.157.204"
    ],
    "millsfield:images_texts_ids": [
      1527842149,
      1527842153
    ],
    "millsfield:primary_image": 1527842149,
    "sfomuseum:accession_number": "1998.157.204",
    "sfomuseum:airline": "Toa Domestic Airlines (TDA)",
    "sfomuseum:category": "Passenger Amenity, Archive",
    "sfomuseum:collection": "Aviation Archive",
    "sfomuseum:creditline": "Gift of The Henry Steiner Air Sickness Bag Collection",
    "sfomuseum:date": "c. 1980",
    "sfomuseum:date_acquired": "1999-07-13",
    "sfomuseum:daterange_end": "1985-12-31",
    "sfomuseum:daterange_start": "1975-01-01",
    "sfomuseum:description": "Airsickness bag issued by Toa Domestic Airlines (TDA); white bag with dark blue servicemark and pictorial and written instructions for use in Japanese and English; tear-off paper tab, used to open bag, at top; flat bottom, wire tab closure.",
    "sfomuseum:dimensions": "9 3/4 x 5 1/4 inches (24.8 x 13.3 cm)",
    "sfomuseum:media_ids": [
      1527842149,
      1527842153
    ],
    "sfomuseum:medium": "paper, metal, plastic, ink",
    "sfomuseum:placetype": "object",
    "sfomuseum:publication": ": , c. 1980.",
    "sfomuseum:subcategory": "Airsickness Bag",
    "wof:depicts": [
      1159285303,
      1159288737
    ],
    "wof:name": "airsickness bag: Toa Domestic Airlines (TDA)",
    "wof:placetype": "custom",
    "wof:placetype_alt": [
      "object"
    ]
  },
  "geometry": {"coordinates":[-122.386155,37.616357],"type":"Point"}
}
