{
  "type": "Feature",
  "properties": {
    "date:cessation_lower":"1947-12-31",
    "date:cessation_upper":"1947-12-31",
    "date:inception_lower":"1947-01-01",
    "date:inception_upper":"1947-01-01",
    "iso:country":"XX",
    "sfomuseum:accession_number":"2004.051.018",
    "sfomuseum:aircraft":"Lockheed L-049 Constellation",
    "sfomuseum:airline":"TWA (Trans World Airlines)",
    "sfomuseum:artist":"William T. Larkins",
    "sfomuseum:category":"Photograph",
    "sfomuseum:collection":"Aviation Archive",
    "sfomuseum:creditline":"Gift of William T. Larkins",
    "sfomuseum:date":"1947",
    "sfomuseum:daterange_end":"1947-12-31",
    "sfomuseum:daterange_start":"1947-01-01",
    "sfomuseum:description":"Black and white photograph depicting profile view of TWA (Trans World Airlines) Lockheed L-049 Constellation on tarmac; aircraft registration number \u201cNC86509\u201d; photo taken by William T. Larkins.",
    "sfomuseum:medium":"photograph",
    "sfomuseum:placetype":"object",
    "sfomuseum:subcategory":"Print, Photograph",
    "wof:depicts":[
        1159285393,
        1159291095
    ],
    "wof:name":"photograph: TWA (Trans World Airlines), Lockheed L-049 Constellation",
    "wof:placetype":"venue"
},
  "geometry": {"coordinates":[-122.386155,37.616357],"type":"Point"}
}