{
  "type": "Feature",
  "properties": {
    "date:cessation_lower": "1935-12-31",
    "date:cessation_upper": "1935-12-31",
    "date:inception_lower": "1935-01-01",
    "date:inception_upper": "1935-01-01",
    "iso:country": "XX",
    "millsfield:images": [
      1527820431,
      1527820435
    ],
    "sfomuseum:accession_number": "2001.013.023",
    "sfomuseum:airline": "Pan American Airways  (Pan American World Airways)",
    "sfomuseum:category": "Philately",
    "sfomuseum:collection": "Aviation Archive",
    "sfomuseum:creditline": "Purchase",
    "sfomuseum:date": "3/31/1935",
    "sfomuseum:daterange_end": "1935-03-31",
    "sfomuseum:daterange_start": "1935-03-31",
    "sfomuseum:description": "Airmail flight cover issued by Alameda Chamber of Commerce, commemorating arrival of Pan American Airways Clipper to Alameda Airport; brown cachet with text; postmarked March 31, 1935 in Alameda with football-shaped cancellation mark over 3-cent stamp; no backstamp.",
    "sfomuseum:dimensions": "3 1/2 x 6 1/2 inches (8.9 x 16.5 cm)",
    "sfomuseum:media_ids": [
      1527820435,
      1527820431
    ],
    "sfomuseum:medium": "paper, ink",
    "sfomuseum:placetype": "object",
    "sfomuseum:subcategory": "Airmail Flight Cover",
    "wof:depicts": [
      1159284991
    ],
    "wof:name": "airmail flight cover: Pan American Airways, Alameda Chamber of Commerce \r",
    "wof:placetype": "venue"
  },
  "geometry": {"coordinates":[-122.386155,37.616357],"type":"Point"}
}
