{
  "type": "Feature",
  "properties": {
    "date:cessation_lower":"1935-12-31",
    "date:cessation_upper":"1935-12-31",
    "date:inception_lower":"1935-01-01",
    "date:inception_upper":"1935-01-01",
    "iso:country":"XX",
    "millsfield:images":[
        1527851833
    ],
    "sfomuseum:accession_number":"2008.075.148 a b",
    "sfomuseum:airline":"Pan American Airways  (Pan American World Airways)",
    "sfomuseum:category":"Philately",
    "sfomuseum:collection":"Aviation Archive",
    "sfomuseum:creditline":"Gift of Jon E. Krupnick",
    "sfomuseum:date":"10/05/1935",
    "sfomuseum:daterange_end":"1935-10-05",
    "sfomuseum:daterange_start":"1935-10-05",
    "sfomuseum:description":"Airmail flight cover, Pan American Airways, fourth Pacific survey flight, first flight from San Francisco to Guam and back; fourth Pacific survey; identified by donor with additional information: \"San Francisco - Honolulu, October 5-6; Honolulu - Midway, October 10; Midway - Wake, October 11-12; Wake-Guam, October 13\".\ra. cover: green cachet at left with text, \"First flight eastbound from Guam, Pan American Clipper\"; purple cachet at right with text, \"First flight westbound to Guam, Pan American Clipper\"; three postmarks on front: October 5, 1935, San Francisco, October 16 1935, Guam, and October 24, 1935, San Francisco with football-shaped and wavy cancellations; two backstamps: October 5, 1935, Alameda, California, and October 13, 1935, Guam; three brown 6-cent postage stamps at upper edge; addressed to A.E.A. Bronson.\rb. information sheet: 8 1/2 x 11 with black text; additional information prepared by donor, including route information; flight cover was received mounted to sheet with photo corners.",
    "sfomuseum:media_ids":[
        1527851833
    ],
    "sfomuseum:medium":"paper, ink",
    "sfomuseum:placetype":"object",
    "sfomuseum:subcategory":"Airmail Flight Cover",
    "wof:depicts":[
        1159284991
    ],
    "wof:name":"airmail flight cover: Pan American Airways, Fourth Pacific survey flight, San Francisco to Guam",
    "wof:placetype":"venue"
},
  "geometry": {"coordinates":[-122.386155,37.616357],"type":"Point"}
}