{
  "type": "Feature",
  "properties": {
    "date:cessation_lower": "1997-01-01",
    "date:cessation_upper": "1997-12-31",
    "date:inception_lower": "1997-01-01",
    "date:inception_upper": "1997-12-31",
    "iso:country": "XX",
    "millsfield:images": [
      1527837483
    ],
    "millsfield:images_texts": [
      "Maxwell J's\n33 Solway Drive\nSunshine Beach Qld 4567\nPh (07) 5474 5343\nANSETTAUSTRALIA\nTIMETABLE\nEffective 26th October 1997-\n28th March 1998\n.. ANSETTAUSTRALIA\nSydney 2000\nMember of\nthe Sydney 2000\nOlympic Airline Team"
    ],
    "millsfield:images_texts_ids": [
      1527837483
    ],
    "millsfield:primary_image": 1527837483,
    "sfomuseum:accession_number": "2006.059.156",
    "sfomuseum:aircraft": "Boeing 747",
    "sfomuseum:airline": "Ansett Airlines of Australia",
    "sfomuseum:category": "Scheduling / Ticketing",
    "sfomuseum:collection": "Aviation Archive",
    "sfomuseum:creditline": "Gift of the Paul Edward Fair Estate",
    "sfomuseum:date": "1997",
    "sfomuseum:date_acquired": "2006-10-19",
    "sfomuseum:daterange_end": "1997-12-31",
    "sfomuseum:daterange_start": "1997-01-01",
    "sfomuseum:description": "Timetable issued by Ansett Airlines of Australia, effective October 27, 1997 to March 28, 1998; multipage booklet; white cover with color photographic image of Boeing 747 in flight; promotes 2000 Summer Olympic Games in Sydney.",
    "sfomuseum:dimensions": "8 1/2 x 4 inches (21.6 x 10.2 cm)",
    "sfomuseum:media_ids": [
      1527837483
    ],
    "sfomuseum:medium": "paper, ink",
    "sfomuseum:placetype": "object",
    "sfomuseum:publication": ": , 1997.",
    "sfomuseum:subcategory": "Timetable",
    "sfomuseum:subject": "Airlines -- timetables",
    "wof:depicts": [
      1159287295,
      1159285745,
      1159288271,
      1159283877,
      1159289873,
      1159293593
    ],
    "wof:name": "timetable: AnsettAustralia",
    "wof:placetype": "custom",
    "wof:placetype_alt": [
      "object"
    ]
  },
  "geometry": {"coordinates":[-122.386155,37.616357],"type":"Point"}
}
