{
  "type": "Feature",
  "properties": {
    "date:cessation_lower":"1997-12-31",
    "date:cessation_upper":"1997-12-31",
    "date:inception_lower":"1997-01-01",
    "date:inception_upper":"1997-01-01",
    "iso:country":"XX",
    "sfomuseum:accession_number":"2006.059.156",
    "sfomuseum:category":"Scheduling / Ticketing",
    "sfomuseum:collection":"Aviation Archive",
    "sfomuseum:creditline":"Gift of the Paul Edward Fair Estate",
    "sfomuseum:date":"1997",
    "sfomuseum:daterange_end":"1997-12-31",
    "sfomuseum:daterange_start":"1997-01-01",
    "sfomuseum:description":"Timetable issued by Ansett Airlines of Australia, effective October 27, 1997 to March 28, 1998. White cover with full color photographic image of jet in flight. Logo for Sydney 2000 Olympics at bottom; includes fold-out color map of Australia with flight routes (including Kendell, Flight West Airlines, Aeropelican, Hazelton, Skywest Airlines) on obverse and flight routes on world map with Star Alliance partner airlines on reverse.",
    "sfomuseum:media_ids":[
        1527837483
    ],
    "sfomuseum:medium":"paper, ink",
    "sfomuseum:placetype":"object",
    "sfomuseum:subcategory":"Timetable",
    "wof:name":"timetable: Ansett Airlines of Australia",
    "wof:placetype":"venue"
},
  "geometry": {"coordinates":[-122.386155,37.616358],"type":"Point"}
}