{
  "type": "Feature",
  "properties": {
    "date:cessation_lower": "2010-12-31",
    "date:cessation_upper": "2010-12-31",
    "date:inception_lower": "2000-01-01",
    "date:inception_upper": "2000-01-01",
    "iso:country": "XX",
    "sfomuseum:accession_number": "2007.086.087",
    "sfomuseum:category": "Food Service",
    "sfomuseum:collection": "Aviation Museum",
    "sfomuseum:creditline": "Gift of Ian H. Dally of Auckland, New Zealand",
    "sfomuseum:date": "c. 2005",
    "sfomuseum:daterange_end": "2010-12-31",
    "sfomuseum:daterange_start": "2000-01-01",
    "sfomuseum:description": "Menu produced by Malaysia Airlines, Auckland - Brisbane - Kuala Lumpur route; cover with color illustration of lemongrass stems; menu items include sweet and sour blue nose, chicken cacciatore, and peppered beef with ginger; menu number: MH136 AUCKLAND-BRISBANE-KUALA LUMPUR; undated.",
    "sfomuseum:media_ids": [
      1527845231, 
      1527845233
    ],
    "sfomuseum:medium": "paper, ink, metal",
    "sfomuseum:placetype": "object",
    "sfomuseum:subcategory": "Menu",
    "wof:name": "menu: Malaysia Airlines",
    "wof:placetype": "venue"
  },
  "geometry": {"coordinates":[-122.386155,37.616358],"type":"Point"}
}
