{
  "type": "Feature",
  "properties": {
    "date:cessation_lower": "1971-01-01",
    "date:cessation_upper": "1971-12-31",
    "date:inception_lower": "1971-01-01",
    "date:inception_upper": "1971-12-31",
    "iso:country": "XX",
    "sfomuseum:accession_number": "00-1601",
    "sfomuseum:author": "Hoekstra, Harold D",
    "sfomuseum:callnumber": "TL553.5 .H64 1971",
    "sfomuseum:category": "Book",
    "sfomuseum:collection": "Aviation Library",
    "sfomuseum:date": "1971",
    "sfomuseum:daterange_end": "1971-12-31",
    "sfomuseum:daterange_start": "1971-01-01",
    "sfomuseum:description": "iv, 126 p. illus. 27 cm.",
    "sfomuseum:description_library": "iv, 126 p. illus. 27 cm.",
    "sfomuseum:medium": "paper, ink",
    "sfomuseum:placetype": "object",
    "sfomuseum:publication": "Arlington, VA: Flight Safety Foundation, 1971.",
    "sfomuseum:publisher": "Flight Safety Foundation",
    "sfomuseum:publisher_location": "Arlington, VA",
    "sfomuseum:subcategory": "Book",
    "sfomuseum:subject": "Aircraft accidents.Aeronautics Safety measures.",
    "wof:name": "Safety in general aviation",
    "wof:placetype": "custom",
    "wof:placetype_alt": "object"
  },
  "geometry": {"coordinates":[-122.386155,37.616357],"type":"Point"}
}
