{
  "type": "Feature",
  "properties": {
    "date:cessation_lower": "1965-01-01",
    "date:cessation_upper": "1965-12-31",
    "date:inception_lower": "1965-01-01",
    "date:inception_upper": "1965-12-31",
    "iso:country": "AU",
    "millsfield:images": [
      1729565645,
      1729565647
    ],
    "millsfield:images_texts": [
      "RUSTRALIA\nDANTAS",
      "CANTAS AIRWAYS\nPANTAS BOEING 707\nCruises at 550 m.p.h. Carries 112-132 passen-\ngers and 7 tons of cargo. Wingspan 145' 9',\noverall length 152' 11\".\n491.\nFLY QANTAS -THERE'S A WORLD OF DIFFERENCE\nPOST CARD\nPrinted in Jaban. Toboan Printing Co"
    ],
    "millsfield:images_texts_ids": [
      1729565645,
      1729565647
    ],
    "millsfield:primary_image": 1729565645,
    "sfomuseum:accession_number": "1997.04.03",
    "sfomuseum:aircraft": "Boeing 707",
    "sfomuseum:airline": "Qantas Airways",
    "sfomuseum:category": "Philately",
    "sfomuseum:collection": "Aviation Archive",
    "sfomuseum:continent": "Australia",
    "sfomuseum:country": "Australia",
    "sfomuseum:creditline": "Gift of Catherine J. Allen Paulsen",
    "sfomuseum:date": "c. 1965",
    "sfomuseum:date_acquired": "1997-05-26",
    "sfomuseum:daterange_end": "1970-12-31",
    "sfomuseum:daterange_start": "1960-01-01",
    "sfomuseum:description": "Postcard with color photographic image of Qantas Boeing 707 in flight with clouds and blue sky in the background. Aircraft is flying from left to right side of image; caption on reverse: \"Fly QANTAS, there's a world of difference. Qantas Boeing 707 cruises at 550 miles per hour. Carries 112-132 passengers with 7 tons of cargo. Wingspan 145 feet 9 inches, overall length 152 feet 11 inches.\"",
    "sfomuseum:dimensions": "3 1/2 x 5 1/2 inches (8.9 x 14 cm)",
    "sfomuseum:medium": "paper, ink",
    "sfomuseum:placetype": "object",
    "sfomuseum:publication": ": , c. 1965.",
    "sfomuseum:subcategory": "Postcard",
    "wof:depicts": [
      1159287479,
      1159293593,
      1159289653,
      1159285043
    ],
    "wof:name": "postcard: Qantas Airways, Boeing 707",
    "wof:placetype": "custom",
    "wof:placetype_alt": "object"
  },
  "geometry": {"coordinates":[-122.386155,37.616357],"type":"Point"}
}
