{
  "type": "Feature",
  "properties": {
    "date:cessation_lower": "1987-12-31",
    "date:cessation_upper": "1987-12-31",
    "date:inception_lower": "1987-01-01",
    "date:inception_upper": "1987-01-01",
    "iso:country": "XX",
    "sfomuseum:accession_number": "2003.063.016",
    "sfomuseum:author": "Stokes, Peter (Peter R.)",
    "sfomuseum:callnumber": "TL686.D4 S76 1987",
    "sfomuseum:category": "Book",
    "sfomuseum:collection": "Aviation Library",
    "sfomuseum:creditline": "Purchase",
    "sfomuseum:date": "1987",
    "sfomuseum:daterange_end": "1987-12-31",
    "sfomuseum:daterange_start": "1987-01-01",
    "sfomuseum:description": "126 p. : ill. ; 21 cm.",
    "sfomuseum:medium": "paper, ink",
    "sfomuseum:placetype": "object",
    "sfomuseum:publisher": "Rolls-Royce Heritage Trust",
    "sfomuseum:publisher_location": "Derby, England",
    "sfomuseum:series": "Historical series ; no. 10",
    "sfomuseum:subcategory": "Book",
    "sfomuseum:subject": "De Havilland aircraft Motors History.",
    "wof:name": "From Gipsy to Gem with diversions, 1926-1986: a history of the de Havilland aero engine, Napier \u0026 other associations \u0026 of the Rolls-Royce, Small Engine Division/ byHelicopter Engine Group, 1987",
    "wof:placetype": "venue"
  },
  "geometry": {"coordinates":[-122.386155,37.616357],"type":"Point"}
}
