{
  "type": "Feature",
  "properties": {
    "date:cessation_lower": "1969-01-01",
    "date:cessation_upper": "1969-12-31",
    "date:inception_lower": "1969-01-01",
    "date:inception_upper": "1969-12-31",
    "iso:country": "XX",
    "sfomuseum:accession_number": "2000.181.036",
    "sfomuseum:author": "Pillai, K. G. J.",
    "sfomuseum:callnumber": "HE9783.5 .P55 1969",
    "sfomuseum:category": "Book",
    "sfomuseum:collection": "Aviation Library",
    "sfomuseum:creditline": "Gift of William A. Mathis",
    "sfomuseum:date": "1969",
    "sfomuseum:date_acquired": "1999-10-05",
    "sfomuseum:daterange_end": "1969-12-31",
    "sfomuseum:daterange_start": "1969-01-01",
    "sfomuseum:description": "xix, 212 p. 21 cm.",
    "sfomuseum:description_library": "xix, 212 p. 21 cm.",
    "sfomuseum:medium": "paper, ink",
    "sfomuseum:placetype": "object",
    "sfomuseum:publication": "New York: Grossman Publishers, 1969.",
    "sfomuseum:publisher": "Grossman Publishers",
    "sfomuseum:publisher_location": "New York",
    "sfomuseum:subcategory": "Book",
    "sfomuseum:subject": "International Air Transport Association.Cartels.Airlines Rates.",
    "wof:name": "The air net: the case against the world aviation cartel",
    "wof:placetype": "custom",
    "wof:placetype_alt": "object"
  },
  "geometry": {"coordinates":[-122.386155,37.616357],"type":"Point"}
}
