{
  "type": "Feature",
  "properties": {
    "date:cessation_lower": "1951-01-01",
    "date:cessation_upper": "1951-12-31",
    "date:inception_lower": "1951-01-01",
    "date:inception_upper": "1951-12-31",
    "iso:country": "XX",
    "millsfield:images": [
      1729565485,
      1729565489
    ],
    "millsfield:images_texts": [
      ".. here is your\nPASSENGER TICKET and\nBAGGAGE CHECK\nYou will be\nWELCOME ABOARD-\nenjoy a pleasant flight\nissued by\nTRANS WORLD AIRLINES, Inc.\n10 RICHARDS ROAD, KANSAS CITY 6, MO., U.S. A.\nMember of International Air Transport Association\nMember Air Transport Association\nEach passenger should carefully examine this ticket, particularly the\n152 A\n663128\nIMPORTANT-Tickets covering\nIn-\nternational\ntransportation require\nreconfirmation\nof\nreturn\nreserva-\ntions,\nas well as reservations be-\nyond stopover points at TWA Office,\nnot less than 72 hours before sched-\nuled departure. Failure to do so will\nsubject reservations to cancellation.\nIf transportation covers a portion\nof journey for which no reservation\nhas been made, it is advisable to\nmake such reservations as far in\nadvance as possible.\nTWA\nTRANS WORLD AIRLINES\nU.S.A. • EUROPE • AFRICA • ASIA\nconditions on the inside front cover",
      "ACROSS THE UNITED STATES\nand in\nEUROPE, AFRICA, ASIA\n6692. 10005011\nYOU CAN\nDEPEND\nON\nTWA\nTRANS WORLD AIRLINES\n1S 4122 220\n008"
    ],
    "millsfield:images_texts_ids": [
      1729565485,
      1729565489
    ],
    "millsfield:primary_image": 1729565485,
    "sfomuseum:accession_number": "2000.126.008",
    "sfomuseum:airline": "TWA (Trans World Airlines)",
    "sfomuseum:category": "Scheduling / Ticketing",
    "sfomuseum:collection": "Aviation Archive",
    "sfomuseum:creditline": "Jane Glickman Cavala",
    "sfomuseum:date": "1951",
    "sfomuseum:daterange_end": "1951-12-31",
    "sfomuseum:daterange_start": "1951-01-01",
    "sfomuseum:description": "Passenger ticket and baggage check issued by issued by TWA (Trans World Airlines) to passenger H.M. Iversen, San Francisco to Chicago to Detroit,  serial number 152 A 663128; stamp on reverse from Central Travel Agency, Oakland; date of use May 4, 1951.",
    "sfomuseum:dimensions": "3 1/4 x 6 1/4 inches (8.3 x 15.9 cm)",
    "sfomuseum:medium": "paper, ink",
    "sfomuseum:placetype": "object",
    "sfomuseum:publication": ": , 1951.",
    "sfomuseum:subcategory": "Ticket Jacket / Ticket",
    "wof:depicts": [
      1159285393,
      1159287531
    ],
    "wof:name": "ticket: TWA (Trans World Airlines)",
    "wof:placetype": "custom",
    "wof:placetype_alt": "object"
  },
  "geometry": {"coordinates":[-122.386155,37.616357],"type":"Point"}
}
