{
  "type": "Feature",
  "properties": {
    "date:cessation_lower": "1951-12-31",
    "date:cessation_upper": "1951-12-31",
    "date:inception_lower": "1951-01-01",
    "date:inception_upper": "1951-01-01",
    "iso:country": "XX",
    "sfomuseum:accession_number": "2000.126.008",
    "sfomuseum:airline": "TWA (Trans World Airlines)",
    "sfomuseum:category": "Scheduling / Ticketing",
    "sfomuseum:collection": "Aviation Archive",
    "sfomuseum:creditline": "Jane Glickman Cavala",
    "sfomuseum:date": "1951",
    "sfomuseum:daterange_end": "1951-12-31",
    "sfomuseum:daterange_start": "1951-01-01",
    "sfomuseum:description": "Ticket number 152 A 663128 issued by TWA (Trans World Airlines) to passenger H.M. Iversen, San Francisco to Chicago to Detroit; stamp on reverse from Central Travel Agency, Oakland; date of use May 4, 1951.",
    "sfomuseum:dimensions": "3 1/4 x 6 1/4 inches (8.3 x 15.9 cm)",
    "sfomuseum:medium": "paper, ink",
    "sfomuseum:placetype": "object",
    "sfomuseum:subcategory": "Ticket Jacket / Ticket",
    "wof:depicts": [
      1159285393
    ],
    "wof:name": "ticket: TWA (Trans World Airlines)",
    "wof:placetype": "venue"
  },
  "geometry": {"coordinates":[-122.386155,37.616357],"type":"Point"}
}
