{
  "type": "Feature",
  "properties": {
    "date:cessation_lower":"1999-12-31",
    "date:cessation_upper":"1999-12-31",
    "date:inception_lower":"1990-01-01",
    "date:inception_upper":"1990-01-01",
    "iso:country":"XX",
    "sfomuseum:accession_number":"2001.124.006",
    "sfomuseum:category":"Food Service",
    "sfomuseum:collection":"Aviation Museum",
    "sfomuseum:creditline":"Purchase",
    "sfomuseum:date":"1990s",
    "sfomuseum:daterange_end":"1999-12-31",
    "sfomuseum:daterange_start":"1990-01-01",
    "sfomuseum:description":"First class; white background with black abstract expressionist design (on both sides",
    "sfomuseum:maker":"Schonwald",
    "sfomuseum:medium":"ceramic",
    "sfomuseum:placetype":"object",
    "sfomuseum:subcategory":"Tableware",
    "wof:name":"chopstick rest: Lufthansa German Airlines",
    "wof:placetype":"venue"
},
  "geometry": {"coordinates":[-122.386155,37.616358],"type":"Point"}
}