{
  "type": "Feature",
  "properties": {
    "date:cessation_lower": "1990-01-01",
    "date:cessation_upper": "1999-12-31",
    "date:inception_lower": "1990-01-01",
    "date:inception_upper": "1999-12-31",
    "iso:country": "XX",
    "millsfield:images": [
      1527851019
    ],
    "millsfield:primary_image": 1527851019,
    "sfomuseum:accession_number": "2001.124.006",
    "sfomuseum:airline": "Lufthansa",
    "sfomuseum:category": "Meal Service",
    "sfomuseum:collection": "Aviation Museum",
    "sfomuseum:creditline": "Purchase",
    "sfomuseum:date": "1990s",
    "sfomuseum:date_acquired": "2001-11-28",
    "sfomuseum:daterange_end": "1999-12-31",
    "sfomuseum:daterange_start": "1990-01-01",
    "sfomuseum:description": "Chopstick rest issued by Lufthansa for inflight first class meal service, used on service to Japan; white curved shape chopstick rest with black abstract design on both sides.",
    "sfomuseum:dimensions": "3/4 x 2 1/2 x 3/4 inches (1.9 x 6.4 x 1.9 cm)",
    "sfomuseum:maker": "Schonwald",
    "sfomuseum:media_ids": [
      1527851019
    ],
    "sfomuseum:medium": "glazed porcelain",
    "sfomuseum:placetype": "object",
    "sfomuseum:publication": ": , 1990s.",
    "sfomuseum:subcategory": "Tableware",
    "wof:depicts": [
      1159284711,
      1159288215
    ],
    "wof:name": "chopstick rest: Lufthansa",
    "wof:placetype": "custom",
    "wof:placetype_alt": "object"
  },
  "geometry": {"coordinates":[-122.386155,37.616357],"type":"Point"}
}
