{
  "type": "Feature",
  "properties": {
    "date:cessation_lower": "1960-12-31",
    "date:cessation_upper": "1960-12-31",
    "date:inception_lower": "1950-01-01",
    "date:inception_upper": "1950-01-01",
    "iso:country": "XX",
    "sfomuseum:accession_number": "2010.019.026",
    "sfomuseum:category": "Employee Career History",
    "sfomuseum:collection": "Aviation Archive",
    "sfomuseum:creditline": "Gift of Patricia A. Lionberger in memory of Captain Edward M. Lionberger",
    "sfomuseum:date": "c. 1955",
    "sfomuseum:daterange_end": "1960-12-31",
    "sfomuseum:daterange_start": "1950-01-01",
    "sfomuseum:description": "Employee credit union brochure, titled “Answers to your questions about the employees credit union, United Air Lines”; green and white cover with cartoon depicting business exchange among two male figures; folded brochure containing questions and answers about employee credit union.",
    "sfomuseum:media_ids": [
      1527850813
    ],
    "sfomuseum:medium": "paper, ink",
    "sfomuseum:placetype": "object",
    "sfomuseum:subcategory": "Other, Employee Career History",
    "wof:name": "employee credit union brochure: United Air Lines",
    "wof:placetype": "venue"
  },
  "geometry": {"coordinates":[-122.386155,37.616358],"type":"Point"}
}
