{
  "type": "Feature",
  "properties": {
    "date:cessation_lower": "1960-01-01",
    "date:cessation_upper": "1969-12-31",
    "date:inception_lower": "1960-01-01",
    "date:inception_upper": "1969-12-31",
    "iso:country": "XX",
    "millsfield:images": [
      1729565979,
      1729565981
    ],
    "millsfield:primary_image": 1729565979,
    "sfomuseum:accession_number": "2008.055.557",
    "sfomuseum:aircraft": "Boeing 707",
    "sfomuseum:airline": "Qantas Empire Airways",
    "sfomuseum:category": "Philately",
    "sfomuseum:collection": "Aviation Archive",
    "sfomuseum:creditline": "Gift of the William Hough Collection",
    "sfomuseum:date": "1960s",
    "sfomuseum:date_acquired": "2008-04-13",
    "sfomuseum:daterange_end": "1969-12-31",
    "sfomuseum:daterange_start": "1960-01-01",
    "sfomuseum:description": "Postcard with color photographic image of Qantas Airways Boeing 707 in flight against a blue sky; caption on reverse, “Qantas Boeing 707 V-Jet / Cruises at 580 m.p.h Carries 90 to 120 passengers and 5 tons of cargo. Wingspan 130’ 10”. Overall length 134’ 6”.”.",
    "sfomuseum:dimensions": "3 1/2 x 5 1/2 inches (8.9 x 14 cm)",
    "sfomuseum:medium": "paper, ink",
    "sfomuseum:placetype": "object",
    "sfomuseum:publication": ": , 1960s.",
    "sfomuseum:subcategory": "Postcard",
    "sfomuseum:subject": "Airlines -- Commercial -- Qantas",
    "wof:depicts": [
      1159285825,
      1159287479,
      1159289653,
      1159285043
    ],
    "wof:name": "postcard: Qantas Airways, Boeing 707",
    "wof:placetype": "custom",
    "wof:placetype_alt": "object"
  },
  "geometry": {"coordinates":[-122.386155,37.616357],"type":"Point"}
}
