{
  "type": "Feature",
  "properties": {
    "date:cessation_lower": "1980-01-01",
    "date:cessation_upper": "1980-12-31",
    "date:inception_lower": "1980-01-01",
    "date:inception_upper": "1980-12-31",
    "iso:country": "XX",
    "sfomuseum:accession_number": "99-0560",
    "sfomuseum:author": "Air Force Historical Foundation",
    "sfomuseum:callnumber": "D790 .I46 1980 v.6",
    "sfomuseum:category": "Book",
    "sfomuseum:collection": "Aviation Library",
    "sfomuseum:date": "c. 1980",
    "sfomuseum:daterange_end": "1985-12-31",
    "sfomuseum:daterange_start": "1975-01-01",
    "sfomuseum:description": "8 v. : ill. ; 28 cm.",
    "sfomuseum:description_library": "8 v. : ill. ; 28 cm.",
    "sfomuseum:medium": "paper, ink",
    "sfomuseum:placetype": "object",
    "sfomuseum:publication": "New York: J. Parton, c. 1980.",
    "sfomuseum:publisher": "J. Parton",
    "sfomuseum:publisher_location": "New York",
    "sfomuseum:subcategory": "Book",
    "sfomuseum:subject": "Air warfare Pictorial works.World War, 1939-1945 Aerial operations, American Pictorial works.",
    "wof:name": "Impact: the Army Air Forces' confidential picture history of World War II: in eight books, declassified and now published for the general public for the first time, with fourteen new retrospective essays by World War II leaders and journalists",
    "wof:placetype": "custom",
    "wof:placetype_alt": "object"
  },
  "geometry": {"coordinates":[-122.386155,37.616357],"type":"Point"}
}
