{
  "type": "Feature",
  "properties": {
    "date:cessation_lower": "1965-12-31",
    "date:cessation_upper": "1965-12-31",
    "date:inception_lower": "1965-01-01",
    "date:inception_upper": "1965-01-01",
    "iso:country": "XX",
    "sfomuseum:accession_number": "2011.032.1306",
    "sfomuseum:artist": "Marshall Moxom",
    "sfomuseum:category": "Photograph",
    "sfomuseum:collection": "Aviation Archive",
    "sfomuseum:creditline": "Transfer",
    "sfomuseum:date": "1965",
    "sfomuseum:daterange_end": "1965-12-31",
    "sfomuseum:daterange_start": "1965-01-01",
    "sfomuseum:description": "From attached handwritten note: “03890 / 1-14-65 / Geo Hansen \u0026 Bel Brown / taken by: Moxom”. Black and white photographic negative depicting southwest oblique aerial view of George Hansen, departing Airport Director (right), and Belford Brown, incoming Airport Director (left), on top of building, overlooking parking garage construction and South Terminal (now Terminal 1 / T1) on the landside of airport; photo taken January 14, 1965, by Marshall Moxom.",
    "sfomuseum:media_ids": [
      1527825269
    ],
    "sfomuseum:medium": "negative",
    "sfomuseum:placetype": "object",
    "sfomuseum:subcategory": "Negative",
    "wof:name": "negative: San Francisco International Airport (SFO), Belford Brown and George Hansen",
    "wof:placetype": "venue"
  },
  "geometry": {"coordinates":[-122.386155,37.616358],"type":"Point"}
}
