{
  "type": "Feature",
  "properties": {
    "date:cessation_lower": "1990-01-01",
    "date:cessation_upper": "1999-12-31",
    "date:inception_lower": "1990-01-01",
    "date:inception_upper": "1999-12-31",
    "iso:country": "XX",
    "millsfield:images": [
      1527823353,
      1527823355
    ],
    "sfomuseum:accession_number": "1998.157.005",
    "sfomuseum:airline": "Air China",
    "sfomuseum:category": "Passenger Amenity",
    "sfomuseum:collection": "Aviation Archive",
    "sfomuseum:creditline": "Gift of The Henry Steiner Air Sickness Bag Collection",
    "sfomuseum:date": "1990s",
    "sfomuseum:daterange_end": "1999-12-31",
    "sfomuseum:daterange_start": "1990-01-01",
    "sfomuseum:description": "Flat bottom, adhesive closure. White bag, blue print. \"Air China\" printed across center with logo above it. Asian characters at top, bottom and center of bag.",
    "sfomuseum:dimensions": "9 1/2 x 5 1/4 inches (24.1 x 13.3 cm)",
    "sfomuseum:media_ids": [
      1527823353,
      1527823355
    ],
    "sfomuseum:medium": "paper",
    "sfomuseum:placetype": "object",
    "sfomuseum:subcategory": "Airsickness Bag",
    "wof:depicts": [
      1159283605
    ],
    "wof:name": "airsickness bag: Air China",
    "wof:placetype": "venue"
  },
  "geometry": {"coordinates":[-122.386155,37.616357],"type":"Point"}
}
