{
  "type": "Feature",
  "properties": {
    "date:cessation_lower": "1972-01-01",
    "date:cessation_upper": "1972-12-31",
    "date:inception_lower": "1972-01-01",
    "date:inception_upper": "1972-12-31",
    "isbn:number": "0875840973, 9780875840970",
    "iso:country": "XX",
    "sfomuseum:accession_number": "2000.181.008",
    "sfomuseum:author": "Fruhan, William E",
    "sfomuseum:callnumber": "HE9803.A4 F77 1972",
    "sfomuseum:category": "Book",
    "sfomuseum:collection": "Aviation Library",
    "sfomuseum:creditline": "Gift of William A. Mathis",
    "sfomuseum:date": "1972",
    "sfomuseum:date_acquired": "1999-10-05",
    "sfomuseum:daterange_end": "1972-12-31",
    "sfomuseum:daterange_start": "1972-01-01",
    "sfomuseum:description": "xii, 200 p. illus. 27 cm.",
    "sfomuseum:description_library": "xii, 200 p. illus. 27 cm.",
    "sfomuseum:medium": "paper, ink",
    "sfomuseum:placetype": "object",
    "sfomuseum:publication": "Boston: Division of Research, Graduate School of Business Administration, Harvard University, 1972.",
    "sfomuseum:publisher": "Division of Research, Graduate School of Business Administration, Harvard University",
    "sfomuseum:publisher_location": "Boston",
    "sfomuseum:subcategory": "Book",
    "sfomuseum:subject": "Airlines United States.Aeronautics, Commercial United States.",
    "wof:name": "The fight for competitive advantage: a study of the United States domestic trunk air carriers",
    "wof:placetype": "custom",
    "wof:placetype_alt": [
      "object"
    ]
  },
  "geometry": {"coordinates":[-122.386155,37.616357],"type":"Point"}
}
