{
  "type": "Feature",
  "properties": {
    "date:cessation_lower": "1955-12-31",
    "date:cessation_upper": "1955-12-31",
    "date:inception_lower": "1955-01-01",
    "date:inception_upper": "1955-01-01",
    "iso:country": "XX",
    "sfomuseum:accession_number": "2000.171.050",
    "sfomuseum:category": "Book",
    "sfomuseum:collection": "Aviation Library",
    "sfomuseum:creditline": "Purchase",
    "sfomuseum:date": "1955",
    "sfomuseum:daterange_end": "1955-12-31",
    "sfomuseum:daterange_start": "1955-01-01",
    "sfomuseum:description": "151 p. illus. 21 cm.",
    "sfomuseum:medium": "paper, ink",
    "sfomuseum:placetype": "object",
    "sfomuseum:subcategory": "Book",
    "wof:name": "Wings in your future: aviation for young people",
    "wof:placetype": "venue"
  },
  "geometry": {"coordinates":[-122.386155,37.616357],"type":"Point"}
}
