{
  "type": "Feature",
  "properties": {
    "date:cessation_lower": "1998-01-01",
    "date:cessation_upper": "1998-12-31",
    "date:inception_lower": "1998-01-01",
    "date:inception_upper": "1998-12-31",
    "isbn:number": "1574320599 (v. 1), 9781574320596 (v. 1), 157432148X (v. 2), 9781574321487 (v. 2)",
    "iso:country": "XX",
    "sfomuseum:accession_number": "2011.048.013",
    "sfomuseum:author": "Conroy, Barbara J",
    "sfomuseum:callnumber": "NK8725 .C66 1998 v.2  c.2",
    "sfomuseum:category": "Book",
    "sfomuseum:collection": "Aviation Library",
    "sfomuseum:creditline": "Collection of SFO Museum",
    "sfomuseum:date": "1998",
    "sfomuseum:date_acquired": "2011-06-21",
    "sfomuseum:daterange_end": "1998-12-31",
    "sfomuseum:daterange_start": "1998-01-01",
    "sfomuseum:description": "2 v. : ill. (some col.) ; 29 cm.",
    "sfomuseum:description_library": "2 v. : ill. (some col.) ; 29 cm.",
    "sfomuseum:medium": "paper, ink",
    "sfomuseum:placetype": "object",
    "sfomuseum:publication": "Paducah, KY: Collector Books, 1998.",
    "sfomuseum:publisher": "Collector Books",
    "sfomuseum:publisher_location": "Paducah, KY",
    "sfomuseum:subcategory": "Book",
    "sfomuseum:subject": "Commercial china -- Collectors and collecting -- Catalogs.",
    "wof:name": "Restaurant china: identification \u0026 value guide for restaurant, airline, ship \u0026 railroad dinnerware",
    "wof:placetype": "custom",
    "wof:placetype_alt": "object"
  },
  "geometry": {"coordinates":[-122.386155,37.616357],"type":"Point"}
}
