{
  "type": "Feature",
  "properties": {
    "date:cessation_lower": "1967-01-01",
    "date:cessation_upper": "1967-12-31",
    "date:inception_lower": "1967-01-01",
    "date:inception_upper": "1967-12-31",
    "iso:country": "XX",
    "sfomuseum:accession_number": "2001.161.001",
    "sfomuseum:author": "Bongers, Hans M.",
    "sfomuseum:callnumber": "HE9849.D4 B6 1967",
    "sfomuseum:category": "Book",
    "sfomuseum:collection": "Aviation Library",
    "sfomuseum:creditline": "Gift of Hans Steuck",
    "sfomuseum:date": "1967",
    "sfomuseum:date_acquired": "2002-11-13",
    "sfomuseum:daterange_end": "1967-12-31",
    "sfomuseum:daterange_start": "1967-01-01",
    "sfomuseum:description": "280 p. illus., diagrs., charts.",
    "sfomuseum:description_library": "280 p. illus., diagrs., charts.",
    "sfomuseum:medium": "paper, ink",
    "sfomuseum:notes_library": "Includes bibliographical references.",
    "sfomuseum:placetype": "object",
    "sfomuseum:publication": "Bad Godesberg, Germany: Kirschbaum, 1967.",
    "sfomuseum:publisher": "Kirschbaum",
    "sfomuseum:publisher_location": "Bad Godesberg, Germany",
    "sfomuseum:subcategory": "Book",
    "sfomuseum:subject": "Airlines Germany.Aeronautics, Commercial Germany.Deutsche Lufthansa (1926-1945)",
    "wof:name": "Deutscher Luftverkehr: Entwicklung, Politik Wirtschaft, Organisation. Versuch einer Analyse der Lufthansa",
    "wof:placetype": "venue"
  },
  "geometry": {"coordinates":[-122.386155,37.616357],"type":"Point"}
}
