{
  "type": "Feature",
  "properties": {
    "date:cessation_lower": "1980-01-01",
    "date:cessation_upper": "1980-12-31",
    "date:inception_lower": "1980-01-01",
    "date:inception_upper": "1980-12-31",
    "iso:country": "XX",
    "millsfield:images": [
      1729566241
    ],
    "millsfield:primary_image": 1729566241,
    "sfomuseum:accession_number": "1999.058.003",
    "sfomuseum:airline": "TWA (Trans World Airlines)",
    "sfomuseum:category": "Scheduling / Ticketing",
    "sfomuseum:collection": "Aviation Archive",
    "sfomuseum:continent": "World Routes",
    "sfomuseum:creditline": "Gift of John Zukowsky",
    "sfomuseum:date": "1980",
    "sfomuseum:date_acquired": "2000-02-22",
    "sfomuseum:daterange_end": "1980-12-31",
    "sfomuseum:daterange_start": "1980-01-01",
    "sfomuseum:description": "Luggage identification tag issued by Trans World Airlines, Royal Ambassador (first) class; blue and yellow tag with ribbon servicemark and elastic attachment; form number PAS-270RA.",
    "sfomuseum:dimensions": "2 3/4 x 4 1/2 inches (7 x 11.4 cm)",
    "sfomuseum:medium": "paper, elastic, ink",
    "sfomuseum:placetype": "object",
    "sfomuseum:publication": ": , 1980.",
    "sfomuseum:subcategory": "Identification Tag / Form, Paper",
    "wof:depicts": [
      1159285393
    ],
    "wof:name": "luggage identification tag: TWA (Trans World Airlines)",
    "wof:placetype": "venue"
  },
  "geometry": {"coordinates":[-122.386155,37.616357],"type":"Point"}
}
