{
  "type": "Feature",
  "properties": {
    "date:cessation_lower": "1982-01-01",
    "date:cessation_upper": "1982-12-31",
    "date:inception_lower": "1982-01-01",
    "date:inception_upper": "1982-12-31",
    "isbn:number": "0370000323, 9780370000329,0370309421, 9780370309422",
    "iso:country": "XX",
    "sfomuseum:accession_number": "1999.669.065",
    "sfomuseum:author": "Davies, R. E. G. (Ronald Edward George)",
    "sfomuseum:callnumber": "TL726.2 .D38 1982 ",
    "sfomuseum:category": "Book",
    "sfomuseum:collection": "Aviation Library",
    "sfomuseum:creditline": "Purchase",
    "sfomuseum:date": "1982",
    "sfomuseum:date_acquired": "1999-01-01",
    "sfomuseum:daterange_end": "1982-12-31",
    "sfomuseum:daterange_start": "1982-01-01",
    "sfomuseum:description": "xiii, 746 p. : ill., maps, ports. ; 21 cm.",
    "sfomuseum:description_library": "xiii, 746 p. : ill., maps, ports. ; 21 cm.",
    "sfomuseum:medium": "paper, ink",
    "sfomuseum:placetype": "object",
    "sfomuseum:publication": "London: Putnam, 1982.",
    "sfomuseum:publisher": "Putnam",
    "sfomuseum:publisher_location": "London",
    "sfomuseum:subcategory": "Book",
    "sfomuseum:subject": "Airlines United States History.",
    "wof:name": "Airlines of the United States since 1914",
    "wof:placetype": "custom",
    "wof:placetype_alt": "object"
  },
  "geometry": {"coordinates":[-122.386155,37.616357],"type":"Point"}
}
