{
  "type": "Feature",
  "properties": {
    "date:cessation_lower": "1939-05-23",
    "date:cessation_upper": "1939-05-23",
    "date:inception_lower": "1939-05-23",
    "date:inception_upper": "1939-05-23",
    "iso:country": "XX",
    "millsfield:images": [
      1527820365,
      1527820369
    ],
    "millsfield:images_texts": [
      "Capt. le E. la torle\nPAR PREMIER SERVICE ABRIEN ER\n1er SERVICE POSTAL\nAÉRIEN\n939\nSCH58 DUB\n23\n-5\n39\nSTRANGES\nMr. José N. da Silva,\nNo. 4 Rua Cláudio Nunes,\nBemfica, Lisbon, PORTUGAL\nREPUBLIQUE FRANCAISE\nFRANCE • ETATS-UNIS",
      "26.5.33 -348\n26.5.39. -51\n26.5.02 -01\nSBO%\nAViA\n30995*\n00 00227\nBIN:\nMLA COS C7\nTAN 2-10 S\n2000.038.126"
    ],
    "millsfield:images_texts_ids": [
      1527820365,
      1527820369
    ],
    "millsfield:primary_image": 1527820365,
    "sfomuseum:accession_number": "2000.058.1266",
    "sfomuseum:airline": "Pan American Airways",
    "sfomuseum:category": "Philately",
    "sfomuseum:collection": "Aviation Archive",
    "sfomuseum:creditline": "Gift of the Pan Am Association",
    "sfomuseum:date": "05/23/1939",
    "sfomuseum:date_acquired": "2000-12-14",
    "sfomuseum:daterange_end": "1939-05-23",
    "sfomuseum:daterange_start": "1939-05-23",
    "sfomuseum:description": "Airmail flight cover, Pan American Airways, first airmail flight, Paris - New York route; red cachet depicting aircraft in flight and Statue of Liberty; signed by Captain A.E. La Porte; postmarked May 23, 1939 in Paris and May 225, 1939 in Marseilles over French stamps; backstamp: May 26, 1939 in Lisbon.",
    "sfomuseum:dimensions": "3 3/4 x 6 1/2 inches (9.5 x 16.5 cm)",
    "sfomuseum:media_ids": [
      1527820365,
      1527820369
    ],
    "sfomuseum:medium": "paper, ink",
    "sfomuseum:placetype": "object",
    "sfomuseum:publication": ": , 05/23/1939.",
    "sfomuseum:subcategory": "Airmail Flight Cover",
    "wof:depicts": [
      1159284991,
      1159286839
    ],
    "wof:name": "airmail flight cover: Pan American Airways, first airmail flight, France - United States route",
    "wof:placetype": "custom",
    "wof:placetype_alt": [
      "object"
    ]
  },
  "geometry": {"coordinates":[-122.386155,37.616357],"type":"Point"}
}
