{
  "type": "Feature",
  "properties": {
    "date:cessation_lower": "1932-01-01",
    "date:cessation_upper": "1932-12-31",
    "date:inception_lower": "1932-01-01",
    "date:inception_upper": "1932-12-31",
    "iso:country": "XX",
    "sfomuseum:accession_number": "2000.160.0734",
    "sfomuseum:author": "Murray, Kenneth Malcolm",
    "sfomuseum:callnumber": "DK440 .M87 1932 SC",
    "sfomuseum:category": "Book",
    "sfomuseum:collection": "Aviation Library",
    "sfomuseum:creditline": "The Tony Bill Aviation Library Collection",
    "sfomuseum:date": "1932",
    "sfomuseum:date_acquired": "1999-05-18",
    "sfomuseum:daterange_end": "1932-12-31",
    "sfomuseum:daterange_start": "1932-01-01",
    "sfomuseum:description": "ix, [1] p., 3 l., 362, [1] p. front., plates, ports. 23 cm.",
    "sfomuseum:description_library": "ix, [1] p., 3 l., 362, [1] p. front., plates, ports. 23 cm.",
    "sfomuseum:medium": "paper, ink",
    "sfomuseum:placetype": "object",
    "sfomuseum:publication": "New York; London: D. Appleton, 1932.",
    "sfomuseum:publisher": "D. Appleton",
    "sfomuseum:publisher_location": "New York; London",
    "sfomuseum:subcategory": "Book",
    "sfomuseum:subject": "Poland History Wars of 1918-1921",
    "wof:name": "Wings over Poland: the story of the 7th (Kosciuszko) squadron of the Polish air service, 1919, 1920, 1921",
    "wof:placetype": "custom",
    "wof:placetype_alt": "object"
  },
  "geometry": {"coordinates":[-122.386155,37.616357],"type":"Point"}
}
