{
  "type": "Feature",
  "properties": {
    "date:cessation_lower": "1992-01-01",
    "date:cessation_upper": "1992-12-31",
    "date:inception_lower": "1992-01-01",
    "date:inception_upper": "1992-12-31",
    "iso:country": "XX",
    "sfomuseum:accession_number": "2005.009.009",
    "sfomuseum:author": "Geer, Mary Wells",
    "sfomuseum:callnumber": "TL540.W399 G44 1992",
    "sfomuseum:category": "Book",
    "sfomuseum:collection": "Aviation Library",
    "sfomuseum:creditline": "Purchase",
    "sfomuseum:date": "c. 1992",
    "sfomuseum:date_acquired": "2005-12-31",
    "sfomuseum:daterange_end": "1997-12-31",
    "sfomuseum:daterange_start": "1987-01-01",
    "sfomuseum:description": "ix, 179 p. : ill. ; 24 cm.",
    "sfomuseum:description_library": "ix, 179 p. : ill. ; 24 cm.",
    "sfomuseum:medium": "paper, ink",
    "sfomuseum:notes_library": "Includes bibliographical references and index.",
    "sfomuseum:placetype": "object",
    "sfomuseum:publication": "Seattle, WA: University of Washington Press, c. 1992.",
    "sfomuseum:publisher": "University of Washington Press",
    "sfomuseum:publisher_location": "Seattle, WA",
    "sfomuseum:subcategory": "Book",
    "sfomuseum:subject": "Wells, Edward Curtis, 1910-",
    "wof:name": "Boeing's Ed Wells",
    "wof:placetype": "venue"
  },
  "geometry": {"coordinates":[-122.386155,37.616357],"type":"Point"}
}
