{
  "type": "Feature",
  "properties": {
    "date:cessation_lower": "2005-12-31",
    "date:cessation_upper": "2005-12-31",
    "date:inception_lower": "2005-01-01",
    "date:inception_upper": "2005-01-01",
    "iso:country": "XX",
    "sfomuseum:accession_number": "2005.050.004",
    "sfomuseum:airline": "Pan American World Airways",
    "sfomuseum:author": "Krupnick, Jon E.",
    "sfomuseum:callnumber": "TL521.A4 S6 2005 no.4 c.1",
    "sfomuseum:category": "Book",
    "sfomuseum:collection": "Aviation Library",
    "sfomuseum:creditline": "Transfer from City and County of San Francisco",
    "sfomuseum:date": "2005",
    "sfomuseum:daterange_end": "2005-12-31",
    "sfomuseum:daterange_start": "2005-01-01",
    "sfomuseum:medium": "paper, ink",
    "sfomuseum:placetype": "object",
    "sfomuseum:publisher": "San Francisco Aeronautical Society",
    "sfomuseum:publisher_location": "San Francisco",
    "sfomuseum:series": "Spirit of Flight Lectures",
    "sfomuseum:subcategory": "Book",
    "sfomuseum:subject": "Pan American World Airways, inc. History. Postmarks Collectors and collecting United States. Covers (Philately)",
    "wof:depicts": [
      1159284989
    ],
    "wof:name": "Pan American's pacific pioneers [Spirit of Flight lecture] ",
    "wof:placetype": "venue"
  },
  "geometry": {"coordinates":[-122.386155,37.616357],"type":"Point"}
}
