{
  "type": "Feature",
  "properties": {
    "date:cessation_lower": "1969-12-31",
    "date:cessation_upper": "1969-12-31",
    "date:inception_lower": "1969-01-01",
    "date:inception_upper": "1969-01-01",
    "iso:country": "XX",
    "millsfield:images": [
      1527830203,
      1527830205
    ],
    "sfomuseum:accession_number": "2009.145.004",
    "sfomuseum:category": "Philately",
    "sfomuseum:collection": "Aviation Archive",
    "sfomuseum:creditline": "Anonymous gift",
    "sfomuseum:date": "10/01/1969",
    "sfomuseum:daterange_end": "1969-10-01",
    "sfomuseum:daterange_start": "1969-10-01",
    "sfomuseum:description": "Airmail flight cover commemorating the first airmail flight of AM-31, San Francisco to Atlanta; black cachet with image of in-flight aircraft; postmark: October 1, 1969, San Francisco, with four-line cancellation mark over 2-cent and 8-cent stamps; backstamp: October 1, 1969, Atlanta; white envelope.",
    "sfomuseum:media_ids": [
      1527830203,
      1527830205
    ],
    "sfomuseum:medium": "paper, ink",
    "sfomuseum:placetype": "object",
    "sfomuseum:subcategory": "Airmail Flight Cover",
    "wof:name": "airmail flight cover: Commemoration of first airmail flight, AM-31, San Francisco to Atlanta",
    "wof:placetype": "venue"
  },
  "geometry": {"coordinates":[-122.386155,37.616357],"type":"Point"}
}
