{
  "type": "Feature",
  "properties": {
    "date:cessation_lower": "1997-01-01",
    "date:cessation_upper": "1997-12-31",
    "date:inception_lower": "1997-01-01",
    "date:inception_upper": "1997-12-31",
    "iso:country": "XX",
    "millsfield:images": [
      1527847399
    ],
    "millsfield:images_texts": [
      "DIRECT FLIGHT TIMETABLE\nAlagka Airlines\nINCLUDES HORIZON AIR\nCelebrating 65 years\nof service.\nAlaska Airlines offers more flights to, from and within Alaska than any other airline.\nEFFECTIVE JUNE 8, 1997\nFor flight information \u0026 reservations call 1 800 426 0333.\nOr online at http://www.alaskaair.com\nIncludes Horizon Air and codeshare flights operated by Northwest Airlines."
    ],
    "millsfield:images_texts_ids": [
      1527847399
    ],
    "millsfield:primary_image": 1527847399,
    "sfomuseum:accession_number": "2011.126.008.003",
    "sfomuseum:airline": "Alaska Airlines",
    "sfomuseum:category": "Scheduling / Ticketing",
    "sfomuseum:collection": "Aviation Archive",
    "sfomuseum:creditline": "Gift of the Paul H. Kowalewski Collection",
    "sfomuseum:date": "1997",
    "sfomuseum:date_acquired": "2011-12-22",
    "sfomuseum:daterange_end": "1997-12-31",
    "sfomuseum:daterange_start": "1997-01-01",
    "sfomuseum:description": "Direct flight timetable issued by Alaska Airlines, including Horizon Air, effective June 8, 1997; brown cover with color photographic image of Northwest coastal Native American carving and text “Celebrating 65 years of service”.",
    "sfomuseum:dimensions": "8 1/2 x 4 inches (21.6 x 10.2 cm)",
    "sfomuseum:media_ids": [
      1527847399
    ],
    "sfomuseum:medium": "paper, ink",
    "sfomuseum:placetype": "object",
    "sfomuseum:publication": ": , 1997.",
    "sfomuseum:subcategory": "Timetable",
    "wof:depicts": [
      1159283813,
      1159284505,
      1159287275
    ],
    "wof:name": "timetable: Alaska Airlines, includes Horizon Air",
    "wof:placetype": "custom",
    "wof:placetype_alt": "object"
  },
  "geometry": {"coordinates":[-122.386155,37.616357],"type":"Point"}
}
