{
  "type": "Feature",
  "properties": {
    "date:cessation_lower": "1968-01-01",
    "date:cessation_upper": "1968-12-31",
    "date:inception_lower": "1968-01-01",
    "date:inception_upper": "1968-12-31",
    "iso:country": "XX",
    "millsfield:images": [
      1746680735
    ],
    "millsfield:images_texts": [
      "PSA\nFLIGHT SCHEDULES\nNOW ALL JET SERVICE\nNEW! Hollywood-Burbank/San Jose\nand Oakland Service\nEffective September 9, 1968\nSchedule sabiect to change\nMONDAY THROUGH THURSDAY\nSOUTHBOUND\nLV\nILV\nSAC\nLV TAR ILV\nSUBININE\nAR\nAR\n7:00\nTRANSIT\n7:00 7:30 8:10\n8:00\n8:05 8:25\n8:108:30\n8:20\n8:40\n8:50\n8:30\n10-30\n0-15\n12:00\n1:15\n1:55\n215\n9:30\n9:50\n9:55\n10.00 10-20 10-40\n10:10 10.30 10:50\n11:25\n11:00 11:20 11:40\n11:4512:0512:20\n11:45\n12:45\n1:05\n1:25\n2:40\n255\n424\nThere\n• 46\n872"
    ],
    "millsfield:images_texts_ids": [
      1746680735
    ],
    "millsfield:primary_image": 1746680735,
    "sfomuseum:accession_number": "2005.132.042.009",
    "sfomuseum:airline": "Pacific Southwest Airlines (PSA)",
    "sfomuseum:category": "Scheduling / Ticketing",
    "sfomuseum:collection": "Aviation Archive",
    "sfomuseum:creditline": "Gift of the William Hough Collection",
    "sfomuseum:date": "1968",
    "sfomuseum:date_acquired": "2006-12-05",
    "sfomuseum:daterange_end": "1968-12-31",
    "sfomuseum:daterange_start": "1968-01-01",
    "sfomuseum:description": "Timetable issued by Pacific Southwest Airlines (PSA), effective September 9, 1968; four page double-sided fold-out; white cover with list of Monday through Thursday southbound routes.",
    "sfomuseum:dimensions": "9 x 3 1/4 inches (22.9 x 8.3 cm)",
    "sfomuseum:medium": "paper, ink",
    "sfomuseum:placetype": "object",
    "sfomuseum:publication": ": , 1968.",
    "sfomuseum:subcategory": "Timetable",
    "wof:depicts": [
      1159286629,
      1159284973
    ],
    "wof:name": "timetable: Pacific Southwest Airlines (PSA)",
    "wof:placetype": "custom",
    "wof:placetype_alt": "object"
  },
  "geometry": {"coordinates":[-122.386155,37.616357],"type":"Point"}
}
