{
  "type": "Feature",
  "properties": {
    "date:cessation_lower": "1968-01-01",
    "date:cessation_upper": "1968-12-31",
    "date:inception_lower": "1968-01-01",
    "date:inception_upper": "1968-12-31",
    "iso:country": "XX",
    "millsfield:images": [
      1746680735
    ],
    "millsfield:images_texts": [
      "PSA\nFLIGHT SCHEDULES\nNOW! ALL JET SERVICE\nNEW! Hollywood-Burbank/San Jose\nand Oakland Service\nEffective September 9, 1968\nSchedule subject to change without notice.\nMONDAY THROUGH THURSDAY\nSOUTHBOUND\nFit.\nNo.\nS\nS\n760\n710\n780\n702\nS\n752\n778\nD\n854\n810\n84\n870\n910\nD\n940\n960\nS\n984\n172\n102\n114\n132\nS\n144\n14\nS\nD\n120\n254\n270\n182\nS\nS\n10\n124\n272\n244\n330\n302\nD 360\nS\n422\nS\n480\n472\n44\n442\n510\nS\n588\n54\nS\n632\n642\n602\n670\nS\nS\n684\n610\n740\nS\n762\n872\nS\n912\n92\nS\n852\nLV\nSAC\n7:00\n9:30\n1:15\n4:00\n5:00\n6:45\nLV\nSF\n7:00\n7:30\n8:20\n8:30\n9:15\n10:00\n10:15\n11:00\n12:00\n1:15\n1:30\n2:45\n3: 00\n4: 00\n4:30\n5:00\n6: 00\n6:45\n7:00\n7:45\n8: 15\nLV\nOAK\nLV\nSJ\n7:00\n7:00\n7:15\n7:30\n8:00\n8:30\n9:20\n9:30\n10:00 10:30\n11:00\n11:30\n1:00\n1:30\n2:45\n3: 00\n3:30\n3:30\n4:30\n4:45\n5:30\n6:15\n6:20\n6:50\n7:15\n7:30\n8:30\n8:30\nAR\nLV\nHWB HWB\nAR\nLA\nLV\nLA\nAR\nSD\n7:40\n7:45\n7:50\n8:05\n8:10\n8:10\n8:25\n8:00\n8:20\n8:25\n8:30\n8:50\n8:40\n8:10\n8:50\n9:05\n9:10\n9:10\n9:30\n9:30\n9:50\n9:55\n10:00\n10:20\n10:40\n10:10\n10:10\n10:30\n10:50\n10:20\n10:40\n11:00\n11:10\n11:25\n11:00 11:20\n11:40\n11:45\n12: 05\n12:25\n11:45\n12:15\n12:45\n1:05\n1:25\n1:50\n1:55\n2: 15\n2:40\n2:05\n2:10\n2:15\n2:35\n3:25\n3:45\n2:55\n4:10\n3:30\n3: 45\n4: 05\n4:25\n4:10\n4:15\n4: 45\n4:50\n5:10\n5:10\n5:30\n5:30\n5:55\n7:30\n7:25\n5:10\n5:30\n5:45\n5:50\n6:10\n6:45\n7:05\n5:50\n6: 05\n6:10\n6:25\n7:25\n7:45\n7:45\n7:35\n7:45\n8: 00\n8:10\n7:55\n8:05\n8:10\n8: 15\n8:25\n8:25\n9:00\n9: 10\n9: 15\n9:20\n9:40"
    ],
    "millsfield:images_texts_ids": [
      1746680735
    ],
    "millsfield:primary_image": 1746680735,
    "sfomuseum:accession_number": "2005.132.042.009",
    "sfomuseum:airline": "Pacific Southwest Airlines (PSA)",
    "sfomuseum:category": "Scheduling / Ticketing",
    "sfomuseum:collection": "Aviation Archive",
    "sfomuseum:creditline": "Gift of the William Hough Collection",
    "sfomuseum:date": "1968",
    "sfomuseum:date_acquired": "2006-12-05",
    "sfomuseum:daterange_end": "1968-12-31",
    "sfomuseum:daterange_start": "1968-01-01",
    "sfomuseum:description": "Timetable issued by Pacific Southwest Airlines (PSA), effective September 9, 1968; four page double-sided fold-out; white cover with list of Monday through Thursday southbound routes.",
    "sfomuseum:dimensions": "9 x 3 1/4 inches (22.9 x 8.3 cm)",
    "sfomuseum:medium": "paper, ink",
    "sfomuseum:placetype": "object",
    "sfomuseum:publication": ": , 1968.",
    "sfomuseum:subcategory": "Timetable",
    "wof:depicts": [
      1159284973,
      1159286629
    ],
    "wof:name": "timetable: Pacific Southwest Airlines (PSA)",
    "wof:placetype": "custom",
    "wof:placetype_alt": "object"
  },
  "geometry": {"coordinates":[-122.386155,37.616357],"type":"Point"}
}
