{
  "type": "Feature",
  "properties": {
    "date:cessation_lower": "1944-01-01",
    "date:cessation_upper": "1944-12-31",
    "date:inception_lower": "1944-01-01",
    "date:inception_upper": "1944-12-31",
    "iso:country": "XX",
    "sfomuseum:accession_number": "2002.113.024",
    "sfomuseum:airline": "Transcontinental \u0026 Western Air",
    "sfomuseum:artist": "Ida and Greer, Howard Staggers , Christian Dior",
    "sfomuseum:category": "Clothing",
    "sfomuseum:collection": "Aviation Museum",
    "sfomuseum:creditline": "Gift of TWA Clipped Wings International",
    "sfomuseum:date": "1944",
    "sfomuseum:date_acquired": "2004-12-08",
    "sfomuseum:daterange_end": "1944-12-31",
    "sfomuseum:daterange_start": "1944-01-01",
    "sfomuseum:description": "Air hostess blouse-slip issued by Transcontinental \u0026 Western Air (TWA) for \"Cutout\" uniform; navy blue knee-length with short sleeves and jewel neckline, zipper at back; red embroidered “TWA” on proper right breast with button flap; worn 1944-1955.",
    "sfomuseum:dimensions": "40 x 30 inches (101.6 x 76.2 cm)",
    "sfomuseum:maker": "Briny Marlin",
    "sfomuseum:medium": "rayon",
    "sfomuseum:placetype": "object",
    "sfomuseum:publication": ": , 1944.",
    "sfomuseum:subcategory": "Blouse / Shirt",
    "wof:depicts": [
      1159285395,
      1159287531
    ],
    "wof:name": "air hostess blouse-slip: Transcontinental \u0026 Western Air (TWA), \"Cutout\"",
    "wof:placetype": "custom",
    "wof:placetype_alt": "object"
  },
  "geometry": {"coordinates":[-122.386155,37.616357],"type":"Point"}
}
