{
  "type": "Feature",
  "properties": {
    "date:cessation_lower": "1944-01-01",
    "date:cessation_upper": "1944-12-31",
    "date:inception_lower": "1944-01-01",
    "date:inception_upper": "1944-12-31",
    "iso:country": "XX",
    "millsfield:exhibition_ids": [
      1159160129
    ],
    "millsfield:images": [
      1763447421,
      1763447425
    ],
    "millsfield:on_view": 0,
    "millsfield:primary_image": 1763447421,
    "sfomuseum:accession_number": "2002.113.024",
    "sfomuseum:airline": "Transcontinental \u0026 Western Air",
    "sfomuseum:artist": "Howard Greer",
    "sfomuseum:category": "Uniform",
    "sfomuseum:collection": "Aviation Museum",
    "sfomuseum:creditline": "Gift of TWA Clipped Wings International",
    "sfomuseum:date": "1944",
    "sfomuseum:date_acquired": "2004-12-08",
    "sfomuseum:daterange_end": "1944-12-31",
    "sfomuseum:daterange_start": "1944-01-01",
    "sfomuseum:description": "Hostess blouse-slip issued by Transcontinental \u0026 Western Air (TWA) for \"Cutout\" uniform; navy blue knee-length with short sleeves and jewel neckline, zipper at back; red embroidered “TWA” on proper right breast with button flap; worn 1944-1955.",
    "sfomuseum:dimensions": "40 x 30 inches (101.6 x 76.2 cm)",
    "sfomuseum:exhibition_ids": [
      1075
    ],
    "sfomuseum:maker": "Briny Marlin Coat and Suit Company",
    "sfomuseum:medium": "rayon, metal, plastic",
    "sfomuseum:placetype": "object",
    "sfomuseum:publication": ": , 1944.",
    "sfomuseum:subcategory": "Blouse / Shirt",
    "wof:depicts": [
      1159285395,
      1159287531
    ],
    "wof:name": "hostess blouse-slip: Transcontinental \u0026 Western Air (TWA), \"Cutout\"",
    "wof:placetype": "custom",
    "wof:placetype_alt": [
      "object"
    ]
  },
  "geometry": {"coordinates":[-122.386155,37.616357],"type":"Point"}
}
