{
  "type": "Feature",
  "properties": {
    "date:cessation_lower": "1980-12-31",
    "date:cessation_upper": "1980-12-31",
    "date:inception_lower": "1970-01-01",
    "date:inception_upper": "1970-01-01",
    "iso:country": "XX",
    "millsfield:images": [
      1527843631,
      1527843633
    ],
    "sfomuseum:accession_number": "2001.080.228",
    "sfomuseum:airline": "BOAC (British Overseas Airways Corporation)",
    "sfomuseum:category": "Passenger Amenity",
    "sfomuseum:collection": "Aviation Archive",
    "sfomuseum:continent": "World Routes",
    "sfomuseum:creditline": "Gift of Thomas G. Dragges",
    "sfomuseum:date": "c. 1975",
    "sfomuseum:daterange_end": "1980-12-31",
    "sfomuseum:daterange_start": "1970-01-01",
    "sfomuseum:description": "Menu issued by BOAC (British Overseas Airways Corporation), South Pacific (New York - Sydney) route; white cover with color photographic image of a flower (poinsettia) on a woven background; dinner and breakfast menu items include steak, duckling, and omelet; menu number: 531 Y/2 768; undated.",
    "sfomuseum:media_ids": [
      1527843631,
      1527843633
    ],
    "sfomuseum:medium": "paper, ink",
    "sfomuseum:placetype": "object",
    "sfomuseum:subcategory": "Menu",
    "wof:depicts": [
      1159283999
    ],
    "wof:name": "menu: BOAC (British Overseas Airways Corporation)",
    "wof:placetype": "venue"
  },
  "geometry": {"coordinates":[-122.386155,37.616357],"type":"Point"}
}
