{
  "type": "Feature",
  "properties": {
    "date:cessation_lower": "1975-01-01",
    "date:cessation_upper": "1975-12-31",
    "date:inception_lower": "1975-01-01",
    "date:inception_upper": "1975-12-31",
    "iso:country": "XX",
    "millsfield:images": [
      1527843631,
      1527843633
    ],
    "millsfield:images_texts": [
      "\u003e BOAC\nSouth Pacific Route Menu",
      "\u003e BOAC\nNew York\n5 hrs 50 mins.\nDinner\nSan Francisco\n4 hrs. bo mins\nSupper\nHonolulu\n6 hrs. 15 mins\nRefreshments\nContinental breakfast\nNandi-\n4 hrs. 15 mins.\nBreakfast\nSydney\nFor alconolic drinks and cigarettes\nplease refer to the Bar Tariff\nDinner\nSupper\nRefreshments\nBreakfast\nsmoked salmon nors d oeuvre\nGrilled fillet steak nicoise\nButtered sliced beans\nFruit tartlet\nCheese and biscuits\nCoffee\nHors d'oeuvre Pacific\nCold duckling Montmorency\nvirolnia nam\nCalifornian fresh fruits\nCheese and biscuits\nCoffee\nOpen style sandwiches\nCheese and biscuits\nTea. Coffee\nFruit appetizer\nTomato and bacon omelet\nGrilled lamb cutlets\nRolls. Croissants. Butter.\nPreserves\nTea • Coffee\n331 T2 768"
    ],
    "millsfield:images_texts_ids": [
      1527843631,
      1527843633
    ],
    "millsfield:primary_image": 1527843631,
    "sfomuseum:accession_number": "2001.080.228",
    "sfomuseum:airline": "British Overseas Airways Corporation (BOAC)",
    "sfomuseum:category": "Passenger Amenity, Archive",
    "sfomuseum:collection": "Aviation Archive",
    "sfomuseum:continent": "World Routes",
    "sfomuseum:creditline": "Gift of Thomas G. Dragges",
    "sfomuseum:date": "c. 1975",
    "sfomuseum:date_acquired": "2002-12-24",
    "sfomuseum:daterange_end": "1980-12-31",
    "sfomuseum:daterange_start": "1970-01-01",
    "sfomuseum:description": "Menu issued by British Overseas Airways Corporation (BOAC), South Pacific (New York - Sydney) route; white cover with color photographic image of a flower (poinsettia) on a woven background; dinner and breakfast menu items include steak, duckling, and omelet; menu number: 531 Y/2 768; undated.",
    "sfomuseum:dimensions": "10 x 8 1/2 inches (25.4 x 21.6 cm)",
    "sfomuseum:media_ids": [
      1527843631,
      1527843633
    ],
    "sfomuseum:medium": "paper, ink",
    "sfomuseum:placetype": "object",
    "sfomuseum:publication": ": , c. 1975.",
    "sfomuseum:subcategory": "Menu",
    "wof:depicts": [
      1159283999,
      1159286529
    ],
    "wof:name": "menu: British Overseas Airways Corporation (BOAC)",
    "wof:placetype": "custom",
    "wof:placetype_alt": "object"
  },
  "geometry": {"coordinates":[-122.386155,37.616357],"type":"Point"}
}
