{
  "type": "Feature",
  "properties": {
    "date:cessation_lower":"1991-12-31",
    "date:cessation_upper":"1991-12-31",
    "date:inception_lower":"1991-01-01",
    "date:inception_upper":"1991-01-01",
    "iso:country":"XX",
    "sfomuseum:accession_number":"2011.061.0411",
    "sfomuseum:category":"Scheduling / Ticketing",
    "sfomuseum:collection":"Aviation Archive",
    "sfomuseum:creditline":"Gift of the Frank J. Lichtanski Collection",
    "sfomuseum:date":"1991",
    "sfomuseum:daterange_end":"1991-12-31",
    "sfomuseum:daterange_start":"1991-01-01",
    "sfomuseum:description":"Promotional flyer issued by Malaysia Airlines with timetable on verso, effective through October 26, 1991; blue background with white text, \u201cAnnouncing 6th Flight to Malaysia from Los Angeles.\u201d",
    "sfomuseum:medium":"paper, ink",
    "sfomuseum:placetype":"object",
    "sfomuseum:subcategory":"Timetable",
    "wof:name":"timetable: Malaysia Airlines",
    "wof:placetype":"venue"
},
  "geometry": {"coordinates":[-122.386155,37.616358],"type":"Point"}
}