{
  "type": "Feature",
  "properties": {
    "date:cessation_lower": "1991-01-01",
    "date:cessation_upper": "1991-12-31",
    "date:inception_lower": "1991-01-01",
    "date:inception_upper": "1991-12-31",
    "iso:country": "XX",
    "millsfield:images": [
      1527851353,
      1527851355
    ],
    "millsfield:images_texts": [
      "VALID UNTIL 26 OCTOBER 1991\nLOS ANGELES INTO KUALA LUMPUR\n93\n747\n95a\n744\n93\n74M\n4,6\n1530\n2345\n1345\n95\n74E\n5,7\n2345\nD\n1845*\n2000\n0155+\n0200*\n0330\n0730\n0900\n1310\n1700*\n1815\n0010+\n0200*\n0330\n0730+\n0900\n1310\nD\nAll Times Local.\na: Effective 17 July 1991.\n*Next Day.\nThird Day.\nFLIGHT NO. MH\nTYPE OF AIRCRAFT\nDAYS OF OPERATION\nLOS ANGELES\nHONOLULU\nTOKYO\nTAIPEI\nKUALA LUMPUR\n92\n747\n1\n1205\n94a\n744\n2130\n1335\n1220\n92\n74M\n4,6\n1205\n94\n74E\n5,7\n2130\n1335\n1220\n1815\n1700\n1815\n1700\nD\n0930\n2100\n1930\n1515\n2100\n1930\n0930\n1515\nAccurate at time of printing.\nBRISBANE\nMalaysia Airlines International Route Network\nE malaysia\nFor reserations and more no mato, art yes Vines, Tol. re: 1800-421 8641.\n2011.06/0411",
      "ANNO\nCING\n6TH FLIGHT\n1° MALAYSIA\n..........\nmalaysia\nFROM LOS ANGELES\nmalaysia\nmessage"
    ],
    "millsfield:images_texts_ids": [
      1527851353,
      1527851355
    ],
    "millsfield:primary_image": 1527851355,
    "sfomuseum:accession_number": "2011.061.0411",
    "sfomuseum:airline": "Malaysia Airlines",
    "sfomuseum:category": "Scheduling / Ticketing",
    "sfomuseum:collection": "Aviation Archive",
    "sfomuseum:creditline": "Gift of the Frank J. Lichtanski Collection",
    "sfomuseum:date": "1991",
    "sfomuseum:date_acquired": "2011-08-02",
    "sfomuseum:daterange_end": "1991-12-31",
    "sfomuseum:daterange_start": "1991-01-01",
    "sfomuseum:description": "Promotional flyer issued by Malaysia Airlines with timetable on verso, effective through October 26, 1991; blue background with text, “Announcing 6th Flight to Malaysia from Los Angeles.”",
    "sfomuseum:dimensions": "10 3/4 x 8 inches (27.3 x 20.3 cm)",
    "sfomuseum:media_ids": [
      1527851353,
      1527851355
    ],
    "sfomuseum:medium": "paper, ink",
    "sfomuseum:placetype": "object",
    "sfomuseum:publication": ": , 1991.",
    "sfomuseum:subcategory": "Timetable",
    "wof:depicts": [
      1159284731,
      1159288691
    ],
    "wof:name": "timetable: Malaysia Airlines",
    "wof:placetype": "custom",
    "wof:placetype_alt": [
      "object"
    ]
  },
  "geometry": {"coordinates":[-122.386155,37.616357],"type":"Point"}
}
