{
  "type": "Feature",
  "properties": {
    "date:cessation_lower": "1991-01-01",
    "date:cessation_upper": "1991-12-31",
    "date:inception_lower": "1991-01-01",
    "date:inception_upper": "1991-12-31",
    "iso:country": "XX",
    "millsfield:images": [
      1527851353,
      1527851355
    ],
    "millsfield:primary_image": 1527851355,
    "sfomuseum:accession_number": "2011.061.0411",
    "sfomuseum:airline": "Malaysia Airlines",
    "sfomuseum:category": "Scheduling / Ticketing",
    "sfomuseum:collection": "Aviation Archive",
    "sfomuseum:creditline": "Gift of the Frank J. Lichtanski Collection",
    "sfomuseum:date": "1991",
    "sfomuseum:date_acquired": "2011-08-02",
    "sfomuseum:daterange_end": "1991-12-31",
    "sfomuseum:daterange_start": "1991-01-01",
    "sfomuseum:description": "Promotional flyer issued by Malaysia Airlines with timetable on verso, effective through October 26, 1991; blue background with text, “Announcing 6th Flight to Malaysia from Los Angeles.”",
    "sfomuseum:dimensions": "10 3/4 x 8 inches (27.3 x 20.3 cm)",
    "sfomuseum:media_ids": [
      1527851353,
      1527851355
    ],
    "sfomuseum:medium": "paper, ink",
    "sfomuseum:placetype": "object",
    "sfomuseum:publication": ": , 1991.",
    "sfomuseum:subcategory": "Timetable",
    "wof:depicts": [
      1159284731
    ],
    "wof:name": "timetable: Malaysia Airlines",
    "wof:placetype": "venue"
  },
  "geometry": {"coordinates":[-122.386155,37.616357],"type":"Point"}
}
