{
  "type": "Feature",
  "properties": {
    "date:cessation_lower": "1996-01-01",
    "date:cessation_upper": "1996-12-31",
    "date:inception_lower": "1996-01-01",
    "date:inception_upper": "1996-12-31",
    "iso:country": "XX",
    "sfomuseum:accession_number": "2002.075.003",
    "sfomuseum:author": "Martin, Phillip",
    "sfomuseum:callnumber": "TL538 .M37 1996 c.1",
    "sfomuseum:category": "Book",
    "sfomuseum:collection": "Aviation Library",
    "sfomuseum:creditline": "Gift of Thomas G. Dragges",
    "sfomuseum:date": "1996",
    "sfomuseum:date_acquired": "2022-04-18",
    "sfomuseum:daterange_end": "1996-12-31",
    "sfomuseum:daterange_start": "1996-01-01",
    "sfomuseum:description": "xvi, 232, [6] p. : ill. (some col.) ; 28 cm.",
    "sfomuseum:description_library": "xvi, 232, [6] p. : ill. (some col.) ; 28 cm.",
    "sfomuseum:medium": "paper, ink",
    "sfomuseum:placetype": "object",
    "sfomuseum:publication": "Long Beach, CA: Beach Cities Pub. Co., 1996.",
    "sfomuseum:publisher": "Beach Cities Pub. Co.",
    "sfomuseum:publisher_location": "Long Beach, CA",
    "sfomuseum:subcategory": "Book",
    "sfomuseum:subject": "Wings (Insignia) -- Collectors and collecting -- United States -- Catalogs",
    "wof:name": "Pilot’s wings of the United States: civilian and commercial, 1913-1995",
    "wof:placetype": "custom",
    "wof:placetype_alt": "object"
  },
  "geometry": {"coordinates":[-122.386155,37.616357],"type":"Point"}
}
