{
  "type": "Feature",
  "properties": {
    "date:cessation_lower": "2005-01-01",
    "date:cessation_upper": "2005-12-31",
    "date:inception_lower": "2005-01-01",
    "date:inception_upper": "2005-12-31",
    "iso:country": "XX",
    "sfomuseum:accession_number": "2007.056.046",
    "sfomuseum:author": "Norris, Guy",
    "sfomuseum:callnumber": "TL686.B65 B57 2005",
    "sfomuseum:category": "Book",
    "sfomuseum:collection": "Aviation Library",
    "sfomuseum:creditline": "Purchase",
    "sfomuseum:date": "2005",
    "sfomuseum:date_acquired": "2007-07-17",
    "sfomuseum:daterange_end": "2005-12-31",
    "sfomuseum:daterange_start": "2005-01-01",
    "sfomuseum:description": "152 p. : col. ill. ; 30 cm.",
    "sfomuseum:description_library": "152 p. : col. ill. ; 30 cm.",
    "sfomuseum:medium": "paper, ink",
    "sfomuseum:placetype": "object",
    "sfomuseum:publication": "Perth, Australia: Aerospace Technical Publications International, 2005.",
    "sfomuseum:publisher": "Aerospace Technical Publications International",
    "sfomuseum:publisher_location": "Perth, Australia",
    "sfomuseum:subcategory": "Book",
    "sfomuseum:subject": "Boeing 787 (Jet transport)",
    "wof:depicts": [
      1159292849,
      1159293593,
      1159289995
    ],
    "wof:name": "Boeing 787 Dreamliner: flying redefined",
    "wof:placetype": "venue"
  },
  "geometry": {"coordinates":[-122.386155,37.616357],"type":"Point"}
}
