{
  "type": "Feature",
  "properties": {
    "date:cessation_lower": "1951-12-31",
    "date:cessation_upper": "1951-12-31",
    "date:inception_lower": "1951-01-01",
    "date:inception_upper": "1951-01-01",
    "iso:country": "XX",
    "millsfield:images": [
      1527821903
    ],
    "sfomuseum:accession_number": "2011.032.0268",
    "sfomuseum:airport": "San Francisco Airport",
    "sfomuseum:category": "Photograph",
    "sfomuseum:collection": "Aviation Archive",
    "sfomuseum:creditline": "Transfer",
    "sfomuseum:date": "1951",
    "sfomuseum:daterange_end": "1951-12-31",
    "sfomuseum:daterange_start": "1951-01-01",
    "sfomuseum:description": "From attached handwritten note: “03400 / 1-11-51 / Storm damage view of tire marks of private plane blown off apron”. Black and white photograph of wetland waterway through field, with standing water; grass on both sides; more water in the distance, tire marks visible; damage from storm at San Francisco Airport; photo taken on January 11, 1951.",
    "sfomuseum:media_ids": [
      1527821903
    ],
    "sfomuseum:medium": "negative",
    "sfomuseum:placetype": "object",
    "sfomuseum:subcategory": "Negative",
    "wof:depicts": [
      102527513,
      1360695655
    ],
    "wof:name": "negative: San Francisco Airport, storm damage, 1951",
    "wof:placetype": "venue"
  },
  "geometry": {"coordinates":[-122.386155,37.616357],"type":"Point"}
}
