{
  "type": "Feature",
  "properties": {
    "date:cessation_lower":"1952-12-31",
    "date:cessation_upper":"1952-12-31",
    "date:inception_lower":"1952-01-01",
    "date:inception_upper":"1952-01-01",
    "iso:country":"XX",
    "millsfield:images":[
        1527821939
    ],
    "sfomuseum:accession_number":"2011.032.0284",
    "sfomuseum:category":"Photograph",
    "sfomuseum:collection":"Aviation Archive",
    "sfomuseum:creditline":"Transfer",
    "sfomuseum:date":"1952",
    "sfomuseum:daterange_end":"1952-12-31",
    "sfomuseum:daterange_start":"1952-01-01",
    "sfomuseum:description":"Black and white photograph of event around 25th anniversary celebration for San Francisco Airport; candy sales counter at Golden State Theatre; text in cursive neon: \u201cCandy\u201d; text on sign affixed to front of machine \u201cThe San Francisco Chamber of Commerce Salutes\u201d; text on white sign inside machine: San Francisco Airport is 25 Years Old\u201d; model of dual engine plane and four aerial photos of the airport, with captions, in back of machine; candy in bottom, including  Robin Hood\u201d brand; photograph taken on July 3, 1952.",
    "sfomuseum:media_ids":[
        1527821939
    ],
    "sfomuseum:medium":"negative",
    "sfomuseum:placetype":"object",
    "sfomuseum:subcategory":"Negative",
    "wof:name":"negative: San Francisco Airport, 25th anniversary celebration",
    "wof:placetype":"venue"
},
  "geometry": {"coordinates":[-122.386155,37.616358],"type":"Point"}
}