{
  "type": "Feature",
  "properties": {
    "date:cessation_lower": "1963-01-01",
    "date:cessation_upper": "1963-12-31",
    "date:inception_lower": "1962-01-01",
    "date:inception_upper": "1962-12-31",
    "iso:country": "XX",
    "sfomuseum:accession_number": "2000.168.243",
    "sfomuseum:author": "Laidlaw-Dickson, D. J.; and Rushbrooke, C. S",
    "sfomuseum:callnumber": "TL770.A1 A37 1962-63",
    "sfomuseum:category": "Book",
    "sfomuseum:collection": "Aviation Library",
    "sfomuseum:creditline": "Purchase",
    "sfomuseum:date": "1962-1963",
    "sfomuseum:daterange_end": "1963-12-31",
    "sfomuseum:daterange_start": "1962-01-01",
    "sfomuseum:description": "v. : ill. ; 22 cm.",
    "sfomuseum:medium": "paper, ink",
    "sfomuseum:placetype": "object",
    "sfomuseum:publisher": "Model Aeronautical Press",
    "sfomuseum:publisher_location": "Watford, Hertfordshire, England",
    "sfomuseum:subcategory": "Book",
    "sfomuseum:subject": "Airplanes Models Periodicals.",
    "wof:name": "Aeromodeller annual",
    "wof:placetype": "venue"
  },
  "geometry": {"coordinates":[-122.386155,37.616357],"type":"Point"}
}
