{
  "type": "Feature",
  "properties": {
    "date:cessation_lower": "1998-01-01",
    "date:cessation_upper": "1998-12-31",
    "date:inception_lower": "1998-01-01",
    "date:inception_upper": "1998-12-31",
    "isbn:number": "1550171852 9781550171853 ",
    "iso:country": "XX",
    "sfomuseum:accession_number": "2001.106.461",
    "sfomuseum:airline": "Canadian Airlines International",
    "sfomuseum:author": "Pigott, Peter",
    "sfomuseum:callnumber": "HE9815.A3 P544 1998",
    "sfomuseum:category": "Book",
    "sfomuseum:collection": "Aviation Library",
    "sfomuseum:creditline": "Gift of Mark F. Adams Collection",
    "sfomuseum:date": "c. 1998",
    "sfomuseum:date_acquired": "2001-10-18",
    "sfomuseum:daterange_end": "2003-12-31",
    "sfomuseum:daterange_start": "1993-01-01",
    "sfomuseum:description": "391 p. : ill. ; 24 cm.",
    "sfomuseum:description_library": "391 p. : ill. ; 24 cm.",
    "sfomuseum:medium": "paper, ink",
    "sfomuseum:placetype": "object",
    "sfomuseum:publication": "Madeira Park, British Columbia, Canada: Harbour, c. 1998.",
    "sfomuseum:publisher": "Harbour",
    "sfomuseum:publisher_location": "Madeira Park, British Columbia, Canada",
    "sfomuseum:subcategory": "Book",
    "sfomuseum:subject": "Canadian Airlines International -- History.\rCanadian Airlines International -- Biography.\rLignes aériennes Canadian international -- Histoire.\rLignes aériennes Canadian international -- Biographies.\r",
    "wof:depicts": [
      1159284085,
      1159288139
    ],
    "wof:name": "Wingwalkers: a history of Canadian Airlines International",
    "wof:placetype": "custom",
    "wof:placetype_alt": [
      "object"
    ]
  },
  "geometry": {"coordinates":[-122.386155,37.616357],"type":"Point"}
}
