{
  "type": "Feature",
  "properties": {
    "date:cessation_lower": "1974-12-31",
    "date:cessation_upper": "1974-12-31",
    "date:inception_lower": "1974-01-01",
    "date:inception_upper": "1974-01-01",
    "iso:country": "XX",
    "sfomuseum:accession_number": "2011.195.109",
    "sfomuseum:category": "Scheduling / Ticketing",
    "sfomuseum:collection": "Aviation Archive",
    "sfomuseum:creditline": "Gift of David Winckoski",
    "sfomuseum:date": "1974",
    "sfomuseum:daterange_end": "1974-12-31",
    "sfomuseum:daterange_start": "1974-01-01",
    "sfomuseum:description": "Quick reference schedule / timetable for service to and from Dallas / Ft. Worth issued by Delta Air Lines, effective February 1, 1974; blue, red, and white cover; contains flight schedule for domestic routes.",
    "sfomuseum:media_ids": [
      1527836161
    ],
    "sfomuseum:medium": "paper, ink",
    "sfomuseum:placetype": "object",
    "sfomuseum:subcategory": "Timetable",
    "wof:name": "timetable: Delta Air Lines, quick reference, Dallas / Ft. Worth",
    "wof:placetype": "venue"
  },
  "geometry": {"coordinates":[-122.386155,37.616358],"type":"Point"}
}
