{
  "type": "Feature",
  "properties": {
    "date:cessation_lower": "1989-01-01",
    "date:cessation_upper": "1989-12-31",
    "date:inception_lower": "1989-01-01",
    "date:inception_upper": "1989-12-31",
    "iso:country": "XX",
    "sfomuseum:accession_number": "2000.160.0941",
    "sfomuseum:author": "Penrose, Harald",
    "sfomuseum:callnumber": "TL540.S77 P46 1989 c.1",
    "sfomuseum:category": "Book",
    "sfomuseum:collection": "Aviation Library",
    "sfomuseum:creditline": "The Tony Bill Aviation Library Collection",
    "sfomuseum:date": "1989",
    "sfomuseum:daterange_end": "1989-12-31",
    "sfomuseum:daterange_start": "1989-01-01",
    "sfomuseum:description": "183 p. : ill., ports. ; 23 cm.",
    "sfomuseum:medium": "paper, ink",
    "sfomuseum:placetype": "object",
    "sfomuseum:publication": "Washington, D.C.: Smithsonian Institution Press, 1989.",
    "sfomuseum:publisher": "Smithsonian Institution Press",
    "sfomuseum:publisher_location": "Washington, D.C.",
    "sfomuseum:subcategory": "Book",
    "sfomuseum:subject": "Stringfellow, John, 1799-1883.Aeronautics History 19th century.Aeronautical engineers Great Britain Biography.",
    "wof:name": "An ancient air: a biography of John Stringfellow of Chard, the Victorian aeronautical pioneer",
    "wof:placetype": "venue"
  },
  "geometry": {"coordinates":[-122.386155,37.616357],"type":"Point"}
}
