{
  "type": "Feature",
  "properties": {
    "date:cessation_lower":"1958-12-31",
    "date:cessation_upper":"1958-12-31",
    "date:inception_lower":"1948-01-01",
    "date:inception_upper":"1948-01-01",
    "iso:country":"US",
    "sfomuseum:accession_number":"2001.109.003",
    "sfomuseum:aircraft":"Lockheed L-1049 Super Constellation",
    "sfomuseum:airline":"TWA (Trans World Airlines)",
    "sfomuseum:category":"Promotional",
    "sfomuseum:collection":"Aviation Archive",
    "sfomuseum:continent":"North America",
    "sfomuseum:country":"United States",
    "sfomuseum:creditline":"Gift of Thomas G. Dragges in memory of Robert May",
    "sfomuseum:date":"c. 1953",
    "sfomuseum:daterange_end":"1958-12-31",
    "sfomuseum:daterange_start":"1948-01-01",
    "sfomuseum:description":"Luggage label promoting TWA (Trans World Airlines) Lockheed L-1049 Super Constellation service; blue and white label, parallelogram shape with image of in-flight Lockheed Constellation, wing tip extending beyond top edge; text, \"Fly TWA Super Constellations.\"",
    "sfomuseum:medium":"paper, ink, adhesive",
    "sfomuseum:placetype":"object",
    "sfomuseum:subcategory":"Luggage Label",
    "wof:depicts":[
        1159285393,
        1159291139
    ],
    "wof:name":"luggage label: TWA (Trans World Airlines), Lockheed L-1049 Super Constellation",
    "wof:placetype":"venue"
},
  "geometry": {"coordinates":[-122.386155,37.616357],"type":"Point"}
}