{
  "type": "Feature",
  "properties": {
    "date:cessation_lower": "1957-01-01",
    "date:cessation_upper": "1957-12-31",
    "date:inception_lower": "1957-01-01",
    "date:inception_upper": "1957-12-31",
    "iso:country": "XX",
    "millsfield:images": [
      1763388413
    ],
    "millsfield:images_texts": [
      "Panagna\nPANAGRA\nla Ruta\nINTERAMERICANO\nGo Now!\n* SouttA\nsmerica\nThis year,\nsmart people are\nSOAN *\nspending their\n-PORT OF SPAIN\nvacations in\nSouth America\n*LA PAL\nEl InterAmericano — only daily DC-6 to Panama, 4½ hours;\nGuayaquil, 8½ hours; Lima, 11 hours; Santiago, 17 hours;\nBuenos Aires, 18½ hours from Miami.\n• Did you know the shortest way to Buenos Aires is to fly\nstraight down South America's West Coast? This way saves\nyou so miles trom New rork. And it adds the orvilege ol\nstopping over in thriving Guayaquil, in old Spanish Lima,\nand ultra-modern Santiago. One-way fare is $510 from Miami\nMoreover, you travel in the highest style. Panagra's Red\nCarpet service includes Gourmet Galley meals with cocktails\nand wines; the exclusive Fiesta Lounge; bed-sized berths,\nif you like, for moderate extra cost.\nattention in the air and on the ground by Panagra and Pan\nAmerican, two airlines with 22 years' leadership in South\nAmerica. Call your Travel Agent or the nearest Pan American\nWorld Airways office, U.S. Sales agents for\nPAN AMERICAN\nGRACE AIRWAYS\nHOLIDAY/APRIL"
    ],
    "millsfield:images_texts_ids": [
      1763388413
    ],
    "millsfield:primary_image": 1763388413,
    "sfomuseum:accession_number": "2001.038.164.090",
    "sfomuseum:airline": "Panagra (Pan American-Grace Airways)",
    "sfomuseum:category": "Promotional, Archive",
    "sfomuseum:collection": "Aviation Archive",
    "sfomuseum:creditline": "Gift of Barnaby Conrad III",
    "sfomuseum:date": "1957",
    "sfomuseum:date_acquired": "2003-05-16",
    "sfomuseum:daterange_end": "1957-12-31",
    "sfomuseum:daterange_start": "1957-01-01",
    "sfomuseum:description": "Advertisement from April 1957 issue of Holiday promoting Panagra (Pan American - Grace Airways), titled “Fastest / Go now! to South America” with color illustration depicting woman and man disembarking airplane.",
    "sfomuseum:dimensions": "14 x 10 1/2 inches (35.6 x 26.7 cm)",
    "sfomuseum:medium": "paper, ink",
    "sfomuseum:placetype": "object",
    "sfomuseum:publication": ": , 1957.",
    "sfomuseum:subcategory": "Advertisement, 2D",
    "sfomuseum:subject": "Pan Am promotional advertisement",
    "wof:depicts": [
      1159288567,
      1159284993
    ],
    "wof:name": "advertisement: Panagra (Pan American-Grace Airways), Holiday",
    "wof:placetype": "custom",
    "wof:placetype_alt": "object"
  },
  "geometry": {"coordinates":[-122.386155,37.616357],"type":"Point"}
}
