{
  "type": "Feature",
  "properties": {
    "date:cessation_lower": "1970-12-31",
    "date:cessation_upper": "1970-12-31",
    "date:inception_lower": "1970-01-01",
    "date:inception_upper": "1970-01-01",
    "iso:country": "XX",
    "sfomuseum:accession_number": "2011.032.2406",
    "sfomuseum:artist": "Marshall Moxom",
    "sfomuseum:category": "Photograph",
    "sfomuseum:collection": "Aviation Archive",
    "sfomuseum:creditline": "Transfer",
    "sfomuseum:date": "1970",
    "sfomuseum:daterange_end": "1970-12-31",
    "sfomuseum:daterange_start": "1970-01-01",
    "sfomuseum:description": "From attached handwritten note: “03322 / 6-30-70 / Main entrance road underpass / taken by: Moxom”. Black and white photographic negative depicting north-facing view of McDonnell Road underpass at San Francisco International Airport (SFO); evening lighting conditions; photo taken by Marshall Moxom on June 30, 1970.",
    "sfomuseum:media_ids": [
      1527827737
    ],
    "sfomuseum:medium": "negative",
    "sfomuseum:placetype": "object",
    "sfomuseum:subcategory": "Negative",
    "wof:name": "negative: San Francisco International Airport (SFO), McDonnell Road",
    "wof:placetype": "venue"
  },
  "geometry": {"coordinates":[-122.386155,37.616358],"type":"Point"}
}
