{
  "type": "Feature",
  "properties": {
    "date:cessation_lower": "1945-01-01",
    "date:cessation_upper": "1945-12-31",
    "date:inception_lower": "1941-01-01",
    "date:inception_upper": "1941-12-31",
    "iso:country": "XX",
    "sfomuseum:accession_number": "2003.042.005",
    "sfomuseum:author": "United States Army. Enlisted Student and Service Regt. The Engineer School",
    "sfomuseum:callnumber": "D790 .K55 1943 SC ENV",
    "sfomuseum:category": "Book",
    "sfomuseum:collection": "Aviation Library",
    "sfomuseum:creditline": "Gift of Geroge M. Geralis",
    "sfomuseum:date": "1941-1945",
    "sfomuseum:daterange_end": "1945-12-31",
    "sfomuseum:daterange_start": "1941-01-01",
    "sfomuseum:description": "1 folded page, 8 in x 5 in. Undated but known to be from 1941-1945.",
    "sfomuseum:medium": "paper, ink",
    "sfomuseum:placetype": "object",
    "sfomuseum:publication": "Washington, D.C.: War Dept., 1941-1945.",
    "sfomuseum:publisher": "War Dept.",
    "sfomuseum:publisher_location": "Washington, D.C.",
    "sfomuseum:subcategory": "Book",
    "sfomuseum:subject": "World War, 1939-1945. United States Army -- Operations and training.",
    "wof:name": "Know Your Guard Duty",
    "wof:placetype": "custom"
  },
  "geometry": {"coordinates":[-122.386155,37.616357],"type":"Point"}
}
