{
  "type": "Feature",
  "properties": {
    "date:cessation_lower": "1978-01-01",
    "date:cessation_upper": "1978-12-31",
    "date:inception_lower": "1978-01-01",
    "date:inception_upper": "1978-12-31",
    "iso:country": "XX",
    "sfomuseum:accession_number": "2013.073.009",
    "sfomuseum:author": "Reinhardt, Richard",
    "sfomuseum:callnumber": "T876 1939.B1 R44 1978",
    "sfomuseum:category": "Book",
    "sfomuseum:collection": "Aviation Library",
    "sfomuseum:creditline": "Purchase",
    "sfomuseum:date": "1978",
    "sfomuseum:daterange_end": "1978-12-31",
    "sfomuseum:daterange_start": "1978-01-01",
    "sfomuseum:description": "169, [6] p. : ill., ports. ; 26 cm.",
    "sfomuseum:edition": "1st Squarebooks ed.",
    "sfomuseum:medium": "paper, ink",
    "sfomuseum:placetype": "object",
    "sfomuseum:publication": "Mill Valley, CA: Squarebooks, 1978.",
    "sfomuseum:publisher": "Squarebooks",
    "sfomuseum:publisher_location": "Mill Valley, CA",
    "sfomuseum:subcategory": "Book",
    "sfomuseum:subject": "San Francisco (Calif.) (1939-1940)",
    "wof:name": "Treasure Island: San Francisco's exposition years 1st Squarebooks ed.",
    "wof:placetype": "venue"
  },
  "geometry": {"coordinates":[-122.386155,37.616357],"type":"Point"}
}
