{
  "type": "Feature",
  "properties": {
    "date:cessation_lower": "1973-01-01",
    "date:cessation_upper": "1973-12-31",
    "date:inception_lower": "1973-01-01",
    "date:inception_upper": "1973-12-31",
    "iso:country": "XX",
    "loc:subject_headings": [
      "sh85015466"
    ],
    "sfomuseum:accession_number": "2000.172.019",
    "sfomuseum:author": "Gunston, Bill",
    "sfomuseum:callnumber": "TL685.3 .G84 1973",
    "sfomuseum:category": "Book",
    "sfomuseum:collection": "Aviation Library",
    "sfomuseum:creditline": "Purchase",
    "sfomuseum:date": "1973",
    "sfomuseum:date_acquired": "1999-12-08",
    "sfomuseum:daterange_end": "1973-12-31",
    "sfomuseum:daterange_start": "1973-01-01",
    "sfomuseum:description": "283, [12] p. col. illus. 24 cm.",
    "sfomuseum:description_library": "283, [12] p. col. illus. 24 cm.",
    "sfomuseum:medium": "paper, ink",
    "sfomuseum:placetype": "object",
    "sfomuseum:publication": "London: Allan, 1973.",
    "sfomuseum:publisher": "Allan",
    "sfomuseum:publisher_location": "London",
    "sfomuseum:subcategory": "Book",
    "sfomuseum:subject": "Bombers.",
    "wof:name": "Bombers of the West",
    "wof:placetype": "venue"
  },
  "geometry": {"coordinates":[-122.386155,37.616357],"type":"Point"}
}
