{
  "type": "Feature",
  "properties": {
    "date:cessation_lower": "1947-06-29",
    "date:cessation_upper": "1947-06-29",
    "date:inception_lower": "1947-06-29",
    "date:inception_upper": "1947-06-29",
    "iso:country": "XX",
    "millsfield:images": [
      1527854227
    ],
    "millsfield:primary_image": 1527854227,
    "sfomuseum:accession_number": "1994.18.062 b",
    "sfomuseum:airline": "Pan American World Airways",
    "sfomuseum:category": "Philately",
    "sfomuseum:collection": "Aviation Archive",
    "sfomuseum:continent": "Transpacific",
    "sfomuseum:creditline": "Purchase",
    "sfomuseum:date": "6/29/1947",
    "sfomuseum:date_acquired": "1994-06-29",
    "sfomuseum:daterange_end": "1947-06-29",
    "sfomuseum:daterange_start": "1947-06-29",
    "sfomuseum:description": "b. Airmail flight cover insert with text \"Aviation Safety Award Conferred by Inter-American Safety Council, Inc. for the year 1946 to Pan American World Airways For flying over its 48,440-mile network a total of 43,878,591 flying miles, totaling 760,238,654 passenger miles without an accident or fatality to passengers or crews.\"",
    "sfomuseum:dimensions": "3 1/2 x 6 1/2 inches (8.9 x 16.5 cm)",
    "sfomuseum:maker": "Pan American Airways, Inc.",
    "sfomuseum:media_ids": [
      1527854227
    ],
    "sfomuseum:medium": "paper, ink",
    "sfomuseum:placetype": "object",
    "sfomuseum:publication": ": , 6/29/1947.",
    "sfomuseum:subcategory": "Airmail Flight Cover",
    "wof:depicts": [
      1159284989,
      1159286839
    ],
    "wof:name": "airmail flight cover insert: Pan American World Airways, Guam - Bangkok route",
    "wof:placetype": "custom",
    "wof:placetype_alt": "object"
  },
  "geometry": {"coordinates":[-122.386155,37.616357],"type":"Point"}
}
