{
  "type": "Feature",
  "properties": {
    "date:cessation_lower": "1937-01-01",
    "date:cessation_upper": "1937-12-31",
    "date:inception_lower": "1937-01-01",
    "date:inception_upper": "1937-12-31",
    "iso:country": "XX",
    "millsfield:images": [
      1527821063
    ],
    "millsfield:primary_image": 1527821063,
    "sfomuseum:accession_number": "2008.056.1138",
    "sfomuseum:aircraft": "Martin M-130 China Clipper",
    "sfomuseum:airline": "Pan American Airways",
    "sfomuseum:category": "Photograph",
    "sfomuseum:collection": "Aviation Archive",
    "sfomuseum:creditline": "Gift of Jon E. Krupnick",
    "sfomuseum:date": "1937",
    "sfomuseum:daterange_end": "1937-12-31",
    "sfomuseum:daterange_start": "1937-01-01",
    "sfomuseum:description": "Black and white photograph depicting Pan American Airways System Martin M-130 China Clipper in flight (side view as seen from slightly below); blank background. Paper taped to verso identifies photo as the China Clipper on route from San Francisco to Manila, where \"cargo was transferred to Pan-American Airways Clipper that flew the remainder of the way to Hong-Kong\" on May 19th, 1937. Writing in pencil indicates 4-engine Martin Clipper.",
    "sfomuseum:dimensions": "8 x 10 1/4 inches (20.3 x 26 cm)",
    "sfomuseum:issues_held": "\r",
    "sfomuseum:media_ids": [
      1527821063
    ],
    "sfomuseum:medium": "photograph",
    "sfomuseum:placetype": "object",
    "sfomuseum:publication": ": , 1937.",
    "sfomuseum:subcategory": "Print, Photograph",
    "sfomuseum:subject": "Airlines -- Commercial -- Pan American World Airways\r",
    "wof:depicts": [
      1159291191,
      1159291193,
      1159284991
    ],
    "wof:name": "photograph: Pan American Airways System, Martin M-130 “China Clipper”",
    "wof:placetype": "venue"
  },
  "geometry": {"coordinates":[-122.386155,37.616357],"type":"Point"}
}
