{
  "type": "Feature",
  "properties": {
    "date:cessation_lower": "1970-12-31",
    "date:cessation_upper": "1970-12-31",
    "date:inception_lower": "1968-01-01",
    "date:inception_upper": "1968-01-01",
    "iso:country": "XX",
    "millsfield:images": [
      1527828735
    ],
    "sfomuseum:accession_number": "2001.150.006.001-.002",
    "sfomuseum:airline": "Pan American World Airways",
    "sfomuseum:category": "Company Record / Document",
    "sfomuseum:collection": "Aviation Archive",
    "sfomuseum:creditline": "Gift of Helene Daugherty Hills",
    "sfomuseum:date": "1968-1970",
    "sfomuseum:daterange_end": "1970-12-31",
    "sfomuseum:daterange_start": "1968-01-01",
    "sfomuseum:description": "On cover: black and white illustration of barbecue tools and foods with text, “Barbecuing from cave to penthouse” in red circle.",
    "sfomuseum:media_ids": [
      1527828735
    ],
    "sfomuseum:medium": "paper, ink",
    "sfomuseum:placetype": "object",
    "sfomuseum:subcategory": "Company Newsletter",
    "wof:depicts": [
      1159284989
    ],
    "wof:name": "employee newsletter: United Air Lines, Wing tips: a monthly publication by flight service for flight service [2 issues: July 1968 and June 1970]",
    "wof:placetype": "venue"
  },
  "geometry": {"coordinates":[-122.386155,37.616357],"type":"Point"}
}
