{
  "type": "Feature",
  "properties": {
    "date:cessation_lower": "1970-01-01",
    "date:cessation_upper": "1970-12-31",
    "date:inception_lower": "1968-01-01",
    "date:inception_upper": "1968-12-31",
    "iso:country": "XX",
    "millsfield:images": [
      1527828735
    ],
    "millsfield:primary_image": 1527828735,
    "sfomuseum:accession_number": "2001.150.006.001-.002",
    "sfomuseum:airline": "Pan American World Airways",
    "sfomuseum:category": "Company Record / Document",
    "sfomuseum:collection": "Aviation Archive",
    "sfomuseum:creditline": "Gift of Helene Daugherty Hills",
    "sfomuseum:date": "1968-1970",
    "sfomuseum:date_acquired": "2004-12-08",
    "sfomuseum:daterange_end": "1970-12-31",
    "sfomuseum:daterange_start": "1968-01-01",
    "sfomuseum:description": "On cover: black and white illustration of barbecue tools and foods with text, “Barbecuing from cave to penthouse” in red circle.",
    "sfomuseum:dimensions": "11 x 8 inches (27.9 x 20.3 cm)",
    "sfomuseum:issue": "2 issues: July 1968 and June 1970",
    "sfomuseum:issues_held": "1968 (Jul)\r1970 (Jun)",
    "sfomuseum:media_ids": [
      1527828735
    ],
    "sfomuseum:medium": "paper, ink",
    "sfomuseum:placetype": "object",
    "sfomuseum:publication": "New York: Pan American World Airways, 1968-1970.",
    "sfomuseum:publisher": "Pan American World Airways",
    "sfomuseum:publisher_location": "New York",
    "sfomuseum:subcategory": "Company Newsletter",
    "sfomuseum:subject": "Pan American World Airways, Inc. -- Flight attendants -- Periodicals",
    "wof:depicts": [
      1159284989
    ],
    "wof:name": "employee newsletter: United Air Lines, Wing tips: a monthly publication by flight service for flight service [2 issues: July 1968 and June 1970]",
    "wof:placetype": "custom",
    "wof:placetype_alt": "object"
  },
  "geometry": {"coordinates":[-122.386155,37.616357],"type":"Point"}
}
