{
  "type": "Feature",
  "properties": {
    "date:cessation_lower": "1984-12-31",
    "date:cessation_upper": "1984-12-31",
    "date:inception_lower": "1984-01-01",
    "date:inception_upper": "1984-01-01",
    "iso:country": "XX",
    "millsfield:images": [
      1527839521,
      1527839519,
      1527839517
    ],
    "sfomuseum:accession_number": "2001.136.073.002 a b",
    "sfomuseum:airline": "United Airlines",
    "sfomuseum:category": "Scheduling / Ticketing",
    "sfomuseum:collection": "Aviation Archive",
    "sfomuseum:creditline": "Gift of Howard Knapp",
    "sfomuseum:date": "1984",
    "sfomuseum:daterange_end": "1984-12-31",
    "sfomuseum:daterange_start": "1984-01-01",
    "sfomuseum:description": "a. City timetable issued by United Airlines for service to and from San Francisco / Oakland / San Jose, effective April 28, 1984; fourteen-page schedule; white cover with illustration of Boeing 747 in flight in center with text, “First to fly all 50 states”.\rb. Single, double-sided Macy’s advertisement promoting women’s wear.",
    "sfomuseum:dimensions": "9 x 4 inches (22.9 x 10.2 cm)",
    "sfomuseum:media_ids": [
      1527839517,
      1527839519,
      1527839521
    ],
    "sfomuseum:medium": "paper, ink",
    "sfomuseum:placetype": "object",
    "sfomuseum:subcategory": "Timetable",
    "wof:depicts": [
      1159293593,
      1159285413,
      85921881,
      85688637,
      85633793,
      1159289873
    ],
    "wof:name": "timetable: United Airlines, quick reference San Francisco / Oakland / San Jose",
    "wof:placetype": "venue"
  },
  "geometry": {"coordinates":[-122.386155,37.616357],"type":"Point"}
}
