{
  "type": "Feature",
  "properties": {
    "date:cessation_lower": "1926-06-07",
    "date:cessation_upper": "1926-06-07",
    "date:inception_lower": "1926-06-07",
    "date:inception_upper": "1926-06-07",
    "iso:country": "US",
    "millsfield:images": [
      1527820033,
      1527820035
    ],
    "millsfield:images_texts": [
      "CHICAGO\nILL.\n5:30 A. M.\nJUNE 7\nVIA AIR MAIL\nEDWARD C. WORDEN,\n% POSTMASTER,\nMILWAUKEE, WIS.: NO.C.A.M. 9\nONDUVEI\nTING\nJUNE\n926\nTWIN\nJUN T\n1926",
      "JUN 7\n830 AM\n1926\n2002.011.004"
    ],
    "millsfield:images_texts_ids": [
      1527820033,
      1527820035
    ],
    "millsfield:primary_image": 1527820033,
    "sfomuseum:accession_number": "2002.011.004",
    "sfomuseum:category": "Philately",
    "sfomuseum:collection": "Aviation Archive",
    "sfomuseum:continent": "North America",
    "sfomuseum:country": "United States",
    "sfomuseum:creditline": "Purchase",
    "sfomuseum:date": "06/07/1926",
    "sfomuseum:date_acquired": "2002-03-01",
    "sfomuseum:daterange_end": "1926-06-07",
    "sfomuseum:daterange_start": "1926-06-07",
    "sfomuseum:description": "Airmail flight cover, first flight inaugurating contract air mail from Chicago, Chicago - Twin Cities route; two round black cachets with commemorative cancellation mark; postmarked June 7, 1926 in Chicago with wavy cancellation mark over 10-cent stamp; backstamp: June 7, 1926, Milwaukee.",
    "sfomuseum:dimensions": "3 3/4 x 6 1/2 inches (9.5 x 16.5 cm)",
    "sfomuseum:media_ids": [
      1527820035,
      1527820033
    ],
    "sfomuseum:medium": "paper, ink",
    "sfomuseum:placetype": "object",
    "sfomuseum:publication": ": , 06/07/1926.",
    "sfomuseum:subcategory": "Airmail Flight Cover",
    "wof:name": "airmail flight cover: First airmail flight, CAM-9, Chicago - Milwaukee",
    "wof:placetype": "custom",
    "wof:placetype_alt": "object"
  },
  "geometry": {"coordinates":[-122.386155,37.616357],"type":"Point"}
}
