{
  "type": "Feature",
  "properties": {
    "date:cessation_lower":"1926-12-31",
    "date:cessation_upper":"1926-12-31",
    "date:inception_lower":"1926-01-01",
    "date:inception_upper":"1926-01-01",
    "iso:country":"US",
    "sfomuseum:accession_number":"2002.011.004",
    "sfomuseum:category":"Philately",
    "sfomuseum:collection":"Aviation Archive",
    "sfomuseum:continent":"North America",
    "sfomuseum:country":"United States",
    "sfomuseum:creditline":"Purchase",
    "sfomuseum:date":"06/07/1926",
    "sfomuseum:daterange_end":"1926-06-07",
    "sfomuseum:daterange_start":"1926-06-07",
    "sfomuseum:description":"Airmail flight cover, first flight inaugurating contract air mail from Chicago, Chicago - Twin Cities route; two round black cachets with commemorative cancellation mark; postmarked June 7, 1926 in Chicago with wavy cancellation mark over 10-cent stamp; backstamp: June 7, 1926, Milwaukee.",
    "sfomuseum:medium":"paper, ink",
    "sfomuseum:placetype":"object",
    "sfomuseum:subcategory":"Airmail Flight Cover",
    "wof:name":"airmail flight cover: First airmail flight, CAM-9, Chicago - Milwaukee",
    "wof:placetype":"venue"
},
  "geometry": {"coordinates":[-122.386155,37.616358],"type":"Point"}
}