{
  "type": "Feature",
  "properties": {
    "date:cessation_lower":"1984-12-31",
    "date:cessation_upper":"1984-12-31",
    "date:inception_lower":"1984-01-01",
    "date:inception_upper":"1984-01-01",
    "iso:country":"XX",
    "sfomuseum:accession_number":"2003.105.107.003",
    "sfomuseum:airline":"TWA (Trans World Airlines)",
    "sfomuseum:category":"Scheduling / Ticketing",
    "sfomuseum:collection":"Aviation Archive",
    "sfomuseum:creditline":"Gift of Craig Lynes",
    "sfomuseum:date":"1984",
    "sfomuseum:daterange_end":"1984-12-31",
    "sfomuseum:daterange_start":"1984-01-01",
    "sfomuseum:description":"Timetable issued by TWA (Trans World Airlines), effective July 1 through September 5, 1984; ninety-nine page schedule. The cover is white servicemark at the top in red and a pattern of TWA logos outlined in red below.",
    "sfomuseum:medium":"paper, ink",
    "sfomuseum:placetype":"object",
    "sfomuseum:subcategory":"Timetable",
    "wof:depicts":[
        1159285393
    ],
    "wof:name":"timetable: TWA (Trans World Airlines)",
    "wof:placetype":"venue"
},
  "geometry": {"coordinates":[-122.386155,37.616357],"type":"Point"}
}