{
  "type": "Feature",
  "properties": {
    "date:cessation_lower": "1967-01-01",
    "date:cessation_upper": "1967-12-31",
    "date:inception_lower": "1967-01-01",
    "date:inception_upper": "1967-12-31",
    "iso:country": "US",
    "millsfield:images": [
      1527838339,
      1527851067
    ],
    "millsfield:images_texts": [
      "SAN FRANCISCO\nOAKLAND\nUNITED\nEFFECTIVE JULY 9. 1967 THROUGH SEPTEMBER S.\nArrivals and departures for the State of Michigan ore EASTERN\nSTANDARD TIME (Uniform Advanced - 1 hour). Proposed legis\nTonionamorearcourosmichigon\nUniform Advanced limo IF so ADD ONE HOUR\nshown for all Michigon cities.\nShe\nfriendly skies\nUnited",
      "TRANSCONTINENTAL NONSTOP JET SERVICE\nUNITED EXPANDS\nBLUE CARPET SERVICE\nUnited's Blue Corpet is a funway to save money on your\nvacation\nCoach was never like this: Top sirloin steak, or chicken\nCordou Bleu, if you wish. Champagne or fine red wine.\nyours al nomina cost, color movies and stereo. too, auro-\nside check-in for your luggage. Fun'n games to keep the\nkids busy. And even a children's menu if they prefer hot\ndogs to steak.\nWe even have nine kinds of baby food\n(and diapers and baby food).\nAll this at the regular coach fare . . . United's Blue\nCarpet.\nBlue Carpet nonstop to Boston, Newark, New York,\nPhiladelphia and Washington-Baltimore.\nfly the friendly skies of United"
    ],
    "millsfield:images_texts_ids": [
      1527838339,
      1527851067
    ],
    "millsfield:primary_image": 1527838339,
    "sfomuseum:accession_number": "1999.015.172",
    "sfomuseum:airline": "United Air Lines",
    "sfomuseum:category": "Scheduling / Ticketing",
    "sfomuseum:collection": "Aviation Archive",
    "sfomuseum:continent": "North America",
    "sfomuseum:country": "United States",
    "sfomuseum:creditline": "Gift of Homer Hudson",
    "sfomuseum:date": "1967",
    "sfomuseum:date_acquired": "1999-07-06",
    "sfomuseum:daterange_end": "1967-12-31",
    "sfomuseum:daterange_start": "1967-01-01",
    "sfomuseum:description": "City timetable issued by United Air Lines for service to and from San Francisco and Oakland, effective July 9 through September 8, 1967; red, white, and blue cover with text “Fly the friendly skies of United”.",
    "sfomuseum:dimensions": "9 x 4 inches (22.9 x 10.2 cm)",
    "sfomuseum:media_ids": [
      1527838339,
      1527851067
    ],
    "sfomuseum:medium": "paper, ink",
    "sfomuseum:placetype": "object",
    "sfomuseum:publication": ": , 1967.",
    "sfomuseum:subcategory": "Timetable",
    "wof:depicts": [
      85921881,
      85688637,
      85633793,
      1159288779,
      1159285415
    ],
    "wof:name": "timetable: United Air Lines, San Francisco and Oakland",
    "wof:placetype": "custom",
    "wof:placetype_alt": "object"
  },
  "geometry": {"coordinates":[-122.386155,37.616357],"type":"Point"}
}
