{
  "type": "Feature",
  "properties": {
    "date:cessation_lower": "1969-09-02",
    "date:cessation_upper": "1969-09-02",
    "date:inception_lower": "1969-09-02",
    "date:inception_upper": "1969-09-02",
    "iso:country": "XX",
    "millsfield:images": [
      1527830157,
      1527830159
    ],
    "millsfield:images_texts": [
      "PAN AMERICAN\nWORLD AIRWAYS\nNEW\nYORK\nTOKYO\n*R • = 1-3-\n* At 62 A\nFIRST GREAT CIRCLE FLIGHT\nTOKYO TO NEW YORK\nVIA PAN AM JET\nЯЛ 72 #3152\nVIA AIR MAIL\nPAR AVION\nCORREO AEREO\n1967\n-21X30 8-\n50\nNIPPON\n#1300#HAE\nVIA AIR MAIL\nMr. J. G. O'Donnell\nVice. President-Sales - Pacific\nPan American World Airways\nPan Am Building\nNew York, New York\n10017",
      "SAMAICA,\nA.M.F.\nA.M.F.\nSEP\nTENNEDY\n2002.050.010"
    ],
    "millsfield:images_texts_ids": [
      1527830157,
      1527830159
    ],
    "millsfield:primary_image": 1527830157,
    "sfomuseum:accession_number": "2002.050.010",
    "sfomuseum:airline": "Pan American World Airways",
    "sfomuseum:category": "Philately",
    "sfomuseum:collection": "Aviation Archive",
    "sfomuseum:creditline": "Gift of Jerry O'Donnell",
    "sfomuseum:date": "09/02/1969",
    "sfomuseum:daterange_end": "1969-09-02",
    "sfomuseum:daterange_start": "1969-09-02",
    "sfomuseum:description": "Airmail flight cover commemorating first Pan American World Airways “Great Circle” route from Tokyo to New York; black cachet with image of route map; blue “Via Pan Am Jet” courtesy stamp; postmarked November 2, 1969 over 50-yen stamp; backstamp: September 2, 1969, Jamaica, NY.",
    "sfomuseum:dimensions": "3 1/2 x 6 1/2 inches (8.9 x 16.5 cm)",
    "sfomuseum:media_ids": [
      1527830157,
      1527830159
    ],
    "sfomuseum:medium": "paper, ink",
    "sfomuseum:placetype": "object",
    "sfomuseum:publication": ": , 09/02/1969.",
    "sfomuseum:subcategory": "Airmail Flight Cover",
    "wof:depicts": [
      1159286839,
      1159284989
    ],
    "wof:name": "airmail cover: Pan American World Airways, first “Great Circle” flight, Tokyo - New York",
    "wof:placetype": "custom",
    "wof:placetype_alt": [
      "object"
    ]
  },
  "geometry": {"coordinates":[-122.386155,37.616357],"type":"Point"}
}
