{
  "type": "Feature",
  "properties": {
    "date:cessation_lower": "1996-01-01",
    "date:cessation_upper": "1996-12-31",
    "date:inception_lower": "1996-01-01",
    "date:inception_upper": "1996-12-31",
    "iso:country": "XX",
    "sfomuseum:accession_number": "2006.023.036",
    "sfomuseum:airport": "Paris Charles de Gaulle Airport",
    "sfomuseum:author": "Gesar, Aram",
    "sfomuseum:callnumber": "HE984.A8 P37 1996",
    "sfomuseum:category": "Book",
    "sfomuseum:collection": "Aviation Library",
    "sfomuseum:creditline": "Gift of the collection of Frank J. Lichtanski",
    "sfomuseum:date": "c. 1996",
    "sfomuseum:date_acquired": "2006-08-03",
    "sfomuseum:daterange_end": "2001-12-31",
    "sfomuseum:daterange_start": "1991-01-01",
    "sfomuseum:description": "120 p. : col. ill., maps ; 21 x 22 cm.",
    "sfomuseum:description_library": "120 p. : col. ill., maps ; 21 x 22 cm.",
    "sfomuseum:medium": "paper, ink",
    "sfomuseum:placetype": "object",
    "sfomuseum:publication": "Shrewsbury, England: Airlife, c. 1996.",
    "sfomuseum:publisher": "Airlife",
    "sfomuseum:publisher_location": "Shrewsbury, England",
    "sfomuseum:subcategory": "Book",
    "sfomuseum:subject": "A‚eroport d'Orly (Paris, France)",
    "wof:depicts": [
      102544455,
      102544459
    ],
    "wof:name": "Paris airports: Orly, Charles de Gaulle, Le Bourget",
    "wof:placetype": "custom",
    "wof:placetype_alt": "object"
  },
  "geometry": {"coordinates":[-122.386155,37.616357],"type":"Point"}
}
