{
  "type": "Feature",
  "properties": {
    "date:cessation_lower": "1953-01-01",
    "date:cessation_upper": "1953-12-31",
    "date:inception_lower": "1953-01-01",
    "date:inception_upper": "1953-12-31",
    "iso:country": "XX",
    "millsfield:images": [
      1729566559,
      1729566561
    ],
    "millsfield:primary_image": 1729566559,
    "sfomuseum:accession_number": "2014.084.1382",
    "sfomuseum:airline": "British Commonwealth Pacific Airlines (BCPA)",
    "sfomuseum:category": "Scheduling / Ticketing",
    "sfomuseum:collection": "Aviation Archive",
    "sfomuseum:creditline": "Gift of Thomas G. Dragges",
    "sfomuseum:date": "1953",
    "sfomuseum:daterange_end": "1953-12-31",
    "sfomuseum:daterange_start": "1953-01-01",
    "sfomuseum:description": "Quick reference timetable issued by BCPA (British Commonwealth Pacific Airlines) for transpacific service routes, effective April 25, 1953; fold-out format; blue, white, and red cover with illustration of silhouetted planform aircraft and text “DC-6 sleeper service” followed by caption promoting service to Canada, USA, Hawaii, Fiji, Australia, and New Zealand.",
    "sfomuseum:dimensions": "9 x 4 inches (22.9 x 10.2 cm)",
    "sfomuseum:medium": "paper, ink",
    "sfomuseum:placetype": "object",
    "sfomuseum:subcategory": "Timetable",
    "wof:depicts": [
      1159284025
    ],
    "wof:name": "timetable: British Commonwealth Pacific Airlines (BCPA), quick reference, transpacific",
    "wof:placetype": "venue"
  },
  "geometry": {"coordinates":[-122.386155,37.616357],"type":"Point"}
}
