{
  "type": "Feature",
  "properties": {
    "date:cessation_lower": "2010-01-01",
    "date:cessation_upper": "2010-12-31",
    "date:inception_lower": "2010-01-01",
    "date:inception_upper": "2010-12-31",
    "iso:country": "XX",
    "sfomuseum:accession_number": "2012.122.003",
    "sfomuseum:airline": "Pan American World Airways",
    "sfomuseum:author": "King, Derek",
    "sfomuseum:callnumber": "TL686.B7 K56 2011",
    "sfomuseum:category": "Book",
    "sfomuseum:collection": "Aviation Library",
    "sfomuseum:creditline": "Purchase",
    "sfomuseum:date": "2010",
    "sfomuseum:daterange_end": "2010-12-31",
    "sfomuseum:daterange_start": "2010-01-01",
    "sfomuseum:description": "288 p. : col., 330 photo. ; 30 cm.",
    "sfomuseum:medium": "paper, ink",
    "sfomuseum:placetype": "object",
    "sfomuseum:publication": "Tonbridge: Air Britain Historians, 2010.",
    "sfomuseum:publisher": "Air Britain Historians",
    "sfomuseum:publisher_location": "Tonbridge",
    "sfomuseum:subcategory": "Book",
    "sfomuseum:subject": "Bristol Type 170 (Transport plane) -- History. \rBristol Type 170 (Transport plane) -- Design and construction. \rAirplanes -- Markings -- Great Britain. \rAirplanes -- Markings.",
    "wof:depicts": [
      1159284989
    ],
    "wof:name": "The Bristol type 170: freighter, wayfarer and superfreighter",
    "wof:placetype": "venue"
  },
  "geometry": {"coordinates":[-122.386155,37.616357],"type":"Point"}
}
