{
  "type": "Feature",
  "properties": {
    "date:cessation_lower": "1960-01-01",
    "date:cessation_upper": "1960-12-31",
    "date:inception_lower": "1960-01-01",
    "date:inception_upper": "1960-12-31",
    "iso:country": "XX",
    "millsfield:images": [
      1527854127,
      1527858359,
      1729566889
    ],
    "millsfield:images_texts": [
      "recional",
      "cecional"
    ],
    "millsfield:images_texts_ids": [
      1527854127,
      1729566889
    ],
    "millsfield:primary_image": 1527858359,
    "sfomuseum:accession_number": "2012.147.374",
    "sfomuseum:airline": "Air India",
    "sfomuseum:category": "Insignia",
    "sfomuseum:collection": "Aviation Museum",
    "sfomuseum:creditline": "Gift of the Captain John B. Russell Family",
    "sfomuseum:date": "c. 1960",
    "sfomuseum:date_acquired": "2014-04-17",
    "sfomuseum:daterange_end": "1965-12-31",
    "sfomuseum:daterange_start": "1955-01-01",
    "sfomuseum:description": "Flight officer wings issued by Air India; gold wings with black enamel logo on circle at center; pin with turn-clasp closure on back.",
    "sfomuseum:dimensions": "1/2 x 1 3/4 x 1/4 inches (1.3 x 4.4 x .6 cm)",
    "sfomuseum:media_ids": [
      1527854127,
      1527858359
    ],
    "sfomuseum:medium": "metal, enamel",
    "sfomuseum:placetype": "object",
    "sfomuseum:publication": ": , c. 1960.",
    "sfomuseum:subcategory": "Uniform Wing(s), Flight Crew",
    "wof:depicts": [
      1159287863,
      1159283649
    ],
    "wof:name": "flight officer wings: Air India",
    "wof:placetype": "custom",
    "wof:placetype_alt": "object"
  },
  "geometry": {"coordinates":[-122.386155,37.616357],"type":"Point"}
}
