{
  "type": "Feature",
  "properties": {
    "date:cessation_lower": "2000-01-01",
    "date:cessation_upper": "2000-12-31",
    "date:inception_lower": "2000-01-01",
    "date:inception_upper": "2000-12-31",
    "iso:country": "XX",
    "millsfield:images": [
      1763442179
    ],
    "millsfield:primary_image": 1763442179,
    "sfomuseum:accession_number": "2004.115.0735",
    "sfomuseum:aircraft": "Boeing 747-400",
    "sfomuseum:airline": "KLM asia",
    "sfomuseum:artist": "William “Bill” Hough",
    "sfomuseum:category": "Photograph",
    "sfomuseum:collection": "Aviation Archive",
    "sfomuseum:creditline": "Gift of the William Hough Collection",
    "sfomuseum:date": "2000",
    "sfomuseum:date_acquired": "2004-12-28",
    "sfomuseum:daterange_end": "2000-12-31",
    "sfomuseum:daterange_start": "2000-01-01",
    "sfomuseum:description": "Color photographic slide depicting KLM Asia Boeing 747-400, March 4, 2000.",
    "sfomuseum:dimensions": "1 x 1 1/2 inches (2.5 x 3.8 cm)",
    "sfomuseum:medium": "color slide",
    "sfomuseum:placetype": "object",
    "sfomuseum:publication": ": , 2000.",
    "sfomuseum:subcategory": "Slide",
    "wof:depicts": [
      1159284615,
      1159287541,
      1159289873,
      1159289915,
      1159293593
    ],
    "wof:name": "slide: KLM Asia, Boeing 747-400",
    "wof:placetype": "custom",
    "wof:placetype_alt": "object"
  },
  "geometry": {"coordinates":[-122.386155,37.616357],"type":"Point"}
}
