{
  "type": "Feature",
  "properties": {
    "date:cessation_lower": "2010-01-01",
    "date:cessation_upper": "2010-12-31",
    "date:inception_lower": "2010-01-01",
    "date:inception_upper": "2010-12-31",
    "iso:country": "XX",
    "loc:named_authorities": [
      "n42001331"
    ],
    "loc:subject_headings": [
      "sh85143926"
    ],
    "sfomuseum:accession_number": "2011.007.004",
    "sfomuseum:author": "Gibb, Randy. \rGray, Rob. \rScharff, Lauren",
    "sfomuseum:callnumber": "RC1075 .G53 2010",
    "sfomuseum:category": "Book",
    "sfomuseum:collection": "Aviation Library",
    "sfomuseum:creditline": "Purchase",
    "sfomuseum:date": "2010",
    "sfomuseum:date_acquired": "2010-12-27",
    "sfomuseum:daterange_end": "2010-12-31",
    "sfomuseum:daterange_start": "2010-01-01",
    "sfomuseum:description": "xii, 299 p. : ill., map ; 24 cm.",
    "sfomuseum:description_library": "xii, 299 p. : ill., map ; 24 cm.",
    "sfomuseum:medium": "paper, ink",
    "sfomuseum:placetype": "object",
    "sfomuseum:publication": "Farnham, Surrey, England ;\rBurlington, VT: Ashgate, 2010.",
    "sfomuseum:publisher": "Ashgate",
    "sfomuseum:publisher_location": "Farnham, Surrey, England ;\rBurlington, VT",
    "sfomuseum:series": "Ashgate studies in human factors for flight operations.",
    "sfomuseum:subcategory": "Book",
    "sfomuseum:subject": "Flight -- Physiological aspects. \rVisual perception. \rAeronautics -- Human factors. \rVisual Perception -- physiology. \rAerospace Medicine -- methods. \rAircraft.",
    "wof:name": "Aviation visual perception: research, misperception and mishaps",
    "wof:placetype": "venue"
  },
  "geometry": {"coordinates":[-122.386155,37.616357],"type":"Point"}
}
