{
  "type": "Feature",
  "properties": {
    "date:cessation_lower": "1975-01-01",
    "date:cessation_upper": "1975-12-31",
    "date:inception_lower": "1975-01-01",
    "date:inception_upper": "1975-12-31",
    "iso:country": "XX",
    "millsfield:images": [
      1527848195,
      1527848197
    ],
    "millsfield:primary_image": 1527848195,
    "sfomuseum:accession_number": "2007.002.031",
    "sfomuseum:airline": "United Air Lines",
    "sfomuseum:category": "Passenger Amenity, Archive",
    "sfomuseum:collection": "Aviation Archive",
    "sfomuseum:creditline": "Gift of John J. Larish",
    "sfomuseum:date": "c. 1975",
    "sfomuseum:date_acquired": "2006-12-26",
    "sfomuseum:daterange_end": "1980-12-31",
    "sfomuseum:daterange_start": "1970-01-01",
    "sfomuseum:description": "Menu issued by United Air Lines; color photographic image of woman holding ukulele (Hilo Hattie); menu items include poached eggs, omelette, beef brochette, and deli items; menu prepared in San Francisco; menu number: SFOHK R21-1N; class: First; date: 11/99.",
    "sfomuseum:dimensions": "11 x 8 1/2 inches (27.9 x 21.6 cm)",
    "sfomuseum:media_ids": [
      1527848195,
      1527848197
    ],
    "sfomuseum:medium": "paper, ink",
    "sfomuseum:placetype": "object",
    "sfomuseum:publication": ": , c. 1975.",
    "sfomuseum:subcategory": "Menu",
    "wof:depicts": [
      1159285415,
      1159288779,
      1159285413
    ],
    "wof:name": "menu: United Air Lines, First Class",
    "wof:placetype": "custom",
    "wof:placetype_alt": "object"
  },
  "geometry": {"coordinates":[-122.386155,37.616357],"type":"Point"}
}
