{
  "type": "Feature",
  "properties": {
    "date:cessation_lower": "1929-12-31",
    "date:cessation_upper": "1929-12-31",
    "date:inception_lower": "1929-01-01",
    "date:inception_upper": "1929-01-01",
    "iso:country": "XX",
    "sfomuseum:accession_number": "2000.018.043",
    "sfomuseum:category": "Photograph",
    "sfomuseum:collection": "Aviation Archive",
    "sfomuseum:creditline": "Transfer from City and County of San Francisco",
    "sfomuseum:date": "1929",
    "sfomuseum:daterange_end": "1929-12-31",
    "sfomuseum:daterange_start": "1929-01-01",
    "sfomuseum:description": "Black and white photograph depicting potential site for airport south of San Francisco, with sign at right, “Industrial Property / For Sale / W. R. Hoag \u0026 Co. / 703 M K T St., S.F.”",
    "sfomuseum:media_ids": [
      1527830385
    ],
    "sfomuseum:medium": "photograph",
    "sfomuseum:placetype": "object",
    "sfomuseum:subcategory": "Print, Photograph",
    "wof:name": "photograph: Mills Field area, industrial property for sale",
    "wof:placetype": "venue"
  },
  "geometry": {"coordinates":[-122.386155,37.616358],"type":"Point"}
}
