{
  "type": "Feature",
  "properties": {
    "date:cessation_lower": "1939-05-25",
    "date:cessation_upper": "1939-05-25",
    "date:inception_lower": "1939-05-25",
    "date:inception_upper": "1939-05-25",
    "iso:country": "XX",
    "millsfield:images": [
      1527852193,
      1527852197
    ],
    "millsfield:images_texts": [
      "FRANCE •ETATS-UNIS\nPOSTES\nRASE\nRE\nS R\nCARCASSONNE\n39\nVIA AIR MAIL\nMARSEILLES TO\nAZORES\nMr. Herman Zbinden\n810 Nebraska Ave.\nTOLEDO\nOhio\nU. S. A.",
      "K. M. WALSH\n433 Westchester Ave.\nCRESTWOOD, N.Y.\n0 S3H08\nMAR,\n26MA139\n1012.149.2250"
    ],
    "millsfield:images_texts_ids": [
      1527852193,
      1527852197
    ],
    "millsfield:primary_image": 1527852193,
    "sfomuseum:accession_number": "2012.149.2250 a b",
    "sfomuseum:airline": "Pan American Airways",
    "sfomuseum:category": "Philately",
    "sfomuseum:collection": "Aviation Archive",
    "sfomuseum:creditline": "Gift of the Captain John B. Russell Family",
    "sfomuseum:date": "05/25/1939",
    "sfomuseum:date_acquired": "2013-05-31",
    "sfomuseum:daterange_end": "1939-05-25",
    "sfomuseum:daterange_start": "1939-05-25",
    "sfomuseum:description": "a. Airmail flight cover, Pan American Airways, first Clipper flight, FAM-18, Marseilles - Horta route; black stamped cachet with image of airplane flying toward Statue of Liberty at left; postmarked May 25, 1939 in Marseilles with one red stamp and one blue stamp; backstamp: May 26, 1939 in Horta; red and blue diagonally striped border at all edges.\rb. Backing sheet with two sets of black backing and mounting corners, with typewritten caption: “F18-6b Marseilles - Horta; May 25, 1939 - arrived May 26, 1939; pilot - Arthur E. LaPorte”.",
    "sfomuseum:dimensions": "3 3/4 x 6 1/2 inches (9.5 x 16.5 cm)",
    "sfomuseum:media_ids": [
      1527852193,
      1527852197
    ],
    "sfomuseum:medium": "paper, ink",
    "sfomuseum:placetype": "object",
    "sfomuseum:publication": ": , 05/25/1939.",
    "sfomuseum:subcategory": "Airmail Flight Cover",
    "sfomuseum:subject": "Airlines -- Commercial -- Pan American Airways.",
    "wof:depicts": [
      1159284991,
      1159286839
    ],
    "wof:name": "airmail flight cover: Pan American Airways, FAM-18, first airmail flight, Marseilles - Horta route",
    "wof:placetype": "custom",
    "wof:placetype_alt": "object"
  },
  "geometry": {"coordinates":[-122.386155,37.616357],"type":"Point"}
}
