{
  "type": "Feature",
  "properties": {
    "date:cessation_lower": "1987-01-01",
    "date:cessation_upper": "1987-12-31",
    "date:inception_lower": "1987-01-01",
    "date:inception_upper": "1987-12-31",
    "isbn:number": "0851406173, 9780851406176",
    "iso:country": "XX",
    "sfomuseum:accession_number": "2005.040.001",
    "sfomuseum:author": "Doyle, Richard",
    "sfomuseum:callnumber": "PR6054.O9 D6 1987",
    "sfomuseum:category": "Book",
    "sfomuseum:collection": "Aviation Library",
    "sfomuseum:creditline": "Collection of SFO Museum",
    "sfomuseum:date": "1987",
    "sfomuseum:date_acquired": "2005-12-31",
    "sfomuseum:daterange_end": "1987-12-31",
    "sfomuseum:daterange_start": "1987-01-01",
    "sfomuseum:description": "515 p. ; 24 cm.",
    "sfomuseum:description_library": "515 p. ; 24 cm.",
    "sfomuseum:medium": "paper, ink",
    "sfomuseum:placetype": "object",
    "sfomuseum:publication": "London: Arlington, 1987.",
    "sfomuseum:publisher": "Arlington",
    "sfomuseum:publisher_location": "London",
    "sfomuseum:subcategory": "Book",
    "sfomuseum:subject": "Fiction in English, 1945- - Texts",
    "wof:name": "Pacific clipper",
    "wof:placetype": "custom",
    "wof:placetype_alt": "object"
  },
  "geometry": {"coordinates":[-122.386155,37.616357],"type":"Point"}
}
