{
  "type": "Feature",
  "properties": {
    "date:cessation_lower":"2004-12-31",
    "date:cessation_upper":"2004-12-31",
    "date:inception_lower":"1994-01-01",
    "date:inception_upper":"1994-01-01",
    "iso:country":"XX",
    "sfomuseum:accession_number":"2006.034.071 a b",
    "sfomuseum:category":"Food Service",
    "sfomuseum:collection":"Aviation Museum",
    "sfomuseum:creditline":"Gift of Adan Wong",
    "sfomuseum:date":"c. 1999",
    "sfomuseum:daterange_end":"2004-12-31",
    "sfomuseum:daterange_start":"1994-01-01",
    "sfomuseum:description":"Menu and wine list produced by Cathay Pacific Airways, Hong Kong - Los Angeles route; red and black cover with color photographic image of kiwi fruit slices; dinner and breakfast menu items include chicken in cream sauce, pasta with pesto, roasted duck with rice noodles.\ra. menu; menu number: CX880-2058 F JUN; class: first; undated\rb. wine list; menu number CX838, 839, 888, 839; class: first; date: 1-8-99",
    "sfomuseum:medium":"paper, ink, string",
    "sfomuseum:placetype":"object",
    "sfomuseum:subcategory":"Menu",
    "wof:name":"menu: Cathay Pacific Airways, First Class",
    "wof:placetype":"venue"
},
  "geometry": {"coordinates":[-122.386155,37.616358],"type":"Point"}
}