{
  "type": "Feature",
  "properties": {
    "date:cessation_lower":"1920-12-31",
    "date:cessation_upper":"1920-12-31",
    "date:inception_lower":"1910-01-01",
    "date:inception_upper":"1910-01-01",
    "iso:country":"XX",
    "sfomuseum:accession_number":"2010.174.504 a",
    "sfomuseum:artist":"Stanley Henry Page",
    "sfomuseum:category":"Photograph",
    "sfomuseum:collection":"Aviation Archive",
    "sfomuseum:creditline":"Gift of Charles Page",
    "sfomuseum:date":"c. 1915",
    "sfomuseum:daterange_end":"1920-12-31",
    "sfomuseum:daterange_start":"1910-01-01",
    "sfomuseum:description":"Black and white photograph depicting aerial view over San Francisco Bay with detailed view of anchored vessels in parallel formation; photograph from employee career history of S. H. Page, mechanical engineer and photographer.",
    "sfomuseum:media_ids":[
        1527856055
    ],
    "sfomuseum:medium":"photograph",
    "sfomuseum:placetype":"object",
    "sfomuseum:subcategory":"Print, Photograph",
    "wof:name":"photograph: San Francisco Bay Area aerial, fleet of ships in Bay",
    "wof:placetype":"venue"
},
  "geometry": {"coordinates":[-122.386155,37.616358],"type":"Point"}
}