{
  "type": "Feature",
  "properties": {
    "date:cessation_lower": "1975-01-01",
    "date:cessation_upper": "1975-12-31",
    "date:inception_lower": "1975-01-01",
    "date:inception_upper": "1975-12-31",
    "iso:country": "XX",
    "millsfield:images": [
      1746680829
    ],
    "millsfield:images_texts": [
      "SEABOARD WORLD AIRLINES\nLIGHT STEWARDESS MANUAL"
    ],
    "millsfield:images_texts_ids": [
      1746680829
    ],
    "millsfield:primary_image": 1746680829,
    "sfomuseum:accession_number": "2001.078.003",
    "sfomuseum:airline": "Seaboard World Airlines",
    "sfomuseum:category": "Company Record / Document",
    "sfomuseum:collection": "Aviation Archive",
    "sfomuseum:creditline": "Gift of Thomas G. Dragges",
    "sfomuseum:date": "c. 1975",
    "sfomuseum:date_acquired": "2022-04-18",
    "sfomuseum:daterange_end": "1980-12-31",
    "sfomuseum:daterange_start": "1970-01-01",
    "sfomuseum:description": "Flight attendant / stewardess manual produced by Seaboard World Airlines; black binder; divided into sections including organization, operating instructions, emergencies, training, foreign instructions, aircraft, etc. ",
    "sfomuseum:dimensions": "10 x 7 1/2 inches (25.4 x 19.1 cm)",
    "sfomuseum:medium": "paper, ink, vinyl, metal",
    "sfomuseum:placetype": "object",
    "sfomuseum:publication": ": , c. 1975.",
    "sfomuseum:subcategory": "Manual, Crew",
    "wof:depicts": [
      1159285135,
      1159288077
    ],
    "wof:name": "flight attendant manual: Seaboard World Airlines",
    "wof:placetype": "custom",
    "wof:placetype_alt": "object"
  },
  "geometry": {"coordinates":[-122.386155,37.616357],"type":"Point"}
}
