{
  "type": "Feature",
  "properties": {
    "date:cessation_lower": "1979-01-01",
    "date:cessation_upper": "1979-12-31",
    "date:inception_lower": "1979-01-01",
    "date:inception_upper": "1979-12-31",
    "iso:country": "XX",
    "sfomuseum:accession_number": "2008.107.074",
    "sfomuseum:author": "Mackintosh, Ian",
    "sfomuseum:callnumber": "TL603 .M33 1979",
    "sfomuseum:category": "Book",
    "sfomuseum:collection": "Aviation Library",
    "sfomuseum:creditline": "Gift of Thomas G. Dragges",
    "sfomuseum:date": "1979",
    "sfomuseum:date_acquired": "2009-12-31",
    "sfomuseum:daterange_end": "1979-12-31",
    "sfomuseum:daterange_start": "1979-01-01",
    "sfomuseum:description": "v. : ill. ; 22 cm.",
    "sfomuseum:description_library": "v. : ill. ; 22 cm.",
    "sfomuseum:medium": "paper, ink",
    "sfomuseum:placetype": "object",
    "sfomuseum:publication": "Hounslow, England: Airline Publications \u0026 Sales, 1979.",
    "sfomuseum:publisher": "Airline Publications \u0026 Sales",
    "sfomuseum:publisher_location": "Hounslow, England",
    "sfomuseum:subcategory": "Book",
    "sfomuseum:subject": "Transport planes Decoration.",
    "wof:name": "Encyclopedia of airline colour schemes",
    "wof:placetype": "custom",
    "wof:placetype_alt": "object"
  },
  "geometry": {"coordinates":[-122.386155,37.616357],"type":"Point"}
}
