{
  "type": "Feature",
  "properties": {
    "date:cessation_lower": "1964-01-01",
    "date:cessation_upper": "1964-12-31",
    "date:inception_lower": "1964-01-01",
    "date:inception_upper": "1964-12-31",
    "iso:country": "XX",
    "millsfield:images": [
      1527819443
    ],
    "millsfield:images_texts": [
      "*IR FRANCE\nWORLD'S\nLARGEST\nDESTINATION:\nI EUROPE\no W\nPARIS\nFIRST STOP:\nBIG FARE SAVINGS\nWITH LOW GROUP FARES\nGERMaNY\nSE AT FLIGHTS WEEKLY\nTalY\n40 JET FLIGHTS WEEKLY\nENGLAND\nOBJET FLIGHTS WEEKLY\nGReeCe\nHAT FLIGHIS WEEKLY\nISRaeL\n1 AT RIGHTS WEEKLY\nSMITZERLaND\n35 JET FLIGHTS WEEKLY\nRiviera\n36 JET FUGHTS WEEKLY\nFROM PaRiS\nJetAway,\nHolidays\nSKIESIN\nAND AIR-\nSEA CRUISES\nMore Jets\nFROM PARIS\n1o More Cities\nin FUROPE\nTHAN ANY OTHER\nAIRLINE\nSEE YOUR\nTRAVEL\nAGENT\nFIRST"
    ],
    "millsfield:images_texts_ids": [
      1527819443
    ],
    "millsfield:primary_image": 1527819443,
    "sfomuseum:accession_number": "2011.001.046.069",
    "sfomuseum:airline": "Air France",
    "sfomuseum:category": "Promotional, Archive",
    "sfomuseum:collection": "Aviation Archive",
    "sfomuseum:creditline": "Gift of Robert Behr",
    "sfomuseum:date": "1964",
    "sfomuseum:date_acquired": "2011-05-25",
    "sfomuseum:daterange_end": "1964-12-31",
    "sfomuseum:daterange_start": "1964-01-01",
    "sfomuseum:description": "Advertisement from Sunset magazine promoting Air France, with main caption incorporated in color photographic image of advertisement booth in front of flower market stand, “Air France / Destination: Europe / First stop: Paris / Big fare savings with low group fares”.",
    "sfomuseum:dimensions": "11 x 8 1/2 inches (27.9 x 21.6 cm)",
    "sfomuseum:media_ids": [
      1527819443
    ],
    "sfomuseum:medium": "paper, ink",
    "sfomuseum:placetype": "object",
    "sfomuseum:publication": ": , 1964.",
    "sfomuseum:subcategory": "Advertisement, 2D",
    "wof:depicts": [
      1159283627,
      1360700617
    ],
    "wof:name": "advertisement: Air France, Sunset",
    "wof:placetype": "custom",
    "wof:placetype_alt": "object"
  },
  "geometry": {"coordinates":[-122.386155,37.616357],"type":"Point"}
}
