{
  "type": "Feature",
  "properties": {
    "date:cessation_lower": "1980-01-01",
    "date:cessation_upper": "1989-12-31",
    "date:inception_lower": "1980-01-01",
    "date:inception_upper": "1989-12-31",
    "iso:country": "XX",
    "millsfield:images": [
      1763380563
    ],
    "millsfield:images_texts": [
      "THE HISTORY OF\nPASSENGER FLIGHT\nPLAYING CARDS\nBRITISH AIRWAYS"
    ],
    "millsfield:images_texts_ids": [
      1763380563
    ],
    "millsfield:primary_image": 1763380563,
    "sfomuseum:accession_number": "2010.104.168",
    "sfomuseum:airline": "British Airways",
    "sfomuseum:category": "Passenger Amenity, Museum",
    "sfomuseum:collection": "Aviation Museum",
    "sfomuseum:creditline": "Gift of Thomas G. Dragges",
    "sfomuseum:date": "1980s",
    "sfomuseum:date_acquired": "2011-02-24",
    "sfomuseum:daterange_end": "1989-12-31",
    "sfomuseum:daterange_start": "1980-01-01",
    "sfomuseum:description": "Deck of bridge cards issued by British Airways; blue box with white border and text, “The history of passenger flight / playing cards”, and airline servicemark at bottom; reverse blue with airline servicemark in double-ended format; servicemark on long sides; top and bottom blue; box sealed.",
    "sfomuseum:dimensions": "3 19/32 x 2 13/32 x 3/4 inches (9.1 x 6.1 x 1.9 cm)",
    "sfomuseum:medium": "cardboard, ink",
    "sfomuseum:placetype": "object",
    "sfomuseum:publication": ": , 1980s.",
    "sfomuseum:subcategory": "Playing Cards",
    "wof:depicts": [
      1159284021,
      1159287729
    ],
    "wof:name": "playing cards: British Airways",
    "wof:placetype": "custom",
    "wof:placetype_alt": [
      "object"
    ]
  },
  "geometry": {"coordinates":[-122.386155,37.616357],"type":"Point"}
}
