{
  "type": "Feature",
  "properties": {
    "date:cessation_lower": "1994-01-01",
    "date:cessation_upper": "1994-12-31",
    "date:inception_lower": "1994-01-01",
    "date:inception_upper": "1994-12-31",
    "iso:country": "XX",
    "sfomuseum:accession_number": "1999.659.162",
    "sfomuseum:airport": "John F. Kennedy International Airport",
    "sfomuseum:author": "Gesar, Aram",
    "sfomuseum:callnumber": "TL726.4.N5 G47 1994",
    "sfomuseum:category": "Book",
    "sfomuseum:collection": "Aviation Library",
    "sfomuseum:creditline": "Purchase",
    "sfomuseum:date": "c. 1994",
    "sfomuseum:daterange_end": "1999-12-31",
    "sfomuseum:daterange_start": "1989-01-01",
    "sfomuseum:description": "1 v. (unpaged) : ill. (some col.), maps ; 21 x 22 cm.",
    "sfomuseum:description_library": "1 v. (unpaged) : ill. (some col.), maps ; 21 x 22 cm.",
    "sfomuseum:medium": "paper, ink",
    "sfomuseum:notes_library": "Foreword by David Z. Plavin, Director of Aviation, The Port Authority of New York and New Jersey. A book edited and produced for Airlife by Pyramid Media Group --T.p. verso. Edited by David Quast --T.p. verso. Text by Aram Gesar --T.p. verso.Chiefly photographs.",
    "sfomuseum:placetype": "object",
    "sfomuseum:publication": "Shrewsbury, England: Airlife, c. 1994.",
    "sfomuseum:publisher": "Airlife",
    "sfomuseum:publisher_location": "Shrewsbury, England",
    "sfomuseum:subcategory": "Book",
    "sfomuseum:subject": "Port Authority of New York and New JerseyNewark International Airport.Airports New York Metropolitain Area.La Guardia Airport (N.Y.)John F. Kennedy International Airport (N.Y.)New York (State)Airports",
    "wof:depicts": [
      102530049,
      102534365
    ],
    "wof:name": "New York's airports: John F. Kennedy, Newark, LaGuardia",
    "wof:placetype": "venue"
  },
  "geometry": {"coordinates":[-122.386155,37.616357],"type":"Point"}
}
