{
  "type": "Feature",
  "properties": {
    "date:cessation_lower": "1970-01-01",
    "date:cessation_upper": "1979-12-31",
    "date:inception_lower": "1970-01-01",
    "date:inception_upper": "1979-12-31",
    "iso:country": "XX",
    "millsfield:images": [
      1527818101,
      1527819335
    ],
    "millsfield:primary_image": 1527818101,
    "sfomuseum:accession_number": "2001.124.001",
    "sfomuseum:airline": "Air Vietnam",
    "sfomuseum:category": "Promotional, Museum",
    "sfomuseum:collection": "Aviation Museum",
    "sfomuseum:continent": "World Routes",
    "sfomuseum:creditline": "Purchase",
    "sfomuseum:date": "1970s",
    "sfomuseum:date_acquired": "2001-11-28",
    "sfomuseum:daterange_end": "1979-12-31",
    "sfomuseum:daterange_start": "1970-01-01",
    "sfomuseum:description": "Airline bag issued by Air Vietnam; off-white background with blue dragon and logotype on front pocket and back; adjustable long shoulder strap and top zipper closure.",
    "sfomuseum:dimensions": "11 1/2 x 13 1/2 x 6 inches (29.2 x 34.3 x 15.2 cm)",
    "sfomuseum:media_ids": [
      1527819335,
      1527818101
    ],
    "sfomuseum:medium": "vinyl, metal, ink",
    "sfomuseum:placetype": "object",
    "sfomuseum:publication": ": , 1970s.",
    "sfomuseum:subcategory": "Airline Bag",
    "wof:depicts": [
      1159283771,
      1159287421
    ],
    "wof:name": "airline bag: Air Vietnam",
    "wof:placetype": "custom",
    "wof:placetype_alt": "object"
  },
  "geometry": {"coordinates":[-122.386155,37.616358],"type":"Point"}
}
