{
  "type": "Feature",
  "properties": {
    "date:cessation_lower": "1950-12-31",
    "date:cessation_upper": "1950-12-31",
    "date:inception_lower": "1950-01-01",
    "date:inception_upper": "1950-01-01",
    "iso:country": "XX",
    "millsfield:images": [
      1527836279
    ],
    "sfomuseum:accession_number": "2005.132.007.007",
    "sfomuseum:airline": "American Airlines",
    "sfomuseum:category": "Scheduling / Ticketing",
    "sfomuseum:collection": "Aviation Archive",
    "sfomuseum:creditline": "Gift of the William Hough Collection",
    "sfomuseum:date": "1950",
    "sfomuseum:daterange_end": "1950-12-31",
    "sfomuseum:daterange_start": "1950-01-01",
    "sfomuseum:description": "Timetable issued by American Airlines for Mexican and Central American service, effective April 30, 1950; four page double-sided fold-out. The cover is white and maroon with drawings of a serape and guitar. The company logo is bottom left.",
    "sfomuseum:dimensions": "9 x 4 inches (22.9 x 10.2 cm)",
    "sfomuseum:media_ids": [
      1527836279
    ],
    "sfomuseum:medium": "paper, ink",
    "sfomuseum:placetype": "object",
    "sfomuseum:subcategory": "Timetable",
    "wof:depicts": [
      1159283849
    ],
    "wof:name": "timetable: American Airlines, Mexico",
    "wof:placetype": "venue"
  },
  "geometry": {"coordinates":[-122.386155,37.616357],"type":"Point"}
}
