{
  "type": "Feature",
  "properties": {
    "date:cessation_lower":"1962-12-31",
    "date:cessation_upper":"1962-12-31",
    "date:inception_lower":"1952-01-01",
    "date:inception_upper":"1952-01-01",
    "iso:country":"US",
    "sfomuseum:accession_number":"1997.57.05",
    "sfomuseum:aircraft":"Douglas DC-7C",
    "sfomuseum:airline":"Pan American World Airways",
    "sfomuseum:category":"Company Record / Document",
    "sfomuseum:collection":"Aviation Archive",
    "sfomuseum:continent":"North America",
    "sfomuseum:country":"United States",
    "sfomuseum:creditline":"Gift of Lamar Lay",
    "sfomuseum:date":"c. 1957",
    "sfomuseum:daterange_end":"1962-12-31",
    "sfomuseum:daterange_start":"1952-01-01",
    "sfomuseum:description":"Aircraft operating manual produced by Pan American World Airways.  Black coated canvas spiral bound notebook with removable typed pages. \"B-377\" in white letters on spine. \"Aircraft Operating Manual, Pan American World Airways\" and winged world logo in silver on cover. Chapters: Cruising Control, Emergencies, Loading, Operating Information, Performance, Radio, Systems and Design, Appendix, Flight Info File.",
    "sfomuseum:maker":"Pan American World Airways, Inc.",
    "sfomuseum:medium":"coated canvas, metal, typed pages.",
    "sfomuseum:placetype":"object",
    "sfomuseum:subcategory":"Manual, Flight",
    "wof:depicts":[
        1159290439,
        1159290435,
        1159284989,
        1159289651
    ],
    "wof:name":"operating manual: Pan American World Airways, Douglas DC-7C",
    "wof:placetype":"venue"
},
  "geometry": {"coordinates":[-122.386155,37.616357],"type":"Point"}
}