{
  "type": "Feature",
  "properties": {
    "date:cessation_lower": "1955-12-31",
    "date:cessation_upper": "1955-12-31",
    "date:inception_lower": "1945-01-01",
    "date:inception_upper": "1945-01-01",
    "iso:country": "XX",
    "sfomuseum:accession_number": "2001.173.001",
    "sfomuseum:author": "Campbell, Julie",
    "sfomuseum:callnumber": "PZ7.W46 T21 Cl 1950",
    "sfomuseum:category": "Book",
    "sfomuseum:collection": "Aviation Library",
    "sfomuseum:creditline": "Anonymous gift",
    "sfomuseum:date": "c. 1950",
    "sfomuseum:daterange_end": "1955-12-31",
    "sfomuseum:daterange_start": "1945-01-01",
    "sfomuseum:description": "211 p. : ill. ; 20 cm.",
    "sfomuseum:medium": "paper, ink",
    "sfomuseum:placetype": "object",
    "sfomuseum:publisher": "Grosset \u0026 Dunlap",
    "sfomuseum:publisher_location": "New York",
    "sfomuseum:series": "The Vicki Barr flight stewardess series",
    "sfomuseum:subcategory": "Book",
    "sfomuseum:subject": "Juvenile literature -- Adult format.\rBarr, Vicki (Fictitious character) Juvenile fiction.Flight attendants Juvenile fiction.Adventure and adventurers Juvenile fiction.Women detectives Juvenile fiction.Mystery and detective stories.Mystery fiction. ",
    "wof:name": "The clue of the broken blossom",
    "wof:placetype": "venue"
  },
  "geometry": {"coordinates":[-122.386155,37.616357],"type":"Point"}
}
