{
  "type": "Feature",
  "properties": {
    "date:cessation_lower":"1936-12-31",
    "date:cessation_upper":"1936-12-31",
    "date:inception_lower":"1936-01-01",
    "date:inception_upper":"1936-01-01",
    "iso:country":"XX",
    "sfomuseum:accession_number":"2000.055.008",
    "sfomuseum:category":"Scheduling / Ticketing",
    "sfomuseum:collection":"Aviation Archive",
    "sfomuseum:creditline":"Purchase",
    "sfomuseum:date":"1936",
    "sfomuseum:daterange_end":"1936-12-31",
    "sfomuseum:daterange_start":"1936-01-01",
    "sfomuseum:description":"Timetable issued by Northwest Airlines, effective February 1, 1936; red, black and white cover with illustration of airplane flying over route map of continental United States and text, \"The short scenic route between Chicago and the Pacific Northwest.\" ",
    "sfomuseum:media_ids":[
        1527837517,
        1527850553,
        1527850555
    ],
    "sfomuseum:medium":"paper, ink",
    "sfomuseum:placetype":"object",
    "sfomuseum:subcategory":"Timetable",
    "wof:name":"timetable: Northwest Airlines",
    "wof:placetype":"venue"
},
  "geometry": {"coordinates":[-122.386155,37.616358],"type":"Point"}
}