{
  "type": "Feature",
  "properties": {
    "date:cessation_lower": "1936-01-01",
    "date:cessation_upper": "1936-12-31",
    "date:inception_lower": "1936-01-01",
    "date:inception_upper": "1936-12-31",
    "iso:country": "XX",
    "millsfield:images": [
      1527850553,
      1527850555,
      1527837517
    ],
    "sfomuseum:accession_number": "2000.055.008",
    "sfomuseum:aircraft": "Lockheed Model 10 Electra",
    "sfomuseum:airline": "Northwest Airlines",
    "sfomuseum:category": "Scheduling / Ticketing",
    "sfomuseum:collection": "Aviation Archive",
    "sfomuseum:creditline": "Purchase",
    "sfomuseum:date": "1936",
    "sfomuseum:daterange_end": "1936-12-31",
    "sfomuseum:daterange_start": "1936-01-01",
    "sfomuseum:description": "Timetable issued by Northwest Airlines, effective February 1, 1936; red, black and white cover with illustration of airplane flying over route map of continental United States and text, \"The short scenic route between Chicago and the Pacific Northwest.\" ",
    "sfomuseum:dimensions": "9 x 4 inches (22.9 x 10.2 cm)",
    "sfomuseum:media_ids": [
      1527837517,
      1527850553,
      1527850555
    ],
    "sfomuseum:medium": "paper, ink",
    "sfomuseum:placetype": "object",
    "sfomuseum:subcategory": "Timetable",
    "sfomuseum:subject": "Airlines -- Timetables -- Northwest Airlines",
    "wof:depicts": [
      1159284907,
      1159291101
    ],
    "wof:name": "timetable: Northwest Airlines",
    "wof:placetype": "custom"
  },
  "geometry": {"coordinates":[-122.386155,37.616357],"type":"Point"}
}
