{
  "type": "Feature",
  "properties": {
    "date:cessation_lower": "1981-01-01",
    "date:cessation_upper": "1981-12-31",
    "date:inception_lower": "1981-01-01",
    "date:inception_upper": "1981-12-31",
    "iso:country": "XX",
    "millsfield:images": [
      1527842413
    ],
    "millsfield:primary_image": 1527842413,
    "sfomuseum:accession_number": "2012.173.325",
    "sfomuseum:airline": "Pan American World Airways",
    "sfomuseum:category": "Scheduling / Ticketing",
    "sfomuseum:collection": "Aviation Archive",
    "sfomuseum:creditline": "Gift of Willard F. Keeney",
    "sfomuseum:date": "1981",
    "sfomuseum:date_acquired": "2013-03-28",
    "sfomuseum:daterange_end": "1981-12-31",
    "sfomuseum:daterange_start": "1981-01-01",
    "sfomuseum:description": "System timetable issued by Pan American World Airways, effective October 25, 1981; fold-out format; on cover: color photographic image of airplane tail engine at night; includes route map.",
    "sfomuseum:dimensions": "9 x 4 inches (22.9 x 10.2 cm)",
    "sfomuseum:media_ids": [
      1527842413
    ],
    "sfomuseum:medium": "paper, ink",
    "sfomuseum:placetype": "object",
    "sfomuseum:publication": ": , 1981.",
    "sfomuseum:subcategory": "Timetable",
    "sfomuseum:subject": "Airlines -- Commercial -- Pan American World Airways",
    "wof:depicts": [
      1159284989,
      1159286839
    ],
    "wof:name": "timetable: Pan American World Airways",
    "wof:placetype": "custom",
    "wof:placetype_alt": "object"
  },
  "geometry": {"coordinates":[-122.386155,37.616357],"type":"Point"}
}
