{
  "type": "Feature",
  "properties": {
    "date:cessation_lower": "1927-01-01",
    "date:cessation_upper": "1927-12-31",
    "date:inception_lower": "1927-01-01",
    "date:inception_upper": "1927-12-31",
    "iso:country": "XX",
    "millsfield:images": [
      1527856943
    ],
    "millsfield:primary_image": 1527856943,
    "sfomuseum:accession_number": "2000.018.040.025",
    "sfomuseum:airport": "Mills Field Municipal Airport of San Francisco",
    "sfomuseum:category": "Company Record / Document",
    "sfomuseum:collection": "Aviation Archive",
    "sfomuseum:creditline": "Transfer",
    "sfomuseum:date": "1927",
    "sfomuseum:date_acquired": "2009-12-11",
    "sfomuseum:daterange_end": "1927-12-31",
    "sfomuseum:daterange_start": "1927-01-01",
    "sfomuseum:description": "Facsimile of correspondence from Joseph J. Phillips, Right of Way Agent for City and County of San Francisco, to W. H. Howard Estate Company, dated May 18, 1927, concerning request to install meteorological station in conjunction with lease of Mills Estate property in San Mateo County for use as airport; file copy, not signed or mailed.",
    "sfomuseum:dimensions": "11 x 8 1/2 inches (27.9 x 21.6 cm)",
    "sfomuseum:media_ids": [
      1527856943
    ],
    "sfomuseum:medium": "paper, ink",
    "sfomuseum:placetype": "object",
    "sfomuseum:publication": ": , 1927.",
    "sfomuseum:subcategory": "Correspondence, Company",
    "wof:depicts": [
      1360695653
    ],
    "wof:name": "correspondence: Joseph J. Phillips, Right of Way Agent for City and County of San Francisco",
    "wof:placetype": "custom",
    "wof:placetype_alt": "object"
  },
  "geometry": {"coordinates":[-122.386155,37.616357],"type":"Point"}
}
