{
  "type": "Feature",
  "properties": {
    "date:cessation_lower": "1940-01-01",
    "date:cessation_upper": "1949-12-31",
    "date:inception_lower": "1940-01-01",
    "date:inception_upper": "1949-12-31",
    "iso:country": "XX",
    "sfomuseum:accession_number": "2012.147.085",
    "sfomuseum:category": "Insignia",
    "sfomuseum:collection": "Aviation Museum",
    "sfomuseum:creditline": "Gift of the Captain John B. Russell Family",
    "sfomuseum:date": "1940s",
    "sfomuseum:date_acquired": "2014-04-17",
    "sfomuseum:daterange_end": "1949-12-31",
    "sfomuseum:daterange_start": "1940-01-01",
    "sfomuseum:description": "Service pin issued by Republic Aviation for 1 year of service; silver wings with blue logo on center; post with screw-back closure on back; aircraft corporation.",
    "sfomuseum:dimensions": "1/4 x 1 x 1/4 inches (.6 x 2.5 x .6 cm)",
    "sfomuseum:medium": "metal, enamel",
    "sfomuseum:placetype": "object",
    "sfomuseum:publication": ": , 1940s.",
    "sfomuseum:subcategory": "Pin, Service",
    "wof:name": "service pin: Republic Aviation, 1 year",
    "wof:placetype": "custom",
    "wof:placetype_alt": "object"
  },
  "geometry": {"coordinates":[-122.386155,37.616357],"type":"Point"}
}
