{
  "type": "Feature",
  "properties": {
    "date:cessation_lower": "1970-01-01",
    "date:cessation_upper": "1979-12-31",
    "date:inception_lower": "1970-01-01",
    "date:inception_upper": "1979-12-31",
    "iso:country": "XX",
    "millsfield:images": [
      1527858429
    ],
    "millsfield:primary_image": 1527858429,
    "sfomuseum:accession_number": "2002.018.039",
    "sfomuseum:airline": "Qantas Airways",
    "sfomuseum:category": "Meal Service",
    "sfomuseum:collection": "Aviation Museum",
    "sfomuseum:creditline": "Gift of Thomas G. Dragges",
    "sfomuseum:date": "1970s",
    "sfomuseum:daterange_end": "1979-12-31",
    "sfomuseum:daterange_start": "1970-01-01",
    "sfomuseum:description": "Entree plate issued by Qantas Airways for inflight meal service; white with gold “Alice Springs” pattern near top edge and stripe along edge.",
    "sfomuseum:dimensions": "3/4 x 8 1/4 x 8 1/4 inches (1.9 x 21 x 21 cm)",
    "sfomuseum:maker": "Wedgwood",
    "sfomuseum:media_ids": [
      1527858429
    ],
    "sfomuseum:medium": "glazed bone china",
    "sfomuseum:placetype": "object",
    "sfomuseum:publication": ": , 1970s.",
    "sfomuseum:subcategory": "Plate / Dish / Bowl",
    "wof:depicts": [
      1159285043,
      1159287479
    ],
    "wof:name": "entree plate: Qantas Airways",
    "wof:placetype": "custom",
    "wof:placetype_alt": "object"
  },
  "geometry": {"coordinates":[-122.386155,37.616357],"type":"Point"}
}
