{
  "type": "Feature",
  "properties": {
    "date:cessation_lower":"1954-12-31",
    "date:cessation_upper":"1954-12-31",
    "date:inception_lower":"1954-01-01",
    "date:inception_upper":"1954-01-01",
    "iso:country":"XX",
    "sfomuseum:accession_number":"2011.032.0339",
    "sfomuseum:category":"Photograph",
    "sfomuseum:collection":"Aviation Archive",
    "sfomuseum:creditline":"Transfer",
    "sfomuseum:date":"1954",
    "sfomuseum:daterange_end":"1954-12-31",
    "sfomuseum:daterange_start":"1954-01-01",
    "sfomuseum:description":"From attached handwritten note: \u201c03459 / 5-19-54 / Passenger terminal building\u201d. Black and white photographic negative depicting baggage handling equipment in the Terminal Building (later Central Terminal, now Terminal 2 / T2) at San Francisco International Airport (SFO); photograph taken on May 19, 1954.",
    "sfomuseum:media_ids":[
        1527822061
    ],
    "sfomuseum:medium":"negative",
    "sfomuseum:placetype":"object",
    "sfomuseum:subcategory":"Negative",
    "wof:name":"negative: San Francisco International Airport (SFO), Terminal Building construction",
    "wof:placetype":"venue"
},
  "geometry": {"coordinates":[-122.386155,37.616358],"type":"Point"}
}