{
  "type": "Feature",
  "properties": {
    "date:cessation_lower": "1950-01-01",
    "date:cessation_upper": "1959-12-31",
    "date:inception_lower": "1950-01-01",
    "date:inception_upper": "1959-12-31",
    "iso:country": "XX",
    "millsfield:images": [
      1527856143,
      1527856145,
      1527856147
    ],
    "millsfield:images_texts": [
      "If you would care to mail this Menu home\nor to a friend, just address it and give it to\nyour Clipper Steward or Stewardess.\nSi vous desirez envoyer ce Menu chez vous ou ¿\ndes amis, remettez-le simplement au Commis-\nsaire de Bord, ou a l'Hôtesse, qui s'en chargera.\nMESSAGE\nCOPYRIGHT 1949 P.A.A.. INC. PRINTED IN U.S.A.\nADDRESS ONLY\nADRESSE SEULEMENT",
      "The Presidenti\nBLUE RIBBON\nTRANSATLANTIC FLIGHT\nPAN AMERICAN WORLD AIRWAYS\nThe Worlds Most Experienced Airline",
      "on bread The President en route\nMENU\nPETIT DEJEUNER\nJus de Fruits\nDemi-Pamplemousse\nPetits Pains ou Toast\nEufs (de toutes manières)\navec\nJambon ou Bacon\nPains Danois\nBeurre\nThé\nCafé ou Café \"Sanka\"\nChocolat Chaud\nPAN AMERICAN WORLD AIRWAYS\nThe System of the Hying Clippers"
    ],
    "millsfield:images_texts_ids": [
      1527856143,
      1527856145,
      1527856147
    ],
    "millsfield:primary_image": 1527856145,
    "sfomuseum:accession_number": "2014.095.200",
    "sfomuseum:airline": "Pan American World Airways",
    "sfomuseum:category": "Passenger Amenity, Archive",
    "sfomuseum:collection": "Aviation Archive",
    "sfomuseum:creditline": "Gift of Thomas G. Dragges",
    "sfomuseum:date": "1950s",
    "sfomuseum:date_acquired": "2015-01-06",
    "sfomuseum:daterange_end": "1959-12-31",
    "sfomuseum:daterange_start": "1950-01-01",
    "sfomuseum:description": "Menu issued by Pan American World Airways, transatlantic routes; off-white cover with color illustration of waiter holding tray of food; breakfast menu items include eggs and bacon; no menu number; class: President (first); date: copyright 1949.",
    "sfomuseum:dimensions": "9 x 4 inches (22.9 x 10.2 cm)",
    "sfomuseum:media_ids": [
      1527856143,
      1527856145,
      1527856147
    ],
    "sfomuseum:medium": "paper, ink",
    "sfomuseum:placetype": "object",
    "sfomuseum:publication": ": , 1950s.",
    "sfomuseum:subcategory": "Menu",
    "wof:depicts": [
      1159286839,
      1159284989
    ],
    "wof:name": "menu: Pan American World Airways, President (first) class",
    "wof:placetype": "custom",
    "wof:placetype_alt": "object"
  },
  "geometry": {"coordinates":[-122.386155,37.616357],"type":"Point"}
}
