{
  "type": "Feature",
  "properties": {
    "date:cessation_lower": "1971-12-31",
    "date:cessation_upper": "1971-12-31",
    "date:inception_lower": "1971-01-01",
    "date:inception_upper": "1971-01-01",
    "iso:country": "XX",
    "sfomuseum:accession_number": "2005.132.042.024",
    "sfomuseum:airline": "Pacific Southwest Airlines (PSA)",
    "sfomuseum:category": "Scheduling / Ticketing",
    "sfomuseum:collection": "Aviation Archive",
    "sfomuseum:creditline": "Gift of the William Hough Collection",
    "sfomuseum:date": "1971",
    "sfomuseum:daterange_end": "1971-12-31",
    "sfomuseum:daterange_start": "1971-01-01",
    "sfomuseum:description": "Timetable issued by Pacific Southwest Airlines (PSA), effective September 17, 1971; seven page fold-out. The cover is orange with white and black lettering. The company logo is at the top. Nine destinations are listed at the bottom.",
    "sfomuseum:medium": "paper, ink",
    "sfomuseum:placetype": "object",
    "sfomuseum:subcategory": "Timetable",
    "wof:depicts": [
      1159284973
    ],
    "wof:name": "timetable: Pacific Southwest Airlines (PSA)",
    "wof:placetype": "venue"
  },
  "geometry": {"coordinates":[-122.386155,37.616357],"type":"Point"}
}
