{
  "type": "Feature",
  "properties": {
    "date:cessation_lower": "1980-01-01",
    "date:cessation_upper": "1980-12-31",
    "date:inception_lower": "1980-01-01",
    "date:inception_upper": "1980-12-31",
    "iso:country": "XX",
    "millsfield:images": [
      1527839845
    ],
    "millsfield:images_texts": [
      "GOLDEN WEST\nAIRLINES\nGOLDEN WEST\nSystem Timetable\nEFFECTIVE DECEMBER 14, 1980\nFEATURING De HAVILLAND DASH 7\nNEW SERVICE TO LAKE TAHOE—\nFROM LOS ANGELES, ORANGE COUNTY AND\nSAN DIEGO ... STARTING JAN. 28, 1981\nFLY THE NEW THE GOLDEN WEST:\nLOS ANGELES, ONTARIO, ORANGE COUNTY,\nSAN DIEGO, SANTA BARBARA, OXNARD,\nINYOKERN, PALMDALE, EDWARDS AFB"
    ],
    "millsfield:images_texts_ids": [
      1527839845
    ],
    "millsfield:primary_image": 1527839845,
    "sfomuseum:accession_number": "2008.108.348",
    "sfomuseum:aircraft": "de Havilland (Canada) DHC-7 Dash 7",
    "sfomuseum:airline": "Golden West Airlines",
    "sfomuseum:category": "Scheduling / Ticketing",
    "sfomuseum:collection": "Aviation Archive",
    "sfomuseum:creditline": "Gift of the William Hough Collection",
    "sfomuseum:date": "1980",
    "sfomuseum:date_acquired": "2008-11-10",
    "sfomuseum:daterange_end": "1980-12-31",
    "sfomuseum:daterange_start": "1980-01-01",
    "sfomuseum:description": "System timetable issued by Golden West Airlines, effective December 14, 1980; white and red cover with text “Featuring new De Havilland Dash 7 service” and illustration of four-engine aircraft.",
    "sfomuseum:dimensions": "9 x 4 inches (22.9 x 10.2 cm)",
    "sfomuseum:media_ids": [
      1527839845
    ],
    "sfomuseum:medium": "paper, ink",
    "sfomuseum:placetype": "object",
    "sfomuseum:publication": ": , 1980.",
    "sfomuseum:subcategory": "Timetable",
    "sfomuseum:subject": "Airlines -- Commercial -- Golden West",
    "wof:depicts": [
      1159290341,
      1159293743,
      1159292629,
      1159284453
    ],
    "wof:name": "timetable: Golden West Airlines",
    "wof:placetype": "custom",
    "wof:placetype_alt": [
      "object"
    ]
  },
  "geometry": {"coordinates":[-122.386155,37.616357],"type":"Point"}
}
