{
  "type": "Feature",
  "properties": {
    "date:cessation_lower": "1978-01-01",
    "date:cessation_upper": "1978-12-31",
    "date:inception_lower": "1978-01-01",
    "date:inception_upper": "1978-12-31",
    "iso:country": "XX",
    "millsfield:images": [
      1527835899
    ],
    "millsfield:images_texts": [
      "Australia-Asia-Europe\nREAD\nDOWN\nLOCAL\nTIMES\nMELBOURNE\nSYDNEY\nPORT MORESBY\nMANILA\nBANGKOK\nKARACHI\nROME\nFRANKFURT\nAMSTERDAM\n- No local traffic: SYD-MEL v.v.\n- From March 3, local times SYD and MEL\none hour earlier except as Note O\nFLIGHT NO.\nAIRCRAFT\nCLASS\nDAYS OPERATED\nAr.\n0930 0\n1420 2\n0840\n1135\n0840\n1135\nAr.\nAr.\nAr.\nAr.\nAr.\nAr.\nPR 212\nD10\nF-Y\nFR MO\n1115\n1225\n1330\n1805\nPR 202\nD8\nF-Y\nTH\nPR 284\nD8\nF-Y\nPR 284\nD8\nF-Y\nPR 822\nD10\nF-Y\nMO\nPR 824\nD10\nF-Y\nMO\n2000\n2230\n2330\nTU\n0235\n0335\n0700\n0800\n0955\n1045\n1150\nTU\n2000\n2230\n2330\nSA\n0235\n0335\n0700\n0800\n0955\n1045\n1150\nSA\nD - Local time in effect.\n2 - From March 3, arrival at 1520 H.\n3 - From November 19 to January 29 only, subject to government approval.\nPhilippine Airlines\nInternational Winter Schedule\nEffective: Nov. 1, 1978 to March 31, 1979"
    ],
    "millsfield:images_texts_ids": [
      1527835899
    ],
    "millsfield:primary_image": 1527835899,
    "sfomuseum:accession_number": "2009.122.529",
    "sfomuseum:airline": "Philippine Airlines",
    "sfomuseum:category": "Scheduling / Ticketing",
    "sfomuseum:collection": "Aviation Archive",
    "sfomuseum:creditline": "Gift of the William Hough Collection",
    "sfomuseum:date": "1978",
    "sfomuseum:date_acquired": "2010-06-08",
    "sfomuseum:daterange_end": "1978-12-31",
    "sfomuseum:daterange_start": "1978-01-01",
    "sfomuseum:description": "International timetable issued by Philippine Airlines, effective November 1, 1978 through March 31, 1979, winter service; two page double-sided fold-out card; white and green cover.",
    "sfomuseum:dimensions": "9 x 4 inches (22.9 x 10.2 cm)",
    "sfomuseum:media_ids": [
      1527835899
    ],
    "sfomuseum:medium": "paper, ink",
    "sfomuseum:placetype": "object",
    "sfomuseum:publication": ": , 1978.",
    "sfomuseum:subcategory": "Timetable",
    "wof:depicts": [
      1159287151,
      1159285015
    ],
    "wof:name": "timetable: Philippine Airlines, international winter schedule",
    "wof:placetype": "custom",
    "wof:placetype_alt": "object"
  },
  "geometry": {"coordinates":[-122.386155,37.616357],"type":"Point"}
}
