{
  "type": "Feature",
  "properties": {
    "date:cessation_lower": "1978-01-01",
    "date:cessation_upper": "1978-12-31",
    "date:inception_lower": "1978-01-01",
    "date:inception_upper": "1978-12-31",
    "iso:country": "XX",
    "millsfield:images": [
      1527843313
    ],
    "millsfield:primary_image": 1527843313,
    "sfomuseum:accession_number": "2008.108.356",
    "sfomuseum:airline": "Hawaiian Airlines",
    "sfomuseum:category": "Scheduling / Ticketing",
    "sfomuseum:collection": "Aviation Archive",
    "sfomuseum:creditline": "Gift of the William Hough Collection",
    "sfomuseum:date": "1978",
    "sfomuseum:date_acquired": "2008-11-10",
    "sfomuseum:daterange_end": "1978-12-31",
    "sfomuseum:daterange_start": "1978-01-01",
    "sfomuseum:description": "Pocket timetable issued by Hawaiian Air, effective April 30, 1978; six page double-sided fold-out; white cover with orange and blue logotype.",
    "sfomuseum:dimensions": "2 x 3 1/2 inches (5.1 x 8.9 cm)",
    "sfomuseum:media_ids": [
      1527843313
    ],
    "sfomuseum:medium": "paper, ink",
    "sfomuseum:placetype": "object",
    "sfomuseum:publication": ": , 1978.",
    "sfomuseum:subcategory": "Timetable",
    "sfomuseum:subject": "Airlines -- Commercial -- Hawaiian",
    "wof:depicts": [
      1159284489,
      1159287913
    ],
    "wof:name": "timetable: Hawaiian Air, pocket schedule",
    "wof:placetype": "venue"
  },
  "geometry": {"coordinates":[-122.386155,37.616357],"type":"Point"}
}
