{
  "type": "Feature",
  "properties": {
    "date:cessation_lower": "1939-12-31",
    "date:cessation_upper": "1939-12-31",
    "date:inception_lower": "1939-01-01",
    "date:inception_upper": "1939-01-01",
    "iso:country": "XX",
    "sfomuseum:accession_number": "2008.075.160 a b",
    "sfomuseum:category": "Philately",
    "sfomuseum:collection": "Aviation Archive",
    "sfomuseum:creditline": "Gift of Jon E. Krupnick",
    "sfomuseum:date": "09/05/1939",
    "sfomuseum:daterange_end": "1939-09-05",
    "sfomuseum:daterange_start": "1939-09-05",
    "sfomuseum:description": "Airmail flight cover for Pan American Airways, first survey flight to New Zealand, accompanied by information sheet (b); identified by donor.\ra. envelope: square wooden block cachet at upper left and on reverse at center, thick black ink with text \"First Flight PAA 1939 Canton Island\" and outline of island and PAA wing globe logo; postmarked September 5, 1939, Hawaii with football-shaped killer with 1 at center over green 20-cent stamp; addressed (typewritten) to Mr. \u0026 Mrs. Jas. Blair; return address typewritten \"D. C. Mucci  % Pan American Airways\"; cachet is over return address.\rb. information sheet: 8 1/2 x 11 with black text; additional information prepared by donor, including outbound and inbound stops; flight cover was received mounted to sheet with photo corners.",
    "sfomuseum:media_ids": [
      1527851845
    ],
    "sfomuseum:medium": "paper, ink",
    "sfomuseum:placetype": "object",
    "sfomuseum:subcategory": "Airmail Flight Cover",
    "wof:name": "airmail flight cover: Pan American Airways, Canton Island, first survey flight to New Zealand",
    "wof:placetype": "venue"
  },
  "geometry": {"coordinates":[-122.386155,37.616358],"type":"Point"}
}
