{
  "type": "Feature",
  "properties": {
    "date:cessation_lower":"1969-12-31",
    "date:cessation_upper":"1969-12-31",
    "date:inception_lower":"1969-01-01",
    "date:inception_upper":"1969-01-01",
    "iso:country":"XX",
    "sfomuseum:accession_number":"2009.046.028",
    "sfomuseum:airline":"Pacific Air Lines",
    "sfomuseum:category":"Insignia",
    "sfomuseum:collection":"Aviation Museum",
    "sfomuseum:creditline":"Gift of Tom Flickinger",
    "sfomuseum:date":"1969",
    "sfomuseum:daterange_end":"1969-12-31",
    "sfomuseum:daterange_start":"1969-01-01",
    "sfomuseum:description":"Silver captain\u2019s insignia wings; two stylized wings flank center circle; red enamel center with profile of eagle; \u201cPacific Air Lines\u201d printed in center of eagle. ",
    "sfomuseum:medium":"metal, enamel",
    "sfomuseum:placetype":"object",
    "sfomuseum:subcategory":"Uniform Wing(s), Flight Crew",
    "wof:depicts":[
        1159284947
    ],
    "wof:name":"flight officer wings: Pacific Air Lines",
    "wof:placetype":"venue"
},
  "geometry": {"coordinates":[-122.386155,37.616357],"type":"Point"}
}