{
  "type": "Feature",
  "properties": {
    "date:cessation_lower": "1950-01-01",
    "date:cessation_upper": "1959-12-31",
    "date:inception_lower": "1950-01-01",
    "date:inception_upper": "1959-12-31",
    "iso:country": "XX",
    "millsfield:images": [
      1527856239,
      1527856273
    ],
    "millsfield:images_texts": [
      "Pan American Management Club\nSAN FRANCISCO\nwelcomes\nVice President Harold M. Bixby\nVice President Erwin E. Balluder\nVice President Henry J. Friendly\nVice President Willis G. Lipscomb\nCover Design\nby Lillian Sader.\nOne of America's leading\nyoung artists, Miss Sader\ncombines a deft color touch\nwith a sensilive flair\nfor intricate design.\nFor the Orient\nshe has created\na unique tableau of\nthese familiar attractions-\nTypical Chinese Gateway\nDaibutsu—giant image of Buddha\nFujiyama\nThe Torii-formal Japanese Gateway\nGeisha Girl in Japanese Garden\nA Chinese Pagoda, Pedicab\nPhilippine Rice Field\nSampan and Siamese Temples\nComplete set of menus\nsuitable for framing may be\nobtained upon request\nmenu\nOCTOBER 17, 1950\nVin Grenache Rosé\nCelery\nItalían Salami\nAssorted Olives\nImported Swiss Cheese\nCarrots en Branch\nPickles\nSupreme of Melon Flavored with Fresh Mint\nChef's Special Salad\nBroiled Choice New York Cut Steak\nFresh Mushroom Sauce\nBaked Idaho Potato in Jacket\nFrench Cut String Beans au Beurre\nFrench Roll\nButter Gem\nCoffee\nDessert\nTea\nMilk\nPAN AMERICAN WORLD AIRWAYSE\nPRINTED IN U,S,A"
    ],
    "millsfield:images_texts_ids": [
      1527856239
    ],
    "millsfield:primary_image": 1527856273,
    "sfomuseum:accession_number": "2014.095.198",
    "sfomuseum:airline": "Pan American World Airways",
    "sfomuseum:artist": "Lillian Sader",
    "sfomuseum:category": "Passenger Amenity, Archive",
    "sfomuseum:collection": "Aviation Archive",
    "sfomuseum:creditline": "Gift of Thomas G. Dragges",
    "sfomuseum:date": "1950s",
    "sfomuseum:date_acquired": "2015-01-06",
    "sfomuseum:daterange_end": "1959-12-31",
    "sfomuseum:daterange_start": "1950-01-01",
    "sfomuseum:description": "Menu issued by Pan American World Airways for the Pan American Management Club of San Francisco, dated October 17, 1950; bi-fold postcard format; white background with color montage of East Asian scenes; menu items include broiled New York steak and mushroom sauce.",
    "sfomuseum:dimensions": "8 1/4 x 5 1/2 inches (21 x 14 cm)",
    "sfomuseum:media_ids": [
      1527856239,
      1527856273
    ],
    "sfomuseum:medium": "paper, ink",
    "sfomuseum:placetype": "object",
    "sfomuseum:publication": ": , 1950s.",
    "sfomuseum:subcategory": "Menu",
    "wof:depicts": [
      1159284989,
      1159286839
    ],
    "wof:name": "menu: Pan American World Airways",
    "wof:placetype": "custom",
    "wof:placetype_alt": "object"
  },
  "geometry": {"coordinates":[-122.386155,37.616357],"type":"Point"}
}
