{
  "type": "Feature",
  "properties": {
    "date:cessation_lower": "1977-01-01",
    "date:cessation_upper": "1977-12-31",
    "date:inception_lower": "1977-01-01",
    "date:inception_upper": "1977-12-31",
    "iso:country": "XX",
    "millsfield:images": [
      1527830241
    ],
    "millsfield:primary_image": 1527830241,
    "sfomuseum:accession_number": "2010.009.0138.078",
    "sfomuseum:airline": "JAL (Japan Air Lines)",
    "sfomuseum:category": "Photograph",
    "sfomuseum:collection": "Aviation Archive",
    "sfomuseum:creditline": "Gift of Thomas G. Dragges",
    "sfomuseum:date": "1977",
    "sfomuseum:date_acquired": "2010-11-29",
    "sfomuseum:daterange_end": "1977-12-31",
    "sfomuseum:daterange_start": "1977-01-01",
    "sfomuseum:description": "From set of 143 color slides, “Commercial accounts, slide presentation, 1977 West Coast version”, JAL (Japan Air Lines) publicity stills. In-flight scene depicting female flight attendant in kimono serving sake to couple.",
    "sfomuseum:dimensions": "2 x 2 inches (5.1 x 5.1 cm)",
    "sfomuseum:issues_held": "1988 (Jun-Dec), 1989 (Jan-Dec), 1990 (Jan, Feb, Apr, Jun-Oct).",
    "sfomuseum:media_ids": [
      1527830241
    ],
    "sfomuseum:medium": "slide film, paper, plastic",
    "sfomuseum:placetype": "object",
    "sfomuseum:publication": ": , 1977.",
    "sfomuseum:subcategory": "Slide",
    "sfomuseum:subject": "Airlines -- Commercial -- Japan Air Lines (JAL).",
    "wof:depicts": [
      1159285785,
      1159288505
    ],
    "wof:name": "slide: JAL (Japan Air Lines), publicity still",
    "wof:placetype": "venue"
  },
  "geometry": {"coordinates":[-122.386155,37.616357],"type":"Point"}
}
