{
  "type": "Feature",
  "properties": {
    "date:cessation_lower":"1977-12-31",
    "date:cessation_upper":"1977-12-31",
    "date:inception_lower":"1977-01-01",
    "date:inception_upper":"1977-01-01",
    "iso:country":"XX",
    "sfomuseum:accession_number":"2010.009.0138.078",
    "sfomuseum:category":"Photograph",
    "sfomuseum:collection":"Aviation Archive",
    "sfomuseum:creditline":"Gift of Thomas G. Dragges",
    "sfomuseum:date":"1977",
    "sfomuseum:daterange_end":"1977-12-31",
    "sfomuseum:daterange_start":"1977-01-01",
    "sfomuseum:description":"From set of 143 color slides, \u201cCommercial accounts, slide presentation, 1977 West Coast version\u201d, JAL (Japan Air Lines) publicity stills. In-flight scene depicting female flight attendant in kimono serving sake to couple.",
    "sfomuseum:medium":"slide film, paper, plastic",
    "sfomuseum:placetype":"object",
    "sfomuseum:subcategory":"Slide",
    "wof:name":"slide: JAL (Japan Air Lines), publicity still",
    "wof:placetype":"venue"
},
  "geometry": {"coordinates":[-122.386155,37.616358],"type":"Point"}
}