{
  "type": "Feature",
  "properties": {
    "date:cessation_lower": "2000-12-31",
    "date:cessation_upper": "2000-12-31",
    "date:inception_lower": "2000-01-01",
    "date:inception_upper": "2000-01-01",
    "iso:country": "XX",
    "sfomuseum:accession_number": "2007.056.063",
    "sfomuseum:author": "Endres, GËunter G.",
    "sfomuseum:callnumber": "TL686.A43 E53 2000",
    "sfomuseum:category": "Book",
    "sfomuseum:collection": "Aviation Library",
    "sfomuseum:creditline": "Purchase",
    "sfomuseum:date": "2000",
    "sfomuseum:daterange_end": "2000-12-31",
    "sfomuseum:daterange_start": "2000-01-01",
    "sfomuseum:description": "128 p. : ill.",
    "sfomuseum:medium": "paper, ink",
    "sfomuseum:placetype": "object",
    "sfomuseum:publisher": "Airlife",
    "sfomuseum:publisher_location": "Shrewsbury, England",
    "sfomuseum:series": "Airlife's airliners ; 10",
    "sfomuseum:subcategory": "Book",
    "sfomuseum:subject": "Airbus (Jet transport) History.",
    "wof:depicts": [
      1159289401,
      1159293829
    ],
    "wof:name": "Airbus A310",
    "wof:placetype": "venue"
  },
  "geometry": {"coordinates":[-122.386155,37.616357],"type":"Point"}
}
