{
  "type": "Feature",
  "properties": {
    "date:cessation_lower": "2012-01-01",
    "date:cessation_upper": "2012-12-31",
    "date:inception_lower": "2012-01-01",
    "date:inception_upper": "2012-12-31",
    "iso:country": "XX",
    "millsfield:images": [
      1527858111,
      1527858113,
      1527858115,
      1527858119,
      1527858121,
      1527858123,
      1527858125
    ],
    "millsfield:primary_image": 1527858111,
    "sfomuseum:accession_number": "2013.069.001 a b",
    "sfomuseum:aircraft": "Lockheed L-18 Lodestar",
    "sfomuseum:category": "Décor",
    "sfomuseum:collection": "Aviation Museum",
    "sfomuseum:creditline": "Gift of 1940 Air Terminal Museum, Houston, Texas",
    "sfomuseum:date": "2012",
    "sfomuseum:date_acquired": "2013-07-16",
    "sfomuseum:daterange_end": "2012-12-31",
    "sfomuseum:daterange_start": "2012-01-01",
    "sfomuseum:description": "a. Silver Lockheed Model 14 Super Electra model with two vertical stabilizers, two engines each with three propellers on wings.\rb. Brown rectangular base with brushed metal arm.",
    "sfomuseum:dimensions": "5 1/2 x 11 x 8 1/2 inches (14 x 27.9 x 21.6 cm)",
    "sfomuseum:media_ids": [
      1527858111,
      1527858113,
      1527858115,
      1527858119,
      1527858121,
      1527858123,
      1527858125
    ],
    "sfomuseum:medium": "wood, metal, pigment",
    "sfomuseum:placetype": "object",
    "sfomuseum:publication": ": , 2012.",
    "sfomuseum:subcategory": "Table Top / Desk Set",
    "wof:depicts": [
      1159291111,
      1159293697
    ],
    "wof:name": "model airplane: Lockheed Model 14 Super Electra",
    "wof:placetype": "venue"
  },
  "geometry": {"coordinates":[-122.386155,37.616357],"type":"Point"}
}
