{
  "type": "Feature",
  "properties": {
    "iso:country": "XX",
    "sfomuseum:accession_number": "2012.147.125",
    "sfomuseum:category": "Passenger Amenity",
    "sfomuseum:collection": "Aviation Museum",
    "sfomuseum:creditline": "Gift of the Captain John B. Russell Family",
    "sfomuseum:description": "Silver double-wing pin with circular shape on center, small black script “Wings” and small “Sunglasses” on center with “Bausch,” “\u0026 Lomb” on top and bottom edge; straight pin with hook closure on back.",
    "sfomuseum:dimensions": "2 3/4 x 1 1/4 inches (7 x 3.2 cm)",
    "sfomuseum:maker": "Stoffel Seals",
    "sfomuseum:medium": "plastic, ink",
    "sfomuseum:placetype": "object",
    "sfomuseum:subcategory": "Children’s Amenity, Toys",
    "wof:name": "children's souvenir wings: Bausch and Lomb",
    "wof:placetype": "venue"
  },
  "geometry": {"coordinates":[-122.386155,37.616357],"type":"Point"}
}
