{
  "type": "Feature",
  "properties": {
    "date:cessation_lower": "1980-01-01",
    "date:cessation_upper": "1989-12-31",
    "date:inception_lower": "1980-01-01",
    "date:inception_upper": "1989-12-31",
    "iso:country": "XX",
    "millsfield:images": [
      1763379411
    ],
    "millsfield:primary_image": 1763379411,
    "sfomuseum:accession_number": "2012.147.125",
    "sfomuseum:category": "Passenger Amenity, Museum",
    "sfomuseum:collection": "Aviation Museum",
    "sfomuseum:creditline": "Gift of the Captain John B. Russell Family",
    "sfomuseum:date": "1980s",
    "sfomuseum:date_acquired": "2014-04-17",
    "sfomuseum:daterange_end": "1989-12-31",
    "sfomuseum:daterange_start": "1980-01-01",
    "sfomuseum:description": "Souvenir children’s wing issued by Bausch and Lomb; silver wings pin with logotype and “Wings” at center; straight pin with hook closure on back.",
    "sfomuseum:dimensions": "2 3/4 x 1 1/4 inches (7 x 3.2 cm)",
    "sfomuseum:maker": "Stoffel Seals",
    "sfomuseum:medium": "plastic, ink",
    "sfomuseum:placetype": "object",
    "sfomuseum:publication": ": , 1980s.",
    "sfomuseum:subcategory": "Children’s Amenity, Toys",
    "wof:name": "children's souvenir wings: Bausch and Lomb",
    "wof:placetype": "custom",
    "wof:placetype_alt": "object"
  },
  "geometry": {"coordinates":[-122.386155,37.616357],"type":"Point"}
}
