{
  "type": "Feature",
  "properties": {
    "date:cessation_lower": "1995-01-01",
    "date:cessation_upper": "1995-12-31",
    "date:inception_lower": "1995-01-01",
    "date:inception_upper": "1995-12-31",
    "iso:country": "XX",
    "millsfield:images": [
      1527848489
    ],
    "millsfield:primary_image": 1527848489,
    "sfomuseum:accession_number": "2011.061.0526",
    "sfomuseum:airline": "LOT Polish Airlines",
    "sfomuseum:category": "Promotional",
    "sfomuseum:collection": "Aviation Archive",
    "sfomuseum:creditline": "Gift of the Frank J. Lichtanski Collection",
    "sfomuseum:date": "c. 1995",
    "sfomuseum:daterange_end": "2000-12-31",
    "sfomuseum:daterange_start": "1990-01-01",
    "sfomuseum:description": "Promotional brochure issued by LOT (Polish Airlines), titled “Wir setzen Zeichen fur das nachste Jahrtausend” [”We set the standard for the next millennium”]; blue and white cover with close-up image depicting frontal view of aircraft nose; folded brochure contains text and route map.",
    "sfomuseum:dimensions": "8 1/4 x 4 inches (21 x 10.2 cm)",
    "sfomuseum:media_ids": [
      1527848489
    ],
    "sfomuseum:medium": "paper, ink",
    "sfomuseum:placetype": "object",
    "sfomuseum:subcategory": "Brochure, Airline",
    "wof:depicts": [
      1159284705
    ],
    "wof:name": "brochure: LOT (Polish Airlines)",
    "wof:placetype": "venue"
  },
  "geometry": {"coordinates":[-122.386155,37.616357],"type":"Point"}
}
