{
  "type": "Feature",
  "properties": {
    "date:cessation_lower": "1960-01-01",
    "date:cessation_upper": "1960-12-31",
    "date:inception_lower": "1960-01-01",
    "date:inception_upper": "1960-12-31",
    "iso:country": "XX",
    "millsfield:images": [
      1527819269
    ],
    "millsfield:primary_image": 1527819269,
    "sfomuseum:accession_number": "2011.061.0644",
    "sfomuseum:airline": "Australian National Airways",
    "sfomuseum:category": "Promotional",
    "sfomuseum:collection": "Aviation Archive",
    "sfomuseum:creditline": "Gift of the Frank J. Lichtanski Collection",
    "sfomuseum:date": "c. 1960",
    "sfomuseum:date_acquired": "2011-08-02",
    "sfomuseum:daterange_end": "1965-12-31",
    "sfomuseum:daterange_start": "1955-01-01",
    "sfomuseum:description": "Luggage label promoting Australian National Airways; rectangular shape with rounded corners, yellow and blue background with “ANA” airline name over globe.",
    "sfomuseum:dimensions": "3 x 4 inches (7.6 x 10.2 cm)",
    "sfomuseum:media_ids": [
      1527819269
    ],
    "sfomuseum:medium": "paper, ink, adhesive",
    "sfomuseum:placetype": "object",
    "sfomuseum:publication": ": , c. 1960.",
    "sfomuseum:subcategory": "Luggage Label",
    "wof:depicts": [
      1159283945
    ],
    "wof:name": "luggage label: Australian National Airways",
    "wof:placetype": "venue"
  },
  "geometry": {"coordinates":[-122.386155,37.616357],"type":"Point"}
}
