{
  "type": "Feature",
  "properties": {
    "date:cessation_lower":"1934-12-31",
    "date:cessation_upper":"1934-12-31",
    "date:inception_lower":"1934-01-01",
    "date:inception_upper":"1934-01-01",
    "iso:country":"XX",
    "millsfield:images":[
        1527831785
    ],
    "sfomuseum:accession_number":"2008.075.033",
    "sfomuseum:category":"Philately",
    "sfomuseum:collection":"Aviation Archive",
    "sfomuseum:creditline":"Gift of Jon E. Krupnick",
    "sfomuseum:date":"01/11/1934",
    "sfomuseum:daterange_end":"1934-01-11",
    "sfomuseum:daterange_start":"1934-01-11",
    "sfomuseum:description":"Airmail flight cover, First U.S. Navy Squadron Flight, San Francisco - Hawaii, January 10, 1934; two-line blue cachet on front at upper left, \"Navy VP Squadron 10-F Calif. to Hawaii Flight,\" with printed brown shield, \"The Nation's First Line of Defense\"; five-line cachet on reverse; postmarked January 11, 1934 from picket ship U.S.S. Breese, with cancellation mark \"Lat. 29-40 N Long. 140-45 W\"; blue 3-cent postage stamp adhered upside down.",
    "sfomuseum:media_ids":[
        1527831785
    ],
    "sfomuseum:medium":"paper, ink",
    "sfomuseum:placetype":"object",
    "sfomuseum:subcategory":"Airmail Flight Cover",
    "wof:name":"airmail flight cover: First U.S. Navy Squadron flight, San Francisco - Hawaii, January 10, 1934",
    "wof:placetype":"venue"
},
  "geometry": {"coordinates":[-122.386155,37.616358],"type":"Point"}
}