{
  "type": "Feature",
  "properties": {
    "date:cessation_lower": "2002-01-01",
    "date:cessation_upper": "2002-12-31",
    "date:inception_lower": "2002-01-01",
    "date:inception_upper": "2002-12-31",
    "iso:country": "XX",
    "sfomuseum:accession_number": "2004.004.052",
    "sfomuseum:author": "Ciotti, Paul",
    "sfomuseum:callnumber": "TL540.M227 C56 2002",
    "sfomuseum:category": "Book",
    "sfomuseum:collection": "Aviation Library",
    "sfomuseum:creditline": "Purchase",
    "sfomuseum:date": "2002",
    "sfomuseum:date_acquired": "2004-12-31",
    "sfomuseum:daterange_end": "2002-12-31",
    "sfomuseum:daterange_start": "2002-01-01",
    "sfomuseum:description": "259 p. ; 24 cm.",
    "sfomuseum:description_library": "259 p. ; 24 cm.",
    "sfomuseum:medium": "paper, ink",
    "sfomuseum:notes_library": "Includes bibliographical references (p. 231-251) and index.",
    "sfomuseum:placetype": "object",
    "sfomuseum:publication": "San Francisco: Encounter Books, 2002.",
    "sfomuseum:publisher": "Encounter Books",
    "sfomuseum:publisher_location": "San Francisco",
    "sfomuseum:subcategory": "Book",
    "sfomuseum:subject": "MacCready, Paul B.",
    "wof:name": "More with less: Paul MacCready and the dream of efficient flight",
    "wof:placetype": "venue"
  },
  "geometry": {"coordinates":[-122.386155,37.616357],"type":"Point"}
}
