{
  "type": "Feature",
  "properties": {
    "date:cessation_lower": "1935-01-01",
    "date:cessation_upper": "1935-12-31",
    "date:inception_lower": "1935-01-01",
    "date:inception_upper": "1935-12-31",
    "iso:country": "XX",
    "sfomuseum:accession_number": "2000.160.1369",
    "sfomuseum:author": "Reaves, John S., ed.",
    "sfomuseum:callnumber": "TL512 .A45 1935 SC",
    "sfomuseum:category": "Book",
    "sfomuseum:collection": "Aviation Library",
    "sfomuseum:creditline": "The Tony Bill Aviation Library Collection",
    "sfomuseum:date": "c. 1935",
    "sfomuseum:date_acquired": "1999-05-18",
    "sfomuseum:daterange_end": "1940-12-31",
    "sfomuseum:daterange_start": "1930-01-01",
    "sfomuseum:description": "v. illus. (part col.; incl. maps, plans) 23 cm.",
    "sfomuseum:description_library": "v. illus. (part col.; incl. maps, plans) 23 cm.",
    "sfomuseum:medium": "paper, ink",
    "sfomuseum:notes_library": "Contains data of special interest to private airplane owners, airport section, registration of private aircraft insignia, record holders, rules and regulations for sport flying contests, etc.Editors: 1935-   John S. Reaves and others.",
    "sfomuseum:placetype": "object",
    "sfomuseum:publication": "New York: Air Pilots Register Co., c. 1935.",
    "sfomuseum:publisher": "Air Pilots Register Co.",
    "sfomuseum:publisher_location": "New York",
    "sfomuseum:subcategory": "Book",
    "sfomuseum:subject": "Aeronautics.Aeronautics United States.Airports United States.",
    "wof:name": "The air pilots register",
    "wof:placetype": "venue"
  },
  "geometry": {"coordinates":[-122.386155,37.616357],"type":"Point"}
}
