{
  "type": "Feature",
  "properties": {
    "date:cessation_lower": "1942-01-01",
    "date:cessation_upper": "1942-12-31",
    "date:inception_lower": "1942-01-01",
    "date:inception_upper": "1942-12-31",
    "iso:country": "XX",
    "loc:named_authorities": {
      "n79023147": "Great Britain"
    },
    "loc:subject_heading": {
      "sh85056605": "Great Britain"
    },
    "sfomuseum:accession_number": "2000.160.0491",
    "sfomuseum:author": "Kennerly, Byron",
    "sfomuseum:callnumber": "D786 .K46 1942",
    "sfomuseum:category": "Book",
    "sfomuseum:collection": "Aviation Library",
    "sfomuseum:creditline": "The Tony Bill Aviation Library Collection",
    "sfomuseum:date": "1942",
    "sfomuseum:daterange_end": "1942-12-31",
    "sfomuseum:daterange_start": "1942-01-01",
    "sfomuseum:description": "xviii p., 1 æ., 271 p. plates, ports. 23 cm.",
    "sfomuseum:medium": "paper, ink",
    "sfomuseum:placetype": "object",
    "sfomuseum:publication": "New York; London: Harper \u0026 Brothers, 1942.",
    "sfomuseum:publisher": "Harper \u0026 Brothers",
    "sfomuseum:publisher_location": "New York; London",
    "sfomuseum:subcategory": "Book",
    "sfomuseum:subject": "Great Britain. Royal Air Force. Eagle Squadron.World War, 1939-1945 Aerial operations, British.",
    "wof:name": "The Eagles roar!",
    "wof:placetype": "venue"
  },
  "geometry": {"coordinates":[-122.386155,37.616357],"type":"Point"}
}
