{
  "type": "Feature",
  "properties": {
    "date:cessation_lower": "1960-01-01",
    "date:cessation_upper": "1969-12-31",
    "date:inception_lower": "1960-01-01",
    "date:inception_upper": "1969-12-31",
    "iso:country": "XX",
    "millsfield:images": [
      1527835029
    ],
    "millsfield:images_texts": [
      "ANGLERS PARADISE\nFIRST\n• • NCA\nPROP-JETS IN\nALASKA\nKATMAI - VALLEY OF 10,000 SMOKES\nAIRLINES: ING\nANCHORAGE, ALASKA"
    ],
    "millsfield:images_texts_ids": [
      1527835029
    ],
    "millsfield:primary_image": 1527835029,
    "sfomuseum:accession_number": "2012.149.1352",
    "sfomuseum:airline": "Northern Consolidated Airlines",
    "sfomuseum:category": "Promotional, Archive",
    "sfomuseum:collection": "Aviation Archive",
    "sfomuseum:creditline": "Gift of the Captain John B. Russell Family",
    "sfomuseum:date": "1960s",
    "sfomuseum:date_acquired": "2013-05-31",
    "sfomuseum:daterange_end": "1960-12-31",
    "sfomuseum:daterange_start": "1960-01-01",
    "sfomuseum:description": "Luggage label promoting Northern Consolidated Airlines; red oval shape with text, “Anglers Paradise / First Prop-Jets in Alaska / Katmai - Valley of 10,000 Smokes” and illustrations of fish and airplane in flight.",
    "sfomuseum:dimensions": "3 1/2 x 5 1/2 inches (8.9 x 14 cm)",
    "sfomuseum:media_ids": [
      1527835029
    ],
    "sfomuseum:medium": "paper, ink, adhesive",
    "sfomuseum:placetype": "object",
    "sfomuseum:publication": ": , 1960s.",
    "sfomuseum:subcategory": "Luggage Label",
    "wof:depicts": [
      1159286971,
      1159284903
    ],
    "wof:name": "luggage label: Northern Consolidated Airlines",
    "wof:placetype": "custom",
    "wof:placetype_alt": "object"
  },
  "geometry": {"coordinates":[-122.386155,37.616357],"type":"Point"}
}
