{
  "type": "Feature",
  "properties": {
    "date:cessation_lower": "1936-01-01",
    "date:cessation_upper": "1936-12-31",
    "date:inception_lower": "1936-01-01",
    "date:inception_upper": "1936-12-31",
    "iso:country": "XX",
    "loc:named_authorities": [
      "n50080338"
    ],
    "millsfield:images": [
      1729565297
    ],
    "millsfield:primary_image": 1729565297,
    "sfomuseum:accession_number": "2006.025.008",
    "sfomuseum:aircraft": "Douglas DC-2",
    "sfomuseum:airline": "Transcontinental \u0026 Western Air",
    "sfomuseum:category": "Photograph",
    "sfomuseum:collection": "Aviation Archive",
    "sfomuseum:creditline": "Gift of Denis Neumann",
    "sfomuseum:date": "c. 1936",
    "sfomuseum:date_acquired": "2006-05-31",
    "sfomuseum:daterange_end": "1941-12-31",
    "sfomuseum:daterange_start": "1931-01-01",
    "sfomuseum:description": "Black and white photograph depicting Transcontinental \u0026 Western Air (TWA) flight captain Harold Neumann (upper right), Bob Springer (upper left), Frances E. Ice (sp?; lower left) and Frank Leasure (sp?; lower right) posing on stairway next to plane (DC-2); signatures near each of persons; \"TWA, The Lindbergh Line\" on door.",
    "sfomuseum:dimensions": "10 x 8 inches (25.4 x 20.3 cm)",
    "sfomuseum:medium": "photograph, ink",
    "sfomuseum:placetype": "object",
    "sfomuseum:publication": "New York: TWA Master Executive Council, c. 1936.",
    "sfomuseum:publisher": "TWA Master Executive Council",
    "sfomuseum:publisher_location": "New York",
    "sfomuseum:subcategory": "Print, Photograph",
    "sfomuseum:subject": "Trans World Airlines.",
    "wof:depicts": [
      1159290415,
      1159285395
    ],
    "wof:name": "photograph: Transcontinental \u0026 Western Air (TWA), Douglas DC-2 and flight crew",
    "wof:placetype": "venue"
  },
  "geometry": {"coordinates":[-122.386155,37.616357],"type":"Point"}
}
