{
  "type": "Feature",
  "properties": {
    "date:cessation_lower":"1940-12-31",
    "date:cessation_upper":"1940-12-31",
    "date:inception_lower":"1930-01-01",
    "date:inception_upper":"1930-01-01",
    "iso:country":"XX",
    "sfomuseum:accession_number":"2008.056.0178",
    "sfomuseum:category":"Promotional",
    "sfomuseum:collection":"Aviation Archive",
    "sfomuseum:creditline":"Gift of Jon E. Krupnick",
    "sfomuseum:date":"c. 1935",
    "sfomuseum:daterange_end":"1940-12-31",
    "sfomuseum:daterange_start":"1930-01-01",
    "sfomuseum:description":"20-page brochure for Pratt & Whitney Aircraft Company's Wasp and Hornet engines. Includes profiles on aviators such as Amelia Earhart, James H. Doolittle, Mae Haizlip, Roscoe Turner and James Haizlip, James J. Mattern, Bennet H. Griffin, James Wedell, and airlines and military clients; with black and white photographic images and illustrations.",
    "sfomuseum:medium":"ink, paper",
    "sfomuseum:placetype":"object",
    "sfomuseum:subcategory":"Brochure, Aircraft",
    "wof:name":"brochure: Pratt & Whitney, Wasp and Hornet engines",
    "wof:placetype":"venue"
},
  "geometry": {"coordinates":[-122.386155,37.616358],"type":"Point"}
}