{
  "type": "Feature",
  "properties": {
    "date:cessation_lower": "2003-01-01",
    "date:cessation_upper": "2003-12-31",
    "date:inception_lower": "2003-01-01",
    "date:inception_upper": "2003-12-31",
    "isbn:number": "0071427392 alk. paper), 9780071427395 alk. paper), 0071427406 alk. paper), 9780071427401 alk. paper)",
    "iso:country": "XX",
    "sfomuseum:accession_number": "2004.004.049",
    "sfomuseum:author": "Boll창ee, L창eon",
    "sfomuseum:callnumber": "TL540.W7 B67 2003",
    "sfomuseum:category": "Book",
    "sfomuseum:collection": "Aviation Library",
    "sfomuseum:creditline": "Collection of SFO Museum",
    "sfomuseum:date": "c. 2003",
    "sfomuseum:date_acquired": "2004-12-31",
    "sfomuseum:daterange_end": "2008-12-31",
    "sfomuseum:daterange_start": "1998-01-01",
    "sfomuseum:description": "viii, 75 p. : ill. ; 29 x 35 cm.",
    "sfomuseum:description_library": "viii, 75 p. : ill. ; 29 x 35 cm.",
    "sfomuseum:medium": "paper, ink",
    "sfomuseum:placetype": "object",
    "sfomuseum:publication": "New York: McGraw-Hill, c. 2003.",
    "sfomuseum:publisher": "McGraw-Hill",
    "sfomuseum:publisher_location": "New York",
    "sfomuseum:series": "An Aviation Week book",
    "sfomuseum:subcategory": "Book",
    "sfomuseum:subject": "Wright, Wilbur, 1867-1912 Travel France.",
    "wof:name": "Wilbur Wright's flights in France: L창eon Boll창ee's photographic record, 1908-1909",
    "wof:placetype": "custom",
    "wof:placetype_alt": "object"
  },
  "geometry": {"coordinates":[-122.386155,37.616357],"type":"Point"}
}
