{
  "type": "Feature",
  "properties": {
    "date:cessation_lower": "1936-12-31",
    "date:cessation_upper": "1936-12-31",
    "date:inception_lower": "1936-01-01",
    "date:inception_upper": "1936-01-01",
    "iso:country": "XX",
    "millsfield:images": [
      1527851841
    ],
    "sfomuseum:accession_number": "2008.075.154 a b",
    "sfomuseum:airline": "Pan American Airways  (Pan American World Airways)",
    "sfomuseum:category": "Philately",
    "sfomuseum:collection": "Aviation Archive",
    "sfomuseum:creditline": "Gift of Jon E. Krupnick",
    "sfomuseum:date": "01/05/1936",
    "sfomuseum:daterange_end": "1936-01-05",
    "sfomuseum:daterange_start": "1936-01-05",
    "sfomuseum:description": "Airmail flight cover, Pan American Airways, Westbound from Camden, New Jersey to Guam, January 5, 1936; identified by donor with additional information: \"Service was suspended due to mechanical problems of needing more power in the engines. Service was not resumed until February 14, 1936. Did not leave San Francisco until February 23\";\ra. cover: two postmarks on front: January 5, 1936, in Camden, New Jersey with football-shaped “1” cancellation mark over two 25-cent stamps; one illegible backstamp; Red Cross Christmas stamp on reverse; addressed to Mrs. E. Goodbody; stamped, \"Via Air Mail\" on front.\rb. information sheet: 8 1/2 x 11 with black text; additional information prepared by donor; flight cover was received mounted to sheet with photo corners.",
    "sfomuseum:media_ids": [
      1527851841
    ],
    "sfomuseum:medium": "paper, ink",
    "sfomuseum:placetype": "object",
    "sfomuseum:subcategory": "Airmail Flight Cover",
    "wof:depicts": [
      1159284991
    ],
    "wof:name": "airmail flight cover: Pan American Airways, Westbound from Camden, New Jersey to Guam, January 5, 1936",
    "wof:placetype": "venue"
  },
  "geometry": {"coordinates":[-122.386155,37.616357],"type":"Point"}
}
