{
  "type": "Feature",
  "properties": {
    "date:cessation_lower": "1936-01-05",
    "date:cessation_upper": "1936-01-05",
    "date:inception_lower": "1936-01-05",
    "date:inception_upper": "1936-01-05",
    "iso:country": "XX",
    "millsfield:images": [
      1527851841
    ],
    "millsfield:images_texts": [
      "Phila. Pou. AS.A.\nJAN, 5\nseverabbin\nVIA AIR MAIL\nMas E. good body\nC AM DA\n11.5. Naval Norpital\nJAN 5 1\nJuam\n1 PM\nMi\n1936"
    ],
    "millsfield:images_texts_ids": [
      1527851841
    ],
    "millsfield:primary_image": 1527851841,
    "sfomuseum:accession_number": "2008.075.154 a b",
    "sfomuseum:airline": "Pan American Airways",
    "sfomuseum:category": "Philately",
    "sfomuseum:collection": "Aviation Archive",
    "sfomuseum:creditline": "Gift of Jon E. Krupnick",
    "sfomuseum:date": "01/05/1936",
    "sfomuseum:date_acquired": "2008-12-31",
    "sfomuseum:daterange_end": "1936-01-05",
    "sfomuseum:daterange_start": "1936-01-05",
    "sfomuseum:description": "Airmail flight cover, Pan American Airways, Westbound from Camden, New Jersey to Guam, January 5, 1936; identified by donor with additional information: \"Service was suspended due to mechanical problems of needing more power in the engines. Service was not resumed until February 14, 1936. Did not leave San Francisco until February 23\";\ra. cover: two postmarks on front: January 5, 1936, in Camden, New Jersey with football-shaped “1” cancellation mark over two 25-cent stamps; one illegible backstamp; Red Cross Christmas stamp on reverse; addressed to Mrs. E. Goodbody; stamped, \"Via Air Mail\" on front.\rb. information sheet: 8 1/2 x 11 with black text; additional information prepared by donor; flight cover was received mounted to sheet with photo corners.",
    "sfomuseum:dimensions": "3 1/2 x 5 1/2 inches (8.9 x 14 cm)",
    "sfomuseum:issues_held": "\r",
    "sfomuseum:media_ids": [
      1527851841
    ],
    "sfomuseum:medium": "paper, ink",
    "sfomuseum:placetype": "object",
    "sfomuseum:publication": ": , 01/05/1936.",
    "sfomuseum:subcategory": "Airmail Flight Cover",
    "sfomuseum:subject": "Airlines -- Commercial -- Pan American Airways",
    "wof:depicts": [
      1159284991,
      1159286839
    ],
    "wof:name": "airmail flight cover: Pan American Airways, Westbound from Camden, New Jersey to Guam, January 5, 1936",
    "wof:placetype": "custom",
    "wof:placetype_alt": [
      "object"
    ]
  },
  "geometry": {"coordinates":[-122.386155,37.616357],"type":"Point"}
}
