{
  "type": "Feature",
  "properties": {
    "date:cessation_lower": "1988-01-01",
    "date:cessation_upper": "1988-12-31",
    "date:inception_lower": "1988-01-01",
    "date:inception_upper": "1988-12-31",
    "iso:country": "XX",
    "millsfield:images": [
      1527835487
    ],
    "sfomuseum:accession_number": "2006.059.232",
    "sfomuseum:airline": "TWA (Trans World Airlines)",
    "sfomuseum:category": "Scheduling / Ticketing",
    "sfomuseum:collection": "Aviation Archive",
    "sfomuseum:creditline": "Gift of the Paul Edward Fair Estate",
    "sfomuseum:date": "1988",
    "sfomuseum:daterange_end": "1988-12-31",
    "sfomuseum:daterange_start": "1988-01-01",
    "sfomuseum:description": "Timetable issued by TWA (Trans World Airlines), effective October 30, 1988. White cover with pattern of red logos; includes Trans World Express Service and route maps.",
    "sfomuseum:dimensions": "9 x 4 inches (22.9 x 10.2 cm)",
    "sfomuseum:media_ids": [
      1527835487
    ],
    "sfomuseum:medium": "paper, ink",
    "sfomuseum:placetype": "object",
    "sfomuseum:subcategory": "Timetable",
    "sfomuseum:subject": "Airlines -- Commercial -- TWA (Trans World Airlines)\rAirlines -- timetables",
    "wof:depicts": [
      1159285393
    ],
    "wof:name": "timetable: TWA (Trans World Airlines)",
    "wof:placetype": "venue"
  },
  "geometry": {"coordinates":[-122.386155,37.616357],"type":"Point"}
}
