{
  "type": "Feature",
  "properties": {
    "date:cessation_lower": "1940-01-01",
    "date:cessation_upper": "1949-12-31",
    "date:inception_lower": "1940-01-01",
    "date:inception_upper": "1949-12-31",
    "iso:country": "XX",
    "sfomuseum:accession_number": "2012.065.315",
    "sfomuseum:airline": "Inland Airways",
    "sfomuseum:category": "Promotional",
    "sfomuseum:collection": "Aviation Museum",
    "sfomuseum:creditline": "Gift of Thomas G. Dragges",
    "sfomuseum:date": "1940s",
    "sfomuseum:date_acquired": "2013-03-21",
    "sfomuseum:daterange_end": "1949-12-31",
    "sfomuseum:daterange_start": "1940-01-01",
    "sfomuseum:description": "Matchbook issued by Inland Airways; white cover with servicemark; airline phone numbers on saddle; text, “Daily Flights Seattle-Walla Walla Richland - Pasco - Kennewick Speed Comfort Safety Serving Washington’s Inland Empire” on reverse; logotype and wings flanking geographic outline of Washington state on interior; red-tipped matches. ",
    "sfomuseum:dimensions": "2 x 1 1/2 x 1/4 inches (5.1 x 3.8 x .6 cm)",
    "sfomuseum:maker": "Atlas Match Corporation",
    "sfomuseum:medium": "cardboard, ink, phosphorus, metal",
    "sfomuseum:placetype": "object",
    "sfomuseum:publication": ": , 1940s.",
    "sfomuseum:subcategory": "Matchbook / Matchbox",
    "wof:depicts": [
      1159285911,
      1159288597
    ],
    "wof:name": "matchbook: Inland Airways",
    "wof:placetype": "custom",
    "wof:placetype_alt": "object"
  },
  "geometry": {"coordinates":[-122.386155,37.616357],"type":"Point"}
}
