{
  "type": "Feature",
  "properties": {
    "date:cessation_lower":"1949-12-31",
    "date:cessation_upper":"1949-12-31",
    "date:inception_lower":"1940-01-01",
    "date:inception_upper":"1940-01-01",
    "iso:country":"XX",
    "sfomuseum:accession_number":"2012.065.315",
    "sfomuseum:category":"Promotional",
    "sfomuseum:collection":"Aviation Museum",
    "sfomuseum:creditline":"Gift of Thomas G. Dragges",
    "sfomuseum:date":"1940s",
    "sfomuseum:daterange_end":"1949-12-31",
    "sfomuseum:daterange_start":"1940-01-01",
    "sfomuseum:description":"Matchbook issued by Inland Airways; white cover with airline servicemark at center; airline phone numbers on saddle; text on reverse, \u201cDaily Flights / Seattle-Wallawalla / Richland - Pasco - Kennewick / Speed / Comfort / Safety / Serving Washington\u2019s / Inland Empire\u201d; airline logotype and wings flanking geographic outline of Washington state on interior; red-tipped matches. ",
    "sfomuseum:maker":"Atlas Match Corporation",
    "sfomuseum:medium":"cardboard, ink, phosphorus, metal",
    "sfomuseum:placetype":"object",
    "sfomuseum:subcategory":"Matchbook / Matchbox",
    "wof:name":"matchbook: Inland Airways",
    "wof:placetype":"venue"
},
  "geometry": {"coordinates":[-122.386155,37.616358],"type":"Point"}
}