{
  "type": "Feature",
  "properties": {
    "date:cessation_lower": "1996-01-01",
    "date:cessation_upper": "1996-12-31",
    "date:inception_lower": "1996-01-01",
    "date:inception_upper": "1996-12-31",
    "iso:country": "XX",
    "millsfield:images": [
      1527843947,
      1527843949
    ],
    "millsfield:primary_image": 1527843947,
    "sfomuseum:accession_number": "2007.086.015",
    "sfomuseum:airline": "American Airlines",
    "sfomuseum:category": "Passenger Amenity, Archive",
    "sfomuseum:collection": "Aviation Archive",
    "sfomuseum:creditline": "Gift of Ian H. Dally of Auckland, New Zealand",
    "sfomuseum:date": "1996",
    "sfomuseum:date_acquired": "2009-08-08",
    "sfomuseum:daterange_end": "1996-12-31",
    "sfomuseum:daterange_start": "1996-01-01",
    "sfomuseum:description": "Menu issued by American Airlines; white cover with color reproduction of painting titled “Educational Freedom”; breakfast menu items include omelette and pancakes; in English and Spanish; menu number: C-MED-U-BR-1 241C065-1; class: business; date: 10/96.",
    "sfomuseum:dimensions": "11 x 6 1/2 inches (27.9 x 16.5 cm)",
    "sfomuseum:media_ids": [
      1527843947,
      1527843949
    ],
    "sfomuseum:medium": "paper, metal, ink",
    "sfomuseum:placetype": "object",
    "sfomuseum:publication": ": , 1996.",
    "sfomuseum:subcategory": "Menu",
    "wof:depicts": [
      1159283849,
      1360700619
    ],
    "wof:name": "menu: American Airlines, business class",
    "wof:placetype": "custom",
    "wof:placetype_alt": "object"
  },
  "geometry": {"coordinates":[-122.386155,37.616357],"type":"Point"}
}
