{
  "type": "Feature",
  "properties": {
    "date:cessation_lower": "1996-12-31",
    "date:cessation_upper": "1996-12-31",
    "date:inception_lower": "1996-01-01",
    "date:inception_upper": "1996-01-01",
    "iso:country": "XX",
    "sfomuseum:accession_number": "2007.086.015",
    "sfomuseum:category": "Food Service",
    "sfomuseum:collection": "Aviation Museum",
    "sfomuseum:creditline": "Gift of Ian H. Dally of Auckland, New Zealand",
    "sfomuseum:date": "1996",
    "sfomuseum:daterange_end": "1996-12-31",
    "sfomuseum:daterange_start": "1996-01-01",
    "sfomuseum:description": "Menu produced by American Airlines; white cover with color reproduction of painting titled “Educational Freedom”; breakfast menu items include omelette and pancakes; in English and Spanish; menu number: C-MED-U-BR-1 241C065-1; class: business; date: 10/96.",
    "sfomuseum:media_ids": [
      1527843947, 
      1527843949
    ],
    "sfomuseum:medium": "paper, ink, metal",
    "sfomuseum:placetype": "object",
    "sfomuseum:subcategory": "Menu",
    "wof:name": "menu: American Airlines, Business Class",
    "wof:placetype": "venue"
  },
  "geometry": {"coordinates":[-122.386155,37.616358],"type":"Point"}
}
