{
  "type": "Feature",
  "properties": {
    "date:cessation_lower":"1969-12-31",
    "date:cessation_upper":"1969-12-31",
    "date:inception_lower":"1969-01-01",
    "date:inception_upper":"1969-01-01",
    "iso:country":"XX",
    "millsfield:images":[
        1527830209,
        1527830207
    ],
    "sfomuseum:accession_number":"2009.145.005",
    "sfomuseum:category":"Philately",
    "sfomuseum:collection":"Aviation Archive",
    "sfomuseum:creditline":"Anonymous gift",
    "sfomuseum:date":"10/25/1969",
    "sfomuseum:daterange_end":"1969-10-25",
    "sfomuseum:daterange_start":"1969-10-25",
    "sfomuseum:description":"Airmail flight cover commemorating first airmail flight of AM-29 from San Francisco; red cachet with image of San Francisco cable car; postmark: October 25, 1969, San Francisco with four-line cancellation mark over 10-cent stamp; backstamp: October 25, 1969, Albuquerque; white envelope with red and blue rhomboids around the border (border type I).",
    "sfomuseum:media_ids":[
        1527830207,
        1527830209
    ],
    "sfomuseum:medium":"paper, ink",
    "sfomuseum:placetype":"object",
    "sfomuseum:subcategory":"Airmail Flight Cover",
    "wof:name":"airmail flight cover: Commemoration of first airmail flight, AM-29, San Francisco",
    "wof:placetype":"venue"
},
  "geometry": {"coordinates":[-122.386155,37.616358],"type":"Point"}
}