{
  "type": "Feature",
  "properties": {
    "iso:country": "XX",
    "sfomuseum:accession_number": "2006.037.273",
    "sfomuseum:aircraft": "Airspeed Ambassador",
    "sfomuseum:category": "Subject File / Research File",
    "sfomuseum:collection": "Aviation Archive",
    "sfomuseum:creditline": "Gift of Rare Birds Collection",
    "sfomuseum:description": "Monty Grove's reference file of Airspeed manufacturer.  Includes:\rnewspaper articles, magazine tearsheets, photographs.",
    "sfomuseum:medium": "paper, ink",
    "sfomuseum:placetype": "object",
    "sfomuseum:subcategory": "Aircraft / Manufacturers",
    "sfomuseum:subject": "Aircraft manufacturer -- Airspeed",
    "wof:depicts": [
      1159292117
    ],
    "wof:name": "research file: Airspeed",
    "wof:placetype": "venue"
  },
  "geometry": {"coordinates":[-122.386155,37.616357],"type":"Point"}
}
