{
  "type": "Feature",
  "properties": {
    "date:cessation_lower": "1972-01-01",
    "date:cessation_upper": "1972-12-31",
    "date:inception_lower": "1972-01-01",
    "date:inception_upper": "1972-12-31",
    "iso:country": "XX",
    "sfomuseum:accession_number": "2010.025.001 a c",
    "sfomuseum:airline": "National Airlines",
    "sfomuseum:category": "Audio / Visual",
    "sfomuseum:collection": "Aviation Archive",
    "sfomuseum:creditline": "Purchase",
    "sfomuseum:date": "1972",
    "sfomuseum:daterange_end": "1972-12-31",
    "sfomuseum:daterange_start": "1972-01-01",
    "sfomuseum:description": "a. phonograph cover in with large color photographic image of orange sky with clouds and sun, small in-flight airliner, white “Watch Us Shine” in center, color image of orange sky with white airline “Sun King” logo and “National Airlines presents ‘Watch Us Shine’” at upper left corner and description of music on back cover.\rb. black record with black center, color of RCA dog logo and gray “RCA Victor” above, same on reverse.\rc. plastic sleeve.",
    "sfomuseum:dimensions": "12 1/2 x 12 1/2 inches (31.8 x 31.8 cm)",
    "sfomuseum:maker": "RCA Corporation",
    "sfomuseum:medium": "cardboard, paper, ink, vinyl",
    "sfomuseum:placetype": "object",
    "sfomuseum:publication": ": , 1972.",
    "sfomuseum:subcategory": "Phonograph Record",
    "wof:depicts": [
      1159284841
    ],
    "wof:name": "phonograph record: National Airlines, Watch Us Shine",
    "wof:placetype": "venue"
  },
  "geometry": {"coordinates":[-122.386155,37.616357],"type":"Point"}
}
