{
  "type": "Feature",
  "properties": {
    "date:cessation_lower": "1992-01-01",
    "date:cessation_upper": "1992-12-31",
    "date:inception_lower": "1992-01-01",
    "date:inception_upper": "1992-12-31",
    "iso:country": "XX",
    "loc:subject_heading": {
      "sh85031312": "Constellation (Transport planes)"
    },
    "loc:subject_headings": [
      "sh85031312"
    ],
    "sfomuseum:accession_number": "99-1150",
    "sfomuseum:aircraft": "Lockheed L-049 Constellation",
    "sfomuseum:author": "Stingfellow, Curtis K",
    "sfomuseum:callnumber": "TL686.L6 S77 1992",
    "sfomuseum:category": "Book",
    "sfomuseum:collection": "Aviation Library",
    "sfomuseum:creditline": "Purchase",
    "sfomuseum:date": "c. 1992",
    "sfomuseum:daterange_end": "1997-12-31",
    "sfomuseum:daterange_start": "1987-01-01",
    "sfomuseum:description": "144 p.: ill. (some col.) ; 27 cm.\r\r\r",
    "sfomuseum:description_library": "144 p.: ill. (some col.) ; 27 cm.\r\r\r",
    "sfomuseum:medium": "paper, ink",
    "sfomuseum:placetype": "object",
    "sfomuseum:publication": "Osceola, WI: Motorbooks International, c. 1992.",
    "sfomuseum:publisher": "Motorbooks International",
    "sfomuseum:publisher_location": "Osceola, WI",
    "sfomuseum:subcategory": "Book",
    "sfomuseum:subject": "Constellation (Transport planes).",
    "wof:depicts": [
      1159292981,
      1159293697,
      1159291095
    ],
    "wof:name": "Lockheed Constellation",
    "wof:placetype": "venue"
  },
  "geometry": {"coordinates":[-122.386155,37.616357],"type":"Point"}
}
