{
  "type": "Feature",
  "properties": {
    "date:cessation_lower": "1968-12-03",
    "date:cessation_upper": "1968-12-03",
    "date:inception_lower": "1968-12-03",
    "date:inception_upper": "1968-12-03",
    "iso:country": "XX",
    "millsfield:images": [
      1527830117,
      1527830119
    ],
    "millsfield:images_texts": [
      "FIRST\nDIRECT SERVICE\nBANGKOK - SYDNEY\nSydney\nPAN AMERICAN\nH.M. THE QUEENS\n3rd CYCLE ANNIVERSARY\n12* AUGUST 1953\n342583 7)\nPOSTAGE\nвАнт\nTHAILAND\nMr. J. G. 0'Donnell\nVice President-Sales - Pacific\nPan American World Airways\nPan Am Building\nNew York, New York\n10017",
      "2002.050.001"
    ],
    "millsfield:images_texts_ids": [
      1527830117,
      1527830119
    ],
    "millsfield:primary_image": 1527830117,
    "sfomuseum:accession_number": "2002.050.001",
    "sfomuseum:airline": "Pan American World Airways",
    "sfomuseum:category": "Philately",
    "sfomuseum:collection": "Aviation Archive",
    "sfomuseum:creditline": "Gift of Jerry O'Donnell",
    "sfomuseum:date": "12/03/1968",
    "sfomuseum:daterange_end": "1968-12-03",
    "sfomuseum:daterange_start": "1968-12-03",
    "sfomuseum:description": "Airmail flight cover commemorating first Pan American World Airways direct service from Bangkok to Sydney; blue cachet with image of route map; postmarked Dec. 3, 1968, Bangkok GPO over 5-baht stamp; no backstamp.",
    "sfomuseum:dimensions": "3 1/2 x 6 1/2 inches (8.9 x 16.5 cm)",
    "sfomuseum:media_ids": [
      1527830117,
      1527830119
    ],
    "sfomuseum:medium": "paper, ink",
    "sfomuseum:placetype": "object",
    "sfomuseum:publication": ": , 12/03/1968.",
    "sfomuseum:subcategory": "Airmail Flight Cover",
    "wof:depicts": [
      1159286839,
      1159284989
    ],
    "wof:name": "airmail cover: Pan American World Airways, first direct flight, Bangkok - Sydney route",
    "wof:placetype": "custom",
    "wof:placetype_alt": "object"
  },
  "geometry": {"coordinates":[-122.386155,37.616357],"type":"Point"}
}
