{
  "type": "Feature",
  "properties": {
    "date:cessation_lower": "1980-01-01",
    "date:cessation_upper": "1989-12-31",
    "date:inception_lower": "1980-01-01",
    "date:inception_upper": "1989-12-31",
    "iso:country": "XX",
    "millsfield:images": [
      1527823599,
      1527823597
    ],
    "sfomuseum:accession_number": "1998.157.049",
    "sfomuseum:airline": "British Eagle International Airlines",
    "sfomuseum:category": "Passenger Amenity",
    "sfomuseum:collection": "Aviation Archive",
    "sfomuseum:creditline": "Gift of The Henry Steiner Air Sickness Bag Collection",
    "sfomuseum:date": "1980s",
    "sfomuseum:daterange_end": "1989-12-31",
    "sfomuseum:daterange_start": "1980-01-01",
    "sfomuseum:description": "Gusset wedge, no closure. White bag, blue and red print. \"Britannia Airways\" printed in blue on lower portion of bag. Above is logo, red and blue print, two diagonal lines with blue circle depicting profile view of spartan holding shield bearing British flag design.",
    "sfomuseum:dimensions": "10 x 6 1/4 inches (25.4 x 15.9 cm)",
    "sfomuseum:media_ids": [
      1527823597,
      1527823599
    ],
    "sfomuseum:medium": "paper",
    "sfomuseum:placetype": "object",
    "sfomuseum:subcategory": "Airsickness Bag",
    "wof:depicts": [
      1159284017
    ],
    "wof:name": "airsickness bag: Britannia Airways",
    "wof:placetype": "venue"
  },
  "geometry": {"coordinates":[-122.386155,37.616357],"type":"Point"}
}
