{
  "type": "Feature",
  "properties": {
    "date:cessation_lower": "1927-12-31",
    "date:cessation_upper": "1927-12-31",
    "date:inception_lower": "1927-01-01",
    "date:inception_upper": "1927-01-01",
    "iso:country": "XX",
    "sfomuseum:accession_number": "99-0392       ",
    "sfomuseum:author": "Lindbergh, Charles A. (Charles Augustus)",
    "sfomuseum:callnumber": "TL540.L5 A3 1927 c.2 SC",
    "sfomuseum:category": "Book",
    "sfomuseum:collection": "Aviation Library",
    "sfomuseum:date": "1927",
    "sfomuseum:daterange_end": "1927-12-31",
    "sfomuseum:daterange_start": "1927-01-01",
    "sfomuseum:description": "318 p. front., plates, ports. 21 cm.",
    "sfomuseum:medium": "paper, ink",
    "sfomuseum:placetype": "object",
    "sfomuseum:publisher": "G.P. Putnam's sons",
    "sfomuseum:publisher_location": "New York; London",
    "sfomuseum:subcategory": "Book",
    "sfomuseum:subject": "Lindbergh, Charles A. (Charles Augustus), 1902-1974.                                       Air pilots -- United States -- Biography.",
    "wof:name": "We ... the famous flier's own story of his life and his transatlantic flight, together with his views on the future of aviation",
    "wof:placetype": "custom"
  },
  "geometry": {"coordinates":[-122.386155,37.616357],"type":"Point"}
}
