{
  "type": "Feature",
  "properties": {
    "date:cessation_lower":"1970-12-31",
    "date:cessation_upper":"1970-12-31",
    "date:inception_lower":"1970-01-01",
    "date:inception_upper":"1970-01-01",
    "iso:country":"XX",
    "millsfield:images":[
        1527844879,
        1527844877
    ],
    "sfomuseum:accession_number":"2004.093.005",
    "sfomuseum:category":"Food Service",
    "sfomuseum:collection":"Aviation Museum",
    "sfomuseum:creditline":"Gift of John M. Burnard",
    "sfomuseum:date":"1970s",
    "sfomuseum:daterange_end":"1970-12-31",
    "sfomuseum:daterange_start":"1970-01-01",
    "sfomuseum:description":"Menu produced by Malaysia Airlines; white cover with color photographic image of fruit (Java Apple) on a tree; menu items include consomm\u00e9 and filet of beef silver kris; menu number: 105Y; undated.",
    "sfomuseum:media_ids":[
        1527844877,
        1527844879
    ],
    "sfomuseum:medium":"paper, ink",
    "sfomuseum:placetype":"object",
    "sfomuseum:subcategory":"Menu",
    "wof:name":"menu: Malaysian Airways",
    "wof:placetype":"venue"
},
  "geometry": {"coordinates":[-122.386155,37.616358],"type":"Point"}
}