{
  "type": "Feature",
  "properties": {
    "date:cessation_lower": "1978-12-31",
    "date:cessation_upper": "1978-12-31",
    "date:inception_lower": "1978-01-01",
    "date:inception_upper": "1978-01-01",
    "iso:country": "XX",
    "sfomuseum:accession_number": "2002.135.035.011",
    "sfomuseum:category": "Scheduling / Ticketing",
    "sfomuseum:collection": "Aviation Archive",
    "sfomuseum:creditline": "Gift of Thomas G. Dragges",
    "sfomuseum:date": "1978",
    "sfomuseum:daterange_end": "1978-12-31",
    "sfomuseum:daterange_start": "1978-01-01",
    "sfomuseum:description": "System timetable issued by Western Airlines, effective October 29, 1978 through January 15, 1979; red and white cover with white “W” logo and 50th anniversary logo; contains listing of U.S. and Mexico flights.",
    "sfomuseum:media_ids": [
      1527836969
    ],
    "sfomuseum:medium": "paper, ink",
    "sfomuseum:placetype": "object",
    "sfomuseum:subcategory": "Timetable",
    "wof:name": "timetable: Western Airlines",
    "wof:placetype": "venue"
  },
  "geometry": {"coordinates":[-122.386155,37.616358],"type":"Point"}
}
