{
  "type": "Feature",
  "properties": {
    "date:cessation_lower": "1931-01-01",
    "date:cessation_upper": "1931-12-31",
    "date:inception_lower": "1931-01-01",
    "date:inception_upper": "1931-12-31",
    "iso:country": "US",
    "loc:subject_headings": [
      "sh85002782",
      "sh85001319"
    ],
    "sfomuseum:accession_number": "2006.015.001",
    "sfomuseum:author": "Aeronautical Chamber of Commerce of America",
    "sfomuseum:callnumber": "TL501 .A37 1931 c.3 REF",
    "sfomuseum:category": "Book",
    "sfomuseum:collection": "Aviation Library",
    "sfomuseum:continent": "North America",
    "sfomuseum:country": "United States",
    "sfomuseum:creditline": "Gift of Marion L. Yates in memory of John A. Yates, PAA April 1938 -1973",
    "sfomuseum:date": "1931",
    "sfomuseum:date_acquired": "2006-06-20",
    "sfomuseum:daterange_end": "1931-12-31",
    "sfomuseum:daterange_start": "1931-01-01",
    "sfomuseum:description": "Compiled, written and edited by the Aeronautical Chamber of Commerce of America, Inc.",
    "sfomuseum:description_library": "Compiled, written and edited by the Aeronautical Chamber of Commerce of America, Inc.",
    "sfomuseum:issue": "1931",
    "sfomuseum:medium": "printed, bound paper",
    "sfomuseum:placetype": "object",
    "sfomuseum:publication": "Washington, D.C.: Lincoln Press, 1931.",
    "sfomuseum:publisher": "Lincoln Press",
    "sfomuseum:publisher_location": "Washington, D.C.",
    "sfomuseum:subcategory": "Reference",
    "sfomuseum:subject": "Airplanes.\rAeronautics.",
    "wof:name": "Aircraft year book [1931]",
    "wof:placetype": "custom",
    "wof:placetype_alt": "object"
  },
  "geometry": {"coordinates":[-122.386155,37.616357],"type":"Point"}
}
