{
  "type": "Feature",
  "properties": {
    "date:cessation_lower": "1915-01-01",
    "date:cessation_upper": "1915-12-31",
    "date:inception_lower": "1915-01-01",
    "date:inception_upper": "1915-12-31",
    "iso:country": "XX",
    "millsfield:images": [
      1527830305
    ],
    "millsfield:primary_image": 1527830305,
    "sfomuseum:accession_number": "2010.282.019 a b",
    "sfomuseum:aircraft": "Lockheed G",
    "sfomuseum:category": "Photograph",
    "sfomuseum:collection": "Aviation Archive",
    "sfomuseum:creditline": "Gift of Edwin I. Power, Jr. and Linda L. Liscom",
    "sfomuseum:date": "1915",
    "sfomuseum:date_acquired": "2011-01-28",
    "sfomuseum:daterange_end": "1915-12-31",
    "sfomuseum:daterange_start": "1915-01-01",
    "sfomuseum:description": "a. Glass negative depicting scene from Panama-Pacific International Exposition, San Francisco, February 20 through December 4, 1915; three unidentified men seated in Loughead (Lockheed) Model G biplane on pier; San Francisco Bay and military ship visible in background; “22440 at lower left corner;\rb. handwritten inscription on original sleeve, “22440 / A. G. Hunt.”",
    "sfomuseum:dimensions": "5 x 7 inches (12.7 x 17.8 cm)",
    "sfomuseum:media_ids": [
      1527830305
    ],
    "sfomuseum:medium": "glass negative",
    "sfomuseum:placetype": "object",
    "sfomuseum:publication": ": , 1915.",
    "sfomuseum:subcategory": "Glass Negative",
    "wof:depicts": [
      1159292069
    ],
    "wof:name": "glass negative: Panama-Pacific International Exposition",
    "wof:placetype": "custom",
    "wof:placetype_alt": "object"
  },
  "geometry": {"coordinates":[-122.386155,37.616357],"type":"Point"}
}
