{
  "type": "Feature",
  "properties": {
    "date:cessation_lower": "1987-01-01",
    "date:cessation_upper": "1987-12-31",
    "date:inception_lower": "1987-01-01",
    "date:inception_upper": "1987-12-31",
    "isbn:number": "085130141X (pbk.), 9780851301419 (pbk.)",
    "iso:country": "XX",
    "sfomuseum:accession_number": "00-3046",
    "sfomuseum:author": "Ingham, M. J. (Michael J.)",
    "sfomuseum:callnumber": "HE9787.5.G7 I36 1987",
    "sfomuseum:category": "Book",
    "sfomuseum:collection": "Aviation Library",
    "sfomuseum:date": "1987",
    "sfomuseum:daterange_end": "1987-12-31",
    "sfomuseum:daterange_start": "1987-01-01",
    "sfomuseum:description": "76 p. : ill., maps, ports. ; 30 cm.",
    "sfomuseum:description_library": "76 p. : ill., maps, ports. ; 30 cm.",
    "sfomuseum:medium": "paper, ink",
    "sfomuseum:placetype": "object",
    "sfomuseum:publication": "Tonbridge, Kent , England: Air-Britain (Historians), 1987.",
    "sfomuseum:publisher": "Air-Britain (Historians)",
    "sfomuseum:publisher_location": "Tonbridge, Kent , England",
    "sfomuseum:subcategory": "Book",
    "sfomuseum:subject": "Airlines England Scilly, Isles of History.",
    "wof:name": "To the sunset bound: a history of the development of civil air services to the Isles of Scilly",
    "wof:placetype": "custom",
    "wof:placetype_alt": "object"
  },
  "geometry": {"coordinates":[-122.386155,37.616357],"type":"Point"}
}
