{
  "type": "Feature",
  "properties": {
    "date:cessation_lower": "1987-01-01",
    "date:cessation_upper": "1987-12-31",
    "date:inception_lower": "1987-01-01",
    "date:inception_upper": "1987-12-31",
    "iso:country": "XX",
    "millsfield:images": [
      1527845743
    ],
    "millsfield:images_texts": [
      "SUPPLEMENT TO\nEXECUTIVE TRAVEL\nGULFAIR\nThe Falcon flies on"
    ],
    "millsfield:images_texts_ids": [
      1527845743
    ],
    "millsfield:primary_image": 1527845743,
    "sfomuseum:accession_number": "2011.061.0508",
    "sfomuseum:airline": "Gulf Air",
    "sfomuseum:category": "Promotional, Archive",
    "sfomuseum:collection": "Aviation Archive",
    "sfomuseum:creditline": "Gift of the Frank J. Lichtanski Collection",
    "sfomuseum:date": "1987",
    "sfomuseum:date_acquired": "2011-08-02",
    "sfomuseum:daterange_end": "1987-12-31",
    "sfomuseum:daterange_start": "1987-01-01",
    "sfomuseum:description": "Promotional brochure issued by Gulf Air, titled “The Falcon flies on”; multipage booklet; blue cover with depiction of gold eagle logo; contains printed information with images; October 1987 issue.",
    "sfomuseum:dimensions": "11 x 8 1/4 inches (27.9 x 21 cm)",
    "sfomuseum:media_ids": [
      1527845743
    ],
    "sfomuseum:medium": "paper, metal, ink",
    "sfomuseum:placetype": "object",
    "sfomuseum:publication": ": , 1987.",
    "sfomuseum:subcategory": "Brochure, Airline",
    "wof:depicts": [
      1159287827,
      1159284467
    ],
    "wof:name": "brochure: Gulf Air",
    "wof:placetype": "custom",
    "wof:placetype_alt": [
      "object"
    ]
  },
  "geometry": {"coordinates":[-122.386155,37.616357],"type":"Point"}
}
