{
  "type": "Feature",
  "properties": {
    "date:cessation_lower": "1987-12-31",
    "date:cessation_upper": "1987-12-31",
    "date:inception_lower": "1987-01-01",
    "date:inception_upper": "1987-01-01",
    "iso:country": "XX",
    "millsfield:images": [
      1527845743
    ],
    "sfomuseum:accession_number": "2011.061.0508",
    "sfomuseum:airline": "Gulf Air",
    "sfomuseum:category": "Promotional",
    "sfomuseum:collection": "Aviation Archive",
    "sfomuseum:creditline": "Gift of the Frank J. Lichtanski Collection",
    "sfomuseum:date": "1987",
    "sfomuseum:daterange_end": "1987-12-31",
    "sfomuseum:daterange_start": "1987-01-01",
    "sfomuseum:description": "Promotional brochure issued by Gulf Air, titled “The Falcon flies on” with depiction of gold eagle logo; brochure contains printed information with images; October 1987 issue.",
    "sfomuseum:media_ids": [
      1527845743
    ],
    "sfomuseum:medium": "paper, ink",
    "sfomuseum:placetype": "object",
    "sfomuseum:subcategory": "Brochure, Airline",
    "wof:depicts": [
      1159284467
    ],
    "wof:name": "brochure: Gulf Air",
    "wof:placetype": "venue"
  },
  "geometry": {"coordinates":[-122.386155,37.616357],"type":"Point"}
}
