{
  "type": "Feature",
  "properties": {
    "date:cessation_lower": "1922-01-01",
    "date:cessation_upper": "1922-12-31",
    "date:inception_lower": "1922-01-01",
    "date:inception_upper": "1922-12-31",
    "iso:country": "XX",
    "sfomuseum:accession_number": "2000.160.1029",
    "sfomuseum:author": "Smithsonian Institution. Board of Regents",
    "sfomuseum:callnumber": "Q11 .S66 1922 REF",
    "sfomuseum:category": "Book",
    "sfomuseum:collection": "Aviation Library",
    "sfomuseum:creditline": "The Tony Bill Aviation Library Collection",
    "sfomuseum:date": "1922",
    "sfomuseum:date_acquired": "1999-05-18",
    "sfomuseum:daterange_end": "1922-12-31",
    "sfomuseum:daterange_start": "1922-01-01",
    "sfomuseum:description": "554 p. : ill. maps ; 23-24 cm.",
    "sfomuseum:description_library": "554 p. : ill. maps ; 23-24 cm.",
    "sfomuseum:medium": "paper, ink",
    "sfomuseum:notes_library": "Description based on: 4th (1849).Vols. for 1849-1963/64 include  General appendix to the Smithsonian report  (varies slightly).Vols. for 1847-1963/64 include the Institution's Report of the Secretary, also published separately.Some reports issued in various congressional series: Senate miscellaneous documents, House miscellaneous documents, House executive documents, and House documents.Published: Washington : U.S. G.P.O., \u003c1880-1897\u003e Showing the operations, expenditures, and condition of the Institution.  ; subtitle varies.Reports for 1884-1886/87 issued in 2 pts., pt. 2 being the Report of the National Museum.Reports for 1848-1855 called 3d-10th.Report year for 1885-1964 ends June 30.Author-subject: 1849-1961.  1 v.Merged with: Smithsonian Institution.  Report of the Secretary and financial report of the Executive Committee of the Board of Regents, and: United States National Museum.  Annual report for the year ended June 30 ..., to form: Smithsonian Institution.  Smithsonian year (",
    "sfomuseum:placetype": "object",
    "sfomuseum:publication": "Washington, D.C.: Institution, 1922.",
    "sfomuseum:publisher": "Institution",
    "sfomuseum:publisher_location": "Washington, D.C.",
    "sfomuseum:series": "1917/18-1963/64: Publication / Smithsonian Institution",
    "sfomuseum:subcategory": "Reference",
    "sfomuseum:subject": "Smithsonian Institution Periodicals.",
    "wof:name": "Annual report of the Board of Regents of the Smithsonian Institution: showing the operations, expenditures, and condition of the Institution for the year ending June 30, 1922",
    "wof:placetype": "venue"
  },
  "geometry": {"coordinates":[-122.386155,37.616357],"type":"Point"}
}
