{
  "type": "Feature",
  "properties": {
    "date:cessation_lower": "1918-01-01",
    "date:cessation_upper": "1918-12-31",
    "date:inception_lower": "1918-01-01",
    "date:inception_upper": "1918-12-31",
    "iso:country": "XX",
    "sfomuseum:accession_number": "2000.171.001",
    "sfomuseum:author": "Berry, William Hibbert",
    "sfomuseum:callnumber": "TL545 .B6 1918 c.1 SC",
    "sfomuseum:category": "Book",
    "sfomuseum:collection": "Aviation Library",
    "sfomuseum:creditline": "Collection of SFO Museum",
    "sfomuseum:date": "c. 1918",
    "sfomuseum:daterange_end": "1923-12-31",
    "sfomuseum:daterange_start": "1913-01-01",
    "sfomuseum:description": "292 p. illus. 20 cm.",
    "sfomuseum:description_library": "292 p. illus. 20 cm.",
    "sfomuseum:medium": "paper, ink",
    "sfomuseum:placetype": "object",
    "sfomuseum:publication": "New York: George H. Doran company, c. 1918.",
    "sfomuseum:publisher": "George H. Doran company",
    "sfomuseum:publisher_location": "New York",
    "sfomuseum:subcategory": "Book",
    "sfomuseum:subject": "World War, 1914-1918 Aerial operations.Aeronautics, Commercial.Aeronautics, Military.Aeronautics.",
    "wof:name": "Aircraft in war and commerce",
    "wof:placetype": "custom",
    "wof:placetype_alt": "object"
  },
  "geometry": {"coordinates":[-122.386155,37.616357],"type":"Point"}
}
