{
  "type": "Feature",
  "properties": {
    "date:cessation_lower": "1944-01-01",
    "date:cessation_upper": "1944-12-31",
    "date:inception_lower": "1944-01-01",
    "date:inception_upper": "1944-12-31",
    "iso:country": "XX",
    "loc:subject_headings": [
      "sh85001360",
      "sh85054016",
      "sh85003003"
    ],
    "sfomuseum:accession_number": "2002.004.008 ",
    "sfomuseum:author": "Van Zandt, J. Parker (John Parker)",
    "sfomuseum:callnumber": "TL552 .V36 1944",
    "sfomuseum:category": "Book",
    "sfomuseum:collection": "Aviation Library",
    "sfomuseum:creditline": "Purchase",
    "sfomuseum:date": "1944",
    "sfomuseum:daterange_end": "1944-12-31",
    "sfomuseum:daterange_start": "1944-01-01",
    "sfomuseum:description": "67 p.",
    "sfomuseum:medium": "paper, ink",
    "sfomuseum:placetype": "object",
    "sfomuseum:publication": "Washington, D.C.: The Brookings Institution, 1944.",
    "sfomuseum:publisher": "The Brookings Institution",
    "sfomuseum:publisher_location": "Washington, D.C.",
    "sfomuseum:series": "America faces the air age, v.1",
    "sfomuseum:subcategory": "Book",
    "sfomuseum:subject": "Aeronautics, Commercial. \rEconomic geography. \rAirways.",
    "wof:name": "The geography of world air transport",
    "wof:placetype": "venue"
  },
  "geometry": {"coordinates":[-122.386155,37.616357],"type":"Point"}
}
