{
  "type": "Feature",
  "properties": {
    "date:cessation_lower": "1999-01-01",
    "date:cessation_upper": "1999-12-31",
    "date:inception_lower": "1996-01-01",
    "date:inception_upper": "1996-12-31",
    "iso:country": "XX",
    "sfomuseum:accession_number": "2002.038.001, 2002.038.002",
    "sfomuseum:author": "U.S. Department of Transportation. Bureau of Transportation Statistics. Office of Airline Information",
    "sfomuseum:callnumber": "TL521 .A24152 REF",
    "sfomuseum:category": "Book",
    "sfomuseum:collection": "Aviation Library",
    "sfomuseum:creditline": "Purchase",
    "sfomuseum:date": "1996-1999",
    "sfomuseum:daterange_end": "1999-12-31",
    "sfomuseum:daterange_start": "1996-01-01",
    "sfomuseum:description": "v. : maps : 28 cm.",
    "sfomuseum:description_library": "v. : maps : 28 cm.",
    "sfomuseum:issues_held": "1996 (2002.038.001), 1997, 1998 (00-3392, 2002.038.002), 1999",
    "sfomuseum:medium": "paper, ink",
    "sfomuseum:placetype": "object",
    "sfomuseum:publication": "Washington, D.C.: The Office, 1996-1999.",
    "sfomuseum:publisher": "The Office",
    "sfomuseum:publisher_location": "Washington, D.C.",
    "sfomuseum:subcategory": "Reference",
    "sfomuseum:subject": "Aeronautics, Commercial United States Passenger traffic Statistics Periodicals.Aeronautics, Commercial United States Freight Statistics Periodicals.Airports United States Statistics Periodicals.",
    "wof:name": "Airport activity statistics of certificated air carriers. Summary tables",
    "wof:placetype": "custom",
    "wof:placetype_alt": "object"
  },
  "geometry": {"coordinates":[-122.386155,37.616357],"type":"Point"}
}
