{
  "type": "Feature",
  "properties": {
    "date:cessation_lower": "1964-06-24",
    "date:cessation_upper": "1964-06-24",
    "date:inception_lower": "1964-06-24",
    "date:inception_upper": "1964-06-24",
    "iso:country": "XX",
    "millsfield:images": [
      1527833431,
      1527833435
    ],
    "millsfield:images_texts": [
      "PAN AM\n25TH ANNIVERSARY\nFIRST AIR MAIL\nFLIGHT\nIRELAND\nUN 24\nPM\n1964\n?\n5\nCIVIL WAR\nCENTENNIAL\n1864-1964\nWILDERNESS\nTES POSTAGE\nGLOW FROM THAT FIRE CAN TRULY\nAND THE\nOSCAR H. FATOUT.\n4000 E. 5TH ST\nLONG BEACH\nCALIF.\n90814",
      "NA\nМАРНОР,\n125\nVI\n64\n2012.140. 1890"
    ],
    "millsfield:images_texts_ids": [
      1527833431,
      1527833435
    ],
    "millsfield:primary_image": 1527833431,
    "sfomuseum:accession_number": "2012.149.1890",
    "sfomuseum:airline": "Pan American World Airways",
    "sfomuseum:category": "Philately",
    "sfomuseum:collection": "Aviation Archive",
    "sfomuseum:creditline": "Gift of the Captain John B. Russell Family",
    "sfomuseum:date": "06/24/1964",
    "sfomuseum:date_acquired": "2013-05-31",
    "sfomuseum:daterange_end": "1964-06-24",
    "sfomuseum:daterange_start": "1964-06-24",
    "sfomuseum:description": "Airmail flight cover, Pan American World Airways; blue cachet at left depicting transatlantic route map with text, “Pan Am / 25th Anniversary / First Air Mail Flight”; postmarked June 24, 1964, New York, with three postage stamps; backstamp: June 25, 1964 in Aerphort Na Sionainne (Shannon); addressed to Oscar H. Fatout.",
    "sfomuseum:dimensions": "3 1/2 x 6 1/2 inches (8.9 x 16.5 cm)",
    "sfomuseum:media_ids": [
      1527833431,
      1527833435
    ],
    "sfomuseum:medium": "paper, ink",
    "sfomuseum:placetype": "object",
    "sfomuseum:publication": ": , 06/24/1964.",
    "sfomuseum:subcategory": "Airmail Flight Cover",
    "wof:depicts": [
      1159284989,
      1159286839
    ],
    "wof:name": "airmail flight cover: Pan American World Airways, United States - Ireland route, 25th Anniversary",
    "wof:placetype": "custom",
    "wof:placetype_alt": [
      "object"
    ]
  },
  "geometry": {"coordinates":[-122.386155,37.616357],"type":"Point"}
}
