{
  "type": "Feature",
  "properties": {
    "date:cessation_lower": "1974-12-31",
    "date:cessation_upper": "1974-12-31",
    "date:inception_lower": "1964-01-01",
    "date:inception_upper": "1964-01-01",
    "iso:country": "XX",
    "sfomuseum:accession_number": "2012.149.2408",
    "sfomuseum:category": "Scheduling / Ticketing",
    "sfomuseum:collection": "Aviation Archive",
    "sfomuseum:creditline": "Gift of the Captain John B. Russell Family",
    "sfomuseum:date": "c. 1969",
    "sfomuseum:daterange_end": "1974-12-31",
    "sfomuseum:daterange_start": "1964-01-01",
    "sfomuseum:description": "Red crew luggage tag produced by Pan American World Airways; text at top reads “Do not touch”; text on reverse states “Caution / Do not use until repaired or tested”; tag probably used to ship airline equipment.",
    "sfomuseum:media_ids": [
      1527853103, 
      1527853105
    ],
    "sfomuseum:medium": "paper, ink",
    "sfomuseum:placetype": "object",
    "sfomuseum:subcategory": "Luggage Tag, Crew",
    "wof:name": "crew luggage tag: Pan American World Airways",
    "wof:placetype": "venue"
  },
  "geometry": {"coordinates":[-122.386155,37.616358],"type":"Point"}
}
