{
  "type": "Feature",
  "properties": {
    "date:cessation_lower": "2009-01-01",
    "date:cessation_upper": "2009-12-31",
    "date:inception_lower": "2009-01-01",
    "date:inception_upper": "2009-12-31",
    "iso:country": "XX",
    "sfomuseum:accession_number": "2011.045.001",
    "sfomuseum:author": "Sall, Larry D.",
    "sfomuseum:callnumber": "TL553.8 .A37 2009 c.2",
    "sfomuseum:category": "Book",
    "sfomuseum:collection": "Aviation Library",
    "sfomuseum:creditline": "Gift of Renee Lym Robertson",
    "sfomuseum:date": "2009",
    "sfomuseum:daterange_end": "2009-12-31",
    "sfomuseum:daterange_start": "2009-01-01",
    "sfomuseum:medium": "paper, ink",
    "sfomuseum:placetype": "object",
    "sfomuseum:publisher": "University of Texas at Dallas",
    "sfomuseum:publisher_location": "Richardson, TX",
    "sfomuseum:subcategory": "Book",
    "sfomuseum:subject": "United States. Central Intelligence Agency. \rAir America -- History. \rCivil Air Transport. \rSearch and rescue operations -- Southeast Asia. \rTransport planes -- Southeast Asia -- History. \rVietnam War, 1961-1975 -- Aerial operations, American.",
    "wof:name": "Air America: upholding the airmen's bond",
    "wof:placetype": "venue"
  },
  "geometry": {"coordinates":[-122.386155,37.616357],"type":"Point"}
}
