{
  "type": "Feature",
  "properties": {
    "date:cessation_lower": "1999-01-01",
    "date:cessation_upper": "1999-12-31",
    "date:inception_lower": "1999-01-01",
    "date:inception_upper": "1999-12-31",
    "isbn:number": "0760307008 alk. paper), 9780760307007 alk. paper)",
    "iso:country": "XX",
    "sfomuseum:accession_number": "00-0148",
    "sfomuseum:author": "Bullock, Freddy",
    "sfomuseum:callnumber": "TL685.4 .B85 1999",
    "sfomuseum:category": "Book",
    "sfomuseum:collection": "Aviation Library",
    "sfomuseum:date": "c. 1999",
    "sfomuseum:daterange_end": "2004-12-31",
    "sfomuseum:daterange_start": "1994-01-01",
    "sfomuseum:description": "112 p. : col. ill. ; 28 cm.",
    "sfomuseum:description_library": "112 p. : col. ill. ; 28 cm.",
    "sfomuseum:medium": "paper, ink",
    "sfomuseum:placetype": "object",
    "sfomuseum:publication": "Osceola, WI: MBI, c. 1999.",
    "sfomuseum:publisher": "MBI",
    "sfomuseum:publisher_location": "Osceola, WI",
    "sfomuseum:subcategory": "Book",
    "sfomuseum:subject": "Airlines -- Pacific area -- Pictorial works. Transport planes -- Pictorial works.",
    "wof:name": "Pacific Glory: airlines of the great ocean",
    "wof:placetype": "custom",
    "wof:placetype_alt": [
      "object"
    ]
  },
  "geometry": {"coordinates":[-122.386155,37.616357],"type":"Point"}
}
