{
  "type": "Feature",
  "properties": {
    "date:cessation_lower": "1959-12-31",
    "date:cessation_upper": "1959-12-31",
    "date:inception_lower": "1950-01-01",
    "date:inception_upper": "1950-01-01",
    "iso:country": "JP",
    "sfomuseum:accession_number": "1998.095.001",
    "sfomuseum:aircraft": "Douglas DC-7",
    "sfomuseum:airline": "Northwest Airlines",
    "sfomuseum:category": "Toys",
    "sfomuseum:collection": "Aviation Museum",
    "sfomuseum:continent": "Asia",
    "sfomuseum:country": "Japan",
    "sfomuseum:creditline": "Purchase",
    "sfomuseum:date": "1950s",
    "sfomuseum:daterange_end": "1959-12-31",
    "sfomuseum:daterange_start": "1950-01-01",
    "sfomuseum:description": "Northwest Airlines Douglas DC-7 push-toy with four spinning propellers and wheels.",
    "sfomuseum:maker": "Asahi Toy",
    "sfomuseum:medium": "aluminum, rubber",
    "sfomuseum:placetype": "object",
    "sfomuseum:subcategory": "Toy Airplane",
    "wof:depicts": [
      1159290435,
      1159284907
    ],
    "wof:name": "toy airplane: Douglas DC-7 Northwest Airlines",
    "wof:placetype": "venue"
  },
  "geometry": {"coordinates":[-122.386155,37.616357],"type":"Point"}
}
