{
  "type": "Feature",
  "properties": {
    "date:cessation_lower": "1950-01-01",
    "date:cessation_upper": "1959-12-31",
    "date:inception_lower": "1950-01-01",
    "date:inception_upper": "1959-12-31",
    "iso:country": "JP",
    "millsfield:images": [
      1746680289
    ],
    "millsfield:images_texts": [
      "NORTHWEST"
    ],
    "millsfield:images_texts_ids": [
      1746680289
    ],
    "millsfield:primary_image": 1746680289,
    "sfomuseum:accession_number": "1998.095.001",
    "sfomuseum:aircraft": "Douglas DC-7",
    "sfomuseum:airline": "Northwest Airlines",
    "sfomuseum:category": "Toys",
    "sfomuseum:collection": "Aviation Museum",
    "sfomuseum:continent": "Asia",
    "sfomuseum:country": "Japan",
    "sfomuseum:creditline": "Purchase",
    "sfomuseum:date": "1950s",
    "sfomuseum:date_acquired": "1998-04-15",
    "sfomuseum:daterange_end": "1959-12-31",
    "sfomuseum:daterange_start": "1950-01-01",
    "sfomuseum:description": "Toy airplane manufactured by Asahi Toy; Northwest Airlines Douglas DC-7 push-toy; red and blue livery with four engines.",
    "sfomuseum:dimensions": "5 1/2 x 16 x 20 inches (14 x 40.6 x 50.8 cm)",
    "sfomuseum:maker": "Asahi Toy",
    "sfomuseum:medium": "aluminum, rubber",
    "sfomuseum:placetype": "object",
    "sfomuseum:publication": ": , 1950s.",
    "sfomuseum:subcategory": "Toy Airplane",
    "wof:depicts": [
      1159284907,
      1159290435
    ],
    "wof:name": "toy airplane: Douglas DC-7 Northwest Airlines",
    "wof:placetype": "custom",
    "wof:placetype_alt": "object"
  },
  "geometry": {"coordinates":[-122.386155,37.616357],"type":"Point"}
}
