{
  "type": "Feature",
  "properties": {
    "date:cessation_lower": "1932-01-01",
    "date:cessation_upper": "1932-12-31",
    "date:inception_lower": "1932-01-01",
    "date:inception_upper": "1932-12-31",
    "iso:country": "XX",
    "sfomuseum:accession_number": "2001.205.019",
    "sfomuseum:author": "Powell, Van.\r",
    "sfomuseum:callnumber": "PZ7 .P88 1932 SC",
    "sfomuseum:category": "Book",
    "sfomuseum:collection": "Aviation Library",
    "sfomuseum:creditline": "Purchase",
    "sfomuseum:date": "1932",
    "sfomuseum:daterange_end": "1932-12-31",
    "sfomuseum:daterange_start": "1932-01-01",
    "sfomuseum:description": "280 p. [1] leaf of plates ; p., 20 cm.\rFull color dust jacket.",
    "sfomuseum:medium": "paper, ink",
    "sfomuseum:placetype": "object",
    "sfomuseum:publisher": "Saalfield",
    "sfomuseum:publisher_location": "Akron, OH",
    "sfomuseum:subcategory": "Book",
    "sfomuseum:subject": "Airports -- Juvenile literature.",
    "wof:name": "The ghost of mystery airport",
    "wof:placetype": "venue"
  },
  "geometry": {"coordinates":[-122.386155,37.616357],"type":"Point"}
}
