{
  "type": "Feature",
  "properties": {
    "date:cessation_lower": "1991-01-01",
    "date:cessation_upper": "1991-12-31",
    "date:inception_lower": "1991-01-01",
    "date:inception_upper": "1991-12-31",
    "iso:country": "XX",
    "sfomuseum:accession_number": "1999.657.152",
    "sfomuseum:aircraft": "Martin M-130",
    "sfomuseum:airline": "Pan American World Airways",
    "sfomuseum:author": "Gandt, Robert L.",
    "sfomuseum:callnumber": "TL684.2 .G36 1991 c.2",
    "sfomuseum:category": "Book",
    "sfomuseum:collection": "Aviation Library",
    "sfomuseum:creditline": "Purchase",
    "sfomuseum:date": "1991",
    "sfomuseum:date_acquired": "1995-05-25",
    "sfomuseum:daterange_end": "1991-12-31",
    "sfomuseum:daterange_start": "1991-01-01",
    "sfomuseum:description": "xi, 214 p., [32] p. of plates: ill., map ; 24 cm.\r",
    "sfomuseum:description_library": "xi, 214 p., [32] p. of plates: ill., map ; 24 cm.\r",
    "sfomuseum:medium": "printed, bound paper",
    "sfomuseum:placetype": "object",
    "sfomuseum:publication": "Annapolis, MD: Naval Institute Press, 1991.",
    "sfomuseum:publisher": "Naval Institute Press",
    "sfomuseum:publisher_location": "Annapolis, MD",
    "sfomuseum:subcategory": "Book",
    "sfomuseum:subject": "Pan American Airways -- China Clipper (Airplane)\rSeaplanes--History.\r",
    "wof:depicts": [
      1159286839,
      1159284989,
      1159291191
    ],
    "wof:name": "China Clipper: the age of the great flying boats",
    "wof:placetype": "custom",
    "wof:placetype_alt": "object"
  },
  "geometry": {"coordinates":[-122.386155,37.616357],"type":"Point"}
}
