{
  "type": "Feature",
  "properties": {
    "date:cessation_lower": "2010-12-31",
    "date:cessation_upper": "2010-12-31",
    "date:inception_lower": "2010-01-01",
    "date:inception_upper": "2010-01-01",
    "iso:country": "XX",
    "millsfield:images": [
      1527848569
    ],
    "sfomuseum:accession_number": "2010.225.107",
    "sfomuseum:airline": "Emirates Airline",
    "sfomuseum:category": "Passenger Amenity",
    "sfomuseum:collection": "Aviation Archive",
    "sfomuseum:creditline": "Gift of the William Hough Collection",
    "sfomuseum:date": "2010",
    "sfomuseum:daterange_end": "2010-12-31",
    "sfomuseum:daterange_start": "2010-01-01",
    "sfomuseum:description": "In-flight entertainment guide issued by Emirates, titled “Ice / digital widescreen”, February 2010; full color photographic image on cover depicting two men playing video game; contains playlists for inflight multimedia entertainment, including movies, games, and music; 73 pages.",
    "sfomuseum:dimensions": "5 3/4 x 8 1/4 inches (14.6 x 21 cm)",
    "sfomuseum:media_ids": [
      1527848569
    ],
    "sfomuseum:medium": "paper, ink",
    "sfomuseum:placetype": "object",
    "sfomuseum:subcategory": "Entertainment, Guide",
    "wof:depicts": [
      1159284333
    ],
    "wof:name": "inflight entertainment guide: Emirates",
    "wof:placetype": "venue"
  },
  "geometry": {"coordinates":[-122.386155,37.616357],"type":"Point"}
}
