{
  "type": "Feature",
  "properties": {
    "date:cessation_lower": "2014-12-31",
    "date:cessation_upper": "2014-12-31",
    "date:inception_lower": "2004-01-01",
    "date:inception_upper": "2004-01-01",
    "iso:country": "XX",
    "millsfield:images": [
      1527845109,
      1527845111
    ],
    "sfomuseum:accession_number": "2010.093.001",
    "sfomuseum:airline": "Delta Air Lines",
    "sfomuseum:category": "Passenger Amenity",
    "sfomuseum:collection": "Aviation Archive",
    "sfomuseum:creditline": "Gift of Patricia Austin",
    "sfomuseum:date": "c. 2009",
    "sfomuseum:daterange_end": "2014-12-31",
    "sfomuseum:daterange_start": "2004-01-01",
    "sfomuseum:description": "Menu issued by Delta Air Lines, Europe - United States route; black cover with color photographic image of a champagne flute and bottle; menu items include roasted chicken breast, steak, and rigatoni pasta; menu number: BE Europe-US C11A (LHR-MAN-DUB-ATL; LHR-MSP); class: BusinessElite; date: 10/09.",
    "sfomuseum:media_ids": [
      1527845109,
      1527845111
    ],
    "sfomuseum:medium": "paper, ink, metal",
    "sfomuseum:placetype": "object",
    "sfomuseum:subcategory": "Menu",
    "wof:depicts": [
      1159284261
    ],
    "wof:name": "menu: Delta Air Lines, BusinessElite Class",
    "wof:placetype": "venue"
  },
  "geometry": {"coordinates":[-122.386155,37.616357],"type":"Point"}
}
