{
  "type": "Feature",
  "properties": {
    "date:cessation_lower": "1999-12-31",
    "date:cessation_upper": "1999-12-31",
    "date:inception_lower": "1990-01-01",
    "date:inception_upper": "1990-01-01",
    "iso:country": "XX",
    "millsfield:images": [
      1527842355
    ],
    "sfomuseum:accession_number": "2003.065.158",
    "sfomuseum:airline": "Virgin Atlantic",
    "sfomuseum:category": "Passenger Amenity",
    "sfomuseum:collection": "Aviation Museum",
    "sfomuseum:creditline": "Gift of Thomas G. Dragges",
    "sfomuseum:date": "1990s",
    "sfomuseum:daterange_end": "1999-12-31",
    "sfomuseum:daterange_start": "1990-01-01",
    "sfomuseum:description": "Gusset wedge, no closure. Ivory-colored bag with gray and red print. \"Air sickness bag\" printed in top quadrant in dark gray; Virgin Atlantic logo in dark gray and red in bottom quadrant. Reverse is blank.",
    "sfomuseum:dimensions": "10 x 5 inches (25.4 x 12.7 cm)",
    "sfomuseum:media_ids": [
      1527842355
    ],
    "sfomuseum:medium": "paper, ink",
    "sfomuseum:placetype": "object",
    "sfomuseum:subcategory": "Airsickness Bag",
    "wof:depicts": [
      1159285483
    ],
    "wof:name": "airsickness bag: Virgin Atlantic",
    "wof:placetype": "venue"
  },
  "geometry": {"coordinates":[-122.386155,37.616357],"type":"Point"}
}
