{
  "type": "Feature",
  "properties": {
    "date:cessation_lower": "1981-01-01",
    "date:cessation_upper": "1981-12-31",
    "date:inception_lower": "1981-01-01",
    "date:inception_upper": "1981-12-31",
    "iso:country": "XX",
    "millsfield:images": [
      1527838989
    ],
    "millsfield:images_texts": [
      "UNITED AIRLINES\nOur Friendly Times\nJuly 2, 1981\nVol. 4\nWICHITA\nTULSA\nOKLAHOMA CTY\nCINCHHATT"
    ],
    "millsfield:images_texts_ids": [
      1527838989
    ],
    "millsfield:primary_image": 1527838989,
    "sfomuseum:accession_number": "2012.173.454",
    "sfomuseum:airline": "United Airlines",
    "sfomuseum:category": "Scheduling / Ticketing",
    "sfomuseum:collection": "Aviation Archive",
    "sfomuseum:creditline": "Gift of Willard F. Keeney",
    "sfomuseum:date": "1981",
    "sfomuseum:date_acquired": "2013-03-28",
    "sfomuseum:daterange_end": "1981-12-31",
    "sfomuseum:daterange_start": "1981-01-01",
    "sfomuseum:description": "Timetable issued by United Airlines, effective July 2, 1981; white cover with color photographic image of sunset with superimposed text \"Wichita, Tulsa, Oklahoma City, Cincinnati\"; includes route map.",
    "sfomuseum:dimensions": "9 x 4 inches (22.9 x 10.2 cm)",
    "sfomuseum:media_ids": [
      1527838989
    ],
    "sfomuseum:medium": "paper, ink",
    "sfomuseum:placetype": "object",
    "sfomuseum:publication": ": , 1981.",
    "sfomuseum:subcategory": "Timetable",
    "sfomuseum:subject": "Airlines -- Commercial -- United Air Lines",
    "wof:depicts": [
      1159285413,
      1159288779
    ],
    "wof:name": "timetable: United Airlines",
    "wof:placetype": "custom",
    "wof:placetype_alt": "object"
  },
  "geometry": {"coordinates":[-122.386155,37.616357],"type":"Point"}
}
