{
  "type": "Feature",
  "properties": {
    "date:cessation_lower": "1918-01-01",
    "date:cessation_upper": "1918-12-31",
    "date:inception_lower": "1918-01-01",
    "date:inception_upper": "1918-12-31",
    "iso:country": "XX",
    "loc:subject_headings": [
      "sh85001319"
    ],
    "sfomuseum:accession_number": "2000.160.0559",
    "sfomuseum:author": "McMinnies, William Gordon",
    "sfomuseum:callnumber": "TL710 .M36 1918b SC",
    "sfomuseum:category": "Book",
    "sfomuseum:collection": "Aviation Library",
    "sfomuseum:creditline": "The Tony Bill Aviation Library Collection",
    "sfomuseum:date": "c. 1918",
    "sfomuseum:date_acquired": "1999-05-18",
    "sfomuseum:daterange_end": "1923-12-31",
    "sfomuseum:daterange_start": "1913-01-01",
    "sfomuseum:description": "xiii p., 1 l., 246 p. incl. front., illus.  fold. map 21 cm.",
    "sfomuseum:description_library": "xiii p., 1 l., 246 p. incl. front., illus.  fold. map 21 cm.",
    "sfomuseum:medium": "paper, ink",
    "sfomuseum:placetype": "object",
    "sfomuseum:publication": "New York: George H. Doran, c. 1918.",
    "sfomuseum:publisher": "George H. Doran",
    "sfomuseum:publisher_location": "New York",
    "sfomuseum:subcategory": "Book",
    "sfomuseum:subject": "Aeronautics.",
    "wof:name": "Practical flying: complete course of flying instruction",
    "wof:placetype": "custom",
    "wof:placetype_alt": "object"
  },
  "geometry": {"coordinates":[-122.386155,37.616357],"type":"Point"}
}
