{
  "type": "Feature",
  "properties": {
    "date:cessation_lower": "2008-01-01",
    "date:cessation_upper": "2008-12-31",
    "date:inception_lower": "2008-01-01",
    "date:inception_upper": "2008-12-31",
    "isbn:number": "0785824421, 9780785824428",
    "iso:country": "XX",
    "loc:named_authorities": [
      "n78095330"
    ],
    "loc:subject_headings": [
      "sh00000231",
      "sh85002782",
      "sh85002992",
      "sh00000231"
    ],
    "sfomuseum:accession_number": "2016.130.001",
    "sfomuseum:author": "Youngblood, Wayne",
    "sfomuseum:callnumber": "TL720 .Y68 2008",
    "sfomuseum:category": "Book",
    "sfomuseum:collection": "Aviation Library",
    "sfomuseum:creditline": "Anonymous gift",
    "sfomuseum:date": "2008",
    "sfomuseum:date_acquired": "2016-11-28",
    "sfomuseum:daterange_end": "2008-12-31",
    "sfomuseum:daterange_start": "2008-01-01",
    "sfomuseum:description": "164 pages (some folded) : illustrations (some color), color maps ; 29 x 33 cm.",
    "sfomuseum:description_library": "164 pages (some folded) : illustrations (some color), color maps ; 29 x 33 cm.",
    "sfomuseum:medium": "paper, ink",
    "sfomuseum:placetype": "object",
    "sfomuseum:publication": "Edison, NJ: Chartwell Books, 2008.",
    "sfomuseum:publisher": "Chartwell Books",
    "sfomuseum:publisher_location": "Edison, NJ",
    "sfomuseum:subcategory": "Book",
    "sfomuseum:subject": "Airships -- History. \rAirships -- Pictorial works. \rAirplanes -- History. \rAirplanes -- Pictorial works. \rAntique and classic aircraft. \rTransportation -- United States -- History. \rAirplanes. \rAirships. \rAntique and classic aircraft. \rTransportation. \rUnited States. ",
    "wof:name": "The open skies",
    "wof:placetype": "custom",
    "wof:placetype_alt": "object"
  },
  "geometry": {"coordinates":[-122.386155,37.616357],"type":"Point"}
}
