{
  "type": "Feature",
  "properties": {
    "date:cessation_lower": "1960-12-31",
    "date:cessation_upper": "1960-12-31",
    "date:inception_lower": "1950-01-01",
    "date:inception_upper": "1950-01-01",
    "iso:country": "XX",
    "sfomuseum:accession_number": "2013.126.023",
    "sfomuseum:category": "Photograph",
    "sfomuseum:collection": "Aviation Archive",
    "sfomuseum:creditline": "Gift of Julian Veovich",
    "sfomuseum:date": "c. 1955",
    "sfomuseum:daterange_end": "1960-12-31",
    "sfomuseum:daterange_start": "1950-01-01",
    "sfomuseum:description": "Black and white photograph depicting KLM (Royal Dutch Airlines) employee Julian Veovich (left) and stewardess Monica Stuart standing with group of young men in front of TWA (Trans World Airlines) ramp stairs; men holding souvenir “KLM” flight bags; photo taken by Keith Cole Studio, San Francisco International Airport (SFO).",
    "sfomuseum:media_ids": [
      1527853505
    ],
    "sfomuseum:medium": "photograph",
    "sfomuseum:placetype": "object",
    "sfomuseum:subcategory": "Print, Photograph",
    "wof:name": "photograph: KLM (Royal Dutch Airlines), TWA (Trans World Airlines), San Francisco International Airport (SFO), Julian Veovich",
    "wof:placetype": "venue"
  },
  "geometry": {"coordinates":[-122.386155,37.616358],"type":"Point"}
}
