{
  "type": "Feature",
  "properties": {
    "date:cessation_lower": "1939-01-01",
    "date:cessation_upper": "1939-12-31",
    "date:inception_lower": "1939-01-01",
    "date:inception_upper": "1939-12-31",
    "iso:country": "XX",
    "millsfield:images": [
      1527838185,
      1527851123
    ],
    "millsfield:images_texts": [
      "UNITED\nAIR LINES\nThe\nMAIN LINE AIRWAY\nThe Year 'Round Route\nSEE INDEX. PAGE\nEFFECTIVE NOVEMBER 1.1939",
      "UNITED\nYEAR 'ROUND\nTHE\nMAIN LINE AIRWAY\nTWENTy years ago the Federal Gov-\nernment decided to develop the\nfirst coast-to-coast airway.\nWith the\nwhole country to choose from, the route\nthat is today United's famous Main Line\nAirway was the one selected . . . the\ndirect, short mid-continent route linking\nthe East, the Great Lakes region, and\nthe Mid-West with the entire Pacific\nCoast.\nOver this favored airway United has\nattained the unmatched record of\n140,000,000 miles of flying, including\n30,000 coast-to-coast flights and 55,000\nChicago-New York flights.\nAnd over this route United provides\nthe fastest, shortest service between the\nEast and most Pacific coast cities, in-\ncluding its famous coast-to-coast Main-\nliner sleeper service\nA"
    ],
    "millsfield:images_texts_ids": [
      1527838185,
      1527851123
    ],
    "millsfield:primary_image": 1527838185,
    "sfomuseum:accession_number": "2005.132.036.008",
    "sfomuseum:airline": "United Air Lines",
    "sfomuseum:category": "Scheduling / Ticketing",
    "sfomuseum:collection": "Aviation Archive",
    "sfomuseum:creditline": "Gift of the William Hough Collection",
    "sfomuseum:date": "1939",
    "sfomuseum:date_acquired": "2006-12-05",
    "sfomuseum:daterange_end": "1939-12-31",
    "sfomuseum:daterange_start": "1939-01-01",
    "sfomuseum:description": "Timetable issued by United Air Lines, effective November 1, 1939; 11-page fold-out; white cover with airline’s shield servicemark and text “The main line highway / Shortest, fastest - fair to fair”.",
    "sfomuseum:dimensions": "9 x 4 inches (22.9 x 10.2 cm)",
    "sfomuseum:media_ids": [
      1527838185,
      1527851123
    ],
    "sfomuseum:medium": "paper, ink",
    "sfomuseum:placetype": "object",
    "sfomuseum:publication": ": , 1939.",
    "sfomuseum:subcategory": "Timetable",
    "wof:depicts": [
      1159288779,
      1159285415
    ],
    "wof:name": "timetable: United Air Lines",
    "wof:placetype": "custom",
    "wof:placetype_alt": "object"
  },
  "geometry": {"coordinates":[-122.386155,37.616357],"type":"Point"}
}
