{
  "type": "Feature",
  "properties": {
    "date:cessation_lower": "1996-12-31",
    "date:cessation_upper": "1996-12-31",
    "date:inception_lower": "1996-01-01",
    "date:inception_upper": "1996-01-01",
    "iso:country": "XX",
    "sfomuseum:accession_number": "2006.059.101.072",
    "sfomuseum:category": "Scheduling / Ticketing",
    "sfomuseum:collection": "Aviation Archive",
    "sfomuseum:creditline": "Gift of the Paul Edward Fair Estate",
    "sfomuseum:date": "1996",
    "sfomuseum:daterange_end": "1996-12-31",
    "sfomuseum:daterange_start": "1996-01-01",
    "sfomuseum:description": "Timetable issued by United Airlines, effective October 27 through December 17, 1996. Dark red and white cover with map of the world with United destination cities illuminated in yellow. Including United Express and Shuttle by United.",
    "sfomuseum:media_ids": [
      1527840365
    ],
    "sfomuseum:medium": "paper, ink",
    "sfomuseum:placetype": "object",
    "sfomuseum:subcategory": "Timetable",
    "wof:name": "timetable: United Airlines",
    "wof:placetype": "venue"
  },
  "geometry": {"coordinates":[-122.386155,37.616358],"type":"Point"}
}
