{
  "type": "Feature",
  "properties": {
    "date:cessation_lower": "1939-01-01",
    "date:cessation_upper": "1939-12-31",
    "date:inception_lower": "1939-01-01",
    "date:inception_upper": "1939-12-31",
    "iso:country": "XX",
    "sfomuseum:accession_number": "2001.186.001",
    "sfomuseum:author": "San Francisco Bay Exposition",
    "sfomuseum:callnumber": "T876 .A12 1939 c.1 SC",
    "sfomuseum:category": "Book",
    "sfomuseum:collection": "Aviation Library",
    "sfomuseum:creditline": "Anonymous gift",
    "sfomuseum:date": "1939",
    "sfomuseum:date_acquired": "2002-11-13",
    "sfomuseum:daterange_end": "1939-12-31",
    "sfomuseum:daterange_start": "1939-01-01",
    "sfomuseum:description": "116 p.; ill., maps (1 folded), color photographs, black and white photographs. Fragile condition.",
    "sfomuseum:description_library": "116 p.; ill., maps (1 folded), color photographs, black and white photographs. Fragile condition.",
    "sfomuseum:medium": "paper, ink",
    "sfomuseum:placetype": "object",
    "sfomuseum:publication": "San Francisco, CA: Golden Gate International Exposition by The Crocker Company, 1939.",
    "sfomuseum:publisher": "Golden Gate International Exposition by The Crocker Company",
    "sfomuseum:publisher_location": "San Francisco, CA",
    "sfomuseum:subcategory": "Book",
    "sfomuseum:subject": "Golden Gate International Exposition, 1939 -- Treasure Island -- Guidebooks.\r",
    "wof:name": "Official Guide Book: Golden Gate International Exposition on San Francisco Bay. [Treasure Island, 1939]",
    "wof:placetype": "custom",
    "wof:placetype_alt": "object"
  },
  "geometry": {"coordinates":[-122.386155,37.616357],"type":"Point"}
}
