{
  "type": "Feature",
  "properties": {
    "date:cessation_lower": "1996-01-01",
    "date:cessation_upper": "1996-12-31",
    "date:inception_lower": "1996-01-01",
    "date:inception_upper": "1996-12-31",
    "isbn:number": "1857800435 (pbk.), 9781857800432 (pbk.)",
    "iso:country": "XX",
    "sfomuseum:accession_number": "1999.657.086",
    "sfomuseum:author": "Wright, Alan J. (Alan James)",
    "sfomuseum:callnumber": "HE9843.A3 W75 1996",
    "sfomuseum:category": "Book",
    "sfomuseum:collection": "Aviation Library",
    "sfomuseum:creditline": "Collection of SFO Museum",
    "sfomuseum:date": "c. 1996",
    "sfomuseum:date_acquired": "1995-05-25",
    "sfomuseum:daterange_end": "2001-12-31",
    "sfomuseum:daterange_start": "1991-01-01",
    "sfomuseum:description": "84 p. : ill. (some col.), ports. ; 21 cm.",
    "sfomuseum:description_library": "84 p. : ill. (some col.), ports. ; 21 cm.",
    "sfomuseum:medium": "paper, ink",
    "sfomuseum:placetype": "object",
    "sfomuseum:publication": "Leicester, England: Midland, c. 1996.",
    "sfomuseum:publisher": "Midland",
    "sfomuseum:publisher_location": "Leicester, England",
    "sfomuseum:subcategory": "Book",
    "sfomuseum:subject": "Aeronautics, Commercial Great Britain History.",
    "wof:name": "The British world airlines story",
    "wof:placetype": "custom",
    "wof:placetype_alt": "object"
  },
  "geometry": {"coordinates":[-122.386155,37.616357],"type":"Point"}
}
