{
  "type": "Feature",
  "properties": {
    "date:cessation_lower": "1950-01-01",
    "date:cessation_upper": "1950-12-31",
    "date:inception_lower": "1950-01-01",
    "date:inception_upper": "1950-12-31",
    "iso:country": "XX",
    "millsfield:images": [
      1527845621
    ],
    "millsfield:images_texts": [
      "BUFFALO\nLEVELAND\nLOUISVILLE\nOXLAROMA CIT\nDALLAS\nWe Shine where the Sun does!\nOthcial Weather bureau ngures show\nsummer sunshine all winter long\non the Southern Route of the Flagships\nJ's are at or lose an aspect rom Decenter wugh\nFebruary along the southern Sunshine Koute that Flagships\ntravelers bound for California, Mexico or the Sun Country.\nthat people want to go, stops at most of the sights that people\nSosit vou like to follow the sun on your winter vacation. vou\nwant to see. And friendly Paoshin service makes.\nprobabl v find it beaming from the moment vou step aboard vour\nof your journey as bright and enjoyable\nFlagship. No wonder American Airlines is the first choice of\nas the sunshine around you.\nAmericas Leading Airline AMERICAN AIRLINES NC.\nReprint of 4-color spread advertisement appearing in Saturday Evening Post, October 28th; Life, November 6th and Time, November 6th."
    ],
    "millsfield:images_texts_ids": [
      1527845621
    ],
    "millsfield:primary_image": 1527845621,
    "sfomuseum:accession_number": "2013.049.002",
    "sfomuseum:airline": "American Airlines",
    "sfomuseum:category": "Promotional, Archive",
    "sfomuseum:collection": "Aviation Archive",
    "sfomuseum:creditline": "Gift of Schein \u0026 Schein Maps",
    "sfomuseum:date": "1950",
    "sfomuseum:date_acquired": "2013-07-16",
    "sfomuseum:daterange_end": "1950-12-31",
    "sfomuseum:daterange_start": "1950-01-01",
    "sfomuseum:description": "Color route map produced by American Airlines; topographical map of United States with “Sunshine Route” depicted with icons representing the number of average sunny days from December through February; reproduced from Saturday Evening Post, October 28; Life Magazine, November 6; Time Magazine, November 6.",
    "sfomuseum:dimensions": "16 x 22 inches (40.6 x 55.9 cm)",
    "sfomuseum:media_ids": [
      1527845621
    ],
    "sfomuseum:medium": "paper, ink",
    "sfomuseum:placetype": "object",
    "sfomuseum:publication": ": , 1950.",
    "sfomuseum:subcategory": "Advertisement, 2D",
    "sfomuseum:subject": "Airlines -- Commercial -- American Airlines.\rAdvertisements -- American Airlines.\rAirlines -- Advertisements.",
    "wof:depicts": [
      1159283849,
      1360700619
    ],
    "wof:name": "advertisement: American Airlines, Sunshine route",
    "wof:placetype": "custom",
    "wof:placetype_alt": "object"
  },
  "geometry": {"coordinates":[-122.386155,37.616357],"type":"Point"}
}
