{
  "type": "Feature",
  "properties": {
    "date:cessation_lower": "1950-01-01",
    "date:cessation_upper": "1950-12-31",
    "date:inception_lower": "1950-01-01",
    "date:inception_upper": "1950-12-31",
    "iso:country": "XX",
    "millsfield:images": [
      1527845621
    ],
    "millsfield:primary_image": 1527845621,
    "sfomuseum:accession_number": "2013.049.002",
    "sfomuseum:airline": "American Airlines",
    "sfomuseum:category": "Promotional",
    "sfomuseum:collection": "Aviation Archive",
    "sfomuseum:creditline": "Gift of Schein \u0026 Schein Maps",
    "sfomuseum:date": "1950",
    "sfomuseum:daterange_end": "1950-12-31",
    "sfomuseum:daterange_start": "1950-01-01",
    "sfomuseum:description": "Color route map produced by American Airlines; topographical map of United States with “Sunshine Route” depicted with icons representing the number of average sunny days from December through February. Reproduced from Saturday Evening Post, October 28; Life Magazine, November 6; Time Magazine, November 6.",
    "sfomuseum:dimensions": "16 x 22 inches (40.6 x 55.9 cm)",
    "sfomuseum:media_ids": [
      1527845621
    ],
    "sfomuseum:medium": "paper, ink",
    "sfomuseum:placetype": "object",
    "sfomuseum:publication": ": , 1950.",
    "sfomuseum:subcategory": "Advertisement, 2D",
    "sfomuseum:subject": "Airlines -- Commercial -- American Airlines.\rAdvertisements -- American Airlines.\rAirlines -- Advertisements.",
    "wof:depicts": [
      1159283849
    ],
    "wof:name": "advertisement: American Airlines, Sunshine route",
    "wof:placetype": "venue"
  },
  "geometry": {"coordinates":[-122.386155,37.616357],"type":"Point"}
}
