{
  "type": "Feature",
  "properties": {
    "date:cessation_lower": "1950-12-31",
    "date:cessation_upper": "1950-12-31",
    "date:inception_lower": "1950-01-01",
    "date:inception_upper": "1950-01-01",
    "iso:country": "XX",
    "sfomuseum:accession_number": "2013.049.002",
    "sfomuseum:category": "Promotional",
    "sfomuseum:collection": "Aviation Archive",
    "sfomuseum:creditline": "Gift of Schein \u0026 Schein Maps",
    "sfomuseum:date": "1950",
    "sfomuseum:daterange_end": "1950-12-31",
    "sfomuseum:daterange_start": "1950-01-01",
    "sfomuseum:description": "Color route map produced by American Airlines; topographical map of United States with “Sunshine Route” depicted with icons representing the number of average sunny days from December through February. Reproduced from Saturday Evening Post, October 28; Life Magazine, November 6; Time Magazine, November 6.",
    "sfomuseum:media_ids": [
      1527845621
    ],
    "sfomuseum:medium": "lithograph, paper",
    "sfomuseum:placetype": "object",
    "sfomuseum:subcategory": "Advertisement, 2D",
    "wof:name": "advertisement: American Airlines, Sunshine route",
    "wof:placetype": "venue"
  },
  "geometry": {"coordinates":[-122.386155,37.616358],"type":"Point"}
}
