{
  "type": "Feature",
  "properties": {
    "date:cessation_lower": "2003-01-01",
    "date:cessation_upper": "2003-12-31",
    "date:inception_lower": "2003-01-01",
    "date:inception_upper": "2003-12-31",
    "iso:country": "XX",
    "loc:subject_heading": {
      "sh85002650": "Airlines"
    },
    "sfomuseum:accession_number": "2008.044.020",
    "sfomuseum:author": "Taneja, Nawal K.",
    "sfomuseum:callnumber": "HE9776 .T358 2003",
    "sfomuseum:category": "Book",
    "sfomuseum:collection": "Aviation Library",
    "sfomuseum:creditline": "Gift of Michael Roach",
    "sfomuseum:date": "2003",
    "sfomuseum:daterange_end": "2003-12-31",
    "sfomuseum:daterange_start": "2003-01-01",
    "sfomuseum:description": "xxx, 191 p. : ill., maps ; 24 cm.",
    "sfomuseum:medium": "paper, ink",
    "sfomuseum:placetype": "object",
    "sfomuseum:publication": "Aldershot, Hants, England; Burlington, VT: Ashgate, 2003.",
    "sfomuseum:publisher": "Ashgate",
    "sfomuseum:publisher_location": "Aldershot, Hants, England; Burlington, VT",
    "sfomuseum:subcategory": "Book",
    "sfomuseum:subject": "Airlines.",
    "wof:name": "Airline survival kit: breaking out of the zero profit game",
    "wof:placetype": "venue"
  },
  "geometry": {"coordinates":[-122.386155,37.616357],"type":"Point"}
}
