{
  "type": "Feature",
  "properties": {
    "date:cessation_lower": "1980-01-01",
    "date:cessation_upper": "1980-12-31",
    "date:inception_lower": "1980-01-01",
    "date:inception_upper": "1980-12-31",
    "iso:country": "XX",
    "millsfield:images": [
      1527853181,
      1746281537
    ],
    "millsfield:primary_image": 1746281537,
    "sfomuseum:accession_number": "2013.095.027",
    "sfomuseum:airline": "Pan American World Airways",
    "sfomuseum:category": "Passenger Amenity, Archive",
    "sfomuseum:collection": "Aviation Archive",
    "sfomuseum:creditline": "Gift of the Estate of Jane Gottschall",
    "sfomuseum:date": "1980",
    "sfomuseum:date_acquired": "2014-05-21",
    "sfomuseum:daterange_end": "1980-12-31",
    "sfomuseum:daterange_start": "1980-01-01",
    "sfomuseum:description": "Menu issued by Pan American World Airways for Pan Am Management Club Gala Dinner, dated August 26, 1980; color reproduction of print titled “Sovereign of the Seas”; includes list of employees in management retiring in September 1980.",
    "sfomuseum:dimensions": "10 x 12 1/2 inches (25.4 x 31.8 cm)",
    "sfomuseum:media_ids": [
      1527853181
    ],
    "sfomuseum:medium": "paper, ink",
    "sfomuseum:placetype": "object",
    "sfomuseum:publication": ": , 1980.",
    "sfomuseum:subcategory": "Menu",
    "wof:depicts": [
      1159286839,
      1159284989
    ],
    "wof:name": "menu: Pan American World Airways",
    "wof:placetype": "custom",
    "wof:placetype_alt": "object"
  },
  "geometry": {"coordinates":[-122.386155,37.616357],"type":"Point"}
}
