{
  "type": "Feature",
  "properties": {
    "date:cessation_lower": "1980-01-01",
    "date:cessation_upper": "1980-12-31",
    "date:inception_lower": "1980-01-01",
    "date:inception_upper": "1980-12-31",
    "iso:country": "XX",
    "millsfield:images": [
      1527853181,
      1746281537,
      1863469941,
      1863469943,
      1863469945
    ],
    "millsfield:images_texts": [
      "To Demald Mo Key arg breller of the Magnifecand\nCLIPPER SHIP \"SOVEREIGN OF THE SEAS\"\nprint is soups alfally dediated by the Pallache.",
      "I. Donald Me Kary as builder of the\nCLIPPER SHIP «SOVEREIGN OF THE SEAS\nI be ok",
      "FAN AM MANAGEMENT CLUB\nGALA DINNER\nHonoring San Francisco Management\nEmployees\nRetiring September 1, 1980\nAirport Sheraton Hotel\n7 p.m.\nAugust 26, 1980\nCLASS OF 1980\nSam Acust\nRenania\nBob Johns\nBB8\n858:52858888\nCal Kennard\nSam sinoshss\nari Koense\nTheer Lilie\nDave Malones\nBel Marsh\nJoe Maschewssi\nTrentesameneli\nKinssare\nCeciNente\nTra a orde rom\nJohn Oakes\nMinO\nCliff Pierce\nFrank Quigley\nJim Robinson\nFrank Scott\nShores\n8888\nYEARS O\n88888575388886585",
      "MENU\nTossed Green Garden Salad\n\"Chef's Dressing\nRoast Prime Rib of Beef au jus Royal Cut\nRoasted New Potatoes with Butter and Paprika\nStringbeans with Almonds\nRolls\nButter\nDessert\nCoffee\nTea\nAlmaden Cabernet Sauvignon\nAlmaden Pinot Chardonnay\n- 16. 16. 18-1-16-",
      "+20 260'2106"
    ],
    "millsfield:images_texts_ids": [
      1527853181,
      1746281537,
      1863469941,
      1863469943,
      1863469945
    ],
    "millsfield:primary_image": 1746281537,
    "sfomuseum:accession_number": "2013.095.027",
    "sfomuseum:airline": "Pan American World Airways",
    "sfomuseum:category": "Passenger Amenity, Archive",
    "sfomuseum:collection": "Aviation Archive",
    "sfomuseum:creditline": "Gift of the Estate of Jane Gottschall",
    "sfomuseum:date": "1980",
    "sfomuseum:date_acquired": "2014-05-21",
    "sfomuseum:daterange_end": "1980-12-31",
    "sfomuseum:daterange_start": "1980-01-01",
    "sfomuseum:description": "Menu issued by Pan American World Airways for Pan Am Management Club Gala Dinner, dated August 26, 1980; color reproduction of print titled “Sovereign of the Seas”; includes list of employees in management retiring in September 1980.",
    "sfomuseum:dimensions": "10 x 12 1/2 inches (25.4 x 31.8 cm)",
    "sfomuseum:media_ids": [
      1527853181
    ],
    "sfomuseum:medium": "paper, ink",
    "sfomuseum:placetype": "object",
    "sfomuseum:publication": ": , 1980.",
    "sfomuseum:subcategory": "Menu",
    "wof:depicts": [
      1159284989,
      1159286839
    ],
    "wof:name": "menu: Pan American World Airways",
    "wof:placetype": "custom",
    "wof:placetype_alt": "object"
  },
  "geometry": {"coordinates":[-122.386155,37.616357],"type":"Point"}
}
