{
  "type": "Feature",
  "properties": {
    "date:cessation_lower": "1953-01-01",
    "date:cessation_upper": "1953-12-31",
    "date:inception_lower": "1953-01-01",
    "date:inception_upper": "1953-12-31",
    "iso:country": "XX",
    "sfomuseum:accession_number": "1999.669.148",
    "sfomuseum:author": "Arpee, Edward",
    "sfomuseum:callnumber": "E746.M6 A7 1953",
    "sfomuseum:category": "Book",
    "sfomuseum:collection": "Aviation Library",
    "sfomuseum:creditline": "Purchase",
    "sfomuseum:date": "1953",
    "sfomuseum:daterange_end": "1953-12-31",
    "sfomuseum:daterange_start": "1953-01-01",
    "sfomuseum:description": "xx, 276 p. illus. 27 cm.",
    "sfomuseum:description_library": "xx, 276 p. illus. 27 cm.",
    "sfomuseum:medium": "paper, ink",
    "sfomuseum:placetype": "object",
    "sfomuseum:publication": "Lake Forest, IL: , 1953.",
    "sfomuseum:publisher_location": "Lake Forest, IL",
    "sfomuseum:subcategory": "Book",
    "sfomuseum:subject": "Moffett, William Adger, 1869-1933.Aeronautics, Military United States.",
    "wof:name": "From frigates to flat-tops: the story of the life and achievements of Rear Admiral William Adger Moffett, U.S.N.,  the father of naval aviation, October 31, 1869-April 4, 1933",
    "wof:placetype": "custom",
    "wof:placetype_alt": "object"
  },
  "geometry": {"coordinates":[-122.386155,37.616357],"type":"Point"}
}
