{
  "type": "Feature",
  "properties": {
    "date:cessation_lower": "1963-01-01",
    "date:cessation_upper": "1963-12-31",
    "date:inception_lower": "1963-01-01",
    "date:inception_upper": "1963-12-31",
    "iso:country": "US",
    "millsfield:images": [
      1527842841,
      1527851253
    ],
    "millsfield:images_texts": [
      "West Coast Airlines\nInstant Schedule • Effective April 28, 1963",
      "Port Angeles\nAberdeen/Hoquiam\nAstoria\nPortland/Vancouver\nCorvallis/ Albany\nCoos Bay\nNorth Bend\nRoseburg\nMedford\nEugene\nBellingham\nWASHINGTON\nSeattle\nWenatchee\nSpokane\nOlympia\nYakima\nEphrata\n\"Moses\nLake\nKennewick\nRichland\nPasco\nWalla\nPendleton\nSalem\nOREGON\n• Baker\nBend/Redmond\nPayette/Ontario\nBurns\nBoise\nLakeview\nWest Coast Airlines\nCalgary\nALBERTA\nShelby/Cut Bank\nKalispell\nCoeur d'Alene\nGreat Falls\nMoscow/Pullman\nLewiston/Clarkston\nMONTANA\nIDAHO\nKlamath\nFalls\nCALIFORNIA\nTwin Falls\nNEVADA\nSun Valley/Hailey/Ketchum\nIdaho Falls\nPocatello\nBurley/Rupert\nLogan\nSalt Lake City\nUTAH\nSacramento\n• Oakland\nSan Francisco"
    ],
    "millsfield:images_texts_ids": [
      1527842841,
      1527851253
    ],
    "millsfield:primary_image": 1527842841,
    "sfomuseum:accession_number": "1999.015.232",
    "sfomuseum:airline": "West Coast Airlines",
    "sfomuseum:category": "Scheduling / Ticketing",
    "sfomuseum:collection": "Aviation Archive",
    "sfomuseum:continent": "North America",
    "sfomuseum:country": "United States",
    "sfomuseum:creditline": "Gift of Homer Hudson",
    "sfomuseum:date": "1963",
    "sfomuseum:date_acquired": "1999-07-06",
    "sfomuseum:daterange_end": "1963-12-31",
    "sfomuseum:daterange_start": "1963-01-01",
    "sfomuseum:description": "Instant schedule issued by West Coast Airlines effective April 28, 1963; white cover with black logo.",
    "sfomuseum:dimensions": "9 x 4 inches (22.9 x 10.2 cm)",
    "sfomuseum:media_ids": [
      1527842841,
      1527851253
    ],
    "sfomuseum:medium": "paper, ink",
    "sfomuseum:placetype": "object",
    "sfomuseum:publication": ": , 1963.",
    "sfomuseum:subcategory": "Timetable",
    "wof:depicts": [
      1159285505,
      1159287343
    ],
    "wof:name": "timetable: West Coast Airlines",
    "wof:placetype": "custom",
    "wof:placetype_alt": "object"
  },
  "geometry": {"coordinates":[-122.386155,37.616357],"type":"Point"}
}
