{
  "type": "Feature",
  "properties": {
    "date:cessation_lower": "2010-12-31",
    "date:cessation_upper": "2010-12-31",
    "date:inception_lower": "2000-01-01",
    "date:inception_upper": "2000-01-01",
    "iso:country": "XX",
    "millsfield:images": [
      1527843669,
      1527843667,
      1527844609,
      1527844611
    ],
    "sfomuseum:accession_number": "2006.034.075 a b",
    "sfomuseum:airline": "Cathay Pacific Airways",
    "sfomuseum:category": "Passenger Amenity",
    "sfomuseum:collection": "Aviation Archive",
    "sfomuseum:creditline": "Gift of Adan Wong",
    "sfomuseum:date": "c. 2005",
    "sfomuseum:daterange_end": "2010-12-31",
    "sfomuseum:daterange_start": "2000-01-01",
    "sfomuseum:description": "Menu and wine list issued by Cathay Pacific Airways, Hong Kong - Bangkok route; white cover with color photographic image of snow peas in water; dinner menu items include braised chicken and pan-fried halibut.\ra. menu; menu number: CX7703B-2484J \u003cJUL\u003e; class: business; undated\rb. wine list; menu number CX701/703 (HKG/BKK/CMB/KHI), 721, 723, 725, 751 (HKG/BKK/BOM/DXB), 753, 777, 781, 785, 787; class: business; date: 1-6-2005",
    "sfomuseum:media_ids": [
      1527843667,
      1527843669,
      1527844609,
      1527844611
    ],
    "sfomuseum:medium": "paper, ink, string",
    "sfomuseum:placetype": "object",
    "sfomuseum:subcategory": "Menu",
    "wof:depicts": [
      1159284127
    ],
    "wof:name": "menu: Cathay Pacific Airways, Business Class",
    "wof:placetype": "venue"
  },
  "geometry": {"coordinates":[-122.386155,37.616357],"type":"Point"}
}
