{
  "type": "Feature",
  "properties": {
    "date:cessation_lower": "1961-01-01",
    "date:cessation_upper": "1961-12-31",
    "date:inception_lower": "1961-01-01",
    "date:inception_upper": "1961-12-31",
    "iso:country": "XX",
    "millsfield:images": [
      1527820725,
      1527853423
    ],
    "millsfield:primary_image": 1527820725,
    "sfomuseum:accession_number": "2008.055.992",
    "sfomuseum:aircraft": "Convair 880",
    "sfomuseum:airline": "Northeast Airlines",
    "sfomuseum:category": "Promotional, Archive",
    "sfomuseum:collection": "Aviation Archive",
    "sfomuseum:creditline": "Gift of the William Hough Collection",
    "sfomuseum:date": "c. 1961",
    "sfomuseum:date_acquired": "2008-04-13",
    "sfomuseum:daterange_end": "1966-12-31",
    "sfomuseum:daterange_start": "1956-01-01",
    "sfomuseum:description": "Brochure issued by Northeast Airlines promoting general service; color photographic image on cover depicting close-up view of Convair 880 engine; interior contains images of cabin service, interior, seating chart, and engine with general description and technical data; eight pages.",
    "sfomuseum:dimensions": "12 1/2 x 9 1/4 inches (31.8 x 23.5 cm)",
    "sfomuseum:media_ids": [
      1527853423,
      1527820725
    ],
    "sfomuseum:medium": "paper, metal, ink",
    "sfomuseum:placetype": "object",
    "sfomuseum:publication": ": , c. 1961.",
    "sfomuseum:subcategory": "Brochure, Airline",
    "sfomuseum:subject": "Airlines -- Commercial -- Northeast Airlines",
    "wof:depicts": [
      1159288917,
      1159284893,
      1159290217
    ],
    "wof:name": "brochure: Northeast Airlines",
    "wof:placetype": "custom",
    "wof:placetype_alt": "object"
  },
  "geometry": {"coordinates":[-122.386155,37.616357],"type":"Point"}
}
