{
  "type": "Feature",
  "properties": {
    "date:cessation_lower": "1955-01-01",
    "date:cessation_upper": "1955-12-31",
    "date:inception_lower": "1955-01-01",
    "date:inception_upper": "1955-12-31",
    "iso:country": "XX",
    "millsfield:images": [
      1527830431
    ],
    "millsfield:images_texts": [
      "САЛ\nCivil Air Tranaport Pra"
    ],
    "millsfield:images_texts_ids": [
      1527830431
    ],
    "millsfield:primary_image": 1527830431,
    "sfomuseum:accession_number": "2011.061.0745",
    "sfomuseum:airline": "Civil Air Transport (CAT)",
    "sfomuseum:category": "Promotional, Archive",
    "sfomuseum:collection": "Aviation Archive",
    "sfomuseum:creditline": "Gift of the Frank J. Lichtanski Collection",
    "sfomuseum:date": "c. 1955",
    "sfomuseum:date_acquired": "2011-08-02",
    "sfomuseum:daterange_end": "1960-12-31",
    "sfomuseum:daterange_start": "1950-01-01",
    "sfomuseum:description": "Luggage label promoting Civil Air Transport (CAT); circular shape, red “CAT” initials and yellow cat logo.",
    "sfomuseum:dimensions": "3 1/2 x 3 1/2 inches (8.9 x 8.9 cm)",
    "sfomuseum:media_ids": [
      1527830431
    ],
    "sfomuseum:medium": "paper, ink, adhesive",
    "sfomuseum:placetype": "object",
    "sfomuseum:publication": ": , c. 1955.",
    "sfomuseum:subcategory": "Luggage Label",
    "wof:depicts": [
      1159284179,
      1159288589
    ],
    "wof:name": "luggage label: Civil Air Transport (CAT)",
    "wof:placetype": "custom",
    "wof:placetype_alt": [
      "object"
    ]
  },
  "geometry": {"coordinates":[-122.386155,37.616357],"type":"Point"}
}
