{
  "type": "Feature",
  "properties": {
    "date:cessation_lower": "1999-01-01",
    "date:cessation_upper": "1999-12-31",
    "date:inception_lower": "1999-01-01",
    "date:inception_upper": "1999-12-31",
    "iso:country": "XX",
    "sfomuseum:accession_number": "2000.176.001",
    "sfomuseum:airline": "TWA (Trans World Airlines)",
    "sfomuseum:author": "Stoller, Ezra",
    "sfomuseum:callnumber": "NA6303.N5 T83 1999",
    "sfomuseum:category": "Book",
    "sfomuseum:collection": "Aviation Library",
    "sfomuseum:date": "1999",
    "sfomuseum:daterange_end": "1999-12-31",
    "sfomuseum:daterange_start": "1999-01-01",
    "sfomuseum:description": "p. cm.",
    "sfomuseum:description_library": "p. cm.",
    "sfomuseum:medium": "paper, ink",
    "sfomuseum:placetype": "object",
    "sfomuseum:publication": "New York: Princeton Architectural Press, 1999.",
    "sfomuseum:publisher": "Princeton Architectural Press",
    "sfomuseum:publisher_location": "New York",
    "sfomuseum:series": "The Building blocks series",
    "sfomuseum:subcategory": "Book",
    "sfomuseum:subject": "Saarinen, Eero, 1910-1961 Criticism and interpretation.John F. Kennedy International Airport Trans World Airline Terminal Building Pictorial works.New York (N.Y.) Buildings, structures, etc. Pictorial works.",
    "wof:depicts": [
      1159285393
    ],
    "wof:name": "The TWA Terminal",
    "wof:placetype": "venue"
  },
  "geometry": {"coordinates":[-122.386155,37.616357],"type":"Point"}
}
