{
  "type": "Feature",
  "properties": {
    "date:cessation_lower": "1955-01-01",
    "date:cessation_upper": "1955-12-31",
    "date:inception_lower": "1955-01-01",
    "date:inception_upper": "1955-12-31",
    "iso:country": "XX",
    "millsfield:images": [
      1527819293
    ],
    "millsfield:primary_image": 1527819293,
    "sfomuseum:accession_number": "2011.061.0739",
    "sfomuseum:airline": "Chicago \u0026 Southern Air Lines (C\u0026S)",
    "sfomuseum:category": "Scheduling / Ticketing",
    "sfomuseum:collection": "Aviation Archive",
    "sfomuseum:creditline": "Gift of the Frank J. Lichtanski Collection",
    "sfomuseum:date": "c. 1955",
    "sfomuseum:date_acquired": "2011-08-02",
    "sfomuseum:daterange_end": "1960-12-31",
    "sfomuseum:daterange_start": "1950-01-01",
    "sfomuseum:description": "Luggage identification label issued by Chicago and Southern Air Lines; rectangular shape, yellow and white with black printed “CS” logo followed by blank spaces for personal identification.",
    "sfomuseum:dimensions": "3 x 4 3/4 inches (7.6 x 12.1 cm)",
    "sfomuseum:media_ids": [
      1527819293
    ],
    "sfomuseum:medium": "paper, ink, adhesive",
    "sfomuseum:placetype": "object",
    "sfomuseum:publication": ": , c. 1955.",
    "sfomuseum:subcategory": "Identification Tag / Form, Paper",
    "wof:depicts": [
      1159284263,
      1159287931
    ],
    "wof:name": "luggage identification label: Chicago \u0026 Southern Air Lines (C\u0026S)",
    "wof:placetype": "custom",
    "wof:placetype_alt": "object"
  },
  "geometry": {"coordinates":[-122.386155,37.616357],"type":"Point"}
}
