{
  "type": "Feature",
  "properties": {
    "date:cessation_lower":"1929-12-31",
    "date:cessation_upper":"1929-12-31",
    "date:inception_lower":"1929-01-01",
    "date:inception_upper":"1929-01-01",
    "iso:country":"XX",
    "sfomuseum:accession_number":"2000.018.064.012",
    "sfomuseum:category":"Company Record / Document",
    "sfomuseum:collection":"Aviation Archive",
    "sfomuseum:creditline":"Transfer from City and County of San Francisco",
    "sfomuseum:date":"1929",
    "sfomuseum:daterange_end":"1929-12-31",
    "sfomuseum:daterange_start":"1929-01-01",
    "sfomuseum:description":"Typed facsimile of correspondence from Lt. Col. Gerald C. Brandt, Crissy Field, Presidio of San Francisco, to Milo H. Kent, Chairman of Airport Committee of San Francisco Board of Supervisors, dated September 23, 1929, concerning title to Mills Field Municipal Airport; file copy, not signed.",
    "sfomuseum:media_ids":[
        1527857053
    ],
    "sfomuseum:medium":"paper, ink",
    "sfomuseum:placetype":"object",
    "sfomuseum:subcategory":"Correspondence, Company",
    "wof:depicts":[
        85865991,
        85922583,
        85688637,
        85633793
    ],
    "wof:name":"correspondence: Presidio of San Francisco, Airport Committee of Board of Supervisors, Mills Field Municipal Airport of San Francisco",
    "wof:placetype":"venue"
},
  "geometry": {"coordinates":[-122.386155,37.616358],"type":"Point"}
}