{
  "type": "Feature",
  "properties": {
    "date:cessation_lower":"1932-12-31",
    "date:cessation_upper":"1932-12-31",
    "date:inception_lower":"1932-01-01",
    "date:inception_upper":"1932-01-01",
    "iso:country":"XX",
    "sfomuseum:accession_number":"2012.149.1619",
    "sfomuseum:category":"Philately",
    "sfomuseum:collection":"Aviation Archive",
    "sfomuseum:creditline":"Gift of the Captain John B. Russell Family",
    "sfomuseum:date":"06/15/1932",
    "sfomuseum:daterange_end":"1932-06-15",
    "sfomuseum:daterange_start":"1932-06-15",
    "sfomuseum:description":"Airmail flight cover, American Airways first airmail flight, AM-33 from San Diego, California; signed by pilot Hap Russell and postmaster [illegible]; purple cachet at lower left depicting palm tree; postmarked June 15, 1932 in San Diego with \u201cAir mail saves time\u201d cancellation mark over 5-cent postage stamp; no backstamp; addressed to William Couter.",
    "sfomuseum:media_ids":[
        1527833721,
        1527833723
    ],
    "sfomuseum:medium":"paper, ink",
    "sfomuseum:placetype":"object",
    "sfomuseum:subcategory":"Airmail Flight Cover",
    "wof:name":"airmail flight cover: American Airways, first airmail flight, AM-33, San Diego",
    "wof:placetype":"venue"
},
  "geometry": {"coordinates":[-122.386155,37.616358],"type":"Point"}
}