{
  "type": "Feature",
  "properties": {
    "date:cessation_lower": "2003-01-01",
    "date:cessation_upper": "2003-12-31",
    "date:inception_lower": "2003-01-01",
    "date:inception_upper": "2003-12-31",
    "iso:country": "XX",
    "loc:named_authorities": [
      "n79063636"
    ],
    "sfomuseum:accession_number": "2004.004.047",
    "sfomuseum:author": "Hoffman, Paul",
    "sfomuseum:callnumber": "TL540.S25 H64 2003",
    "sfomuseum:category": "Book",
    "sfomuseum:collection": "Aviation Library",
    "sfomuseum:creditline": "Purchase",
    "sfomuseum:date": "c. 2003",
    "sfomuseum:daterange_end": "2008-12-31",
    "sfomuseum:daterange_start": "1998-01-01",
    "sfomuseum:description": "ix, 369 p. : ill. ; 22 cm.",
    "sfomuseum:medium": "paper, ink",
    "sfomuseum:placetype": "object",
    "sfomuseum:publication": "New York: Theia, c. 2003.",
    "sfomuseum:publisher": "Theia",
    "sfomuseum:publisher_location": "New York",
    "sfomuseum:subcategory": "Book",
    "sfomuseum:subject": "Santos-Dumont, Alberto, 1873-1932.",
    "wof:name": "Wings of madness: Alberto Santos-Dumont and the invention of flight",
    "wof:placetype": "venue"
  },
  "geometry": {"coordinates":[-122.386155,37.616357],"type":"Point"}
}
