{
  "type": "Feature",
  "properties": {
    "date:cessation_lower": "1990-01-01",
    "date:cessation_upper": "1999-12-31",
    "date:inception_lower": "1990-01-01",
    "date:inception_upper": "1999-12-31",
    "iso:country": "XX",
    "millsfield:images": [
      1527824395,
      1527824397
    ],
    "millsfield:primary_image": 1527824395,
    "sfomuseum:accession_number": "1998.157.093",
    "sfomuseum:airline": "Croatia Airlines",
    "sfomuseum:category": "Passenger Amenity",
    "sfomuseum:collection": "Aviation Archive",
    "sfomuseum:creditline": "Gift of The Henry Steiner Air Sickness Bag Collection",
    "sfomuseum:date": "1990s",
    "sfomuseum:date_acquired": "1999-07-13",
    "sfomuseum:daterange_end": "1999-12-31",
    "sfomuseum:daterange_start": "1990-01-01",
    "sfomuseum:description": "Gusset wedge, no closure. Gray bag, red and blue print. \"Croatia Airlines\" in blue on lower portion of bag. To left is red triangle. White stripe along bottom edge. Design is on both sides.",
    "sfomuseum:dimensions": "10 x 6 inches (25.4 x 15.2 cm)",
    "sfomuseum:media_ids": [
      1527824395,
      1527824397
    ],
    "sfomuseum:medium": "paper",
    "sfomuseum:placetype": "object",
    "sfomuseum:publication": ": , 1990s.",
    "sfomuseum:subcategory": "Airsickness Bag",
    "wof:depicts": [
      1159284219
    ],
    "wof:name": "airsickness bag: Croatia Airlines",
    "wof:placetype": "venue"
  },
  "geometry": {"coordinates":[-122.386155,37.616357],"type":"Point"}
}
