{
  "type": "Feature",
  "properties": {
    "date:cessation_lower": "1948-01-01",
    "date:cessation_upper": "1948-12-31",
    "date:inception_lower": "1948-01-01",
    "date:inception_upper": "1948-12-31",
    "iso:country": "XX",
    "sfomuseum:accession_number": "00-3209",
    "sfomuseum:author": "Great Britain. Ministry of Supply",
    "sfomuseum:callnumber": "TL671.1 .G75 1948 SC",
    "sfomuseum:category": "Book",
    "sfomuseum:collection": "Aviation Library",
    "sfomuseum:date": "1948",
    "sfomuseum:daterange_end": "1948-12-31",
    "sfomuseum:daterange_start": "1948-01-01",
    "sfomuseum:description": "1 v. (loose leaf) 26 cm.",
    "sfomuseum:medium": "paper, ink",
    "sfomuseum:placetype": "object",
    "sfomuseum:publisher": "H. M. Stationery Office",
    "sfomuseum:publisher_location": "London",
    "sfomuseum:series": "Great Britain. Air Ministry. Air publication 970",
    "sfomuseum:subcategory": "Book",
    "sfomuseum:subject": "Airplanes Specifications.",
    "wof:name": "Design requirements for aeroplanes for the Royal Air Force and Royal Navy",
    "wof:placetype": "venue"
  },
  "geometry": {"coordinates":[-122.386155,37.616357],"type":"Point"}
}
