{
  "type": "Feature",
  "properties": {
    "date:cessation_lower": "2005-01-01",
    "date:cessation_upper": "2005-12-31",
    "date:inception_lower": "2005-01-01",
    "date:inception_upper": "2005-12-31",
    "isbn:number": "393771832X, 9783937718323",
    "iso:country": "XX",
    "sfomuseum:accession_number": "2007.056.055",
    "sfomuseum:callnumber": "TL725 .A37 2005",
    "sfomuseum:category": "Book",
    "sfomuseum:collection": "Aviation Library",
    "sfomuseum:creditline": "Collection of SFO Museum",
    "sfomuseum:date": "2005",
    "sfomuseum:date_acquired": "2007-07-17",
    "sfomuseum:daterange_end": "2005-12-31",
    "sfomuseum:daterange_start": "2005-01-01",
    "sfomuseum:description": "399 p. : col. ill. ; 24 cm.",
    "sfomuseum:description_library": "399 p. : col. ill. ; 24 cm.",
    "sfomuseum:medium": "paper, ink",
    "sfomuseum:placetype": "object",
    "sfomuseum:publication": "Cologne (Köln); London: Daab, 2005.",
    "sfomuseum:publisher": "Daab",
    "sfomuseum:publisher_location": "Cologne (Köln); London",
    "sfomuseum:subcategory": "Book",
    "sfomuseum:subject": "Airports Design and construction.",
    "wof:name": "Airport design",
    "wof:placetype": "custom",
    "wof:placetype_alt": "object"
  },
  "geometry": {"coordinates":[-122.386155,37.616357],"type":"Point"}
}
