{
  "type": "Feature",
  "properties": {
    "date:cessation_lower": "1967-12-31",
    "date:cessation_upper": "1967-12-31",
    "date:inception_lower": "1967-01-01",
    "date:inception_upper": "1967-01-01",
    "iso:country": "XX",
    "millsfield:images": [
      1527825651
    ],
    "sfomuseum:accession_number": "2011.032.1481",
    "sfomuseum:airport": "San Francisco International Airport",
    "sfomuseum:artist": "Marshall Moxom",
    "sfomuseum:category": "Photograph",
    "sfomuseum:collection": "Aviation Archive",
    "sfomuseum:creditline": "Transfer",
    "sfomuseum:date": "1967",
    "sfomuseum:daterange_end": "1967-12-31",
    "sfomuseum:daterange_start": "1967-01-01",
    "sfomuseum:description": "From attached handwritten note: “03340 / 4-25-67 / S. Terminal ventilator fire damage. / taken by: Moxom”. Black and white photographic negative depicting a bucket on its side with burned and broken material spilling out; San Francisco International Airport (SFO); photograph taken by Marshall Moxom on April 25, 1967.",
    "sfomuseum:media_ids": [
      1527825651
    ],
    "sfomuseum:medium": "negative",
    "sfomuseum:placetype": "object",
    "sfomuseum:subcategory": "Negative",
    "wof:depicts": [
      102527513
    ],
    "wof:name": "negative: San Francisco International Airport (SFO), South Terminal, fire damage",
    "wof:placetype": "venue"
  },
  "geometry": {"coordinates":[-122.386155,37.616357],"type":"Point"}
}
