{
  "type": "Feature",
  "properties": {
    "date:cessation_lower": "1937-01-01",
    "date:cessation_upper": "1937-12-31",
    "date:inception_lower": "1937-01-01",
    "date:inception_upper": "1937-12-31",
    "iso:country": "XX",
    "sfomuseum:accession_number": "2000.160.0838",
    "sfomuseum:author": "Strode, Hudson",
    "sfomuseum:callnumber": "F2223 .S898 1937 SC",
    "sfomuseum:category": "Book",
    "sfomuseum:collection": "Aviation Library",
    "sfomuseum:creditline": "The Tony Bill Aviation Library Collection",
    "sfomuseum:date": "c. 1937",
    "sfomuseum:daterange_end": "1942-12-31",
    "sfomuseum:daterange_start": "1932-01-01",
    "sfomuseum:description": "xxix, [1],388 p. front., 27 pl. 23 cm.",
    "sfomuseum:medium": "paper, ink",
    "sfomuseum:placetype": "object",
    "sfomuseum:publisher": "Random House",
    "sfomuseum:publisher_location": "New York",
    "sfomuseum:subcategory": "Book",
    "sfomuseum:subject": "South America Description and travel.",
    "wof:name": "South by thunderbird",
    "wof:placetype": "venue"
  },
  "geometry": {"coordinates":[-122.386155,37.616357],"type":"Point"}
}
