{
  "type": "Feature",
  "properties": {
    "date:cessation_lower": "1955-01-01",
    "date:cessation_upper": "1955-12-31",
    "date:inception_lower": "1955-01-01",
    "date:inception_upper": "1955-12-31",
    "iso:country": "XX",
    "millsfield:images": [
      1527829231
    ],
    "millsfield:images_texts": [
      "THE SATURDAY EVENING FUST\nJanuary 20. 1955\nIn every man's heart there's a\nTHE SATURDAY BYENING LUST\necret place he would like to go\nEnd now you can go-\nanywhere-on the new, original\nPan Am \"Pay-Later\" Plan\nit took TOO MUCh CAsh to go.\nThere's no more \"TOO LONG\"' No citv. in\nEurope, for example, is more than overnicht bv the\nbree or soe 40 pous away no place in the\nThere's no more \"TOO MUCH CASH'! The Pan\nfor you to put on a rew donars downana go\nThe box below shows the facts. The key that\nyour Lan Amenican Travel Agent or Lan American\nFLY THERE NOW-PAY LATER!\nLTh it on on one please, Mochad or time of down poym\nore people\nfly overseas by\nsuitable for fran\nAmerican. Write Box 111, New York 17, N. X. Der. or.\nPAN AMERICAN\nWORLD'S MOST EXPERIENCED AIRLINE"
    ],
    "millsfield:images_texts_ids": [
      1527829231
    ],
    "millsfield:primary_image": 1527829231,
    "sfomuseum:accession_number": "2001.038.164.080 a b",
    "sfomuseum:airline": "Pan American World Airways",
    "sfomuseum:category": "Promotional, Archive",
    "sfomuseum:collection": "Aviation Archive",
    "sfomuseum:creditline": "Gift of Barnaby Conrad III",
    "sfomuseum:date": "1955",
    "sfomuseum:date_acquired": "2003-05-16",
    "sfomuseum:daterange_end": "1955-12-31",
    "sfomuseum:daterange_start": "1955-01-01",
    "sfomuseum:description": "Two-page advertisement from January 29, 1955 issue of Saturday Evening Post promoting Pan American World Airways, titled “In every man’s heart there’s a secret place he would like to go / More people fly overseas by Pan American” with large color photographic image depicting Neuschwanstein Castle, Bavaria; contains abbreviated price chart.",
    "sfomuseum:dimensions": "14 x 21 inches (35.6 x 53.3 cm)",
    "sfomuseum:media_ids": [
      1527829231
    ],
    "sfomuseum:medium": "paper, ink",
    "sfomuseum:placetype": "object",
    "sfomuseum:publication": ": , 1955.",
    "sfomuseum:subcategory": "Advertisement, 2D",
    "sfomuseum:subject": "Pan Am promotional advertisement",
    "wof:depicts": [
      1159286839,
      1159284989
    ],
    "wof:name": "advertisement: Pan American World Airways, Saturday Evening Post",
    "wof:placetype": "custom",
    "wof:placetype_alt": [
      "object"
    ]
  },
  "geometry": {"coordinates":[-122.386155,37.616357],"type":"Point"}
}
