{
  "type": "Feature",
  "properties": {
    "date:cessation_lower": "1973-01-01",
    "date:cessation_upper": "1973-12-31",
    "date:inception_lower": "1973-01-01",
    "date:inception_upper": "1973-12-31",
    "iso:country": "XX",
    "sfomuseum:accession_number": "2009.108.017",
    "sfomuseum:airline": "El Al Israel Airlines",
    "sfomuseum:author": "Sherman, Arnold",
    "sfomuseum:callnumber": "HE9881.I8 E47 1973",
    "sfomuseum:category": "Book",
    "sfomuseum:collection": "Aviation Library",
    "sfomuseum:creditline": "Gift of the William Hough Collection",
    "sfomuseum:date": "1973",
    "sfomuseum:date_acquired": "2010-03-03",
    "sfomuseum:daterange_end": "1973-12-31",
    "sfomuseum:daterange_start": "1973-01-01",
    "sfomuseum:description": "[5], 201, [8] p. : ill., ports. ; 23 cm.",
    "sfomuseum:description_library": "[5], 201, [8] p. : ill., ports. ; 23 cm.",
    "sfomuseum:medium": "paper, ink",
    "sfomuseum:placetype": "object",
    "sfomuseum:publication": "London: Vallentine, Mitchell, 1973.",
    "sfomuseum:publisher": "Vallentine, Mitchell",
    "sfomuseum:publisher_location": "London",
    "sfomuseum:subcategory": "Book",
    "sfomuseum:subject": "El al",
    "wof:depicts": [
      1159284327,
      1159287585
    ],
    "wof:name": "To the skies: the El Al story",
    "wof:placetype": "custom",
    "wof:placetype_alt": "object"
  },
  "geometry": {"coordinates":[-122.386155,37.616357],"type":"Point"}
}
