{
  "type": "Feature",
  "properties": {
    "date:cessation_lower": "1955-01-01",
    "date:cessation_upper": "1955-12-31",
    "date:inception_lower": "1955-01-01",
    "date:inception_upper": "1955-12-31",
    "iso:country": "XX",
    "millsfield:images": [
      1729566381
    ],
    "sfomuseum:accession_number": "2001.082.107",
    "sfomuseum:aircraft": "Lockheed L-1049 Super Constellation",
    "sfomuseum:airline": "TWA (Trans World Airlines)",
    "sfomuseum:category": "Promotional, Archive",
    "sfomuseum:collection": "Aviation Archive",
    "sfomuseum:creditline": "Gift of George Gayuski ",
    "sfomuseum:date": "c. 1955",
    "sfomuseum:date_acquired": "2001-12-18",
    "sfomuseum:daterange_end": "1960-12-31",
    "sfomuseum:daterange_start": "1950-01-01",
    "sfomuseum:description": "Brochure issued by TWA (Trans World Airlines) promoting Lockheed L-1049 Super Constellation fleet; multipage booklet; brown cover with illustration of note card with text “An invitation to all discriminating air travelers / Fly the luxurious Super Constellation”; contains illustrated description of inflight services with aircraft diagrams.",
    "sfomuseum:dimensions": "10 1/4 x 7 1/4 inches (26 x 18.4 cm)",
    "sfomuseum:medium": "paper, metal, ink",
    "sfomuseum:placetype": "object",
    "sfomuseum:publication": ": , c. 1955.",
    "sfomuseum:subcategory": "Brochure, Airline",
    "wof:depicts": [
      1159285393,
      1159291139,
      1159293697
    ],
    "wof:name": "Brochure: TWA (Trans World Airlines), Lockheed L-1049 Super Constellation",
    "wof:placetype": "custom",
    "wof:placetype_alt": "object"
  },
  "geometry": {"coordinates":[-122.386155,37.616357],"type":"Point"}
}
