{
  "type": "Feature",
  "properties": {
    "date:cessation_lower": "1960-12-31",
    "date:cessation_upper": "1960-12-31",
    "date:inception_lower": "1950-01-01",
    "date:inception_upper": "1950-01-01",
    "iso:country": "XX",
    "sfomuseum:accession_number": "2001.082.107",
    "sfomuseum:aircraft": "Lockheed L-1049 Super Constellation",
    "sfomuseum:airline": "TWA (Trans World Airlines)",
    "sfomuseum:category": "Promotional",
    "sfomuseum:collection": "Aviation Archive",
    "sfomuseum:creditline": "Gift of George Gayuski ",
    "sfomuseum:date": "c. 1955",
    "sfomuseum:daterange_end": "1960-12-31",
    "sfomuseum:daterange_start": "1950-01-01",
    "sfomuseum:description": "Multipage pamphlet issued by TWA (Trans World Airlines) promoting Lockheed L-1049 Super Constellation fleet; image of note card on cover with caption, “An invitation to all discriminating air travelers / Fly the luxurious Super Constellation”; contains illustrated description of inflight services with aircraft diagrams.",
    "sfomuseum:dimensions": "10 1/4 x 7 1/4 inches (26 x 18.4 cm)",
    "sfomuseum:medium": "paper, ink",
    "sfomuseum:placetype": "object",
    "sfomuseum:subcategory": "Brochure, Airline",
    "wof:depicts": [
      1159291139,
      1159285393
    ],
    "wof:name": "Brochure: TWA (Trans World Airlines), Lockheed L-1049 Super Constellation",
    "wof:placetype": "venue"
  },
  "geometry": {"coordinates":[-122.386155,37.616357],"type":"Point"}
}
