{
  "type": "Feature",
  "properties": {
    "date:cessation_lower": "1955-01-01",
    "date:cessation_upper": "1955-12-31",
    "date:inception_lower": "1955-01-01",
    "date:inception_upper": "1955-12-31",
    "iso:country": "XX",
    "millsfield:images": [
      1729566381,
      1763388247,
      1763388249
    ],
    "millsfield:images_texts": [
      "stinest...\nFLY TWA\nSUPER CONSTELLATIONS",
      "An invitation\nto all discriminating\nair travelers\nfly the luxurious\nSuper\nConstellation",
      "TWA takes pride in its new Super Constellations,\nlatest additions to the Trans World Airlines fleet.\nThey represent our steadfast purpose to achieve the\nvery best in airline service to the public. Referred to\nas the most luxuriously-appointed airplanes in the\nskies, we are sure you will agree that TWA's Super\nConstellations give you a new experience in modern\ntravel — the enjoyment of true luxury living aloft.\nFly the Tinese... Er TWA\nvitation to a traveler\nA great new airplane with revolutionary new passenger\naccommodations is waiting to carry you to glamorous\ndestinations throughout the world. Whether you are a seasoned\nair traveler, or a first flighter is of no consequence,\nsince sky luxury like this has never been available to\nany air passengers. In the Super Constellation the\nultimate in gracious, spacious comfort has been achieved."
    ],
    "millsfield:images_texts_ids": [
      1729566381,
      1763388247,
      1763388249
    ],
    "millsfield:primary_image": 1763388247,
    "sfomuseum:accession_number": "2001.082.107",
    "sfomuseum:aircraft": "Lockheed L-1049 Super Constellation",
    "sfomuseum:airline": "TWA (Trans World Airlines)",
    "sfomuseum:category": "Promotional, Archive",
    "sfomuseum:collection": "Aviation Archive",
    "sfomuseum:creditline": "Gift of George Gayuski ",
    "sfomuseum:date": "c. 1955",
    "sfomuseum:date_acquired": "2001-12-18",
    "sfomuseum:daterange_end": "1960-12-31",
    "sfomuseum:daterange_start": "1950-01-01",
    "sfomuseum:description": "Brochure issued by TWA (Trans World Airlines) promoting Lockheed L-1049 Super Constellation fleet; multipage booklet; brown cover with illustration of note card with text “An invitation to all discriminating air travelers / Fly the luxurious Super Constellation”; contains illustrated description of inflight services with aircraft diagrams.",
    "sfomuseum:dimensions": "10 1/4 x 7 1/4 inches (26 x 18.4 cm)",
    "sfomuseum:medium": "paper, metal, ink",
    "sfomuseum:placetype": "object",
    "sfomuseum:publication": ": , c. 1955.",
    "sfomuseum:subcategory": "Brochure, Airline",
    "wof:depicts": [
      1159293697,
      1159285393,
      1159291139
    ],
    "wof:name": "Brochure: TWA (Trans World Airlines), Lockheed L-1049 Super Constellation",
    "wof:placetype": "custom",
    "wof:placetype_alt": "object"
  },
  "geometry": {"coordinates":[-122.386155,37.616357],"type":"Point"}
}
