{
  "type": "Feature",
  "properties": {
    "date:cessation_lower": "1950-01-01",
    "date:cessation_upper": "1959-12-31",
    "date:inception_lower": "1950-01-01",
    "date:inception_upper": "1959-12-31",
    "iso:country": "XX",
    "millsfield:images": [
      1729565453,
      1729566017
    ],
    "millsfield:images_texts": [
      "AMÉRICAN\nOVERSEAS\nANERICAN",
      "AOA-AMERICAN OVERSEAS AIRLINES\nBoeing 377 Stratocruiser\ninaugurated Stratocruiser service\nLondon route on August 17th, 1949,\nBritain'.\nis shown on this card.\n1950 the airline's eighth and last 377 had joined\nthe fleet which linked New York and Boston with\nEngland, Scotland and Scandinavia.\nline.\nPhoto courtesy Boeing Commercial Airplane Company\nPublished by Aviation World, Inc., P.O. Box 188, Bethel, Conn. 06801 U.S.A.\nN90941 c/n 15957\nB-013\n65838-D\npost card\n2001.082.137"
    ],
    "millsfield:images_texts_ids": [
      1729565453,
      1729566017
    ],
    "millsfield:primary_image": 1729565453,
    "millsfield:tailnumbers": [
      "N90941"
    ],
    "sfomuseum:accession_number": "2001.082.137",
    "sfomuseum:aircraft": "Boeing 377 Stratocruiser",
    "sfomuseum:airline": "American Overseas Airlines (AOA)",
    "sfomuseum:category": "Philately",
    "sfomuseum:collection": "Aviation Archive",
    "sfomuseum:creditline": "Gift of George Gayuski ",
    "sfomuseum:date": "1950s",
    "sfomuseum:date_acquired": "2001-12-18",
    "sfomuseum:daterange_end": "1959-12-31",
    "sfomuseum:daterange_start": "1950-01-01",
    "sfomuseum:description": "Postcard with color photographic image of American Overseas Airlines (AOA) Boeing 377 Stratocruiser with aircraft registration number N90941 in flight over clouds; text on reverse, “AOA, a wholly owned subsidiary of American Airlines, inaugurate Stratocruiser service on its New York’London route on August 17th, 1949...”; unmailed.",
    "sfomuseum:dimensions": "3 1/2 x 5 1/2 inches (8.9 x 14 cm)",
    "sfomuseum:maker": "Boeing Commercial Airline Company",
    "sfomuseum:medium": "paper, ink",
    "sfomuseum:placetype": "object",
    "sfomuseum:publication": ": , 1950s.",
    "sfomuseum:subcategory": "Postcard",
    "wof:depicts": [
      1159283867,
      1159289651,
      1159293593
    ],
    "wof:name": "Aviation World postcard: American Overseas Airlines (AOA), Boeing 377 Stratocruiser",
    "wof:placetype": "custom",
    "wof:placetype_alt": "object"
  },
  "geometry": {"coordinates":[-122.386155,37.616357],"type":"Point"}
}
