{
  "type": "Feature",
  "properties": {
    "date:cessation_lower":"1934-12-31",
    "date:cessation_upper":"1934-12-31",
    "date:inception_lower":"1934-01-01",
    "date:inception_upper":"1934-01-01",
    "iso:country":"XX",
    "sfomuseum:accession_number":"2012.149.2304 a b",
    "sfomuseum:category":"Philately",
    "sfomuseum:collection":"Aviation Archive",
    "sfomuseum:creditline":"Gift of the Captain John B. Russell Family",
    "sfomuseum:date":"01/10/1934",
    "sfomuseum:daterange_end":"1934-01-10",
    "sfomuseum:daterange_start":"1934-01-10",
    "sfomuseum:description":"a. Airmail flight cover, massed naval flight from San Francisco to Pearl Harbor, Tenth Patrol Squadron, U.S. Navy; text at upper left corner, \u201cFlown on the 10-P-4 by pilot T.D. [Erwin] and co-pilot J.C. Clarke\u201d and signed by both men; postmarked January 10, 1934 at Aircraft Base Force with \u201cSan Francisco, California\u201d cancellation mark over four 2-cent stamps; backstamp: January 11, 1934 at Fleet Air Base, Pearl Harbor.\rb. Backing sheet with two sets of mounting corners, with handwritten caption: \u201c1934, first U.S. Navy squadron flight - San Francisco to Hawaii\u201d, with black and white photographic image of Consolidated Navy P2Y-1.",
    "sfomuseum:medium":"paper, ink",
    "sfomuseum:placetype":"object",
    "sfomuseum:subcategory":"Airmail Flight Cover",
    "wof:name":"airmail flight cover: Massed flight from San Francisco to Pearl Harbor, U.S. Navy, Tenth Patrol Squadron",
    "wof:placetype":"venue"
},
  "geometry": {"coordinates":[-122.386155,37.616358],"type":"Point"}
}