{
  "type": "Feature",
  "properties": {
    "date:cessation_lower": "1934-01-10",
    "date:cessation_upper": "1934-01-10",
    "date:inception_lower": "1934-01-10",
    "date:inception_upper": "1934-01-10",
    "iso:country": "XX",
    "millsfield:images": [
      1527852485,
      1527853751,
      1527853753
    ],
    "millsfield:primary_image": 1527853753,
    "sfomuseum:accession_number": "2012.149.2304 a b",
    "sfomuseum:airline": "U.S. Navy",
    "sfomuseum:category": "Philately",
    "sfomuseum:collection": "Aviation Archive",
    "sfomuseum:creditline": "Gift of the Captain John B. Russell Family",
    "sfomuseum:date": "01/10/1934",
    "sfomuseum:date_acquired": "2013-05-31",
    "sfomuseum:daterange_end": "1934-01-10",
    "sfomuseum:daterange_start": "1934-01-10",
    "sfomuseum:description": "a. Airmail flight cover, massed naval flight from San Francisco to Pearl Harbor, Tenth Patrol Squadron, U.S. Navy; text at upper left corner, “Flown on the 10-P-4 by pilot T.D. [Erwin] and co-pilot J.C. Clarke” and signed by both men; postmarked January 10, 1934 at Aircraft Base Force with “San Francisco, California” cancellation mark over four 2-cent stamps; backstamp: January 11, 1934 at Fleet Air Base, Pearl Harbor.\rb. Backing sheet with two sets of mounting corners, with handwritten caption: “1934, first U.S. Navy squadron flight - San Francisco to Hawaii”, with black and white photographic image of Consolidated Navy P2Y-1.",
    "sfomuseum:dimensions": "3 3/4 x 6 1/2 inches (9.5 x 16.5 cm)",
    "sfomuseum:media_ids": [
      1527852485,
      1527853751,
      1527853753
    ],
    "sfomuseum:medium": "paper, ink",
    "sfomuseum:placetype": "object",
    "sfomuseum:publication": ": , 01/10/1934.",
    "sfomuseum:subcategory": "Airmail Flight Cover",
    "sfomuseum:subject": "Airlines -- Commercial -- Pan American Airways.",
    "wof:depicts": [
      1159286573,
      1159285407
    ],
    "wof:name": "airmail flight cover: Massed flight from San Francisco to Pearl Harbor, U.S. Navy, Tenth Patrol Squadron",
    "wof:placetype": "custom",
    "wof:placetype_alt": "object"
  },
  "geometry": {"coordinates":[-122.386155,37.616357],"type":"Point"}
}
