{
  "type": "Feature",
  "properties": {
    "date:cessation_lower":"1928-12-31",
    "date:cessation_upper":"1928-12-31",
    "date:inception_lower":"1928-01-01",
    "date:inception_upper":"1928-01-01",
    "iso:country":"XX",
    "sfomuseum:accession_number":"2011.032.0101",
    "sfomuseum:category":"Photograph",
    "sfomuseum:collection":"Aviation Archive",
    "sfomuseum:creditline":"Transfer",
    "sfomuseum:date":"1928",
    "sfomuseum:daterange_end":"1928-12-31",
    "sfomuseum:daterange_start":"1928-01-01",
    "sfomuseum:description":"From attached handwritten note: \u201c02870 / 9-15-28 Power control for doors and lighting in Hangar #2\". Black and white photographic negative of interior of Hangar No. 2 with open doors; power and control boxes affixed to wall; lights and exposed beams overhead; Mills Field Municipal Airport of San Francisco; photograph taken on September 15, 1928. Inscribed on black border, right \u201cA 1384 9/15/28 Power control for doors, lighting & power in so compartment hangar No 2.\u201d",
    "sfomuseum:medium":"nitrate negative",
    "sfomuseum:placetype":"object",
    "sfomuseum:subcategory":"Negative",
    "wof:name":"negative: Mills Field Municipal Airport of San Francisco, Hangar No. 2",
    "wof:placetype":"venue"
},
  "geometry": {"coordinates":[-122.386155,37.616358],"type":"Point"}
}