{
  "type": "Feature",
  "properties": {
    "date:cessation_lower": "1942-01-01",
    "date:cessation_upper": "1942-12-31",
    "date:inception_lower": "1942-01-01",
    "date:inception_upper": "1942-12-31",
    "iso:country": "XX",
    "sfomuseum:accession_number": "2000.171.034",
    "sfomuseum:author": "Smith, Henry Ladd",
    "sfomuseum:callnumber": "TL521 .S5 1942",
    "sfomuseum:category": "Book",
    "sfomuseum:collection": "Aviation Library",
    "sfomuseum:creditline": "Purchase",
    "sfomuseum:date": "1942",
    "sfomuseum:daterange_end": "1942-12-31",
    "sfomuseum:daterange_start": "1942-01-01",
    "sfomuseum:description": "3 p. æ., [iii]-xiv, 430, xv p., 1 æ. illus. (maps) XXXII pl. (incl. ports.) tables (1 fold.) diagrs.",
    "sfomuseum:description_library": "3 p. æ., [iii]-xiv, 430, xv p., 1 æ. illus. (maps) XXXII pl. (incl. ports.) tables (1 fold.) diagrs.",
    "sfomuseum:medium": "paper, ink",
    "sfomuseum:placetype": "object",
    "sfomuseum:publication": "New York: A.A. Knopf, 1942.",
    "sfomuseum:publisher": "A.A. Knopf",
    "sfomuseum:publisher_location": "New York",
    "sfomuseum:subcategory": "Book",
    "sfomuseum:subject": "Aeronautics, Commercial United States.",
    "wof:name": "Airways: the history of commercial aviation in the United States",
    "wof:placetype": "venue"
  },
  "geometry": {"coordinates":[-122.386155,37.616357],"type":"Point"}
}
