{
  "type": "Feature",
  "properties": {
    "date:cessation_lower": "1954-01-01",
    "date:cessation_upper": "1954-12-31",
    "date:inception_lower": "1954-01-01",
    "date:inception_upper": "1954-12-31",
    "iso:country": "XX",
    "millsfield:images": [
      1527847867,
      1527839331
    ],
    "sfomuseum:accession_number": "2005.132.076.001",
    "sfomuseum:aircraft": "Lockheed L-1049G Super Constellation",
    "sfomuseum:airline": "Iberia",
    "sfomuseum:category": "Scheduling / Ticketing",
    "sfomuseum:collection": "Aviation Archive",
    "sfomuseum:creditline": "Gift of the William Hough Collection",
    "sfomuseum:date": "1954",
    "sfomuseum:daterange_end": "1954-12-31",
    "sfomuseum:daterange_start": "1954-01-01",
    "sfomuseum:description": "Timetable issued by Iberia, effective November 1, 1954; two page fold-out; white and red cover with servicemark and text, “Air lines of Spain / Direct to Madrid”; includes flight schedules for Spain to Europe, Africa and New York; includes an illustration of a Lockheed L-1049G Super Constellation in flight. ",
    "sfomuseum:dimensions": "9 x 4 inches (22.9 x 10.2 cm)",
    "sfomuseum:media_ids": [
      1527847867,
      1527839331
    ],
    "sfomuseum:medium": "paper, ink",
    "sfomuseum:placetype": "object",
    "sfomuseum:subcategory": "Timetable",
    "wof:depicts": [
      1159291141,
      1159293697,
      1159284511
    ],
    "wof:name": "timetable: Iberia, Lockheed L-1049G Super Constellation",
    "wof:placetype": "venue"
  },
  "geometry": {"coordinates":[-122.386155,37.616357],"type":"Point"}
}
