{
  "type": "Feature",
  "properties": {
    "date:cessation_lower": "1954-01-01",
    "date:cessation_upper": "1954-12-31",
    "date:inception_lower": "1954-01-01",
    "date:inception_upper": "1954-12-31",
    "iso:country": "XX",
    "millsfield:images": [
      1527839331,
      1527847867
    ],
    "millsfield:images_texts": [
      "beria\nAIR LINES OF SPAIN\nFLIGHT\nSCHEDULE\nEffective November 1, 1954\nDIRECT TO MADRID\nSp din\nALL EUROPE. AFRICA\nFROM NEW YORK",
      "Fly to MADRID in HALF A DAY\nFLIGHTS MONDAYS, WEDNESDAYS, FRIDAYS-\nNON-STOP NEW YORK-MADRID\nIn Lockheed Super E Constellations.\n11¼ hours of luxury flight.\nCombined First and Tourist class service.\nNEW YORK-MADRID\nFlight 952\nbondav\nFlight 952\n5 00 PM Wed 5 00 PM Fri\nFlight 952\nFrosv\nAll Times Shown are Local\nReacH Down\nRed in\n5 00 PM Ly NEW YORK\nAr SANTA MARIA, Azores..\nLv SANTA MARIA, Azores.\nFlight 951\nSundar\nFlight 951\nFlight 951\nOTHER TRANSATLANTIC SERVICES\n[88)\nflat:\nsO\n89\n88\n8668\n-Tourist Class Service\n190 at Octed 31."
    ],
    "millsfield:images_texts_ids": [
      1527839331,
      1527847867
    ],
    "millsfield:primary_image": 1527839331,
    "sfomuseum:accession_number": "2005.132.076.001",
    "sfomuseum:aircraft": "Lockheed L-1049 Super Constellation",
    "sfomuseum:airline": "Iberia",
    "sfomuseum:category": "Scheduling / Ticketing",
    "sfomuseum:collection": "Aviation Archive",
    "sfomuseum:creditline": "Gift of the William Hough Collection",
    "sfomuseum:date": "1954",
    "sfomuseum:date_acquired": "2006-12-05",
    "sfomuseum:daterange_end": "1954-12-31",
    "sfomuseum:daterange_start": "1954-01-01",
    "sfomuseum:description": "Timetable issued by Iberia, effective November 1, 1954; two page fold-out; white and red cover with illustration of a Lockheed L-1049E Super Constellation in flight and text, “Direct to Madrid / Spain / all Europe, Africa from New York”. ",
    "sfomuseum:dimensions": "9 x 4 inches (22.9 x 10.2 cm)",
    "sfomuseum:media_ids": [
      1527847867,
      1527839331
    ],
    "sfomuseum:medium": "paper, ink",
    "sfomuseum:placetype": "object",
    "sfomuseum:publication": ": , 1954.",
    "sfomuseum:subcategory": "Timetable",
    "wof:depicts": [
      1159284511,
      1159291141,
      1159293697,
      1159291139
    ],
    "wof:name": "timetable: Iberia, Lockheed L-1049E Super Constellation",
    "wof:placetype": "custom",
    "wof:placetype_alt": "object"
  },
  "geometry": {"coordinates":[-122.386155,37.616357],"type":"Point"}
}
