{
  "type": "Feature",
  "properties": {
    "date:cessation_lower":"1954-12-31",
    "date:cessation_upper":"1954-12-31",
    "date:inception_lower":"1954-01-01",
    "date:inception_upper":"1954-01-01",
    "iso:country":"XX",
    "sfomuseum:accession_number":"2005.132.076.001",
    "sfomuseum:category":"Scheduling / Ticketing",
    "sfomuseum:collection":"Aviation Archive",
    "sfomuseum:creditline":"Gift of the William Hough Collection",
    "sfomuseum:date":"1954",
    "sfomuseum:daterange_end":"1954-12-31",
    "sfomuseum:daterange_start":"1954-01-01",
    "sfomuseum:description":"Timetable issued by Iberia, effective November 1, 1954; two page fold-out; white and red cover with servicemark and text, \u201cAir lines of Spain / Direct to Madrid\u201d; includes flight schedules for Spain to Europe, Africa and New York; includes an illustration of a Lockheed L-1049G Super Constellation in flight. ",
    "sfomuseum:media_ids":[
        1527847867,
        1527839331
    ],
    "sfomuseum:medium":"paper, ink",
    "sfomuseum:placetype":"object",
    "sfomuseum:subcategory":"Timetable",
    "wof:depicts":[
        1159291141,
        1159293697
    ],
    "wof:name":"timetable: Iberia, Lockheed L-1049G Super Constellation",
    "wof:placetype":"venue"
},
  "geometry": {"coordinates":[-122.386155,37.616358],"type":"Point"}
}