{
  "type": "Feature",
  "properties": {
    "date:cessation_lower":"2009-12-31",
    "date:cessation_upper":"2009-12-31",
    "date:inception_lower":"1999-01-01",
    "date:inception_upper":"1999-01-01",
    "iso:country":"XX",
    "sfomuseum:accession_number":"2007.086.141",
    "sfomuseum:category":"Food Service",
    "sfomuseum:collection":"Aviation Museum",
    "sfomuseum:creditline":"Gift of Ian H. Dally of Auckland, New Zealand",
    "sfomuseum:date":"c. 2004",
    "sfomuseum:daterange_end":"2009-12-31",
    "sfomuseum:daterange_start":"1999-01-01",
    "sfomuseum:description":"Menu produced by Thai Airways International, Bangkok - Melbourne route; red cover with color photographic image of chilis; menu items include broiled pork with mushroom cream sauce, stir-fried chicken with black bean sauce, and poached egg Florentine; menu number: TG 981 C - MAR/SEP; class: Royal Executive (first); undated.",
    "sfomuseum:media_ids":[
        1527846451,
        1527846455
    ],
    "sfomuseum:medium":"paper, ink",
    "sfomuseum:placetype":"object",
    "sfomuseum:subcategory":"Menu",
    "wof:name":"menu: Thai Airways International, Royal Executive (First) Class",
    "wof:placetype":"venue"
},
  "geometry": {"coordinates":[-122.386155,37.616358],"type":"Point"}
}