{
  "type": "Feature",
  "properties": {
    "date:cessation_lower":"1948-12-31",
    "date:cessation_upper":"1948-12-31",
    "date:inception_lower":"1948-01-01",
    "date:inception_upper":"1948-01-01",
    "iso:country":"XX",
    "sfomuseum:accession_number":"2001.038.164.039",
    "sfomuseum:category":"Promotional",
    "sfomuseum:collection":"Aviation Archive",
    "sfomuseum:creditline":"Gift of Barnaby Conrad III",
    "sfomuseum:date":"1948",
    "sfomuseum:daterange_end":"1948-12-31",
    "sfomuseum:daterange_start":"1948-01-01",
    "sfomuseum:description":"Advertisement from October 23, 1948 issue of Saturday Evening Post promoting Pan American World Airways, titled \u201cTake-off place for 6 continents\u201d; color illustration of hand holding phone receiver over telephone with brochures for travel to England and Rio de Janeiro.",
    "sfomuseum:medium":"paper, ink",
    "sfomuseum:placetype":"object",
    "sfomuseum:subcategory":"Advertisement, 2D",
    "wof:name":"advertisement: Pan American World Airways, Saturday Evening Post",
    "wof:placetype":"venue"
},
  "geometry": {"coordinates":[-122.386155,37.616358],"type":"Point"}
}