{
  "type": "Feature",
  "properties": {
    "date:cessation_lower": "1984-01-01",
    "date:cessation_upper": "1984-12-31",
    "date:inception_lower": "1984-01-01",
    "date:inception_upper": "1984-12-31",
    "iso:country": "XX",
    "sfomuseum:accession_number": "2002.031.009",
    "sfomuseum:author": "Farmer, James H.",
    "sfomuseum:callnumber": "PN1995.9.F58 F3 1984",
    "sfomuseum:category": "Book",
    "sfomuseum:collection": "Aviation Library",
    "sfomuseum:creditline": "Purchase",
    "sfomuseum:date": "c. 1984",
    "sfomuseum:date_acquired": "1997-01-10",
    "sfomuseum:daterange_end": "1989-12-31",
    "sfomuseum:daterange_start": "1979-01-01",
    "sfomuseum:description": "xiii, 369 p. : ill. ; 28 cm.",
    "sfomuseum:description_library": "xiii, 369 p. : ill. ; 28 cm.",
    "sfomuseum:medium": "paper, ink",
    "sfomuseum:placetype": "object",
    "sfomuseum:publication": "Blue Ridge Summit, PA: Tab Books, c. 1984.",
    "sfomuseum:publisher": "Tab Books",
    "sfomuseum:publisher_location": "Blue Ridge Summit, PA",
    "sfomuseum:subcategory": "Book",
    "sfomuseum:subject": "Flight in motion pictures.American cinema films Special subjects: Aviation - Critical studies",
    "wof:name": "Celluloid wings",
    "wof:placetype": "custom",
    "wof:placetype_alt": "object"
  },
  "geometry": {"coordinates":[-122.386155,37.616357],"type":"Point"}
}
