{
  "type": "Feature",
  "properties": {
    "date:cessation_lower": "1940-12-31",
    "date:cessation_upper": "1940-12-31",
    "date:inception_lower": "1940-01-01",
    "date:inception_upper": "1940-01-01",
    "iso:country": "XX",
    "millsfield:images": [
      1527829121
    ],
    "sfomuseum:accession_number": "1994.18.148",
    "sfomuseum:aircraft": "Boeing 314 Clipper",
    "sfomuseum:airline": "Pan American Airways  (Pan American World Airways)",
    "sfomuseum:category": "Philately",
    "sfomuseum:collection": "Aviation Archive",
    "sfomuseum:continent": "Transpacific",
    "sfomuseum:creditline": "Purchase",
    "sfomuseum:date": "7/21/1940",
    "sfomuseum:daterange_end": "1940-07-21",
    "sfomuseum:daterange_start": "1940-07-21",
    "sfomuseum:description": "Airmail flight cover, Pan American Airways, part of first airmail service between United States and New Zealand, Noumea - Los Angeles route; green cachet with image of Boeing 314 in flight over coastline; three stamps: purple/brown 50-centime, purple/brown 10-franc, and blue 9-franc (New Caledonia); four postmarks: July 21, 1940 in Noumea; backstamp: July 24, 1940 in Los Angeles; additional stamp: Pan American Airways “1er courrier Noumea N’lle Caledonie”; envelope: white air mail with blue and red rhomboids around border.",
    "sfomuseum:maker": "Pan American Airways, Inc.",
    "sfomuseum:media_ids": [
      1527829121
    ],
    "sfomuseum:medium": "ink on paper",
    "sfomuseum:placetype": "object",
    "sfomuseum:subcategory": "Airmail Flight Cover",
    "wof:depicts": [
      1159284991,
      1159289619
    ],
    "wof:name": "airmail flight cover: Pan American Airways, first airmail flight, Noumea (New Caledonia) - Los Angeles route",
    "wof:placetype": "venue"
  },
  "geometry": {"coordinates":[-122.386155,37.616357],"type":"Point"}
}
