{
  "type": "Feature",
  "properties": {
    "date:cessation_lower":"1950-12-31",
    "date:cessation_upper":"1950-12-31",
    "date:inception_lower":"1940-01-01",
    "date:inception_upper":"1940-01-01",
    "iso:country":"XX",
    "millsfield:images":[
        1527852991
    ],
    "sfomuseum:accession_number":"2012.149.1499",
    "sfomuseum:category":"Philately",
    "sfomuseum:collection":"Aviation Archive",
    "sfomuseum:creditline":"Gift of the Captain John B. Russell Family",
    "sfomuseum:date":"c. 1945",
    "sfomuseum:daterange_end":"1950-12-31",
    "sfomuseum:daterange_start":"1940-01-01",
    "sfomuseum:description":"Set of four 24-cent airmail postage stamps issued by United States postal service; red and blue biplane design.",
    "sfomuseum:media_ids":[
        1527852991
    ],
    "sfomuseum:medium":"paper, ink",
    "sfomuseum:placetype":"object",
    "sfomuseum:subcategory":"Stamp, Postage",
    "wof:name":"postage stamps: United States Airmail",
    "wof:placetype":"venue"
},
  "geometry": {"coordinates":[-122.386155,37.616358],"type":"Point"}
}