{
  "type": "Feature",
  "properties": {
    "date:cessation_lower": "1977-10-28",
    "date:cessation_upper": "1977-10-28",
    "date:inception_lower": "1977-10-28",
    "date:inception_upper": "1977-10-28",
    "iso:country": "XX",
    "millsfield:images": [
      1527820277,
      1527820279
    ],
    "millsfield:primary_image": 1527820277,
    "sfomuseum:accession_number": "2000.058.0213 d",
    "sfomuseum:airline": "Pan American World Airways",
    "sfomuseum:category": "Philately",
    "sfomuseum:collection": "Aviation Archive",
    "sfomuseum:creditline": "Gift of the Pan Am Association",
    "sfomuseum:date": "10/28/1977",
    "sfomuseum:date_acquired": "2000-12-14",
    "sfomuseum:daterange_end": "1977-10-28",
    "sfomuseum:daterange_start": "1977-10-28",
    "sfomuseum:description": "Airmail flight cover, Pan American World Airways, Havana - Key West route; printed blue cachet with route map and commemorative text; postmarked October 28, 1977 in San Francisco with 31-cent stamp; backstamp: October 30, 1977 in San Francisco.",
    "sfomuseum:dimensions": " ",
    "sfomuseum:media_ids": [
      1527820277,
      1527820279
    ],
    "sfomuseum:medium": "paper, ink",
    "sfomuseum:placetype": "object",
    "sfomuseum:publication": ": , 10/28/1977.",
    "sfomuseum:subcategory": "Airmail Flight Cover",
    "wof:depicts": [
      1159286839,
      1159284989
    ],
    "wof:name": "airmail flight cover: Pan American World Airways, Havana - Key West route, 50th anniversary",
    "wof:placetype": "custom",
    "wof:placetype_alt": "object"
  },
  "geometry": {"coordinates":[-122.386155,37.616357],"type":"Point"}
}
