{
  "type": "Feature",
  "properties": {
    "date:cessation_lower": "1937-01-28",
    "date:cessation_upper": "1937-01-28",
    "date:inception_lower": "1937-01-28",
    "date:inception_upper": "1937-01-28",
    "iso:country": "XX",
    "millsfield:images": [
      1527851761
    ],
    "millsfield:images_texts": [
      "This envelope was carried\nFiRST\nFLIGHT\nSan Diggo Calif\nPeari hair borTi\nFrom\nTo\nThrough courtestioN 6-F\nU. S. Nave\n19 3\nA.M.\nS. FLEES\nMUUBD STA\nSAN DIEGO\nCALISES.\nVIA AIR MAIL\nMr. Louis Kaplan\nCollegiate Tilatelic Soc.\n% Mail Clerk\nFleet Air Base\nPearl Harbor,\n, T. Ч."
    ],
    "millsfield:images_texts_ids": [
      1527851761
    ],
    "millsfield:primary_image": 1527851761,
    "sfomuseum:accession_number": "2008.075.104",
    "sfomuseum:airline": "U.S. Navy",
    "sfomuseum:category": "Philately",
    "sfomuseum:collection": "Aviation Archive",
    "sfomuseum:creditline": "Gift of Jon E. Krupnick",
    "sfomuseum:date": "01/28/1937",
    "sfomuseum:date_acquired": "2008-12-31",
    "sfomuseum:daterange_end": "1937-01-28",
    "sfomuseum:daterange_start": "1937-01-28",
    "sfomuseum:description": "Airmail flight cover for First U.S. Navy San Diego - Pearl Harbor Mass Flight, January 28-29, 1937; envelope with rectangular black cachet at left with text \"First Flight San Diego Calif Pearl Harbor T.H. Patrol Sqd'n 6-F U.S. Navy 1937\" with small winged horse inside circle; postmarked January 28, 1937 at Aircraft Base Force U.S. Fleet with three-bar “San Diego Calif” cancellation mark over orange 6-cent stamp; backstamp: January 29, 1937, Honolulu T.H.F.A.B.; addressed to Louis Kaplan.",
    "sfomuseum:dimensions": "3 3/4 x 6 1/4 inches (9.5 x 15.9 cm)",
    "sfomuseum:issues_held": "\r",
    "sfomuseum:media_ids": [
      1527851761
    ],
    "sfomuseum:medium": "paper, ink",
    "sfomuseum:placetype": "object",
    "sfomuseum:publication": ": , 01/28/1937.",
    "sfomuseum:subcategory": "Airmail Flight Cover",
    "wof:depicts": [
      1159286573,
      1159285407
    ],
    "wof:name": "airmail flight cover: First U.S. Navy San Diego - Pearl Harbor mass flight, January 28-29, 1937",
    "wof:placetype": "custom",
    "wof:placetype_alt": "object"
  },
  "geometry": {"coordinates":[-122.386155,37.616357],"type":"Point"}
}
