{
  "type": "Feature",
  "properties": {
    "date:cessation_lower": "1934-01-01",
    "date:cessation_upper": "1934-12-31",
    "date:inception_lower": "1934-01-01",
    "date:inception_upper": "1934-12-31",
    "iso:country": "XX",
    "sfomuseum:accession_number": "2000.160.0900",
    "sfomuseum:author": "Mollison, James Allan",
    "sfomuseum:callnumber": "TL515 .M575 1934 SC",
    "sfomuseum:category": "Book",
    "sfomuseum:collection": "Aviation Library",
    "sfomuseum:creditline": "The Tony Bill Aviation Library Collection",
    "sfomuseum:date": "c. 1934",
    "sfomuseum:date_acquired": "1999-05-18",
    "sfomuseum:daterange_end": "1939-12-31",
    "sfomuseum:daterange_start": "1929-01-01",
    "sfomuseum:description": "190, [1] p. col. front., illus. (incl. ports.) col. plates. 26 x 20 cm.",
    "sfomuseum:description_library": "190, [1] p. col. front., illus. (incl. ports.) col. plates. 26 x 20 cm.",
    "sfomuseum:medium": "paper, ink",
    "sfomuseum:placetype": "object",
    "sfomuseum:publication": "London; Glasgow, Scotland: Collins' Clear-type Press, c. 1934.",
    "sfomuseum:publisher": "Collins' Clear-type Press",
    "sfomuseum:publisher_location": "London; Glasgow, Scotland",
    "sfomuseum:subcategory": "Book",
    "sfomuseum:subject": "Aeronautics Biography.Aeronautics History.",
    "wof:name": "The book of famous flyers",
    "wof:placetype": "custom",
    "wof:placetype_alt": "object"
  },
  "geometry": {"coordinates":[-122.386155,37.616357],"type":"Point"}
}
