{
  "type": "Feature",
  "properties": {
    "date:cessation_lower": "1955-12-31",
    "date:cessation_upper": "1955-12-31",
    "date:inception_lower": "1945-01-01",
    "date:inception_upper": "1945-01-01",
    "iso:country": "XX",
    "millsfield:images": [
      1527834755
    ],
    "sfomuseum:accession_number": "2012.149.2056",
    "sfomuseum:airline": "Braniff International Airways  (Braniff International)",
    "sfomuseum:category": "Philately",
    "sfomuseum:collection": "Aviation Archive",
    "sfomuseum:creditline": "Gift of the Captain John B. Russell Family",
    "sfomuseum:date": "c. 1950",
    "sfomuseum:daterange_end": "1955-12-31",
    "sfomuseum:daterange_start": "1945-01-01",
    "sfomuseum:description": "Airmail courtesy label issued by Braniff International Airways; red, white, and blue with text, “Branigram via Air Mail.”",
    "sfomuseum:dimensions": "1 x 2 inches (2.5 x 5.1 cm)",
    "sfomuseum:media_ids": [
      1527834755
    ],
    "sfomuseum:medium": "paper, ink",
    "sfomuseum:placetype": "object",
    "sfomuseum:subcategory": "Stamp, Courtesy",
    "wof:depicts": [
      1159284009
    ],
    "wof:name": "airmail courtesy label: Braniff International Airways",
    "wof:placetype": "venue"
  },
  "geometry": {"coordinates":[-122.386155,37.616357],"type":"Point"}
}
