{
  "type": "Feature",
  "properties": {
    "date:cessation_lower": "1940-01-01",
    "date:cessation_upper": "1940-12-31",
    "date:inception_lower": "1940-01-01",
    "date:inception_upper": "1940-12-31",
    "iso:country": "XX",
    "millsfield:images": [
      1527835135
    ],
    "millsfield:primary_image": 1527835135,
    "sfomuseum:accession_number": "2012.149.1265",
    "sfomuseum:airline": "Mexicana de Aviación",
    "sfomuseum:category": "Promotional",
    "sfomuseum:collection": "Aviation Archive",
    "sfomuseum:creditline": "Gift of the Captain John B. Russell Family",
    "sfomuseum:date": "c. 1940",
    "sfomuseum:date_acquired": "2013-05-31",
    "sfomuseum:daterange_end": "1945-12-31",
    "sfomuseum:daterange_start": "1935-01-01",
    "sfomuseum:description": "Luggage label promoting Mexicana de Aviacion; circular shape with color illustration of DC-3 airplane in flight over mountains with various Mexican objects in the foreground and text, “CIA. Mexicana de Aviacion S.A./Agentes Del Sistema Pan American Airways.”",
    "sfomuseum:dimensions": "3 1/2 x 3 1/2 inches (8.9 x 8.9 cm)",
    "sfomuseum:media_ids": [
      1527835135
    ],
    "sfomuseum:medium": "paper, ink, adhesive",
    "sfomuseum:placetype": "object",
    "sfomuseum:publication": ": , c. 1940.",
    "sfomuseum:subcategory": "Luggage Label",
    "wof:depicts": [
      1159286839,
      1159284779,
      1159284991
    ],
    "wof:name": "luggage label: Mexicana de Aviación S.A., Pan American Airways",
    "wof:placetype": "venue"
  },
  "geometry": {"coordinates":[-122.386155,37.616357],"type":"Point"}
}
