{
  "type": "Feature",
  "properties": {
    "date:cessation_lower": "1935-01-01",
    "date:cessation_upper": "1935-12-31",
    "date:inception_lower": "1935-01-01",
    "date:inception_upper": "1935-12-31",
    "iso:country": "XX",
    "sfomuseum:accession_number": "2000.168.034",
    "sfomuseum:author": "Burge, Cyril Gordon",
    "sfomuseum:callnumber": "TL509 .B87 1935 SC",
    "sfomuseum:category": "Book",
    "sfomuseum:collection": "Aviation Library",
    "sfomuseum:creditline": "Collection of SFO Museum",
    "sfomuseum:date": "1935",
    "sfomuseum:date_acquired": "1998-06-18",
    "sfomuseum:daterange_end": "1935-12-31",
    "sfomuseum:daterange_start": "1935-01-01",
    "sfomuseum:description": "641, [1] p. incl. illus., plates (1 col.) diagrs. 25 x 19 cm.",
    "sfomuseum:description_library": "641, [1] p. incl. illus., plates (1 col.) diagrs. 25 x 19 cm.",
    "sfomuseum:medium": "paper, ink",
    "sfomuseum:placetype": "object",
    "sfomuseum:publication": "London: Sir I. Pitman \u0026 Sons, 1935.",
    "sfomuseum:publisher": "Sir I. Pitman \u0026 Sons",
    "sfomuseum:publisher_location": "London",
    "sfomuseum:subcategory": "Book",
    "sfomuseum:subject": "Aeronautics Biography.Aeronautics Pictorial works.Aeronautics Dictionaries.",
    "wof:name": "Encyclopaedia of aviation",
    "wof:placetype": "custom",
    "wof:placetype_alt": "object"
  },
  "geometry": {"coordinates":[-122.386155,37.616357],"type":"Point"}
}
