{
  "type": "Feature",
  "properties": {
    "date:cessation_lower": "1949-01-01",
    "date:cessation_upper": "1949-12-31",
    "date:inception_lower": "1949-01-01",
    "date:inception_upper": "1949-12-31",
    "iso:country": "XX",
    "millsfield:images": [
      1527852999
    ],
    "millsfield:primary_image": 1527852999,
    "sfomuseum:accession_number": "2012.149.1516",
    "sfomuseum:category": "Philately",
    "sfomuseum:collection": "Aviation Archive",
    "sfomuseum:creditline": "Gift of the Captain John B. Russell Family",
    "sfomuseum:date": "c. 1949",
    "sfomuseum:daterange_end": "1954-12-31",
    "sfomuseum:daterange_start": "1944-01-01",
    "sfomuseum:description": "Set of six 25-cent airmail postage stamps issued by United States postal service; blue design depicting frontal view of flying boat in flight; issue number 21476.",
    "sfomuseum:dimensions": "3 x 4 3/4 inches (7.6 x 12.1 cm)",
    "sfomuseum:media_ids": [
      1527852999
    ],
    "sfomuseum:medium": "paper, ink",
    "sfomuseum:placetype": "object",
    "sfomuseum:publication": ": , c. 1949.",
    "sfomuseum:subcategory": "Stamp, Postage",
    "wof:name": "postage stamps: United States Airmail",
    "wof:placetype": "venue"
  },
  "geometry": {"coordinates":[-122.386155,37.616357],"type":"Point"}
}
