{
  "type": "Feature",
  "properties": {
    "date:cessation_lower": "1999-01-01",
    "date:cessation_upper": "1999-12-31",
    "date:inception_lower": "1999-01-01",
    "date:inception_upper": "1999-12-31",
    "iso:country": "XX",
    "millsfield:images": [
      1527843721,
      1527843723
    ],
    "millsfield:images_texts": [
      "m\ne\nn\nu\nCLUR\nANA",
      "WINE LIST\nCHAMPAGNE\nPiper-Heidsieck Cuvée Brut\nWHITE WINES [8919\nFrance Bourgogne 7597 /J-=2\nSaint-Véran 96\n'96\nU.S.A. California U›*/=7\nLouis M Martini Chardonnay 96\n-17 I4 351-59#K7'96\nJapan Koshu B# M\nPolaire Koshu Katsunuma Sur Lie\nRED WINES\nFrance Bordeaux */K-\nChateau Noillac 95\nFrance Bourgogne 7597 7N3-=a\nSantenay SC\n†\u003e+* '96\nU.S.A. California *M=P\nConcannon Cabernet Sauvignon '95\nBEER (E-))\nJAPANESE SAKES\nGozenshu 20807 (P)L)\nBishounen 72›# (IS#)\nMine no Hakubal MOBN(58)\nBEVERAGE LIST\nAPERITES \u0026 COCKTAILS\nSherry Dry SIU-K51\nVermouth Dry or Sweet SillE» + R54 a 794-*\nBum Wine r\nKir al\nMartini 871-=\nManhattan 779S\nGin \u0026 Tonic 7 rEuS\nBloody Mary 75 ?!-\nChivas Regal 15 Years Old Scotch Whisky ½-/7 U-tIl 15 %.\nOld Parr Scotch Whisky *-)K C-\nJack Daniel's Black Tennessee Whiskey\nSuntory Yamazaki Japanese Whisky #*N- M\nVodka\nRum 54\nDIGESTIFS\n12517\nCourvoisier Napoleon Cognac SINI tRU*S\nDrambuie '9994\nGrand Marnier 95% R=I\nSOFT DRINKS\nSERUSS!\nOrange Juice *U\u003e99a-7\nApple Juice FuSSa-7\nTomato Juice +8+9a-7\nGrapefruit Juice 9-79-*a-7\nCoca-Cola 37•3-5\nCoca-Cola Light 3•3-55 k\nSprite k\nOolong Tea 5-OV*"
    ],
    "millsfield:images_texts_ids": [
      1527843721,
      1527843723
    ],
    "millsfield:primary_image": 1527843721,
    "sfomuseum:accession_number": "2006.034.019",
    "sfomuseum:airline": "ANA (All Nippon Airways)",
    "sfomuseum:category": "Passenger Amenity, Archive",
    "sfomuseum:collection": "Aviation Archive",
    "sfomuseum:creditline": "Gift of Adan Wong",
    "sfomuseum:date": "1999",
    "sfomuseum:date_acquired": "2007-04-06",
    "sfomuseum:daterange_end": "1999-12-31",
    "sfomuseum:daterange_start": "1999-01-01",
    "sfomuseum:description": "Menu issued by ANA (All Nippon Airways), San Francisco - Tokyo route; light green cover with oval cutout revealing color illustration on next page; Japanese and western lunch items; in Japanese and English; menu number: SFO-NRT 990301; class: Club ANA (business); date: 990301.",
    "sfomuseum:dimensions": "11 3/4 x 5 3/4 inches (29.8 x 14.6 cm)",
    "sfomuseum:media_ids": [
      1527843721,
      1527843723
    ],
    "sfomuseum:medium": "paper, ink, metal",
    "sfomuseum:placetype": "object",
    "sfomuseum:publication": ": , 1999.",
    "sfomuseum:subcategory": "Menu",
    "wof:depicts": [
      1159287625,
      1159283875
    ],
    "wof:name": "menu: ANA (All Nippon Airways), Club ANA (Business Class)",
    "wof:placetype": "custom",
    "wof:placetype_alt": "object"
  },
  "geometry": {"coordinates":[-122.386155,37.616357],"type":"Point"}
}
