{
  "type": "Feature",
  "properties": {
    "date:cessation_lower": "1962-12-31",
    "date:cessation_upper": "1962-12-31",
    "date:inception_lower": "1962-01-01",
    "date:inception_upper": "1962-01-01",
    "iso:country": "XX",
    "sfomuseum:accession_number": "2005.132.020.006",
    "sfomuseum:category": "Scheduling / Ticketing",
    "sfomuseum:collection": "Aviation Archive",
    "sfomuseum:creditline": "Gift of the William Hough Collection",
    "sfomuseum:date": "1962",
    "sfomuseum:daterange_end": "1962-12-31",
    "sfomuseum:daterange_start": "1962-01-01",
    "sfomuseum:description": "Timetable issued by Frontier Airlines, effective February 7, 1962; black and orange cover with black and white photographic image of a man carrying a golf bag and a woman sitting by a pool; text at bottom promotes Frontiersman service and Convair aircraft; seven pages.",
    "sfomuseum:media_ids": [
      1527846213
    ],
    "sfomuseum:medium": "paper, ink",
    "sfomuseum:placetype": "object",
    "sfomuseum:subcategory": "Timetable",
    "wof:name": "timetable: Frontier Airlines",
    "wof:placetype": "venue"
  },
  "geometry": {"coordinates":[-122.386155,37.616358],"type":"Point"}
}
