{
  "type": "Feature",
  "properties": {
    "date:cessation_lower": "1980-01-01",
    "date:cessation_upper": "1989-12-31",
    "date:inception_lower": "1980-01-01",
    "date:inception_upper": "1989-12-31",
    "iso:country": "XX",
    "millsfield:images": [
      1527840251
    ],
    "millsfield:primary_image": 1527840251,
    "sfomuseum:accession_number": "2012.160.004",
    "sfomuseum:airline": "Thai Airways International",
    "sfomuseum:category": "Promotional",
    "sfomuseum:collection": "Aviation Museum",
    "sfomuseum:creditline": "Gift of Vincent Ma",
    "sfomuseum:date": "1980s",
    "sfomuseum:date_acquired": "2013-05-31",
    "sfomuseum:daterange_end": "1989-12-31",
    "sfomuseum:daterange_start": "1980-01-01",
    "sfomuseum:description": "Small rectangular white bag with exterior pocket; purple, gold, and pink logo with “Thai” wordmark at lower right; single handle and zipper closure across top.",
    "sfomuseum:dimensions": "9 x 6 x 2 inches (22.9 x 15.2 x 5.1 cm)",
    "sfomuseum:media_ids": [
      1527840251
    ],
    "sfomuseum:medium": "vinyl, ink, plastic, metal",
    "sfomuseum:placetype": "object",
    "sfomuseum:publication": ": , 1980s.",
    "sfomuseum:subcategory": "Airline Bag",
    "wof:depicts": [
      1159285291
    ],
    "wof:name": "miniature airline bag: Thai Airways International",
    "wof:placetype": "venue"
  },
  "geometry": {"coordinates":[-122.386155,37.616357],"type":"Point"}
}
