{
  "type": "Feature",
  "properties": {
    "date:cessation_lower": "1986-12-31",
    "date:cessation_upper": "1986-12-31",
    "date:inception_lower": "1986-01-01",
    "date:inception_upper": "1986-01-01",
    "iso:country": "XX",
    "millsfield:images": [
      1527846995
    ],
    "sfomuseum:accession_number": "2002.135.037.023",
    "sfomuseum:airline": "Alaska Airlines",
    "sfomuseum:category": "Scheduling / Ticketing",
    "sfomuseum:collection": "Aviation Archive",
    "sfomuseum:creditline": "Gift of Thomas G. Dragges",
    "sfomuseum:date": "1986",
    "sfomuseum:daterange_end": "1986-12-31",
    "sfomuseum:daterange_start": "1986-01-01",
    "sfomuseum:description": "Timetable issued by Alaska Airlines, effective December 1, 1986; on cover: full color photographic image  of a white Spanish mission-style church with red and green flora in the foreground and blue sky in the background.",
    "sfomuseum:dimensions": "8 1/2 x 4 inches (21.6 x 10.2 cm)",
    "sfomuseum:media_ids": [
      1527846995
    ],
    "sfomuseum:medium": "paper, ink",
    "sfomuseum:placetype": "object",
    "sfomuseum:subcategory": "Timetable",
    "sfomuseum:subject": "Airlines -- Commercial -- Alaska",
    "wof:depicts": [
      1159283813
    ],
    "wof:name": "timetable: Alaska Airlines",
    "wof:placetype": "custom"
  },
  "geometry": {"coordinates":[-122.386155,37.616357],"type":"Point"}
}
