{
  "type": "Feature",
  "properties": {
    "date:cessation_lower": "1977-01-01",
    "date:cessation_upper": "1977-12-31",
    "date:inception_lower": "1977-01-01",
    "date:inception_upper": "1977-12-31",
    "isbn:number": "0442224508, 9780442224509",
    "iso:country": "XX",
    "sfomuseum:accession_number": "00-0311",
    "sfomuseum:author": "Editors of Flying magazine",
    "sfomuseum:callnumber": "TL710 .B26 1977",
    "sfomuseum:category": "Book",
    "sfomuseum:collection": "Aviation Library",
    "sfomuseum:date": "1977",
    "sfomuseum:daterange_end": "1977-12-31",
    "sfomuseum:daterange_start": "1977-01-01",
    "sfomuseum:description": "208 p. ; 24 cm.",
    "sfomuseum:description_library": "208 p. ; 24 cm.",
    "sfomuseum:medium": "paper, ink",
    "sfomuseum:placetype": "object",
    "sfomuseum:publication": "New York: Van Nostrand Reinhold Co., 1977.",
    "sfomuseum:publisher": "Van Nostrand Reinhold Co.",
    "sfomuseum:publisher_location": "New York",
    "sfomuseum:subcategory": "Book",
    "sfomuseum:subject": "Airplanes.Airplanes Piloting.Light aircraft Flying - Manuals",
    "wof:name": "Back to basics: aircraft construction, cockpit mechanics, and flight procedures",
    "wof:placetype": "custom",
    "wof:placetype_alt": [
      "object"
    ]
  },
  "geometry": {"coordinates":[-122.386155,37.616357],"type":"Point"}
}
