{
  "type": "Feature",
  "properties": {
    "date:cessation_lower": "1949-12-31",
    "date:cessation_upper": "1949-12-31",
    "date:inception_lower": "1947-01-01",
    "date:inception_upper": "1947-01-01",
    "iso:country": "XX",
    "millsfield:images": [
      1527823659,
      1527823661
    ],
    "sfomuseum:accession_number": "1998.157.064",
    "sfomuseum:airline": "Burma Airways  (Myanmar Airways)",
    "sfomuseum:category": "Passenger Amenity",
    "sfomuseum:collection": "Aviation Museum",
    "sfomuseum:creditline": "Gift of The Henry Steiner Air Sickness Bag Collection",
    "sfomuseum:date": "late 1940s",
    "sfomuseum:daterange_end": "1949-12-31",
    "sfomuseum:daterange_start": "1947-01-01",
    "sfomuseum:description": "Flat bag, no closure. Beige bag, black print. \"Burma Airways Corporation\" on lower portion. Logo, inside circle are pilot wings with Burma Airways at top and Burmese characters on bottom, at upper portion of bag. Burmese characters on front. Plastic interior also covers top outer edge.",
    "sfomuseum:dimensions": "10 3/4 x 7 inches (27.3 x 17.8 cm)",
    "sfomuseum:media_ids": [
      1527823659,
      1527823661
    ],
    "sfomuseum:medium": "paper",
    "sfomuseum:placetype": "object",
    "sfomuseum:subcategory": "Airsickness Bag",
    "wof:depicts": [
      1159284837
    ],
    "wof:name": "airsickness bag: Burma Airways",
    "wof:placetype": "venue"
  },
  "geometry": {"coordinates":[-122.386155,37.616357],"type":"Point"}
}
