{
  "type": "Feature",
  "properties": {
    "date:cessation_lower": "1980-12-31",
    "date:cessation_upper": "1980-12-31",
    "date:inception_lower": "1970-01-01",
    "date:inception_upper": "1970-01-01",
    "iso:country": "XX",
    "millsfield:images": [
      1527853577
    ],
    "sfomuseum:accession_number": "2010.009.0001 a c",
    "sfomuseum:airline": "JAL (Japan Airlines)",
    "sfomuseum:category": "Equipment",
    "sfomuseum:collection": "Aviation Museum",
    "sfomuseum:creditline": "Gift of Thomas G. Dragges",
    "sfomuseum:date": "c. 1975",
    "sfomuseum:daterange_end": "1980-12-31",
    "sfomuseum:daterange_start": "1970-01-01",
    "sfomuseum:description": "a. Large circular sign for JAL (Japan Airlines) ticket counter; white background with large red crane logo and “JAL” initials at lower right; four flat clips on back.\rb. Wooden wall cleat with flat clips.\rc. Wooden wall cleat with flat clips.",
    "sfomuseum:dimensions": "32 x 32 x 1/4 inches (81.3 x 81.3 x .6 cm)",
    "sfomuseum:media_ids": [
      1527853577
    ],
    "sfomuseum:medium": "aluminum, paint",
    "sfomuseum:placetype": "object",
    "sfomuseum:subcategory": "Sign",
    "wof:depicts": [
      1159284563
    ],
    "wof:name": "sign: JAL (Japan Airlines)",
    "wof:placetype": "venue"
  },
  "geometry": {"coordinates":[-122.386155,37.616357],"type":"Point"}
}
