{
  "type": "Feature",
  "properties": {
    "date:cessation_lower":"1959-12-31",
    "date:cessation_upper":"1959-12-31",
    "date:inception_lower":"1950-01-01",
    "date:inception_upper":"1950-01-01",
    "iso:country":"XX",
    "millsfield:images":[
        1527819355
    ],
    "sfomuseum:accession_number":"2001.146.067",
    "sfomuseum:airline":"VARIG",
    "sfomuseum:category":"Promotional",
    "sfomuseum:collection":"Aviation Museum",
    "sfomuseum:creditline":"Gift of Thomas G. Dragges",
    "sfomuseum:date":"1950s",
    "sfomuseum:daterange_end":"1959-12-31",
    "sfomuseum:daterange_start":"1950-01-01",
    "sfomuseum:description":"Navy blue bag with white trim and \"VARIG Airlines\" servicemark at upper left, slanted diagonally; single navy blue and white handle strap, zipper closure around front rim; flat bottom.\r",
    "sfomuseum:media_ids":[
        1527819355
    ],
    "sfomuseum:medium":"vinyl, metal, plastic, cardboard",
    "sfomuseum:placetype":"object",
    "sfomuseum:subcategory":"Airline Bag",
    "wof:depicts":[
        1159285461
    ],
    "wof:name":"airline bag: VARIG",
    "wof:placetype":"venue"
},
  "geometry": {"coordinates":[-122.386155,37.616357],"type":"Point"}
}