{
  "type": "Feature",
  "properties": {
    "date:cessation_lower": "1950-01-01",
    "date:cessation_upper": "1959-12-31",
    "date:inception_lower": "1950-01-01",
    "date:inception_upper": "1959-12-31",
    "iso:country": "XX",
    "millsfield:images": [
      1527819355
    ],
    "millsfield:primary_image": 1527819355,
    "sfomuseum:accession_number": "2001.146.067",
    "sfomuseum:airline": "VARIG",
    "sfomuseum:category": "Promotional, Museum",
    "sfomuseum:collection": "Aviation Museum",
    "sfomuseum:creditline": "Gift of Thomas G. Dragges",
    "sfomuseum:date": "1950s",
    "sfomuseum:date_acquired": "2003-07-24",
    "sfomuseum:daterange_end": "1959-12-31",
    "sfomuseum:daterange_start": "1950-01-01",
    "sfomuseum:description": "Airline bag issued by VARIG; blue background with white logotype; white piping with wraparound zipper closure and one handle.",
    "sfomuseum:dimensions": "11 x 14 1/2 x 4 inches (27.9 x 36.8 x 10.2 cm)",
    "sfomuseum:media_ids": [
      1527819355
    ],
    "sfomuseum:medium": "vinyl, metal, plastic, cardboard",
    "sfomuseum:placetype": "object",
    "sfomuseum:publication": ": , 1950s.",
    "sfomuseum:subcategory": "Airline Bag",
    "wof:depicts": [
      1159288487,
      1159285461
    ],
    "wof:name": "airline bag: VARIG",
    "wof:placetype": "custom",
    "wof:placetype_alt": "object"
  },
  "geometry": {"coordinates":[-122.386155,37.616357],"type":"Point"}
}
