{
  "type": "Feature",
  "properties": {
    "date:cessation_lower": "1985-12-31",
    "date:cessation_upper": "1985-12-31",
    "date:inception_lower": "1975-01-01",
    "date:inception_upper": "1975-01-01",
    "iso:country": "XX",
    "sfomuseum:accession_number": "2000.168.012",
    "sfomuseum:author": "Robinson, Anthony",
    "sfomuseum:callnumber": "UG630 .A388 1980",
    "sfomuseum:category": "Book",
    "sfomuseum:collection": "Aviation Library",
    "sfomuseum:creditline": "Purchase",
    "sfomuseum:date": "c. 1980",
    "sfomuseum:daterange_end": "1985-12-31",
    "sfomuseum:daterange_start": "1975-01-01",
    "sfomuseum:description": "viii, 304 p. : col. ill. ; 31 cm.",
    "sfomuseum:medium": "paper, ink",
    "sfomuseum:placetype": "object",
    "sfomuseum:publisher": "Orbis",
    "sfomuseum:publisher_location": "London",
    "sfomuseum:subcategory": "Book",
    "sfomuseum:subject": "Air forces.Air forces",
    "wof:name": "Air power: the world's air forces",
    "wof:placetype": "venue"
  },
  "geometry": {"coordinates":[-122.386155,37.616357],"type":"Point"}
}
