{
  "type": "Feature",
  "properties": {
    "date:cessation_lower": "1985-12-31",
    "date:cessation_upper": "1985-12-31",
    "date:inception_lower": "1975-01-01",
    "date:inception_upper": "1975-01-01",
    "iso:country": "XX",
    "sfomuseum:accession_number": "00-1422",
    "sfomuseum:author": "Weis, Norm",
    "sfomuseum:callnumber": "TL540.W39 A37 1980",
    "sfomuseum:category": "Book",
    "sfomuseum:collection": "Aviation Library",
    "sfomuseum:date": "c. 1980",
    "sfomuseum:daterange_end": "1985-12-31",
    "sfomuseum:daterange_start": "1975-01-01",
    "sfomuseum:description": "171 p., [4] leaves of plates : ill. ; 22 cm.",
    "sfomuseum:medium": "paper, ink",
    "sfomuseum:placetype": "object",
    "sfomuseum:publisher": "Prentice-Hall",
    "sfomuseum:publisher_location": "Englewood Cliffs, NJ",
    "sfomuseum:subcategory": "Book",
    "sfomuseum:subject": "Weis, Norm, 1923-Weis, Norm, 1923-Airplanes, Home-built.Air pilots.Air pilots United States Biography.Airplanes, Home-built.",
    "wof:name": "The starduster",
    "wof:placetype": "venue"
  },
  "geometry": {"coordinates":[-122.386155,37.616357],"type":"Point"}
}
