{
  "type": "Feature",
  "properties": {
    "date:cessation_lower": "1990-01-01",
    "date:cessation_upper": "1999-12-31",
    "date:inception_lower": "1990-01-01",
    "date:inception_upper": "1999-12-31",
    "iso:country": "XX",
    "millsfield:images": [
      1527842167
    ],
    "millsfield:images_colors_refs": {
      "crayola": [
        {
          "hex": "#9f8170",
          "name": "Beaver",
          "reference": "crayola"
        },
        {
          "hex": "#95918c",
          "name": "Gray",
          "reference": "crayola"
        },
        {
          "hex": "#cdc5c2",
          "name": "Silver",
          "reference": "crayola"
        },
        {
          "hex": "#414a4c",
          "name": "Outer Space",
          "reference": "crayola"
        }
      ],
      "css4": [
        {
          "hex": "#bc8f8f",
          "name": "rosybrown",
          "reference": "css4"
        },
        {
          "hex": "#2f4f4f",
          "name": "darkslategrey",
          "reference": "css4"
        },
        {
          "hex": "#808080",
          "name": "grey",
          "reference": "css4"
        },
        {
          "hex": "#c0c0c0",
          "name": "silver",
          "reference": "css4"
        }
      ],
      "marekm4": [
        {
          "hex": "#2b2c2e",
          "name": "#2b2c2e",
          "reference": "marekm4"
        },
        {
          "hex": "#948e7b",
          "name": "#948e7b",
          "reference": "marekm4"
        },
        {
          "hex": "#a19c8b",
          "name": "#a19c8b",
          "reference": "marekm4"
        }
      ]
    },
    "millsfield:images_texts": [
      "TURKISH AIRLINES\nTURK HAVA YOLLARI"
    ],
    "millsfield:images_texts_ids": [
      1527842167
    ],
    "millsfield:primary_image": 1527842167,
    "sfomuseum:accession_number": "1998.157.212",
    "sfomuseum:airline": "Turkish Airlines",
    "sfomuseum:category": "Passenger Amenity, Archive",
    "sfomuseum:collection": "Aviation Archive",
    "sfomuseum:creditline": "Gift of The Henry Steiner Air Sickness Bag Collection",
    "sfomuseum:date": "1990s",
    "sfomuseum:date_acquired": "1999-07-13",
    "sfomuseum:daterange_end": "1999-12-31",
    "sfomuseum:daterange_start": "1990-01-01",
    "sfomuseum:description": "Airsickness bag issued by Turkish Airlines; gray and white bag with servicemark; flat bottom, wire tab closure.",
    "sfomuseum:dimensions": "9 1/2 x 5 inches (24.1 x 12.7 cm)",
    "sfomuseum:media_ids": [
      1527842167
    ],
    "sfomuseum:medium": "paper, metal, plastic, ink",
    "sfomuseum:placetype": "object",
    "sfomuseum:publication": ": , 1990s.",
    "sfomuseum:subcategory": "Airsickness Bag",
    "wof:depicts": [
      1159285391,
      1159286977
    ],
    "wof:name": "airsickness bag: Turkish Airlines",
    "wof:placetype": "custom",
    "wof:placetype_alt": [
      "object"
    ]
  },
  "geometry": {"coordinates":[-122.386155,37.616357],"type":"Point"}
}
