{
  "type": "Feature",
  "properties": {
    "date:cessation_lower": "1990-01-01",
    "date:cessation_upper": "1999-12-31",
    "date:inception_lower": "1990-01-01",
    "date:inception_upper": "1999-12-31",
    "iso:country": "XX",
    "millsfield:images": [
      1527842167
    ],
    "millsfield:primary_image": 1527842167,
    "sfomuseum:accession_number": "1998.157.212",
    "sfomuseum:airline": "Turkish Airlines",
    "sfomuseum:category": "Passenger Amenity",
    "sfomuseum:collection": "Aviation Archive",
    "sfomuseum:creditline": "Gift of The Henry Steiner Air Sickness Bag Collection",
    "sfomuseum:date": "1990s",
    "sfomuseum:date_acquired": "1999-07-13",
    "sfomuseum:daterange_end": "1999-12-31",
    "sfomuseum:daterange_start": "1990-01-01",
    "sfomuseum:description": "Flat bottom, wire tab closure. Gray bag, white print. \"Turkish Airlines\" in white on center. Logo to right, white border circle with white bird shape in center. Design on both sides.",
    "sfomuseum:dimensions": "9 1/2 x 5 inches (24.1 x 12.7 cm)",
    "sfomuseum:media_ids": [
      1527842167
    ],
    "sfomuseum:medium": "paper",
    "sfomuseum:placetype": "object",
    "sfomuseum:publication": ": , 1990s.",
    "sfomuseum:subcategory": "Airsickness Bag",
    "wof:depicts": [
      1159285391
    ],
    "wof:name": "airsickness bag: Turkish Airlines",
    "wof:placetype": "venue"
  },
  "geometry": {"coordinates":[-122.386155,37.616357],"type":"Point"}
}
