{
  "type": "Feature",
  "properties": {
    "date:cessation_lower":"1969-12-31",
    "date:cessation_upper":"1969-12-31",
    "date:inception_lower":"1960-01-01",
    "date:inception_upper":"1960-01-01",
    "iso:country":"XX",
    "millsfield:images":[
        1527850877
    ],
    "sfomuseum:accession_number":"2011.013.002",
    "sfomuseum:category":"Food Service",
    "sfomuseum:collection":"Aviation Museum",
    "sfomuseum:creditline":"Purchase",
    "sfomuseum:date":"1960s",
    "sfomuseum:daterange_end":"1969-12-31",
    "sfomuseum:daterange_start":"1960-01-01",
    "sfomuseum:description":"Bowl issued by Air France; \u201cPremiere\u201d pattern; white rimless scalloped edge plate with seahorse illustration at center, \u201cDecor De, Jean Picart le Doux, Realise Pour, Air France, PAR,\u201d manufacture stamp on bottom.",
    "sfomuseum:media_ids":[
        1527850877
    ],
    "sfomuseum:medium":"porcelain, glaze",
    "sfomuseum:placetype":"object",
    "sfomuseum:subcategory":"Tableware",
    "wof:name":"soup bowl: Air France",
    "wof:placetype":"venue"
},
  "geometry": {"coordinates":[-122.386155,37.616358],"type":"Point"}
}