{
  "type": "Feature",
  "properties": {
    "date:cessation_lower": "1970-01-01",
    "date:cessation_upper": "1979-12-31",
    "date:inception_lower": "1970-01-01",
    "date:inception_upper": "1979-12-31",
    "iso:country": "XX",
    "millsfield:images": [
      1527850877
    ],
    "millsfield:primary_image": 1527850877,
    "sfomuseum:accession_number": "2011.013.002",
    "sfomuseum:airline": "Air France",
    "sfomuseum:category": "Meal Service",
    "sfomuseum:collection": "Aviation Museum",
    "sfomuseum:creditline": "Purchase",
    "sfomuseum:date": "1970s",
    "sfomuseum:daterange_end": "1979-12-31",
    "sfomuseum:daterange_start": "1970-01-01",
    "sfomuseum:description": "Bowl issued by Air France for inflight meal service; \"Premiere\" pattern by Jean Picart le Doux; white scalloped bowl with navy blue and green drop design around edge and airline \"Hippocampe\" with seven star logo at center interior. ",
    "sfomuseum:dimensions": "1 1/2 x 7 x 7 inches (3.8 x 17.8 x 17.8 cm)",
    "sfomuseum:media_ids": [
      1527850877
    ],
    "sfomuseum:medium": "glazed porcelain",
    "sfomuseum:placetype": "object",
    "sfomuseum:publication": ": , 1970s.",
    "sfomuseum:subcategory": "Plate / Dish / Bowl",
    "wof:depicts": [
      1159283627
    ],
    "wof:name": "bowl: Air France",
    "wof:placetype": "venue"
  },
  "geometry": {"coordinates":[-122.386155,37.616357],"type":"Point"}
}
