{
  "type": "Feature",
  "properties": {
    "iso:country": "XX",
    "sfomuseum:accession_number": "2006.037.274",
    "sfomuseum:aircraft": "Albatros D.I",
    "sfomuseum:category": "Subject File / Research File",
    "sfomuseum:collection": "Aviation Archive",
    "sfomuseum:creditline": "Gift of Rare Birds Collection",
    "sfomuseum:description": "Monty Grove's reference file of Albatros manufacturer, model: D-1.  Includes:\rnewspaper articles, magazine tearsheets, photographs, drawings, illustrations.",
    "sfomuseum:medium": "paper, ink",
    "sfomuseum:placetype": "object",
    "sfomuseum:subcategory": "Aircraft / Manufacturers",
    "wof:depicts": [
      1159292125,
      1159293773
    ],
    "wof:name": "research file: Albatros D.I",
    "wof:placetype": "venue"
  },
  "geometry": {"coordinates":[-122.386155,37.616357],"type":"Point"}
}
