{
  "type": "Feature",
  "properties": {
    "date:cessation_lower": "2003-07-08",
    "date:cessation_upper": "2003-07-08",
    "date:inception_lower": "2003-07-08",
    "date:inception_upper": "2003-07-08",
    "iso:country": "XX",
    "sfomuseum:accession_number": "2004.115.0098",
    "sfomuseum:airline": "VARIG",
    "sfomuseum:airport": "Santos Dumont Airport",
    "sfomuseum:artist": "William “Bill” Hough",
    "sfomuseum:category": "Photograph",
    "sfomuseum:collection": "Aviation Archive",
    "sfomuseum:creditline": "Gift of the William Hough Collection",
    "sfomuseum:date": "7/8/2003",
    "sfomuseum:date_acquired": "2004-12-28",
    "sfomuseum:daterange_end": "2003-07-08",
    "sfomuseum:daterange_start": "2003-07-08",
    "sfomuseum:description": "Color photographic slide depicting profile view of VARIG Rio Sul Embraer ERJ 145 at Santos Dumont Airport (SDU), Rio de Janeiro, Brazil, July 8, 2003; photo credit William Hough.",
    "sfomuseum:dimensions": "1 x 1 1/2 inches (2.5 x 3.8 cm)",
    "sfomuseum:medium": "color slide",
    "sfomuseum:placetype": "object",
    "sfomuseum:publication": ": , 7/8/2003.",
    "sfomuseum:subcategory": "Slide",
    "wof:depicts": [
      102534549,
      1159285461,
      1159290517,
      1159292327,
      1159294367
    ],
    "wof:name": "slide: VARIG Rio Sul, Embraer ERJ 145, Santos Dumont Airport (SDU)",
    "wof:placetype": "custom",
    "wof:placetype_alt": "object"
  },
  "geometry": {"coordinates":[-122.386155,37.616357],"type":"Point"}
}
