{
  "type": "Feature",
  "properties": {
    "date:cessation_lower": "1991-01-01",
    "date:cessation_upper": "1991-12-31",
    "date:inception_lower": "1991-01-01",
    "date:inception_upper": "1991-12-31",
    "iso:country": "XX",
    "loc:named_authorities": [
      "n91058978"
    ],
    "sfomuseum:accession_number": "2001.106.450",
    "sfomuseum:author": "Putnam, Howard D.",
    "sfomuseum:callnumber": "HE9781.W6 P88 1991",
    "sfomuseum:category": "Book",
    "sfomuseum:collection": "Aviation Library",
    "sfomuseum:creditline": "Gift of Mark F. Adams Collection",
    "sfomuseum:date": "c. 1991",
    "sfomuseum:date_acquired": "2001-10-18",
    "sfomuseum:daterange_end": "1996-12-31",
    "sfomuseum:daterange_start": "1986-01-01",
    "sfomuseum:description": "xvii, 227 p. ; 24 cm.",
    "sfomuseum:description_library": "xvii, 227 p. ; 24 cm.",
    "sfomuseum:medium": "paper, ink",
    "sfomuseum:placetype": "object",
    "sfomuseum:publication": "New York: HarperBusiness, c. 1991.",
    "sfomuseum:publisher": "HarperBusiness",
    "sfomuseum:publisher_location": "New York",
    "sfomuseum:subcategory": "Book",
    "sfomuseum:subject": "Putnam, Howard D., 1937- \rUnited Air Lines, inc. -- Management.\rBraniff Airways - -Management.\rSouthwest Airlines Co. -- Management.\rAirlines--United States -- Management.\rChief executive officers -- United States.\r",
    "wof:name": "The winds of turbulence: a CEO's reflections on surviving and thriving on the cutting edge of corporate crisis",
    "wof:placetype": "venue"
  },
  "geometry": {"coordinates":[-122.386155,37.616357],"type":"Point"}
}
