{
  "type": "Feature",
  "properties": {
    "date:cessation_lower": "1971-01-01",
    "date:cessation_upper": "1971-12-31",
    "date:inception_lower": "1971-01-01",
    "date:inception_upper": "1971-12-31",
    "iso:country": "XX",
    "sfomuseum:accession_number": "99-0003",
    "sfomuseum:author": "United States. Dept. of the Army",
    "sfomuseum:callnumber": "UG1243 .P35 1971 SC",
    "sfomuseum:category": "Book",
    "sfomuseum:collection": "Aviation Library",
    "sfomuseum:date": "1971",
    "sfomuseum:daterange_end": "1971-12-31",
    "sfomuseum:daterange_start": "1971-01-01",
    "sfomuseum:description": "1 v. (various pagings) : ill. ; 28 cm.",
    "sfomuseum:description_library": "1 v. (various pagings) : ill. ; 28 cm.",
    "sfomuseum:medium": "paper, ink",
    "sfomuseum:placetype": "object",
    "sfomuseum:publication": "Washington, D.C.: Headquarters, Dept. of the Army, 1971.",
    "sfomuseum:publisher": "Headquarters, Dept. of the Army",
    "sfomuseum:publisher_location": "Washington, D.C.",
    "sfomuseum:series": "Department of the Army technical bulletin ; TB 746-93-2",
    "sfomuseum:subcategory": "Book",
    "sfomuseum:subject": "Airplanes, Military Markings United States.Airplanes, Military United States Painting Handbooks, manuals, etc.",
    "wof:name": "Painting and marking of Army aircraft",
    "wof:placetype": "custom",
    "wof:placetype_alt": "object"
  },
  "geometry": {"coordinates":[-122.386155,37.616357],"type":"Point"}
}
