{
  "type": "Feature",
  "properties": {
    "date:cessation_lower": "1944-01-01",
    "date:cessation_upper": "1944-12-31",
    "date:inception_lower": "1944-01-01",
    "date:inception_upper": "1944-12-31",
    "iso:country": "XX",
    "sfomuseum:accession_number": "01-3824",
    "sfomuseum:author": "Friskey, Margaret",
    "sfomuseum:callnumber": "PZ10.3 .F93 1944 JUV",
    "sfomuseum:category": "Book",
    "sfomuseum:collection": "Aviation Library",
    "sfomuseum:date": "1944",
    "sfomuseum:daterange_end": "1944-12-31",
    "sfomuseum:daterange_start": "1944-01-01",
    "sfomuseum:description": "[32] p. illus. (part col.) 24 x 19 cm.\r",
    "sfomuseum:description_library": "[32] p. illus. (part col.) 24 x 19 cm.\r",
    "sfomuseum:medium": "paper, ink",
    "sfomuseum:placetype": "object",
    "sfomuseum:publication": "Chicago: Wilcox \u0026 Follett, 1944.",
    "sfomuseum:publisher": "Wilcox \u0026 Follett",
    "sfomuseum:publisher_location": "Chicago",
    "sfomuseum:subcategory": "Book",
    "sfomuseum:subject": "Aeronautics -- Juvenile literature.",
    "wof:name": "Scuttlebutt and the carrier kitten",
    "wof:placetype": "custom",
    "wof:placetype_alt": "object"
  },
  "geometry": {"coordinates":[-122.386155,37.616357],"type":"Point"}
}
