{
  "type": "Feature",
  "properties": {
    "date:cessation_lower": "1946-01-01",
    "date:cessation_upper": "1946-12-31",
    "date:inception_lower": "1946-01-01",
    "date:inception_upper": "1946-12-31",
    "iso:country": "XX",
    "loc:subject_headings": [
      "sh85002934"
    ],
    "sfomuseum:accession_number": "2006.002.008",
    "sfomuseum:author": "Fahey, James C. (James Charles)",
    "sfomuseum:callnumber": "TL685.3 .F27 1946 SC ENV",
    "sfomuseum:category": "Book",
    "sfomuseum:collection": "Aviation Library",
    "sfomuseum:creditline": "Robert W. Jackson",
    "sfomuseum:date": "c. 1946",
    "sfomuseum:date_acquired": "2006-01-18",
    "sfomuseum:daterange_end": "1951-12-31",
    "sfomuseum:daterange_start": "1941-01-01",
    "sfomuseum:description": "64 p. incl. illus., tables. 24 cm.",
    "sfomuseum:medium": "paper, ink",
    "sfomuseum:placetype": "object",
    "sfomuseum:publication": "New York: Ships and Aircraft, c. 1946.",
    "sfomuseum:publisher": "Ships and Aircraft",
    "sfomuseum:publisher_location": "New York",
    "sfomuseum:subcategory": "Book",
    "sfomuseum:subject": "Airplanes, Military.",
    "wof:name": "U.S. Army aircraft (heavier-than-air) 1908-1946",
    "wof:placetype": "venue"
  },
  "geometry": {"coordinates":[-122.386155,37.616357],"type":"Point"}
}
