{
  "type": "Feature",
  "properties": {
    "date:cessation_lower": "2006-01-01",
    "date:cessation_upper": "2006-12-31",
    "date:inception_lower": "2006-01-01",
    "date:inception_upper": "2006-12-31",
    "iso:country": "XX",
    "loc:named_authorities": [
      "n82252037"
    ],
    "sfomuseum:accession_number": "2012.075.002",
    "sfomuseum:author": "Nasht, Simon",
    "sfomuseum:callnumber": "G585.W55 N37 2006",
    "sfomuseum:category": "Book",
    "sfomuseum:collection": "Aviation Library",
    "sfomuseum:creditline": "Purchase",
    "sfomuseum:date": "2006",
    "sfomuseum:date_acquired": "2012-03-16",
    "sfomuseum:daterange_end": "2006-12-31",
    "sfomuseum:daterange_start": "2006-01-01",
    "sfomuseum:description": "xxi, 346 p., [16] p. of plates : ill., maps ; 25 cm.",
    "sfomuseum:description_library": "xxi, 346 p., [16] p. of plates : ill., maps ; 25 cm.",
    "sfomuseum:edition": "1st North American ed.",
    "sfomuseum:medium": "paper, ink",
    "sfomuseum:placetype": "object",
    "sfomuseum:publication": "New York: Arcade Pub., 2006.",
    "sfomuseum:publisher": "Arcade Pub.",
    "sfomuseum:publisher_location": "New York",
    "sfomuseum:subcategory": "Book",
    "sfomuseum:subject": "Wilkins, George H. (George Hubert), Sir, 1888-1958.\rExplorers -- Australia -- Biography. \rPolar regions -- Discovery and exploration -- Australian.",
    "wof:name": "The last explorer: Hubert Wilkins, hero of the great age of polar exploration 1st North American ed.",
    "wof:placetype": "custom",
    "wof:placetype_alt": "object"
  },
  "geometry": {"coordinates":[-122.386155,37.616357],"type":"Point"}
}
