{
  "type": "Feature",
  "properties": {
    "date:cessation_lower": "1993-01-01",
    "date:cessation_upper": "1993-12-31",
    "date:inception_lower": "1993-01-01",
    "date:inception_upper": "1993-12-31",
    "isbn:number": "0879388315, 9780879388317",
    "iso:country": "XX",
    "sfomuseum:accession_number": "1999.657.162",
    "sfomuseum:author": "Ballantine, Colin",
    "sfomuseum:callnumber": "TL685.7 .B3 1993",
    "sfomuseum:category": "Book",
    "sfomuseum:collection": "Aviation Library",
    "sfomuseum:creditline": "Collection of SFO Museum",
    "sfomuseum:date": "1993",
    "sfomuseum:date_acquired": "1995-05-25",
    "sfomuseum:daterange_end": "1993-12-31",
    "sfomuseum:daterange_start": "1993-01-01",
    "sfomuseum:description": "1 v. (unpaged) : col. ill. ; 27 cm.",
    "sfomuseum:description_library": "1 v. (unpaged) : col. ill. ; 27 cm.",
    "sfomuseum:medium": "paper, ink",
    "sfomuseum:placetype": "object",
    "sfomuseum:publication": "Osceola, WI: Motorbooks International, 1993.",
    "sfomuseum:publisher": "Motorbooks International",
    "sfomuseum:publisher_location": "Osceola, WI",
    "sfomuseum:subcategory": "Book",
    "sfomuseum:subject": "Jet transports Soviet Union Pictorial works.Turboprop transports Pictorial works.Jet transports Russia (Federation) Pictorial works.Turboprop transports Pictorial works.",
    "wof:name": "Russian propliners \u0026 jetliners",
    "wof:placetype": "custom",
    "wof:placetype_alt": [
      "object"
    ]
  },
  "geometry": {"coordinates":[-122.386155,37.616357],"type":"Point"}
}
