{
  "type": "Feature",
  "properties": {
    "date:cessation_lower": "1955-01-01",
    "date:cessation_upper": "1955-12-31",
    "date:inception_lower": "1955-01-01",
    "date:inception_upper": "1955-12-31",
    "iso:country": "XX",
    "millsfield:images": [
      1527819423
    ],
    "millsfield:primary_image": 1527819423,
    "sfomuseum:accession_number": "2005.065.001",
    "sfomuseum:airline": "Pan American World Airways",
    "sfomuseum:category": "Promotional",
    "sfomuseum:collection": "Aviation Archive",
    "sfomuseum:creditline": "Gift of Barbara Sharfstein",
    "sfomuseum:date": "c. 1955",
    "sfomuseum:daterange_end": "1960-12-31",
    "sfomuseum:daterange_start": "1950-01-01",
    "sfomuseum:description": "Color advertisement from Saturday Evening Post promoting Pan American World Airways, with caption, “Here are wings for your dreams” and illustration of aircraft, globe, and Pan Am gift certificate among ornaments hanging from bough of Christmas tree; includes listing of fares to various tropical destinations.",
    "sfomuseum:dimensions": "11 x 8 inches (27.9 x 20.3 cm)",
    "sfomuseum:media_ids": [
      1527819423
    ],
    "sfomuseum:medium": "paper, ink",
    "sfomuseum:placetype": "object",
    "sfomuseum:subcategory": "Advertisement, 2D",
    "wof:depicts": [
      1159284989
    ],
    "wof:name": "advertisement: Pan American World Airways, Saturday Evening Post",
    "wof:placetype": "venue"
  },
  "geometry": {"coordinates":[-122.386155,37.616357],"type":"Point"}
}
