{
  "type": "Feature",
  "properties": {
    "date:cessation_lower": "1955-01-01",
    "date:cessation_upper": "1955-12-31",
    "date:inception_lower": "1955-01-01",
    "date:inception_upper": "1955-12-31",
    "iso:country": "XX",
    "millsfield:images": [
      1527819423
    ],
    "millsfield:images_texts": [
      "Here are Wings for your dreams\nTOSS BALDER CONTAINS TORI\nGift Certificate\nFOR AIR TRAVEL IT RUNES CUPER\nBut thieves\nhose\nBill\nYou can make definite rescrostions\nfor over the Holidays\n* Bunada, Mexico, Hawaii,\nthe West Indies or where\nyou chesse\n-or you can let the person who receives\nthe gift Certificate decide that later.\nWithout fighting your way through Christmas\nyon can offer one of the most unmanal, most appre\nciated Christmas presents vou have ever\nA Pan American ift Gertificate, which son car\narrange for by telephoning your Travel Agent or\nPan Alicrican, can make the most untorettable\ngIlt 01 19 18.\nUnly Pan American, you know, flies to all 6\nContinents--offering vou a cboice of 61 countries\nanterestesteroneerno\nMEXIcO CITY from Houston .........$48\nBERMUDA roes Newe Yorks ...m. ........Sto\nHAWAII from Los Angeles or San Fran\nPaRts frees\nNese York, $370; round trip. ..$$93.30\ntO DEJANEERO rom Siam.\n0.00.8125\nAROUND THE WORLD. . . . . ...........81300\ndetails... and for other trip suegestions ... call\nyoar Travel Agent or Pan American direct.\nPAN AMERICAN WORLD AIRWAYS\nWORLD'S MOST EXPERIENCED AIRLINE"
    ],
    "millsfield:images_texts_ids": [
      1527819423
    ],
    "millsfield:primary_image": 1527819423,
    "sfomuseum:accession_number": "2005.065.001",
    "sfomuseum:airline": "Pan American World Airways",
    "sfomuseum:category": "Promotional, Archive",
    "sfomuseum:collection": "Aviation Archive",
    "sfomuseum:creditline": "Gift of Barbara Sharfstein",
    "sfomuseum:date": "c. 1955",
    "sfomuseum:date_acquired": "2005-06-10",
    "sfomuseum:daterange_end": "1960-12-31",
    "sfomuseum:daterange_start": "1950-01-01",
    "sfomuseum:description": "Advertisement from Saturday Evening Post promoting Pan American World Airways, with caption, “Here are wings for your dreams” and illustration of aircraft, globe, and Pan Am gift certificate among ornaments hanging from bough of Christmas tree; includes listing of fares to various tropical destinations.",
    "sfomuseum:dimensions": "11 x 8 inches (27.9 x 20.3 cm)",
    "sfomuseum:media_ids": [
      1527819423
    ],
    "sfomuseum:medium": "paper, ink",
    "sfomuseum:placetype": "object",
    "sfomuseum:publication": ": , c. 1955.",
    "sfomuseum:subcategory": "Advertisement, 2D",
    "wof:depicts": [
      1159286839,
      1159284989
    ],
    "wof:name": "advertisement: Pan American World Airways, Saturday Evening Post",
    "wof:placetype": "custom",
    "wof:placetype_alt": "object"
  },
  "geometry": {"coordinates":[-122.386155,37.616357],"type":"Point"}
}
