{
  "type": "Feature",
  "properties": {
    "iso:country": "XX",
    "sfomuseum:accession_number": "2000.172.060",
    "sfomuseum:author": "Society of Experimental Test Pilots. Symposium; and the Society of Experimental Test Pilots",
    "sfomuseum:callnumber": "TL671.7 .S55a",
    "sfomuseum:category": "Book",
    "sfomuseum:collection": "Aviation Library",
    "sfomuseum:creditline": "Purchase",
    "sfomuseum:date_acquired": "1999-12-08",
    "sfomuseum:description": "v. : ill., ports. ; 22 cm.",
    "sfomuseum:description_library": "v. : ill., ports. ; 22 cm.",
    "sfomuseum:medium": "paper, ink",
    "sfomuseum:placetype": "object",
    "sfomuseum:publication": "Lancaster, CA: The Society, .",
    "sfomuseum:publisher": "The Society",
    "sfomuseum:publisher_location": "Lancaster, CA",
    "sfomuseum:subcategory": "Book",
    "sfomuseum:subject": "Airplanes Testing Congresses.",
    "wof:name": "Symposium proceedings",
    "wof:placetype": "custom",
    "wof:placetype_alt": "object"
  },
  "geometry": {"coordinates":[-122.386155,37.616357],"type":"Point"}
}
