{
  "type": "Feature",
  "properties": {
    "date:cessation_lower": "1950-01-01",
    "date:cessation_upper": "1959-12-31",
    "date:inception_lower": "1950-01-01",
    "date:inception_upper": "1959-12-31",
    "iso:country": "XX",
    "millsfield:images": [
      1527835069
    ],
    "millsfield:primary_image": 1527835069,
    "sfomuseum:accession_number": "2012.149.1374",
    "sfomuseum:airline": "Pan American World Airways",
    "sfomuseum:category": "Promotional",
    "sfomuseum:collection": "Aviation Archive",
    "sfomuseum:creditline": "Gift of the Captain John B. Russell Family",
    "sfomuseum:date": "1950s",
    "sfomuseum:date_acquired": "2013-05-31",
    "sfomuseum:daterange_end": "1959-12-31",
    "sfomuseum:daterange_start": "1950-01-01",
    "sfomuseum:description": "Luggage label promoting Pan American World Airways; oval shape with blue border and white text, “Pan American World Airways / The System of the Flying Clipper”; color illustration of outdoor scene with totem pole and blue text in center, “Alaska”.",
    "sfomuseum:dimensions": "3 1/2 x 5 1/2 inches (8.9 x 14 cm)",
    "sfomuseum:media_ids": [
      1527835069
    ],
    "sfomuseum:medium": "paper, ink, adhesive",
    "sfomuseum:placetype": "object",
    "sfomuseum:publication": ": , 1950s.",
    "sfomuseum:subcategory": "Luggage Label",
    "wof:depicts": [
      1159284989
    ],
    "wof:name": "luggage label: Pan American World Airways, Alaska",
    "wof:placetype": "venue"
  },
  "geometry": {"coordinates":[-122.386155,37.616357],"type":"Point"}
}
