{
  "type": "Feature",
  "properties": {
    "date:cessation_lower": "1935-05-09",
    "date:cessation_upper": "1935-05-09",
    "date:inception_lower": "1935-05-09",
    "date:inception_upper": "1935-05-09",
    "iso:country": "XX",
    "millsfield:exhibition_ids": [
      1159160119
    ],
    "millsfield:images": [
      1527831847
    ],
    "millsfield:images_texts": [
      "UNITED STATES FLEE\nCONCENTRATION\n1935\nHawaiian\nHAWAII\n•ASE\nMiss Patrici\nЯск Німон\n% Lieut A.K. Himan\n1. К\nI PUT DIS AVESPOSITER\nGO BAC\nQUADRON 8-FR\nFIRST FLIGHT\nVP. SQUADRON EIGHT•\nU.S. NAVY\n1935"
    ],
    "millsfield:images_texts_ids": [
      1527831847
    ],
    "millsfield:on_view": 0,
    "millsfield:primary_image": 1527831847,
    "sfomuseum:accession_number": "2008.075.062",
    "sfomuseum:airline": "U.S. Navy",
    "sfomuseum:category": "Philately",
    "sfomuseum:collection": "Aviation Archive",
    "sfomuseum:creditline": "Gift of Jon E. Krupnick",
    "sfomuseum:date": "05/09/1935",
    "sfomuseum:date_acquired": "2008-12-31",
    "sfomuseum:daterange_end": "1935-05-09",
    "sfomuseum:daterange_start": "1935-05-09",
    "sfomuseum:description": "Airmail flight cover, U.S. Navy Pacific Fleet, Midway Island Mass Flight, May 9-11, 1935; blue and green square cachet on front at lower left with text \"United States Fleet Concentration 1935\"; purple square cachet on front at lower right, \"First Flight AP Squadron Eight-F, U.S. Navy\"; postmarked May 9, 1935, Fleet Air Base, Pearl Harbor with football-shaped killer; orange 6-cent postage stamp; addressed to Patricia Nieman, Midway Island; backstamp: May 11, 1935, U.S.S. Beaver, with stamped clock receipt.",
    "sfomuseum:dimensions": "3 3/4 x 6 1/2 inches (9.5 x 16.5 cm)",
    "sfomuseum:exhibition_ids": [
      1070
    ],
    "sfomuseum:issues_held": "\r",
    "sfomuseum:media_ids": [
      1527831847
    ],
    "sfomuseum:medium": "paper, ink",
    "sfomuseum:placetype": "object",
    "sfomuseum:publication": ": , 05/09/1935.",
    "sfomuseum:subcategory": "Airmail Flight Cover",
    "wof:depicts": [
      1159285407,
      1159286573
    ],
    "wof:name": "airmail flight cover: U.S. Navy Hawaii, Midway Island Mass Flight, May 9-11, 1935",
    "wof:placetype": "custom",
    "wof:placetype_alt": [
      "object"
    ]
  },
  "geometry": {"coordinates":[-122.386155,37.616357],"type":"Point"}
}
