{
  "type": "Feature",
  "properties": {
    "date:cessation_lower": "1971-01-01",
    "date:cessation_upper": "1971-12-31",
    "date:inception_lower": "1971-01-01",
    "date:inception_upper": "1971-12-31",
    "iso:country": "XX",
    "loc:subject_headings": [
      "sh85060060"
    ],
    "sfomuseum:accession_number": "99-0029",
    "sfomuseum:author": "Hill, Richard Mahler",
    "sfomuseum:callnumber": "TL685.3 .H55 1971",
    "sfomuseum:category": "Book",
    "sfomuseum:collection": "Aviation Library",
    "sfomuseum:date": "1971",
    "sfomuseum:daterange_end": "1971-12-31",
    "sfomuseum:daterange_start": "1971-01-01",
    "sfomuseum:description": "[48] p. illus. (part col.) 25 cm.",
    "sfomuseum:description_library": "[48] p. illus. (part col.) 25 cm.",
    "sfomuseum:medium": "paper, ink",
    "sfomuseum:placetype": "object",
    "sfomuseum:publication": "New York: Arco, 1971.",
    "sfomuseum:publisher": "Arco",
    "sfomuseum:publisher_location": "New York",
    "sfomuseum:series": "Arco-Aircam aviation series, no. 23",
    "sfomuseum:subcategory": "Book",
    "sfomuseum:subject": "Hellcat (Fighter planes)",
    "wof:name": "Grumman F6F-3/5 Hellcat in USN, USMC, FAA, Aeronavale \u0026 Uruguayan service",
    "wof:placetype": "custom",
    "wof:placetype_alt": "object"
  },
  "geometry": {"coordinates":[-122.386155,37.616357],"type":"Point"}
}
