{
  "type": "Feature",
  "properties": {
    "date:cessation_lower": "1926-01-01",
    "date:cessation_upper": "1926-12-31",
    "date:inception_lower": "1926-01-01",
    "date:inception_upper": "1926-12-31",
    "iso:country": "XX",
    "sfomuseum:accession_number": "2000.160.0254",
    "sfomuseum:author": "Davis, Warren Jefferson",
    "sfomuseum:callnumber": "HE9925 .U7 D38 1926 SC",
    "sfomuseum:category": "Book",
    "sfomuseum:collection": "Aviation Library",
    "sfomuseum:creditline": "The Tony Bill Aviation Library Collection",
    "sfomuseum:date": "c. 1926",
    "sfomuseum:date_acquired": "1999-05-18",
    "sfomuseum:daterange_end": "1931-12-31",
    "sfomuseum:daterange_start": "1921-01-01",
    "sfomuseum:description": "2 p. l., 96, 12 p. 26 cm.",
    "sfomuseum:description_library": "2 p. l., 96, 12 p. 26 cm.",
    "sfomuseum:medium": "paper, ink",
    "sfomuseum:placetype": "object",
    "sfomuseum:publication": "Whittier, CA: Newsprint, c. 1926.",
    "sfomuseum:publisher": "Newsprint",
    "sfomuseum:publisher_location": "Whittier, CA",
    "sfomuseum:subcategory": "Book",
    "sfomuseum:subject": "Aeronautics Law and legislation.",
    "wof:name": "Putting laws over wings",
    "wof:placetype": "custom",
    "wof:placetype_alt": "object"
  },
  "geometry": {"coordinates":[-122.386155,37.616357],"type":"Point"}
}
