{
  "type": "Feature",
  "properties": {
    "date:cessation_lower": "1980-01-01",
    "date:cessation_upper": "1989-12-31",
    "date:inception_lower": "1980-01-01",
    "date:inception_upper": "1989-12-31",
    "iso:country": "US",
    "millsfield:images": [
      1527857867,
      1527857869,
      1527857871,
      1527857873,
      1527857875,
      1527857877,
      1729566933
    ],
    "millsfield:primary_image": 1527857867,
    "sfomuseum:accession_number": "2001.106.043 a b",
    "sfomuseum:aircraft": "Boeing 707",
    "sfomuseum:airline": "Braniff International",
    "sfomuseum:category": "Model Aircraft",
    "sfomuseum:collection": "Aviation Museum",
    "sfomuseum:continent": "North America",
    "sfomuseum:country": "United States",
    "sfomuseum:creditline": "Gift of Mark F. Adams Collection",
    "sfomuseum:date": "1980s",
    "sfomuseum:date_acquired": "2001-10-18",
    "sfomuseum:daterange_end": "1989-12-31",
    "sfomuseum:daterange_start": "1980-01-01",
    "sfomuseum:description": "Model airplane of Braniff International, Boeing 707;\ra. yellow fuselage, white wings and tail; \"BI\" on vertical stabilizer and logotype on fuselage; aircraft registration number “N7102”;\rb. black plastic stand. ",
    "sfomuseum:dimensions": "3 x 12 x 12 3/4 inches (7.6 x 30.5 x 32.4 cm)",
    "sfomuseum:media_ids": [
      1527857867,
      1527857869,
      1527857871,
      1527857873,
      1527857875,
      1527857877
    ],
    "sfomuseum:medium": "plastic, paint",
    "sfomuseum:placetype": "object",
    "sfomuseum:publication": ": , 1980s.",
    "sfomuseum:subcategory": "Model Airplane",
    "wof:depicts": [
      1159286455,
      1159289653,
      1159293593,
      1159284009
    ],
    "wof:name": "model airplane: Braniff International, Boeing 707",
    "wof:placetype": "venue"
  },
  "geometry": {"coordinates":[-122.386155,37.616357],"type":"Point"}
}
