{
  "type": "Feature",
  "properties": {
    "date:cessation_lower":"1999-12-31",
    "date:cessation_upper":"1999-12-31",
    "date:inception_lower":"1990-01-01",
    "date:inception_upper":"1990-01-01",
    "iso:country":"XX",
    "millsfield:images":[
        1527823363,
        1527823365
    ],
    "sfomuseum:accession_number":"1998.157.008",
    "sfomuseum:airline":"Air Europa",
    "sfomuseum:category":"Passenger Amenity",
    "sfomuseum:collection":"Aviation Museum",
    "sfomuseum:creditline":"Gift of The Henry Steiner Air Sickness Bag Collection",
    "sfomuseum:date":"1990s",
    "sfomuseum:daterange_end":"1999-12-31",
    "sfomuseum:daterange_start":"1990-01-01",
    "sfomuseum:description":"Gusset wedge. White bag, red print. \"Air Europa\" in red print toward lower portion of bag. \u201cAir Europa\u201d underlined with four red lines. Design on both sides.",
    "sfomuseum:media_ids":[
        1527823363,
        1527823365
    ],
    "sfomuseum:medium":"paper",
    "sfomuseum:placetype":"object",
    "sfomuseum:subcategory":"Airsickness Bag",
    "wof:depicts":[
        1159283617
    ],
    "wof:name":"airsickness bag: Air Europa",
    "wof:placetype":"venue"
},
  "geometry": {"coordinates":[-122.386155,37.616357],"type":"Point"}
}