{
  "type": "Feature",
  "properties": {
    "date:cessation_lower":"1930-12-31",
    "date:cessation_upper":"1930-12-31",
    "date:inception_lower":"1930-01-01",
    "date:inception_upper":"1930-01-01",
    "iso:country":"PE",
    "sfomuseum:accession_number":"1998.126.049",
    "sfomuseum:category":"Insignia",
    "sfomuseum:collection":"Aviation Museum",
    "sfomuseum:continent":"South America",
    "sfomuseum:country":"Peru",
    "sfomuseum:creditline":"Purchase",
    "sfomuseum:date":"1930s",
    "sfomuseum:daterange_end":"1930-12-31",
    "sfomuseum:daterange_start":"1930-01-01",
    "sfomuseum:description":"Circular gold pin, Pan American Airways, South American Division, outlined with leaf border; single wing globe logo in gold with green enamel on globe in center; five gold stars and \u201cPANAIR\u201d printed in center; red flag and black and white checkered flag crisscrossed beneath logo.",
    "sfomuseum:medium":"metal",
    "sfomuseum:placetype":"object",
    "sfomuseum:subcategory":"Uniform Wing(s), Other",
    "wof:name":"airport manager/station manager wing: Panair do Brasil",
    "wof:placetype":"venue"
},
  "geometry": {"coordinates":[-122.386155,37.616358],"type":"Point"}
}