{
  "type": "Feature",
  "properties": {
    "date:cessation_lower": "1930-01-01",
    "date:cessation_upper": "1939-12-31",
    "date:inception_lower": "1930-01-01",
    "date:inception_upper": "1939-12-31",
    "iso:country": "PE",
    "millsfield:images": [
      1746680901
    ],
    "millsfield:images_texts": [
      "* *\nPANAIB"
    ],
    "millsfield:images_texts_ids": [
      1746680901
    ],
    "millsfield:primary_image": 1746680901,
    "sfomuseum:accession_number": "1998.126.049",
    "sfomuseum:airline": "Panair do Brasil",
    "sfomuseum:category": "Insignia",
    "sfomuseum:collection": "Aviation Museum",
    "sfomuseum:continent": "South America",
    "sfomuseum:country": "Peru",
    "sfomuseum:creditline": "Purchase",
    "sfomuseum:date": "1930s",
    "sfomuseum:daterange_end": "1930-12-31",
    "sfomuseum:daterange_start": "1930-01-01",
    "sfomuseum:description": "Airport or station manager wing issued by Panair do Brasil; gold circular disc with laurels and single wing; gold with green enamel globe logo at center; red flag and black and white checkered flag beneath logo.",
    "sfomuseum:dimensions": "1 x 1 1/2 inches (2.5 x 3.8 cm)",
    "sfomuseum:medium": "metal, enamel",
    "sfomuseum:placetype": "object",
    "sfomuseum:publication": ": , 1930s.",
    "sfomuseum:subcategory": "Uniform Wing(s), Ground Crew",
    "wof:depicts": [
      1159287213,
      1159284995
    ],
    "wof:name": "airport manager/station manager wing: Panair do Brasil",
    "wof:placetype": "custom",
    "wof:placetype_alt": "object"
  },
  "geometry": {"coordinates":[-122.386155,37.616357],"type":"Point"}
}
