{
  "type": "Feature",
  "properties": {
    "date:cessation_lower":"1985-12-31",
    "date:cessation_upper":"1985-12-31",
    "date:inception_lower":"1985-01-01",
    "date:inception_upper":"1985-01-01",
    "iso:country":"XX",
    "sfomuseum:accession_number":"2000.058.1457",
    "sfomuseum:artist":"Dong Kingman",
    "sfomuseum:category":"Food Service",
    "sfomuseum:collection":"Aviation Museum",
    "sfomuseum:creditline":"Gift of the Pan Am Association",
    "sfomuseum:date":"1985",
    "sfomuseum:daterange_end":"1985-12-31",
    "sfomuseum:daterange_start":"1985-01-01",
    "sfomuseum:description":"Menu produced by Pan American World Airways, Honolulu - Manila route; gray cover with color reproduction of Dong Kingman illustration of a Martin M-130 flying past the Golden Gate Bridge; menu for flight commemorating the first China Clipper flight on November 22, 1935; menu items included for several meals; no menu number; undated (presumably November 22, 1985).",
    "sfomuseum:media_ids":[
        1527844999,
        1527845003
    ],
    "sfomuseum:medium":"paper, ink",
    "sfomuseum:placetype":"object",
    "sfomuseum:subcategory":"Menu",
    "wof:name":"menu: Pan American World Airways, Historic First Flights series, Martin M-130",
    "wof:placetype":"venue"
},
  "geometry": {"coordinates":[-122.386155,37.616358],"type":"Point"}
}