{
  "type": "Feature",
  "properties": {
    "date:cessation_lower":"1979-12-31",
    "date:cessation_upper":"1979-12-31",
    "date:inception_lower":"1979-01-01",
    "date:inception_upper":"1979-01-01",
    "iso:country":"XX",
    "millsfield:images":[
        1527858389,
        1527848839,
        1527848837
    ],
    "sfomuseum:accession_number":"2007.048.024",
    "sfomuseum:airport":"San Francisco International Airport",
    "sfomuseum:category":"Passenger Amenity",
    "sfomuseum:collection":"Aviation Archive",
    "sfomuseum:creditline":"Transfer",
    "sfomuseum:date":"1979",
    "sfomuseum:daterange_end":"1979-12-31",
    "sfomuseum:daterange_start":"1979-01-01",
    "sfomuseum:description":"Traveler information guide issued by San Francisco International Airport (SFO), titled \u201cTransit & Parking Guide\u201d, June 1979; fold-out pamphlet with black cover and color illustrations of traffic signs; contains ground transport and mass transit information with telephone directory and map of airport parking lots, terminals, and car rental facilities.",
    "sfomuseum:media_ids":[
        1527848837,
        1527848839,
        1527858389
    ],
    "sfomuseum:medium":"paper, ink",
    "sfomuseum:placetype":"object",
    "sfomuseum:subcategory":"Traveler Information",
    "wof:depicts":[
        102527513
    ],
    "wof:name":"traveler information guide: San Francisco International Airport (SFO), transit and parking",
    "wof:placetype":"venue"
},
  "geometry": {"coordinates":[-122.386155,37.616357],"type":"Point"}
}