{
  "type": "Feature",
  "properties": {
    "date:cessation_lower": "1965-01-01",
    "date:cessation_upper": "1965-12-31",
    "date:inception_lower": "1965-01-01",
    "date:inception_upper": "1965-12-31",
    "iso:country": "XX",
    "millsfield:images": [
      1527848529
    ],
    "millsfield:primary_image": 1527848529,
    "sfomuseum:accession_number": "2007.007.018",
    "sfomuseum:airline": "Mount Cook Airlines",
    "sfomuseum:category": "Promotional",
    "sfomuseum:collection": "Aviation Archive",
    "sfomuseum:creditline": "Gift of Hiller Aviation Museum",
    "sfomuseum:date": "c. 1965",
    "sfomuseum:date_acquired": "2008-03-03",
    "sfomuseum:daterange_end": "1970-12-31",
    "sfomuseum:daterange_start": "1960-01-01",
    "sfomuseum:description": "Folded tourist information brochure issued by Mount Cook Airlines, titled \"Meet New Zealand's, Mount Cook Airlines, Flying the world's most scenic air routes\". Cover features color photograph of airplane on the tarmac; interior contains color images describing travel destinations.",
    "sfomuseum:dimensions": "8 1/2 x 3 1/2 inches (21.6 x 8.9 cm)",
    "sfomuseum:media_ids": [
      1527848529
    ],
    "sfomuseum:medium": "paper, ink",
    "sfomuseum:placetype": "object",
    "sfomuseum:publication": ": , c. 1965.",
    "sfomuseum:subcategory": "Brochure, Tourist Information",
    "sfomuseum:subject": "Airlines -- Commercial -- Mount Cook Airlines",
    "wof:depicts": [
      1159284827
    ],
    "wof:name": "brochure: Mount Cook Airlines, general service",
    "wof:placetype": "venue"
  },
  "geometry": {"coordinates":[-122.386155,37.616357],"type":"Point"}
}
