{
  "type": "Feature",
  "properties": {
    "date:cessation_lower": "1936-01-01",
    "date:cessation_upper": "1936-12-31",
    "date:inception_lower": "1936-01-01",
    "date:inception_upper": "1936-12-31",
    "iso:country": "XX",
    "sfomuseum:accession_number": "2014.048.010",
    "sfomuseum:author": "Burge, C.G",
    "sfomuseum:callnumber": "TL501 .A553 1935-6 SC",
    "sfomuseum:category": "Book",
    "sfomuseum:collection": "Aviation Library",
    "sfomuseum:creditline": "Gift of Helene and Rudy Stahl",
    "sfomuseum:date": "1936",
    "sfomuseum:date_acquired": "2014-07-25",
    "sfomuseum:daterange_end": "1936-12-31",
    "sfomuseum:daterange_start": "1936-01-01",
    "sfomuseum:description": "ill., port., plates (part col.) maps (part fold.) diag. 25 cm.",
    "sfomuseum:description_library": "ill., port., plates (part col.) maps (part fold.) diag. 25 cm.",
    "sfomuseum:medium": "paper, ink",
    "sfomuseum:placetype": "object",
    "sfomuseum:publication": "London: Gale \u0026 Polden, 1936.",
    "sfomuseum:publisher": "Gale \u0026 Polden",
    "sfomuseum:publisher_location": "London",
    "sfomuseum:subcategory": "Book",
    "sfomuseum:subject": "Aeronautics Great Britain.Aeronautics Yearbooks.Great Britain Colonies Aeronautics.",
    "wof:name": "The air annual of the British Empire",
    "wof:placetype": "venue"
  },
  "geometry": {"coordinates":[-122.386155,37.616357],"type":"Point"}
}
