{
  "type": "Feature",
  "properties": {
    "date:cessation_lower":"1959-12-31",
    "date:cessation_upper":"1959-12-31",
    "date:inception_lower":"1950-01-01",
    "date:inception_upper":"1950-01-01",
    "iso:country":"XX",
    "sfomuseum:accession_number":"2002.113.315",
    "sfomuseum:airline":"TWA (Trans World Airlines)",
    "sfomuseum:category":"Promotional",
    "sfomuseum:collection":"Aviation Archive",
    "sfomuseum:creditline":"Gift of TWA Clipped Wings International",
    "sfomuseum:date":"1950s",
    "sfomuseum:daterange_end":"1959-12-31",
    "sfomuseum:daterange_start":"1950-01-01",
    "sfomuseum:description":"cookbook: TWA (Trans World Airlines) \u201cInternational Recipes\u201d.",
    "sfomuseum:medium":"paper, ink",
    "sfomuseum:placetype":"object",
    "sfomuseum:subcategory":"Brochure, Airline",
    "wof:depicts":[
        1159285393
    ],
    "wof:name":"cookbook: TWA (Trans World Airlines), \u201cInternational Recipes\u201d",
    "wof:placetype":"venue"
},
  "geometry": {"coordinates":[-122.386155,37.616357],"type":"Point"}
}