{
  "type": "Feature",
  "properties": {
    "date:cessation_lower": "1970-01-01",
    "date:cessation_upper": "1979-12-31",
    "date:inception_lower": "1970-01-01",
    "date:inception_upper": "1979-12-31",
    "iso:country": "XX",
    "millsfield:exhibition_ids": [
      1159160127
    ],
    "millsfield:images": [
      1527828827,
      1729566919
    ],
    "millsfield:on_view": 0,
    "millsfield:primary_image": 1729566919,
    "sfomuseum:accession_number": "2007.051.146",
    "sfomuseum:airline": "Pacific Southwest Airlines (PSA)",
    "sfomuseum:category": "Insignia",
    "sfomuseum:collection": "Aviation Museum",
    "sfomuseum:creditline": "Collection of SFO Museum",
    "sfomuseum:date": "1970s",
    "sfomuseum:date_acquired": "2007-06-22",
    "sfomuseum:daterange_end": "1979-12-31",
    "sfomuseum:daterange_start": "1970-01-01",
    "sfomuseum:description": "Flight officer wings issued by Pacific Southwest Airlines; silver wings with raised “PSA” logo on shield and openwork star at center; two posts with screw-fasteners on back; worn by first officer, 1970-1986.",
    "sfomuseum:dimensions": "1 1/4 x 3 1/2 x 1/2 inches (3.2 x 8.9 x 1.3 cm)",
    "sfomuseum:exhibition_ids": [
      1074
    ],
    "sfomuseum:media_ids": [
      1527828827
    ],
    "sfomuseum:medium": "metal",
    "sfomuseum:placetype": "object",
    "sfomuseum:publication": ": , 1970s.",
    "sfomuseum:subcategory": "Uniform Wing(s), Flight Crew",
    "wof:depicts": [
      1159284973,
      1159286629
    ],
    "wof:name": "flight officer wings: Pacific Southwest Airlines",
    "wof:placetype": "custom",
    "wof:placetype_alt": [
      "object"
    ]
  },
  "geometry": {"coordinates":[-122.386155,37.616357],"type":"Point"}
}
